/*  1 */
package f;

public final class A extends Qa0 implements r60 {
    public static final SimpleDateFormat Ds0 = new SimpleDateFormat("dd MMM hh:mm:ss a");
    public final boolean zk;
    public Vq0 sr;
    public byte[] E60;
    public lK0 X3;
    public YA0 vz0;
    public zT EL0;
    public Rm bl;
    public BS ii;
    public Gn0 bk;
    public of TK0;
    public of zr0;
    public Un ir0;
    public int Ea;
    public bh[] YD0;
    public JG0 z8;
    public fv0[] uC0;
    public Te Vi;
    public oo dL;
    public boolean i6;

    public static void kA(fv0 paramfv0) {
        R8 r8 = km.u4;
        int i = paramfv0.y60;
        r8
/*  2 */.e20
/*  3 */.W3(new CoM1(i));
    }

    public static void Bg(fv0 paramfv0) {
        R8 r8 = km.u4;
        int i = paramfv0.y60;
        boolean bool = true;
        r8.e20.W3(new nS(i, bool));
    }

    public static void Wj(fv0 paramfv0) {
        R8 r8 = km.u4;
        int i = paramfv0.y60;
        boolean bool = true;
        r8.e20.W3(new nS(i, bool));
    }

    public static void u10(bh parambh) {
        boolean bool;
        if (parambh.CG0() == 0) {
            bool = true;
        } else {
            bool = false;
        }
        parambh.dX.Z30(bool);
    }

    public static void vf(bh parambh) {
        byte b;
        if (parambh.CG0() == 2) {
            b = 3;
        } else {
            b = 2;
        }
        parambh.dX.Z30(b);
    }

    private void yW(Te paramTe, byte paramByte, int paramInt1, fv0[] paramArrayOffv0, int paramInt2, boolean paramBoolean, Qr paramQr) { // Byte code:
        /*    */     //   0: aload_0
        /*    */     //   1: getfield E60 : [B
        /*    */     //   4: aload_1
        /*    */     //   5: getfield HC0 : B
        /*    */     //   8: baload
        /*    */     //   9: iload_2
        /*    */     //   10: if_icmpeq -> 14
        /*    */     //   13: return
        /*    */     //   14: new f/TV
        /*    */     //   17: dup
        /*    */     //   18: dup2
        /*    */     //   19: astore_2
        /*    */     //   20: aload_0
        /*    */     //   21: aload_1
        /*    */     //   22: iload_3
        /*    */     //   23: invokespecial <init> : (Lf/A;Lf/Te;I)V
        /*    */     //   26: ldc '/broker-table'
        /*    */     //   28: invokevirtual Xu : (Ljava/lang/String;)V
        /*    */     //   31: getfield Dv0 : Lf/SA;
        /*    */     //   34: dup
        /*    */     //   35: astore #8
        /*    */     //   37: getfield RT : Lf/nJ0;
        /*    */     //   40: fconst_1
        /*    */     //   41: invokevirtual Xj0 : (F)Lf/nJ0;
        /*    */     //   44: invokevirtual Xs0 : ()Lf/nJ0;
        /*    */     //   47: astore #9
        /*    */     //   49: invokestatic XU : ()Z
        /*    */     //   52: ifeq -> 62
        /*    */     //   55: ldc 40.0
        /*    */     //   57: fstore #10
        /*    */     //   59: goto -> 66
        /*    */     //   62: ldc 36.0
        /*    */     //   64: fstore #10
        /*    */     //   66: aload #9
        /*    */     //   68: fload #10
        /*    */     //   70: invokevirtual fJ : (F)Lf/nJ0;
        /*    */     //   73: pop
        /*    */     //   74: invokestatic XU : ()Z
        /*    */     //   77: ifeq -> 92
        /*    */     //   80: aload #8
        /*    */     //   82: iconst_1
        /*    */     //   83: invokevirtual JP : (I)Lf/nJ0;
        /*    */     //   86: ldc 46.0
        /*    */     //   88: invokevirtual Je0 : (F)Lf/nJ0;
        /*    */     //   91: pop
        /*    */     //   92: aload #4
        /*    */     //   94: arraylength
        /*    */     //   95: iconst_1
        /*    */     //   96: if_icmpge -> 105
        /*    */     //   99: iconst_1
        /*    */     //   100: istore #9
        /*    */     //   102: goto -> 108
        /*    */     //   105: iconst_0
        /*    */     //   106: istore #9
        /*    */     //   108: aload #4
        /*    */     //   110: iload #5
        /*    */     //   112: aload_0
        /*    */     //   113: aload_1
        /*    */     //   114: aload_2
        /*    */     //   115: iload #9
        /*    */     //   117: invokevirtual JC : (Lf/Te;Lf/YA0;Z)V
        /*    */     //   120: bipush #10
        /*    */     //   122: imul
        /*    */     //   123: istore #5
        /*    */     //   125: new f/dQ
        /*    */     //   128: astore #9
        /*    */     //   130: sipush #8028
        /*    */     //   133: istore #10
        /*    */     //   135: iconst_3
        /*    */     //   136: anewarray java/lang/String
        /*    */     //   139: astore #11
        /*    */     //   141: iconst_0
        /*    */     //   142: istore #12
        /*    */     //   144: invokestatic getInstance : ()Ljava/text/NumberFormat;
        /*    */     //   147: astore #13
        /*    */     //   149: arraylength
        /*    */     //   150: ifle -> 159
        /*    */     //   153: iconst_1
        /*    */     //   154: istore #14
        /*    */     //   156: goto -> 162
        /*    */     //   159: iconst_0
        /*    */     //   160: istore #14
        /*    */     //   162: iload #6
        /*    */     //   164: aload #11
        /*    */     //   166: dup
        /*    */     //   167: iload #12
        /*    */     //   169: aload #13
        /*    */     //   171: iload #5
        /*    */     //   173: iload #14
        /*    */     //   175: iadd
        /*    */     //   176: i2l
        /*    */     //   177: invokevirtual format : (J)Ljava/lang/String;
        /*    */     //   180: aastore
        /*    */     //   181: invokestatic getInstance : ()Ljava/text/NumberFormat;
        /*    */     //   184: iload #5
        /*    */     //   186: aload #4
        /*    */     //   188: arraylength
        /*    */     //   189: iadd
        /*    */     //   190: i2l
        /*    */     //   191: invokevirtual format : (J)Ljava/lang/String;
        /*    */     //   194: iconst_1
        /*    */     //   195: swap
        /*    */     //   196: aastore
        /*    */     //   197: iconst_2
        /*    */     //   198: istore #5
        /*    */     //   200: new java/lang/StringBuilder
        /*    */     //   203: dup
        /*    */     //   204: invokespecial <init> : ()V
        /*    */     //   207: invokestatic getInstance : ()Ljava/text/NumberFormat;
        /*    */     //   210: iload_3
        /*    */     //   211: i2l
        /*    */     //   212: invokevirtual format : (J)Ljava/lang/String;
        /*    */     //   215: invokevirtual append : (Ljava/lang/String;)Ljava/lang/StringBuilder;
        /*    */     //   218: astore #6
        /*    */     //   220: ifeq -> 230
        /*    */     //   223: ldc '+'
        /*    */     //   225: astore #12
        /*    */     //   227: goto -> 234
        /*    */     //   230: ldc ''
        /*    */     //   232: astore #12
        /*    */     //   234: aload #4
        /*    */     //   236: aload #9
        /*    */     //   238: dup
        /*    */     //   239: dup
        /*    */     //   240: iload #10
        /*    */     //   242: aload #11
        /*    */     //   244: dup
        /*    */     //   245: iload #5
        /*    */     //   247: aload #6
        /*    */     //   249: aload #12
        /*    */     //   251: invokevirtual append : (Ljava/lang/String;)Ljava/lang/StringBuilder;
        /*    */     //   254: invokevirtual toString : ()Ljava/lang/String;
        /*    */     //   257: aastore
        /*    */     //   258: invokestatic sB : (I[Ljava/lang/String;)Ljava/lang/String;
        /*    */     //   261: astore #5
        /*    */     //   263: invokespecial <init> : ()V
        /*    */     //   266: aload #5
        /*    */     //   268: invokevirtual E1 : (Ljava/lang/String;)V
        /*    */     //   271: ldc 'label-info'
        /*    */     //   273: invokevirtual Xu : (Ljava/lang/String;)V
        /*    */     //   276: arraylength
        /*    */     //   277: istore #5
        /*    */     //   279: iconst_0
        /*    */     //   280: istore #6
        /*    */     //   282: iload #6
        /*    */     //   284: iload #5
        /*    */     //   286: if_icmpge -> 2615
        /*    */     //   289: aload #4
        /*    */     //   291: iload #6
        /*    */     //   293: aaload
        /*    */     //   294: dup
        /*    */     //   295: astore #10
        /*    */     //   297: getfield Z6 : Lf/Te;
        /*    */     //   300: dup
        /*    */     //   301: astore #11
        /*    */     //   303: getstatic f/Te.QK0 : Lf/Te;
        /*    */     //   306: if_acmpne -> 923
        /*    */     //   309: new f/ey
        /*    */     //   312: dup
        /*    */     //   313: astore #11
        /*    */     //   315: aload #10
        /*    */     //   317: aload #11
        /*    */     //   319: dup
        /*    */     //   320: dup2
        /*    */     //   321: invokespecial <init> : ()V
        /*    */     //   324: iconst_0
        /*    */     //   325: putfield XC0 : Z
        /*    */     //   328: iconst_0
        /*    */     //   329: putfield ZF : Z
        /*    */     //   332: iconst_0
        /*    */     //   333: putfield FO : Z
        /*    */     //   336: invokevirtual sB0 : (Lf/fv0;)V
        /*    */     //   339: invokestatic XU : ()Z
        /*    */     //   342: ifeq -> 374
        /*    */     //   345: aload #11
        /*    */     //   347: dup
        /*    */     //   348: dup2
        /*    */     //   349: iconst_0
        /*    */     //   350: putfield un0 : I
        /*    */     //   353: iconst_0
        /*    */     //   354: putfield ST : I
        /*    */     //   357: getfield As : Lf/rH;
        /*    */     //   360: iconst_0
        /*    */     //   361: bipush #-20
        /*    */     //   363: invokevirtual zT : (II)Lf/JG0;
        /*    */     //   366: pop
        /*    */     //   367: getfield As : Lf/rH;
        /*    */     //   370: fconst_2
        /*    */     //   371: putfield V1 : F
        /*    */     //   374: aload #8
        /*    */     //   376: aload #11
        /*    */     //   378: invokevirtual S7 : (Ljava/lang/Object;)Lf/nJ0;
        /*    */     //   381: astore #12
        /*    */     //   383: invokestatic XU : ()Z
        /*    */     //   386: ifeq -> 397
        /*    */     //   389: ldc_w 120.0
        /*    */     //   392: fstore #13
        /*    */     //   394: goto -> 402
        /*    */     //   397: ldc_w 70.0
        /*    */     //   400: fstore #13
        /*    */     //   402: aload #10
        /*    */     //   404: aload #12
        /*    */     //   406: fload #13
        /*    */     //   408: invokevirtual Ig0 : (F)Lf/nJ0;
        /*    */     //   411: invokevirtual fu : ()Lf/nJ0;
        /*    */     //   414: pop
        /*    */     //   415: getfield mm0 : Lf/Q90;
        /*    */     //   418: dup
        /*    */     //   419: astore #12
        /*    */     //   421: ifnull -> 434
        /*    */     //   424: aload #12
        /*    */     //   426: getfield od : B
        /*    */     //   429: istore #13
        /*    */     //   431: goto -> 441
        /*    */     //   434: aload #10
        /*    */     //   436: getfield nj0 : B
        /*    */     //   439: istore #13
        /*    */     //   441: aload #12
        /*    */     //   443: ifnull -> 456
        /*    */     //   446: aload #12
        /*    */     //   448: getfield Cw0 : S
        /*    */     //   451: istore #12
        /*    */     //   453: goto -> 463
        /*    */     //   456: aload #10
        /*    */     //   458: getfield bn : S
        /*    */     //   461: istore #12
        /*    */     //   463: aload #10
        /*    */     //   465: new f/Un
        /*    */     //   468: dup
        /*    */     //   469: astore #14
        /*    */     //   471: new java/lang/StringBuilder
        /*    */     //   474: dup
        /*    */     //   475: invokespecial <init> : ()V
        /*    */     //   478: bipush #59
        /*    */     //   480: invokestatic OH0 : (I)Ljava/lang/String;
        /*    */     //   483: invokevirtual append : (Ljava/lang/String;)Ljava/lang/StringBuilder;
        /*    */     //   486: ldc_w ' '
        /*    */     //   489: invokevirtual append : (Ljava/lang/String;)Ljava/lang/StringBuilder;
        /*    */     //   492: iload #13
        /*    */     //   494: invokevirtual append : (I)Ljava/lang/StringBuilder;
        /*    */     //   497: ldc_w ' '
        /*    */     //   500: invokevirtual append : (Ljava/lang/String;)Ljava/lang/StringBuilder;
        /*    */     //   503: iload #12
        /*    */     //   505: ldc_w 150000
        /*    */     //   508: iadd
        /*    */     //   509: invokestatic OH0 : (I)Ljava/lang/String;
        /*    */     //   512: invokevirtual append : (Ljava/lang/String;)Ljava/lang/StringBuilder;
        /*    */     //   515: invokevirtual toString : ()Ljava/lang/String;
        /*    */     //   518: invokespecial <init> : (Ljava/lang/String;)V
        /*    */     //   521: getfield mm0 : Lf/Q90;
        /*    */     //   524: ifnull -> 568
        /*    */     //   527: aload #14
        /*    */     //   529: dup
        /*    */     //   530: aload #11
        /*    */     //   532: aload_0
        /*    */     //   533: aload #11
        /*    */     //   535: ldc_w 'button-monster'
        /*    */     //   538: invokevirtual Xu : (Ljava/lang/String;)V
        /*    */     //   541: aload #11
        /*    */     //   543: <illegal opcode> run : (Lf/A;Lf/ey;)Ljava/lang/Runnable;
        /*    */     //   548: dup
        /*    */     //   549: astore #11
        /*    */     //   551: putfield n0 : Ljava/lang/Runnable;
        /*    */     //   554: ldc_w 'button-species'
        /*    */     //   557: invokevirtual Xu : (Ljava/lang/String;)V
        /*    */     //   560: aload #11
        /*    */     //   562: invokevirtual tW : (Ljava/lang/Runnable;)V
        /*    */     //   565: goto -> 584
        /*    */     //   568: aload #14
        /*    */     //   570: aload #11
        /*    */     //   572: ldc_w 'cell'
        /*    */     //   575: invokevirtual Xu : (Ljava/lang/String;)V
        /*    */     //   578: ldc_w 'cell'
        /*    */     //   581: invokevirtual Xu : (Ljava/lang/String;)V
        /*    */     //   584: invokestatic XU : ()Z
        /*    */     //   587: ifeq -> 618
        /*    */     //   590: aload #8
        /*    */     //   592: aload #14
        /*    */     //   594: invokevirtual S7 : (Ljava/lang/Object;)Lf/nJ0;
        /*    */     //   597: invokevirtual ti0 : ()Lf/nJ0;
        /*    */     //   600: ldc_w 190.0
        /*    */     //   603: invokevirtual Ig0 : (F)Lf/nJ0;
        /*    */     //   606: dup
        /*    */     //   607: invokevirtual Kw : ()Lf/nJ0;
        /*    */     //   610: pop
        /*    */     //   611: invokevirtual x70 : ()Lf/nJ0;
        /*    */     //   614: pop
        /*    */     //   615: goto -> 662
        /*    */     //   618: aload_1
        /*    */     //   619: aload #8
        /*    */     //   621: aload #14
        /*    */     //   623: invokevirtual S7 : (Ljava/lang/Object;)Lf/nJ0;
        /*    */     //   626: invokevirtual Kw : ()Lf/nJ0;
        /*    */     //   629: astore #11
        /*    */     //   631: getstatic f/Te.EE : Lf/Te;
        /*    */     //   634: if_acmpeq -> 641
        /*    */     //   637: iconst_1
        /*    */     //   638: goto -> 642
        /*    */     //   641: iconst_0
        /*    */     //   642: invokestatic valueOf : (I)Ljava/lang/Integer;
        /*    */     //   645: astore #12
        /*    */     //   647: aload #11
        /*    */     //   649: dup
        /*    */     //   650: aload #12
        /*    */     //   652: putfield Ls : Ljava/lang/Integer;
        /*    */     //   655: iconst_0
        /*    */     //   656: invokestatic valueOf : (I)Ljava/lang/Integer;
        /*    */     //   659: putfield C10 : Ljava/lang/Integer;
        /*    */     //   662: aload_1
        /*    */     //   663: getstatic f/Te.EE : Lf/Te;
        /*    */     //   666: if_acmpeq -> 1571
        /*    */     //   669: aload #10
        /*    */     //   671: aload #8
        /*    */     //   673: aload #10
        /*    */     //   675: getfield mm0 : Lf/Q90;
        /*    */     //   678: getfield k0 : Lf/nV;
        /*    */     //   681: invokevirtual toString : ()Ljava/lang/String;
        /*    */     //   684: dup
        /*    */     //   685: astore #11
        /*    */     //   687: ldc_w 'cell'
        /*    */     //   690: invokevirtual fe : (Ljava/lang/String;Ljava/lang/String;)Lf/nJ0;
        /*    */     //   693: dup
        /*    */     //   694: invokevirtual Kw : ()Lf/nJ0;
        /*    */     //   697: pop
        /*    */     //   698: getfield ZX : Ljava/lang/Object;
        /*    */     //   701: checkcast f/JG0
        /*    */     //   704: dup
        /*    */     //   705: astore #12
        /*    */     //   707: bipush #50
        /*    */     //   709: invokevirtual Pb0 : (I)V
        /*    */     //   712: getfield mm0 : Lf/Q90;
        /*    */     //   715: getfield k0 : Lf/nV;
        /*    */     //   718: getfield Qc0 : Lf/hR;
        /*    */     //   721: ifnonnull -> 752
        /*    */     //   724: aload #12
        /*    */     //   726: aload #11
        /*    */     //   728: ldc_w '\\n'
        /*    */     //   731: invokestatic vz : (Ljava/lang/String;Ljava/lang/String;)Ljava/lang/StringBuilder;
        /*    */     //   734: sipush #1806
        /*    */     //   737: invokestatic OH0 : (I)Ljava/lang/String;
        /*    */     //   740: invokevirtual append : (Ljava/lang/String;)Ljava/lang/StringBuilder;
        /*    */     //   743: invokevirtual toString : ()Ljava/lang/String;
        /*    */     //   746: invokevirtual Gq0 : (Ljava/lang/Object;)V
        /*    */     //   749: goto -> 782
        /*    */     //   752: aload #12
        /*    */     //   754: aload #11
        /*    */     //   756: ldc_w '\\n'
        /*    */     //   759: invokestatic vz : (Ljava/lang/String;Ljava/lang/String;)Ljava/lang/StringBuilder;
        /*    */     //   762: aload #10
        /*    */     //   764: getfield mm0 : Lf/Q90;
        /*    */     //   767: getfield k0 : Lf/nV;
        /*    */     //   770: invokestatic Em0 : (Lf/nV;)Ljava/lang/String;
        /*    */     //   773: invokevirtual append : (Ljava/lang/String;)Ljava/lang/StringBuilder;
        /*    */     //   776: invokevirtual toString : ()Ljava/lang/String;
        /*    */     //   779: invokevirtual Gq0 : (Ljava/lang/Object;)V
        /*    */     //   782: getstatic f/hR.Tm0 : [Lf/hR;
        /*    */     //   785: dup
        /*    */     //   786: astore #11
        /*    */     //   788: arraylength
        /*    */     //   789: istore #12
        /*    */     //   791: iconst_0
        /*    */     //   792: istore #13
        /*    */     //   794: iload #13
        /*    */     //   796: iload #12
        /*    */     //   798: if_icmpge -> 1571
        /*    */     //   801: aload #10
        /*    */     //   803: aload #11
        /*    */     //   805: iload #13
        /*    */     //   807: aaload
        /*    */     //   808: astore #14
        /*    */     //   810: getfield mm0 : Lf/Q90;
        /*    */     //   813: aload #14
        /*    */     //   815: invokevirtual Hc : (Lf/hR;)B
        /*    */     //   818: dup
        /*    */     //   819: istore #15
        /*    */     //   821: aload #10
        /*    */     //   823: getfield mm0 : Lf/Q90;
        /*    */     //   826: aload #14
        /*    */     //   828: invokevirtual Hc : (Lf/hR;)B
        /*    */     //   831: invokestatic valueOf : (I)Ljava/lang/String;
        /*    */     //   834: astore #14
        /*    */     //   836: bipush #31
        /*    */     //   838: if_icmpne -> 857
        /*    */     //   841: aload #14
        /*    */     //   843: ldc_w '31'
        /*    */     //   846: ldc_w '[#6fb76f]31[]'
        /*    */     //   849: invokevirtual replace : (Ljava/lang/CharSequence;Ljava/lang/CharSequence;)Ljava/lang/String;
        /*    */     //   852: astore #14
        /*    */     //   854: goto -> 875
        /*    */     //   857: iload #15
        /*    */     //   859: ifne -> 875
        /*    */     //   862: aload #14
        /*    */     //   864: ldc_w '0'
        /*    */     //   867: ldc_w '[#ff6666]0[]'
        /*    */     //   870: invokevirtual replace : (Ljava/lang/CharSequence;Ljava/lang/CharSequence;)Ljava/lang/String;
        /*    */     //   873: astore #14
        /*    */     //   875: aload #8
        /*    */     //   877: aload #14
        /*    */     //   879: ldc_w 'cell-markup'
        /*    */     //   882: invokevirtual fe : (Ljava/lang/String;Ljava/lang/String;)Lf/nJ0;
        /*    */     //   885: astore #14
        /*    */     //   887: invokestatic XU : ()Z
        /*    */     //   890: ifeq -> 901
        /*    */     //   893: ldc_w 20.0
        /*    */     //   896: fstore #15
        /*    */     //   898: goto -> 906
        /*    */     //   901: ldc_w 30.0
        /*    */     //   904: fstore #15
        /*    */     //   906: aload #14
        /*    */     //   908: fload #15
        /*    */     //   910: invokevirtual Ig0 : (F)Lf/nJ0;
        /*    */     //   913: invokevirtual Kw : ()Lf/nJ0;
        /*    */     //   916: pop
        /*    */     //   917: iinc #13, 1
        /*    */     //   920: goto -> 794
        /*    */     //   923: aload #11
        /*    */     //   925: getstatic f/Te.Qu : Lf/Te;
        /*    */     //   928: dup
        /*    */     //   929: astore #11
        /*    */     //   931: if_acmpne -> 1571
        /*    */     //   934: getstatic f/Of.eH : Lf/Of;
        /*    */     //   937: aload #10
        /*    */     //   939: getfield bn : S
        /*    */     //   942: invokevirtual On0 : (S)Lf/LPT3;
        /*    */     //   945: astore #12
        /*    */     //   947: new f/vF0
        /*    */     //   950: dup
        /*    */     //   951: dup
        /*    */     //   952: dup2
        /*    */     //   953: dup2
        /*    */     //   954: astore #13
        /*    */     //   956: invokespecial <init> : ()V
        /*    */     //   959: getfield TS : Lf/rH;
        /*    */     //   962: iconst_1
        /*    */     //   963: anewarray f/U70
        /*    */     //   966: dup
        /*    */     //   967: getstatic f/wm0.y0 : Lf/wm0;
        /*    */     //   970: aload #12
        /*    */     //   972: iconst_0
        /*    */     //   973: invokevirtual HR : (Lf/LPT3;Z)Lf/U70;
        /*    */     //   976: iconst_0
        /*    */     //   977: swap
        /*    */     //   978: aastore
        /*    */     //   979: invokevirtual qt : ([Lf/U70;)Lf/JG0;
        /*    */     //   982: pop
        /*    */     //   983: getfield TS : Lf/rH;
        /*    */     //   986: bipush #24
        /*    */     //   988: bipush #24
        /*    */     //   990: invokevirtual tL : (II)V
        /*    */     //   993: getfield TS : Lf/rH;
        /*    */     //   996: iconst_1
        /*    */     //   997: putfield xB0 : I
        /*    */     //   1000: invokevirtual mM : ()V
        /*    */     //   1003: ldc_w 'cell-icon'
        /*    */     //   1006: invokevirtual Xu : (Ljava/lang/String;)V
        /*    */     //   1009: invokestatic XU : ()Z
        /*    */     //   1012: ifeq -> 1024
        /*    */     //   1015: aload #13
        /*    */     //   1017: getfield TS : Lf/rH;
        /*    */     //   1020: fconst_2
        /*    */     //   1021: putfield V1 : F
        /*    */     //   1024: aload #8
        /*    */     //   1026: aload #13
        /*    */     //   1028: invokevirtual S7 : (Ljava/lang/Object;)Lf/nJ0;
        /*    */     //   1031: astore #14
        /*    */     //   1033: invokestatic XU : ()Z
        /*    */     //   1036: ifeq -> 1080
        /*    */     //   1039: invokestatic XU : ()Z
        /*    */     //   1042: ifeq -> 1060
        /*    */     //   1045: aload_1
        /*    */     //   1046: getstatic f/Te.EE : Lf/Te;
        /*    */     //   1049: if_acmpne -> 1060
        /*    */     //   1052: ldc_w 120.0
        /*    */     //   1055: fstore #15
        /*    */     //   1057: goto -> 1063
        /*    */     //   1060: fconst_0
        /*    */     //   1061: fstore #15
        /*    */     //   1063: aload #14
        /*    */     //   1065: fload #15
        /*    */     //   1067: invokevirtual Ig0 : (F)Lf/nJ0;
        /*    */     //   1070: invokevirtual fu : ()Lf/nJ0;
        /*    */     //   1073: invokevirtual Kw : ()Lf/nJ0;
        /*    */     //   1076: pop
        /*    */     //   1077: goto -> 1092
        /*    */     //   1080: aload #14
        /*    */     //   1082: ldc_w 70.0
        /*    */     //   1085: invokevirtual dO : (F)Lf/nJ0;
        /*    */     //   1088: invokevirtual R7 : ()Lf/nJ0;
        /*    */     //   1091: pop
        /*    */     //   1092: aload #12
        /*    */     //   1094: dup
        /*    */     //   1095: getfield Iu : I
        /*    */     //   1098: invokestatic OH0 : (I)Ljava/lang/String;
        /*    */     //   1101: astore #14
        /*    */     //   1103: getfield Y8 : Lf/Hu0;
        /*    */     //   1106: getstatic f/Hu0.w2 : Lf/Hu0;
        /*    */     //   1109: if_acmpne -> 1201
        /*    */     //   1112: aload #12
        /*    */     //   1114: getfield c3 : Lf/wc;
        /*    */     //   1117: dup
        /*    */     //   1118: astore #15
        /*    */     //   1120: ifnull -> 1201
        /*    */     //   1123: aload #15
        /*    */     //   1125: invokevirtual XF0 : ()Z
        /*    */     //   1128: ifeq -> 1201
        /*    */     //   1131: aload #10
        /*    */     //   1133: aload #14
        /*    */     //   1135: ldc_w ' ('
        /*    */     //   1138: invokestatic vz : (Ljava/lang/String;Ljava/lang/String;)Ljava/lang/StringBuilder;
        /*    */     //   1141: astore #14
        /*    */     //   1143: getfield nj0 : B
        /*    */     //   1146: invokestatic Er : (B)Lf/UX;
        /*    */     //   1149: dup
        /*    */     //   1150: astore #15
        /*    */     //   1152: getfield Ii : B
        /*    */     //   1155: sipush #32000
        /*    */     //   1158: iadd
        /*    */     //   1159: istore #16
        /*    */     //   1161: getstatic f/Ml0.nW : Lf/Ut0;
        /*    */     //   1164: iload #16
        /*    */     //   1166: invokevirtual return : (I)Z
        /*    */     //   1169: ifeq -> 1182
        /*    */     //   1172: iload #16
        /*    */     //   1174: invokestatic OH0 : (I)Ljava/lang/String;
        /*    */     //   1177: astore #15
        /*    */     //   1179: goto -> 1189
        /*    */     //   1182: aload #15
        /*    */     //   1184: invokevirtual toString : ()Ljava/lang/String;
        /*    */     //   1187: astore #15
        /*    */     //   1189: aload #14
        /*    */     //   1191: aload #15
        /*    */     //   1193: ldc_w ')'
        /*    */     //   1196: invokestatic Vr0 : (Ljava/lang/StringBuilder;Ljava/lang/String;Ljava/lang/String;)Ljava/lang/String;
        /*    */     //   1199: astore #14
        /*    */     //   1201: invokestatic XU : ()Z
        /*    */     //   1204: ifeq -> 1305
        /*    */     //   1207: aload #14
        /*    */     //   1209: invokevirtual length : ()I
        /*    */     //   1212: bipush #36
        /*    */     //   1214: if_icmple -> 1256
        /*    */     //   1217: aload_1
        /*    */     //   1218: aload #11
        /*    */     //   1220: if_acmpne -> 1256
        /*    */     //   1223: new java/lang/StringBuilder
        /*    */     //   1226: dup
        /*    */     //   1227: aload #14
        /*    */     //   1229: swap
        /*    */     //   1230: invokespecial <init> : ()V
        /*    */     //   1233: iconst_0
        /*    */     //   1234: bipush #33
        /*    */     //   1236: invokevirtual substring : (II)Ljava/lang/String;
        /*    */     //   1239: invokevirtual append : (Ljava/lang/String;)Ljava/lang/StringBuilder;
        /*    */     //   1242: ldc_w '...'
        /*    */     //   1245: invokevirtual append : (Ljava/lang/String;)Ljava/lang/StringBuilder;
        /*    */     //   1248: invokevirtual toString : ()Ljava/lang/String;
        /*    */     //   1251: astore #14
        /*    */     //   1253: goto -> 1351
        /*    */     //   1256: aload #14
        /*    */     //   1258: invokevirtual length : ()I
        /*    */     //   1261: bipush #20
        /*    */     //   1263: if_icmple -> 1351
        /*    */     //   1266: aload_1
        /*    */     //   1267: aload #11
        /*    */     //   1269: if_acmpeq -> 1351
        /*    */     //   1272: new java/lang/StringBuilder
        /*    */     //   1275: dup
        /*    */     //   1276: aload #14
        /*    */     //   1278: swap
        /*    */     //   1279: invokespecial <init> : ()V
        /*    */     //   1282: iconst_0
        /*    */     //   1283: bipush #17
        /*    */     //   1285: invokevirtual substring : (II)Ljava/lang/String;
        /*    */     //   1288: invokevirtual append : (Ljava/lang/String;)Ljava/lang/StringBuilder;
        /*    */     //   1291: ldc_w '...'
        /*    */     //   1294: invokevirtual append : (Ljava/lang/String;)Ljava/lang/StringBuilder;
        /*    */     //   1297: invokevirtual toString : ()Ljava/lang/String;
        /*    */     //   1300: astore #14
        /*    */     //   1302: goto -> 1351
        /*    */     //   1305: invokestatic Nr : ()Z
        /*    */     //   1308: ifeq -> 1351
        /*    */     //   1311: aload #14
        /*    */     //   1313: invokevirtual length : ()I
        /*    */     //   1316: bipush #32
        /*    */     //   1318: if_icmple -> 1351
        /*    */     //   1321: new java/lang/StringBuilder
        /*    */     //   1324: dup
        /*    */     //   1325: aload #14
        /*    */     //   1327: swap
        /*    */     //   1328: invokespecial <init> : ()V
        /*    */     //   1331: iconst_0
        /*    */     //   1332: bipush #29
        /*    */     //   1334: invokevirtual substring : (II)Ljava/lang/String;
        /*    */     //   1337: invokevirtual append : (Ljava/lang/String;)Ljava/lang/StringBuilder;
        /*    */     //   1340: ldc_w '...'
        /*    */     //   1343: invokevirtual append : (Ljava/lang/String;)Ljava/lang/StringBuilder;
        /*    */     //   1346: invokevirtual toString : ()Ljava/lang/String;
        /*    */     //   1349: astore #14
        /*    */     //   1351: aload #12
        /*    */     //   1353: getfield c3 : Lf/wc;
        /*    */     //   1356: ifnull -> 1440
        /*    */     //   1359: aload #8
        /*    */     //   1361: aload #13
        /*    */     //   1363: dup
        /*    */     //   1364: dup
        /*    */     //   1365: new f/Un
        /*    */     //   1368: dup
        /*    */     //   1369: dup
        /*    */     //   1370: astore #11
        /*    */     //   1372: aload #10
        /*    */     //   1374: aload #12
        /*    */     //   1376: aload #11
        /*    */     //   1378: dup
        /*    */     //   1379: aload #14
        /*    */     //   1381: invokespecial <init> : (Ljava/lang/String;)V
        /*    */     //   1384: ldc_w 'cell-button-addon'
        /*    */     //   1387: invokevirtual Xu : (Ljava/lang/String;)V
        /*    */     //   1390: <illegal opcode> run : (Lf/fv0;Lf/LPT3;)Ljava/lang/Runnable;
        /*    */     //   1395: invokevirtual tW : (Ljava/lang/Runnable;)V
        /*    */     //   1398: iconst_1
        /*    */     //   1399: putfield jl : I
        /*    */     //   1402: iconst_1
        /*    */     //   1403: putfield jl : I
        /*    */     //   1406: new f/pQ
        /*    */     //   1409: dup
        /*    */     //   1410: aload #12
        /*    */     //   1412: aload #10
        /*    */     //   1414: getfield nj0 : B
        /*    */     //   1417: iconst_1
        /*    */     //   1418: iconst_1
        /*    */     //   1419: ldc ''
        /*    */     //   1421: invokespecial <init> : (Lf/LPT3;BZZLjava/lang/String;)V
        /*    */     //   1424: putfield z4 : Ljava/lang/Object;
        /*    */     //   1427: invokevirtual zn : ()V
        /*    */     //   1430: aload #11
        /*    */     //   1432: invokevirtual S7 : (Ljava/lang/Object;)Lf/nJ0;
        /*    */     //   1435: astore #11
        /*    */     //   1437: goto -> 1511
        /*    */     //   1440: new f/dQ
        /*    */     //   1443: dup
        /*    */     //   1444: dup
        /*    */     //   1445: astore #11
        /*    */     //   1447: aload #12
        /*    */     //   1449: aload #13
        /*    */     //   1451: dup
        /*    */     //   1452: aload #12
        /*    */     //   1454: aload #11
        /*    */     //   1456: aload #13
        /*    */     //   1458: aload #8
        /*    */     //   1460: aload #11
        /*    */     //   1462: dup
        /*    */     //   1463: dup
        /*    */     //   1464: aload #14
        /*    */     //   1466: aload #11
        /*    */     //   1468: invokespecial <init> : ()V
        /*    */     //   1471: invokevirtual E1 : (Ljava/lang/String;)V
        /*    */     //   1474: ldc_w 'cell'
        /*    */     //   1477: invokevirtual Xu : (Ljava/lang/String;)V
        /*    */     //   1480: invokevirtual S7 : (Ljava/lang/Object;)Lf/nJ0;
        /*    */     //   1483: astore #11
        /*    */     //   1485: iconst_1
        /*    */     //   1486: putfield jl : I
        /*    */     //   1489: iconst_1
        /*    */     //   1490: putfield jl : I
        /*    */     //   1493: invokestatic kh0 : (Lf/LPT3;)Ljava/lang/String;
        /*    */     //   1496: putfield z4 : Ljava/lang/Object;
        /*    */     //   1499: invokevirtual zn : ()V
        /*    */     //   1502: invokestatic kh0 : (Lf/LPT3;)Ljava/lang/String;
        /*    */     //   1505: putfield z4 : Ljava/lang/Object;
        /*    */     //   1508: invokevirtual zn : ()V
        /*    */     //   1511: invokestatic XU : ()Z
        /*    */     //   1514: ifeq -> 1531
        /*    */     //   1517: aload #11
        /*    */     //   1519: dup
        /*    */     //   1520: invokevirtual Kw : ()Lf/nJ0;
        /*    */     //   1523: pop
        /*    */     //   1524: invokevirtual x70 : ()Lf/nJ0;
        /*    */     //   1527: pop
        /*    */     //   1528: goto -> 1540
        /*    */     //   1531: aload #11
        /*    */     //   1533: invokevirtual fu : ()Lf/nJ0;
        /*    */     //   1536: invokevirtual Kw : ()Lf/nJ0;
        /*    */     //   1539: pop
        /*    */     //   1540: aload_1
        /*    */     //   1541: getstatic f/Te.EE : Lf/Te;
        /*    */     //   1544: if_acmpeq -> 1571
        /*    */     //   1547: aload #8
        /*    */     //   1549: invokestatic getInstance : ()Ljava/text/NumberFormat;
        /*    */     //   1552: aload #10
        /*    */     //   1554: getfield gh : S
        /*    */     //   1557: i2l
        /*    */     //   1558: invokevirtual format : (J)Ljava/lang/String;
        /*    */     //   1561: ldc_w 'cell'
        /*    */     //   1564: invokevirtual fe : (Ljava/lang/String;Ljava/lang/String;)Lf/nJ0;
        /*    */     //   1567: invokevirtual Kw : ()Lf/nJ0;
        /*    */     //   1570: pop
        /*    */     //   1571: aload_1
        /*    */     //   1572: getstatic f/Te.EE : Lf/Te;
        /*    */     //   1575: dup
        /*    */     //   1576: astore #11
        /*    */     //   1578: if_acmpne -> 1605
        /*    */     //   1581: aload #8
        /*    */     //   1583: invokestatic getInstance : ()Ljava/text/NumberFormat;
        /*    */     //   1586: aload #10
        /*    */     //   1588: getfield gh : S
        /*    */     //   1591: i2l
        /*    */     //   1592: invokevirtual format : (J)Ljava/lang/String;
        /*    */     //   1595: ldc_w 'cell'
        /*    */     //   1598: invokevirtual fe : (Ljava/lang/String;Ljava/lang/String;)Lf/nJ0;
        /*    */     //   1601: invokevirtual Kw : ()Lf/nJ0;
        /*    */     //   1604: pop
        /*    */     //   1605: aload_1
        /*    */     //   1606: aload #8
        /*    */     //   1608: new f/dQ
        /*    */     //   1611: dup
        /*    */     //   1612: dup
        /*    */     //   1613: astore #12
        /*    */     //   1615: aload_0
        /*    */     //   1616: aload #10
        /*    */     //   1618: aload #12
        /*    */     //   1620: dup
        /*    */     //   1621: dup
        /*    */     //   1622: ldc_w '$'
        /*    */     //   1625: invokestatic df : (Ljava/lang/String;)Ljava/lang/StringBuilder;
        /*    */     //   1628: invokestatic getInstance : ()Ljava/text/NumberFormat;
        /*    */     //   1631: aload #10
        /*    */     //   1633: getfield B90 : I
        /*    */     //   1636: i2l
        /*    */     //   1637: invokevirtual format : (J)Ljava/lang/String;
        /*    */     //   1640: invokevirtual append : (Ljava/lang/String;)Ljava/lang/StringBuilder;
        /*    */     //   1643: invokevirtual toString : ()Ljava/lang/String;
        /*    */     //   1646: astore #13
        /*    */     //   1648: invokespecial <init> : ()V
        /*    */     //   1651: aload #13
        /*    */     //   1653: invokevirtual E1 : (Ljava/lang/String;)V
        /*    */     //   1656: ldc_w 'cell'
        /*    */     //   1659: invokevirtual Xu : (Ljava/lang/String;)V
        /*    */     //   1662: aload #12
        /*    */     //   1664: <illegal opcode> yb0 : (Lf/A;Lf/fv0;Lf/dQ;)Lf/tC0;
        /*    */     //   1669: invokevirtual lPt3 : (Lf/tC0;)V
        /*    */     //   1672: invokevirtual S7 : (Ljava/lang/Object;)Lf/nJ0;
        /*    */     //   1675: invokevirtual Kw : ()Lf/nJ0;
        /*    */     //   1678: pop
        /*    */     //   1679: getstatic f/Te.Qu : Lf/Te;
        /*    */     //   1682: if_acmpne -> 1772
        /*    */     //   1685: aload #7
        /*    */     //   1687: ifnull -> 1772
        /*    */     //   1690: aload #7
        /*    */     //   1692: aload #10
        /*    */     //   1694: getfield bn : S
        /*    */     //   1697: invokevirtual gS : (S)Z
        /*    */     //   1700: ifeq -> 1772
        /*    */     //   1703: aload #10
        /*    */     //   1705: getfield B90 : I
        /*    */     //   1708: i2d
        /*    */     //   1709: aload #7
        /*    */     //   1711: aload #10
        /*    */     //   1713: getfield bn : S
        /*    */     //   1716: invokevirtual X60 : (S)I
        /*    */     //   1719: i2d
        /*    */     //   1720: ldc2_w 1.5
        /*    */     //   1723: dmul
        /*    */     //   1724: dcmpl
        /*    */     //   1725: ifle -> 1739
        /*    */     //   1728: aload #12
        /*    */     //   1730: ldc_w 'cell-danger'
        /*    */     //   1733: invokevirtual Xu : (Ljava/lang/String;)V
        /*    */     //   1736: goto -> 1772
        /*    */     //   1739: aload #10
        /*    */     //   1741: getfield B90 : I
        /*    */     //   1744: i2d
        /*    */     //   1745: aload #7
        /*    */     //   1747: aload #10
        /*    */     //   1749: getfield bn : S
        /*    */     //   1752: invokevirtual X60 : (S)I
        /*    */     //   1755: i2d
        /*    */     //   1756: ldc2_w 1.25
        /*    */     //   1759: dmul
        /*    */     //   1760: dcmpl
        /*    */     //   1761: ifle -> 1772
        /*    */     //   1764: aload #12
        /*    */     //   1766: ldc_w 'cell-warn'
        /*    */     //   1769: invokevirtual Xu : (Ljava/lang/String;)V
        /*    */     //   1772: aload_1
        /*    */     //   1773: aload #11
        /*    */     //   1775: if_acmpne -> 1839
        /*    */     //   1778: aload #8
        /*    */     //   1780: new f/dQ
        /*    */     //   1783: dup
        /*    */     //   1784: dup2
        /*    */     //   1785: ldc_w '$'
        /*    */     //   1788: invokestatic df : (Ljava/lang/String;)Ljava/lang/StringBuilder;
        /*    */     //   1791: invokestatic getInstance : ()Ljava/text/NumberFormat;
        /*    */     //   1794: aload #10
        /*    */     //   1796: getfield B90 : I
        /*    */     //   1799: i2l
        /*    */     //   1800: aload #10
        /*    */     //   1802: getfield CoM9 : S
        /*    */     //   1805: i2l
        /*    */     //   1806: lmul
        /*    */     //   1807: invokevirtual format : (J)Ljava/lang/String;
        /*    */     //   1810: invokevirtual append : (Ljava/lang/String;)Ljava/lang/StringBuilder;
        /*    */     //   1813: invokevirtual toString : ()Ljava/lang/String;
        /*    */     //   1816: astore #12
        /*    */     //   1818: invokespecial <init> : ()V
        /*    */     //   1821: aload #12
        /*    */     //   1823: invokevirtual E1 : (Ljava/lang/String;)V
        /*    */     //   1826: ldc_w 'cell'
        /*    */     //   1829: invokevirtual Xu : (Ljava/lang/String;)V
        /*    */     //   1832: invokevirtual S7 : (Ljava/lang/Object;)Lf/nJ0;
        /*    */     //   1835: invokevirtual Kw : ()Lf/nJ0;
        /*    */     //   1838: pop
        /*    */     //   1839: aload_1
        /*    */     //   1840: aload #11
        /*    */     //   1842: new java/util/Date
        /*    */     //   1845: dup
        /*    */     //   1846: astore #11
        /*    */     //   1848: aload #10
        /*    */     //   1850: aload #11
        /*    */     //   1852: invokespecial <init> : ()V
        /*    */     //   1855: getfield vA : I
        /*    */     //   1858: i2l
        /*    */     //   1859: ldc2_w 1000
        /*    */     //   1862: lmul
        /*    */     //   1863: invokevirtual setTime : (J)V
        /*    */     //   1866: new java/util/Date
        /*    */     //   1869: dup
        /*    */     //   1870: astore #12
        /*    */     //   1872: aload #10
        /*    */     //   1874: aload #12
        /*    */     //   1876: invokespecial <init> : ()V
        /*    */     //   1879: getfield Lg0 : I
        /*    */     //   1882: i2l
        /*    */     //   1883: ldc2_w 1000
        /*    */     //   1886: lmul
        /*    */     //   1887: invokevirtual setTime : (J)V
        /*    */     //   1890: if_acmpne -> 2154
        /*    */     //   1893: aload #10
        /*    */     //   1895: new f/Un
        /*    */     //   1898: astore #11
        /*    */     //   1900: getfield kF0 : B
        /*    */     //   1903: ifne -> 1912
        /*    */     //   1906: sipush #8022
        /*    */     //   1909: goto -> 1915
        /*    */     //   1912: sipush #8023
        /*    */     //   1915: invokestatic OH0 : (I)Ljava/lang/String;
        /*    */     //   1918: astore #13
        /*    */     //   1920: aload #10
        /*    */     //   1922: aload #8
        /*    */     //   1924: aload #11
        /*    */     //   1926: dup
        /*    */     //   1927: dup2
        /*    */     //   1928: dup2
        /*    */     //   1929: aload #13
        /*    */     //   1931: invokespecial <init> : (Ljava/lang/String;)V
        /*    */     //   1934: ldc_w 'cell'
        /*    */     //   1937: invokevirtual Xu : (Ljava/lang/String;)V
        /*    */     //   1940: getstatic f/A.Ds0 : Ljava/text/SimpleDateFormat;
        /*    */     //   1943: aload #12
        /*    */     //   1945: invokevirtual format : (Ljava/util/Date;)Ljava/lang/String;
        /*    */     //   1948: putfield z4 : Ljava/lang/Object;
        /*    */     //   1951: invokevirtual zn : ()V
        /*    */     //   1954: sipush #150
        /*    */     //   1957: putfield jl : I
        /*    */     //   1960: invokevirtual S7 : (Ljava/lang/Object;)Lf/nJ0;
        /*    */     //   1963: invokevirtual Kw : ()Lf/nJ0;
        /*    */     //   1966: pop
        /*    */     //   1967: new f/Un
        /*    */     //   1970: astore #11
        /*    */     //   1972: getfield kF0 : B
        /*    */     //   1975: ifne -> 1984
        /*    */     //   1978: sipush #8020
        /*    */     //   1981: goto -> 1987
        /*    */     //   1984: sipush #8024
        /*    */     //   1987: invokestatic OH0 : (I)Ljava/lang/String;
        /*    */     //   1990: astore #12
        /*    */     //   1992: aload #10
        /*    */     //   1994: aload #11
        /*    */     //   1996: aload #12
        /*    */     //   1998: invokespecial <init> : (Ljava/lang/String;)V
        /*    */     //   2001: getfield kF0 : B
        /*    */     //   2004: ifne -> 2013
        /*    */     //   2007: iconst_1
        /*    */     //   2008: istore #12
        /*    */     //   2010: goto -> 2016
        /*    */     //   2013: iconst_0
        /*    */     //   2014: istore #12
        /*    */     //   2016: aload #10
        /*    */     //   2018: aload #8
        /*    */     //   2020: aload #11
        /*    */     //   2022: dup
        /*    */     //   2023: aload_0
        /*    */     //   2024: aload #10
        /*    */     //   2026: aload #11
        /*    */     //   2028: dup
        /*    */     //   2029: dup
        /*    */     //   2030: iload #12
        /*    */     //   2032: invokevirtual sk0 : (Z)V
        /*    */     //   2035: getstatic f/et.Wi0 : Lf/et;
        /*    */     //   2038: dup
        /*    */     //   2039: astore #11
        /*    */     //   2041: invokevirtual C70 : (Lf/et;)V
        /*    */     //   2044: ldc_w 'cell-button'
        /*    */     //   2047: invokevirtual Xu : (Ljava/lang/String;)V
        /*    */     //   2050: <illegal opcode> run : (Lf/A;Lf/fv0;)Ljava/lang/Runnable;
        /*    */     //   2055: invokevirtual tW : (Ljava/lang/Runnable;)V
        /*    */     //   2058: invokevirtual S7 : (Ljava/lang/Object;)Lf/nJ0;
        /*    */     //   2061: invokevirtual Kw : ()Lf/nJ0;
        /*    */     //   2064: pop
        /*    */     //   2065: new f/Un
        /*    */     //   2068: dup
        /*    */     //   2069: astore #12
        /*    */     //   2071: sipush #8021
        /*    */     //   2074: invokestatic OH0 : (I)Ljava/lang/String;
        /*    */     //   2077: invokespecial <init> : (Ljava/lang/String;)V
        /*    */     //   2080: getfield kF0 : B
        /*    */     //   2083: iconst_1
        /*    */     //   2084: if_icmpeq -> 2104
        /*    */     //   2087: aload #10
        /*    */     //   2089: getfield CoM9 : S
        /*    */     //   2092: ifle -> 2098
        /*    */     //   2095: goto -> 2104
        /*    */     //   2098: iconst_0
        /*    */     //   2099: istore #13
        /*    */     //   2101: goto -> 2107
        /*    */     //   2104: iconst_1
        /*    */     //   2105: istore #13
        /*    */     //   2107: aload #8
        /*    */     //   2109: aload #12
        /*    */     //   2111: dup
        /*    */     //   2112: aload_0
        /*    */     //   2113: aload #10
        /*    */     //   2115: aload #12
        /*    */     //   2117: dup
        /*    */     //   2118: aload #11
        /*    */     //   2120: aload #12
        /*    */     //   2122: iload #13
        /*    */     //   2124: invokevirtual sk0 : (Z)V
        /*    */     //   2127: invokevirtual C70 : (Lf/et;)V
        /*    */     //   2130: ldc_w 'cell-button'
        /*    */     //   2133: invokevirtual Xu : (Ljava/lang/String;)V
        /*    */     //   2136: <illegal opcode> run : (Lf/A;Lf/fv0;)Ljava/lang/Runnable;
        /*    */     //   2141: invokevirtual tW : (Ljava/lang/Runnable;)V
        /*    */     //   2144: invokevirtual S7 : (Ljava/lang/Object;)Lf/nJ0;
        /*    */     //   2147: invokevirtual Kw : ()Lf/nJ0;
        /*    */     //   2150: pop
        /*    */     //   2151: goto -> 2603
        /*    */     //   2154: aload #10
        /*    */     //   2156: dup
        /*    */     //   2157: invokestatic currentTimeMillis : ()J
        /*    */     //   2160: ldc2_w 1000
        /*    */     //   2163: ldiv
        /*    */     //   2164: l2i
        /*    */     //   2165: aload #10
        /*    */     //   2167: getfield vA : I
        /*    */     //   2170: isub
        /*    */     //   2171: iconst_0
        /*    */     //   2172: invokestatic da0 : (IZ)Ljava/lang/String;
        /*    */     //   2175: astore #13
        /*    */     //   2177: getfield Lg0 : I
        /*    */     //   2180: i2l
        /*    */     //   2181: invokestatic currentTimeMillis : ()J
        /*    */     //   2184: ldc2_w 1000
        /*    */     //   2187: ldiv
        /*    */     //   2188: lsub
        /*    */     //   2189: l2i
        /*    */     //   2190: istore #14
        /*    */     //   2192: getfield Lg0 : I
        /*    */     //   2195: aload #10
        /*    */     //   2197: getfield vA : I
        /*    */     //   2200: isub
        /*    */     //   2201: istore #15
        /*    */     //   2203: invokestatic XU : ()Z
        /*    */     //   2206: ifeq -> 2449
        /*    */     //   2209: new f/Xq0
        /*    */     //   2212: dup
        /*    */     //   2213: dup
        /*    */     //   2214: astore #16
        /*    */     //   2216: aload #13
        /*    */     //   2218: aload #16
        /*    */     //   2220: iload #14
        /*    */     //   2222: aload #16
        /*    */     //   2224: invokespecial <init> : ()V
        /*    */     //   2227: i2f
        /*    */     //   2228: iload #15
        /*    */     //   2230: i2f
        /*    */     //   2231: fdiv
        /*    */     //   2232: invokevirtual Nu : (F)V
        /*    */     //   2235: invokevirtual HC : (Ljava/lang/CharSequence;)V
        /*    */     //   2238: getfield Yp : F
        /*    */     //   2241: dup
        /*    */     //   2242: fstore #13
        /*    */     //   2244: ldc_w 0.8
        /*    */     //   2247: fcmpl
        /*    */     //   2248: ifle -> 2262
        /*    */     //   2251: aload #16
        /*    */     //   2253: ldc_w 'progressbar-100'
        /*    */     //   2256: invokevirtual Xu : (Ljava/lang/String;)V
        /*    */     //   2259: goto -> 2330
        /*    */     //   2262: fload #13
        /*    */     //   2264: ldc_w 0.6
        /*    */     //   2267: fcmpl
        /*    */     //   2268: ifle -> 2282
        /*    */     //   2271: aload #16
        /*    */     //   2273: ldc_w 'progressbar-80'
        /*    */     //   2276: invokevirtual Xu : (Ljava/lang/String;)V
        /*    */     //   2279: goto -> 2330
        /*    */     //   2282: fload #13
        /*    */     //   2284: ldc_w 0.4
        /*    */     //   2287: fcmpl
        /*    */     //   2288: ifle -> 2302
        /*    */     //   2291: aload #16
        /*    */     //   2293: ldc_w 'progressbar-60'
        /*    */     //   2296: invokevirtual Xu : (Ljava/lang/String;)V
        /*    */     //   2299: goto -> 2330
        /*    */     //   2302: fload #13
        /*    */     //   2304: ldc_w 0.2
        /*    */     //   2307: fcmpl
        /*    */     //   2308: ifle -> 2322
        /*    */     //   2311: aload #16
        /*    */     //   2313: ldc_w 'progressbar-40'
        /*    */     //   2316: invokevirtual Xu : (Ljava/lang/String;)V
        /*    */     //   2319: goto -> 2330
        /*    */     //   2322: aload #16
        /*    */     //   2324: ldc_w 'progressbar-20'
        /*    */     //   2327: invokevirtual Xu : (Ljava/lang/String;)V
        /*    */     //   2330: aload #8
        /*    */     //   2332: aload #16
        /*    */     //   2334: dup
        /*    */     //   2335: dup
        /*    */     //   2336: dup2
        /*    */     //   2337: iconst_1
        /*    */     //   2338: putfield zI0 : Z
        /*    */     //   2341: sipush #150
        /*    */     //   2344: putfield jl : I
        /*    */     //   2347: new f/YA0
        /*    */     //   2350: dup
        /*    */     //   2351: dup
        /*    */     //   2352: invokespecial <init> : ()V
        /*    */     //   2355: getfield Dv0 : Lf/SA;
        /*    */     //   2358: dup
        /*    */     //   2359: dup2
        /*    */     //   2360: astore #13
        /*    */     //   2362: fconst_1
        /*    */     //   2363: invokevirtual Dl0 : (F)V
        /*    */     //   2366: sipush #8037
        /*    */     //   2369: invokevirtual mv0 : (I)Lf/nJ0;
        /*    */     //   2372: invokevirtual ti0 : ()Lf/nJ0;
        /*    */     //   2375: ldc_w 8.0
        /*    */     //   2378: invokevirtual sg : (F)Lf/nJ0;
        /*    */     //   2381: pop
        /*    */     //   2382: getstatic f/A.Ds0 : Ljava/text/SimpleDateFormat;
        /*    */     //   2385: dup
        /*    */     //   2386: astore #14
        /*    */     //   2388: aload #12
        /*    */     //   2390: aload #13
        /*    */     //   2392: dup
        /*    */     //   2393: aload #14
        /*    */     //   2395: aload #11
        /*    */     //   2397: invokevirtual format : (Ljava/util/Date;)Ljava/lang/String;
        /*    */     //   2400: invokevirtual IR : (Ljava/lang/String;)Lf/nJ0;
        /*    */     //   2403: getfield Ox : Lf/ZP;
        /*    */     //   2406: invokevirtual wP : ()Lf/nJ0;
        /*    */     //   2409: pop
        /*    */     //   2410: sipush #8013
        /*    */     //   2413: invokevirtual mv0 : (I)Lf/nJ0;
        /*    */     //   2416: invokevirtual ti0 : ()Lf/nJ0;
        /*    */     //   2419: ldc_w 8.0
        /*    */     //   2422: invokevirtual sg : (F)Lf/nJ0;
        /*    */     //   2425: pop
        /*    */     //   2426: invokevirtual format : (Ljava/util/Date;)Ljava/lang/String;
        /*    */     //   2429: invokevirtual IR : (Ljava/lang/String;)Lf/nJ0;
        /*    */     //   2432: pop
        /*    */     //   2433: putfield z4 : Ljava/lang/Object;
        /*    */     //   2436: invokevirtual zn : ()V
        /*    */     //   2439: invokevirtual S7 : (Ljava/lang/Object;)Lf/nJ0;
        /*    */     //   2442: invokevirtual Kw : ()Lf/nJ0;
        /*    */     //   2445: pop
        /*    */     //   2446: goto -> 2551
        /*    */     //   2449: aload #8
        /*    */     //   2451: dup
        /*    */     //   2452: new f/Un
        /*    */     //   2455: dup
        /*    */     //   2456: dup2
        /*    */     //   2457: dup2
        /*    */     //   2458: aload #13
        /*    */     //   2460: invokespecial <init> : (Ljava/lang/String;)V
        /*    */     //   2463: ldc_w 'cell'
        /*    */     //   2466: invokevirtual Xu : (Ljava/lang/String;)V
        /*    */     //   2469: getstatic f/A.Ds0 : Ljava/text/SimpleDateFormat;
        /*    */     //   2472: dup
        /*    */     //   2473: astore #13
        /*    */     //   2475: aload #11
        /*    */     //   2477: invokevirtual format : (Ljava/util/Date;)Ljava/lang/String;
        /*    */     //   2480: putfield z4 : Ljava/lang/Object;
        /*    */     //   2483: invokevirtual zn : ()V
        /*    */     //   2486: sipush #150
        /*    */     //   2489: putfield jl : I
        /*    */     //   2492: invokevirtual S7 : (Ljava/lang/Object;)Lf/nJ0;
        /*    */     //   2495: invokevirtual Kw : ()Lf/nJ0;
        /*    */     //   2498: pop
        /*    */     //   2499: new f/Un
        /*    */     //   2502: dup
        /*    */     //   2503: dup
        /*    */     //   2504: dup2
        /*    */     //   2505: astore #11
        /*    */     //   2507: aload #13
        /*    */     //   2509: aload #12
        /*    */     //   2511: aload #11
        /*    */     //   2513: dup
        /*    */     //   2514: iload #14
        /*    */     //   2516: iconst_1
        /*    */     //   2517: invokestatic da0 : (IZ)Ljava/lang/String;
        /*    */     //   2520: invokespecial <init> : (Ljava/lang/String;)V
        /*    */     //   2523: ldc_w 'cell'
        /*    */     //   2526: invokevirtual Xu : (Ljava/lang/String;)V
        /*    */     //   2529: invokevirtual format : (Ljava/util/Date;)Ljava/lang/String;
        /*    */     //   2532: putfield z4 : Ljava/lang/Object;
        /*    */     //   2535: invokevirtual zn : ()V
        /*    */     //   2538: sipush #150
        /*    */     //   2541: putfield jl : I
        /*    */     //   2544: invokevirtual S7 : (Ljava/lang/Object;)Lf/nJ0;
        /*    */     //   2547: invokevirtual Kw : ()Lf/nJ0;
        /*    */     //   2550: pop
        /*    */     //   2551: aload #8
        /*    */     //   2553: new f/Un
        /*    */     //   2556: dup
        /*    */     //   2557: dup
        /*    */     //   2558: astore #11
        /*    */     //   2560: aload_0
        /*    */     //   2561: aload #10
        /*    */     //   2563: aload #11
        /*    */     //   2565: dup
        /*    */     //   2566: dup
        /*    */     //   2567: sipush #8014
        /*    */     //   2570: invokestatic OH0 : (I)Ljava/lang/String;
        /*    */     //   2573: invokespecial <init> : (Ljava/lang/String;)V
        /*    */     //   2576: ldc_w 'cell-button'
        /*    */     //   2579: invokevirtual Xu : (Ljava/lang/String;)V
        /*    */     //   2582: getstatic f/et.Wi0 : Lf/et;
        /*    */     //   2585: invokevirtual C70 : (Lf/et;)V
        /*    */     //   2588: <illegal opcode> run : (Lf/A;Lf/fv0;)Ljava/lang/Runnable;
        /*    */     //   2593: invokevirtual tW : (Ljava/lang/Runnable;)V
        /*    */     //   2596: invokevirtual S7 : (Ljava/lang/Object;)Lf/nJ0;
        /*    */     //   2599: invokevirtual Kw : ()Lf/nJ0;
        /*    */     //   2602: pop
        /*    */     //   2603: aload #8
        /*    */     //   2605: invokevirtual wP : ()Lf/nJ0;
        /*    */     //   2608: pop
        /*    */     //   2609: iinc #6, 1
        /*    */     //   2612: goto -> 282
        /*    */     //   2615: aload #4
        /*    */     //   2617: arraylength
        /*    */     //   2618: iconst_1
        /*    */     //   2619: if_icmpge -> 2658
        /*    */     //   2622: aload #8
        /*    */     //   2624: sipush #1655
        /*    */     //   2627: ldc_w 'cell'
        /*    */     //   2630: invokevirtual SB : (ILjava/lang/String;)Lf/nJ0;
        /*    */     //   2633: dup
        /*    */     //   2634: aload #8
        /*    */     //   2636: getfield Nb0 : I
        /*    */     //   2639: invokestatic valueOf : (I)Ljava/lang/Integer;
        /*    */     //   2642: putfield ss : Ljava/lang/Integer;
        /*    */     //   2645: invokevirtual R7 : ()Lf/nJ0;
        /*    */     //   2648: invokevirtual Kw : ()Lf/nJ0;
        /*    */     //   2651: getfield Ox : Lf/ZP;
        /*    */     //   2654: invokevirtual wP : ()Lf/nJ0;
        /*    */     //   2657: pop
        /*    */     //   2658: aload_0
        /*    */     //   2659: aload #8
        /*    */     //   2661: aload #9
        /*    */     //   2663: invokevirtual S7 : (Ljava/lang/Object;)Lf/nJ0;
        /*    */     //   2666: dup
        /*    */     //   2667: aload #8
        /*    */     //   2669: getfield Nb0 : I
        /*    */     //   2672: invokestatic valueOf : (I)Ljava/lang/Integer;
        /*    */     //   2675: putfield ss : Ljava/lang/Integer;
        /*    */     //   2678: ldc_w 30.0
        /*    */     //   2681: invokevirtual Je0 : (F)Lf/nJ0;
        /*    */     //   2684: invokevirtual R7 : ()Lf/nJ0;
        /*    */     //   2687: invokevirtual Kw : ()Lf/nJ0;
        /*    */     //   2690: getfield Ox : Lf/ZP;
        /*    */     //   2693: invokevirtual wP : ()Lf/nJ0;
        /*    */     //   2696: pop
        /*    */     //   2697: getfield YD0 : [Lf/bh;
        /*    */     //   2700: aload_1
        /*    */     //   2701: getfield HC0 : B
        /*    */     //   2704: aaload
        /*    */     //   2705: dup
        /*    */     //   2706: astore #4
        /*    */     //   2708: getfield oL0 : Lf/JA0;
        /*    */     //   2711: dup
        /*    */     //   2712: astore #5
        /*    */     //   2714: ifnull -> 2728
        /*    */     //   2717: aload #5
        /*    */     //   2719: aload #4
        /*    */     //   2721: getfield Ag : S
        /*    */     //   2724: iload_3
        /*    */     //   2725: invokevirtual r1 : (II)V
        /*    */     //   2728: aload_0
        /*    */     //   2729: dup
        /*    */     //   2730: aload #8
        /*    */     //   2732: new f/JG0
        /*    */     //   2735: dup
        /*    */     //   2736: invokespecial <init> : ()V
        /*    */     //   2739: invokevirtual S7 : (Ljava/lang/Object;)Lf/nJ0;
        /*    */     //   2742: fconst_0
        /*    */     //   2743: invokevirtual Je0 : (F)Lf/nJ0;
        /*    */     //   2746: dup
        /*    */     //   2747: dup
        /*    */     //   2748: aload #8
        /*    */     //   2750: getfield Nb0 : I
        /*    */     //   2753: invokestatic valueOf : (I)Ljava/lang/Integer;
        /*    */     //   2756: putfield ss : Ljava/lang/Integer;
        /*    */     //   2759: invokevirtual kp0 : ()Lf/nJ0;
        /*    */     //   2762: pop
        /*    */     //   2763: invokevirtual i40 : ()Lf/nJ0;
        /*    */     //   2766: pop
        /*    */     //   2767: getfield YD0 : [Lf/bh;
        /*    */     //   2770: aload_1
        /*    */     //   2771: getfield HC0 : B
        /*    */     //   2774: aaload
        /*    */     //   2775: getfield v20 : Lf/nJ0;
        /*    */     //   2778: aload_2
        /*    */     //   2779: invokevirtual cd : (Lf/JG0;)Lf/nJ0;
        /*    */     //   2782: pop
        /*    */     //   2783: getfield YD0 : [Lf/bh;
        /*    */     //   2786: aload_1
        /*    */     //   2787: getfield HC0 : B
        /*    */     //   2790: aaload
        /*    */     //   2791: invokevirtual p3 : ()Z
        /*    */     //   2794: ifeq -> 2829
        /*    */     //   2797: aload_0
        /*    */     //   2798: getfield YD0 : [Lf/bh;
        /*    */     //   2801: aload_1
        /*    */     //   2802: getfield HC0 : B
        /*    */     //   2805: aaload
        /*    */     //   2806: getfield mo0 : Lf/of;
        /*    */     //   2809: invokevirtual p3 : ()Z
        /*    */     //   2812: ifne -> 2829
        /*    */     //   2815: aload_0
        /*    */     //   2816: getfield YD0 : [Lf/bh;
        /*    */     //   2819: aload_1
        /*    */     //   2820: getfield HC0 : B
        /*    */     //   2823: aaload
        /*    */     //   2824: iconst_0
        /*    */     //   2825: iconst_0
        /*    */     //   2826: invokevirtual x10 : (II)V
        /*    */     //   2829: return
        /*    */     // Line number table:
        /*    */     //   Java source line number -> byte code offset
        /*    */     //   #1	-> 5
        /*    */     //   #2	-> 8
        /*    */     //   #3	-> 37
        /*    */     //   #4	-> 41
        /*    */     //   #5	-> 263
        /*    */     //   #6	-> 271
        /*    */     //   #7	-> 297
        /*    */     //   #8	-> 303
        /*    */     //   #9	-> 325
        /*    */     //   #10	-> 329
        /*    */     //   #11	-> 333
        /*    */     //   #12	-> 336
        /*    */     //   #13	-> 350
        /*    */     //   #14	-> 357
        /*    */     //   #15	-> 363
        /*    */     //   #16	-> 367
        /*    */     //   #17	-> 371
        /*    */     //   #18	-> 378
        /*    */     //   #19	-> 415
        /*    */     //   #20	-> 426
        /*    */     //   #21	-> 436
        /*    */     //   #22	-> 448
        /*    */     //   #23	-> 458
        /*    */     //   #24	-> 465
        /*    */     //   #25	-> 521
        /*    */     //   #26	-> 535
        /*    */     //   #27	-> 551
        /*    */     //   #28	-> 554
        /*    */     //   #29	-> 607
        /*    */     //   #30	-> 623
        /*    */     //   #31	-> 642
        /*    */     //   #32	-> 663
        /*    */     //   #33	-> 675
        /*    */     //   #34	-> 678
        /*    */     //   #35	-> 681
        /*    */     //   #36	-> 698
        /*    */     //   #37	-> 701
        /*    */     //   #38	-> 712
        /*    */     //   #39	-> 715
        /*    */     //   #40	-> 718
        /*    */     //   #41	-> 728
        /*    */     //   #42	-> 737
        /*    */     //   #43	-> 756
        /*    */     //   #44	-> 764
        /*    */     //   #45	-> 767
        /*    */     //   #46	-> 770
        /*    */     //   #47	-> 810
        /*    */     //   #48	-> 815
        /*    */     //   #49	-> 823
        /*    */     //   #50	-> 828
        /*    */     //   #51	-> 934
        /*    */     //   #52	-> 939
        /*    */     //   #53	-> 942
        /*    */     //   #54	-> 959
        /*    */     //   #55	-> 963
        /*    */     //   #56	-> 967
        /*    */     //   #57	-> 973
        /*    */     //   #58	-> 978
        /*    */     //   #59	-> 983
        /*    */     //   #60	-> 990
        /*    */     //   #61	-> 993
        /*    */     //   #62	-> 997
        /*    */     //   #63	-> 1000
        /*    */     //   #64	-> 1017
        /*    */     //   #65	-> 1021
        /*    */     //   #66	-> 1028
        /*    */     //   #67	-> 1095
        /*    */     //   #68	-> 1103
        /*    */     //   #69	-> 1106
        /*    */     //   #70	-> 1114
        /*    */     //   #71	-> 1125
        /*    */     //   #72	-> 1135
        /*    */     //   #73	-> 1143
        /*    */     //   #74	-> 1146
        /*    */     //   #75	-> 1152
        /*    */     //   #76	-> 1161
        /*    */     //   #77	-> 1166
        /*    */     //   #78	-> 1174
        /*    */     //   #79	-> 1193
        /*    */     //   #80	-> 1201
        /*    */     //   #81	-> 1353
        /*    */     //   #82	-> 1365
        /*    */     //   #83	-> 1399
        /*    */     //   #84	-> 1406
        /*    */     //   #85	-> 1414
        /*    */     //   #86	-> 1419
        /*    */     //   #87	-> 1424
        /*    */     //   #88	-> 1432
        /*    */     //   #89	-> 1468
        /*    */     //   #90	-> 1474
        /*    */     //   #91	-> 1486
        /*    */     //   #92	-> 1493
        /*    */     //   #93	-> 1496
        /*    */     //   #94	-> 1502
        /*    */     //   #95	-> 1505
        /*    */     //   #96	-> 1511
        /*    */     //   #97	-> 1520
        /*    */     //   #98	-> 1533
        /*    */     //   #99	-> 1554
        /*    */     //   #100	-> 1558
        /*    */     //   #101	-> 1588
        /*    */     //   #102	-> 1592
        /*    */     //   #103	-> 1622
        /*    */     //   #104	-> 1628
        /*    */     //   #105	-> 1633
        /*    */     //   #106	-> 1637
        /*    */     //   #107	-> 1648
        /*    */     //   #108	-> 1656
        /*    */     //   #109	-> 1694
        /*    */     //   #110	-> 1697
        /*    */     //   #111	-> 1705
        /*    */     //   #112	-> 1713
        /*    */     //   #113	-> 1716
        /*    */     //   #114	-> 1741
        /*    */     //   #115	-> 1749
        /*    */     //   #116	-> 1752
        /*    */     //   #117	-> 1785
        /*    */     //   #118	-> 1791
        /*    */     //   #119	-> 1796
        /*    */     //   #120	-> 1802
        /*    */     //   #121	-> 1807
        /*    */     //   #122	-> 1818
        /*    */     //   #123	-> 1826
        /*    */     //   #124	-> 1855
        /*    */     //   #125	-> 1863
        /*    */     //   #126	-> 1879
        /*    */     //   #127	-> 1887
        /*    */     //   #128	-> 1900
        /*    */     //   #129	-> 1915
        /*    */     //   #130	-> 1948
        /*    */     //   #131	-> 1957
        /*    */     //   #132	-> 1960
        /*    */     //   #133	-> 1972
        /*    */     //   #134	-> 1987
        /*    */     //   #135	-> 2001
        /*    */     //   #136	-> 2032
        /*    */     //   #137	-> 2080
        /*    */     //   #138	-> 2089
        /*    */     //   #139	-> 2124
        /*    */     //   #140	-> 2167
        /*    */     //   #141	-> 2172
        /*    */     //   #142	-> 2177
        /*    */     //   #143	-> 2181
        /*    */     //   #144	-> 2192
        /*    */     //   #145	-> 2197
        /*    */     //   #146	-> 2203
        /*    */     //   #147	-> 2235
        /*    */     //   #148	-> 2238
        /*    */     //   #149	-> 2253
        /*    */     //   #150	-> 2338
        /*    */     //   #151	-> 2344
        /*    */     //   #152	-> 2347
        /*    */     //   #153	-> 2403
        /*    */     //   #154	-> 2413
        /*    */     //   #155	-> 2433
        /*    */     //   #156	-> 2439
        /*    */     //   #157	-> 2480
        /*    */     //   #158	-> 2489
        /*    */     //   #159	-> 2492
        /*    */     //   #160	-> 2532
        /*    */     //   #161	-> 2541
        /*    */     //   #162	-> 2544
        /*    */     //   #163	-> 2636
        /*    */     //   #164	-> 2639
        /*    */     //   #165	-> 2642
        /*    */     //   #166	-> 2645
        /*    */     //   #167	-> 2651
        /*    */     //   #168	-> 2663
        /*    */     //   #169	-> 2669
        /*    */     //   #170	-> 2672
        /*    */     //   #171	-> 2675
        /*    */     //   #172	-> 2681
        /*    */     //   #173	-> 2690
        /*    */     //   #174	-> 2697
        /*    */     //   #175	-> 2701
        /*    */     //   #176	-> 2704
        /*    */     //   #177	-> 2708
        /*    */     //   #178	-> 2721
        /*    */     //   #179	-> 2725
        /*    */     //   #180	-> 2750
        /*    */     //   #181	-> 2753
        /*    */     //   #182	-> 2756
        /*    */     //   #183	-> 2759
        /*    */     //   #184	-> 2767
        /*    */     //   #185	-> 2771
        /*    */     //   #186	-> 2774
        /*    */     //   #187	-> 2775
        /*    */     //   #188	-> 2779
        /*    */     //   #189	-> 2783
        /*    */     //   #190	-> 2787
        /*    */     //   #191	-> 2790
        /*    */     //   #192	-> 2802
        /*    */     //   #193	-> 2805
        /*    */     //   #194	-> 2806
        /*    */     //   #195	-> 2809
        /*    */     //   #196	-> 2820
        /*    */     //   #197	-> 2823 }
        /*  4 */
        private void PI0 (fv0 paramfv0){
            if (!this.zk) {
                km.u4.Pq(Ml0.OH0(8029));
            } else {
                int[] arrayOfInt;
                (arrayOfInt = new int[1])[0] = paramfv0.y60;
                km.u4.e20
/*  5 */.W3(new Pt(this));
            }
        }
        public static void Qd0 (fv0 paramfv0, LPT3 paramLPT3){
            this(paramfv0, paramLPT3, paramfv0.nj0);
            Th0 th0;
            JG0 jG0;
            A a;
            /*  6 */
            if ((jG0 = (a = pA.Dg0.QI0).z8) == null) {
                a
                        /*  7 */.z8 = th0;
            } else {
                jG0
/*  8 */.ra0();
                a.z8 = th0;
            }
            a
/*  9 */.si(th0, a.Ub());
        }
        private void Wp (ey paramey){
            j40 j40 = paramey.t70;
            pA.Dg0.u30(e9(), this);
        }
        public static void o7 (fv0 paramfv0){
            UB0.LL0.Zq(B40.df("https://manage.pokemmo.com/auctions/").append(paramfv0.y60).toString());
        }
        public static void pb (fv0 paramfv0){
            bF.wG0(paramfv0.y60 + "");
            js.vu0.Pu(-1, "Auction id copied to clipboard");
        }
        public static void Ac (Te paramTe,int paramInt1, int paramInt2, short paramShort){
            km.u4.e20.W3(new cJ(paramTe, paramInt1, paramInt2, paramShort));
        }
        public static void If (Calendar paramCalendar, SA paramSA, iv paramiv){ // Byte code:
            /*    */     //   0: aload_2
            /*    */     //   1: new java/lang/StringBuilder
            /*    */     //   4: dup
            /*    */     //   5: astore_3
            /*    */     //   6: invokespecial <init> : ()V
            /*    */     //   9: new java/lang/StringBuilder
            /*    */     //   12: dup
            /*    */     //   13: astore #4
            /*    */     //   15: invokespecial <init> : ()V
            /*    */     //   18: getfield sZ : [Lf/ya0;
            /*    */     //   21: dup
            /*    */     //   22: astore #5
            /*    */     //   24: arraylength
            /*    */     //   25: ifne -> 29
            /*    */     //   28: return
            /*    */     //   29: aload_3
            /*    */     //   30: aload #5
            /*    */     //   32: invokestatic stream : ([Ljava/lang/Object;)Ljava/util/stream/Stream;
            /*    */     //   35: aload #4
            /*    */     //   37: aload_3
            /*    */     //   38: <illegal opcode> accept : (Ljava/lang/StringBuilder;Ljava/lang/StringBuilder;)Ljava/util/function/Consumer;
            /*    */     //   43: invokeinterface forEach : (Ljava/util/function/Consumer;)V
            /*    */     //   48: invokevirtual length : ()I
            /*    */     //   51: ifne -> 62
            /*    */     //   54: aload_3
            /*    */     //   55: ldc_w '----'
            /*    */     //   58: invokevirtual append : (Ljava/lang/String;)Ljava/lang/StringBuilder;
            /*    */     //   61: pop
            /*    */     //   62: aload #4
            /*    */     //   64: invokevirtual length : ()I
            /*    */     //   67: ifne -> 79
            /*    */     //   70: aload #4
            /*    */     //   72: ldc_w '----'
            /*    */     //   75: invokevirtual append : (Ljava/lang/String;)Ljava/lang/StringBuilder;
            /*    */     //   78: pop
            /*    */     //   79: aload_1
            /*    */     //   80: dup
            /*    */     //   81: dup
            /*    */     //   82: aload_2
            /*    */     //   83: aload_1
            /*    */     //   84: aload #4
            /*    */     //   86: aload_1
            /*    */     //   87: aload_3
            /*    */     //   88: aload_0
            /*    */     //   89: aload_2
            /*    */     //   90: getfield Et0 : J
            /*    */     //   93: invokevirtual setTimeInMillis : (J)V
            /*    */     //   96: invokestatic getDateInstance : ()Ljava/text/DateFormat;
            /*    */     //   99: aload_0
            /*    */     //   100: invokevirtual getTime : ()Ljava/util/Date;
            /*    */     //   103: invokevirtual format : (Ljava/util/Date;)Ljava/lang/String;
            /*    */     //   106: astore_0
            /*    */     //   107: invokevirtual toString : ()Ljava/lang/String;
            /*    */     //   110: invokevirtual trim : ()Ljava/lang/String;
            /*    */     //   113: ldc_w 'cell'
            /*    */     //   116: invokevirtual fe : (Ljava/lang/String;Ljava/lang/String;)Lf/nJ0;
            /*    */     //   119: dup
            /*    */     //   120: ldc_w 250.0
            /*    */     //   123: fstore_1
            /*    */     //   124: new f/Ln
            /*    */     //   127: dup
            /*    */     //   128: fload_1
            /*    */     //   129: invokespecial <init> : (F)V
            /*    */     //   132: putfield Of0 : Lf/Ir;
            /*    */     //   135: invokevirtual kp0 : ()Lf/nJ0;
            /*    */     //   138: pop
            /*    */     //   139: invokevirtual toString : ()Ljava/lang/String;
            /*    */     //   142: invokevirtual trim : ()Ljava/lang/String;
            /*    */     //   145: ldc_w 'cell'
            /*    */     //   148: invokevirtual fe : (Ljava/lang/String;Ljava/lang/String;)Lf/nJ0;
            /*    */     //   151: pop
            /*    */     //   152: sipush #8074
            /*    */     //   155: istore_1
            /*    */     //   156: getfield Nc : Lf/QF;
            /*    */     //   159: getfield c40 : B
            /*    */     //   162: iload_1
            /*    */     //   163: iadd
            /*    */     //   164: ldc_w 'cell'
            /*    */     //   167: invokevirtual SB : (ILjava/lang/String;)Lf/nJ0;
            /*    */     //   170: invokevirtual kp0 : ()Lf/nJ0;
            /*    */     //   173: pop
            /*    */     //   174: aload_0
            /*    */     //   175: ldc_w 'cell'
            /*    */     //   178: invokevirtual fe : (Ljava/lang/String;Ljava/lang/String;)Lf/nJ0;
            /*    */     //   181: invokevirtual kp0 : ()Lf/nJ0;
            /*    */     //   184: pop
            /*    */     //   185: invokevirtual wP : ()Lf/nJ0;
            /*    */     //   188: ldc_w 3.0
            /*    */     //   191: invokevirtual fa0 : (F)Lf/nJ0;
            /*    */     //   194: pop
            /*    */     //   195: return
            /*    */     // Line number table:
            /*    */     //   Java source line number -> byte code offset
            /*    */     //   #1	-> 18
            /*    */     //   #2	-> 24
            /*    */     //   #3	-> 90
            /*    */     //   #4	-> 93
            /*    */     //   #5	-> 124
            /*    */     //   #6	-> 135
            /*    */     //   #7	-> 156
            /*    */     //   #8	-> 159
            /*    */     //   #9	-> 164 } public static void hv(StringBuilder paramStringBuilder1, StringBuilder paramStringBuilder2, ya0 paramya0) { // Byte code:
            /*    */     //   0: aload_2
            /*    */     //   1: getfield j8 : Lf/UD0;
            /*    */     //   4: dup
            /*    */     //   5: astore_3
            /*    */     //   6: ifnull -> 37
            /*    */     //   9: aload_2
            /*    */     //   10: aload_3
            /*    */     //   11: iconst_0
            /*    */     //   12: invokevirtual o60 : (Z)Ljava/lang/String;
            /*    */     //   15: astore_3
            /*    */     //   16: getfield Fe0 : Lf/LPT3;
            /*    */     //   19: ifnull -> 105
            /*    */     //   22: aload_2
            /*    */     //   23: aload_3
            /*    */     //   24: ldc_w ' + '
            /*    */     //   27: invokestatic vz : (Ljava/lang/String;Ljava/lang/String;)Ljava/lang/StringBuilder;
            /*    */     //   30: astore_3
            /*    */     //   31: getfield Fe0 : Lf/LPT3;
            /*    */     //   34: goto -> 70
            /*    */     //   37: aload_2
            /*    */     //   38: getfield Fe0 : Lf/LPT3;
            /*    */     //   41: ifnull -> 88
            /*    */     //   44: aload_2
            /*    */     //   45: new java/lang/StringBuilder
            /*    */     //   48: dup
            /*    */     //   49: aload_2
            /*    */     //   50: swap
            /*    */     //   51: invokespecial <init> : ()V
            /*    */     //   54: getfield DJ0 : I
            /*    */     //   57: invokevirtual append : (I)Ljava/lang/StringBuilder;
            /*    */     //   60: ldc_w 'x '
            /*    */     //   63: invokevirtual append : (Ljava/lang/String;)Ljava/lang/StringBuilder;
            /*    */     //   66: astore_3
            /*    */     //   67: getfield Fe0 : Lf/LPT3;
            /*    */     //   70: getfield Iu : I
            /*    */     //   73: aload_3
            /*    */     //   74: swap
            /*    */     //   75: invokestatic OH0 : (I)Ljava/lang/String;
            /*    */     //   78: invokevirtual append : (Ljava/lang/String;)Ljava/lang/StringBuilder;
            /*    */     //   81: invokevirtual toString : ()Ljava/lang/String;
            /*    */     //   84: astore_3
            /*    */     //   85: goto -> 105
            /*    */     //   88: ldc_w '$'
            /*    */     //   91: invokestatic df : (Ljava/lang/String;)Ljava/lang/StringBuilder;
            /*    */     //   94: aload_2
            /*    */     //   95: getfield DJ0 : I
            /*    */     //   98: invokevirtual append : (I)Ljava/lang/StringBuilder;
            /*    */     //   101: invokevirtual toString : ()Ljava/lang/String;
            /*    */     //   104: astore_3
            /*    */     //   105: aload_2
            /*    */     //   106: getfield p20 : Z
            /*    */     //   109: ifeq -> 127
            /*    */     //   112: aload_0
            /*    */     //   113: aload_3
            /*    */     //   114: invokevirtual append : (Ljava/lang/String;)Ljava/lang/StringBuilder;
            /*    */     //   117: ldc_w '\\n'
            /*    */     //   120: invokevirtual append : (Ljava/lang/String;)Ljava/lang/StringBuilder;
            /*    */     //   123: pop
            /*    */     //   124: goto -> 139
            /*    */     //   127: aload_1
            /*    */     //   128: aload_3
            /*    */     //   129: invokevirtual append : (Ljava/lang/String;)Ljava/lang/StringBuilder;
            /*    */     //   132: ldc_w '\\n'
            /*    */     //   135: invokevirtual append : (Ljava/lang/String;)Ljava/lang/StringBuilder;
            /*    */     //   138: pop
            /*    */     //   139: return
            /*    */     // Line number table:
            /*    */     //   Java source line number -> byte code offset
            /*    */     //   #1	-> 1
            /*    */     //   #2	-> 12
            /*    */     //   #3	-> 16
            /*    */     //   #4	-> 24
            /*    */     //   #5	-> 31
            /*    */     //   #6	-> 45
            /*    */     //   #7	-> 54
            /*    */     //   #8	-> 57
            /*    */     //   #9	-> 67
            /*    */     //   #10	-> 70
            /*    */     //   #11	-> 75
            /*    */     //   #12	-> 78
            /*    */     //   #13	-> 88
            /*    */     //   #14	-> 95
            /*    */     //   #15	-> 98
            /*    */     //   #16	-> 106
            /*  9 */     //   #17	-> 114 } public static boolean xe(iv paramiv) { return (paramiv.sZ.length > 0); } private void e80() { F7.Yo(JB0.n7(this.bk, km.u4.z2), this.bk); } private void Jf0() { if (this.bk.t70 != null) this.ii.Tm0(null);  T10(); } private void si(Te paramTe) { this(); YA0 yA0; float f; (new YA0()).Xu("/broker-table"); nJ0 nJ0 = (new YA0()).Dv0.RT.Xj0(1.0F).Xs0(); if (km.XU()) { f = 40.0F; } else { f = 36.0F; }  nJ0.fJ(f); SA sA = yA0.Dv0; if (km.XU()) sA.JP(1).Je0(46.0F);  JC(paramTe, yA0, true); (sA.SB(55, "label-info")).tf = Integer.valueOf(1); (sA.SB(55, "label-info")).ss = Integer.valueOf(sA.Nb0); sA.SB(55, "label-info").Xs0().i40().Kw(); (this.YD0[paramTe.HC0])
            /* 10 */       .v20
/* 11 */.cd(yA0);
            /* 12 */
            ((YA0) sA.Vs)
/* 13 */.MJ0();
        } private void tP () {
            boolean bool;
            Rc rc = JB0.CE0;
            BS bS;
            if ((bS = this.ii).hC0 > 0) {
                bool = true;
            } else {
                bool = false;
            }
            F7.Yo(JB0.Ww(bS, rc, bool), this.ii);
        }
        private void Wy0 () {
            if (this.ii.hC0 > 0) this.bk.zf(null);
            T10();
        }
        private void al () {
            if (this.sr.nv0() == 4) km.u4.e20.W3(new J4());
        }
        private void N60 (Te paramTe){
            byte b;
            if (this.sr.nv0() == (b = paramTe.HC0)) {
                this.YD0[b].VI0();
                mg(paramTe);
            }
        } public A(j40 paramj40, boolean paramBoolean){ // Byte code:
            /*    */     //   0: aload_0
            /*    */     //   1: iload_2
            /*    */     //   2: aload_0
            /*    */     //   3: dup
            /*    */     //   4: dup
            /*    */     //   5: dup2
            /*    */     //   6: invokestatic XU : ()Z
            /*    */     //   9: invokespecial <init> : (Z)V
            /*    */     //   12: iconst_0
            /*    */     //   13: putfield Ea : I
            /*    */     //   16: iconst_0
            /*    */     //   17: anewarray f/fv0
            /*    */     //   20: putfield uC0 : [Lf/fv0;
            /*    */     //   23: aconst_null
            /*    */     //   24: putfield dL : Lf/oo;
            /*    */     //   27: iconst_0
            /*    */     //   28: putfield i6 : Z
            /*    */     //   31: putfield zk : Z
            /*    */     //   34: new java/lang/StringBuilder
            /*    */     //   37: dup
            /*    */     //   38: astore_3
            /*    */     //   39: invokespecial <init> : ()V
            /*    */     //   42: invokestatic XU : ()Z
            /*    */     //   45: ifeq -> 56
            /*    */     //   48: ldc_w 'mobile-'
            /*    */     //   51: astore #4
            /*    */     //   53: goto -> 60
            /*    */     //   56: ldc ''
            /*    */     //   58: astore #4
            /*    */     //   60: aload_0
            /*    */     //   61: dup
            /*    */     //   62: dup
            /*    */     //   63: dup2
            /*    */     //   64: aload_3
            /*    */     //   65: aload #4
            /*    */     //   67: invokevirtual append : (Ljava/lang/String;)Ljava/lang/StringBuilder;
            /*    */     //   70: ldc_w 'broker-window'
            /*    */     //   73: invokevirtual append : (Ljava/lang/String;)Ljava/lang/StringBuilder;
            /*    */     //   76: invokevirtual toString : ()Ljava/lang/String;
            /*    */     //   79: invokevirtual Xu : (Ljava/lang/String;)V
            /*    */     //   82: sipush #8000
            /*    */     //   85: invokestatic OH0 : (I)Ljava/lang/String;
            /*    */     //   88: invokevirtual Lo : (Ljava/lang/String;)V
            /*    */     //   91: iconst_1
            /*    */     //   92: invokevirtual EP : (I)V
            /*    */     //   95: <illegal opcode> run : (Lf/A;)Ljava/lang/Runnable;
            /*    */     //   100: invokevirtual TG0 : (Ljava/lang/Runnable;)V
            /*    */     //   103: new f/Vq0
            /*    */     //   106: dup
            /*    */     //   107: aload_0
            /*    */     //   108: swap
            /*    */     //   109: dup
            /*    */     //   110: invokespecial <init> : ()V
            /*    */     //   113: putfield sr : Lf/Vq0;
            /*    */     //   116: iconst_0
            /*    */     //   117: invokevirtual T1 : (Z)V
            /*    */     //   120: getstatic f/Te.ZL0 : [Lf/Te;
            /*    */     //   123: dup
            /*    */     //   124: astore_3
            /*    */     //   125: aload_0
            /*    */     //   126: aload_3
            /*    */     //   127: aload_0
            /*    */     //   128: aload_3
            /*    */     //   129: arraylength
            /*    */     //   130: newarray byte
            /*    */     //   132: putfield E60 : [B
            /*    */     //   135: arraylength
            /*    */     //   136: anewarray f/bh
            /*    */     //   139: putfield YD0 : [Lf/bh;
            /*    */     //   142: arraylength
            /*    */     //   143: istore #4
            /*    */     //   145: iconst_0
            /*    */     //   146: istore #5
            /*    */     //   148: iload #5
            /*    */     //   150: iload #4
            /*    */     //   152: if_icmpge -> 188
            /*    */     //   155: aload_0
            /*    */     //   156: aload_3
            /*    */     //   157: iload #5
            /*    */     //   159: aaload
            /*    */     //   160: astore #6
            /*    */     //   162: getfield YD0 : [Lf/bh;
            /*    */     //   165: aload #6
            /*    */     //   167: invokevirtual Gr0 : ()B
            /*    */     //   170: new f/bh
            /*    */     //   173: dup
            /*    */     //   174: aload_0
            /*    */     //   175: aload #6
            /*    */     //   177: iload_2
            /*    */     //   178: invokespecial <init> : (Lf/A;Lf/Te;Z)V
            /*    */     //   181: aastore
            /*    */     //   182: iinc #5, 1
            /*    */     //   185: goto -> 148
            /*    */     //   188: aload_0
            /*    */     //   189: dup
            /*    */     //   190: invokevirtual sK0 : ()V
            /*    */     //   193: getstatic f/Te.QK0 : Lf/Te;
            /*    */     //   196: invokevirtual mg : (Lf/Te;)V
            /*    */     //   199: getstatic f/Te.ZL0 : [Lf/Te;
            /*    */     //   202: dup
            /*    */     //   203: astore_3
            /*    */     //   204: arraylength
            /*    */     //   205: istore #4
            /*    */     //   207: iconst_0
            /*    */     //   208: istore #5
            /*    */     //   210: iload #5
            /*    */     //   212: iload #4
            /*    */     //   214: if_icmpge -> 291
            /*    */     //   217: aload_3
            /*    */     //   218: iload #5
            /*    */     //   220: aaload
            /*    */     //   221: dup
            /*    */     //   222: astore #6
            /*    */     //   224: invokevirtual Gr0 : ()B
            /*    */     //   227: sipush #8001
            /*    */     //   230: iadd
            /*    */     //   231: invokestatic OH0 : (I)Ljava/lang/String;
            /*    */     //   234: astore #7
            /*    */     //   236: invokestatic XU : ()Z
            /*    */     //   239: ifeq -> 255
            /*    */     //   242: aload #7
            /*    */     //   244: ldc_w ' '
            /*    */     //   247: ldc_w '\\n'
            /*    */     //   250: invokevirtual replaceAll : (Ljava/lang/String;Ljava/lang/String;)Ljava/lang/String;
            /*    */     //   253: astore #7
            /*    */     //   255: aload_0
            /*    */     //   256: getfield sr : Lf/Vq0;
            /*    */     //   259: aload_0
            /*    */     //   260: getfield YD0 : [Lf/bh;
            /*    */     //   263: aload #6
            /*    */     //   265: invokevirtual Gr0 : ()B
            /*    */     //   268: aaload
            /*    */     //   269: aload #7
            /*    */     //   271: invokevirtual WS : (Lf/JG0;Ljava/lang/String;)Lf/Li0;
            /*    */     //   274: aload_0
            /*    */     //   275: aload #6
            /*    */     //   277: <illegal opcode> run : (Lf/A;Lf/Te;)Ljava/lang/Runnable;
            /*    */     //   282: invokevirtual Ac0 : (Ljava/lang/Runnable;)V
            /*    */     //   285: iinc #5, 1
            /*    */     //   288: goto -> 210
            /*    */     //   291: sipush #8004
            /*    */     //   294: invokestatic OH0 : (I)Ljava/lang/String;
            /*    */     //   297: astore_3
            /*    */     //   298: invokestatic XU : ()Z
            /*    */     //   301: ifeq -> 315
            /*    */     //   304: aload_3
            /*    */     //   305: ldc_w ' '
            /*    */     //   308: ldc_w '\\n'
            /*    */     //   311: invokevirtual replaceAll : (Ljava/lang/String;Ljava/lang/String;)Ljava/lang/String;
            /*    */     //   314: astore_3
            /*    */     //   315: iload_2
            /*    */     //   316: ifeq -> 335
            /*    */     //   319: aload_0
            /*    */     //   320: getfield sr : Lf/Vq0;
            /*    */     //   323: aload_0
            /*    */     //   324: getfield X3 : Lf/lK0;
            /*    */     //   327: aload_3
            /*    */     //   328: invokevirtual WS : (Lf/JG0;Ljava/lang/String;)Lf/Li0;
            /*    */     //   331: pop
            /*    */     //   332: goto -> 417
            /*    */     //   335: aload_0
            /*    */     //   336: new f/Ip
            /*    */     //   339: dup
            /*    */     //   340: dup2
            /*    */     //   341: dup2
            /*    */     //   342: astore_2
            /*    */     //   343: invokespecial <init> : ()V
            /*    */     //   346: new f/dQ
            /*    */     //   349: dup
            /*    */     //   350: dup
            /*    */     //   351: astore #4
            /*    */     //   353: sipush #8029
            /*    */     //   356: invokestatic OH0 : (I)Ljava/lang/String;
            /*    */     //   359: invokespecial <init> : (Ljava/lang/String;)V
            /*    */     //   362: ldc 'label-info'
            /*    */     //   364: invokevirtual Xu : (Ljava/lang/String;)V
            /*    */     //   367: invokevirtual d7 : ()Lf/cr0;
            /*    */     //   370: invokevirtual Em0 : ()Lf/U90;
            /*    */     //   373: iconst_1
            /*    */     //   374: anewarray f/JG0
            /*    */     //   377: dup
            /*    */     //   378: iconst_0
            /*    */     //   379: aload #4
            /*    */     //   381: aastore
            /*    */     //   382: invokevirtual Mg : ([Lf/JG0;)Lf/U90;
            /*    */     //   385: invokevirtual Em0 : ()Lf/U90;
            /*    */     //   388: invokevirtual rK0 : (Lf/U90;)V
            /*    */     //   391: invokevirtual d7 : ()Lf/cr0;
            /*    */     //   394: invokevirtual Em0 : ()Lf/U90;
            /*    */     //   397: aload #4
            /*    */     //   399: invokevirtual Ya : (Lf/JG0;)Lf/U90;
            /*    */     //   402: invokevirtual Em0 : ()Lf/U90;
            /*    */     //   405: invokevirtual WN : (Lf/U90;)V
            /*    */     //   408: getfield sr : Lf/Vq0;
            /*    */     //   411: aload_2
            /*    */     //   412: aload_3
            /*    */     //   413: invokevirtual WS : (Lf/JG0;Ljava/lang/String;)Lf/Li0;
            /*    */     //   416: pop
            /*    */     //   417: sipush #8070
            /*    */     //   420: invokestatic OH0 : (I)Ljava/lang/String;
            /*    */     //   423: astore_2
            /*    */     //   424: invokestatic XU : ()Z
            /*    */     //   427: ifeq -> 441
            /*    */     //   430: aload_2
            /*    */     //   431: ldc_w ' '
            /*    */     //   434: ldc_w '\\n'
            /*    */     //   437: invokevirtual replaceAll : (Ljava/lang/String;Ljava/lang/String;)Ljava/lang/String;
            /*    */     //   440: astore_2
            /*    */     //   441: aload_1
            /*    */     //   442: aload_0
            /*    */     //   443: dup
            /*    */     //   444: dup2
            /*    */     //   445: getfield sr : Lf/Vq0;
            /*    */     //   448: aload_0
            /*    */     //   449: invokevirtual this : ()Lf/Ip;
            /*    */     //   452: aload_2
            /*    */     //   453: invokevirtual WS : (Lf/JG0;Ljava/lang/String;)Lf/Li0;
            /*    */     //   456: aload_0
            /*    */     //   457: <illegal opcode> run : (Lf/A;)Ljava/lang/Runnable;
            /*    */     //   462: invokevirtual Ac0 : (Ljava/lang/Runnable;)V
            /*    */     //   465: getfield sr : Lf/Vq0;
            /*    */     //   468: invokevirtual J8 : (Lf/JG0;)V
            /*    */     //   471: invokestatic ae0 : (Lf/JG0;)V
            /*    */     //   474: ifnull -> 497
            /*    */     //   477: aload_0
            /*    */     //   478: dup
            /*    */     //   479: getfield bk : Lf/Gn0;
            /*    */     //   482: aload_1
            /*    */     //   483: invokevirtual zf : (Lf/j40;)V
            /*    */     //   486: getfield sr : Lf/Vq0;
            /*    */     //   489: dup
            /*    */     //   490: iconst_3
            /*    */     //   491: invokevirtual Hf : (I)Lf/Li0;
            /*    */     //   494: invokevirtual dA0 : (Lf/Li0;)V
            /* 13 */     //   497: return } public static void MW(fv0 paramfv0, SA paramSA) { if (paramfv0.Z6 == Te.Qu) { vF0 vF0; float f; LPT3 lPT3 = Of.eH.On0(paramfv0.bn); this(); (new vF0()).TS.qt(new U70[] { wm0.y0.HR(lPT3, false) }); (new vF0()).TS.tL(24, 24); (new vF0()).TS
            /* 14 */         .xB0 = 1;
            /* 15 */
            if (km.XU())
                /* 16 */ vF0.TS
                    /* 17 */.V1 = 2.0F;
            paramSA
/* 18 */.S7(new JG0())
/* 19 */.Kw();
            paramSA.S7(new JG0()).x70();
            /* 20 */
            nJ0 nJ0 = paramSA.S7(vF0).Ig0(32.0F);
            if (km.XU()) {
                f = 10.0F;
            } else {
                f = 5.0F;
            }
            nJ0.sg(f);
            paramSA
/*    */
/*    */
/*    */
/* 24 */.fe(paramfv0.gh + "x " + Ml0.OH0(lPT3.Iu), "label-lalign").Kw();
            paramSA.S7(new JG0())
/* 25 */.Kw();
            paramSA.S7(new JG0()).x70();
        } else if (paramfv0
                /* 26 */.mm0 != null)
            /* 27 */ {
            short s;
            byte b;
            this();
            ey
                    /* 28 */.XC0 = false;
            /* 29 */
            ey.ZF = false;
            /* 30 */
            ey.FO = false;
            ey ey;
            /* 31 */
            (ey = new ey()).sB0(paramfv0);
            if (km.XU()) {
                ey
                        /* 32 */.un0 = 0;
                ey.ST = 0;
                /* 33 */
                ey.As
/* 34 */.zT(0, -20);
                /* 35 */
                ey.As
                        /* 36 */.V1 = 2.0F;
                /* 37 */
                ey.Xu("label");
            }
            nJ0 nJ0;
            (nJ0 = paramSA.S7(ey)).fu();
            if (km.XU()) {
                nJ0.fJ(48.0F);
                nJ0.Ig0(130.0F);
            } else {
                nJ0.Ig0(70.0F);
                nJ0.fJ(40.0F);
            }
            /* 38 */
            Q90 q90;
            if ((q90 = paramfv0.mm0) != null)
                /* 39 */ {
                b = q90.od;
            }
            /* 40 */
            else {
                b = paramfv0.nj0;
            }
            if (q90 != null)
                /* 41 */ {
                s = q90.Cw0;
            }
            /* 42 */
            else {
                s = s.bn;
            }
            paramSA
/* 43 */.S7(new Un(Ml0.OH0(59) + " " + b + " " + Ml0.OH0(s + 150000)))
/* 44 */.Kw();
            paramSA.S7(new Un(Ml0.OH0(59) + " " + b + " " + Ml0.OH0(s + 150000))).x70();
            /* 45 */
            paramSA.S7(new Un(Ml0.OH0(59) + " " + b + " " + Ml0.OH0(s + 150000))).kp0();
        }
        paramSA.wP();
    }

    public static void Ur0(fv0 paramfv0, JG0 paramJG0) {
        if (!km.D70(1)) return;
        this();
        String str = B40.df("Auction #").append(paramfv0.y60).toString();
        b3.mD(str, paramfv0::pb);
        b3.mD("ACP", paramfv0::o7);
        B3 b3;
        F7.Yo(b3 = new B3(), paramJG0);
    }

    /*    */
    public final void T10() {
        int i = 1, k = 1, m = 2000000000;
        BS bS;
        short s;
        if ((s = (bS = this.ii).hC0) > 0) {
            if ((k = bS.op0) > 0) i = k;
            short s1 = gm.Ti0;
            LPT3 lPT3;
            if ((lPT3 = Of.eH.On0(s)).ID0 > 1) if (lPT3.wg0 != v7.Kj0) {
                m = 250000000;
            } else {
                m = 20000000;
            }
            if (lPT3.TA0 && (int) ((m = Math.round(lPT3.ph0 * 1.105F)) * gm.u90) < (s = gm.Ti0)) {
                m = Math.round(lPT3.ph0 * 1.05F + s);
                short s2 = s1;
            } else {
                short s2 = s1;
            }
        }
        j40 j40;
        if ((j40 = this.bk.t70) != null) if (j40.Zs.tm0()) {
            k = gm.md;
        } else {
            k = gm.K20;
        }
        int n = this.bl.T8;
        this(0, m, n);
        String str;
        zT zT1;
        this.EL0 = new zT();
        this.bl.pe(zT1);
        this.bl.l4(this.bl.T8);
        this.Ea = k;
        this.EL0.Ac0(this::T10);
        int j;
        if (((m = (int) ((j = this.bl.T8) * gm.u90)) < (n = gm.K20) && this.bk.t70 != null) || m < (n = gm.Ti0)) m = n;
        if (m > (n = gm.gx0))
            /* 47 */ m = n;
        i = m * i;
        this.TK0.Be0(B40.df("$").append(NumberFormat.getInstance().format(i)).toString(), false);
        long l;
        if ((l = i * j) > 2000000000L) {
            str = Ml0.Go(8048, NumberFormat.getInstance().format(2000000000L));
            this.ir0.z4 = this;
            this.ir0.zn();
            this.ir0.sk0(false);
            this.ir0.jl = 0;
            this.zr0.z4 = this;
            this.zr0.zn();
            this.zr0.jl = 0;
            this.zr0.Be0(B40.df("(!!) $").append(NumberFormat.getInstance().format(l)).toString(), false);
        } else {
            ((A) super).ir0.z4 = null;
            ((A) super).ir0.zn();
            ((A) super).zr0.Be0(B40.df("$").append(NumberFormat.getInstance().format(l)).toString(), false);
            /* 48 */
            ((A) super).zr0
                    /* 49 */.z4 = null;
            /* 50 */
            ((A) super).zr0.zn();
            if (l > 0L) ((A) super)
/* 51 */.ir0.sk0(true);
        }
        /*    */
    }

    /*    */
    /*    */
    /*    */
    public final void sK0() {
        /*    */
        this.X3 = new lK0(this);
        /*    */
        this();
        /*    */
        YA0 yA01, yA02;
        /*    */
        float f;
        /*    */
        (new YA0()).Xu("/broker-table");
        /*    */
        (new YA0()).Ho0 = true;
        /*    */
        (new YA0()).TG0 = true;
        /*    */
        SA sA;
        /*    */
        (sA = (new YA0()).Dv0).Dl0(5.0F);
        /*    */
        nJ0 nJ03 = (new YA0()).Dv0.RT.fu().Xs0().Kw();
        /*    */
        if (km.XU()) {
            /*    */
            f = 72.0F;
            /*    */
        } else {
            /*    */
            f = 36.0F;
            /*    */
        }
        /*    */
        nJ03.fJ(f).Xj0(1.0F);
        /*    */
        sA.JP(0).Ig0(160.0F);
        /*    */
        ((SA) sA.HI0()).yh0();
        /*    */
        if (km.XU()) {
            /*    */
            sA.F(40.0F);
            /*    */
        } else {
            /*    */
            sA.F(10.0F);
            /*    */
        }
        /*    */
        this();
        /*    */
        this.ii = bS;
        /*    */
        BS bS;
        /*    */
        (bS = new BS()).tW(this::Wy0);
        /*    */
        this.ii.Tw0 = this::tP;
        /*    */
        nJ0 nJ02 = sA.SB(8005, "header-column");
        /*    */
        if (km.XU()) {
            /*    */
            f = 96.0F;
            /*    */
        } else {
            /*    */
            f = 48.0F;
            /*    */
        }
        /*    */
        nJ02.fJ(f);
        /*    */
        sA.S7(this.ii);
        /*    */
        sA.wP();
        /*    */
        this();
        /*    */
        this.bk = gn0;
        /*    */
        gn0.ZF = true;
        /*    */
        gn0.FO = true;
        /*    */
        gn0.XC0 = false;
        /*    */
        Gn0 gn0;
        /*    */
        (gn0 = new Gn0()).tW(this::Jf0);
        /*    */
        this.bk.n0 = this::e80;
        /*    */
        if (km.XU()) {
            /*    */
            this.bk.un0 = 100;
            /*    */
            this.bk.ST = 120;
            /*    */
            this.bk.As.zT(14, 30);
            /*    */
        }
        /*    */
        nJ0 nJ01 = sA.SB(0, "header-column");
        /*    */
        if (km.XU()) {
            /*    */
            f = 120.0F;
            /*    */
        } else {
            /*    */
            f = 48.0F;
            /*    */
        }
        /*    */
        nJ01.fJ(f);
        /*    */
        sA.S7(this.bk);
        /*    */
        sA.wP();
        /*    */
        this.EL0 = new zT(0, 2147483647, 0);
        /*    */
        (this.bl = new Rm(this.EL0)).W70 = "$";
        /*    */
        (new Rm(this.EL0)).t90();
        /*    */
        sA.SB(8006, "header-column");
        /*    */
        sA.S7(this.bl).Ig0(180.0F);
        /*    */
        sA.wP();
        /*    */
        (this.TK0 = new of(null)).sk0(false);
        /*    */
        Ml0.OH0(8007);
        /*    */
        this.TK0.getClass();
        /*    */
        sA.SB(8007, "header-column");
        /*    */
        sA.S7(this.TK0);
        /*    */
        sA.wP();
        /*    */
        (this.zr0 = new of(null)).sk0(false);
        /*    */
        Ml0.OH0(8047);
        /*    */
        this.zr0.getClass();
        /*    */
        sA.SB(8047, "header-column");
        /*    */
        sA.S7(this.zr0);
        /*    */
        sA.wP();
        /*    */
        et et;
        /*    */
        (this.ir0 = new Un(Ml0.OH0(8009))).C70(et = et.Wi0);
        /*    */
        this.ir0.Xu("cell-button");
        /*    */
        this.ir0.tW(this::rD);
        /*    */
        this(Ml0.OH0(8008));
        /*    */
        un.C70(et);
        /*    */
        un.Xu("cell-button");
        /*    */
        Un un;
        /*    */
        (un = new Un()).tW(this::WB);
        /*    */
        this();
        /*    */
        (new YA0()).Dv0.RT.Ig0(100.0F).fJ(36.0F);
        /*    */
        (new YA0()).Dv0.S7(un).x70().fu();
        /*    */
        un = this.ir0;
        /*    */
        yA02.Dv0.S7(un).ti0();
        /*    */
        (sA.S7(yA02).Kw()).ss = Integer.valueOf(2);
        /*    */
        sA.wP();
        /*    */
        T10();
        /*    */
        lK0 lK02;
        /*    */
        (lK02 = this.X3).getClass();
        /*    */
        this.X3.rK0((new g0(lK02)).cOM8(new U90[]{this.X3.vo0(new JG0[]{yA01})}));
        /*    */
        (lK02 = this.X3).getClass();
        /*    */
        lK0 lK01;
        /*    */
        (lK01 = this.X3).getClass();
        /*    */
        this.X3.WN((new cr0(lK02)).Aq(30).cOM8(new U90[]{(new g0(this)).Ya(yA01)}));
        /*    */
    }

    /*    */
    /*    */
    public final void C40(iv[] paramArrayOfiv) {
        /*    */     // Byte code:
        /*    */     //   0: aload_0
        /*    */     //   1: getfield vz0 : Lf/YA0;
        /*    */     //   4: dup
        /*    */     //   5: astore_0
        /*    */     //   6: ifnonnull -> 10
        /*    */     //   9: return
        /*    */     //   10: aload_0
        /*    */     //   11: getfield Dv0 : Lf/SA;
        /*    */     //   14: dup
        /*    */     //   15: dup2
        /*    */     //   16: astore_0
        /*    */     //   17: invokevirtual kp0 : ()V
        /*    */     //   20: invokevirtual HI0 : ()Lf/ZP;
        /*    */     //   23: checkcast f/SA
        /*    */     //   26: iconst_1
        /*    */     //   27: putfield Fh : I
        /*    */     //   30: getfield RT : Lf/nJ0;
        /*    */     //   33: invokevirtual R7 : ()Lf/nJ0;
        /*    */     //   36: dup
        /*    */     //   37: dup
        /*    */     //   38: fconst_1
        /*    */     //   39: invokestatic valueOf : (F)Ljava/lang/Float;
        /*    */     //   42: putfield X50 : Ljava/lang/Float;
        /*    */     //   45: fconst_1
        /*    */     //   46: invokestatic valueOf : (F)Ljava/lang/Float;
        /*    */     //   49: putfield Q7 : Ljava/lang/Float;
        /*    */     //   52: invokevirtual Xs0 : ()Lf/nJ0;
        /*    */     //   55: fconst_1
        /*    */     //   56: invokevirtual Xj0 : (F)Lf/nJ0;
        /*    */     //   59: ldc 36.0
        /*    */     //   61: invokevirtual fJ : (F)Lf/nJ0;
        /*    */     //   64: pop
        /*    */     //   65: invokestatic XU : ()Z
        /*    */     //   68: ifeq -> 78
        /*    */     //   71: ldc_w 5.0
        /*    */     //   74: fstore_2
        /*    */     //   75: goto -> 80
        /*    */     //   78: fconst_0
        /*    */     //   79: fstore_2
        /*    */     //   80: aload_0
        /*    */     //   81: fload_2
        /*    */     //   82: invokevirtual to : (F)Lf/ZP;
        /*    */     //   85: pop
        /*    */     //   86: invokestatic XU : ()Z
        /*    */     //   89: ifeq -> 97
        /*    */     //   92: fconst_0
        /*    */     //   93: fstore_2
        /*    */     //   94: goto -> 101
        /*    */     //   97: ldc_w 5.0
        /*    */     //   100: fstore_2
        /*    */     //   101: aload_0
        /*    */     //   102: fload_2
        /*    */     //   103: invokevirtual Ty0 : (F)V
        /*    */     //   106: invokestatic XU : ()Z
        /*    */     //   109: ifeq -> 119
        /*    */     //   112: ldc_w 5.0
        /*    */     //   115: fstore_2
        /*    */     //   116: goto -> 121
        /*    */     //   119: fconst_0
        /*    */     //   120: fstore_2
        /*    */     //   121: aload_1
        /*    */     //   122: aload_0
        /*    */     //   123: dup
        /*    */     //   124: dup2
        /*    */     //   125: dup2
        /*    */     //   126: fload_2
        /*    */     //   127: invokevirtual F : (F)Lf/ZP;
        /*    */     //   130: pop
        /*    */     //   131: sipush #8071
        /*    */     //   134: ldc_w 'header-column'
        /*    */     //   137: invokevirtual SB : (ILjava/lang/String;)Lf/nJ0;
        /*    */     //   140: ldc_w 250.0
        /*    */     //   143: invokevirtual Ig0 : (F)Lf/nJ0;
        /*    */     //   146: invokevirtual Xs0 : ()Lf/nJ0;
        /*    */     //   149: invokevirtual Kw : ()Lf/nJ0;
        /*    */     //   152: pop
        /*    */     //   153: sipush #8072
        /*    */     //   156: ldc_w 'header-column'
        /*    */     //   159: invokevirtual SB : (ILjava/lang/String;)Lf/nJ0;
        /*    */     //   162: ldc_w 140.0
        /*    */     //   165: invokevirtual Ig0 : (F)Lf/nJ0;
        /*    */     //   168: invokevirtual Kw : ()Lf/nJ0;
        /*    */     //   171: pop
        /*    */     //   172: sipush #8073
        /*    */     //   175: ldc_w 'header-column'
        /*    */     //   178: invokevirtual SB : (ILjava/lang/String;)Lf/nJ0;
        /*    */     //   181: ldc_w 100.0
        /*    */     //   184: invokevirtual Ig0 : (F)Lf/nJ0;
        /*    */     //   187: invokevirtual Kw : ()Lf/nJ0;
        /*    */     //   190: pop
        /*    */     //   191: sipush #5837
        /*    */     //   194: ldc_w 'header-column'
        /*    */     //   197: invokevirtual SB : (ILjava/lang/String;)Lf/nJ0;
        /*    */     //   200: ldc_w 100.0
        /*    */     //   203: invokevirtual Ig0 : (F)Lf/nJ0;
        /*    */     //   206: invokevirtual Kw : ()Lf/nJ0;
        /*    */     //   209: pop
        /*    */     //   210: invokevirtual wP : ()Lf/nJ0;
        /*    */     //   213: ldc_w 3.0
        /*    */     //   216: invokevirtual fa0 : (F)Lf/nJ0;
        /*    */     //   219: pop
        /*    */     //   220: arraylength
        /*    */     //   221: ifeq -> 271
        /*    */     //   224: aload_1
        /*    */     //   225: invokestatic stream : ([Ljava/lang/Object;)Ljava/util/stream/Stream;
        /*    */     //   228: <illegal opcode> test : ()Ljava/util/function/Predicate;
        /*    */     //   233: invokeinterface noneMatch : (Ljava/util/function/Predicate;)Z
        /*    */     //   238: ifeq -> 244
        /*    */     //   241: goto -> 271
        /*    */     //   244: aload_1
        /*    */     //   245: ldc_w 'UTC'
        /*    */     //   248: invokestatic getTimeZone : (Ljava/lang/String;)Ljava/util/TimeZone;
        /*    */     //   251: invokestatic getInstance : (Ljava/util/TimeZone;)Ljava/util/Calendar;
        /*    */     //   254: astore_1
        /*    */     //   255: invokestatic stream : ([Ljava/lang/Object;)Ljava/util/stream/Stream;
        /*    */     //   258: aload_1
        /*    */     //   259: aload_0
        /*    */     //   260: <illegal opcode> accept : (Ljava/util/Calendar;Lf/SA;)Ljava/util/function/Consumer;
        /*    */     //   265: invokeinterface forEach : (Ljava/util/function/Consumer;)V
        /*    */     //   270: return
        /*    */     //   271: aload_0
        /*    */     //   272: dup
        /*    */     //   273: dup
        /*    */     //   274: new f/dQ
        /*    */     //   277: dup
        /*    */     //   278: dup2
        /*    */     //   279: sipush #8069
        /*    */     //   282: invokestatic OH0 : (I)Ljava/lang/String;
        /*    */     //   285: astore_0
        /*    */     //   286: invokespecial <init> : ()V
        /*    */     //   289: aload_0
        /*    */     //   290: invokevirtual E1 : (Ljava/lang/String;)V
        /*    */     //   293: ldc 'label-info'
        /*    */     //   295: invokevirtual Xu : (Ljava/lang/String;)V
        /*    */     //   298: invokevirtual S7 : (Ljava/lang/Object;)Lf/nJ0;
        /*    */     //   301: dup
        /*    */     //   302: iconst_4
        /*    */     //   303: invokestatic valueOf : (I)Ljava/lang/Integer;
        /*    */     //   306: putfield ss : Ljava/lang/Integer;
        /*    */     //   309: invokevirtual Kw : ()Lf/nJ0;
        /*    */     //   312: pop
        /*    */     //   313: invokevirtual wP : ()Lf/nJ0;
        /*    */     //   316: pop
        /*    */     //   317: new f/JG0
        /*    */     //   320: dup
        /*    */     //   321: invokespecial <init> : ()V
        /*    */     //   324: invokevirtual S7 : (Ljava/lang/Object;)Lf/nJ0;
        /*    */     //   327: dup
        /*    */     //   328: dup
        /*    */     //   329: iconst_4
        /*    */     //   330: invokestatic valueOf : (I)Ljava/lang/Integer;
        /*    */     //   333: putfield ss : Ljava/lang/Integer;
        /*    */     //   336: invokevirtual kp0 : ()Lf/nJ0;
        /*    */     //   339: pop
        /*    */     //   340: invokevirtual i40 : ()Lf/nJ0;
        /*    */     //   343: pop
        /*    */     //   344: return
        /*    */     // Line number table:
        /*    */     //   Java source line number -> byte code offset
        /*    */     //   #1	-> 27
        /*    */     //   #2	-> 30
        /*    */     //   #3	-> 33
        /*    */     //   #4	-> 39
        /*    */     //   #5	-> 52
        /*    */     //   #6	-> 286
        /*    */     //   #7	-> 293
        /*    */     //   #8	-> 306
        /*    */     //   #9	-> 309
        /*    */     //   #10	-> 333
        /*    */     //   #11	-> 336
        /*    */
    }

    /*    */
    /*    */
    public final void close() {
        /*    */
        pA pA;
        /*    */
        if (this.zk && (pA = js.vu0.MH0).dk0 == null && this.AL == null)
            /*    */ km.u4.e20.W3(new nC());
        /*    */
        pA.Dg0.A4(null, false, false);
        /*    */
    }

    /*    */
    /*    */
    public final void ED0(throws paramthrows) {
        /*    */
        VA0.nR(this, false);
        /*    */
        JG0 jG0;
        /*    */
        if ((jG0 = VA0.q10) != null)
            /*    */ jG0.BA();
        /*    */
        super.ED0(paramthrows);
        /*    */
    }

    /*    */
    /*    */
    public final void mg(Te paramTe) {
        /*    */
        oo oo1;
        /*    */
        if ((oo1 = this.dL) != null) {
            /*    */
            oo1.uw0();
            /*    */
            this.dL = null;
            /*    */
        }
        /*    */
        this();
        /*    */
        fv0[] arrayOfFv0;
        /*    */
        fQ fQ;
        /*    */
        dg0 dg0;
        /*    */
        bh bh1;
        /*    */
        String str = LF.Ll0((bh1 = this.YD0[paramTe.HC0]).mo0.F2.PH0.toString(), true);
        /*    */
        int i;
        /*    */
        if ((i = paramTe.ordinal()) != 0) {
            /*    */
            fQ.OG0(bh1.ma0());
            /*    */
            if (i == 1 && !str.isEmpty()) {
                /*    */
                Lw lw;
                /*    */
                this();
                /*    */
                for (Iterator<LPT3> iterator = Of.eH.cOm7.values().iterator(); iterator.hasNext(); ) {
                    /*    */
                    if ((lPT3 = iterator.next()).vx() && !lPT3.IK0 && LF.qS(Ml0.OH0(lPT3.Iu), str))
                        /*    */ lw.Ye0(lPT3.bj0);
                    /*    */
                }
                /*    */
                this(lw);
                /*    */
                fQ.Com3(dg0);
                /*    */
            }
            /*    */
        } else {
            /*    */
            fQ.OG0(bh1.ma0());
            /*    */
            DO dO;
            /*    */
            Hc0 hc01;
            /*    */
            for (dO = null, hc01 = fQ.r30(); hc01.hasNext(); ) {
                /*    */
                if ((sK = (sK) hc01.next()) != null && sK instanceof Tj0)
                    /*    */ dO = DO.kk((byte) sK.a7());
                /*    */
            }
            /*    */
            if (!dg0.isEmpty() || dO != null) {
                /*    */
                Lw lw;
                /*    */
                this();
                /*    */
                for (Iterator<UD0> iterator = (On.v30()).iI0.values().iterator(); iterator.hasNext(); ) {
                    /*    */
                    boolean bool;
                    /*    */
                    UD0 uD0;
                    /*    */
                    if ((uD0 = iterator.next()).h3 != null) {
                        /*    */
                        bool = true;
                        /*    */
                    } else {
                        /*    */
                        bool = false;
                        /*    */
                    }
                    /*    */
                    if (!bool && uD0.AP < 1000 && LF.qS(uD0.o60(false), (String) dg0)) {
                        /*    */
                        if (dO == null || uD0.ee == dO) {
                            /*    */
                            bool = true;
                            /*    */
                        } else {
                            /*    */
                            bool = uD0.G2.contains(dO);
                            /*    */
                        }
                        /*    */
                        if (bool)
                            /*    */ lw.Ye0(uD0.AP);
                        /*    */
                    }
                    /*    */
                }
                /*    */
                this(lw);
                /*    */
                fQ.Com3(dg0);
                /*    */
            }
            /*    */
        }
        /*    */
        Hc0 hc0;
        /*    */
        byte b2;
        /*    */
        for (i = (byte) (this.E60[b2 = paramTe.HC0] + 1), this.E60[b2] = i, hc0 = fQ.r30(); hc0.hasNext(); ) {
            /*    */
            if (((sK) hc0.next()).UW()) {
                /*    */
                arrayOfFv0 = new fv0[0];
                /*    */
                uZ(i, paramTe, 0, 0, this, null);
                /*    */
                return;
                /*    */
            }
            /*    */
        }
        /*    */
        super.bg0(paramTe);
        /*    */
        sK[] arrayOfSK = (sK[]) fQ.Ib(sK.class);
        /*    */
        R8 r8 = km.u4;
        /*    */
        byte b1 = bh1.CG0();
        /*    */
        short s = (((A) super).YD0[paramTe.HC0]).Ag;
        /*    */
        r8.e20.W3(new Kx0(i, paramTe, b1, s, arrayOfSK));
        /*    */
    }

    /*    */
    /*    */
    public final void rD() {
        /*    */     // Byte code:
        /*    */     //   0: aload_0
        /*    */     //   1: dup
        /*    */     //   2: getfield ir0 : Lf/Un;
        /*    */     //   5: iconst_0
        /*    */     //   6: invokevirtual sk0 : (Z)V
        /*    */     //   9: iconst_1
        /*    */     //   10: istore_1
        /*    */     //   11: getfield bl : Lf/Rm;
        /*    */     //   14: getfield T8 : I
        /*    */     //   17: dup
        /*    */     //   18: istore_2
        /*    */     //   19: aload_0
        /*    */     //   20: getfield Ea : I
        /*    */     //   23: if_icmpge -> 58
        /*    */     //   26: aload_0
        /*    */     //   27: getstatic f/km.u4 : Lf/R8;
        /*    */     //   30: invokestatic getInstance : ()Ljava/text/NumberFormat;
        /*    */     //   33: aload_0
        /*    */     //   34: getfield Ea : I
        /*    */     //   37: i2l
        /*    */     //   38: invokevirtual format : (J)Ljava/lang/String;
        /*    */     //   41: sipush #5895
        /*    */     //   44: swap
        /*    */     //   45: invokestatic Go : (ILjava/lang/String;)Ljava/lang/String;
        /*    */     //   48: invokevirtual Pq : (Ljava/lang/String;)V
        /*    */     //   51: getstatic f/wk.TN : Lf/wk;
        /*    */     //   54: invokevirtual Ek : (Lf/wk;)V
        /*    */     //   57: return
        /*    */     //   58: aload_0
        /*    */     //   59: getfield bk : Lf/Gn0;
        /*    */     //   62: getfield t70 : Lf/j40;
        /*    */     //   65: dup
        /*    */     //   66: astore_3
        /*    */     //   67: ifnull -> 84
        /*    */     //   70: aload_3
        /*    */     //   71: getstatic f/Te.QK0 : Lf/Te;
        /*    */     //   74: astore #4
        /*    */     //   76: getfield Jg : I
        /*    */     //   79: istore #5
        /*    */     //   81: goto -> 113
        /*    */     //   84: aload_0
        /*    */     //   85: getfield ii : Lf/BS;
        /*    */     //   88: dup
        /*    */     //   89: astore_1
        /*    */     //   90: getfield Hs0 : I
        /*    */     //   93: dup
        /*    */     //   94: istore #5
        /*    */     //   96: ifle -> 307
        /*    */     //   99: aload_1
        /*    */     //   100: getfield op0 : S
        /*    */     //   103: dup
        /*    */     //   104: istore_1
        /*    */     //   105: ifle -> 307
        /*    */     //   108: getstatic f/Te.Qu : Lf/Te;
        /*    */     //   111: astore #4
        /*    */     //   113: aload_3
        /*    */     //   114: ifnull -> 272
        /*    */     //   117: aload_3
        /*    */     //   118: iconst_0
        /*    */     //   119: istore #6
        /*    */     //   121: iconst_0
        /*    */     //   122: istore #7
        /*    */     //   124: getfield Zs : Lf/Q90;
        /*    */     //   127: invokevirtual Gf : ()Z
        /*    */     //   130: ifeq -> 151
        /*    */     //   133: iload_2
        /*    */     //   134: ldc_w 7500000
        /*    */     //   137: if_icmpge -> 151
        /*    */     //   140: iconst_1
        /*    */     //   141: istore #6
        /*    */     //   143: sipush #5062
        /*    */     //   146: istore #7
        /*    */     //   148: goto -> 176
        /*    */     //   151: aload_3
        /*    */     //   152: getfield Zs : Lf/Q90;
        /*    */     //   155: invokevirtual tm0 : ()Z
        /*    */     //   158: ifeq -> 176
        /*    */     //   161: iload_2
        /*    */     //   162: ldc_w 600000
        /*    */     //   165: if_icmpge -> 176
        /*    */     //   168: iconst_1
        /*    */     //   169: istore #6
        /*    */     //   171: sipush #5019
        /*    */     //   174: istore #7
        /*    */     //   176: iload #6
        /*    */     //   178: ifeq -> 272
        /*    */     //   181: aload_0
        /*    */     //   182: getstatic f/js.vu0 : Lf/js;
        /*    */     //   185: new f/h70
        /*    */     //   188: dup
        /*    */     //   189: dup
        /*    */     //   190: aload #4
        /*    */     //   192: iload #5
        /*    */     //   194: iconst_2
        /*    */     //   195: anewarray java/lang/String
        /*    */     //   198: dup
        /*    */     //   199: dup
        /*    */     //   200: astore_0
        /*    */     //   201: iload #7
        /*    */     //   203: aload_3
        /*    */     //   204: invokevirtual m : ()Ljava/lang/String;
        /*    */     //   207: invokestatic Go : (ILjava/lang/String;)Ljava/lang/String;
        /*    */     //   210: iconst_0
        /*    */     //   211: swap
        /*    */     //   212: aastore
        /*    */     //   213: ldc_w '$'
        /*    */     //   216: invokestatic df : (Ljava/lang/String;)Ljava/lang/StringBuilder;
        /*    */     //   219: invokestatic getInstance : ()Ljava/text/NumberFormat;
        /*    */     //   222: iload_2
        /*    */     //   223: i2l
        /*    */     //   224: invokevirtual format : (J)Ljava/lang/String;
        /*    */     //   227: invokevirtual append : (Ljava/lang/String;)Ljava/lang/StringBuilder;
        /*    */     //   230: invokevirtual toString : ()Ljava/lang/String;
        /*    */     //   233: iconst_1
        /*    */     //   234: swap
        /*    */     //   235: aastore
        /*    */     //   236: sipush #8044
        /*    */     //   239: aload_0
        /*    */     //   240: invokestatic sB : (I[Ljava/lang/String;)Ljava/lang/String;
        /*    */     //   243: astore_0
        /*    */     //   244: iload_2
        /*    */     //   245: iload_1
        /*    */     //   246: <illegal opcode> run : (Lf/Te;IIS)Ljava/lang/Runnable;
        /*    */     //   251: aload_0
        /*    */     //   252: swap
        /*    */     //   253: aconst_null
        /*    */     //   254: invokespecial <init> : (Ljava/lang/String;Ljava/lang/Runnable;Lf/JG0;)V
        /*    */     //   257: iconst_1
        /*    */     //   258: putfield sD0 : Z
        /*    */     //   261: invokevirtual uh : (Lf/h70;)V
        /*    */     //   264: getfield ir0 : Lf/Un;
        /*    */     //   267: iconst_1
        /*    */     //   268: invokevirtual sk0 : (Z)V
        /*    */     //   271: return
        /*    */     //   272: aload_3
        /*    */     //   273: ifnull -> 284
        /*    */     //   276: aload_3
        /*    */     //   277: getfield Zs : Lf/Q90;
        /*    */     //   280: invokevirtual getClass : ()Ljava/lang/Class;
        /*    */     //   283: pop
        /*    */     //   284: getstatic f/km.u4 : Lf/R8;
        /*    */     //   287: getfield e20 : Lf/c4;
        /*    */     //   290: new f/cJ
        /*    */     //   293: dup
        /*    */     //   294: aload #4
        /*    */     //   296: iload #5
        /*    */     //   298: iload_2
        /*    */     //   299: iload_1
        /*    */     //   300: invokespecial <init> : (Lf/Te;IIS)V
        /*    */     //   303: invokevirtual W3 : (Lf/Bi;)V
        /*    */     //   306: return
        /*    */     //   307: aload_0
        /*    */     //   308: getstatic f/wk.TN : Lf/wk;
        /*    */     //   311: invokevirtual Ek : (Lf/wk;)V
        /*    */     //   314: return
        /*    */     // Line number table:
        /*    */     //   Java source line number -> byte code offset
        /*    */     //   #1	-> 14
        /*    */     //   #2	-> 20
        /*    */     //   #3	-> 62
        /*    */     //   #4	-> 71
        /*    */     //   #5	-> 76
        /*    */     //   #6	-> 85
        /*    */     //   #7	-> 90
        /*    */     //   #8	-> 100
        /*    */     //   #9	-> 108
        /*    */     //   #10	-> 124
        /*    */     //   #11	-> 127
        /*    */     //   #12	-> 152
        /*    */     //   #13	-> 182
        /*    */     //   #14	-> 185
        /*    */     //   #15	-> 213
        /*    */     //   #16	-> 219
        /*    */     //   #17	-> 258
        /*    */     //   #18	-> 261
        /*    */     //   #19	-> 277
        /*    */     //   #20	-> 284
        /*    */     //   #21	-> 287
        /*    */     //   #22	-> 290
        /*    */     //   #23	-> 308
        /*    */
    }

    /*    */
    /*    */
    public final void Ek(wk paramwk) {
        /*    */
        Te te;
        /*    */
        this.ir0.sk0(true);
        /*    */
        switch (paramwk.ordinal()) {
            /*    */
            default:
                /*    */
                return;
            /*    */
            case 20:
                /*    */
            case 23:
                /*    */
                mg(Te.EE);
                /*    */
            case 17:
                /*    */
            case 18:
                /*    */
                if ((te = this.Vi) != null)
                    /*    */ mg(te);
                /*    */
            case 1:
                /*    */
            case 2:
                /*    */
            case 3:
                /*    */
            case 4:
                /*    */
            case 5:
                /*    */
            case 6:
                /*    */
            case 7:
                /*    */
            case 8:
                /*    */
            case 9:
                /*    */
            case 10:
                /*    */
            case 12:
                /*    */
            case 13:
                /*    */
            case 14:
                /*    */
            case 15:
                /*    */
                this.ir0.sk0(true);
                /*    */
            case 0:
                /*    */
                break;
            /*    */
        }
        /*    */
        WB();
        /*    */
    }

    /*    */
    /*    */
    public final void bg0(Te paramTe) {
        /*    */     // Byte code:
        /*    */     //   0: getstatic f/UB0.Kg0 : Lf/Q50;
        /*    */     //   3: aload_0
        /*    */     //   4: aload_1
        /*    */     //   5: <illegal opcode> run : (Lf/A;Lf/Te;)Ljava/lang/Runnable;
        /*    */     //   10: invokevirtual fN : (Ljava/lang/Runnable;)V
        /*    */     //   13: return
        /*    */
    }

    /*    */
    /*    */
    public final void uZ(byte paramByte, Te paramTe, int paramInt1, int paramInt2, fv0[] paramArrayOffv0, Qr paramQr) {
        /*    */     // Byte code:
        /*    */     //   0: aload_2
        /*    */     //   1: getstatic f/Te.EE : Lf/Te;
        /*    */     //   4: if_acmpne -> 13
        /*    */     //   7: aload_0
        /*    */     //   8: aload #5
        /*    */     //   10: putfield uC0 : [Lf/fv0;
        /*    */     //   13: iload #4
        /*    */     //   15: ifge -> 24
        /*    */     //   18: iconst_1
        /*    */     //   19: istore #7
        /*    */     //   21: goto -> 27
        /*    */     //   24: iconst_0
        /*    */     //   25: istore #7
        /*    */     //   27: iload #7
        /*    */     //   29: ifeq -> 37
        /*    */     //   32: iload #4
        /*    */     //   34: ineg
        /*    */     //   35: istore #4
        /*    */     //   37: getstatic f/UB0.Kg0 : Lf/Q50;
        /*    */     //   40: aload_0
        /*    */     //   41: aload_2
        /*    */     //   42: iload_1
        /*    */     //   43: iload #4
        /*    */     //   45: aload #5
        /*    */     //   47: iload_3
        /*    */     //   48: iload #7
        /*    */     //   50: aload #6
        /*    */     //   52: <illegal opcode> run : (Lf/A;Lf/Te;BI[Lf/fv0;IZLf/Qr;)Ljava/lang/Runnable;
        /*    */     //   57: invokevirtual fN : (Ljava/lang/Runnable;)V
        /*    */     //   60: return
        /*    */
    }

    /*    */
    /*    */
    public final void JC(Te paramTe, YA0 paramYA0, boolean paramBoolean) {
        /*    */     // Byte code:
        /*    */     //   0: aload_2
        /*    */     //   1: getfield Dv0 : Lf/SA;
        /*    */     //   4: astore_2
        /*    */     //   5: invokestatic XU : ()Z
        /*    */     //   8: ifeq -> 19
        /*    */     //   11: aload_2
        /*    */     //   12: ldc_w 5.0
        /*    */     //   15: invokevirtual to : (F)Lf/ZP;
        /*    */     //   18: pop
        /*    */     //   19: aload_2
        /*    */     //   20: dup
        /*    */     //   21: getfield RT : Lf/nJ0;
        /*    */     //   24: invokevirtual kp0 : ()Lf/nJ0;
        /*    */     //   27: pop
        /*    */     //   28: invokevirtual HI0 : ()Lf/ZP;
        /*    */     //   31: checkcast f/SA
        /*    */     //   34: iconst_1
        /*    */     //   35: putfield Fh : I
        /*    */     //   38: aconst_null
        /*    */     //   39: astore #4
        /*    */     //   41: invokestatic XU : ()Z
        /*    */     //   44: ifeq -> 107
        /*    */     //   47: aload_2
        /*    */     //   48: new f/dQ
        /*    */     //   51: dup
        /*    */     //   52: dup2
        /*    */     //   53: invokestatic getInstance : ()Ljava/text/NumberFormat;
        /*    */     //   56: getstatic f/km.u4 : Lf/R8;
        /*    */     //   59: getfield Lz : Lf/fH0;
        /*    */     //   62: getfield Ii : I
        /*    */     //   65: i2l
        /*    */     //   66: invokevirtual format : (J)Ljava/lang/String;
        /*    */     //   69: sipush #1928
        /*    */     //   72: swap
        /*    */     //   73: invokestatic Go : (ILjava/lang/String;)Ljava/lang/String;
        /*    */     //   76: astore #4
        /*    */     //   78: invokespecial <init> : ()V
        /*    */     //   81: aload #4
        /*    */     //   83: invokevirtual E1 : (Ljava/lang/String;)V
        /*    */     //   86: ldc 'label-info'
        /*    */     //   88: invokevirtual Xu : (Ljava/lang/String;)V
        /*    */     //   91: invokevirtual S7 : (Ljava/lang/Object;)Lf/nJ0;
        /*    */     //   94: dup
        /*    */     //   95: astore #4
        /*    */     //   97: invokevirtual fu : ()Lf/nJ0;
        /*    */     //   100: getfield Ox : Lf/ZP;
        /*    */     //   103: invokevirtual wP : ()Lf/nJ0;
        /*    */     //   106: pop
        /*    */     //   107: aload_1
        /*    */     //   108: getstatic f/Te.QK0 : Lf/Te;
        /*    */     //   111: if_acmpne -> 258
        /*    */     //   114: aload_2
        /*    */     //   115: iconst_0
        /*    */     //   116: ldc_w 'header-column'
        /*    */     //   119: invokevirtual SB : (ILjava/lang/String;)Lf/nJ0;
        /*    */     //   122: astore #5
        /*    */     //   124: invokestatic XU : ()Z
        /*    */     //   127: ifeq -> 138
        /*    */     //   130: ldc_w 315.0
        /*    */     //   133: fstore #6
        /*    */     //   135: goto -> 141
        /*    */     //   138: fconst_0
        /*    */     //   139: fstore #6
        /*    */     //   141: aload_2
        /*    */     //   142: aload #5
        /*    */     //   144: fload #6
        /*    */     //   146: invokevirtual Ig0 : (F)Lf/nJ0;
        /*    */     //   149: dup
        /*    */     //   150: dup
        /*    */     //   151: iconst_2
        /*    */     //   152: invokestatic valueOf : (I)Ljava/lang/Integer;
        /*    */     //   155: putfield ss : Ljava/lang/Integer;
        /*    */     //   158: invokevirtual Kw : ()Lf/nJ0;
        /*    */     //   161: pop
        /*    */     //   162: invokevirtual x70 : ()Lf/nJ0;
        /*    */     //   165: pop
        /*    */     //   166: sipush #8106
        /*    */     //   169: ldc_w 'header-column'
        /*    */     //   172: invokevirtual SB : (ILjava/lang/String;)Lf/nJ0;
        /*    */     //   175: astore #5
        /*    */     //   177: invokestatic XU : ()Z
        /*    */     //   180: ifeq -> 191
        /*    */     //   183: ldc_w 95.0
        /*    */     //   186: fstore #6
        /*    */     //   188: goto -> 196
        /*    */     //   191: ldc_w 63.0
        /*    */     //   194: fstore #6
        /*    */     //   196: iload_3
        /*    */     //   197: aload_2
        /*    */     //   198: aload #5
        /*    */     //   200: fload #6
        /*    */     //   202: invokevirtual Ig0 : (F)Lf/nJ0;
        /*    */     //   205: invokevirtual Kw : ()Lf/nJ0;
        /*    */     //   208: pop
        /*    */     //   209: ldc_w 'IVs'
        /*    */     //   212: ldc_w 'header-column'
        /*    */     //   215: invokevirtual fe : (Ljava/lang/String;Ljava/lang/String;)Lf/nJ0;
        /*    */     //   218: astore_3
        /*    */     //   219: ifeq -> 226
        /*    */     //   222: iconst_1
        /*    */     //   223: goto -> 228
        /*    */     //   226: bipush #6
        /*    */     //   228: invokestatic valueOf : (I)Ljava/lang/Integer;
        /*    */     //   231: aload_3
        /*    */     //   232: swap
        /*    */     //   233: putfield ss : Ljava/lang/Integer;
        /*    */     //   236: invokestatic XU : ()Z
        /*    */     //   239: ifeq -> 250
        /*    */     //   242: ldc_w 200.0
        /*    */     //   245: fstore #5
        /*    */     //   247: goto -> 480
        /*    */     //   250: ldc_w 190.0
        /*    */     //   253: fstore #5
        /*    */     //   255: goto -> 480
        /*    */     //   258: aload_1
        /*    */     //   259: getstatic f/Te.Qu : Lf/Te;
        /*    */     //   262: if_acmpne -> 365
        /*    */     //   265: aload_2
        /*    */     //   266: ldc ''
        /*    */     //   268: ldc_w 'header-column'
        /*    */     //   271: invokevirtual fe : (Ljava/lang/String;Ljava/lang/String;)Lf/nJ0;
        /*    */     //   274: astore_3
        /*    */     //   275: invokestatic XU : ()Z
        /*    */     //   278: ifeq -> 289
        /*    */     //   281: ldc_w 120.0
        /*    */     //   284: fstore #5
        /*    */     //   286: goto -> 294
        /*    */     //   289: ldc_w 70.0
        /*    */     //   292: fstore #5
        /*    */     //   294: aload_2
        /*    */     //   295: aload_3
        /*    */     //   296: fload #5
        /*    */     //   298: invokevirtual Ig0 : (F)Lf/nJ0;
        /*    */     //   301: invokevirtual Kw : ()Lf/nJ0;
        /*    */     //   304: pop
        /*    */     //   305: sipush #8015
        /*    */     //   308: ldc_w 'header-column'
        /*    */     //   311: invokevirtual SB : (ILjava/lang/String;)Lf/nJ0;
        /*    */     //   314: astore_3
        /*    */     //   315: invokestatic XU : ()Z
        /*    */     //   318: ifeq -> 334
        /*    */     //   321: aload_3
        /*    */     //   322: dup
        /*    */     //   323: invokevirtual Kw : ()Lf/nJ0;
        /*    */     //   326: pop
        /*    */     //   327: invokevirtual x70 : ()Lf/nJ0;
        /*    */     //   330: pop
        /*    */     //   331: goto -> 345
        /*    */     //   334: aload_3
        /*    */     //   335: ldc_w 220.0
        /*    */     //   338: invokevirtual Ig0 : (F)Lf/nJ0;
        /*    */     //   341: invokevirtual Kw : ()Lf/nJ0;
        /*    */     //   344: pop
        /*    */     //   345: aload_2
        /*    */     //   346: sipush #8016
        /*    */     //   349: ldc_w 'header-column'
        /*    */     //   352: invokevirtual SB : (ILjava/lang/String;)Lf/nJ0;
        /*    */     //   355: astore_3
        /*    */     //   356: invokestatic Nr : ()Z
        /*    */     //   359: ifeq -> 477
        /*    */     //   362: goto -> 469
        /*    */     //   365: aload_1
        /*    */     //   366: getstatic f/Te.EE : Lf/Te;
        /*    */     //   369: if_acmpne -> 490
        /*    */     //   372: aload_2
        /*    */     //   373: ldc ''
        /*    */     //   375: ldc_w 'header-column'
        /*    */     //   378: invokevirtual fe : (Ljava/lang/String;Ljava/lang/String;)Lf/nJ0;
        /*    */     //   381: astore_3
        /*    */     //   382: invokestatic XU : ()Z
        /*    */     //   385: ifeq -> 396
        /*    */     //   388: ldc_w 120.0
        /*    */     //   391: fstore #5
        /*    */     //   393: goto -> 401
        /*    */     //   396: ldc_w 70.0
        /*    */     //   399: fstore #5
        /*    */     //   401: aload_2
        /*    */     //   402: aload_3
        /*    */     //   403: fload #5
        /*    */     //   405: invokevirtual Ig0 : (F)Lf/nJ0;
        /*    */     //   408: invokevirtual Kw : ()Lf/nJ0;
        /*    */     //   411: pop
        /*    */     //   412: sipush #8015
        /*    */     //   415: ldc_w 'header-column'
        /*    */     //   418: invokevirtual SB : (ILjava/lang/String;)Lf/nJ0;
        /*    */     //   421: astore_3
        /*    */     //   422: invokestatic XU : ()Z
        /*    */     //   425: ifeq -> 441
        /*    */     //   428: aload_3
        /*    */     //   429: dup
        /*    */     //   430: invokevirtual Kw : ()Lf/nJ0;
        /*    */     //   433: pop
        /*    */     //   434: invokevirtual x70 : ()Lf/nJ0;
        /*    */     //   437: pop
        /*    */     //   438: goto -> 452
        /*    */     //   441: aload_3
        /*    */     //   442: ldc_w 220.0
        /*    */     //   445: invokevirtual Ig0 : (F)Lf/nJ0;
        /*    */     //   448: invokevirtual Kw : ()Lf/nJ0;
        /*    */     //   451: pop
        /*    */     //   452: aload_2
        /*    */     //   453: sipush #8017
        /*    */     //   456: ldc_w 'header-column'
        /*    */     //   459: invokevirtual SB : (ILjava/lang/String;)Lf/nJ0;
        /*    */     //   462: astore_3
        /*    */     //   463: invokestatic Nr : ()Z
        /*    */     //   466: ifeq -> 477
        /*    */     //   469: ldc_w 60.0
        /*    */     //   472: fstore #5
        /*    */     //   474: goto -> 480
        /*    */     //   477: fconst_0
        /*    */     //   478: fstore #5
        /*    */     //   480: aload_3
        /*    */     //   481: fload #5
        /*    */     //   483: invokevirtual Ig0 : (F)Lf/nJ0;
        /*    */     //   486: invokevirtual Kw : ()Lf/nJ0;
        /*    */     //   489: pop
        /*    */     //   490: aload_2
        /*    */     //   491: new f/Un
        /*    */     //   494: dup
        /*    */     //   495: dup
        /*    */     //   496: astore_3
        /*    */     //   497: sipush #8012
        /*    */     //   500: invokestatic OH0 : (I)Ljava/lang/String;
        /*    */     //   503: invokespecial <init> : (Ljava/lang/String;)V
        /*    */     //   506: invokevirtual S7 : (Ljava/lang/Object;)Lf/nJ0;
        /*    */     //   509: invokevirtual Kw : ()Lf/nJ0;
        /*    */     //   512: astore #5
        /*    */     //   514: invokestatic XU : ()Z
        /*    */     //   517: ifeq -> 528
        /*    */     //   520: ldc_w 148.0
        /*    */     //   523: fstore #6
        /*    */     //   525: goto -> 533
        /*    */     //   528: ldc_w 102.0
        /*    */     //   531: fstore #6
        /*    */     //   533: aload_1
        /*    */     //   534: aload #5
        /*    */     //   536: fload #6
        /*    */     //   538: invokevirtual Ig0 : (F)Lf/nJ0;
        /*    */     //   541: pop
        /*    */     //   542: getstatic f/Te.EE : Lf/Te;
        /*    */     //   545: dup
        /*    */     //   546: astore #5
        /*    */     //   548: if_acmpne -> 561
        /*    */     //   551: aload_3
        /*    */     //   552: ldc_w 'header-column'
        /*    */     //   555: invokevirtual Xu : (Ljava/lang/String;)V
        /*    */     //   558: goto -> 627
        /*    */     //   561: aload_0
        /*    */     //   562: getfield YD0 : [Lf/bh;
        /*    */     //   565: aload_1
        /*    */     //   566: getfield HC0 : B
        /*    */     //   569: aaload
        /*    */     //   570: dup
        /*    */     //   571: astore #6
        /*    */     //   573: invokevirtual CG0 : ()B
        /*    */     //   576: iconst_2
        /*    */     //   577: if_icmpne -> 590
        /*    */     //   580: aload_3
        /*    */     //   581: ldc_w 'header-column-sort-desc'
        /*    */     //   584: invokevirtual Xu : (Ljava/lang/String;)V
        /*    */     //   587: goto -> 616
        /*    */     //   590: aload #6
        /*    */     //   592: invokevirtual CG0 : ()B
        /*    */     //   595: iconst_3
        /*    */     //   596: if_icmpne -> 609
        /*    */     //   599: aload_3
        /*    */     //   600: ldc_w 'header-column-sort-asc'
        /*    */     //   603: invokevirtual Xu : (Ljava/lang/String;)V
        /*    */     //   606: goto -> 616
        /*    */     //   609: aload_3
        /*    */     //   610: ldc_w 'header-column-sort-default'
        /*    */     //   613: invokevirtual Xu : (Ljava/lang/String;)V
        /*    */     //   616: aload_3
        /*    */     //   617: aload #6
        /*    */     //   619: <illegal opcode> run : (Lf/bh;)Ljava/lang/Runnable;
        /*    */     //   624: invokevirtual tW : (Ljava/lang/Runnable;)V
        /*    */     //   627: aload_1
        /*    */     //   628: aload #5
        /*    */     //   630: if_acmpne -> 767
        /*    */     //   633: aload_2
        /*    */     //   634: dup
        /*    */     //   635: sipush #8018
        /*    */     //   638: ldc_w 'header-column'
        /*    */     //   641: invokevirtual SB : (ILjava/lang/String;)Lf/nJ0;
        /*    */     //   644: ldc_w 92.0
        /*    */     //   647: invokevirtual Ig0 : (F)Lf/nJ0;
        /*    */     //   650: invokevirtual Kw : ()Lf/nJ0;
        /*    */     //   653: pop
        /*    */     //   654: sipush #8019
        /*    */     //   657: ldc_w 'header-column'
        /*    */     //   660: invokevirtual SB : (ILjava/lang/String;)Lf/nJ0;
        /*    */     //   663: astore_0
        /*    */     //   664: invokestatic XU : ()Z
        /*    */     //   667: ifeq -> 677
        /*    */     //   670: ldc_w 48.0
        /*    */     //   673: fstore_1
        /*    */     //   674: goto -> 681
        /*    */     //   677: ldc_w 90.0
        /*    */     //   680: fstore_1
        /*    */     //   681: aload_2
        /*    */     //   682: aload_0
        /*    */     //   683: fload_1
        /*    */     //   684: invokevirtual Ig0 : (F)Lf/nJ0;
        /*    */     //   687: invokevirtual Kw : ()Lf/nJ0;
        /*    */     //   690: pop
        /*    */     //   691: sipush #8020
        /*    */     //   694: ldc_w 'header-column'
        /*    */     //   697: invokevirtual SB : (ILjava/lang/String;)Lf/nJ0;
        /*    */     //   700: astore_0
        /*    */     //   701: invokestatic Nr : ()Z
        /*    */     //   704: ifeq -> 714
        /*    */     //   707: ldc_w 105.0
        /*    */     //   710: fstore_1
        /*    */     //   711: goto -> 718
        /*    */     //   714: ldc_w 140.0
        /*    */     //   717: fstore_1
        /*    */     //   718: aload_2
        /*    */     //   719: aload_0
        /*    */     //   720: fload_1
        /*    */     //   721: invokevirtual Ig0 : (F)Lf/nJ0;
        /*    */     //   724: invokevirtual Kw : ()Lf/nJ0;
        /*    */     //   727: pop
        /*    */     //   728: sipush #8021
        /*    */     //   731: ldc_w 'header-column'
        /*    */     //   734: invokevirtual SB : (ILjava/lang/String;)Lf/nJ0;
        /*    */     //   737: astore_0
        /*    */     //   738: invokestatic Nr : ()Z
        /*    */     //   741: ifeq -> 751
        /*    */     //   744: ldc_w 105.0
        /*    */     //   747: fstore_1
        /*    */     //   748: goto -> 755
        /*    */     //   751: ldc_w 140.0
        /*    */     //   754: fstore_1
        /*    */     //   755: aload_0
        /*    */     //   756: fload_1
        /*    */     //   757: invokevirtual Ig0 : (F)Lf/nJ0;
        /*    */     //   760: invokevirtual Kw : ()Lf/nJ0;
        /*    */     //   763: pop
        /*    */     //   764: goto -> 955
        /*    */     //   767: aload_0
        /*    */     //   768: new f/Un
        /*    */     //   771: dup
        /*    */     //   772: astore_0
        /*    */     //   773: sipush #8037
        /*    */     //   776: invokestatic OH0 : (I)Ljava/lang/String;
        /*    */     //   779: invokespecial <init> : (Ljava/lang/String;)V
        /*    */     //   782: getfield YD0 : [Lf/bh;
        /*    */     //   785: aload_1
        /*    */     //   786: getfield HC0 : B
        /*    */     //   789: aaload
        /*    */     //   790: dup
        /*    */     //   791: astore_1
        /*    */     //   792: invokevirtual CG0 : ()B
        /*    */     //   795: ifne -> 808
        /*    */     //   798: aload_0
        /*    */     //   799: ldc_w 'header-column-sort-desc'
        /*    */     //   802: invokevirtual Xu : (Ljava/lang/String;)V
        /*    */     //   805: goto -> 833
        /*    */     //   808: aload_1
        /*    */     //   809: invokevirtual CG0 : ()B
        /*    */     //   812: iconst_1
        /*    */     //   813: if_icmpne -> 826
        /*    */     //   816: aload_0
        /*    */     //   817: ldc_w 'header-column-sort-asc'
        /*    */     //   820: invokevirtual Xu : (Ljava/lang/String;)V
        /*    */     //   823: goto -> 833
        /*    */     //   826: aload_0
        /*    */     //   827: ldc_w 'header-column-sort-default'
        /*    */     //   830: invokevirtual Xu : (Ljava/lang/String;)V
        /*    */     //   833: aload_2
        /*    */     //   834: aload_0
        /*    */     //   835: dup
        /*    */     //   836: aload_1
        /*    */     //   837: <illegal opcode> run : (Lf/bh;)Ljava/lang/Runnable;
        /*    */     //   842: invokevirtual tW : (Ljava/lang/Runnable;)V
        /*    */     //   845: invokevirtual S7 : (Ljava/lang/Object;)Lf/nJ0;
        /*    */     //   848: invokevirtual Kw : ()Lf/nJ0;
        /*    */     //   851: astore_0
        /*    */     //   852: invokestatic XU : ()Z
        /*    */     //   855: ifeq -> 865
        /*    */     //   858: ldc_w 150.0
        /*    */     //   861: fstore_1
        /*    */     //   862: goto -> 869
        /*    */     //   865: ldc_w 92.0
        /*    */     //   868: fstore_1
        /*    */     //   869: aload_0
        /*    */     //   870: fload_1
        /*    */     //   871: invokevirtual Ig0 : (F)Lf/nJ0;
        /*    */     //   874: pop
        /*    */     //   875: invokestatic Nr : ()Z
        /*    */     //   878: ifeq -> 918
        /*    */     //   881: aload_2
        /*    */     //   882: sipush #8013
        /*    */     //   885: ldc_w 'header-column'
        /*    */     //   888: invokevirtual SB : (ILjava/lang/String;)Lf/nJ0;
        /*    */     //   891: invokevirtual Kw : ()Lf/nJ0;
        /*    */     //   894: astore_0
        /*    */     //   895: invokestatic XU : ()Z
        /*    */     //   898: ifeq -> 908
        /*    */     //   901: ldc_w 120.0
        /*    */     //   904: fstore_1
        /*    */     //   905: goto -> 912
        /*    */     //   908: ldc_w 92.0
        /*    */     //   911: fstore_1
        /*    */     //   912: aload_0
        /*    */     //   913: fload_1
        /*    */     //   914: invokevirtual Ig0 : (F)Lf/nJ0;
        /*    */     //   917: pop
        /*    */     //   918: aload_2
        /*    */     //   919: sipush #8014
        /*    */     //   922: ldc_w 'header-column'
        /*    */     //   925: invokevirtual SB : (ILjava/lang/String;)Lf/nJ0;
        /*    */     //   928: invokevirtual Kw : ()Lf/nJ0;
        /*    */     //   931: astore_0
        /*    */     //   932: invokestatic XU : ()Z
        /*    */     //   935: ifeq -> 945
        /*    */     //   938: ldc_w 100.0
        /*    */     //   941: fstore_1
        /*    */     //   942: goto -> 949
        /*    */     //   945: ldc_w 96.0
        /*    */     //   948: fstore_1
        /*    */     //   949: aload_0
        /*    */     //   950: fload_1
        /*    */     //   951: invokevirtual Ig0 : (F)Lf/nJ0;
        /*    */     //   954: pop
        /*    */     //   955: aload_2
        /*    */     //   956: invokevirtual wP : ()Lf/nJ0;
        /*    */     //   959: pop
        /*    */     //   960: invokestatic XU : ()Z
        /*    */     //   963: ifeq -> 983
        /*    */     //   966: aload #4
        /*    */     //   968: ifnull -> 983
        /*    */     //   971: aload #4
        /*    */     //   973: aload_2
        /*    */     //   974: getfield Nb0 : I
        /*    */     //   977: invokestatic valueOf : (I)Ljava/lang/Integer;
        /*    */     //   980: putfield ss : Ljava/lang/Integer;
        /*    */     //   983: return
        /*    */     // Line number table:
        /*    */     //   Java source line number -> byte code offset
        /*    */     //   #1	-> 21
        /*    */     //   #2	-> 24
        /*    */     //   #3	-> 35
        /*    */     //   #4	-> 41
        /*    */     //   #5	-> 59
        /*    */     //   #6	-> 62
        /*    */     //   #7	-> 66
        /*    */     //   #8	-> 78
        /*    */     //   #9	-> 86
        /*    */     //   #10	-> 100
        /*    */     //   #11	-> 108
        /*    */     //   #12	-> 155
        /*    */     //   #13	-> 158
        /*    */     //   #14	-> 169
        /*    */     //   #15	-> 233
        /*    */     //   #16	-> 236
        /*    */     //   #17	-> 323
        /*    */     //   #18	-> 338
        /*    */     //   #19	-> 430
        /*    */     //   #20	-> 445
        /*    */     //   #21	-> 566
        /*    */     //   #22	-> 569
        /*    */     //   #23	-> 786
        /*    */     //   #24	-> 789
        /*    */     //   #25	-> 974
        /*    */     //   #26	-> 977
        /*    */     //   #27	-> 980
        /*    */
    }

    /*    */
    /*    */
    public final void Ky0(fv0 paramfv0) {
        /*    */
        if ((this.Vi = paramfv0.Z6) == Te.Qu) {
            /*    */
            Runnable runnable1;
            /*    */
            AD0 aD02, aD01;
            /*    */
            if ((aD01 = (AD0) vC0.Bv0(js.vu0, AD0.class)) != null)
                /*    */ js.vu0.jf0(aD01);
            /*    */
            String str1 = Ml0.OH0((Of.eH.On0(paramfv0.bn)).Iu);
            /*    */
            if (paramfv0.gh < 2) {
                /*    */
                h70 h70;
                /*    */
                String[] arrayOfString;
                /*    */
                (arrayOfString = new String[3])[0] = "1";
                /*    */
                (new String[3])[1] = str1;
                /*    */
                (new String[3])[2] = B40.df("$").append(NumberFormat.getInstance().format(paramfv0.B90)).toString();
                /*    */
                str1 = Ml0.sB(8039, arrayOfString);
                /*    */
                runnable1 = paramfv0::Wj;
                /*    */
                this(str1, this, e9());
                /*    */
            } else {
                /*    */
                gZ gZ;
                /*    */
                str = Ml0.Go(8031, str1);
                /*    */
                short s = paramfv0.gh;
                /*    */
                this(str1, paramfv0);
                /*    */
                jG0 = e9();
                /*    */
                this(this, s, gZ, jG0);
                /*    */
            }
            /*    */
            js.vu0.si(aD02, js.vu0.Ub());
            /*    */
            return;
            /*    */
        }
        /*    */
        this();
        /*    */
        String str;
        /*    */
        JG0 jG0;
        /*    */
        YA0 yA0;
        /*    */
        SA sA;
        /*    */
        MW((fv0) jG0, sA = (new YA0()).Dv0);
        /*    */
        if (((fv0) jG0).Z6 == Te.QK0) {
            /*    */
            String str1;
            /*    */
            short s;
            /*    */
            byte b;
            /*    */
            Q90 q90;
            /*    */
            if ((q90 = ((fv0) jG0).mm0) != null) {
                /*    */
                b = q90.od;
                /*    */
            } else {
                /*    */
                b = ((fv0) jG0).nj0;
                /*    */
            }
            /*    */
            if (q90 != null) {
                /*    */
                s = q90.Cw0;
                /*    */
            } else {
                /*    */
                s = ((fv0) jG0).bn;
                /*    */
            }
            /*    */
            if (b > km.u4.fF0.ry0(km.a3.eA)) {
                /*    */
                str1 = Ml0.OH0(s + 150000);
                /*    */
                arrayOfString[0] = str1;
                /*    */
                String[] arrayOfString;
                /*    */
                (arrayOfString = new String[2])[1] = Integer.toString(b);
                /*    */
                (sA.IR(Ml0.sB(8038, arrayOfString)).fa0(15.0F).AuX(10.0F)).ss = Integer.valueOf(4);
                /*    */
            } else {
                /*    */
                (str1.mv0(8032)).ss = Integer.valueOf(4);
                /*    */
                str1.mv0(8032).fa0(10.0F).AuX(10.0F);
                /*    */
            }
            /*    */
        }
        /*    */
        Runnable runnable = jG0::Bg;
        /*    */
        js.vu0.uh(new h70(yA0, this, e9(), 1));
        /*    */
    }

    /*    */
    /*    */
    public final void ua(fv0 paramfv0) {
        /*    */
        if (!this.zk) {
            /*    */
            km.u4.Pq(Ml0.OH0(8029));
            /*    */
            return;
            /*    */
        }
        /*    */
        this();
        /*    */
        YA0 yA0;
        /*    */
        MW(paramfv0, (new YA0()).Dv0);
        /*    */
        ((new YA0()).Dv0.mv0(8030).fa0(10.0F).AuX(10.0F)).ss = Integer.valueOf(4);
        /*    */
        ((new YA0()).Dv0.mv0(8030).fa0(10.0F).AuX(10.0F)).Ox.wP();
        /*    */
        js.vu0.uh(new h70(this, paramfv0::kA));
        /*    */
    }

    /*    */
    /*    */
    public final void WB() {
        /*    */
        this.bl.l4(0);
        /*    */
        this.bk.zf(null);
        /*    */
        this.ii.Tm0(null);
        /*    */
        T10();
        /*    */
    }

    /*    */
    /*    */
    public final void d40() {
        /*    */
        super.d40();
        /*    */
        if (km.XU()) {
            /*    */
            ME(0, 0);
            /*    */
            Tm(this.Bo0.xY, this.Bo0.HC);
            /*    */
            this.sr.xQ.mM();
            /*    */
            et et = et.COM2;
            /*    */
            byte b1 = 0, b2 = 0;
            /*    */
            JG0 jG0;
            /*    */
            if ((jG0 = this.sr.xQ).fr0 != null) {
                /*    */
                int i = jG0.Bo0.xY;
                /*    */
                i = et.Sp(i, jG0.xY) + b1;
                /*    */
                int j = jG0.Bo0.HC;
                /*    */
                jG0.ME(i, et.nV(j, jG0.HC) + b2);
                /*    */
            }
            /*    */
            this.Ki.mM();
            /*    */
            this.Ki.QJ0(et.t9, 0, 0);
            /*    */
            this.kM = 0;
            /*    */
        } else if (!this.i6) {
            /*    */
            this.i6 = true;
            /*    */
            js0(et.Wi0);
            /*    */
        }
        /*    */
    }

    /*    */
    /*    */
    public final void IG0() {
        /*    */
        VA0.c90(this.sr);
        /*    */
    }

    /*    */
    /*    */
    public final boolean i2(oa0 paramoa0) {
        /*    */
        JG0 jG0;
        /*    */
        if (B8.Wm0(paramoa0.cz0) && paramoa0.oO()) {
            /*    */
            if (js.com3(this))
                /*    */ return super.i2(paramoa0);
            /*    */
            int i = paramoa0.GG0;
            /*    */
            if (this.sr.p3() && this.sr.LG == null) {
                /*    */
                if (h1.J20(i, BM.Oq) || h1.J20(i, BM.fN)) {
                    /*    */
                    this.sr.E00(-1);
                    /*    */
                    if ((jG0 = this.sr.LG) != null)
                        /*    */ xI0();
                    /*    */
                    return true;
                    /*    */
                }
                /*    */
                if (h1.J20(i, BM.M8) || h1.J20(i, BM.PW)) {
                    /*    */
                    ((A) super).sr.E00(1);
                    /*    */
                    if ((jG0 = ((A) super).sr.LG) != null)
                        /*    */ xI0();
                    /*    */
                    return true;
                    /*    */
                }
                /*    */
                if (h1.J20(i, BM.lc)) {
                    /*    */
                    super.close();
                    /*    */
                    return true;
                    /*    */
                }
                /*    */
                if (h1.J20(i, BM.bC)) {
                    /*    */
                    if (((A) super).sr.nv0() >= 3) {
                        /*    */
                        if (((A) super).sr.nv0() == 3)
                            /*    */ ((A) super).X3.Ev0();
                        /*    */
                    } else {
                        /*    */
                        ((A) super).YD0[((A) super).sr.nv0()].x10(0, 0);
                        /*    */
                    }
                    /*    */
                    return true;
                    /*    */
                }
                /*    */
            }
            /*    */
            of of1;
            /*    */
            if (paramoa0.GG0 == 34 && paramoa0.com8 == 4 && (of1 = (((A) super).YD0[((A) super).sr.nv0()]).mo0) != null) {
                /*    */
                of1.BA();
                /*    */
                return true;
                /*    */
            }
            /*    */
        }
        /*    */
        return super.i2(paramoa0);
        /*    */
    }

    /*    */
    /*    */
    public final boolean jf0(JG0 paramJG0) {
        /*    */
        if (paramJG0 == this.z8)
            /*    */ this.z8 = null;
        /*    */
        return super.jf0(paramJG0);
        /*    */
    }

    /*    */
    /*    */
    public final void V90(throws paramthrows) {
        /*    */
        super.V90(paramthrows);
        /*    */
        if (p3() && this.LG == null)
            /*    */ VA0.c90(this.sr);
        /*    */
    }
    /*    */
    /*    */   public final Ip this()

    {
        /*    */
        this();
        /*    */
        Ip ip;
        /*    */
        rS rS;
        /*    */
        (this.vz0 = new YA0()).Xu("/broker-table");
        /*    */
        if (km.Nr())
            /*    */ this.vz0.Dv0.RT.sg(2.0F);
        /*    */
        byte b1 = 38, b2 = 0;
        /*    */
        char c = Character.MIN_VALUE;
        /*    */
        if (km.XU()) {
            /*    */
            b1 = 61;
            /*    */
            b2 = 61;
            /*    */
            c = 'ĝ';
            /*    */
        }
        /*    */
        this(this.vz0);
        /*    */
        (new rS()).zG0(2);
        /*    */
        ip.rK0(new g0(ip));
        /*    */
        ip.WN(new cr0(ip));
        /*    */
        ip.Xz0.ee0(ip.vo0(new JG0[]{rS}).Aq(c));
        /*    */
        ip.o30.ee0((new cr0(ip)).Aq(b1).Ya(rS).Aq(b2));
        /*    */
        return ip;
        /*    */
    }
}


/* Location:              /Users/vnnsnnt/Documents/Codespace/JavaWorkspace/RedTrainer/src/main/java/org/trainer/client/PokeMMO.jar!/f/A.class
 * Java compiler version: 8 (52.0)
 * JD-Core Version:       1.1.3
 */