/*    */ package f;public final class aC0 extends so0 { public fl Ly0; public aC0(sM paramsM) { super(null, (short)0); this.ge.s6(Ml0.OH0(56)); this.ge.tW(new iL0(this, paramsM)); fa0(Of.b20().On0(paramsM.i4())); } public aC0(Y paramY) { // Byte code:
/*    */     //   0: aload_0
/*    */     //   1: aload_1
/*    */     //   2: aload_0
/*    */     //   3: dup
/*    */     //   4: dup
/*    */     //   5: aconst_null
/*    */     //   6: iconst_0
/*    */     //   7: invokespecial <init> : (Lf/Vp0;S)V
/*    */     //   10: getfield ge : Lf/Un;
/*    */     //   13: sipush #8501
/*    */     //   16: invokestatic OH0 : (I)Ljava/lang/String;
/*    */     //   19: invokevirtual s6 : (Ljava/lang/String;)V
/*    */     //   22: getfield ge : Lf/Un;
/*    */     //   25: aload_0
/*    */     //   26: aload_1
/*    */     //   27: <illegal opcode> run : (Lf/aC0;Lf/Y;)Ljava/lang/Runnable;
/*    */     //   32: invokevirtual tW : (Ljava/lang/Runnable;)V
/*    */     //   35: invokevirtual Ng : ()Lf/LPT3;
/*    */     //   38: invokevirtual fa0 : (Lf/LPT3;)V
/*  1 */     //   41: return } private void q90() { this.fr0
/*  2 */       .jf0(this); } private void yK(Y paramY) { // Byte code:
/*    */     //   0: aload_0
/*    */     //   1: getfield Ly0 : Lf/fl;
/*    */     //   4: getfield hC0 : S
/*    */     //   7: iconst_1
/*    */     //   8: if_icmpge -> 24
/*    */     //   11: getstatic f/km.u4 : Lf/R8;
/*    */     //   14: sipush #8504
/*    */     //   17: invokestatic OH0 : (I)Ljava/lang/String;
/*    */     //   20: invokevirtual Pq : (Ljava/lang/String;)V
/*    */     //   23: return
/*    */     //   24: getstatic f/js.vu0 : Lf/js;
/*    */     //   27: new f/h70
/*    */     //   30: dup
/*    */     //   31: aload_0
/*    */     //   32: aload_1
/*    */     //   33: sipush #8502
/*    */     //   36: invokestatic OH0 : (I)Ljava/lang/String;
/*    */     //   39: astore_1
/*    */     //   40: <illegal opcode> run : (Lf/aC0;Lf/Y;)Ljava/lang/Runnable;
/*    */     //   45: aload_1
/*    */     //   46: swap
/*    */     //   47: aload_0
/*    */     //   48: invokespecial <init> : (Ljava/lang/String;Ljava/lang/Runnable;Lf/JG0;)V
/*    */     //   51: invokevirtual uh : (Lf/h70;)V
/*    */     //   54: return
/*    */     // Line number table:
/*    */     //   Java source line number -> byte code offset
/*    */     //   #1	-> 4
/*    */     //   #2	-> 11
/*    */     //   #3	-> 24
/*  2 */     //   #4	-> 27 } private void Hr(Y paramY) { this.fr0.jf0(this);
/*    */     
/*  4 */     short s = paramY.Lh.p1;
/*  5 */     int i = paramY.Lh.Wy;
/*    */     
/*  7 */     int j = this.Ly0.Yn0;
/*  8 */     Dn0 dn0 = this.UF;
/*    */ 
/*    */ 
/*    */     
/* 12 */     s = dn0.QL0[dn0.wh0.gw0];
/* 13 */     km.u4.tq0(s, i, j, (short)1, s); } public final void fa0(LPT3 paramLPT3) { Xu("previewwidget"); this.ms0 = new Ip(); this.Zc.tW(this::q90); String str = Ml0.OH0(8500); this(); dQ dQ; (new dQ()).E1(str); Dn0 dn0 = this.UF; this.Ly0 = new fl(dn0, this.qf); Ip ip2 = this.ms0; si(ip2, Ub()); this.Yp0.wI0(true); UX[] arrayOfUX; int i; byte b; for (i = (arrayOfUX = UX.jj).length, b = 0; b < i; ) { UX uX; byte b1; if ((b1 = (uX = arrayOfUX[b]).Ii) < paramLPT3.ED0 || b1 > paramLPT3.bi)
/* 14 */       { this.qf[b1].sk0(false); byte b2 = (byte)uX.mZ.Mv();
/*    */         
/*    */         Un un;
/* 17 */         (un = this.qf[uX.Ii]).db0 = new I(un, new pRn((byte)uX.mZ.k90(), b2, (byte)uX.mZ.jz(), (byte)60)); }  b++; }
/*    */ 
/*    */     
/* 20 */     arrayOfU902[0] = this.ms0.AUX(new JG0[] { this.Yp0 }); arrayOfU902[1] = this.ms0.AUX(new JG0[] { dQ, this.Ly0 }); arrayOfU902[2] = this.ms0.AUX(new JG0[] { this.HK, this.Lj0 }); arrayOfU902[3] = this.ms0.AUX(new JG0[] { this.DW }); U90[] arrayOfU902; (arrayOfU902 = new U90[5])[4] = this.ms0.vo0(new JG0[] { this.ge, this.Zc }); this.ms0.WN(V2.Ur(this.ms0, this.ms0).cOM8(new U90[5]));
/*    */     Ip ip1;
/* 22 */     (ip1 = this.ms0).getClass(); (new U90[2])[
/*    */         
/* 24 */         0] = (new cr0(ip1)).Em0().Ya(this.Yp0).Em0(); (ip1 = this.ms0).getClass();
/*    */ 
/*    */ 
/*    */     
/* 28 */     arrayOfU901[0] = this.ms0.vo0(new JG0[] { dQ }).Aq(10).Ya(this.Ly0); arrayOfU901[1] = this.ms0.vo0(new JG0[] { this.HK }).Em0().Ya(this.Lj0); arrayOfU901[2] = this.ms0.vo0(new JG0[] { this.DW }); U90[] arrayOfU901; (arrayOfU901 = new U90[4])[3] = this.ms0.AUX(new JG0[] { this.ge, this.Zc }); this.ms0.rK0(Mr.X60(this.ms0, this.ms0).cOM8(new U90[] { null, (new cr0(ip1)).Aq(300).ee0(Mr.X60(this.ms0, this.ms0).cOM8(new U90[4])) })); }
/*    */ 
/*    */   
/*    */   public final void LM(throws paramthrows) {
/*    */     VA0.c90(this);
/*    */   }
/*    */   
/*    */   public final void d40() {
/*    */     this.ms0.mM();
/*    */     mM();
/*    */     ec(et.Wi0, 0);
/*    */   } }


/* Location:              /Users/vnnsnnt/Documents/Codespace/JavaWorkspace/RedTrainer/src/main/java/org/trainer/client/PokeMMO.jar!/f/aC0.class
 * Java compiler version: 8 (52.0)
 * JD-Core Version:       1.1.3
 */