/*    */ package f;public final class AD0 extends Qa0 implements r60 { public final Ip i2; public final Un cOm6; public final zT COM5; public Un[] DJ0; public int OJ0; public AD0(String paramString, int paramInt, q5 paramq5, JG0 paramJG0) { // Byte code:
/*    */     //   0: aload_0
/*    */     //   1: dup
/*    */     //   2: dup2
/*    */     //   3: invokestatic XU : ()Z
/*    */     //   6: invokespecial <init> : (Z)V
/*    */     //   9: iconst_3
/*    */     //   10: putfield OJ0 : I
/*    */     //   13: ldc 'confirm-widget'
/*    */     //   15: invokevirtual Xu : (Ljava/lang/String;)V
/*    */     //   18: new f/Ip
/*    */     //   21: dup
/*    */     //   22: dup2
/*    */     //   23: dup2
/*    */     //   24: astore #5
/*    */     //   26: aload_0
/*    */     //   27: dup
/*    */     //   28: aload #5
/*    */     //   30: aload_0
/*    */     //   31: aload #5
/*    */     //   33: dup
/*    */     //   34: invokespecial <init> : ()V
/*    */     //   37: putfield i2 : Lf/Ip;
/*    */     //   40: ldc 'confirm-panel'
/*    */     //   42: invokevirtual Xu : (Ljava/lang/String;)V
/*    */     //   45: new f/dQ
/*    */     //   48: dup
/*    */     //   49: dup
/*    */     //   50: astore #6
/*    */     //   52: aload_1
/*    */     //   53: invokespecial <init> : (Ljava/lang/String;)V
/*    */     //   56: ldc 'label'
/*    */     //   58: invokevirtual Xu : (Ljava/lang/String;)V
/*    */     //   61: new f/zT
/*    */     //   64: dup
/*    */     //   65: dup
/*    */     //   66: astore_1
/*    */     //   67: iconst_1
/*    */     //   68: iload_2
/*    */     //   69: iconst_1
/*    */     //   70: invokespecial <init> : (III)V
/*    */     //   73: putfield COM5 : Lf/zT;
/*    */     //   76: new f/Rm
/*    */     //   79: dup
/*    */     //   80: astore #7
/*    */     //   82: aload_1
/*    */     //   83: invokespecial <init> : (Lf/zT;)V
/*    */     //   86: new f/Un
/*    */     //   89: dup
/*    */     //   90: astore_1
/*    */     //   91: aload_0
/*    */     //   92: iload_2
/*    */     //   93: aload_1
/*    */     //   94: bipush #49
/*    */     //   96: invokestatic OH0 : (I)Ljava/lang/String;
/*    */     //   99: invokespecial <init> : (Ljava/lang/String;)V
/*    */     //   102: <illegal opcode> run : (Lf/AD0;I)Ljava/lang/Runnable;
/*    */     //   107: invokevirtual tW : (Ljava/lang/Runnable;)V
/*    */     //   110: new f/Un
/*    */     //   113: dup
/*    */     //   114: astore_2
/*    */     //   115: aload_0
/*    */     //   116: aload_3
/*    */     //   117: aload_2
/*    */     //   118: bipush #60
/*    */     //   120: invokestatic OH0 : (I)Ljava/lang/String;
/*    */     //   123: invokespecial <init> : (Ljava/lang/String;)V
/*    */     //   126: aload #4
/*    */     //   128: <illegal opcode> run : (Lf/AD0;Lf/q5;Lf/JG0;)Ljava/lang/Runnable;
/*    */     //   133: invokevirtual tW : (Ljava/lang/Runnable;)V
/*    */     //   136: new f/Un
/*    */     //   139: dup
/*    */     //   140: astore_3
/*    */     //   141: aload_0
/*    */     //   142: aload #4
/*    */     //   144: aload_0
/*    */     //   145: aload_3
/*    */     //   146: dup
/*    */     //   147: bipush #53
/*    */     //   149: invokestatic OH0 : (I)Ljava/lang/String;
/*    */     //   152: invokespecial <init> : (Ljava/lang/String;)V
/*    */     //   155: putfield cOm6 : Lf/Un;
/*    */     //   158: <illegal opcode> run : (Lf/AD0;Lf/JG0;)Ljava/lang/Runnable;
/*    */     //   163: invokevirtual tW : (Ljava/lang/Runnable;)V
/*    */     //   166: iconst_5
/*    */     //   167: anewarray f/Un
/*    */     //   170: dup
/*    */     //   171: dup2
/*    */     //   172: dup2
/*    */     //   173: aload #7
/*    */     //   175: swap
/*    */     //   176: aload #7
/*    */     //   178: getfield mc0 : Lf/Un;
/*    */     //   181: iconst_0
/*    */     //   182: swap
/*    */     //   183: aastore
/*    */     //   184: getfield Xx : Lf/Un;
/*    */     //   187: iconst_1
/*    */     //   188: swap
/*    */     //   189: aastore
/*    */     //   190: iconst_2
/*    */     //   191: aload_1
/*    */     //   192: aastore
/*    */     //   193: iconst_3
/*    */     //   194: aload_2
/*    */     //   195: aastore
/*    */     //   196: iconst_4
/*    */     //   197: aload_3
/*    */     //   198: aastore
/*    */     //   199: putfield DJ0 : [Lf/Un;
/*    */     //   202: invokevirtual d7 : ()Lf/cr0;
/*    */     //   205: aload #6
/*    */     //   207: invokevirtual Ya : (Lf/JG0;)Lf/U90;
/*    */     //   210: aload #5
/*    */     //   212: invokevirtual mE0 : ()Lf/g0;
/*    */     //   215: iconst_2
/*    */     //   216: anewarray f/JG0
/*    */     //   219: dup
/*    */     //   220: dup
/*    */     //   221: iconst_0
/*    */     //   222: aload #7
/*    */     //   224: aastore
/*    */     //   225: iconst_1
/*    */     //   226: aload_1
/*    */     //   227: aastore
/*    */     //   228: invokevirtual Mg : ([Lf/JG0;)Lf/U90;
/*    */     //   231: invokevirtual ee0 : (Lf/U90;)Lf/U90;
/*    */     //   234: aload #5
/*    */     //   236: invokevirtual d7 : ()Lf/cr0;
/*    */     //   239: iconst_2
/*    */     //   240: anewarray f/JG0
/*    */     //   243: dup
/*    */     //   244: dup
/*    */     //   245: iconst_0
/*    */     //   246: aload_2
/*    */     //   247: aastore
/*    */     //   248: iconst_1
/*    */     //   249: aload_3
/*    */     //   250: aastore
/*    */     //   251: invokevirtual Mg : ([Lf/JG0;)Lf/U90;
/*    */     //   254: invokevirtual ee0 : (Lf/U90;)Lf/U90;
/*    */     //   257: invokevirtual Em0 : ()Lf/U90;
/*    */     //   260: invokevirtual WN : (Lf/U90;)V
/*    */     //   263: invokevirtual mE0 : ()Lf/g0;
/*    */     //   266: aload #6
/*    */     //   268: invokevirtual Ya : (Lf/JG0;)Lf/U90;
/*    */     //   271: aload #5
/*    */     //   273: invokevirtual d7 : ()Lf/cr0;
/*    */     //   276: aload #7
/*    */     //   278: invokevirtual Ya : (Lf/JG0;)Lf/U90;
/*    */     //   281: invokevirtual Em0 : ()Lf/U90;
/*    */     //   284: aload_1
/*    */     //   285: invokevirtual Ya : (Lf/JG0;)Lf/U90;
/*    */     //   288: invokevirtual ee0 : (Lf/U90;)Lf/U90;
/*    */     //   291: aload #5
/*    */     //   293: invokevirtual mE0 : ()Lf/g0;
/*    */     //   296: aload_2
/*    */     //   297: invokevirtual Ya : (Lf/JG0;)Lf/U90;
/*    */     //   300: aload_3
/*    */     //   301: invokevirtual Ya : (Lf/JG0;)Lf/U90;
/*    */     //   304: invokevirtual ee0 : (Lf/U90;)Lf/U90;
/*    */     //   307: invokevirtual rK0 : (Lf/U90;)V
/*    */     //   310: invokevirtual J8 : (Lf/JG0;)V
/*  1 */     //   313: return } private void Zr(q5 paramq5, JG0 paramJG0) { paramq5
/*  2 */       .AB0(this.COM5.hk); ra0(); if (paramJG0 != null) VA0.c90(paramJG0);  } public final void LM(throws paramthrows) { super.LM(paramthrows); /* monitor enter BinaryOperatorExpression{ClassFileLocalVariableReferenceExpression{type=ObjectType{java/lang/Object}, name=null} = FieldReferenceExpression{lastType=ObjectType{java/lang/Object}, expression=ClassFileLocalVariableReferenceExpression{type=ObjectType{f/throws}, name=paramthrows}, name=zr0, descriptor=Ljava/lang/Object;}} */ Runnable runnable; if ((runnable = (() -> VA0.c90(this.DJ0[this.OJ0]))) != null) { Object object; try { int j; Runnable[] arrayOfRunnable; if ((j = paramthrows.ey) == (arrayOfRunnable = paramthrows.AT).length) { arrayOfRunnable = new Runnable[j * 2]; System.arraycopy(arrayOfRunnable, 0, arrayOfRunnable, 0, j); paramthrows.AT = arrayOfRunnable; }
/*  3 */          int i; paramthrows.ey = (i = paramthrows.ey) + 1; return; } finally { runnable = null; /* monitor exit ClassFileLocalVariableReferenceExpression{type=ObjectType{java/lang/Object}, name=null} */ }  }  throw new IllegalArgumentException("runnable is null"); } public final void d40() { super.d40(); this.i2.mM(); QI(); this.i2.js0(et.Wi0); } public final boolean i2(oa0 paramoa0) { Un[] arrayOfUn; if (B8.Wm0(paramoa0.cz0) && paramoa0.oO())
/*    */     { int i;
/*  5 */       if (h1.J20(i = paramoa0.GG0, BM.bC)) {
/*    */ 
/*    */         
/*  8 */         hm.Fz0((this.DJ0[this.OJ0]).TG0.oh0); return true;
/*  9 */       }  if (h1.J20(i, BM.lc)) {
/*    */ 
/*    */         
/* 12 */         hm.Fz0(this.cOm6.TG0.oh0); return true;
/* 13 */       }  if (h1.J20(i, BM.ni)) { if (--this.OJ0 < 0) this.OJ0 = 0;  VA0.c90(this.DJ0[this.OJ0]); return true; }  if (h1.J20(i, BM.N70)) { this.OJ0 = j; int j; if ((j = this.OJ0 + 1) >= (arrayOfUn = this.DJ0).length - 1) this.OJ0 = arrayOfUn.length - 1;  VA0.c90(arrayOfUn[this.OJ0]); return true; }  if (h1.J20(i, BM.Oq)) { if (--this.OJ0 < 0) this.OJ0 = 0;  VA0.c90(this.DJ0[this.OJ0]); return true; }  if (h1.J20(i, BM.M8)) { this.OJ0 = j; int j; if ((j = this.OJ0 + 1) >= (arrayOfUn = this.DJ0).length - 1) this.OJ0 = arrayOfUn.length - 1;  VA0.c90(arrayOfUn[this.OJ0]); return true; }  }  return super.i2((oa0)arrayOfUn); }
/*    */    }


/* Location:              /Users/vnnsnnt/Documents/Codespace/JavaWorkspace/RedTrainer/src/main/java/org/trainer/client/PokeMMO.jar!/f/AD0.class
 * Java compiler version: 8 (52.0)
 * JD-Core Version:       1.1.3
 */