/* 1 */ package f;public final class AF0 { public final void Hj0() { fl0.Qi0.info("Error report submission failed"); km.f70.iJ0(Ml0.la(40, "Fatal Render Error"), Ml0.la(43, "Error submitting error report."), LP.Od0, new s0(this), false); }
/*   */ 
/*   */   
/*   */   public AF0(boolean paramBoolean) {}
/*   */   
/*   */   public final void bR(uy paramuy) {
/*   */     // Byte code:
/*   */     //   0: aload_1
/*   */     //   1: getstatic f/fl0.Qi0 : Lf/ik;
/*   */     //   4: ldc 'Error report status code: '
/*   */     //   6: invokestatic df : (Ljava/lang/String;)Ljava/lang/StringBuilder;
/*   */     //   9: aload_1
/*   */     //   10: getfield Mg : Lf/RH;
/*   */     //   13: getfield HG : I
/*   */     //   16: invokevirtual append : (I)Ljava/lang/StringBuilder;
/*   */     //   19: invokevirtual toString : ()Ljava/lang/String;
/*   */     //   22: invokeinterface info : (Ljava/lang/String;)V
/*   */     //   27: getfield RV : Ljava/net/HttpURLConnection;
/*   */     //   30: invokevirtual getInputStream : ()Ljava/io/InputStream;
/*   */     //   33: astore_2
/*   */     //   34: goto -> 52
/*   */     //   37: astore_1
/*   */     //   38: goto -> 601
/*   */     //   41: pop
/*   */     //   42: aload_1
/*   */     //   43: getfield RV : Ljava/net/HttpURLConnection;
/*   */     //   46: invokevirtual getErrorStream : ()Ljava/io/InputStream;
/*   */     //   49: goto -> 33
/*   */     //   52: aload_2
/*   */     //   53: ifnonnull -> 62
/*   */     //   56: ldc ''
/*   */     //   58: astore_2
/*   */     //   59: goto -> 93
/*   */     //   62: aload_2
/*   */     //   63: aload_1
/*   */     //   64: getfield RV : Ljava/net/HttpURLConnection;
/*   */     //   67: invokevirtual getContentLength : ()I
/*   */     //   70: invokestatic RK : (Ljava/io/InputStream;I)Ljava/lang/String;
/*   */     //   73: astore_3
/*   */     //   74: goto -> 87
/*   */     //   77: astore_1
/*   */     //   78: goto -> 595
/*   */     //   81: pop
/*   */     //   82: ldc ''
/*   */     //   84: goto -> 73
/*   */     //   87: aload_2
/*   */     //   88: invokestatic JC0 : (Ljava/io/Closeable;)V
/*   */     //   91: aload_3
/*   */     //   92: astore_2
/*   */     //   93: aload_1
/*   */     //   94: getstatic f/fl0.Qi0 : Lf/ik;
/*   */     //   97: new java/lang/StringBuilder
/*   */     //   100: dup
/*   */     //   101: invokespecial <init> : ()V
/*   */     //   104: ldc 'Raw Response: ''
/*   */     //   106: invokevirtual append : (Ljava/lang/String;)Ljava/lang/StringBuilder;
/*   */     //   109: aload_2
/*   */     //   110: invokevirtual append : (Ljava/lang/String;)Ljava/lang/StringBuilder;
/*   */     //   113: ldc '''
/*   */     //   115: invokevirtual append : (Ljava/lang/String;)Ljava/lang/StringBuilder;
/*   */     //   118: invokevirtual toString : ()Ljava/lang/String;
/*   */     //   121: invokeinterface info : (Ljava/lang/String;)V
/*   */     //   126: getfield Mg : Lf/RH;
/*   */     //   129: getfield HG : I
/*   */     //   132: sipush #200
/*   */     //   135: if_icmpne -> 612
/*   */     //   138: new f/nP
/*   */     //   141: dup
/*   */     //   142: aload_2
/*   */     //   143: swap
/*   */     //   144: invokespecial <init> : ()V
/*   */     //   147: invokevirtual toCharArray : ()[C
/*   */     //   150: dup
/*   */     //   151: arraylength
/*   */     //   152: invokevirtual Tg : ([CI)Lf/bM0;
/*   */     //   155: dup
/*   */     //   156: astore_1
/*   */     //   157: getstatic f/fl0.Qi0 : Lf/ik;
/*   */     //   160: astore_2
/*   */     //   161: new java/lang/StringBuilder
/*   */     //   164: dup
/*   */     //   165: invokespecial <init> : ()V
/*   */     //   168: ldc 'Response 'success': '
/*   */     //   170: invokevirtual append : (Ljava/lang/String;)Ljava/lang/StringBuilder;
/*   */     //   173: astore_3
/*   */     //   174: ldc 'success'
/*   */     //   176: dup
/*   */     //   177: astore #4
/*   */     //   179: invokevirtual Jb : (Ljava/lang/String;)Lf/bM0;
/*   */     //   182: dup
/*   */     //   183: astore #5
/*   */     //   185: ifnull -> 567
/*   */     //   188: aload_1
/*   */     //   189: aload_2
/*   */     //   190: aload_3
/*   */     //   191: aload #5
/*   */     //   193: invokevirtual gI0 : ()Z
/*   */     //   196: invokevirtual append : (Z)Ljava/lang/StringBuilder;
/*   */     //   199: invokevirtual toString : ()Ljava/lang/String;
/*   */     //   202: invokeinterface info : (Ljava/lang/String;)V
/*   */     //   207: getstatic f/fl0.Qi0 : Lf/ik;
/*   */     //   210: new java/lang/StringBuilder
/*   */     //   213: dup
/*   */     //   214: invokespecial <init> : ()V
/*   */     //   217: ldc 'Response 'id':  has '
/*   */     //   219: invokevirtual append : (Ljava/lang/String;)Ljava/lang/StringBuilder;
/*   */     //   222: aload_1
/*   */     //   223: ldc 'id'
/*   */     //   225: invokevirtual Ua : (Ljava/lang/String;)Z
/*   */     //   228: invokevirtual append : (Z)Ljava/lang/StringBuilder;
/*   */     //   231: ldc ' string: '
/*   */     //   233: invokevirtual append : (Ljava/lang/String;)Ljava/lang/StringBuilder;
/*   */     //   236: aload_1
/*   */     //   237: ldc 'id'
/*   */     //   239: invokevirtual ty : (Ljava/lang/String;)Ljava/lang/String;
/*   */     //   242: invokevirtual append : (Ljava/lang/String;)Ljava/lang/StringBuilder;
/*   */     //   245: invokevirtual toString : ()Ljava/lang/String;
/*   */     //   248: invokeinterface info : (Ljava/lang/String;)V
/*   */     //   253: ldc 'success'
/*   */     //   255: dup
/*   */     //   256: astore_2
/*   */     //   257: invokevirtual Jb : (Ljava/lang/String;)Lf/bM0;
/*   */     //   260: dup
/*   */     //   261: astore_3
/*   */     //   262: ifnull -> 540
/*   */     //   265: aload_3
/*   */     //   266: invokevirtual gI0 : ()Z
/*   */     //   269: ifeq -> 612
/*   */     //   272: aload_1
/*   */     //   273: ldc 'id'
/*   */     //   275: invokevirtual Ua : (Ljava/lang/String;)Z
/*   */     //   278: ifeq -> 612
/*   */     //   281: aload_1
/*   */     //   282: getstatic f/fl0.Qi0 : Lf/ik;
/*   */     //   285: ldc 'Valid all, doing clipboard'
/*   */     //   287: invokeinterface info : (Ljava/lang/String;)V
/*   */     //   292: ldc 'id'
/*   */     //   294: invokevirtual ty : (Ljava/lang/String;)Ljava/lang/String;
/*   */     //   297: astore_2
/*   */     //   298: getstatic f/km.iE0 : Lf/r9;
/*   */     //   301: dup
/*   */     //   302: astore_3
/*   */     //   303: ifnull -> 315
/*   */     //   306: aload_3
/*   */     //   307: aload_2
/*   */     //   308: invokevirtual Wf : (Ljava/lang/String;)Z
/*   */     //   311: pop
/*   */     //   312: goto -> 326
/*   */     //   315: getstatic f/UB0.Kg0 : Lf/Q50;
/*   */     //   318: invokevirtual getClass : ()Ljava/lang/Class;
/*   */     //   321: pop
/*   */     //   322: getstatic f/Dp0.uM : Lf/Dp0;
/*   */     //   325: pop
/*   */     //   326: aload_1
/*   */     //   327: getstatic f/fl0.Qi0 : Lf/ik;
/*   */     //   330: ldc 'Valid all, showing notification'
/*   */     //   332: invokeinterface info : (Ljava/lang/String;)V
/*   */     //   337: bipush #42
/*   */     //   339: istore_3
/*   */     //   340: ldc 'string_id'
/*   */     //   342: invokevirtual Ua : (Ljava/lang/String;)Z
/*   */     //   345: ifeq -> 398
/*   */     //   348: aload_1
/*   */     //   349: ldc 'string_id'
/*   */     //   351: dup
/*   */     //   352: astore_3
/*   */     //   353: invokevirtual Jb : (Ljava/lang/String;)Lf/bM0;
/*   */     //   356: dup
/*   */     //   357: astore #4
/*   */     //   359: ifnull -> 371
/*   */     //   362: aload #4
/*   */     //   364: invokevirtual v60 : ()I
/*   */     //   367: istore_3
/*   */     //   368: goto -> 398
/*   */     //   371: new java/lang/IllegalArgumentException
/*   */     //   374: dup
/*   */     //   375: new java/lang/StringBuilder
/*   */     //   378: dup
/*   */     //   379: invokespecial <init> : ()V
/*   */     //   382: ldc 'Named value not found: '
/*   */     //   384: invokevirtual append : (Ljava/lang/String;)Ljava/lang/StringBuilder;
/*   */     //   387: aload_3
/*   */     //   388: invokevirtual append : (Ljava/lang/String;)Ljava/lang/StringBuilder;
/*   */     //   391: invokevirtual toString : ()Ljava/lang/String;
/*   */     //   394: invokespecial <init> : (Ljava/lang/String;)V
/*   */     //   397: athrow
/*   */     //   398: aload_1
/*   */     //   399: ldc ''
/*   */     //   401: astore #4
/*   */     //   403: ldc 'region_id'
/*   */     //   405: invokevirtual Ua : (Ljava/lang/String;)Z
/*   */     //   408: ifeq -> 470
/*   */     //   411: aload_1
/*   */     //   412: bipush #90
/*   */     //   414: istore_1
/*   */     //   415: ldc 'region_id'
/*   */     //   417: dup
/*   */     //   418: astore #4
/*   */     //   420: invokevirtual Jb : (Ljava/lang/String;)Lf/bM0;
/*   */     //   423: dup
/*   */     //   424: astore #5
/*   */     //   426: ifnull -> 442
/*   */     //   429: aload #5
/*   */     //   431: invokevirtual v60 : ()I
/*   */     //   434: iload_1
/*   */     //   435: iadd
/*   */     //   436: invokestatic OH0 : (I)Ljava/lang/String;
/*   */     //   439: goto -> 485
/*   */     //   442: new java/lang/IllegalArgumentException
/*   */     //   445: dup
/*   */     //   446: new java/lang/StringBuilder
/*   */     //   449: dup
/*   */     //   450: invokespecial <init> : ()V
/*   */     //   453: ldc 'Named value not found: '
/*   */     //   455: invokevirtual append : (Ljava/lang/String;)Ljava/lang/StringBuilder;
/*   */     //   458: aload #4
/*   */     //   460: invokevirtual append : (Ljava/lang/String;)Ljava/lang/StringBuilder;
/*   */     //   463: invokevirtual toString : ()Ljava/lang/String;
/*   */     //   466: invokespecial <init> : (Ljava/lang/String;)V
/*   */     //   469: athrow
/*   */     //   470: aload_1
/*   */     //   471: ldc 'mod_name'
/*   */     //   473: invokevirtual Ua : (Ljava/lang/String;)Z
/*   */     //   476: ifeq -> 489
/*   */     //   479: aload_1
/*   */     //   480: ldc 'mod_name'
/*   */     //   482: invokevirtual ty : (Ljava/lang/String;)Ljava/lang/String;
/*   */     //   485: astore_1
/*   */     //   486: aload_1
/*   */     //   487: astore #4
/*   */     //   489: getstatic f/km.f70 : Lf/k7;
/*   */     //   492: iload_3
/*   */     //   493: sipush #2910
/*   */     //   496: ldc 'Error report successful.'
/*   */     //   498: invokestatic la : (ILjava/lang/String;)Ljava/lang/String;
/*   */     //   501: astore_1
/*   */     //   502: iconst_2
/*   */     //   503: anewarray java/lang/String
/*   */     //   506: dup
/*   */     //   507: dup
/*   */     //   508: iconst_0
/*   */     //   509: aload_2
/*   */     //   510: aastore
/*   */     //   511: iconst_1
/*   */     //   512: aload #4
/*   */     //   514: aastore
/*   */     //   515: invokestatic sB : (I[Ljava/lang/String;)Ljava/lang/String;
/*   */     //   518: astore_2
/*   */     //   519: aload_1
/*   */     //   520: getstatic f/LP.fw : Lf/LP;
/*   */     //   523: new f/A40
/*   */     //   526: dup
/*   */     //   527: astore_1
/*   */     //   528: aload_0
/*   */     //   529: invokespecial <init> : (Lf/AF0;)V
/*   */     //   532: aload_2
/*   */     //   533: swap
/*   */     //   534: aload_1
/*   */     //   535: iconst_1
/*   */     //   536: invokevirtual iJ0 : (Ljava/lang/String;Ljava/lang/String;Lf/LP;Ljava/lang/Runnable;Z)V
/*   */     //   539: return
/*   */     //   540: new java/lang/IllegalArgumentException
/*   */     //   543: dup
/*   */     //   544: new java/lang/StringBuilder
/*   */     //   547: dup
/*   */     //   548: invokespecial <init> : ()V
/*   */     //   551: ldc 'Named value not found: '
/*   */     //   553: invokevirtual append : (Ljava/lang/String;)Ljava/lang/StringBuilder;
/*   */     //   556: aload_2
/*   */     //   557: invokevirtual append : (Ljava/lang/String;)Ljava/lang/StringBuilder;
/*   */     //   560: invokevirtual toString : ()Ljava/lang/String;
/*   */     //   563: invokespecial <init> : (Ljava/lang/String;)V
/*   */     //   566: athrow
/*   */     //   567: new java/lang/IllegalArgumentException
/*   */     //   570: dup
/*   */     //   571: new java/lang/StringBuilder
/*   */     //   574: dup
/*   */     //   575: invokespecial <init> : ()V
/*   */     //   578: ldc 'Named value not found: '
/*   */     //   580: invokevirtual append : (Ljava/lang/String;)Ljava/lang/StringBuilder;
/*   */     //   583: aload #4
/*   */     //   585: invokevirtual append : (Ljava/lang/String;)Ljava/lang/StringBuilder;
/*   */     //   588: invokevirtual toString : ()Ljava/lang/String;
/*   */     //   591: invokespecial <init> : (Ljava/lang/String;)V
/*   */     //   594: athrow
/*   */     //   595: aload_1
/*   */     //   596: aload_2
/*   */     //   597: invokestatic JC0 : (Ljava/io/Closeable;)V
/*   */     //   600: athrow
/*   */     //   601: getstatic f/fl0.Qi0 : Lf/ik;
/*   */     //   604: ldc 'Error handling error report response'
/*   */     //   606: aload_1
/*   */     //   607: invokeinterface error : (Ljava/lang/String;Ljava/lang/Throwable;)V
/*   */     //   612: aload_0
/*   */     //   613: getstatic f/fl0.Qi0 : Lf/ik;
/*   */     //   616: ldc 'Error report response end, calling failure'
/*   */     //   618: invokeinterface info : (Ljava/lang/String;)V
/*   */     //   623: invokevirtual Hj0 : ()V
/*   */     //   626: return
/*   */     // Line number table:
/*   */     //   Java source line number -> byte code offset
/*   */     //   #1	-> 4
/*   */     //   #2	-> 10
/*   */     //   #3	-> 13
/*   */     //   #4	-> 16
/*   */     //   #5	-> 27
/*   */     //   #6	-> 56
/*   */     //   #7	-> 94
/*   */     //   #8	-> 126
/*   */     //   #9	-> 129
/*   */     //   #10	-> 138
/*   */     //   #11	-> 147
/*   */     //   #12	-> 157
/*   */     //   #13	-> 174
/*   */     //   #14	-> 179
/*   */     //   #15	-> 193
/*   */     //   #16	-> 196
/*   */     //   #17	-> 253
/*   */     //   #18	-> 257
/*   */     //   #19	-> 273
/*   */     //   #20	-> 322
/*   */     //   #21	-> 327
/*   */     //   #22	-> 353
/*   */     //   #23	-> 399
/*   */     //   #24	-> 420
/*   */     //   #25	-> 436
/*   */     //   #26	-> 442
/*   */     //   #27	-> 471
/*   */     //   #28	-> 540
/*   */     //   #29	-> 597
/*   */     //   #30	-> 601
/*   */     // Exception table:
/*   */     //   from	to	target	type
/*   */     //   27	33	41	java/io/IOException
/*   */     //   27	33	37	java/lang/Exception
/*   */     //   42	52	37	java/lang/Exception
/*   */     //   56	58	37	java/lang/Exception
/*   */     //   62	73	81	java/io/IOException
/*   */     //   62	73	77	finally
/*   */     //   82	87	77	finally
/*   */     //   87	91	37	java/lang/Exception
/*   */     //   93	132	37	java/lang/Exception
/*   */     //   138	141	37	java/lang/Exception
/*   */     //   142	155	37	java/lang/Exception
/*   */     //   157	160	37	java/lang/Exception
/*   */     //   161	173	37	java/lang/Exception
/*   */     //   174	176	37	java/lang/Exception
/*   */     //   179	182	37	java/lang/Exception
/*   */     //   188	255	37	java/lang/Exception
/*   */     //   257	260	37	java/lang/Exception
/*   */     //   265	269	37	java/lang/Exception
/*   */     //   272	278	37	java/lang/Exception
/*   */     //   281	297	37	java/lang/Exception
/*   */     //   298	301	37	java/lang/Exception
/*   */     //   306	311	37	java/lang/Exception
/*   */     //   315	321	37	java/lang/Exception
/*   */     //   322	325	37	java/lang/Exception
/*   */     //   326	337	37	java/lang/Exception
/*   */     //   340	345	37	java/lang/Exception
/*   */     //   348	351	37	java/lang/Exception
/*   */     //   353	356	37	java/lang/Exception
/*   */     //   362	367	37	java/lang/Exception
/*   */     //   371	401	37	java/lang/Exception
/*   */     //   403	408	37	java/lang/Exception
/*   */     //   415	417	37	java/lang/Exception
/*   */     //   420	423	37	java/lang/Exception
/*   */     //   429	434	37	java/lang/Exception
/*   */     //   436	476	37	java/lang/Exception
/*   */     //   479	485	37	java/lang/Exception
/*   */     //   489	492	37	java/lang/Exception
/*   */     //   496	501	37	java/lang/Exception
/*   */     //   502	518	37	java/lang/Exception
/*   */     //   519	526	37	java/lang/Exception
/*   */     //   528	539	37	java/lang/Exception
/*   */     //   540	601	37	java/lang/Exception
/*   */   } }


/* Location:              /Users/vnnsnnt/Documents/Codespace/JavaWorkspace/RedTrainer/src/main/java/org/trainer/client/PokeMMO.jar!/f/AF0.class
 * Java compiler version: 8 (52.0)
 * JD-Core Version:       1.1.3
 */