/*   */ package f;public final class aH0 implements con { public final void ng(Object paramObject, int paramInt, float[] paramArrayOffloat) { // Byte code:
/*   */     //   0: iload_2
/*   */     //   1: aload_1
/*   */     //   2: checkcast f/uT
/*   */     //   5: astore_0
/*   */     //   6: tableswitch default -> 72, 1 -> 416, 2 -> 403, 3 -> 390, 4 -> 368, 5 -> 346, 6 -> 321, 7 -> 306, 8 -> 280, 9 -> 241, 10 -> 215, 11 -> 133, 12 -> 107, 13 -> 81
/*   */     //   72: getstatic f/aH0.CU : Z
/*   */     //   75: ifeq -> 427
/*   */     //   78: goto -> 426
/*   */     //   81: aload_0
/*   */     //   82: dup
/*   */     //   83: aload_3
/*   */     //   84: iconst_0
/*   */     //   85: faload
/*   */     //   86: dup
/*   */     //   87: fstore_0
/*   */     //   88: putfield Kh : F
/*   */     //   91: getfield L1 : Lf/UA0;
/*   */     //   94: dup
/*   */     //   95: astore_1
/*   */     //   96: ifnull -> 426
/*   */     //   99: aload_1
/*   */     //   100: fload_0
/*   */     //   101: putfield rS : F
/*   */     //   104: goto -> 426
/*   */     //   107: aload_0
/*   */     //   108: aload_3
/*   */     //   109: aload_0
/*   */     //   110: aload_3
/*   */     //   111: iconst_0
/*   */     //   112: faload
/*   */     //   113: fstore_0
/*   */     //   114: getfield He0 : Lf/eo;
/*   */     //   117: getfield y : F
/*   */     //   120: fstore_1
/*   */     //   121: iconst_1
/*   */     //   122: faload
/*   */     //   123: fstore_2
/*   */     //   124: fload_0
/*   */     //   125: fload_1
/*   */     //   126: fload_2
/*   */     //   127: invokevirtual WQ : (FFF)V
/*   */     //   130: goto -> 426
/*   */     //   133: aload_0
/*   */     //   134: getfield native : Lf/s5;
/*   */     //   137: dup
/*   */     //   138: astore_1
/*   */     //   139: ifnull -> 150
/*   */     //   142: aload_1
/*   */     //   143: getfield lx : Lcom/badlogic/gdx/graphics/Color;
/*   */     //   146: astore_2
/*   */     //   147: goto -> 152
/*   */     //   150: aconst_null
/*   */     //   151: astore_2
/*   */     //   152: aload_1
/*   */     //   153: aload_2
/*   */     //   154: getfield r : F
/*   */     //   157: fstore_2
/*   */     //   158: ifnull -> 170
/*   */     //   161: aload_1
/*   */     //   162: getfield lx : Lcom/badlogic/gdx/graphics/Color;
/*   */     //   165: astore #4
/*   */     //   167: goto -> 173
/*   */     //   170: aconst_null
/*   */     //   171: astore #4
/*   */     //   173: aload_1
/*   */     //   174: aload #4
/*   */     //   176: getfield g : F
/*   */     //   179: fstore #4
/*   */     //   181: ifnull -> 192
/*   */     //   184: aload_1
/*   */     //   185: getfield lx : Lcom/badlogic/gdx/graphics/Color;
/*   */     //   188: astore_1
/*   */     //   189: goto -> 194
/*   */     //   192: aconst_null
/*   */     //   193: astore_1
/*   */     //   194: aload_0
/*   */     //   195: aload_3
/*   */     //   196: aload_1
/*   */     //   197: getfield b : F
/*   */     //   200: fstore_0
/*   */     //   201: iconst_0
/*   */     //   202: faload
/*   */     //   203: fstore_1
/*   */     //   204: fload_2
/*   */     //   205: fload #4
/*   */     //   207: fload_0
/*   */     //   208: fload_1
/*   */     //   209: invokevirtual hA0 : (FFFF)V
/*   */     //   212: goto -> 426
/*   */     //   215: aload_0
/*   */     //   216: aload_3
/*   */     //   217: dup
/*   */     //   218: dup2
/*   */     //   219: iconst_0
/*   */     //   220: faload
/*   */     //   221: fstore_0
/*   */     //   222: iconst_1
/*   */     //   223: faload
/*   */     //   224: fstore_1
/*   */     //   225: iconst_2
/*   */     //   226: faload
/*   */     //   227: fstore_2
/*   */     //   228: iconst_3
/*   */     //   229: faload
/*   */     //   230: fstore_3
/*   */     //   231: fload_0
/*   */     //   232: fload_1
/*   */     //   233: fload_2
/*   */     //   234: fload_3
/*   */     //   235: invokevirtual hA0 : (FFFF)V
/*   */     //   238: goto -> 426
/*   */     //   241: aload_0
/*   */     //   242: aload_3
/*   */     //   243: aload_0
/*   */     //   244: dup
/*   */     //   245: dup
/*   */     //   246: invokevirtual G10 : ()Lcom/badlogic/gdx/graphics/Color;
/*   */     //   249: getfield r : F
/*   */     //   252: fstore_0
/*   */     //   253: invokevirtual G10 : ()Lcom/badlogic/gdx/graphics/Color;
/*   */     //   256: getfield g : F
/*   */     //   259: fstore_1
/*   */     //   260: invokevirtual G10 : ()Lcom/badlogic/gdx/graphics/Color;
/*   */     //   263: getfield b : F
/*   */     //   266: fstore_2
/*   */     //   267: iconst_0
/*   */     //   268: faload
/*   */     //   269: fstore_3
/*   */     //   270: fload_0
/*   */     //   271: fload_1
/*   */     //   272: fload_2
/*   */     //   273: fload_3
/*   */     //   274: invokevirtual Bp : (FFFF)V
/*   */     //   277: goto -> 426
/*   */     //   280: aload_0
/*   */     //   281: aload_3
/*   */     //   282: dup
/*   */     //   283: dup2
/*   */     //   284: iconst_0
/*   */     //   285: faload
/*   */     //   286: fstore_0
/*   */     //   287: iconst_1
/*   */     //   288: faload
/*   */     //   289: fstore_1
/*   */     //   290: iconst_2
/*   */     //   291: faload
/*   */     //   292: fstore_2
/*   */     //   293: iconst_3
/*   */     //   294: faload
/*   */     //   295: fstore_3
/*   */     //   296: fload_0
/*   */     //   297: fload_1
/*   */     //   298: fload_2
/*   */     //   299: fload_3
/*   */     //   300: invokevirtual Bp : (FFFF)V
/*   */     //   303: goto -> 426
/*   */     //   306: aload_0
/*   */     //   307: aload_3
/*   */     //   308: iconst_0
/*   */     //   309: faload
/*   */     //   310: aload_0
/*   */     //   311: getfield ys : F
/*   */     //   314: fmul
/*   */     //   315: invokevirtual zO : (F)V
/*   */     //   318: goto -> 426
/*   */     //   321: aload_0
/*   */     //   322: aload_3
/*   */     //   323: aload_0
/*   */     //   324: getfield FC0 : Lf/eo;
/*   */     //   327: getfield x : F
/*   */     //   330: fstore_1
/*   */     //   331: iconst_0
/*   */     //   332: faload
/*   */     //   333: aload_0
/*   */     //   334: getfield ys : F
/*   */     //   337: fmul
/*   */     //   338: fload_1
/*   */     //   339: swap
/*   */     //   340: invokevirtual Kk0 : (FF)V
/*   */     //   343: goto -> 426
/*   */     //   346: aload_0
/*   */     //   347: aload_3
/*   */     //   348: iconst_0
/*   */     //   349: faload
/*   */     //   350: aload_0
/*   */     //   351: getfield ys : F
/*   */     //   354: fmul
/*   */     //   355: aload_0
/*   */     //   356: getfield FC0 : Lf/eo;
/*   */     //   359: getfield y : F
/*   */     //   362: invokevirtual Kk0 : (FF)V
/*   */     //   365: goto -> 426
/*   */     //   368: aload_0
/*   */     //   369: aload_3
/*   */     //   370: dup
/*   */     //   371: dup
/*   */     //   372: iconst_0
/*   */     //   373: faload
/*   */     //   374: fstore_0
/*   */     //   375: iconst_1
/*   */     //   376: faload
/*   */     //   377: fstore_1
/*   */     //   378: iconst_2
/*   */     //   379: faload
/*   */     //   380: fstore_2
/*   */     //   381: fload_0
/*   */     //   382: fload_1
/*   */     //   383: fload_2
/*   */     //   384: invokevirtual WQ : (FFF)V
/*   */     //   387: goto -> 426
/*   */     //   390: aload_0
/*   */     //   391: getfield He0 : Lf/eo;
/*   */     //   394: aload_3
/*   */     //   395: iconst_0
/*   */     //   396: faload
/*   */     //   397: putfield z : F
/*   */     //   400: goto -> 426
/*   */     //   403: aload_0
/*   */     //   404: getfield He0 : Lf/eo;
/*   */     //   407: aload_3
/*   */     //   408: iconst_0
/*   */     //   409: faload
/*   */     //   410: putfield y : F
/*   */     //   413: goto -> 426
/*   */     //   416: aload_0
/*   */     //   417: getfield He0 : Lf/eo;
/*   */     //   420: aload_3
/*   */     //   421: iconst_0
/*   */     //   422: faload
/*   */     //   423: putfield x : F
/*   */     //   426: return
/*   */     //   427: new java/lang/AssertionError
/*   */     //   430: dup
/*   */     //   431: invokespecial <init> : ()V
/*   */     //   434: athrow
/*   */     // Line number table:
/*   */     //   Java source line number -> byte code offset
/*   */     //   #1	-> 72
/*   */     //   #2	-> 88
/*   */     //   #3	-> 91
/*   */     //   #4	-> 101
/*   */     //   #5	-> 112
/*   */     //   #6	-> 134
/*   */     //   #7	-> 143
/*   */     //   #8	-> 154
/*   */     //   #9	-> 162
/*   */     //   #10	-> 176
/*   */     //   #11	-> 185
/*   */     //   #12	-> 197
/*   */     //   #13	-> 311
/*   */     //   #14	-> 315
/*   */     //   #15	-> 334
/*   */     //   #16	-> 340
/*   */     //   #17	-> 351
/* 1 */     //   #18	-> 356 } public final int Uu0(Object paramObject, int paramInt, float[] paramArrayOffloat) { s5 s5; Color color; eo eo; uT uT = (uT)paramObject; switch (paramInt) { default: if (CU);
/*   */ 
/*   */ 
/*   */ 
/*   */ 
/*   */ 
/*   */ 
/*   */         
/* 9 */         throw new AssertionError();case 13: paramArrayOffloat[0] = this.Kh;case 12: paramArrayOffloat[0] = this.He0.x; paramArrayOffloat[1] = this.He0.z;case 11: if ((s5 = this.native) != null) { Color color1 = this.lx; } else { s5 = null; }  paramArrayOffloat[0] = ((Color)this).a;case 10: if ((s5 = ((uT)this).native) != null) { Color color1 = this.lx; } else { s5 = null; }  paramArrayOffloat[0] = ((Color)this).r; paramArrayOffloat[1] = ((Color)this).g; paramArrayOffloat[2] = ((Color)this).b; paramArrayOffloat[3] = ((Color)this).a;case 9: paramArrayOffloat[0] = (G10()).a;case 8: paramArrayOffloat[0] = this.r; paramArrayOffloat[1] = this.g; paramArrayOffloat[2] = this.b; paramArrayOffloat[3] = (color = G10()).a;case 7: paramArrayOffloat[0] = nx0.SA0(((uT)this).FC0.x * 100.0F, 0.0F, 1.0F); paramArrayOffloat[1] = nx0.SA0(((uT)this).FC0.y * 100.0F, 0.0F, 1.0F);case 6: paramArrayOffloat[0] = nx0.SA0(((uT)this).FC0.y * 100.0F, 0.0F, 1.0F);case 5: paramArrayOffloat[0] = nx0.SA0(((uT)this).FC0.x * 100.0F, 0.0F, 1.0F);case 4: paramArrayOffloat[0] = this.x; paramArrayOffloat[1] = this.y; paramArrayOffloat[2] = (eo = ((uT)this).He0).z;case 3: paramArrayOffloat[0] = ((uT)this).He0.z;case 2: paramArrayOffloat[0] = ((uT)this).He0.y;case 1: break; }  paramArrayOffloat[0] = ((uT)this).He0.x; return 1; }
/*   */    }


/* Location:              /Users/vnnsnnt/Documents/Codespace/JavaWorkspace/RedTrainer/src/main/java/org/trainer/client/PokeMMO.jar!/f/aH0.class
 * Java compiler version: 8 (52.0)
 * JD-Core Version:       1.1.3
 */