/* 1 */ package f;public final class AH0 { public final int[] mr = new int[433]; public int wJ; public byte[] qr = new byte[1732]; public int jU; public int ab0; public int v; public Float uF; public boolean Oy0; public final void ov() { try { this.pf0.close(); return; } catch (IOException iOException) { throw new z60(258, this); }  } public final int[] kG = new int[] { 0, 1, 3, 7, 15, 31, 63, 127, 255, 511, 1023, 2047, 4095, 8191, 16383, 32767, 65535, 131071 }; public final PushbackInputStream pf0; public final Ym0 IJ0 = new Ym0(); public final byte[] K10 = new byte[4]; public ls0[] mt0 = new ls0[1]; public byte[] sd0 = null; public boolean Sk0 = true; public AH0(InputStream paramInputStream) { if (paramInputStream != null) { BufferedInputStream bufferedInputStream; this(paramInputStream); LPt6(this); this.Sk0 = true; super(this, 1732); this.pf0 = (PushbackInputStream)paramInputStream; nt(); return; }  throw new NullPointerException("in"); } public static int u20(BufferedInputStream paramBufferedInputStream) { int i = -10; paramBufferedInputStream.read(arrayOfByte, 0, 3); byte[] arrayOfByte; if ((arrayOfByte = new byte[4])[0] == 73 && arrayOfByte[1] == 68 && arrayOfByte[2] == 51) { paramBufferedInputStream.read(arrayOfByte, 0, 3); paramBufferedInputStream.read(arrayOfByte, 0, 4); i = (arrayOfByte[0] << 21) + (arrayOfByte[1] << 14) + (arrayOfByte[2] << 7) + arrayOfByte[3]; }  return i + 10; } public final Ym0 sv() { Ym0 ym0 = null; try { ym0 = H0(); if (this.Sk0 == true) { ym0.bt0(this.qr); this.Sk0 = false; }  } catch (z60 z60) { int i; int j; if ((j = z60.n60) == 261) { 
/* 2 */         try { nt(); ym0 = H0(); } catch (z60 z601)
/* 3 */         { if ((i = this.n60) != 260)
/* 4 */             throw new z60(i, this);  }  }
/* 5 */       else if (j != 260)
/* 6 */       { throw new z60(j, i); }
/*   */        }
/*   */     
/*   */     return ym0; }
/*   */ 
/*   */   
/*   */   public final void nt() {
/*   */     this.wJ = -1;
/*   */     this.jU = -1;
/*   */     this.ab0 = -1;
/*   */   }
/*   */   
/*   */   public final boolean Em0(int paramInt) {
/*   */     byte[] arrayOfByte;
/*   */     int i, j, k;
/*   */     for (arrayOfByte = this.K10, i = 0, j = 4, k = 0; j > 0;) {
/*   */       try {
/*   */         int m;
/*   */         if ((m = this.pf0.read(arrayOfByte, i, j)) == -1)
/*   */           break; 
/*   */         k += m;
/*   */         i += m;
/*   */         j -= m;
/*   */       } catch (IOException iOException) {
/*   */         throw new z60(258, this);
/*   */       } 
/*   */     } 
/*   */     i = (arrayOfByte = ((AH0)super).K10)[0] << 24 & 0xFF000000 | arrayOfByte[1] << 16 & 0xFF0000 | arrayOfByte[2] << 8 & 0xFF00 | arrayOfByte[3] << 0 & 0xFF;
/*   */     try {
/*   */       ((AH0)super).pf0.unread(arrayOfByte, 0, k);
/*   */     } catch (IOException iOException1) {}
/*   */     boolean bool = false;
/*   */     if (k != 0) {
/*   */       if (k == 4) {
/*   */         int m = ((AH0)super).v;
/*   */         bool = super.u10(i, paramInt, m);
/*   */       } 
/*   */     } else {
/*   */       bool = true;
/*   */     } 
/*   */     return bool;
/*   */   }
/*   */   
/*   */   public final boolean u10(int paramInt1, int paramInt2, int paramInt3) {
/*   */     boolean bool;
/*   */     if ((paramInt2 == 0) ? ((paramInt1 & 0xFFE00000) == -2097152) : ((paramInt1 & 0xFFF80C00) == paramInt3 && (((paramInt1 & 0xC0) == 192)) == this.Oy0)) {
/*   */       bool = true;
/*   */     } else {
/*   */       bool = false;
/*   */     } 
/*   */     if (bool)
/*   */       if ((paramInt1 >>> 10 & 0x3) != 3) {
/*   */         bool = true;
/*   */       } else {
/*   */         bool = false;
/*   */       }  
/*   */     if (bool)
/*   */       if ((paramInt1 >>> 17 & 0x3) != 0) {
/*   */         bool = true;
/*   */       } else {
/*   */         bool = false;
/*   */       }  
/*   */     if (bool)
/*   */       if ((paramInt1 >>> 19 & 0x3) != 1) {
/*   */         bool = true;
/*   */       } else {
/*   */         bool = false;
/*   */       }  
/*   */     return bool;
/*   */   }
/*   */   
/*   */   public final int Ze0(int paramInt) {
/*   */     int j;
/*   */     int k = (j = this.ab0) + paramInt;
/*   */     if (this.jU < 0)
/*   */       this.jU = 0; 
/*   */     if (k <= 32) {
/*   */       paramInt = this.mr[j = this.jU] >>> 32 - k & this.kG[paramInt];
/*   */       if ((this.ab0 = j + paramInt) == 32) {
/*   */         this.ab0 = 0;
/*   */         this.jU = j + 1;
/*   */       } 
/*   */       return paramInt;
/*   */     } 
/*   */     int i = m + 1;
/*   */     i = arrayOfInt[i] & 0xFFFF0000;
/*   */     this.ab0 = k - 32;
/*   */     int[] arrayOfInt;
/*   */     int m;
/*   */     return (((arrayOfInt = this.mr)[m = this.jU] & 0xFFFF) << 16 & 0xFFFF0000 | i >>> 16 & 0xFFFF) >>> 48 - k & this.kG[paramInt];
/*   */   }
/*   */   
/*   */   public final void LPt6(BufferedInputStream paramBufferedInputStream) {
/*   */     int i = -1;
/*   */     try {
/*   */       paramBufferedInputStream.mark(10);
/*   */       i = u20(paramBufferedInputStream);
/*   */       try {
/*   */         paramBufferedInputStream.reset();
/*   */       } catch (IOException iOException) {}
/*   */     } catch (IOException iOException) {
/*   */       paramBufferedInputStream.reset();
/*   */     } finally {}
/*   */     if (i > 0)
/*   */       try {
/*   */         byte[] arrayOfByte = new byte[i];
/*   */         paramBufferedInputStream.read(this, 0, i);
/*   */         VD0(this.sd0);
/*   */       } catch (IOException iOException) {} 
/*   */   }
/*   */   
/*   */   public final void VD0(byte[] paramArrayOfbyte) {
/*   */     // Byte code:
/*   */     //   0: aload_1
/*   */     //   1: ifnonnull -> 5
/*   */     //   4: return
/*   */     //   5: new java/lang/String
/*   */     //   8: dup
/*   */     //   9: astore_2
/*   */     //   10: aload_1
/*   */     //   11: iconst_0
/*   */     //   12: iconst_3
/*   */     //   13: invokespecial <init> : ([BII)V
/*   */     //   16: ldc 'ID3'
/*   */     //   18: aload_2
/*   */     //   19: invokevirtual equals : (Ljava/lang/Object;)Z
/*   */     //   22: ifne -> 26
/*   */     //   25: return
/*   */     //   26: aload_1
/*   */     //   27: iconst_3
/*   */     //   28: baload
/*   */     //   29: sipush #255
/*   */     //   32: iand
/*   */     //   33: dup
/*   */     //   34: istore_2
/*   */     //   35: iconst_2
/*   */     //   36: if_icmplt -> 628
/*   */     //   39: iload_2
/*   */     //   40: iconst_4
/*   */     //   41: if_icmple -> 47
/*   */     //   44: goto -> 628
/*   */     //   47: aconst_null
/*   */     //   48: astore_3
/*   */     //   49: aconst_null
/*   */     //   50: astore #4
/*   */     //   52: bipush #10
/*   */     //   54: istore #5
/*   */     //   56: iload #5
/*   */     //   58: aload_1
/*   */     //   59: arraylength
/*   */     //   60: if_icmpge -> 572
/*   */     //   63: aload_1
/*   */     //   64: iload #5
/*   */     //   66: baload
/*   */     //   67: ifle -> 572
/*   */     //   70: iload_2
/*   */     //   71: iconst_3
/*   */     //   72: if_icmpeq -> 315
/*   */     //   75: iload_2
/*   */     //   76: iconst_4
/*   */     //   77: if_icmpne -> 83
/*   */     //   80: goto -> 315
/*   */     //   83: new java/lang/String
/*   */     //   86: dup
/*   */     //   87: astore #6
/*   */     //   89: aload_1
/*   */     //   90: iload #5
/*   */     //   92: aload #6
/*   */     //   94: aload_1
/*   */     //   95: iload #5
/*   */     //   97: iconst_3
/*   */     //   98: invokespecial <init> : ([BII)V
/*   */     //   101: iconst_0
/*   */     //   102: istore #6
/*   */     //   104: iconst_3
/*   */     //   105: iadd
/*   */     //   106: baload
/*   */     //   107: bipush #16
/*   */     //   109: ishl
/*   */     //   110: iload #6
/*   */     //   112: iadd
/*   */     //   113: aload_1
/*   */     //   114: iload #5
/*   */     //   116: iconst_4
/*   */     //   117: iadd
/*   */     //   118: baload
/*   */     //   119: bipush #8
/*   */     //   121: ishl
/*   */     //   122: iadd
/*   */     //   123: aload_1
/*   */     //   124: iload #5
/*   */     //   126: iconst_5
/*   */     //   127: iadd
/*   */     //   128: baload
/*   */     //   129: iadd
/*   */     //   130: istore #6
/*   */     //   132: iinc #5, 6
/*   */     //   135: ldc 'TXXX'
/*   */     //   137: invokevirtual equals : (Ljava/lang/Object;)Z
/*   */     //   140: ifeq -> 562
/*   */     //   143: iconst_1
/*   */     //   144: istore #7
/*   */     //   146: aconst_null
/*   */     //   147: astore #8
/*   */     //   149: iconst_4
/*   */     //   150: anewarray java/lang/String
/*   */     //   153: dup
/*   */     //   154: dup
/*   */     //   155: dup2
/*   */     //   156: astore #9
/*   */     //   158: iconst_0
/*   */     //   159: ldc 'ISO-8859-1'
/*   */     //   161: aastore
/*   */     //   162: iconst_1
/*   */     //   163: ldc 'UTF16'
/*   */     //   165: aastore
/*   */     //   166: iconst_2
/*   */     //   167: ldc 'UTF-16BE'
/*   */     //   169: aastore
/*   */     //   170: iconst_3
/*   */     //   171: ldc 'UTF-8'
/*   */     //   173: aastore
/*   */     //   174: new java/lang/String
/*   */     //   177: dup
/*   */     //   178: astore #10
/*   */     //   180: aload_1
/*   */     //   181: aload #9
/*   */     //   183: aload_1
/*   */     //   184: iload #5
/*   */     //   186: iload #6
/*   */     //   188: iload #7
/*   */     //   190: iload #5
/*   */     //   192: iload #7
/*   */     //   194: iadd
/*   */     //   195: istore #7
/*   */     //   197: isub
/*   */     //   198: istore #9
/*   */     //   200: baload
/*   */     //   201: aaload
/*   */     //   202: astore #11
/*   */     //   204: iload #7
/*   */     //   206: iload #9
/*   */     //   208: aload #11
/*   */     //   210: invokespecial <init> : ([BIILjava/lang/String;)V
/*   */     //   213: aload #10
/*   */     //   215: astore #8
/*   */     //   217: goto -> 225
/*   */     //   220: pop
/*   */     //   221: goto -> 627
/*   */     //   224: pop
/*   */     //   225: aload #8
/*   */     //   227: ldc ' '
/*   */     //   229: invokevirtual split : (Ljava/lang/String;)[Ljava/lang/String;
/*   */     //   232: dup
/*   */     //   233: astore #7
/*   */     //   235: arraylength
/*   */     //   236: iconst_2
/*   */     //   237: if_icmpne -> 562
/*   */     //   240: aload #7
/*   */     //   242: iconst_0
/*   */     //   243: aaload
/*   */     //   244: dup
/*   */     //   245: astore #8
/*   */     //   247: aload #7
/*   */     //   249: iconst_1
/*   */     //   250: aaload
/*   */     //   251: astore #7
/*   */     //   253: ldc 'replaygain_track_peak'
/*   */     //   255: invokevirtual equals : (Ljava/lang/Object;)Z
/*   */     //   258: ifeq -> 278
/*   */     //   261: aload_3
/*   */     //   262: aload #7
/*   */     //   264: invokestatic parseFloat : (Ljava/lang/String;)F
/*   */     //   267: invokestatic valueOf : (F)Ljava/lang/Float;
/*   */     //   270: astore #4
/*   */     //   272: ifnull -> 562
/*   */     //   275: goto -> 572
/*   */     //   278: aload #8
/*   */     //   280: ldc 'replaygain_track_gain'
/*   */     //   282: invokevirtual equals : (Ljava/lang/Object;)Z
/*   */     //   285: ifeq -> 562
/*   */     //   288: aload #4
/*   */     //   290: aload #7
/*   */     //   292: ldc ' dB'
/*   */     //   294: ldc ''
/*   */     //   296: invokevirtual replace : (Ljava/lang/CharSequence;Ljava/lang/CharSequence;)Ljava/lang/String;
/*   */     //   299: invokestatic parseFloat : (Ljava/lang/String;)F
/*   */     //   302: ldc 3.0
/*   */     //   304: fadd
/*   */     //   305: invokestatic valueOf : (F)Ljava/lang/Float;
/*   */     //   308: astore_3
/*   */     //   309: ifnull -> 562
/*   */     //   312: goto -> 572
/*   */     //   315: new java/lang/String
/*   */     //   318: dup
/*   */     //   319: astore #6
/*   */     //   321: aload_1
/*   */     //   322: iload #5
/*   */     //   324: aload #6
/*   */     //   326: aload_1
/*   */     //   327: iload #5
/*   */     //   329: iconst_4
/*   */     //   330: invokespecial <init> : ([BII)V
/*   */     //   333: iconst_4
/*   */     //   334: iadd
/*   */     //   335: baload
/*   */     //   336: bipush #24
/*   */     //   338: ishl
/*   */     //   339: ldc -16777216
/*   */     //   341: iand
/*   */     //   342: aload_1
/*   */     //   343: iload #5
/*   */     //   345: iconst_5
/*   */     //   346: iadd
/*   */     //   347: baload
/*   */     //   348: bipush #16
/*   */     //   350: ishl
/*   */     //   351: ldc 16711680
/*   */     //   353: iand
/*   */     //   354: ior
/*   */     //   355: aload_1
/*   */     //   356: iload #5
/*   */     //   358: bipush #6
/*   */     //   360: iadd
/*   */     //   361: baload
/*   */     //   362: bipush #8
/*   */     //   364: ishl
/*   */     //   365: ldc 65280
/*   */     //   367: iand
/*   */     //   368: ior
/*   */     //   369: aload_1
/*   */     //   370: iload #5
/*   */     //   372: bipush #7
/*   */     //   374: iadd
/*   */     //   375: baload
/*   */     //   376: sipush #255
/*   */     //   379: iand
/*   */     //   380: ior
/*   */     //   381: istore #6
/*   */     //   383: iinc #5, 10
/*   */     //   386: ldc 'TXXX'
/*   */     //   388: invokevirtual equals : (Ljava/lang/Object;)Z
/*   */     //   391: ifeq -> 562
/*   */     //   394: iconst_1
/*   */     //   395: istore #7
/*   */     //   397: aconst_null
/*   */     //   398: astore #8
/*   */     //   400: iconst_4
/*   */     //   401: anewarray java/lang/String
/*   */     //   404: dup
/*   */     //   405: dup
/*   */     //   406: dup2
/*   */     //   407: astore #9
/*   */     //   409: iconst_0
/*   */     //   410: ldc 'ISO-8859-1'
/*   */     //   412: aastore
/*   */     //   413: iconst_1
/*   */     //   414: ldc 'UTF16'
/*   */     //   416: aastore
/*   */     //   417: iconst_2
/*   */     //   418: ldc 'UTF-16BE'
/*   */     //   420: aastore
/*   */     //   421: iconst_3
/*   */     //   422: ldc 'UTF-8'
/*   */     //   424: aastore
/*   */     //   425: new java/lang/String
/*   */     //   428: dup
/*   */     //   429: astore #10
/*   */     //   431: aload_1
/*   */     //   432: aload #9
/*   */     //   434: aload_1
/*   */     //   435: iload #5
/*   */     //   437: iload #6
/*   */     //   439: iload #7
/*   */     //   441: iload #5
/*   */     //   443: iload #7
/*   */     //   445: iadd
/*   */     //   446: istore #7
/*   */     //   448: isub
/*   */     //   449: istore #9
/*   */     //   451: baload
/*   */     //   452: aaload
/*   */     //   453: astore #11
/*   */     //   455: iload #7
/*   */     //   457: iload #9
/*   */     //   459: aload #11
/*   */     //   461: invokespecial <init> : ([BIILjava/lang/String;)V
/*   */     //   464: aload #10
/*   */     //   466: astore #8
/*   */     //   468: goto -> 472
/*   */     //   471: pop
/*   */     //   472: aload #8
/*   */     //   474: ldc ' '
/*   */     //   476: invokevirtual split : (Ljava/lang/String;)[Ljava/lang/String;
/*   */     //   479: dup
/*   */     //   480: astore #7
/*   */     //   482: arraylength
/*   */     //   483: iconst_2
/*   */     //   484: if_icmpne -> 562
/*   */     //   487: aload #7
/*   */     //   489: iconst_0
/*   */     //   490: aaload
/*   */     //   491: dup
/*   */     //   492: astore #8
/*   */     //   494: aload #7
/*   */     //   496: iconst_1
/*   */     //   497: aaload
/*   */     //   498: astore #7
/*   */     //   500: ldc 'replaygain_track_peak'
/*   */     //   502: invokevirtual equals : (Ljava/lang/Object;)Z
/*   */     //   505: ifeq -> 525
/*   */     //   508: aload_3
/*   */     //   509: aload #7
/*   */     //   511: invokestatic parseFloat : (Ljava/lang/String;)F
/*   */     //   514: invokestatic valueOf : (F)Ljava/lang/Float;
/*   */     //   517: astore #4
/*   */     //   519: ifnull -> 562
/*   */     //   522: goto -> 572
/*   */     //   525: aload #8
/*   */     //   527: ldc 'replaygain_track_gain'
/*   */     //   529: invokevirtual equals : (Ljava/lang/Object;)Z
/*   */     //   532: ifeq -> 562
/*   */     //   535: aload #4
/*   */     //   537: aload #7
/*   */     //   539: ldc ' dB'
/*   */     //   541: ldc ''
/*   */     //   543: invokevirtual replace : (Ljava/lang/CharSequence;Ljava/lang/CharSequence;)Ljava/lang/String;
/*   */     //   546: invokestatic parseFloat : (Ljava/lang/String;)F
/*   */     //   549: ldc 3.0
/*   */     //   551: fadd
/*   */     //   552: invokestatic valueOf : (F)Ljava/lang/Float;
/*   */     //   555: astore_3
/*   */     //   556: ifnull -> 562
/*   */     //   559: goto -> 572
/*   */     //   562: iload #5
/*   */     //   564: iload #6
/*   */     //   566: iadd
/*   */     //   567: istore #5
/*   */     //   569: goto -> 56
/*   */     //   572: aload_3
/*   */     //   573: ifnull -> 627
/*   */     //   576: aload #4
/*   */     //   578: ifnull -> 627
/*   */     //   581: aload_0
/*   */     //   582: dup
/*   */     //   583: ldc2_w 10.0
/*   */     //   586: aload_3
/*   */     //   587: invokevirtual floatValue : ()F
/*   */     //   590: ldc 20.0
/*   */     //   592: fdiv
/*   */     //   593: f2d
/*   */     //   594: invokestatic pow : (DD)D
/*   */     //   597: d2f
/*   */     //   598: invokestatic valueOf : (F)Ljava/lang/Float;
/*   */     //   601: putfield uF : Ljava/lang/Float;
/*   */     //   604: fconst_1
/*   */     //   605: aload #4
/*   */     //   607: invokevirtual floatValue : ()F
/*   */     //   610: fdiv
/*   */     //   611: aload_0
/*   */     //   612: getfield uF : Ljava/lang/Float;
/*   */     //   615: invokevirtual floatValue : ()F
/*   */     //   618: invokestatic min : (FF)F
/*   */     //   621: invokestatic valueOf : (F)Ljava/lang/Float;
/*   */     //   624: putfield uF : Ljava/lang/Float;
/*   */     //   627: return
/*   */     //   628: return
/*   */     // Line number table:
/*   */     //   Java source line number -> byte code offset
/*   */     //   #1	-> 150
/*   */     //   #2	-> 227
/*   */     //   #3	-> 401
/*   */     //   #4	-> 474
/*   */     // Exception table:
/*   */     //   from	to	target	type
/*   */     //   56	60	220	java/lang/RuntimeException
/*   */     //   63	67	220	java/lang/RuntimeException
/*   */     //   83	86	220	java/lang/RuntimeException
/*   */     //   89	101	220	java/lang/RuntimeException
/*   */     //   106	107	220	java/lang/RuntimeException
/*   */     //   118	119	220	java/lang/RuntimeException
/*   */     //   128	129	220	java/lang/RuntimeException
/*   */     //   135	140	220	java/lang/RuntimeException
/*   */     //   149	153	224	java/io/UnsupportedEncodingException
/*   */     //   149	153	220	java/lang/RuntimeException
/*   */     //   159	162	224	java/io/UnsupportedEncodingException
/*   */     //   159	162	220	java/lang/RuntimeException
/*   */     //   163	166	224	java/io/UnsupportedEncodingException
/*   */     //   163	166	220	java/lang/RuntimeException
/*   */     //   167	170	224	java/io/UnsupportedEncodingException
/*   */     //   167	170	220	java/lang/RuntimeException
/*   */     //   171	177	224	java/io/UnsupportedEncodingException
/*   */     //   171	177	220	java/lang/RuntimeException
/*   */     //   200	202	224	java/io/UnsupportedEncodingException
/*   */     //   200	202	220	java/lang/RuntimeException
/*   */     //   204	213	224	java/io/UnsupportedEncodingException
/*   */     //   204	213	220	java/lang/RuntimeException
/*   */     //   225	232	220	java/lang/RuntimeException
/*   */     //   235	236	220	java/lang/RuntimeException
/*   */     //   240	244	220	java/lang/RuntimeException
/*   */     //   247	251	220	java/lang/RuntimeException
/*   */     //   253	258	220	java/lang/RuntimeException
/*   */     //   261	270	220	java/lang/RuntimeException
/*   */     //   278	285	220	java/lang/RuntimeException
/*   */     //   288	302	220	java/lang/RuntimeException
/*   */     //   305	308	220	java/lang/RuntimeException
/*   */     //   315	318	220	java/lang/RuntimeException
/*   */     //   321	333	220	java/lang/RuntimeException
/*   */     //   335	336	220	java/lang/RuntimeException
/*   */     //   347	348	220	java/lang/RuntimeException
/*   */     //   361	362	220	java/lang/RuntimeException
/*   */     //   375	376	220	java/lang/RuntimeException
/*   */     //   386	391	220	java/lang/RuntimeException
/*   */     //   400	404	471	java/io/UnsupportedEncodingException
/*   */     //   400	404	220	java/lang/RuntimeException
/*   */     //   410	413	471	java/io/UnsupportedEncodingException
/*   */     //   410	413	220	java/lang/RuntimeException
/*   */     //   414	417	471	java/io/UnsupportedEncodingException
/*   */     //   414	417	220	java/lang/RuntimeException
/*   */     //   418	421	471	java/io/UnsupportedEncodingException
/*   */     //   418	421	220	java/lang/RuntimeException
/*   */     //   422	428	471	java/io/UnsupportedEncodingException
/*   */     //   422	428	220	java/lang/RuntimeException
/*   */     //   451	453	471	java/io/UnsupportedEncodingException
/*   */     //   451	453	220	java/lang/RuntimeException
/*   */     //   455	464	471	java/io/UnsupportedEncodingException
/*   */     //   455	464	220	java/lang/RuntimeException
/*   */     //   472	479	220	java/lang/RuntimeException
/*   */     //   482	483	220	java/lang/RuntimeException
/*   */     //   487	491	220	java/lang/RuntimeException
/*   */     //   494	498	220	java/lang/RuntimeException
/*   */     //   500	505	220	java/lang/RuntimeException
/*   */     //   508	517	220	java/lang/RuntimeException
/*   */     //   525	532	220	java/lang/RuntimeException
/*   */     //   535	549	220	java/lang/RuntimeException
/*   */     //   552	555	220	java/lang/RuntimeException
/*   */     //   586	590	220	java/lang/RuntimeException
/*   */     //   594	597	220	java/lang/RuntimeException
/*   */     //   598	604	220	java/lang/RuntimeException
/*   */     //   605	610	220	java/lang/RuntimeException
/*   */     //   611	627	220	java/lang/RuntimeException
/*   */   }
/*   */   
/*   */   public final Ym0 H0() {
/*   */     // Byte code:
/*   */     //   0: aload_0
/*   */     //   1: getfield wJ : I
/*   */     //   4: iconst_m1
/*   */     //   5: if_icmpne -> 1433
/*   */     //   8: aload_0
/*   */     //   9: dup
/*   */     //   10: getfield IJ0 : Lf/Ym0;
/*   */     //   13: astore_1
/*   */     //   14: getfield mt0 : [Lf/ls0;
/*   */     //   17: astore_2
/*   */     //   18: iconst_0
/*   */     //   19: istore_3
/*   */     //   20: aload_0
/*   */     //   21: aload_1
/*   */     //   22: getfield coM4 : B
/*   */     //   25: istore #4
/*   */     //   27: getfield K10 : [B
/*   */     //   30: astore #5
/*   */     //   32: iconst_0
/*   */     //   33: istore #6
/*   */     //   35: iconst_3
/*   */     //   36: istore #7
/*   */     //   38: iconst_0
/*   */     //   39: istore #8
/*   */     //   41: iload #7
/*   */     //   43: ifle -> 106
/*   */     //   46: aload_0
/*   */     //   47: getfield pf0 : Ljava/io/PushbackInputStream;
/*   */     //   50: aload #5
/*   */     //   52: iload #6
/*   */     //   54: iload #7
/*   */     //   56: invokevirtual read : ([BII)I
/*   */     //   59: dup
/*   */     //   60: istore #9
/*   */     //   62: iconst_m1
/*   */     //   63: if_icmpne -> 69
/*   */     //   66: goto -> 106
/*   */     //   69: iload #7
/*   */     //   71: iload #6
/*   */     //   73: iload #8
/*   */     //   75: iload #9
/*   */     //   77: iadd
/*   */     //   78: istore #8
/*   */     //   80: iload #9
/*   */     //   82: iadd
/*   */     //   83: istore #6
/*   */     //   85: iload #9
/*   */     //   87: isub
/*   */     //   88: istore #7
/*   */     //   90: goto -> 41
/*   */     //   93: astore_0
/*   */     //   94: new f/z60
/*   */     //   97: dup
/*   */     //   98: sipush #258
/*   */     //   101: aload_0
/*   */     //   102: invokespecial <init> : (ILjava/lang/Exception;)V
/*   */     //   105: athrow
/*   */     //   106: iload #8
/*   */     //   108: iconst_3
/*   */     //   109: if_icmpne -> 1421
/*   */     //   112: aload_0
/*   */     //   113: getfield K10 : [B
/*   */     //   116: dup
/*   */     //   117: astore #5
/*   */     //   119: iconst_0
/*   */     //   120: baload
/*   */     //   121: bipush #16
/*   */     //   123: ishl
/*   */     //   124: ldc 16711680
/*   */     //   126: iand
/*   */     //   127: aload #5
/*   */     //   129: iconst_1
/*   */     //   130: baload
/*   */     //   131: bipush #8
/*   */     //   133: ishl
/*   */     //   134: ldc 65280
/*   */     //   136: iand
/*   */     //   137: ior
/*   */     //   138: aload #5
/*   */     //   140: iconst_2
/*   */     //   141: baload
/*   */     //   142: iconst_0
/*   */     //   143: ishl
/*   */     //   144: sipush #255
/*   */     //   147: iand
/*   */     //   148: ior
/*   */     //   149: istore #5
/*   */     //   151: aload_0
/*   */     //   152: iload #5
/*   */     //   154: bipush #8
/*   */     //   156: ishl
/*   */     //   157: istore #5
/*   */     //   159: getfield K10 : [B
/*   */     //   162: astore #6
/*   */     //   164: iconst_3
/*   */     //   165: istore #7
/*   */     //   167: iconst_1
/*   */     //   168: istore #8
/*   */     //   170: iconst_0
/*   */     //   171: istore #9
/*   */     //   173: iload #8
/*   */     //   175: ifle -> 238
/*   */     //   178: aload_0
/*   */     //   179: getfield pf0 : Ljava/io/PushbackInputStream;
/*   */     //   182: aload #6
/*   */     //   184: iload #7
/*   */     //   186: iload #8
/*   */     //   188: invokevirtual read : ([BII)I
/*   */     //   191: dup
/*   */     //   192: istore #10
/*   */     //   194: iconst_m1
/*   */     //   195: if_icmpne -> 201
/*   */     //   198: goto -> 238
/*   */     //   201: iload #8
/*   */     //   203: iload #7
/*   */     //   205: iload #9
/*   */     //   207: iload #10
/*   */     //   209: iadd
/*   */     //   210: istore #9
/*   */     //   212: iload #10
/*   */     //   214: iadd
/*   */     //   215: istore #7
/*   */     //   217: iload #10
/*   */     //   219: isub
/*   */     //   220: istore #8
/*   */     //   222: goto -> 173
/*   */     //   225: astore_0
/*   */     //   226: new f/z60
/*   */     //   229: dup
/*   */     //   230: sipush #258
/*   */     //   233: aload_0
/*   */     //   234: invokespecial <init> : (ILjava/lang/Exception;)V
/*   */     //   237: athrow
/*   */     //   238: iload #9
/*   */     //   240: iconst_1
/*   */     //   241: if_icmpne -> 1409
/*   */     //   244: aload_0
/*   */     //   245: dup
/*   */     //   246: iload #5
/*   */     //   248: aload_0
/*   */     //   249: getfield K10 : [B
/*   */     //   252: iconst_3
/*   */     //   253: baload
/*   */     //   254: sipush #255
/*   */     //   257: iand
/*   */     //   258: ior
/*   */     //   259: istore #5
/*   */     //   261: getfield v : I
/*   */     //   264: istore #6
/*   */     //   266: iload #5
/*   */     //   268: iload #4
/*   */     //   270: iload #6
/*   */     //   272: invokevirtual u10 : (III)Z
/*   */     //   275: ifeq -> 151
/*   */     //   278: aload_1
/*   */     //   279: getfield coM4 : B
/*   */     //   282: ifne -> 370
/*   */     //   285: iload #5
/*   */     //   287: aload_1
/*   */     //   288: iload #5
/*   */     //   290: bipush #19
/*   */     //   292: iushr
/*   */     //   293: iconst_1
/*   */     //   294: iand
/*   */     //   295: dup
/*   */     //   296: istore #4
/*   */     //   298: putfield OB : I
/*   */     //   301: bipush #20
/*   */     //   303: iushr
/*   */     //   304: iconst_1
/*   */     //   305: iand
/*   */     //   306: ifne -> 336
/*   */     //   309: iload #4
/*   */     //   311: ifne -> 322
/*   */     //   314: aload_1
/*   */     //   315: iconst_2
/*   */     //   316: putfield OB : I
/*   */     //   319: goto -> 336
/*   */     //   322: sipush #256
/*   */     //   325: istore_0
/*   */     //   326: new f/z60
/*   */     //   329: dup
/*   */     //   330: iload_0
/*   */     //   331: aconst_null
/*   */     //   332: invokespecial <init> : (ILjava/lang/Exception;)V
/*   */     //   335: athrow
/*   */     //   336: iload #5
/*   */     //   338: bipush #10
/*   */     //   340: iushr
/*   */     //   341: iconst_3
/*   */     //   342: iand
/*   */     //   343: dup
/*   */     //   344: aload_1
/*   */     //   345: swap
/*   */     //   346: putfield x70 : I
/*   */     //   349: iconst_3
/*   */     //   350: if_icmpeq -> 356
/*   */     //   353: goto -> 370
/*   */     //   356: sipush #256
/*   */     //   359: istore_0
/*   */     //   360: new f/z60
/*   */     //   363: dup
/*   */     //   364: iload_0
/*   */     //   365: aconst_null
/*   */     //   366: invokespecial <init> : (ILjava/lang/Exception;)V
/*   */     //   369: athrow
/*   */     //   370: iload #5
/*   */     //   372: dup
/*   */     //   373: aload_1
/*   */     //   374: iload #5
/*   */     //   376: aload_1
/*   */     //   377: iload #5
/*   */     //   379: aload_1
/*   */     //   380: iload #5
/*   */     //   382: bipush #17
/*   */     //   384: iushr
/*   */     //   385: iconst_4
/*   */     //   386: swap
/*   */     //   387: isub
/*   */     //   388: iconst_3
/*   */     //   389: iand
/*   */     //   390: dup
/*   */     //   391: istore #4
/*   */     //   393: putfield f0 : I
/*   */     //   396: bipush #16
/*   */     //   398: iushr
/*   */     //   399: iconst_1
/*   */     //   400: iand
/*   */     //   401: dup
/*   */     //   402: istore #6
/*   */     //   404: putfield rq : I
/*   */     //   407: bipush #12
/*   */     //   409: iushr
/*   */     //   410: bipush #15
/*   */     //   412: iand
/*   */     //   413: dup
/*   */     //   414: istore #7
/*   */     //   416: putfield Dw0 : I
/*   */     //   419: bipush #9
/*   */     //   421: iushr
/*   */     //   422: iconst_1
/*   */     //   423: iand
/*   */     //   424: istore #8
/*   */     //   426: bipush #6
/*   */     //   428: iushr
/*   */     //   429: iconst_3
/*   */     //   430: iand
/*   */     //   431: dup
/*   */     //   432: istore #9
/*   */     //   434: aload_1
/*   */     //   435: iload #5
/*   */     //   437: aload_1
/*   */     //   438: iload #9
/*   */     //   440: putfield kb0 : I
/*   */     //   443: iconst_4
/*   */     //   444: iushr
/*   */     //   445: iconst_3
/*   */     //   446: iand
/*   */     //   447: dup
/*   */     //   448: istore #10
/*   */     //   450: putfield Mh0 : I
/*   */     //   453: iconst_1
/*   */     //   454: if_icmpne -> 470
/*   */     //   457: aload_1
/*   */     //   458: iload #10
/*   */     //   460: iconst_2
/*   */     //   461: ishl
/*   */     //   462: iconst_4
/*   */     //   463: iadd
/*   */     //   464: putfield ne0 : I
/*   */     //   467: goto -> 475
/*   */     //   470: aload_1
/*   */     //   471: iconst_0
/*   */     //   472: putfield ne0 : I
/*   */     //   475: iload #4
/*   */     //   477: iconst_1
/*   */     //   478: if_icmpne -> 490
/*   */     //   481: aload_1
/*   */     //   482: bipush #32
/*   */     //   484: putfield hh : I
/*   */     //   487: goto -> 601
/*   */     //   490: iload #9
/*   */     //   492: iconst_3
/*   */     //   493: if_icmpeq -> 518
/*   */     //   496: iload #7
/*   */     //   498: iconst_4
/*   */     //   499: if_icmpne -> 508
/*   */     //   502: iconst_1
/*   */     //   503: istore #10
/*   */     //   505: goto -> 522
/*   */     //   508: iload #7
/*   */     //   510: bipush #-4
/*   */     //   512: iadd
/*   */     //   513: istore #10
/*   */     //   515: goto -> 522
/*   */     //   518: iload #7
/*   */     //   520: istore #10
/*   */     //   522: iload #10
/*   */     //   524: iconst_1
/*   */     //   525: if_icmpeq -> 578
/*   */     //   528: iload #10
/*   */     //   530: iconst_2
/*   */     //   531: if_icmpne -> 537
/*   */     //   534: goto -> 578
/*   */     //   537: aload_1
/*   */     //   538: getfield x70 : I
/*   */     //   541: iconst_1
/*   */     //   542: if_icmpeq -> 569
/*   */     //   545: iload #10
/*   */     //   547: iconst_3
/*   */     //   548: if_icmplt -> 560
/*   */     //   551: iload #10
/*   */     //   553: iconst_5
/*   */     //   554: if_icmpgt -> 560
/*   */     //   557: goto -> 569
/*   */     //   560: aload_1
/*   */     //   561: bipush #30
/*   */     //   563: putfield hh : I
/*   */     //   566: goto -> 601
/*   */     //   569: aload_1
/*   */     //   570: bipush #27
/*   */     //   572: putfield hh : I
/*   */     //   575: goto -> 601
/*   */     //   578: aload_1
/*   */     //   579: getfield x70 : I
/*   */     //   582: iconst_2
/*   */     //   583: if_icmpne -> 595
/*   */     //   586: aload_1
/*   */     //   587: bipush #12
/*   */     //   589: putfield hh : I
/*   */     //   592: goto -> 601
/*   */     //   595: aload_1
/*   */     //   596: bipush #8
/*   */     //   598: putfield hh : I
/*   */     //   601: aload_1
/*   */     //   602: getfield ne0 : I
/*   */     //   605: aload_1
/*   */     //   606: getfield hh : I
/*   */     //   609: dup
/*   */     //   610: istore #10
/*   */     //   612: if_icmple -> 621
/*   */     //   615: aload_1
/*   */     //   616: iload #10
/*   */     //   618: putfield ne0 : I
/*   */     //   621: iload #4
/*   */     //   623: iconst_1
/*   */     //   624: if_icmpne -> 696
/*   */     //   627: iload #8
/*   */     //   629: aload_1
/*   */     //   630: getstatic f/Ym0.Da : [[[I
/*   */     //   633: aload_1
/*   */     //   634: getfield OB : I
/*   */     //   637: dup
/*   */     //   638: istore #4
/*   */     //   640: aaload
/*   */     //   641: iconst_0
/*   */     //   642: aaload
/*   */     //   643: iload #7
/*   */     //   645: iaload
/*   */     //   646: bipush #12
/*   */     //   648: imul
/*   */     //   649: getstatic f/Ym0.bH : [[I
/*   */     //   652: iload #4
/*   */     //   654: aaload
/*   */     //   655: aload_1
/*   */     //   656: getfield x70 : I
/*   */     //   659: iaload
/*   */     //   660: idiv
/*   */     //   661: dup
/*   */     //   662: istore #4
/*   */     //   664: putfield Ln0 : I
/*   */     //   667: ifeq -> 678
/*   */     //   670: aload_1
/*   */     //   671: iload #4
/*   */     //   673: iconst_1
/*   */     //   674: iadd
/*   */     //   675: putfield Ln0 : I
/*   */     //   678: aload_1
/*   */     //   679: dup
/*   */     //   680: dup
/*   */     //   681: getfield Ln0 : I
/*   */     //   684: iconst_2
/*   */     //   685: ishl
/*   */     //   686: putfield Ln0 : I
/*   */     //   689: iconst_0
/*   */     //   690: putfield eb0 : I
/*   */     //   693: goto -> 889
/*   */     //   696: aload_1
/*   */     //   697: getstatic f/Ym0.Da : [[[I
/*   */     //   700: astore #10
/*   */     //   702: getfield OB : I
/*   */     //   705: dup
/*   */     //   706: istore #11
/*   */     //   708: aload_1
/*   */     //   709: aload #10
/*   */     //   711: iload #11
/*   */     //   713: aaload
/*   */     //   714: iload #4
/*   */     //   716: iconst_1
/*   */     //   717: isub
/*   */     //   718: aaload
/*   */     //   719: iload #7
/*   */     //   721: iaload
/*   */     //   722: sipush #144
/*   */     //   725: imul
/*   */     //   726: getstatic f/Ym0.bH : [[I
/*   */     //   729: iload #11
/*   */     //   731: aaload
/*   */     //   732: aload_1
/*   */     //   733: getfield x70 : I
/*   */     //   736: iaload
/*   */     //   737: idiv
/*   */     //   738: dup
/*   */     //   739: istore #7
/*   */     //   741: putfield Ln0 : I
/*   */     //   744: ifeq -> 753
/*   */     //   747: iload #11
/*   */     //   749: iconst_2
/*   */     //   750: if_icmpne -> 761
/*   */     //   753: aload_1
/*   */     //   754: iload #7
/*   */     //   756: iconst_1
/*   */     //   757: ishr
/*   */     //   758: putfield Ln0 : I
/*   */     //   761: iload #8
/*   */     //   763: ifeq -> 776
/*   */     //   766: aload_1
/*   */     //   767: dup
/*   */     //   768: getfield Ln0 : I
/*   */     //   771: iconst_1
/*   */     //   772: iadd
/*   */     //   773: putfield Ln0 : I
/*   */     //   776: iload #4
/*   */     //   778: iconst_3
/*   */     //   779: if_icmpne -> 884
/*   */     //   782: iload #11
/*   */     //   784: iconst_1
/*   */     //   785: if_icmpne -> 826
/*   */     //   788: iload #9
/*   */     //   790: aload_1
/*   */     //   791: getfield Ln0 : I
/*   */     //   794: istore #4
/*   */     //   796: iconst_3
/*   */     //   797: if_icmpne -> 807
/*   */     //   800: bipush #17
/*   */     //   802: istore #7
/*   */     //   804: goto -> 811
/*   */     //   807: bipush #32
/*   */     //   809: istore #7
/*   */     //   811: iload #6
/*   */     //   813: iload #4
/*   */     //   815: iload #7
/*   */     //   817: isub
/*   */     //   818: istore #4
/*   */     //   820: ifeq -> 867
/*   */     //   823: goto -> 861
/*   */     //   826: iload #9
/*   */     //   828: aload_1
/*   */     //   829: getfield Ln0 : I
/*   */     //   832: istore #4
/*   */     //   834: iconst_3
/*   */     //   835: if_icmpne -> 845
/*   */     //   838: bipush #9
/*   */     //   840: istore #7
/*   */     //   842: goto -> 849
/*   */     //   845: bipush #17
/*   */     //   847: istore #7
/*   */     //   849: iload #6
/*   */     //   851: iload #4
/*   */     //   853: iload #7
/*   */     //   855: isub
/*   */     //   856: istore #4
/*   */     //   858: ifeq -> 867
/*   */     //   861: iconst_0
/*   */     //   862: istore #6
/*   */     //   864: goto -> 870
/*   */     //   867: iconst_2
/*   */     //   868: istore #6
/*   */     //   870: aload_1
/*   */     //   871: iload #4
/*   */     //   873: iload #6
/*   */     //   875: isub
/*   */     //   876: iconst_4
/*   */     //   877: isub
/*   */     //   878: putfield eb0 : I
/*   */     //   881: goto -> 889
/*   */     //   884: aload_1
/*   */     //   885: iconst_0
/*   */     //   886: putfield eb0 : I
/*   */     //   889: aload_0
/*   */     //   890: aload_1
/*   */     //   891: dup
/*   */     //   892: getfield Ln0 : I
/*   */     //   895: iconst_4
/*   */     //   896: isub
/*   */     //   897: dup
/*   */     //   898: istore #4
/*   */     //   900: putfield Ln0 : I
/*   */     //   903: getfield qr : [B
/*   */     //   906: astore #6
/*   */     //   908: iconst_0
/*   */     //   909: istore #7
/*   */     //   911: iconst_0
/*   */     //   912: istore #8
/*   */     //   914: iload #4
/*   */     //   916: istore #9
/*   */     //   918: iload #9
/*   */     //   920: ifle -> 1009
/*   */     //   923: aload_0
/*   */     //   924: getfield pf0 : Ljava/io/PushbackInputStream;
/*   */     //   927: aload #6
/*   */     //   929: iload #7
/*   */     //   931: iload #9
/*   */     //   933: invokevirtual read : ([BII)I
/*   */     //   936: dup
/*   */     //   937: istore #10
/*   */     //   939: iconst_m1
/*   */     //   940: if_icmpne -> 972
/*   */     //   943: iload #9
/*   */     //   945: dup
/*   */     //   946: iconst_m1
/*   */     //   947: iadd
/*   */     //   948: istore #9
/*   */     //   950: ifle -> 1009
/*   */     //   953: aload #6
/*   */     //   955: iload #7
/*   */     //   957: iconst_1
/*   */     //   958: iadd
/*   */     //   959: istore #10
/*   */     //   961: iload #7
/*   */     //   963: iconst_0
/*   */     //   964: bastore
/*   */     //   965: iload #10
/*   */     //   967: istore #7
/*   */     //   969: goto -> 943
/*   */     //   972: iload #9
/*   */     //   974: iload #7
/*   */     //   976: iload #8
/*   */     //   978: iload #10
/*   */     //   980: iadd
/*   */     //   981: istore #8
/*   */     //   983: iload #10
/*   */     //   985: iadd
/*   */     //   986: istore #7
/*   */     //   988: iload #10
/*   */     //   990: isub
/*   */     //   991: istore #9
/*   */     //   993: goto -> 918
/*   */     //   996: astore_0
/*   */     //   997: new f/z60
/*   */     //   1000: dup
/*   */     //   1001: sipush #258
/*   */     //   1004: aload_0
/*   */     //   1005: invokespecial <init> : (ILjava/lang/Exception;)V
/*   */     //   1008: athrow
/*   */     //   1009: aload_1
/*   */     //   1010: aload_0
/*   */     //   1011: dup
/*   */     //   1012: dup
/*   */     //   1013: iload #4
/*   */     //   1015: putfield wJ : I
/*   */     //   1018: iconst_m1
/*   */     //   1019: putfield jU : I
/*   */     //   1022: iconst_m1
/*   */     //   1023: putfield ab0 : I
/*   */     //   1026: getfield Ln0 : I
/*   */     //   1029: dup
/*   */     //   1030: istore #4
/*   */     //   1032: iflt -> 1059
/*   */     //   1035: iload #8
/*   */     //   1037: iload #4
/*   */     //   1039: if_icmpne -> 1045
/*   */     //   1042: goto -> 1059
/*   */     //   1045: sipush #261
/*   */     //   1048: istore_0
/*   */     //   1049: new f/z60
/*   */     //   1052: dup
/*   */     //   1053: iload_0
/*   */     //   1054: aconst_null
/*   */     //   1055: invokespecial <init> : (ILjava/lang/Exception;)V
/*   */     //   1058: athrow
/*   */     //   1059: aload_0
/*   */     //   1060: aload_1
/*   */     //   1061: getfield coM4 : B
/*   */     //   1064: invokevirtual Em0 : (I)Z
/*   */     //   1067: ifeq -> 1125
/*   */     //   1070: aload_1
/*   */     //   1071: getfield coM4 : B
/*   */     //   1074: ifne -> 1120
/*   */     //   1077: iload #5
/*   */     //   1079: aload_1
/*   */     //   1080: iconst_1
/*   */     //   1081: putfield coM4 : B
/*   */     //   1084: ldc_w -521024
/*   */     //   1087: iand
/*   */     //   1088: dup
/*   */     //   1089: aload_0
/*   */     //   1090: swap
/*   */     //   1091: sipush #-193
/*   */     //   1094: iand
/*   */     //   1095: putfield v : I
/*   */     //   1098: sipush #192
/*   */     //   1101: iand
/*   */     //   1102: sipush #192
/*   */     //   1105: if_icmpne -> 1113
/*   */     //   1108: iconst_1
/*   */     //   1109: istore_3
/*   */     //   1110: goto -> 1115
/*   */     //   1113: iconst_0
/*   */     //   1114: istore_3
/*   */     //   1115: aload_0
/*   */     //   1116: iload_3
/*   */     //   1117: putfield Oy0 : Z
/*   */     //   1120: iconst_1
/*   */     //   1121: istore_3
/*   */     //   1122: goto -> 1183
/*   */     //   1125: aload_0
/*   */     //   1126: getfield jU : I
/*   */     //   1129: iconst_m1
/*   */     //   1130: if_icmpne -> 1183
/*   */     //   1133: aload_0
/*   */     //   1134: getfield ab0 : I
/*   */     //   1137: iconst_m1
/*   */     //   1138: if_icmpne -> 1183
/*   */     //   1141: aload_0
/*   */     //   1142: getfield wJ : I
/*   */     //   1145: dup
/*   */     //   1146: istore #4
/*   */     //   1148: ifle -> 1183
/*   */     //   1151: aload_0
/*   */     //   1152: getfield pf0 : Ljava/io/PushbackInputStream;
/*   */     //   1155: aload_0
/*   */     //   1156: getfield qr : [B
/*   */     //   1159: iconst_0
/*   */     //   1160: iload #4
/*   */     //   1162: invokevirtual unread : ([BII)V
/*   */     //   1165: goto -> 1183
/*   */     //   1168: pop
/*   */     //   1169: sipush #258
/*   */     //   1172: istore_0
/*   */     //   1173: new f/z60
/*   */     //   1176: dup
/*   */     //   1177: iload_0
/*   */     //   1178: aconst_null
/*   */     //   1179: invokespecial <init> : (ILjava/lang/Exception;)V
/*   */     //   1182: athrow
/*   */     //   1183: iload_3
/*   */     //   1184: ifeq -> 20
/*   */     //   1187: aload_0
/*   */     //   1188: dup
/*   */     //   1189: iconst_0
/*   */     //   1190: istore_3
/*   */     //   1191: getfield qr : [B
/*   */     //   1194: astore #4
/*   */     //   1196: getfield wJ : I
/*   */     //   1199: istore #6
/*   */     //   1201: iconst_0
/*   */     //   1202: istore #7
/*   */     //   1204: iload #7
/*   */     //   1206: iload #6
/*   */     //   1208: if_icmpge -> 1332
/*   */     //   1211: aload #4
/*   */     //   1213: iconst_0
/*   */     //   1214: istore #8
/*   */     //   1216: iconst_0
/*   */     //   1217: istore #9
/*   */     //   1219: iconst_0
/*   */     //   1220: istore #10
/*   */     //   1222: iload #7
/*   */     //   1224: baload
/*   */     //   1225: istore #11
/*   */     //   1227: iload #7
/*   */     //   1229: iconst_1
/*   */     //   1230: iadd
/*   */     //   1231: dup
/*   */     //   1232: istore #12
/*   */     //   1234: iload #6
/*   */     //   1236: if_icmpge -> 1246
/*   */     //   1239: aload #4
/*   */     //   1241: iload #12
/*   */     //   1243: baload
/*   */     //   1244: istore #8
/*   */     //   1246: iload #7
/*   */     //   1248: iconst_2
/*   */     //   1249: iadd
/*   */     //   1250: dup
/*   */     //   1251: istore #12
/*   */     //   1253: iload #6
/*   */     //   1255: if_icmpge -> 1265
/*   */     //   1258: aload #4
/*   */     //   1260: iload #12
/*   */     //   1262: baload
/*   */     //   1263: istore #9
/*   */     //   1265: iload #7
/*   */     //   1267: iconst_3
/*   */     //   1268: iadd
/*   */     //   1269: dup
/*   */     //   1270: istore #12
/*   */     //   1272: iload #6
/*   */     //   1274: if_icmpge -> 1284
/*   */     //   1277: aload #4
/*   */     //   1279: iload #12
/*   */     //   1281: baload
/*   */     //   1282: istore #10
/*   */     //   1284: aload_0
/*   */     //   1285: getfield mr : [I
/*   */     //   1288: iload_3
/*   */     //   1289: iload #11
/*   */     //   1291: iinc #3, 1
/*   */     //   1294: bipush #24
/*   */     //   1296: ishl
/*   */     //   1297: ldc -16777216
/*   */     //   1299: iand
/*   */     //   1300: iload #8
/*   */     //   1302: bipush #16
/*   */     //   1304: ishl
/*   */     //   1305: ldc 16711680
/*   */     //   1307: iand
/*   */     //   1308: ior
/*   */     //   1309: iload #9
/*   */     //   1311: bipush #8
/*   */     //   1313: ishl
/*   */     //   1314: ldc 65280
/*   */     //   1316: iand
/*   */     //   1317: ior
/*   */     //   1318: iload #10
/*   */     //   1320: sipush #255
/*   */     //   1323: iand
/*   */     //   1324: ior
/*   */     //   1325: iastore
/*   */     //   1326: iinc #7, 4
/*   */     //   1329: goto -> 1204
/*   */     //   1332: aload_1
/*   */     //   1333: aload_0
/*   */     //   1334: dup
/*   */     //   1335: iconst_0
/*   */     //   1336: putfield jU : I
/*   */     //   1339: iconst_0
/*   */     //   1340: putfield ab0 : I
/*   */     //   1343: getfield rq : I
/*   */     //   1346: ifne -> 1402
/*   */     //   1349: aload_1
/*   */     //   1350: dup
/*   */     //   1351: aload_0
/*   */     //   1352: bipush #16
/*   */     //   1354: invokevirtual Ze0 : (I)I
/*   */     //   1357: i2s
/*   */     //   1358: putfield U30 : S
/*   */     //   1361: getfield vw0 : Lf/ls0;
/*   */     //   1364: ifnonnull -> 1380
/*   */     //   1367: aload_1
/*   */     //   1368: new f/ls0
/*   */     //   1371: dup
/*   */     //   1372: astore_3
/*   */     //   1373: invokespecial <init> : ()V
/*   */     //   1376: aload_3
/*   */     //   1377: putfield vw0 : Lf/ls0;
/*   */     //   1380: aload_2
/*   */     //   1381: aload_1
/*   */     //   1382: dup
/*   */     //   1383: getfield vw0 : Lf/ls0;
/*   */     //   1386: iload #5
/*   */     //   1388: bipush #16
/*   */     //   1390: invokevirtual Zc0 : (II)V
/*   */     //   1393: getfield vw0 : Lf/ls0;
/*   */     //   1396: iconst_0
/*   */     //   1397: swap
/*   */     //   1398: aastore
/*   */     //   1399: goto -> 1433
/*   */     //   1402: aload_2
/*   */     //   1403: iconst_0
/*   */     //   1404: aconst_null
/*   */     //   1405: aastore
/*   */     //   1406: goto -> 1433
/*   */     //   1409: new f/z60
/*   */     //   1412: dup
/*   */     //   1413: sipush #260
/*   */     //   1416: aconst_null
/*   */     //   1417: invokespecial <init> : (ILjava/lang/Exception;)V
/*   */     //   1420: athrow
/*   */     //   1421: new f/z60
/*   */     //   1424: dup
/*   */     //   1425: sipush #260
/*   */     //   1428: aconst_null
/*   */     //   1429: invokespecial <init> : (ILjava/lang/Exception;)V
/*   */     //   1432: athrow
/*   */     //   1433: aload_0
/*   */     //   1434: getfield IJ0 : Lf/Ym0;
/*   */     //   1437: areturn
/*   */     // Line number table:
/*   */     //   Java source line number -> byte code offset
/*   */     //   #1	-> 10
/*   */     //   #2	-> 22
/*   */     //   #3	-> 27
/*   */     //   #4	-> 47
/*   */     //   #5	-> 94
/*   */     //   #6	-> 105
/*   */     //   #7	-> 113
/*   */     //   #8	-> 179
/*   */     //   #9	-> 226
/*   */     //   #10	-> 237
/*   */     //   #11	-> 249
/*   */     //   #12	-> 279
/*   */     //   #13	-> 326
/*   */     //   #14	-> 335
/*   */     //   #15	-> 360
/*   */     //   #16	-> 369
/*   */     //   #17	-> 630
/*   */     //   #18	-> 903
/*   */     //   #19	-> 924
/*   */     //   #20	-> 997
/*   */     //   #21	-> 1008
/*   */     //   #22	-> 1015
/*   */     //   #23	-> 1026
/*   */     //   #24	-> 1049
/*   */     //   #25	-> 1058
/*   */     //   #26	-> 1095
/*   */     //   #27	-> 1126
/*   */     //   #28	-> 1173
/*   */     //   #29	-> 1182
/*   */     //   #30	-> 1191
/*   */     //   #31	-> 1343
/*   */     //   #32	-> 1409
/*   */     //   #33	-> 1420
/*   */     //   #34	-> 1421
/*   */     //   #35	-> 1432
/*   */     //   #36	-> 1434
/*   */     // Exception table:
/*   */     //   from	to	target	type
/*   */     //   46	59	93	java/io/IOException
/*   */     //   178	191	225	java/io/IOException
/*   */     //   923	936	996	java/io/IOException
/*   */     //   961	965	996	java/io/IOException
/*   */     //   1151	1159	1168	java/io/IOException
/*   */     //   1160	1168	1168	java/io/IOException
/*   */   } }


/* Location:              /Users/vnnsnnt/Documents/Codespace/JavaWorkspace/RedTrainer/src/main/java/org/trainer/client/PokeMMO.jar!/f/AH0.class
 * Java compiler version: 6 (50.0)
 * JD-Core Version:       1.1.3
 */