package f;

public final class AK implements Runnable {
  public AK(YC paramYC, i parami, byte paramByte) {}
  
  public final void run() {
    // Byte code:
    //   0: aload_0
    //   1: dup
    //   2: getfield Xe : Lf/YC;
    //   5: astore_1
    //   6: getfield implements : Lf/i;
    //   9: dup
    //   10: astore_2
    //   11: aload_1
    //   12: dup
    //   13: aload_0
    //   14: getfield F30 : B
    //   17: istore_0
    //   18: aload_2
    //   19: putfield wm : Lf/i;
    //   22: iload_0
    //   23: putfield EN : B
    //   26: ifnonnull -> 73
    //   29: aload_1
    //   30: dup
    //   31: dup2
    //   32: getfield EF : Lf/dQ;
    //   35: ldc ''
    //   37: invokevirtual E1 : (Ljava/lang/String;)V
    //   40: getfield M2 : Lf/dQ;
    //   43: ldc ''
    //   45: invokevirtual E1 : (Ljava/lang/String;)V
    //   48: getfield qZ : Lf/dQ;
    //   51: ldc ''
    //   53: invokevirtual E1 : (Ljava/lang/String;)V
    //   56: getfield CV : Lf/dQ;
    //   59: sipush #1925
    //   62: ldc '0'
    //   64: invokestatic Go : (ILjava/lang/String;)Ljava/lang/String;
    //   67: invokevirtual E1 : (Ljava/lang/String;)V
    //   70: goto -> 225
    //   73: aload_2
    //   74: getfield B70 : Lf/UD0;
    //   77: dup
    //   78: astore_0
    //   79: ifnull -> 96
    //   82: aload_0
    //   83: aload_1
    //   84: getfield EF : Lf/dQ;
    //   87: astore_0
    //   88: iconst_0
    //   89: invokevirtual o60 : (Z)Ljava/lang/String;
    //   92: astore_3
    //   93: goto -> 135
    //   96: aload_2
    //   97: getfield cZ : Lf/lj0;
    //   100: dup
    //   101: astore_0
    //   102: ifnull -> 119
    //   105: aload_1
    //   106: getfield EF : Lf/dQ;
    //   109: aload_0
    //   110: invokevirtual s60 : ()Ljava/lang/String;
    //   113: invokevirtual E1 : (Ljava/lang/String;)V
    //   116: goto -> 140
    //   119: aload_2
    //   120: aload_1
    //   121: getfield EF : Lf/dQ;
    //   124: astore_0
    //   125: getfield BC : Lf/LPT3;
    //   128: getfield Iu : I
    //   131: invokestatic OH0 : (I)Ljava/lang/String;
    //   134: astore_3
    //   135: aload_0
    //   136: aload_3
    //   137: invokevirtual E1 : (Ljava/lang/String;)V
    //   140: aload_1
    //   141: dup
    //   142: dup
    //   143: getfield M2 : Lf/dQ;
    //   146: aload_2
    //   147: invokevirtual H0 : ()Ljava/lang/String;
    //   150: invokevirtual E1 : (Ljava/lang/String;)V
    //   153: getfield qZ : Lf/dQ;
    //   156: new java/lang/StringBuilder
    //   159: dup
    //   160: aload_2
    //   161: swap
    //   162: invokespecial <init> : ()V
    //   165: invokevirtual SK0 : ()I
    //   168: invokevirtual append : (I)Ljava/lang/StringBuilder;
    //   171: ldc ''
    //   173: invokevirtual append : (Ljava/lang/String;)Ljava/lang/StringBuilder;
    //   176: invokevirtual toString : ()Ljava/lang/String;
    //   179: sipush #1940
    //   182: swap
    //   183: invokestatic Go : (ILjava/lang/String;)Ljava/lang/String;
    //   186: invokevirtual E1 : (Ljava/lang/String;)V
    //   189: getfield CV : Lf/dQ;
    //   192: new java/lang/StringBuilder
    //   195: dup
    //   196: aload_2
    //   197: swap
    //   198: invokespecial <init> : ()V
    //   201: invokevirtual SK0 : ()I
    //   204: invokevirtual append : (I)Ljava/lang/StringBuilder;
    //   207: ldc ''
    //   209: invokevirtual append : (Ljava/lang/String;)Ljava/lang/StringBuilder;
    //   212: invokevirtual toString : ()Ljava/lang/String;
    //   215: sipush #1940
    //   218: swap
    //   219: invokestatic Go : (ILjava/lang/String;)Ljava/lang/String;
    //   222: invokevirtual E1 : (Ljava/lang/String;)V
    //   225: aload_2
    //   226: getfield B70 : Lf/UD0;
    //   229: ifnonnull -> 268
    //   232: aload_2
    //   233: getfield cZ : Lf/lj0;
    //   236: ifnonnull -> 268
    //   239: aload_2
    //   240: getfield BC : Lf/LPT3;
    //   243: getfield c3 : Lf/wc;
    //   246: ifnonnull -> 252
    //   249: goto -> 268
    //   252: aload_1
    //   253: getfield MX : Lf/Un;
    //   256: sipush #3006
    //   259: invokestatic OH0 : (I)Ljava/lang/String;
    //   262: invokevirtual s6 : (Ljava/lang/String;)V
    //   265: goto -> 280
    //   268: aload_1
    //   269: getfield MX : Lf/Un;
    //   272: bipush #56
    //   274: invokestatic OH0 : (I)Ljava/lang/String;
    //   277: invokevirtual s6 : (Ljava/lang/String;)V
    //   280: aload_1
    //   281: getfield wm : Lf/i;
    //   284: ifnonnull -> 298
    //   287: aload_1
    //   288: getfield MX : Lf/Un;
    //   291: iconst_0
    //   292: invokevirtual sk0 : (Z)V
    //   295: goto -> 306
    //   298: aload_1
    //   299: getfield MX : Lf/Un;
    //   302: iconst_1
    //   303: invokevirtual sk0 : (Z)V
    //   306: return
    // Line number table:
    //   Java source line number -> byte code offset
    //   #1	-> 19
    //   #2	-> 23
    //   #3	-> 74
    //   #4	-> 84
    //   #5	-> 89
    //   #6	-> 97
    //   #7	-> 106
    //   #8	-> 125
    //   #9	-> 128
    //   #10	-> 131
    //   #11	-> 137
    //   #12	-> 226
    //   #13	-> 233
    //   #14	-> 240
    //   #15	-> 243
    //   #16	-> 253
    //   #17	-> 281
  }
}


/* Location:              /Users/vnnsnnt/Documents/Codespace/JavaWorkspace/RedTrainer/src/main/java/org/trainer/client/PokeMMO.jar!/f/AK.class
 * Java compiler version: 8 (52.0)
 * JD-Core Version:       1.1.3
 */