/*  1 */ package f;public final class Ay extends Qa0 { public static final ik Xs0 = C00.gd(Ay.class); public final Ip lg; public rS vw; public ge0[] Com7; public bx0[] Tp; public boolean Sb; public ArrayList l4; private void R2() { O90 o90; JG0 jG0; if ((jG0 = (o90 = this.Sr).fr0) != null) jG0
/*  2 */         .jf0(o90);  this
/*  3 */       .Sr = null;
/*  4 */     js.vu0
/*    */       
/*  6 */       .Pu(-1, Ml0.OH0(1226)); }
/*    */   public Un YH; public ge0 H6; public O90 Sr; public float tt0; public e2 GT; public Ay() { super(km.XU(), false); Ip ip; Un un2; this.Sb = false; this.l4 = h1.ls0(); this.GT = new e2(100); TG0(this::close); jJ0(false); PX pX; if (!km.iE0.wG0(pX = PX.vr)) js.N2().Pu(10000, km.iE0.MK(pX));  this(); this.lg = new Ip(); Xu("mods-panel"); Lo(Ml0.OH0(1190)); this(Ml0.OH0(54)); this.YH = un1; Un un1; (un1 = new Un()).tW(() -> { dE0(); close(); }); this(Ml0.OH0(1191)); (new Un()).tW(Ay::Sx0); this(Ml0.OH0(1189)); (new Un()).tW(Ay::qD); if (km.ER()) un2 = null;  this(Ml0.OH0(1225)); Un un3; (un3 = new Un()).tW(() -> km.iE0.ar((), new String[] { "mod", "zip" })); (this.vw = new rS()).Xu("scrollpane"); update(); (this.H6 = new ge0("    ")).Gq0(Ml0.OH0(1199)); this.H6.Pb0(150); this.H6.zs(h1.zE); this(Ml0.OH0(1198)); dQ.Gq0(Ml0.OH0(1199)); dQ.Pb0(150); dQ dQ; (dQ = new dQ()).VH(this.H6); if (km.XU()) { ip.WN(ip.vo0(new JG0[] { this.vw }).ee0(ip.AUX(new JG0[] { un1, un3, un2, this.H6, dQ }))); ip.rK0(ip.AUX(new JG0[] { this.vw }).ee0(ip.vo0(new JG0[] { un1, un3, un2 }).Em0().Ya(this.H6).Ya(dQ))); } else { arrayOfJG0[0] = un1; arrayOfJG0[1] = un3; arrayOfJG0[2] = un2; arrayOfJG0[3] = this.H6; arrayOfJG0[4] = dQ; JG0[] arrayOfJG0; (arrayOfJG0 = new JG0[6])[5] = this.YH; ip.WN(ip.vo0(new JG0[] { this.vw }).ee0(ip.AUX(new JG0[6])).Aq(5)); ip.rK0(ip.AUX(new JG0[] { this.vw }).ee0(ip.vo0(new JG0[] { un1, un3, un2 }).Em0().Ya(this.H6).Ya(dQ).Em0().Ya(this.YH))); }  J8(ip); if (km.XU()) { this.YH.Xu("mobile-save-icon"); this.YH.s6(""); J8(this.YH); }  } private void xx(bx0 parambx0, RD0 paramRD01, RD0 paramRD02, RD0 paramRD03) { // Byte code:
/*    */     //   0: aload_1
/*    */     //   1: invokevirtual getClass : ()Ljava/lang/Class;
/*    */     //   4: pop
/*    */     //   5: new java/util/zip/ZipInputStream
/*    */     //   8: dup
/*    */     //   9: astore #5
/*    */     //   11: aload_1
/*    */     //   12: getfield a80 : Lf/RD0;
/*    */     //   15: sipush #2048
/*    */     //   18: invokevirtual hQ : (I)Ljava/io/BufferedInputStream;
/*    */     //   21: invokespecial <init> : (Ljava/io/InputStream;)V
/*    */     //   24: iconst_0
/*    */     //   25: istore #6
/*    */     //   27: aload #5
/*    */     //   29: invokevirtual getNextEntry : ()Ljava/util/zip/ZipEntry;
/*    */     //   32: dup
/*    */     //   33: astore #7
/*    */     //   35: ifnull -> 80
/*    */     //   38: aload #7
/*    */     //   40: invokevirtual getName : ()Ljava/lang/String;
/*    */     //   43: ldc_w 'info.xml'
/*    */     //   46: invokevirtual equals : (Ljava/lang/Object;)Z
/*    */     //   49: ifeq -> 27
/*    */     //   52: aload_1
/*    */     //   53: aload #5
/*    */     //   55: aload #7
/*    */     //   57: invokevirtual getSize : ()J
/*    */     //   60: l2i
/*    */     //   61: invokestatic Vn : (Ljava/io/InputStream;I)[B
/*    */     //   64: astore #6
/*    */     //   66: new java/io/ByteArrayInputStream
/*    */     //   69: dup
/*    */     //   70: aload #6
/*    */     //   72: invokespecial <init> : ([B)V
/*    */     //   75: invokevirtual g00 : (Ljava/io/InputStream;)Z
/*    */     //   78: istore #6
/*    */     //   80: iload #6
/*    */     //   82: aload #5
/*    */     //   84: invokevirtual close : ()V
/*    */     //   87: ifeq -> 102
/*    */     //   90: aload_1
/*    */     //   91: getfield XH0 : Z
/*    */     //   94: ifeq -> 102
/*    */     //   97: aload_1
/*    */     //   98: iconst_1
/*    */     //   99: putfield jA : Z
/*    */     //   102: aload_1
/*    */     //   103: getfield jA : Z
/*    */     //   106: istore_1
/*    */     //   107: goto -> 183
/*    */     //   110: astore #5
/*    */     //   112: goto -> 117
/*    */     //   115: astore #5
/*    */     //   117: getstatic f/bx0.aK : Lf/ik;
/*    */     //   120: ldc_w 'Error validating mod '
/*    */     //   123: invokestatic df : (Ljava/lang/String;)Ljava/lang/StringBuilder;
/*    */     //   126: aload_1
/*    */     //   127: getfield a80 : Lf/RD0;
/*    */     //   130: getfield ml : Ljava/io/File;
/*    */     //   133: invokevirtual getName : ()Ljava/lang/String;
/*    */     //   136: invokevirtual append : (Ljava/lang/String;)Ljava/lang/StringBuilder;
/*    */     //   139: invokevirtual toString : ()Ljava/lang/String;
/*    */     //   142: aload #5
/*    */     //   144: invokeinterface error : (Ljava/lang/String;Ljava/lang/Throwable;)V
/*    */     //   149: getstatic f/bx0.fX : Lf/ik;
/*    */     //   152: ldc_w 'Error validating mod '
/*    */     //   155: invokestatic df : (Ljava/lang/String;)Ljava/lang/StringBuilder;
/*    */     //   158: aload_1
/*    */     //   159: getfield a80 : Lf/RD0;
/*    */     //   162: getfield ml : Ljava/io/File;
/*    */     //   165: invokevirtual getName : ()Ljava/lang/String;
/*    */     //   168: invokevirtual append : (Ljava/lang/String;)Ljava/lang/StringBuilder;
/*    */     //   171: invokevirtual toString : ()Ljava/lang/String;
/*    */     //   174: aload #5
/*    */     //   176: invokeinterface error : (Ljava/lang/String;Ljava/lang/Throwable;)V
/*    */     //   181: iconst_0
/*    */     //   182: istore_1
/*    */     //   183: iload_1
/*    */     //   184: ifeq -> 390
/*    */     //   187: aload_3
/*    */     //   188: aload_2
/*    */     //   189: getstatic f/UB0.Kg0 : Lf/Q50;
/*    */     //   192: aload_0
/*    */     //   193: <illegal opcode> run : (Lf/Ay;)Ljava/lang/Runnable;
/*    */     //   198: invokevirtual fN : (Ljava/lang/Runnable;)V
/*    */     //   201: invokevirtual wT : ()Lf/RD0;
/*    */     //   204: invokevirtual iz0 : ()V
/*    */     //   207: invokevirtual L0 : ()Z
/*    */     //   210: ifne -> 214
/*    */     //   213: return
/*    */     //   214: aload_3
/*    */     //   215: aload_2
/*    */     //   216: aload_3
/*    */     //   217: aload #4
/*    */     //   219: aconst_null
/*    */     //   220: astore_1
/*    */     //   221: aconst_null
/*    */     //   222: astore_3
/*    */     //   223: ldc ''
/*    */     //   225: aconst_null
/*    */     //   226: invokevirtual vF0 : (Ljava/lang/String;Ljava/lang/String;)V
/*    */     //   229: invokevirtual Yc : ()Ljava/io/InputStream;
/*    */     //   232: astore_1
/*    */     //   233: invokevirtual hh : ()Ljava/io/OutputStream;
/*    */     //   236: astore_3
/*    */     //   237: invokevirtual tN : ()J
/*    */     //   240: lstore #5
/*    */     //   242: sipush #1024
/*    */     //   245: newarray byte
/*    */     //   247: astore #7
/*    */     //   249: lconst_0
/*    */     //   250: lstore #8
/*    */     //   252: aload_1
/*    */     //   253: aload #7
/*    */     //   255: invokevirtual read : ([B)I
/*    */     //   258: dup
/*    */     //   259: istore #10
/*    */     //   261: iconst_m1
/*    */     //   262: if_icmpeq -> 295
/*    */     //   265: aload_3
/*    */     //   266: aload #7
/*    */     //   268: aload_0
/*    */     //   269: lload #8
/*    */     //   271: iload #10
/*    */     //   273: i2l
/*    */     //   274: ladd
/*    */     //   275: dup2
/*    */     //   276: lstore #8
/*    */     //   278: l2f
/*    */     //   279: lload #5
/*    */     //   281: l2f
/*    */     //   282: fdiv
/*    */     //   283: putfield tt0 : F
/*    */     //   286: iconst_0
/*    */     //   287: iload #10
/*    */     //   289: invokevirtual write : ([BII)V
/*    */     //   292: goto -> 252
/*    */     //   295: aload_3
/*    */     //   296: aload_1
/*    */     //   297: aload #4
/*    */     //   299: aload_3
/*    */     //   300: aload_1
/*    */     //   301: invokevirtual close : ()V
/*    */     //   304: invokevirtual close : ()V
/*    */     //   307: invokevirtual La0 : ()Z
/*    */     //   310: pop
/*    */     //   311: invokestatic JC0 : (Ljava/io/Closeable;)V
/*    */     //   314: invokestatic JC0 : (Ljava/io/Closeable;)V
/*    */     //   317: getstatic f/UB0.Kg0 : Lf/Q50;
/*    */     //   320: aload_0
/*    */     //   321: aload_2
/*    */     //   322: <illegal opcode> run : (Lf/Ay;Lf/RD0;)Ljava/lang/Runnable;
/*    */     //   327: invokevirtual fN : (Ljava/lang/Runnable;)V
/*    */     //   330: goto -> 402
/*    */     //   333: astore_0
/*    */     //   334: goto -> 380
/*    */     //   337: astore_0
/*    */     //   338: aload_3
/*    */     //   339: aload_1
/*    */     //   340: aload #4
/*    */     //   342: aload_2
/*    */     //   343: getstatic f/Ay.Xs0 : Lf/ik;
/*    */     //   346: ldc ''
/*    */     //   348: aload_0
/*    */     //   349: invokeinterface error : (Ljava/lang/String;Ljava/lang/Throwable;)V
/*    */     //   354: invokevirtual La0 : ()Z
/*    */     //   357: pop
/*    */     //   358: invokevirtual La0 : ()Z
/*    */     //   361: pop
/*    */     //   362: getstatic f/UB0.Kg0 : Lf/Q50;
/*    */     //   365: <illegal opcode> run : ()Ljava/lang/Runnable;
/*    */     //   370: invokevirtual fN : (Ljava/lang/Runnable;)V
/*    */     //   373: invokestatic JC0 : (Ljava/io/Closeable;)V
/*    */     //   376: invokestatic JC0 : (Ljava/io/Closeable;)V
/*    */     //   379: return
/*    */     //   380: aload_0
/*    */     //   381: aload_3
/*    */     //   382: aload_1
/*    */     //   383: invokestatic JC0 : (Ljava/io/Closeable;)V
/*    */     //   386: invokestatic JC0 : (Ljava/io/Closeable;)V
/*    */     //   389: athrow
/*    */     //   390: getstatic f/UB0.Kg0 : Lf/Q50;
/*    */     //   393: aload_0
/*    */     //   394: <illegal opcode> run : (Lf/Ay;)Ljava/lang/Runnable;
/*    */     //   399: invokevirtual fN : (Ljava/lang/Runnable;)V
/*    */     //   402: return
/*    */     // Line number table:
/*    */     //   Java source line number -> byte code offset
/*    */     //   #1	-> 5
/*    */     //   #2	-> 120
/*    */     //   #3	-> 127
/*    */     //   #4	-> 130
/*    */     //   #5	-> 133
/*    */     //   #6	-> 136
/*    */     //   #7	-> 152
/*    */     //   #8	-> 159
/*    */     //   #9	-> 162
/*    */     //   #10	-> 165
/*    */     //   #11	-> 168
/*    */     //   #12	-> 189
/*    */     //   #13	-> 226
/*    */     //   #14	-> 229
/*    */     // Exception table:
/*    */     //   from	to	target	type
/*    */     //   5	8	115	java/io/IOException
/*    */     //   5	8	110	java/lang/IllegalArgumentException
/*    */     //   11	24	115	java/io/IOException
/*    */     //   11	24	110	java/lang/IllegalArgumentException
/*    */     //   27	32	115	java/io/IOException
/*    */     //   27	32	110	java/lang/IllegalArgumentException
/*    */     //   38	49	115	java/io/IOException
/*    */     //   38	49	110	java/lang/IllegalArgumentException
/*    */     //   52	60	115	java/io/IOException
/*    */     //   52	60	110	java/lang/IllegalArgumentException
/*    */     //   61	64	115	java/io/IOException
/*    */     //   61	64	110	java/lang/IllegalArgumentException
/*    */     //   66	78	115	java/io/IOException
/*    */     //   66	78	110	java/lang/IllegalArgumentException
/*    */     //   80	87	115	java/io/IOException
/*    */     //   80	87	110	java/lang/IllegalArgumentException
/*    */     //   90	94	115	java/io/IOException
/*    */     //   90	94	110	java/lang/IllegalArgumentException
/*    */     //   97	106	115	java/io/IOException
/*    */     //   97	106	110	java/lang/IllegalArgumentException
/*    */     //   223	232	337	java/lang/Exception
/*    */     //   223	232	333	finally
/*    */     //   233	236	337	java/lang/Exception
/*    */     //   233	236	333	finally
/*    */     //   237	240	337	java/lang/Exception
/*    */     //   237	240	333	finally
/*    */     //   242	247	337	java/lang/Exception
/*    */     //   242	247	333	finally
/*    */     //   252	258	337	java/lang/Exception
/*    */     //   252	258	333	finally
/*    */     //   283	310	337	java/lang/Exception
/*    */     //   283	310	333	finally
/*    */     //   338	357	333	finally
/*    */     //   358	361	333	finally
/*  7 */     //   362	373	333	finally } private void k30(RD0 paramRD0) { O90 o90; JG0 jG0; if ((jG0 = (o90 = this.Sr).fr0) != null) jG0.jf0(o90);  this.Sr = null; if (d00.Je.Tq0(paramRD0, false)) { this.l4.add(0, paramRD0.ml.getName()); this.Sb = true; dE0();
/*  8 */       js.vu0
/*    */         
/* 10 */         .Pu(-1, Ml0.OH0(1227));
/* 11 */       UB0.Kg0.fN(this::update); } else { paramRD0.La0();
/* 12 */       js.vu0
/*    */         
/* 14 */         .Pu(-1, Ml0.OH0(1226)); }  } public static void iq() { js.vu0.Pu(-1, Ml0.OH0(1138)); } private void XU() { String str = Ml0.OH0(1139); this.Sr.Su.E1(this); } private void lv(bx0 parambx0) { int i; if ((i = this.l4.indexOf(parambx0.a80.ml.getName())) > 0) Collections.swap(this.l4, i - 1, i);  update(); } private void jM(bx0 parambx0) { int i; int j; if ((j = (i = this.l4.indexOf(parambx0.a80.ml.getName())) + 1) < this.l4.size()) Collections.swap(this.l4, i, j);  update(); } public static void pA0(ge0 paramge0) { if (!paramge0.TG0.nm0()) { boolean bool = true; paramge0.TG0.Fx0(bool); }  js.vu0.Pu(-1, Ml0.OH0(1197)); } private void Y1(bx0 parambx0, Un paramUn) { // Byte code:
/*    */     //   0: getstatic f/js.vu0 : Lf/js;
/*    */     //   3: new f/h70
/*    */     //   6: dup
/*    */     //   7: aload_0
/*    */     //   8: aload_1
/*    */     //   9: sipush #1229
/*    */     //   12: aload_1
/*    */     //   13: getfield aj : Ljava/lang/String;
/*    */     //   16: invokestatic Go : (ILjava/lang/String;)Ljava/lang/String;
/*    */     //   19: astore_0
/*    */     //   20: <illegal opcode> run : (Lf/Ay;Lf/bx0;)Ljava/lang/Runnable;
/*    */     //   25: aload_0
/*    */     //   26: swap
/*    */     //   27: aload_2
/*    */     //   28: invokespecial <init> : (Ljava/lang/String;Ljava/lang/Runnable;Lf/JG0;)V
/*    */     //   31: invokevirtual uh : (Lf/h70;)V
/*    */     //   34: return
/*    */     // Line number table:
/*    */     //   Java source line number -> byte code offset
/*    */     //   #1	-> 0
/*    */     //   #2	-> 3
/*    */     //   #3	-> 13
/*    */     //   #4	-> 16 } private void nl0(bx0 parambx0) { parambx0.a80.La0(); d00.Je.nr0.remove(parambx0); this.Sb = true; update(); }
/*    */   public static void Wk(bx0 parambx0) { if (parambx0.Nq0.isEmpty() || ((parambx0.Nq0.startsWith("http://") ^ true) & (parambx0.Nq0.startsWith("https://") ^ true)) != 0) { js.vu0.Pu(-1, Ml0.OH0(1196)); return; }  UB0.LL0.Zq(parambx0.Nq0); }
/*    */   private void Uq(bx0 parambx0, ge0 paramge0) { if (parambx0.YE) return;  if (paramge0.TG0.nm0()) { this.l4.add(0, parambx0.a80.ml.getName()); } else { this.l4.remove(parambx0.a80.ml.getName()); }  update(); }
/*    */   private int bN(bx0 parambx01, bx0 parambx02) { boolean bool1; boolean bool2; if ((bool1 = parambx01.YE) != (bool2 = parambx02.YE)) return bool2 - bool1;  if ((bool1 = this.l4.contains(parambx01.a80.ml.getName())) != (bool2 = this.l4.contains(parambx02.a80.ml.getName()))) return bool2 - bool1;  if (!bool1) {
/* 18 */       return parambx02.a80.ml.getName().compareTo(parambx01.a80.ml.getName());
/*    */     }
/*    */ 
/*    */ 
/*    */ 
/*    */ 
/*    */ 
/*    */     
/* 26 */     return this.l4.indexOf(parambx01.a80.ml.getName()) - this.l4.indexOf(parambx02.a80.ml.getName()); }
/*    */ 
/*    */   
/*    */   public final void update() {
/*    */     // Byte code:
/*    */     //   0: new f/Ip
/*    */     //   3: dup
/*    */     //   4: dup
/*    */     //   5: astore_1
/*    */     //   6: invokespecial <init> : ()V
/*    */     //   9: ldc_w 'settings-label-area'
/*    */     //   12: invokevirtual Xu : (Ljava/lang/String;)V
/*    */     //   15: new f/cr0
/*    */     //   18: dup
/*    */     //   19: astore_2
/*    */     //   20: aload_1
/*    */     //   21: invokespecial <init> : (Lf/Ip;)V
/*    */     //   24: new f/g0
/*    */     //   27: dup
/*    */     //   28: astore_3
/*    */     //   29: aload_1
/*    */     //   30: invokespecial <init> : (Lf/Ip;)V
/*    */     //   33: getstatic f/d00.Je : Lf/d00;
/*    */     //   36: dup
/*    */     //   37: invokevirtual getClass : ()Ljava/lang/Class;
/*    */     //   40: pop
/*    */     //   41: new java/util/ArrayList
/*    */     //   44: dup
/*    */     //   45: astore #4
/*    */     //   47: invokespecial <init> : ()V
/*    */     //   50: getfield nr0 : Ljava/util/ArrayList;
/*    */     //   53: invokevirtual iterator : ()Ljava/util/Iterator;
/*    */     //   56: astore #5
/*    */     //   58: aload #5
/*    */     //   60: invokeinterface hasNext : ()Z
/*    */     //   65: ifeq -> 98
/*    */     //   68: aload #5
/*    */     //   70: invokeinterface next : ()Ljava/lang/Object;
/*    */     //   75: checkcast f/bx0
/*    */     //   78: dup
/*    */     //   79: astore #6
/*    */     //   81: getfield YE : Z
/*    */     //   84: ifne -> 58
/*    */     //   87: aload #4
/*    */     //   89: aload #6
/*    */     //   91: invokevirtual add : (Ljava/lang/Object;)Z
/*    */     //   94: pop
/*    */     //   95: goto -> 58
/*    */     //   98: aload #4
/*    */     //   100: iconst_0
/*    */     //   101: anewarray f/bx0
/*    */     //   104: invokevirtual toArray : ([Ljava/lang/Object;)[Ljava/lang/Object;
/*    */     //   107: checkcast [Lf/bx0;
/*    */     //   110: dup
/*    */     //   111: astore #4
/*    */     //   113: aload_0
/*    */     //   114: dup
/*    */     //   115: aload #4
/*    */     //   117: aload_0
/*    */     //   118: aload #4
/*    */     //   120: putfield Tp : [Lf/bx0;
/*    */     //   123: arraylength
/*    */     //   124: anewarray f/ge0
/*    */     //   127: putfield Com7 : [Lf/ge0;
/*    */     //   130: <illegal opcode> compare : (Lf/Ay;)Ljava/util/Comparator;
/*    */     //   135: invokestatic sort : ([Ljava/lang/Object;Ljava/util/Comparator;)V
/*    */     //   138: iconst_0
/*    */     //   139: istore #4
/*    */     //   141: iload #4
/*    */     //   143: aload_0
/*    */     //   144: getfield Tp : [Lf/bx0;
/*    */     //   147: dup
/*    */     //   148: astore #5
/*    */     //   150: arraylength
/*    */     //   151: if_icmpge -> 1081
/*    */     //   154: aload #5
/*    */     //   156: iload #4
/*    */     //   158: aaload
/*    */     //   159: dup
/*    */     //   160: astore #5
/*    */     //   162: new java/lang/StringBuilder
/*    */     //   165: dup
/*    */     //   166: astore #6
/*    */     //   168: aload #5
/*    */     //   170: aload #6
/*    */     //   172: dup
/*    */     //   173: aload #5
/*    */     //   175: aload #6
/*    */     //   177: dup
/*    */     //   178: invokespecial <init> : ()V
/*    */     //   181: new java/lang/StringBuilder
/*    */     //   184: dup
/*    */     //   185: aload #5
/*    */     //   187: swap
/*    */     //   188: invokespecial <init> : ()V
/*    */     //   191: getfield aj : Ljava/lang/String;
/*    */     //   194: invokevirtual append : (Ljava/lang/String;)Ljava/lang/StringBuilder;
/*    */     //   197: ldc_w '\\n'
/*    */     //   200: invokevirtual append : (Ljava/lang/String;)Ljava/lang/StringBuilder;
/*    */     //   203: invokevirtual toString : ()Ljava/lang/String;
/*    */     //   206: invokevirtual append : (Ljava/lang/String;)Ljava/lang/StringBuilder;
/*    */     //   209: pop
/*    */     //   210: getfield d10 : Ljava/lang/String;
/*    */     //   213: sipush #1192
/*    */     //   216: swap
/*    */     //   217: invokestatic Go : (ILjava/lang/String;)Ljava/lang/String;
/*    */     //   220: invokevirtual append : (Ljava/lang/String;)Ljava/lang/StringBuilder;
/*    */     //   223: pop
/*    */     //   224: ldc_w '\\n'
/*    */     //   227: invokevirtual append : (Ljava/lang/String;)Ljava/lang/StringBuilder;
/*    */     //   230: pop
/*    */     //   231: getfield Xq0 : Ljava/lang/String;
/*    */     //   234: sipush #1193
/*    */     //   237: swap
/*    */     //   238: invokestatic Go : (ILjava/lang/String;)Ljava/lang/String;
/*    */     //   241: invokevirtual append : (Ljava/lang/String;)Ljava/lang/StringBuilder;
/*    */     //   244: pop
/*    */     //   245: new f/dQ
/*    */     //   248: dup
/*    */     //   249: dup2
/*    */     //   250: astore #7
/*    */     //   252: aload #6
/*    */     //   254: invokevirtual toString : ()Ljava/lang/String;
/*    */     //   257: astore #6
/*    */     //   259: invokespecial <init> : ()V
/*    */     //   262: aload #6
/*    */     //   264: invokevirtual E1 : (Ljava/lang/String;)V
/*    */     //   267: ldc_w 'label-settings-title'
/*    */     //   270: invokevirtual Xu : (Ljava/lang/String;)V
/*    */     //   273: new f/vF0
/*    */     //   276: dup
/*    */     //   277: astore #6
/*    */     //   279: bipush #64
/*    */     //   281: bipush #64
/*    */     //   283: iconst_0
/*    */     //   284: invokespecial <init> : (III)V
/*    */     //   287: getfield Gz0 : Lf/U70;
/*    */     //   290: dup
/*    */     //   291: astore #8
/*    */     //   293: ifnull -> 330
/*    */     //   296: aload #6
/*    */     //   298: aload #8
/*    */     //   300: invokevirtual HA0 : ()Lcom/badlogic/gdx/graphics/Texture;
/*    */     //   303: getstatic f/cu0.IE : Lf/cu0;
/*    */     //   306: dup
/*    */     //   307: invokevirtual setFilter : (Lf/cu0;Lf/cu0;)V
/*    */     //   310: getfield TS : Lf/rH;
/*    */     //   313: iconst_1
/*    */     //   314: anewarray f/U70
/*    */     //   317: dup
/*    */     //   318: aload #5
/*    */     //   320: getfield Gz0 : Lf/U70;
/*    */     //   323: iconst_0
/*    */     //   324: swap
/*    */     //   325: aastore
/*    */     //   326: invokevirtual qt : ([Lf/U70;)Lf/JG0;
/*    */     //   329: pop
/*    */     //   330: aload #5
/*    */     //   332: aload #6
/*    */     //   334: dup
/*    */     //   335: dup
/*    */     //   336: aload #5
/*    */     //   338: aload #7
/*    */     //   340: dup
/*    */     //   341: dup
/*    */     //   342: aload #5
/*    */     //   344: aload #6
/*    */     //   346: getfield TS : Lf/rH;
/*    */     //   349: bipush #64
/*    */     //   351: bipush #64
/*    */     //   353: invokevirtual tL : (II)V
/*    */     //   356: getfield Vu0 : Ljava/lang/String;
/*    */     //   359: putfield z4 : Ljava/lang/Object;
/*    */     //   362: invokevirtual zn : ()V
/*    */     //   365: sipush #250
/*    */     //   368: putfield jl : I
/*    */     //   371: getfield Vu0 : Ljava/lang/String;
/*    */     //   374: putfield z4 : Ljava/lang/Object;
/*    */     //   377: invokevirtual zn : ()V
/*    */     //   380: sipush #250
/*    */     //   383: putfield jl : I
/*    */     //   386: new f/ge0
/*    */     //   389: dup
/*    */     //   390: astore #8
/*    */     //   392: aload_0
/*    */     //   393: aload #5
/*    */     //   395: aload #8
/*    */     //   397: aload_0
/*    */     //   398: aload #8
/*    */     //   400: aload_0
/*    */     //   401: aload #8
/*    */     //   403: invokespecial <init> : ()V
/*    */     //   406: getfield l4 : Ljava/util/ArrayList;
/*    */     //   409: aload #5
/*    */     //   411: getfield a80 : Lf/RD0;
/*    */     //   414: getfield ml : Ljava/io/File;
/*    */     //   417: invokevirtual getName : ()Ljava/lang/String;
/*    */     //   420: invokevirtual contains : (Ljava/lang/Object;)Z
/*    */     //   423: istore #9
/*    */     //   425: getfield TG0 : Lf/protected;
/*    */     //   428: iload #9
/*    */     //   430: invokevirtual Fx0 : (Z)V
/*    */     //   433: getfield Com7 : [Lf/ge0;
/*    */     //   436: iload #4
/*    */     //   438: aload #8
/*    */     //   440: aastore
/*    */     //   441: bipush #80
/*    */     //   443: bipush #30
/*    */     //   445: invokevirtual Tm : (II)Z
/*    */     //   448: pop
/*    */     //   449: aload #8
/*    */     //   451: <illegal opcode> run : (Lf/Ay;Lf/bx0;Lf/ge0;)Ljava/lang/Runnable;
/*    */     //   456: invokevirtual tW : (Ljava/lang/Runnable;)V
/*    */     //   459: new f/Un
/*    */     //   462: dup
/*    */     //   463: astore #10
/*    */     //   465: aload #5
/*    */     //   467: aload #10
/*    */     //   469: sipush #1195
/*    */     //   472: invokestatic OH0 : (I)Ljava/lang/String;
/*    */     //   475: invokespecial <init> : (Ljava/lang/String;)V
/*    */     //   478: <illegal opcode> run : (Lf/bx0;)Ljava/lang/Runnable;
/*    */     //   483: invokevirtual tW : (Ljava/lang/Runnable;)V
/*    */     //   486: new f/Un
/*    */     //   489: dup
/*    */     //   490: astore #11
/*    */     //   492: aload_0
/*    */     //   493: aload #5
/*    */     //   495: aload #11
/*    */     //   497: aload #5
/*    */     //   499: aload #11
/*    */     //   501: sipush #1228
/*    */     //   504: invokestatic OH0 : (I)Ljava/lang/String;
/*    */     //   507: invokespecial <init> : (Ljava/lang/String;)V
/*    */     //   510: getfield YE : Z
/*    */     //   513: iconst_1
/*    */     //   514: ixor
/*    */     //   515: invokevirtual sk0 : (Z)V
/*    */     //   518: aload #11
/*    */     //   520: <illegal opcode> run : (Lf/Ay;Lf/bx0;Lf/Un;)Ljava/lang/Runnable;
/*    */     //   525: invokevirtual tW : (Ljava/lang/Runnable;)V
/*    */     //   528: getfield YE : Z
/*    */     //   531: ifeq -> 553
/*    */     //   534: aload #8
/*    */     //   536: dup
/*    */     //   537: dup
/*    */     //   538: getfield TG0 : Lf/protected;
/*    */     //   541: iconst_1
/*    */     //   542: invokevirtual Fx0 : (Z)V
/*    */     //   545: <illegal opcode> run : (Lf/ge0;)Ljava/lang/Runnable;
/*    */     //   550: invokevirtual tW : (Ljava/lang/Runnable;)V
/*    */     //   553: aload_0
/*    */     //   554: new f/Ip
/*    */     //   557: dup
/*    */     //   558: dup
/*    */     //   559: dup2
/*    */     //   560: astore #12
/*    */     //   562: invokespecial <init> : ()V
/*    */     //   565: ldc_w 'label-settings-value-modbuttons'
/*    */     //   568: invokevirtual Xu : (Ljava/lang/String;)V
/*    */     //   571: new f/cr0
/*    */     //   574: dup
/*    */     //   575: dup
/*    */     //   576: astore #13
/*    */     //   578: aload #12
/*    */     //   580: invokespecial <init> : (Lf/Ip;)V
/*    */     //   583: new f/g0
/*    */     //   586: dup
/*    */     //   587: astore #14
/*    */     //   589: aload #12
/*    */     //   591: aload #13
/*    */     //   593: aload #12
/*    */     //   595: aload #14
/*    */     //   597: aload #12
/*    */     //   599: invokespecial <init> : (Lf/Ip;)V
/*    */     //   602: iconst_3
/*    */     //   603: anewarray f/JG0
/*    */     //   606: dup
/*    */     //   607: dup2
/*    */     //   608: iconst_0
/*    */     //   609: aload #8
/*    */     //   611: aastore
/*    */     //   612: iconst_1
/*    */     //   613: aload #11
/*    */     //   615: aastore
/*    */     //   616: iconst_2
/*    */     //   617: aload #10
/*    */     //   619: aastore
/*    */     //   620: invokevirtual vo0 : ([Lf/JG0;)Lf/U90;
/*    */     //   623: invokevirtual ee0 : (Lf/U90;)Lf/U90;
/*    */     //   626: pop
/*    */     //   627: iconst_3
/*    */     //   628: anewarray f/JG0
/*    */     //   631: dup
/*    */     //   632: dup2
/*    */     //   633: iconst_0
/*    */     //   634: aload #8
/*    */     //   636: aastore
/*    */     //   637: iconst_1
/*    */     //   638: aload #11
/*    */     //   640: aastore
/*    */     //   641: iconst_2
/*    */     //   642: aload #10
/*    */     //   644: aastore
/*    */     //   645: invokevirtual AUX : ([Lf/JG0;)Lf/U90;
/*    */     //   648: invokevirtual ee0 : (Lf/U90;)Lf/U90;
/*    */     //   651: pop
/*    */     //   652: invokevirtual WN : (Lf/U90;)V
/*    */     //   655: aload #14
/*    */     //   657: invokevirtual rK0 : (Lf/U90;)V
/*    */     //   660: new f/Ip
/*    */     //   663: dup
/*    */     //   664: dup
/*    */     //   665: astore #8
/*    */     //   667: invokespecial <init> : ()V
/*    */     //   670: ldc_w 'label-settings-value-modbuttons'
/*    */     //   673: invokevirtual Xu : (Ljava/lang/String;)V
/*    */     //   676: getfield Tp : [Lf/bx0;
/*    */     //   679: iload #4
/*    */     //   681: aaload
/*    */     //   682: getfield YE : Z
/*    */     //   685: ifne -> 920
/*    */     //   688: iload #9
/*    */     //   690: ifeq -> 920
/*    */     //   693: aload_0
/*    */     //   694: new f/Un
/*    */     //   697: dup
/*    */     //   698: astore #9
/*    */     //   700: aload_0
/*    */     //   701: aload #5
/*    */     //   703: aload #9
/*    */     //   705: dup
/*    */     //   706: ldc_w '↑'
/*    */     //   709: invokespecial <init> : (Ljava/lang/String;)V
/*    */     //   712: ldc_w 'button-symbol'
/*    */     //   715: invokevirtual Xu : (Ljava/lang/String;)V
/*    */     //   718: new f/Un
/*    */     //   721: dup
/*    */     //   722: astore #10
/*    */     //   724: aload_0
/*    */     //   725: aload #5
/*    */     //   727: aload #10
/*    */     //   729: dup
/*    */     //   730: ldc_w '↓'
/*    */     //   733: invokespecial <init> : (Ljava/lang/String;)V
/*    */     //   736: ldc_w 'button-symbol'
/*    */     //   739: invokevirtual Xu : (Ljava/lang/String;)V
/*    */     //   742: <illegal opcode> run : (Lf/Ay;Lf/bx0;)Ljava/lang/Runnable;
/*    */     //   747: invokevirtual tW : (Ljava/lang/Runnable;)V
/*    */     //   750: <illegal opcode> run : (Lf/Ay;Lf/bx0;)Ljava/lang/Runnable;
/*    */     //   755: invokevirtual tW : (Ljava/lang/Runnable;)V
/*    */     //   758: getfield l4 : Ljava/util/ArrayList;
/*    */     //   761: aload #5
/*    */     //   763: getfield a80 : Lf/RD0;
/*    */     //   766: getfield ml : Ljava/io/File;
/*    */     //   769: invokevirtual getName : ()Ljava/lang/String;
/*    */     //   772: invokevirtual indexOf : (Ljava/lang/Object;)I
/*    */     //   775: dup
/*    */     //   776: istore #5
/*    */     //   778: ifne -> 798
/*    */     //   781: aload_0
/*    */     //   782: getfield l4 : Ljava/util/ArrayList;
/*    */     //   785: invokevirtual size : ()I
/*    */     //   788: iconst_1
/*    */     //   789: if_icmple -> 798
/*    */     //   792: aload #9
/*    */     //   794: iconst_0
/*    */     //   795: invokevirtual wI0 : (Z)V
/*    */     //   798: iload #5
/*    */     //   800: iconst_1
/*    */     //   801: iadd
/*    */     //   802: aload_0
/*    */     //   803: getfield l4 : Ljava/util/ArrayList;
/*    */     //   806: invokevirtual size : ()I
/*    */     //   809: if_icmplt -> 818
/*    */     //   812: aload #10
/*    */     //   814: iconst_0
/*    */     //   815: invokevirtual wI0 : (Z)V
/*    */     //   818: aload #8
/*    */     //   820: dup
/*    */     //   821: aload #10
/*    */     //   823: aload #9
/*    */     //   825: bipush #10
/*    */     //   827: bipush #40
/*    */     //   829: invokevirtual RI : (II)V
/*    */     //   832: bipush #10
/*    */     //   834: bipush #40
/*    */     //   836: invokevirtual RI : (II)V
/*    */     //   839: new f/cr0
/*    */     //   842: dup
/*    */     //   843: dup
/*    */     //   844: astore #5
/*    */     //   846: aload #8
/*    */     //   848: invokespecial <init> : (Lf/Ip;)V
/*    */     //   851: new f/g0
/*    */     //   854: dup
/*    */     //   855: astore #11
/*    */     //   857: aload #8
/*    */     //   859: aload #5
/*    */     //   861: aload #8
/*    */     //   863: aload #11
/*    */     //   865: aload #8
/*    */     //   867: invokespecial <init> : (Lf/Ip;)V
/*    */     //   870: iconst_2
/*    */     //   871: anewarray f/JG0
/*    */     //   874: dup
/*    */     //   875: dup
/*    */     //   876: iconst_0
/*    */     //   877: aload #9
/*    */     //   879: aastore
/*    */     //   880: iconst_1
/*    */     //   881: aload #10
/*    */     //   883: aastore
/*    */     //   884: invokevirtual vo0 : ([Lf/JG0;)Lf/U90;
/*    */     //   887: invokevirtual ee0 : (Lf/U90;)Lf/U90;
/*    */     //   890: pop
/*    */     //   891: iconst_2
/*    */     //   892: anewarray f/JG0
/*    */     //   895: dup
/*    */     //   896: dup
/*    */     //   897: iconst_0
/*    */     //   898: aload #9
/*    */     //   900: aastore
/*    */     //   901: iconst_1
/*    */     //   902: aload #10
/*    */     //   904: aastore
/*    */     //   905: invokevirtual AUX : ([Lf/JG0;)Lf/U90;
/*    */     //   908: invokevirtual ee0 : (Lf/U90;)Lf/U90;
/*    */     //   911: pop
/*    */     //   912: invokevirtual WN : (Lf/U90;)V
/*    */     //   915: aload #11
/*    */     //   917: invokevirtual rK0 : (Lf/U90;)V
/*    */     //   920: aload_3
/*    */     //   921: aload_1
/*    */     //   922: aload_2
/*    */     //   923: aload_1
/*    */     //   924: new f/Ip
/*    */     //   927: dup
/*    */     //   928: dup2
/*    */     //   929: astore #5
/*    */     //   931: invokespecial <init> : ()V
/*    */     //   934: new f/cr0
/*    */     //   937: dup
/*    */     //   938: dup
/*    */     //   939: astore #9
/*    */     //   941: aload #5
/*    */     //   943: invokespecial <init> : (Lf/Ip;)V
/*    */     //   946: new f/g0
/*    */     //   949: dup
/*    */     //   950: astore #10
/*    */     //   952: aload #5
/*    */     //   954: aload #9
/*    */     //   956: aload #10
/*    */     //   958: aload #5
/*    */     //   960: invokespecial <init> : (Lf/Ip;)V
/*    */     //   963: new f/g0
/*    */     //   966: dup
/*    */     //   967: aload #5
/*    */     //   969: invokespecial <init> : (Lf/Ip;)V
/*    */     //   972: getstatic f/et.Wi0 : Lf/et;
/*    */     //   975: aload #6
/*    */     //   977: invokevirtual lW : (Lf/et;Lf/JG0;)Lf/U90;
/*    */     //   980: iconst_3
/*    */     //   981: anewarray f/JG0
/*    */     //   984: dup
/*    */     //   985: dup2
/*    */     //   986: iconst_0
/*    */     //   987: aload #7
/*    */     //   989: aastore
/*    */     //   990: iconst_1
/*    */     //   991: aload #12
/*    */     //   993: aastore
/*    */     //   994: iconst_2
/*    */     //   995: aload #8
/*    */     //   997: aastore
/*    */     //   998: invokevirtual Mg : ([Lf/JG0;)Lf/U90;
/*    */     //   1001: invokevirtual ee0 : (Lf/U90;)Lf/U90;
/*    */     //   1004: pop
/*    */     //   1005: iconst_4
/*    */     //   1006: anewarray f/JG0
/*    */     //   1009: dup
/*    */     //   1010: dup
/*    */     //   1011: dup2
/*    */     //   1012: iconst_0
/*    */     //   1013: aload #6
/*    */     //   1015: aastore
/*    */     //   1016: iconst_1
/*    */     //   1017: aload #7
/*    */     //   1019: aastore
/*    */     //   1020: iconst_2
/*    */     //   1021: aload #12
/*    */     //   1023: aastore
/*    */     //   1024: iconst_3
/*    */     //   1025: aload #8
/*    */     //   1027: aastore
/*    */     //   1028: invokevirtual vo0 : ([Lf/JG0;)Lf/U90;
/*    */     //   1031: invokevirtual ee0 : (Lf/U90;)Lf/U90;
/*    */     //   1034: pop
/*    */     //   1035: invokevirtual WN : (Lf/U90;)V
/*    */     //   1038: aload #10
/*    */     //   1040: invokevirtual rK0 : (Lf/U90;)V
/*    */     //   1043: iconst_1
/*    */     //   1044: anewarray f/JG0
/*    */     //   1047: dup
/*    */     //   1048: iconst_0
/*    */     //   1049: aload #5
/*    */     //   1051: aastore
/*    */     //   1052: invokevirtual AUX : ([Lf/JG0;)Lf/U90;
/*    */     //   1055: invokevirtual ee0 : (Lf/U90;)Lf/U90;
/*    */     //   1058: pop
/*    */     //   1059: iconst_1
/*    */     //   1060: anewarray f/JG0
/*    */     //   1063: dup
/*    */     //   1064: iconst_0
/*    */     //   1065: aload #5
/*    */     //   1067: aastore
/*    */     //   1068: invokevirtual vo0 : ([Lf/JG0;)Lf/U90;
/*    */     //   1071: invokevirtual ee0 : (Lf/U90;)Lf/U90;
/*    */     //   1074: pop
/*    */     //   1075: iinc #4, 1
/*    */     //   1078: goto -> 141
/*    */     //   1081: aload_0
/*    */     //   1082: getfield Com7 : [Lf/ge0;
/*    */     //   1085: arraylength
/*    */     //   1086: ifne -> 1167
/*    */     //   1089: aload_0
/*    */     //   1090: aload_3
/*    */     //   1091: aload_2
/*    */     //   1092: new f/dQ
/*    */     //   1095: dup
/*    */     //   1096: dup
/*    */     //   1097: astore #4
/*    */     //   1099: sipush #1230
/*    */     //   1102: invokestatic OH0 : (I)Ljava/lang/String;
/*    */     //   1105: astore #5
/*    */     //   1107: invokespecial <init> : ()V
/*    */     //   1110: aload #5
/*    */     //   1112: invokevirtual E1 : (Ljava/lang/String;)V
/*    */     //   1115: new f/cr0
/*    */     //   1118: dup
/*    */     //   1119: aload_1
/*    */     //   1120: invokespecial <init> : (Lf/Ip;)V
/*    */     //   1123: invokevirtual Em0 : ()Lf/U90;
/*    */     //   1126: aload #4
/*    */     //   1128: invokevirtual Ya : (Lf/JG0;)Lf/U90;
/*    */     //   1131: invokevirtual Em0 : ()Lf/U90;
/*    */     //   1134: invokevirtual ee0 : (Lf/U90;)Lf/U90;
/*    */     //   1137: pop
/*    */     //   1138: new f/cr0
/*    */     //   1141: dup
/*    */     //   1142: aload_1
/*    */     //   1143: invokespecial <init> : (Lf/Ip;)V
/*    */     //   1146: invokevirtual Em0 : ()Lf/U90;
/*    */     //   1149: aload #4
/*    */     //   1151: invokevirtual Ya : (Lf/JG0;)Lf/U90;
/*    */     //   1154: invokevirtual Em0 : ()Lf/U90;
/*    */     //   1157: invokevirtual ee0 : (Lf/U90;)Lf/U90;
/*    */     //   1160: pop
/*    */     //   1161: getfield vw : Lf/rS;
/*    */     //   1164: invokevirtual xZ : ()V
/*    */     //   1167: aload_0
/*    */     //   1168: aload_1
/*    */     //   1169: aload_3
/*    */     //   1170: aload_1
/*    */     //   1171: aload_2
/*    */     //   1172: invokevirtual WN : (Lf/U90;)V
/*    */     //   1175: invokevirtual rK0 : (Lf/U90;)V
/*    */     //   1178: getfield vw : Lf/rS;
/*    */     //   1181: aload_1
/*    */     //   1182: invokevirtual Gz0 : (Lf/JG0;)V
/*    */     //   1185: return
/*    */     // Line number table:
/*    */     //   Java source line number -> byte code offset
/*    */     //   #1	-> 15
/*    */     //   #2	-> 24
/*    */     //   #3	-> 33
/*    */     //   #4	-> 37
/*    */     //   #5	-> 41
/*    */     //   #6	-> 81
/*    */     //   #7	-> 91
/*    */     //   #8	-> 101
/*    */     //   #9	-> 191
/*    */     //   #10	-> 194
/*    */     //   #11	-> 210
/*    */     //   #12	-> 217
/*    */     //   #13	-> 231
/*    */     //   #14	-> 238
/*    */     //   #15	-> 259
/*    */     //   #16	-> 267
/*    */     //   #17	-> 284
/*    */     //   #18	-> 287
/*    */     //   #19	-> 300
/*    */     //   #20	-> 310
/*    */     //   #21	-> 314
/*    */     //   #22	-> 320
/*    */     //   #23	-> 325
/*    */     //   #24	-> 346
/*    */     //   #25	-> 353
/*    */     //   #26	-> 356
/*    */     //   #27	-> 359
/*    */     //   #28	-> 368
/*    */     //   #29	-> 371
/*    */     //   #30	-> 374
/*    */     //   #31	-> 383
/*    */     //   #32	-> 386
/*    */     //   #33	-> 411
/*    */     //   #34	-> 414
/*    */     //   #35	-> 417
/*    */     //   #36	-> 420
/*    */     //   #37	-> 425
/*    */     //   #38	-> 430
/*    */     //   #39	-> 433
/*    */     //   #40	-> 510
/*    */     //   #41	-> 515
/*    */     //   #42	-> 528
/*    */     //   #43	-> 538
/*    */     //   #44	-> 542
/*    */     //   #45	-> 545
/*    */     //   #46	-> 571
/*    */     //   #47	-> 583
/*    */     //   #48	-> 603
/*    */     //   #49	-> 682
/*    */     //   #50	-> 694
/*    */     //   #51	-> 763
/*    */     //   #52	-> 766
/*    */     //   #53	-> 769
/*    */     //   #54	-> 772
/*    */     //   #55	-> 839
/*    */     //   #56	-> 851
/*    */     //   #57	-> 871
/*    */     //   #58	-> 934
/*    */     //   #59	-> 946
/*    */     //   #60	-> 972
/*    */     //   #61	-> 1107
/*    */     //   #62	-> 1115
/*    */     //   #63	-> 1123
/*    */     //   #64	-> 1138
/*    */     //   #65	-> 1146
/*    */   }
/*    */   
/*    */   public final void dE0() {
/*    */     String str = h1.Na;
/*    */     boolean bool = h1.zE;
/*    */     this();
/*    */     StringBuilder stringBuilder;
/*    */     for (String str1 : this.l4) {
/*    */       if (stringBuilder.length() > 0)
/*    */         stringBuilder.append("/"); 
/*    */       stringBuilder.append(str1);
/*    */     } 
/*    */     if (str.equals(stringBuilder.toString()) && bool == this.H6.TG0.nm0())
/*    */       return; 
/*    */     this.Sb = str.equals(stringBuilder.toString()) ^ true;
/*    */     h1.Na = stringBuilder.toString();
/*    */     h1.zE = this.H6.TG0.nm0();
/*    */     js js;
/*    */     if (!h1.Td() && (js = js.vu0) != null)
/*    */       Pu(-1, Ml0.OH0(87)); 
/*    */   }
/*    */   
/*    */   public final void RJ0(RD0 paramRD0) {
/*    */     // Byte code:
/*    */     //   0: getstatic f/UB0.vj0 : Lf/XG;
/*    */     //   3: ldc_w 'data/mods/'
/*    */     //   6: invokevirtual N0 : (Ljava/lang/String;)Lf/hZ;
/*    */     //   9: aload_1
/*    */     //   10: getfield ml : Ljava/io/File;
/*    */     //   13: invokevirtual getName : ()Ljava/lang/String;
/*    */     //   16: invokevirtual f0 : (Ljava/lang/String;)Lf/RD0;
/*    */     //   19: astore_2
/*    */     //   20: getstatic f/UB0.vj0 : Lf/XG;
/*    */     //   23: ldc_w 'data/mods/'
/*    */     //   26: invokevirtual N0 : (Ljava/lang/String;)Lf/hZ;
/*    */     //   29: new java/lang/StringBuilder
/*    */     //   32: dup
/*    */     //   33: aload_1
/*    */     //   34: swap
/*    */     //   35: invokespecial <init> : ()V
/*    */     //   38: getfield ml : Ljava/io/File;
/*    */     //   41: invokevirtual getName : ()Ljava/lang/String;
/*    */     //   44: invokevirtual append : (Ljava/lang/String;)Ljava/lang/StringBuilder;
/*    */     //   47: ldc_w '.lock'
/*    */     //   50: invokevirtual append : (Ljava/lang/String;)Ljava/lang/StringBuilder;
/*    */     //   53: invokevirtual toString : ()Ljava/lang/String;
/*    */     //   56: invokevirtual f0 : (Ljava/lang/String;)Lf/RD0;
/*    */     //   59: dup
/*    */     //   60: astore_3
/*    */     //   61: invokevirtual L0 : ()Z
/*    */     //   64: ifeq -> 77
/*    */     //   67: aload_3
/*    */     //   68: aload_2
/*    */     //   69: invokevirtual La0 : ()Z
/*    */     //   72: pop
/*    */     //   73: invokevirtual La0 : ()Z
/*    */     //   76: pop
/*    */     //   77: aload_2
/*    */     //   78: invokevirtual L0 : ()Z
/*    */     //   81: ifeq -> 99
/*    */     //   84: getstatic f/js.vu0 : Lf/js;
/*    */     //   87: sipush #1232
/*    */     //   90: invokestatic OH0 : (I)Ljava/lang/String;
/*    */     //   93: iconst_m1
/*    */     //   94: swap
/*    */     //   95: invokevirtual Pu : (ILjava/lang/String;)V
/*    */     //   98: return
/*    */     //   99: aload_0
/*    */     //   100: dup
/*    */     //   101: dup
/*    */     //   102: new f/O90
/*    */     //   105: dup
/*    */     //   106: dup
/*    */     //   107: astore_0
/*    */     //   108: getstatic f/js.iK : Lf/ik;
/*    */     //   111: pop
/*    */     //   112: sipush #1095
/*    */     //   115: invokestatic OH0 : (I)Ljava/lang/String;
/*    */     //   118: invokespecial <init> : (Ljava/lang/String;)V
/*    */     //   121: putfield Sr : Lf/O90;
/*    */     //   124: getstatic f/js.vu0 : Lf/js;
/*    */     //   127: dup
/*    */     //   128: aload_0
/*    */     //   129: swap
/*    */     //   130: invokevirtual Ub : ()I
/*    */     //   133: invokevirtual si : (Lf/JG0;I)V
/*    */     //   136: ldc_w -1.0
/*    */     //   139: putfield tt0 : F
/*    */     //   142: new f/bx0
/*    */     //   145: dup
/*    */     //   146: aload_2
/*    */     //   147: swap
/*    */     //   148: aload_1
/*    */     //   149: iconst_0
/*    */     //   150: invokespecial <init> : (Lf/RD0;Z)V
/*    */     //   153: getstatic f/A1.L7 : Lf/A1;
/*    */     //   156: astore_0
/*    */     //   157: aload_1
/*    */     //   158: aload_3
/*    */     //   159: <illegal opcode> run : (Lf/Ay;Lf/bx0;Lf/RD0;Lf/RD0;Lf/RD0;)Ljava/lang/Runnable;
/*    */     //   164: aload_0
/*    */     //   165: getfield nc : Lf/cK0;
/*    */     //   168: swap
/*    */     //   169: invokevirtual execute : (Ljava/lang/Runnable;)V
/*    */     //   172: goto -> 188
/*    */     //   175: astore_0
/*    */     //   176: getstatic f/Ay.Xs0 : Lf/ik;
/*    */     //   179: ldc_w 'Unable to load mod'
/*    */     //   182: aload_0
/*    */     //   183: invokeinterface info : (Ljava/lang/String;Ljava/lang/Throwable;)V
/*    */     //   188: return
/*    */     // Line number table:
/*    */     //   Java source line number -> byte code offset
/*    */     //   #1	-> 10
/*    */     //   #2	-> 13
/*    */     //   #3	-> 16
/*    */     //   #4	-> 38
/*    */     //   #5	-> 44
/*    */     //   #6	-> 84
/*    */     //   #7	-> 90
/*    */     //   #8	-> 95
/*    */     //   #9	-> 102
/*    */     //   #10	-> 108
/*    */     //   #11	-> 115
/*    */     //   #12	-> 124
/*    */     //   #13	-> 130
/*    */     //   #14	-> 133
/*    */     //   #15	-> 139
/*    */     //   #16	-> 153
/*    */     //   #17	-> 159
/*    */     //   #18	-> 165
/*    */     //   #19	-> 169
/*    */     //   #20	-> 176
/*    */     // Exception table:
/*    */     //   from	to	target	type
/*    */     //   0	19	175	java/lang/Exception
/*    */     //   20	32	175	java/lang/Exception
/*    */     //   33	59	175	java/lang/Exception
/*    */     //   61	64	175	java/lang/Exception
/*    */     //   67	72	175	java/lang/Exception
/*    */     //   73	76	175	java/lang/Exception
/*    */     //   77	81	175	java/lang/Exception
/*    */     //   84	98	175	java/lang/Exception
/*    */     //   99	105	175	java/lang/Exception
/*    */     //   108	111	175	java/lang/Exception
/*    */     //   112	127	175	java/lang/Exception
/*    */     //   128	145	175	java/lang/Exception
/*    */     //   146	156	175	java/lang/Exception
/*    */     //   157	175	175	java/lang/Exception
/*    */   }
/*    */   
/*    */   public final void close() {
/*    */     r9 r9;
/*    */     if (this.Sb) {
/*    */       (r9 = km.iE0).getClass();
/*    */       js js;
/*    */       if ((js = js.vu0) == null) {
/*    */         bn();
/*    */       } else {
/*    */         lPt6 lPt6;
/*    */         String str = Ml0.OH0(1179);
/*    */         this(this);
/*    */         js.DJ(str, lPt6);
/*    */       } 
/*    */       return;
/*    */     } 
/*    */     ra0();
/*    */   }
/*    */   
/*    */   public final void V90(throws paramthrows) {
/*    */     super.V90(paramthrows);
/*    */     if (this.Sr != null && this.GT.Po0())
/*    */       this.Sr.uc0(this.tt0); 
/*    */   }
/*    */   
/*    */   public final void d40() {
/*    */     if (this.fr0 == null)
/*    */       return; 
/*    */     if (km.XU()) {
/*    */       QI();
/*    */     } else {
/*    */       this.lg.uh0(510, 100);
/*    */       mM();
/*    */       this.lg.mM();
/*    */     } 
/*    */     super.d40();
/*    */     if (km.XU()) {
/*    */       this.YH.mM();
/*    */       this.YH.QJ0(et.t9, -68, 0);
/*    */     } 
/*    */   } }


/* Location:              /Users/vnnsnnt/Documents/Codespace/JavaWorkspace/RedTrainer/src/main/java/org/trainer/client/PokeMMO.jar!/f/Ay.class
 * Java compiler version: 8 (52.0)
 * JD-Core Version:       1.1.3
 */