/* 1 */ package f;public final class b extends bB { public final fQ getDependencies(String paramString, RD0 paramRD0, wP paramwP) { if ((paramwP = paramwP) == null) paramwP = this.ML0;  this = null; try { BufferedReader bufferedReader; int i = ((LPt4)paramwP).nt; paramRD0.getClass();
/* 2 */       this(new InputStreamReader(paramRD0.Yc()), i);
/* 3 */       String str = (new BufferedReader()).readLine(); }
/*   */     catch (IOException iOException)
/* 5 */     { throw new JU(
/* 6 */           m0.tF0("Error reading ", paramString), this); }
/*   */      }
/*   */ 
/*   */   
/*   */   public LPt4 ML0;
/*   */   public Du n8;
/*   */   
/*   */   public b() {
/*   */     this();
/*   */     ax ax;
/*   */     this(this);
/*   */   }
/*   */   
/*   */   public b(Xt0 paramXt0) {
/*   */     super(paramXt0);
/*   */     LPt4 lPt4;
/*   */     Du du;
/*   */     this();
/*   */     this.ML0 = this;
/*   */     this();
/*   */     this.n8 = this;
/*   */   }
/*   */   
/*   */   public final Object oH(sz0 paramsz0, String paramString, RD0 paramRD0, wP paramwP) {
/*   */     // Byte code:
/*   */     //   0: aload_1
/*   */     //   1: dup
/*   */     //   2: dup2
/*   */     //   3: dup2
/*   */     //   4: aload #4
/*   */     //   6: checkcast f/LPt4
/*   */     //   9: pop
/*   */     //   10: monitorenter
/*   */     //   11: getfield r70 : Lf/f7;
/*   */     //   14: aload_2
/*   */     //   15: invokevirtual pd0 : (Ljava/lang/Object;)Ljava/lang/Object;
/*   */     //   18: checkcast f/fQ
/*   */     //   21: astore_2
/*   */     //   22: monitorexit
/*   */     //   23: aload_2
/*   */     //   24: invokevirtual first : ()Ljava/lang/Object;
/*   */     //   27: checkcast java/lang/String
/*   */     //   30: astore_2
/*   */     //   31: monitorenter
/*   */     //   32: monitorenter
/*   */     //   33: getfield g30 : Lf/f7;
/*   */     //   36: aload_2
/*   */     //   37: invokevirtual pd0 : (Ljava/lang/Object;)Ljava/lang/Object;
/*   */     //   40: checkcast java/lang/Class
/*   */     //   43: dup
/*   */     //   44: astore #4
/*   */     //   46: ifnull -> 325
/*   */     //   49: aload_1
/*   */     //   50: getfield MO : Lf/f7;
/*   */     //   53: aload #4
/*   */     //   55: invokevirtual pd0 : (Ljava/lang/Object;)Ljava/lang/Object;
/*   */     //   58: checkcast f/f7
/*   */     //   61: dup
/*   */     //   62: astore #4
/*   */     //   64: ifnull -> 325
/*   */     //   67: aload #4
/*   */     //   69: aload_2
/*   */     //   70: invokevirtual pd0 : (Ljava/lang/Object;)Ljava/lang/Object;
/*   */     //   73: checkcast f/UI
/*   */     //   76: dup
/*   */     //   77: astore #4
/*   */     //   79: ifnull -> 325
/*   */     //   82: aload_3
/*   */     //   83: aload #4
/*   */     //   85: getfield pE0 : Ljava/lang/Object;
/*   */     //   88: aload_1
/*   */     //   89: dup
/*   */     //   90: monitorexit
/*   */     //   91: monitorexit
/*   */     //   92: checkcast com/badlogic/gdx/graphics/Texture
/*   */     //   95: astore_1
/*   */     //   96: new f/pe0
/*   */     //   99: dup
/*   */     //   100: astore_2
/*   */     //   101: aload_1
/*   */     //   102: invokespecial <init> : (Lcom/badlogic/gdx/graphics/Texture;)V
/*   */     //   105: sipush #256
/*   */     //   108: istore_1
/*   */     //   109: invokevirtual getClass : ()Ljava/lang/Class;
/*   */     //   112: pop
/*   */     //   113: new java/io/BufferedReader
/*   */     //   116: dup
/*   */     //   117: astore #4
/*   */     //   119: new java/io/InputStreamReader
/*   */     //   122: dup
/*   */     //   123: aload_3
/*   */     //   124: invokevirtual Yc : ()Ljava/io/InputStream;
/*   */     //   127: invokespecial <init> : (Ljava/io/InputStream;)V
/*   */     //   130: iload_1
/*   */     //   131: invokespecial <init> : (Ljava/io/Reader;I)V
/*   */     //   134: aload #4
/*   */     //   136: invokevirtual readLine : ()Ljava/lang/String;
/*   */     //   139: dup
/*   */     //   140: astore_1
/*   */     //   141: ifnull -> 258
/*   */     //   144: aload_1
/*   */     //   145: ldc 's'
/*   */     //   147: invokevirtual startsWith : (Ljava/lang/String;)Z
/*   */     //   150: ifeq -> 134
/*   */     //   153: aload_1
/*   */     //   154: iconst_1
/*   */     //   155: invokevirtual substring : (I)Ljava/lang/String;
/*   */     //   158: invokevirtual trim : ()Ljava/lang/String;
/*   */     //   161: ldc ','
/*   */     //   163: invokevirtual split : (Ljava/lang/String;)[Ljava/lang/String;
/*   */     //   166: dup
/*   */     //   167: astore_1
/*   */     //   168: arraylength
/*   */     //   169: dup
/*   */     //   170: istore #5
/*   */     //   172: newarray float
/*   */     //   174: astore #6
/*   */     //   176: iconst_0
/*   */     //   177: istore #7
/*   */     //   179: iload #7
/*   */     //   181: iload #5
/*   */     //   183: if_icmpge -> 204
/*   */     //   186: aload #6
/*   */     //   188: iload #7
/*   */     //   190: aload_1
/*   */     //   191: iload #7
/*   */     //   193: aaload
/*   */     //   194: invokestatic parseFloat : (Ljava/lang/String;)F
/*   */     //   197: fastore
/*   */     //   198: iinc #7, 1
/*   */     //   201: goto -> 179
/*   */     //   204: new f/ws0
/*   */     //   207: dup
/*   */     //   208: aload #4
/*   */     //   210: swap
/*   */     //   211: aload_2
/*   */     //   212: aload #6
/*   */     //   214: aload_0
/*   */     //   215: getfield n8 : Lf/Du;
/*   */     //   218: aload #6
/*   */     //   220: invokevirtual C5 : ([F)Lf/Wk0;
/*   */     //   223: dup
/*   */     //   224: getfield AK0 : I
/*   */     //   227: dup
/*   */     //   228: istore_0
/*   */     //   229: newarray short
/*   */     //   231: astore_1
/*   */     //   232: getfield YJ0 : [S
/*   */     //   235: iconst_0
/*   */     //   236: aload_1
/*   */     //   237: iconst_0
/*   */     //   238: iload_0
/*   */     //   239: invokestatic arraycopy : (Ljava/lang/Object;ILjava/lang/Object;II)V
/*   */     //   242: aload_1
/*   */     //   243: invokespecial <init> : (Lf/pe0;[F[S)V
/*   */     //   246: invokestatic JC0 : (Ljava/io/Closeable;)V
/*   */     //   249: areturn
/*   */     //   250: astore_0
/*   */     //   251: goto -> 318
/*   */     //   254: astore_0
/*   */     //   255: goto -> 290
/*   */     //   258: aload #4
/*   */     //   260: invokestatic JC0 : (Ljava/io/Closeable;)V
/*   */     //   263: new f/JU
/*   */     //   266: dup
/*   */     //   267: new java/lang/StringBuilder
/*   */     //   270: dup
/*   */     //   271: invokespecial <init> : ()V
/*   */     //   274: ldc 'Polygon shape not found: '
/*   */     //   276: invokevirtual append : (Ljava/lang/String;)Ljava/lang/StringBuilder;
/*   */     //   279: aload_3
/*   */     //   280: invokevirtual append : (Ljava/lang/Object;)Ljava/lang/StringBuilder;
/*   */     //   283: invokevirtual toString : ()Ljava/lang/String;
/*   */     //   286: invokespecial <init> : (Ljava/lang/String;)V
/*   */     //   289: athrow
/*   */     //   290: new f/JU
/*   */     //   293: dup
/*   */     //   294: new java/lang/StringBuilder
/*   */     //   297: dup
/*   */     //   298: invokespecial <init> : ()V
/*   */     //   301: ldc 'Error reading polygon shape file: '
/*   */     //   303: invokevirtual append : (Ljava/lang/String;)Ljava/lang/StringBuilder;
/*   */     //   306: aload_3
/*   */     //   307: invokevirtual append : (Ljava/lang/Object;)Ljava/lang/StringBuilder;
/*   */     //   310: invokevirtual toString : ()Ljava/lang/String;
/*   */     //   313: aload_0
/*   */     //   314: invokespecial <init> : (Ljava/lang/String;Ljava/lang/Throwable;)V
/*   */     //   317: athrow
/*   */     //   318: aload_0
/*   */     //   319: aload #4
/*   */     //   321: invokestatic JC0 : (Ljava/io/Closeable;)V
/*   */     //   324: athrow
/*   */     //   325: new f/JU
/*   */     //   328: dup
/*   */     //   329: new java/lang/StringBuilder
/*   */     //   332: dup
/*   */     //   333: invokespecial <init> : ()V
/*   */     //   336: ldc 'Asset not loaded: '
/*   */     //   338: invokevirtual append : (Ljava/lang/String;)Ljava/lang/StringBuilder;
/*   */     //   341: aload_2
/*   */     //   342: invokevirtual append : (Ljava/lang/String;)Ljava/lang/StringBuilder;
/*   */     //   345: invokevirtual toString : ()Ljava/lang/String;
/*   */     //   348: invokespecial <init> : (Ljava/lang/String;)V
/*   */     //   351: athrow
/*   */     //   352: astore_0
/*   */     //   353: aload_0
/*   */     //   354: aload_1
/*   */     //   355: monitorexit
/*   */     //   356: athrow
/*   */     //   357: aload_1
/*   */     //   358: monitorexit
/*   */     //   359: athrow
/*   */     //   360: aload_1
/*   */     //   361: monitorexit
/*   */     //   362: athrow
/*   */     // Line number table:
/*   */     //   Java source line number -> byte code offset
/*   */     //   #1	-> 10
/*   */     //   #2	-> 11
/*   */     //   #3	-> 24
/*   */     //   #4	-> 32
/*   */     //   #5	-> 33
/*   */     //   #6	-> 92
/*   */     //   #7	-> 109
/*   */     //   #8	-> 113
/*   */     //   #9	-> 136
/*   */     //   #10	-> 224
/*   */     //   #11	-> 243
/*   */     //   #12	-> 325
/*   */     // Exception table:
/*   */     //   from	to	target	type
/*   */     //   11	21	360	finally
/*   */     //   32	33	357	finally
/*   */     //   33	43	352	finally
/*   */     //   49	61	352	finally
/*   */     //   67	76	352	finally
/*   */     //   82	88	352	finally
/*   */     //   88	91	357	finally
/*   */     //   134	139	254	java/io/IOException
/*   */     //   134	139	250	finally
/*   */     //   144	150	254	java/io/IOException
/*   */     //   144	150	250	finally
/*   */     //   153	166	254	java/io/IOException
/*   */     //   153	166	250	finally
/*   */     //   168	169	254	java/io/IOException
/*   */     //   168	169	250	finally
/*   */     //   172	174	254	java/io/IOException
/*   */     //   172	174	250	finally
/*   */     //   186	198	254	java/io/IOException
/*   */     //   186	198	250	finally
/*   */     //   204	207	254	java/io/IOException
/*   */     //   204	207	250	finally
/*   */     //   208	227	254	java/io/IOException
/*   */     //   208	227	250	finally
/*   */     //   229	231	254	java/io/IOException
/*   */     //   229	231	250	finally
/*   */     //   232	246	254	java/io/IOException
/*   */     //   232	246	250	finally
/*   */     //   290	318	250	finally
/*   */     //   325	352	352	finally
/*   */     //   353	357	357	finally
/*   */   } }


/* Location:              /Users/vnnsnnt/Documents/Codespace/JavaWorkspace/RedTrainer/src/main/java/org/trainer/client/PokeMMO.jar!/f/b.class
 * Java compiler version: 7 (51.0)
 * JD-Core Version:       1.1.3
 */