/*   */ package f;public final class bh extends YA0 { public static final e2 ci = new e2(100); public A am; public Te ys0; public of mo0; public W1 dX; public nJ0 v20; public Un dD0; public JA0 oL0; public Un v70; public Un md; public Un yW; public short Ag; public boolean pm; public lg0 fp; public p ur; public final fQ Sh; public final fQ zM; public int hr0; public int Wg0; public bh(A paramA, Te paramTe, boolean paramBoolean) { // Byte code:
/*   */     //   0: aload_0
/*   */     //   1: dup
/*   */     //   2: dup
/*   */     //   3: dup2
/*   */     //   4: invokespecial <init> : ()V
/*   */     //   7: new f/fQ
/*   */     //   10: dup
/*   */     //   11: astore #4
/*   */     //   13: invokespecial <init> : ()V
/*   */     //   16: aload #4
/*   */     //   18: putfield Sh : Lf/fQ;
/*   */     //   21: new f/fQ
/*   */     //   24: dup
/*   */     //   25: astore #4
/*   */     //   27: invokespecial <init> : ()V
/*   */     //   30: aload #4
/*   */     //   32: putfield zM : Lf/fQ;
/*   */     //   35: aload_1
/*   */     //   36: putfield am : Lf/A;
/*   */     //   39: aload_2
/*   */     //   40: putfield ys0 : Lf/Te;
/*   */     //   43: iconst_4
/*   */     //   44: dup
/*   */     //   45: istore #4
/*   */     //   47: anewarray java/lang/String
/*   */     //   50: astore #5
/*   */     //   52: iconst_0
/*   */     //   53: istore #6
/*   */     //   55: iload #6
/*   */     //   57: iload #4
/*   */     //   59: if_icmpge -> 81
/*   */     //   62: aload #5
/*   */     //   64: iload #6
/*   */     //   66: dup
/*   */     //   67: sipush #8050
/*   */     //   70: iadd
/*   */     //   71: invokestatic OH0 : (I)Ljava/lang/String;
/*   */     //   74: aastore
/*   */     //   75: iinc #6, 1
/*   */     //   78: goto -> 55
/*   */     //   81: iload_3
/*   */     //   82: aload_0
/*   */     //   83: dup
/*   */     //   84: dup2
/*   */     //   85: dup2
/*   */     //   86: new f/OZ
/*   */     //   89: dup
/*   */     //   90: astore #4
/*   */     //   92: aload #5
/*   */     //   94: invokespecial <init> : ([Ljava/lang/Object;)V
/*   */     //   97: new f/W1
/*   */     //   100: dup
/*   */     //   101: aload_0
/*   */     //   102: swap
/*   */     //   103: dup
/*   */     //   104: aload #4
/*   */     //   106: invokespecial <init> : (Lf/cQ;)V
/*   */     //   109: putfield dX : Lf/W1;
/*   */     //   112: iconst_0
/*   */     //   113: invokevirtual Z30 : (I)V
/*   */     //   116: getfield dX : Lf/W1;
/*   */     //   119: aload_0
/*   */     //   120: aload_1
/*   */     //   121: aload_2
/*   */     //   122: <illegal opcode> run : (Lf/bh;Lf/A;Lf/Te;)Ljava/lang/Runnable;
/*   */     //   127: invokevirtual D30 : (Ljava/lang/Runnable;)V
/*   */     //   130: new f/of
/*   */     //   133: dup
/*   */     //   134: aload_0
/*   */     //   135: swap
/*   */     //   136: dup
/*   */     //   137: invokespecial <init> : ()V
/*   */     //   140: putfield mo0 : Lf/of;
/*   */     //   143: invokevirtual LE : ()V
/*   */     //   146: getfield mo0 : Lf/of;
/*   */     //   149: aload_0
/*   */     //   150: aload_1
/*   */     //   151: aload_2
/*   */     //   152: <illegal opcode> SX : (Lf/bh;Lf/A;Lf/Te;)Lf/a70;
/*   */     //   157: invokevirtual JD0 : (Lf/a70;)V
/*   */     //   160: new f/Un
/*   */     //   163: dup
/*   */     //   164: astore #4
/*   */     //   166: aload_0
/*   */     //   167: aload_2
/*   */     //   168: aload_0
/*   */     //   169: aload #4
/*   */     //   171: dup
/*   */     //   172: sipush #8010
/*   */     //   175: invokestatic OH0 : (I)Ljava/lang/String;
/*   */     //   178: invokespecial <init> : (Ljava/lang/String;)V
/*   */     //   181: putfield v70 : Lf/Un;
/*   */     //   184: aload_1
/*   */     //   185: <illegal opcode> run : (Lf/bh;Lf/Te;Lf/A;)Ljava/lang/Runnable;
/*   */     //   190: invokevirtual tW : (Ljava/lang/Runnable;)V
/*   */     //   193: new f/Un
/*   */     //   196: dup
/*   */     //   197: aload_0
/*   */     //   198: swap
/*   */     //   199: dup
/*   */     //   200: ldc '↻'
/*   */     //   202: invokespecial <init> : (Ljava/lang/String;)V
/*   */     //   205: putfield md : Lf/Un;
/*   */     //   208: ldc 'button-symbol'
/*   */     //   210: invokevirtual Xu : (Ljava/lang/String;)V
/*   */     //   213: getfield md : Lf/Un;
/*   */     //   216: sipush #8035
/*   */     //   219: invokestatic OH0 : (I)Ljava/lang/String;
/*   */     //   222: invokevirtual Gq0 : (Ljava/lang/Object;)V
/*   */     //   225: getfield md : Lf/Un;
/*   */     //   228: bipush #100
/*   */     //   230: invokevirtual Pb0 : (I)V
/*   */     //   233: getfield md : Lf/Un;
/*   */     //   236: new f/Mz
/*   */     //   239: dup
/*   */     //   240: aload_1
/*   */     //   241: aload_2
/*   */     //   242: invokespecial <init> : (Lf/A;Lf/Te;)V
/*   */     //   245: invokevirtual tW : (Ljava/lang/Runnable;)V
/*   */     //   248: new f/Un
/*   */     //   251: dup
/*   */     //   252: dup
/*   */     //   253: astore #4
/*   */     //   255: sipush #8042
/*   */     //   258: invokestatic OH0 : (I)Ljava/lang/String;
/*   */     //   261: invokespecial <init> : (Ljava/lang/String;)V
/*   */     //   264: putfield yW : Lf/Un;
/*   */     //   267: ifne -> 276
/*   */     //   270: aload #4
/*   */     //   272: iconst_0
/*   */     //   273: invokevirtual sk0 : (Z)V
/*   */     //   276: aload_2
/*   */     //   277: aload_0
/*   */     //   278: dup
/*   */     //   279: getfield yW : Lf/Un;
/*   */     //   282: iload_3
/*   */     //   283: aload_1
/*   */     //   284: <illegal opcode> run : (ZLf/A;)Ljava/lang/Runnable;
/*   */     //   289: invokevirtual tW : (Ljava/lang/Runnable;)V
/*   */     //   292: new f/p
/*   */     //   295: dup
/*   */     //   296: aload_0
/*   */     //   297: invokespecial <init> : (Lf/bh;)V
/*   */     //   300: putfield ur : Lf/p;
/*   */     //   303: getstatic f/Te.QK0 : Lf/Te;
/*   */     //   306: if_acmpeq -> 345
/*   */     //   309: aload_2
/*   */     //   310: getstatic f/Te.Qu : Lf/Te;
/*   */     //   313: if_acmpne -> 319
/*   */     //   316: goto -> 345
/*   */     //   319: aload_2
/*   */     //   320: getstatic f/Te.EE : Lf/Te;
/*   */     //   323: if_acmpne -> 440
/*   */     //   326: aload_0
/*   */     //   327: new f/kp0
/*   */     //   330: dup
/*   */     //   331: astore_3
/*   */     //   332: aload_0
/*   */     //   333: aload_1
/*   */     //   334: aload_2
/*   */     //   335: invokespecial <init> : (Lf/bh;Lf/A;Lf/Te;)V
/*   */     //   338: aload_3
/*   */     //   339: putfield oL0 : Lf/JA0;
/*   */     //   342: goto -> 440
/*   */     //   345: aload_0
/*   */     //   346: dup
/*   */     //   347: dup2
/*   */     //   348: dup2
/*   */     //   349: new f/Un
/*   */     //   352: dup
/*   */     //   353: aload_0
/*   */     //   354: swap
/*   */     //   355: dup
/*   */     //   356: ldc '☒'
/*   */     //   358: invokespecial <init> : (Ljava/lang/String;)V
/*   */     //   361: putfield dD0 : Lf/Un;
/*   */     //   364: ldc 'button-symbol'
/*   */     //   366: invokevirtual Xu : (Ljava/lang/String;)V
/*   */     //   369: getfield dD0 : Lf/Un;
/*   */     //   372: sipush #8036
/*   */     //   375: invokestatic OH0 : (I)Ljava/lang/String;
/*   */     //   378: invokevirtual Gq0 : (Ljava/lang/Object;)V
/*   */     //   381: getfield dD0 : Lf/Un;
/*   */     //   384: bipush #100
/*   */     //   386: invokevirtual Pb0 : (I)V
/*   */     //   389: getfield dD0 : Lf/Un;
/*   */     //   392: iconst_1
/*   */     //   393: invokevirtual sk0 : (Z)V
/*   */     //   396: getfield dD0 : Lf/Un;
/*   */     //   399: aload_0
/*   */     //   400: aload_1
/*   */     //   401: aload_2
/*   */     //   402: <illegal opcode> run : (Lf/bh;Lf/A;Lf/Te;)Ljava/lang/Runnable;
/*   */     //   407: invokevirtual tW : (Ljava/lang/Runnable;)V
/*   */     //   410: new f/l4
/*   */     //   413: dup
/*   */     //   414: aload_0
/*   */     //   415: aload_1
/*   */     //   416: aload_2
/*   */     //   417: invokespecial <init> : (Lf/bh;Lf/A;Lf/Te;)V
/*   */     //   420: putfield oL0 : Lf/JA0;
/*   */     //   423: invokevirtual ma0 : ()Lf/fQ;
/*   */     //   426: getfield Z8 : I
/*   */     //   429: ifne -> 440
/*   */     //   432: aload_0
/*   */     //   433: getfield dD0 : Lf/Un;
/*   */     //   436: iconst_0
/*   */     //   437: invokevirtual sk0 : (Z)V
/*   */     //   440: aload_0
/*   */     //   441: dup
/*   */     //   442: aload_2
/*   */     //   443: invokevirtual Xy : (Lf/Te;)V
/*   */     //   446: getfield ys0 : Lf/Te;
/*   */     //   449: getstatic f/Te.EE : Lf/Te;
/*   */     //   452: if_acmpne -> 471
/*   */     //   455: aload_0
/*   */     //   456: dup
/*   */     //   457: getfield mo0 : Lf/of;
/*   */     //   460: iconst_0
/*   */     //   461: invokevirtual wI0 : (Z)V
/*   */     //   464: getfield dX : Lf/W1;
/*   */     //   467: iconst_0
/*   */     //   468: invokevirtual wI0 : (Z)V
/* 1 */     //   471: return } public static void zy(boolean paramBoolean, A paramA) { if (!paramBoolean) { km.u4.Pq(Ml0.OH0(8029)); return; }  this(); o0 o0; fv0[] arrayOfFv0; int i; byte b; for (i = (arrayOfFv0 = paramA.uC0).length, b = 0; b < i; ) { fv0 fv0; if ((fv0 = arrayOfFv0[b]) != null && (fv0.kF0 == 1 || fv0
/* 2 */         .CoM9 > 0)) o0
/*   */           
/* 4 */           .oU(fv0.y60);  b++; }
/* 5 */      if (!((o0.mG0 == 0) ? 1 : 0))
/* 6 */     { R8 r8 = km.u4; int[] arrayOfInt = o0.zt(); r8
/* 7 */         .e20
/* 8 */         .W3(new Pt(arrayOfInt)); }  } private void YR(Te paramTe, A paramA) { nJ0 nJ01; if (!this.pm) { this.pm = true; if (paramTe == Te.QK0) { Yw(paramTe); } else if (paramTe == Te.Qu) { RU(paramTe); }  this.Dv0.kp0(); (nJ01 = this.Dv0.S7(this.fp)).sV(); if (km.XU()) { nJ01.sg(160.0F); nJ01.fa0(0.0F); }  VA0.c90(this.fp.lPt3(3)); } else { this.pm = false; paramA.mg((Te)nJ01); }  } public final void x10(int paramInt1, int paramInt2) { int i = 0; ArrayList<?> arrayList; Iterator<?> iterator = (arrayList = ((YA0)this.v20.ZX).Dv0.XC).iterator(); do { i = ((nJ0)iterator.next()).ss.intValue() + i; } while (iterator.hasNext() && !((nJ0)iterator.next()).Sb0); if (i == 0) return;  this.hr0 = nx0.Uw0(paramInt1, 0, arrayList.size() / i - 1); this.Wg0 = nx0.Uw0(paramInt2, 0, i - 1); wD0(); } private void c10(A paramA, Te paramTe, int paramInt) { // Byte code:
/*   */     //   0: aload_1
/*   */     //   1: aload_0
/*   */     //   2: iconst_0
/*   */     //   3: putfield Ag : S
/*   */     //   6: ldc2_w 250
/*   */     //   9: lstore #4
/*   */     //   11: getfield dL : Lf/oo;
/*   */     //   14: dup
/*   */     //   15: astore_3
/*   */     //   16: ifnull -> 76
/*   */     //   19: aload_3
/*   */     //   20: dup
/*   */     //   21: monitorenter
/*   */     //   22: getfield lu0 : J
/*   */     //   25: aload_3
/*   */     //   26: monitorexit
/*   */     //   27: lconst_0
/*   */     //   28: lcmp
/*   */     //   29: ifle -> 76
/*   */     //   32: aload_1
/*   */     //   33: dup
/*   */     //   34: dup
/*   */     //   35: getfield dL : Lf/oo;
/*   */     //   38: dup
/*   */     //   39: dup
/*   */     //   40: astore_3
/*   */     //   41: monitorenter
/*   */     //   42: getfield lu0 : J
/*   */     //   45: aload_3
/*   */     //   46: monitorexit
/*   */     //   47: invokestatic nanoTime : ()J
/*   */     //   50: ldc2_w 1000000
/*   */     //   53: ldiv
/*   */     //   54: lsub
/*   */     //   55: lstore #4
/*   */     //   57: getfield dL : Lf/oo;
/*   */     //   60: invokevirtual uw0 : ()V
/*   */     //   63: aconst_null
/*   */     //   64: putfield dL : Lf/oo;
/*   */     //   67: goto -> 76
/*   */     //   70: aload_3
/*   */     //   71: monitorexit
/*   */     //   72: athrow
/*   */     //   73: aload_3
/*   */     //   74: monitorexit
/*   */     //   75: athrow
/*   */     //   76: aload_0
/*   */     //   77: aload_1
/*   */     //   78: lload #4
/*   */     //   80: aload_1
/*   */     //   81: aload_2
/*   */     //   82: invokevirtual bg0 : (Lf/Te;)V
/*   */     //   85: new f/T00
/*   */     //   88: dup
/*   */     //   89: astore_0
/*   */     //   90: aload_1
/*   */     //   91: aload_2
/*   */     //   92: invokespecial <init> : (Lf/A;Lf/Te;)V
/*   */     //   95: l2f
/*   */     //   96: ldc_w 1000.0
/*   */     //   99: fdiv
/*   */     //   100: fstore_1
/*   */     //   101: invokestatic k6 : ()Lf/HC;
/*   */     //   104: aload_0
/*   */     //   105: fload_1
/*   */     //   106: invokevirtual S : (Lf/oo;F)Lf/oo;
/*   */     //   109: putfield dL : Lf/oo;
/*   */     //   112: getfield mo0 : Lf/of;
/*   */     //   115: getfield F2 : Lf/ak0;
/*   */     //   118: invokevirtual toString : ()Ljava/lang/String;
/*   */     //   121: pop
/*   */     //   122: return
/*   */     // Line number table:
/*   */     //   Java source line number -> byte code offset
/*   */     //   #1	-> 11
/*   */     //   #2	-> 21
/*   */     //   #3	-> 22
/*   */     //   #4	-> 35
/*   */     //   #5	-> 42
/*   */     //   #6	-> 47
/*   */     //   #7	-> 101
/*   */     //   #8	-> 109
/*   */     //   #9	-> 112
/*   */     //   #10	-> 115
/*   */     //   #11	-> 118
/*   */     // Exception table:
/*   */     //   from	to	target	type
/*   */     //   22	25	73	finally
/*   */     //   42	45	70	finally } public final void Xy(Te paramTe) { // Byte code:
/*   */     //   0: aload_0
/*   */     //   1: dup
/*   */     //   2: dup2
/*   */     //   3: getfield Dv0 : Lf/SA;
/*   */     //   6: invokevirtual kp0 : ()V
/*   */     //   9: getfield ur : Lf/p;
/*   */     //   12: getfield Dv0 : Lf/SA;
/*   */     //   15: invokevirtual kp0 : ()V
/*   */     //   18: getfield Dv0 : Lf/SA;
/*   */     //   21: getfield RT : Lf/nJ0;
/*   */     //   24: fconst_2
/*   */     //   25: invokevirtual sg : (F)Lf/nJ0;
/*   */     //   28: pop
/*   */     //   29: getfield ur : Lf/p;
/*   */     //   32: getfield Dv0 : Lf/SA;
/*   */     //   35: getfield RT : Lf/nJ0;
/*   */     //   38: fconst_2
/*   */     //   39: invokevirtual sg : (F)Lf/nJ0;
/*   */     //   42: pop
/*   */     //   43: invokestatic Nr : ()Z
/*   */     //   46: ifeq -> 60
/*   */     //   49: aload_0
/*   */     //   50: getfield Dv0 : Lf/SA;
/*   */     //   53: ldc_w 3.0
/*   */     //   56: invokevirtual F : (F)Lf/ZP;
/*   */     //   59: pop
/*   */     //   60: aload_1
/*   */     //   61: getstatic f/Te.QK0 : Lf/Te;
/*   */     //   64: if_acmpeq -> 147
/*   */     //   67: aload_1
/*   */     //   68: getstatic f/Te.Qu : Lf/Te;
/*   */     //   71: if_acmpne -> 77
/*   */     //   74: goto -> 147
/*   */     //   77: aload_1
/*   */     //   78: getstatic f/Te.EE : Lf/Te;
/*   */     //   81: if_acmpne -> 277
/*   */     //   84: aload_0
/*   */     //   85: dup
/*   */     //   86: dup
/*   */     //   87: getfield ur : Lf/p;
/*   */     //   90: getfield Dv0 : Lf/SA;
/*   */     //   93: new f/JG0
/*   */     //   96: dup
/*   */     //   97: invokespecial <init> : ()V
/*   */     //   100: invokevirtual S7 : (Ljava/lang/Object;)Lf/nJ0;
/*   */     //   103: dup
/*   */     //   104: dup
/*   */     //   105: astore_1
/*   */     //   106: invokevirtual Kw : ()Lf/nJ0;
/*   */     //   109: pop
/*   */     //   110: invokevirtual x70 : ()Lf/nJ0;
/*   */     //   113: pop
/*   */     //   114: getfield yW : Lf/Un;
/*   */     //   117: aload_1
/*   */     //   118: getfield Ox : Lf/ZP;
/*   */     //   121: swap
/*   */     //   122: invokevirtual S7 : (Ljava/lang/Object;)Lf/nJ0;
/*   */     //   125: astore_1
/*   */     //   126: getfield md : Lf/Un;
/*   */     //   129: aload_1
/*   */     //   130: getfield Ox : Lf/ZP;
/*   */     //   133: swap
/*   */     //   134: invokevirtual S7 : (Ljava/lang/Object;)Lf/nJ0;
/*   */     //   137: astore_1
/*   */     //   138: invokestatic XU : ()Z
/*   */     //   141: ifeq -> 263
/*   */     //   144: goto -> 256
/*   */     //   147: aload_0
/*   */     //   148: dup
/*   */     //   149: dup2
/*   */     //   150: dup2
/*   */     //   151: getfield ur : Lf/p;
/*   */     //   154: getfield Dv0 : Lf/SA;
/*   */     //   157: new f/JG0
/*   */     //   160: dup
/*   */     //   161: invokespecial <init> : ()V
/*   */     //   164: invokevirtual S7 : (Ljava/lang/Object;)Lf/nJ0;
/*   */     //   167: dup
/*   */     //   168: dup
/*   */     //   169: astore_1
/*   */     //   170: invokevirtual Kw : ()Lf/nJ0;
/*   */     //   173: pop
/*   */     //   174: invokevirtual x70 : ()Lf/nJ0;
/*   */     //   177: pop
/*   */     //   178: getfield mo0 : Lf/of;
/*   */     //   181: aload_1
/*   */     //   182: getfield Ox : Lf/ZP;
/*   */     //   185: swap
/*   */     //   186: invokevirtual S7 : (Ljava/lang/Object;)Lf/nJ0;
/*   */     //   189: ldc_w 5.0
/*   */     //   192: invokevirtual sg : (F)Lf/nJ0;
/*   */     //   195: invokevirtual R7 : ()Lf/nJ0;
/*   */     //   198: astore_1
/*   */     //   199: getfield v70 : Lf/Un;
/*   */     //   202: aload_1
/*   */     //   203: getfield Ox : Lf/ZP;
/*   */     //   206: swap
/*   */     //   207: invokevirtual S7 : (Ljava/lang/Object;)Lf/nJ0;
/*   */     //   210: astore_1
/*   */     //   211: getfield dD0 : Lf/Un;
/*   */     //   214: aload_1
/*   */     //   215: getfield Ox : Lf/ZP;
/*   */     //   218: swap
/*   */     //   219: invokevirtual S7 : (Ljava/lang/Object;)Lf/nJ0;
/*   */     //   222: astore_1
/*   */     //   223: getfield md : Lf/Un;
/*   */     //   226: aload_1
/*   */     //   227: getfield Ox : Lf/ZP;
/*   */     //   230: swap
/*   */     //   231: invokevirtual S7 : (Ljava/lang/Object;)Lf/nJ0;
/*   */     //   234: astore_1
/*   */     //   235: getfield dX : Lf/W1;
/*   */     //   238: aload_1
/*   */     //   239: getfield Ox : Lf/ZP;
/*   */     //   242: swap
/*   */     //   243: invokevirtual S7 : (Ljava/lang/Object;)Lf/nJ0;
/*   */     //   246: invokevirtual kp0 : ()Lf/nJ0;
/*   */     //   249: astore_1
/*   */     //   250: invokestatic XU : ()Z
/*   */     //   253: ifeq -> 263
/*   */     //   256: ldc_w 60.0
/*   */     //   259: fstore_2
/*   */     //   260: goto -> 265
/*   */     //   263: fconst_0
/*   */     //   264: fstore_2
/*   */     //   265: aload_1
/*   */     //   266: fload_2
/*   */     //   267: invokevirtual sg : (F)Lf/nJ0;
/*   */     //   270: getfield Ox : Lf/ZP;
/*   */     //   273: invokevirtual wP : ()Lf/nJ0;
/*   */     //   276: pop
/*   */     //   277: aload_0
/*   */     //   278: dup
/*   */     //   279: getfield Dv0 : Lf/SA;
/*   */     //   282: aload_0
/*   */     //   283: getfield ur : Lf/p;
/*   */     //   286: invokevirtual S7 : (Ljava/lang/Object;)Lf/nJ0;
/*   */     //   289: dup
/*   */     //   290: dup
/*   */     //   291: invokevirtual Kw : ()Lf/nJ0;
/*   */     //   294: pop
/*   */     //   295: invokevirtual x70 : ()Lf/nJ0;
/*   */     //   298: pop
/*   */     //   299: getfield Ox : Lf/ZP;
/*   */     //   302: invokevirtual wP : ()Lf/nJ0;
/*   */     //   305: pop
/*   */     //   306: getfield Dv0 : Lf/SA;
/*   */     //   309: new f/JG0
/*   */     //   312: dup
/*   */     //   313: invokespecial <init> : ()V
/*   */     //   316: invokevirtual S7 : (Ljava/lang/Object;)Lf/nJ0;
/*   */     //   319: dup
/*   */     //   320: aload_0
/*   */     //   321: swap
/*   */     //   322: putfield v20 : Lf/nJ0;
/*   */     //   325: invokevirtual R7 : ()Lf/nJ0;
/*   */     //   328: dup
/*   */     //   329: dup
/*   */     //   330: invokevirtual kp0 : ()Lf/nJ0;
/*   */     //   333: pop
/*   */     //   334: invokevirtual i40 : ()Lf/nJ0;
/*   */     //   337: pop
/*   */     //   338: invokevirtual Kw : ()Lf/nJ0;
/*   */     //   341: getfield Ox : Lf/ZP;
/*   */     //   344: invokevirtual wP : ()Lf/nJ0;
/*   */     //   347: pop
/*   */     //   348: invokestatic Nr : ()Z
/*   */     //   351: ifeq -> 365
/*   */     //   354: aload_0
/*   */     //   355: getfield v20 : Lf/nJ0;
/*   */     //   358: ldc_w 10.0
/*   */     //   361: invokevirtual fa0 : (F)Lf/nJ0;
/*   */     //   364: pop
/*   */     //   365: aload_0
/*   */     //   366: getfield Dv0 : Lf/SA;
/*   */     //   369: aload_0
/*   */     //   370: getfield oL0 : Lf/JA0;
/*   */     //   373: invokevirtual S7 : (Ljava/lang/Object;)Lf/nJ0;
/*   */     //   376: invokevirtual R7 : ()Lf/nJ0;
/*   */     //   379: aload_0
/*   */     //   380: getfield Dv0 : Lf/SA;
/*   */     //   383: getfield Nb0 : I
/*   */     //   386: invokestatic valueOf : (I)Ljava/lang/Integer;
/*   */     //   389: putfield ss : Ljava/lang/Integer;
/*   */     //   392: return
/*   */     // Line number table:
/*   */     //   Java source line number -> byte code offset
/*   */     //   #1	-> 21
/*   */     //   #2	-> 25
/*   */     //   #3	-> 32
/*   */     //   #4	-> 35
/*   */     //   #5	-> 39
/*   */     //   #6	-> 106
/*   */     //   #7	-> 114
/*   */     //   #8	-> 118
/*   */     //   #9	-> 126
/*   */     //   #10	-> 130
/*   */     //   #11	-> 138
/*   */     //   #12	-> 170
/*   */     //   #13	-> 178
/*   */     //   #14	-> 182
/*   */     //   #15	-> 192
/*   */     //   #16	-> 203
/*   */     //   #17	-> 211
/*   */     //   #18	-> 215
/*   */     //   #19	-> 223
/*   */     //   #20	-> 227
/*   */     //   #21	-> 235
/*   */     //   #22	-> 239
/*   */     //   #23	-> 246
/*   */     //   #24	-> 270
/*   */     //   #25	-> 279
/*   */     //   #26	-> 291
/*   */     //   #27	-> 299
/*   */     //   #28	-> 306
/*   */     //   #29	-> 330
/*   */     //   #30	-> 338
/*   */     //   #31	-> 341
/*   */     //   #32	-> 348
/*   */     //   #33	-> 383
/*   */     //   #34	-> 386
/* 8 */     //   #35	-> 389 } public final void wD0() { byte b = -1; byte b1 = 0; for (nJ0 nJ01 : ((YA0)this.v20.ZX).Dv0.XC) { if (b == this.hr0) { if (b1 == this.Wg0) { VA0.c90((JG0)nJ01.ZX); return; }  b1++; }  if (nJ01.Sb0) b++;  }  x10(0, 0); }
/*   */ 
/*   */   
/*   */   public final byte CG0() {
/*   */     return (byte)this.dX.Wa0.go;
/*   */   }
/*   */   
/*   */   public final fQ ma0() {
/*   */     return (this.ys0 == Te.Qu) ? this.Sh : this.zM;
/*   */   }
/*   */   
/*   */   public final void VI0() {
/*   */     this.pm = false;
/*   */     Un un;
/*   */     if ((un = this.dD0) != null) {
/*   */       boolean bool;
/*   */       if ((ma0()).Z8 > 0) {
/*   */         bool = true;
/*   */       } else {
/*   */         bool = false;
/*   */       } 
/*   */       un.sk0(bool);
/*   */     } 
/*   */     Xy(this.ys0);
/*   */   }
/*   */   
/*   */   public final void Yw(Te paramTe) {
/*   */     if (this.fp != null)
/*   */       return; 
/*   */     Runnable runnable1 = () -> {
/*   */         VI0();
/*   */         this.fp = null;
/*   */         ma0().clear();
/*   */         this.am.mg(paramTe);
/*   */       };
/*   */     Runnable runnable2 = () -> {
/*   */         VI0();
/*   */         this.Ag = 0;
/*   */         this.am.mg(paramTe);
/*   */       };
/*   */     this.fp = T80.N2(ma0(), true, this, runnable2);
/*   */   }
/*   */   
/*   */   public final void RU(Te paramTe) {
/*   */     if (this.fp != null)
/*   */       return; 
/*   */     Runnable runnable = () -> {
/*   */         VI0();
/*   */         this.fp = null;
/*   */         ma0().clear();
/*   */         this.am.mg(paramTe);
/*   */       };
/*   */     this.fp = T80.dp0(ma0(), this, () -> {
/*   */           VI0();
/*   */           this.Ag = 0;
/*   */           this.am.mg(paramTe);
/*   */         });
/*   */   }
/*   */   
/*   */   public final void d40() {
/*   */     super.d40();
/*   */     if (km.XU()) {
/*   */       QI();
/*   */       this.v20.sg(this.am.sr.xQ.xY);
/*   */     } 
/*   */   } }


/* Location:              /Users/vnnsnnt/Documents/Codespace/JavaWorkspace/RedTrainer/src/main/java/org/trainer/client/PokeMMO.jar!/f/bh.class
 * Java compiler version: 8 (52.0)
 * JD-Core Version:       1.1.3
 */