/* 1 */ package f;public final class bn extends t40 { public final t40 hn(int paramInt1, int paramInt2, int paramInt3) { if (--paramInt3 == 0) { if ((paramInt3 = xn(paramInt1, paramInt2, this.sX)) != this.sX) { t40 t401 = this.B60[paramInt3]; if (Zl || t401.getClass() != bn.class)
/* 2 */         { if ((paramInt1 = t401.O20 - paramInt1) == 0)
/* 3 */             paramInt1 = t401.GP - paramInt2;  if (paramInt1 == 0) { this
/* 4 */               .sX = paramInt1 = this.sX - 1; paramInt1 = paramInt3 + 1; paramInt2 = paramInt1 - paramInt3; System.arraycopy(this.B60, paramInt1, this.B60, paramInt3, paramInt2); this.B60[paramInt1 = this.sX] = null; if (paramInt3 == paramInt1 && paramInt1 > 0)
/* 5 */               xk0();  return t401; }  } else { throw new AssertionError(); }  }  return null; }
/* 6 */      int i = xn(paramInt1, paramInt2, this.sX - 1); if (Zl || i < this.sX) { t40 t401; bn bn1; if ((t401 = (bn1 = (bn)this.B60[i]).hn(paramInt1, paramInt2, paramInt3)) != null) { if (bn1.sX == 0) { AH(i); } else if (bn1.NS() && (
/* 7 */           paramInt2 = this.sX) != 0 && paramInt2 != 1) { if (paramInt2 != 2) { if (i + 1 == paramInt2) { Ex(i - 1); } else if (i == 0) { Ex(1); } else { Ex(i); }  } else { zH(); }  }
/* 8 */          xk0(); }  return t401; }
/*   */     
/*   */     throw new AssertionError(); }
/*   */ 
/*   */   
/*   */   public final t40[] B60;
/*   */   public int sX;
/*   */   public bn ww;
/*   */   public bn nt;
/*   */   
/*   */   public bn(int paramInt) {
/*   */     this.B60 = new t40[paramInt];
/*   */   }
/*   */   
/*   */   public final boolean zB0(int paramInt, tH0 paramtH0) {
/*   */     // Byte code:
/*   */     //   0: iload_1
/*   */     //   1: iconst_m1
/*   */     //   2: iadd
/*   */     //   3: dup
/*   */     //   4: istore_1
/*   */     //   5: ifne -> 233
/*   */     //   8: aload_0
/*   */     //   9: dup
/*   */     //   10: aload_2
/*   */     //   11: dup
/*   */     //   12: getfield O20 : I
/*   */     //   15: istore_1
/*   */     //   16: getfield GP : I
/*   */     //   19: istore_3
/*   */     //   20: getfield sX : I
/*   */     //   23: istore #4
/*   */     //   25: iload_1
/*   */     //   26: iload_3
/*   */     //   27: iload #4
/*   */     //   29: invokevirtual xn : (III)I
/*   */     //   32: dup
/*   */     //   33: istore_1
/*   */     //   34: aload_0
/*   */     //   35: getfield sX : I
/*   */     //   38: if_icmpge -> 148
/*   */     //   41: aload_0
/*   */     //   42: getfield B60 : [Lf/t40;
/*   */     //   45: iload_1
/*   */     //   46: aaload
/*   */     //   47: astore_3
/*   */     //   48: getstatic f/bn.Zl : Z
/*   */     //   51: dup
/*   */     //   52: istore #4
/*   */     //   54: ifne -> 77
/*   */     //   57: aload_3
/*   */     //   58: invokevirtual getClass : ()Ljava/lang/Class;
/*   */     //   61: ldc f/bn
/*   */     //   63: if_acmpeq -> 69
/*   */     //   66: goto -> 77
/*   */     //   69: new java/lang/AssertionError
/*   */     //   72: dup
/*   */     //   73: invokespecial <init> : ()V
/*   */     //   76: athrow
/*   */     //   77: aload_3
/*   */     //   78: aload_2
/*   */     //   79: dup
/*   */     //   80: getfield O20 : I
/*   */     //   83: istore #5
/*   */     //   85: getfield GP : I
/*   */     //   88: istore #6
/*   */     //   90: getfield O20 : I
/*   */     //   93: iload #5
/*   */     //   95: isub
/*   */     //   96: dup
/*   */     //   97: istore #5
/*   */     //   99: ifne -> 111
/*   */     //   102: aload_3
/*   */     //   103: getfield GP : I
/*   */     //   106: iload #6
/*   */     //   108: isub
/*   */     //   109: istore #5
/*   */     //   111: iload #5
/*   */     //   113: ifne -> 127
/*   */     //   116: aload_0
/*   */     //   117: getfield B60 : [Lf/t40;
/*   */     //   120: iload_1
/*   */     //   121: aload_2
/*   */     //   122: aastore
/*   */     //   123: iconst_1
/*   */     //   124: goto -> 232
/*   */     //   127: iload #4
/*   */     //   129: ifne -> 148
/*   */     //   132: iload #5
/*   */     //   134: ifle -> 140
/*   */     //   137: goto -> 148
/*   */     //   140: new java/lang/AssertionError
/*   */     //   143: dup
/*   */     //   144: invokespecial <init> : ()V
/*   */     //   147: athrow
/*   */     //   148: aload_0
/*   */     //   149: getfield sX : I
/*   */     //   152: dup
/*   */     //   153: istore_3
/*   */     //   154: aload_0
/*   */     //   155: getfield B60 : [Lf/t40;
/*   */     //   158: dup
/*   */     //   159: astore #4
/*   */     //   161: arraylength
/*   */     //   162: if_icmpne -> 171
/*   */     //   165: iconst_1
/*   */     //   166: istore #5
/*   */     //   168: goto -> 174
/*   */     //   171: iconst_0
/*   */     //   172: istore #5
/*   */     //   174: iload #5
/*   */     //   176: ifeq -> 183
/*   */     //   179: iconst_0
/*   */     //   180: goto -> 232
/*   */     //   183: iload_1
/*   */     //   184: aload_0
/*   */     //   185: dup
/*   */     //   186: dup
/*   */     //   187: aload #4
/*   */     //   189: iload_1
/*   */     //   190: iload_3
/*   */     //   191: iload_1
/*   */     //   192: dup
/*   */     //   193: iconst_1
/*   */     //   194: iadd
/*   */     //   195: istore_3
/*   */     //   196: isub
/*   */     //   197: istore #5
/*   */     //   199: aload #4
/*   */     //   201: iload_3
/*   */     //   202: iload #5
/*   */     //   204: invokestatic arraycopy : (Ljava/lang/Object;ILjava/lang/Object;II)V
/*   */     //   207: getfield B60 : [Lf/t40;
/*   */     //   210: iload_1
/*   */     //   211: aload_2
/*   */     //   212: aastore
/*   */     //   213: getfield sX : I
/*   */     //   216: dup
/*   */     //   217: istore_1
/*   */     //   218: iconst_1
/*   */     //   219: iadd
/*   */     //   220: putfield sX : I
/*   */     //   223: iload_1
/*   */     //   224: if_icmpne -> 231
/*   */     //   227: aload_0
/*   */     //   228: invokevirtual xk0 : ()V
/*   */     //   231: iconst_1
/*   */     //   232: ireturn
/*   */     //   233: aload_0
/*   */     //   234: aload_2
/*   */     //   235: dup
/*   */     //   236: getfield O20 : I
/*   */     //   239: istore_3
/*   */     //   240: getfield GP : I
/*   */     //   243: istore #4
/*   */     //   245: iload_3
/*   */     //   246: aload_0
/*   */     //   247: getfield sX : I
/*   */     //   250: iconst_1
/*   */     //   251: isub
/*   */     //   252: iload #4
/*   */     //   254: swap
/*   */     //   255: invokevirtual xn : (III)I
/*   */     //   258: istore_3
/*   */     //   259: getstatic f/bn.Zl : Z
/*   */     //   262: ifne -> 284
/*   */     //   265: iload_3
/*   */     //   266: aload_0
/*   */     //   267: getfield sX : I
/*   */     //   270: if_icmpge -> 276
/*   */     //   273: goto -> 284
/*   */     //   276: new java/lang/AssertionError
/*   */     //   279: dup
/*   */     //   280: invokespecial <init> : ()V
/*   */     //   283: athrow
/*   */     //   284: aload_0
/*   */     //   285: getfield B60 : [Lf/t40;
/*   */     //   288: iload_3
/*   */     //   289: aaload
/*   */     //   290: checkcast f/bn
/*   */     //   293: dup
/*   */     //   294: astore #4
/*   */     //   296: iload_1
/*   */     //   297: aload_2
/*   */     //   298: invokevirtual zB0 : (ILf/tH0;)Z
/*   */     //   301: ifne -> 522
/*   */     //   304: aload_0
/*   */     //   305: getfield sX : I
/*   */     //   308: aload_0
/*   */     //   309: getfield B60 : [Lf/t40;
/*   */     //   312: arraylength
/*   */     //   313: if_icmpne -> 322
/*   */     //   316: iconst_1
/*   */     //   317: istore #5
/*   */     //   319: goto -> 325
/*   */     //   322: iconst_0
/*   */     //   323: istore #5
/*   */     //   325: iload #5
/*   */     //   327: ifeq -> 332
/*   */     //   330: iconst_0
/*   */     //   331: ireturn
/*   */     //   332: new f/bn
/*   */     //   335: dup
/*   */     //   336: astore #5
/*   */     //   338: aload #4
/*   */     //   340: aload #5
/*   */     //   342: aload #4
/*   */     //   344: dup
/*   */     //   345: aload #5
/*   */     //   347: aload #4
/*   */     //   349: aload #5
/*   */     //   351: aload #4
/*   */     //   353: aload #5
/*   */     //   355: dup
/*   */     //   356: aload #4
/*   */     //   358: aload #5
/*   */     //   360: aload #4
/*   */     //   362: getfield B60 : [Lf/t40;
/*   */     //   365: arraylength
/*   */     //   366: invokespecial <init> : (I)V
/*   */     //   369: getfield sX : I
/*   */     //   372: dup
/*   */     //   373: iconst_2
/*   */     //   374: idiv
/*   */     //   375: dup
/*   */     //   376: istore #6
/*   */     //   378: isub
/*   */     //   379: dup
/*   */     //   380: istore #7
/*   */     //   382: aload #4
/*   */     //   384: dup
/*   */     //   385: getfield B60 : [Lf/t40;
/*   */     //   388: iload #6
/*   */     //   390: aload #5
/*   */     //   392: getfield B60 : [Lf/t40;
/*   */     //   395: iconst_0
/*   */     //   396: iload #7
/*   */     //   398: invokestatic arraycopy : (Ljava/lang/Object;ILjava/lang/Object;II)V
/*   */     //   401: getfield B60 : [Lf/t40;
/*   */     //   404: iload #6
/*   */     //   406: aload #4
/*   */     //   408: getfield sX : I
/*   */     //   411: aconst_null
/*   */     //   412: invokestatic fill : ([Ljava/lang/Object;IILjava/lang/Object;)V
/*   */     //   415: putfield sX : I
/*   */     //   418: invokevirtual xk0 : ()V
/*   */     //   421: putfield nt : Lf/bn;
/*   */     //   424: getfield ww : Lf/bn;
/*   */     //   427: putfield ww : Lf/bn;
/*   */     //   430: iload #6
/*   */     //   432: putfield sX : I
/*   */     //   435: invokevirtual xk0 : ()V
/*   */     //   438: putfield ww : Lf/bn;
/*   */     //   441: getfield ww : Lf/bn;
/*   */     //   444: dup
/*   */     //   445: astore #4
/*   */     //   447: ifnull -> 457
/*   */     //   450: aload #4
/*   */     //   452: aload #5
/*   */     //   454: putfield nt : Lf/bn;
/*   */     //   457: iload_3
/*   */     //   458: iconst_1
/*   */     //   459: iadd
/*   */     //   460: dup
/*   */     //   461: istore_3
/*   */     //   462: aload_0
/*   */     //   463: dup
/*   */     //   464: dup2
/*   */     //   465: getfield B60 : [Lf/t40;
/*   */     //   468: dup
/*   */     //   469: astore #4
/*   */     //   471: iload_3
/*   */     //   472: aload_0
/*   */     //   473: iload_3
/*   */     //   474: iconst_1
/*   */     //   475: iadd
/*   */     //   476: istore #6
/*   */     //   478: getfield sX : I
/*   */     //   481: iload_3
/*   */     //   482: isub
/*   */     //   483: istore #7
/*   */     //   485: aload #4
/*   */     //   487: iload #6
/*   */     //   489: iload #7
/*   */     //   491: invokestatic arraycopy : (Ljava/lang/Object;ILjava/lang/Object;II)V
/*   */     //   494: getfield B60 : [Lf/t40;
/*   */     //   497: iload_3
/*   */     //   498: aload #5
/*   */     //   500: aastore
/*   */     //   501: getfield sX : I
/*   */     //   504: dup
/*   */     //   505: istore_3
/*   */     //   506: iconst_1
/*   */     //   507: iadd
/*   */     //   508: putfield sX : I
/*   */     //   511: iload_3
/*   */     //   512: if_icmpne -> 233
/*   */     //   515: aload_0
/*   */     //   516: invokevirtual xk0 : ()V
/*   */     //   519: goto -> 233
/*   */     //   522: aload_0
/*   */     //   523: invokevirtual xk0 : ()V
/*   */     //   526: iconst_1
/*   */     //   527: ireturn
/*   */     // Line number table:
/*   */     //   Java source line number -> byte code offset
/*   */     //   #1	-> 12
/*   */     //   #2	-> 90
/*   */     //   #3	-> 103
/*   */     //   #4	-> 117
/*   */     //   #5	-> 149
/*   */     //   #6	-> 204
/*   */     //   #7	-> 236
/*   */     //   #8	-> 305
/*   */     //   #9	-> 332
/*   */     //   #10	-> 465
/*   */     //   #11	-> 523
/*   */   }
/*   */   
/*   */   public final int xn(int paramInt1, int paramInt2, int paramInt3) {
/*   */     int i;
/*   */     for (i = 0; i < paramInt3; ) {
/*   */       int j = i + paramInt3 >>> 1;
/*   */       t40 t401;
/*   */       int k;
/*   */       if ((k = (t401 = this.B60[j]).O20 - paramInt1) == 0)
/*   */         k = t401.GP - paramInt2; 
/*   */       if (k > 0) {
/*   */         paramInt3 = j;
/*   */         continue;
/*   */       } 
/*   */       if (k < 0) {
/*   */         i = j + 1;
/*   */         continue;
/*   */       } 
/*   */       return j;
/*   */     } 
/*   */     return i;
/*   */   }
/*   */   
/*   */   public final void m4(int paramInt1, int paramInt2, int paramInt3) {
/*   */     if (--paramInt3 > 0) {
/*   */       int i = this.sX;
/*   */       bn bn1;
/*   */       while (i-- > 0 && (bn1 = (bn)this.B60[i]).O20 >= paramInt1)
/*   */         bn1.m4(paramInt1, paramInt2, paramInt3); 
/*   */     } else {
/*   */       paramInt3 = this.sX;
/*   */       t40 t401;
/*   */       int i;
/*   */       while (paramInt3-- > 0 && (i = (t401 = this.B60[paramInt3]).O20) >= paramInt1)
/*   */         t401.O20 = i + paramInt2; 
/*   */     } 
/*   */     xk0();
/*   */   }
/*   */   
/*   */   public final boolean GW(int paramInt1, int paramInt2, int paramInt3) {
/*   */     if (--paramInt3 > 0) {
/*   */       boolean bool;
/*   */       int i;
/*   */       bn bn1;
/*   */       for (bool = false, i = this.sX; i-- > 0 && (bn1 = (bn)this.B60[i]).O20 >= paramInt1; ) {
/*   */         if (bn1.GW(paramInt1, paramInt2, paramInt3)) {
/*   */           AH(i);
/*   */           continue;
/*   */         } 
/*   */         bool |= bn1.NS();
/*   */       } 
/*   */       if (bool && (paramInt1 = this.sX) > 1)
/*   */         if (paramInt1 == 2) {
/*   */           zH();
/*   */         } else {
/*   */           for (paramInt1 = --paramInt1 + -1; --paramInt1 > 1;) {
/*   */             if (Ex(paramInt1))
/*   */               paramInt1--; 
/*   */           } 
/*   */         }  
/*   */     } else {
/*   */       t40[] arrayOfT40;
/*   */       t40 t401;
/*   */       int i;
/*   */       for (paramInt3 = this.sX; paramInt3-- > 0 && (i = (t401 = (arrayOfT40 = this.B60)[paramInt3]).O20) >= paramInt1;) {
/*   */         if ((t401.O20 = i - paramInt2) < paramInt1) {
/*   */           this.sX = j;
/*   */           int j = paramInt3 + 1;
/*   */           i = (j = this.sX - 1) - paramInt3;
/*   */           System.arraycopy(arrayOfT40, j, arrayOfT40, paramInt3, i);
/*   */           this.B60[this.sX] = null;
/*   */         } 
/*   */       } 
/*   */     } 
/*   */     if (this.sX == 0)
/*   */       return true; 
/*   */     xk0();
/*   */     return false;
/*   */   }
/*   */   
/*   */   public final void AH(int paramInt) {
/*   */     t40[] arrayOfT40;
/*   */     bn bn1, bn2;
/*   */     if ((bn2 = (bn1 = (bn)(arrayOfT40 = this.B60)[paramInt]).ww) != null)
/*   */       bn2.nt = bn1.nt; 
/*   */     bn bn3;
/*   */     if ((bn3 = bn1.nt) != null)
/*   */       bn3.ww = bn2; 
/*   */     bn1.ww = null;
/*   */     bn1.nt = null;
/*   */     this.sX = i;
/*   */     int i = paramInt + 1, j = (i = this.sX - 1) - paramInt;
/*   */     System.arraycopy(arrayOfT40, i, arrayOfT40, paramInt, j);
/*   */     this.B60[this.sX] = null;
/*   */   }
/*   */   
/*   */   public final boolean NS() {
/*   */     return (this.sX * 2 < this.B60.length);
/*   */   }
/*   */   
/*   */   public final void xk0() {
/*   */     t40 t401;
/*   */     this.O20 = (t401 = this.B60[this.sX - 1]).O20;
/*   */     this.GP = this.GP;
/*   */   }
/*   */   
/*   */   public final void zH() {
/*   */     bn bn1 = (bn)this.B60[0];
/*   */     int i;
/*   */     bn bn2 = (bn)this.B60[i = 1];
/*   */     if (bn1.NS() || bn2.NS()) {
/*   */       int j;
/*   */       int k;
/*   */       int m;
/*   */       if ((m = (j = bn1.sX) + (k = bn2.sX)) < this.B60.length) {
/*   */         System.arraycopy(bn2.B60, 0, bn1.B60, j, k);
/*   */         bn1.sX = m;
/*   */         bn1.xk0();
/*   */         AH(i);
/*   */       } else {
/*   */         System.arraycopy(bn1.B60, 0, this, 0, j);
/*   */         int i2 = bn1.sX;
/*   */         i = bn2.sX;
/*   */         System.arraycopy(bn2.B60, 0, this, i2, i);
/*   */         int i1 = m / 2;
/*   */         bn2.sX = m - i1;
/*   */         t40[] arrayOfT401 = bn1.B60;
/*   */         i2 = bn1.sX;
/*   */         System.arraycopy(this, 0, this, 0, i2);
/*   */         int n = bn1.sX;
/*   */         t40[] arrayOfT402 = bn2.B60;
/*   */         i = bn2.sX;
/*   */         Object[] arrayOfObject;
/*   */         System.arraycopy(arrayOfObject = new Object[m], n, arrayOfT402, 0, i);
/*   */         bn1.xk0();
/*   */         bn2.xk0();
/*   */       } 
/*   */     } 
/*   */   }
/*   */   
/*   */   public final boolean Ex(int paramInt) {
/*   */     // Byte code:
/*   */     //   0: aload_0
/*   */     //   1: getfield B60 : [Lf/t40;
/*   */     //   4: dup
/*   */     //   5: dup
/*   */     //   6: iload_1
/*   */     //   7: swap
/*   */     //   8: iload_1
/*   */     //   9: iconst_1
/*   */     //   10: isub
/*   */     //   11: aaload
/*   */     //   12: checkcast f/bn
/*   */     //   15: astore_2
/*   */     //   16: aaload
/*   */     //   17: checkcast f/bn
/*   */     //   20: astore_3
/*   */     //   21: iload_1
/*   */     //   22: iconst_1
/*   */     //   23: iadd
/*   */     //   24: dup
/*   */     //   25: istore #4
/*   */     //   27: aaload
/*   */     //   28: checkcast f/bn
/*   */     //   31: astore #5
/*   */     //   33: aload_2
/*   */     //   34: invokevirtual NS : ()Z
/*   */     //   37: ifne -> 55
/*   */     //   40: aload_3
/*   */     //   41: invokevirtual NS : ()Z
/*   */     //   44: ifne -> 55
/*   */     //   47: aload #5
/*   */     //   49: invokevirtual NS : ()Z
/*   */     //   52: ifeq -> 442
/*   */     //   55: aload_2
/*   */     //   56: getfield sX : I
/*   */     //   59: dup
/*   */     //   60: istore #6
/*   */     //   62: aload_3
/*   */     //   63: getfield sX : I
/*   */     //   66: dup
/*   */     //   67: istore #7
/*   */     //   69: iadd
/*   */     //   70: aload #5
/*   */     //   72: getfield sX : I
/*   */     //   75: iadd
/*   */     //   76: dup
/*   */     //   77: istore #8
/*   */     //   79: aload_0
/*   */     //   80: getfield B60 : [Lf/t40;
/*   */     //   83: arraylength
/*   */     //   84: if_icmpge -> 160
/*   */     //   87: aload_0
/*   */     //   88: iload_1
/*   */     //   89: aload_0
/*   */     //   90: iload #4
/*   */     //   92: aload_2
/*   */     //   93: dup
/*   */     //   94: iload #8
/*   */     //   96: aload #5
/*   */     //   98: aload_3
/*   */     //   99: getfield B60 : [Lf/t40;
/*   */     //   102: aload_2
/*   */     //   103: getfield B60 : [Lf/t40;
/*   */     //   106: iconst_0
/*   */     //   107: swap
/*   */     //   108: iload #6
/*   */     //   110: iload #7
/*   */     //   112: invokestatic arraycopy : (Ljava/lang/Object;ILjava/lang/Object;II)V
/*   */     //   115: getfield B60 : [Lf/t40;
/*   */     //   118: aload #5
/*   */     //   120: aload_2
/*   */     //   121: dup
/*   */     //   122: getfield B60 : [Lf/t40;
/*   */     //   125: astore_0
/*   */     //   126: getfield sX : I
/*   */     //   129: aload_3
/*   */     //   130: getfield sX : I
/*   */     //   133: iadd
/*   */     //   134: istore_1
/*   */     //   135: getfield sX : I
/*   */     //   138: istore_2
/*   */     //   139: iconst_0
/*   */     //   140: aload_0
/*   */     //   141: iload_1
/*   */     //   142: iload_2
/*   */     //   143: invokestatic arraycopy : (Ljava/lang/Object;ILjava/lang/Object;II)V
/*   */     //   146: putfield sX : I
/*   */     //   149: invokevirtual xk0 : ()V
/*   */     //   152: invokevirtual AH : (I)V
/*   */     //   155: invokevirtual AH : (I)V
/*   */     //   158: iconst_1
/*   */     //   159: ireturn
/*   */     //   160: iload #8
/*   */     //   162: aload_0
/*   */     //   163: aload #5
/*   */     //   165: aload_3
/*   */     //   166: aload_2
/*   */     //   167: iload #8
/*   */     //   169: anewarray java/lang/Object
/*   */     //   172: astore_1
/*   */     //   173: getfield B60 : [Lf/t40;
/*   */     //   176: iconst_0
/*   */     //   177: aload_1
/*   */     //   178: iconst_0
/*   */     //   179: iload #6
/*   */     //   181: invokestatic arraycopy : (Ljava/lang/Object;ILjava/lang/Object;II)V
/*   */     //   184: getfield B60 : [Lf/t40;
/*   */     //   187: aload_3
/*   */     //   188: aload_2
/*   */     //   189: getfield sX : I
/*   */     //   192: istore #6
/*   */     //   194: getfield sX : I
/*   */     //   197: istore #7
/*   */     //   199: iconst_0
/*   */     //   200: aload_1
/*   */     //   201: iload #6
/*   */     //   203: iload #7
/*   */     //   205: invokestatic arraycopy : (Ljava/lang/Object;ILjava/lang/Object;II)V
/*   */     //   208: getfield B60 : [Lf/t40;
/*   */     //   211: aload #5
/*   */     //   213: aload_2
/*   */     //   214: getfield sX : I
/*   */     //   217: aload_3
/*   */     //   218: getfield sX : I
/*   */     //   221: iadd
/*   */     //   222: istore #6
/*   */     //   224: getfield sX : I
/*   */     //   227: istore #7
/*   */     //   229: iconst_0
/*   */     //   230: aload_1
/*   */     //   231: iload #6
/*   */     //   233: iload #7
/*   */     //   235: invokestatic arraycopy : (Ljava/lang/Object;ILjava/lang/Object;II)V
/*   */     //   238: getfield B60 : [Lf/t40;
/*   */     //   241: arraylength
/*   */     //   242: iconst_2
/*   */     //   243: imul
/*   */     //   244: if_icmpge -> 323
/*   */     //   247: aload_0
/*   */     //   248: iload #4
/*   */     //   250: aload_3
/*   */     //   251: aload_2
/*   */     //   252: aload_1
/*   */     //   253: aload_3
/*   */     //   254: dup
/*   */     //   255: aload_2
/*   */     //   256: aload_1
/*   */     //   257: aload_2
/*   */     //   258: dup
/*   */     //   259: aload_3
/*   */     //   260: iload #8
/*   */     //   262: aload_2
/*   */     //   263: iload #8
/*   */     //   265: iconst_2
/*   */     //   266: idiv
/*   */     //   267: dup
/*   */     //   268: istore_0
/*   */     //   269: putfield sX : I
/*   */     //   272: iload_0
/*   */     //   273: isub
/*   */     //   274: putfield sX : I
/*   */     //   277: getfield B60 : [Lf/t40;
/*   */     //   280: astore_0
/*   */     //   281: getfield sX : I
/*   */     //   284: istore_1
/*   */     //   285: iconst_0
/*   */     //   286: aload_0
/*   */     //   287: iconst_0
/*   */     //   288: iload_1
/*   */     //   289: invokestatic arraycopy : (Ljava/lang/Object;ILjava/lang/Object;II)V
/*   */     //   292: getfield sX : I
/*   */     //   295: istore_0
/*   */     //   296: getfield B60 : [Lf/t40;
/*   */     //   299: astore_1
/*   */     //   300: getfield sX : I
/*   */     //   303: istore_2
/*   */     //   304: iload_0
/*   */     //   305: aload_1
/*   */     //   306: iconst_0
/*   */     //   307: iload_2
/*   */     //   308: invokestatic arraycopy : (Ljava/lang/Object;ILjava/lang/Object;II)V
/*   */     //   311: invokevirtual xk0 : ()V
/*   */     //   314: invokevirtual xk0 : ()V
/*   */     //   317: invokevirtual AH : (I)V
/*   */     //   320: goto -> 442
/*   */     //   323: aload #5
/*   */     //   325: aload_3
/*   */     //   326: aload_2
/*   */     //   327: aload_1
/*   */     //   328: aload #5
/*   */     //   330: dup
/*   */     //   331: aload_2
/*   */     //   332: aload_1
/*   */     //   333: aload_3
/*   */     //   334: dup
/*   */     //   335: aload_2
/*   */     //   336: aload_1
/*   */     //   337: aload_2
/*   */     //   338: dup
/*   */     //   339: aload #5
/*   */     //   341: iload #8
/*   */     //   343: aload_2
/*   */     //   344: aload_3
/*   */     //   345: iload #8
/*   */     //   347: aload_2
/*   */     //   348: iload #8
/*   */     //   350: iconst_3
/*   */     //   351: idiv
/*   */     //   352: dup
/*   */     //   353: istore_0
/*   */     //   354: putfield sX : I
/*   */     //   357: iload_0
/*   */     //   358: isub
/*   */     //   359: iconst_2
/*   */     //   360: idiv
/*   */     //   361: dup
/*   */     //   362: istore_0
/*   */     //   363: putfield sX : I
/*   */     //   366: getfield sX : I
/*   */     //   369: iload_0
/*   */     //   370: iadd
/*   */     //   371: isub
/*   */     //   372: putfield sX : I
/*   */     //   375: getfield B60 : [Lf/t40;
/*   */     //   378: astore_0
/*   */     //   379: getfield sX : I
/*   */     //   382: istore_1
/*   */     //   383: iconst_0
/*   */     //   384: aload_0
/*   */     //   385: iconst_0
/*   */     //   386: iload_1
/*   */     //   387: invokestatic arraycopy : (Ljava/lang/Object;ILjava/lang/Object;II)V
/*   */     //   390: getfield sX : I
/*   */     //   393: istore_0
/*   */     //   394: getfield B60 : [Lf/t40;
/*   */     //   397: astore_1
/*   */     //   398: getfield sX : I
/*   */     //   401: istore_2
/*   */     //   402: iload_0
/*   */     //   403: aload_1
/*   */     //   404: iconst_0
/*   */     //   405: iload_2
/*   */     //   406: invokestatic arraycopy : (Ljava/lang/Object;ILjava/lang/Object;II)V
/*   */     //   409: getfield sX : I
/*   */     //   412: aload_3
/*   */     //   413: getfield sX : I
/*   */     //   416: iadd
/*   */     //   417: istore_0
/*   */     //   418: getfield B60 : [Lf/t40;
/*   */     //   421: astore_1
/*   */     //   422: getfield sX : I
/*   */     //   425: istore_2
/*   */     //   426: iload_0
/*   */     //   427: aload_1
/*   */     //   428: iconst_0
/*   */     //   429: iload_2
/*   */     //   430: invokestatic arraycopy : (Ljava/lang/Object;ILjava/lang/Object;II)V
/*   */     //   433: invokevirtual xk0 : ()V
/*   */     //   436: invokevirtual xk0 : ()V
/*   */     //   439: invokevirtual xk0 : ()V
/*   */     //   442: iconst_0
/*   */     //   443: ireturn
/*   */     // Line number table:
/*   */     //   Java source line number -> byte code offset
/*   */     //   #1	-> 169
/*   */     //   #2	-> 238
/*   */     //   #3	-> 266
/*   */     //   #4	-> 317
/*   */     //   #5	-> 351
/*   */   } }


/* Location:              /Users/vnnsnnt/Documents/Codespace/JavaWorkspace/RedTrainer/src/main/java/org/trainer/client/PokeMMO.jar!/f/bn.class
 * Java compiler version: 8 (52.0)
 * JD-Core Version:       1.1.3
 */