package f;

public final class BP implements con {
  public final void ng(Object paramObject, int paramInt, float[] paramArrayOffloat) {
    // Byte code:
    //   0: iload_2
    //   1: aload_1
    //   2: checkcast f/T0
    //   5: astore_0
    //   6: tableswitch default -> 36, 10 -> 269, 11 -> 181, 12 -> 113, 13 -> 45
    //   36: getstatic f/BP.Fb0 : Z
    //   39: ifeq -> 339
    //   42: goto -> 338
    //   45: aload_0
    //   46: getstatic f/F4.Qr0 : J
    //   49: dup2
    //   50: lstore_1
    //   51: invokevirtual gV : (J)Z
    //   54: ifne -> 92
    //   57: aload_0
    //   58: getstatic com/badlogic/gdx/graphics/Color.CLEAR : Lcom/badlogic/gdx/graphics/Color;
    //   61: astore_0
    //   62: fconst_0
    //   63: fstore #4
    //   65: new f/F4
    //   68: dup
    //   69: dup
    //   70: astore #5
    //   72: lload_1
    //   73: aload_0
    //   74: fload #4
    //   76: invokespecial <init> : (JLcom/badlogic/gdx/graphics/Color;F)V
    //   79: ldc 0.8
    //   81: putfield nj0 : F
    //   84: aload #5
    //   86: invokevirtual Tz0 : (Lf/dj;)V
    //   89: goto -> 102
    //   92: aload_0
    //   93: lload_1
    //   94: invokevirtual cOM1 : (J)Lf/dj;
    //   97: checkcast f/F4
    //   100: astore #5
    //   102: aload #5
    //   104: aload_3
    //   105: iconst_0
    //   106: faload
    //   107: putfield A8 : F
    //   110: goto -> 338
    //   113: aload_0
    //   114: getstatic f/F4.Qr0 : J
    //   117: dup2
    //   118: lstore_1
    //   119: invokevirtual gV : (J)Z
    //   122: ifne -> 160
    //   125: aload_0
    //   126: getstatic com/badlogic/gdx/graphics/Color.CLEAR : Lcom/badlogic/gdx/graphics/Color;
    //   129: astore_0
    //   130: fconst_0
    //   131: fstore #4
    //   133: new f/F4
    //   136: dup
    //   137: dup
    //   138: astore #5
    //   140: lload_1
    //   141: aload_0
    //   142: fload #4
    //   144: invokespecial <init> : (JLcom/badlogic/gdx/graphics/Color;F)V
    //   147: ldc 0.8
    //   149: putfield nj0 : F
    //   152: aload #5
    //   154: invokevirtual Tz0 : (Lf/dj;)V
    //   157: goto -> 170
    //   160: aload_0
    //   161: lload_1
    //   162: invokevirtual cOM1 : (J)Lf/dj;
    //   165: checkcast f/F4
    //   168: astore #5
    //   170: aload #5
    //   172: aload_3
    //   173: iconst_0
    //   174: faload
    //   175: putfield nj0 : F
    //   178: goto -> 338
    //   181: aload_0
    //   182: getstatic f/F4.Qr0 : J
    //   185: dup2
    //   186: lstore_1
    //   187: invokevirtual gV : (J)Z
    //   190: ifne -> 228
    //   193: aload_0
    //   194: getstatic com/badlogic/gdx/graphics/Color.CLEAR : Lcom/badlogic/gdx/graphics/Color;
    //   197: astore_0
    //   198: fconst_1
    //   199: fstore #4
    //   201: new f/F4
    //   204: dup
    //   205: dup
    //   206: astore #5
    //   208: lload_1
    //   209: aload_0
    //   210: fload #4
    //   212: invokespecial <init> : (JLcom/badlogic/gdx/graphics/Color;F)V
    //   215: ldc 0.8
    //   217: putfield nj0 : F
    //   220: aload #5
    //   222: invokevirtual Tz0 : (Lf/dj;)V
    //   225: goto -> 238
    //   228: aload_0
    //   229: lload_1
    //   230: invokevirtual cOM1 : (J)Lf/dj;
    //   233: checkcast f/F4
    //   236: astore #5
    //   238: aload #5
    //   240: getfield Nx0 : Lcom/badlogic/gdx/graphics/Color;
    //   243: aload_3
    //   244: dup
    //   245: dup2
    //   246: iconst_0
    //   247: faload
    //   248: fstore_0
    //   249: iconst_1
    //   250: faload
    //   251: fstore_1
    //   252: iconst_2
    //   253: faload
    //   254: fstore_2
    //   255: iconst_3
    //   256: faload
    //   257: fstore_3
    //   258: fload_0
    //   259: fload_1
    //   260: fload_2
    //   261: fload_3
    //   262: invokevirtual set : (FFFF)Lcom/badlogic/gdx/graphics/Color;
    //   265: pop
    //   266: goto -> 338
    //   269: aload_0
    //   270: getstatic f/s5.DR : J
    //   273: dup2
    //   274: lstore_1
    //   275: invokevirtual gV : (J)Z
    //   278: ifne -> 304
    //   281: aload_0
    //   282: getstatic com/badlogic/gdx/graphics/Color.CLEAR : Lcom/badlogic/gdx/graphics/Color;
    //   285: astore #4
    //   287: new f/s5
    //   290: dup
    //   291: astore #5
    //   293: lload_1
    //   294: aload #4
    //   296: invokespecial <init> : (JLcom/badlogic/gdx/graphics/Color;)V
    //   299: aload #5
    //   301: invokevirtual Tz0 : (Lf/dj;)V
    //   304: aload_0
    //   305: lload_1
    //   306: invokevirtual cOM1 : (J)Lf/dj;
    //   309: checkcast f/s5
    //   312: getfield lx : Lcom/badlogic/gdx/graphics/Color;
    //   315: aload_3
    //   316: dup
    //   317: dup2
    //   318: iconst_0
    //   319: faload
    //   320: fstore_0
    //   321: iconst_1
    //   322: faload
    //   323: fstore_1
    //   324: iconst_2
    //   325: faload
    //   326: fstore_2
    //   327: iconst_3
    //   328: faload
    //   329: fstore_3
    //   330: fload_0
    //   331: fload_1
    //   332: fload_2
    //   333: fload_3
    //   334: invokevirtual set : (FFFF)Lcom/badlogic/gdx/graphics/Color;
    //   337: pop
    //   338: return
    //   339: new java/lang/AssertionError
    //   342: dup
    //   343: invokespecial <init> : ()V
    //   346: athrow
    // Line number table:
    //   Java source line number -> byte code offset
    //   #1	-> 36
    //   #2	-> 65
    //   #3	-> 81
    //   #4	-> 133
    //   #5	-> 149
    //   #6	-> 201
    //   #7	-> 217
    //   #8	-> 287
    //   #9	-> 301
    //   #10	-> 306
    //   #11	-> 309
  }
  
  public final int Uu0(Object paramObject, int paramInt, float[] paramArrayOffloat) {
    // Byte code:
    //   0: iload_2
    //   1: aload_1
    //   2: checkcast f/T0
    //   5: astore_0
    //   6: tableswitch default -> 36, 10 -> 188, 11 -> 121, 12 -> 84, 13 -> 47
    //   36: getstatic f/BP.Fb0 : Z
    //   39: ifeq -> 254
    //   42: iconst_0
    //   43: istore_0
    //   44: goto -> 252
    //   47: aload_0
    //   48: fconst_0
    //   49: fstore_1
    //   50: getstatic f/F4.Qr0 : J
    //   53: dup2
    //   54: lstore #4
    //   56: invokevirtual gV : (J)Z
    //   59: ifeq -> 75
    //   62: aload_0
    //   63: lload #4
    //   65: invokevirtual cOM1 : (J)Lf/dj;
    //   68: checkcast f/F4
    //   71: getfield A8 : F
    //   74: fstore_1
    //   75: aload_3
    //   76: iconst_0
    //   77: fload_1
    //   78: fastore
    //   79: iconst_1
    //   80: istore_0
    //   81: goto -> 252
    //   84: aload_0
    //   85: fconst_1
    //   86: fstore_1
    //   87: getstatic f/F4.Qr0 : J
    //   90: dup2
    //   91: lstore #4
    //   93: invokevirtual gV : (J)Z
    //   96: ifeq -> 112
    //   99: aload_0
    //   100: lload #4
    //   102: invokevirtual cOM1 : (J)Lf/dj;
    //   105: checkcast f/F4
    //   108: getfield nj0 : F
    //   111: fstore_1
    //   112: aload_3
    //   113: iconst_0
    //   114: fload_1
    //   115: fastore
    //   116: iconst_1
    //   117: istore_0
    //   118: goto -> 252
    //   121: aload_0
    //   122: getstatic com/badlogic/gdx/graphics/Color.CLEAR : Lcom/badlogic/gdx/graphics/Color;
    //   125: astore_1
    //   126: getstatic f/F4.Qr0 : J
    //   129: dup2
    //   130: lstore #4
    //   132: invokevirtual gV : (J)Z
    //   135: ifeq -> 151
    //   138: aload_0
    //   139: lload #4
    //   141: invokevirtual cOM1 : (J)Lf/dj;
    //   144: checkcast f/F4
    //   147: getfield Nx0 : Lcom/badlogic/gdx/graphics/Color;
    //   150: astore_1
    //   151: aload_3
    //   152: aload_1
    //   153: aload_3
    //   154: aload_1
    //   155: aload_3
    //   156: aload_1
    //   157: aload_3
    //   158: aload_1
    //   159: getfield r : F
    //   162: iconst_0
    //   163: swap
    //   164: fastore
    //   165: getfield g : F
    //   168: iconst_1
    //   169: swap
    //   170: fastore
    //   171: getfield b : F
    //   174: iconst_2
    //   175: swap
    //   176: fastore
    //   177: getfield a : F
    //   180: iconst_3
    //   181: swap
    //   182: fastore
    //   183: iconst_4
    //   184: istore_0
    //   185: goto -> 252
    //   188: aload_0
    //   189: getstatic com/badlogic/gdx/graphics/Color.CLEAR : Lcom/badlogic/gdx/graphics/Color;
    //   192: astore_1
    //   193: getstatic f/s5.DR : J
    //   196: dup2
    //   197: lstore #4
    //   199: invokevirtual gV : (J)Z
    //   202: ifeq -> 218
    //   205: aload_0
    //   206: lload #4
    //   208: invokevirtual cOM1 : (J)Lf/dj;
    //   211: checkcast f/s5
    //   214: getfield lx : Lcom/badlogic/gdx/graphics/Color;
    //   217: astore_1
    //   218: aload_3
    //   219: aload_1
    //   220: aload_3
    //   221: aload_1
    //   222: aload_3
    //   223: aload_1
    //   224: aload_3
    //   225: aload_1
    //   226: getfield r : F
    //   229: iconst_0
    //   230: swap
    //   231: fastore
    //   232: getfield g : F
    //   235: iconst_1
    //   236: swap
    //   237: fastore
    //   238: getfield b : F
    //   241: iconst_2
    //   242: swap
    //   243: fastore
    //   244: getfield a : F
    //   247: iconst_3
    //   248: swap
    //   249: fastore
    //   250: iconst_4
    //   251: istore_0
    //   252: iload_0
    //   253: ireturn
    //   254: new java/lang/AssertionError
    //   257: dup
    //   258: invokespecial <init> : ()V
    //   261: athrow
    // Line number table:
    //   Java source line number -> byte code offset
    //   #1	-> 36
    //   #2	-> 65
    //   #3	-> 68
    //   #4	-> 102
    //   #5	-> 105
    //   #6	-> 141
    //   #7	-> 144
    //   #8	-> 208
    //   #9	-> 211
  }
}


/* Location:              /Users/vnnsnnt/Documents/Codespace/JavaWorkspace/RedTrainer/src/main/java/org/trainer/client/PokeMMO.jar!/f/BP.class
 * Java compiler version: 8 (52.0)
 * JD-Core Version:       1.1.3
 */