/*  1 */ package f;public final class BR extends QZ { public final byte wy; public final short Zo0; public C30[] Zp0 = null; public UA0 Gz = null; public ArrayList hn = null; public dK0 lL; public mi T90; public ArrayList nn0; public final byte No; public final void synchronized() { UA0 uA0; if ((uA0 = this.np0) != null) { uA0.Nh0 = 1; uA0.of = false; uA0.P6 = false; uA0.K5 = false; uA0.bL = true; }  this
/*  2 */       .AS = true; } public final int gB0; public final String Fd0; public U70 uY = null; public UA0 np0 = null; public boolean AS = false; public BR(byte paramByte1, byte paramByte2, short paramShort) { super(paramByte1); this.wy = paramByte2; this.Zo0 = paramShort; Xk xk; if ((xk = T30.b00().Xr(paramByte2, paramShort)) == null) xk = T30.b00().UG0();  this.No = xk.YF(); this.gB0 = AD.cU(xk.NO()); this.Fd0 = xk.m20(); } public final String Xy0() { int i = this.wy * 120; byte b; if ((b = this.No) == 110) i = 0;  return Ml0.OH0(i + 190000 + b); } public final String wG() { byte b1; byte b2; return ((b1 = this.wy) == 0 && ((b2 = this.No) == 81 || b2 == 89 || b2 == 90)) ? Ml0.kd0(b1) : ((b1 == 3 && this.No == 63) ? Ml0.kd0(b1) : this.Fd0); } public final void s6(float paramFloat1, float paramFloat2) { // Byte code:
/*    */     //   0: aload_0
/*    */     //   1: dup
/*    */     //   2: dup
/*    */     //   3: new java/util/ArrayList
/*    */     //   6: dup
/*    */     //   7: invokespecial <init> : ()V
/*    */     //   10: putfield nn0 : Ljava/util/ArrayList;
/*    */     //   13: aconst_null
/*    */     //   14: astore_1
/*    */     //   15: getstatic f/AD.case : Lf/AD;
/*    */     //   18: astore_3
/*    */     //   19: getfield wy : B
/*    */     //   22: istore #4
/*    */     //   24: getfield gB0 : I
/*    */     //   27: istore #5
/*    */     //   29: aload_3
/*    */     //   30: getfield Hm : Lf/ak;
/*    */     //   33: iload #4
/*    */     //   35: invokevirtual Ha0 : (B)Ljava/lang/Object;
/*    */     //   38: checkcast f/c9
/*    */     //   41: dup
/*    */     //   42: astore_3
/*    */     //   43: ifnonnull -> 50
/*    */     //   46: iconst_0
/*    */     //   47: goto -> 59
/*    */     //   50: aload_3
/*    */     //   51: getfield CX : Lf/Ut0;
/*    */     //   54: iload #5
/*    */     //   56: invokevirtual return : (I)Z
/*    */     //   59: ifne -> 676
/*    */     //   62: aload_0
/*    */     //   63: getfield wy : B
/*    */     //   66: dup
/*    */     //   67: istore_3
/*    */     //   68: iconst_2
/*    */     //   69: if_icmpne -> 266
/*    */     //   72: aload_0
/*    */     //   73: getfield gB0 : I
/*    */     //   76: dup
/*    */     //   77: istore #4
/*    */     //   79: bipush #37
/*    */     //   81: if_icmpeq -> 98
/*    */     //   84: iload #4
/*    */     //   86: bipush #38
/*    */     //   88: if_icmpeq -> 98
/*    */     //   91: iload #4
/*    */     //   93: bipush #40
/*    */     //   95: if_icmpne -> 266
/*    */     //   98: aload_0
/*    */     //   99: getstatic f/km.mI0 : Lf/P1;
/*    */     //   102: getfield AN : Lf/Wo;
/*    */     //   105: astore_3
/*    */     //   106: new f/ig
/*    */     //   109: dup
/*    */     //   110: astore #5
/*    */     //   112: aload_3
/*    */     //   113: getfield TI : Lf/RD;
/*    */     //   116: ldc '/a/0/7/2'
/*    */     //   118: invokevirtual B8 : (Ljava/lang/String;)Lf/T7;
/*    */     //   121: invokespecial <init> : (Lf/T7;)V
/*    */     //   124: new f/LD
/*    */     //   127: dup
/*    */     //   128: astore_3
/*    */     //   129: aload #5
/*    */     //   131: iload #4
/*    */     //   133: bipush #8
/*    */     //   135: imul
/*    */     //   136: dup
/*    */     //   137: istore #4
/*    */     //   139: iconst_2
/*    */     //   140: iadd
/*    */     //   141: invokevirtual zz : (I)Lf/T7;
/*    */     //   144: iconst_0
/*    */     //   145: invokespecial <init> : (Lf/T7;Z)V
/*    */     //   148: new f/vJ
/*    */     //   151: dup
/*    */     //   152: astore #6
/*    */     //   154: aload #5
/*    */     //   156: iload #4
/*    */     //   158: bipush #7
/*    */     //   160: iadd
/*    */     //   161: invokevirtual zz : (I)Lf/T7;
/*    */     //   164: invokespecial <init> : (Lf/T7;)V
/*    */     //   167: new f/ek0
/*    */     //   170: dup
/*    */     //   171: astore #7
/*    */     //   173: aload #5
/*    */     //   175: iload #4
/*    */     //   177: iconst_1
/*    */     //   178: iadd
/*    */     //   179: invokevirtual zz : (I)Lf/T7;
/*    */     //   182: iconst_1
/*    */     //   183: invokespecial <init> : (Lf/T7;Z)V
/*    */     //   186: new f/jJ
/*    */     //   189: dup
/*    */     //   190: astore #8
/*    */     //   192: aload #5
/*    */     //   194: iload #4
/*    */     //   196: iconst_3
/*    */     //   197: iadd
/*    */     //   198: invokevirtual zz : (I)Lf/T7;
/*    */     //   201: iconst_1
/*    */     //   202: invokespecial <init> : (Lf/T7;Z)V
/*    */     //   205: new f/Y3
/*    */     //   208: dup
/*    */     //   209: astore #9
/*    */     //   211: aload #5
/*    */     //   213: iload #4
/*    */     //   215: iconst_4
/*    */     //   216: iadd
/*    */     //   217: invokevirtual zz : (I)Lf/T7;
/*    */     //   220: invokespecial <init> : (Lf/T7;)V
/*    */     //   223: new f/jJ
/*    */     //   226: dup
/*    */     //   227: astore #10
/*    */     //   229: aload #5
/*    */     //   231: iload #4
/*    */     //   233: iconst_5
/*    */     //   234: iadd
/*    */     //   235: invokevirtual zz : (I)Lf/T7;
/*    */     //   238: iconst_0
/*    */     //   239: invokespecial <init> : (Lf/T7;Z)V
/*    */     //   242: new f/UA0
/*    */     //   245: dup
/*    */     //   246: aload #6
/*    */     //   248: aload #7
/*    */     //   250: aload_3
/*    */     //   251: aload #8
/*    */     //   253: aload #9
/*    */     //   255: aload #10
/*    */     //   257: invokespecial <init> : (Lf/vJ;Lf/ek0;Lf/LD;Lf/jJ;Lf/Y3;Lf/jJ;)V
/*    */     //   260: putfield np0 : Lf/UA0;
/*    */     //   263: goto -> 586
/*    */     //   266: iload_3
/*    */     //   267: iconst_3
/*    */     //   268: if_icmpne -> 423
/*    */     //   271: aload_0
/*    */     //   272: getstatic f/km.mI0 : Lf/P1;
/*    */     //   275: getfield MT : Lf/gD;
/*    */     //   278: astore_3
/*    */     //   279: getfield gB0 : I
/*    */     //   282: istore #4
/*    */     //   284: new f/ig
/*    */     //   287: dup
/*    */     //   288: astore #5
/*    */     //   290: aload_3
/*    */     //   291: getfield TI : Lf/RD;
/*    */     //   294: ldc '/poketool/trgra/trfgra.narc'
/*    */     //   296: invokevirtual B8 : (Ljava/lang/String;)Lf/T7;
/*    */     //   299: invokespecial <init> : (Lf/T7;)V
/*    */     //   302: new f/jJ
/*    */     //   305: dup
/*    */     //   306: dup
/*    */     //   307: astore_3
/*    */     //   308: aload #5
/*    */     //   310: iload #4
/*    */     //   312: iconst_5
/*    */     //   313: imul
/*    */     //   314: dup
/*    */     //   315: istore #4
/*    */     //   317: iconst_3
/*    */     //   318: iadd
/*    */     //   319: invokevirtual zz : (I)Lf/T7;
/*    */     //   322: iconst_0
/*    */     //   323: invokespecial <init> : (Lf/T7;Z)V
/*    */     //   326: iconst_1
/*    */     //   327: invokevirtual su : (I)I
/*    */     //   330: iconst_1
/*    */     //   331: if_icmpge -> 337
/*    */     //   334: goto -> 491
/*    */     //   337: new f/vJ
/*    */     //   340: dup
/*    */     //   341: astore #6
/*    */     //   343: aload #5
/*    */     //   345: iload #4
/*    */     //   347: iconst_1
/*    */     //   348: iadd
/*    */     //   349: invokevirtual zz : (I)Lf/T7;
/*    */     //   352: invokespecial <init> : (Lf/T7;)V
/*    */     //   355: new f/ek0
/*    */     //   358: dup
/*    */     //   359: astore #7
/*    */     //   361: aload #5
/*    */     //   363: iload #4
/*    */     //   365: invokevirtual zz : (I)Lf/T7;
/*    */     //   368: iconst_1
/*    */     //   369: invokespecial <init> : (Lf/T7;Z)V
/*    */     //   372: new f/LD
/*    */     //   375: dup
/*    */     //   376: astore #8
/*    */     //   378: aload #5
/*    */     //   380: iload #4
/*    */     //   382: iconst_2
/*    */     //   383: iadd
/*    */     //   384: invokevirtual zz : (I)Lf/T7;
/*    */     //   387: iconst_0
/*    */     //   388: invokespecial <init> : (Lf/T7;Z)V
/*    */     //   391: new f/UA0
/*    */     //   394: dup
/*    */     //   395: dup2
/*    */     //   396: astore #4
/*    */     //   398: aload #6
/*    */     //   400: aload #7
/*    */     //   402: aload #8
/*    */     //   404: aconst_null
/*    */     //   405: aconst_null
/*    */     //   406: aload_3
/*    */     //   407: invokespecial <init> : (Lf/vJ;Lf/ek0;Lf/LD;Lf/jJ;Lf/Y3;Lf/jJ;)V
/*    */     //   410: bipush #80
/*    */     //   412: putfield BU : I
/*    */     //   415: bipush #80
/*    */     //   417: putfield B30 : I
/*    */     //   420: goto -> 580
/*    */     //   423: iload_3
/*    */     //   424: iconst_4
/*    */     //   425: if_icmpne -> 586
/*    */     //   428: aload_0
/*    */     //   429: getstatic f/km.mI0 : Lf/P1;
/*    */     //   432: getfield yE : Lf/BE;
/*    */     //   435: astore_3
/*    */     //   436: getfield gB0 : I
/*    */     //   439: istore #4
/*    */     //   441: new f/ig
/*    */     //   444: dup
/*    */     //   445: astore #5
/*    */     //   447: aload_3
/*    */     //   448: getfield TI : Lf/RD;
/*    */     //   451: ldc '/a/0/5/8'
/*    */     //   453: invokevirtual B8 : (Ljava/lang/String;)Lf/T7;
/*    */     //   456: invokespecial <init> : (Lf/T7;)V
/*    */     //   459: new f/jJ
/*    */     //   462: dup
/*    */     //   463: dup
/*    */     //   464: astore_3
/*    */     //   465: aload #5
/*    */     //   467: iload #4
/*    */     //   469: iconst_5
/*    */     //   470: imul
/*    */     //   471: dup
/*    */     //   472: istore #4
/*    */     //   474: iconst_3
/*    */     //   475: iadd
/*    */     //   476: invokevirtual zz : (I)Lf/T7;
/*    */     //   479: iconst_0
/*    */     //   480: invokespecial <init> : (Lf/T7;Z)V
/*    */     //   483: iconst_1
/*    */     //   484: invokevirtual su : (I)I
/*    */     //   487: iconst_1
/*    */     //   488: if_icmpge -> 497
/*    */     //   491: aconst_null
/*    */     //   492: astore #4
/*    */     //   494: goto -> 580
/*    */     //   497: new f/vJ
/*    */     //   500: dup
/*    */     //   501: astore #6
/*    */     //   503: aload #5
/*    */     //   505: iload #4
/*    */     //   507: iconst_1
/*    */     //   508: iadd
/*    */     //   509: invokevirtual zz : (I)Lf/T7;
/*    */     //   512: invokespecial <init> : (Lf/T7;)V
/*    */     //   515: new f/ek0
/*    */     //   518: dup
/*    */     //   519: astore #7
/*    */     //   521: aload #5
/*    */     //   523: iload #4
/*    */     //   525: invokevirtual zz : (I)Lf/T7;
/*    */     //   528: iconst_1
/*    */     //   529: invokespecial <init> : (Lf/T7;Z)V
/*    */     //   532: new f/LD
/*    */     //   535: dup
/*    */     //   536: astore #8
/*    */     //   538: aload #5
/*    */     //   540: iload #4
/*    */     //   542: iconst_2
/*    */     //   543: iadd
/*    */     //   544: invokevirtual zz : (I)Lf/T7;
/*    */     //   547: iconst_0
/*    */     //   548: invokespecial <init> : (Lf/T7;Z)V
/*    */     //   551: new f/UA0
/*    */     //   554: dup
/*    */     //   555: dup2
/*    */     //   556: astore #4
/*    */     //   558: aload #6
/*    */     //   560: aload #7
/*    */     //   562: aload #8
/*    */     //   564: aconst_null
/*    */     //   565: aconst_null
/*    */     //   566: aload_3
/*    */     //   567: invokespecial <init> : (Lf/vJ;Lf/ek0;Lf/LD;Lf/jJ;Lf/Y3;Lf/jJ;)V
/*    */     //   570: bipush #80
/*    */     //   572: putfield BU : I
/*    */     //   575: bipush #80
/*    */     //   577: putfield B30 : I
/*    */     //   580: aload_0
/*    */     //   581: aload #4
/*    */     //   583: putfield np0 : Lf/UA0;
/*    */     //   586: aload_0
/*    */     //   587: getfield np0 : Lf/UA0;
/*    */     //   590: dup
/*    */     //   591: astore_3
/*    */     //   592: ifnull -> 676
/*    */     //   595: aload_3
/*    */     //   596: dup
/*    */     //   597: dup
/*    */     //   598: dup2
/*    */     //   599: dup2
/*    */     //   600: iconst_1
/*    */     //   601: putfield Nh0 : I
/*    */     //   604: iconst_0
/*    */     //   605: putfield of : Z
/*    */     //   608: iconst_0
/*    */     //   609: putfield P6 : Z
/*    */     //   612: iconst_0
/*    */     //   613: putfield K5 : Z
/*    */     //   616: iconst_1
/*    */     //   617: putfield bL : Z
/*    */     //   620: iconst_0
/*    */     //   621: putfield bL : Z
/*    */     //   624: invokevirtual OB0 : ()Lf/pe0;
/*    */     //   627: astore_1
/*    */     //   628: new f/uT
/*    */     //   631: dup
/*    */     //   632: dup2
/*    */     //   633: astore_3
/*    */     //   634: aload_1
/*    */     //   635: dup
/*    */     //   636: getfield H0 : I
/*    */     //   639: istore #4
/*    */     //   641: getfield Vn0 : I
/*    */     //   644: iload #4
/*    */     //   646: swap
/*    */     //   647: aload_1
/*    */     //   648: iconst_1
/*    */     //   649: invokespecial <init> : (IILf/pe0;Z)V
/*    */     //   652: getstatic f/vH.xC : Lf/eo;
/*    */     //   655: invokevirtual WI0 : (Lf/eo;)V
/*    */     //   658: getfield He0 : Lf/eo;
/*    */     //   661: fload_2
/*    */     //   662: ldc_w 0.25
/*    */     //   665: fadd
/*    */     //   666: ldc_w 0.025
/*    */     //   669: fconst_0
/*    */     //   670: invokevirtual Tz : (FFF)Lf/eo;
/*    */     //   673: pop
/*    */     //   674: aload_3
/*    */     //   675: astore_1
/*    */     //   676: aload_1
/*    */     //   677: ifnonnull -> 834
/*    */     //   680: aload_0
/*    */     //   681: dup
/*    */     //   682: getstatic f/AD.case : Lf/AD;
/*    */     //   685: astore_1
/*    */     //   686: getfield wy : B
/*    */     //   689: istore_3
/*    */     //   690: getfield gB0 : I
/*    */     //   693: istore #4
/*    */     //   695: aload_1
/*    */     //   696: getfield Hm : Lf/ak;
/*    */     //   699: iload_3
/*    */     //   700: invokevirtual Ha0 : (B)Ljava/lang/Object;
/*    */     //   703: checkcast f/c9
/*    */     //   706: dup
/*    */     //   707: astore_1
/*    */     //   708: ifnonnull -> 718
/*    */     //   711: getstatic f/U70.ah0 : Lf/U70;
/*    */     //   714: astore_1
/*    */     //   715: goto -> 761
/*    */     //   718: aload_1
/*    */     //   719: getfield CX : Lf/Ut0;
/*    */     //   722: iload #4
/*    */     //   724: invokevirtual Z6 : (I)Ljava/lang/Object;
/*    */     //   727: checkcast f/U70
/*    */     //   730: dup
/*    */     //   731: astore_3
/*    */     //   732: ifnonnull -> 748
/*    */     //   735: aload_1
/*    */     //   736: getfield Nn0 : Lf/Ut0;
/*    */     //   739: iload #4
/*    */     //   741: invokevirtual Z6 : (I)Ljava/lang/Object;
/*    */     //   744: checkcast f/U70
/*    */     //   747: astore_3
/*    */     //   748: aload_3
/*    */     //   749: ifnonnull -> 759
/*    */     //   752: getstatic f/U70.ah0 : Lf/U70;
/*    */     //   755: astore_1
/*    */     //   756: goto -> 761
/*    */     //   759: aload_3
/*    */     //   760: astore_1
/*    */     //   761: aload_1
/*    */     //   762: aload_0
/*    */     //   763: dup
/*    */     //   764: aload_1
/*    */     //   765: putfield uY : Lf/U70;
/*    */     //   768: invokevirtual lu : (Ljava/lang/Object;)V
/*    */     //   771: new f/pe0
/*    */     //   774: dup
/*    */     //   775: astore_1
/*    */     //   776: aload_0
/*    */     //   777: getfield uY : Lf/U70;
/*    */     //   780: invokevirtual HA0 : ()Lcom/badlogic/gdx/graphics/Texture;
/*    */     //   783: invokespecial <init> : (Lcom/badlogic/gdx/graphics/Texture;)V
/*    */     //   786: new f/uT
/*    */     //   789: dup
/*    */     //   790: dup2
/*    */     //   791: astore_3
/*    */     //   792: aload_1
/*    */     //   793: dup
/*    */     //   794: getfield H0 : I
/*    */     //   797: istore #4
/*    */     //   799: getfield Vn0 : I
/*    */     //   802: iload #4
/*    */     //   804: swap
/*    */     //   805: aload_1
/*    */     //   806: iconst_1
/*    */     //   807: invokespecial <init> : (IILf/pe0;Z)V
/*    */     //   810: getstatic f/vH.xC : Lf/eo;
/*    */     //   813: invokevirtual WI0 : (Lf/eo;)V
/*    */     //   816: getfield He0 : Lf/eo;
/*    */     //   819: fload_2
/*    */     //   820: ldc_w 0.25
/*    */     //   823: fadd
/*    */     //   824: ldc_w -0.025
/*    */     //   827: fconst_0
/*    */     //   828: invokevirtual Tz : (FFF)Lf/eo;
/*    */     //   831: pop
/*    */     //   832: aload_3
/*    */     //   833: astore_1
/*    */     //   834: aload_0
/*    */     //   835: getfield nn0 : Ljava/util/ArrayList;
/*    */     //   838: aload_1
/*    */     //   839: invokevirtual add : (Ljava/lang/Object;)Z
/*    */     //   842: pop
/*    */     //   843: return
/*    */     // Line number table:
/*    */     //   Java source line number -> byte code offset
/*    */     //   #1	-> 15
/*    */     //   #2	-> 19
/*    */     //   #3	-> 30
/*    */     //   #4	-> 35
/*    */     //   #5	-> 51
/*    */     //   #6	-> 56
/*    */     //   #7	-> 63
/*    */     //   #8	-> 106
/*    */     //   #9	-> 113
/*    */     //   #10	-> 116
/*    */     //   #11	-> 141
/*    */     //   #12	-> 145
/*    */     //   #13	-> 148
/*    */     //   #14	-> 161
/*    */     //   #15	-> 164
/*    */     //   #16	-> 179
/*    */     //   #17	-> 183
/*    */     //   #18	-> 198
/*    */     //   #19	-> 202
/*    */     //   #20	-> 217
/*    */     //   #21	-> 220
/*    */     //   #22	-> 223
/*    */     //   #23	-> 235
/*    */     //   #24	-> 239
/*    */     //   #25	-> 242
/*    */     //   #26	-> 260
/*    */     //   #27	-> 284
/*    */     //   #28	-> 291
/*    */     //   #29	-> 294
/*    */     //   #30	-> 319
/*    */     //   #31	-> 323
/*    */     //   #32	-> 327
/*    */     //   #33	-> 349
/*    */     //   #34	-> 352
/*    */     //   #35	-> 365
/*    */     //   #36	-> 369
/*    */     //   #37	-> 384
/*    */     //   #38	-> 388
/*    */     //   #39	-> 391
/*    */     //   #40	-> 412
/*    */     //   #41	-> 429
/*    */     //   #42	-> 441
/*    */     //   #43	-> 448
/*    */     //   #44	-> 451
/*    */     //   #45	-> 476
/*    */     //   #46	-> 480
/*    */     //   #47	-> 484
/*    */     //   #48	-> 509
/*    */     //   #49	-> 512
/*    */     //   #50	-> 525
/*    */     //   #51	-> 529
/*    */     //   #52	-> 544
/*    */     //   #53	-> 548
/*    */     //   #54	-> 551
/*    */     //   #55	-> 572
/*    */     //   #56	-> 583
/*    */     //   #57	-> 601
/*    */     //   #58	-> 621
/*    */     //   #59	-> 624
/*    */     //   #60	-> 628
/*    */     //   #61	-> 636
/*    */     //   #62	-> 641
/*    */     //   #63	-> 649
/*    */     //   #64	-> 652
/*    */     //   #65	-> 658
/*    */     //   #66	-> 670
/*    */     //   #67	-> 682
/*    */     //   #68	-> 686
/*    */     //   #69	-> 696
/*    */     //   #70	-> 700
/*    */     //   #71	-> 719
/*    */     //   #72	-> 765
/*    */     //   #73	-> 786
/*    */     //   #74	-> 794
/*    */     //   #75	-> 799
/*    */     //   #76	-> 807
/*    */     //   #77	-> 810
/*    */     //   #78	-> 816
/*    */     //   #79	-> 828 } public final void zV() { UA0 uA0; if ((uA0 = this.np0) != null) UB0.Kg0.fN(this);  } public final List lK() { return (this.wy == 3 && this.gB0 == 65 && !this.AS) ? Collections.emptyList() : this.nn0; } public final void kO(int paramInt1, int paramInt2) { // Byte code:
/*    */     //   0: aload_0
/*    */     //   1: iconst_0
/*    */     //   2: istore_2
/*    */     //   3: getfield wy : B
/*    */     //   6: dup
/*    */     //   7: istore_3
/*    */     //   8: iconst_2
/*    */     //   9: if_icmpne -> 394
/*    */     //   12: aload_0
/*    */     //   13: getfield No : B
/*    */     //   16: bipush #37
/*    */     //   18: if_icmpne -> 394
/*    */     //   21: getstatic f/km.mI0 : Lf/P1;
/*    */     //   24: getfield AN : Lf/Wo;
/*    */     //   27: astore_2
/*    */     //   28: new f/ig
/*    */     //   31: dup
/*    */     //   32: astore_3
/*    */     //   33: aload_2
/*    */     //   34: getfield TI : Lf/RD;
/*    */     //   37: ldc_w '/a/0/6/4'
/*    */     //   40: invokevirtual B8 : (Ljava/lang/String;)Lf/T7;
/*    */     //   43: invokespecial <init> : (Lf/T7;)V
/*    */     //   46: new f/LD
/*    */     //   49: dup
/*    */     //   50: dup
/*    */     //   51: astore_2
/*    */     //   52: aload_3
/*    */     //   53: bipush #26
/*    */     //   55: invokevirtual zz : (I)Lf/T7;
/*    */     //   58: iconst_0
/*    */     //   59: invokespecial <init> : (Lf/T7;Z)V
/*    */     //   62: new f/vJ
/*    */     //   65: dup
/*    */     //   66: astore #4
/*    */     //   68: aload_3
/*    */     //   69: bipush #31
/*    */     //   71: invokevirtual zz : (I)Lf/T7;
/*    */     //   74: invokespecial <init> : (Lf/T7;)V
/*    */     //   77: new f/ek0
/*    */     //   80: dup
/*    */     //   81: astore #5
/*    */     //   83: aload_3
/*    */     //   84: bipush #25
/*    */     //   86: invokevirtual zz : (I)Lf/T7;
/*    */     //   89: iconst_1
/*    */     //   90: invokespecial <init> : (Lf/T7;Z)V
/*    */     //   93: new f/jJ
/*    */     //   96: dup
/*    */     //   97: astore #6
/*    */     //   99: aload_3
/*    */     //   100: bipush #27
/*    */     //   102: invokevirtual zz : (I)Lf/T7;
/*    */     //   105: iconst_1
/*    */     //   106: invokespecial <init> : (Lf/T7;Z)V
/*    */     //   109: new f/Y3
/*    */     //   112: dup
/*    */     //   113: astore #7
/*    */     //   115: aload_3
/*    */     //   116: bipush #28
/*    */     //   118: invokevirtual zz : (I)Lf/T7;
/*    */     //   121: invokespecial <init> : (Lf/T7;)V
/*    */     //   124: new f/jJ
/*    */     //   127: dup
/*    */     //   128: astore #8
/*    */     //   130: aload_3
/*    */     //   131: bipush #29
/*    */     //   133: invokevirtual zz : (I)Lf/T7;
/*    */     //   136: iconst_0
/*    */     //   137: invokespecial <init> : (Lf/T7;Z)V
/*    */     //   140: getfield ql : Lf/Ie;
/*    */     //   143: getfield RM : S
/*    */     //   146: istore_3
/*    */     //   147: iconst_0
/*    */     //   148: istore #9
/*    */     //   150: iload #9
/*    */     //   152: iload_3
/*    */     //   153: if_icmpge -> 282
/*    */     //   156: iload #9
/*    */     //   158: aload_2
/*    */     //   159: new f/NC0
/*    */     //   162: dup
/*    */     //   163: astore #10
/*    */     //   165: invokespecial <init> : ()V
/*    */     //   168: new f/NC0
/*    */     //   171: dup
/*    */     //   172: astore #11
/*    */     //   174: invokespecial <init> : ()V
/*    */     //   177: iload #9
/*    */     //   179: aload #10
/*    */     //   181: aload #11
/*    */     //   183: invokevirtual rb0 : (ILf/NC0;Lf/NC0;)V
/*    */     //   186: bipush #9
/*    */     //   188: if_icmplt -> 228
/*    */     //   191: iload #9
/*    */     //   193: bipush #13
/*    */     //   195: if_icmpgt -> 228
/*    */     //   198: aload #11
/*    */     //   200: dup
/*    */     //   201: aload #10
/*    */     //   203: dup
/*    */     //   204: ldc_w 48.0
/*    */     //   207: putfield x : F
/*    */     //   210: ldc_w 48.0
/*    */     //   213: putfield y : F
/*    */     //   216: ldc_w 24.0
/*    */     //   219: putfield x : F
/*    */     //   222: ldc_w 24.0
/*    */     //   225: putfield y : F
/*    */     //   228: new f/ZH
/*    */     //   231: dup
/*    */     //   232: astore #12
/*    */     //   234: aload_2
/*    */     //   235: dup
/*    */     //   236: iload #9
/*    */     //   238: aload #5
/*    */     //   240: aload #4
/*    */     //   242: aload #12
/*    */     //   244: aload #10
/*    */     //   246: getfield x : F
/*    */     //   249: f2i
/*    */     //   250: aload #10
/*    */     //   252: getfield y : F
/*    */     //   255: f2i
/*    */     //   256: getstatic f/Uc.xi0 : Lf/Uc;
/*    */     //   259: invokespecial <init> : (IILf/Uc;)V
/*    */     //   262: aload #12
/*    */     //   264: aload #11
/*    */     //   266: aconst_null
/*    */     //   267: invokevirtual Ll : (ILf/ek0;Lf/vJ;Lf/ZH;Lf/NC0;[S)V
/*    */     //   270: invokevirtual VE0 : ()V
/*    */     //   273: invokevirtual dispose : ()V
/*    */     //   276: iinc #9, 1
/*    */     //   279: goto -> 150
/*    */     //   282: aload_0
/*    */     //   283: new f/UA0
/*    */     //   286: dup
/*    */     //   287: aload_0
/*    */     //   288: swap
/*    */     //   289: dup
/*    */     //   290: aload #4
/*    */     //   292: aload #5
/*    */     //   294: aload_2
/*    */     //   295: aload #6
/*    */     //   297: aload #7
/*    */     //   299: aload #8
/*    */     //   301: invokespecial <init> : (Lf/vJ;Lf/ek0;Lf/LD;Lf/jJ;Lf/Y3;Lf/jJ;)V
/*    */     //   304: putfield Gz : Lf/UA0;
/*    */     //   307: iconst_1
/*    */     //   308: invokevirtual od0 : (I)Lf/COm1;
/*    */     //   311: getfield ui0 : Lf/fQ;
/*    */     //   314: dup
/*    */     //   315: astore_2
/*    */     //   316: getfield Z8 : I
/*    */     //   319: anewarray f/C30
/*    */     //   322: putfield Zp0 : [Lf/C30;
/*    */     //   325: iconst_0
/*    */     //   326: istore_3
/*    */     //   327: iload_3
/*    */     //   328: aload_2
/*    */     //   329: getfield Z8 : I
/*    */     //   332: if_icmpge -> 366
/*    */     //   335: aload_0
/*    */     //   336: getfield Zp0 : [Lf/C30;
/*    */     //   339: iload_3
/*    */     //   340: new f/C30
/*    */     //   343: dup
/*    */     //   344: astore #4
/*    */     //   346: aload_2
/*    */     //   347: iload_3
/*    */     //   348: invokevirtual get : (I)Ljava/lang/Object;
/*    */     //   351: checkcast f/pe0
/*    */     //   354: invokespecial <init> : (Lf/pe0;)V
/*    */     //   357: aload #4
/*    */     //   359: aastore
/*    */     //   360: iinc #3, 1
/*    */     //   363: goto -> 327
/*    */     //   366: iload_1
/*    */     //   367: aload_0
/*    */     //   368: new f/mi
/*    */     //   371: dup
/*    */     //   372: aload_0
/*    */     //   373: getfield Zp0 : [Lf/C30;
/*    */     //   376: iconst_0
/*    */     //   377: aaload
/*    */     //   378: dup
/*    */     //   379: astore_2
/*    */     //   380: invokespecial <init> : (Lf/C30;)V
/*    */     //   383: putfield T90 : Lf/mi;
/*    */     //   386: sipush #296
/*    */     //   389: iadd
/*    */     //   390: istore_3
/*    */     //   391: goto -> 809
/*    */     //   394: iload_3
/*    */     //   395: iconst_3
/*    */     //   396: if_icmpne -> 822
/*    */     //   399: aload_0
/*    */     //   400: iconst_m1
/*    */     //   401: istore_3
/*    */     //   402: getfield No : B
/*    */     //   405: dup
/*    */     //   406: istore #4
/*    */     //   408: bipush #63
/*    */     //   410: if_icmpeq -> 498
/*    */     //   413: iload #4
/*    */     //   415: tableswitch default -> 456, 90 -> 493, 91 -> 488, 92 -> 483, 93 -> 477, 94 -> 471, 95 -> 465, 96 -> 459
/*    */     //   456: goto -> 500
/*    */     //   459: bipush #9
/*    */     //   461: istore_3
/*    */     //   462: goto -> 500
/*    */     //   465: bipush #8
/*    */     //   467: istore_3
/*    */     //   468: goto -> 500
/*    */     //   471: bipush #7
/*    */     //   473: istore_3
/*    */     //   474: goto -> 500
/*    */     //   477: bipush #6
/*    */     //   479: istore_3
/*    */     //   480: goto -> 500
/*    */     //   483: iconst_5
/*    */     //   484: istore_3
/*    */     //   485: goto -> 500
/*    */     //   488: iconst_4
/*    */     //   489: istore_3
/*    */     //   490: goto -> 500
/*    */     //   493: iconst_3
/*    */     //   494: istore_3
/*    */     //   495: goto -> 500
/*    */     //   498: iconst_2
/*    */     //   499: istore_3
/*    */     //   500: iload_3
/*    */     //   501: iconst_m1
/*    */     //   502: if_icmple -> 822
/*    */     //   505: getstatic f/km.mI0 : Lf/P1;
/*    */     //   508: getfield MT : Lf/gD;
/*    */     //   511: astore_2
/*    */     //   512: new f/ig
/*    */     //   515: dup
/*    */     //   516: astore #4
/*    */     //   518: aload_2
/*    */     //   519: getfield TI : Lf/RD;
/*    */     //   522: ldc_w '/poketool/trgra/trbgra.narc'
/*    */     //   525: invokevirtual B8 : (Ljava/lang/String;)Lf/T7;
/*    */     //   528: invokespecial <init> : (Lf/T7;)V
/*    */     //   531: new f/LD
/*    */     //   534: dup
/*    */     //   535: dup
/*    */     //   536: astore_2
/*    */     //   537: aload #4
/*    */     //   539: iload_3
/*    */     //   540: iconst_5
/*    */     //   541: imul
/*    */     //   542: dup
/*    */     //   543: istore_3
/*    */     //   544: iconst_2
/*    */     //   545: iadd
/*    */     //   546: invokevirtual zz : (I)Lf/T7;
/*    */     //   549: iconst_0
/*    */     //   550: invokespecial <init> : (Lf/T7;Z)V
/*    */     //   553: new f/vJ
/*    */     //   556: dup
/*    */     //   557: astore #5
/*    */     //   559: aload #4
/*    */     //   561: iload_3
/*    */     //   562: iconst_1
/*    */     //   563: iadd
/*    */     //   564: invokevirtual zz : (I)Lf/T7;
/*    */     //   567: invokespecial <init> : (Lf/T7;)V
/*    */     //   570: new f/ek0
/*    */     //   573: dup
/*    */     //   574: astore #6
/*    */     //   576: aload #4
/*    */     //   578: iload_3
/*    */     //   579: iconst_0
/*    */     //   580: iadd
/*    */     //   581: invokevirtual zz : (I)Lf/T7;
/*    */     //   584: iconst_0
/*    */     //   585: invokespecial <init> : (Lf/T7;Z)V
/*    */     //   588: new f/jJ
/*    */     //   591: aload #4
/*    */     //   593: iload_3
/*    */     //   594: iconst_3
/*    */     //   595: iadd
/*    */     //   596: invokevirtual zz : (I)Lf/T7;
/*    */     //   599: iconst_0
/*    */     //   600: invokespecial <init> : (Lf/T7;Z)V
/*    */     //   603: new java/util/ArrayList
/*    */     //   606: dup
/*    */     //   607: astore_3
/*    */     //   608: invokespecial <init> : ()V
/*    */     //   611: getfield ql : Lf/Ie;
/*    */     //   614: getfield RM : S
/*    */     //   617: istore #4
/*    */     //   619: iconst_0
/*    */     //   620: istore #7
/*    */     //   622: iload #7
/*    */     //   624: iload #4
/*    */     //   626: if_icmpge -> 723
/*    */     //   629: aload_2
/*    */     //   630: iload #7
/*    */     //   632: new f/NC0
/*    */     //   635: dup
/*    */     //   636: dup
/*    */     //   637: astore #8
/*    */     //   639: invokespecial <init> : ()V
/*    */     //   642: new f/NC0
/*    */     //   645: dup
/*    */     //   646: dup
/*    */     //   647: astore #9
/*    */     //   649: invokespecial <init> : ()V
/*    */     //   652: invokevirtual rb0 : (ILf/NC0;Lf/NC0;)V
/*    */     //   655: new f/ZH
/*    */     //   658: dup
/*    */     //   659: astore #10
/*    */     //   661: aload_3
/*    */     //   662: aload_2
/*    */     //   663: dup
/*    */     //   664: iload #7
/*    */     //   666: aload #6
/*    */     //   668: aload #5
/*    */     //   670: aload #10
/*    */     //   672: aload #8
/*    */     //   674: getfield x : F
/*    */     //   677: f2i
/*    */     //   678: aload #8
/*    */     //   680: getfield y : F
/*    */     //   683: f2i
/*    */     //   684: getstatic f/Uc.xi0 : Lf/Uc;
/*    */     //   687: invokespecial <init> : (IILf/Uc;)V
/*    */     //   690: aload #10
/*    */     //   692: aload #9
/*    */     //   694: aconst_null
/*    */     //   695: invokevirtual Ll : (ILf/ek0;Lf/vJ;Lf/ZH;Lf/NC0;[S)V
/*    */     //   698: invokevirtual VE0 : ()V
/*    */     //   701: new com/badlogic/gdx/graphics/Texture
/*    */     //   704: dup
/*    */     //   705: aload #10
/*    */     //   707: invokespecial <init> : (Lf/ZH;)V
/*    */     //   710: invokevirtual add : (Ljava/lang/Object;)Z
/*    */     //   713: pop
/*    */     //   714: invokevirtual dispose : ()V
/*    */     //   717: iinc #7, 1
/*    */     //   720: goto -> 622
/*    */     //   723: aload_0
/*    */     //   724: aload_3
/*    */     //   725: aload_0
/*    */     //   726: aload_3
/*    */     //   727: putfield hn : Ljava/util/ArrayList;
/*    */     //   730: invokevirtual size : ()I
/*    */     //   733: anewarray f/C30
/*    */     //   736: putfield Zp0 : [Lf/C30;
/*    */     //   739: iconst_0
/*    */     //   740: istore_2
/*    */     //   741: iload_2
/*    */     //   742: aload_0
/*    */     //   743: getfield hn : Ljava/util/ArrayList;
/*    */     //   746: invokevirtual size : ()I
/*    */     //   749: if_icmpge -> 784
/*    */     //   752: aload_0
/*    */     //   753: getfield Zp0 : [Lf/C30;
/*    */     //   756: iload_2
/*    */     //   757: new f/C30
/*    */     //   760: dup
/*    */     //   761: astore_3
/*    */     //   762: aload_0
/*    */     //   763: getfield hn : Ljava/util/ArrayList;
/*    */     //   766: iload_2
/*    */     //   767: invokevirtual get : (I)Ljava/lang/Object;
/*    */     //   770: checkcast com/badlogic/gdx/graphics/Texture
/*    */     //   773: invokespecial <init> : (Lcom/badlogic/gdx/graphics/Texture;)V
/*    */     //   776: aload_3
/*    */     //   777: aastore
/*    */     //   778: iinc #2, 1
/*    */     //   781: goto -> 741
/*    */     //   784: iload_1
/*    */     //   785: aload_0
/*    */     //   786: new f/mi
/*    */     //   789: dup
/*    */     //   790: aload_0
/*    */     //   791: getfield Zp0 : [Lf/C30;
/*    */     //   794: iconst_0
/*    */     //   795: aaload
/*    */     //   796: dup
/*    */     //   797: astore_2
/*    */     //   798: invokespecial <init> : (Lf/C30;)V
/*    */     //   801: putfield T90 : Lf/mi;
/*    */     //   804: sipush #296
/*    */     //   807: iadd
/*    */     //   808: istore_3
/*    */     //   809: aload_2
/*    */     //   810: dup
/*    */     //   811: iload_3
/*    */     //   812: putfield ec : I
/*    */     //   815: bipush #32
/*    */     //   817: putfield hv : I
/*    */     //   820: iconst_1
/*    */     //   821: istore_2
/*    */     //   822: iload_2
/*    */     //   823: ifne -> 892
/*    */     //   826: getstatic f/km.q00 : Lf/Hk;
/*    */     //   829: dup
/*    */     //   830: invokevirtual getClass : ()Ljava/lang/Class;
/*    */     //   833: pop
/*    */     //   834: new f/H10
/*    */     //   837: dup
/*    */     //   838: astore_2
/*    */     //   839: invokespecial <init> : ()V
/*    */     //   842: new f/OE0
/*    */     //   845: dup
/*    */     //   846: iconst_0
/*    */     //   847: aload_2
/*    */     //   848: invokespecial <init> : (BLf/H10;)V
/*    */     //   851: invokevirtual zZ : (Lf/OE0;)[Lf/C30;
/*    */     //   854: dup
/*    */     //   855: aload_0
/*    */     //   856: swap
/*    */     //   857: putfield Zp0 : [Lf/C30;
/*    */     //   860: new f/mi
/*    */     //   863: astore_2
/*    */     //   864: iconst_0
/*    */     //   865: aaload
/*    */     //   866: dup
/*    */     //   867: dup
/*    */     //   868: astore_3
/*    */     //   869: iload_1
/*    */     //   870: aload_0
/*    */     //   871: aload_2
/*    */     //   872: dup
/*    */     //   873: aload_3
/*    */     //   874: invokespecial <init> : (Lf/C30;)V
/*    */     //   877: putfield T90 : Lf/mi;
/*    */     //   880: sipush #296
/*    */     //   883: iadd
/*    */     //   884: putfield ec : I
/*    */     //   887: bipush #32
/*    */     //   889: putfield hv : I
/*    */     //   892: return
/*    */     // Line number table:
/*    */     //   Java source line number -> byte code offset
/*    */     //   #1	-> 28
/*    */     //   #2	-> 34
/*    */     //   #3	-> 37
/*    */     //   #4	-> 55
/*    */     //   #5	-> 59
/*    */     //   #6	-> 62
/*    */     //   #7	-> 71
/*    */     //   #8	-> 74
/*    */     //   #9	-> 86
/*    */     //   #10	-> 90
/*    */     //   #11	-> 102
/*    */     //   #12	-> 106
/*    */     //   #13	-> 118
/*    */     //   #14	-> 121
/*    */     //   #15	-> 124
/*    */     //   #16	-> 133
/*    */     //   #17	-> 137
/*    */     //   #18	-> 140
/*    */     //   #19	-> 159
/*    */     //   #20	-> 304
/*    */     //   #21	-> 311
/*    */     //   #22	-> 316
/*    */     //   #23	-> 512
/*    */     //   #24	-> 519
/*    */     //   #25	-> 522
/*    */     //   #26	-> 546
/*    */     //   #27	-> 550
/*    */     //   #28	-> 553
/*    */     //   #29	-> 564
/*    */     //   #30	-> 567
/*    */     //   #31	-> 581
/*    */     //   #32	-> 585
/*    */     //   #33	-> 588
/*    */     //   #34	-> 596
/*    */     //   #35	-> 600
/*    */     //   #36	-> 603
/*    */     //   #37	-> 611
/*    */     //   #38	-> 632
/*    */     //   #39	-> 727
/*    */     //   #40	-> 812
/*    */     //   #41	-> 817
/*    */     //   #42	-> 826
/*    */     //   #43	-> 834
/*    */     //   #44	-> 857
/*    */     //   #45	-> 884
/*  2 */     //   #46	-> 889 } public final ET PN() { return ET.mi0; } public final String dn(Gp0 paramGp0) { StringBuilder stringBuilder; rK rK; if ((rK = paramGp0.dd) == rK.oi) { this();
/*    */       
/*  4 */       return pv.X9(200490, this, "\n\n").append(Ml0.OH0(200491)).toString(); }  if (this == rK.Ev0) { this();
/*    */ 
/*    */       
/*  7 */       return pv.X9(200506, this, "\n\n").append(Ml0.Go(200507, String.valueOf(paramGp0.N9))).toString(); }  return ""; } public final String DP() { arrayOfString[0] = Xy0(); String[] arrayOfString; (arrayOfString = new String[2])[1] = wG(); return Ml0.lz((byte)2, F40.ef0, 15, 7, arrayOfString); } public final String FM(Gp0 paramGp0) { this(); arrayList.add(Xy0()); ArrayList<String> arrayList; (arrayList = new ArrayList<>()).add(wG()); byte b = 0; byte b1 = 0; while (b1 < paramGp0.wI(this.Fu)) { hm0 hm0; if ((hm0 = paramGp0.N0(this.Fu, b1)) == null || hm0.K0.AL()) { arrayList.add(""); } else { b++; arrayList.add(hm0.fA()); }  b1 = (byte)(b1 + 1); }  if (b < 1) return "";  int i = b + 13; if (paramGp0.rx
/*    */       
/*  9 */       .coM9(this.Fu) > 3) { i = 5022; arrayList.clear(); arrayList.add(Xy0()); arrayList.add(wG()); }  F40 f40 = F40.ef0; String[] arrayOfString = arrayList.<String>toArray(new String[0]);
/* 10 */     return Ml0.lz((byte)2, this, 15, i, arrayOfString); }
/*    */ 
/*    */   
/*    */   public final void up(float paramFloat1, float paramFloat2, byte paramByte) {
/*    */     if (this.Fu != km.MR.hG0())
/*    */       km.wI0.K7.s2(this.Fu, paramFloat2, paramByte); 
/*    */   }
/*    */   
/*    */   public final mi pW() {
/*    */     return this.T90;
/*    */   }
/*    */   
/*    */   public final String Lc() {
/*    */     return Ml0.Qf0(F40.ef0, 15, 76);
/*    */   }
/*    */   
/*    */   public final boolean GT(kf paramkf, boolean paramBoolean, String paramString, byte paramByte, hj[] paramArrayOfhj, int paramInt) {
/*    */     int i = paramBoolean ^ true;
/*    */     if (!paramBoolean) {
/*    */       byte b1 = 15, b2 = 44;
/*    */       arrayOfString[0] = Xy0();
/*    */       String[] arrayOfString;
/*    */       (arrayOfString = new String[2])[1] = wG();
/*    */       paramkf.Kq(Ml0.lz((byte)2, F40.ef0, b1, b2, arrayOfString));
/*    */     } 
/*    */     boolean bool = i | super.GT(paramkf, paramBoolean, paramString, paramByte, paramArrayOfhj, paramInt);
/*    */     if (!paramBoolean && paramInt > 0) {
/*    */       byte b1 = 15, b2 = 58;
/*    */       String[] arrayOfString;
/*    */       (arrayOfString = new String[2])[0] = paramString;
/*    */       (new String[2])[1] = paramInt + "";
/*    */       paramkf.Kq(Ml0.lz((byte)2, F40.ef0, b1, b2, arrayOfString));
/*    */     } 
/*    */     return bool;
/*    */   }
/*    */   
/*    */   public final String dy() {
/*    */     return Xy0() + " " + wG();
/*    */   }
/*    */   
/*    */   public final String K5() {
/*    */     return wG();
/*    */   }
/*    */   
/*    */   public final String s7(byte paramByte) {
/*    */     return wG();
/*    */   }
/*    */   
/*    */   public final short HA0() {
/*    */     return this.Zo0;
/*    */   }
/*    */   
/*    */   public final byte d5() {
/*    */     byte b;
/*    */     return ((b = this.wy) == 4 && this.No == 109) ? 2 : b;
/*    */   }
/*    */   
/*    */   public final short COm8() {
/*    */     switch (this.wy) {
/*    */       default:
/*    */       
/*    */       case 4:
/*    */         if ((b = this.No) != 23)
/*    */           if (b != 55 && b != 62) {
/*    */             if (b != 70 && b != 112)
/*    */               if (b != 114 && b != 124) {
/*    */                 if (b != 66 && b != 67)
/*    */                   switch (b) {
/*    */                     default:
/*    */                       switch (b) {
/*    */                         default:
/*    */                           switch (b) {
/*    */                             default:
/*    */                               switch (b) {
/*    */                                 default:
/*    */                                 
/*    */                                 case 116:
/*    */                                 case 117:
/*    */                                 case 118:
/*    */                                   return 1120;
/*    */                                 case 119:
/*    */                                   break;
/*    */                               } 
/*    */                               return 1119;
/*    */                             case 109:
/*    */                               return 1165;
/*    */                             case 97:
/*    */                             case 99:
/*    */                             case 100:
/*    */                             case 101:
/*    */                             case 102:
/*    */                               return 1147;
/*    */                             case 98:
/*    */                             case 103:
/*    */                             case 104:
/*    */                             case 105:
/*    */                             case 106:
/*    */                             case 107:
/*    */                             case 108:
/*    */                             case 110:
/*    */                               break;
/*    */                           } 
/*    */                           break;
/*    */                         case 86:
/*    */                           return 1124;
/*    */                         case 87:
/*    */                         case 88:
/*    */                         case 89:
/*    */                           break;
/*    */                       } 
/*    */                       break;
/*    */                     case 72:
/*    */                     case 73:
/*    */                     case 74:
/*    */                     case 75:
/*    */                     case 76:
/*    */                       break;
/*    */                   }  
/*    */                 return 1118;
/*    */               }  
/*    */             return 1118;
/*    */           }  
/*    */         return 1119;
/*    */       case 3:
/*    */         if ((b = this.No) != 97) {
/*    */           switch (b) {
/*    */             default:
/*    */               switch (b) {
/*    */                 default:
/*    */                   switch (b) {
/*    */                     default:
/*    */                       switch (b) {
/*    */                         default:
/*    */                         
/*    */                         case 99:
/*    */                         case 100:
/*    */                         case 101:
/*    */                         case 102:
/*    */                           break;
/*    */                       } 
/*    */                       return 1202;
/*    */                     case 89:
/*    */                       return 1123;
/*    */                     case 87:
/*    */                     case 88:
/*    */                     case 86:
/*    */                       break;
/*    */                   } 
/*    */                   return 1120;
/*    */                 case 74:
/*    */                 case 75:
/*    */                 case 76:
/*    */                 case 77:
/*    */                 case 78:
/*    */                 case 79:
/*    */                   break;
/*    */                 case 73:
/*    */                 
/*    */                 case 72:
/*    */                   break;
/*    */               } 
/*    */               return 1134;
/*    */             case 69:
/*    */               return 1122;
/*    */             case 65:
/*    */             case 66:
/*    */             case 67:
/*    */             case 68:
/*    */               return 1136;
/*    */             case 63:
/*    */               return 1124;
/*    */             case 62:
/*    */             case 64:
/*    */               break;
/*    */           } 
/*    */           return 1117;
/*    */         } 
/*    */         return 1202;
/*    */       case 2:
/*    */         if ((b = this.No) != 47) {
/*    */           if (b != 89) {
/*    */             if (b != 100) {
/*    */               if (b != 101) {
/*    */                 switch (b) {
/*    */                   default:
/*    */                     switch (b) {
/*    */                       default:
/*    */                         switch (b) {
/*    */                           default:
/*    */                             switch (b) {
/*    */                               default:
/*    */                                 switch (b) {
/*    */                                   default:
/*    */                                   
/*    */                                   case 82:
/*    */                                     return 1139;
/*    */                                   case 78:
/*    */                                   case 79:
/*    */                                   case 80:
/*    */                                   case 81:
/*    */                                     return 1135;
/*    */                                   case 77:
/*    */                                     break;
/*    */                                 } 
/*    */                               case 54:
/*    */                               case 55:
/*    */                               case 56:
/*    */                                 break;
/*    */                             } 
/*    */                             break;
/*    */                           case 37:
/*    */                           case 38:
/*    */                             return 1133;
/*    */                           case 39:
/*    */                             return 1134;
/*    */                           case 40:
/*    */                             break;
/*    */                         } 
/*    */                         return 1137;
/*    */                       case 19:
/*    */                       case 20:
/*    */                       case 21:
/*    */                       case 22:
/*    */                       case 23:
/*    */                         break;
/*    */                     } 
/*    */                     break;
/*    */                   case 10:
/*    */                   case 11:
/*    */                   case 12:
/*    */                     break;
/*    */                 } 
/*    */                 return 1132;
/*    */               } 
/*    */               return 1138;
/*    */             } 
/*    */             return 1145;
/*    */           } 
/*    */           return 1136;
/*    */         } 
/*    */         return 1137;
/*    */       case 1:
/*    */         switch (this.No) {
/*    */           default:
/*    */             return super.COm8();
/*    */           case 50:
/*    */             return 481;
/*    */           case 38:
/*    */             return 478;
/*    */           case 32:
/*    */             return 477;
/*    */           case 31:
/*    */             return 482;
/*    */           case 13:
/*    */           case 53:
/*    */             return 483;
/*    */           case 3:
/*    */           case 9:
/*    */           case 11:
/*    */           case 49:
/*    */             break;
/*    */         } 
/*    */         return 475;
/*    */       case 0:
/*    */         break;
/*    */     } 
/*    */     byte b;
/*    */     if ((b = this.No) != 23 && b != 24)
/*    */       if (b != 30) {
/*    */         if (b != 84 && b != 87) {
/*    */           if (b != 90);
/*    */           return 299;
/*    */         } 
/*    */       } else {
/*    */         return 299;
/*    */       }  
/*    */     return 296;
/*    */   }
/*    */   
/*    */   public final byte Gp() {
/*    */     if (this.wy == 4 && this.No == 109)
/*    */       return 2; 
/*    */     return km.a3.eA;
/*    */   }
/*    */   
/*    */   public final short p7() {
/*    */     // Byte code:
/*    */     //   0: aload_0
/*    */     //   1: getfield wy : B
/*    */     //   4: dup
/*    */     //   5: istore_1
/*    */     //   6: tableswitch default -> 40, 0 -> 676, 1 -> 603, 2 -> 423, 3 -> 223, 4 -> 43
/*    */     //   40: goto -> 724
/*    */     //   43: aload_0
/*    */     //   44: getfield No : B
/*    */     //   47: dup
/*    */     //   48: istore_0
/*    */     //   49: bipush #66
/*    */     //   51: if_icmpeq -> 219
/*    */     //   54: iload_0
/*    */     //   55: bipush #67
/*    */     //   57: if_icmpeq -> 219
/*    */     //   60: iload_0
/*    */     //   61: bipush #70
/*    */     //   63: if_icmpeq -> 219
/*    */     //   66: iload_0
/*    */     //   67: bipush #112
/*    */     //   69: if_icmpeq -> 219
/*    */     //   72: iload_0
/*    */     //   73: tableswitch default -> 108, 72 -> 219, 73 -> 219, 74 -> 219, 75 -> 219, 76 -> 219
/*    */     //   108: iload_0
/*    */     //   109: tableswitch default -> 136, 87 -> 219, 88 -> 219, 89 -> 219
/*    */     //   136: iload_0
/*    */     //   137: tableswitch default -> 208, 97 -> 215, 98 -> 219, 99 -> 215, 100 -> 215, 101 -> 215, 102 -> 215, 103 -> 219, 104 -> 219, 105 -> 219, 106 -> 219, 107 -> 219, 108 -> 219, 109 -> 211, 110 -> 219
/*    */     //   208: goto -> 724
/*    */     //   211: sipush #1152
/*    */     //   214: ireturn
/*    */     //   215: sipush #1148
/*    */     //   218: ireturn
/*    */     //   219: sipush #1131
/*    */     //   222: ireturn
/*    */     //   223: aload_0
/*    */     //   224: getfield No : B
/*    */     //   227: dup
/*    */     //   228: istore_0
/*    */     //   229: bipush #97
/*    */     //   231: if_icmpeq -> 419
/*    */     //   234: iload_0
/*    */     //   235: tableswitch default -> 280, 62 -> 403, 63 -> 399, 64 -> 403, 65 -> 395, 66 -> 395, 67 -> 395, 68 -> 395, 69 -> 391
/*    */     //   280: iload_0
/*    */     //   281: tableswitch default -> 324, 73 -> 407, 74 -> 403, 75 -> 403, 76 -> 403, 77 -> 403, 78 -> 403, 79 -> 403
/*    */     //   324: iload_0
/*    */     //   325: tableswitch default -> 356, 86 -> 415, 87 -> 411, 88 -> 411, 89 -> 407
/*    */     //   356: iload_0
/*    */     //   357: tableswitch default -> 388, 99 -> 419, 100 -> 419, 101 -> 419, 102 -> 419
/*    */     //   388: goto -> 724
/*    */     //   391: sipush #1130
/*    */     //   394: ireturn
/*    */     //   395: sipush #1133
/*    */     //   398: ireturn
/*    */     //   399: sipush #1128
/*    */     //   402: ireturn
/*    */     //   403: sipush #1129
/*    */     //   406: ireturn
/*    */     //   407: sipush #1131
/*    */     //   410: ireturn
/*    */     //   411: sipush #1131
/*    */     //   414: ireturn
/*    */     //   415: sipush #1132
/*    */     //   418: ireturn
/*    */     //   419: sipush #1203
/*    */     //   422: ireturn
/*    */     //   423: aload_0
/*    */     //   424: getfield No : B
/*    */     //   427: dup
/*    */     //   428: istore_0
/*    */     //   429: bipush #39
/*    */     //   431: if_icmpeq -> 599
/*    */     //   434: iload_0
/*    */     //   435: bipush #47
/*    */     //   437: if_icmpeq -> 595
/*    */     //   440: iload_0
/*    */     //   441: bipush #89
/*    */     //   443: if_icmpeq -> 591
/*    */     //   446: iload_0
/*    */     //   447: bipush #101
/*    */     //   449: if_icmpeq -> 595
/*    */     //   452: iload_0
/*    */     //   453: tableswitch default -> 480, 10 -> 587, 11 -> 587, 12 -> 587
/*    */     //   480: iload_0
/*    */     //   481: tableswitch default -> 516, 19 -> 587, 20 -> 587, 21 -> 587, 22 -> 587, 23 -> 587
/*    */     //   516: iload_0
/*    */     //   517: tableswitch default -> 544, 54 -> 587, 55 -> 587, 56 -> 587
/*    */     //   544: iload_0
/*    */     //   545: tableswitch default -> 584, 77 -> 599, 78 -> 591, 79 -> 591, 80 -> 591, 81 -> 591, 82 -> 595
/*    */     //   584: goto -> 724
/*    */     //   587: sipush #1150
/*    */     //   590: ireturn
/*    */     //   591: sipush #1152
/*    */     //   594: ireturn
/*    */     //   595: sipush #1151
/*    */     //   598: ireturn
/*    */     //   599: sipush #1151
/*    */     //   602: ireturn
/*    */     //   603: aload_0
/*    */     //   604: getfield No : B
/*    */     //   607: dup
/*    */     //   608: istore_0
/*    */     //   609: iconst_3
/*    */     //   610: if_icmpeq -> 672
/*    */     //   613: iload_0
/*    */     //   614: bipush #9
/*    */     //   616: if_icmpeq -> 672
/*    */     //   619: iload_0
/*    */     //   620: bipush #11
/*    */     //   622: if_icmpeq -> 672
/*    */     //   625: iload_0
/*    */     //   626: bipush #13
/*    */     //   628: if_icmpeq -> 672
/*    */     //   631: iload_0
/*    */     //   632: bipush #38
/*    */     //   634: if_icmpeq -> 668
/*    */     //   637: iload_0
/*    */     //   638: bipush #49
/*    */     //   640: if_icmpeq -> 672
/*    */     //   643: iload_0
/*    */     //   644: bipush #53
/*    */     //   646: if_icmpeq -> 672
/*    */     //   649: iload_0
/*    */     //   650: bipush #31
/*    */     //   652: if_icmpeq -> 668
/*    */     //   655: iload_0
/*    */     //   656: bipush #32
/*    */     //   658: if_icmpeq -> 664
/*    */     //   661: goto -> 724
/*    */     //   664: sipush #354
/*    */     //   667: ireturn
/*    */     //   668: sipush #355
/*    */     //   671: ireturn
/*    */     //   672: sipush #424
/*    */     //   675: ireturn
/*    */     //   676: aload_0
/*    */     //   677: getfield No : B
/*    */     //   680: dup
/*    */     //   681: istore_0
/*    */     //   682: bipush #23
/*    */     //   684: if_icmpeq -> 720
/*    */     //   687: iload_0
/*    */     //   688: bipush #24
/*    */     //   690: if_icmpeq -> 720
/*    */     //   693: iload_0
/*    */     //   694: bipush #30
/*    */     //   696: if_icmpeq -> 720
/*    */     //   699: iload_0
/*    */     //   700: bipush #84
/*    */     //   702: if_icmpeq -> 720
/*    */     //   705: iload_0
/*    */     //   706: bipush #87
/*    */     //   708: if_icmpeq -> 720
/*    */     //   711: iload_0
/*    */     //   712: bipush #90
/*    */     //   714: if_icmpeq -> 720
/*    */     //   717: goto -> 724
/*    */     //   720: sipush #312
/*    */     //   723: ireturn
/*    */     //   724: iload_1
/*    */     //   725: getstatic f/ET.mi0 : Lf/ET;
/*    */     //   728: astore_0
/*    */     //   729: iflt -> 753
/*    */     //   732: iload_1
/*    */     //   733: aload_0
/*    */     //   734: getfield ii0 : [S
/*    */     //   737: dup
/*    */     //   738: astore_2
/*    */     //   739: arraylength
/*    */     //   740: if_icmplt -> 746
/*    */     //   743: goto -> 753
/*    */     //   746: aload_2
/*    */     //   747: iload_1
/*    */     //   748: saload
/*    */     //   749: istore_0
/*    */     //   750: goto -> 760
/*    */     //   753: aload_0
/*    */     //   754: getfield ii0 : [S
/*    */     //   757: iconst_0
/*    */     //   758: saload
/*    */     //   759: istore_0
/*    */     //   760: iload_0
/*    */     //   761: ireturn
/*    */     // Line number table:
/*    */     //   Java source line number -> byte code offset
/*    */     //   #1	-> 734
/*    */   }
/*    */   
/*    */   public final void dispose() {
/*    */     UA0 uA02;
/*    */     if ((uA02 = this.Gz) != null) {
/*    */       uA02.dispose();
/*    */       this.Gz = null;
/*    */     } 
/*    */     ArrayList arrayList;
/*    */     if ((arrayList = this.hn) != null) {
/*    */       Iterator<Texture> iterator = arrayList.iterator();
/*    */       while (iterator.hasNext())
/*    */         ((Texture)iterator.next()).dispose(); 
/*    */       this.hn = null;
/*    */     } 
/*    */     U70 u70;
/*    */     if ((u70 = this.uY) != null) {
/*    */       u70.gH0(this);
/*    */       this.uY = null;
/*    */     } 
/*    */     UA0 uA01;
/*    */     if ((uA01 = this.np0) != null)
/*    */       dispose(); 
/*    */   }
/*    */   
/*    */   public BR(int paramInt, byte paramByte1, byte paramByte2, byte paramByte3, byte paramByte4) {
/*    */     super(paramByte1);
/*    */     this.wy = paramByte2;
/*    */     this.Zo0 = -1;
/*    */     this.No = paramByte3;
/*    */     this.gB0 = AD.cU(paramByte4);
/*    */     this.Fd0 = Ml0.OH0(paramInt);
/*    */   }
/*    */   
/*    */   public final void ub(int paramInt1, int paramInt2, boolean paramBoolean) {
/*    */     if (paramBoolean) {
/*    */       dK0 dK01;
/*    */       byte b;
/*    */       for (byte[] arrayOfByte = new byte[paramInt2 = km.MR.wI(this.Fu)]; b < paramInt2; ) {
/*    */         hm0 hm0;
/*    */         if ((hm0 = km.MR.N0(this.Fu, b)) == null) {
/*    */           arrayOfByte[b] = -1;
/*    */         } else {
/*    */           arrayOfByte[b] = hm0.oi();
/*    */         } 
/*    */         b = (byte)(b + 1);
/*    */       } 
/*    */       this(this.Zp0, paramInt1);
/*    */       this.lL = new dK0();
/*    */       if (this.wy == 2 && this.No == 37)
/*    */         dK01.PT = 60; 
/*    */       dK01.ff0();
/*    */     } 
/*    */     this.T90 = null;
/*    */   }
/*    */   
/*    */   public final void Ll0(tH paramtH) {
/*    */     if (this.T90 != null)
/*    */       this.Zp0[0].Ht(paramtH); 
/*    */     dK0 dK01;
/*    */     if ((dK01 = this.lL) != null)
/*    */       Yo0(paramtH); 
/*    */   } }


/* Location:              /Users/vnnsnnt/Documents/Codespace/JavaWorkspace/RedTrainer/src/main/java/org/trainer/client/PokeMMO.jar!/f/BR.class
 * Java compiler version: 8 (52.0)
 * JD-Core Version:       1.1.3
 */