/*  1 */ package f;public final class BX extends JG0 { public final ys0[] Yp; public final Un ec0; public Un Au; public final Un JB; public static void n50(String paramString1, T60 paramT60, String paramString2) { if (!paramString1.equalsIgnoreCase(paramString2))
/*  2 */       return;  int i = paramT60.lpT3.OU; R8 r8;
/*  3 */     if ((r8 = km.u4).dm0() == 3) r8
/*  4 */         .e20.W3(new G40(i));  } public final Wr XA; public final Ip jd0; public int Cs; public BX(js paramjs, ro paramro) { // Byte code:
/*    */     //   0: aload_2
/*    */     //   1: aload_0
/*    */     //   2: aload_2
/*    */     //   3: aload_0
/*    */     //   4: dup
/*    */     //   5: dup
/*    */     //   6: invokespecial <init> : ()V
/*    */     //   9: iconst_0
/*    */     //   10: putfield Cs : I
/*    */     //   13: ldc 'characterselectgui'
/*    */     //   15: invokevirtual Xu : (Ljava/lang/String;)V
/*    */     //   18: new f/Wr
/*    */     //   21: dup
/*    */     //   22: dup2
/*    */     //   23: aload_0
/*    */     //   24: swap
/*    */     //   25: dup
/*    */     //   26: invokespecial <init> : ()V
/*    */     //   29: putfield XA : Lf/Wr;
/*    */     //   32: sipush #1049
/*    */     //   35: invokestatic OH0 : (I)Ljava/lang/String;
/*    */     //   38: invokevirtual Lo : (Ljava/lang/String;)V
/*    */     //   41: ldc 'login-panel'
/*    */     //   43: invokevirtual Xu : (Ljava/lang/String;)V
/*    */     //   46: iconst_1
/*    */     //   47: invokevirtual EP : (I)V
/*    */     //   50: new f/Ip
/*    */     //   53: dup
/*    */     //   54: aload_0
/*    */     //   55: swap
/*    */     //   56: dup
/*    */     //   57: invokespecial <init> : ()V
/*    */     //   60: putfield jd0 : Lf/Ip;
/*    */     //   63: ldc 'container'
/*    */     //   65: invokevirtual Xu : (Ljava/lang/String;)V
/*    */     //   68: invokevirtual UK : ()Lf/qN;
/*    */     //   71: invokevirtual size : ()I
/*    */     //   74: anewarray f/ys0
/*    */     //   77: putfield Yp : [Lf/ys0;
/*    */     //   80: iconst_0
/*    */     //   81: istore_3
/*    */     //   82: new java/util/ArrayList
/*    */     //   85: dup
/*    */     //   86: astore #4
/*    */     //   88: invokespecial <init> : ()V
/*    */     //   91: invokevirtual UK : ()Lf/qN;
/*    */     //   94: invokevirtual iterator : ()Ljava/util/Iterator;
/*    */     //   97: astore #5
/*    */     //   99: aload #5
/*    */     //   101: invokeinterface hasNext : ()Z
/*    */     //   106: ifeq -> 128
/*    */     //   109: aload #4
/*    */     //   111: aload #5
/*    */     //   113: invokeinterface next : ()Ljava/lang/Object;
/*    */     //   118: checkcast f/T60
/*    */     //   121: invokevirtual add : (Ljava/lang/Object;)Z
/*    */     //   124: pop
/*    */     //   125: goto -> 99
/*    */     //   128: aload #4
/*    */     //   130: dup
/*    */     //   131: new f/gq
/*    */     //   134: dup
/*    */     //   135: astore #5
/*    */     //   137: invokespecial <init> : ()V
/*    */     //   140: aload #5
/*    */     //   142: invokestatic sort : (Ljava/util/List;Ljava/util/Comparator;)V
/*    */     //   145: invokevirtual iterator : ()Ljava/util/Iterator;
/*    */     //   148: astore #5
/*    */     //   150: aload #5
/*    */     //   152: invokeinterface hasNext : ()Z
/*    */     //   157: ifeq -> 218
/*    */     //   160: aload_0
/*    */     //   161: dup
/*    */     //   162: aload #5
/*    */     //   164: invokeinterface next : ()Ljava/lang/Object;
/*    */     //   169: checkcast f/T60
/*    */     //   172: astore #6
/*    */     //   174: getfield Yp : [Lf/ys0;
/*    */     //   177: iload_3
/*    */     //   178: new f/ys0
/*    */     //   181: dup
/*    */     //   182: astore #7
/*    */     //   184: aload #6
/*    */     //   186: invokespecial <init> : (Lf/T60;)V
/*    */     //   189: aload #7
/*    */     //   191: aastore
/*    */     //   192: getfield Yp : [Lf/ys0;
/*    */     //   195: iload_3
/*    */     //   196: aaload
/*    */     //   197: new f/yc0
/*    */     //   200: dup
/*    */     //   201: aload_0
/*    */     //   202: aload #6
/*    */     //   204: aload_1
/*    */     //   205: aload_2
/*    */     //   206: invokespecial <init> : (Lf/BX;Lf/T60;Lf/js;Lf/ro;)V
/*    */     //   209: invokevirtual tW : (Ljava/lang/Runnable;)V
/*    */     //   212: iinc #3, 1
/*    */     //   215: goto -> 150
/*    */     //   218: aload_0
/*    */     //   219: dup
/*    */     //   220: dup2
/*    */     //   221: dup2
/*    */     //   222: new f/Un
/*    */     //   225: dup
/*    */     //   226: aload_0
/*    */     //   227: swap
/*    */     //   228: dup
/*    */     //   229: sipush #1050
/*    */     //   232: invokestatic OH0 : (I)Ljava/lang/String;
/*    */     //   235: invokespecial <init> : (Ljava/lang/String;)V
/*    */     //   238: putfield ec0 : Lf/Un;
/*    */     //   241: new f/pa
/*    */     //   244: dup
/*    */     //   245: aload_1
/*    */     //   246: invokespecial <init> : (Lf/js;)V
/*    */     //   249: invokevirtual tW : (Ljava/lang/Runnable;)V
/*    */     //   252: new f/Un
/*    */     //   255: dup
/*    */     //   256: astore_3
/*    */     //   257: aload_0
/*    */     //   258: aload_2
/*    */     //   259: aload_0
/*    */     //   260: aload_3
/*    */     //   261: dup
/*    */     //   262: sipush #1065
/*    */     //   265: invokestatic OH0 : (I)Ljava/lang/String;
/*    */     //   268: invokespecial <init> : (Ljava/lang/String;)V
/*    */     //   271: putfield Au : Lf/Un;
/*    */     //   274: <illegal opcode> run : (Lf/BX;Lf/ro;)Ljava/lang/Runnable;
/*    */     //   279: invokevirtual tW : (Ljava/lang/Runnable;)V
/*    */     //   282: new f/Un
/*    */     //   285: dup
/*    */     //   286: aload_0
/*    */     //   287: swap
/*    */     //   288: dup
/*    */     //   289: sipush #1159
/*    */     //   292: invokestatic OH0 : (I)Ljava/lang/String;
/*    */     //   295: invokevirtual toUpperCase : ()Ljava/lang/String;
/*    */     //   298: invokespecial <init> : (Ljava/lang/String;)V
/*    */     //   301: putfield JB : Lf/Un;
/*    */     //   304: new f/jz
/*    */     //   307: dup
/*    */     //   308: aload_0
/*    */     //   309: aload_1
/*    */     //   310: invokespecial <init> : (Lf/BX;Lf/js;)V
/*    */     //   313: invokevirtual tW : (Ljava/lang/Runnable;)V
/*    */     //   316: getfield jd0 : Lf/Ip;
/*    */     //   319: invokevirtual d7 : ()Lf/cr0;
/*    */     //   322: astore_1
/*    */     //   323: getfield jd0 : Lf/Ip;
/*    */     //   326: invokevirtual mE0 : ()Lf/g0;
/*    */     //   329: astore_2
/*    */     //   330: getfield jd0 : Lf/Ip;
/*    */     //   333: aload_1
/*    */     //   334: invokevirtual WN : (Lf/U90;)V
/*    */     //   337: getfield jd0 : Lf/Ip;
/*    */     //   340: aload_2
/*    */     //   341: invokevirtual rK0 : (Lf/U90;)V
/*    */     //   344: getfield jd0 : Lf/Ip;
/*    */     //   347: invokevirtual mE0 : ()Lf/g0;
/*    */     //   350: astore_1
/*    */     //   351: getfield jd0 : Lf/Ip;
/*    */     //   354: invokevirtual d7 : ()Lf/cr0;
/*    */     //   357: astore_2
/*    */     //   358: iconst_0
/*    */     //   359: istore_3
/*    */     //   360: iload_3
/*    */     //   361: aload_0
/*    */     //   362: getfield Yp : [Lf/ys0;
/*    */     //   365: dup
/*    */     //   366: astore #5
/*    */     //   368: arraylength
/*    */     //   369: if_icmpge -> 398
/*    */     //   372: aload_1
/*    */     //   373: aload_0
/*    */     //   374: aload_2
/*    */     //   375: aload #5
/*    */     //   377: iload_3
/*    */     //   378: aaload
/*    */     //   379: invokevirtual Ya : (Lf/JG0;)Lf/U90;
/*    */     //   382: pop
/*    */     //   383: getfield Yp : [Lf/ys0;
/*    */     //   386: iload_3
/*    */     //   387: aaload
/*    */     //   388: invokevirtual Ya : (Lf/JG0;)Lf/U90;
/*    */     //   391: pop
/*    */     //   392: iinc #3, 1
/*    */     //   395: goto -> 360
/*    */     //   398: aload #4
/*    */     //   400: aload_0
/*    */     //   401: dup
/*    */     //   402: getfield jd0 : Lf/Ip;
/*    */     //   405: invokevirtual iJ0 : ()Lf/U90;
/*    */     //   408: aload_2
/*    */     //   409: invokevirtual ee0 : (Lf/U90;)Lf/U90;
/*    */     //   412: pop
/*    */     //   413: getfield jd0 : Lf/Ip;
/*    */     //   416: invokevirtual xh : ()Lf/U90;
/*    */     //   419: aload_1
/*    */     //   420: invokevirtual ee0 : (Lf/U90;)Lf/U90;
/*    */     //   423: pop
/*    */     //   424: invokevirtual isEmpty : ()Z
/*    */     //   427: ifne -> 436
/*    */     //   430: getstatic f/gm.P4 : Z
/*    */     //   433: ifne -> 441
/*    */     //   436: aload_0
/*    */     //   437: aconst_null
/*    */     //   438: putfield Au : Lf/Un;
/*    */     //   441: aload_0
/*    */     //   442: dup
/*    */     //   443: dup
/*    */     //   444: dup2
/*    */     //   445: getfield jd0 : Lf/Ip;
/*    */     //   448: invokevirtual iJ0 : ()Lf/U90;
/*    */     //   451: aload_0
/*    */     //   452: getfield jd0 : Lf/Ip;
/*    */     //   455: iconst_3
/*    */     //   456: anewarray f/JG0
/*    */     //   459: dup
/*    */     //   460: dup
/*    */     //   461: astore_1
/*    */     //   462: aload_0
/*    */     //   463: aload_1
/*    */     //   464: aload_0
/*    */     //   465: aload_1
/*    */     //   466: aload_0
/*    */     //   467: getfield ec0 : Lf/Un;
/*    */     //   470: iconst_0
/*    */     //   471: swap
/*    */     //   472: aastore
/*    */     //   473: getfield Au : Lf/Un;
/*    */     //   476: iconst_1
/*    */     //   477: swap
/*    */     //   478: aastore
/*    */     //   479: getfield JB : Lf/Un;
/*    */     //   482: iconst_2
/*    */     //   483: swap
/*    */     //   484: aastore
/*    */     //   485: invokevirtual AUX : ([Lf/JG0;)Lf/U90;
/*    */     //   488: invokevirtual ee0 : (Lf/U90;)Lf/U90;
/*    */     //   491: pop
/*    */     //   492: getfield jd0 : Lf/Ip;
/*    */     //   495: invokevirtual xh : ()Lf/U90;
/*    */     //   498: aload_0
/*    */     //   499: getfield jd0 : Lf/Ip;
/*    */     //   502: iconst_3
/*    */     //   503: anewarray f/JG0
/*    */     //   506: dup
/*    */     //   507: dup
/*    */     //   508: astore_1
/*    */     //   509: aload_0
/*    */     //   510: aload_1
/*    */     //   511: aload_0
/*    */     //   512: aload_1
/*    */     //   513: aload_0
/*    */     //   514: getfield ec0 : Lf/Un;
/*    */     //   517: iconst_0
/*    */     //   518: swap
/*    */     //   519: aastore
/*    */     //   520: getfield Au : Lf/Un;
/*    */     //   523: iconst_1
/*    */     //   524: swap
/*    */     //   525: aastore
/*    */     //   526: getfield JB : Lf/Un;
/*    */     //   529: iconst_2
/*    */     //   530: swap
/*    */     //   531: aastore
/*    */     //   532: invokevirtual vo0 : ([Lf/JG0;)Lf/U90;
/*    */     //   535: invokevirtual ee0 : (Lf/U90;)Lf/U90;
/*    */     //   538: pop
/*    */     //   539: getfield XA : Lf/Wr;
/*    */     //   542: aload_0
/*    */     //   543: getfield jd0 : Lf/Ip;
/*    */     //   546: invokevirtual J8 : (Lf/JG0;)V
/*    */     //   549: getfield XA : Lf/Wr;
/*    */     //   552: invokevirtual J8 : (Lf/JG0;)V
/*    */     //   555: return } private void Z2(ro paramro) { // Byte code:
/*    */     //   0: aload_0
/*    */     //   1: dup
/*    */     //   2: new f/VH
/*    */     //   5: dup
/*    */     //   6: dup
/*    */     //   7: astore_2
/*    */     //   8: aload_0
/*    */     //   9: aload_1
/*    */     //   10: sipush #1066
/*    */     //   13: istore_0
/*    */     //   14: bipush #16
/*    */     //   16: istore_1
/*    */     //   17: <illegal opcode> Bn : (Lf/BX;Lf/ro;)Lf/Tx;
/*    */     //   22: astore_3
/*    */     //   23: iload_0
/*    */     //   24: invokestatic OH0 : (I)Ljava/lang/String;
/*    */     //   27: iload_1
/*    */     //   28: aload_3
/*    */     //   29: invokespecial <init> : (Ljava/lang/String;ILf/Tx;)V
/*    */     //   32: getfield Hl : Lf/of;
/*    */     //   35: dup
/*    */     //   36: dup
/*    */     //   37: bipush #16
/*    */     //   39: putfield mK0 : I
/*    */     //   42: ldc_w '[a-zA-Z]'
/*    */     //   45: invokevirtual Lpt5 : (Ljava/lang/String;)V
/*    */     //   48: iconst_1
/*    */     //   49: putfield n00 : Z
/*    */     //   52: invokevirtual Ub : ()I
/*    */     //   55: aload_2
/*    */     //   56: swap
/*    */     //   57: invokevirtual si : (Lf/JG0;I)V
/*    */     //   60: return
/*    */     // Line number table:
/*    */     //   Java source line number -> byte code offset
/*    */     //   #1	-> 24
/*    */     //   #2	-> 32
/*    */     //   #3	-> 39
/*    */     //   #4	-> 42
/*    */     //   #5	-> 49
/*  4 */     //   #6	-> 52 } private void Rg0(ro paramro, String paramString) { for (Iterator<T60> iterator = paramro.sE.iterator(); iterator.hasNext();) { if ((t60 = iterator.next()).lpT3.tu
/*  5 */         .equalsIgnoreCase(paramString)) { WF(t60); return; }  }  km.u4.b00(Ml0.OH0(6015)); } public final void WF(T60 paramT60) { // Byte code:
/*    */     //   0: aload_0
/*    */     //   1: dup
/*    */     //   2: sipush #1068
/*    */     //   5: invokestatic OH0 : (I)Ljava/lang/String;
/*    */     //   8: astore_0
/*    */     //   9: iconst_2
/*    */     //   10: anewarray java/lang/String
/*    */     //   13: dup
/*    */     //   14: dup
/*    */     //   15: astore_2
/*    */     //   16: aload_1
/*    */     //   17: getfield lpT3 : Lf/fH0;
/*    */     //   20: getfield tu : Ljava/lang/String;
/*    */     //   23: iconst_0
/*    */     //   24: swap
/*    */     //   25: aastore
/*    */     //   26: iconst_1
/*    */     //   27: aload_0
/*    */     //   28: aastore
/*    */     //   29: sipush #1067
/*    */     //   32: aload_2
/*    */     //   33: invokestatic sB : (I[Ljava/lang/String;)Ljava/lang/String;
/*    */     //   36: astore_2
/*    */     //   37: new f/kB0
/*    */     //   40: dup
/*    */     //   41: astore_3
/*    */     //   42: aload_2
/*    */     //   43: aload_0
/*    */     //   44: aload_1
/*    */     //   45: <illegal opcode> Bn : (Ljava/lang/String;Lf/T60;)Lf/Tx;
/*    */     //   50: aload_0
/*    */     //   51: swap
/*    */     //   52: invokespecial <init> : (Ljava/lang/String;Ljava/lang/String;Lf/Tx;)V
/*    */     //   55: invokevirtual Ub : ()I
/*    */     //   58: aload_3
/*    */     //   59: swap
/*    */     //   60: invokevirtual si : (Lf/JG0;I)V
/*    */     //   63: return
/*    */     // Line number table:
/*    */     //   Java source line number -> byte code offset
/*    */     //   #1	-> 17
/*    */     //   #2	-> 20
/*    */     //   #3	-> 25
/*  5 */     //   #4	-> 55 } public final boolean i2(oa0 paramoa0) { ys0[] arrayOfYs0; boolean bool; if (bool = super.i2(paramoa0)) return true;  if (B8.Wm0(paramoa0.cz0) && paramoa0.oO()) { int i; if (h1.J20(i = paramoa0.GG0, BM.Oq)) { this.Cs--; VA0.c90(Fy()); return true; }
/*  6 */        if (h1.J20(i, BM.M8)) { this.Cs++;
/*  7 */         VA0.c90(Fy()); return true; }
/*  8 */        if (h1.J20(i, BM.N70)) { if ((i = this.Cs) < (arrayOfYs0 = this.Yp).length) { this.Cs = arrayOfYs0.length; } else { this.Cs = i + 1; }
/*  9 */          VA0.c90(Fy()); return true; }
/* 10 */        if (h1.J20(i, BM.ni)) { if ((i = this.Cs) <= this.Yp.length) { this.Cs = 0; } else { this.Cs = i - 1; }
/* 11 */          VA0.c90(Fy()); return true; }
/* 12 */        if (h1.J20(i, BM.bC))
/*    */       
/*    */       { 
/* 15 */         hm.Fz0((Fy()).TG0.oh0); return true; }  }  return arrayOfYs0; }
/*    */ 
/*    */   
/*    */   public final void LM(throws paramthrows) {
/*    */     if (Fl0.NM)
/*    */       UB0.Kg0.fN(new lv(this)); 
/*    */   }
/*    */   
/*    */   public final Un Fy() {
/*    */     if (this.Cs < 0)
/*    */       this.Cs = 0; 
/*    */     int i;
/*    */     ys0[] arrayOfYs0;
/*    */     if ((i = this.Cs) < (arrayOfYs0 = this.Yp).length)
/*    */       return arrayOfYs0[i]; 
/*    */     if (i == arrayOfYs0.length)
/*    */       return this.ec0; 
/*    */     Un un;
/*    */     if ((un = this.Au) != null) {
/*    */       if (i == arrayOfYs0.length + 1)
/*    */         return un; 
/*    */       if (i > arrayOfYs0.length + 1) {
/*    */         this.Cs = arrayOfYs0.length + 2;
/*    */         return this.JB;
/*    */       } 
/*    */       return this.JB;
/*    */     } 
/*    */     if (i > arrayOfYs0.length + 1)
/*    */       this.Cs = arrayOfYs0.length + 1; 
/*    */     return this.JB;
/*    */   }
/*    */   
/*    */   public final void d40() {
/*    */     this.XA.mM();
/*    */     int i = this.fr0.RS();
/*    */     i = this.fr0.e3();
/*    */     this.XA.ME(JO.Se0(this.fr0.qF(), this.XA.xY, 2, i), (this.fr0.Hy() - this.XA.HC) / 2 + i);
/*    */   } }


/* Location:              /Users/vnnsnnt/Documents/Codespace/JavaWorkspace/RedTrainer/src/main/java/org/trainer/client/PokeMMO.jar!/f/BX.class
 * Java compiler version: 8 (52.0)
 * JD-Core Version:       1.1.3
 */