/*    */ package f;public final class Bx0 extends Qa0 implements r60 { public final Ip l4; public final JG0 Aa; public final Q90 rD0; private void uC(dQ paramdQ) { int i;
/*  2 */     if ((i = this.tr.Wa0.go) != 0) { paramdQ
/*  3 */         .E1(rG0.Em0(nV.ko0[i - 1])); } else { paramdQ.E1(""); }  } public final Y FU; public W1 tr; public Rm[] ML0; public Bx0(Y paramY, Q90 paramQ90) { // Byte code:
/*    */     //   0: aload_0
/*    */     //   1: aload_1
/*    */     //   2: aload_0
/*    */     //   3: aload_2
/*    */     //   4: aload_0
/*    */     //   5: dup
/*    */     //   6: dup2
/*    */     //   7: iconst_0
/*    */     //   8: iconst_0
/*    */     //   9: invokespecial <init> : (ZZ)V
/*    */     //   12: aconst_null
/*    */     //   13: putfield tr : Lf/W1;
/*    */     //   16: ldc 'confirm-widget'
/*    */     //   18: invokevirtual Xu : (Ljava/lang/String;)V
/*    */     //   21: aconst_null
/*    */     //   22: putfield Aa : Lf/JG0;
/*    */     //   25: putfield rD0 : Lf/Q90;
/*    */     //   28: putfield FU : Lf/Y;
/*    */     //   31: new f/Ip
/*    */     //   34: dup
/*    */     //   35: dup2
/*    */     //   36: astore_1
/*    */     //   37: aload_0
/*    */     //   38: aload_1
/*    */     //   39: dup
/*    */     //   40: invokespecial <init> : ()V
/*    */     //   43: putfield l4 : Lf/Ip;
/*    */     //   46: ldc 'confirm-panel'
/*    */     //   48: invokevirtual Xu : (Ljava/lang/String;)V
/*    */     //   51: new f/dQ
/*    */     //   54: dup
/*    */     //   55: astore_3
/*    */     //   56: aload_1
/*    */     //   57: dup
/*    */     //   58: dup2
/*    */     //   59: aload_3
/*    */     //   60: dup
/*    */     //   61: invokespecial <init> : ()V
/*    */     //   64: ldc 'label-title'
/*    */     //   66: invokevirtual E1 : (Ljava/lang/String;)V
/*    */     //   69: iconst_1
/*    */     //   70: anewarray f/JG0
/*    */     //   73: dup
/*    */     //   74: iconst_0
/*    */     //   75: aload_3
/*    */     //   76: aastore
/*    */     //   77: invokevirtual vo0 : ([Lf/JG0;)Lf/U90;
/*    */     //   80: invokevirtual WN : (Lf/U90;)V
/*    */     //   83: iconst_1
/*    */     //   84: anewarray f/JG0
/*    */     //   87: dup
/*    */     //   88: iconst_0
/*    */     //   89: aload_3
/*    */     //   90: aastore
/*    */     //   91: invokevirtual AUX : ([Lf/JG0;)Lf/U90;
/*    */     //   94: invokevirtual rK0 : (Lf/U90;)V
/*    */     //   97: sipush #5613
/*    */     //   100: invokestatic OH0 : (I)Ljava/lang/String;
/*    */     //   103: invokevirtual E1 : (Ljava/lang/String;)V
/*    */     //   106: invokestatic v30 : ()Lf/On;
/*    */     //   109: aload_2
/*    */     //   110: invokevirtual u60 : ()S
/*    */     //   113: invokevirtual lpT3 : (S)Lf/UD0;
/*    */     //   116: astore_1
/*    */     //   117: new f/dQ
/*    */     //   120: dup
/*    */     //   121: astore_3
/*    */     //   122: new java/lang/StringBuilder
/*    */     //   125: dup
/*    */     //   126: astore #4
/*    */     //   128: invokespecial <init> : ()V
/*    */     //   131: bipush #59
/*    */     //   133: aload #4
/*    */     //   135: ldc ' '
/*    */     //   137: invokestatic X9 : (ILjava/lang/StringBuilder;Ljava/lang/String;)Ljava/lang/StringBuilder;
/*    */     //   140: aload_2
/*    */     //   141: invokevirtual Y20 : ()B
/*    */     //   144: invokevirtual append : (I)Ljava/lang/StringBuilder;
/*    */     //   147: ldc ' '
/*    */     //   149: invokevirtual append : (Ljava/lang/String;)Ljava/lang/StringBuilder;
/*    */     //   152: aload_1
/*    */     //   153: invokevirtual wp : ()Ljava/lang/String;
/*    */     //   156: invokevirtual append : (Ljava/lang/String;)Ljava/lang/StringBuilder;
/*    */     //   159: invokevirtual toString : ()Ljava/lang/String;
/*    */     //   162: invokespecial <init> : (Ljava/lang/String;)V
/*    */     //   165: invokevirtual xh : ()Lf/U90;
/*    */     //   168: aload_3
/*    */     //   169: invokevirtual Ya : (Lf/JG0;)Lf/U90;
/*    */     //   172: pop
/*    */     //   173: invokevirtual iJ0 : ()Lf/U90;
/*    */     //   176: aload_3
/*    */     //   177: invokevirtual Ya : (Lf/JG0;)Lf/U90;
/*    */     //   180: pop
/*    */     //   181: new f/dQ
/*    */     //   184: dup
/*    */     //   185: astore_1
/*    */     //   186: sipush #8106
/*    */     //   189: invokestatic OH0 : (I)Ljava/lang/String;
/*    */     //   192: invokespecial <init> : (Ljava/lang/String;)V
/*    */     //   195: new f/dQ
/*    */     //   198: dup
/*    */     //   199: astore_3
/*    */     //   200: ldc ''
/*    */     //   202: invokespecial <init> : (Ljava/lang/String;)V
/*    */     //   205: getstatic f/nV.ko0 : [Lf/nV;
/*    */     //   208: dup
/*    */     //   209: dup
/*    */     //   210: astore #4
/*    */     //   212: arraylength
/*    */     //   213: iconst_1
/*    */     //   214: iadd
/*    */     //   215: anewarray java/lang/String
/*    */     //   218: dup
/*    */     //   219: astore #5
/*    */     //   221: iconst_0
/*    */     //   222: ldc '-'
/*    */     //   224: aastore
/*    */     //   225: arraylength
/*    */     //   226: istore #6
/*    */     //   228: iconst_0
/*    */     //   229: istore #7
/*    */     //   231: iload #7
/*    */     //   233: iload #6
/*    */     //   235: if_icmpge -> 266
/*    */     //   238: aload #5
/*    */     //   240: aload #4
/*    */     //   242: iload #7
/*    */     //   244: aaload
/*    */     //   245: dup
/*    */     //   246: invokevirtual LPt8 : ()B
/*    */     //   249: iconst_1
/*    */     //   250: iadd
/*    */     //   251: istore #8
/*    */     //   253: invokevirtual cK0 : ()Ljava/lang/String;
/*    */     //   256: iload #8
/*    */     //   258: swap
/*    */     //   259: aastore
/*    */     //   260: iinc #7, 1
/*    */     //   263: goto -> 231
/*    */     //   266: aload_0
/*    */     //   267: dup
/*    */     //   268: dup2
/*    */     //   269: dup2
/*    */     //   270: dup2
/*    */     //   271: new f/OZ
/*    */     //   274: dup
/*    */     //   275: astore #4
/*    */     //   277: aload #5
/*    */     //   279: invokespecial <init> : ([Ljava/lang/Object;)V
/*    */     //   282: new f/W1
/*    */     //   285: dup
/*    */     //   286: aload_0
/*    */     //   287: swap
/*    */     //   288: dup
/*    */     //   289: aload #4
/*    */     //   291: invokespecial <init> : (Lf/cQ;)V
/*    */     //   294: putfield tr : Lf/W1;
/*    */     //   297: iconst_0
/*    */     //   298: invokevirtual Z30 : (I)V
/*    */     //   301: getfield tr : Lf/W1;
/*    */     //   304: aload_0
/*    */     //   305: aload_3
/*    */     //   306: <illegal opcode> run : (Lf/Bx0;Lf/dQ;)Ljava/lang/Runnable;
/*    */     //   311: invokevirtual D30 : (Ljava/lang/Runnable;)V
/*    */     //   314: getfield l4 : Lf/Ip;
/*    */     //   317: invokevirtual xh : ()Lf/U90;
/*    */     //   320: aload_0
/*    */     //   321: getfield l4 : Lf/Ip;
/*    */     //   324: invokevirtual mE0 : ()Lf/g0;
/*    */     //   327: iconst_2
/*    */     //   328: anewarray f/JG0
/*    */     //   331: dup
/*    */     //   332: dup
/*    */     //   333: aload_0
/*    */     //   334: swap
/*    */     //   335: iconst_0
/*    */     //   336: aload_1
/*    */     //   337: aastore
/*    */     //   338: getfield tr : Lf/W1;
/*    */     //   341: iconst_1
/*    */     //   342: swap
/*    */     //   343: aastore
/*    */     //   344: invokevirtual Mg : ([Lf/JG0;)Lf/U90;
/*    */     //   347: invokevirtual ee0 : (Lf/U90;)Lf/U90;
/*    */     //   350: pop
/*    */     //   351: getfield l4 : Lf/Ip;
/*    */     //   354: invokevirtual iJ0 : ()Lf/U90;
/*    */     //   357: aload_0
/*    */     //   358: getfield l4 : Lf/Ip;
/*    */     //   361: invokevirtual d7 : ()Lf/cr0;
/*    */     //   364: aload_1
/*    */     //   365: invokevirtual Ya : (Lf/JG0;)Lf/U90;
/*    */     //   368: invokevirtual Em0 : ()Lf/U90;
/*    */     //   371: aload_0
/*    */     //   372: getfield tr : Lf/W1;
/*    */     //   375: invokevirtual Ya : (Lf/JG0;)Lf/U90;
/*    */     //   378: invokevirtual ee0 : (Lf/U90;)Lf/U90;
/*    */     //   381: pop
/*    */     //   382: getfield l4 : Lf/Ip;
/*    */     //   385: invokevirtual xh : ()Lf/U90;
/*    */     //   388: aload_3
/*    */     //   389: invokevirtual Ya : (Lf/JG0;)Lf/U90;
/*    */     //   392: pop
/*    */     //   393: getfield l4 : Lf/Ip;
/*    */     //   396: invokevirtual iJ0 : ()Lf/U90;
/*    */     //   399: aload_3
/*    */     //   400: invokevirtual Ya : (Lf/JG0;)Lf/U90;
/*    */     //   403: pop
/*    */     //   404: new f/dQ
/*    */     //   407: dup
/*    */     //   408: astore_1
/*    */     //   409: sipush #1800
/*    */     //   412: invokestatic OH0 : (I)Ljava/lang/String;
/*    */     //   415: invokespecial <init> : (Ljava/lang/String;)V
/*    */     //   418: getfield l4 : Lf/Ip;
/*    */     //   421: invokevirtual xh : ()Lf/U90;
/*    */     //   424: aload_1
/*    */     //   425: invokevirtual Ya : (Lf/JG0;)Lf/U90;
/*    */     //   428: pop
/*    */     //   429: getfield l4 : Lf/Ip;
/*    */     //   432: invokevirtual iJ0 : ()Lf/U90;
/*    */     //   435: aload_1
/*    */     //   436: invokevirtual Ya : (Lf/JG0;)Lf/U90;
/*    */     //   439: pop
/*    */     //   440: bipush #6
/*    */     //   442: anewarray f/dQ
/*    */     //   445: astore_1
/*    */     //   446: bipush #6
/*    */     //   448: anewarray f/Rm
/*    */     //   451: putfield ML0 : [Lf/Rm;
/*    */     //   454: iconst_0
/*    */     //   455: istore_3
/*    */     //   456: iload_3
/*    */     //   457: getstatic f/hR.Tm0 : [Lf/hR;
/*    */     //   460: dup
/*    */     //   461: astore #4
/*    */     //   463: arraylength
/*    */     //   464: if_icmpge -> 558
/*    */     //   467: aload_0
/*    */     //   468: dup
/*    */     //   469: aload #4
/*    */     //   471: iload_3
/*    */     //   472: aaload
/*    */     //   473: astore #4
/*    */     //   475: new f/dQ
/*    */     //   478: dup
/*    */     //   479: astore #5
/*    */     //   481: aload_1
/*    */     //   482: iload_3
/*    */     //   483: aload #5
/*    */     //   485: aload #4
/*    */     //   487: invokevirtual toString : ()Ljava/lang/String;
/*    */     //   490: invokespecial <init> : (Ljava/lang/String;)V
/*    */     //   493: aload #5
/*    */     //   495: aastore
/*    */     //   496: ldc 'label-title'
/*    */     //   498: invokevirtual Xu : (Ljava/lang/String;)V
/*    */     //   501: new f/zT
/*    */     //   504: dup
/*    */     //   505: astore #5
/*    */     //   507: aload_2
/*    */     //   508: aload #4
/*    */     //   510: invokevirtual Uu0 : (Lf/hR;)S
/*    */     //   513: istore #4
/*    */     //   515: iconst_0
/*    */     //   516: sipush #252
/*    */     //   519: iload #4
/*    */     //   521: invokespecial <init> : (III)V
/*    */     //   524: getfield ML0 : [Lf/Rm;
/*    */     //   527: iload_3
/*    */     //   528: new f/Rm
/*    */     //   531: dup
/*    */     //   532: astore #4
/*    */     //   534: aload #5
/*    */     //   536: invokespecial <init> : (Lf/zT;)V
/*    */     //   539: aload #4
/*    */     //   541: aastore
/*    */     //   542: getfield ML0 : [Lf/Rm;
/*    */     //   545: iload_3
/*    */     //   546: aaload
/*    */     //   547: ldc 'valueadjuster-small'
/*    */     //   549: invokevirtual Xu : (Ljava/lang/String;)V
/*    */     //   552: iinc #3, 1
/*    */     //   555: goto -> 456
/*    */     //   558: aload_0
/*    */     //   559: dup
/*    */     //   560: dup2
/*    */     //   561: dup2
/*    */     //   562: dup2
/*    */     //   563: dup2
/*    */     //   564: getfield l4 : Lf/Ip;
/*    */     //   567: invokevirtual d7 : ()Lf/cr0;
/*    */     //   570: aload_0
/*    */     //   571: getfield l4 : Lf/Ip;
/*    */     //   574: invokevirtual mE0 : ()Lf/g0;
/*    */     //   577: iconst_2
/*    */     //   578: anewarray f/JG0
/*    */     //   581: dup
/*    */     //   582: dup
/*    */     //   583: aload_0
/*    */     //   584: swap
/*    */     //   585: aload_1
/*    */     //   586: iconst_0
/*    */     //   587: aaload
/*    */     //   588: iconst_0
/*    */     //   589: swap
/*    */     //   590: aastore
/*    */     //   591: getfield ML0 : [Lf/Rm;
/*    */     //   594: iconst_0
/*    */     //   595: aaload
/*    */     //   596: iconst_1
/*    */     //   597: swap
/*    */     //   598: aastore
/*    */     //   599: invokevirtual Mg : ([Lf/JG0;)Lf/U90;
/*    */     //   602: invokevirtual ee0 : (Lf/U90;)Lf/U90;
/*    */     //   605: aload_0
/*    */     //   606: getfield l4 : Lf/Ip;
/*    */     //   609: invokevirtual mE0 : ()Lf/g0;
/*    */     //   612: iconst_2
/*    */     //   613: anewarray f/JG0
/*    */     //   616: dup
/*    */     //   617: dup
/*    */     //   618: aload_0
/*    */     //   619: swap
/*    */     //   620: aload_1
/*    */     //   621: iconst_1
/*    */     //   622: aaload
/*    */     //   623: iconst_0
/*    */     //   624: swap
/*    */     //   625: aastore
/*    */     //   626: getfield ML0 : [Lf/Rm;
/*    */     //   629: iconst_1
/*    */     //   630: aaload
/*    */     //   631: iconst_1
/*    */     //   632: swap
/*    */     //   633: aastore
/*    */     //   634: invokevirtual Mg : ([Lf/JG0;)Lf/U90;
/*    */     //   637: invokevirtual ee0 : (Lf/U90;)Lf/U90;
/*    */     //   640: aload_0
/*    */     //   641: getfield l4 : Lf/Ip;
/*    */     //   644: invokevirtual mE0 : ()Lf/g0;
/*    */     //   647: iconst_2
/*    */     //   648: anewarray f/JG0
/*    */     //   651: dup
/*    */     //   652: dup
/*    */     //   653: aload_0
/*    */     //   654: swap
/*    */     //   655: aload_1
/*    */     //   656: iconst_2
/*    */     //   657: aaload
/*    */     //   658: iconst_0
/*    */     //   659: swap
/*    */     //   660: aastore
/*    */     //   661: getfield ML0 : [Lf/Rm;
/*    */     //   664: iconst_2
/*    */     //   665: aaload
/*    */     //   666: iconst_1
/*    */     //   667: swap
/*    */     //   668: aastore
/*    */     //   669: invokevirtual Mg : ([Lf/JG0;)Lf/U90;
/*    */     //   672: invokevirtual ee0 : (Lf/U90;)Lf/U90;
/*    */     //   675: aload_0
/*    */     //   676: getfield l4 : Lf/Ip;
/*    */     //   679: invokevirtual mE0 : ()Lf/g0;
/*    */     //   682: iconst_2
/*    */     //   683: anewarray f/JG0
/*    */     //   686: dup
/*    */     //   687: dup
/*    */     //   688: aload_0
/*    */     //   689: swap
/*    */     //   690: aload_1
/*    */     //   691: iconst_3
/*    */     //   692: aaload
/*    */     //   693: iconst_0
/*    */     //   694: swap
/*    */     //   695: aastore
/*    */     //   696: getfield ML0 : [Lf/Rm;
/*    */     //   699: iconst_3
/*    */     //   700: aaload
/*    */     //   701: iconst_1
/*    */     //   702: swap
/*    */     //   703: aastore
/*    */     //   704: invokevirtual Mg : ([Lf/JG0;)Lf/U90;
/*    */     //   707: invokevirtual ee0 : (Lf/U90;)Lf/U90;
/*    */     //   710: aload_0
/*    */     //   711: getfield l4 : Lf/Ip;
/*    */     //   714: invokevirtual mE0 : ()Lf/g0;
/*    */     //   717: iconst_2
/*    */     //   718: anewarray f/JG0
/*    */     //   721: dup
/*    */     //   722: dup
/*    */     //   723: aload_0
/*    */     //   724: swap
/*    */     //   725: aload_1
/*    */     //   726: iconst_4
/*    */     //   727: aaload
/*    */     //   728: iconst_0
/*    */     //   729: swap
/*    */     //   730: aastore
/*    */     //   731: getfield ML0 : [Lf/Rm;
/*    */     //   734: iconst_4
/*    */     //   735: aaload
/*    */     //   736: iconst_1
/*    */     //   737: swap
/*    */     //   738: aastore
/*    */     //   739: invokevirtual Mg : ([Lf/JG0;)Lf/U90;
/*    */     //   742: invokevirtual ee0 : (Lf/U90;)Lf/U90;
/*    */     //   745: aload_0
/*    */     //   746: getfield l4 : Lf/Ip;
/*    */     //   749: invokevirtual mE0 : ()Lf/g0;
/*    */     //   752: iconst_2
/*    */     //   753: anewarray f/JG0
/*    */     //   756: dup
/*    */     //   757: dup
/*    */     //   758: aload_0
/*    */     //   759: swap
/*    */     //   760: aload_1
/*    */     //   761: iconst_5
/*    */     //   762: aaload
/*    */     //   763: iconst_0
/*    */     //   764: swap
/*    */     //   765: aastore
/*    */     //   766: getfield ML0 : [Lf/Rm;
/*    */     //   769: iconst_5
/*    */     //   770: aaload
/*    */     //   771: iconst_1
/*    */     //   772: swap
/*    */     //   773: aastore
/*    */     //   774: invokevirtual Mg : ([Lf/JG0;)Lf/U90;
/*    */     //   777: invokevirtual ee0 : (Lf/U90;)Lf/U90;
/*    */     //   780: astore_2
/*    */     //   781: getfield l4 : Lf/Ip;
/*    */     //   784: invokevirtual mE0 : ()Lf/g0;
/*    */     //   787: aload_0
/*    */     //   788: getfield l4 : Lf/Ip;
/*    */     //   791: invokevirtual d7 : ()Lf/cr0;
/*    */     //   794: aload_1
/*    */     //   795: iconst_0
/*    */     //   796: aaload
/*    */     //   797: invokevirtual Ya : (Lf/JG0;)Lf/U90;
/*    */     //   800: invokevirtual Em0 : ()Lf/U90;
/*    */     //   803: iconst_1
/*    */     //   804: anewarray f/JG0
/*    */     //   807: dup
/*    */     //   808: aload_0
/*    */     //   809: getfield ML0 : [Lf/Rm;
/*    */     //   812: iconst_0
/*    */     //   813: aaload
/*    */     //   814: iconst_0
/*    */     //   815: swap
/*    */     //   816: aastore
/*    */     //   817: invokevirtual Mg : ([Lf/JG0;)Lf/U90;
/*    */     //   820: invokevirtual ee0 : (Lf/U90;)Lf/U90;
/*    */     //   823: aload_0
/*    */     //   824: getfield l4 : Lf/Ip;
/*    */     //   827: invokevirtual d7 : ()Lf/cr0;
/*    */     //   830: aload_1
/*    */     //   831: iconst_1
/*    */     //   832: aaload
/*    */     //   833: invokevirtual Ya : (Lf/JG0;)Lf/U90;
/*    */     //   836: invokevirtual Em0 : ()Lf/U90;
/*    */     //   839: iconst_1
/*    */     //   840: anewarray f/JG0
/*    */     //   843: dup
/*    */     //   844: aload_0
/*    */     //   845: getfield ML0 : [Lf/Rm;
/*    */     //   848: iconst_1
/*    */     //   849: aaload
/*    */     //   850: iconst_0
/*    */     //   851: swap
/*    */     //   852: aastore
/*    */     //   853: invokevirtual Mg : ([Lf/JG0;)Lf/U90;
/*    */     //   856: invokevirtual ee0 : (Lf/U90;)Lf/U90;
/*    */     //   859: aload_0
/*    */     //   860: getfield l4 : Lf/Ip;
/*    */     //   863: invokevirtual d7 : ()Lf/cr0;
/*    */     //   866: aload_1
/*    */     //   867: iconst_2
/*    */     //   868: aaload
/*    */     //   869: invokevirtual Ya : (Lf/JG0;)Lf/U90;
/*    */     //   872: invokevirtual Em0 : ()Lf/U90;
/*    */     //   875: iconst_1
/*    */     //   876: anewarray f/JG0
/*    */     //   879: dup
/*    */     //   880: aload_0
/*    */     //   881: getfield ML0 : [Lf/Rm;
/*    */     //   884: iconst_2
/*    */     //   885: aaload
/*    */     //   886: iconst_0
/*    */     //   887: swap
/*    */     //   888: aastore
/*    */     //   889: invokevirtual Mg : ([Lf/JG0;)Lf/U90;
/*    */     //   892: invokevirtual ee0 : (Lf/U90;)Lf/U90;
/*    */     //   895: aload_0
/*    */     //   896: getfield l4 : Lf/Ip;
/*    */     //   899: invokevirtual d7 : ()Lf/cr0;
/*    */     //   902: aload_1
/*    */     //   903: iconst_3
/*    */     //   904: aaload
/*    */     //   905: invokevirtual Ya : (Lf/JG0;)Lf/U90;
/*    */     //   908: invokevirtual Em0 : ()Lf/U90;
/*    */     //   911: iconst_1
/*    */     //   912: anewarray f/JG0
/*    */     //   915: dup
/*    */     //   916: aload_0
/*    */     //   917: getfield ML0 : [Lf/Rm;
/*    */     //   920: iconst_3
/*    */     //   921: aaload
/*    */     //   922: iconst_0
/*    */     //   923: swap
/*    */     //   924: aastore
/*    */     //   925: invokevirtual Mg : ([Lf/JG0;)Lf/U90;
/*    */     //   928: invokevirtual ee0 : (Lf/U90;)Lf/U90;
/*    */     //   931: aload_0
/*    */     //   932: getfield l4 : Lf/Ip;
/*    */     //   935: invokevirtual d7 : ()Lf/cr0;
/*    */     //   938: aload_1
/*    */     //   939: iconst_4
/*    */     //   940: aaload
/*    */     //   941: invokevirtual Ya : (Lf/JG0;)Lf/U90;
/*    */     //   944: invokevirtual Em0 : ()Lf/U90;
/*    */     //   947: iconst_1
/*    */     //   948: anewarray f/JG0
/*    */     //   951: dup
/*    */     //   952: aload_0
/*    */     //   953: getfield ML0 : [Lf/Rm;
/*    */     //   956: iconst_4
/*    */     //   957: aaload
/*    */     //   958: iconst_0
/*    */     //   959: swap
/*    */     //   960: aastore
/*    */     //   961: invokevirtual Mg : ([Lf/JG0;)Lf/U90;
/*    */     //   964: invokevirtual ee0 : (Lf/U90;)Lf/U90;
/*    */     //   967: aload_0
/*    */     //   968: getfield l4 : Lf/Ip;
/*    */     //   971: invokevirtual d7 : ()Lf/cr0;
/*    */     //   974: aload_1
/*    */     //   975: iconst_5
/*    */     //   976: aaload
/*    */     //   977: invokevirtual Ya : (Lf/JG0;)Lf/U90;
/*    */     //   980: invokevirtual Em0 : ()Lf/U90;
/*    */     //   983: iconst_1
/*    */     //   984: anewarray f/JG0
/*    */     //   987: dup
/*    */     //   988: aload_0
/*    */     //   989: getfield ML0 : [Lf/Rm;
/*    */     //   992: iconst_5
/*    */     //   993: aaload
/*    */     //   994: iconst_0
/*    */     //   995: swap
/*    */     //   996: aastore
/*    */     //   997: invokevirtual Mg : ([Lf/JG0;)Lf/U90;
/*    */     //   1000: invokevirtual ee0 : (Lf/U90;)Lf/U90;
/*    */     //   1003: astore_1
/*    */     //   1004: getfield l4 : Lf/Ip;
/*    */     //   1007: invokevirtual xh : ()Lf/U90;
/*    */     //   1010: aload_2
/*    */     //   1011: invokevirtual ee0 : (Lf/U90;)Lf/U90;
/*    */     //   1014: pop
/*    */     //   1015: getfield l4 : Lf/Ip;
/*    */     //   1018: invokevirtual iJ0 : ()Lf/U90;
/*    */     //   1021: aload_1
/*    */     //   1022: invokevirtual ee0 : (Lf/U90;)Lf/U90;
/*    */     //   1025: pop
/*    */     //   1026: new f/Un
/*    */     //   1029: dup
/*    */     //   1030: astore_1
/*    */     //   1031: aload_0
/*    */     //   1032: aload_1
/*    */     //   1033: bipush #52
/*    */     //   1035: invokestatic OH0 : (I)Ljava/lang/String;
/*    */     //   1038: invokespecial <init> : (Ljava/lang/String;)V
/*    */     //   1041: <illegal opcode> run : (Lf/Bx0;)Ljava/lang/Runnable;
/*    */     //   1046: invokevirtual tW : (Ljava/lang/Runnable;)V
/*    */     //   1049: getfield l4 : Lf/Ip;
/*    */     //   1052: invokevirtual xh : ()Lf/U90;
/*    */     //   1055: aload_1
/*    */     //   1056: invokevirtual Ya : (Lf/JG0;)Lf/U90;
/*    */     //   1059: pop
/*    */     //   1060: getfield l4 : Lf/Ip;
/*    */     //   1063: invokevirtual iJ0 : ()Lf/U90;
/*    */     //   1066: aload_1
/*    */     //   1067: invokevirtual Ya : (Lf/JG0;)Lf/U90;
/*    */     //   1070: pop
/*    */     //   1071: new f/Un
/*    */     //   1074: dup
/*    */     //   1075: astore_1
/*    */     //   1076: aload_0
/*    */     //   1077: aload_1
/*    */     //   1078: bipush #53
/*    */     //   1080: invokestatic OH0 : (I)Ljava/lang/String;
/*    */     //   1083: invokespecial <init> : (Ljava/lang/String;)V
/*    */     //   1086: <illegal opcode> run : (Lf/Bx0;)Ljava/lang/Runnable;
/*    */     //   1091: invokevirtual tW : (Ljava/lang/Runnable;)V
/*    */     //   1094: getfield l4 : Lf/Ip;
/*    */     //   1097: invokevirtual xh : ()Lf/U90;
/*    */     //   1100: bipush #25
/*    */     //   1102: invokevirtual Aq : (I)Lf/U90;
/*    */     //   1105: aload_1
/*    */     //   1106: invokevirtual Ya : (Lf/JG0;)Lf/U90;
/*    */     //   1109: pop
/*    */     //   1110: getfield l4 : Lf/Ip;
/*    */     //   1113: invokevirtual iJ0 : ()Lf/U90;
/*    */     //   1116: aload_1
/*    */     //   1117: invokevirtual Ya : (Lf/JG0;)Lf/U90;
/*    */     //   1120: pop
/*    */     //   1121: getfield l4 : Lf/Ip;
/*    */     //   1124: invokevirtual J8 : (Lf/JG0;)V
/*    */     //   1127: return
/*    */     // Line number table:
/*    */     //   Java source line number -> byte code offset
/*    */     //   #1	-> 135
/*  3 */     //   #2	-> 141 } public final void hh0() { nV nV; if ((nV = nV.Y4((byte)(this.tr.Wa0.go - 1))) == null) { km.u4.Pq(Ml0.OH0(5618)); return; }  hR[] arrayOfHR; short[] arrayOfShort; int i, j; byte b; for (arrayOfShort = new short[(arrayOfHR = hR.ka).length], i = 0, j = hR.ka.length, b = 0; b < j; )
/*    */     
/*    */     { 
/*  6 */       i = (short)(this.ML0[(arrayOfHR[b]).It0]).T8;
/*  7 */       arrayOfShort[(arrayOfHR[b]).dL] = i;
/*  8 */       i += i; b++; }  if (i != 510) { km.u4.Pq(Ml0.Go(5636, "510")); return; }  this(this.rD0, nV, arrayOfShort);
/*    */     jH jH;
/* 10 */     short s = this.FU.Lh.p1;
/* 11 */     km.u4.e20
/* 12 */       .W3(new k80(s, jH));
/* 13 */     ra0(); }
/*    */ 
/*    */   
/*    */   public final void d40() {
/*    */     super.d40();
/*    */     this.l4.mM();
/*    */     QI();
/*    */     this.l4.js0(et.Wi0);
/*    */   }
/*    */   
/*    */   public final void jA0() {
/*    */     super.jA0();
/*    */     JG0 jG0;
/*    */     if ((jG0 = this.Aa) != null)
/*    */       VA0.c90(this); 
/*    */   } }


/* Location:              /Users/vnnsnnt/Documents/Codespace/JavaWorkspace/RedTrainer/src/main/java/org/trainer/client/PokeMMO.jar!/f/Bx0.class
 * Java compiler version: 8 (52.0)
 * JD-Core Version:       1.1.3
 */