/*    */ package f;
/*  2 */ public final class bZ extends Ij implements r60 { public sn0 m70; public G9 PD; public G9 NF; public Ip sb0; public static int sF(j40 paramj40) { return paramj40.Zs.Tl0; } public Un Od; public Un jH0; public xo0 break; public bZ(Y paramY) { // Byte code:
/*    */     //   0: aload_0
/*    */     //   1: dup
/*    */     //   2: dup
/*    */     //   3: invokespecial <init> : ()V
/*    */     //   6: <illegal opcode> run : (Lf/bZ;)Ljava/lang/Runnable;
/*    */     //   11: invokevirtual TG0 : (Ljava/lang/Runnable;)V
/*    */     //   14: invokestatic XU : ()Z
/*    */     //   17: ifeq -> 29
/*    */     //   20: aload_0
/*    */     //   21: ldc 'mysterious-gem'
/*    */     //   23: invokevirtual Xu : (Ljava/lang/String;)V
/*    */     //   26: goto -> 44
/*    */     //   29: aload_0
/*    */     //   30: dup
/*    */     //   31: ldc 'seed-plant-dialog'
/*    */     //   33: invokevirtual Xu : (Ljava/lang/String;)V
/*    */     //   36: ldc 101176
/*    */     //   38: invokestatic OH0 : (I)Ljava/lang/String;
/*    */     //   41: invokevirtual Lo : (Ljava/lang/String;)V
/*    */     //   44: aload_0
/*    */     //   45: dup
/*    */     //   46: dup2
/*    */     //   47: dup2
/*    */     //   48: dup2
/*    */     //   49: new f/Ip
/*    */     //   52: dup
/*    */     //   53: invokespecial <init> : ()V
/*    */     //   56: putfield sb0 : Lf/Ip;
/*    */     //   59: new f/Un
/*    */     //   62: dup
/*    */     //   63: ldc 16780461
/*    */     //   65: invokestatic OH0 : (I)Ljava/lang/String;
/*    */     //   68: invokespecial <init> : (Ljava/lang/String;)V
/*    */     //   71: putfield Od : Lf/Un;
/*    */     //   74: new f/Un
/*    */     //   77: dup
/*    */     //   78: bipush #53
/*    */     //   80: invokestatic OH0 : (I)Ljava/lang/String;
/*    */     //   83: invokespecial <init> : (Ljava/lang/String;)V
/*    */     //   86: putfield jH0 : Lf/Un;
/*    */     //   89: getfield Od : Lf/Un;
/*    */     //   92: aload_0
/*    */     //   93: <illegal opcode> run : (Lf/bZ;)Ljava/lang/Runnable;
/*    */     //   98: invokevirtual tW : (Ljava/lang/Runnable;)V
/*    */     //   101: getfield jH0 : Lf/Un;
/*    */     //   104: aload_0
/*    */     //   105: <illegal opcode> run : (Lf/bZ;)Ljava/lang/Runnable;
/*    */     //   110: invokevirtual tW : (Ljava/lang/Runnable;)V
/*    */     //   113: getfield Od : Lf/Un;
/*    */     //   116: iconst_0
/*    */     //   117: invokevirtual sk0 : (Z)V
/*    */     //   120: new f/G9
/*    */     //   123: dup
/*    */     //   124: invokespecial <init> : ()V
/*    */     //   127: putfield PD : Lf/G9;
/*    */     //   130: new f/G9
/*    */     //   133: dup
/*    */     //   134: dup
/*    */     //   135: astore_2
/*    */     //   136: invokespecial <init> : ()V
/*    */     //   139: putfield NF : Lf/G9;
/*    */     //   142: iconst_2
/*    */     //   143: dup
/*    */     //   144: istore_3
/*    */     //   145: anewarray f/G9
/*    */     //   148: dup
/*    */     //   149: dup
/*    */     //   150: astore #4
/*    */     //   152: aload_0
/*    */     //   153: getfield PD : Lf/G9;
/*    */     //   156: iconst_0
/*    */     //   157: swap
/*    */     //   158: aastore
/*    */     //   159: iconst_1
/*    */     //   160: aload_2
/*    */     //   161: aastore
/*    */     //   162: iconst_0
/*    */     //   163: istore_2
/*    */     //   164: iload_2
/*    */     //   165: iload_3
/*    */     //   166: if_icmpge -> 214
/*    */     //   169: aload #4
/*    */     //   171: iload_2
/*    */     //   172: aaload
/*    */     //   173: dup
/*    */     //   174: astore #5
/*    */     //   176: aload_0
/*    */     //   177: aload #5
/*    */     //   179: dup
/*    */     //   180: dup
/*    */     //   181: aload_0
/*    */     //   182: aload #5
/*    */     //   184: <illegal opcode> run : (Lf/bZ;Lf/G9;)Ljava/lang/Runnable;
/*    */     //   189: invokevirtual L1 : (Ljava/lang/Runnable;)V
/*    */     //   192: iconst_1
/*    */     //   193: invokevirtual wU : (Z)V
/*    */     //   196: iconst_0
/*    */     //   197: invokevirtual hC : (Z)V
/*    */     //   200: <illegal opcode> run : (Lf/bZ;)Ljava/lang/Runnable;
/*    */     //   205: invokevirtual tW : (Ljava/lang/Runnable;)V
/*    */     //   208: iinc #2, 1
/*    */     //   211: goto -> 164
/*    */     //   214: aload_0
/*    */     //   215: dup
/*    */     //   216: dup2
/*    */     //   217: dup2
/*    */     //   218: new f/sn0
/*    */     //   221: dup
/*    */     //   222: aload_0
/*    */     //   223: swap
/*    */     //   224: dup
/*    */     //   225: aload_1
/*    */     //   226: invokespecial <init> : (Lf/Y;)V
/*    */     //   229: putfield m70 : Lf/sn0;
/*    */     //   232: iconst_0
/*    */     //   233: invokevirtual sk0 : (Z)V
/*    */     //   236: getfield m70 : Lf/sn0;
/*    */     //   239: ldc 'item-slot'
/*    */     //   241: invokevirtual Xu : (Ljava/lang/String;)V
/*    */     //   244: new f/xo0
/*    */     //   247: dup
/*    */     //   248: aload_0
/*    */     //   249: swap
/*    */     //   250: dup
/*    */     //   251: ldc '\\n\\n'
/*    */     //   253: invokespecial <init> : (Ljava/lang/String;)V
/*    */     //   256: putfield break : Lf/xo0;
/*    */     //   259: iconst_0
/*    */     //   260: invokevirtual wI0 : (Z)V
/*    */     //   263: getfield sb0 : Lf/Ip;
/*    */     //   266: dup
/*    */     //   267: astore_1
/*    */     //   268: aload_0
/*    */     //   269: dup
/*    */     //   270: aload_1
/*    */     //   271: invokevirtual d7 : ()Lf/cr0;
/*    */     //   274: bipush #15
/*    */     //   276: invokevirtual Aq : (I)Lf/U90;
/*    */     //   279: astore_1
/*    */     //   280: getfield sb0 : Lf/Ip;
/*    */     //   283: invokevirtual mE0 : ()Lf/g0;
/*    */     //   286: iconst_3
/*    */     //   287: anewarray f/JG0
/*    */     //   290: dup
/*    */     //   291: dup
/*    */     //   292: astore_2
/*    */     //   293: aload_0
/*    */     //   294: aload_2
/*    */     //   295: aload_0
/*    */     //   296: aload_2
/*    */     //   297: aload_0
/*    */     //   298: getfield PD : Lf/G9;
/*    */     //   301: iconst_0
/*    */     //   302: swap
/*    */     //   303: aastore
/*    */     //   304: getfield m70 : Lf/sn0;
/*    */     //   307: iconst_1
/*    */     //   308: swap
/*    */     //   309: aastore
/*    */     //   310: getfield NF : Lf/G9;
/*    */     //   313: iconst_2
/*    */     //   314: swap
/*    */     //   315: aastore
/*    */     //   316: aload_1
/*    */     //   317: bipush #15
/*    */     //   319: invokestatic aj0 : (Lf/g0;[Lf/JG0;Lf/U90;I)Lf/U90;
/*    */     //   322: astore_1
/*    */     //   323: getfield sb0 : Lf/Ip;
/*    */     //   326: invokevirtual mE0 : ()Lf/g0;
/*    */     //   329: iconst_1
/*    */     //   330: anewarray f/JG0
/*    */     //   333: dup
/*    */     //   334: aload_0
/*    */     //   335: getfield break : Lf/xo0;
/*    */     //   338: iconst_0
/*    */     //   339: swap
/*    */     //   340: aastore
/*    */     //   341: aload_1
/*    */     //   342: bipush #15
/*    */     //   344: invokestatic aj0 : (Lf/g0;[Lf/JG0;Lf/U90;I)Lf/U90;
/*    */     //   347: aload_0
/*    */     //   348: getfield sb0 : Lf/Ip;
/*    */     //   351: invokevirtual d7 : ()Lf/cr0;
/*    */     //   354: iconst_2
/*    */     //   355: anewarray f/JG0
/*    */     //   358: dup
/*    */     //   359: dup
/*    */     //   360: aload_0
/*    */     //   361: swap
/*    */     //   362: aload_0
/*    */     //   363: getfield Od : Lf/Un;
/*    */     //   366: iconst_0
/*    */     //   367: swap
/*    */     //   368: aastore
/*    */     //   369: getfield jH0 : Lf/Un;
/*    */     //   372: iconst_1
/*    */     //   373: swap
/*    */     //   374: aastore
/*    */     //   375: invokevirtual Mg : ([Lf/JG0;)Lf/U90;
/*    */     //   378: invokevirtual ee0 : (Lf/U90;)Lf/U90;
/*    */     //   381: invokevirtual Em0 : ()Lf/U90;
/*    */     //   384: invokevirtual WN : (Lf/U90;)V
/*    */     //   387: getfield sb0 : Lf/Ip;
/*    */     //   390: dup
/*    */     //   391: invokevirtual mE0 : ()Lf/g0;
/*    */     //   394: aload_0
/*    */     //   395: getfield sb0 : Lf/Ip;
/*    */     //   398: invokevirtual d7 : ()Lf/cr0;
/*    */     //   401: invokevirtual Em0 : ()Lf/U90;
/*    */     //   404: aload_0
/*    */     //   405: getfield PD : Lf/G9;
/*    */     //   408: invokevirtual Ya : (Lf/JG0;)Lf/U90;
/*    */     //   411: invokevirtual Em0 : ()Lf/U90;
/*    */     //   414: aload_0
/*    */     //   415: getfield m70 : Lf/sn0;
/*    */     //   418: invokevirtual Ya : (Lf/JG0;)Lf/U90;
/*    */     //   421: invokevirtual Em0 : ()Lf/U90;
/*    */     //   424: iconst_1
/*    */     //   425: anewarray f/JG0
/*    */     //   428: dup
/*    */     //   429: aload_0
/*    */     //   430: getfield NF : Lf/G9;
/*    */     //   433: iconst_0
/*    */     //   434: swap
/*    */     //   435: aastore
/*    */     //   436: invokevirtual Mg : ([Lf/JG0;)Lf/U90;
/*    */     //   439: invokevirtual Em0 : ()Lf/U90;
/*    */     //   442: invokevirtual ee0 : (Lf/U90;)Lf/U90;
/*    */     //   445: aload_0
/*    */     //   446: getfield sb0 : Lf/Ip;
/*    */     //   449: invokevirtual d7 : ()Lf/cr0;
/*    */     //   452: invokevirtual Em0 : ()Lf/U90;
/*    */     //   455: aload_0
/*    */     //   456: getfield break : Lf/xo0;
/*    */     //   459: invokevirtual Ya : (Lf/JG0;)Lf/U90;
/*    */     //   462: invokevirtual Em0 : ()Lf/U90;
/*    */     //   465: invokevirtual ee0 : (Lf/U90;)Lf/U90;
/*    */     //   468: aload_0
/*    */     //   469: getfield sb0 : Lf/Ip;
/*    */     //   472: invokevirtual mE0 : ()Lf/g0;
/*    */     //   475: iconst_2
/*    */     //   476: anewarray f/JG0
/*    */     //   479: dup
/*    */     //   480: dup
/*    */     //   481: aload_0
/*    */     //   482: swap
/*    */     //   483: aload_0
/*    */     //   484: getfield Od : Lf/Un;
/*    */     //   487: iconst_0
/*    */     //   488: swap
/*    */     //   489: aastore
/*    */     //   490: getfield jH0 : Lf/Un;
/*    */     //   493: iconst_1
/*    */     //   494: swap
/*    */     //   495: aastore
/*    */     //   496: invokevirtual Mg : ([Lf/JG0;)Lf/U90;
/*    */     //   499: invokevirtual ee0 : (Lf/U90;)Lf/U90;
/*    */     //   502: invokevirtual rK0 : (Lf/U90;)V
/*    */     //   505: getfield sb0 : Lf/Ip;
/*    */     //   508: invokevirtual J8 : (Lf/JG0;)V
/*    */     //   511: invokevirtual Yf : ()V
/*    */     //   514: return
/*    */     // Line number table:
/*    */     //   Java source line number -> byte code offset
/*    */     //   #1	-> 319
/*    */     //   #2	-> 323
/*    */     //   #3	-> 344
/*  2 */     //   #4	-> 348 } private boolean TC0(j40 paramj40) { return (paramj40 != null && paramj40 != this.PD.t70 && paramj40 != this.NF
/*  3 */       .t70); } private void Vp0(G9 paramG9) { boolean bool; List list = s90(); if (paramG9.t70 != null) { bool = true; } else { bool = false; }  F7.Yo(JB0.at0(paramG9, this, bool), paramG9); } public final void nv0() { j40 j401, j402; if ((j401 = this.PD.t70) == null || (j402 = this.NF.t70) == null)
/*    */     
/*    */     { 
/*    */ 
/*    */       
/*  8 */       close(); return; }  R8 r8 = km.u4; int i = j401.Jg, j = j402.Jg; this.e20.W3(new Ho(i, j)); close(); } public final void close() { pA pA; bZ bZ1; if ((bZ1 = (pA = pA.Dg0).A0) != null) { bZ1.ra0(); this.A0 = null; }  } public final boolean i2(oa0 paramoa0) { if (B8.Wm0(paramoa0.cz0) && paramoa0.oO()) { BM bM; if (h1.J20(paramoa0.GG0, bM = BM.bC) && this.Od.p3()) { hm.Fz0(this.Od.TG0.oh0); return true; }
/*    */       
/* 10 */       if (h1.J20(paramoa0.GG0, BM.lc) || (
/*    */         
/* 12 */         h1.J20(paramoa0.GG0, bM) && this.jH0.p3()))
/*    */       
/*    */       { 
/*    */ 
/*    */ 
/*    */ 
/*    */ 
/*    */ 
/*    */ 
/*    */ 
/*    */         
/* 23 */         hm.Fz0(this.jH0.TG0.oh0); return true; }  if (h1.J20(paramoa0.GG0, BM.ni) || h1.J20(paramoa0.GG0, BM.Oq)) { q0(); return true; }  if (h1.J20(paramoa0.GG0, BM.N70) || h1.J20(paramoa0.GG0, BM.M8)) { oZ(); return true; }  }
/* 24 */      return super.i2(paramoa0); }
/*    */ 
/*    */   
/*    */   public final void IG0() {}
/*    */   
/*    */   public final void d40() {
/*    */     if (km.XU()) {
/*    */       QI();
/*    */       this.sb0.js0(et.Wi0);
/*    */       this.sb0.Tm(550, 550);
/*    */     } else {
/*    */       super.d40();
/*    */       mM();
/*    */       qB0(et.Wi0);
/*    */     } 
/*    */   }
/*    */   
/*    */   public final List s90() {
/*    */     return (List)Arrays.<j40>stream(km.u4.s40(aq0.LI).lPt3()).filter(this::TC0).sorted(Comparator.comparingInt(bZ::sF)).collect(Collectors.toList());
/*    */   }
/*    */   
/*    */   public final void Yf() {
/*    */     // Byte code:
/*    */     //   0: aload_0
/*    */     //   1: getfield PD : Lf/G9;
/*    */     //   4: getfield t70 : Lf/j40;
/*    */     //   7: dup
/*    */     //   8: astore_1
/*    */     //   9: aload_0
/*    */     //   10: dup
/*    */     //   11: getfield NF : Lf/G9;
/*    */     //   14: getfield t70 : Lf/j40;
/*    */     //   17: astore_2
/*    */     //   18: getfield break : Lf/xo0;
/*    */     //   21: iconst_1
/*    */     //   22: invokevirtual wI0 : (Z)V
/*    */     //   25: ifnull -> 629
/*    */     //   28: aload_2
/*    */     //   29: ifnonnull -> 35
/*    */     //   32: goto -> 629
/*    */     //   35: aload_1
/*    */     //   36: getfield Zs : Lf/Q90;
/*    */     //   39: invokevirtual YC : ()Z
/*    */     //   42: ifne -> 607
/*    */     //   45: aload_2
/*    */     //   46: getfield Zs : Lf/Q90;
/*    */     //   49: invokevirtual YC : ()Z
/*    */     //   52: ifeq -> 58
/*    */     //   55: goto -> 607
/*    */     //   58: aload_1
/*    */     //   59: getfield VP : Lf/UD0;
/*    */     //   62: dup
/*    */     //   63: astore_3
/*    */     //   64: aload_2
/*    */     //   65: getfield VP : Lf/UD0;
/*    */     //   68: astore #4
/*    */     //   70: invokevirtual getClass : ()Ljava/lang/Class;
/*    */     //   73: pop
/*    */     //   74: aload #4
/*    */     //   76: getfield AP : S
/*    */     //   79: aload_3
/*    */     //   80: getfield AP : S
/*    */     //   83: if_icmpne -> 89
/*    */     //   86: goto -> 192
/*    */     //   89: aload_3
/*    */     //   90: aload #4
/*    */     //   92: invokevirtual Fk0 : ()Lf/UD0;
/*    */     //   95: getfield AP : S
/*    */     //   98: istore #5
/*    */     //   100: invokevirtual Fk0 : ()Lf/UD0;
/*    */     //   103: getfield AP : S
/*    */     //   106: dup
/*    */     //   107: istore #6
/*    */     //   109: bipush #29
/*    */     //   111: if_icmpeq -> 171
/*    */     //   114: iload #6
/*    */     //   116: bipush #32
/*    */     //   118: if_icmpeq -> 171
/*    */     //   121: iload #6
/*    */     //   123: sipush #313
/*    */     //   126: if_icmpeq -> 152
/*    */     //   129: iload #6
/*    */     //   131: sipush #314
/*    */     //   134: if_icmpeq -> 152
/*    */     //   137: aload_3
/*    */     //   138: invokevirtual Fk0 : ()Lf/UD0;
/*    */     //   141: aload #4
/*    */     //   143: invokevirtual Fk0 : ()Lf/UD0;
/*    */     //   146: if_acmpne -> 188
/*    */     //   149: goto -> 192
/*    */     //   152: iload #5
/*    */     //   154: sipush #313
/*    */     //   157: if_icmpeq -> 192
/*    */     //   160: iload #5
/*    */     //   162: sipush #314
/*    */     //   165: if_icmpne -> 188
/*    */     //   168: goto -> 192
/*    */     //   171: iload #5
/*    */     //   173: bipush #29
/*    */     //   175: if_icmpeq -> 192
/*    */     //   178: iload #5
/*    */     //   180: bipush #32
/*    */     //   182: if_icmpne -> 188
/*    */     //   185: goto -> 192
/*    */     //   188: iconst_0
/*    */     //   189: goto -> 193
/*    */     //   192: iconst_1
/*    */     //   193: ifne -> 218
/*    */     //   196: aload_0
/*    */     //   197: dup
/*    */     //   198: getfield break : Lf/xo0;
/*    */     //   201: ldc_w 16780467
/*    */     //   204: invokestatic OH0 : (I)Ljava/lang/String;
/*    */     //   207: invokevirtual E1 : (Ljava/lang/String;)V
/*    */     //   210: getfield Od : Lf/Un;
/*    */     //   213: iconst_0
/*    */     //   214: invokevirtual sk0 : (Z)V
/*    */     //   217: return
/*    */     //   218: aload_1
/*    */     //   219: getfield Zs : Lf/Q90;
/*    */     //   222: invokevirtual iL : ()Z
/*    */     //   225: ifne -> 260
/*    */     //   228: aload_2
/*    */     //   229: getfield Zs : Lf/Q90;
/*    */     //   232: invokevirtual iL : ()Z
/*    */     //   235: ifne -> 260
/*    */     //   238: aload_0
/*    */     //   239: dup
/*    */     //   240: getfield break : Lf/xo0;
/*    */     //   243: ldc_w 16780466
/*    */     //   246: invokestatic OH0 : (I)Ljava/lang/String;
/*    */     //   249: invokevirtual E1 : (Ljava/lang/String;)V
/*    */     //   252: getfield Od : Lf/Un;
/*    */     //   255: iconst_0
/*    */     //   256: invokevirtual sk0 : (Z)V
/*    */     //   259: return
/*    */     //   260: aload_1
/*    */     //   261: getfield Zs : Lf/Q90;
/*    */     //   264: invokevirtual iL : ()Z
/*    */     //   267: ifeq -> 302
/*    */     //   270: aload_2
/*    */     //   271: getfield Zs : Lf/Q90;
/*    */     //   274: invokevirtual iL : ()Z
/*    */     //   277: ifeq -> 302
/*    */     //   280: aload_0
/*    */     //   281: dup
/*    */     //   282: getfield break : Lf/xo0;
/*    */     //   285: ldc_w 16780465
/*    */     //   288: invokestatic OH0 : (I)Ljava/lang/String;
/*    */     //   291: invokevirtual E1 : (Ljava/lang/String;)V
/*    */     //   294: getfield Od : Lf/Un;
/*    */     //   297: iconst_0
/*    */     //   298: invokevirtual sk0 : (Z)V
/*    */     //   301: return
/*    */     //   302: aload_1
/*    */     //   303: getfield Zs : Lf/Q90;
/*    */     //   306: invokevirtual iL : ()Z
/*    */     //   309: ifeq -> 317
/*    */     //   312: aload_1
/*    */     //   313: astore_3
/*    */     //   314: goto -> 319
/*    */     //   317: aload_2
/*    */     //   318: astore_3
/*    */     //   319: aload_1
/*    */     //   320: aload_3
/*    */     //   321: if_acmpne -> 330
/*    */     //   324: aload_2
/*    */     //   325: astore #4
/*    */     //   327: goto -> 333
/*    */     //   330: aload_1
/*    */     //   331: astore #4
/*    */     //   333: aload #4
/*    */     //   335: getfield Zs : Lf/Q90;
/*    */     //   338: invokevirtual tm0 : ()Z
/*    */     //   341: ifeq -> 348
/*    */     //   344: iconst_3
/*    */     //   345: goto -> 349
/*    */     //   348: iconst_1
/*    */     //   349: i2s
/*    */     //   350: istore #5
/*    */     //   352: aload_1
/*    */     //   353: new java/lang/StringBuilder
/*    */     //   356: dup
/*    */     //   357: astore #6
/*    */     //   359: invokespecial <init> : ()V
/*    */     //   362: getfield Zs : Lf/Q90;
/*    */     //   365: getfield Cw0 : S
/*    */     //   368: aload_2
/*    */     //   369: getfield Zs : Lf/Q90;
/*    */     //   372: getfield Cw0 : S
/*    */     //   375: if_icmpne -> 440
/*    */     //   378: aload #4
/*    */     //   380: aload_1
/*    */     //   381: if_acmpne -> 389
/*    */     //   384: iconst_1
/*    */     //   385: istore_1
/*    */     //   386: goto -> 391
/*    */     //   389: iconst_0
/*    */     //   390: istore_1
/*    */     //   391: iload_1
/*    */     //   392: ifeq -> 402
/*    */     //   395: ldc_w 16780473
/*    */     //   398: istore_2
/*    */     //   399: goto -> 406
/*    */     //   402: ldc_w 16780474
/*    */     //   405: istore_2
/*    */     //   406: iload_1
/*    */     //   407: iload_2
/*    */     //   408: aload #4
/*    */     //   410: invokevirtual m : ()Ljava/lang/String;
/*    */     //   413: invokestatic Go : (ILjava/lang/String;)Ljava/lang/String;
/*    */     //   416: astore_1
/*    */     //   417: ifeq -> 426
/*    */     //   420: ldc_w 16780474
/*    */     //   423: goto -> 429
/*    */     //   426: ldc_w 16780473
/*    */     //   429: aload_3
/*    */     //   430: invokevirtual m : ()Ljava/lang/String;
/*    */     //   433: invokestatic Go : (ILjava/lang/String;)Ljava/lang/String;
/*    */     //   436: astore_2
/*    */     //   437: goto -> 451
/*    */     //   440: aload_3
/*    */     //   441: aload #4
/*    */     //   443: invokevirtual m : ()Ljava/lang/String;
/*    */     //   446: astore_1
/*    */     //   447: invokevirtual m : ()Ljava/lang/String;
/*    */     //   450: astore_2
/*    */     //   451: aload #4
/*    */     //   453: getfield VP : Lf/UD0;
/*    */     //   456: invokevirtual ct : ()Z
/*    */     //   459: ifeq -> 507
/*    */     //   462: aload #6
/*    */     //   464: iconst_2
/*    */     //   465: anewarray java/lang/String
/*    */     //   468: dup
/*    */     //   469: astore_3
/*    */     //   470: aload #4
/*    */     //   472: aload_3
/*    */     //   473: iconst_0
/*    */     //   474: aload_1
/*    */     //   475: aastore
/*    */     //   476: getfield VP : Lf/UD0;
/*    */     //   479: iconst_2
/*    */     //   480: invokevirtual zq0 : (I)S
/*    */     //   483: ldc_w 210000
/*    */     //   486: iadd
/*    */     //   487: invokestatic OH0 : (I)Ljava/lang/String;
/*    */     //   490: iconst_1
/*    */     //   491: swap
/*    */     //   492: aastore
/*    */     //   493: ldc_w 16780470
/*    */     //   496: aload_3
/*    */     //   497: invokestatic sB : (I[Ljava/lang/String;)Ljava/lang/String;
/*    */     //   500: invokevirtual append : (Ljava/lang/String;)Ljava/lang/StringBuilder;
/*    */     //   503: pop
/*    */     //   504: goto -> 520
/*    */     //   507: aload #6
/*    */     //   509: ldc_w 16780471
/*    */     //   512: aload_1
/*    */     //   513: invokestatic Go : (ILjava/lang/String;)Ljava/lang/String;
/*    */     //   516: invokevirtual append : (Ljava/lang/String;)Ljava/lang/StringBuilder;
/*    */     //   519: pop
/*    */     //   520: aload_0
/*    */     //   521: dup
/*    */     //   522: dup
/*    */     //   523: aload #6
/*    */     //   525: iload #5
/*    */     //   527: aload #6
/*    */     //   529: dup
/*    */     //   530: dup
/*    */     //   531: ldc '\\n\\n'
/*    */     //   533: invokevirtual append : (Ljava/lang/String;)Ljava/lang/StringBuilder;
/*    */     //   536: pop
/*    */     //   537: ldc_w 16780464
/*    */     //   540: aload_2
/*    */     //   541: invokestatic Go : (ILjava/lang/String;)Ljava/lang/String;
/*    */     //   544: invokevirtual append : (Ljava/lang/String;)Ljava/lang/StringBuilder;
/*    */     //   547: pop
/*    */     //   548: ldc '\\n\\n'
/*    */     //   550: invokevirtual append : (Ljava/lang/String;)Ljava/lang/StringBuilder;
/*    */     //   553: pop
/*    */     //   554: invokestatic toString : (I)Ljava/lang/String;
/*    */     //   557: ldc_w 16780463
/*    */     //   560: swap
/*    */     //   561: invokestatic Go : (ILjava/lang/String;)Ljava/lang/String;
/*    */     //   564: invokevirtual append : (Ljava/lang/String;)Ljava/lang/StringBuilder;
/*    */     //   567: pop
/*    */     //   568: getfield break : Lf/xo0;
/*    */     //   571: aload #6
/*    */     //   573: invokevirtual toString : ()Ljava/lang/String;
/*    */     //   576: invokevirtual E1 : (Ljava/lang/String;)V
/*    */     //   579: getfield Od : Lf/Un;
/*    */     //   582: astore_0
/*    */     //   583: getfield m70 : Lf/sn0;
/*    */     //   586: getfield op0 : S
/*    */     //   589: iload #5
/*    */     //   591: if_icmplt -> 599
/*    */     //   594: iconst_1
/*    */     //   595: istore_1
/*    */     //   596: goto -> 601
/*    */     //   599: iconst_0
/*    */     //   600: istore_1
/*    */     //   601: aload_0
/*    */     //   602: iload_1
/*    */     //   603: invokevirtual sk0 : (Z)V
/*    */     //   606: return
/*    */     //   607: aload_0
/*    */     //   608: dup
/*    */     //   609: getfield break : Lf/xo0;
/*    */     //   612: ldc_w 16780462
/*    */     //   615: invokestatic OH0 : (I)Ljava/lang/String;
/*    */     //   618: invokevirtual E1 : (Ljava/lang/String;)V
/*    */     //   621: getfield Od : Lf/Un;
/*    */     //   624: iconst_0
/*    */     //   625: invokevirtual sk0 : (Z)V
/*    */     //   628: return
/*    */     //   629: aload_0
/*    */     //   630: dup
/*    */     //   631: getfield Od : Lf/Un;
/*    */     //   634: iconst_0
/*    */     //   635: invokevirtual sk0 : (Z)V
/*    */     //   638: getfield break : Lf/xo0;
/*    */     //   641: ldc_w 16780472
/*    */     //   644: invokestatic OH0 : (I)Ljava/lang/String;
/*    */     //   647: invokevirtual E1 : (Ljava/lang/String;)V
/*    */     //   650: return
/*    */     // Line number table:
/*    */     //   Java source line number -> byte code offset
/*    */     //   #1	-> 4
/*    */     //   #2	-> 11
/*    */     //   #3	-> 14
/*    */     //   #4	-> 18
/*    */     //   #5	-> 36
/*    */     //   #6	-> 59
/*    */     //   #7	-> 70
/*    */     //   #8	-> 76
/*    */     //   #9	-> 80
/*    */     //   #10	-> 95
/*    */     //   #11	-> 100
/*    */     //   #12	-> 103
/*    */     //   #13	-> 138
/*    */     //   #14	-> 198
/*    */     //   #15	-> 219
/*    */     //   #16	-> 222
/*    */     //   #17	-> 229
/*    */     //   #18	-> 232
/*    */     //   #19	-> 261
/*    */     //   #20	-> 264
/*    */     //   #21	-> 271
/*    */     //   #22	-> 274
/*    */     //   #23	-> 303
/*    */     //   #24	-> 306
/*    */     //   #25	-> 335
/*    */     //   #26	-> 338
/*    */     //   #27	-> 353
/*    */     //   #28	-> 362
/*    */     //   #29	-> 365
/*    */     //   #30	-> 369
/*    */     //   #31	-> 372
/*    */     //   #32	-> 410
/*    */     //   #33	-> 453
/*    */     //   #34	-> 456
/*    */     //   #35	-> 476
/*    */     //   #36	-> 480
/*    */     //   #37	-> 586
/*    */     //   #38	-> 603
/*    */   } }


/* Location:              /Users/vnnsnnt/Documents/Codespace/JavaWorkspace/RedTrainer/src/main/java/org/trainer/client/PokeMMO.jar!/f/bZ.class
 * Java compiler version: 8 (52.0)
 * JD-Core Version:       1.1.3
 */