/*  1 */ package f;public final class cE { public static final ik me0 = C00.gd(cE.class); public static final cE eo0 = new cE(); public static int LPT1(cn0 paramcn01, cn0 paramcn02) { byte b1; byte b2; if ((b1 = paramcn02.Wc) != (
/*  2 */       b2 = paramcn01.Wc)) return b1 - b2;
/*    */     
/*  4 */     return (paramcn01.aj0 ^ true) - (paramcn02.aj0 ^ true); }
/*  5 */   public ArrayList yl = new ArrayList(); public Locale Dr = Locale.getDefault(); public static final cE i20() { return eo0; } public final String[] dp0() { this(); ArrayList<String> arrayList; Xv0[] arrayOfXv0; int i; byte b; for (i = (arrayOfXv0 = Xv0.Kf0).length, b = 0; b < i; ) { Xv0 xv0; Iterator<cn0> iterator1; for (xv0 = arrayOfXv0[b], iterator1 = this.yl.iterator(); iterator1.hasNext();) { if (!arrayList.contains((cn0 = iterator1.next()).lI) && LF.M60(cn0.lI, xv0.uz0)) arrayList
/*    */             
/*  7 */             .add(cn0.lI);  }  b++; }  for (Iterator iterator = this.yl.iterator(); hasNext(); ) { cn0 cn0; if (arrayList
/*    */         
/*  9 */         .contains((cn0 = (cn0)next()).lI)) continue;  arrayList
/*    */         
/* 11 */         .add(cn0.lI); }  return arrayList.<String>toArray(new String[0]); }
/*    */ 
/*    */   
/*    */   public static Locale W70(String paramString) {
/*    */     String str1 = "", str2 = "";
/*    */     if (paramString.contains("-")) {
/*    */       paramString = paramString.split("-")[0];
/*    */       str1 = paramString.split("-")[1];
/*    */     } 
/*    */     if (paramString.equalsIgnoreCase("zh") && str1.equalsIgnoreCase("Hant"))
/*    */       return Locale.forLanguageTag("zh-hant"); 
/*    */     Locale locale;
/*    */     byte b1;
/*    */     Locale[] arrayOfLocale;
/*    */     int i;
/*    */     byte b2;
/*    */     for (str1 = str1.toUpperCase(Locale.ENGLISH), locale = Locale.getDefault(), b1 = 0, paramString = (new Locale(paramString)).getLanguage(), i = (arrayOfLocale = Locale.getAvailableLocales()).length, b2 = 0; b2 < i; ) {
/*    */       byte b = 0;
/*    */       b = 1;
/*    */       b = 2;
/*    */       Locale locale1;
/*    */       if ((locale1 = arrayOfLocale[b2]).getLanguage().equalsIgnoreCase(paramString) && locale1.getCountry().equalsIgnoreCase(str1) && locale1.getScript().equalsIgnoreCase(str2))
/*    */         b = 3; 
/*    */       if (b > b1) {
/*    */         b1 = b;
/*    */         locale = locale1;
/*    */       } 
/*    */       b2++;
/*    */     } 
/*    */     return locale;
/*    */   }
/*    */   
/*    */   public static boolean cj0() {
/*    */     // Byte code:
/*    */     //   0: iconst_0
/*    */     //   1: istore_0
/*    */     //   2: iload_0
/*    */     //   3: iconst_5
/*    */     //   4: if_icmpge -> 1347
/*    */     //   7: getstatic f/km.mI0 : Lf/P1;
/*    */     //   10: iload_0
/*    */     //   11: invokevirtual Sa : (B)Lf/s40;
/*    */     //   14: dup
/*    */     //   15: astore_1
/*    */     //   16: ifnull -> 635
/*    */     //   19: aload_1
/*    */     //   20: dup
/*    */     //   21: getfield wJ : Lf/uq;
/*    */     //   24: getfield lp0 : Ljava/lang/String;
/*    */     //   27: astore_2
/*    */     //   28: new java/lang/StringBuilder
/*    */     //   31: dup
/*    */     //   32: aload_1
/*    */     //   33: swap
/*    */     //   34: invokespecial <init> : ()V
/*    */     //   37: getfield coM7 : Ljava/lang/String;
/*    */     //   40: iconst_0
/*    */     //   41: iconst_3
/*    */     //   42: invokevirtual substring : (II)Ljava/lang/String;
/*    */     //   45: invokevirtual append : (Ljava/lang/String;)Ljava/lang/StringBuilder;
/*    */     //   48: ldc '_'
/*    */     //   50: invokevirtual append : (Ljava/lang/String;)Ljava/lang/StringBuilder;
/*    */     //   53: aload_2
/*    */     //   54: ldc '.xml'
/*    */     //   56: invokestatic Vr0 : (Ljava/lang/StringBuilder;Ljava/lang/String;Ljava/lang/String;)Ljava/lang/String;
/*    */     //   59: astore_3
/*    */     //   60: new java/util/TreeSet
/*    */     //   63: dup
/*    */     //   64: astore #4
/*    */     //   66: invokespecial <init> : ()V
/*    */     //   69: aconst_null
/*    */     //   70: astore #5
/*    */     //   72: getfield wJ : Lf/uq;
/*    */     //   75: getfield sd0 : Lf/p3;
/*    */     //   78: dup
/*    */     //   79: astore #6
/*    */     //   81: ifnull -> 88
/*    */     //   84: iconst_1
/*    */     //   85: goto -> 89
/*    */     //   88: iconst_0
/*    */     //   89: ifeq -> 99
/*    */     //   92: aload #6
/*    */     //   94: astore #5
/*    */     //   96: goto -> 168
/*    */     //   99: getstatic f/n50.eJ0 : Ljava/util/HashMap;
/*    */     //   102: invokevirtual values : ()Ljava/util/Collection;
/*    */     //   105: invokeinterface iterator : ()Ljava/util/Iterator;
/*    */     //   110: astore #6
/*    */     //   112: aload #6
/*    */     //   114: invokeinterface hasNext : ()Z
/*    */     //   119: ifeq -> 168
/*    */     //   122: aload #6
/*    */     //   124: invokeinterface next : ()Ljava/lang/Object;
/*    */     //   129: checkcast f/uq
/*    */     //   132: dup
/*    */     //   133: astore #7
/*    */     //   135: getfield sd0 : Lf/p3;
/*    */     //   138: ifnull -> 145
/*    */     //   141: iconst_1
/*    */     //   142: goto -> 146
/*    */     //   145: iconst_0
/*    */     //   146: ifeq -> 112
/*    */     //   149: aload #7
/*    */     //   151: getfield F9 : B
/*    */     //   154: aload_1
/*    */     //   155: invokevirtual in : ()B
/*    */     //   158: if_icmpne -> 112
/*    */     //   161: aload #7
/*    */     //   163: getfield sd0 : Lf/p3;
/*    */     //   166: astore #5
/*    */     //   168: aload #5
/*    */     //   170: ifnonnull -> 177
/*    */     //   173: iconst_0
/*    */     //   174: goto -> 630
/*    */     //   177: aload #5
/*    */     //   179: dup
/*    */     //   180: iconst_1
/*    */     //   181: invokevirtual oz : (Z)Z
/*    */     //   184: pop
/*    */     //   185: getfield oe : Lf/Xj0;
/*    */     //   188: dup
/*    */     //   189: astore #5
/*    */     //   191: ifnonnull -> 202
/*    */     //   194: iconst_0
/*    */     //   195: newarray int
/*    */     //   197: astore #5
/*    */     //   199: goto -> 278
/*    */     //   202: aload #5
/*    */     //   204: dup
/*    */     //   205: getfield ir0 : I
/*    */     //   208: newarray int
/*    */     //   210: astore #6
/*    */     //   212: getfield R3 : [I
/*    */     //   215: dup
/*    */     //   216: astore #7
/*    */     //   218: aload #5
/*    */     //   220: getfield JO : [B
/*    */     //   223: astore #5
/*    */     //   225: arraylength
/*    */     //   226: istore #8
/*    */     //   228: iconst_0
/*    */     //   229: istore #9
/*    */     //   231: iload #8
/*    */     //   233: dup
/*    */     //   234: iconst_m1
/*    */     //   235: iadd
/*    */     //   236: istore #8
/*    */     //   238: ifle -> 274
/*    */     //   241: aload #5
/*    */     //   243: iload #8
/*    */     //   245: baload
/*    */     //   246: iconst_1
/*    */     //   247: if_icmpne -> 231
/*    */     //   250: aload #6
/*    */     //   252: aload #7
/*    */     //   254: iload #9
/*    */     //   256: iconst_1
/*    */     //   257: iadd
/*    */     //   258: istore #10
/*    */     //   260: iload #8
/*    */     //   262: iaload
/*    */     //   263: iload #9
/*    */     //   265: swap
/*    */     //   266: iastore
/*    */     //   267: iload #10
/*    */     //   269: istore #9
/*    */     //   271: goto -> 231
/*    */     //   274: aload #6
/*    */     //   276: astore #5
/*    */     //   278: aload #5
/*    */     //   280: arraylength
/*    */     //   281: istore #6
/*    */     //   283: iconst_0
/*    */     //   284: istore #7
/*    */     //   286: iload #7
/*    */     //   288: iload #6
/*    */     //   290: if_icmpge -> 325
/*    */     //   293: aload #5
/*    */     //   295: iload #7
/*    */     //   297: iaload
/*    */     //   298: dup
/*    */     //   299: istore #8
/*    */     //   301: iconst_1
/*    */     //   302: if_icmpge -> 308
/*    */     //   305: goto -> 319
/*    */     //   308: aload #4
/*    */     //   310: iload #8
/*    */     //   312: invokestatic valueOf : (I)Ljava/lang/Integer;
/*    */     //   315: invokevirtual add : (Ljava/lang/Object;)Z
/*    */     //   318: pop
/*    */     //   319: iinc #7, 1
/*    */     //   322: goto -> 286
/*    */     //   325: aload #4
/*    */     //   327: invokestatic newInstance : ()Ljavax/xml/parsers/DocumentBuilderFactory;
/*    */     //   330: invokevirtual newDocumentBuilder : ()Ljavax/xml/parsers/DocumentBuilder;
/*    */     //   333: invokevirtual newDocument : ()Lorg/w3c/dom/Document;
/*    */     //   336: dup
/*    */     //   337: dup
/*    */     //   338: astore #4
/*    */     //   340: ldc_w 'strings'
/*    */     //   343: invokeinterface createElement : (Ljava/lang/String;)Lorg/w3c/dom/Element;
/*    */     //   348: dup
/*    */     //   349: dup
/*    */     //   350: dup2
/*    */     //   351: astore #5
/*    */     //   353: ldc_w 'lang'
/*    */     //   356: aload_2
/*    */     //   357: invokeinterface setAttribute : (Ljava/lang/String;Ljava/lang/String;)V
/*    */     //   362: ldc_w 'is_primary'
/*    */     //   365: ldc_w '0'
/*    */     //   368: invokeinterface setAttribute : (Ljava/lang/String;Ljava/lang/String;)V
/*    */     //   373: ldc_w 'is_override'
/*    */     //   376: ldc_w '0'
/*    */     //   379: invokeinterface setAttribute : (Ljava/lang/String;Ljava/lang/String;)V
/*    */     //   384: invokeinterface appendChild : (Lorg/w3c/dom/Node;)Lorg/w3c/dom/Node;
/*    */     //   389: pop
/*    */     //   390: invokevirtual iterator : ()Ljava/util/Iterator;
/*    */     //   393: astore_2
/*    */     //   394: aload_2
/*    */     //   395: invokeinterface hasNext : ()Z
/*    */     //   400: ifeq -> 525
/*    */     //   403: aload_2
/*    */     //   404: invokeinterface next : ()Ljava/lang/Object;
/*    */     //   409: checkcast java/lang/Integer
/*    */     //   412: invokevirtual intValue : ()I
/*    */     //   415: dup
/*    */     //   416: istore #6
/*    */     //   418: iconst_0
/*    */     //   419: aload_1
/*    */     //   420: aconst_null
/*    */     //   421: invokestatic fj : (IZLf/s40;Lf/s40;)Ljava/lang/String;
/*    */     //   424: invokevirtual trim : ()Ljava/lang/String;
/*    */     //   427: dup
/*    */     //   428: astore #7
/*    */     //   430: invokevirtual isEmpty : ()Z
/*    */     //   433: ifeq -> 439
/*    */     //   436: goto -> 394
/*    */     //   439: aload #5
/*    */     //   441: aload #4
/*    */     //   443: iload #6
/*    */     //   445: aload_1
/*    */     //   446: ldc_w 268435456
/*    */     //   449: istore #6
/*    */     //   451: invokevirtual in : ()B
/*    */     //   454: iload #6
/*    */     //   456: imul
/*    */     //   457: ior
/*    */     //   458: istore #6
/*    */     //   460: ldc_w 'string'
/*    */     //   463: invokeinterface createElement : (Ljava/lang/String;)Lorg/w3c/dom/Element;
/*    */     //   468: dup
/*    */     //   469: dup
/*    */     //   470: aload #7
/*    */     //   472: swap
/*    */     //   473: ldc_w 'id'
/*    */     //   476: new java/lang/StringBuilder
/*    */     //   479: dup
/*    */     //   480: iload #6
/*    */     //   482: swap
/*    */     //   483: invokespecial <init> : ()V
/*    */     //   486: invokevirtual append : (I)Ljava/lang/StringBuilder;
/*    */     //   489: ldc ''
/*    */     //   491: invokevirtual append : (Ljava/lang/String;)Ljava/lang/StringBuilder;
/*    */     //   494: invokevirtual toString : ()Ljava/lang/String;
/*    */     //   497: invokeinterface setAttribute : (Ljava/lang/String;Ljava/lang/String;)V
/*    */     //   502: ldc_w '\\\n'
/*    */     //   505: ldc_w '\\n'
/*    */     //   508: invokevirtual replaceAll : (Ljava/lang/String;Ljava/lang/String;)Ljava/lang/String;
/*    */     //   511: invokeinterface setTextContent : (Ljava/lang/String;)V
/*    */     //   516: invokeinterface appendChild : (Lorg/w3c/dom/Node;)Lorg/w3c/dom/Node;
/*    */     //   521: pop
/*    */     //   522: goto -> 394
/*    */     //   525: invokestatic newInstance : ()Ljavax/xml/transform/TransformerFactory;
/*    */     //   528: invokevirtual newTransformer : ()Ljavax/xml/transform/Transformer;
/*    */     //   531: dup
/*    */     //   532: dup
/*    */     //   533: new javax/xml/transform/dom/DOMSource
/*    */     //   536: dup
/*    */     //   537: astore_1
/*    */     //   538: aload #4
/*    */     //   540: invokespecial <init> : (Lorg/w3c/dom/Node;)V
/*    */     //   543: getstatic f/UB0.vj0 : Lf/XG;
/*    */     //   546: new java/lang/StringBuilder
/*    */     //   549: dup
/*    */     //   550: invokespecial <init> : ()V
/*    */     //   553: ldc_w 'dump/strings/dump_'
/*    */     //   556: invokevirtual append : (Ljava/lang/String;)Ljava/lang/StringBuilder;
/*    */     //   559: aload_3
/*    */     //   560: invokevirtual append : (Ljava/lang/String;)Ljava/lang/StringBuilder;
/*    */     //   563: invokevirtual toString : ()Ljava/lang/String;
/*    */     //   566: invokevirtual N0 : (Ljava/lang/String;)Lf/hZ;
/*    */     //   569: dup
/*    */     //   570: astore_2
/*    */     //   571: invokevirtual wT : ()Lf/RD0;
/*    */     //   574: invokevirtual iz0 : ()V
/*    */     //   577: new javax/xml/transform/stream/StreamResult
/*    */     //   580: dup
/*    */     //   581: astore_3
/*    */     //   582: aload_2
/*    */     //   583: invokevirtual hh : ()Ljava/io/OutputStream;
/*    */     //   586: invokespecial <init> : (Ljava/io/OutputStream;)V
/*    */     //   589: ldc_w 'indent'
/*    */     //   592: ldc_w 'yes'
/*    */     //   595: invokevirtual setOutputProperty : (Ljava/lang/String;Ljava/lang/String;)V
/*    */     //   598: ldc_w '{http://xml.apache.org/xslt}indent-amount'
/*    */     //   601: ldc_w '4'
/*    */     //   604: invokevirtual setOutputProperty : (Ljava/lang/String;Ljava/lang/String;)V
/*    */     //   607: aload_1
/*    */     //   608: aload_3
/*    */     //   609: invokevirtual transform : (Ljavax/xml/transform/Source;Ljavax/xml/transform/Result;)V
/*    */     //   612: iconst_1
/*    */     //   613: goto -> 630
/*    */     //   616: astore_1
/*    */     //   617: getstatic f/cE.me0 : Lf/ik;
/*    */     //   620: ldc_w 'dump error'
/*    */     //   623: aload_1
/*    */     //   624: invokeinterface error : (Ljava/lang/String;Ljava/lang/Throwable;)V
/*    */     //   629: iconst_0
/*    */     //   630: ifne -> 635
/*    */     //   633: iconst_0
/*    */     //   634: ireturn
/*    */     //   635: getstatic f/km.mI0 : Lf/P1;
/*    */     //   638: iload_0
/*    */     //   639: invokevirtual LpT7 : (B)Lf/HI;
/*    */     //   642: dup
/*    */     //   643: astore_1
/*    */     //   644: ifnull -> 1339
/*    */     //   647: aload_1
/*    */     //   648: invokevirtual SO : ()Ljava/lang/String;
/*    */     //   651: astore_2
/*    */     //   652: invokestatic values : ()[Lf/F40;
/*    */     //   655: dup
/*    */     //   656: astore_3
/*    */     //   657: arraylength
/*    */     //   658: istore #4
/*    */     //   660: iconst_0
/*    */     //   661: istore #5
/*    */     //   663: iload #5
/*    */     //   665: iload #4
/*    */     //   667: if_icmpge -> 1333
/*    */     //   670: aload_1
/*    */     //   671: aload_3
/*    */     //   672: iload #5
/*    */     //   674: aaload
/*    */     //   675: dup
/*    */     //   676: astore #6
/*    */     //   678: invokevirtual Ft0 : (Lf/F40;)Lf/YK0;
/*    */     //   681: dup
/*    */     //   682: astore #7
/*    */     //   684: getfield te0 : Lf/F40;
/*    */     //   687: aload #6
/*    */     //   689: if_acmpeq -> 695
/*    */     //   692: goto -> 1279
/*    */     //   695: new java/lang/StringBuilder
/*    */     //   698: dup
/*    */     //   699: aload_1
/*    */     //   700: swap
/*    */     //   701: invokespecial <init> : ()V
/*    */     //   704: getfield qa0 : Lf/ml;
/*    */     //   707: getfield UI : Ljava/lang/String;
/*    */     //   710: invokevirtual append : (Ljava/lang/String;)Ljava/lang/StringBuilder;
/*    */     //   713: ldc '_'
/*    */     //   715: invokevirtual append : (Ljava/lang/String;)Ljava/lang/StringBuilder;
/*    */     //   718: aload #6
/*    */     //   720: getfield DX : B
/*    */     //   723: invokevirtual append : (I)Ljava/lang/StringBuilder;
/*    */     //   726: ldc '_'
/*    */     //   728: invokevirtual append : (Ljava/lang/String;)Ljava/lang/StringBuilder;
/*    */     //   731: aload_2
/*    */     //   732: invokevirtual append : (Ljava/lang/String;)Ljava/lang/StringBuilder;
/*    */     //   735: ldc '.xml'
/*    */     //   737: invokevirtual append : (Ljava/lang/String;)Ljava/lang/StringBuilder;
/*    */     //   740: invokevirtual toString : ()Ljava/lang/String;
/*    */     //   743: astore #8
/*    */     //   745: invokestatic newInstance : ()Ljavax/xml/parsers/DocumentBuilderFactory;
/*    */     //   748: invokevirtual newDocumentBuilder : ()Ljavax/xml/parsers/DocumentBuilder;
/*    */     //   751: invokevirtual newDocument : ()Lorg/w3c/dom/Document;
/*    */     //   754: dup
/*    */     //   755: dup
/*    */     //   756: astore #9
/*    */     //   758: ldc_w 'ds_strings_archive'
/*    */     //   761: invokeinterface createElement : (Ljava/lang/String;)Lorg/w3c/dom/Element;
/*    */     //   766: dup
/*    */     //   767: dup
/*    */     //   768: dup2
/*    */     //   769: astore #10
/*    */     //   771: ldc_w 'lang'
/*    */     //   774: aload_2
/*    */     //   775: invokeinterface setAttribute : (Ljava/lang/String;Ljava/lang/String;)V
/*    */     //   780: ldc_w 'region_id'
/*    */     //   783: new java/lang/StringBuilder
/*    */     //   786: dup
/*    */     //   787: aload_1
/*    */     //   788: swap
/*    */     //   789: invokespecial <init> : ()V
/*    */     //   792: invokevirtual bO : ()B
/*    */     //   795: invokevirtual append : (I)Ljava/lang/StringBuilder;
/*    */     //   798: ldc ''
/*    */     //   800: invokevirtual append : (Ljava/lang/String;)Ljava/lang/StringBuilder;
/*    */     //   803: invokevirtual toString : ()Ljava/lang/String;
/*    */     //   806: invokeinterface setAttribute : (Ljava/lang/String;Ljava/lang/String;)V
/*    */     //   811: ldc_w 'archive_type'
/*    */     //   814: new java/lang/StringBuilder
/*    */     //   817: dup
/*    */     //   818: aload #6
/*    */     //   820: swap
/*    */     //   821: invokespecial <init> : ()V
/*    */     //   824: getfield DX : B
/*    */     //   827: invokevirtual append : (I)Ljava/lang/StringBuilder;
/*    */     //   830: ldc ''
/*    */     //   832: invokevirtual append : (Ljava/lang/String;)Ljava/lang/StringBuilder;
/*    */     //   835: invokevirtual toString : ()Ljava/lang/String;
/*    */     //   838: invokeinterface setAttribute : (Ljava/lang/String;Ljava/lang/String;)V
/*    */     //   843: invokeinterface appendChild : (Lorg/w3c/dom/Node;)Lorg/w3c/dom/Node;
/*    */     //   848: pop
/*    */     //   849: iconst_0
/*    */     //   850: istore #11
/*    */     //   852: iload #11
/*    */     //   854: aload #7
/*    */     //   856: getfield Pv0 : [[[Ljava/lang/String;
/*    */     //   859: arraylength
/*    */     //   860: if_icmpge -> 1185
/*    */     //   863: iconst_0
/*    */     //   864: istore #12
/*    */     //   866: aload #7
/*    */     //   868: iload #11
/*    */     //   870: invokevirtual sk0 : (I)I
/*    */     //   873: dup
/*    */     //   874: istore #13
/*    */     //   876: iflt -> 925
/*    */     //   879: iload #13
/*    */     //   881: aload #7
/*    */     //   883: getfield Pv0 : [[[Ljava/lang/String;
/*    */     //   886: dup
/*    */     //   887: astore #14
/*    */     //   889: arraylength
/*    */     //   890: if_icmplt -> 896
/*    */     //   893: goto -> 925
/*    */     //   896: aload #14
/*    */     //   898: iload #13
/*    */     //   900: aaload
/*    */     //   901: ifnonnull -> 911
/*    */     //   904: aload #7
/*    */     //   906: iload #13
/*    */     //   908: invokevirtual PH0 : (I)V
/*    */     //   911: aload #7
/*    */     //   913: getfield Pv0 : [[[Ljava/lang/String;
/*    */     //   916: iload #13
/*    */     //   918: aaload
/*    */     //   919: arraylength
/*    */     //   920: istore #13
/*    */     //   922: goto -> 928
/*    */     //   925: iconst_0
/*    */     //   926: istore #13
/*    */     //   928: iload #12
/*    */     //   930: iload #13
/*    */     //   932: if_icmpge -> 1179
/*    */     //   935: iconst_0
/*    */     //   936: istore #13
/*    */     //   938: aload #7
/*    */     //   940: iload #11
/*    */     //   942: invokevirtual sk0 : (I)I
/*    */     //   945: dup
/*    */     //   946: istore #14
/*    */     //   948: iflt -> 1019
/*    */     //   951: iload #14
/*    */     //   953: aload #7
/*    */     //   955: getfield Pv0 : [[[Ljava/lang/String;
/*    */     //   958: dup
/*    */     //   959: astore #15
/*    */     //   961: arraylength
/*    */     //   962: if_icmplt -> 968
/*    */     //   965: goto -> 1019
/*    */     //   968: aload #15
/*    */     //   970: iload #14
/*    */     //   972: aaload
/*    */     //   973: ifnonnull -> 983
/*    */     //   976: aload #7
/*    */     //   978: iload #14
/*    */     //   980: invokevirtual PH0 : (I)V
/*    */     //   983: iload #12
/*    */     //   985: iflt -> 1019
/*    */     //   988: iload #12
/*    */     //   990: aload #7
/*    */     //   992: getfield Pv0 : [[[Ljava/lang/String;
/*    */     //   995: iload #14
/*    */     //   997: aaload
/*    */     //   998: dup
/*    */     //   999: astore #14
/*    */     //   1001: arraylength
/*    */     //   1002: if_icmplt -> 1008
/*    */     //   1005: goto -> 1019
/*    */     //   1008: aload #14
/*    */     //   1010: iload #12
/*    */     //   1012: aaload
/*    */     //   1013: arraylength
/*    */     //   1014: istore #14
/*    */     //   1016: goto -> 1022
/*    */     //   1019: iconst_0
/*    */     //   1020: istore #14
/*    */     //   1022: iload #13
/*    */     //   1024: iload #14
/*    */     //   1026: if_icmpge -> 1173
/*    */     //   1029: aload #10
/*    */     //   1031: aload #9
/*    */     //   1033: ldc_w 'string'
/*    */     //   1036: invokeinterface createElement : (Ljava/lang/String;)Lorg/w3c/dom/Element;
/*    */     //   1041: dup
/*    */     //   1042: dup
/*    */     //   1043: astore #14
/*    */     //   1045: aload #7
/*    */     //   1047: iload #11
/*    */     //   1049: iload #12
/*    */     //   1051: aload #14
/*    */     //   1053: dup
/*    */     //   1054: dup
/*    */     //   1055: ldc_w 'table_id'
/*    */     //   1058: new java/lang/StringBuilder
/*    */     //   1061: dup
/*    */     //   1062: iload #11
/*    */     //   1064: swap
/*    */     //   1065: invokespecial <init> : ()V
/*    */     //   1068: invokevirtual append : (I)Ljava/lang/StringBuilder;
/*    */     //   1071: ldc ''
/*    */     //   1073: invokevirtual append : (Ljava/lang/String;)Ljava/lang/StringBuilder;
/*    */     //   1076: invokevirtual toString : ()Ljava/lang/String;
/*    */     //   1079: invokeinterface setAttribute : (Ljava/lang/String;Ljava/lang/String;)V
/*    */     //   1084: ldc_w 'block_id'
/*    */     //   1087: new java/lang/StringBuilder
/*    */     //   1090: dup
/*    */     //   1091: iload #12
/*    */     //   1093: swap
/*    */     //   1094: invokespecial <init> : ()V
/*    */     //   1097: invokevirtual append : (I)Ljava/lang/StringBuilder;
/*    */     //   1100: ldc ''
/*    */     //   1102: invokevirtual append : (Ljava/lang/String;)Ljava/lang/StringBuilder;
/*    */     //   1105: invokevirtual toString : ()Ljava/lang/String;
/*    */     //   1108: invokeinterface setAttribute : (Ljava/lang/String;Ljava/lang/String;)V
/*    */     //   1113: ldc_w 'entry_id'
/*    */     //   1116: new java/lang/StringBuilder
/*    */     //   1119: dup
/*    */     //   1120: iload #13
/*    */     //   1122: swap
/*    */     //   1123: invokespecial <init> : ()V
/*    */     //   1126: invokevirtual append : (I)Ljava/lang/StringBuilder;
/*    */     //   1129: ldc ''
/*    */     //   1131: invokevirtual append : (Ljava/lang/String;)Ljava/lang/StringBuilder;
/*    */     //   1134: invokevirtual toString : ()Ljava/lang/String;
/*    */     //   1137: invokeinterface setAttribute : (Ljava/lang/String;Ljava/lang/String;)V
/*    */     //   1142: iload #13
/*    */     //   1144: invokevirtual j0 : (III)Ljava/lang/String;
/*    */     //   1147: ldc_w '\\\n'
/*    */     //   1150: ldc_w '\\n'
/*    */     //   1153: invokevirtual replaceAll : (Ljava/lang/String;Ljava/lang/String;)Ljava/lang/String;
/*    */     //   1156: invokeinterface setTextContent : (Ljava/lang/String;)V
/*    */     //   1161: invokeinterface appendChild : (Lorg/w3c/dom/Node;)Lorg/w3c/dom/Node;
/*    */     //   1166: pop
/*    */     //   1167: iinc #13, 1
/*    */     //   1170: goto -> 938
/*    */     //   1173: iinc #12, 1
/*    */     //   1176: goto -> 866
/*    */     //   1179: iinc #11, 1
/*    */     //   1182: goto -> 852
/*    */     //   1185: invokestatic newInstance : ()Ljavax/xml/transform/TransformerFactory;
/*    */     //   1188: invokevirtual newTransformer : ()Ljavax/xml/transform/Transformer;
/*    */     //   1191: dup
/*    */     //   1192: dup
/*    */     //   1193: new javax/xml/transform/dom/DOMSource
/*    */     //   1196: dup
/*    */     //   1197: astore #7
/*    */     //   1199: aload #9
/*    */     //   1201: invokespecial <init> : (Lorg/w3c/dom/Node;)V
/*    */     //   1204: getstatic f/UB0.vj0 : Lf/XG;
/*    */     //   1207: new java/lang/StringBuilder
/*    */     //   1210: dup
/*    */     //   1211: invokespecial <init> : ()V
/*    */     //   1214: ldc_w 'dump/strings/dump_'
/*    */     //   1217: invokevirtual append : (Ljava/lang/String;)Ljava/lang/StringBuilder;
/*    */     //   1220: aload #8
/*    */     //   1222: invokevirtual append : (Ljava/lang/String;)Ljava/lang/StringBuilder;
/*    */     //   1225: invokevirtual toString : ()Ljava/lang/String;
/*    */     //   1228: invokevirtual N0 : (Ljava/lang/String;)Lf/hZ;
/*    */     //   1231: dup
/*    */     //   1232: astore #8
/*    */     //   1234: invokevirtual wT : ()Lf/RD0;
/*    */     //   1237: invokevirtual iz0 : ()V
/*    */     //   1240: new javax/xml/transform/stream/StreamResult
/*    */     //   1243: dup
/*    */     //   1244: astore #9
/*    */     //   1246: aload #8
/*    */     //   1248: invokevirtual hh : ()Ljava/io/OutputStream;
/*    */     //   1251: invokespecial <init> : (Ljava/io/OutputStream;)V
/*    */     //   1254: ldc_w 'indent'
/*    */     //   1257: ldc_w 'yes'
/*    */     //   1260: invokevirtual setOutputProperty : (Ljava/lang/String;Ljava/lang/String;)V
/*    */     //   1263: ldc_w '{http://xml.apache.org/xslt}indent-amount'
/*    */     //   1266: ldc_w '4'
/*    */     //   1269: invokevirtual setOutputProperty : (Ljava/lang/String;Ljava/lang/String;)V
/*    */     //   1272: aload #7
/*    */     //   1274: aload #9
/*    */     //   1276: invokevirtual transform : (Ljavax/xml/transform/Source;Ljavax/xml/transform/Result;)V
/*    */     //   1279: iinc #5, 1
/*    */     //   1282: goto -> 663
/*    */     //   1285: astore_2
/*    */     //   1286: getstatic f/cE.me0 : Lf/ik;
/*    */     //   1289: new java/lang/StringBuilder
/*    */     //   1292: dup
/*    */     //   1293: invokespecial <init> : ()V
/*    */     //   1296: ldc_w 'dump error archive_type = '
/*    */     //   1299: invokevirtual append : (Ljava/lang/String;)Ljava/lang/StringBuilder;
/*    */     //   1302: aload #6
/*    */     //   1304: invokevirtual append : (Ljava/lang/Object;)Ljava/lang/StringBuilder;
/*    */     //   1307: ldc_w ' region_id = '
/*    */     //   1310: invokevirtual append : (Ljava/lang/String;)Ljava/lang/StringBuilder;
/*    */     //   1313: aload_1
/*    */     //   1314: invokevirtual bO : ()B
/*    */     //   1317: invokevirtual append : (I)Ljava/lang/StringBuilder;
/*    */     //   1320: invokevirtual toString : ()Ljava/lang/String;
/*    */     //   1323: aload_2
/*    */     //   1324: invokeinterface error : (Ljava/lang/String;Ljava/lang/Throwable;)V
/*    */     //   1329: iconst_0
/*    */     //   1330: goto -> 1334
/*    */     //   1333: iconst_1
/*    */     //   1334: ifne -> 1339
/*    */     //   1337: iconst_0
/*    */     //   1338: ireturn
/*    */     //   1339: iload_0
/*    */     //   1340: iconst_1
/*    */     //   1341: iadd
/*    */     //   1342: i2b
/*    */     //   1343: istore_0
/*    */     //   1344: goto -> 2
/*    */     //   1347: iconst_1
/*    */     //   1348: ireturn
/*    */     // Line number table:
/*    */     //   Java source line number -> byte code offset
/*    */     //   #1	-> 21
/*    */     //   #2	-> 24
/*    */     //   #3	-> 28
/*    */     //   #4	-> 37
/*    */     //   #5	-> 42
/*    */     //   #6	-> 54
/*    */     //   #7	-> 60
/*    */     //   #8	-> 72
/*    */     //   #9	-> 75
/*    */     //   #10	-> 99
/*    */     //   #11	-> 105
/*    */     //   #12	-> 135
/*    */     //   #13	-> 151
/*    */     //   #14	-> 155
/*    */     //   #15	-> 163
/*    */     //   #16	-> 181
/*    */     //   #17	-> 185
/*    */     //   #18	-> 205
/*    */     //   #19	-> 208
/*    */     //   #20	-> 280
/*    */     //   #21	-> 635
/*    */     //   #22	-> 648
/*    */     //   #23	-> 684
/*    */     //   #24	-> 695
/*    */     //   #25	-> 704
/*    */     //   #26	-> 707
/*    */     //   #27	-> 720
/*    */     //   #28	-> 723
/*    */     //   #29	-> 824
/*    */     //   #30	-> 827
/*    */     //   #31	-> 856
/*    */     //   #32	-> 870
/*    */     //   #33	-> 942
/*    */     //   #34	-> 1033
/*    */     // Exception table:
/*    */     //   from	to	target	type
/*    */     //   325	336	616	java/lang/Exception
/*    */     //   340	348	616	java/lang/Exception
/*    */     //   353	389	616	java/lang/Exception
/*    */     //   390	393	616	java/lang/Exception
/*    */     //   394	400	616	java/lang/Exception
/*    */     //   403	415	616	java/lang/Exception
/*    */     //   418	427	616	java/lang/Exception
/*    */     //   430	433	616	java/lang/Exception
/*    */     //   451	454	616	java/lang/Exception
/*    */     //   460	468	616	java/lang/Exception
/*    */     //   470	479	616	java/lang/Exception
/*    */     //   480	521	616	java/lang/Exception
/*    */     //   525	536	616	java/lang/Exception
/*    */     //   538	569	616	java/lang/Exception
/*    */     //   571	580	616	java/lang/Exception
/*    */     //   582	612	616	java/lang/Exception
/*    */     //   745	754	1285	java/lang/Exception
/*    */     //   758	766	1285	java/lang/Exception
/*    */     //   771	786	1285	java/lang/Exception
/*    */     //   787	817	1285	java/lang/Exception
/*    */     //   818	848	1285	java/lang/Exception
/*    */     //   852	860	1285	java/lang/Exception
/*    */     //   866	873	1285	java/lang/Exception
/*    */     //   879	886	1285	java/lang/Exception
/*    */     //   889	890	1285	java/lang/Exception
/*    */     //   896	901	1285	java/lang/Exception
/*    */     //   904	920	1285	java/lang/Exception
/*    */     //   938	945	1285	java/lang/Exception
/*    */     //   951	958	1285	java/lang/Exception
/*    */     //   961	962	1285	java/lang/Exception
/*    */     //   968	973	1285	java/lang/Exception
/*    */     //   976	983	1285	java/lang/Exception
/*    */     //   988	998	1285	java/lang/Exception
/*    */     //   1001	1002	1285	java/lang/Exception
/*    */     //   1008	1014	1285	java/lang/Exception
/*    */     //   1029	1041	1285	java/lang/Exception
/*    */     //   1045	1061	1285	java/lang/Exception
/*    */     //   1062	1090	1285	java/lang/Exception
/*    */     //   1091	1119	1285	java/lang/Exception
/*    */     //   1120	1166	1285	java/lang/Exception
/*    */     //   1185	1196	1285	java/lang/Exception
/*    */     //   1199	1231	1285	java/lang/Exception
/*    */     //   1234	1243	1285	java/lang/Exception
/*    */     //   1246	1279	1285	java/lang/Exception
/*    */   }
/*    */   
/*    */   public final void qK0(boolean paramBoolean) {
/*    */     // Byte code:
/*    */     //   0: iload_1
/*    */     //   1: iconst_2
/*    */     //   2: dup
/*    */     //   3: istore_2
/*    */     //   4: anewarray f/RD0
/*    */     //   7: dup
/*    */     //   8: dup
/*    */     //   9: astore_3
/*    */     //   10: getstatic f/UB0.vj0 : Lf/XG;
/*    */     //   13: ldc_w 'data/strings'
/*    */     //   16: invokevirtual aP : (Ljava/lang/String;)Lf/hZ;
/*    */     //   19: iconst_0
/*    */     //   20: swap
/*    */     //   21: aastore
/*    */     //   22: getstatic f/UB0.vj0 : Lf/XG;
/*    */     //   25: ldc_w 'data/strings'
/*    */     //   28: invokevirtual N0 : (Ljava/lang/String;)Lf/hZ;
/*    */     //   31: iconst_1
/*    */     //   32: swap
/*    */     //   33: aastore
/*    */     //   34: ifeq -> 158
/*    */     //   37: aload_0
/*    */     //   38: getfield yl : Ljava/util/ArrayList;
/*    */     //   41: invokevirtual clear : ()V
/*    */     //   44: iconst_0
/*    */     //   45: istore #4
/*    */     //   47: iload #4
/*    */     //   49: iload_2
/*    */     //   50: if_icmpge -> 154
/*    */     //   53: aload_3
/*    */     //   54: iload #4
/*    */     //   56: aaload
/*    */     //   57: dup
/*    */     //   58: astore #5
/*    */     //   60: getfield KU : Lf/G20;
/*    */     //   63: getstatic f/G20.XS : Lf/G20;
/*    */     //   66: if_acmpne -> 78
/*    */     //   69: invokestatic ER : ()Z
/*    */     //   72: ifne -> 78
/*    */     //   75: goto -> 148
/*    */     //   78: aload #5
/*    */     //   80: ldc '.xml'
/*    */     //   82: invokevirtual XX : (Ljava/lang/String;)[Lf/RD0;
/*    */     //   85: dup
/*    */     //   86: astore #5
/*    */     //   88: arraylength
/*    */     //   89: istore #6
/*    */     //   91: iconst_0
/*    */     //   92: istore #7
/*    */     //   94: iload #7
/*    */     //   96: iload #6
/*    */     //   98: if_icmpge -> 148
/*    */     //   101: aload #5
/*    */     //   103: iload #7
/*    */     //   105: aaload
/*    */     //   106: astore #8
/*    */     //   108: new f/cn0
/*    */     //   111: dup
/*    */     //   112: dup
/*    */     //   113: astore #9
/*    */     //   115: aload #8
/*    */     //   117: invokespecial <init> : (Lf/RD0;)V
/*    */     //   120: getfield dG0 : Z
/*    */     //   123: ifeq -> 142
/*    */     //   126: aload_0
/*    */     //   127: getfield yl : Ljava/util/ArrayList;
/*    */     //   130: aload #9
/*    */     //   132: invokevirtual add : (Ljava/lang/Object;)Z
/*    */     //   135: pop
/*    */     //   136: goto -> 142
/*    */     //   139: invokevirtual printStackTrace : ()V
/*    */     //   142: iinc #7, 1
/*    */     //   145: goto -> 94
/*    */     //   148: iinc #4, 1
/*    */     //   151: goto -> 47
/*    */     //   154: aconst_null
/*    */     //   155: putstatic f/t90.md0 : Ljava/lang/String;
/*    */     //   158: aload_0
/*    */     //   159: getfield yl : Ljava/util/ArrayList;
/*    */     //   162: invokevirtual iterator : ()Ljava/util/Iterator;
/*    */     //   165: astore_2
/*    */     //   166: aload_2
/*    */     //   167: invokeinterface hasNext : ()Z
/*    */     //   172: ifeq -> 195
/*    */     //   175: aload_2
/*    */     //   176: invokeinterface next : ()Ljava/lang/Object;
/*    */     //   181: checkcast f/cn0
/*    */     //   184: dup
/*    */     //   185: astore_3
/*    */     //   186: getfield LA : Z
/*    */     //   189: ifeq -> 166
/*    */     //   192: goto -> 197
/*    */     //   195: aconst_null
/*    */     //   196: astore_3
/*    */     //   197: aload_3
/*    */     //   198: ifnonnull -> 215
/*    */     //   201: getstatic f/cE.me0 : Lf/ik;
/*    */     //   204: ldc_w 'ERROR: Unable to find a primary string container.'
/*    */     //   207: invokeinterface error : (Ljava/lang/String;)V
/*    */     //   212: goto -> 279
/*    */     //   215: aload_3
/*    */     //   216: iload_1
/*    */     //   217: invokevirtual f3 : (Z)V
/*    */     //   220: getstatic f/cE.me0 : Lf/ik;
/*    */     //   223: ldc_w 'Populating primary string container: '
/*    */     //   226: invokestatic df : (Ljava/lang/String;)Ljava/lang/StringBuilder;
/*    */     //   229: aload_3
/*    */     //   230: getfield lI : Ljava/lang/String;
/*    */     //   233: invokevirtual append : (Ljava/lang/String;)Ljava/lang/StringBuilder;
/*    */     //   236: ldc_w ' from '
/*    */     //   239: invokevirtual append : (Ljava/lang/String;)Ljava/lang/StringBuilder;
/*    */     //   242: aload_3
/*    */     //   243: getfield jd0 : Lf/RD0;
/*    */     //   246: invokevirtual append : (Ljava/lang/Object;)Ljava/lang/StringBuilder;
/*    */     //   249: ldc_w ' ('
/*    */     //   252: invokevirtual append : (Ljava/lang/String;)Ljava/lang/StringBuilder;
/*    */     //   255: aload_3
/*    */     //   256: getfield jd0 : Lf/RD0;
/*    */     //   259: getfield KU : Lf/G20;
/*    */     //   262: invokevirtual append : (Ljava/lang/Object;)Ljava/lang/StringBuilder;
/*    */     //   265: ldc_w ')'
/*    */     //   268: invokevirtual append : (Ljava/lang/String;)Ljava/lang/StringBuilder;
/*    */     //   271: invokevirtual toString : ()Ljava/lang/String;
/*    */     //   274: invokeinterface info : (Ljava/lang/String;)V
/*    */     //   279: aload_0
/*    */     //   280: dup
/*    */     //   281: getstatic f/h1.pB0 : Ljava/lang/String;
/*    */     //   284: invokestatic W70 : (Ljava/lang/String;)Ljava/util/Locale;
/*    */     //   287: putfield Dr : Ljava/util/Locale;
/*    */     //   290: getstatic f/h1.pB0 : Ljava/lang/String;
/*    */     //   293: invokevirtual cO : (Ljava/lang/String;)Ljava/util/ArrayList;
/*    */     //   296: invokevirtual iterator : ()Ljava/util/Iterator;
/*    */     //   299: astore_0
/*    */     //   300: aload_0
/*    */     //   301: invokeinterface hasNext : ()Z
/*    */     //   306: ifeq -> 391
/*    */     //   309: aload_0
/*    */     //   310: invokeinterface next : ()Ljava/lang/Object;
/*    */     //   315: checkcast f/cn0
/*    */     //   318: dup
/*    */     //   319: astore_2
/*    */     //   320: aload_3
/*    */     //   321: if_acmpeq -> 300
/*    */     //   324: aload_2
/*    */     //   325: iload_1
/*    */     //   326: invokevirtual f3 : (Z)V
/*    */     //   329: getstatic f/cE.me0 : Lf/ik;
/*    */     //   332: ldc_w 'Populating secondary string container: '
/*    */     //   335: invokestatic df : (Ljava/lang/String;)Ljava/lang/StringBuilder;
/*    */     //   338: aload_2
/*    */     //   339: getfield lI : Ljava/lang/String;
/*    */     //   342: invokevirtual append : (Ljava/lang/String;)Ljava/lang/StringBuilder;
/*    */     //   345: ldc_w ' from '
/*    */     //   348: invokevirtual append : (Ljava/lang/String;)Ljava/lang/StringBuilder;
/*    */     //   351: aload_2
/*    */     //   352: getfield jd0 : Lf/RD0;
/*    */     //   355: invokevirtual append : (Ljava/lang/Object;)Ljava/lang/StringBuilder;
/*    */     //   358: ldc_w ' ('
/*    */     //   361: invokevirtual append : (Ljava/lang/String;)Ljava/lang/StringBuilder;
/*    */     //   364: aload_2
/*    */     //   365: getfield jd0 : Lf/RD0;
/*    */     //   368: getfield KU : Lf/G20;
/*    */     //   371: invokevirtual append : (Ljava/lang/Object;)Ljava/lang/StringBuilder;
/*    */     //   374: ldc_w ')'
/*    */     //   377: invokevirtual append : (Ljava/lang/String;)Ljava/lang/StringBuilder;
/*    */     //   380: invokevirtual toString : ()Ljava/lang/String;
/*    */     //   383: invokeinterface info : (Ljava/lang/String;)V
/*    */     //   388: goto -> 300
/*    */     //   391: return
/*    */     // Line number table:
/*    */     //   Java source line number -> byte code offset
/*    */     //   #1	-> 38
/*    */     //   #2	-> 60
/*    */     //   #3	-> 63
/*    */     //   #4	-> 108
/*    */     //   #5	-> 120
/*    */     //   #6	-> 127
/*    */     //   #7	-> 155
/*    */     //   #8	-> 159
/*    */     //   #9	-> 186
/*    */     //   #10	-> 201
/*    */     //   #11	-> 223
/*    */     //   #12	-> 230
/*    */     //   #13	-> 233
/*    */     //   #14	-> 243
/*    */     //   #15	-> 246
/*    */     //   #16	-> 256
/*    */     //   #17	-> 259
/*    */     //   #18	-> 262
/*    */     //   #19	-> 332
/*    */     //   #20	-> 339
/*    */     //   #21	-> 342
/*    */     //   #22	-> 352
/*    */     //   #23	-> 355
/*    */     //   #24	-> 365
/*    */     //   #25	-> 368
/*    */     //   #26	-> 371
/*    */     // Exception table:
/*    */     //   from	to	target	type
/*    */     //   108	111	139	java/lang/Exception
/*    */     //   115	123	139	java/lang/Exception
/*    */     //   126	135	139	java/lang/Exception
/*    */   }
/*    */   
/*    */   public final String P00() {
/*    */     // Byte code:
/*    */     //   0: invokestatic getDefault : ()Ljava/util/Locale;
/*    */     //   3: dup
/*    */     //   4: dup
/*    */     //   5: astore_1
/*    */     //   6: ldc ''
/*    */     //   8: astore_2
/*    */     //   9: invokevirtual getLanguage : ()Ljava/lang/String;
/*    */     //   12: astore_3
/*    */     //   13: invokevirtual getCountry : ()Ljava/lang/String;
/*    */     //   16: invokevirtual isEmpty : ()Z
/*    */     //   19: ifne -> 39
/*    */     //   22: aload_3
/*    */     //   23: ldc '-'
/*    */     //   25: invokestatic vz : (Ljava/lang/String;Ljava/lang/String;)Ljava/lang/StringBuilder;
/*    */     //   28: aload_1
/*    */     //   29: invokevirtual getCountry : ()Ljava/lang/String;
/*    */     //   32: invokevirtual append : (Ljava/lang/String;)Ljava/lang/StringBuilder;
/*    */     //   35: invokevirtual toString : ()Ljava/lang/String;
/*    */     //   38: astore_3
/*    */     //   39: aload_1
/*    */     //   40: invokevirtual getScript : ()Ljava/lang/String;
/*    */     //   43: ldc_w 'hant'
/*    */     //   46: invokevirtual equalsIgnoreCase : (Ljava/lang/String;)Z
/*    */     //   49: ifeq -> 56
/*    */     //   52: ldc_w 'zh-Hant'
/*    */     //   55: astore_3
/*    */     //   56: aload_3
/*    */     //   57: getstatic f/LF.xL0 : Lf/ik;
/*    */     //   60: pop
/*    */     //   61: iconst_1
/*    */     //   62: iconst_0
/*    */     //   63: ldc_w 'zh-TW'
/*    */     //   66: iconst_0
/*    */     //   67: iconst_5
/*    */     //   68: invokevirtual regionMatches : (ZILjava/lang/String;II)Z
/*    */     //   71: ifne -> 88
/*    */     //   74: aload_3
/*    */     //   75: iconst_1
/*    */     //   76: iconst_0
/*    */     //   77: ldc_w 'zh-HK'
/*    */     //   80: iconst_0
/*    */     //   81: iconst_5
/*    */     //   82: invokevirtual regionMatches : (ZILjava/lang/String;II)Z
/*    */     //   85: ifeq -> 92
/*    */     //   88: ldc_w 'zh-Hant'
/*    */     //   91: astore_3
/*    */     //   92: aload_3
/*    */     //   93: bipush #45
/*    */     //   95: invokevirtual indexOf : (I)I
/*    */     //   98: aload_3
/*    */     //   99: bipush #45
/*    */     //   101: invokevirtual lastIndexOf : (I)I
/*    */     //   104: if_icmpeq -> 123
/*    */     //   107: aload_3
/*    */     //   108: dup
/*    */     //   109: bipush #45
/*    */     //   111: invokevirtual lastIndexOf : (I)I
/*    */     //   114: iconst_0
/*    */     //   115: swap
/*    */     //   116: invokevirtual substring : (II)Ljava/lang/String;
/*    */     //   119: astore_3
/*    */     //   120: goto -> 92
/*    */     //   123: aload_0
/*    */     //   124: getfield yl : Ljava/util/ArrayList;
/*    */     //   127: invokevirtual iterator : ()Ljava/util/Iterator;
/*    */     //   130: astore_1
/*    */     //   131: aload_1
/*    */     //   132: invokeinterface hasNext : ()Z
/*    */     //   137: ifeq -> 245
/*    */     //   140: aload_1
/*    */     //   141: invokeinterface next : ()Ljava/lang/Object;
/*    */     //   146: checkcast f/cn0
/*    */     //   149: dup
/*    */     //   150: astore #4
/*    */     //   152: getfield lI : Ljava/lang/String;
/*    */     //   155: aload_3
/*    */     //   156: invokevirtual equalsIgnoreCase : (Ljava/lang/String;)Z
/*    */     //   159: ifeq -> 171
/*    */     //   162: aload #4
/*    */     //   164: getfield lI : Ljava/lang/String;
/*    */     //   167: astore_2
/*    */     //   168: goto -> 296
/*    */     //   171: aload #4
/*    */     //   173: getfield lI : Ljava/lang/String;
/*    */     //   176: invokevirtual length : ()I
/*    */     //   179: iconst_2
/*    */     //   180: if_icmple -> 198
/*    */     //   183: aload #4
/*    */     //   185: getfield lI : Ljava/lang/String;
/*    */     //   188: iconst_0
/*    */     //   189: iconst_2
/*    */     //   190: invokevirtual substring : (II)Ljava/lang/String;
/*    */     //   193: astore #5
/*    */     //   195: goto -> 205
/*    */     //   198: aload #4
/*    */     //   200: getfield lI : Ljava/lang/String;
/*    */     //   203: astore #5
/*    */     //   205: aload_3
/*    */     //   206: aload #5
/*    */     //   208: invokestatic M60 : (Ljava/lang/String;Ljava/lang/String;)Z
/*    */     //   211: ifeq -> 131
/*    */     //   214: aload_2
/*    */     //   215: invokevirtual isEmpty : ()Z
/*    */     //   218: ifne -> 236
/*    */     //   221: aload #4
/*    */     //   223: getfield lI : Ljava/lang/String;
/*    */     //   226: invokevirtual length : ()I
/*    */     //   229: aload_2
/*    */     //   230: invokevirtual length : ()I
/*    */     //   233: if_icmpge -> 131
/*    */     //   236: aload #4
/*    */     //   238: getfield lI : Ljava/lang/String;
/*    */     //   241: astore_2
/*    */     //   242: goto -> 131
/*    */     //   245: aload_2
/*    */     //   246: invokevirtual isEmpty : ()Z
/*    */     //   249: ifeq -> 296
/*    */     //   252: aload_0
/*    */     //   253: getfield yl : Ljava/util/ArrayList;
/*    */     //   256: invokevirtual iterator : ()Ljava/util/Iterator;
/*    */     //   259: astore_0
/*    */     //   260: aload_0
/*    */     //   261: invokeinterface hasNext : ()Z
/*    */     //   266: ifeq -> 289
/*    */     //   269: aload_0
/*    */     //   270: invokeinterface next : ()Ljava/lang/Object;
/*    */     //   275: checkcast f/cn0
/*    */     //   278: dup
/*    */     //   279: astore_1
/*    */     //   280: getfield LA : Z
/*    */     //   283: ifeq -> 260
/*    */     //   286: goto -> 291
/*    */     //   289: aconst_null
/*    */     //   290: astore_1
/*    */     //   291: aload_1
/*    */     //   292: getfield lI : Ljava/lang/String;
/*    */     //   295: astore_2
/*    */     //   296: aload_2
/*    */     //   297: areturn
/*    */     // Line number table:
/*    */     //   Java source line number -> byte code offset
/*    */     //   #1	-> 6
/*    */     //   #2	-> 23
/*    */     //   #3	-> 29
/*    */     //   #4	-> 63
/*    */     //   #5	-> 88
/*    */     //   #6	-> 152
/*    */     //   #7	-> 156
/*    */     //   #8	-> 164
/*    */     //   #9	-> 173
/*    */     //   #10	-> 208
/*    */     //   #11	-> 223
/*    */     //   #12	-> 226
/*    */     //   #13	-> 238
/*    */     //   #14	-> 246
/*    */     //   #15	-> 253
/*    */     //   #16	-> 280
/*    */     //   #17	-> 292
/*    */   }
/*    */   
/*    */   public final Locale PH() {
/*    */     return this.Dr;
/*    */   }
/*    */   
/*    */   public final String nB(String paramString) {
/*    */     for (Iterator iterator = this.yl.iterator(); hasNext();) {
/*    */       if (paramString.equals((cn0 = (cn0)next()).lI) && cn0.H30.length() > paramString.length())
/*    */         return cn0.H30; 
/*    */     } 
/*    */     return paramString;
/*    */   }
/*    */   
/*    */   public final boolean sG(String paramString) {
/*    */     if (!"en".equals(paramString))
/*    */       sG("en"); 
/*    */     this.Dr = W70(paramString);
/*    */     ArrayList<?> arrayList;
/*    */     if ((arrayList = cO(paramString)).isEmpty())
/*    */       return false; 
/*    */     Iterator<E> iterator;
/*    */     for (t90.md0 = null, iterator = iterator(); hasNext(); ) {
/*    */       cn0 cn0;
/*    */       String str;
/*    */       if ((str = (cn0 = (cn0)next()).TO) != null)
/*    */         t90.md0 = str; 
/*    */       cn0.f3(false);
/*    */     } 
/*    */     UB0.Kg0.fN(new Cu0(paramString));
/*    */     return true;
/*    */   }
/*    */   
/*    */   public final boolean DB() {
/*    */     boolean bool = false;
/*    */     Iterator<cn0> iterator = this.yl.iterator();
/*    */     while (iterator.hasNext()) {
/*    */       if (!((cn0)iterator.next()).Ha0())
/*    */         bool = true; 
/*    */     } 
/*    */     return bool ^ true;
/*    */   }
/*    */   
/*    */   public final ArrayList cO(String paramString) {
/*    */     this();
/*    */     ArrayList<cn0> arrayList;
/*    */     for (Iterator<cn0> iterator1 = this.yl.iterator(); iterator1.hasNext();) {
/*    */       if ((cn0 = iterator1.next()).Wc == 1 && paramString.equals(cn0.lI))
/*    */         arrayList.add(cn0); 
/*    */     } 
/*    */     for (Iterator iterator = this.yl.iterator(); hasNext();) {
/*    */       if ((cn0 = (cn0)next()).Wc == 0 && paramString.equals(cn0.lI))
/*    */         arrayList.add(cn0); 
/*    */     } 
/*    */     arrayList.sort(cE::LPT1);
/*    */     return arrayList;
/*    */   } }


/* Location:              /Users/vnnsnnt/Documents/Codespace/JavaWorkspace/RedTrainer/src/main/java/org/trainer/client/PokeMMO.jar!/f/cE.class
 * Java compiler version: 8 (52.0)
 * JD-Core Version:       1.1.3
 */