package f;

public final class Cf0 extends Fy0 {
  public Cf0(fr paramfr, C6 paramC6, int paramInt) {
    // Byte code:
    //   0: aload_0
    //   1: aload_1
    //   2: aload_2
    //   3: aload_0
    //   4: dup
    //   5: dup
    //   6: dup2
    //   7: dup2
    //   8: iload_3
    //   9: bipush #16
    //   11: imul
    //   12: istore_0
    //   13: ldc ''
    //   15: iload_0
    //   16: dup
    //   17: invokespecial <init> : (Ljava/lang/String;II)V
    //   20: invokevirtual zY : ()Lf/rH;
    //   23: invokestatic ds0 : ()Lf/NL;
    //   26: invokevirtual fr : ()[Lf/zh0;
    //   29: invokevirtual sm : ([Lf/zh0;)V
    //   32: invokevirtual zY : ()Lf/rH;
    //   35: iload_3
    //   36: bipush #-3
    //   38: imul
    //   39: dup
    //   40: invokevirtual zT : (II)Lf/JG0;
    //   43: pop
    //   44: invokevirtual zY : ()Lf/rH;
    //   47: invokevirtual HY : ()V
    //   50: invokevirtual zY : ()Lf/rH;
    //   53: sipush #800
    //   56: invokevirtual EV : (I)V
    //   59: invokevirtual zY : ()Lf/rH;
    //   62: iload_0
    //   63: dup
    //   64: invokevirtual tL : (II)V
    //   67: ldc 'townmap-cursor'
    //   69: invokevirtual Xu : (Ljava/lang/String;)V
    //   72: <illegal opcode> run : (Lf/fr;Lf/C6;)Ljava/lang/Runnable;
    //   77: invokevirtual tW : (Ljava/lang/Runnable;)V
    //   80: return
  }
}


/* Location:              /Users/vnnsnnt/Documents/Codespace/JavaWorkspace/RedTrainer/src/main/java/org/trainer/client/PokeMMO.jar!/f/Cf0.class
 * Java compiler version: 8 (52.0)
 * JD-Core Version:       1.1.3
 */