/*    */ package f;public final class ck extends JG0 { public final wg0 xs0; public dQ c60; public dQ kK0; public rS za0; public Un LPt3; public Un CD; public Un Lg0; private void lP(Y paramY) { short s;
/*  2 */     if ((s = paramY.Lh.Sf0) > 1)
/*    */     { Ok0 ok0; AD0 aD02, aD01;
/*  4 */       if ((aD01 = (AD0)vC0.Bv0(js.vu0, AD0.class)) != null) { VA0.c90(aD01);
/*    */         
/*    */         return; }
/*    */       
/*  8 */       String str = Ml0.Go(1432, Ml0.OH0(paramY.Bp0.Iu)); this(this, paramY);
/*    */ 
/*    */       
/* 11 */       this(str, s, ok0, this.fr0);
/* 12 */       js.vu0
/*    */         
/* 14 */         .si(aD02, js.vu0.Ub()); }
/* 15 */     else { ((wg0)this.fr0)
/*    */         
/* 17 */         .sd0(paramY, (short)1); }  } public Un synchronized; public Un wI; public Un kN; public Un Cq0; public Un Es0; public vF0 ZY; public pQ K70; public ck(wg0 paramwg0) { Xu("inventory-item-info"); this.xs0 = paramwg0; this.c60 = new dQ(); this.kK0 = new dQ(); this.za0 = new rS(this.kK0); this.LPt3 = new Un(Ml0.OH0(1410)); this.CD = new Un(Ml0.OH0(3006)); this.Lg0 = new Un(Ml0.OH0(1412)); this.synchronized = new Un(Ml0.OH0(1414)); this.wI = new Un(Ml0.OH0(1411)); this.kN = new Un(Ml0.OH0(8551)); this.Cq0 = new Un(Ml0.OH0(8571)); this.Es0 = new Un(Ml0.OH0(1424)); this.ZY = new vF0(180, 128); this.LPt3.wI0(false); this.CD.wI0(false); this.Lg0.wI0(false); this.synchronized.wI0(false); this.wI.wI0(false); this.kN.wI0(false); this.Cq0.wI0(false); this.Es0.wI0(false); J8(this.c60); J8(this.za0); J8(this.LPt3); J8(this.CD); J8(this.Lg0); J8(this.synchronized); J8(this.wI); J8(this.kN); J8(this.Cq0); J8(this.Es0); J8(this.ZY); } private void oh0(Y paramY) { boolean bool = false; ((wg0)this.fr0).ZN((short)372, bool, paramY.Lh.Wy, (short)0, (byte)-1); } private void Yx0(Y paramY1, Y paramY2) { if (paramY1 == null) { km.u4.Pq(Ml0.OH0(8580)); return; }  short s = paramY1.Lh.p1; int i = paramY1.Lh.Wy; ((wg0)this.fr0).ZN(s, i, paramY2.Lh.Wy, (short)1, (byte)-1); } private void LPT8(Y paramY) { ((wg0)this.fr0).ty(paramY, true); } public final void d40() { Tm(600, this.fr0.HC - 60); QJ0(et.t9, 0, 60); this.za0.uh0(400, this.HC - 50); this.za0.RI(400, this.HC - 50); for (Hc0 hc0 = this.Li0.r30(); hc0.hasNext(); ((JG0)hc0.next()).mM()); this.c60.ec(et.kL0, 10); et et; this.za0.ec(et = et.Em, 40); pQ pQ1; if ((pQ1 = this.K70) != null) pQ1.ec(et, 40);  this.ZY.ec(et = et.t9, 50); char c = '´'; Un un2; if ((un2 = this.LPt3).dP) { un2.ec(et, c); c = 'ð'; }  if ((un2 = this.CD).dP) { un2.ec(et, c); c += '<'; }  if ((un2 = this.Lg0).dP) { un2.ec(et, c); c += '<'; }  if ((un2 = this.synchronized).dP) { un2.ec(et, c); c += '<'; }  if ((un2 = this.wI).dP) { un2.ec(et, c); c += '<'; }  if ((un2 = this.Cq0)
/* 18 */       .dP) { un2
/* 19 */         .ec(et, c); c += '<'; }  if ((un2 = this.kN)
/* 20 */       .dP) { un2
/* 21 */         .ec(et, c); c += '<'; }  Un un1; if ((un1 = this.Es0)
/* 22 */       .dP)
/* 23 */       ec(et, c);  }
/*    */ 
/*    */   
/*    */   private void J80(Y paramY) {
/*    */     xJ0 xJ0;
/*    */     if ((xJ0 = pA.Dg0.WH) != null) {
/*    */       xJ0.Rj(paramY.Lh.p1, (short)0);
/*    */       js.vu0.Pu(-1, Ml0.Go(1416, paramY.JG0()));
/*    */     } 
/*    */     VJ(paramY);
/*    */   }
/*    */   
/*    */   private void M00(Y paramY) {
/*    */     this.xs0.close();
/*    */     Gp0 gp0;
/*    */     if ((gp0 = Lj.UK0(paramY.Bp0.KI)) == null)
/*    */       return; 
/*    */     this();
/*    */     e50 e50;
/*    */     this.W.add(this);
/*    */     km.MR = this;
/*    */   }
/*    */   
/*    */   private void k80(Y paramY) {
/*    */     ((wg0)this.fr0).SL0(paramY);
/*    */   }
/*    */   
/*    */   public final void VJ(Y paramY) {
/*    */     // Byte code:
/*    */     //   0: aload_0
/*    */     //   1: dup
/*    */     //   2: dup
/*    */     //   3: dup2
/*    */     //   4: dup2
/*    */     //   5: dup2
/*    */     //   6: getfield LPt3 : Lf/Un;
/*    */     //   9: iconst_0
/*    */     //   10: invokevirtual wI0 : (Z)V
/*    */     //   13: getfield CD : Lf/Un;
/*    */     //   16: iconst_0
/*    */     //   17: invokevirtual wI0 : (Z)V
/*    */     //   20: getfield Lg0 : Lf/Un;
/*    */     //   23: iconst_0
/*    */     //   24: invokevirtual wI0 : (Z)V
/*    */     //   27: getfield synchronized : Lf/Un;
/*    */     //   30: iconst_0
/*    */     //   31: invokevirtual wI0 : (Z)V
/*    */     //   34: getfield wI : Lf/Un;
/*    */     //   37: iconst_0
/*    */     //   38: invokevirtual wI0 : (Z)V
/*    */     //   41: getfield kN : Lf/Un;
/*    */     //   44: iconst_0
/*    */     //   45: invokevirtual wI0 : (Z)V
/*    */     //   48: getfield Cq0 : Lf/Un;
/*    */     //   51: iconst_0
/*    */     //   52: invokevirtual wI0 : (Z)V
/*    */     //   55: getfield Es0 : Lf/Un;
/*    */     //   58: iconst_0
/*    */     //   59: invokevirtual wI0 : (Z)V
/*    */     //   62: getfield K70 : Lf/pQ;
/*    */     //   65: dup
/*    */     //   66: astore_2
/*    */     //   67: ifnull -> 76
/*    */     //   70: aload_0
/*    */     //   71: aload_2
/*    */     //   72: invokevirtual jf0 : (Lf/JG0;)Z
/*    */     //   75: pop
/*    */     //   76: aload_1
/*    */     //   77: ifnonnull -> 111
/*    */     //   80: aload_0
/*    */     //   81: dup
/*    */     //   82: dup
/*    */     //   83: getfield ZY : Lf/vF0;
/*    */     //   86: getfield TS : Lf/rH;
/*    */     //   89: invokevirtual H : ()V
/*    */     //   92: getfield c60 : Lf/dQ;
/*    */     //   95: ldc_w ''
/*    */     //   98: invokevirtual E1 : (Ljava/lang/String;)V
/*    */     //   101: getfield kK0 : Lf/dQ;
/*    */     //   104: ldc_w ''
/*    */     //   107: invokevirtual E1 : (Ljava/lang/String;)V
/*    */     //   110: return
/*    */     //   111: aload_1
/*    */     //   112: getfield Bp0 : Lf/LPT3;
/*    */     //   115: dup
/*    */     //   116: astore_2
/*    */     //   117: getfield c3 : Lf/wc;
/*    */     //   120: ifnull -> 182
/*    */     //   123: aload_0
/*    */     //   124: dup
/*    */     //   125: dup
/*    */     //   126: dup2
/*    */     //   127: new f/pQ
/*    */     //   130: dup
/*    */     //   131: dup
/*    */     //   132: astore_3
/*    */     //   133: aload_2
/*    */     //   134: aload_1
/*    */     //   135: getfield Lh : Lf/nH0;
/*    */     //   138: getfield Nj : B
/*    */     //   141: iconst_0
/*    */     //   142: iconst_0
/*    */     //   143: ldc_w ''
/*    */     //   146: invokespecial <init> : (Lf/LPT3;BZZLjava/lang/String;)V
/*    */     //   149: putfield K70 : Lf/pQ;
/*    */     //   152: invokevirtual Ub : ()I
/*    */     //   155: aload_3
/*    */     //   156: swap
/*    */     //   157: invokevirtual si : (Lf/JG0;I)V
/*    */     //   160: getfield kK0 : Lf/dQ;
/*    */     //   163: ldc_w ''
/*    */     //   166: invokevirtual E1 : (Ljava/lang/String;)V
/*    */     //   169: getfield c60 : Lf/dQ;
/*    */     //   172: aload_1
/*    */     //   173: invokevirtual JG0 : ()Ljava/lang/String;
/*    */     //   176: invokevirtual E1 : (Ljava/lang/String;)V
/*    */     //   179: goto -> 206
/*    */     //   182: aload_0
/*    */     //   183: dup
/*    */     //   184: getfield kK0 : Lf/dQ;
/*    */     //   187: aload_2
/*    */     //   188: iconst_0
/*    */     //   189: iconst_0
/*    */     //   190: invokestatic Qb0 : (Lf/LPT3;ZZ)Ljava/lang/String;
/*    */     //   193: invokevirtual E1 : (Ljava/lang/String;)V
/*    */     //   196: getfield c60 : Lf/dQ;
/*    */     //   199: aload_1
/*    */     //   200: invokevirtual JG0 : ()Ljava/lang/String;
/*    */     //   203: invokevirtual E1 : (Ljava/lang/String;)V
/*    */     //   206: aload_1
/*    */     //   207: aload_0
/*    */     //   208: dup
/*    */     //   209: dup
/*    */     //   210: getfield ZY : Lf/vF0;
/*    */     //   213: getfield TS : Lf/rH;
/*    */     //   216: iconst_1
/*    */     //   217: anewarray f/U70
/*    */     //   220: dup
/*    */     //   221: getstatic f/wm0.y0 : Lf/wm0;
/*    */     //   224: aload_1
/*    */     //   225: getfield Bp0 : Lf/LPT3;
/*    */     //   228: iconst_0
/*    */     //   229: invokevirtual HR : (Lf/LPT3;Z)Lf/U70;
/*    */     //   232: iconst_0
/*    */     //   233: swap
/*    */     //   234: aastore
/*    */     //   235: invokevirtual qt : ([Lf/U70;)Lf/JG0;
/*    */     //   238: pop
/*    */     //   239: getfield ZY : Lf/vF0;
/*    */     //   242: getfield TS : Lf/rH;
/*    */     //   245: bipush #96
/*    */     //   247: bipush #96
/*    */     //   249: invokevirtual tL : (II)V
/*    */     //   252: getfield ZY : Lf/vF0;
/*    */     //   255: getfield TS : Lf/rH;
/*    */     //   258: getstatic f/et.Wi0 : Lf/et;
/*    */     //   261: invokevirtual uE0 : (Lf/et;)V
/*    */     //   264: getfield Bp0 : Lf/LPT3;
/*    */     //   267: iconst_0
/*    */     //   268: invokevirtual default : (Z)Lf/dv;
/*    */     //   271: getstatic f/dv.wS : Lf/dv;
/*    */     //   274: if_acmpeq -> 466
/*    */     //   277: getstatic f/km.MR : Lf/Gp0;
/*    */     //   280: ifnonnull -> 466
/*    */     //   283: getstatic f/km.u4 : Lf/R8;
/*    */     //   286: invokevirtual NR : ()Z
/*    */     //   289: ifne -> 466
/*    */     //   292: aload_1
/*    */     //   293: aload_0
/*    */     //   294: dup
/*    */     //   295: getfield LPt3 : Lf/Un;
/*    */     //   298: iconst_1
/*    */     //   299: invokevirtual wI0 : (Z)V
/*    */     //   302: getfield LPt3 : Lf/Un;
/*    */     //   305: dup
/*    */     //   306: astore_2
/*    */     //   307: aload_0
/*    */     //   308: aload_1
/*    */     //   309: aload_2
/*    */     //   310: getfield TG0 : Lf/protected;
/*    */     //   313: aconst_null
/*    */     //   314: putfield oh0 : [Ljava/lang/Runnable;
/*    */     //   317: <illegal opcode> run : (Lf/ck;Lf/Y;)Ljava/lang/Runnable;
/*    */     //   322: invokevirtual tW : (Ljava/lang/Runnable;)V
/*    */     //   325: getfield Bp0 : Lf/LPT3;
/*    */     //   328: getfield KI : Lf/mA;
/*    */     //   331: getstatic f/mA.uZ : Lf/mA;
/*    */     //   334: if_acmpeq -> 369
/*    */     //   337: aload_0
/*    */     //   338: dup
/*    */     //   339: getfield CD : Lf/Un;
/*    */     //   342: iconst_1
/*    */     //   343: invokevirtual wI0 : (Z)V
/*    */     //   346: getfield CD : Lf/Un;
/*    */     //   349: dup
/*    */     //   350: astore_2
/*    */     //   351: aload_0
/*    */     //   352: aload_1
/*    */     //   353: aload_2
/*    */     //   354: getfield TG0 : Lf/protected;
/*    */     //   357: aconst_null
/*    */     //   358: putfield oh0 : [Ljava/lang/Runnable;
/*    */     //   361: <illegal opcode> run : (Lf/ck;Lf/Y;)Ljava/lang/Runnable;
/*    */     //   366: invokevirtual tW : (Ljava/lang/Runnable;)V
/*    */     //   369: iconst_m1
/*    */     //   370: istore_2
/*    */     //   371: getstatic f/pA.Dg0 : Lf/pA;
/*    */     //   374: getfield WH : Lf/xJ0;
/*    */     //   377: dup
/*    */     //   378: astore_3
/*    */     //   379: ifnull -> 394
/*    */     //   382: aload_3
/*    */     //   383: aload_1
/*    */     //   384: getfield Lh : Lf/nH0;
/*    */     //   387: getfield p1 : S
/*    */     //   390: invokevirtual dk0 : (S)B
/*    */     //   393: istore_2
/*    */     //   394: iload_2
/*    */     //   395: iconst_m1
/*    */     //   396: if_icmple -> 434
/*    */     //   399: aload_0
/*    */     //   400: dup
/*    */     //   401: getfield synchronized : Lf/Un;
/*    */     //   404: iconst_1
/*    */     //   405: invokevirtual wI0 : (Z)V
/*    */     //   408: getfield synchronized : Lf/Un;
/*    */     //   411: dup
/*    */     //   412: astore_2
/*    */     //   413: aload_0
/*    */     //   414: aload_1
/*    */     //   415: aload_2
/*    */     //   416: getfield TG0 : Lf/protected;
/*    */     //   419: aconst_null
/*    */     //   420: putfield oh0 : [Ljava/lang/Runnable;
/*    */     //   423: <illegal opcode> run : (Lf/ck;Lf/Y;)Ljava/lang/Runnable;
/*    */     //   428: invokevirtual tW : (Ljava/lang/Runnable;)V
/*    */     //   431: goto -> 466
/*    */     //   434: aload_0
/*    */     //   435: dup
/*    */     //   436: getfield Lg0 : Lf/Un;
/*    */     //   439: iconst_1
/*    */     //   440: invokevirtual wI0 : (Z)V
/*    */     //   443: getfield Lg0 : Lf/Un;
/*    */     //   446: dup
/*    */     //   447: getfield TG0 : Lf/protected;
/*    */     //   450: aconst_null
/*    */     //   451: putfield oh0 : [Ljava/lang/Runnable;
/*    */     //   454: new f/OX
/*    */     //   457: dup
/*    */     //   458: aload_0
/*    */     //   459: aload_1
/*    */     //   460: invokespecial <init> : (Lf/ck;Lf/Y;)V
/*    */     //   463: invokevirtual tW : (Ljava/lang/Runnable;)V
/*    */     //   466: aload_1
/*    */     //   467: getfield Bp0 : Lf/LPT3;
/*    */     //   470: dup
/*    */     //   471: astore_2
/*    */     //   472: getfield Y8 : Lf/Hu0;
/*    */     //   475: dup
/*    */     //   476: astore_3
/*    */     //   477: getstatic f/Hu0.Bm : Lf/Hu0;
/*    */     //   480: if_acmpeq -> 529
/*    */     //   483: aload_3
/*    */     //   484: getstatic f/Hu0.w2 : Lf/Hu0;
/*    */     //   487: if_acmpeq -> 529
/*    */     //   490: aload_2
/*    */     //   491: getfield kd : Z
/*    */     //   494: ifeq -> 529
/*    */     //   497: aload_0
/*    */     //   498: dup
/*    */     //   499: getfield wI : Lf/Un;
/*    */     //   502: iconst_1
/*    */     //   503: invokevirtual wI0 : (Z)V
/*    */     //   506: getfield wI : Lf/Un;
/*    */     //   509: dup
/*    */     //   510: astore_2
/*    */     //   511: aload_0
/*    */     //   512: aload_1
/*    */     //   513: aload_2
/*    */     //   514: getfield TG0 : Lf/protected;
/*    */     //   517: aconst_null
/*    */     //   518: putfield oh0 : [Ljava/lang/Runnable;
/*    */     //   521: <illegal opcode> run : (Lf/ck;Lf/Y;)Ljava/lang/Runnable;
/*    */     //   526: invokevirtual tW : (Ljava/lang/Runnable;)V
/*    */     //   529: aload_1
/*    */     //   530: getfield Lh : Lf/nH0;
/*    */     //   533: getfield b8 : Lf/yM;
/*    */     //   536: getfield Gq : Z
/*    */     //   539: ifeq -> 648
/*    */     //   542: aload_1
/*    */     //   543: getfield Bp0 : Lf/LPT3;
/*    */     //   546: invokevirtual lF0 : ()Z
/*    */     //   549: ifeq -> 648
/*    */     //   552: aload_1
/*    */     //   553: getfield Bp0 : Lf/LPT3;
/*    */     //   556: getfield bj0 : S
/*    */     //   559: sipush #1446
/*    */     //   562: if_icmpeq -> 648
/*    */     //   565: aload_0
/*    */     //   566: dup
/*    */     //   567: dup2
/*    */     //   568: getstatic f/km.u4 : Lf/R8;
/*    */     //   571: getstatic f/yM.r4 : Lf/yM;
/*    */     //   574: pop
/*    */     //   575: getfield Fe : [Lf/zr0;
/*    */     //   578: iconst_1
/*    */     //   579: aaload
/*    */     //   580: sipush #1028
/*    */     //   583: invokevirtual C8 : (S)Lf/Y;
/*    */     //   586: astore_2
/*    */     //   587: getfield kN : Lf/Un;
/*    */     //   590: iconst_1
/*    */     //   591: invokevirtual wI0 : (Z)V
/*    */     //   594: getfield kN : Lf/Un;
/*    */     //   597: dup
/*    */     //   598: astore_3
/*    */     //   599: aload_0
/*    */     //   600: aload_2
/*    */     //   601: aload_1
/*    */     //   602: aload_3
/*    */     //   603: getfield TG0 : Lf/protected;
/*    */     //   606: aconst_null
/*    */     //   607: putfield oh0 : [Ljava/lang/Runnable;
/*    */     //   610: <illegal opcode> run : (Lf/ck;Lf/Y;Lf/Y;)Ljava/lang/Runnable;
/*    */     //   615: invokevirtual tW : (Ljava/lang/Runnable;)V
/*    */     //   618: getfield Cq0 : Lf/Un;
/*    */     //   621: iconst_1
/*    */     //   622: invokevirtual wI0 : (Z)V
/*    */     //   625: getfield Cq0 : Lf/Un;
/*    */     //   628: dup
/*    */     //   629: astore_2
/*    */     //   630: aload_0
/*    */     //   631: aload_1
/*    */     //   632: aload_2
/*    */     //   633: getfield TG0 : Lf/protected;
/*    */     //   636: aconst_null
/*    */     //   637: putfield oh0 : [Ljava/lang/Runnable;
/*    */     //   640: <illegal opcode> run : (Lf/ck;Lf/Y;)Ljava/lang/Runnable;
/*    */     //   645: invokevirtual tW : (Ljava/lang/Runnable;)V
/*    */     //   648: aload_1
/*    */     //   649: getfield Bp0 : Lf/LPT3;
/*    */     //   652: iconst_1
/*    */     //   653: invokevirtual rg0 : (Z)Z
/*    */     //   656: ifeq -> 691
/*    */     //   659: aload_0
/*    */     //   660: dup
/*    */     //   661: getfield Es0 : Lf/Un;
/*    */     //   664: iconst_1
/*    */     //   665: invokevirtual wI0 : (Z)V
/*    */     //   668: getfield Es0 : Lf/Un;
/*    */     //   671: dup
/*    */     //   672: astore_2
/*    */     //   673: aload_0
/*    */     //   674: aload_1
/*    */     //   675: aload_2
/*    */     //   676: getfield TG0 : Lf/protected;
/*    */     //   679: aconst_null
/*    */     //   680: putfield oh0 : [Ljava/lang/Runnable;
/*    */     //   683: <illegal opcode> run : (Lf/ck;Lf/Y;)Ljava/lang/Runnable;
/*    */     //   688: invokevirtual tW : (Ljava/lang/Runnable;)V
/*    */     //   691: aload_0
/*    */     //   692: invokevirtual d40 : ()V
/*    */     //   695: return
/*    */     // Line number table:
/*    */     //   Java source line number -> byte code offset
/*    */     //   #1	-> 86
/*    */     //   #2	-> 89
/*    */     //   #3	-> 112
/*    */     //   #4	-> 117
/*    */     //   #5	-> 127
/*    */     //   #6	-> 135
/*    */     //   #7	-> 138
/*    */     //   #8	-> 143
/*    */     //   #9	-> 152
/*    */     //   #10	-> 160
/*    */     //   #11	-> 213
/*    */     //   #12	-> 217
/*    */     //   #13	-> 221
/*    */     //   #14	-> 225
/*    */     //   #15	-> 229
/*    */     //   #16	-> 234
/*    */     //   #17	-> 242
/*    */     //   #18	-> 249
/*    */     //   #19	-> 255
/*    */     //   #20	-> 258
/*    */     //   #21	-> 264
/*    */     //   #22	-> 268
/*    */     //   #23	-> 310
/*    */     //   #24	-> 314
/*    */     //   #25	-> 317
/*    */     //   #26	-> 325
/*    */     //   #27	-> 328
/*    */     //   #28	-> 331
/*    */     //   #29	-> 354
/*    */     //   #30	-> 358
/*    */     //   #31	-> 361
/*    */     //   #32	-> 371
/*    */     //   #33	-> 374
/*    */     //   #34	-> 384
/*    */     //   #35	-> 387
/*    */     //   #36	-> 390
/*    */     //   #37	-> 416
/*    */     //   #38	-> 420
/*    */     //   #39	-> 423
/*    */     //   #40	-> 447
/*    */     //   #41	-> 451
/*    */     //   #42	-> 454
/*    */     //   #43	-> 467
/*    */     //   #44	-> 472
/*    */     //   #45	-> 477
/*    */     //   #46	-> 491
/*    */     //   #47	-> 499
/*    */     //   #48	-> 514
/*    */     //   #49	-> 518
/*    */     //   #50	-> 521
/*    */     //   #51	-> 530
/*    */     //   #52	-> 533
/*    */     //   #53	-> 536
/*    */     //   #54	-> 543
/*    */     //   #55	-> 546
/*    */     //   #56	-> 553
/*    */     //   #57	-> 556
/*    */     //   #58	-> 568
/*    */     //   #59	-> 575
/*    */     //   #60	-> 579
/*    */     //   #61	-> 583
/*    */     //   #62	-> 603
/*    */     //   #63	-> 607
/*    */     //   #64	-> 610
/*    */     //   #65	-> 633
/*    */     //   #66	-> 637
/*    */     //   #67	-> 640
/*    */     //   #68	-> 649
/*    */     //   #69	-> 653
/*    */     //   #70	-> 661
/*    */     //   #71	-> 676
/*    */     //   #72	-> 680
/*    */     //   #73	-> 683
/*    */   } }


/* Location:              /Users/vnnsnnt/Documents/Codespace/JavaWorkspace/RedTrainer/src/main/java/org/trainer/client/PokeMMO.jar!/f/ck.class
 * Java compiler version: 8 (52.0)
 * JD-Core Version:       1.1.3
 */