/*    */ package f;public final class COm3 extends Qa0 implements r60 { public int Cf0; public int hD; public NC0 Bt; public final Ip eL0; public Fy0[] bn0; public Fy0 De; public Fy0 ms0; public Fy0[] gD0; public nR Oe; public AT t2; public cx0 JL0; public int Mx; public COm3(int paramInt) { // Byte code:
/*    */     //   0: aload_0
/*    */     //   1: dup
/*    */     //   2: dup
/*    */     //   3: dup2
/*    */     //   4: dup2
/*    */     //   5: dup2
/*    */     //   6: invokestatic XU : ()Z
/*    */     //   9: iconst_0
/*    */     //   10: invokespecial <init> : (ZZ)V
/*    */     //   13: iconst_2
/*    */     //   14: putfield Cf0 : I
/*    */     //   17: iconst_0
/*    */     //   18: putfield hD : I
/*    */     //   21: new f/NC0
/*    */     //   24: dup
/*    */     //   25: invokespecial <init> : ()V
/*    */     //   28: putfield Bt : Lf/NC0;
/*    */     //   31: new f/cx0
/*    */     //   34: dup
/*    */     //   35: invokespecial <init> : ()V
/*    */     //   38: putfield JL0 : Lf/cx0;
/*    */     //   41: iconst_0
/*    */     //   42: putfield Mx : I
/*    */     //   45: <illegal opcode> run : (Lf/COm3;)Ljava/lang/Runnable;
/*    */     //   50: invokevirtual TG0 : (Ljava/lang/Runnable;)V
/*    */     //   53: new f/I
/*    */     //   56: dup
/*    */     //   57: aload_0
/*    */     //   58: new f/pRn
/*    */     //   61: dup
/*    */     //   62: astore_2
/*    */     //   63: iconst_m1
/*    */     //   64: iconst_m1
/*    */     //   65: iconst_m1
/*    */     //   66: iconst_m1
/*    */     //   67: invokespecial <init> : (BBBB)V
/*    */     //   70: aload_2
/*    */     //   71: invokespecial <init> : (Lf/JG0;Lf/pRn;)V
/*    */     //   74: invokevirtual Vo0 : (Lf/I;)V
/*    */     //   77: invokestatic Nr : ()Z
/*    */     //   80: ifeq -> 92
/*    */     //   83: aload_0
/*    */     //   84: ldc 'base-frame'
/*    */     //   86: invokevirtual Xu : (Ljava/lang/String;)V
/*    */     //   89: goto -> 103
/*    */     //   92: aload_0
/*    */     //   93: dup
/*    */     //   94: iconst_3
/*    */     //   95: putfield Cf0 : I
/*    */     //   98: ldc 'monster-frame-mobile'
/*    */     //   100: invokevirtual Xu : (Ljava/lang/String;)V
/*    */     //   103: aload_0
/*    */     //   104: dup
/*    */     //   105: dup2
/*    */     //   106: dup2
/*    */     //   107: new f/nR
/*    */     //   110: dup
/*    */     //   111: astore_2
/*    */     //   112: iload_1
/*    */     //   113: aload_0
/*    */     //   114: aload_2
/*    */     //   115: dup
/*    */     //   116: aload_0
/*    */     //   117: getfield Cf0 : I
/*    */     //   120: invokespecial <init> : (I)V
/*    */     //   123: putfield Oe : Lf/nR;
/*    */     //   126: invokevirtual WF : (I)V
/*    */     //   129: getfield Oe : Lf/nR;
/*    */     //   132: invokevirtual WK : ()Lf/AT;
/*    */     //   135: putfield t2 : Lf/AT;
/*    */     //   138: iconst_1
/*    */     //   139: invokevirtual No : (Z)V
/*    */     //   142: ldc ''
/*    */     //   144: invokevirtual Lo : (Ljava/lang/String;)V
/*    */     //   147: new f/Ip
/*    */     //   150: dup
/*    */     //   151: invokespecial <init> : ()V
/*    */     //   154: putfield eL0 : Lf/Ip;
/*    */     //   157: bipush #25
/*    */     //   159: anewarray f/Fy0
/*    */     //   162: putfield bn0 : [Lf/Fy0;
/*    */     //   165: iconst_0
/*    */     //   166: istore_1
/*    */     //   167: iload_1
/*    */     //   168: iconst_5
/*    */     //   169: if_icmpge -> 243
/*    */     //   172: iconst_0
/*    */     //   173: istore_2
/*    */     //   174: iload_2
/*    */     //   175: iconst_5
/*    */     //   176: if_icmpge -> 237
/*    */     //   179: aload_0
/*    */     //   180: dup
/*    */     //   181: dup2
/*    */     //   182: getfield bn0 : [Lf/Fy0;
/*    */     //   185: iload_1
/*    */     //   186: iconst_5
/*    */     //   187: imul
/*    */     //   188: iload_2
/*    */     //   189: iadd
/*    */     //   190: dup
/*    */     //   191: istore_3
/*    */     //   192: new f/L40
/*    */     //   195: dup
/*    */     //   196: astore #4
/*    */     //   198: aload_0
/*    */     //   199: iload_1
/*    */     //   200: iload_2
/*    */     //   201: invokespecial <init> : (Lf/COm3;II)V
/*    */     //   204: aload #4
/*    */     //   206: aastore
/*    */     //   207: getfield bn0 : [Lf/Fy0;
/*    */     //   210: iload_3
/*    */     //   211: aaload
/*    */     //   212: aload_0
/*    */     //   213: iload_1
/*    */     //   214: iload_2
/*    */     //   215: <illegal opcode> run : (Lf/COm3;II)Ljava/lang/Runnable;
/*    */     //   220: invokevirtual tW : (Ljava/lang/Runnable;)V
/*    */     //   223: getfield bn0 : [Lf/Fy0;
/*    */     //   226: iload_3
/*    */     //   227: aaload
/*    */     //   228: invokevirtual J8 : (Lf/JG0;)V
/*    */     //   231: iinc #2, 1
/*    */     //   234: goto -> 174
/*    */     //   237: iinc #1, 1
/*    */     //   240: goto -> 167
/*    */     //   243: aload_0
/*    */     //   244: dup
/*    */     //   245: dup
/*    */     //   246: dup2
/*    */     //   247: new f/Fy0
/*    */     //   250: dup
/*    */     //   251: astore_1
/*    */     //   252: aload_0
/*    */     //   253: dup
/*    */     //   254: aload_1
/*    */     //   255: dup
/*    */     //   256: invokespecial <init> : ()V
/*    */     //   259: putfield De : Lf/Fy0;
/*    */     //   262: <illegal opcode> run : (Lf/COm3;)Ljava/lang/Runnable;
/*    */     //   267: invokevirtual tW : (Ljava/lang/Runnable;)V
/*    */     //   270: getfield De : Lf/Fy0;
/*    */     //   273: invokevirtual J8 : (Lf/JG0;)V
/*    */     //   276: new f/Fy0
/*    */     //   279: dup
/*    */     //   280: astore_1
/*    */     //   281: aload_0
/*    */     //   282: dup
/*    */     //   283: aload_1
/*    */     //   284: dup
/*    */     //   285: invokespecial <init> : ()V
/*    */     //   288: putfield ms0 : Lf/Fy0;
/*    */     //   291: <illegal opcode> run : (Lf/COm3;)Ljava/lang/Runnable;
/*    */     //   296: invokevirtual tW : (Ljava/lang/Runnable;)V
/*    */     //   299: getfield ms0 : Lf/Fy0;
/*    */     //   302: invokevirtual J8 : (Lf/JG0;)V
/*    */     //   305: iconst_4
/*    */     //   306: anewarray f/Fy0
/*    */     //   309: putfield gD0 : [Lf/Fy0;
/*    */     //   312: iconst_0
/*    */     //   313: istore_1
/*    */     //   314: iload_1
/*    */     //   315: iconst_2
/*    */     //   316: if_icmpge -> 387
/*    */     //   319: iconst_0
/*    */     //   320: istore_2
/*    */     //   321: iload_2
/*    */     //   322: iconst_2
/*    */     //   323: if_icmpge -> 381
/*    */     //   326: aload_0
/*    */     //   327: dup
/*    */     //   328: dup2
/*    */     //   329: getfield gD0 : [Lf/Fy0;
/*    */     //   332: iload_1
/*    */     //   333: iconst_2
/*    */     //   334: imul
/*    */     //   335: iload_2
/*    */     //   336: iadd
/*    */     //   337: dup
/*    */     //   338: istore_3
/*    */     //   339: new f/Fy0
/*    */     //   342: dup
/*    */     //   343: astore #4
/*    */     //   345: invokespecial <init> : ()V
/*    */     //   348: aload #4
/*    */     //   350: aastore
/*    */     //   351: getfield gD0 : [Lf/Fy0;
/*    */     //   354: iload_3
/*    */     //   355: aaload
/*    */     //   356: aload_0
/*    */     //   357: iload_2
/*    */     //   358: iload_1
/*    */     //   359: <illegal opcode> run : (Lf/COm3;II)Ljava/lang/Runnable;
/*    */     //   364: invokevirtual tW : (Ljava/lang/Runnable;)V
/*    */     //   367: getfield gD0 : [Lf/Fy0;
/*    */     //   370: iload_3
/*    */     //   371: aaload
/*    */     //   372: invokevirtual J8 : (Lf/JG0;)V
/*    */     //   375: iinc #2, 1
/*    */     //   378: goto -> 321
/*    */     //   381: iinc #1, 1
/*    */     //   384: goto -> 314
/*    */     //   387: aload_0
/*    */     //   388: dup
/*    */     //   389: getfield eL0 : Lf/Ip;
/*    */     //   392: invokevirtual J8 : (Lf/JG0;)V
/*  1 */     //   395: return } private void Uf(int paramInt1, int paramInt2) { if (this.t2.Nl0
/*  2 */       .bq0()) { Rg(); return; }  AT aT; int i; int j; if ((aT = this.t2)
/*  3 */       .eo0 == 1 && (
/*  4 */       i = this.lPt2) < 5 && (
/*  5 */       j = this.MR) < 5)
/*    */     { v50 v50;
/*  7 */       if ((v50 = this.Nl0.nuL(i, j))
/*  8 */         .M00(paramInt1 = paramInt2 * 2 + paramInt1)) { this
/*  9 */           .NR &= 1 << paramInt1 ^ 0xFFFFFFFF; } else { this
/* 10 */           .NR |= 1 << paramInt1; }  }  } public final void d40() { NC0 nC03; zl0(); this.eL0.mM(); super.d40(); if (km.XU()) { nC03 = this.Bt; f2 = qF() / 2.0F - (this.Cf0 * 256) / 2.0F; f3 = Hy() / 2.0F - (this.Cf0 * 284) / 2.0F; } else { nC03 = this.Bt; f2 = RS(); f3 = (e3() + 35); }  nC03.x = f2; nC03.y = f3; float f1 = this.Bt.x, f2 = this.Bt.y; f1 = (this.Cf0 * 256); float f3 = (this.Cf0 * 284); this.JL0.jG(f1, f2, f1, f3); byte b; for (b = 0; b < 5; ) { for (byte b1 = 0; b1 < 5; ) { NC0 nC0; int i2 = (int)(nC0 = this.Bt).x; int i3; i2 = (b1 * 32 + 8) * (i3 = this.Cf0) + i2; int i1 = (int)nC0.y; int n; this.bn0[n = b * 5 + b1].ME(i2, (b * 32 + 8) * i3 + i1); this.bn0[n].Tm(this.Cf0 * 24, this.Cf0 * 24); b1++; }  b++; }  for (b = 0; b < 2; ) { for (byte b1 = 0; b1 < 2; ) { NC0 nC0; int i2 = (int)(nC0 = this.Bt).x; int i3; i2 = (b1 * 24 + 200) * (i3 = this.Cf0) + i2; int i1 = (int)nC0.y; int n; this.gD0[n = b * 2 + b1].ME(i2, (b * 24 + 78) * i3 + i1); this.gD0[n].Tm(this.Cf0 * 24, this.Cf0 * 24); b1++; }  b++; }  NC0 nC02; int m = (int)(nC02 = this.Bt).x, k = this.Cf0 * 197 + m; m = (int)nC02.y; this.De.ME(k, this.Cf0 * 10 + m); k = this.Cf0 * 54; this.De.Tm(k, this.Cf0 * 62); NC0 nC01; m = (int)(nC01 = this.Bt).x; int j = this.Cf0 * 192 + m; m = (int)nC01.y; this.ms0.ME(j, this.Cf0 * 166 + m);
/* 11 */     int i = this.Cf0 * 59; this.ms0.Tm(i, this.Cf0 * 24); }
/*    */ 
/*    */   
/*    */   private void sE0() {
/*    */     this(this);
/*    */     dp dp;
/*    */     js.vu0.si(dp, js.vu0.Ub());
/*    */   }
/*    */   
/*    */   private void u4() {
/*    */     boolean bool;
/*    */     if (this.t2.Nl0.bq0()) {
/*    */       Rg();
/*    */       return;
/*    */     } 
/*    */     AT aT;
/*    */     if ((aT = this.t2).eo0 > 0) {
/*    */       bool = false;
/*    */     } else {
/*    */       bool = true;
/*    */     } 
/*    */     this.eo0 = bool;
/*    */   }
/*    */   
/*    */   private void fs(int paramInt1, int paramInt2) {
/*    */     if (this.t2.Nl0.bq0()) {
/*    */       Rg();
/*    */       return;
/*    */     } 
/*    */     this.t2.fb0(paramInt1, paramInt2);
/*    */     AT aT;
/*    */     if ((aT = this.t2).eo0 == 0)
/*    */       this.Nl0.k7(paramInt1, paramInt2); 
/*    */   }
/*    */   
/*    */   public final void Rg() {
/*    */     if (this.Oe.Je())
/*    */       return; 
/*    */     if (!this.t2.Nl0.bq0())
/*    */       return; 
/*    */     int i;
/*    */     if ((i = this.Mx) == 0) {
/*    */       this.Oe.iM();
/*    */       this.Mx = 1;
/*    */       return;
/*    */     } 
/*    */     if (i == 1) {
/*    */       this.Oe.BV();
/*    */       this.Mx = 0;
/*    */       return;
/*    */     } 
/*    */   }
/*    */   
/*    */   public final boolean i2(oa0 paramoa0) {
/*    */     // Byte code:
/*    */     //   0: getstatic f/km.wI0 : Lf/Pw;
/*    */     //   3: getfield oq0 : Z
/*    */     //   6: ifne -> 15
/*    */     //   9: aload_0
/*    */     //   10: aload_1
/*    */     //   11: invokespecial i2 : (Lf/oa0;)Z
/*    */     //   14: ireturn
/*    */     //   15: aload_1
/*    */     //   16: getfield cz0 : I
/*    */     //   19: invokestatic Wm0 : (I)Z
/*    */     //   22: ifeq -> 583
/*    */     //   25: aload_1
/*    */     //   26: invokevirtual oO : ()Z
/*    */     //   29: ifeq -> 583
/*    */     //   32: aload_1
/*    */     //   33: getfield GG0 : I
/*    */     //   36: dup
/*    */     //   37: istore_2
/*    */     //   38: getstatic f/BM.N70 : Lf/BM;
/*    */     //   41: invokestatic J20 : (ILf/BM;)Z
/*    */     //   44: ifeq -> 77
/*    */     //   47: aload_0
/*    */     //   48: getfield t2 : Lf/AT;
/*    */     //   51: getfield Nl0 : Lf/wq0;
/*    */     //   54: invokevirtual bq0 : ()Z
/*    */     //   57: ifeq -> 66
/*    */     //   60: aload_0
/*    */     //   61: invokevirtual Rg : ()V
/*    */     //   64: iconst_1
/*    */     //   65: ireturn
/*    */     //   66: aload_0
/*    */     //   67: getfield t2 : Lf/AT;
/*    */     //   70: iconst_1
/*    */     //   71: iconst_0
/*    */     //   72: invokevirtual rd : (II)V
/*    */     //   75: iconst_1
/*    */     //   76: ireturn
/*    */     //   77: iload_2
/*    */     //   78: getstatic f/BM.ni : Lf/BM;
/*    */     //   81: invokestatic J20 : (ILf/BM;)Z
/*    */     //   84: ifeq -> 117
/*    */     //   87: aload_0
/*    */     //   88: getfield t2 : Lf/AT;
/*    */     //   91: getfield Nl0 : Lf/wq0;
/*    */     //   94: invokevirtual bq0 : ()Z
/*    */     //   97: ifeq -> 106
/*    */     //   100: aload_0
/*    */     //   101: invokevirtual Rg : ()V
/*    */     //   104: iconst_1
/*    */     //   105: ireturn
/*    */     //   106: aload_0
/*    */     //   107: getfield t2 : Lf/AT;
/*    */     //   110: iconst_m1
/*    */     //   111: iconst_0
/*    */     //   112: invokevirtual rd : (II)V
/*    */     //   115: iconst_1
/*    */     //   116: ireturn
/*    */     //   117: iload_2
/*    */     //   118: getstatic f/BM.Oq : Lf/BM;
/*    */     //   121: invokestatic J20 : (ILf/BM;)Z
/*    */     //   124: ifeq -> 157
/*    */     //   127: aload_0
/*    */     //   128: getfield t2 : Lf/AT;
/*    */     //   131: getfield Nl0 : Lf/wq0;
/*    */     //   134: invokevirtual bq0 : ()Z
/*    */     //   137: ifeq -> 146
/*    */     //   140: aload_0
/*    */     //   141: invokevirtual Rg : ()V
/*    */     //   144: iconst_1
/*    */     //   145: ireturn
/*    */     //   146: aload_0
/*    */     //   147: getfield t2 : Lf/AT;
/*    */     //   150: iconst_0
/*    */     //   151: iconst_m1
/*    */     //   152: invokevirtual rd : (II)V
/*    */     //   155: iconst_1
/*    */     //   156: ireturn
/*    */     //   157: iload_2
/*    */     //   158: getstatic f/BM.M8 : Lf/BM;
/*    */     //   161: invokestatic J20 : (ILf/BM;)Z
/*    */     //   164: ifeq -> 197
/*    */     //   167: aload_0
/*    */     //   168: getfield t2 : Lf/AT;
/*    */     //   171: getfield Nl0 : Lf/wq0;
/*    */     //   174: invokevirtual bq0 : ()Z
/*    */     //   177: ifeq -> 186
/*    */     //   180: aload_0
/*    */     //   181: invokevirtual Rg : ()V
/*    */     //   184: iconst_1
/*    */     //   185: ireturn
/*    */     //   186: aload_0
/*    */     //   187: getfield t2 : Lf/AT;
/*    */     //   190: iconst_0
/*    */     //   191: iconst_1
/*    */     //   192: invokevirtual rd : (II)V
/*    */     //   195: iconst_1
/*    */     //   196: ireturn
/*    */     //   197: iload_2
/*    */     //   198: getstatic f/BM.lc : Lf/BM;
/*    */     //   201: invokestatic J20 : (ILf/BM;)Z
/*    */     //   204: ifeq -> 247
/*    */     //   207: aload_0
/*    */     //   208: getfield t2 : Lf/AT;
/*    */     //   211: dup
/*    */     //   212: astore_1
/*    */     //   213: getfield eo0 : I
/*    */     //   216: dup
/*    */     //   217: istore_2
/*    */     //   218: ifle -> 231
/*    */     //   221: aload_1
/*    */     //   222: iload_2
/*    */     //   223: iconst_1
/*    */     //   224: isub
/*    */     //   225: putfield eo0 : I
/*    */     //   228: goto -> 245
/*    */     //   231: aload_0
/*    */     //   232: getfield Oe : Lf/nR;
/*    */     //   235: invokevirtual Je : ()Z
/*    */     //   238: ifne -> 245
/*    */     //   241: aload_0
/*    */     //   242: invokevirtual rH0 : ()V
/*    */     //   245: iconst_1
/*    */     //   246: ireturn
/*    */     //   247: iload_2
/*    */     //   248: getstatic f/BM.bC : Lf/BM;
/*    */     //   251: invokestatic J20 : (ILf/BM;)Z
/*    */     //   254: ifeq -> 506
/*    */     //   257: aload_0
/*    */     //   258: getfield t2 : Lf/AT;
/*    */     //   261: getfield Nl0 : Lf/wq0;
/*    */     //   264: invokevirtual bq0 : ()Z
/*    */     //   267: ifeq -> 277
/*    */     //   270: aload_0
/*    */     //   271: invokevirtual Rg : ()V
/*    */     //   274: goto -> 504
/*    */     //   277: aload_0
/*    */     //   278: getfield t2 : Lf/AT;
/*    */     //   281: dup
/*    */     //   282: astore_1
/*    */     //   283: getfield eo0 : I
/*    */     //   286: dup
/*    */     //   287: istore_2
/*    */     //   288: iconst_2
/*    */     //   289: if_icmpne -> 394
/*    */     //   292: aload_1
/*    */     //   293: getfield mr : I
/*    */     //   296: iconst_2
/*    */     //   297: if_icmplt -> 307
/*    */     //   300: aload_1
/*    */     //   301: iconst_1
/*    */     //   302: putfield eo0 : I
/*    */     //   305: iconst_1
/*    */     //   306: ireturn
/*    */     //   307: aload_1
/*    */     //   308: getfield lPt2 : I
/*    */     //   311: dup
/*    */     //   312: istore_2
/*    */     //   313: iconst_5
/*    */     //   314: if_icmpge -> 504
/*    */     //   317: aload_1
/*    */     //   318: getfield MR : I
/*    */     //   321: dup
/*    */     //   322: istore_3
/*    */     //   323: iconst_5
/*    */     //   324: if_icmpge -> 504
/*    */     //   327: aload_1
/*    */     //   328: getfield Nl0 : Lf/wq0;
/*    */     //   331: iload_2
/*    */     //   332: iload_3
/*    */     //   333: invokevirtual nuL : (II)Lf/v50;
/*    */     //   336: dup
/*    */     //   337: astore_1
/*    */     //   338: aload_0
/*    */     //   339: getfield t2 : Lf/AT;
/*    */     //   342: dup
/*    */     //   343: getfield kJ : I
/*    */     //   346: istore_0
/*    */     //   347: getfield mr : I
/*    */     //   350: iconst_2
/*    */     //   351: imul
/*    */     //   352: iload_0
/*    */     //   353: iadd
/*    */     //   354: dup
/*    */     //   355: istore_0
/*    */     //   356: invokevirtual M00 : (I)Z
/*    */     //   359: ifeq -> 379
/*    */     //   362: aload_1
/*    */     //   363: dup
/*    */     //   364: getfield NR : I
/*    */     //   367: iconst_1
/*    */     //   368: iload_0
/*    */     //   369: ishl
/*    */     //   370: iconst_m1
/*    */     //   371: ixor
/*    */     //   372: iand
/*    */     //   373: putfield NR : I
/*    */     //   376: goto -> 504
/*    */     //   379: aload_1
/*    */     //   380: dup
/*    */     //   381: getfield NR : I
/*    */     //   384: iconst_1
/*    */     //   385: iload_0
/*    */     //   386: ishl
/*    */     //   387: ior
/*    */     //   388: putfield NR : I
/*    */     //   391: goto -> 504
/*    */     //   394: aload_1
/*    */     //   395: getfield lPt2 : I
/*    */     //   398: dup
/*    */     //   399: istore_3
/*    */     //   400: ifne -> 436
/*    */     //   403: aload_1
/*    */     //   404: getfield MR : I
/*    */     //   407: iconst_5
/*    */     //   408: if_icmpne -> 436
/*    */     //   411: iload_2
/*    */     //   412: ifle -> 420
/*    */     //   415: iconst_0
/*    */     //   416: istore_0
/*    */     //   417: goto -> 422
/*    */     //   420: iconst_1
/*    */     //   421: istore_0
/*    */     //   422: aload_1
/*    */     //   423: dup
/*    */     //   424: iload_0
/*    */     //   425: putfield eo0 : I
/*    */     //   428: iconst_0
/*    */     //   429: iconst_0
/*    */     //   430: invokevirtual fb0 : (II)V
/*    */     //   433: goto -> 504
/*    */     //   436: iload_3
/*    */     //   437: iconst_1
/*    */     //   438: if_icmpne -> 465
/*    */     //   441: aload_1
/*    */     //   442: getfield MR : I
/*    */     //   445: iconst_5
/*    */     //   446: if_icmpne -> 465
/*    */     //   449: aload_0
/*    */     //   450: getfield ms0 : Lf/Fy0;
/*    */     //   453: getfield TG0 : Lf/protected;
/*    */     //   456: getfield oh0 : [Ljava/lang/Runnable;
/*    */     //   459: invokestatic Fz0 : ([Ljava/lang/Runnable;)V
/*    */     //   462: goto -> 504
/*    */     //   465: iload_2
/*    */     //   466: ifne -> 484
/*    */     //   469: aload_1
/*    */     //   470: getfield Nl0 : Lf/wq0;
/*    */     //   473: iload_3
/*    */     //   474: aload_1
/*    */     //   475: getfield MR : I
/*    */     //   478: invokevirtual k7 : (II)V
/*    */     //   481: goto -> 504
/*    */     //   484: iload_2
/*    */     //   485: iconst_1
/*    */     //   486: if_icmpne -> 504
/*    */     //   489: aload_1
/*    */     //   490: dup
/*    */     //   491: dup
/*    */     //   492: iconst_0
/*    */     //   493: putfield mr : I
/*    */     //   496: iconst_0
/*    */     //   497: putfield kJ : I
/*    */     //   500: iconst_2
/*    */     //   501: putfield eo0 : I
/*    */     //   504: iconst_1
/*    */     //   505: ireturn
/*    */     //   506: iload_2
/*    */     //   507: getstatic f/BM.go0 : Lf/BM;
/*    */     //   510: invokestatic J20 : (ILf/BM;)Z
/*    */     //   513: ifeq -> 583
/*    */     //   516: aload_0
/*    */     //   517: getfield t2 : Lf/AT;
/*    */     //   520: getfield Nl0 : Lf/wq0;
/*    */     //   523: invokevirtual bq0 : ()Z
/*    */     //   526: ifeq -> 536
/*    */     //   529: aload_0
/*    */     //   530: invokevirtual Rg : ()V
/*    */     //   533: goto -> 581
/*    */     //   536: aload_0
/*    */     //   537: getfield t2 : Lf/AT;
/*    */     //   540: dup
/*    */     //   541: astore_0
/*    */     //   542: getfield eo0 : I
/*    */     //   545: ifle -> 553
/*    */     //   548: iconst_0
/*    */     //   549: istore_1
/*    */     //   550: goto -> 576
/*    */     //   553: aload_0
/*    */     //   554: getfield MR : I
/*    */     //   557: iconst_5
/*    */     //   558: if_icmpge -> 574
/*    */     //   561: aload_0
/*    */     //   562: getfield lPt2 : I
/*    */     //   565: iconst_5
/*    */     //   566: if_icmpge -> 574
/*    */     //   569: iconst_2
/*    */     //   570: istore_1
/*    */     //   571: goto -> 576
/*    */     //   574: iconst_1
/*    */     //   575: istore_1
/*    */     //   576: aload_0
/*    */     //   577: iload_1
/*    */     //   578: putfield eo0 : I
/*    */     //   581: iconst_1
/*    */     //   582: ireturn
/*    */     //   583: aload_1
/*    */     //   584: getfield cz0 : I
/*    */     //   587: dup
/*    */     //   588: istore_2
/*    */     //   589: invokestatic Pg : (I)Z
/*    */     //   592: ifeq -> 632
/*    */     //   595: iload_2
/*    */     //   596: iconst_1
/*    */     //   597: if_icmpeq -> 605
/*    */     //   600: iload_2
/*    */     //   601: iconst_3
/*    */     //   602: if_icmpne -> 632
/*    */     //   605: aload_0
/*    */     //   606: getfield t2 : Lf/AT;
/*    */     //   609: getfield Nl0 : Lf/wq0;
/*    */     //   612: invokevirtual bq0 : ()Z
/*    */     //   615: ifeq -> 630
/*    */     //   618: aload_1
/*    */     //   619: getfield cz0 : I
/*    */     //   622: iconst_3
/*    */     //   623: if_icmpne -> 630
/*    */     //   626: aload_0
/*    */     //   627: invokevirtual Rg : ()V
/*    */     //   630: iconst_1
/*    */     //   631: ireturn
/*    */     //   632: iconst_0
/*    */     //   633: ireturn
/*    */     // Line number table:
/*    */     //   Java source line number -> byte code offset
/*    */     //   #1	-> 3
/*    */     //   #2	-> 11
/*    */     //   #3	-> 16
/*    */     //   #4	-> 19
/*    */     //   #5	-> 26
/*    */     //   #6	-> 33
/*    */     //   #7	-> 38
/*    */     //   #8	-> 51
/*    */     //   #9	-> 54
/*    */     //   #10	-> 91
/*    */     //   #11	-> 94
/*    */     //   #12	-> 131
/*    */     //   #13	-> 134
/*    */     //   #14	-> 171
/*    */     //   #15	-> 174
/*    */     //   #16	-> 213
/*    */     //   #17	-> 225
/*    */     //   #18	-> 232
/*    */     //   #19	-> 261
/*    */     //   #20	-> 264
/*    */     //   #21	-> 283
/*    */     //   #22	-> 293
/*    */     //   #23	-> 302
/*    */     //   #24	-> 308
/*    */     //   #25	-> 318
/*    */     //   #26	-> 328
/*    */     //   #27	-> 333
/*    */     //   #28	-> 343
/*    */     //   #29	-> 347
/*    */     //   #30	-> 356
/*    */     //   #31	-> 364
/*    */     //   #32	-> 381
/*    */     //   #33	-> 395
/*    */     //   #34	-> 404
/*    */     //   #35	-> 425
/*    */     //   #36	-> 430
/*    */     //   #37	-> 442
/*    */     //   #38	-> 450
/*    */     //   #39	-> 453
/*    */     //   #40	-> 456
/*    */     //   #41	-> 459
/*    */     //   #42	-> 470
/*    */     //   #43	-> 475
/*    */     //   #44	-> 478
/*    */     //   #45	-> 493
/*    */     //   #46	-> 501
/*    */     //   #47	-> 507
/*    */     //   #48	-> 520
/*    */     //   #49	-> 523
/*    */     //   #50	-> 542
/*    */     //   #51	-> 554
/*    */     //   #52	-> 562
/*    */     //   #53	-> 578
/*    */     //   #54	-> 584
/*    */     //   #55	-> 606
/*    */     //   #56	-> 609
/*    */     //   #57	-> 612
/*    */     //   #58	-> 619
/*    */     //   #59	-> 627
/*    */   }
/*    */   
/*    */   public final void LM(throws paramthrows) {
/*    */     super.LM(paramthrows);
/*    */     zl0();
/*    */     VA0.c90(this);
/*    */   }
/*    */   
/*    */   public final void ED0(throws paramthrows) {
/*    */     super.ED0(paramthrows);
/*    */     this.Oe.dispose();
/*    */   }
/*    */   
/*    */   public final void V90(throws paramthrows) {
/*    */     // Byte code:
/*    */     //   0: aload_0
/*    */     //   1: invokevirtual p3 : ()Z
/*    */     //   4: ifne -> 72
/*    */     //   7: getstatic f/js.vu0 : Lf/js;
/*    */     //   10: dup
/*    */     //   11: astore_2
/*    */     //   12: <illegal opcode> evaluate : ()Lf/Yb0;
/*    */     //   17: astore_3
/*    */     //   18: invokevirtual p3 : ()Z
/*    */     //   21: ifne -> 27
/*    */     //   24: goto -> 63
/*    */     //   27: aload_3
/*    */     //   28: aload_2
/*    */     //   29: invokeinterface evaluate : (Ljava/lang/Object;)Z
/*    */     //   34: ifeq -> 40
/*    */     //   37: goto -> 59
/*    */     //   40: aload_2
/*    */     //   41: getfield LG : Lf/JG0;
/*    */     //   44: dup
/*    */     //   45: astore_2
/*    */     //   46: ifnull -> 63
/*    */     //   49: aload_3
/*    */     //   50: aload_2
/*    */     //   51: invokeinterface evaluate : (Ljava/lang/Object;)Z
/*    */     //   56: ifeq -> 40
/*    */     //   59: iconst_1
/*    */     //   60: goto -> 64
/*    */     //   63: iconst_0
/*    */     //   64: ifne -> 72
/*    */     //   67: aload_0
/*    */     //   68: invokestatic c90 : (Lf/JG0;)Z
/*    */     //   71: pop
/*    */     //   72: aload_0
/*    */     //   73: dup
/*    */     //   74: aload_1
/*    */     //   75: invokespecial V90 : (Lf/throws;)V
/*    */     //   78: getfield hD : I
/*    */     //   81: aload_0
/*    */     //   82: getfield t2 : Lf/AT;
/*    */     //   85: getfield Nl0 : Lf/wq0;
/*    */     //   88: getfield yY : I
/*    */     //   91: if_icmpeq -> 161
/*    */     //   94: aload_0
/*    */     //   95: getfield Oe : Lf/nR;
/*    */     //   98: invokevirtual Je : ()Z
/*    */     //   101: ifne -> 161
/*    */     //   104: aload_0
/*    */     //   105: dup
/*    */     //   106: dup
/*    */     //   107: getfield t2 : Lf/AT;
/*    */     //   110: getfield Nl0 : Lf/wq0;
/*    */     //   113: getfield yY : I
/*    */     //   116: putfield hD : I
/*    */     //   119: getstatic f/F40.ef0 : Lf/F40;
/*    */     //   122: iconst_1
/*    */     //   123: anewarray f/LPT1
/*    */     //   126: dup
/*    */     //   127: astore_2
/*    */     //   128: new f/LPT1
/*    */     //   131: dup
/*    */     //   132: astore_3
/*    */     //   133: aload_0
/*    */     //   134: getfield hD : I
/*    */     //   137: istore #4
/*    */     //   139: iconst_0
/*    */     //   140: iconst_3
/*    */     //   141: iload #4
/*    */     //   143: invokespecial <init> : (BBI)V
/*    */     //   146: iconst_0
/*    */     //   147: aload_3
/*    */     //   148: aastore
/*    */     //   149: iconst_4
/*    */     //   150: swap
/*    */     //   151: bipush #39
/*    */     //   153: iconst_0
/*    */     //   154: aload_2
/*    */     //   155: invokestatic tm0 : (BLf/F40;II[Lf/LPT1;)Ljava/lang/String;
/*    */     //   158: invokevirtual Lo : (Ljava/lang/String;)V
/*    */     //   161: aload_0
/*    */     //   162: aload_1
/*    */     //   163: getfield IB0 : Lf/VI;
/*    */     //   166: checkcast f/tw
/*    */     //   169: dup
/*    */     //   170: astore_1
/*    */     //   171: getfield yT : Lf/JX;
/*    */     //   174: invokevirtual end : ()V
/*    */     //   177: getfield Oe : Lf/nR;
/*    */     //   180: dup
/*    */     //   181: astore_2
/*    */     //   182: aload_0
/*    */     //   183: getfield JL0 : Lf/cx0;
/*    */     //   186: astore_0
/*    */     //   187: getfield Rc0 : [Lf/GM;
/*    */     //   190: dup
/*    */     //   191: astore_3
/*    */     //   192: arraylength
/*    */     //   193: istore #4
/*    */     //   195: iconst_0
/*    */     //   196: istore #5
/*    */     //   198: iload #5
/*    */     //   200: iload #4
/*    */     //   202: if_icmpge -> 218
/*    */     //   205: aload_3
/*    */     //   206: iload #5
/*    */     //   208: aaload
/*    */     //   209: invokevirtual Wv : ()V
/*    */     //   212: iinc #5, 1
/*    */     //   215: goto -> 198
/*    */     //   218: aload_2
/*    */     //   219: getfield eO : [Lf/YP;
/*    */     //   222: dup
/*    */     //   223: astore_3
/*    */     //   224: arraylength
/*    */     //   225: istore #4
/*    */     //   227: iconst_0
/*    */     //   228: istore #5
/*    */     //   230: iload #5
/*    */     //   232: iload #4
/*    */     //   234: if_icmpge -> 782
/*    */     //   237: aload_3
/*    */     //   238: iload #5
/*    */     //   240: aaload
/*    */     //   241: dup
/*    */     //   242: astore #6
/*    */     //   244: getfield ID : I
/*    */     //   247: iconst_1
/*    */     //   248: if_icmpne -> 267
/*    */     //   251: aload #6
/*    */     //   253: getfield Dr : Lf/nR;
/*    */     //   256: getfield xb : Lf/AT;
/*    */     //   259: getfield Ox : I
/*    */     //   262: istore #7
/*    */     //   264: goto -> 350
/*    */     //   267: aload #6
/*    */     //   269: getfield Dr : Lf/nR;
/*    */     //   272: getfield xb : Lf/AT;
/*    */     //   275: getfield Nl0 : Lf/wq0;
/*    */     //   278: iconst_0
/*    */     //   279: istore #7
/*    */     //   281: getfield r50 : [Lf/v50;
/*    */     //   284: dup
/*    */     //   285: astore #8
/*    */     //   287: arraylength
/*    */     //   288: istore #9
/*    */     //   290: iconst_0
/*    */     //   291: istore #10
/*    */     //   293: iload #10
/*    */     //   295: iload #9
/*    */     //   297: if_icmpge -> 350
/*    */     //   300: aload #8
/*    */     //   302: iload #10
/*    */     //   304: aaload
/*    */     //   305: dup
/*    */     //   306: astore #11
/*    */     //   308: getfield F4 : Z
/*    */     //   311: ifeq -> 344
/*    */     //   314: aload #11
/*    */     //   316: getfield Ua0 : I
/*    */     //   319: dup
/*    */     //   320: istore #11
/*    */     //   322: ifle -> 344
/*    */     //   325: iload #7
/*    */     //   327: ifne -> 337
/*    */     //   330: iload #11
/*    */     //   332: istore #7
/*    */     //   334: goto -> 344
/*    */     //   337: iload #7
/*    */     //   339: iload #11
/*    */     //   341: imul
/*    */     //   342: istore #7
/*    */     //   344: iinc #10, 1
/*    */     //   347: goto -> 293
/*    */     //   350: aload #6
/*    */     //   352: getfield ov : I
/*    */     //   355: dup
/*    */     //   356: istore #8
/*    */     //   358: iload #7
/*    */     //   360: if_icmpeq -> 613
/*    */     //   363: aload #6
/*    */     //   365: iload #7
/*    */     //   367: iload #8
/*    */     //   369: isub
/*    */     //   370: istore #8
/*    */     //   372: getfield TE0 : I
/*    */     //   375: dup
/*    */     //   376: istore #9
/*    */     //   378: iload #7
/*    */     //   380: if_icmpeq -> 417
/*    */     //   383: aload #6
/*    */     //   385: iload #8
/*    */     //   387: aload #6
/*    */     //   389: iload #7
/*    */     //   391: aload #6
/*    */     //   393: iload #9
/*    */     //   395: putfield ov : I
/*    */     //   398: putfield TE0 : I
/*    */     //   401: invokestatic abs : (I)I
/*    */     //   404: i2d
/*    */     //   405: invokestatic log10 : (D)D
/*    */     //   408: d2f
/*    */     //   409: fconst_1
/*    */     //   410: swap
/*    */     //   411: invokestatic max : (FF)F
/*    */     //   414: putfield KC0 : F
/*    */     //   417: iload #8
/*    */     //   419: ifle -> 544
/*    */     //   422: iload #8
/*    */     //   424: aload #6
/*    */     //   426: getfield ov : I
/*    */     //   429: istore #8
/*    */     //   431: i2f
/*    */     //   432: getstatic f/UB0.M60 : Lf/w70;
/*    */     //   435: getfield Qy : F
/*    */     //   438: fmul
/*    */     //   439: aload #6
/*    */     //   441: getfield KC0 : F
/*    */     //   444: fmul
/*    */     //   445: invokestatic round : (F)I
/*    */     //   448: iconst_1
/*    */     //   449: swap
/*    */     //   450: invokestatic max : (II)I
/*    */     //   453: iload #8
/*    */     //   455: iadd
/*    */     //   456: dup
/*    */     //   457: istore #8
/*    */     //   459: iload #7
/*    */     //   461: aload #6
/*    */     //   463: iload #8
/*    */     //   465: putfield ov : I
/*    */     //   468: if_icmplt -> 503
/*    */     //   471: aload #6
/*    */     //   473: dup
/*    */     //   474: dup
/*    */     //   475: iload #7
/*    */     //   477: putfield ov : I
/*    */     //   480: fconst_0
/*    */     //   481: putfield KC0 : F
/*    */     //   484: getfield ID : I
/*    */     //   487: iconst_1
/*    */     //   488: if_icmpne -> 503
/*    */     //   491: getstatic f/km.pm0 : Lf/VD0;
/*    */     //   494: iconst_1
/*    */     //   495: iconst_4
/*    */     //   496: sipush #2347
/*    */     //   499: fconst_0
/*    */     //   500: invokevirtual bA0 : (ZBSF)V
/*    */     //   503: getstatic f/zm0.u20 : J
/*    */     //   506: dup2
/*    */     //   507: lstore #8
/*    */     //   509: aload #6
/*    */     //   511: getfield coM2 : J
/*    */     //   514: lsub
/*    */     //   515: ldc2_w 100
/*    */     //   518: lcmp
/*    */     //   519: iflt -> 599
/*    */     //   522: aload #6
/*    */     //   524: lload #8
/*    */     //   526: putfield coM2 : J
/*    */     //   529: getstatic f/km.pm0 : Lf/VD0;
/*    */     //   532: iconst_1
/*    */     //   533: iconst_4
/*    */     //   534: sipush #2346
/*    */     //   537: fconst_0
/*    */     //   538: invokevirtual bA0 : (ZBSF)V
/*    */     //   541: goto -> 599
/*    */     //   544: iload #8
/*    */     //   546: aload #6
/*    */     //   548: getfield ov : I
/*    */     //   551: istore #8
/*    */     //   553: i2f
/*    */     //   554: getstatic f/UB0.M60 : Lf/w70;
/*    */     //   557: getfield Qy : F
/*    */     //   560: fmul
/*    */     //   561: aload #6
/*    */     //   563: getfield KC0 : F
/*    */     //   566: fmul
/*    */     //   567: invokestatic round : (F)I
/*    */     //   570: iconst_m1
/*    */     //   571: swap
/*    */     //   572: invokestatic min : (II)I
/*    */     //   575: iload #8
/*    */     //   577: iadd
/*    */     //   578: dup
/*    */     //   579: aload #6
/*    */     //   581: swap
/*    */     //   582: putfield ov : I
/*    */     //   585: ifge -> 599
/*    */     //   588: aload #6
/*    */     //   590: dup
/*    */     //   591: iconst_0
/*    */     //   592: putfield ov : I
/*    */     //   595: fconst_0
/*    */     //   596: putfield KC0 : F
/*    */     //   599: iload #7
/*    */     //   601: aload #6
/*    */     //   603: getfield ov : I
/*    */     //   606: if_icmpne -> 613
/*    */     //   609: iconst_1
/*    */     //   610: goto -> 614
/*    */     //   613: iconst_0
/*    */     //   614: ifeq -> 776
/*    */     //   617: aload #6
/*    */     //   619: getfield ID : I
/*    */     //   622: iconst_1
/*    */     //   623: if_icmpne -> 776
/*    */     //   626: getstatic f/km.u4 : Lf/R8;
/*    */     //   629: dup
/*    */     //   630: astore #6
/*    */     //   632: ifnull -> 776
/*    */     //   635: aload_2
/*    */     //   636: getfield Li : S
/*    */     //   639: dup
/*    */     //   640: istore #7
/*    */     //   642: aload_2
/*    */     //   643: aload #6
/*    */     //   645: getfield fF0 : Lf/BF;
/*    */     //   648: iconst_4
/*    */     //   649: sipush #1495
/*    */     //   652: invokevirtual eb : (BS)S
/*    */     //   655: dup
/*    */     //   656: istore #6
/*    */     //   658: putfield Li : S
/*    */     //   661: iload #6
/*    */     //   663: if_icmpeq -> 776
/*    */     //   666: iload #6
/*    */     //   668: iconst_1
/*    */     //   669: iand
/*    */     //   670: iload #7
/*    */     //   672: iconst_1
/*    */     //   673: iand
/*    */     //   674: if_icmpeq -> 699
/*    */     //   677: getstatic f/km.u4 : Lf/R8;
/*    */     //   680: invokestatic getInstance : ()Ljava/text/NumberFormat;
/*    */     //   683: ldc2_w 500
/*    */     //   686: invokevirtual format : (J)Ljava/lang/String;
/*    */     //   689: ldc_w 16777266
/*    */     //   692: swap
/*    */     //   693: invokestatic Go : (ILjava/lang/String;)Ljava/lang/String;
/*    */     //   696: invokevirtual Pq : (Ljava/lang/String;)V
/*    */     //   699: aload_2
/*    */     //   700: getfield Li : S
/*    */     //   703: iconst_2
/*    */     //   704: iand
/*    */     //   705: iload #7
/*    */     //   707: iconst_2
/*    */     //   708: iand
/*    */     //   709: if_icmpeq -> 734
/*    */     //   712: getstatic f/km.u4 : Lf/R8;
/*    */     //   715: invokestatic getInstance : ()Ljava/text/NumberFormat;
/*    */     //   718: ldc2_w 5000
/*    */     //   721: invokevirtual format : (J)Ljava/lang/String;
/*    */     //   724: ldc_w 16777266
/*    */     //   727: swap
/*    */     //   728: invokestatic Go : (ILjava/lang/String;)Ljava/lang/String;
/*    */     //   731: invokevirtual Pq : (Ljava/lang/String;)V
/*    */     //   734: aload_2
/*    */     //   735: getfield Li : S
/*    */     //   738: iconst_4
/*    */     //   739: iand
/*    */     //   740: iload #7
/*    */     //   742: iconst_4
/*    */     //   743: iand
/*    */     //   744: if_icmpeq -> 776
/*    */     //   747: getstatic f/Of.eH : Lf/Of;
/*    */     //   750: sipush #4675
/*    */     //   753: invokevirtual On0 : (S)Lf/LPT3;
/*    */     //   756: getstatic f/km.u4 : Lf/R8;
/*    */     //   759: swap
/*    */     //   760: getfield Iu : I
/*    */     //   763: invokestatic OH0 : (I)Ljava/lang/String;
/*    */     //   766: ldc_w 16777267
/*    */     //   769: swap
/*    */     //   770: invokestatic Go : (ILjava/lang/String;)Ljava/lang/String;
/*    */     //   773: invokevirtual Pq : (Ljava/lang/String;)V
/*    */     //   776: iinc #5, 1
/*    */     //   779: goto -> 230
/*    */     //   782: aload_2
/*    */     //   783: dup
/*    */     //   784: aload_0
/*    */     //   785: aload_2
/*    */     //   786: dup
/*    */     //   787: new f/Tm
/*    */     //   790: dup
/*    */     //   791: dup
/*    */     //   792: astore_3
/*    */     //   793: aload_0
/*    */     //   794: dup
/*    */     //   795: aload_3
/*    */     //   796: aload_2
/*    */     //   797: aload_3
/*    */     //   798: invokespecial <init> : ()V
/*    */     //   801: getfield Ki0 : I
/*    */     //   804: i2f
/*    */     //   805: fconst_1
/*    */     //   806: swap
/*    */     //   807: fdiv
/*    */     //   808: putfield nUl : F
/*    */     //   811: getfield af : F
/*    */     //   814: fstore #4
/*    */     //   816: getfield sf0 : F
/*    */     //   819: fload #4
/*    */     //   821: swap
/*    */     //   822: iconst_1
/*    */     //   823: invokevirtual Wt : (FFZ)V
/*    */     //   826: iconst_1
/*    */     //   827: invokevirtual UX : (Z)V
/*    */     //   830: getfield sD0 : Lf/tH;
/*    */     //   833: aload_3
/*    */     //   834: getfield VD0 : Lcom/badlogic/gdx/math/Matrix4;
/*    */     //   837: invokevirtual d60 : (Lcom/badlogic/gdx/math/Matrix4;)V
/*    */     //   840: getfield sD0 : Lf/tH;
/*    */     //   843: invokevirtual Tx : ()V
/*    */     //   846: getfield dA : F
/*    */     //   849: getstatic f/km.wI0 : Lf/Pw;
/*    */     //   852: dup
/*    */     //   853: astore_3
/*    */     //   854: getfield vH0 : F
/*    */     //   857: fdiv
/*    */     //   858: f2i
/*    */     //   859: aload_0
/*    */     //   860: aload_3
/*    */     //   861: invokevirtual k1 : ()I
/*    */     //   864: i2f
/*    */     //   865: aload_0
/*    */     //   866: getfield zA0 : F
/*    */     //   869: fsub
/*    */     //   870: fstore_3
/*    */     //   871: getfield sf0 : F
/*    */     //   874: dup
/*    */     //   875: fload_3
/*    */     //   876: swap
/*    */     //   877: fsub
/*    */     //   878: getstatic f/km.wI0 : Lf/Pw;
/*    */     //   881: getfield vH0 : F
/*    */     //   884: dup
/*    */     //   885: fstore_3
/*    */     //   886: fdiv
/*    */     //   887: f2i
/*    */     //   888: istore #4
/*    */     //   890: fload_3
/*    */     //   891: aload_0
/*    */     //   892: getfield af : F
/*    */     //   895: fload_3
/*    */     //   896: fdiv
/*    */     //   897: f2i
/*    */     //   898: istore_0
/*    */     //   899: fdiv
/*    */     //   900: f2i
/*    */     //   901: istore_3
/*    */     //   902: iload #4
/*    */     //   904: iload_0
/*    */     //   905: iload_3
/*    */     //   906: invokestatic com8 : (IIII)V
/*    */     //   909: getfield sD0 : Lf/tH;
/*    */     //   912: aload_2
/*    */     //   913: getfield zj0 : Lcom/badlogic/gdx/graphics/Texture;
/*    */     //   916: fconst_0
/*    */     //   917: fconst_0
/*    */     //   918: invokevirtual VI : (Lcom/badlogic/gdx/graphics/Texture;FF)V
/*    */     //   921: getfield sD0 : Lf/tH;
/*    */     //   924: aload_2
/*    */     //   925: getfield cn0 : Lcom/badlogic/gdx/graphics/Texture;
/*    */     //   928: fconst_0
/*    */     //   929: ldc_w 200.0
/*    */     //   932: invokevirtual VI : (Lcom/badlogic/gdx/graphics/Texture;FF)V
/*    */     //   935: iconst_0
/*    */     //   936: istore_0
/*    */     //   937: iload_0
/*    */     //   938: iconst_5
/*    */     //   939: if_icmpge -> 1148
/*    */     //   942: aload_2
/*    */     //   943: getfield xb : Lf/AT;
/*    */     //   946: getfield Nl0 : Lf/wq0;
/*    */     //   949: astore_3
/*    */     //   950: iconst_0
/*    */     //   951: istore #4
/*    */     //   953: iconst_0
/*    */     //   954: istore #5
/*    */     //   956: iload #5
/*    */     //   958: iconst_5
/*    */     //   959: if_icmpge -> 983
/*    */     //   962: iload #4
/*    */     //   964: aload_3
/*    */     //   965: iload_0
/*    */     //   966: iload #5
/*    */     //   968: invokevirtual nuL : (II)Lf/v50;
/*    */     //   971: getfield Ua0 : I
/*    */     //   974: iadd
/*    */     //   975: istore #4
/*    */     //   977: iinc #5, 1
/*    */     //   980: goto -> 956
/*    */     //   983: aload_2
/*    */     //   984: dup
/*    */     //   985: dup
/*    */     //   986: dup2
/*    */     //   987: aload_3
/*    */     //   988: invokevirtual getClass : ()Ljava/lang/Class;
/*    */     //   991: pop
/*    */     //   992: getfield sD0 : Lf/tH;
/*    */     //   995: iload_0
/*    */     //   996: aload_2
/*    */     //   997: getfield wt : [Lf/pe0;
/*    */     //   1000: iload #4
/*    */     //   1002: bipush #10
/*    */     //   1004: idiv
/*    */     //   1005: aaload
/*    */     //   1006: astore_3
/*    */     //   1007: bipush #32
/*    */     //   1009: imul
/*    */     //   1010: istore #5
/*    */     //   1012: aload_3
/*    */     //   1013: iload #5
/*    */     //   1015: bipush #8
/*    */     //   1017: iadd
/*    */     //   1018: i2f
/*    */     //   1019: fstore_3
/*    */     //   1020: ldc_w 176.0
/*    */     //   1023: fload_3
/*    */     //   1024: invokevirtual TB : (Lf/pe0;FF)V
/*    */     //   1027: getfield sD0 : Lf/tH;
/*    */     //   1030: aload_2
/*    */     //   1031: getfield wt : [Lf/pe0;
/*    */     //   1034: iload #4
/*    */     //   1036: bipush #10
/*    */     //   1038: irem
/*    */     //   1039: aaload
/*    */     //   1040: ldc_w 184.0
/*    */     //   1043: fload_3
/*    */     //   1044: invokevirtual TB : (Lf/pe0;FF)V
/*    */     //   1047: getfield sD0 : Lf/tH;
/*    */     //   1050: astore_3
/*    */     //   1051: getfield wt : [Lf/pe0;
/*    */     //   1054: astore #4
/*    */     //   1056: getfield xb : Lf/AT;
/*    */     //   1059: getfield Nl0 : Lf/wq0;
/*    */     //   1062: astore #6
/*    */     //   1064: iconst_0
/*    */     //   1065: istore #7
/*    */     //   1067: iconst_0
/*    */     //   1068: istore #8
/*    */     //   1070: iload #8
/*    */     //   1072: iconst_5
/*    */     //   1073: if_icmpge -> 1112
/*    */     //   1076: aload #6
/*    */     //   1078: iload_0
/*    */     //   1079: iload #8
/*    */     //   1081: invokevirtual nuL : (II)Lf/v50;
/*    */     //   1084: getfield Ua0 : I
/*    */     //   1087: ifne -> 1096
/*    */     //   1090: iconst_1
/*    */     //   1091: istore #9
/*    */     //   1093: goto -> 1099
/*    */     //   1096: iconst_0
/*    */     //   1097: istore #9
/*    */     //   1099: iload #7
/*    */     //   1101: iload #9
/*    */     //   1103: iadd
/*    */     //   1104: istore #7
/*    */     //   1106: iinc #8, 1
/*    */     //   1109: goto -> 1070
/*    */     //   1112: aload_3
/*    */     //   1113: iload #5
/*    */     //   1115: aload #4
/*    */     //   1117: iload #7
/*    */     //   1119: aload #6
/*    */     //   1121: invokevirtual getClass : ()Ljava/lang/Class;
/*    */     //   1124: pop
/*    */     //   1125: aaload
/*    */     //   1126: astore_3
/*    */     //   1127: bipush #21
/*    */     //   1129: iadd
/*    */     //   1130: i2f
/*    */     //   1131: fstore #4
/*    */     //   1133: aload_3
/*    */     //   1134: ldc_w 184.0
/*    */     //   1137: fload #4
/*    */     //   1139: invokevirtual TB : (Lf/pe0;FF)V
/*    */     //   1142: iinc #0, 1
/*    */     //   1145: goto -> 937
/*    */     //   1148: iconst_0
/*    */     //   1149: istore_0
/*    */     //   1150: iload_0
/*    */     //   1151: iconst_5
/*    */     //   1152: if_icmpge -> 1360
/*    */     //   1155: aload_2
/*    */     //   1156: getfield xb : Lf/AT;
/*    */     //   1159: getfield Nl0 : Lf/wq0;
/*    */     //   1162: astore_3
/*    */     //   1163: iconst_0
/*    */     //   1164: istore #4
/*    */     //   1166: iconst_0
/*    */     //   1167: istore #5
/*    */     //   1169: iload #5
/*    */     //   1171: iconst_5
/*    */     //   1172: if_icmpge -> 1196
/*    */     //   1175: iload #4
/*    */     //   1177: aload_3
/*    */     //   1178: iload #5
/*    */     //   1180: iload_0
/*    */     //   1181: invokevirtual nuL : (II)Lf/v50;
/*    */     //   1184: getfield Ua0 : I
/*    */     //   1187: iadd
/*    */     //   1188: istore #4
/*    */     //   1190: iinc #5, 1
/*    */     //   1193: goto -> 1169
/*    */     //   1196: aload_2
/*    */     //   1197: dup
/*    */     //   1198: dup
/*    */     //   1199: dup2
/*    */     //   1200: aload_3
/*    */     //   1201: invokevirtual getClass : ()Ljava/lang/Class;
/*    */     //   1204: pop
/*    */     //   1205: getfield sD0 : Lf/tH;
/*    */     //   1208: iload_0
/*    */     //   1209: aload_2
/*    */     //   1210: getfield wt : [Lf/pe0;
/*    */     //   1213: iload #4
/*    */     //   1215: bipush #10
/*    */     //   1217: idiv
/*    */     //   1218: aaload
/*    */     //   1219: astore_3
/*    */     //   1220: bipush #32
/*    */     //   1222: imul
/*    */     //   1223: istore #5
/*    */     //   1225: aload_3
/*    */     //   1226: iload #5
/*    */     //   1228: bipush #16
/*    */     //   1230: iadd
/*    */     //   1231: i2f
/*    */     //   1232: ldc_w 168.0
/*    */     //   1235: invokevirtual TB : (Lf/pe0;FF)V
/*    */     //   1238: getfield sD0 : Lf/tH;
/*    */     //   1241: iload #5
/*    */     //   1243: aload_2
/*    */     //   1244: getfield wt : [Lf/pe0;
/*    */     //   1247: iload #4
/*    */     //   1249: bipush #10
/*    */     //   1251: irem
/*    */     //   1252: aaload
/*    */     //   1253: astore_3
/*    */     //   1254: bipush #24
/*    */     //   1256: iadd
/*    */     //   1257: i2f
/*    */     //   1258: fstore #4
/*    */     //   1260: aload_3
/*    */     //   1261: fload #4
/*    */     //   1263: ldc_w 168.0
/*    */     //   1266: invokevirtual TB : (Lf/pe0;FF)V
/*    */     //   1269: getfield sD0 : Lf/tH;
/*    */     //   1272: astore_3
/*    */     //   1273: getfield wt : [Lf/pe0;
/*    */     //   1276: astore #5
/*    */     //   1278: getfield xb : Lf/AT;
/*    */     //   1281: getfield Nl0 : Lf/wq0;
/*    */     //   1284: astore #6
/*    */     //   1286: iconst_0
/*    */     //   1287: istore #7
/*    */     //   1289: iconst_0
/*    */     //   1290: istore #8
/*    */     //   1292: iload #8
/*    */     //   1294: iconst_5
/*    */     //   1295: if_icmpge -> 1334
/*    */     //   1298: aload #6
/*    */     //   1300: iload #8
/*    */     //   1302: iload_0
/*    */     //   1303: invokevirtual nuL : (II)Lf/v50;
/*    */     //   1306: getfield Ua0 : I
/*    */     //   1309: ifne -> 1318
/*    */     //   1312: iconst_1
/*    */     //   1313: istore #9
/*    */     //   1315: goto -> 1321
/*    */     //   1318: iconst_0
/*    */     //   1319: istore #9
/*    */     //   1321: iload #7
/*    */     //   1323: iload #9
/*    */     //   1325: iadd
/*    */     //   1326: istore #7
/*    */     //   1328: iinc #8, 1
/*    */     //   1331: goto -> 1292
/*    */     //   1334: aload_3
/*    */     //   1335: aload #5
/*    */     //   1337: iload #7
/*    */     //   1339: aload #6
/*    */     //   1341: invokevirtual getClass : ()Ljava/lang/Class;
/*    */     //   1344: pop
/*    */     //   1345: aaload
/*    */     //   1346: fload #4
/*    */     //   1348: ldc_w 181.0
/*    */     //   1351: invokevirtual TB : (Lf/pe0;FF)V
/*    */     //   1354: iinc #0, 1
/*    */     //   1357: goto -> 1150
/*    */     //   1360: aload_2
/*    */     //   1361: dup
/*    */     //   1362: dup
/*    */     //   1363: iconst_0
/*    */     //   1364: invokevirtual aK : (I)V
/*    */     //   1367: iconst_1
/*    */     //   1368: invokevirtual aK : (I)V
/*    */     //   1371: getfield Rc0 : [Lf/GM;
/*    */     //   1374: dup
/*    */     //   1375: astore_0
/*    */     //   1376: arraylength
/*    */     //   1377: istore_3
/*    */     //   1378: iconst_0
/*    */     //   1379: istore #4
/*    */     //   1381: iload #4
/*    */     //   1383: iload_3
/*    */     //   1384: if_icmpge -> 1858
/*    */     //   1387: aload_0
/*    */     //   1388: iload #4
/*    */     //   1390: aaload
/*    */     //   1391: dup
/*    */     //   1392: dup
/*    */     //   1393: astore #5
/*    */     //   1395: getfield SM : Lf/nR;
/*    */     //   1398: getfield xb : Lf/AT;
/*    */     //   1401: getfield Nl0 : Lf/wq0;
/*    */     //   1404: aload #5
/*    */     //   1406: dup
/*    */     //   1407: getfield YB : I
/*    */     //   1410: istore #6
/*    */     //   1412: getfield Tx : I
/*    */     //   1415: iload #6
/*    */     //   1417: swap
/*    */     //   1418: invokevirtual nuL : (II)Lf/v50;
/*    */     //   1421: astore #6
/*    */     //   1423: getfield Gd : I
/*    */     //   1426: dup
/*    */     //   1427: istore #7
/*    */     //   1429: ifle -> 1491
/*    */     //   1432: aload #5
/*    */     //   1434: getfield SM : Lf/nR;
/*    */     //   1437: dup
/*    */     //   1438: astore #8
/*    */     //   1440: getfield sD0 : Lf/tH;
/*    */     //   1443: aload #8
/*    */     //   1445: getfield PZ : [[Lf/pe0;
/*    */     //   1448: aload #6
/*    */     //   1450: getfield Ua0 : I
/*    */     //   1453: aaload
/*    */     //   1454: iload #7
/*    */     //   1456: aaload
/*    */     //   1457: aload #5
/*    */     //   1459: dup
/*    */     //   1460: getfield Tx : I
/*    */     //   1463: bipush #32
/*    */     //   1465: imul
/*    */     //   1466: bipush #8
/*    */     //   1468: iadd
/*    */     //   1469: i2f
/*    */     //   1470: fstore #6
/*    */     //   1472: getfield YB : I
/*    */     //   1475: bipush #32
/*    */     //   1477: imul
/*    */     //   1478: bipush #8
/*    */     //   1480: iadd
/*    */     //   1481: i2f
/*    */     //   1482: fload #6
/*    */     //   1484: swap
/*    */     //   1485: invokevirtual TB : (Lf/pe0;FF)V
/*    */     //   1488: goto -> 1735
/*    */     //   1491: aload #6
/*    */     //   1493: iconst_0
/*    */     //   1494: invokevirtual M00 : (I)Z
/*    */     //   1497: ifeq -> 1549
/*    */     //   1500: aload #5
/*    */     //   1502: getfield SM : Lf/nR;
/*    */     //   1505: dup
/*    */     //   1506: astore #7
/*    */     //   1508: getfield sD0 : Lf/tH;
/*    */     //   1511: aload #7
/*    */     //   1513: getfield pn : [Lf/pe0;
/*    */     //   1516: iconst_0
/*    */     //   1517: aaload
/*    */     //   1518: aload #5
/*    */     //   1520: dup
/*    */     //   1521: getfield Tx : I
/*    */     //   1524: bipush #32
/*    */     //   1526: imul
/*    */     //   1527: bipush #8
/*    */     //   1529: iadd
/*    */     //   1530: i2f
/*    */     //   1531: fstore #7
/*    */     //   1533: getfield YB : I
/*    */     //   1536: bipush #32
/*    */     //   1538: imul
/*    */     //   1539: bipush #8
/*    */     //   1541: iadd
/*    */     //   1542: i2f
/*    */     //   1543: fload #7
/*    */     //   1545: swap
/*    */     //   1546: invokevirtual TB : (Lf/pe0;FF)V
/*    */     //   1549: aload #6
/*    */     //   1551: iconst_1
/*    */     //   1552: invokevirtual M00 : (I)Z
/*    */     //   1555: ifeq -> 1610
/*    */     //   1558: aload #5
/*    */     //   1560: getfield SM : Lf/nR;
/*    */     //   1563: dup
/*    */     //   1564: astore #7
/*    */     //   1566: getfield sD0 : Lf/tH;
/*    */     //   1569: aload #7
/*    */     //   1571: getfield pn : [Lf/pe0;
/*    */     //   1574: iconst_1
/*    */     //   1575: aaload
/*    */     //   1576: aload #5
/*    */     //   1578: dup
/*    */     //   1579: getfield Tx : I
/*    */     //   1582: bipush #32
/*    */     //   1584: imul
/*    */     //   1585: bipush #8
/*    */     //   1587: iadd
/*    */     //   1588: bipush #16
/*    */     //   1590: iadd
/*    */     //   1591: i2f
/*    */     //   1592: fstore #7
/*    */     //   1594: getfield YB : I
/*    */     //   1597: bipush #32
/*    */     //   1599: imul
/*    */     //   1600: bipush #8
/*    */     //   1602: iadd
/*    */     //   1603: i2f
/*    */     //   1604: fload #7
/*    */     //   1606: swap
/*    */     //   1607: invokevirtual TB : (Lf/pe0;FF)V
/*    */     //   1610: aload #6
/*    */     //   1612: iconst_2
/*    */     //   1613: invokevirtual M00 : (I)Z
/*    */     //   1616: ifeq -> 1671
/*    */     //   1619: aload #5
/*    */     //   1621: getfield SM : Lf/nR;
/*    */     //   1624: dup
/*    */     //   1625: astore #7
/*    */     //   1627: getfield sD0 : Lf/tH;
/*    */     //   1630: aload #7
/*    */     //   1632: getfield pn : [Lf/pe0;
/*    */     //   1635: iconst_2
/*    */     //   1636: aaload
/*    */     //   1637: aload #5
/*    */     //   1639: dup
/*    */     //   1640: getfield Tx : I
/*    */     //   1643: bipush #32
/*    */     //   1645: imul
/*    */     //   1646: bipush #8
/*    */     //   1648: iadd
/*    */     //   1649: i2f
/*    */     //   1650: fstore #7
/*    */     //   1652: getfield YB : I
/*    */     //   1655: bipush #32
/*    */     //   1657: imul
/*    */     //   1658: bipush #8
/*    */     //   1660: iadd
/*    */     //   1661: bipush #15
/*    */     //   1663: iadd
/*    */     //   1664: i2f
/*    */     //   1665: fload #7
/*    */     //   1667: swap
/*    */     //   1668: invokevirtual TB : (Lf/pe0;FF)V
/*    */     //   1671: aload #6
/*    */     //   1673: iconst_3
/*    */     //   1674: invokevirtual M00 : (I)Z
/*    */     //   1677: ifeq -> 1735
/*    */     //   1680: aload #5
/*    */     //   1682: getfield SM : Lf/nR;
/*    */     //   1685: dup
/*    */     //   1686: astore #6
/*    */     //   1688: getfield sD0 : Lf/tH;
/*    */     //   1691: aload #6
/*    */     //   1693: getfield pn : [Lf/pe0;
/*    */     //   1696: iconst_3
/*    */     //   1697: aaload
/*    */     //   1698: aload #5
/*    */     //   1700: dup
/*    */     //   1701: getfield Tx : I
/*    */     //   1704: bipush #32
/*    */     //   1706: imul
/*    */     //   1707: bipush #8
/*    */     //   1709: iadd
/*    */     //   1710: bipush #16
/*    */     //   1712: iadd
/*    */     //   1713: i2f
/*    */     //   1714: fstore #6
/*    */     //   1716: getfield YB : I
/*    */     //   1719: bipush #32
/*    */     //   1721: imul
/*    */     //   1722: bipush #8
/*    */     //   1724: iadd
/*    */     //   1725: bipush #15
/*    */     //   1727: iadd
/*    */     //   1728: i2f
/*    */     //   1729: fload #6
/*    */     //   1731: swap
/*    */     //   1732: invokevirtual TB : (Lf/pe0;FF)V
/*    */     //   1735: aload #5
/*    */     //   1737: getfield YB : I
/*    */     //   1740: dup
/*    */     //   1741: istore #6
/*    */     //   1743: aload #5
/*    */     //   1745: getfield SM : Lf/nR;
/*    */     //   1748: dup
/*    */     //   1749: astore #7
/*    */     //   1751: getfield xb : Lf/AT;
/*    */     //   1754: dup
/*    */     //   1755: astore #8
/*    */     //   1757: getfield lPt2 : I
/*    */     //   1760: if_icmpne -> 1852
/*    */     //   1763: aload #5
/*    */     //   1765: getfield Tx : I
/*    */     //   1768: dup
/*    */     //   1769: istore #5
/*    */     //   1771: aload #8
/*    */     //   1773: getfield MR : I
/*    */     //   1776: if_icmpne -> 1852
/*    */     //   1779: aload #8
/*    */     //   1781: bipush #11
/*    */     //   1783: istore #8
/*    */     //   1785: getfield eo0 : I
/*    */     //   1788: dup
/*    */     //   1789: istore #9
/*    */     //   1791: iconst_1
/*    */     //   1792: if_icmpne -> 1802
/*    */     //   1795: bipush #38
/*    */     //   1797: istore #8
/*    */     //   1799: goto -> 1812
/*    */     //   1802: iload #9
/*    */     //   1804: iconst_2
/*    */     //   1805: if_icmpne -> 1812
/*    */     //   1808: bipush #39
/*    */     //   1810: istore #8
/*    */     //   1812: aload #7
/*    */     //   1814: getfield sD0 : Lf/tH;
/*    */     //   1817: iload #6
/*    */     //   1819: iload #5
/*    */     //   1821: aload #7
/*    */     //   1823: getfield Fn0 : [Lcom/badlogic/gdx/graphics/Texture;
/*    */     //   1826: iload #8
/*    */     //   1828: aaload
/*    */     //   1829: astore #5
/*    */     //   1831: bipush #32
/*    */     //   1833: imul
/*    */     //   1834: i2f
/*    */     //   1835: fstore #6
/*    */     //   1837: bipush #32
/*    */     //   1839: imul
/*    */     //   1840: i2f
/*    */     //   1841: fstore #7
/*    */     //   1843: aload #5
/*    */     //   1845: fload #6
/*    */     //   1847: fload #7
/*    */     //   1849: invokevirtual VI : (Lcom/badlogic/gdx/graphics/Texture;FF)V
/*    */     //   1852: iinc #4, 1
/*    */     //   1855: goto -> 1381
/*    */     //   1858: aload_2
/*    */     //   1859: dup
/*    */     //   1860: getfield sD0 : Lf/tH;
/*    */     //   1863: aload_2
/*    */     //   1864: getfield Fn0 : [Lcom/badlogic/gdx/graphics/Texture;
/*    */     //   1867: bipush #12
/*    */     //   1869: aaload
/*    */     //   1870: ldc_w 192.0
/*    */     //   1873: ldc_w 8.0
/*    */     //   1876: invokevirtual VI : (Lcom/badlogic/gdx/graphics/Texture;FF)V
/*    */     //   1879: getfield xb : Lf/AT;
/*    */     //   1882: dup
/*    */     //   1883: astore_0
/*    */     //   1884: getfield lPt2 : I
/*    */     //   1887: ifne -> 1938
/*    */     //   1890: aload_0
/*    */     //   1891: getfield MR : I
/*    */     //   1894: iconst_5
/*    */     //   1895: if_icmpne -> 1938
/*    */     //   1898: aload_2
/*    */     //   1899: dup
/*    */     //   1900: getfield sD0 : Lf/tH;
/*    */     //   1903: aload_2
/*    */     //   1904: getfield Fn0 : [Lcom/badlogic/gdx/graphics/Texture;
/*    */     //   1907: bipush #14
/*    */     //   1909: aaload
/*    */     //   1910: ldc_w 194.0
/*    */     //   1913: ldc_w 8.0
/*    */     //   1916: invokevirtual VI : (Lcom/badlogic/gdx/graphics/Texture;FF)V
/*    */     //   1919: getfield sD0 : Lf/tH;
/*    */     //   1922: ldc_w 0.95686275
/*    */     //   1925: ldc_w 0.24705882
/*    */     //   1928: ldc_w 0.18431373
/*    */     //   1931: fconst_1
/*    */     //   1932: invokevirtual implements : (FFFF)V
/*    */     //   1935: goto -> 1955
/*    */     //   1938: aload_2
/*    */     //   1939: getfield sD0 : Lf/tH;
/*    */     //   1942: ldc_w 0.24705882
/*    */     //   1945: ldc_w 0.24705882
/*    */     //   1948: ldc_w 0.24705882
/*    */     //   1951: fconst_1
/*    */     //   1952: invokevirtual implements : (FFFF)V
/*    */     //   1955: aload_2
/*    */     //   1956: dup
/*    */     //   1957: dup
/*    */     //   1958: getfield sD0 : Lf/tH;
/*    */     //   1961: invokestatic ZZ : ()Lf/interface;
/*    */     //   1964: getfield Com6 : Lf/pe0;
/*    */     //   1967: ldc_w 208.0
/*    */     //   1970: ldc_w 30.0
/*    */     //   1973: ldc_w 32.0
/*    */     //   1976: ldc_w 32.0
/*    */     //   1979: invokevirtual Yo0 : (Lf/pe0;FFFF)V
/*    */     //   1982: getfield sD0 : Lf/tH;
/*    */     //   1985: getstatic com/badlogic/gdx/graphics/Color.WHITE_FLOAT_BITS : F
/*    */     //   1988: dup
/*    */     //   1989: fstore_0
/*    */     //   1990: invokevirtual og0 : (F)V
/*    */     //   1993: getfield xb : Lf/AT;
/*    */     //   1996: getfield eo0 : I
/*    */     //   1999: ifle -> 2025
/*    */     //   2002: aload_2
/*    */     //   2003: getfield sD0 : Lf/tH;
/*    */     //   2006: aload_2
/*    */     //   2007: getfield Fn0 : [Lcom/badlogic/gdx/graphics/Texture;
/*    */     //   2010: bipush #33
/*    */     //   2012: aaload
/*    */     //   2013: ldc_w 192.0
/*    */     //   2016: ldc_w 70.0
/*    */     //   2019: invokevirtual VI : (Lcom/badlogic/gdx/graphics/Texture;FF)V
/*    */     //   2022: goto -> 2270
/*    */     //   2025: aload_2
/*    */     //   2026: dup
/*    */     //   2027: getfield sD0 : Lf/tH;
/*    */     //   2030: aload_2
/*    */     //   2031: getfield Fn0 : [Lcom/badlogic/gdx/graphics/Texture;
/*    */     //   2034: bipush #6
/*    */     //   2036: aaload
/*    */     //   2037: ldc_w 190.0
/*    */     //   2040: ldc_w 162.0
/*    */     //   2043: invokevirtual VI : (Lcom/badlogic/gdx/graphics/Texture;FF)V
/*    */     //   2046: getfield xb : Lf/AT;
/*    */     //   2049: dup
/*    */     //   2050: astore_3
/*    */     //   2051: getfield lPt2 : I
/*    */     //   2054: iconst_1
/*    */     //   2055: if_icmpne -> 2086
/*    */     //   2058: aload_3
/*    */     //   2059: getfield MR : I
/*    */     //   2062: iconst_5
/*    */     //   2063: if_icmpne -> 2086
/*    */     //   2066: aload_2
/*    */     //   2067: getfield sD0 : Lf/tH;
/*    */     //   2070: aload_2
/*    */     //   2071: getfield Fn0 : [Lcom/badlogic/gdx/graphics/Texture;
/*    */     //   2074: bipush #8
/*    */     //   2076: aaload
/*    */     //   2077: ldc_w 190.0
/*    */     //   2080: ldc_w 162.0
/*    */     //   2083: invokevirtual VI : (Lcom/badlogic/gdx/graphics/Texture;FF)V
/*    */     //   2086: aload_2
/*    */     //   2087: dup
/*    */     //   2088: getfield sD0 : Lf/tH;
/*    */     //   2091: astore_3
/*    */     //   2092: getfield Li : S
/*    */     //   2095: iconst_1
/*    */     //   2096: iand
/*    */     //   2097: ifeq -> 2108
/*    */     //   2100: getstatic com/badlogic/gdx/graphics/Color.GOLD : Lcom/badlogic/gdx/graphics/Color;
/*    */     //   2103: astore #4
/*    */     //   2105: goto -> 2113
/*    */     //   2108: getstatic com/badlogic/gdx/graphics/Color.WHITE : Lcom/badlogic/gdx/graphics/Color;
/*    */     //   2111: astore #4
/*    */     //   2113: aload_2
/*    */     //   2114: dup
/*    */     //   2115: dup
/*    */     //   2116: aload_3
/*    */     //   2117: aload #4
/*    */     //   2119: invokevirtual HK0 : (Lcom/badlogic/gdx/graphics/Color;)V
/*    */     //   2122: getfield sD0 : Lf/tH;
/*    */     //   2125: invokestatic ZZ : ()Lf/interface;
/*    */     //   2128: getfield dR : Lf/pe0;
/*    */     //   2131: ldc_w 204.0
/*    */     //   2134: ldc_w 168.0
/*    */     //   2137: ldc_w 12.0
/*    */     //   2140: ldc_w 15.5
/*    */     //   2143: invokevirtual Yo0 : (Lf/pe0;FFFF)V
/*    */     //   2146: getfield sD0 : Lf/tH;
/*    */     //   2149: astore_3
/*    */     //   2150: getfield Li : S
/*    */     //   2153: iconst_2
/*    */     //   2154: iand
/*    */     //   2155: ifeq -> 2166
/*    */     //   2158: getstatic com/badlogic/gdx/graphics/Color.GOLD : Lcom/badlogic/gdx/graphics/Color;
/*    */     //   2161: astore #4
/*    */     //   2163: goto -> 2171
/*    */     //   2166: getstatic com/badlogic/gdx/graphics/Color.WHITE : Lcom/badlogic/gdx/graphics/Color;
/*    */     //   2169: astore #4
/*    */     //   2171: aload_2
/*    */     //   2172: dup
/*    */     //   2173: dup
/*    */     //   2174: aload_3
/*    */     //   2175: aload #4
/*    */     //   2177: invokevirtual HK0 : (Lcom/badlogic/gdx/graphics/Color;)V
/*    */     //   2180: getfield sD0 : Lf/tH;
/*    */     //   2183: invokestatic ZZ : ()Lf/interface;
/*    */     //   2186: getfield dR : Lf/pe0;
/*    */     //   2189: sipush #216
/*    */     //   2192: i2f
/*    */     //   2193: ldc_w 168.0
/*    */     //   2196: ldc_w 12.0
/*    */     //   2199: ldc_w 15.5
/*    */     //   2202: invokevirtual Yo0 : (Lf/pe0;FFFF)V
/*    */     //   2205: getfield sD0 : Lf/tH;
/*    */     //   2208: astore_3
/*    */     //   2209: getfield Li : S
/*    */     //   2212: iconst_4
/*    */     //   2213: iand
/*    */     //   2214: ifeq -> 2225
/*    */     //   2217: getstatic com/badlogic/gdx/graphics/Color.GOLD : Lcom/badlogic/gdx/graphics/Color;
/*    */     //   2220: astore #4
/*    */     //   2222: goto -> 2230
/*    */     //   2225: getstatic com/badlogic/gdx/graphics/Color.WHITE : Lcom/badlogic/gdx/graphics/Color;
/*    */     //   2228: astore #4
/*    */     //   2230: aload_2
/*    */     //   2231: dup
/*    */     //   2232: aload_3
/*    */     //   2233: aload #4
/*    */     //   2235: invokevirtual HK0 : (Lcom/badlogic/gdx/graphics/Color;)V
/*    */     //   2238: getfield sD0 : Lf/tH;
/*    */     //   2241: invokestatic ZZ : ()Lf/interface;
/*    */     //   2244: getfield dR : Lf/pe0;
/*    */     //   2247: sipush #228
/*    */     //   2250: i2f
/*    */     //   2251: ldc_w 168.0
/*    */     //   2254: ldc_w 12.0
/*    */     //   2257: ldc_w 15.5
/*    */     //   2260: invokevirtual Yo0 : (Lf/pe0;FFFF)V
/*    */     //   2263: getfield sD0 : Lf/tH;
/*    */     //   2266: fload_0
/*    */     //   2267: invokevirtual og0 : (F)V
/*    */     //   2270: aload_2
/*    */     //   2271: getfield xb : Lf/AT;
/*    */     //   2274: dup
/*    */     //   2275: astore_0
/*    */     //   2276: getfield eo0 : I
/*    */     //   2279: ifle -> 2569
/*    */     //   2282: aload_0
/*    */     //   2283: getfield lPt2 : I
/*    */     //   2286: dup
/*    */     //   2287: istore_3
/*    */     //   2288: iconst_5
/*    */     //   2289: if_icmpge -> 2492
/*    */     //   2292: aload_0
/*    */     //   2293: getfield MR : I
/*    */     //   2296: dup
/*    */     //   2297: istore #4
/*    */     //   2299: iconst_5
/*    */     //   2300: if_icmpge -> 2492
/*    */     //   2303: aload_0
/*    */     //   2304: getfield Nl0 : Lf/wq0;
/*    */     //   2307: iload_3
/*    */     //   2308: iload #4
/*    */     //   2310: invokevirtual nuL : (II)Lf/v50;
/*    */     //   2313: dup
/*    */     //   2314: astore_0
/*    */     //   2315: aload_2
/*    */     //   2316: dup
/*    */     //   2317: getfield sD0 : Lf/tH;
/*    */     //   2320: astore_3
/*    */     //   2321: getfield Fn0 : [Lcom/badlogic/gdx/graphics/Texture;
/*    */     //   2324: astore #4
/*    */     //   2326: iconst_0
/*    */     //   2327: invokevirtual M00 : (I)Z
/*    */     //   2330: ifeq -> 2340
/*    */     //   2333: bipush #15
/*    */     //   2335: istore #5
/*    */     //   2337: goto -> 2344
/*    */     //   2340: bipush #19
/*    */     //   2342: istore #5
/*    */     //   2344: aload_0
/*    */     //   2345: aload_2
/*    */     //   2346: dup
/*    */     //   2347: aload_3
/*    */     //   2348: aload #4
/*    */     //   2350: iload #5
/*    */     //   2352: aaload
/*    */     //   2353: ldc_w 200.0
/*    */     //   2356: ldc_w 78.0
/*    */     //   2359: invokevirtual VI : (Lcom/badlogic/gdx/graphics/Texture;FF)V
/*    */     //   2362: getfield sD0 : Lf/tH;
/*    */     //   2365: astore_3
/*    */     //   2366: getfield Fn0 : [Lcom/badlogic/gdx/graphics/Texture;
/*    */     //   2369: astore #4
/*    */     //   2371: iconst_1
/*    */     //   2372: invokevirtual M00 : (I)Z
/*    */     //   2375: ifeq -> 2385
/*    */     //   2378: bipush #18
/*    */     //   2380: istore #5
/*    */     //   2382: goto -> 2389
/*    */     //   2385: bipush #22
/*    */     //   2387: istore #5
/*    */     //   2389: aload_0
/*    */     //   2390: aload_2
/*    */     //   2391: dup
/*    */     //   2392: aload_3
/*    */     //   2393: aload #4
/*    */     //   2395: iload #5
/*    */     //   2397: aaload
/*    */     //   2398: ldc_w 224.0
/*    */     //   2401: ldc_w 78.0
/*    */     //   2404: invokevirtual VI : (Lcom/badlogic/gdx/graphics/Texture;FF)V
/*    */     //   2407: getfield sD0 : Lf/tH;
/*    */     //   2410: astore_3
/*    */     //   2411: getfield Fn0 : [Lcom/badlogic/gdx/graphics/Texture;
/*    */     //   2414: astore #4
/*    */     //   2416: iconst_2
/*    */     //   2417: invokevirtual M00 : (I)Z
/*    */     //   2420: ifeq -> 2430
/*    */     //   2423: bipush #17
/*    */     //   2425: istore #5
/*    */     //   2427: goto -> 2434
/*    */     //   2430: bipush #21
/*    */     //   2432: istore #5
/*    */     //   2434: aload_0
/*    */     //   2435: aload_2
/*    */     //   2436: dup
/*    */     //   2437: aload_3
/*    */     //   2438: aload #4
/*    */     //   2440: iload #5
/*    */     //   2442: aaload
/*    */     //   2443: ldc_w 200.0
/*    */     //   2446: ldc_w 102.0
/*    */     //   2449: invokevirtual VI : (Lcom/badlogic/gdx/graphics/Texture;FF)V
/*    */     //   2452: getfield sD0 : Lf/tH;
/*    */     //   2455: astore_0
/*    */     //   2456: getfield Fn0 : [Lcom/badlogic/gdx/graphics/Texture;
/*    */     //   2459: astore_3
/*    */     //   2460: iconst_3
/*    */     //   2461: invokevirtual M00 : (I)Z
/*    */     //   2464: ifeq -> 2474
/*    */     //   2467: bipush #16
/*    */     //   2469: istore #4
/*    */     //   2471: goto -> 2478
/*    */     //   2474: bipush #20
/*    */     //   2476: istore #4
/*    */     //   2478: aload_0
/*    */     //   2479: aload_3
/*    */     //   2480: iload #4
/*    */     //   2482: aaload
/*    */     //   2483: ldc_w 224.0
/*    */     //   2486: ldc_w 102.0
/*    */     //   2489: invokevirtual VI : (Lcom/badlogic/gdx/graphics/Texture;FF)V
/*    */     //   2492: aload_2
/*    */     //   2493: getfield xb : Lf/AT;
/*    */     //   2496: getfield eo0 : I
/*    */     //   2499: iconst_2
/*    */     //   2500: if_icmpne -> 2569
/*    */     //   2503: aload_2
/*    */     //   2504: dup
/*    */     //   2505: getfield sD0 : Lf/tH;
/*    */     //   2508: aload_2
/*    */     //   2509: getfield Fn0 : [Lcom/badlogic/gdx/graphics/Texture;
/*    */     //   2512: bipush #9
/*    */     //   2514: aaload
/*    */     //   2515: ldc_w 224.0
/*    */     //   2518: ldc_w 126.0
/*    */     //   2521: invokevirtual VI : (Lcom/badlogic/gdx/graphics/Texture;FF)V
/*    */     //   2524: getfield sD0 : Lf/tH;
/*    */     //   2527: aload_2
/*    */     //   2528: dup
/*    */     //   2529: getfield Fn0 : [Lcom/badlogic/gdx/graphics/Texture;
/*    */     //   2532: bipush #11
/*    */     //   2534: aaload
/*    */     //   2535: astore_0
/*    */     //   2536: getfield xb : Lf/AT;
/*    */     //   2539: aload_0
/*    */     //   2540: swap
/*    */     //   2541: dup
/*    */     //   2542: getfield kJ : I
/*    */     //   2545: bipush #24
/*    */     //   2547: imul
/*    */     //   2548: sipush #192
/*    */     //   2551: iadd
/*    */     //   2552: i2f
/*    */     //   2553: fstore_0
/*    */     //   2554: getfield mr : I
/*    */     //   2557: bipush #24
/*    */     //   2559: imul
/*    */     //   2560: bipush #70
/*    */     //   2562: iadd
/*    */     //   2563: i2f
/*    */     //   2564: fload_0
/*    */     //   2565: swap
/*    */     //   2566: invokevirtual VI : (Lcom/badlogic/gdx/graphics/Texture;FF)V
/*    */     //   2569: aload_2
/*    */     //   2570: getfield Rc0 : [Lf/GM;
/*    */     //   2573: dup
/*    */     //   2574: astore_0
/*    */     //   2575: arraylength
/*    */     //   2576: istore_3
/*    */     //   2577: iconst_0
/*    */     //   2578: istore #4
/*    */     //   2580: iload #4
/*    */     //   2582: iload_3
/*    */     //   2583: if_icmpge -> 2722
/*    */     //   2586: aload_0
/*    */     //   2587: iload #4
/*    */     //   2589: aaload
/*    */     //   2590: dup
/*    */     //   2591: astore #5
/*    */     //   2593: getfield pS : I
/*    */     //   2596: dup
/*    */     //   2597: istore #6
/*    */     //   2599: ifle -> 2716
/*    */     //   2602: aload #5
/*    */     //   2604: getfield SM : Lf/nR;
/*    */     //   2607: dup
/*    */     //   2608: astore #7
/*    */     //   2610: getfield sD0 : Lf/tH;
/*    */     //   2613: dup
/*    */     //   2614: aload #5
/*    */     //   2616: dup
/*    */     //   2617: aload #7
/*    */     //   2619: getfield Fn0 : [Lcom/badlogic/gdx/graphics/Texture;
/*    */     //   2622: iload #6
/*    */     //   2624: aaload
/*    */     //   2625: astore #6
/*    */     //   2627: getfield Tx : I
/*    */     //   2630: bipush #32
/*    */     //   2632: imul
/*    */     //   2633: bipush #8
/*    */     //   2635: iadd
/*    */     //   2636: aload #6
/*    */     //   2638: invokevirtual getWidth : ()I
/*    */     //   2641: bipush #24
/*    */     //   2643: isub
/*    */     //   2644: iconst_2
/*    */     //   2645: idiv
/*    */     //   2646: isub
/*    */     //   2647: i2f
/*    */     //   2648: fstore #7
/*    */     //   2650: getfield YB : I
/*    */     //   2653: bipush #32
/*    */     //   2655: imul
/*    */     //   2656: bipush #8
/*    */     //   2658: iadd
/*    */     //   2659: aload #5
/*    */     //   2661: getfield SM : Lf/nR;
/*    */     //   2664: getfield Fn0 : [Lcom/badlogic/gdx/graphics/Texture;
/*    */     //   2667: aload #5
/*    */     //   2669: getfield pS : I
/*    */     //   2672: aaload
/*    */     //   2673: invokevirtual getHeight : ()I
/*    */     //   2676: bipush #24
/*    */     //   2678: isub
/*    */     //   2679: iconst_2
/*    */     //   2680: idiv
/*    */     //   2681: isub
/*    */     //   2682: i2f
/*    */     //   2683: fstore #5
/*    */     //   2685: invokevirtual getClass : ()Ljava/lang/Class;
/*    */     //   2688: pop
/*    */     //   2689: aload #6
/*    */     //   2691: dup
/*    */     //   2692: dup
/*    */     //   2693: invokevirtual getWidth : ()I
/*    */     //   2696: i2f
/*    */     //   2697: fstore #6
/*    */     //   2699: invokevirtual getHeight : ()I
/*    */     //   2702: i2f
/*    */     //   2703: fstore #8
/*    */     //   2705: fload #7
/*    */     //   2707: fload #5
/*    */     //   2709: fload #6
/*    */     //   2711: fload #8
/*    */     //   2713: invokevirtual Ap0 : (Lcom/badlogic/gdx/graphics/Texture;FFFF)V
/*    */     //   2716: iinc #4, 1
/*    */     //   2719: goto -> 2580
/*    */     //   2722: aload_1
/*    */     //   2723: dup
/*    */     //   2724: aload_2
/*    */     //   2725: getfield sD0 : Lf/tH;
/*    */     //   2728: invokevirtual end : ()V
/*    */     //   2731: getfield P9 : Lf/Ur0;
/*    */     //   2734: iconst_0
/*    */     //   2735: invokevirtual wO : (Z)V
/*    */     //   2738: getfield yT : Lf/JX;
/*    */     //   2741: invokevirtual Tx : ()V
/*    */     //   2744: return
/*    */     // Line number table:
/*    */     //   Java source line number -> byte code offset
/*    */     //   #1	-> 7
/*    */     //   #2	-> 12
/*    */     //   #3	-> 18
/*    */     //   #4	-> 29
/*    */     //   #5	-> 68
/*    */     //   #6	-> 85
/*    */     //   #7	-> 88
/*    */     //   #8	-> 95
/*    */     //   #9	-> 110
/*    */     //   #10	-> 113
/*    */     //   #11	-> 116
/*    */     //   #12	-> 163
/*    */     //   #13	-> 166
/*    */     //   #14	-> 171
/*    */     //   #15	-> 174
/*    */     //   #16	-> 187
/*    */     //   #17	-> 192
/*    */     //   #18	-> 244
/*    */     //   #19	-> 253
/*    */     //   #20	-> 256
/*    */     //   #21	-> 259
/*    */     //   #22	-> 269
/*    */     //   #23	-> 272
/*    */     //   #24	-> 275
/*    */     //   #25	-> 281
/*    */     //   #26	-> 287
/*    */     //   #27	-> 352
/*    */     //   #28	-> 435
/*    */     //   #29	-> 441
/*    */     //   #30	-> 500
/*    */     //   #31	-> 503
/*    */     //   #32	-> 511
/*    */     //   #33	-> 538
/*    */     //   #34	-> 548
/*    */     //   #35	-> 557
/*    */     //   #36	-> 563
/*    */     //   #37	-> 619
/*    */     //   #38	-> 645
/*    */     //   #39	-> 652
/*    */     //   #40	-> 747
/*    */     //   #41	-> 753
/*    */     //   #42	-> 760
/*    */     //   #43	-> 770
/*    */     //   #44	-> 787
/*    */     //   #45	-> 827
/*    */     //   #46	-> 830
/*    */     //   #47	-> 854
/*    */     //   #48	-> 861
/*    */     //   #49	-> 871
/*    */     //   #50	-> 878
/*    */     //   #51	-> 881
/*    */     //   #52	-> 892
/*    */     //   #53	-> 946
/*    */     //   #54	-> 968
/*    */     //   #55	-> 971
/*    */     //   #56	-> 988
/*    */     //   #57	-> 1059
/*    */     //   #58	-> 1081
/*    */     //   #59	-> 1084
/*    */     //   #60	-> 1121
/*    */     //   #61	-> 1159
/*    */     //   #62	-> 1181
/*    */     //   #63	-> 1184
/*    */     //   #64	-> 1201
/*    */     //   #65	-> 1281
/*    */     //   #66	-> 1303
/*    */     //   #67	-> 1306
/*    */     //   #68	-> 1341
/*    */     //   #69	-> 1395
/*    */     //   #70	-> 1398
/*    */     //   #71	-> 1401
/*    */     //   #72	-> 1407
/*    */     //   #73	-> 1440
/*    */     //   #74	-> 1445
/*    */     //   #75	-> 1450
/*    */     //   #76	-> 1508
/*    */     //   #77	-> 1513
/*    */     //   #78	-> 1517
/*    */     //   #79	-> 1566
/*    */     //   #80	-> 1571
/*    */     //   #81	-> 1575
/*    */     //   #82	-> 1627
/*    */     //   #83	-> 1632
/*    */     //   #84	-> 1636
/*    */     //   #85	-> 1688
/*    */     //   #86	-> 1693
/*    */     //   #87	-> 1697
/*    */     //   #88	-> 1751
/*    */     //   #89	-> 1757
/*    */     //   #90	-> 1765
/*    */     //   #91	-> 1773
/*    */     //   #92	-> 1785
/*    */     //   #93	-> 1814
/*    */     //   #94	-> 1823
/*    */     //   #95	-> 1828
/*    */     //   #96	-> 1860
/*    */     //   #97	-> 1884
/*    */     //   #98	-> 1891
/*    */     //   #99	-> 1900
/*    */     //   #100	-> 1964
/*    */     //   #101	-> 1979
/*    */     //   #102	-> 1996
/*    */     //   #103	-> 2003
/*    */     //   #104	-> 2051
/*    */     //   #105	-> 2059
/*    */     //   #106	-> 2067
/*    */     //   #107	-> 2128
/*    */     //   #108	-> 2143
/*    */     //   #109	-> 2186
/*    */     //   #110	-> 2202
/*    */     //   #111	-> 2244
/*    */     //   #112	-> 2260
/*    */     //   #113	-> 2276
/*    */     //   #114	-> 2283
/*    */     //   #115	-> 2293
/*    */     //   #116	-> 2304
/*    */     //   #117	-> 2310
/*    */     //   #118	-> 2496
/*    */     //   #119	-> 2505
/*    */     //   #120	-> 2542
/*    */     //   #121	-> 2554
/*    */     //   #122	-> 2566
/*    */     //   #123	-> 2593
/*    */     //   #124	-> 2604
/*    */     //   #125	-> 2610
/*    */     //   #126	-> 2619
/*    */     //   #127	-> 2624
/*    */     //   #128	-> 2664
/*    */     //   #129	-> 2669
/*    */     //   #130	-> 2693
/*    */     //   #131	-> 2725
/*    */     //   #132	-> 2731
/*    */     //   #133	-> 2735
/*    */     //   #134	-> 2738
/*    */     //   #135	-> 2741
/*    */   }
/*    */   
/*    */   public final void zl0() {
/*    */     // Byte code:
/*    */     //   0: getstatic f/km.wI0 : Lf/Pw;
/*    */     //   3: invokevirtual dG : ()I
/*    */     //   6: getstatic f/km.wI0 : Lf/Pw;
/*    */     //   9: invokevirtual k1 : ()I
/*    */     //   12: istore_1
/*    */     //   13: sipush #256
/*    */     //   16: idiv
/*    */     //   17: iload_1
/*    */     //   18: sipush #284
/*    */     //   21: idiv
/*    */     //   22: invokestatic min : (II)I
/*    */     //   25: dup
/*    */     //   26: aload_0
/*    */     //   27: swap
/*    */     //   28: putfield Cf0 : I
/*    */     //   31: iconst_1
/*    */     //   32: if_icmpge -> 40
/*    */     //   35: aload_0
/*    */     //   36: iconst_1
/*    */     //   37: putfield Cf0 : I
/*    */     //   40: aload_0
/*    */     //   41: getfield Oe : Lf/nR;
/*    */     //   44: aload_0
/*    */     //   45: getfield Cf0 : I
/*    */     //   48: putfield Ki0 : I
/*    */     //   51: invokestatic Nr : ()Z
/*    */     //   54: ifeq -> 91
/*    */     //   57: aload_0
/*    */     //   58: dup
/*    */     //   59: dup
/*    */     //   60: getfield Cf0 : I
/*    */     //   63: dup
/*    */     //   64: sipush #256
/*    */     //   67: imul
/*    */     //   68: istore_0
/*    */     //   69: sipush #284
/*    */     //   72: imul
/*    */     //   73: bipush #35
/*    */     //   75: iadd
/*    */     //   76: iload_0
/*    */     //   77: swap
/*    */     //   78: invokevirtual Tm : (II)Z
/*    */     //   81: pop
/*    */     //   82: getstatic f/et.Wi0 : Lf/et;
/*    */     //   85: invokevirtual js0 : (Lf/et;)V
/*    */     //   88: goto -> 108
/*    */     //   91: aload_0
/*    */     //   92: getstatic f/km.wI0 : Lf/Pw;
/*    */     //   95: invokevirtual dG : ()I
/*    */     //   98: getstatic f/km.wI0 : Lf/Pw;
/*    */     //   101: invokevirtual k1 : ()I
/*    */     //   104: invokevirtual Tm : (II)Z
/*    */     //   107: pop
/*    */     //   108: return
/*    */     // Line number table:
/*    */     //   Java source line number -> byte code offset
/*    */     //   #1	-> 48
/*    */     //   #2	-> 51
/*    */   }
/*    */   
/*    */   public final void rH0() {
/*    */     String str = Ml0.OH0(5963);
/*    */     (new h70(str, this::close, this)).sD0 = true;
/*    */     js.vu0.uh(new h70(str, this::close, this));
/*    */   }
/*    */   
/*    */   public final void close() {
/*    */     km.u4.FL(dL0.My0, (byte)-1, (short)0);
/*    */     ra0();
/*    */   } }


/* Location:              /Users/vnnsnnt/Documents/Codespace/JavaWorkspace/RedTrainer/src/main/java/org/trainer/client/PokeMMO.jar!/f/COm3.class
 * Java compiler version: 8 (52.0)
 * JD-Core Version:       1.1.3
 */