/*  1 */ package f;public final class cOm6 extends Kl0 { public final void sM() { this
/*  2 */       .P50 = this.Ws.get();
/*  3 */     if ((this
/*  4 */       .p5 = this.Ws.get()) != 0) { this
/*    */         
/*  6 */         .oC0 = this.Ws.get();
/*    */       
/*  8 */       this.st0 = this.Ws.get();
/*    */       
/* 10 */       this.PH0 = this.Ws.getShort();
/*    */       
/* 12 */       this.LPT9 = this.Ws.getShort();
/*    */       
/* 14 */       this.ws = this.Ws.getShort(); }
/*    */      }
/*    */ 
/*    */   
/*    */   public byte P50;
/*    */   public byte oC0;
/*    */   public byte st0;
/*    */   public byte p5;
/*    */   public short PH0;
/*    */   public short LPT9;
/*    */   public short ws;
/*    */   
/*    */   public cOm6(c4 paramc4, ByteBuffer paramByteBuffer) {
/*    */     super(paramc4, paramByteBuffer);
/*    */   }
/*    */   
/*    */   public final void Cx() {
/*    */     // Byte code:
/*    */     //   0: aload_0
/*    */     //   1: getfield p5 : B
/*    */     //   4: dup
/*    */     //   5: istore_1
/*    */     //   6: ifne -> 36
/*    */     //   9: getstatic f/JC0.uu : Lf/JC0;
/*    */     //   12: dup
/*    */     //   13: dup
/*    */     //   14: astore_1
/*    */     //   15: aload_0
/*    */     //   16: getfield P50 : B
/*    */     //   19: istore_0
/*    */     //   20: monitorenter
/*    */     //   21: getfield Sq : Lf/z9;
/*    */     //   24: iload_0
/*    */     //   25: aconst_null
/*    */     //   26: invokevirtual VF : (BLjava/lang/Object;)Ljava/lang/Object;
/*    */     //   29: pop
/*    */     //   30: goto -> 9089
/*    */     //   33: aload_1
/*    */     //   34: monitorexit
/*    */     //   35: athrow
/*    */     //   36: iload_1
/*    */     //   37: aload_0
/*    */     //   38: dup
/*    */     //   39: dup2
/*    */     //   40: getstatic f/JC0.uu : Lf/JC0;
/*    */     //   43: astore_1
/*    */     //   44: getfield P50 : B
/*    */     //   47: istore_2
/*    */     //   48: getfield oC0 : B
/*    */     //   51: istore_3
/*    */     //   52: getfield st0 : B
/*    */     //   55: istore #4
/*    */     //   57: getfield PH0 : S
/*    */     //   60: istore #5
/*    */     //   62: iconst_2
/*    */     //   63: if_icmpne -> 72
/*    */     //   66: iconst_1
/*    */     //   67: istore #6
/*    */     //   69: goto -> 75
/*    */     //   72: iconst_0
/*    */     //   73: istore #6
/*    */     //   75: iload_2
/*    */     //   76: aload_1
/*    */     //   77: aload_0
/*    */     //   78: dup
/*    */     //   79: getfield LPT9 : S
/*    */     //   82: istore_0
/*    */     //   83: getfield ws : S
/*    */     //   86: istore #7
/*    */     //   88: monitorenter
/*    */     //   89: new f/o10
/*    */     //   92: dup
/*    */     //   93: dup
/*    */     //   94: dup2
/*    */     //   95: dup2
/*    */     //   96: dup2
/*    */     //   97: astore #8
/*    */     //   99: invokespecial <init> : ()V
/*    */     //   102: iload_2
/*    */     //   103: putfield hn : B
/*    */     //   106: iload #6
/*    */     //   108: putfield kT : Z
/*    */     //   111: iload #5
/*    */     //   113: putfield GS : S
/*    */     //   116: iload_0
/*    */     //   117: putfield lPT1 : S
/*    */     //   120: iload #7
/*    */     //   122: putfield wH : S
/*    */     //   125: iload_3
/*    */     //   126: putfield vw0 : B
/*    */     //   129: iload #4
/*    */     //   131: putfield m3 : B
/*    */     //   134: tableswitch default -> 168, 0 -> 205, 1 -> 205, 2 -> 171, 3 -> 171, 4 -> 171
/*    */     //   168: goto -> 9076
/*    */     //   171: getstatic f/km.mI0 : Lf/P1;
/*    */     //   174: iload_2
/*    */     //   175: invokevirtual s2 : (B)Z
/*    */     //   178: ifeq -> 9076
/*    */     //   181: aload #8
/*    */     //   183: getstatic f/km.mI0 : Lf/P1;
/*    */     //   186: iload_2
/*    */     //   187: invokevirtual LpT7 : (B)Lf/HI;
/*    */     //   190: iload_3
/*    */     //   191: iload #4
/*    */     //   193: invokestatic mF : (BB)S
/*    */     //   196: invokevirtual gH0 : (I)Lf/Ws0;
/*    */     //   199: putfield RB : Lf/Ws0;
/*    */     //   202: goto -> 9076
/*    */     //   205: iload_2
/*    */     //   206: iload_3
/*    */     //   207: iload #4
/*    */     //   209: invokestatic Zg0 : (BBB)I
/*    */     //   212: getstatic f/LF.xL0 : Lf/ik;
/*    */     //   215: pop
/*    */     //   216: lookupswitch default -> 8068, 0 -> 9067, 256 -> 9062, 512 -> 9057, 768 -> 9052, 1024 -> 9052, 1280 -> 9047, 1536 -> 9042, 1792 -> 9037, 2048 -> 9032, 2304 -> 9027, 2560 -> 9022, 2816 -> 9017, 3072 -> 9012, 3328 -> 9007, 3584 -> 9002, 3840 -> 8997, 4096 -> 8992, 4352 -> 8987, 4608 -> 8982, 4864 -> 8977, 5120 -> 8972, 5376 -> 8967, 5632 -> 8962, 5888 -> 8957, 6144 -> 8952, 6400 -> 8947, 6656 -> 8942, 6912 -> 8937, 7168 -> 8932, 7424 -> 8927, 7680 -> 8922, 7936 -> 8917, 8192 -> 8912, 8448 -> 8907, 8704 -> 8902, 8960 -> 8897, 9216 -> 8892, 9472 -> 8887, 9728 -> 8882, 9984 -> 8877, 10240 -> 8872, 10496 -> 8867, 10752 -> 8862, 11008 -> 8857, 12801 -> 8852, 13313 -> 8848, 13569 -> 8844, 13825 -> 8840, 14081 -> 8836, 14337 -> 8832, 14593 -> 8827, 14849 -> 8852, 15105 -> 8822, 15361 -> 8817, 15617 -> 8812, 15873 -> 8807, 16129 -> 8802, 16385 -> 8797, 16641 -> 8792, 16897 -> 8787, 17153 -> 8782, 17409 -> 8777, 17665 -> 8772, 17921 -> 8767, 18177 -> 8762, 18433 -> 8757, 18689 -> 8752, 18945 -> 8747, 19201 -> 8742, 19457 -> 8737, 19713 -> 8782, 19969 -> 8732, 20225 -> 8727, 20481 -> 8722, 20737 -> 8717, 20993 -> 8712, 21249 -> 8707, 25344 -> 8702, 65536 -> 9067, 65792 -> 8697, 66048 -> 8702, 66304 -> 9047, 66560 -> 9052, 66816 -> 9047, 67072 -> 9042, 67328 -> 9037, 67584 -> 9032, 67840 -> 9027, 68096 -> 9022, 68352 -> 9017, 68608 -> 9012, 68864 -> 9007, 69120 -> 9002, 69376 -> 8997, 69632 -> 8992, 69888 -> 8987, 70144 -> 8982, 70912 -> 8967, 71168 -> 8962, 71424 -> 8957, 71680 -> 8952, 71936 -> 8947, 72192 -> 8942, 73472 -> 8917, 73728 -> 8912, 73984 -> 8907, 74240 -> 8902, 74496 -> 8897, 74752 -> 8892, 75008 -> 8887, 76032 -> 8867, 76544 -> 8857, 78337 -> 8822, 78849 -> 8848, 79105 -> 8844, 79361 -> 8840, 79617 -> 8836, 79873 -> 8832, 80129 -> 8827, 80385 -> 8852, 80641 -> 8822, 80897 -> 8817, 81153 -> 8812, 81409 -> 8807, 81665 -> 8802, 81921 -> 8797, 82177 -> 8792, 82433 -> 8787, 82689 -> 8782, 82945 -> 8777, 83201 -> 8692, 83457 -> 8767, 84481 -> 8747, 84737 -> 8742, 84993 -> 8737, 85249 -> 8782, 85761 -> 8727, 86529 -> 8712, 90880 -> 8702, 131072 -> 9067, 131328 -> 8697, 131584 -> 8702, 131840 -> 9042, 132096 -> 9052, 132352 -> 9047, 132608 -> 9042, 132864 -> 9037, 133120 -> 9032, 133376 -> 9027, 133632 -> 9022, 133888 -> 9017, 134144 -> 9012, 134656 -> 9002, 134912 -> 8997, 136960 -> 8957, 137472 -> 8947, 139008 -> 8917, 139264 -> 8912, 139520 -> 8907, 139776 -> 8902, 140032 -> 8897, 140288 -> 8892, 140544 -> 8887, 142080 -> 8857, 143873 -> 8817, 144385 -> 8848, 144641 -> 8844, 144897 -> 8840, 145153 -> 8836, 145409 -> 8832, 145665 -> 8827, 145921 -> 8852, 146177 -> 8822, 146433 -> 8817, 146689 -> 8812, 146945 -> 8807, 147201 -> 8802, 147457 -> 8797, 147713 -> 8792, 147969 -> 8787, 148993 -> 8767, 150017 -> 8747, 150273 -> 8742, 150529 -> 8737, 151297 -> 8727, 152065 -> 8712, 196608 -> 9067, 196864 -> 8697, 197120 -> 8702, 197376 -> 9037, 197632 -> 9052, 197888 -> 9047, 198144 -> 9042, 198400 -> 9037, 198656 -> 9032, 198912 -> 9027, 199168 -> 9022, 199424 -> 9017, 199680 -> 9012, 200192 -> 9002, 200448 -> 8997, 204544 -> 8917, 204800 -> 8912, 205056 -> 8907, 205312 -> 8902, 205568 -> 8897, 205824 -> 8892, 206080 -> 8887, 207616 -> 8857, 209409 -> 8812, 209921 -> 8848, 210177 -> 8844, 210433 -> 8840, 210689 -> 8836, 210945 -> 8832, 211201 -> 8827, 211457 -> 8852, 211713 -> 8822, 211969 -> 8817, 212225 -> 8812, 212481 -> 8807, 212737 -> 8802, 212993 -> 8797, 213249 -> 8792, 213505 -> 8787, 215553 -> 8747, 215809 -> 8742, 216065 -> 8737, 216833 -> 8727, 262144 -> 9067, 262400 -> 8687, 262656 -> 8702, 262912 -> 9032, 263424 -> 9047, 263680 -> 9042, 263936 -> 9037, 264192 -> 9032, 264448 -> 9027, 264704 -> 9022, 264960 -> 9017, 265216 -> 9012, 265728 -> 9002, 270080 -> 8917, 270336 -> 8912, 270592 -> 8907, 270848 -> 8902, 271104 -> 8897, 271360 -> 8892, 271616 -> 8887, 273152 -> 8857, 274945 -> 8807, 275457 -> 8848, 275713 -> 8844, 275969 -> 8840, 276225 -> 8836, 276481 -> 8832, 276737 -> 8827, 276993 -> 8852, 277249 -> 8822, 277505 -> 8817, 277761 -> 8812, 278017 -> 8807, 278273 -> 8802, 278529 -> 8797, 278785 -> 8792, 279041 -> 8787, 281089 -> 8682, 281345 -> 8742, 281601 -> 8677, 282369 -> 8727, 327936 -> 8687, 328192 -> 8702, 328448 -> 9027, 328960 -> 9047, 329216 -> 9042, 329472 -> 9037, 329728 -> 9032, 329984 -> 9027, 330240 -> 9022, 330496 -> 9017, 330752 -> 9012, 331264 -> 9002, 335616 -> 8917, 336384 -> 8902, 336640 -> 8897, 338688 -> 8857, 340481 -> 8802, 341249 -> 8844, 341505 -> 8840, 341761 -> 8836, 342017 -> 8832, 342273 -> 8827, 342529 -> 8852, 342785 -> 8822, 343041 -> 8817, 343297 -> 8812, 343553 -> 8807, 343809 -> 8802, 344065 -> 8797, 344321 -> 8792, 344577 -> 8787, 346625 -> 8672, 346881 -> 8742, 347137 -> 8677, 347905 -> 8727, 393472 -> 8687, 393728 -> 8702, 393984 -> 9022, 394752 -> 9042, 395008 -> 9037, 395520 -> 9027, 395776 -> 9022, 396032 -> 9017, 396288 -> 9012, 396800 -> 9002, 401152 -> 8917, 401920 -> 8902, 402176 -> 8897, 404224 -> 8857, 406017 -> 8797, 407041 -> 8840, 407297 -> 8836, 407553 -> 8832, 407809 -> 8827, 408065 -> 8852, 408321 -> 8822, 408577 -> 8817, 408833 -> 8812, 409089 -> 8807, 409345 -> 8802, 409601 -> 8797, 409857 -> 8792, 410113 -> 8787, 412161 -> 8667, 412417 -> 8742, 412673 -> 8677, 413441 -> 8727, 459008 -> 8687, 459264 -> 8702, 459520 -> 9017, 460288 -> 9042, 460544 -> 9037, 461056 -> 9027, 461312 -> 9022, 461568 -> 9017, 461824 -> 9012, 462336 -> 9002, 467456 -> 8902, 467712 -> 8897, 469760 -> 8857, 471553 -> 8792, 472833 -> 8836, 473089 -> 8832, 473857 -> 8822, 474113 -> 8817, 474369 -> 8812, 474625 -> 8807, 474881 -> 8802, 475137 -> 8797, 475393 -> 8792, 475649 -> 8787, 477697 -> 8662, 477953 -> 8742, 478209 -> 8677, 478977 -> 8727, 524544 -> 8687, 524800 -> 8702, 525056 -> 9012, 526080 -> 9037, 526848 -> 9022, 527104 -> 9017, 527872 -> 9002, 535296 -> 8857, 537089 -> 8787, 538625 -> 8832, 539393 -> 8822, 539905 -> 8812, 540161 -> 8807, 540417 -> 8802, 540673 -> 8797, 540929 -> 8792, 541185 -> 8787, 543233 -> 8662, 543489 -> 8742, 543745 -> 8677, 544513 -> 8727, 590080 -> 8687, 590336 -> 8702, 590592 -> 9007, 591616 -> 9037, 592384 -> 9022, 592640 -> 9017, 593408 -> 9002, 600832 -> 8857, 604929 -> 8822, 605441 -> 8812, 605697 -> 8807, 605953 -> 8802, 606209 -> 8797, 606465 -> 8792, 606721 -> 8787, 608769 -> 8662, 609025 -> 8742, 609281 -> 8657, 610049 -> 8727, 615168 -> 8702, 655616 -> 8687, 655872 -> 8702, 656128 -> 9002, 657920 -> 9022, 666368 -> 8857, 668161 -> 8848, 670465 -> 8822, 670977 -> 8812, 671489 -> 8802, 671745 -> 8797, 672001 -> 8792, 672257 -> 8787, 674305 -> 8662, 674561 -> 8742, 674817 -> 8657, 675585 -> 8727, 721152 -> 8687, 721408 -> 8702, 721664 -> 9002, 723456 -> 9022, 731904 -> 8857, 733697 -> 8844, 736001 -> 8822, 736513 -> 8812, 737025 -> 8802, 737281 -> 8797, 737537 -> 8792, 737793 -> 8787, 739841 -> 8652, 740097 -> 8742, 740353 -> 8737, 741121 -> 8727, 786688 -> 8687, 786944 -> 8647, 787200 -> 8912, 788992 -> 9022, 797440 -> 8857, 799233 -> 8840, 801537 -> 8822, 802049 -> 8812, 802561 -> 8802, 802817 -> 8797, 803073 -> 8792, 803329 -> 8787, 805377 -> 8692, 805633 -> 8742, 805889 -> 8737, 806657 -> 8727, 852224 -> 8687, 852480 -> 8647, 852736 -> 8907, 854528 -> 9022, 862976 -> 8857, 864769 -> 8836, 867073 -> 8822, 867585 -> 8812, 868097 -> 8802, 868609 -> 8792, 868865 -> 8787, 870913 -> 8642, 871169 -> 8742, 871425 -> 8737, 917760 -> 8687, 918016 -> 8647, 918272 -> 8902, 920064 -> 9022, 928512 -> 8857, 930305 -> 8832, 933121 -> 8812, 933633 -> 8802, 934145 -> 8792, 934401 -> 8787, 936449 -> 8637, 936705 -> 8742, 936961 -> 8677, 983296 -> 8687, 983552 -> 8647, 983808 -> 8897, 985600 -> 9022, 994048 -> 8857, 995841 -> 8827, 998657 -> 8812, 999169 -> 8802, 1001985 -> 8632, 1002241 -> 8742, 1002497 -> 8677, 1048832 -> 8687, 1049088 -> 8647, 1049344 -> 8892, 1051136 -> 9022, 1059584 -> 8857, 1061377 -> 8627, 1064193 -> 8812, 1064705 -> 8802, 1067521 -> 8632, 1067777 -> 8742, 1068033 -> 8677, 1114368 -> 8687, 1114624 -> 8647, 1114880 -> 8917, 1116672 -> 9022, 1125120 -> 8857, 1126913 -> 8622, 1130241 -> 8802, 1133057 -> 8632, 1133313 -> 8742, 1133569 -> 8677, 1179904 -> 8687, 1180160 -> 8647, 1180416 -> 8887, 1182208 -> 9022, 1190656 -> 8857, 1192449 -> 8617, 1195777 -> 8802, 1198593 -> 8632, 1198849 -> 8742, 1199105 -> 8677, 1245440 -> 8687, 1245696 -> 8647, 1245952 -> 8612, 1247744 -> 9022, 1256192 -> 8857, 1257985 -> 8782, 1261313 -> 8802, 1264129 -> 8632, 1264385 -> 8742, 1264641 -> 8677, 1310976 -> 8687, 1311232 -> 8647, 1311488 -> 8997, 1321728 -> 8857, 1323521 -> 8607, 1326849 -> 8802, 1329665 -> 8632, 1329921 -> 8742, 1330177 -> 8677, 1376512 -> 8687, 1376768 -> 8647, 1377024 -> 8602, 1387264 -> 8857, 1389057 -> 8597, 1392385 -> 8802, 1395201 -> 8632, 1395457 -> 8742, 1395713 -> 8677, 1442048 -> 8687, 1442304 -> 8647, 1442560 -> 8992, 1452800 -> 8857, 1454593 -> 8592, 1457921 -> 8802, 1460737 -> 8632, 1460993 -> 8742, 1461249 -> 8677, 1507584 -> 8687, 1507840 -> 8647, 1508096 -> 8987, 1518336 -> 8857, 1520129 -> 8587, 1526273 -> 8582, 1526529 -> 8742, 1526785 -> 8677, 1573120 -> 8687, 1573376 -> 8647, 1573632 -> 8982, 1583872 -> 8857, 1585665 -> 8732, 1591809 -> 8582, 1592065 -> 8577, 1592321 -> 8677, 1638656 -> 8687, 1638912 -> 8647, 1639168 -> 8977, 1649408 -> 8857, 1651201 -> 8727, 1657345 -> 8582, 1657601 -> 8577, 1657857 -> 8677, 1704192 -> 8687, 1704448 -> 8647, 1704704 -> 8972, 1714944 -> 8857, 1716737 -> 8777, 1722881 -> 8572, 1723137 -> 8577, 1723393 -> 8677, 1769728 -> 8687, 1769984 -> 8567, 1770240 -> 8562, 1780480 -> 8857, 1782273 -> 8772, 1788417 -> 8557, 1788673 -> 8577, 1788929 -> 8677, 1835264 -> 8687, 1835520 -> 8552, 1835776 -> 8967, 1846016 -> 8857, 1847809 -> 8722, 1853953 -> 8557, 1854209 -> 8577, 1854465 -> 8677, 1900800 -> 8687, 1901056 -> 8547, 1901312 -> 8962, 1911552 -> 8857, 1913345 -> 8767, 1919489 -> 8557, 1919745 -> 8577, 1920001 -> 8677, 1966336 -> 8542, 1966592 -> 8537, 1966848 -> 8957, 1977088 -> 8857, 1978881 -> 8532, 1985025 -> 8557, 1985281 -> 8577, 1985537 -> 8677, 2031872 -> 8542, 2032128 -> 8527, 2032384 -> 8522, 2042624 -> 8857, 2044417 -> 8762, 2050561 -> 8557, 2050817 -> 8577, 2051073 -> 8677, 2097408 -> 8542, 2097664 -> 8517, 2097920 -> 8512, 2108160 -> 8857, 2109953 -> 8757, 2116097 -> 8557, 2116353 -> 8577, 2116609 -> 8677, 2162944 -> 8507, 2163200 -> 8502, 2163456 -> 8952, 2173696 -> 8857, 2175489 -> 8497, 2181633 -> 8557, 2181889 -> 8577, 2182145 -> 8677, 2228480 -> 8507, 2228736 -> 8492, 2228992 -> 8947, 2239232 -> 8857, 2241025 -> 8712, 2247169 -> 8557, 2247425 -> 8577, 2247681 -> 8677, 2294016 -> 8507, 2294272 -> 8487, 2294528 -> 8482, 2304768 -> 8857, 2306561 -> 8477, 2312705 -> 8557, 2312961 -> 8577, 2313217 -> 8677, 2359552 -> 8472, 2359808 -> 9057, 2360064 -> 8942, 2370304 -> 8857, 2372097 -> 8752, 2378241 -> 8557, 2378497 -> 8577, 2378753 -> 8677, 2425088 -> 8472, 2425344 -> 9057, 2425600 -> 8937, 2435840 -> 8857, 2437633 -> 8467, 2443777 -> 8462, 2444033 -> 8577, 2444289 -> 8677, 2490624 -> 8472, 2490880 -> 9057, 2491136 -> 8457, 2503169 -> 8717, 2509313 -> 8462, 2509569 -> 8577, 2509825 -> 8677, 2556160 -> 8452, 2556416 -> 9057, 2556672 -> 8447, 2568705 -> 8707, 2574849 -> 8462, 2575105 -> 8577, 2575361 -> 8677, 2621696 -> 8452, 2621952 -> 9057, 2622208 -> 8447, 2634241 -> 8442, 2640385 -> 8462, 2640641 -> 8437, 2640897 -> 8677, 2687232 -> 8452, 2687488 -> 9057, 2687744 -> 8932, 2699777 -> 8432, 2705921 -> 8462, 2706177 -> 8577, 2706433 -> 8677, 2752768 -> 8427, 2753024 -> 9057, 2753280 -> 8927, 2765313 -> 8422, 2771457 -> 8462, 2771713 -> 8577, 2771969 -> 8677, 2818304 -> 8427, 2818560 -> 9057, 2818816 -> 8417, 2830849 -> 8412, 2836993 -> 8407, 2837249 -> 8577, 2837505 -> 8677, 2883840 -> 8427, 2884096 -> 9057, 2884352 -> 8922, 2896385 -> 8402, 2902529 -> 8407, 2902785 -> 8577, 2903041 -> 8677, 2949376 -> 8427, 2949632 -> 9057, 2949888 -> 8397, 2961921 -> 8392, 2968065 -> 8407, 2968321 -> 8577, 2968577 -> 8677, 3014912 -> 8427, 3015168 -> 9057, 3015424 -> 8387, 3027457 -> 8382, 3033601 -> 8377, 3033857 -> 8577, 3034113 -> 8677, 3080448 -> 8372, 3080704 -> 9057, 3080960 -> 8872, 3092993 -> 8367, 3099137 -> 8377, 3099393 -> 8577, 3099649 -> 8677, 3145984 -> 8372, 3146240 -> 9057, 3146496 -> 8362, 3158529 -> 8357, 3164673 -> 8377, 3164929 -> 8577, 3165185 -> 8677, 3211520 -> 8372, 3211776 -> 9057, 3212032 -> 8882, 3224065 -> 8352, 3230209 -> 8377, 3230465 -> 8577, 3230721 -> 8677, 3277056 -> 8372, 3277312 -> 9057, 3277568 -> 8347, 3289601 -> 8342, 3295745 -> 8377, 3296001 -> 8577, 3296257 -> 8677, 3342592 -> 8372, 3342848 -> 9057, 3343104 -> 8337, 3355137 -> 8332, 3361281 -> 8377, 3361537 -> 8577, 3361793 -> 8677, 3408128 -> 8372, 3408384 -> 9057, 3408640 -> 8327, 3420673 -> 8322, 3426817 -> 8317, 3427073 -> 8577, 3427329 -> 8677, 3473664 -> 8372, 3473920 -> 9057, 3474176 -> 8312, 3486209 -> 8307, 3492353 -> 8317, 3492609 -> 8577, 3492865 -> 8677, 3539200 -> 8372, 3539456 -> 9057, 3539712 -> 8877, 3551745 -> 8857, 3557889 -> 8302, 3558145 -> 8577, 3558401 -> 8677, 3604736 -> 8372, 3604992 -> 9057, 3605248 -> 8297, 3617281 -> 8292, 3623425 -> 8302, 3623681 -> 8577, 3623937 -> 8677, 3670272 -> 8372, 3670528 -> 8287, 3670784 -> 8282, 3682817 -> 8277, 3688961 -> 8302, 3689217 -> 8577, 3689473 -> 8272, 3735808 -> 8372, 3736064 -> 8267, 3736320 -> 8262, 3754497 -> 8302, 3754753 -> 8577, 3755009 -> 8272, 3801344 -> 8372, 3801600 -> 8287, 3801856 -> 8257, 3820033 -> 8302, 3820289 -> 8577, 3820545 -> 8252, 3866880 -> 8247, 3867136 -> 9057, 3867392 -> 8242, 3885569 -> 8302, 3885825 -> 8577, 3886081 -> 8252, 3932416 -> 8247, 3932928 -> 8867, 3951105 -> 8302, 3951361 -> 8577, 3951617 -> 8237, 3997952 -> 8247, 3998464 -> 8232, 4016641 -> 8302, 4017153 -> 8237, 4063488 -> 8247, 4064000 -> 8227, 4082177 -> 8302, 4082689 -> 8237, 4129024 -> 8222, 4129536 -> 8217, 4147713 -> 8302, 4148225 -> 8237, 4194560 -> 8222, 4195072 -> 8862, 4213249 -> 8302, 4213761 -> 8237, 4260096 -> 8222, 4260608 -> 8212, 4278785 -> 8302, 4279297 -> 8237, 4325632 -> 8222, 4344321 -> 8302, 4344833 -> 8207, 4391168 -> 8222, 4409857 -> 8202, 4410369 -> 8207, 4456704 -> 8222, 4475393 -> 8197, 4475905 -> 8207, 4522240 -> 8222, 4540929 -> 8192, 4541441 -> 8207, 4587776 -> 8222, 4606465 -> 8192, 4606977 -> 8207, 4653312 -> 8222, 4672001 -> 8187, 4672513 -> 8207, 4718848 -> 8182, 4737537 -> 8187, 4738049 -> 8207, 4784384 -> 8182, 4803073 -> 8177, 4803585 -> 8207, 4849920 -> 8182, 4868609 -> 8582, 4869121 -> 8207, 4915456 -> 8172, 4934145 -> 8582, 4934657 -> 8207, 4980992 -> 8172, 4999681 -> 8582, 5000193 -> 8207, 5046528 -> 8172, 5065217 -> 8167, 5065729 -> 8207, 5112064 -> 8172, 5130753 -> 8167, 5131265 -> 8207, 5177600 -> 8172, 5196289 -> 8167, 5196801 -> 8207, 5243136 -> 8172, 5261825 -> 8167, 5262337 -> 8207, 5308672 -> 8162, 5327361 -> 8167, 5327873 -> 8207, 5374208 -> 8162, 5392897 -> 8167, 5393409 -> 8207, 5439744 -> 8157, 5458433 -> 8377, 5458945 -> 8207, 5505280 -> 8157, 5523969 -> 8167, 5524481 -> 8207, 5570816 -> 8157, 5589505 -> 8167, 5590017 -> 8207, 5636352 -> 8157, 5655041 -> 8152, 5655553 -> 8207, 5701888 -> 8157, 5720577 -> 8152, 5721089 -> 8207, 5767424 -> 8147, 5786113 -> 8152, 5786625 -> 8237, 5832960 -> 8147, 5851649 -> 8152, 5898496 -> 8147, 5917185 -> 8152, 5964032 -> 8147, 5982721 -> 8152, 6029568 -> 8147, 6048257 -> 8152, 6095104 -> 8147, 6113793 -> 8152, 6160640 -> 8147, 6179329 -> 8142, 6226176 -> 8137, 6244865 -> 8142, 6291712 -> 8132, 6310401 -> 8142, 6357248 -> 8132, 6375937 -> 8142, 6422784 -> 8132, 6441473 -> 8127, 6488320 -> 8132, 6507009 -> 8122, 6553856 -> 8132, 6554368 -> 9027, 6566401 -> 8822, 6572545 -> 8122, 6619392 -> 8132, 6638081 -> 8117, 6684928 -> 8132, 6703617 -> 8112, 6750464 -> 8132, 6769153 -> 8112, 6816000 -> 8132, 6834689 -> 8107, 6881536 -> 8132, 6900225 -> 8107, 6947072 -> 8132, 6965761 -> 8102, 7012608 -> 8132, 7031297 -> 8747, 7078144 -> 8132, 7143680 -> 8097, 7209216 -> 8092, 7274752 -> 8092, 7340288 -> 8092, 7405824 -> 8092, 7471360 -> 8087, 7536896 -> 8082, 7602432 -> 8082, 7667968 -> 8082, 7733504 -> 8082, 7799040 -> 8082, 7864576 -> 8082, 7930112 -> 8077, 7995648 -> 8072
/*    */     //   8068: iconst_0
/*    */     //   8069: goto -> 9069
/*    */     //   8072: bipush #-73
/*    */     //   8074: goto -> 9069
/*    */     //   8077: bipush #-74
/*    */     //   8079: goto -> 9069
/*    */     //   8082: bipush #-76
/*    */     //   8084: goto -> 9069
/*    */     //   8087: bipush #-78
/*    */     //   8089: goto -> 9069
/*    */     //   8092: bipush #-79
/*    */     //   8094: goto -> 9069
/*    */     //   8097: bipush #-80
/*    */     //   8099: goto -> 9069
/*    */     //   8102: bipush #-46
/*    */     //   8104: goto -> 9069
/*    */     //   8107: bipush #-51
/*    */     //   8109: goto -> 9069
/*    */     //   8112: bipush #-53
/*    */     //   8114: goto -> 9069
/*    */     //   8117: bipush #-52
/*    */     //   8119: goto -> 9069
/*    */     //   8122: bipush #-54
/*    */     //   8124: goto -> 9069
/*    */     //   8127: bipush #-47
/*    */     //   8129: goto -> 9069
/*    */     //   8132: bipush #-81
/*    */     //   8134: goto -> 9069
/*    */     //   8137: bipush #-114
/*    */     //   8139: goto -> 9069
/*    */     //   8142: bipush #-57
/*    */     //   8144: goto -> 9069
/*    */     //   8147: bipush #-116
/*    */     //   8149: goto -> 9069
/*    */     //   8152: bipush #-58
/*    */     //   8154: goto -> 9069
/*    */     //   8157: bipush #-117
/*    */     //   8159: goto -> 9069
/*    */     //   8162: bipush #-118
/*    */     //   8164: goto -> 9069
/*    */     //   8167: bipush #85
/*    */     //   8169: goto -> 9069
/*    */     //   8172: bipush #-119
/*    */     //   8174: goto -> 9069
/*    */     //   8177: bipush #80
/*    */     //   8179: goto -> 9069
/*    */     //   8182: bipush #-115
/*    */     //   8184: goto -> 9069
/*    */     //   8187: bipush #78
/*    */     //   8189: goto -> 9069
/*    */     //   8192: bipush #79
/*    */     //   8194: goto -> 9069
/*    */     //   8197: bipush #83
/*    */     //   8199: goto -> 9069
/*    */     //   8202: bipush #81
/*    */     //   8204: goto -> 9069
/*    */     //   8207: bipush #-45
/*    */     //   8209: goto -> 9069
/*    */     //   8212: bipush #-86
/*    */     //   8214: goto -> 9069
/*    */     //   8217: bipush #-88
/*    */     //   8219: goto -> 9069
/*    */     //   8222: bipush #-120
/*    */     //   8224: goto -> 9069
/*    */     //   8227: bipush #-89
/*    */     //   8229: goto -> 9069
/*    */     //   8232: bipush #-90
/*    */     //   8234: goto -> 9069
/*    */     //   8237: bipush #-44
/*    */     //   8239: goto -> 9069
/*    */     //   8242: bipush #-92
/*    */     //   8244: goto -> 9069
/*    */     //   8247: bipush #-121
/*    */     //   8249: goto -> 9069
/*    */     //   8252: bipush #-56
/*    */     //   8254: goto -> 9069
/*    */     //   8257: bipush #-93
/*    */     //   8259: goto -> 9069
/*    */     //   8262: bipush #-94
/*    */     //   8264: goto -> 9069
/*    */     //   8267: bipush #-61
/*    */     //   8269: goto -> 9069
/*    */     //   8272: bipush #-55
/*    */     //   8274: goto -> 9069
/*    */     //   8277: bipush #-49
/*    */     //   8279: goto -> 9069
/*    */     //   8282: bipush #-95
/*    */     //   8284: goto -> 9069
/*    */     //   8287: bipush #-69
/*    */     //   8289: goto -> 9069
/*    */     //   8292: bipush #-50
/*    */     //   8294: goto -> 9069
/*    */     //   8297: bipush #-96
/*    */     //   8299: goto -> 9069
/*    */     //   8302: bipush #61
/*    */     //   8304: goto -> 9069
/*    */     //   8307: bipush #53
/*    */     //   8309: goto -> 9069
/*    */     //   8312: bipush #-98
/*    */     //   8314: goto -> 9069
/*    */     //   8317: bipush #62
/*    */     //   8319: goto -> 9069
/*    */     //   8322: bipush #52
/*    */     //   8324: goto -> 9069
/*    */     //   8327: bipush #-99
/*    */     //   8329: goto -> 9069
/*    */     //   8332: bipush #51
/*    */     //   8334: goto -> 9069
/*    */     //   8337: bipush #-100
/*    */     //   8339: goto -> 9069
/*    */     //   8342: bipush #50
/*    */     //   8344: goto -> 9069
/*    */     //   8347: bipush #-101
/*    */     //   8349: goto -> 9069
/*    */     //   8352: bipush #49
/*    */     //   8354: goto -> 9069
/*    */     //   8357: bipush #48
/*    */     //   8359: goto -> 9069
/*    */     //   8362: bipush #-103
/*    */     //   8364: goto -> 9069
/*    */     //   8367: bipush #47
/*    */     //   8369: goto -> 9069
/*    */     //   8372: bipush #-122
/*    */     //   8374: goto -> 9069
/*    */     //   8377: bipush #67
/*    */     //   8379: goto -> 9069
/*    */     //   8382: bipush #46
/*    */     //   8384: goto -> 9069
/*    */     //   8387: bipush #-105
/*    */     //   8389: goto -> 9069
/*    */     //   8392: bipush #45
/*    */     //   8394: goto -> 9069
/*    */     //   8397: bipush #-106
/*    */     //   8399: goto -> 9069
/*    */     //   8402: bipush #44
/*    */     //   8404: goto -> 9069
/*    */     //   8407: bipush #70
/*    */     //   8409: goto -> 9069
/*    */     //   8412: bipush #43
/*    */     //   8414: goto -> 9069
/*    */     //   8417: bipush #124
/*    */     //   8419: goto -> 9069
/*    */     //   8422: bipush #42
/*    */     //   8424: goto -> 9069
/*    */     //   8427: bipush #-123
/*    */     //   8429: goto -> 9069
/*    */     //   8432: bipush #41
/*    */     //   8434: goto -> 9069
/*    */     //   8437: bipush #84
/*    */     //   8439: goto -> 9069
/*    */     //   8442: bipush #40
/*    */     //   8444: goto -> 9069
/*    */     //   8447: bipush #121
/*    */     //   8449: goto -> 9069
/*    */     //   8452: bipush #-124
/*    */     //   8454: goto -> 9069
/*    */     //   8457: bipush #120
/*    */     //   8459: goto -> 9069
/*    */     //   8462: bipush #72
/*    */     //   8464: goto -> 9069
/*    */     //   8467: bipush #37
/*    */     //   8469: goto -> 9069
/*    */     //   8472: bipush #-125
/*    */     //   8474: goto -> 9069
/*    */     //   8477: bipush #35
/*    */     //   8479: goto -> 9069
/*    */     //   8482: bipush #117
/*    */     //   8484: goto -> 9069
/*    */     //   8487: bipush #-70
/*    */     //   8489: goto -> 9069
/*    */     //   8492: bipush #-71
/*    */     //   8494: goto -> 9069
/*    */     //   8497: bipush #33
/*    */     //   8499: goto -> 9069
/*    */     //   8502: bipush #-62
/*    */     //   8504: goto -> 9069
/*    */     //   8507: bipush #-126
/*    */     //   8509: goto -> 9069
/*    */     //   8512: bipush #114
/*    */     //   8514: goto -> 9069
/*    */     //   8517: bipush #-63
/*    */     //   8519: goto -> 9069
/*    */     //   8522: bipush #113
/*    */     //   8524: goto -> 9069
/*    */     //   8527: bipush #-64
/*    */     //   8529: goto -> 9069
/*    */     //   8532: bipush #30
/*    */     //   8534: goto -> 9069
/*    */     //   8537: bipush #-65
/*    */     //   8539: goto -> 9069
/*    */     //   8542: bipush #-127
/*    */     //   8544: goto -> 9069
/*    */     //   8547: bipush #-66
/*    */     //   8549: goto -> 9069
/*    */     //   8552: bipush #-67
/*    */     //   8554: goto -> 9069
/*    */     //   8557: bipush #68
/*    */     //   8559: goto -> 9069
/*    */     //   8562: bipush #109
/*    */     //   8564: goto -> 9069
/*    */     //   8567: bipush #-68
/*    */     //   8569: goto -> 9069
/*    */     //   8572: bipush #69
/*    */     //   8574: goto -> 9069
/*    */     //   8577: bipush #87
/*    */     //   8579: goto -> 9069
/*    */     //   8582: bipush #-59
/*    */     //   8584: goto -> 9069
/*    */     //   8587: bipush #23
/*    */     //   8589: goto -> 9069
/*    */     //   8592: bipush #22
/*    */     //   8594: goto -> 9069
/*    */     //   8597: bipush #21
/*    */     //   8599: goto -> 9069
/*    */     //   8602: bipush #103
/*    */     //   8604: goto -> 9069
/*    */     //   8607: bipush #20
/*    */     //   8609: goto -> 9069
/*    */     //   8612: bipush #101
/*    */     //   8614: goto -> 9069
/*    */     //   8617: bipush #18
/*    */     //   8619: goto -> 9069
/*    */     //   8622: bipush #17
/*    */     //   8624: goto -> 9069
/*    */     //   8627: bipush #16
/*    */     //   8629: goto -> 9069
/*    */     //   8632: bipush #65
/*    */     //   8634: goto -> 9069
/*    */     //   8637: bipush #74
/*    */     //   8639: goto -> 9069
/*    */     //   8642: bipush #76
/*    */     //   8644: goto -> 9069
/*    */     //   8647: bipush #-75
/*    */     //   8649: goto -> 9069
/*    */     //   8652: bipush #59
/*    */     //   8654: goto -> 9069
/*    */     //   8657: bipush #73
/*    */     //   8659: goto -> 9069
/*    */     //   8662: bipush #55
/*    */     //   8664: goto -> 9069
/*    */     //   8667: bipush #82
/*    */     //   8669: goto -> 9069
/*    */     //   8672: bipush #54
/*    */     //   8674: goto -> 9069
/*    */     //   8677: bipush #58
/*    */     //   8679: goto -> 9069
/*    */     //   8682: bipush #60
/*    */     //   8684: goto -> 9069
/*    */     //   8687: bipush #-128
/*    */     //   8689: goto -> 9069
/*    */     //   8692: bipush #56
/*    */     //   8694: goto -> 9069
/*    */     //   8697: bipush #127
/*    */     //   8699: goto -> 9069
/*    */     //   8702: bipush #-77
/*    */     //   8704: goto -> 9069
/*    */     //   8707: bipush #39
/*    */     //   8709: goto -> 9069
/*    */     //   8712: bipush #34
/*    */     //   8714: goto -> 9069
/*    */     //   8717: bipush #38
/*    */     //   8719: goto -> 9069
/*    */     //   8722: bipush #28
/*    */     //   8724: goto -> 9069
/*    */     //   8727: bipush #25
/*    */     //   8729: goto -> 9069
/*    */     //   8732: bipush #24
/*    */     //   8734: goto -> 9069
/*    */     //   8737: bipush #57
/*    */     //   8739: goto -> 9069
/*    */     //   8742: bipush #86
/*    */     //   8744: goto -> 9069
/*    */     //   8747: bipush #63
/*    */     //   8749: goto -> 9069
/*    */     //   8752: bipush #36
/*    */     //   8754: goto -> 9069
/*    */     //   8757: bipush #32
/*    */     //   8759: goto -> 9069
/*    */     //   8762: bipush #31
/*    */     //   8764: goto -> 9069
/*    */     //   8767: bipush #29
/*    */     //   8769: goto -> 9069
/*    */     //   8772: bipush #27
/*    */     //   8774: goto -> 9069
/*    */     //   8777: bipush #26
/*    */     //   8779: goto -> 9069
/*    */     //   8782: bipush #19
/*    */     //   8784: goto -> 9069
/*    */     //   8787: bipush #15
/*    */     //   8789: goto -> 9069
/*    */     //   8792: bipush #14
/*    */     //   8794: goto -> 9069
/*    */     //   8797: bipush #13
/*    */     //   8799: goto -> 9069
/*    */     //   8802: bipush #12
/*    */     //   8804: goto -> 9069
/*    */     //   8807: bipush #11
/*    */     //   8809: goto -> 9069
/*    */     //   8812: bipush #10
/*    */     //   8814: goto -> 9069
/*    */     //   8817: bipush #9
/*    */     //   8819: goto -> 9069
/*    */     //   8822: bipush #8
/*    */     //   8824: goto -> 9069
/*    */     //   8827: bipush #6
/*    */     //   8829: goto -> 9069
/*    */     //   8832: iconst_5
/*    */     //   8833: goto -> 9069
/*    */     //   8836: iconst_4
/*    */     //   8837: goto -> 9069
/*    */     //   8840: iconst_3
/*    */     //   8841: goto -> 9069
/*    */     //   8844: iconst_2
/*    */     //   8845: goto -> 9069
/*    */     //   8848: iconst_1
/*    */     //   8849: goto -> 9069
/*    */     //   8852: bipush #7
/*    */     //   8854: goto -> 9069
/*    */     //   8857: bipush #-48
/*    */     //   8859: goto -> 9069
/*    */     //   8862: bipush #-87
/*    */     //   8864: goto -> 9069
/*    */     //   8867: bipush #-91
/*    */     //   8869: goto -> 9069
/*    */     //   8872: bipush #-104
/*    */     //   8874: goto -> 9069
/*    */     //   8877: bipush #-97
/*    */     //   8879: goto -> 9069
/*    */     //   8882: bipush #-102
/*    */     //   8884: goto -> 9069
/*    */     //   8887: bipush #-107
/*    */     //   8889: goto -> 9069
/*    */     //   8892: bipush #-109
/*    */     //   8894: goto -> 9069
/*    */     //   8897: bipush #-110
/*    */     //   8899: goto -> 9069
/*    */     //   8902: bipush #-111
/*    */     //   8904: goto -> 9069
/*    */     //   8907: bipush #-112
/*    */     //   8909: goto -> 9069
/*    */     //   8912: bipush #-113
/*    */     //   8914: goto -> 9069
/*    */     //   8917: bipush #-108
/*    */     //   8919: goto -> 9069
/*    */     //   8922: bipush #125
/*    */     //   8924: goto -> 9069
/*    */     //   8927: bipush #123
/*    */     //   8929: goto -> 9069
/*    */     //   8932: bipush #122
/*    */     //   8934: goto -> 9069
/*    */     //   8937: bipush #119
/*    */     //   8939: goto -> 9069
/*    */     //   8942: bipush #118
/*    */     //   8944: goto -> 9069
/*    */     //   8947: bipush #116
/*    */     //   8949: goto -> 9069
/*    */     //   8952: bipush #115
/*    */     //   8954: goto -> 9069
/*    */     //   8957: bipush #112
/*    */     //   8959: goto -> 9069
/*    */     //   8962: bipush #111
/*    */     //   8964: goto -> 9069
/*    */     //   8967: bipush #110
/*    */     //   8969: goto -> 9069
/*    */     //   8972: bipush #108
/*    */     //   8974: goto -> 9069
/*    */     //   8977: bipush #107
/*    */     //   8979: goto -> 9069
/*    */     //   8982: bipush #106
/*    */     //   8984: goto -> 9069
/*    */     //   8987: bipush #105
/*    */     //   8989: goto -> 9069
/*    */     //   8992: bipush #104
/*    */     //   8994: goto -> 9069
/*    */     //   8997: bipush #102
/*    */     //   8999: goto -> 9069
/*    */     //   9002: bipush #98
/*    */     //   9004: goto -> 9069
/*    */     //   9007: bipush #97
/*    */     //   9009: goto -> 9069
/*    */     //   9012: bipush #96
/*    */     //   9014: goto -> 9069
/*    */     //   9017: bipush #95
/*    */     //   9019: goto -> 9069
/*    */     //   9022: bipush #94
/*    */     //   9024: goto -> 9069
/*    */     //   9027: bipush #93
/*    */     //   9029: goto -> 9069
/*    */     //   9032: bipush #92
/*    */     //   9034: goto -> 9069
/*    */     //   9037: bipush #91
/*    */     //   9039: goto -> 9069
/*    */     //   9042: bipush #90
/*    */     //   9044: goto -> 9069
/*    */     //   9047: bipush #89
/*    */     //   9049: goto -> 9069
/*    */     //   9052: bipush #88
/*    */     //   9054: goto -> 9069
/*    */     //   9057: bipush #-82
/*    */     //   9059: goto -> 9069
/*    */     //   9062: bipush #126
/*    */     //   9064: goto -> 9069
/*    */     //   9067: bipush #-60
/*    */     //   9069: istore_0
/*    */     //   9070: aload #8
/*    */     //   9072: iload_0
/*    */     //   9073: putfield lPt1 : B
/*    */     //   9076: aload_1
/*    */     //   9077: getfield Sq : Lf/z9;
/*    */     //   9080: iload_2
/*    */     //   9081: aload #8
/*    */     //   9083: invokevirtual VF : (BLjava/lang/Object;)Ljava/lang/Object;
/*    */     //   9086: goto -> 29
/*    */     //   9089: aload_1
/*    */     //   9090: monitorexit
/*    */     //   9091: return
/*    */     //   9092: aload_1
/*    */     //   9093: monitorexit
/*    */     //   9094: athrow
/*    */     // Line number table:
/*    */     //   Java source line number -> byte code offset
/*    */     //   #1	-> 9
/*    */     //   #2	-> 16
/*    */     //   #3	-> 21
/*    */     //   #4	-> 40
/*    */     //   #5	-> 44
/*    */     //   #6	-> 89
/*    */     //   #7	-> 9090
/*    */     //   #8	-> 9093
/*    */     // Exception table:
/*    */     //   from	to	target	type
/*    */     //   21	29	33	finally
/*    */     //   89	92	9092	finally
/*    */     //   99	134	9092	finally
/*    */     //   171	178	9092	finally
/*    */     //   181	215	9092	finally
/*    */     //   9070	9089	9092	finally
/*    */   } }


/* Location:              /Users/vnnsnnt/Documents/Codespace/JavaWorkspace/RedTrainer/src/main/java/org/trainer/client/PokeMMO.jar!/f/cOm6.class
 * Java compiler version: 8 (52.0)
 * JD-Core Version:       1.1.3
 */