package f;

public final class cOm7 implements Runnable {
  public cOm7(cN paramcN, int paramInt) {}
  
  public final void run() {
    // Byte code:
    //   0: getstatic f/pA.Dg0 : Lf/pA;
    //   3: getfield WH : Lf/xJ0;
    //   6: dup
    //   7: astore_1
    //   8: ifnull -> 354
    //   11: aload_0
    //   12: aload_1
    //   13: aload_0
    //   14: getfield Lm0 : Lf/cN;
    //   17: getfield q70 : Lf/WD;
    //   20: getfield HA : S
    //   23: iconst_m1
    //   24: imul
    //   25: i2s
    //   26: invokevirtual dk0 : (S)B
    //   29: istore_1
    //   30: getstatic f/pA.Dg0 : Lf/pA;
    //   33: getfield WH : Lf/xJ0;
    //   36: astore_2
    //   37: getfield Ik : I
    //   40: dup
    //   41: istore_3
    //   42: iflt -> 69
    //   45: iload_3
    //   46: aload_2
    //   47: getfield sN : [Lf/SE0;
    //   50: dup
    //   51: astore_2
    //   52: arraylength
    //   53: if_icmplt -> 59
    //   56: goto -> 74
    //   59: aload_2
    //   60: iload_3
    //   61: aaload
    //   62: getfield hC0 : S
    //   65: istore_2
    //   66: goto -> 76
    //   69: aload_2
    //   70: invokevirtual getClass : ()Ljava/lang/Class;
    //   73: pop
    //   74: iconst_0
    //   75: istore_2
    //   76: iload_1
    //   77: iconst_m1
    //   78: if_icmple -> 131
    //   81: iload_1
    //   82: getstatic f/pA.Dg0 : Lf/pA;
    //   85: getfield WH : Lf/xJ0;
    //   88: astore_3
    //   89: iconst_0
    //   90: istore #4
    //   92: iconst_0
    //   93: istore #5
    //   95: iflt -> 126
    //   98: iload_1
    //   99: aload_3
    //   100: getfield sN : [Lf/SE0;
    //   103: dup
    //   104: astore_3
    //   105: arraylength
    //   106: if_icmplt -> 112
    //   109: goto -> 131
    //   112: aload_3
    //   113: iload_1
    //   114: aaload
    //   115: iload #5
    //   117: iload #4
    //   119: iconst_1
    //   120: invokevirtual Kh : (ISZ)V
    //   123: goto -> 131
    //   126: aload_3
    //   127: invokevirtual getClass : ()Ljava/lang/Class;
    //   130: pop
    //   131: aload_0
    //   132: getstatic f/pA.Dg0 : Lf/pA;
    //   135: getfield WH : Lf/xJ0;
    //   138: astore_1
    //   139: getfield Ik : I
    //   142: dup
    //   143: istore_3
    //   144: aload_0
    //   145: getfield Lm0 : Lf/cN;
    //   148: getfield q70 : Lf/WD;
    //   151: getfield HA : S
    //   154: iconst_m1
    //   155: imul
    //   156: i2s
    //   157: istore #4
    //   159: iconst_0
    //   160: istore #5
    //   162: iflt -> 193
    //   165: iload_3
    //   166: aload_1
    //   167: getfield sN : [Lf/SE0;
    //   170: dup
    //   171: astore_1
    //   172: arraylength
    //   173: if_icmplt -> 179
    //   176: goto -> 198
    //   179: aload_1
    //   180: iload_3
    //   181: aaload
    //   182: iload #5
    //   184: iload #4
    //   186: iconst_1
    //   187: invokevirtual Kh : (ISZ)V
    //   190: goto -> 198
    //   193: aload_1
    //   194: invokevirtual getClass : ()Ljava/lang/Class;
    //   197: pop
    //   198: iload_2
    //   199: aload_0
    //   200: getfield Lm0 : Lf/cN;
    //   203: dup
    //   204: astore_1
    //   205: getfield ZU : [Lf/Fy0;
    //   208: aload_1
    //   209: getfield hu : I
    //   212: aaload
    //   213: getfield As : Lf/rH;
    //   216: iconst_1
    //   217: anewarray f/pe0
    //   220: dup
    //   221: invokestatic ZZ : ()Lf/interface;
    //   224: getfield dR : Lf/pe0;
    //   227: iconst_0
    //   228: swap
    //   229: aastore
    //   230: invokevirtual Pn : ([Lf/pe0;)Lf/JG0;
    //   233: pop
    //   234: ifge -> 354
    //   237: aload_0
    //   238: getfield Lm0 : Lf/cN;
    //   241: getfield Pt0 : Lf/j40;
    //   244: getfield Zs : Lf/Q90;
    //   247: ifnull -> 354
    //   250: iconst_0
    //   251: istore_1
    //   252: iload_1
    //   253: aload_0
    //   254: getfield Lm0 : Lf/cN;
    //   257: getfield ZU : [Lf/Fy0;
    //   260: arraylength
    //   261: if_icmpge -> 354
    //   264: invokestatic cw : ()Lf/yk0;
    //   267: aload_0
    //   268: getfield Lm0 : Lf/cN;
    //   271: getfield Pt0 : Lf/j40;
    //   274: getfield Zs : Lf/Q90;
    //   277: getfield En0 : [S
    //   280: iload_1
    //   281: saload
    //   282: invokevirtual mP : (S)Lf/WD;
    //   285: dup
    //   286: astore_3
    //   287: ifnonnull -> 293
    //   290: goto -> 348
    //   293: aload_3
    //   294: getfield HA : S
    //   297: iconst_m1
    //   298: imul
    //   299: iload_2
    //   300: if_icmpne -> 348
    //   303: iload_2
    //   304: aload_0
    //   305: getfield Lm0 : Lf/cN;
    //   308: dup
    //   309: astore_3
    //   310: getfield q70 : Lf/WD;
    //   313: getfield HA : S
    //   316: iconst_m1
    //   317: imul
    //   318: if_icmpeq -> 348
    //   321: aload_3
    //   322: getfield ZU : [Lf/Fy0;
    //   325: iload_1
    //   326: aaload
    //   327: getfield As : Lf/rH;
    //   330: iconst_1
    //   331: anewarray f/pe0
    //   334: dup
    //   335: invokestatic ZZ : ()Lf/interface;
    //   338: getfield N8 : Lf/pe0;
    //   341: iconst_0
    //   342: swap
    //   343: aastore
    //   344: invokevirtual Pn : ([Lf/pe0;)Lf/JG0;
    //   347: pop
    //   348: iinc #1, 1
    //   351: goto -> 252
    //   354: return
    // Line number table:
    //   Java source line number -> byte code offset
    //   #1	-> 0
    //   #2	-> 3
    //   #3	-> 14
    //   #4	-> 20
    //   #5	-> 26
    //   #6	-> 30
    //   #7	-> 33
    //   #8	-> 37
    //   #9	-> 47
    //   #10	-> 52
    //   #11	-> 70
    //   #12	-> 82
    //   #13	-> 85
    //   #14	-> 100
    //   #15	-> 105
    //   #16	-> 120
    //   #17	-> 127
    //   #18	-> 132
    //   #19	-> 135
    //   #20	-> 139
    //   #21	-> 151
    //   #22	-> 167
    //   #23	-> 172
    //   #24	-> 187
    //   #25	-> 194
    //   #26	-> 213
    //   #27	-> 217
    //   #28	-> 224
    //   #29	-> 229
    //   #30	-> 244
    //   #31	-> 254
    //   #32	-> 274
    //   #33	-> 277
    //   #34	-> 281
    //   #35	-> 282
    //   #36	-> 294
    //   #37	-> 305
    //   #38	-> 313
    //   #39	-> 322
    //   #40	-> 327
    //   #41	-> 331
    //   #42	-> 338
    //   #43	-> 343
  }
}


/* Location:              /Users/vnnsnnt/Documents/Codespace/JavaWorkspace/RedTrainer/src/main/java/org/trainer/client/PokeMMO.jar!/f/cOm7.class
 * Java compiler version: 8 (52.0)
 * JD-Core Version:       1.1.3
 */