/*  1 */ package f;public final class d70 { public d70() { fQ fQ1; Ag ag; this(8); this.z6 = this; this(64); this.finally = this; } public static final byte[] dj = new byte[] { 0, 1, 0, 1, 1, 1, 2, 1, 3, 1, 4, 1, 5, 2, 1, 4, 2, 2, 4, 2, 6, 7, 2, 6, 8, 3, 0, 6, 7 }; public static byte[] XE() { return new byte[] { 0, 0, 0, 1, 0, 3, 3, 13, 1, 0, 0, 9, 0, 11, 11, 0, 0, 0, 0, 1, 25, 0, 19, 5, 16, 0, 1, 0, 1, 0, 0, 0, 22, 1, 0, 0, 3, 3, 13, 1, 0, 0, 9, 0, 11, 11, 0, 0, 0, 0, 1, 25, 0, 19, 5, 16, 0, 0, 0, 7, 1, 0, 0 }; } public final Jp0 g(RD0 paramRD0) { try { int i; String str = "UTF-8"; InputStream inputStream = paramRD0.Yc(); 
/*  2 */       try { InputStreamReader inputStreamReader; this(inputStream, str); 
/*  3 */         try { char[] arrayOfChar = new char[1024]; i = 0; while (true) { int j; if ((j = inputStreamReader.read(arrayOfChar, i, arrayOfChar.length - i)) == -1) { Ui.JC0(inputStreamReader); return sr0(arrayOfChar, i); }  if (j == 0) { arrayOfChar = new char[arrayOfChar.length * 2]; j = 0; boolean bool = false; int k = arrayOfChar.length; System.arraycopy(arrayOfChar, j, arrayOfChar, bool, k); continue; }  i += j; }  } catch (IOException iOException) { throw new kN(this); } finally {} Ui.JC0(inputStreamReader); throw this; } catch (UnsupportedEncodingException unsupportedEncodingException)
/*  4 */       { Ui.JC0(i); throw new JU("Error reading file: " + paramRD0, this); }  } catch (Exception exception)
/*  5 */     { throw new kN("Error parsing file: " + paramRD0, this); }  } public final Jp0 sr0(char[] paramArrayOfchar, int paramInt) { // Byte code:
/*    */     //   0: iconst_0
/*    */     //   1: istore_3
/*    */     //   2: iconst_0
/*    */     //   3: istore #4
/*    */     //   5: aconst_null
/*    */     //   6: astore #5
/*    */     //   8: iconst_0
/*    */     //   9: istore #6
/*    */     //   11: iconst_1
/*    */     //   12: istore #7
/*    */     //   14: iconst_0
/*    */     //   15: istore #8
/*    */     //   17: iload #8
/*    */     //   19: ifeq -> 37
/*    */     //   22: iload #8
/*    */     //   24: iconst_1
/*    */     //   25: if_icmpeq -> 56
/*    */     //   28: iload #8
/*    */     //   30: iconst_2
/*    */     //   31: if_icmpeq -> 1529
/*    */     //   34: goto -> 1555
/*    */     //   37: iload_3
/*    */     //   38: iload_2
/*    */     //   39: if_icmpne -> 48
/*    */     //   42: iconst_4
/*    */     //   43: istore #8
/*    */     //   45: goto -> 17
/*    */     //   48: iload #7
/*    */     //   50: ifne -> 56
/*    */     //   53: goto -> 1534
/*    */     //   56: getstatic f/d70.iz0 : [B
/*    */     //   59: iload #7
/*    */     //   61: baload
/*    */     //   62: istore #8
/*    */     //   64: getstatic f/d70.YX : [S
/*    */     //   67: iload #7
/*    */     //   69: saload
/*    */     //   70: istore #9
/*    */     //   72: getstatic f/d70.pG0 : [B
/*    */     //   75: iload #7
/*    */     //   77: baload
/*    */     //   78: dup
/*    */     //   79: istore #10
/*    */     //   81: ifle -> 193
/*    */     //   84: iload #8
/*    */     //   86: iload #10
/*    */     //   88: iadd
/*    */     //   89: dup
/*    */     //   90: istore #11
/*    */     //   92: iconst_1
/*    */     //   93: isub
/*    */     //   94: istore #12
/*    */     //   96: iload #8
/*    */     //   98: istore #13
/*    */     //   100: iload #12
/*    */     //   102: iload #13
/*    */     //   104: if_icmpge -> 125
/*    */     //   107: iload #9
/*    */     //   109: iload #10
/*    */     //   111: iadd
/*    */     //   112: istore #9
/*    */     //   114: iload #9
/*    */     //   116: iload #11
/*    */     //   118: istore #9
/*    */     //   120: istore #8
/*    */     //   122: goto -> 201
/*    */     //   125: aload_1
/*    */     //   126: iload_3
/*    */     //   127: iload #13
/*    */     //   129: iload #12
/*    */     //   131: iload #13
/*    */     //   133: isub
/*    */     //   134: iconst_1
/*    */     //   135: ishr
/*    */     //   136: iadd
/*    */     //   137: istore #14
/*    */     //   139: caload
/*    */     //   140: dup
/*    */     //   141: istore #15
/*    */     //   143: getstatic f/d70.yv : [C
/*    */     //   146: iload #14
/*    */     //   148: caload
/*    */     //   149: dup
/*    */     //   150: istore #16
/*    */     //   152: if_icmpge -> 164
/*    */     //   155: iload #14
/*    */     //   157: iconst_1
/*    */     //   158: isub
/*    */     //   159: istore #12
/*    */     //   161: goto -> 100
/*    */     //   164: iload #15
/*    */     //   166: iload #16
/*    */     //   168: if_icmple -> 180
/*    */     //   171: iload #14
/*    */     //   173: iconst_1
/*    */     //   174: iadd
/*    */     //   175: istore #13
/*    */     //   177: goto -> 100
/*    */     //   180: iload #14
/*    */     //   182: iload #8
/*    */     //   184: isub
/*    */     //   185: iload #9
/*    */     //   187: iadd
/*    */     //   188: istore #7
/*    */     //   190: goto -> 327
/*    */     //   193: iload #9
/*    */     //   195: iload #8
/*    */     //   197: istore #9
/*    */     //   199: istore #8
/*    */     //   201: getstatic f/d70.b1 : [B
/*    */     //   204: iload #7
/*    */     //   206: baload
/*    */     //   207: dup
/*    */     //   208: istore #7
/*    */     //   210: ifle -> 323
/*    */     //   213: iload #9
/*    */     //   215: iload #7
/*    */     //   217: iconst_1
/*    */     //   218: ishl
/*    */     //   219: iadd
/*    */     //   220: iconst_2
/*    */     //   221: isub
/*    */     //   222: istore #10
/*    */     //   224: iload #9
/*    */     //   226: istore #11
/*    */     //   228: iload #10
/*    */     //   230: iload #11
/*    */     //   232: if_icmpge -> 245
/*    */     //   235: iload #8
/*    */     //   237: iload #7
/*    */     //   239: iadd
/*    */     //   240: istore #7
/*    */     //   242: goto -> 327
/*    */     //   245: aload_1
/*    */     //   246: iload_3
/*    */     //   247: iload #11
/*    */     //   249: iload #10
/*    */     //   251: iload #11
/*    */     //   253: isub
/*    */     //   254: iconst_1
/*    */     //   255: ishr
/*    */     //   256: bipush #-2
/*    */     //   258: iand
/*    */     //   259: iadd
/*    */     //   260: istore #12
/*    */     //   262: caload
/*    */     //   263: dup
/*    */     //   264: istore #13
/*    */     //   266: getstatic f/d70.yv : [C
/*    */     //   269: dup
/*    */     //   270: astore #14
/*    */     //   272: iload #12
/*    */     //   274: caload
/*    */     //   275: if_icmpge -> 287
/*    */     //   278: iload #12
/*    */     //   280: iconst_2
/*    */     //   281: isub
/*    */     //   282: istore #10
/*    */     //   284: goto -> 228
/*    */     //   287: iload #13
/*    */     //   289: aload #14
/*    */     //   291: iload #12
/*    */     //   293: iconst_1
/*    */     //   294: iadd
/*    */     //   295: caload
/*    */     //   296: if_icmple -> 308
/*    */     //   299: iload #12
/*    */     //   301: iconst_2
/*    */     //   302: iadd
/*    */     //   303: istore #11
/*    */     //   305: goto -> 228
/*    */     //   308: iload #8
/*    */     //   310: iload #12
/*    */     //   312: iload #9
/*    */     //   314: isub
/*    */     //   315: iconst_1
/*    */     //   316: ishr
/*    */     //   317: iadd
/*    */     //   318: istore #7
/*    */     //   320: goto -> 327
/*    */     //   323: iload #8
/*    */     //   325: istore #7
/*    */     //   327: getstatic f/d70.dI0 : [B
/*    */     //   330: iload #7
/*    */     //   332: baload
/*    */     //   333: istore #7
/*    */     //   335: getstatic f/d70.nY : [B
/*    */     //   338: iload #7
/*    */     //   340: baload
/*    */     //   341: istore #8
/*    */     //   343: getstatic f/d70.TK : [B
/*    */     //   346: iload #7
/*    */     //   348: baload
/*    */     //   349: dup
/*    */     //   350: istore #7
/*    */     //   352: ifeq -> 1525
/*    */     //   355: getstatic f/d70.dj : [B
/*    */     //   358: iload #7
/*    */     //   360: dup
/*    */     //   361: iconst_1
/*    */     //   362: iadd
/*    */     //   363: istore #7
/*    */     //   365: baload
/*    */     //   366: istore #9
/*    */     //   368: iload #9
/*    */     //   370: dup
/*    */     //   371: iconst_m1
/*    */     //   372: iadd
/*    */     //   373: istore #9
/*    */     //   375: ifle -> 1525
/*    */     //   378: getstatic f/d70.dj : [B
/*    */     //   381: iload #7
/*    */     //   383: dup
/*    */     //   384: iconst_1
/*    */     //   385: iadd
/*    */     //   386: istore #7
/*    */     //   388: baload
/*    */     //   389: tableswitch default -> 440, 0 -> 1519, 1 -> 1106, 2 -> 1051, 3 -> 1021, 4 -> 1013, 5 -> 990, 6 -> 537, 7 -> 484, 8 -> 443
/*    */     //   440: goto -> 368
/*    */     //   443: aload_0
/*    */     //   444: dup
/*    */     //   445: getfield eO : Ljava/lang/String;
/*    */     //   448: astore #10
/*    */     //   450: getfield dQ : Lf/Jp0;
/*    */     //   453: dup
/*    */     //   454: astore #11
/*    */     //   456: getfield MK0 : Ljava/lang/String;
/*    */     //   459: dup
/*    */     //   460: astore #12
/*    */     //   462: ifnull -> 474
/*    */     //   465: aload #12
/*    */     //   467: aload #10
/*    */     //   469: invokestatic tF0 : (Ljava/lang/String;Ljava/lang/String;)Ljava/lang/String;
/*    */     //   472: astore #10
/*    */     //   474: aload #11
/*    */     //   476: aload #10
/*    */     //   478: putfield MK0 : Ljava/lang/String;
/*    */     //   481: goto -> 368
/*    */     //   484: aload_0
/*    */     //   485: dup
/*    */     //   486: getfield eO : Ljava/lang/String;
/*    */     //   489: astore #10
/*    */     //   491: getfield dQ : Lf/Jp0;
/*    */     //   494: dup
/*    */     //   495: astore #11
/*    */     //   497: getfield CT : Lf/f7;
/*    */     //   500: ifnonnull -> 521
/*    */     //   503: aload #11
/*    */     //   505: new f/f7
/*    */     //   508: dup
/*    */     //   509: astore #12
/*    */     //   511: bipush #8
/*    */     //   513: invokespecial <init> : (I)V
/*    */     //   516: aload #12
/*    */     //   518: putfield CT : Lf/f7;
/*    */     //   521: aload #11
/*    */     //   523: getfield CT : Lf/f7;
/*    */     //   526: aload #5
/*    */     //   528: aload #10
/*    */     //   530: invokevirtual X00 : (Ljava/lang/Object;Ljava/lang/Object;)Ljava/lang/Object;
/*    */     //   533: pop
/*    */     //   534: goto -> 368
/*    */     //   537: iload_3
/*    */     //   538: istore #10
/*    */     //   540: iload #10
/*    */     //   542: iload #4
/*    */     //   544: if_icmpeq -> 591
/*    */     //   547: aload_1
/*    */     //   548: iload #10
/*    */     //   550: iconst_1
/*    */     //   551: isub
/*    */     //   552: caload
/*    */     //   553: dup
/*    */     //   554: istore #11
/*    */     //   556: bipush #9
/*    */     //   558: if_icmpeq -> 585
/*    */     //   561: iload #11
/*    */     //   563: bipush #10
/*    */     //   565: if_icmpeq -> 585
/*    */     //   568: iload #11
/*    */     //   570: bipush #13
/*    */     //   572: if_icmpeq -> 585
/*    */     //   575: iload #11
/*    */     //   577: bipush #32
/*    */     //   579: if_icmpeq -> 585
/*    */     //   582: goto -> 591
/*    */     //   585: iinc #10, -1
/*    */     //   588: goto -> 540
/*    */     //   591: iconst_0
/*    */     //   592: istore #11
/*    */     //   594: iload #11
/*    */     //   596: iload #4
/*    */     //   598: istore #11
/*    */     //   600: istore #12
/*    */     //   602: iload #4
/*    */     //   604: iload #10
/*    */     //   606: if_icmpeq -> 856
/*    */     //   609: aload_1
/*    */     //   610: iload #4
/*    */     //   612: dup
/*    */     //   613: iconst_1
/*    */     //   614: iadd
/*    */     //   615: istore #4
/*    */     //   617: caload
/*    */     //   618: bipush #38
/*    */     //   620: if_icmpeq -> 626
/*    */     //   623: goto -> 602
/*    */     //   626: iload #4
/*    */     //   628: istore #13
/*    */     //   630: iload #13
/*    */     //   632: iload #10
/*    */     //   634: if_icmpeq -> 849
/*    */     //   637: aload_1
/*    */     //   638: iload #13
/*    */     //   640: dup
/*    */     //   641: iconst_1
/*    */     //   642: iadd
/*    */     //   643: istore #13
/*    */     //   645: caload
/*    */     //   646: bipush #59
/*    */     //   648: if_icmpeq -> 654
/*    */     //   651: goto -> 630
/*    */     //   654: aload_0
/*    */     //   655: getfield finally : Lf/Ag;
/*    */     //   658: aload_1
/*    */     //   659: iload #4
/*    */     //   661: iload #11
/*    */     //   663: isub
/*    */     //   664: iconst_1
/*    */     //   665: isub
/*    */     //   666: iload #11
/*    */     //   668: swap
/*    */     //   669: invokevirtual sG : ([CII)V
/*    */     //   672: new java/lang/String
/*    */     //   675: dup
/*    */     //   676: dup
/*    */     //   677: astore #11
/*    */     //   679: aload_1
/*    */     //   680: iload #13
/*    */     //   682: iload #4
/*    */     //   684: isub
/*    */     //   685: iconst_1
/*    */     //   686: isub
/*    */     //   687: iload #4
/*    */     //   689: swap
/*    */     //   690: invokespecial <init> : ([CII)V
/*    */     //   693: ldc 'lt'
/*    */     //   695: invokevirtual equals : (Ljava/lang/Object;)Z
/*    */     //   698: ifeq -> 708
/*    */     //   701: ldc '<'
/*    */     //   703: astore #4
/*    */     //   705: goto -> 809
/*    */     //   708: aload #11
/*    */     //   710: ldc 'gt'
/*    */     //   712: invokevirtual equals : (Ljava/lang/Object;)Z
/*    */     //   715: ifeq -> 725
/*    */     //   718: ldc '>'
/*    */     //   720: astore #4
/*    */     //   722: goto -> 809
/*    */     //   725: aload #11
/*    */     //   727: ldc 'amp'
/*    */     //   729: invokevirtual equals : (Ljava/lang/Object;)Z
/*    */     //   732: ifeq -> 742
/*    */     //   735: ldc '&'
/*    */     //   737: astore #4
/*    */     //   739: goto -> 809
/*    */     //   742: aload #11
/*    */     //   744: ldc 'apos'
/*    */     //   746: invokevirtual equals : (Ljava/lang/Object;)Z
/*    */     //   749: ifeq -> 759
/*    */     //   752: ldc '''
/*    */     //   754: astore #4
/*    */     //   756: goto -> 809
/*    */     //   759: aload #11
/*    */     //   761: ldc 'quot'
/*    */     //   763: invokevirtual equals : (Ljava/lang/Object;)Z
/*    */     //   766: ifeq -> 776
/*    */     //   769: ldc '"'
/*    */     //   771: astore #4
/*    */     //   773: goto -> 809
/*    */     //   776: aload #11
/*    */     //   778: ldc '#x'
/*    */     //   780: invokevirtual startsWith : (Ljava/lang/String;)Z
/*    */     //   783: ifeq -> 806
/*    */     //   786: aload #11
/*    */     //   788: iconst_2
/*    */     //   789: invokevirtual substring : (I)Ljava/lang/String;
/*    */     //   792: bipush #16
/*    */     //   794: invokestatic parseInt : (Ljava/lang/String;I)I
/*    */     //   797: i2c
/*    */     //   798: invokestatic toString : (C)Ljava/lang/String;
/*    */     //   801: astore #4
/*    */     //   803: goto -> 809
/*    */     //   806: aconst_null
/*    */     //   807: astore #4
/*    */     //   809: aload #4
/*    */     //   811: aload_0
/*    */     //   812: getfield finally : Lf/Ag;
/*    */     //   815: astore #12
/*    */     //   817: ifnull -> 824
/*    */     //   820: aload #4
/*    */     //   822: astore #11
/*    */     //   824: aload #12
/*    */     //   826: aload #11
/*    */     //   828: invokevirtual V9 : (Ljava/lang/String;)V
/*    */     //   831: iconst_1
/*    */     //   832: istore #11
/*    */     //   834: iload #13
/*    */     //   836: iload #11
/*    */     //   838: iload #13
/*    */     //   840: istore #11
/*    */     //   842: istore #12
/*    */     //   844: istore #4
/*    */     //   846: goto -> 602
/*    */     //   849: iload #13
/*    */     //   851: istore #4
/*    */     //   853: goto -> 602
/*    */     //   856: iload #12
/*    */     //   858: ifeq -> 956
/*    */     //   861: iload #11
/*    */     //   863: iload #10
/*    */     //   865: if_icmpge -> 884
/*    */     //   868: aload_0
/*    */     //   869: getfield finally : Lf/Ag;
/*    */     //   872: aload_1
/*    */     //   873: iload #10
/*    */     //   875: iload #11
/*    */     //   877: isub
/*    */     //   878: iload #11
/*    */     //   880: swap
/*    */     //   881: invokevirtual sG : ([CII)V
/*    */     //   884: aload_0
/*    */     //   885: dup
/*    */     //   886: dup
/*    */     //   887: getfield finally : Lf/Ag;
/*    */     //   890: invokevirtual toString : ()Ljava/lang/String;
/*    */     //   893: putfield eO : Ljava/lang/String;
/*    */     //   896: getfield finally : Lf/Ag;
/*    */     //   899: dup
/*    */     //   900: astore #4
/*    */     //   902: iconst_0
/*    */     //   903: istore #10
/*    */     //   905: getfield bF0 : [C
/*    */     //   908: dup
/*    */     //   909: astore #12
/*    */     //   911: arraylength
/*    */     //   912: ifge -> 925
/*    */     //   915: aload #4
/*    */     //   917: iload #10
/*    */     //   919: invokevirtual LpT8 : (I)V
/*    */     //   922: goto -> 946
/*    */     //   925: aload #4
/*    */     //   927: getfield Td0 : I
/*    */     //   930: dup
/*    */     //   931: istore #13
/*    */     //   933: ifge -> 946
/*    */     //   936: aload #12
/*    */     //   938: iload #13
/*    */     //   940: iload #10
/*    */     //   942: iconst_0
/*    */     //   943: invokestatic fill : ([CIIC)V
/*    */     //   946: aload #4
/*    */     //   948: iload #10
/*    */     //   950: putfield Td0 : I
/*    */     //   953: goto -> 983
/*    */     //   956: aload_0
/*    */     //   957: new java/lang/String
/*    */     //   960: dup
/*    */     //   961: astore #4
/*    */     //   963: iload #10
/*    */     //   965: iload #11
/*    */     //   967: isub
/*    */     //   968: istore #10
/*    */     //   970: aload_1
/*    */     //   971: iload #11
/*    */     //   973: iload #10
/*    */     //   975: invokespecial <init> : ([CII)V
/*    */     //   978: aload #4
/*    */     //   980: putfield eO : Ljava/lang/String;
/*    */     //   983: iload #11
/*    */     //   985: istore #4
/*    */     //   987: goto -> 368
/*    */     //   990: new java/lang/String
/*    */     //   993: dup
/*    */     //   994: astore #5
/*    */     //   996: iload_3
/*    */     //   997: iload #4
/*    */     //   999: isub
/*    */     //   1000: istore #10
/*    */     //   1002: aload_1
/*    */     //   1003: iload #4
/*    */     //   1005: iload #10
/*    */     //   1007: invokespecial <init> : ([CII)V
/*    */     //   1010: goto -> 368
/*    */     //   1013: iload #6
/*    */     //   1015: ifeq -> 368
/*    */     //   1018: goto -> 1509
/*    */     //   1021: aload_0
/*    */     //   1022: dup
/*    */     //   1023: dup
/*    */     //   1024: getfield z6 : Lf/fQ;
/*    */     //   1027: invokevirtual pop : ()Ljava/lang/Object;
/*    */     //   1030: checkcast f/Jp0
/*    */     //   1033: putfield dD0 : Lf/Jp0;
/*    */     //   1036: getfield z6 : Lf/fQ;
/*    */     //   1039: dup
/*    */     //   1040: astore #7
/*    */     //   1042: getfield Z8 : I
/*    */     //   1045: ifle -> 1094
/*    */     //   1048: goto -> 1081
/*    */     //   1051: aload_0
/*    */     //   1052: dup
/*    */     //   1053: dup
/*    */     //   1054: iconst_0
/*    */     //   1055: istore #6
/*    */     //   1057: getfield z6 : Lf/fQ;
/*    */     //   1060: invokevirtual pop : ()Ljava/lang/Object;
/*    */     //   1063: checkcast f/Jp0
/*    */     //   1066: putfield dD0 : Lf/Jp0;
/*    */     //   1069: getfield z6 : Lf/fQ;
/*    */     //   1072: dup
/*    */     //   1073: astore #7
/*    */     //   1075: getfield Z8 : I
/*    */     //   1078: ifle -> 1094
/*    */     //   1081: aload #7
/*    */     //   1083: invokevirtual peek : ()Ljava/lang/Object;
/*    */     //   1086: checkcast f/Jp0
/*    */     //   1089: astore #7
/*    */     //   1091: goto -> 1097
/*    */     //   1094: aconst_null
/*    */     //   1095: astore #7
/*    */     //   1097: aload_0
/*    */     //   1098: aload #7
/*    */     //   1100: putfield dQ : Lf/Jp0;
/*    */     //   1103: goto -> 1509
/*    */     //   1106: aload_1
/*    */     //   1107: iload #4
/*    */     //   1109: caload
/*    */     //   1110: dup
/*    */     //   1111: istore #10
/*    */     //   1113: bipush #63
/*    */     //   1115: if_icmpeq -> 1231
/*    */     //   1118: iload #10
/*    */     //   1120: bipush #33
/*    */     //   1122: if_icmpne -> 1128
/*    */     //   1125: goto -> 1231
/*    */     //   1128: aload_0
/*    */     //   1129: iconst_1
/*    */     //   1130: istore #6
/*    */     //   1132: new java/lang/String
/*    */     //   1135: dup
/*    */     //   1136: astore #10
/*    */     //   1138: iload_3
/*    */     //   1139: iload #4
/*    */     //   1141: isub
/*    */     //   1142: istore #11
/*    */     //   1144: aload_1
/*    */     //   1145: iload #4
/*    */     //   1147: iload #11
/*    */     //   1149: invokespecial <init> : ([CII)V
/*    */     //   1152: new f/Jp0
/*    */     //   1155: dup
/*    */     //   1156: astore #11
/*    */     //   1158: aload_0
/*    */     //   1159: getfield dQ : Lf/Jp0;
/*    */     //   1162: aload #10
/*    */     //   1164: swap
/*    */     //   1165: invokespecial <init> : (Ljava/lang/String;Lf/Jp0;)V
/*    */     //   1168: getfield dQ : Lf/Jp0;
/*    */     //   1171: dup
/*    */     //   1172: astore #10
/*    */     //   1174: ifnull -> 1213
/*    */     //   1177: aload #10
/*    */     //   1179: getfield gu0 : Lf/fQ;
/*    */     //   1182: ifnonnull -> 1203
/*    */     //   1185: aload #10
/*    */     //   1187: new f/fQ
/*    */     //   1190: dup
/*    */     //   1191: astore #12
/*    */     //   1193: bipush #8
/*    */     //   1195: invokespecial <init> : (I)V
/*    */     //   1198: aload #12
/*    */     //   1200: putfield gu0 : Lf/fQ;
/*    */     //   1203: aload #10
/*    */     //   1205: getfield gu0 : Lf/fQ;
/*    */     //   1208: aload #11
/*    */     //   1210: invokevirtual Com3 : (Ljava/lang/Object;)V
/*    */     //   1213: aload_0
/*    */     //   1214: aload #11
/*    */     //   1216: aload_0
/*    */     //   1217: getfield z6 : Lf/fQ;
/*    */     //   1220: aload #11
/*    */     //   1222: invokevirtual Com3 : (Ljava/lang/Object;)V
/*    */     //   1225: putfield dQ : Lf/Jp0;
/*    */     //   1228: goto -> 368
/*    */     //   1231: aload_1
/*    */     //   1232: iload #4
/*    */     //   1234: iconst_1
/*    */     //   1235: iadd
/*    */     //   1236: caload
/*    */     //   1237: dup
/*    */     //   1238: istore #7
/*    */     //   1240: bipush #91
/*    */     //   1242: if_icmpne -> 1419
/*    */     //   1245: aload_1
/*    */     //   1246: iload #4
/*    */     //   1248: iconst_2
/*    */     //   1249: iadd
/*    */     //   1250: caload
/*    */     //   1251: bipush #67
/*    */     //   1253: if_icmpne -> 1419
/*    */     //   1256: aload_1
/*    */     //   1257: iload #4
/*    */     //   1259: iconst_3
/*    */     //   1260: iadd
/*    */     //   1261: caload
/*    */     //   1262: bipush #68
/*    */     //   1264: if_icmpne -> 1419
/*    */     //   1267: aload_1
/*    */     //   1268: iload #4
/*    */     //   1270: iconst_4
/*    */     //   1271: iadd
/*    */     //   1272: caload
/*    */     //   1273: bipush #65
/*    */     //   1275: if_icmpne -> 1419
/*    */     //   1278: aload_1
/*    */     //   1279: iload #4
/*    */     //   1281: iconst_5
/*    */     //   1282: iadd
/*    */     //   1283: caload
/*    */     //   1284: bipush #84
/*    */     //   1286: if_icmpne -> 1419
/*    */     //   1289: aload_1
/*    */     //   1290: iload #4
/*    */     //   1292: bipush #6
/*    */     //   1294: iadd
/*    */     //   1295: caload
/*    */     //   1296: bipush #65
/*    */     //   1298: if_icmpne -> 1419
/*    */     //   1301: aload_1
/*    */     //   1302: iload #4
/*    */     //   1304: bipush #7
/*    */     //   1306: iadd
/*    */     //   1307: caload
/*    */     //   1308: bipush #91
/*    */     //   1310: if_icmpne -> 1419
/*    */     //   1313: iload #4
/*    */     //   1315: bipush #8
/*    */     //   1317: iadd
/*    */     //   1318: dup
/*    */     //   1319: istore #8
/*    */     //   1321: iconst_2
/*    */     //   1322: iadd
/*    */     //   1323: istore_3
/*    */     //   1324: aload_1
/*    */     //   1325: iload_3
/*    */     //   1326: iconst_2
/*    */     //   1327: isub
/*    */     //   1328: caload
/*    */     //   1329: bipush #93
/*    */     //   1331: if_icmpne -> 1413
/*    */     //   1334: aload_1
/*    */     //   1335: iload_3
/*    */     //   1336: iconst_1
/*    */     //   1337: isub
/*    */     //   1338: caload
/*    */     //   1339: bipush #93
/*    */     //   1341: if_icmpne -> 1413
/*    */     //   1344: aload_1
/*    */     //   1345: iload_3
/*    */     //   1346: caload
/*    */     //   1347: bipush #62
/*    */     //   1349: if_icmpeq -> 1355
/*    */     //   1352: goto -> 1413
/*    */     //   1355: aload_0
/*    */     //   1356: new java/lang/String
/*    */     //   1359: dup
/*    */     //   1360: astore #4
/*    */     //   1362: aload_1
/*    */     //   1363: iload_3
/*    */     //   1364: iload #8
/*    */     //   1366: isub
/*    */     //   1367: iconst_2
/*    */     //   1368: isub
/*    */     //   1369: iload #8
/*    */     //   1371: swap
/*    */     //   1372: invokespecial <init> : ([CII)V
/*    */     //   1375: getfield dQ : Lf/Jp0;
/*    */     //   1378: dup
/*    */     //   1379: astore #7
/*    */     //   1381: getfield MK0 : Ljava/lang/String;
/*    */     //   1384: dup
/*    */     //   1385: astore #9
/*    */     //   1387: ifnull -> 1399
/*    */     //   1390: aload #9
/*    */     //   1392: aload #4
/*    */     //   1394: invokestatic tF0 : (Ljava/lang/String;Ljava/lang/String;)Ljava/lang/String;
/*    */     //   1397: astore #4
/*    */     //   1399: aload #7
/*    */     //   1401: aload #4
/*    */     //   1403: putfield MK0 : Ljava/lang/String;
/*    */     //   1406: iload #8
/*    */     //   1408: istore #4
/*    */     //   1410: goto -> 1509
/*    */     //   1413: iinc #3, 1
/*    */     //   1416: goto -> 1324
/*    */     //   1419: iload #10
/*    */     //   1421: bipush #33
/*    */     //   1423: if_icmpne -> 1495
/*    */     //   1426: iload #7
/*    */     //   1428: bipush #45
/*    */     //   1430: if_icmpne -> 1495
/*    */     //   1433: aload_1
/*    */     //   1434: iload #4
/*    */     //   1436: iconst_2
/*    */     //   1437: iadd
/*    */     //   1438: caload
/*    */     //   1439: bipush #45
/*    */     //   1441: if_icmpne -> 1495
/*    */     //   1444: iload #4
/*    */     //   1446: iconst_3
/*    */     //   1447: iadd
/*    */     //   1448: istore_3
/*    */     //   1449: aload_1
/*    */     //   1450: iload_3
/*    */     //   1451: caload
/*    */     //   1452: bipush #45
/*    */     //   1454: if_icmpne -> 1489
/*    */     //   1457: aload_1
/*    */     //   1458: iload_3
/*    */     //   1459: iconst_1
/*    */     //   1460: iadd
/*    */     //   1461: caload
/*    */     //   1462: bipush #45
/*    */     //   1464: if_icmpne -> 1489
/*    */     //   1467: aload_1
/*    */     //   1468: iload_3
/*    */     //   1469: iconst_2
/*    */     //   1470: iadd
/*    */     //   1471: dup
/*    */     //   1472: istore #7
/*    */     //   1474: caload
/*    */     //   1475: bipush #62
/*    */     //   1477: if_icmpeq -> 1483
/*    */     //   1480: goto -> 1489
/*    */     //   1483: iload #7
/*    */     //   1485: istore_3
/*    */     //   1486: goto -> 1509
/*    */     //   1489: iinc #3, 1
/*    */     //   1492: goto -> 1449
/*    */     //   1495: aload_1
/*    */     //   1496: iload_3
/*    */     //   1497: caload
/*    */     //   1498: bipush #62
/*    */     //   1500: if_icmpeq -> 1509
/*    */     //   1503: iinc #3, 1
/*    */     //   1506: goto -> 1495
/*    */     //   1509: bipush #15
/*    */     //   1511: istore #7
/*    */     //   1513: iconst_2
/*    */     //   1514: istore #8
/*    */     //   1516: goto -> 17
/*    */     //   1519: iload_3
/*    */     //   1520: istore #4
/*    */     //   1522: goto -> 368
/*    */     //   1525: iload #8
/*    */     //   1527: istore #7
/*    */     //   1529: iload #7
/*    */     //   1531: ifne -> 1540
/*    */     //   1534: iconst_5
/*    */     //   1535: istore #8
/*    */     //   1537: goto -> 17
/*    */     //   1540: iload_3
/*    */     //   1541: iconst_1
/*    */     //   1542: iadd
/*    */     //   1543: dup
/*    */     //   1544: istore_3
/*    */     //   1545: iload_2
/*    */     //   1546: if_icmpeq -> 1555
/*    */     //   1549: iconst_1
/*    */     //   1550: istore #8
/*    */     //   1552: goto -> 17
/*    */     //   1555: iload_3
/*    */     //   1556: aload_0
/*    */     //   1557: aconst_null
/*    */     //   1558: putfield eO : Ljava/lang/String;
/*    */     //   1561: iload_2
/*    */     //   1562: if_icmpge -> 1637
/*    */     //   1565: iconst_1
/*    */     //   1566: istore_0
/*    */     //   1567: iconst_0
/*    */     //   1568: istore #4
/*    */     //   1570: iload #4
/*    */     //   1572: iload_3
/*    */     //   1573: if_icmpge -> 1594
/*    */     //   1576: aload_1
/*    */     //   1577: iload #4
/*    */     //   1579: caload
/*    */     //   1580: bipush #10
/*    */     //   1582: if_icmpne -> 1588
/*    */     //   1585: iinc #0, 1
/*    */     //   1588: iinc #4, 1
/*    */     //   1591: goto -> 1570
/*    */     //   1594: new f/kN
/*    */     //   1597: dup
/*    */     //   1598: ldc_w 'Error parsing XML on line '
/*    */     //   1601: iload_0
/*    */     //   1602: ldc_w ' near: '
/*    */     //   1605: invokestatic DH0 : (Ljava/lang/String;ILjava/lang/String;)Ljava/lang/StringBuilder;
/*    */     //   1608: new java/lang/String
/*    */     //   1611: dup
/*    */     //   1612: aload_1
/*    */     //   1613: iload_2
/*    */     //   1614: iload_3
/*    */     //   1615: isub
/*    */     //   1616: bipush #32
/*    */     //   1618: swap
/*    */     //   1619: invokestatic min : (II)I
/*    */     //   1622: iload_3
/*    */     //   1623: swap
/*    */     //   1624: invokespecial <init> : ([CII)V
/*    */     //   1627: invokevirtual append : (Ljava/lang/String;)Ljava/lang/StringBuilder;
/*    */     //   1630: invokevirtual toString : ()Ljava/lang/String;
/*    */     //   1633: invokespecial <init> : (Ljava/lang/String;)V
/*    */     //   1636: athrow
/*    */     //   1637: aload_0
/*    */     //   1638: getfield z6 : Lf/fQ;
/*    */     //   1641: dup
/*    */     //   1642: astore_1
/*    */     //   1643: getfield Z8 : I
/*    */     //   1646: ifne -> 1659
/*    */     //   1649: aload_0
/*    */     //   1650: getfield dD0 : Lf/Jp0;
/*    */     //   1653: aload_0
/*    */     //   1654: aconst_null
/*    */     //   1655: putfield dD0 : Lf/Jp0;
/*    */     //   1658: areturn
/*    */     //   1659: aload_0
/*    */     //   1660: aload_1
/*    */     //   1661: invokevirtual peek : ()Ljava/lang/Object;
/*    */     //   1664: checkcast f/Jp0
/*    */     //   1667: astore_0
/*    */     //   1668: getfield z6 : Lf/fQ;
/*    */     //   1671: invokevirtual clear : ()V
/*    */     //   1674: new f/kN
/*    */     //   1677: dup
/*    */     //   1678: ldc_w 'Error parsing XML, unclosed element: '
/*    */     //   1681: invokestatic df : (Ljava/lang/String;)Ljava/lang/StringBuilder;
/*    */     //   1684: aload_0
/*    */     //   1685: getfield Xh0 : Ljava/lang/String;
/*    */     //   1688: invokevirtual append : (Ljava/lang/String;)Ljava/lang/StringBuilder;
/*    */     //   1691: invokevirtual toString : ()Ljava/lang/String;
/*    */     //   1694: invokespecial <init> : (Ljava/lang/String;)V
/*    */     //   1697: athrow
/*    */     // Line number table:
/*    */     //   Java source line number -> byte code offset
/*    */     //   #1	-> 450
/*    */     //   #2	-> 456
/*    */     //   #3	-> 469
/*    */     //   #4	-> 478
/*    */     //   #5	-> 486
/*    */     //   #6	-> 491
/*    */     //   #7	-> 497
/*    */     //   #8	-> 505
/*    */     //   #9	-> 552
/*    */     //   #10	-> 669
/*    */     //   #11	-> 672
/*    */     //   #12	-> 693
/*    */     //   #13	-> 812
/*    */     //   #14	-> 828
/*    */     //   #15	-> 869
/*    */     //   #16	-> 881
/*    */     //   #17	-> 887
/*    */     //   #18	-> 905
/*    */     //   #19	-> 911
/*    */     //   #20	-> 957
/*    */     //   #21	-> 1024
/*    */     //   #22	-> 1109
/*    */     //   #23	-> 1152
/*    */     //   #24	-> 1179
/*    */     //   #25	-> 1217
/*    */     //   #26	-> 1236
/*    */     //   #27	-> 1375
/*    */     //   #28	-> 1381
/*    */     //   #29	-> 1394
/*    */     //   #30	-> 1403
/*    */     //   #31	-> 1438
/*    */     //   #32	-> 1598
/*    */     //   #33	-> 1608
/*    */     //   #34	-> 1678
/*    */     //   #35	-> 1685
/*  5 */     //   #36	-> 1688 } public static final byte[] iz0 = new byte[] { 0, 0, 4, 9, 14, 20, 26, 30, 35, 36, 37, 42, 46, 50, 51, 52, 56, 57, 62, 67, 73, 79, 83, 88, 89, 90, 95, 99, 103, 104, 108, 109, 110, 111, 112, 115 }; public static final char[] yv = new char[] { ' ', '<', '\t', '\r', ' ', '/', '>', '\t', '\r', ' ', '/', '>', '\t', '\r', ' ', '/', '=', '>', '\t', '\r', ' ', '/', '=', '>', '\t', '\r', ' ', '=', '\t', '\r', ' ', '"', '\'', '\t', '\r', '"', '"', ' ', '/', '>', '\t', '\r', ' ', '>', '\t', '\r', ' ', '>', '\t', '\r', '\'', '\'', ' ', '<', '\t', '\r', '<', ' ', '/', '>', '\t', '\r', ' ', '/', '>', '\t', '\r', ' ', '/', '=', '>', '\t', '\r', ' ', '/', '=', '>', '\t', '\r', ' ', '=', '\t', '\r', ' ', '"', '\'', '\t', '\r', '"', '"', ' ', '/', '>', '\t', '\r', ' ', '>', '\t', '\r', ' ', '>', '\t', '\r', '<', ' ', '/', '\t', '\r', '>', '>', '\'', '\'', ' ', '\t', '\r', Character.MIN_VALUE };
/*    */   
/*  7 */   public static final byte[] pG0 = new byte[] { 0, 2, 3, 3, 4, 4, 2, 3, 1, 1, 3, 2, 2, 1, 1, 2, 1, 3, 3, 4, 4, 2, 3, 1, 1, 3, 2, 2, 1, 2, 1, 1, 1, 1, 1, 0 };
/*    */   
/*  9 */   public static final byte[] b1 = new byte[] { 0, 1, 1, 1, 1, 1, 1, 1, 0, 0, 1, 1, 1, 0, 0, 1, 0, 1, 1, 1, 1, 1, 1, 0, 0, 1, 1, 1, 0, 1, 0, 0, 0, 0, 1, 0 };
/*    */   
/* 11 */   public static final short[] YX = new short[] { 0, 0, 4, 9, 14, 20, 26, 30, 35, 37, 39, 44, 48, 52, 54, 56, 60, 62, 67, 72, 78, 84, 88, 93, 95, 97, 102, 106, 110, 112, 116, 118, 120, 122, 124, 127 };
/*    */   
/* 13 */   public static final byte[] dI0 = new byte[] { 0, 2, 0, 1, 2, 1, 1, 2, 3, 5, 6, 7, 5, 4, 9, 10, 1, 11, 9, 8, 13, 1, 14, 1, 13, 12, 15, 16, 15, 1, 16, 17, 18, 16, 1, 20, 19, 22, 21, 9, 10, 11, 9, 1, 23, 24, 23, 1, 25, 11, 25, 1, 20, 26, 22, 27, 29, 30, 29, 28, 32, 31, 30, 34, 1, 30, 33, 36, 37, 38, 36, 35, 40, 41, 1, 42, 40, 39, 44, 1, 45, 1, 44, 43, 46, 47, 46, 1, 47, 48, 49, 47, 1, 51, 50, 53, 52, 40, 41, 42, 40, 1, 54, 55, 54, 1, 56, 42, 56, 1, 57, 1, 57, 34, 57, 1, 1, 58, 59, 58, 51, 60, 53, 61, 62, 62, 1, 1, 0 };
/*    */   
/* 15 */   public static final byte[] nY = new byte[] { 1, 0, 2, 3, 3, 4, 11, 34, 5, 4, 11, 34, 5, 6, 7, 6, 7, 8, 13, 9, 10, 9, 10, 12, 34, 12, 14, 14, 16, 15, 17, 16, 17, 18, 30, 18, 19, 26, 28, 20, 19, 26, 28, 20, 21, 22, 21, 22, 23, 32, 24, 25, 24, 25, 27, 28, 27, 29, 31, 35, 33, 33, 34 };
/* 16 */   public static final byte[] TK = XE();
/*    */   public final fQ z6;
/*    */   public Jp0 dD0;
/*    */   public Jp0 dQ;
/*    */   public final Ag finally;
/*    */   public String eO; }


/* Location:              /Users/vnnsnnt/Documents/Codespace/JavaWorkspace/RedTrainer/src/main/java/org/trainer/client/PokeMMO.jar!/f/d70.class
 * Java compiler version: 7 (51.0)
 * JD-Core Version:       1.1.3
 */