/*  1 */ package f;public class da extends JG0 { public static void pe0(Gq0 paramGq0, xc paramxc, GC0 paramGC0, Gj paramGj, Sx0 paramSx0) { boolean bool; if (paramGj != Gj.FC0) { bool = true; } else { bool = false; }  paramGq0.vA0(false); if ((bool || paramSx0 != Sx0.z00) && !bool) { paramGq0.wa0 = paramGq0.qr0(paramGC0.Zq); ArrayList<?> arrayList; int j;
/*  2 */       for (j = (arrayList = paramGq0.lw).size(); j-- > 0;) { if (((GC0)arrayList.get(j)).O80() <= paramGq0.wa0) arrayList.remove(j);  }
/*    */       
/*  4 */       for (j = (arrayList = paramGq0.ph).size(); j-- > 0;) { if (((GC0)arrayList.get(j)).O80() <= paramGq0.wa0) arrayList.remove(j);  }  paramGq0
/*  5 */         .f1(); }
/*  6 */      int i = paramGC0.J1; short s1 = paramGC0.dv0, s2 = paramGC0.WS; paramGq0.DF0(i, s1, s2); if (paramGC0.J1 > (i = paramGq0.yl)) paramGC0.J1 = i;  if (bool) { if (paramGj == Gj.Df) { paramGC0.Iu = paramGq0.XS(paramGC0.WS) - paramGC0.J1; paramGq0.ph.add(paramGC0); } else { paramGC0.Iu = paramGq0.LD(paramGC0.dv0); paramGq0.lw.add(paramGC0); }  } else { int j; if (paramSx0 == Sx0.z00) { if (paramGq0.zt0() < paramGC0.J1 && !paramGq0.Bz()) paramGq0.vA0(false);  j = paramGC0.J1; int k; paramGq0
/*  7 */           .c5 = (k = paramGq0.c5) + j;
/*  8 */         paramGC0.Iu = k; }
/*    */       else
/*    */       { int k;
/*    */         
/*    */         e00 e00;
/* 13 */         if ((k = ((AuX)j.X10.bw0(e00 = e00.HORIZONTAL_ALIGNMENT).rI(e00)).ordinal()) != 1) { if (k != 2 && k != 3) { paramGC0.Iu = paramGq0.LD(paramGC0.dv0); } else { k = paramGq0.Ph0; paramGC0
/*    */               
/* 15 */               .Iu = JO.Se0(paramGq0.yl, paramGC0.J1, 2, k); }  } else { paramGC0.Iu = paramGq0.XS(paramGC0.WS) - paramGC0.J1; }  }  }  paramGq0.mz.add(paramGC0); if (bool) { if (Zu || paramGq0.L30 == paramGq0.mz.size() - 1) { paramGq0.L30++; paramGC0.Bm = paramGq0.qr0(paramGC0.Zq); paramGq0.f1(); return; }  throw new AssertionError(); }  if (paramSx0 != Sx0.z00) { int j = Math.max(0, paramGq0.yl - paramGC0.J1); paramGq0
/* 16 */         .De = Math.min(paramGq0.De, j);
/* 17 */       paramGq0.vA0(false); }
/*    */      }
/*    */ 
/*    */   
/*    */   public static final Ll tf0;
/*    */   public static final char[] ap;
/*    */   public static final vc Bt;
/*    */   public final HashMap Ca = new HashMap<>();
/*    */   public final HashMap bm0 = new HashMap<>();
/*    */   public final HashMap qO = new HashMap<>();
/*    */   public final ArrayList Cc = new ArrayList();
/*    */   public final D60 Ml0 = new D60(this);
/*    */   public Zq0 COM9;
/*    */   public nW rM;
/*    */   public nW Li0;
/*    */   public pe vh0;
/*    */   public LPt7[] AU;
/*    */   public JE0 xP;
/*    */   public JE0 cE0;
/*    */   public final yB ta = new yB(null);
/*    */   public final ArrayList nG = new ArrayList();
/*    */   public final X8 iL = new X8(cOm7());
/*    */   public boolean fq;
/*    */   public boolean COM4;
/*    */   public db gk;
/*    */   public int qk0;
/*    */   public int fV;
/*    */   public boolean h1;
/*    */   public boolean Z5;
/*    */   public GC0 lw0;
/*    */   
/*    */   public da() {}
/*    */   
/*    */   public da(Zq0 paramZq0) {
/*    */     this();
/*    */     Ld(paramZq0);
/*    */   }
/*    */   
/*    */   static {
/*    */     Ll ll = Ll.F10("hover");
/*    */     ap = new char[0];
/*    */     this(ll);
/*    */     x2 x2;
/*    */     Bt = new vc(new Nm0[] { x2 });
/*    */   }
/*    */   
/*    */   public final void xb0() {
/*    */     int i = -1, j = -1;
/*    */     if (this.COM9 == null) {
/*    */       i = 0;
/*    */       j = 0;
/*    */     } else {
/*    */       int k = Ho();
/*    */       int m = Math.max(0, this.fu - k);
/*    */       if (this.fu > 0 && Math.max(0, AW() - k) < m) {
/*    */         yB yB1;
/*    */         this(null);
/*    */         throws throws;
/*    */         if ((throws = this.Bo0) != null)
/*    */           throws.IB0.getClass(); 
/*    */         try {
/*    */           yB1.J1 = m;
/*    */           this(this, yB1, 0, 0, 0, false);
/*    */           F00(gq0, this.COM9);
/*    */           Gq0 gq0;
/*    */           (gq0 = new Gq0()).b60();
/*    */           i = Math.max(0, m - gq0.De);
/*    */           j = (new Gq0()).wa0;
/*    */         } finally {}
/*    */       } 
/*    */     } 
/*    */     this(i, j);
/*    */     db db1;
/*    */     this.gk = this;
/*    */   }
/*    */   
/*    */   public final void Zq0() {
/*    */     GC0 gC0 = null;
/*    */     if (this.h1)
/*    */       gC0 = this.ta.ce0(this.qk0 - RS(), this.fV - e3()); 
/*    */     if (this.lw0 != gC0) {
/*    */       this.lw0 = gC0;
/*    */       this.ta.Q8(gC0);
/*    */       Ll ll1;
/*    */       this.iL.G7.Ym0(ll1 = tf0);
/*    */       this.iL.YH.Ym0(ll1);
/*    */       zn();
/*    */     } 
/*    */     if (gC0 != null && gC0.Gr != null) {
/*    */     
/*    */     } else {
/*    */     
/*    */     } 
/*    */     this.v10 = this.xP;
/*    */     Ll ll = tf0;
/*    */     this.O.gf0(this, this.h1);
/*    */   }
/*    */   
/*    */   public final void F00(Gq0 paramGq0, Iterable paramIterable) {
/*    */     Iterator<xc> iterator = paramIterable.iterator();
/*    */     while (iterator.hasNext())
/*    */       Sl(paramGq0, iterator.next()); 
/*    */   }
/*    */   
/*    */   public final void Sl(Gq0 paramGq0, xc paramxc) {
/*    */     // Byte code:
/*    */     //   0: aload_2
/*    */     //   1: aload_1
/*    */     //   2: aload_2
/*    */     //   3: getfield X10 : Lf/cR;
/*    */     //   6: getstatic f/e00.CLEAR : Lf/e00;
/*    */     //   9: dup
/*    */     //   10: astore_3
/*    */     //   11: invokevirtual bw0 : (Lf/e00;)Lf/cR;
/*    */     //   14: aload_3
/*    */     //   15: invokevirtual rI : (Lf/e00;)Ljava/lang/Object;
/*    */     //   18: checkcast f/UG
/*    */     //   21: invokevirtual ok : (Lf/UG;)V
/*    */     //   24: instanceof f/qn0
/*    */     //   27: ifeq -> 1661
/*    */     //   30: aload_0
/*    */     //   31: aload_2
/*    */     //   32: checkcast f/qn0
/*    */     //   35: dup
/*    */     //   36: dup
/*    */     //   37: astore_0
/*    */     //   38: getfield j5 : Ljava/lang/String;
/*    */     //   41: astore_2
/*    */     //   42: getfield X10 : Lf/cR;
/*    */     //   45: dup
/*    */     //   46: astore_3
/*    */     //   47: invokevirtual VP : (Lf/cR;)Lf/pe;
/*    */     //   50: dup
/*    */     //   51: astore #4
/*    */     //   53: ifnonnull -> 62
/*    */     //   56: aconst_null
/*    */     //   57: astore #4
/*    */     //   59: goto -> 118
/*    */     //   62: new f/q90
/*    */     //   65: dup
/*    */     //   66: astore #5
/*    */     //   68: aload #4
/*    */     //   70: aload_3
/*    */     //   71: dup
/*    */     //   72: getstatic f/e00.COLOR : Lf/e00;
/*    */     //   75: dup
/*    */     //   76: astore #4
/*    */     //   78: invokevirtual bw0 : (Lf/e00;)Lf/cR;
/*    */     //   81: aload #4
/*    */     //   83: invokevirtual rI : (Lf/e00;)Ljava/lang/Object;
/*    */     //   86: checkcast f/pRn
/*    */     //   89: astore #4
/*    */     //   91: getstatic f/e00.COLOR_HOVER : Lf/e00;
/*    */     //   94: dup
/*    */     //   95: astore #6
/*    */     //   97: invokevirtual bw0 : (Lf/e00;)Lf/cR;
/*    */     //   100: aload #6
/*    */     //   102: invokevirtual rI : (Lf/e00;)Ljava/lang/Object;
/*    */     //   105: checkcast f/pRn
/*    */     //   108: aload #4
/*    */     //   110: swap
/*    */     //   111: invokespecial <init> : (Lf/pe;Lf/pRn;Lf/pRn;)V
/*    */     //   114: aload #5
/*    */     //   116: astore #4
/*    */     //   118: aload #4
/*    */     //   120: aload_3
/*    */     //   121: getstatic f/e00.PREFORMATTED : Lf/e00;
/*    */     //   124: dup
/*    */     //   125: astore #5
/*    */     //   127: invokevirtual bw0 : (Lf/e00;)Lf/cR;
/*    */     //   130: aload #5
/*    */     //   132: invokevirtual rI : (Lf/e00;)Ljava/lang/Object;
/*    */     //   135: checkcast java/lang/Boolean
/*    */     //   138: invokevirtual booleanValue : ()Z
/*    */     //   141: istore #5
/*    */     //   143: ifnonnull -> 149
/*    */     //   146: goto -> 5191
/*    */     //   149: aload_3
/*    */     //   150: getstatic f/e00.INHERIT_HOVER : Lf/e00;
/*    */     //   153: dup
/*    */     //   154: astore #6
/*    */     //   156: invokevirtual bw0 : (Lf/e00;)Lf/cR;
/*    */     //   159: aload #6
/*    */     //   161: getfield x10 : I
/*    */     //   164: istore #7
/*    */     //   166: getfield LPt1 : [Ljava/lang/Object;
/*    */     //   169: dup
/*    */     //   170: astore #8
/*    */     //   172: ifnull -> 185
/*    */     //   175: aload #8
/*    */     //   177: iload #7
/*    */     //   179: aaload
/*    */     //   180: astore #7
/*    */     //   182: goto -> 188
/*    */     //   185: aconst_null
/*    */     //   186: astore #7
/*    */     //   188: aload #6
/*    */     //   190: getfield Tw0 : Ljava/lang/Class;
/*    */     //   193: aload #7
/*    */     //   195: invokevirtual cast : (Ljava/lang/Object;)Ljava/lang/Object;
/*    */     //   198: checkcast java/lang/Boolean
/*    */     //   201: dup
/*    */     //   202: astore #6
/*    */     //   204: ifnull -> 217
/*    */     //   207: aload #6
/*    */     //   209: invokevirtual booleanValue : ()Z
/*    */     //   212: istore #6
/*    */     //   214: goto -> 245
/*    */     //   217: aload_1
/*    */     //   218: getfield az : Lf/cR;
/*    */     //   221: dup
/*    */     //   222: astore #6
/*    */     //   224: ifnull -> 242
/*    */     //   227: aload #6
/*    */     //   229: aload_3
/*    */     //   230: getfield g8 : Lf/cR;
/*    */     //   233: if_acmpne -> 242
/*    */     //   236: iconst_1
/*    */     //   237: istore #6
/*    */     //   239: goto -> 245
/*    */     //   242: iconst_0
/*    */     //   243: istore #6
/*    */     //   245: iload #5
/*    */     //   247: aload_1
/*    */     //   248: aload #4
/*    */     //   250: getfield eI : Lf/pe;
/*    */     //   253: aload_3
/*    */     //   254: swap
/*    */     //   255: iconst_0
/*    */     //   256: invokevirtual PB0 : (Lf/cR;Lf/pe;Z)V
/*    */     //   259: ifeq -> 275
/*    */     //   262: aload_1
/*    */     //   263: getfield V4 : Z
/*    */     //   266: ifne -> 275
/*    */     //   269: aload_1
/*    */     //   270: iconst_0
/*    */     //   271: invokevirtual vA0 : (Z)Z
/*    */     //   274: pop
/*    */     //   275: iload #5
/*    */     //   277: ifeq -> 715
/*    */     //   280: iconst_0
/*    */     //   281: istore_3
/*    */     //   282: iload_3
/*    */     //   283: aload_2
/*    */     //   284: invokevirtual length : ()I
/*    */     //   287: if_icmpge -> 1652
/*    */     //   290: aload_2
/*    */     //   291: bipush #10
/*    */     //   293: iload_3
/*    */     //   294: invokevirtual indexOf : (II)I
/*    */     //   297: dup
/*    */     //   298: istore #7
/*    */     //   300: ifge -> 309
/*    */     //   303: aload_2
/*    */     //   304: invokevirtual length : ()I
/*    */     //   307: istore #7
/*    */     //   309: aload #4
/*    */     //   311: getfield eI : Lf/pe;
/*    */     //   314: astore #8
/*    */     //   316: iload_3
/*    */     //   317: iload #7
/*    */     //   319: if_icmpge -> 660
/*    */     //   322: aload_2
/*    */     //   323: iload_3
/*    */     //   324: invokevirtual charAt : (I)C
/*    */     //   327: bipush #9
/*    */     //   329: if_icmpne -> 493
/*    */     //   332: aload_0
/*    */     //   333: iinc #3, 1
/*    */     //   336: getfield X10 : Lf/cR;
/*    */     //   339: aload #8
/*    */     //   341: checkcast f/t90
/*    */     //   344: dup
/*    */     //   345: astore #9
/*    */     //   347: invokevirtual getEM : ()I
/*    */     //   350: istore #10
/*    */     //   352: getstatic f/e00.TAB_SIZE : Lf/e00;
/*    */     //   355: dup
/*    */     //   356: astore #11
/*    */     //   358: aload_1
/*    */     //   359: getfield pH0 : Lf/da;
/*    */     //   362: invokevirtual getClass : ()Ljava/lang/Class;
/*    */     //   365: pop
/*    */     //   366: invokevirtual bw0 : (Lf/e00;)Lf/cR;
/*    */     //   369: aload #11
/*    */     //   371: invokevirtual rI : (Lf/e00;)Ljava/lang/Object;
/*    */     //   374: checkcast java/lang/Integer
/*    */     //   377: invokevirtual intValue : ()I
/*    */     //   380: dup
/*    */     //   381: istore #11
/*    */     //   383: ifle -> 449
/*    */     //   386: iload #10
/*    */     //   388: ifgt -> 394
/*    */     //   391: goto -> 449
/*    */     //   394: aload_1
/*    */     //   395: aload #9
/*    */     //   397: aload_1
/*    */     //   398: iload #11
/*    */     //   400: sipush #32767
/*    */     //   403: iload #10
/*    */     //   405: idiv
/*    */     //   406: invokestatic min : (II)I
/*    */     //   409: iload #10
/*    */     //   411: imul
/*    */     //   412: istore #9
/*    */     //   414: getfield c5 : I
/*    */     //   417: aload_1
/*    */     //   418: getfield Ph0 : I
/*    */     //   421: isub
/*    */     //   422: istore #10
/*    */     //   424: invokevirtual getSpaceWidth : ()I
/*    */     //   427: iload #10
/*    */     //   429: iadd
/*    */     //   430: istore #10
/*    */     //   432: getfield c5 : I
/*    */     //   435: iload #9
/*    */     //   437: iadd
/*    */     //   438: iload #10
/*    */     //   440: iload #9
/*    */     //   442: irem
/*    */     //   443: isub
/*    */     //   444: istore #9
/*    */     //   446: goto -> 465
/*    */     //   449: aload #9
/*    */     //   451: aload_1
/*    */     //   452: getfield c5 : I
/*    */     //   455: istore #9
/*    */     //   457: invokevirtual getSpaceWidth : ()I
/*    */     //   460: iload #9
/*    */     //   462: iadd
/*    */     //   463: istore #9
/*    */     //   465: iload #9
/*    */     //   467: aload_1
/*    */     //   468: getfield yl : I
/*    */     //   471: if_icmpge -> 483
/*    */     //   474: aload_1
/*    */     //   475: iload #9
/*    */     //   477: putfield c5 : I
/*    */     //   480: goto -> 493
/*    */     //   483: aload_1
/*    */     //   484: invokevirtual Bz : ()Z
/*    */     //   487: ifne -> 493
/*    */     //   490: goto -> 660
/*    */     //   493: aload_2
/*    */     //   494: bipush #9
/*    */     //   496: iload_3
/*    */     //   497: invokevirtual indexOf : (II)I
/*    */     //   500: dup
/*    */     //   501: istore #9
/*    */     //   503: iflt -> 516
/*    */     //   506: iload #9
/*    */     //   508: iload #7
/*    */     //   510: if_icmpge -> 516
/*    */     //   513: goto -> 520
/*    */     //   516: iload #7
/*    */     //   518: istore #9
/*    */     //   520: iload #9
/*    */     //   522: iload_3
/*    */     //   523: if_icmple -> 654
/*    */     //   526: aload #8
/*    */     //   528: aload_1
/*    */     //   529: invokevirtual zt0 : ()I
/*    */     //   532: istore #10
/*    */     //   534: checkcast f/t90
/*    */     //   537: aload_2
/*    */     //   538: iload_3
/*    */     //   539: iload #9
/*    */     //   541: iload #10
/*    */     //   543: invokevirtual computeVisibleGlpyhs : (Ljava/lang/CharSequence;III)I
/*    */     //   546: dup
/*    */     //   547: istore #9
/*    */     //   549: ifne -> 562
/*    */     //   552: aload_1
/*    */     //   553: invokevirtual Bz : ()Z
/*    */     //   556: ifne -> 562
/*    */     //   559: goto -> 660
/*    */     //   562: aload_1
/*    */     //   563: iconst_1
/*    */     //   564: iload #9
/*    */     //   566: invokestatic max : (II)I
/*    */     //   569: iload_3
/*    */     //   570: iadd
/*    */     //   571: istore #9
/*    */     //   573: new f/rl0
/*    */     //   576: dup
/*    */     //   577: astore #10
/*    */     //   579: iload #6
/*    */     //   581: aload #10
/*    */     //   583: aload_1
/*    */     //   584: aload #10
/*    */     //   586: aload_1
/*    */     //   587: dup
/*    */     //   588: aload #10
/*    */     //   590: dup
/*    */     //   591: aload_0
/*    */     //   592: aload_1
/*    */     //   593: getfield Jo : Z
/*    */     //   596: istore #11
/*    */     //   598: aload #4
/*    */     //   600: aload_2
/*    */     //   601: iload_3
/*    */     //   602: iload #9
/*    */     //   604: iload #11
/*    */     //   606: invokespecial <init> : (Lf/xc;Lf/q90;Ljava/lang/String;IIZ)V
/*    */     //   609: getfield J1 : I
/*    */     //   612: istore_3
/*    */     //   613: getfield c5 : I
/*    */     //   616: dup
/*    */     //   617: istore #11
/*    */     //   619: iload_3
/*    */     //   620: iadd
/*    */     //   621: putfield c5 : I
/*    */     //   624: iload #11
/*    */     //   626: putfield Iu : I
/*    */     //   629: getfield En : I
/*    */     //   632: i2s
/*    */     //   633: putfield Zq : S
/*    */     //   636: putfield Jz0 : Z
/*    */     //   639: getfield mz : Ljava/util/ArrayList;
/*    */     //   642: aload #10
/*    */     //   644: invokevirtual add : (Ljava/lang/Object;)Z
/*    */     //   647: pop
/*    */     //   648: iload #9
/*    */     //   650: istore_3
/*    */     //   651: goto -> 316
/*    */     //   654: iload #9
/*    */     //   656: istore_3
/*    */     //   657: goto -> 316
/*    */     //   660: iload_3
/*    */     //   661: iload #7
/*    */     //   663: if_icmplt -> 706
/*    */     //   666: iload #7
/*    */     //   668: aload_2
/*    */     //   669: invokevirtual length : ()I
/*    */     //   672: if_icmpge -> 700
/*    */     //   675: aload_2
/*    */     //   676: iload #7
/*    */     //   678: invokevirtual charAt : (I)C
/*    */     //   681: bipush #10
/*    */     //   683: if_icmpne -> 700
/*    */     //   686: aload_1
/*    */     //   687: iload #7
/*    */     //   689: iconst_1
/*    */     //   690: iadd
/*    */     //   691: istore_3
/*    */     //   692: iconst_1
/*    */     //   693: invokevirtual vA0 : (Z)Z
/*    */     //   696: pop
/*    */     //   697: goto -> 282
/*    */     //   700: iload #7
/*    */     //   702: istore_3
/*    */     //   703: goto -> 282
/*    */     //   706: aload_1
/*    */     //   707: iconst_0
/*    */     //   708: invokevirtual vA0 : (Z)Z
/*    */     //   711: pop
/*    */     //   712: goto -> 316
/*    */     //   715: aload_2
/*    */     //   716: iconst_0
/*    */     //   717: istore_3
/*    */     //   718: invokevirtual length : ()I
/*    */     //   721: istore #7
/*    */     //   723: iload_3
/*    */     //   724: iload #7
/*    */     //   726: if_icmpge -> 746
/*    */     //   729: aload_2
/*    */     //   730: iload_3
/*    */     //   731: invokevirtual charAt : (I)C
/*    */     //   734: invokestatic isWhitespace : (C)Z
/*    */     //   737: ifeq -> 746
/*    */     //   740: iinc #3, 1
/*    */     //   743: goto -> 723
/*    */     //   746: iconst_0
/*    */     //   747: istore #8
/*    */     //   749: iload #7
/*    */     //   751: iload_3
/*    */     //   752: if_icmple -> 778
/*    */     //   755: aload_2
/*    */     //   756: iload #7
/*    */     //   758: iconst_1
/*    */     //   759: isub
/*    */     //   760: invokevirtual charAt : (I)C
/*    */     //   763: invokestatic isWhitespace : (C)Z
/*    */     //   766: ifeq -> 778
/*    */     //   769: iconst_1
/*    */     //   770: istore #8
/*    */     //   772: iinc #7, -1
/*    */     //   775: goto -> 749
/*    */     //   778: iload_3
/*    */     //   779: aload #4
/*    */     //   781: getfield eI : Lf/pe;
/*    */     //   784: astore #9
/*    */     //   786: ifle -> 888
/*    */     //   789: aload_1
/*    */     //   790: dup
/*    */     //   791: getfield mz : Ljava/util/ArrayList;
/*    */     //   794: invokevirtual size : ()I
/*    */     //   797: istore #10
/*    */     //   799: getfield L30 : I
/*    */     //   802: iload #10
/*    */     //   804: if_icmpge -> 863
/*    */     //   807: aload_1
/*    */     //   808: getfield mz : Ljava/util/ArrayList;
/*    */     //   811: iload #10
/*    */     //   813: iconst_1
/*    */     //   814: isub
/*    */     //   815: invokevirtual get : (I)Ljava/lang/Object;
/*    */     //   818: checkcast f/GC0
/*    */     //   821: dup
/*    */     //   822: astore #10
/*    */     //   824: instanceof f/rl0
/*    */     //   827: ifeq -> 859
/*    */     //   830: aload #10
/*    */     //   832: checkcast f/rl0
/*    */     //   835: dup
/*    */     //   836: astore #10
/*    */     //   838: getfield gb : Ljava/lang/String;
/*    */     //   841: aload #10
/*    */     //   843: getfield hk0 : I
/*    */     //   846: iconst_1
/*    */     //   847: isub
/*    */     //   848: invokevirtual charAt : (I)C
/*    */     //   851: invokestatic isWhitespace : (C)Z
/*    */     //   854: iconst_1
/*    */     //   855: ixor
/*    */     //   856: goto -> 864
/*    */     //   859: iconst_1
/*    */     //   860: goto -> 864
/*    */     //   863: iconst_0
/*    */     //   864: ifeq -> 888
/*    */     //   867: aload_1
/*    */     //   868: aload #9
/*    */     //   870: aload_1
/*    */     //   871: getfield c5 : I
/*    */     //   874: istore #10
/*    */     //   876: checkcast f/t90
/*    */     //   879: invokevirtual getSpaceWidth : ()I
/*    */     //   882: iload #10
/*    */     //   884: iadd
/*    */     //   885: putfield c5 : I
/*    */     //   888: aconst_null
/*    */     //   889: astore #10
/*    */     //   891: iload_3
/*    */     //   892: iload #7
/*    */     //   894: if_icmpge -> 1621
/*    */     //   897: getstatic f/da.Zu : Z
/*    */     //   900: ifne -> 925
/*    */     //   903: aload_2
/*    */     //   904: iload_3
/*    */     //   905: invokevirtual charAt : (I)C
/*    */     //   908: invokestatic isWhitespace : (C)Z
/*    */     //   911: ifne -> 917
/*    */     //   914: goto -> 925
/*    */     //   917: new java/lang/AssertionError
/*    */     //   920: dup
/*    */     //   921: invokespecial <init> : ()V
/*    */     //   924: athrow
/*    */     //   925: aload_1
/*    */     //   926: getfield kI0 : Lf/AuX;
/*    */     //   929: getstatic f/AuX.Ce0 : Lf/AuX;
/*    */     //   932: if_acmpeq -> 1189
/*    */     //   935: aload #9
/*    */     //   937: aload_1
/*    */     //   938: invokevirtual zt0 : ()I
/*    */     //   941: istore #11
/*    */     //   943: checkcast f/t90
/*    */     //   946: aload_2
/*    */     //   947: iload_3
/*    */     //   948: iload #7
/*    */     //   950: iload #11
/*    */     //   952: invokevirtual computeVisibleGlpyhs : (Ljava/lang/CharSequence;III)I
/*    */     //   955: iload_3
/*    */     //   956: iadd
/*    */     //   957: dup
/*    */     //   958: istore #11
/*    */     //   960: iload #7
/*    */     //   962: if_icmpge -> 1159
/*    */     //   965: iload #11
/*    */     //   967: istore #12
/*    */     //   969: iload #12
/*    */     //   971: iload_3
/*    */     //   972: if_icmple -> 1011
/*    */     //   975: aload_2
/*    */     //   976: iload #12
/*    */     //   978: invokevirtual charAt : (I)C
/*    */     //   981: ldc_w ':;,.-!?'
/*    */     //   984: swap
/*    */     //   985: invokevirtual indexOf : (I)I
/*    */     //   988: iflt -> 997
/*    */     //   991: iconst_1
/*    */     //   992: istore #13
/*    */     //   994: goto -> 1000
/*    */     //   997: iconst_0
/*    */     //   998: istore #13
/*    */     //   1000: iload #13
/*    */     //   1002: ifeq -> 1011
/*    */     //   1005: iinc #12, -1
/*    */     //   1008: goto -> 969
/*    */     //   1011: aload_2
/*    */     //   1012: iload #12
/*    */     //   1014: invokevirtual charAt : (I)C
/*    */     //   1017: dup
/*    */     //   1018: istore #13
/*    */     //   1020: invokestatic isWhitespace : (C)Z
/*    */     //   1023: ifne -> 1070
/*    */     //   1026: ldc_w ':;,.-!?'
/*    */     //   1029: iload #13
/*    */     //   1031: invokevirtual indexOf : (I)I
/*    */     //   1034: iflt -> 1041
/*    */     //   1037: iconst_1
/*    */     //   1038: goto -> 1042
/*    */     //   1041: iconst_0
/*    */     //   1042: ifne -> 1070
/*    */     //   1045: iload #13
/*    */     //   1047: sipush #12289
/*    */     //   1050: if_icmpeq -> 1070
/*    */     //   1053: iload #13
/*    */     //   1055: sipush #12290
/*    */     //   1058: if_icmpne -> 1064
/*    */     //   1061: goto -> 1070
/*    */     //   1064: iconst_0
/*    */     //   1065: istore #13
/*    */     //   1067: goto -> 1073
/*    */     //   1070: iconst_1
/*    */     //   1071: istore #13
/*    */     //   1073: iload #13
/*    */     //   1075: ifne -> 1163
/*    */     //   1078: iload #12
/*    */     //   1080: iload_3
/*    */     //   1081: if_icmple -> 1163
/*    */     //   1084: aload_2
/*    */     //   1085: iload #12
/*    */     //   1087: iconst_1
/*    */     //   1088: isub
/*    */     //   1089: invokevirtual charAt : (I)C
/*    */     //   1092: dup
/*    */     //   1093: istore #13
/*    */     //   1095: invokestatic isWhitespace : (C)Z
/*    */     //   1098: ifne -> 1145
/*    */     //   1101: ldc_w ':;,.-!?'
/*    */     //   1104: iload #13
/*    */     //   1106: invokevirtual indexOf : (I)I
/*    */     //   1109: iflt -> 1116
/*    */     //   1112: iconst_1
/*    */     //   1113: goto -> 1117
/*    */     //   1116: iconst_0
/*    */     //   1117: ifne -> 1145
/*    */     //   1120: iload #13
/*    */     //   1122: sipush #12289
/*    */     //   1125: if_icmpeq -> 1145
/*    */     //   1128: iload #13
/*    */     //   1130: sipush #12290
/*    */     //   1133: if_icmpne -> 1139
/*    */     //   1136: goto -> 1145
/*    */     //   1139: iconst_0
/*    */     //   1140: istore #13
/*    */     //   1142: goto -> 1148
/*    */     //   1145: iconst_1
/*    */     //   1146: istore #13
/*    */     //   1148: iload #13
/*    */     //   1150: ifne -> 1163
/*    */     //   1153: iinc #12, -1
/*    */     //   1156: goto -> 1078
/*    */     //   1159: iload #11
/*    */     //   1161: istore #12
/*    */     //   1163: iload #12
/*    */     //   1165: iload_3
/*    */     //   1166: if_icmple -> 1195
/*    */     //   1169: aload_2
/*    */     //   1170: iload #12
/*    */     //   1172: iconst_1
/*    */     //   1173: isub
/*    */     //   1174: invokevirtual charAt : (I)C
/*    */     //   1177: invokestatic isWhitespace : (C)Z
/*    */     //   1180: ifeq -> 1195
/*    */     //   1183: iinc #12, -1
/*    */     //   1186: goto -> 1163
/*    */     //   1189: iload_3
/*    */     //   1190: iload_3
/*    */     //   1191: istore #11
/*    */     //   1193: istore #12
/*    */     //   1195: iload #12
/*    */     //   1197: iconst_0
/*    */     //   1198: istore #13
/*    */     //   1200: iload_3
/*    */     //   1201: if_icmpne -> 1413
/*    */     //   1204: aload_1
/*    */     //   1205: getfield kI0 : Lf/AuX;
/*    */     //   1208: getstatic f/AuX.Ce0 : Lf/AuX;
/*    */     //   1211: if_acmpeq -> 1225
/*    */     //   1214: aload_1
/*    */     //   1215: iconst_0
/*    */     //   1216: invokevirtual vA0 : (Z)Z
/*    */     //   1219: ifeq -> 1225
/*    */     //   1222: goto -> 891
/*    */     //   1225: aload #10
/*    */     //   1227: ifnonnull -> 1253
/*    */     //   1230: aload_0
/*    */     //   1231: getfield X10 : Lf/cR;
/*    */     //   1234: getstatic f/e00.BREAKWORD : Lf/e00;
/*    */     //   1237: dup
/*    */     //   1238: astore #10
/*    */     //   1240: invokevirtual bw0 : (Lf/e00;)Lf/cR;
/*    */     //   1243: aload #10
/*    */     //   1245: invokevirtual rI : (Lf/e00;)Ljava/lang/Object;
/*    */     //   1248: checkcast java/lang/Boolean
/*    */     //   1251: astore #10
/*    */     //   1253: aload #10
/*    */     //   1255: invokevirtual booleanValue : ()Z
/*    */     //   1258: ifeq -> 1279
/*    */     //   1261: iload #11
/*    */     //   1263: iload_3
/*    */     //   1264: if_icmpne -> 1406
/*    */     //   1267: iload_3
/*    */     //   1268: iconst_1
/*    */     //   1269: iadd
/*    */     //   1270: istore #11
/*    */     //   1272: iload #11
/*    */     //   1274: istore #12
/*    */     //   1276: goto -> 1410
/*    */     //   1279: iload #12
/*    */     //   1281: iload #7
/*    */     //   1283: if_icmpge -> 1359
/*    */     //   1286: aload_2
/*    */     //   1287: iload #12
/*    */     //   1289: invokevirtual charAt : (I)C
/*    */     //   1292: dup
/*    */     //   1293: istore #11
/*    */     //   1295: invokestatic isWhitespace : (C)Z
/*    */     //   1298: ifne -> 1345
/*    */     //   1301: ldc_w ':;,.-!?'
/*    */     //   1304: iload #11
/*    */     //   1306: invokevirtual indexOf : (I)I
/*    */     //   1309: iflt -> 1316
/*    */     //   1312: iconst_1
/*    */     //   1313: goto -> 1317
/*    */     //   1316: iconst_0
/*    */     //   1317: ifne -> 1345
/*    */     //   1320: iload #11
/*    */     //   1322: sipush #12289
/*    */     //   1325: if_icmpeq -> 1345
/*    */     //   1328: iload #11
/*    */     //   1330: sipush #12290
/*    */     //   1333: if_icmpne -> 1339
/*    */     //   1336: goto -> 1345
/*    */     //   1339: iconst_0
/*    */     //   1340: istore #11
/*    */     //   1342: goto -> 1348
/*    */     //   1345: iconst_1
/*    */     //   1346: istore #11
/*    */     //   1348: iload #11
/*    */     //   1350: ifne -> 1359
/*    */     //   1353: iinc #12, 1
/*    */     //   1356: goto -> 1279
/*    */     //   1359: iload #12
/*    */     //   1361: istore #11
/*    */     //   1363: iload #11
/*    */     //   1365: iload #7
/*    */     //   1367: if_icmpge -> 1406
/*    */     //   1370: aload_2
/*    */     //   1371: iload #11
/*    */     //   1373: invokevirtual charAt : (I)C
/*    */     //   1376: ldc_w ':;,.-!?'
/*    */     //   1379: swap
/*    */     //   1380: invokevirtual indexOf : (I)I
/*    */     //   1383: iflt -> 1392
/*    */     //   1386: iconst_1
/*    */     //   1387: istore #12
/*    */     //   1389: goto -> 1395
/*    */     //   1392: iconst_0
/*    */     //   1393: istore #12
/*    */     //   1395: iload #12
/*    */     //   1397: ifeq -> 1406
/*    */     //   1400: iinc #11, 1
/*    */     //   1403: goto -> 1363
/*    */     //   1406: iload #11
/*    */     //   1408: istore #12
/*    */     //   1410: iconst_1
/*    */     //   1411: istore #13
/*    */     //   1413: iload_3
/*    */     //   1414: iload #12
/*    */     //   1416: if_icmpge -> 1595
/*    */     //   1419: iload #13
/*    */     //   1421: new f/rl0
/*    */     //   1424: dup
/*    */     //   1425: astore #11
/*    */     //   1427: aload_1
/*    */     //   1428: getfield Jo : Z
/*    */     //   1431: istore #13
/*    */     //   1433: aload_0
/*    */     //   1434: aload #4
/*    */     //   1436: aload_2
/*    */     //   1437: iload_3
/*    */     //   1438: iload #12
/*    */     //   1440: iload #13
/*    */     //   1442: invokespecial <init> : (Lf/xc;Lf/q90;Ljava/lang/String;IIZ)V
/*    */     //   1445: ifeq -> 1475
/*    */     //   1448: aload_1
/*    */     //   1449: dup
/*    */     //   1450: dup
/*    */     //   1451: aload #11
/*    */     //   1453: getfield J1 : I
/*    */     //   1456: istore_3
/*    */     //   1457: getfield Ji0 : I
/*    */     //   1460: istore #13
/*    */     //   1462: getfield D20 : I
/*    */     //   1465: istore #14
/*    */     //   1467: iload_3
/*    */     //   1468: iload #13
/*    */     //   1470: iload #14
/*    */     //   1472: invokevirtual DF0 : (III)V
/*    */     //   1475: aload_1
/*    */     //   1476: getfield kI0 : Lf/AuX;
/*    */     //   1479: getstatic f/AuX.Ce0 : Lf/AuX;
/*    */     //   1482: if_acmpne -> 1503
/*    */     //   1485: aload_1
/*    */     //   1486: invokevirtual zt0 : ()I
/*    */     //   1489: aload #11
/*    */     //   1491: getfield J1 : I
/*    */     //   1494: if_icmpge -> 1503
/*    */     //   1497: aload_1
/*    */     //   1498: iconst_0
/*    */     //   1499: invokevirtual vA0 : (Z)Z
/*    */     //   1502: pop
/*    */     //   1503: iload #12
/*    */     //   1505: aload #11
/*    */     //   1507: getfield J1 : I
/*    */     //   1510: istore_3
/*    */     //   1511: iload #7
/*    */     //   1513: if_icmpge -> 1539
/*    */     //   1516: aload_2
/*    */     //   1517: iload #12
/*    */     //   1519: invokevirtual charAt : (I)C
/*    */     //   1522: invokestatic isWhitespace : (C)Z
/*    */     //   1525: ifeq -> 1539
/*    */     //   1528: aload #9
/*    */     //   1530: checkcast f/t90
/*    */     //   1533: invokevirtual getSpaceWidth : ()I
/*    */     //   1536: iload_3
/*    */     //   1537: iadd
/*    */     //   1538: istore_3
/*    */     //   1539: aload_1
/*    */     //   1540: aload #11
/*    */     //   1542: iload #6
/*    */     //   1544: aload #11
/*    */     //   1546: aload_1
/*    */     //   1547: aload #11
/*    */     //   1549: aload_1
/*    */     //   1550: aload #11
/*    */     //   1552: aload_1
/*    */     //   1553: dup
/*    */     //   1554: getfield c5 : I
/*    */     //   1557: dup
/*    */     //   1558: istore #13
/*    */     //   1560: iload_3
/*    */     //   1561: iadd
/*    */     //   1562: putfield c5 : I
/*    */     //   1565: iload #13
/*    */     //   1567: putfield Iu : I
/*    */     //   1570: getfield En : I
/*    */     //   1573: i2s
/*    */     //   1574: putfield Zq : S
/*    */     //   1577: getfield rv0 : Ljava/lang/String;
/*    */     //   1580: putfield Gr : Ljava/lang/String;
/*    */     //   1583: putfield Jz0 : Z
/*    */     //   1586: getfield mz : Ljava/util/ArrayList;
/*    */     //   1589: aload #11
/*    */     //   1591: invokevirtual add : (Ljava/lang/Object;)Z
/*    */     //   1594: pop
/*    */     //   1595: iload #12
/*    */     //   1597: istore_3
/*    */     //   1598: iload_3
/*    */     //   1599: iload #7
/*    */     //   1601: if_icmpge -> 891
/*    */     //   1604: aload_2
/*    */     //   1605: iload_3
/*    */     //   1606: invokevirtual charAt : (I)C
/*    */     //   1609: invokestatic isWhitespace : (C)Z
/*    */     //   1612: ifeq -> 891
/*    */     //   1615: iinc #3, 1
/*    */     //   1618: goto -> 1598
/*    */     //   1621: aload_1
/*    */     //   1622: invokevirtual Bz : ()Z
/*    */     //   1625: ifne -> 1652
/*    */     //   1628: iload #8
/*    */     //   1630: ifeq -> 1652
/*    */     //   1633: aload_1
/*    */     //   1634: aload #9
/*    */     //   1636: aload_1
/*    */     //   1637: getfield c5 : I
/*    */     //   1640: istore_0
/*    */     //   1641: checkcast f/t90
/*    */     //   1644: invokevirtual getSpaceWidth : ()I
/*    */     //   1647: iload_0
/*    */     //   1648: iadd
/*    */     //   1649: putfield c5 : I
/*    */     //   1652: aload_1
/*    */     //   1653: iload #5
/*    */     //   1655: putfield V4 : Z
/*    */     //   1658: goto -> 5191
/*    */     //   1661: aload_2
/*    */     //   1662: instanceof f/XA0
/*    */     //   1665: ifeq -> 1677
/*    */     //   1668: aload_1
/*    */     //   1669: iconst_1
/*    */     //   1670: invokevirtual vA0 : (Z)Z
/*    */     //   1673: pop
/*    */     //   1674: goto -> 5191
/*    */     //   1677: aload_1
/*    */     //   1678: getfield V4 : Z
/*    */     //   1681: ifeq -> 1695
/*    */     //   1684: aload_1
/*    */     //   1685: dup
/*    */     //   1686: iconst_0
/*    */     //   1687: invokevirtual vA0 : (Z)Z
/*    */     //   1690: pop
/*    */     //   1691: iconst_0
/*    */     //   1692: putfield V4 : Z
/*    */     //   1695: aload_2
/*    */     //   1696: instanceof f/ft
/*    */     //   1699: ifeq -> 1798
/*    */     //   1702: aload_1
/*    */     //   1703: aload_0
/*    */     //   1704: aload_1
/*    */     //   1705: dup
/*    */     //   1706: dup
/*    */     //   1707: aload_0
/*    */     //   1708: aload_1
/*    */     //   1709: aload_0
/*    */     //   1710: aload_2
/*    */     //   1711: checkcast f/ft
/*    */     //   1714: dup
/*    */     //   1715: astore_2
/*    */     //   1716: getfield X10 : Lf/cR;
/*    */     //   1719: dup
/*    */     //   1720: astore_3
/*    */     //   1721: invokevirtual VP : (Lf/cR;)Lf/pe;
/*    */     //   1724: astore #4
/*    */     //   1726: aload_3
/*    */     //   1727: invokevirtual oA : (Lf/Gq0;Lf/cR;)V
/*    */     //   1730: aload_2
/*    */     //   1731: invokevirtual Um : (Lf/xc;)Lf/GC0;
/*    */     //   1734: astore #5
/*    */     //   1736: aload_3
/*    */     //   1737: aload #4
/*    */     //   1739: iconst_1
/*    */     //   1740: invokevirtual PB0 : (Lf/cR;Lf/pe;Z)V
/*    */     //   1743: aload_2
/*    */     //   1744: invokevirtual F00 : (Lf/Gq0;Ljava/lang/Iterable;)V
/*    */     //   1747: getfield kI0 : Lf/AuX;
/*    */     //   1750: getstatic f/AuX.Ce0 : Lf/AuX;
/*    */     //   1753: if_acmpne -> 1763
/*    */     //   1756: aload_1
/*    */     //   1757: getstatic f/AuX.XT : Lf/AuX;
/*    */     //   1760: putfield kI0 : Lf/AuX;
/*    */     //   1763: aload_0
/*    */     //   1764: aload_1
/*    */     //   1765: aload #5
/*    */     //   1767: aload_1
/*    */     //   1768: dup
/*    */     //   1769: dup
/*    */     //   1770: iconst_0
/*    */     //   1771: invokevirtual vA0 : (Z)Z
/*    */     //   1774: pop
/*    */     //   1775: iconst_0
/*    */     //   1776: putfield cL0 : Z
/*    */     //   1779: getfield wa0 : I
/*    */     //   1782: aload #5
/*    */     //   1784: getfield Bm : I
/*    */     //   1787: isub
/*    */     //   1788: putfield tq0 : I
/*    */     //   1791: aload_3
/*    */     //   1792: invokevirtual GG0 : (Lf/Gq0;Lf/cR;)V
/*    */     //   1795: goto -> 5191
/*    */     //   1798: aload_2
/*    */     //   1799: instanceof f/Cp
/*    */     //   1802: ifeq -> 1854
/*    */     //   1805: aload_0
/*    */     //   1806: aload_2
/*    */     //   1807: checkcast f/Cp
/*    */     //   1810: dup
/*    */     //   1811: astore_2
/*    */     //   1812: getfield mR : Ljava/lang/String;
/*    */     //   1815: invokevirtual qC0 : (Ljava/lang/String;)Lf/mX;
/*    */     //   1818: dup
/*    */     //   1819: astore_3
/*    */     //   1820: ifnonnull -> 1826
/*    */     //   1823: goto -> 5191
/*    */     //   1826: aload_0
/*    */     //   1827: aload_1
/*    */     //   1828: new f/m10
/*    */     //   1831: dup
/*    */     //   1832: astore_0
/*    */     //   1833: aload_1
/*    */     //   1834: aload_0
/*    */     //   1835: aload_2
/*    */     //   1836: aload_3
/*    */     //   1837: invokespecial <init> : (Lf/xc;Lf/mX;)V
/*    */     //   1840: getfield rv0 : Ljava/lang/String;
/*    */     //   1843: putfield Gr : Ljava/lang/String;
/*    */     //   1846: aload_2
/*    */     //   1847: aload_0
/*    */     //   1848: invokevirtual Gv0 : (Lf/Gq0;Lf/xc;Lf/GC0;)V
/*    */     //   1851: goto -> 5191
/*    */     //   1854: aload_2
/*    */     //   1855: instanceof f/ga
/*    */     //   1858: ifeq -> 1997
/*    */     //   1861: aload_0
/*    */     //   1862: aload_2
/*    */     //   1863: checkcast f/ga
/*    */     //   1866: astore_2
/*    */     //   1867: getfield Ca : Ljava/util/HashMap;
/*    */     //   1870: aload_2
/*    */     //   1871: getfield Ap : Ljava/lang/String;
/*    */     //   1874: invokevirtual get : (Ljava/lang/Object;)Ljava/lang/Object;
/*    */     //   1877: checkcast f/JG0
/*    */     //   1880: dup
/*    */     //   1881: astore_3
/*    */     //   1882: ifnonnull -> 1920
/*    */     //   1885: aload_0
/*    */     //   1886: getfield bm0 : Ljava/util/HashMap;
/*    */     //   1889: aload_2
/*    */     //   1890: getfield Ap : Ljava/lang/String;
/*    */     //   1893: invokevirtual get : (Ljava/lang/Object;)Ljava/lang/Object;
/*    */     //   1896: checkcast f/H20
/*    */     //   1899: dup
/*    */     //   1900: astore #4
/*    */     //   1902: ifnull -> 1913
/*    */     //   1905: aload #4
/*    */     //   1907: invokeinterface try : ()Lf/JG0;
/*    */     //   1912: astore_3
/*    */     //   1913: aload_3
/*    */     //   1914: ifnonnull -> 1920
/*    */     //   1917: goto -> 5191
/*    */     //   1920: aload_3
/*    */     //   1921: getfield fr0 : Lf/JG0;
/*    */     //   1924: ifnull -> 1948
/*    */     //   1927: ldc f/da
/*    */     //   1929: invokevirtual getName : ()Ljava/lang/String;
/*    */     //   1932: invokestatic getLogger : (Ljava/lang/String;)Ljava/util/logging/Logger;
/*    */     //   1935: getstatic java/util/logging/Level.SEVERE : Ljava/util/logging/Level;
/*    */     //   1938: ldc_w 'Widget already added: {0}'
/*    */     //   1941: aload_3
/*    */     //   1942: invokevirtual log : (Ljava/util/logging/Level;Ljava/lang/String;Ljava/lang/Object;)V
/*    */     //   1945: goto -> 5191
/*    */     //   1948: aload_0
/*    */     //   1949: aload_1
/*    */     //   1950: aload_2
/*    */     //   1951: aload_3
/*    */     //   1952: aload_0
/*    */     //   1953: aload_3
/*    */     //   1954: aload_0
/*    */     //   1955: invokevirtual Ub : ()I
/*    */     //   1958: invokespecial si : (Lf/JG0;I)V
/*    */     //   1961: invokevirtual mM : ()V
/*    */     //   1964: new f/Hc
/*    */     //   1967: dup
/*    */     //   1968: astore_0
/*    */     //   1969: aload_3
/*    */     //   1970: aload_0
/*    */     //   1971: aload_3
/*    */     //   1972: aload_0
/*    */     //   1973: aload_2
/*    */     //   1974: aload_3
/*    */     //   1975: invokespecial <init> : (Lf/xc;Lf/JG0;)V
/*    */     //   1978: getfield xY : I
/*    */     //   1981: putfield J1 : I
/*    */     //   1984: getfield HC : I
/*    */     //   1987: putfield tq0 : I
/*    */     //   1990: aload_0
/*    */     //   1991: invokevirtual Gv0 : (Lf/Gq0;Lf/xc;Lf/GC0;)V
/*    */     //   1994: goto -> 5191
/*    */     //   1997: aload_2
/*    */     //   1998: instanceof f/Zc0
/*    */     //   2001: ifeq -> 2316
/*    */     //   2004: aload_2
/*    */     //   2005: checkcast f/Zc0
/*    */     //   2008: dup
/*    */     //   2009: astore_2
/*    */     //   2010: getfield X10 : Lf/cR;
/*    */     //   2013: dup
/*    */     //   2014: astore_3
/*    */     //   2015: aload_0
/*    */     //   2016: aload_1
/*    */     //   2017: aload_3
/*    */     //   2018: invokevirtual oA : (Lf/Gq0;Lf/cR;)V
/*    */     //   2021: getstatic f/e00.LIST_STYLE_IMAGE : Lf/e00;
/*    */     //   2024: dup
/*    */     //   2025: astore #4
/*    */     //   2027: invokevirtual bw0 : (Lf/e00;)Lf/cR;
/*    */     //   2030: aload #4
/*    */     //   2032: invokevirtual rI : (Lf/e00;)Ljava/lang/Object;
/*    */     //   2035: checkcast java/lang/String
/*    */     //   2038: dup
/*    */     //   2039: astore #4
/*    */     //   2041: ifnull -> 2055
/*    */     //   2044: aload_0
/*    */     //   2045: aload #4
/*    */     //   2047: invokevirtual qC0 : (Ljava/lang/String;)Lf/mX;
/*    */     //   2050: astore #4
/*    */     //   2052: goto -> 2058
/*    */     //   2055: aconst_null
/*    */     //   2056: astore #4
/*    */     //   2058: aload #4
/*    */     //   2060: ifnull -> 2295
/*    */     //   2063: new f/m10
/*    */     //   2066: dup
/*    */     //   2067: astore #5
/*    */     //   2069: aload_1
/*    */     //   2070: aload #5
/*    */     //   2072: aload_0
/*    */     //   2073: aload_1
/*    */     //   2074: aload #5
/*    */     //   2076: dup
/*    */     //   2077: aload_1
/*    */     //   2078: aload_2
/*    */     //   2079: aload #5
/*    */     //   2081: aload_0
/*    */     //   2082: aload_3
/*    */     //   2083: aload_1
/*    */     //   2084: aload #5
/*    */     //   2086: aload_2
/*    */     //   2087: aload #4
/*    */     //   2089: invokespecial <init> : (Lf/xc;Lf/mX;)V
/*    */     //   2092: getstatic f/e00.PADDING_LEFT : Lf/e00;
/*    */     //   2095: astore #4
/*    */     //   2097: getfield MU : I
/*    */     //   2100: aload #4
/*    */     //   2102: swap
/*    */     //   2103: iconst_0
/*    */     //   2104: invokevirtual QE0 : (Lf/cR;Lf/e00;II)I
/*    */     //   2107: iconst_0
/*    */     //   2108: swap
/*    */     //   2109: invokestatic max : (II)I
/*    */     //   2112: i2s
/*    */     //   2113: putfield WS : S
/*    */     //   2116: getstatic f/Gj.Og0 : Lf/Gj;
/*    */     //   2119: getstatic f/Sx0.nI0 : Lf/Sx0;
/*    */     //   2122: astore #4
/*    */     //   2124: aload #5
/*    */     //   2126: swap
/*    */     //   2127: aload #4
/*    */     //   2129: invokestatic pe0 : (Lf/Gq0;Lf/xc;Lf/GC0;Lf/Gj;Lf/Sx0;)V
/*    */     //   2132: getfield tq0 : I
/*    */     //   2135: istore #4
/*    */     //   2137: sipush #32767
/*    */     //   2140: putfield tq0 : I
/*    */     //   2143: aload_2
/*    */     //   2144: invokevirtual F00 : (Lf/Gq0;Ljava/lang/Iterable;)V
/*    */     //   2147: iload #4
/*    */     //   2149: putfield tq0 : I
/*    */     //   2152: getfield lw : Ljava/util/ArrayList;
/*    */     //   2155: aload #5
/*    */     //   2157: invokevirtual remove : (Ljava/lang/Object;)Z
/*    */     //   2160: pop
/*    */     //   2161: invokevirtual O80 : ()I
/*    */     //   2164: dup
/*    */     //   2165: istore_2
/*    */     //   2166: aload_1
/*    */     //   2167: dup
/*    */     //   2168: iconst_0
/*    */     //   2169: invokevirtual vA0 : (Z)Z
/*    */     //   2172: pop
/*    */     //   2173: getfield wa0 : I
/*    */     //   2176: if_icmple -> 2288
/*    */     //   2179: aload_1
/*    */     //   2180: dup
/*    */     //   2181: iload_2
/*    */     //   2182: putfield wa0 : I
/*    */     //   2185: getfield lw : Ljava/util/ArrayList;
/*    */     //   2188: dup
/*    */     //   2189: astore_2
/*    */     //   2190: invokevirtual size : ()I
/*    */     //   2193: istore #4
/*    */     //   2195: iload #4
/*    */     //   2197: dup
/*    */     //   2198: iconst_m1
/*    */     //   2199: iadd
/*    */     //   2200: istore #4
/*    */     //   2202: ifle -> 2234
/*    */     //   2205: aload_2
/*    */     //   2206: iload #4
/*    */     //   2208: invokevirtual get : (I)Ljava/lang/Object;
/*    */     //   2211: checkcast f/GC0
/*    */     //   2214: invokevirtual O80 : ()I
/*    */     //   2217: aload_1
/*    */     //   2218: getfield wa0 : I
/*    */     //   2221: if_icmpgt -> 2195
/*    */     //   2224: aload_2
/*    */     //   2225: iload #4
/*    */     //   2227: invokevirtual remove : (I)Ljava/lang/Object;
/*    */     //   2230: pop
/*    */     //   2231: goto -> 2195
/*    */     //   2234: aload_1
/*    */     //   2235: getfield ph : Ljava/util/ArrayList;
/*    */     //   2238: dup
/*    */     //   2239: astore_2
/*    */     //   2240: invokevirtual size : ()I
/*    */     //   2243: istore #4
/*    */     //   2245: iload #4
/*    */     //   2247: dup
/*    */     //   2248: iconst_m1
/*    */     //   2249: iadd
/*    */     //   2250: istore #4
/*    */     //   2252: ifle -> 2284
/*    */     //   2255: aload_2
/*    */     //   2256: iload #4
/*    */     //   2258: invokevirtual get : (I)Ljava/lang/Object;
/*    */     //   2261: checkcast f/GC0
/*    */     //   2264: invokevirtual O80 : ()I
/*    */     //   2267: aload_1
/*    */     //   2268: getfield wa0 : I
/*    */     //   2271: if_icmpgt -> 2245
/*    */     //   2274: aload_2
/*    */     //   2275: iload #4
/*    */     //   2277: invokevirtual remove : (I)Ljava/lang/Object;
/*    */     //   2280: pop
/*    */     //   2281: goto -> 2245
/*    */     //   2284: aload_1
/*    */     //   2285: invokevirtual f1 : ()V
/*    */     //   2288: aload_1
/*    */     //   2289: invokevirtual f1 : ()V
/*    */     //   2292: goto -> 2307
/*    */     //   2295: aload_1
/*    */     //   2296: aload_0
/*    */     //   2297: aload_1
/*    */     //   2298: aload_2
/*    */     //   2299: invokevirtual F00 : (Lf/Gq0;Ljava/lang/Iterable;)V
/*    */     //   2302: iconst_0
/*    */     //   2303: invokevirtual vA0 : (Z)Z
/*    */     //   2306: pop
/*    */     //   2307: aload_0
/*    */     //   2308: aload_1
/*    */     //   2309: aload_3
/*    */     //   2310: invokevirtual GG0 : (Lf/Gq0;Lf/cR;)V
/*    */     //   2313: goto -> 5191
/*    */     //   2316: aload_2
/*    */     //   2317: instanceof f/iv0
/*    */     //   2320: ifeq -> 2929
/*    */     //   2323: aload_0
/*    */     //   2324: aload_2
/*    */     //   2325: checkcast f/iv0
/*    */     //   2328: dup
/*    */     //   2329: astore_2
/*    */     //   2330: getfield X10 : Lf/cR;
/*    */     //   2333: dup
/*    */     //   2334: astore_3
/*    */     //   2335: invokevirtual VP : (Lf/cR;)Lf/pe;
/*    */     //   2338: dup
/*    */     //   2339: astore #4
/*    */     //   2341: ifnonnull -> 2350
/*    */     //   2344: aconst_null
/*    */     //   2345: astore #4
/*    */     //   2347: goto -> 2406
/*    */     //   2350: new f/q90
/*    */     //   2353: dup
/*    */     //   2354: astore #5
/*    */     //   2356: aload #4
/*    */     //   2358: aload_3
/*    */     //   2359: dup
/*    */     //   2360: getstatic f/e00.COLOR : Lf/e00;
/*    */     //   2363: dup
/*    */     //   2364: astore #4
/*    */     //   2366: invokevirtual bw0 : (Lf/e00;)Lf/cR;
/*    */     //   2369: aload #4
/*    */     //   2371: invokevirtual rI : (Lf/e00;)Ljava/lang/Object;
/*    */     //   2374: checkcast f/pRn
/*    */     //   2377: astore #4
/*    */     //   2379: getstatic f/e00.COLOR_HOVER : Lf/e00;
/*    */     //   2382: dup
/*    */     //   2383: astore #6
/*    */     //   2385: invokevirtual bw0 : (Lf/e00;)Lf/cR;
/*    */     //   2388: aload #6
/*    */     //   2390: invokevirtual rI : (Lf/e00;)Ljava/lang/Object;
/*    */     //   2393: checkcast f/pRn
/*    */     //   2396: aload #4
/*    */     //   2398: swap
/*    */     //   2399: invokespecial <init> : (Lf/pe;Lf/pRn;Lf/pRn;)V
/*    */     //   2402: aload #5
/*    */     //   2404: astore #4
/*    */     //   2406: aload #4
/*    */     //   2408: ifnonnull -> 2414
/*    */     //   2411: goto -> 5191
/*    */     //   2414: aload_0
/*    */     //   2415: aload_3
/*    */     //   2416: aload_1
/*    */     //   2417: aload_2
/*    */     //   2418: dup
/*    */     //   2419: aload_1
/*    */     //   2420: aload_2
/*    */     //   2421: aload_0
/*    */     //   2422: aload_1
/*    */     //   2423: aload_3
/*    */     //   2424: invokevirtual oA : (Lf/Gq0;Lf/cR;)V
/*    */     //   2427: invokevirtual Um : (Lf/xc;)Lf/GC0;
/*    */     //   2430: astore #5
/*    */     //   2432: getfield ZF : I
/*    */     //   2435: iconst_1
/*    */     //   2436: swap
/*    */     //   2437: invokestatic max : (II)I
/*    */     //   2440: istore #6
/*    */     //   2442: getfield k60 : Ljava/util/ArrayList;
/*    */     //   2445: invokevirtual size : ()I
/*    */     //   2448: dup
/*    */     //   2449: istore #7
/*    */     //   2451: aload_3
/*    */     //   2452: getstatic f/e00.LIST_STYLE_TYPE : Lf/e00;
/*    */     //   2455: dup
/*    */     //   2456: astore #8
/*    */     //   2458: invokevirtual bw0 : (Lf/e00;)Lf/cR;
/*    */     //   2461: aload #8
/*    */     //   2463: invokevirtual rI : (Lf/e00;)Ljava/lang/Object;
/*    */     //   2466: checkcast f/au
/*    */     //   2469: astore #8
/*    */     //   2471: anewarray java/lang/String
/*    */     //   2474: astore #9
/*    */     //   2476: getstatic f/e00.PADDING_LEFT : Lf/e00;
/*    */     //   2479: astore #10
/*    */     //   2481: getfield MU : I
/*    */     //   2484: aload #10
/*    */     //   2486: swap
/*    */     //   2487: iconst_0
/*    */     //   2488: invokevirtual QE0 : (Lf/cR;Lf/e00;II)I
/*    */     //   2491: iconst_0
/*    */     //   2492: swap
/*    */     //   2493: invokestatic max : (II)I
/*    */     //   2496: istore #10
/*    */     //   2498: iconst_0
/*    */     //   2499: istore #11
/*    */     //   2501: iload #11
/*    */     //   2503: iload #7
/*    */     //   2505: if_icmpge -> 2558
/*    */     //   2508: iload #10
/*    */     //   2510: aload #4
/*    */     //   2512: aload #9
/*    */     //   2514: iload #11
/*    */     //   2516: aload #8
/*    */     //   2518: iload #6
/*    */     //   2520: iload #11
/*    */     //   2522: iadd
/*    */     //   2523: invokevirtual kq0 : (I)Ljava/lang/String;
/*    */     //   2526: ldc_w '. '
/*    */     //   2529: invokevirtual concat : (Ljava/lang/String;)Ljava/lang/String;
/*    */     //   2532: dup
/*    */     //   2533: astore #10
/*    */     //   2535: aastore
/*    */     //   2536: getfield eI : Lf/pe;
/*    */     //   2539: checkcast f/t90
/*    */     //   2542: aload #10
/*    */     //   2544: invokevirtual computeTextWidth : (Ljava/lang/CharSequence;)I
/*    */     //   2547: invokestatic max : (II)I
/*    */     //   2550: istore #10
/*    */     //   2552: iinc #11, 1
/*    */     //   2555: goto -> 2501
/*    */     //   2558: iconst_0
/*    */     //   2559: istore #6
/*    */     //   2561: iload #6
/*    */     //   2563: iload #7
/*    */     //   2565: if_icmpge -> 2905
/*    */     //   2568: aload_0
/*    */     //   2569: aload_1
/*    */     //   2570: aload_2
/*    */     //   2571: aload #9
/*    */     //   2573: iload #6
/*    */     //   2575: aaload
/*    */     //   2576: astore #8
/*    */     //   2578: getfield k60 : Ljava/util/ArrayList;
/*    */     //   2581: iload #6
/*    */     //   2583: invokevirtual get : (I)Ljava/lang/Object;
/*    */     //   2586: checkcast f/xc
/*    */     //   2589: dup
/*    */     //   2590: astore #11
/*    */     //   2592: getfield X10 : Lf/cR;
/*    */     //   2595: dup
/*    */     //   2596: astore #12
/*    */     //   2598: invokevirtual oA : (Lf/Gq0;Lf/cR;)V
/*    */     //   2601: new f/rl0
/*    */     //   2604: dup
/*    */     //   2605: astore #13
/*    */     //   2607: aload_1
/*    */     //   2608: aload #13
/*    */     //   2610: aload_0
/*    */     //   2611: aload_1
/*    */     //   2612: aload #13
/*    */     //   2614: dup
/*    */     //   2615: iload #10
/*    */     //   2617: aload #13
/*    */     //   2619: aload_1
/*    */     //   2620: aload_2
/*    */     //   2621: aload #13
/*    */     //   2623: aload_0
/*    */     //   2624: aload #12
/*    */     //   2626: aload_1
/*    */     //   2627: aload #13
/*    */     //   2629: dup
/*    */     //   2630: dup
/*    */     //   2631: aload_2
/*    */     //   2632: aload_1
/*    */     //   2633: aload #8
/*    */     //   2635: invokevirtual length : ()I
/*    */     //   2638: istore #14
/*    */     //   2640: getfield Jo : Z
/*    */     //   2643: istore #15
/*    */     //   2645: aload #4
/*    */     //   2647: aload #8
/*    */     //   2649: iconst_0
/*    */     //   2650: iload #14
/*    */     //   2652: iload #15
/*    */     //   2654: invokespecial <init> : (Lf/xc;Lf/q90;Ljava/lang/String;IIZ)V
/*    */     //   2657: getfield J1 : I
/*    */     //   2660: istore #8
/*    */     //   2662: getfield tq0 : I
/*    */     //   2665: istore #14
/*    */     //   2667: getstatic f/e00.PADDING_LEFT : Lf/e00;
/*    */     //   2670: astore #15
/*    */     //   2672: getfield MU : I
/*    */     //   2675: aload #15
/*    */     //   2677: swap
/*    */     //   2678: iconst_0
/*    */     //   2679: invokevirtual QE0 : (Lf/cR;Lf/e00;II)I
/*    */     //   2682: iconst_0
/*    */     //   2683: swap
/*    */     //   2684: invokestatic max : (II)I
/*    */     //   2687: iload #8
/*    */     //   2689: iadd
/*    */     //   2690: putfield J1 : I
/*    */     //   2693: getstatic f/Gj.Og0 : Lf/Gj;
/*    */     //   2696: getstatic f/Sx0.nI0 : Lf/Sx0;
/*    */     //   2699: astore #15
/*    */     //   2701: aload #13
/*    */     //   2703: swap
/*    */     //   2704: aload #15
/*    */     //   2706: invokestatic pe0 : (Lf/Gq0;Lf/xc;Lf/GC0;Lf/Gj;Lf/Sx0;)V
/*    */     //   2709: getfield Iu : I
/*    */     //   2712: istore #15
/*    */     //   2714: iload #8
/*    */     //   2716: isub
/*    */     //   2717: iconst_0
/*    */     //   2718: swap
/*    */     //   2719: invokestatic max : (II)I
/*    */     //   2722: iload #15
/*    */     //   2724: iadd
/*    */     //   2725: putfield Iu : I
/*    */     //   2728: sipush #32767
/*    */     //   2731: putfield tq0 : I
/*    */     //   2734: aload #11
/*    */     //   2736: invokevirtual Sl : (Lf/Gq0;Lf/xc;)V
/*    */     //   2739: iload #14
/*    */     //   2741: putfield tq0 : I
/*    */     //   2744: getfield lw : Ljava/util/ArrayList;
/*    */     //   2747: aload #13
/*    */     //   2749: invokevirtual remove : (Ljava/lang/Object;)Z
/*    */     //   2752: pop
/*    */     //   2753: invokevirtual O80 : ()I
/*    */     //   2756: dup
/*    */     //   2757: istore #8
/*    */     //   2759: aload_1
/*    */     //   2760: dup
/*    */     //   2761: iconst_0
/*    */     //   2762: invokevirtual vA0 : (Z)Z
/*    */     //   2765: pop
/*    */     //   2766: getfield wa0 : I
/*    */     //   2769: if_icmple -> 2888
/*    */     //   2772: aload_1
/*    */     //   2773: dup
/*    */     //   2774: iload #8
/*    */     //   2776: putfield wa0 : I
/*    */     //   2779: getfield lw : Ljava/util/ArrayList;
/*    */     //   2782: dup
/*    */     //   2783: astore #8
/*    */     //   2785: invokevirtual size : ()I
/*    */     //   2788: istore #11
/*    */     //   2790: iload #11
/*    */     //   2792: dup
/*    */     //   2793: iconst_m1
/*    */     //   2794: iadd
/*    */     //   2795: istore #11
/*    */     //   2797: ifle -> 2831
/*    */     //   2800: aload #8
/*    */     //   2802: iload #11
/*    */     //   2804: invokevirtual get : (I)Ljava/lang/Object;
/*    */     //   2807: checkcast f/GC0
/*    */     //   2810: invokevirtual O80 : ()I
/*    */     //   2813: aload_1
/*    */     //   2814: getfield wa0 : I
/*    */     //   2817: if_icmpgt -> 2790
/*    */     //   2820: aload #8
/*    */     //   2822: iload #11
/*    */     //   2824: invokevirtual remove : (I)Ljava/lang/Object;
/*    */     //   2827: pop
/*    */     //   2828: goto -> 2790
/*    */     //   2831: aload_1
/*    */     //   2832: getfield ph : Ljava/util/ArrayList;
/*    */     //   2835: dup
/*    */     //   2836: astore #8
/*    */     //   2838: invokevirtual size : ()I
/*    */     //   2841: istore #11
/*    */     //   2843: iload #11
/*    */     //   2845: dup
/*    */     //   2846: iconst_m1
/*    */     //   2847: iadd
/*    */     //   2848: istore #11
/*    */     //   2850: ifle -> 2884
/*    */     //   2853: aload #8
/*    */     //   2855: iload #11
/*    */     //   2857: invokevirtual get : (I)Ljava/lang/Object;
/*    */     //   2860: checkcast f/GC0
/*    */     //   2863: invokevirtual O80 : ()I
/*    */     //   2866: aload_1
/*    */     //   2867: getfield wa0 : I
/*    */     //   2870: if_icmpgt -> 2843
/*    */     //   2873: aload #8
/*    */     //   2875: iload #11
/*    */     //   2877: invokevirtual remove : (I)Ljava/lang/Object;
/*    */     //   2880: pop
/*    */     //   2881: goto -> 2843
/*    */     //   2884: aload_1
/*    */     //   2885: invokevirtual f1 : ()V
/*    */     //   2888: aload_0
/*    */     //   2889: aload_1
/*    */     //   2890: invokevirtual f1 : ()V
/*    */     //   2893: aload_1
/*    */     //   2894: aload #12
/*    */     //   2896: invokevirtual GG0 : (Lf/Gq0;Lf/cR;)V
/*    */     //   2899: iinc #6, 1
/*    */     //   2902: goto -> 2561
/*    */     //   2905: aload_0
/*    */     //   2906: aload_1
/*    */     //   2907: aload #5
/*    */     //   2909: aload_1
/*    */     //   2910: getfield wa0 : I
/*    */     //   2913: aload #5
/*    */     //   2915: getfield Bm : I
/*    */     //   2918: isub
/*    */     //   2919: putfield tq0 : I
/*    */     //   2922: aload_3
/*    */     //   2923: invokevirtual GG0 : (Lf/Gq0;Lf/cR;)V
/*    */     //   2926: goto -> 5191
/*    */     //   2929: aload_2
/*    */     //   2930: instanceof f/jr
/*    */     //   2933: ifeq -> 2949
/*    */     //   2936: aload_0
/*    */     //   2937: aload_2
/*    */     //   2938: checkcast f/jr
/*    */     //   2941: aload_1
/*    */     //   2942: swap
/*    */     //   2943: invokevirtual QQ : (Lf/Gq0;Lf/Ct;)V
/*    */     //   2946: goto -> 5191
/*    */     //   2949: aload_2
/*    */     //   2950: instanceof f/KN
/*    */     //   2953: ifeq -> 5024
/*    */     //   2956: aload_2
/*    */     //   2957: checkcast f/KN
/*    */     //   2960: dup
/*    */     //   2961: astore_2
/*    */     //   2962: getfield g50 : I
/*    */     //   2965: dup
/*    */     //   2966: istore_3
/*    */     //   2967: aload_2
/*    */     //   2968: dup
/*    */     //   2969: dup2
/*    */     //   2970: getfield bD : I
/*    */     //   2973: istore #4
/*    */     //   2975: getfield Qi : I
/*    */     //   2978: istore #5
/*    */     //   2980: getfield mE0 : I
/*    */     //   2983: istore #6
/*    */     //   2985: getfield X10 : Lf/cR;
/*    */     //   2988: astore #7
/*    */     //   2990: ifeq -> 5191
/*    */     //   2993: iload #4
/*    */     //   2995: ifne -> 3001
/*    */     //   2998: goto -> 5191
/*    */     //   3001: aload_1
/*    */     //   3002: aload_0
/*    */     //   3003: aload #7
/*    */     //   3005: aload_1
/*    */     //   3006: dup
/*    */     //   3007: aload_0
/*    */     //   3008: aload #7
/*    */     //   3010: aload_1
/*    */     //   3011: dup
/*    */     //   3012: aload_2
/*    */     //   3013: aload_0
/*    */     //   3014: aload_1
/*    */     //   3015: aload #7
/*    */     //   3017: invokevirtual oA : (Lf/Gq0;Lf/cR;)V
/*    */     //   3020: invokevirtual Um : (Lf/xc;)Lf/GC0;
/*    */     //   3023: astore #8
/*    */     //   3025: getstatic f/e00.MARGIN_LEFT : Lf/e00;
/*    */     //   3028: astore #9
/*    */     //   3030: getfield MU : I
/*    */     //   3033: aload #9
/*    */     //   3035: swap
/*    */     //   3036: iconst_0
/*    */     //   3037: invokevirtual QE0 : (Lf/cR;Lf/e00;II)I
/*    */     //   3040: iconst_0
/*    */     //   3041: swap
/*    */     //   3042: invokestatic max : (II)I
/*    */     //   3045: invokevirtual LD : (I)I
/*    */     //   3048: istore #9
/*    */     //   3050: getstatic f/e00.MARGIN_RIGHT : Lf/e00;
/*    */     //   3053: astore #10
/*    */     //   3055: getfield MU : I
/*    */     //   3058: aload #10
/*    */     //   3060: swap
/*    */     //   3061: iconst_0
/*    */     //   3062: invokevirtual QE0 : (Lf/cR;Lf/e00;II)I
/*    */     //   3065: iconst_0
/*    */     //   3066: swap
/*    */     //   3067: invokestatic max : (II)I
/*    */     //   3070: invokevirtual XS : (I)I
/*    */     //   3073: iload #9
/*    */     //   3075: isub
/*    */     //   3076: iconst_0
/*    */     //   3077: swap
/*    */     //   3078: invokestatic max : (II)I
/*    */     //   3081: dup
/*    */     //   3082: istore #10
/*    */     //   3084: aload_0
/*    */     //   3085: aload #7
/*    */     //   3087: aload_1
/*    */     //   3088: getstatic f/e00.WIDTH : Lf/e00;
/*    */     //   3091: astore #11
/*    */     //   3093: getfield MU : I
/*    */     //   3096: aload #11
/*    */     //   3098: swap
/*    */     //   3099: ldc_w -2147483648
/*    */     //   3102: invokevirtual QE0 : (Lf/cR;Lf/e00;II)I
/*    */     //   3105: invokestatic min : (II)I
/*    */     //   3108: dup
/*    */     //   3109: istore #11
/*    */     //   3111: ldc_w -2147483648
/*    */     //   3114: if_icmpne -> 3123
/*    */     //   3117: iconst_1
/*    */     //   3118: istore #12
/*    */     //   3120: goto -> 3126
/*    */     //   3123: iconst_0
/*    */     //   3124: istore #12
/*    */     //   3126: iload #11
/*    */     //   3128: ifgt -> 3135
/*    */     //   3131: iload #10
/*    */     //   3133: istore #11
/*    */     //   3135: aload_2
/*    */     //   3136: dup
/*    */     //   3137: dup2
/*    */     //   3138: iload_3
/*    */     //   3139: newarray int
/*    */     //   3141: astore #13
/*    */     //   3143: iload_3
/*    */     //   3144: iconst_1
/*    */     //   3145: iadd
/*    */     //   3146: dup
/*    */     //   3147: istore #14
/*    */     //   3149: newarray int
/*    */     //   3151: dup
/*    */     //   3152: astore #15
/*    */     //   3154: iload #5
/*    */     //   3156: aload_0
/*    */     //   3157: aload #7
/*    */     //   3159: aload_1
/*    */     //   3160: iload_3
/*    */     //   3161: newarray boolean
/*    */     //   3163: astore #16
/*    */     //   3165: getstatic f/e00.PADDING_LEFT : Lf/e00;
/*    */     //   3168: astore #17
/*    */     //   3170: getfield MU : I
/*    */     //   3173: aload #17
/*    */     //   3175: swap
/*    */     //   3176: iconst_0
/*    */     //   3177: invokevirtual QE0 : (Lf/cR;Lf/e00;II)I
/*    */     //   3180: iconst_0
/*    */     //   3181: swap
/*    */     //   3182: invokestatic max : (II)I
/*    */     //   3185: invokestatic max : (II)I
/*    */     //   3188: iconst_0
/*    */     //   3189: swap
/*    */     //   3190: iastore
/*    */     //   3191: getfield g50 : I
/*    */     //   3194: istore #17
/*    */     //   3196: getfield bD : I
/*    */     //   3199: istore #18
/*    */     //   3201: getfield Qi : I
/*    */     //   3204: istore #19
/*    */     //   3206: getfield mE0 : I
/*    */     //   3209: istore #20
/*    */     //   3211: aconst_null
/*    */     //   3212: astore #21
/*    */     //   3214: iconst_0
/*    */     //   3215: istore #22
/*    */     //   3217: iload #22
/*    */     //   3219: iload #17
/*    */     //   3221: if_icmpge -> 3604
/*    */     //   3224: iconst_0
/*    */     //   3225: istore #23
/*    */     //   3227: iconst_0
/*    */     //   3228: istore #24
/*    */     //   3230: iconst_0
/*    */     //   3231: istore #25
/*    */     //   3233: iconst_0
/*    */     //   3234: istore #26
/*    */     //   3236: iconst_0
/*    */     //   3237: istore #27
/*    */     //   3239: iload #27
/*    */     //   3241: iload #18
/*    */     //   3243: if_icmpge -> 3556
/*    */     //   3246: aload_2
/*    */     //   3247: iload #27
/*    */     //   3249: iload #22
/*    */     //   3251: invokevirtual nF : (II)Lf/bJ;
/*    */     //   3254: dup
/*    */     //   3255: astore #28
/*    */     //   3257: ifnull -> 3550
/*    */     //   3260: aload_0
/*    */     //   3261: aload #28
/*    */     //   3263: dup
/*    */     //   3264: getfield X10 : Lf/cR;
/*    */     //   3267: astore #29
/*    */     //   3269: getfield zd : I
/*    */     //   3272: istore #30
/*    */     //   3274: getstatic f/e00.WIDTH : Lf/e00;
/*    */     //   3277: aload #29
/*    */     //   3279: swap
/*    */     //   3280: iload #11
/*    */     //   3282: ldc_w -2147483648
/*    */     //   3285: invokevirtual QE0 : (Lf/cR;Lf/e00;II)I
/*    */     //   3288: dup
/*    */     //   3289: istore #31
/*    */     //   3291: ldc_w -2147483648
/*    */     //   3294: if_icmpne -> 3404
/*    */     //   3297: iload #30
/*    */     //   3299: iconst_1
/*    */     //   3300: if_icmpgt -> 3308
/*    */     //   3303: iload #26
/*    */     //   3305: ifne -> 3404
/*    */     //   3308: iload #11
/*    */     //   3310: aload_0
/*    */     //   3311: iload #20
/*    */     //   3313: aload_0
/*    */     //   3314: aload #29
/*    */     //   3316: iload #20
/*    */     //   3318: aload_0
/*    */     //   3319: aload #29
/*    */     //   3321: getstatic f/e00.PADDING_LEFT : Lf/e00;
/*    */     //   3324: iload #11
/*    */     //   3326: iconst_0
/*    */     //   3327: invokevirtual QE0 : (Lf/cR;Lf/e00;II)I
/*    */     //   3330: iconst_0
/*    */     //   3331: swap
/*    */     //   3332: invokestatic max : (II)I
/*    */     //   3335: invokestatic max : (II)I
/*    */     //   3338: istore #31
/*    */     //   3340: getstatic f/e00.PADDING_RIGHT : Lf/e00;
/*    */     //   3343: iload #11
/*    */     //   3345: iconst_0
/*    */     //   3346: invokevirtual QE0 : (Lf/cR;Lf/e00;II)I
/*    */     //   3349: iconst_0
/*    */     //   3350: swap
/*    */     //   3351: invokestatic max : (II)I
/*    */     //   3354: invokestatic max : (II)I
/*    */     //   3357: istore #32
/*    */     //   3359: new f/yB
/*    */     //   3362: dup
/*    */     //   3363: astore #33
/*    */     //   3365: iload #11
/*    */     //   3367: aload #33
/*    */     //   3369: iload #11
/*    */     //   3371: aload #33
/*    */     //   3373: aconst_null
/*    */     //   3374: invokespecial <init> : (Lf/xc;)V
/*    */     //   3377: putfield J1 : I
/*    */     //   3380: iload #31
/*    */     //   3382: iload #32
/*    */     //   3384: aload #28
/*    */     //   3386: aconst_null
/*    */     //   3387: iconst_0
/*    */     //   3388: invokevirtual ol : (Lf/yB;IIILf/Ct;Ljava/lang/String;Z)Lf/Gq0;
/*    */     //   3391: dup
/*    */     //   3392: invokevirtual b60 : ()V
/*    */     //   3395: getfield De : I
/*    */     //   3398: isub
/*    */     //   3399: istore #31
/*    */     //   3401: goto -> 3418
/*    */     //   3404: iload #30
/*    */     //   3406: iconst_1
/*    */     //   3407: if_icmpne -> 3418
/*    */     //   3410: iload #31
/*    */     //   3412: iflt -> 3418
/*    */     //   3415: iconst_1
/*    */     //   3416: istore #26
/*    */     //   3418: iload #30
/*    */     //   3420: iconst_1
/*    */     //   3421: if_icmple -> 3493
/*    */     //   3424: aload #21
/*    */     //   3426: ifnonnull -> 3438
/*    */     //   3429: new java/util/HashMap
/*    */     //   3432: dup
/*    */     //   3433: astore #21
/*    */     //   3435: invokespecial <init> : ()V
/*    */     //   3438: aload #21
/*    */     //   3440: iload #22
/*    */     //   3442: bipush #16
/*    */     //   3444: ishl
/*    */     //   3445: iload #30
/*    */     //   3447: iadd
/*    */     //   3448: invokestatic valueOf : (I)Ljava/lang/Integer;
/*    */     //   3451: dup
/*    */     //   3452: astore #28
/*    */     //   3454: invokevirtual get : (Ljava/lang/Object;)Ljava/lang/Object;
/*    */     //   3457: checkcast java/lang/Integer
/*    */     //   3460: dup
/*    */     //   3461: astore #29
/*    */     //   3463: ifnull -> 3476
/*    */     //   3466: iload #31
/*    */     //   3468: aload #29
/*    */     //   3470: invokevirtual intValue : ()I
/*    */     //   3473: if_icmple -> 3550
/*    */     //   3476: aload #21
/*    */     //   3478: iload #31
/*    */     //   3480: invokestatic valueOf : (I)Ljava/lang/Integer;
/*    */     //   3483: aload #28
/*    */     //   3485: swap
/*    */     //   3486: invokevirtual put : (Ljava/lang/Object;Ljava/lang/Object;)Ljava/lang/Object;
/*    */     //   3489: pop
/*    */     //   3490: goto -> 3550
/*    */     //   3493: iload #25
/*    */     //   3495: aload_0
/*    */     //   3496: aload #29
/*    */     //   3498: iload #24
/*    */     //   3500: aload_0
/*    */     //   3501: aload #29
/*    */     //   3503: iload #23
/*    */     //   3505: iload #31
/*    */     //   3507: invokestatic max : (II)I
/*    */     //   3510: istore #23
/*    */     //   3512: getstatic f/e00.MARGIN_LEFT : Lf/e00;
/*    */     //   3515: dup
/*    */     //   3516: astore #24
/*    */     //   3518: iload #11
/*    */     //   3520: iconst_0
/*    */     //   3521: invokevirtual QE0 : (Lf/cR;Lf/e00;II)I
/*    */     //   3524: invokestatic max : (II)I
/*    */     //   3527: istore #25
/*    */     //   3529: aload #24
/*    */     //   3531: iload #11
/*    */     //   3533: iconst_0
/*    */     //   3534: invokevirtual QE0 : (Lf/cR;Lf/e00;II)I
/*    */     //   3537: invokestatic max : (II)I
/*    */     //   3540: istore #24
/*    */     //   3542: iload #25
/*    */     //   3544: iload #24
/*    */     //   3546: istore #25
/*    */     //   3548: istore #24
/*    */     //   3550: iinc #27, 1
/*    */     //   3553: goto -> 3239
/*    */     //   3556: aload #15
/*    */     //   3558: iload #19
/*    */     //   3560: iload #25
/*    */     //   3562: aload #15
/*    */     //   3564: iload #22
/*    */     //   3566: aload #15
/*    */     //   3568: iload #22
/*    */     //   3570: aload #13
/*    */     //   3572: iload #22
/*    */     //   3574: iload #23
/*    */     //   3576: aload #16
/*    */     //   3578: iload #22
/*    */     //   3580: iload #26
/*    */     //   3582: bastore
/*    */     //   3583: iastore
/*    */     //   3584: iaload
/*    */     //   3585: iload #24
/*    */     //   3587: invokestatic max : (II)I
/*    */     //   3590: iastore
/*    */     //   3591: iinc #22, 1
/*    */     //   3594: invokestatic max : (II)I
/*    */     //   3597: iload #22
/*    */     //   3599: swap
/*    */     //   3600: iastore
/*    */     //   3601: goto -> 3217
/*    */     //   3604: aload #21
/*    */     //   3606: ifnull -> 3797
/*    */     //   3609: aload #21
/*    */     //   3611: invokevirtual entrySet : ()Ljava/util/Set;
/*    */     //   3614: invokeinterface iterator : ()Ljava/util/Iterator;
/*    */     //   3619: astore #17
/*    */     //   3621: aload #17
/*    */     //   3623: invokeinterface hasNext : ()Z
/*    */     //   3628: ifeq -> 3797
/*    */     //   3631: aload #17
/*    */     //   3633: invokeinterface next : ()Ljava/lang/Object;
/*    */     //   3638: checkcast java/util/Map$Entry
/*    */     //   3641: dup
/*    */     //   3642: invokeinterface getKey : ()Ljava/lang/Object;
/*    */     //   3647: checkcast java/lang/Integer
/*    */     //   3650: invokevirtual intValue : ()I
/*    */     //   3653: dup
/*    */     //   3654: bipush #16
/*    */     //   3656: iushr
/*    */     //   3657: istore #18
/*    */     //   3659: ldc_w 65535
/*    */     //   3662: iand
/*    */     //   3663: istore #19
/*    */     //   3665: invokeinterface getValue : ()Ljava/lang/Object;
/*    */     //   3670: checkcast java/lang/Integer
/*    */     //   3673: invokevirtual intValue : ()I
/*    */     //   3676: istore #20
/*    */     //   3678: iconst_0
/*    */     //   3679: istore #21
/*    */     //   3681: iload #19
/*    */     //   3683: istore #22
/*    */     //   3685: iload #21
/*    */     //   3687: iload #19
/*    */     //   3689: if_icmpge -> 3725
/*    */     //   3692: aload #16
/*    */     //   3694: iload #18
/*    */     //   3696: iload #21
/*    */     //   3698: iadd
/*    */     //   3699: dup
/*    */     //   3700: istore #23
/*    */     //   3702: baload
/*    */     //   3703: ifeq -> 3719
/*    */     //   3706: iload #20
/*    */     //   3708: aload #13
/*    */     //   3710: iload #23
/*    */     //   3712: iaload
/*    */     //   3713: isub
/*    */     //   3714: istore #20
/*    */     //   3716: iinc #22, -1
/*    */     //   3719: iinc #21, 1
/*    */     //   3722: goto -> 3685
/*    */     //   3725: iload #20
/*    */     //   3727: ifle -> 3621
/*    */     //   3730: iconst_0
/*    */     //   3731: istore #21
/*    */     //   3733: iload #21
/*    */     //   3735: iload #19
/*    */     //   3737: if_icmpge -> 3621
/*    */     //   3740: iload #22
/*    */     //   3742: ifle -> 3621
/*    */     //   3745: aload #16
/*    */     //   3747: iload #18
/*    */     //   3749: iload #21
/*    */     //   3751: iadd
/*    */     //   3752: dup
/*    */     //   3753: istore #23
/*    */     //   3755: baload
/*    */     //   3756: ifne -> 3791
/*    */     //   3759: iload #20
/*    */     //   3761: aload #13
/*    */     //   3763: iload #23
/*    */     //   3765: aload #13
/*    */     //   3767: iload #23
/*    */     //   3769: iload #20
/*    */     //   3771: iload #22
/*    */     //   3773: idiv
/*    */     //   3774: istore #20
/*    */     //   3776: iaload
/*    */     //   3777: iload #20
/*    */     //   3779: invokestatic max : (II)I
/*    */     //   3782: iastore
/*    */     //   3783: iload #20
/*    */     //   3785: isub
/*    */     //   3786: istore #20
/*    */     //   3788: iinc #22, -1
/*    */     //   3791: iinc #21, 1
/*    */     //   3794: goto -> 3733
/*    */     //   3797: aload #15
/*    */     //   3799: iload_3
/*    */     //   3800: aload #15
/*    */     //   3802: iload_3
/*    */     //   3803: iaload
/*    */     //   3804: aload_0
/*    */     //   3805: aload #7
/*    */     //   3807: aload_1
/*    */     //   3808: getstatic f/e00.PADDING_RIGHT : Lf/e00;
/*    */     //   3811: astore #17
/*    */     //   3813: getfield MU : I
/*    */     //   3816: aload #17
/*    */     //   3818: swap
/*    */     //   3819: iconst_0
/*    */     //   3820: invokevirtual QE0 : (Lf/cR;Lf/e00;II)I
/*    */     //   3823: iconst_0
/*    */     //   3824: swap
/*    */     //   3825: invokestatic max : (II)I
/*    */     //   3828: invokestatic max : (II)I
/*    */     //   3831: iastore
/*    */     //   3832: iconst_0
/*    */     //   3833: istore #17
/*    */     //   3835: iconst_0
/*    */     //   3836: istore #18
/*    */     //   3838: iload #18
/*    */     //   3840: iload #14
/*    */     //   3842: if_icmpge -> 3861
/*    */     //   3845: iload #17
/*    */     //   3847: aload #15
/*    */     //   3849: iload #18
/*    */     //   3851: iaload
/*    */     //   3852: iadd
/*    */     //   3853: istore #17
/*    */     //   3855: iinc #18, 1
/*    */     //   3858: goto -> 3838
/*    */     //   3861: iconst_0
/*    */     //   3862: istore #14
/*    */     //   3864: iconst_0
/*    */     //   3865: istore #18
/*    */     //   3867: iload #18
/*    */     //   3869: iload_3
/*    */     //   3870: if_icmpge -> 3889
/*    */     //   3873: iload #14
/*    */     //   3875: aload #13
/*    */     //   3877: iload #18
/*    */     //   3879: iaload
/*    */     //   3880: iadd
/*    */     //   3881: istore #14
/*    */     //   3883: iinc #18, 1
/*    */     //   3886: goto -> 3867
/*    */     //   3889: iload #12
/*    */     //   3891: ifeq -> 3906
/*    */     //   3894: iload #10
/*    */     //   3896: iload #14
/*    */     //   3898: iload #17
/*    */     //   3900: iadd
/*    */     //   3901: invokestatic min : (II)I
/*    */     //   3904: istore #11
/*    */     //   3906: iload #11
/*    */     //   3908: iload #17
/*    */     //   3910: isub
/*    */     //   3911: iconst_0
/*    */     //   3912: swap
/*    */     //   3913: invokestatic max : (II)I
/*    */     //   3916: dup
/*    */     //   3917: istore #10
/*    */     //   3919: iload #14
/*    */     //   3921: if_icmpeq -> 4101
/*    */     //   3924: iload #14
/*    */     //   3926: ifle -> 4101
/*    */     //   3929: iconst_0
/*    */     //   3930: istore #12
/*    */     //   3932: iload #10
/*    */     //   3934: iload #14
/*    */     //   3936: iload_3
/*    */     //   3937: istore #19
/*    */     //   3939: istore #18
/*    */     //   3941: istore #17
/*    */     //   3943: iload #12
/*    */     //   3945: iload_3
/*    */     //   3946: if_icmpge -> 3994
/*    */     //   3949: aload #16
/*    */     //   3951: iload #12
/*    */     //   3953: baload
/*    */     //   3954: ifeq -> 3988
/*    */     //   3957: iload #18
/*    */     //   3959: iload #17
/*    */     //   3961: aload #13
/*    */     //   3963: iload #12
/*    */     //   3965: iaload
/*    */     //   3966: dup
/*    */     //   3967: istore #17
/*    */     //   3969: isub
/*    */     //   3970: istore #18
/*    */     //   3972: iload #17
/*    */     //   3974: isub
/*    */     //   3975: istore #17
/*    */     //   3977: iinc #19, -1
/*    */     //   3980: iload #18
/*    */     //   3982: iload #17
/*    */     //   3984: istore #18
/*    */     //   3986: istore #17
/*    */     //   3988: iinc #12, 1
/*    */     //   3991: goto -> 3943
/*    */     //   3994: iload #10
/*    */     //   3996: iconst_0
/*    */     //   3997: istore #12
/*    */     //   3999: ifge -> 4011
/*    */     //   4002: iconst_1
/*    */     //   4003: istore #12
/*    */     //   4005: iload_3
/*    */     //   4006: istore #19
/*    */     //   4008: goto -> 4019
/*    */     //   4011: iload #17
/*    */     //   4013: iload #18
/*    */     //   4015: istore #14
/*    */     //   4017: istore #10
/*    */     //   4019: iconst_0
/*    */     //   4020: istore #17
/*    */     //   4022: iload #17
/*    */     //   4024: iload_3
/*    */     //   4025: if_icmpge -> 4101
/*    */     //   4028: iload #19
/*    */     //   4030: ifle -> 4101
/*    */     //   4033: iload #12
/*    */     //   4035: ifne -> 4046
/*    */     //   4038: aload #16
/*    */     //   4040: iload #17
/*    */     //   4042: baload
/*    */     //   4043: ifne -> 4095
/*    */     //   4046: iload #14
/*    */     //   4048: aload #13
/*    */     //   4050: iload #17
/*    */     //   4052: iaload
/*    */     //   4053: istore #18
/*    */     //   4055: ifle -> 4071
/*    */     //   4058: iload #18
/*    */     //   4060: iload #10
/*    */     //   4062: imul
/*    */     //   4063: iload #14
/*    */     //   4065: idiv
/*    */     //   4066: istore #20
/*    */     //   4068: goto -> 4074
/*    */     //   4071: iconst_0
/*    */     //   4072: istore #20
/*    */     //   4074: iload #14
/*    */     //   4076: iload #10
/*    */     //   4078: aload #13
/*    */     //   4080: iload #17
/*    */     //   4082: iload #20
/*    */     //   4084: iastore
/*    */     //   4085: iload #20
/*    */     //   4087: isub
/*    */     //   4088: istore #10
/*    */     //   4090: iload #18
/*    */     //   4092: isub
/*    */     //   4093: istore #14
/*    */     //   4095: iinc #17, 1
/*    */     //   4098: goto -> 4022
/*    */     //   4101: iload_3
/*    */     //   4102: aload_1
/*    */     //   4103: iload #5
/*    */     //   4105: aload_0
/*    */     //   4106: aload #7
/*    */     //   4108: aload_1
/*    */     //   4109: dup
/*    */     //   4110: dup
/*    */     //   4111: aload_0
/*    */     //   4112: aload_1
/*    */     //   4113: aload_2
/*    */     //   4114: invokevirtual lJ : (Lf/Gq0;Lf/xc;)Lf/m10;
/*    */     //   4117: astore #10
/*    */     //   4119: getstatic f/AuX.XT : Lf/AuX;
/*    */     //   4122: putfield kI0 : Lf/AuX;
/*    */     //   4125: getfield wa0 : I
/*    */     //   4128: istore #12
/*    */     //   4130: getstatic f/e00.PADDING_TOP : Lf/e00;
/*    */     //   4133: astore #14
/*    */     //   4135: getfield MU : I
/*    */     //   4138: aload #14
/*    */     //   4140: swap
/*    */     //   4141: iconst_0
/*    */     //   4142: invokevirtual QE0 : (Lf/cR;Lf/e00;II)I
/*    */     //   4145: iconst_0
/*    */     //   4146: swap
/*    */     //   4147: invokestatic max : (II)I
/*    */     //   4150: invokestatic max : (II)I
/*    */     //   4153: iload #12
/*    */     //   4155: iadd
/*    */     //   4156: putfield wa0 : I
/*    */     //   4159: anewarray f/m10
/*    */     //   4162: astore #12
/*    */     //   4164: iconst_0
/*    */     //   4165: istore #14
/*    */     //   4167: iload #14
/*    */     //   4169: iload #4
/*    */     //   4171: if_icmpge -> 4795
/*    */     //   4174: iload #14
/*    */     //   4176: ifle -> 4190
/*    */     //   4179: aload_1
/*    */     //   4180: dup
/*    */     //   4181: getfield wa0 : I
/*    */     //   4184: iload #5
/*    */     //   4186: iadd
/*    */     //   4187: putfield wa0 : I
/*    */     //   4190: aload_2
/*    */     //   4191: aconst_null
/*    */     //   4192: astore #16
/*    */     //   4194: getfield nx0 : [Lf/cR;
/*    */     //   4197: iload #14
/*    */     //   4199: aaload
/*    */     //   4200: dup
/*    */     //   4201: astore #17
/*    */     //   4203: ifnull -> 4374
/*    */     //   4206: aload #17
/*    */     //   4208: aload_1
/*    */     //   4209: dup
/*    */     //   4210: aload_0
/*    */     //   4211: aload #17
/*    */     //   4213: getstatic f/e00.MARGIN_TOP : Lf/e00;
/*    */     //   4216: iload #11
/*    */     //   4218: iconst_0
/*    */     //   4219: invokevirtual QE0 : (Lf/cR;Lf/e00;II)I
/*    */     //   4222: iconst_0
/*    */     //   4223: swap
/*    */     //   4224: invokestatic max : (II)I
/*    */     //   4227: invokevirtual qr0 : (I)I
/*    */     //   4230: putfield wa0 : I
/*    */     //   4233: getstatic f/e00.BACKGROUND_IMAGE : Lf/e00;
/*    */     //   4236: dup
/*    */     //   4237: astore #18
/*    */     //   4239: invokevirtual bw0 : (Lf/e00;)Lf/cR;
/*    */     //   4242: aload #18
/*    */     //   4244: invokevirtual rI : (Lf/e00;)Ljava/lang/Object;
/*    */     //   4247: checkcast java/lang/String
/*    */     //   4250: dup
/*    */     //   4251: astore #18
/*    */     //   4253: ifnull -> 4267
/*    */     //   4256: aload_0
/*    */     //   4257: aload #18
/*    */     //   4259: invokevirtual qC0 : (Ljava/lang/String;)Lf/mX;
/*    */     //   4262: astore #18
/*    */     //   4264: goto -> 4270
/*    */     //   4267: aconst_null
/*    */     //   4268: astore #18
/*    */     //   4270: aload #18
/*    */     //   4272: ifnull -> 4323
/*    */     //   4275: aload_1
/*    */     //   4276: new f/m10
/*    */     //   4279: dup
/*    */     //   4280: astore #16
/*    */     //   4282: iload #11
/*    */     //   4284: aload #16
/*    */     //   4286: iload #9
/*    */     //   4288: aload #16
/*    */     //   4290: aload_1
/*    */     //   4291: aload #16
/*    */     //   4293: aload_2
/*    */     //   4294: aload #18
/*    */     //   4296: invokespecial <init> : (Lf/xc;Lf/mX;)V
/*    */     //   4299: getfield wa0 : I
/*    */     //   4302: putfield Bm : I
/*    */     //   4305: putfield Iu : I
/*    */     //   4308: putfield J1 : I
/*    */     //   4311: getfield fa : Lf/yB;
/*    */     //   4314: getfield yb0 : Ljava/util/ArrayList;
/*    */     //   4317: aload #16
/*    */     //   4319: invokevirtual add : (Ljava/lang/Object;)Z
/*    */     //   4322: pop
/*    */     //   4323: aload_1
/*    */     //   4324: aload_0
/*    */     //   4325: aload #17
/*    */     //   4327: aload_1
/*    */     //   4328: aload_0
/*    */     //   4329: aload #17
/*    */     //   4331: aload_1
/*    */     //   4332: getfield wa0 : I
/*    */     //   4335: istore #18
/*    */     //   4337: getstatic f/e00.PADDING_TOP : Lf/e00;
/*    */     //   4340: iload #11
/*    */     //   4342: iconst_0
/*    */     //   4343: invokevirtual QE0 : (Lf/cR;Lf/e00;II)I
/*    */     //   4346: iconst_0
/*    */     //   4347: swap
/*    */     //   4348: invokestatic max : (II)I
/*    */     //   4351: iload #18
/*    */     //   4353: iadd
/*    */     //   4354: putfield wa0 : I
/*    */     //   4357: getstatic f/e00.HEIGHT : Lf/e00;
/*    */     //   4360: iload #11
/*    */     //   4362: iconst_0
/*    */     //   4363: invokevirtual QE0 : (Lf/cR;Lf/e00;II)I
/*    */     //   4366: iconst_0
/*    */     //   4367: swap
/*    */     //   4368: invokestatic max : (II)I
/*    */     //   4371: putfield dM0 : I
/*    */     //   4374: iconst_0
/*    */     //   4375: istore #18
/*    */     //   4377: iload #9
/*    */     //   4379: istore #19
/*    */     //   4381: iload #18
/*    */     //   4383: iload_3
/*    */     //   4384: if_icmpge -> 4673
/*    */     //   4387: aload_2
/*    */     //   4388: iload #14
/*    */     //   4390: iload #19
/*    */     //   4392: aload #15
/*    */     //   4394: iload #18
/*    */     //   4396: iaload
/*    */     //   4397: iadd
/*    */     //   4398: istore #19
/*    */     //   4400: iload #18
/*    */     //   4402: invokevirtual nF : (II)Lf/bJ;
/*    */     //   4405: dup
/*    */     //   4406: astore #20
/*    */     //   4408: aload #13
/*    */     //   4410: iload #18
/*    */     //   4412: iaload
/*    */     //   4413: istore #21
/*    */     //   4415: ifnull -> 4660
/*    */     //   4418: iconst_1
/*    */     //   4419: istore #22
/*    */     //   4421: iload #22
/*    */     //   4423: aload #20
/*    */     //   4425: getfield zd : I
/*    */     //   4428: if_icmpge -> 4459
/*    */     //   4431: aload #15
/*    */     //   4433: iload #18
/*    */     //   4435: iload #22
/*    */     //   4437: iadd
/*    */     //   4438: dup
/*    */     //   4439: istore #23
/*    */     //   4441: iaload
/*    */     //   4442: aload #13
/*    */     //   4444: iload #23
/*    */     //   4446: iaload
/*    */     //   4447: iadd
/*    */     //   4448: iload #21
/*    */     //   4450: iadd
/*    */     //   4451: istore #21
/*    */     //   4453: iinc #22, 1
/*    */     //   4456: goto -> 4421
/*    */     //   4459: aload_0
/*    */     //   4460: aload_1
/*    */     //   4461: aload #20
/*    */     //   4463: iload #6
/*    */     //   4465: aload_0
/*    */     //   4466: iload #6
/*    */     //   4468: aload_0
/*    */     //   4469: aload #20
/*    */     //   4471: getfield X10 : Lf/cR;
/*    */     //   4474: dup
/*    */     //   4475: astore #22
/*    */     //   4477: getstatic f/e00.PADDING_LEFT : Lf/e00;
/*    */     //   4480: iload #11
/*    */     //   4482: iconst_0
/*    */     //   4483: invokevirtual QE0 : (Lf/cR;Lf/e00;II)I
/*    */     //   4486: iconst_0
/*    */     //   4487: swap
/*    */     //   4488: invokestatic max : (II)I
/*    */     //   4491: invokestatic max : (II)I
/*    */     //   4494: istore #23
/*    */     //   4496: aload #22
/*    */     //   4498: getstatic f/e00.PADDING_RIGHT : Lf/e00;
/*    */     //   4501: iload #11
/*    */     //   4503: iconst_0
/*    */     //   4504: invokevirtual QE0 : (Lf/cR;Lf/e00;II)I
/*    */     //   4507: iconst_0
/*    */     //   4508: swap
/*    */     //   4509: invokestatic max : (II)I
/*    */     //   4512: invokestatic max : (II)I
/*    */     //   4515: istore #24
/*    */     //   4517: new f/yB
/*    */     //   4520: dup
/*    */     //   4521: astore #25
/*    */     //   4523: aload #20
/*    */     //   4525: invokespecial <init> : (Lf/xc;)V
/*    */     //   4528: invokevirtual lJ : (Lf/Gq0;Lf/xc;)Lf/m10;
/*    */     //   4531: dup
/*    */     //   4532: astore #26
/*    */     //   4534: ifnull -> 4563
/*    */     //   4537: aload #12
/*    */     //   4539: aload #26
/*    */     //   4541: dup
/*    */     //   4542: dup
/*    */     //   4543: iload #19
/*    */     //   4545: putfield Iu : I
/*    */     //   4548: iload #21
/*    */     //   4550: putfield J1 : I
/*    */     //   4553: aload #25
/*    */     //   4555: putfield RE0 : Lf/GC0;
/*    */     //   4558: iload #18
/*    */     //   4560: aload #26
/*    */     //   4562: aastore
/*    */     //   4563: aload #20
/*    */     //   4565: aload_0
/*    */     //   4566: aload #25
/*    */     //   4568: iload #11
/*    */     //   4570: aload_1
/*    */     //   4571: dup
/*    */     //   4572: aload #25
/*    */     //   4574: aload_0
/*    */     //   4575: aload #22
/*    */     //   4577: aload #25
/*    */     //   4579: iload #21
/*    */     //   4581: aload #25
/*    */     //   4583: aload_1
/*    */     //   4584: aload #25
/*    */     //   4586: iload #19
/*    */     //   4588: putfield Iu : I
/*    */     //   4591: getfield wa0 : I
/*    */     //   4594: putfield Bm : I
/*    */     //   4597: putfield J1 : I
/*    */     //   4600: getstatic f/e00.MARGIN_TOP : Lf/e00;
/*    */     //   4603: iload #11
/*    */     //   4605: iconst_0
/*    */     //   4606: invokevirtual QE0 : (Lf/cR;Lf/e00;II)I
/*    */     //   4609: iconst_0
/*    */     //   4610: swap
/*    */     //   4611: invokestatic max : (II)I
/*    */     //   4614: i2s
/*    */     //   4615: putfield Zq : S
/*    */     //   4618: getfield mz : Ljava/util/ArrayList;
/*    */     //   4621: aload #25
/*    */     //   4623: invokevirtual add : (Ljava/lang/Object;)Z
/*    */     //   4626: pop
/*    */     //   4627: getfield Jo : Z
/*    */     //   4630: istore #22
/*    */     //   4632: iload #23
/*    */     //   4634: iload #24
/*    */     //   4636: aload #20
/*    */     //   4638: aconst_null
/*    */     //   4639: iload #22
/*    */     //   4641: invokevirtual ol : (Lf/yB;IIILf/Ct;Ljava/lang/String;Z)Lf/Gq0;
/*    */     //   4644: pop
/*    */     //   4645: getfield zd : I
/*    */     //   4648: iconst_1
/*    */     //   4649: isub
/*    */     //   4650: iconst_0
/*    */     //   4651: swap
/*    */     //   4652: invokestatic max : (II)I
/*    */     //   4655: iload #18
/*    */     //   4657: iadd
/*    */     //   4658: istore #18
/*    */     //   4660: iload #19
/*    */     //   4662: iload #21
/*    */     //   4664: iadd
/*    */     //   4665: istore #19
/*    */     //   4667: iinc #18, 1
/*    */     //   4670: goto -> 4381
/*    */     //   4673: aload_1
/*    */     //   4674: iconst_0
/*    */     //   4675: invokevirtual vA0 : (Z)Z
/*    */     //   4678: pop
/*    */     //   4679: iconst_0
/*    */     //   4680: istore #18
/*    */     //   4682: iload #18
/*    */     //   4684: iload_3
/*    */     //   4685: if_icmpge -> 4726
/*    */     //   4688: aload #12
/*    */     //   4690: iload #18
/*    */     //   4692: aaload
/*    */     //   4693: dup
/*    */     //   4694: astore #19
/*    */     //   4696: ifnull -> 4720
/*    */     //   4699: aload #12
/*    */     //   4701: iload #18
/*    */     //   4703: aload #19
/*    */     //   4705: aload_1
/*    */     //   4706: getfield wa0 : I
/*    */     //   4709: aload #19
/*    */     //   4711: getfield Bm : I
/*    */     //   4714: isub
/*    */     //   4715: putfield tq0 : I
/*    */     //   4718: aconst_null
/*    */     //   4719: aastore
/*    */     //   4720: iinc #18, 1
/*    */     //   4723: goto -> 4682
/*    */     //   4726: aload #17
/*    */     //   4728: ifnull -> 4789
/*    */     //   4731: aload #16
/*    */     //   4733: aload_1
/*    */     //   4734: aload_0
/*    */     //   4735: aload #17
/*    */     //   4737: aload_1
/*    */     //   4738: getfield wa0 : I
/*    */     //   4741: istore #18
/*    */     //   4743: getstatic f/e00.PADDING_BOTTOM : Lf/e00;
/*    */     //   4746: iload #11
/*    */     //   4748: iconst_0
/*    */     //   4749: invokevirtual QE0 : (Lf/cR;Lf/e00;II)I
/*    */     //   4752: iconst_0
/*    */     //   4753: swap
/*    */     //   4754: invokestatic max : (II)I
/*    */     //   4757: iload #18
/*    */     //   4759: iadd
/*    */     //   4760: dup
/*    */     //   4761: istore #18
/*    */     //   4763: putfield wa0 : I
/*    */     //   4766: ifnull -> 4782
/*    */     //   4769: aload #16
/*    */     //   4771: iload #18
/*    */     //   4773: aload #16
/*    */     //   4775: getfield Bm : I
/*    */     //   4778: isub
/*    */     //   4779: putfield tq0 : I
/*    */     //   4782: aload_0
/*    */     //   4783: aload_1
/*    */     //   4784: aload #17
/*    */     //   4786: invokevirtual GG0 : (Lf/Gq0;Lf/cR;)V
/*    */     //   4789: iinc #14, 1
/*    */     //   4792: goto -> 4167
/*    */     //   4795: aload_1
/*    */     //   4796: dup
/*    */     //   4797: iload #5
/*    */     //   4799: aload_0
/*    */     //   4800: aload #7
/*    */     //   4802: aload_1
/*    */     //   4803: dup
/*    */     //   4804: getfield wa0 : I
/*    */     //   4807: istore_2
/*    */     //   4808: getstatic f/e00.PADDING_BOTTOM : Lf/e00;
/*    */     //   4811: astore_3
/*    */     //   4812: getfield MU : I
/*    */     //   4815: aload_3
/*    */     //   4816: swap
/*    */     //   4817: iconst_0
/*    */     //   4818: invokevirtual QE0 : (Lf/cR;Lf/e00;II)I
/*    */     //   4821: iconst_0
/*    */     //   4822: swap
/*    */     //   4823: invokestatic max : (II)I
/*    */     //   4826: invokestatic max : (II)I
/*    */     //   4829: iload_2
/*    */     //   4830: iadd
/*    */     //   4831: putfield wa0 : I
/*    */     //   4834: getfield lw : Ljava/util/ArrayList;
/*    */     //   4837: dup
/*    */     //   4838: astore_2
/*    */     //   4839: invokevirtual size : ()I
/*    */     //   4842: istore_3
/*    */     //   4843: iload_3
/*    */     //   4844: dup
/*    */     //   4845: iconst_m1
/*    */     //   4846: iadd
/*    */     //   4847: istore_3
/*    */     //   4848: ifle -> 4878
/*    */     //   4851: aload_2
/*    */     //   4852: iload_3
/*    */     //   4853: invokevirtual get : (I)Ljava/lang/Object;
/*    */     //   4856: checkcast f/GC0
/*    */     //   4859: invokevirtual O80 : ()I
/*    */     //   4862: aload_1
/*    */     //   4863: getfield wa0 : I
/*    */     //   4866: if_icmpgt -> 4843
/*    */     //   4869: aload_2
/*    */     //   4870: iload_3
/*    */     //   4871: invokevirtual remove : (I)Ljava/lang/Object;
/*    */     //   4874: pop
/*    */     //   4875: goto -> 4843
/*    */     //   4878: aload_1
/*    */     //   4879: getfield ph : Ljava/util/ArrayList;
/*    */     //   4882: dup
/*    */     //   4883: astore_2
/*    */     //   4884: invokevirtual size : ()I
/*    */     //   4887: istore_3
/*    */     //   4888: iload_3
/*    */     //   4889: dup
/*    */     //   4890: iconst_m1
/*    */     //   4891: iadd
/*    */     //   4892: istore_3
/*    */     //   4893: ifle -> 4923
/*    */     //   4896: aload_2
/*    */     //   4897: iload_3
/*    */     //   4898: invokevirtual get : (I)Ljava/lang/Object;
/*    */     //   4901: checkcast f/GC0
/*    */     //   4904: invokevirtual O80 : ()I
/*    */     //   4907: aload_1
/*    */     //   4908: getfield wa0 : I
/*    */     //   4911: if_icmpgt -> 4888
/*    */     //   4914: aload_2
/*    */     //   4915: iload_3
/*    */     //   4916: invokevirtual remove : (I)Ljava/lang/Object;
/*    */     //   4919: pop
/*    */     //   4920: goto -> 4888
/*    */     //   4923: aload #10
/*    */     //   4925: aload_1
/*    */     //   4926: dup
/*    */     //   4927: dup2
/*    */     //   4928: invokevirtual f1 : ()V
/*    */     //   4931: getfield yl : I
/*    */     //   4934: iload #11
/*    */     //   4936: isub
/*    */     //   4937: iconst_0
/*    */     //   4938: swap
/*    */     //   4939: invokestatic max : (II)I
/*    */     //   4942: istore_2
/*    */     //   4943: getfield De : I
/*    */     //   4946: iload_2
/*    */     //   4947: invokestatic min : (II)I
/*    */     //   4950: putfield De : I
/*    */     //   4953: ifnull -> 4985
/*    */     //   4956: aload #10
/*    */     //   4958: iload #11
/*    */     //   4960: aload #10
/*    */     //   4962: iload #9
/*    */     //   4964: aload #10
/*    */     //   4966: aload_1
/*    */     //   4967: getfield wa0 : I
/*    */     //   4970: aload #10
/*    */     //   4972: getfield Bm : I
/*    */     //   4975: isub
/*    */     //   4976: putfield tq0 : I
/*    */     //   4979: putfield Iu : I
/*    */     //   4982: putfield J1 : I
/*    */     //   4985: aload_0
/*    */     //   4986: aload_1
/*    */     //   4987: aload #8
/*    */     //   4989: aload_1
/*    */     //   4990: aload #8
/*    */     //   4992: iload #11
/*    */     //   4994: aload #8
/*    */     //   4996: iload #9
/*    */     //   4998: putfield Iu : I
/*    */     //   5001: putfield J1 : I
/*    */     //   5004: getfield wa0 : I
/*    */     //   5007: aload #8
/*    */     //   5009: getfield Bm : I
/*    */     //   5012: isub
/*    */     //   5013: putfield tq0 : I
/*    */     //   5016: aload #7
/*    */     //   5018: invokevirtual GG0 : (Lf/Gq0;Lf/cR;)V
/*    */     //   5021: goto -> 5191
/*    */     //   5024: aload_2
/*    */     //   5025: instanceof f/Cq0
/*    */     //   5028: ifeq -> 5122
/*    */     //   5031: aload_1
/*    */     //   5032: dup
/*    */     //   5033: aload_2
/*    */     //   5034: checkcast f/Cq0
/*    */     //   5037: astore_2
/*    */     //   5038: getfield rv0 : Ljava/lang/String;
/*    */     //   5041: astore_3
/*    */     //   5042: aload_2
/*    */     //   5043: getfield RC0 : Ljava/lang/String;
/*    */     //   5046: putfield rv0 : Ljava/lang/String;
/*    */     //   5049: aload_2
/*    */     //   5050: getfield X10 : Lf/cR;
/*    */     //   5053: getstatic f/e00.DISPLAY : Lf/e00;
/*    */     //   5056: dup
/*    */     //   5057: astore #4
/*    */     //   5059: invokevirtual bw0 : (Lf/e00;)Lf/cR;
/*    */     //   5062: aload #4
/*    */     //   5064: invokevirtual rI : (Lf/e00;)Ljava/lang/Object;
/*    */     //   5067: checkcast f/Sx0
/*    */     //   5070: getstatic f/Sx0.nI0 : Lf/Sx0;
/*    */     //   5073: if_acmpne -> 5085
/*    */     //   5076: aload_0
/*    */     //   5077: aload_1
/*    */     //   5078: aload_2
/*    */     //   5079: invokevirtual QQ : (Lf/Gq0;Lf/Ct;)V
/*    */     //   5082: goto -> 5114
/*    */     //   5085: aload_0
/*    */     //   5086: dup
/*    */     //   5087: aload_1
/*    */     //   5088: aload_0
/*    */     //   5089: aload_2
/*    */     //   5090: getfield X10 : Lf/cR;
/*    */     //   5093: astore_0
/*    */     //   5094: aload_1
/*    */     //   5095: aload_0
/*    */     //   5096: invokevirtual oA : (Lf/Gq0;Lf/cR;)V
/*    */     //   5099: aload_2
/*    */     //   5100: invokevirtual Um : (Lf/xc;)Lf/GC0;
/*    */     //   5103: pop
/*    */     //   5104: aload_1
/*    */     //   5105: aload_2
/*    */     //   5106: invokevirtual F00 : (Lf/Gq0;Ljava/lang/Iterable;)V
/*    */     //   5109: aload_1
/*    */     //   5110: aload_0
/*    */     //   5111: invokevirtual GG0 : (Lf/Gq0;Lf/cR;)V
/*    */     //   5114: aload_1
/*    */     //   5115: aload_3
/*    */     //   5116: putfield rv0 : Ljava/lang/String;
/*    */     //   5119: goto -> 5191
/*    */     //   5122: aload_2
/*    */     //   5123: instanceof f/Ct
/*    */     //   5126: ifeq -> 5166
/*    */     //   5129: aload_0
/*    */     //   5130: dup
/*    */     //   5131: aload_1
/*    */     //   5132: aload_0
/*    */     //   5133: aload_2
/*    */     //   5134: checkcast f/Ct
/*    */     //   5137: dup
/*    */     //   5138: astore_0
/*    */     //   5139: getfield X10 : Lf/cR;
/*    */     //   5142: astore_2
/*    */     //   5143: aload_1
/*    */     //   5144: aload_2
/*    */     //   5145: invokevirtual oA : (Lf/Gq0;Lf/cR;)V
/*    */     //   5148: aload_0
/*    */     //   5149: invokevirtual Um : (Lf/xc;)Lf/GC0;
/*    */     //   5152: pop
/*    */     //   5153: aload_1
/*    */     //   5154: aload_0
/*    */     //   5155: invokevirtual F00 : (Lf/Gq0;Ljava/lang/Iterable;)V
/*    */     //   5158: aload_1
/*    */     //   5159: aload_2
/*    */     //   5160: invokevirtual GG0 : (Lf/Gq0;Lf/cR;)V
/*    */     //   5163: goto -> 5191
/*    */     //   5166: ldc f/da
/*    */     //   5168: invokevirtual getName : ()Ljava/lang/String;
/*    */     //   5171: invokestatic getLogger : (Ljava/lang/String;)Ljava/util/logging/Logger;
/*    */     //   5174: aload_2
/*    */     //   5175: getstatic java/util/logging/Level.SEVERE : Ljava/util/logging/Level;
/*    */     //   5178: astore_0
/*    */     //   5179: invokevirtual getClass : ()Ljava/lang/Class;
/*    */     //   5182: astore_1
/*    */     //   5183: aload_0
/*    */     //   5184: ldc_w 'Unknown Element subclass: {0}'
/*    */     //   5187: aload_1
/*    */     //   5188: invokevirtual log : (Ljava/util/logging/Level;Ljava/lang/String;Ljava/lang/Object;)V
/*    */     //   5191: return
/*    */     // Line number table:
/*    */     //   Java source line number -> byte code offset
/*    */     //   #1	-> 3
/*    */     //   #2	-> 6
/*    */     //   #3	-> 11
/*    */     //   #4	-> 15
/*    */     //   #5	-> 18
/*    */     //   #6	-> 38
/*    */     //   #7	-> 42
/*    */     //   #8	-> 47
/*    */     //   #9	-> 78
/*    */     //   #10	-> 86
/*    */     //   #11	-> 97
/*    */     //   #12	-> 105
/*    */     //   #13	-> 121
/*    */     //   #14	-> 127
/*    */     //   #15	-> 135
/*    */     //   #16	-> 161
/*    */     //   #17	-> 166
/*    */     //   #18	-> 190
/*    */     //   #19	-> 195
/*    */     //   #20	-> 198
/*    */     //   #21	-> 230
/*    */     //   #22	-> 250
/*    */     //   #23	-> 294
/*    */     //   #24	-> 311
/*    */     //   #25	-> 336
/*    */     //   #26	-> 341
/*    */     //   #27	-> 366
/*    */     //   #28	-> 371
/*    */     //   #29	-> 374
/*    */     //   #30	-> 468
/*    */     //   #31	-> 613
/*    */     //   #32	-> 626
/*    */     //   #33	-> 669
/*    */     //   #34	-> 708
/*    */     //   #35	-> 718
/*    */     //   #36	-> 731
/*    */     //   #37	-> 734
/*    */     //   #38	-> 760
/*    */     //   #39	-> 763
/*    */     //   #40	-> 781
/*    */     //   #41	-> 791
/*    */     //   #42	-> 794
/*    */     //   #43	-> 851
/*    */     //   #44	-> 871
/*    */     //   #45	-> 908
/*    */     //   #46	-> 917
/*    */     //   #47	-> 981
/*    */     //   #48	-> 1014
/*    */     //   #49	-> 1020
/*    */     //   #50	-> 1026
/*    */     //   #51	-> 1089
/*    */     //   #52	-> 1095
/*    */     //   #53	-> 1101
/*    */     //   #54	-> 1174
/*    */     //   #55	-> 1177
/*    */     //   #56	-> 1205
/*    */     //   #57	-> 1231
/*    */     //   #58	-> 1234
/*    */     //   #59	-> 1240
/*    */     //   #60	-> 1245
/*    */     //   #61	-> 1248
/*    */     //   #62	-> 1295
/*    */     //   #63	-> 1301
/*    */     //   #64	-> 1373
/*    */     //   #65	-> 1376
/*    */     //   #66	-> 1421
/*    */     //   #67	-> 1522
/*    */     //   #68	-> 1530
/*    */     //   #69	-> 1554
/*    */     //   #70	-> 1567
/*    */     //   #71	-> 1609
/*    */     //   #72	-> 1622
/*    */     //   #73	-> 1655
/*    */     //   #74	-> 1662
/*    */     //   #75	-> 1716
/*    */     //   #76	-> 1721
/*    */     //   #77	-> 1799
/*    */     //   #78	-> 1812
/*    */     //   #79	-> 1815
/*    */     //   #80	-> 1855
/*    */     //   #81	-> 1867
/*    */     //   #82	-> 1871
/*    */     //   #83	-> 1874
/*    */     //   #84	-> 1890
/*    */     //   #85	-> 1893
/*    */     //   #86	-> 1921
/*    */     //   #87	-> 1927
/*    */     //   #88	-> 1978
/*    */     //   #89	-> 1981
/*    */     //   #90	-> 1984
/*    */     //   #91	-> 1987
/*    */     //   #92	-> 1998
/*    */     //   #93	-> 2010
/*    */     //   #94	-> 2018
/*    */     //   #95	-> 2027
/*    */     //   #96	-> 2032
/*    */     //   #97	-> 2035
/*    */     //   #98	-> 2063
/*    */     //   #99	-> 2104
/*    */     //   #100	-> 2113
/*    */     //   #101	-> 2169
/*    */     //   #102	-> 2185
/*    */     //   #103	-> 2190
/*    */     //   #104	-> 2235
/*    */     //   #105	-> 2240
/*    */     //   #106	-> 2285
/*    */     //   #107	-> 2289
/*    */     //   #108	-> 2317
/*    */     //   #109	-> 2330
/*    */     //   #110	-> 2335
/*    */     //   #111	-> 2366
/*    */     //   #112	-> 2374
/*    */     //   #113	-> 2385
/*    */     //   #114	-> 2393
/*    */     //   #115	-> 2424
/*    */     //   #116	-> 2432
/*    */     //   #117	-> 2437
/*    */     //   #118	-> 2442
/*    */     //   #119	-> 2452
/*    */     //   #120	-> 2458
/*    */     //   #121	-> 2466
/*    */     //   #122	-> 2488
/*    */     //   #123	-> 2523
/*    */     //   #124	-> 2578
/*    */     //   #125	-> 2592
/*    */     //   #126	-> 2598
/*    */     //   #127	-> 2679
/*    */     //   #128	-> 2690
/*    */     //   #129	-> 2762
/*    */     //   #130	-> 2779
/*    */     //   #131	-> 2785
/*    */     //   #132	-> 2832
/*    */     //   #133	-> 2838
/*    */     //   #134	-> 2885
/*    */     //   #135	-> 2890
/*    */     //   #136	-> 2930
/*    */     //   #137	-> 2962
/*    */     //   #138	-> 2970
/*    */     //   #139	-> 2975
/*    */     //   #140	-> 2980
/*    */     //   #141	-> 2985
/*    */     //   #142	-> 3017
/*    */     //   #143	-> 3037
/*    */     //   #144	-> 3045
/*    */     //   #145	-> 3062
/*    */     //   #146	-> 3070
/*    */     //   #147	-> 3177
/*    */     //   #148	-> 3185
/*    */     //   #149	-> 3191
/*    */     //   #150	-> 3196
/*    */     //   #151	-> 3201
/*    */     //   #152	-> 3206
/*    */     //   #153	-> 3251
/*    */     //   #154	-> 3264
/*    */     //   #155	-> 3269
/*    */     //   #156	-> 3274
/*    */     //   #157	-> 3327
/*    */     //   #158	-> 3335
/*    */     //   #159	-> 3346
/*    */     //   #160	-> 3354
/*    */     //   #161	-> 3803
/*    */     //   #162	-> 3820
/*    */     //   #163	-> 3828
/*    */     //   #164	-> 4142
/*    */     //   #165	-> 4150
/*    */     //   #166	-> 4194
/*    */     //   #167	-> 4213
/*    */     //   #168	-> 4219
/*    */     //   #169	-> 4227
/*    */     //   #170	-> 4239
/*    */     //   #171	-> 4244
/*    */     //   #172	-> 4247
/*    */     //   #173	-> 4276
/*    */     //   #174	-> 4343
/*    */     //   #175	-> 4354
/*    */     //   #176	-> 4363
/*    */     //   #177	-> 4371
/*    */     //   #178	-> 4425
/*    */     //   #179	-> 4441
/*    */     //   #180	-> 4471
/*    */     //   #181	-> 4477
/*    */     //   #182	-> 4483
/*    */     //   #183	-> 4491
/*    */     //   #184	-> 4504
/*    */     //   #185	-> 4512
/*    */     //   #186	-> 4606
/*    */     //   #187	-> 4615
/*    */     //   #188	-> 4645
/*    */     //   #189	-> 4652
/*    */     //   #190	-> 4749
/*    */     //   #191	-> 4763
/*    */     //   #192	-> 4818
/*    */     //   #193	-> 4826
/*    */     //   #194	-> 4834
/*    */     //   #195	-> 4839
/*    */     //   #196	-> 4879
/*    */     //   #197	-> 4884
/*    */     //   #198	-> 4928
/*    */     //   #199	-> 4931
/*    */     //   #200	-> 4943
/*    */     //   #201	-> 4967
/*    */     //   #202	-> 5025
/*    */     //   #203	-> 5038
/*    */     //   #204	-> 5043
/*    */     //   #205	-> 5046
/*    */     //   #206	-> 5050
/*    */     //   #207	-> 5053
/*    */     //   #208	-> 5059
/*    */     //   #209	-> 5064
/*    */     //   #210	-> 5067
/*    */     //   #211	-> 5090
/*    */     //   #212	-> 5096
/*    */     //   #213	-> 5116
/*    */     //   #214	-> 5123
/*    */     //   #215	-> 5139
/*    */     //   #216	-> 5145
/*    */     //   #217	-> 5166
/*    */   }
/*    */   
/*    */   public final void Gv0(Gq0 paramGq0, xc paramxc, GC0 paramGC0) {
/*    */     cR cR;
/*    */     e00 e002;
/*    */     Gj gj = (Gj)(cR = paramxc.X10).bw0(e002 = e00.FLOAT_POSITION).rI(e002);
/*    */     e00 e003;
/*    */     Sx0 sx0 = (Sx0)paramxc.X10.bw0(e003 = e00.DISPLAY).rI(e003);
/*    */     e00 e004 = e00.MARGIN_TOP;
/*    */     int m = paramGq0.MU;
/*    */     paramGC0.Zq = (short)Math.max(0, QE0(cR, e004, m, 0));
/*    */     e004 = e00.MARGIN_LEFT;
/*    */     m = paramGq0.MU;
/*    */     paramGC0.dv0 = (short)Math.max(0, QE0(cR, e004, m, 0));
/*    */     e004 = e00.MARGIN_RIGHT;
/*    */     m = paramGq0.MU;
/*    */     paramGC0.WS = (short)Math.max(0, QE0(cR, e004, m, 0));
/*    */     e004 = e00.MARGIN_BOTTOM;
/*    */     m = paramGq0.MU;
/*    */     paramGC0.Hr0 = (short)Math.max(0, QE0(cR, e004, m, 0));
/*    */     int j = paramGC0.tq0;
/*    */     e00 e005 = e00.WIDTH;
/*    */     int n = paramGq0.MU, i1 = paramGC0.J1;
/*    */     int k;
/*    */     if ((k = QE0(cR, e005, n, i1)) > 0) {
/*    */       if ((n = paramGC0.J1) > 0)
/*    */         j = k * paramGC0.tq0 / n; 
/*    */       paramGC0.J1 = k;
/*    */     } 
/*    */     e00 e001 = e00.HEIGHT;
/*    */     k = paramGC0.tq0;
/*    */     int i;
/*    */     if ((i = QE0(cR, this, k, j)) > 0)
/*    */       paramGC0.tq0 = i; 
/*    */     pe0(paramGq0, paramxc, paramGC0, gj, sx0);
/*    */   }
/*    */   
/*    */   public final pe VP(cR paramcR) {
/*    */     eL eL;
/*    */     e00 e00;
/*    */     if ((eL = (eL)paramcR.bw0(e00 = e00.FONT_FAMILIES).rI(e00)) != null && this.rM != null)
/*    */       do {
/*    */         nW nW1 = this.rM;
/*    */         pe pe1;
/*    */         if ((pe1 = ((q80)nW1).aa0(eL.F2)) != null)
/*    */           return pe1; 
/*    */       } while ((eL = eL.aF) != null); 
/*    */     return this.vh0;
/*    */   }
/*    */   
/*    */   public final mX qC0(String paramString) {
/*    */     mX mX;
/*    */     if ((mX = (mX)this.qO.get(paramString)) != null)
/*    */       return mX; 
/*    */     for (byte b = 0; b < this.Cc.size(); b++) {
/*    */       mX mX1;
/*    */       if ((mX1 = ((nh)this.Cc.get(b)).HM()) != null)
/*    */         return mX1; 
/*    */     } 
/*    */     nW nW1;
/*    */     return ((nW1 = this.Li0) != null) ? ((q80)this).w2(paramString) : null;
/*    */   }
/*    */   
/*    */   public final void oA(Gq0 paramGq0, cR paramcR) {
/*    */     e00 e00 = e00.MARGIN_TOP;
/*    */     int i = Math.max(0, QE0(paramcR, this, paramGq0.MU, 0));
/*    */     paramGq0.vA0(false);
/*    */     paramGq0.vA0(false);
/*    */     if ((i = paramGq0.qr0(i)) > paramGq0.wa0) {
/*    */       paramGq0.wa0 = i;
/*    */       ArrayList<?> arrayList;
/*    */       int j;
/*    */       for (j = (arrayList = paramGq0.lw).size(); j-- > 0;) {
/*    */         if (((GC0)get(j)).O80() <= paramGq0.wa0)
/*    */           remove(j); 
/*    */       } 
/*    */       for (j = (arrayList = paramGq0.ph).size(); j-- > 0;) {
/*    */         if (((GC0)get(j)).O80() <= paramGq0.wa0)
/*    */           remove(j); 
/*    */       } 
/*    */       paramGq0.f1();
/*    */     } 
/*    */   }
/*    */   
/*    */   public final void GG0(Gq0 paramGq0, cR paramcR) {
/*    */     e00 e00 = e00.MARGIN_BOTTOM;
/*    */     int i = Math.max(0, QE0(paramcR, this, paramGq0.MU, 0));
/*    */     if (paramGq0.Bz()) {
/*    */       paramGq0.hK0 = Math.max(paramGq0.hK0, paramGq0.wa0 + i);
/*    */     } else {
/*    */       paramGq0.vR = Math.max(paramGq0.vR, i);
/*    */     } 
/*    */   }
/*    */   
/*    */   public final Gq0 ol(yB paramyB, int paramInt1, int paramInt2, int paramInt3, Ct paramCt, String paramString, boolean paramBoolean) {
/*    */     // Byte code:
/*    */     //   0: aload_0
/*    */     //   1: dup
/*    */     //   2: dup
/*    */     //   3: aload #5
/*    */     //   5: getfield X10 : Lf/cR;
/*    */     //   8: dup
/*    */     //   9: astore #8
/*    */     //   11: getstatic f/e00.PADDING_TOP : Lf/e00;
/*    */     //   14: iload_2
/*    */     //   15: iconst_0
/*    */     //   16: invokevirtual QE0 : (Lf/cR;Lf/e00;II)I
/*    */     //   19: istore #9
/*    */     //   21: aload #8
/*    */     //   23: iconst_0
/*    */     //   24: iload #9
/*    */     //   26: invokestatic max : (II)I
/*    */     //   29: istore #9
/*    */     //   31: getstatic f/e00.PADDING_BOTTOM : Lf/e00;
/*    */     //   34: iload_2
/*    */     //   35: iconst_0
/*    */     //   36: invokevirtual QE0 : (Lf/cR;Lf/e00;II)I
/*    */     //   39: istore #10
/*    */     //   41: aload #8
/*    */     //   43: iconst_0
/*    */     //   44: iload #10
/*    */     //   46: invokestatic max : (II)I
/*    */     //   49: istore #10
/*    */     //   51: getstatic f/e00.MARGIN_BOTTOM : Lf/e00;
/*    */     //   54: iload_2
/*    */     //   55: iconst_0
/*    */     //   56: invokevirtual QE0 : (Lf/cR;Lf/e00;II)I
/*    */     //   59: iconst_0
/*    */     //   60: swap
/*    */     //   61: invokestatic max : (II)I
/*    */     //   64: istore_2
/*    */     //   65: new f/Gq0
/*    */     //   68: dup
/*    */     //   69: dup
/*    */     //   70: astore #11
/*    */     //   72: aload_0
/*    */     //   73: aload #11
/*    */     //   75: aload #5
/*    */     //   77: aload #11
/*    */     //   79: aload #8
/*    */     //   81: aload #11
/*    */     //   83: aload #6
/*    */     //   85: aload #11
/*    */     //   87: aload_0
/*    */     //   88: aload_1
/*    */     //   89: iload_3
/*    */     //   90: iload #4
/*    */     //   92: iload #9
/*    */     //   94: iload #7
/*    */     //   96: invokespecial <init> : (Lf/da;Lf/yB;IIIZ)V
/*    */     //   99: putfield rv0 : Ljava/lang/String;
/*    */     //   102: putfield az : Lf/cR;
/*    */     //   105: invokevirtual F00 : (Lf/Gq0;Ljava/lang/Iterable;)V
/*    */     //   108: invokevirtual b60 : ()V
/*    */     //   111: getfield wa0 : I
/*    */     //   114: iload #10
/*    */     //   116: iadd
/*    */     //   117: dup
/*    */     //   118: istore_3
/*    */     //   119: aload_0
/*    */     //   120: aload #8
/*    */     //   122: getstatic f/e00.HEIGHT : Lf/e00;
/*    */     //   125: iload_3
/*    */     //   126: dup
/*    */     //   127: invokevirtual QE0 : (Lf/cR;Lf/e00;II)I
/*    */     //   130: invokestatic max : (II)I
/*    */     //   133: dup
/*    */     //   134: istore_0
/*    */     //   135: iload_3
/*    */     //   136: if_icmple -> 373
/*    */     //   139: aload #8
/*    */     //   141: iconst_0
/*    */     //   142: istore #4
/*    */     //   144: getstatic f/e00.VERTICAL_ALIGNMENT : Lf/e00;
/*    */     //   147: dup
/*    */     //   148: astore #5
/*    */     //   150: invokevirtual bw0 : (Lf/e00;)Lf/cR;
/*    */     //   153: aload #5
/*    */     //   155: invokevirtual rI : (Lf/e00;)Ljava/lang/Object;
/*    */     //   158: checkcast f/Om0
/*    */     //   161: invokevirtual ordinal : ()I
/*    */     //   164: dup
/*    */     //   165: istore #5
/*    */     //   167: iconst_1
/*    */     //   168: if_icmpeq -> 194
/*    */     //   171: iload #5
/*    */     //   173: iconst_2
/*    */     //   174: if_icmpeq -> 186
/*    */     //   177: iload #5
/*    */     //   179: iconst_3
/*    */     //   180: if_icmpeq -> 194
/*    */     //   183: goto -> 201
/*    */     //   186: iload_0
/*    */     //   187: iload_3
/*    */     //   188: isub
/*    */     //   189: istore #4
/*    */     //   191: goto -> 201
/*    */     //   194: iload_0
/*    */     //   195: iload_3
/*    */     //   196: isub
/*    */     //   197: iconst_2
/*    */     //   198: idiv
/*    */     //   199: istore #4
/*    */     //   201: iload #4
/*    */     //   203: ifle -> 373
/*    */     //   206: aload_1
/*    */     //   207: iconst_0
/*    */     //   208: istore_3
/*    */     //   209: getfield la0 : Ljava/util/ArrayList;
/*    */     //   212: invokevirtual size : ()I
/*    */     //   215: istore #5
/*    */     //   217: iload_3
/*    */     //   218: iload #5
/*    */     //   220: if_icmpge -> 250
/*    */     //   223: aload_1
/*    */     //   224: getfield la0 : Ljava/util/ArrayList;
/*    */     //   227: iload_3
/*    */     //   228: invokevirtual get : (I)Ljava/lang/Object;
/*    */     //   231: checkcast f/GC0
/*    */     //   234: dup
/*    */     //   235: getfield Bm : I
/*    */     //   238: iload #4
/*    */     //   240: iadd
/*    */     //   241: putfield Bm : I
/*    */     //   244: iinc #3, 1
/*    */     //   247: goto -> 217
/*    */     //   250: aload_1
/*    */     //   251: getfield jX : [C
/*    */     //   254: dup
/*    */     //   255: astore_3
/*    */     //   256: arraylength
/*    */     //   257: ifle -> 373
/*    */     //   260: aload_3
/*    */     //   261: iconst_1
/*    */     //   262: caload
/*    */     //   263: ifne -> 280
/*    */     //   266: aload_3
/*    */     //   267: dup
/*    */     //   268: iconst_0
/*    */     //   269: caload
/*    */     //   270: iload #4
/*    */     //   272: iadd
/*    */     //   273: i2c
/*    */     //   274: iconst_0
/*    */     //   275: swap
/*    */     //   276: castore
/*    */     //   277: goto -> 373
/*    */     //   280: aload_3
/*    */     //   281: arraylength
/*    */     //   282: dup
/*    */     //   283: istore_3
/*    */     //   284: iconst_2
/*    */     //   285: iadd
/*    */     //   286: newarray char
/*    */     //   288: dup
/*    */     //   289: astore #5
/*    */     //   291: iload #4
/*    */     //   293: i2c
/*    */     //   294: iconst_0
/*    */     //   295: swap
/*    */     //   296: castore
/*    */     //   297: iconst_0
/*    */     //   298: istore #6
/*    */     //   300: iload #6
/*    */     //   302: iload_3
/*    */     //   303: if_icmpge -> 367
/*    */     //   306: aload_1
/*    */     //   307: getfield jX : [C
/*    */     //   310: dup
/*    */     //   311: astore #7
/*    */     //   313: iload #6
/*    */     //   315: caload
/*    */     //   316: dup
/*    */     //   317: istore #8
/*    */     //   319: ifle -> 329
/*    */     //   322: iload #8
/*    */     //   324: iload #4
/*    */     //   326: iadd
/*    */     //   327: istore #8
/*    */     //   329: aload #5
/*    */     //   331: aload #7
/*    */     //   333: iload #6
/*    */     //   335: aload #5
/*    */     //   337: iload #8
/*    */     //   339: iload #6
/*    */     //   341: iconst_2
/*    */     //   342: iadd
/*    */     //   343: istore #7
/*    */     //   345: i2c
/*    */     //   346: iload #7
/*    */     //   348: swap
/*    */     //   349: castore
/*    */     //   350: iinc #6, 3
/*    */     //   353: iconst_1
/*    */     //   354: iadd
/*    */     //   355: caload
/*    */     //   356: iload #6
/*    */     //   358: swap
/*    */     //   359: castore
/*    */     //   360: iload #7
/*    */     //   362: istore #6
/*    */     //   364: goto -> 300
/*    */     //   367: aload_1
/*    */     //   368: aload #5
/*    */     //   370: putfield jX : [C
/*    */     //   373: aload #11
/*    */     //   375: aload_1
/*    */     //   376: iload_2
/*    */     //   377: aload #11
/*    */     //   379: aload_1
/*    */     //   380: iload_0
/*    */     //   381: putfield tq0 : I
/*    */     //   384: getfield hK0 : I
/*    */     //   387: aload #11
/*    */     //   389: getfield wa0 : I
/*    */     //   392: isub
/*    */     //   393: invokestatic max : (II)I
/*    */     //   396: i2s
/*    */     //   397: putfield Hr0 : S
/*    */     //   400: areturn
/*    */     // Line number table:
/*    */     //   Java source line number -> byte code offset
/*    */     //   #1	-> 5
/*    */     //   #2	-> 11
/*    */     //   #3	-> 16
/*    */     //   #4	-> 31
/*    */     //   #5	-> 36
/*    */     //   #6	-> 51
/*    */     //   #7	-> 56
/*    */     //   #8	-> 65
/*    */     //   #9	-> 150
/*    */     //   #10	-> 158
/*    */     //   #11	-> 209
/*    */     //   #12	-> 381
/*    */   }
/*    */   
/*    */   public final void QQ(Gq0 paramGq0, Ct paramCt) {
/*    */     // Byte code:
/*    */     //   0: aload_2
/*    */     //   1: aload_1
/*    */     //   2: iconst_0
/*    */     //   3: invokevirtual vA0 : (Z)Z
/*    */     //   6: pop
/*    */     //   7: getfield X10 : Lf/cR;
/*    */     //   10: dup
/*    */     //   11: astore_3
/*    */     //   12: getstatic f/e00.FLOAT_POSITION : Lf/e00;
/*    */     //   15: dup
/*    */     //   16: astore #4
/*    */     //   18: invokevirtual bw0 : (Lf/e00;)Lf/cR;
/*    */     //   21: aload #4
/*    */     //   23: invokevirtual rI : (Lf/e00;)Ljava/lang/Object;
/*    */     //   26: checkcast f/Gj
/*    */     //   29: dup
/*    */     //   30: astore #4
/*    */     //   32: aload_0
/*    */     //   33: aload_3
/*    */     //   34: aload_1
/*    */     //   35: aload_0
/*    */     //   36: aload_3
/*    */     //   37: aload_1
/*    */     //   38: dup
/*    */     //   39: dup2
/*    */     //   40: aload_0
/*    */     //   41: aload_3
/*    */     //   42: aload_1
/*    */     //   43: aload_0
/*    */     //   44: aload_3
/*    */     //   45: aload_1
/*    */     //   46: aload_0
/*    */     //   47: aload_3
/*    */     //   48: aload_1
/*    */     //   49: aload_0
/*    */     //   50: aload_1
/*    */     //   51: aload_2
/*    */     //   52: invokevirtual lJ : (Lf/Gq0;Lf/xc;)Lf/m10;
/*    */     //   55: astore #5
/*    */     //   57: getstatic f/e00.MARGIN_TOP : Lf/e00;
/*    */     //   60: astore #6
/*    */     //   62: getfield MU : I
/*    */     //   65: aload #6
/*    */     //   67: swap
/*    */     //   68: iconst_0
/*    */     //   69: invokevirtual QE0 : (Lf/cR;Lf/e00;II)I
/*    */     //   72: iconst_0
/*    */     //   73: swap
/*    */     //   74: invokestatic max : (II)I
/*    */     //   77: istore #6
/*    */     //   79: getstatic f/e00.MARGIN_LEFT : Lf/e00;
/*    */     //   82: astore #7
/*    */     //   84: getfield MU : I
/*    */     //   87: aload #7
/*    */     //   89: swap
/*    */     //   90: iconst_0
/*    */     //   91: invokevirtual QE0 : (Lf/cR;Lf/e00;II)I
/*    */     //   94: iconst_0
/*    */     //   95: swap
/*    */     //   96: invokestatic max : (II)I
/*    */     //   99: istore #7
/*    */     //   101: getstatic f/e00.MARGIN_RIGHT : Lf/e00;
/*    */     //   104: astore #8
/*    */     //   106: getfield MU : I
/*    */     //   109: aload #8
/*    */     //   111: swap
/*    */     //   112: iconst_0
/*    */     //   113: invokevirtual QE0 : (Lf/cR;Lf/e00;II)I
/*    */     //   116: istore #8
/*    */     //   118: iload #7
/*    */     //   120: iconst_0
/*    */     //   121: iload #8
/*    */     //   123: invokestatic max : (II)I
/*    */     //   126: istore #8
/*    */     //   128: invokevirtual LD : (I)I
/*    */     //   131: istore #9
/*    */     //   133: iload #6
/*    */     //   135: invokevirtual qr0 : (I)I
/*    */     //   138: istore #6
/*    */     //   140: iload #8
/*    */     //   142: invokevirtual XS : (I)I
/*    */     //   145: iload #9
/*    */     //   147: isub
/*    */     //   148: iconst_0
/*    */     //   149: swap
/*    */     //   150: invokestatic max : (II)I
/*    */     //   153: istore #10
/*    */     //   155: getstatic f/e00.PADDING_LEFT : Lf/e00;
/*    */     //   158: astore #11
/*    */     //   160: getfield MU : I
/*    */     //   163: aload #11
/*    */     //   165: swap
/*    */     //   166: iconst_0
/*    */     //   167: invokevirtual QE0 : (Lf/cR;Lf/e00;II)I
/*    */     //   170: iconst_0
/*    */     //   171: swap
/*    */     //   172: invokestatic max : (II)I
/*    */     //   175: istore #11
/*    */     //   177: getstatic f/e00.PADDING_RIGHT : Lf/e00;
/*    */     //   180: astore #12
/*    */     //   182: getfield MU : I
/*    */     //   185: aload #12
/*    */     //   187: swap
/*    */     //   188: iconst_0
/*    */     //   189: invokevirtual QE0 : (Lf/cR;Lf/e00;II)I
/*    */     //   192: iconst_0
/*    */     //   193: swap
/*    */     //   194: invokestatic max : (II)I
/*    */     //   197: istore #12
/*    */     //   199: getstatic f/Gj.FC0 : Lf/Gj;
/*    */     //   202: dup
/*    */     //   203: astore #13
/*    */     //   205: if_acmpne -> 224
/*    */     //   208: aload_0
/*    */     //   209: getstatic f/e00.WIDTH : Lf/e00;
/*    */     //   212: aload_3
/*    */     //   213: swap
/*    */     //   214: iload #10
/*    */     //   216: dup
/*    */     //   217: invokevirtual QE0 : (Lf/cR;Lf/e00;II)I
/*    */     //   220: istore_3
/*    */     //   221: goto -> 325
/*    */     //   224: aload_0
/*    */     //   225: aload_1
/*    */     //   226: getstatic f/e00.WIDTH : Lf/e00;
/*    */     //   229: astore #14
/*    */     //   231: getfield MU : I
/*    */     //   234: istore #15
/*    */     //   236: aload_3
/*    */     //   237: aload #14
/*    */     //   239: iload #15
/*    */     //   241: ldc_w -2147483648
/*    */     //   244: invokevirtual QE0 : (Lf/cR;Lf/e00;II)I
/*    */     //   247: dup
/*    */     //   248: istore_3
/*    */     //   249: ldc_w -2147483648
/*    */     //   252: if_icmpne -> 325
/*    */     //   255: aload_0
/*    */     //   256: aload_1
/*    */     //   257: new f/yB
/*    */     //   260: dup
/*    */     //   261: astore_3
/*    */     //   262: aload_1
/*    */     //   263: aload_3
/*    */     //   264: aconst_null
/*    */     //   265: invokespecial <init> : (Lf/xc;)V
/*    */     //   268: getfield yl : I
/*    */     //   271: iload #11
/*    */     //   273: isub
/*    */     //   274: iload #12
/*    */     //   276: isub
/*    */     //   277: iconst_0
/*    */     //   278: swap
/*    */     //   279: invokestatic max : (II)I
/*    */     //   282: putfield J1 : I
/*    */     //   285: getfield MU : I
/*    */     //   288: aload_3
/*    */     //   289: swap
/*    */     //   290: iload #11
/*    */     //   292: iload #12
/*    */     //   294: aload_2
/*    */     //   295: aconst_null
/*    */     //   296: iconst_0
/*    */     //   297: invokevirtual ol : (Lf/yB;IIILf/Ct;Ljava/lang/String;Z)Lf/Gq0;
/*    */     //   300: astore #14
/*    */     //   302: aload_3
/*    */     //   303: aload #14
/*    */     //   305: iconst_0
/*    */     //   306: invokevirtual vA0 : (Z)Z
/*    */     //   309: pop
/*    */     //   310: getfield J1 : I
/*    */     //   313: aload #14
/*    */     //   315: getfield De : I
/*    */     //   318: isub
/*    */     //   319: iconst_0
/*    */     //   320: swap
/*    */     //   321: invokestatic max : (II)I
/*    */     //   324: istore_3
/*    */     //   325: aload #4
/*    */     //   327: aload #13
/*    */     //   329: iconst_0
/*    */     //   330: iload_3
/*    */     //   331: invokestatic max : (II)I
/*    */     //   334: iload #11
/*    */     //   336: iadd
/*    */     //   337: iload #12
/*    */     //   339: iadd
/*    */     //   340: istore_3
/*    */     //   341: if_acmpeq -> 388
/*    */     //   344: aload_1
/*    */     //   345: iload #8
/*    */     //   347: iload #6
/*    */     //   349: aload_1
/*    */     //   350: dup
/*    */     //   351: iload #7
/*    */     //   353: aload_1
/*    */     //   354: iload_3
/*    */     //   355: iload #7
/*    */     //   357: iload #8
/*    */     //   359: invokevirtual DF0 : (III)V
/*    */     //   362: invokevirtual LD : (I)I
/*    */     //   365: istore #9
/*    */     //   367: getfield wa0 : I
/*    */     //   370: invokestatic max : (II)I
/*    */     //   373: istore #6
/*    */     //   375: invokevirtual XS : (I)I
/*    */     //   378: iload #9
/*    */     //   380: isub
/*    */     //   381: iconst_0
/*    */     //   382: swap
/*    */     //   383: invokestatic max : (II)I
/*    */     //   386: istore #10
/*    */     //   388: aload #4
/*    */     //   390: iload_3
/*    */     //   391: iload #10
/*    */     //   393: invokestatic min : (II)I
/*    */     //   396: istore_3
/*    */     //   397: getstatic f/Gj.Df : Lf/Gj;
/*    */     //   400: dup
/*    */     //   401: astore #10
/*    */     //   403: if_acmpne -> 416
/*    */     //   406: aload_1
/*    */     //   407: iload #8
/*    */     //   409: invokevirtual XS : (I)I
/*    */     //   412: iload_3
/*    */     //   413: isub
/*    */     //   414: istore #9
/*    */     //   416: aload #4
/*    */     //   418: aload #13
/*    */     //   420: aload_1
/*    */     //   421: dup
/*    */     //   422: aload_0
/*    */     //   423: aload_1
/*    */     //   424: dup
/*    */     //   425: dup2
/*    */     //   426: new f/yB
/*    */     //   429: dup
/*    */     //   430: astore_0
/*    */     //   431: aload_1
/*    */     //   432: aload_0
/*    */     //   433: iload #8
/*    */     //   435: aload_0
/*    */     //   436: iload #7
/*    */     //   438: aload_0
/*    */     //   439: iload_3
/*    */     //   440: aload_0
/*    */     //   441: iload #6
/*    */     //   443: aload_0
/*    */     //   444: iload #9
/*    */     //   446: aload_0
/*    */     //   447: aload_2
/*    */     //   448: invokespecial <init> : (Lf/xc;)V
/*    */     //   451: putfield Iu : I
/*    */     //   454: putfield Bm : I
/*    */     //   457: putfield J1 : I
/*    */     //   460: i2s
/*    */     //   461: putfield dv0 : S
/*    */     //   464: i2s
/*    */     //   465: putfield WS : S
/*    */     //   468: getfield rv0 : Ljava/lang/String;
/*    */     //   471: putfield Gr : Ljava/lang/String;
/*    */     //   474: getfield mz : Ljava/util/ArrayList;
/*    */     //   477: aload_0
/*    */     //   478: invokevirtual add : (Ljava/lang/Object;)Z
/*    */     //   481: pop
/*    */     //   482: getfield MU : I
/*    */     //   485: istore #7
/*    */     //   487: getfield rv0 : Ljava/lang/String;
/*    */     //   490: astore #8
/*    */     //   492: getfield Jo : Z
/*    */     //   495: istore #13
/*    */     //   497: aload_0
/*    */     //   498: iload #7
/*    */     //   500: iload #11
/*    */     //   502: iload #12
/*    */     //   504: aload_2
/*    */     //   505: aload #8
/*    */     //   507: iload #13
/*    */     //   509: invokevirtual ol : (Lf/yB;IIILf/Ct;Ljava/lang/String;Z)Lf/Gq0;
/*    */     //   512: astore_2
/*    */     //   513: getfield mz : Ljava/util/ArrayList;
/*    */     //   516: invokevirtual size : ()I
/*    */     //   519: putfield L30 : I
/*    */     //   522: if_acmpne -> 731
/*    */     //   525: iload #6
/*    */     //   527: aload_0
/*    */     //   528: getfield tq0 : I
/*    */     //   531: iadd
/*    */     //   532: dup
/*    */     //   533: istore #4
/*    */     //   535: aload_1
/*    */     //   536: dup
/*    */     //   537: iconst_0
/*    */     //   538: invokevirtual vA0 : (Z)Z
/*    */     //   541: pop
/*    */     //   542: getfield wa0 : I
/*    */     //   545: if_icmple -> 664
/*    */     //   548: aload_1
/*    */     //   549: dup
/*    */     //   550: iload #4
/*    */     //   552: putfield wa0 : I
/*    */     //   555: getfield lw : Ljava/util/ArrayList;
/*    */     //   558: dup
/*    */     //   559: astore #4
/*    */     //   561: invokevirtual size : ()I
/*    */     //   564: istore #7
/*    */     //   566: iload #7
/*    */     //   568: dup
/*    */     //   569: iconst_m1
/*    */     //   570: iadd
/*    */     //   571: istore #7
/*    */     //   573: ifle -> 607
/*    */     //   576: aload #4
/*    */     //   578: iload #7
/*    */     //   580: invokevirtual get : (I)Ljava/lang/Object;
/*    */     //   583: checkcast f/GC0
/*    */     //   586: invokevirtual O80 : ()I
/*    */     //   589: aload_1
/*    */     //   590: getfield wa0 : I
/*    */     //   593: if_icmpgt -> 566
/*    */     //   596: aload #4
/*    */     //   598: iload #7
/*    */     //   600: invokevirtual remove : (I)Ljava/lang/Object;
/*    */     //   603: pop
/*    */     //   604: goto -> 566
/*    */     //   607: aload_1
/*    */     //   608: getfield ph : Ljava/util/ArrayList;
/*    */     //   611: dup
/*    */     //   612: astore #4
/*    */     //   614: invokevirtual size : ()I
/*    */     //   617: istore #7
/*    */     //   619: iload #7
/*    */     //   621: dup
/*    */     //   622: iconst_m1
/*    */     //   623: iadd
/*    */     //   624: istore #7
/*    */     //   626: ifle -> 660
/*    */     //   629: aload #4
/*    */     //   631: iload #7
/*    */     //   633: invokevirtual get : (I)Ljava/lang/Object;
/*    */     //   636: checkcast f/GC0
/*    */     //   639: invokevirtual O80 : ()I
/*    */     //   642: aload_1
/*    */     //   643: getfield wa0 : I
/*    */     //   646: if_icmpgt -> 619
/*    */     //   649: aload #4
/*    */     //   651: iload #7
/*    */     //   653: invokevirtual remove : (I)Ljava/lang/Object;
/*    */     //   656: pop
/*    */     //   657: goto -> 619
/*    */     //   660: aload_1
/*    */     //   661: invokevirtual f1 : ()V
/*    */     //   664: aload_1
/*    */     //   665: aload_0
/*    */     //   666: getfield Hr0 : S
/*    */     //   669: istore #4
/*    */     //   671: invokevirtual Bz : ()Z
/*    */     //   674: ifeq -> 698
/*    */     //   677: aload_1
/*    */     //   678: dup
/*    */     //   679: getfield hK0 : I
/*    */     //   682: aload_1
/*    */     //   683: getfield wa0 : I
/*    */     //   686: iload #4
/*    */     //   688: iadd
/*    */     //   689: invokestatic max : (II)I
/*    */     //   692: putfield hK0 : I
/*    */     //   695: goto -> 711
/*    */     //   698: aload_1
/*    */     //   699: dup
/*    */     //   700: getfield vR : I
/*    */     //   703: iload #4
/*    */     //   705: invokestatic max : (II)I
/*    */     //   708: putfield vR : I
/*    */     //   711: aload_1
/*    */     //   712: dup
/*    */     //   713: aload_2
/*    */     //   714: getfield De : I
/*    */     //   717: istore_1
/*    */     //   718: getfield De : I
/*    */     //   721: iload_1
/*    */     //   722: invokestatic min : (II)I
/*    */     //   725: putfield De : I
/*    */     //   728: goto -> 763
/*    */     //   731: aload #4
/*    */     //   733: aload #10
/*    */     //   735: if_acmpne -> 750
/*    */     //   738: aload_1
/*    */     //   739: getfield ph : Ljava/util/ArrayList;
/*    */     //   742: aload_0
/*    */     //   743: invokevirtual add : (Ljava/lang/Object;)Z
/*    */     //   746: pop
/*    */     //   747: goto -> 759
/*    */     //   750: aload_1
/*    */     //   751: getfield lw : Ljava/util/ArrayList;
/*    */     //   754: aload_0
/*    */     //   755: invokevirtual add : (Ljava/lang/Object;)Z
/*    */     //   758: pop
/*    */     //   759: aload_1
/*    */     //   760: invokevirtual f1 : ()V
/*    */     //   763: aload #5
/*    */     //   765: ifnull -> 803
/*    */     //   768: aload #5
/*    */     //   770: aload_0
/*    */     //   771: aload #5
/*    */     //   773: aload_0
/*    */     //   774: aload #5
/*    */     //   776: iload_3
/*    */     //   777: aload #5
/*    */     //   779: iload #6
/*    */     //   781: aload #5
/*    */     //   783: iload #9
/*    */     //   785: putfield Iu : I
/*    */     //   788: putfield Bm : I
/*    */     //   791: putfield J1 : I
/*    */     //   794: getfield tq0 : I
/*    */     //   797: putfield tq0 : I
/*    */     //   800: putfield RE0 : Lf/GC0;
/*    */     //   803: return
/*    */     // Line number table:
/*    */     //   Java source line number -> byte code offset
/*    */     //   #1	-> 7
/*    */     //   #2	-> 12
/*    */     //   #3	-> 18
/*    */     //   #4	-> 23
/*    */     //   #5	-> 26
/*    */     //   #6	-> 69
/*    */     //   #7	-> 79
/*    */     //   #8	-> 91
/*    */     //   #9	-> 101
/*    */     //   #10	-> 113
/*    */     //   #11	-> 128
/*    */     //   #12	-> 167
/*    */     //   #13	-> 177
/*    */     //   #14	-> 189
/*    */     //   #15	-> 199
/*    */     //   #16	-> 538
/*    */     //   #17	-> 555
/*    */     //   #18	-> 561
/*    */     //   #19	-> 608
/*    */     //   #20	-> 614
/*    */     //   #21	-> 661
/*    */     //   #22	-> 666
/*    */     //   #23	-> 671
/*    */     //   #24	-> 714
/*    */     //   #25	-> 718
/*    */     //   #26	-> 739
/*    */   }
/*    */   
/*    */   public final m10 lJ(Gq0 paramGq0, xc paramxc) {
/*    */     pRn pRn;
/*    */     cR cR;
/*    */     String str;
/*    */     e00 e00;
/*    */     if ((str = (String)(cR = paramxc.X10).bw0(e00 = e00.BACKGROUND_IMAGE).rI(e00)) != null) {
/*    */       mX mX = qC0(str);
/*    */     } else {
/*    */       str = null;
/*    */     } 
/*    */     if (str == null) {
/*    */       mX mX;
/*    */       e00 e001;
/*    */       if ((pRn = (pRn)cR.bw0(e001 = e00.BACKGROUND_COLOR).rI(e001)).cj() != 0 && (mX = qC0("white")) != null) {
/*    */         mX mX1 = rv0(pRn);
/*    */         e00 e002;
/*    */         pRn pRn1;
/*    */         if ((pRn1 = (pRn)cR.bw0(e002 = e00.BACKGROUND_COLOR_HOVER).rI(e002)) != null) {
/*    */           Sv0 sv0;
/*    */           vc vc1 = Bt;
/*    */           mX[] arrayOfMX;
/*    */           (arrayOfMX = new mX[2])[0] = rv0(pRn1);
/*    */           (new mX[2])[1] = mX1;
/*    */           this(vc1, null, arrayOfMX);
/*    */           mX1 = sv0;
/*    */         } 
/*    */       } else {
/*    */         pRn = null;
/*    */       } 
/*    */     } 
/*    */     if (pRn != null) {
/*    */       this(paramxc, (mX)pRn);
/*    */       this.Bm = paramGq0.wa0;
/*    */       paramGq0.fa.yb0.add(this);
/*    */       m10 m10;
/*    */       return m10 = new m10();
/*    */     } 
/*    */     return null;
/*    */   }
/*    */   
/*    */   public final String TI() {
/*    */     return "textarea";
/*    */   }
/*    */   
/*    */   public final void Ld(Zq0 paramZq0) {
/*    */     Zq0 zq0;
/*    */     if ((zq0 = this.COM9) != null) {
/*    */       D60 d60 = this.Ml0;
/*    */       ((zA)zq0).nq0(d60);
/*    */     } 
/*    */     this.COM9 = paramZq0;
/*    */     if (paramZq0 != null) {
/*    */       D60 d60 = this.Ml0;
/*    */       ((zA)paramZq0).Ac0(d60);
/*    */     } 
/*    */     this.COM4 = true;
/*    */     this.gk = null;
/*    */     MJ0();
/*    */   }
/*    */   
/*    */   public final void Kh0(LPt7 paramLPt7) {
/*    */     this.AU = (LPt7[])hm.LpT6((Object[])this.AU, paramLPt7, LPt7.class);
/*    */   }
/*    */   
/*    */   public final void Xw(nY paramnY) {
/*    */     super.Xw(paramnY);
/*    */     this.rM = q80.Uz("fonts");
/*    */     this.Li0 = q80.Uz("images");
/*    */     this.vh0 = q80.aa0("font");
/*    */     this.xP = q80.sL("mouseCursor");
/*    */     q80 q80;
/*    */     this.cE0 = (q80 = (q80)paramnY).sL("mouseCursor.link");
/*    */     this.COM4 = true;
/*    */     this.gk = null;
/*    */     MJ0();
/*    */   }
/*    */   
/*    */   public final void LM(throws paramthrows) {
/*    */     this.iL.G7.lg0(paramthrows);
/*    */     this.iL.YH.lg0(paramthrows);
/*    */   }
/*    */   
/*    */   public final void si(JG0 paramJG0, int paramInt) {
/*    */     throw new UnsupportedOperationException("use registerWidget");
/*    */   }
/*    */   
/*    */   public final void gx() {
/*    */     throw new UnsupportedOperationException("use registerWidget");
/*    */   }
/*    */   
/*    */   public final JG0 fG0(int paramInt) {
/*    */     throw new UnsupportedOperationException("use registerWidget");
/*    */   }
/*    */   
/*    */   public final int R80() {
/*    */     if (this.gk == null)
/*    */       xb0(); 
/*    */     int i;
/*    */     if ((i = this.gk.PO) >= 0)
/*    */       return i; 
/*    */     return qF();
/*    */   }
/*    */   
/*    */   public final int tJ0() {
/*    */     if (qF() == 0) {
/*    */       if (this.gk == null)
/*    */         xb0(); 
/*    */       int i;
/*    */       if ((i = this.gk.bJ0) >= 0)
/*    */         return i; 
/*    */     } 
/*    */     uW();
/*    */     return this.ta.tq0;
/*    */   }
/*    */   
/*    */   public final int J50() {
/*    */     short s = this.fu;
/*    */     return JG0.Fr(AW(), super.J50(), s);
/*    */   }
/*    */   
/*    */   public final void RI(int paramInt1, int paramInt2) {
/*    */     if (paramInt1 != this.fu) {
/*    */       this.gk = null;
/*    */       MJ0();
/*    */     } 
/*    */     super.RI(paramInt1, paramInt2);
/*    */   }
/*    */   
/*    */   public final void uh0(int paramInt1, int paramInt2) {
/*    */     if (paramInt1 != AW()) {
/*    */       this.gk = null;
/*    */       MJ0();
/*    */     } 
/*    */     super.uh0(paramInt1, paramInt2);
/*    */   }
/*    */   
/*    */   public void d40() {
/*    */     int i = qF();
/*    */     yB yB1;
/*    */     if ((yB1 = this.ta).J1 != i || this.COM4) {
/*    */       yB1.J1 = i;
/*    */       this.fq = true;
/*    */       this.COM4 = false;
/*    */       if ((null = this.Bo0) != null)
/*    */         null.IB0.getClass(); 
/*    */       try {
/*    */         Gq0 gq0;
/*    */         yB yB2;
/*    */         this.ta.WG();
/*    */         this.nG.clear();
/*    */         super.gx();
/*    */         this(this, this.ta, 0, 0, 0, true);
/*    */         Zq0 zq0;
/*    */         if ((zq0 = this.COM9) != null) {
/*    */           F00(gq0, zq0);
/*    */           gq0.b60();
/*    */           int k = RS();
/*    */           this.ta.IG0(k, e3());
/*    */           k = 0;
/*    */           boolean bool = false;
/*    */           ArrayList arrayList = this.nG;
/*    */           this.ta.NuL(k, bool, arrayList);
/*    */         } 
/*    */         Zq0();
/*    */         int j = gq0.wa0;
/*    */         this.fq = false;
/*    */         yB2.tq0 = j;
/*    */         return;
/*    */       } finally {
/*    */         this.fq = false;
/*    */       } 
/*    */     } 
/*    */   }
/*    */   
/*    */   public final void J00(throws paramthrows) {
/*    */     x8.sN = RS();
/*    */     x8.SW = e3();
/*    */     byte b;
/*    */     ArrayList<?> arrayList;
/*    */     X8 x8;
/*    */     int i;
/*    */     for ((x8 = this.iL).RB0 = paramthrows.IB0, b = 0, i = (arrayList = this.nG).size(); b < i; ) {
/*    */       ((m10)arrayList.get(b)).Zb(x8);
/*    */       b++;
/*    */     } 
/*    */     this.ta.Zb(x8);
/*    */   }
/*    */   
/*    */   public final void Gu() {
/*    */     if (!this.fq)
/*    */       MJ0(); 
/*    */   }
/*    */   
/*    */   public final void zE() {}
/*    */   
/*    */   public final void jA0() {
/*    */     super.jA0();
/*    */     this.ta.WG();
/*    */     this.nG.clear();
/*    */     super.gx();
/*    */     this.COM4 = true;
/*    */     this.gk = null;
/*    */     MJ0();
/*    */   }
/*    */   
/*    */   public final boolean i2(oa0 paramoa0) {
/*    */     // Byte code:
/*    */     //   0: aload_0
/*    */     //   1: aload_1
/*    */     //   2: invokespecial i2 : (Lf/oa0;)Z
/*    */     //   5: ifeq -> 10
/*    */     //   8: iconst_1
/*    */     //   9: ireturn
/*    */     //   10: aload_1
/*    */     //   11: getfield cz0 : I
/*    */     //   14: dup
/*    */     //   15: istore_2
/*    */     //   16: invokestatic Pg : (I)Z
/*    */     //   19: ifeq -> 281
/*    */     //   22: aload_0
/*    */     //   23: getfield Z5 : Z
/*    */     //   26: ifeq -> 82
/*    */     //   29: aload_1
/*    */     //   30: invokevirtual Ud : ()Z
/*    */     //   33: ifeq -> 80
/*    */     //   36: aload_0
/*    */     //   37: dup
/*    */     //   38: aload_1
/*    */     //   39: aload_0
/*    */     //   40: aload_1
/*    */     //   41: aload_0
/*    */     //   42: dup
/*    */     //   43: aload_1
/*    */     //   44: dup
/*    */     //   45: aload_0
/*    */     //   46: iconst_0
/*    */     //   47: putfield Z5 : Z
/*    */     //   50: getfield aK : I
/*    */     //   53: istore_0
/*    */     //   54: getfield gk0 : I
/*    */     //   57: iload_0
/*    */     //   58: swap
/*    */     //   59: invokevirtual mu0 : (II)Z
/*    */     //   62: putfield h1 : Z
/*    */     //   65: getfield aK : I
/*    */     //   68: putfield qk0 : I
/*    */     //   71: getfield gk0 : I
/*    */     //   74: putfield fV : I
/*    */     //   77: invokevirtual Zq0 : ()V
/*    */     //   80: iconst_1
/*    */     //   81: ireturn
/*    */     //   82: iload_2
/*    */     //   83: aload_0
/*    */     //   84: dup
/*    */     //   85: aload_1
/*    */     //   86: aload_0
/*    */     //   87: aload_1
/*    */     //   88: aload_0
/*    */     //   89: dup
/*    */     //   90: aload_1
/*    */     //   91: dup
/*    */     //   92: getfield aK : I
/*    */     //   95: istore_1
/*    */     //   96: getfield gk0 : I
/*    */     //   99: iload_1
/*    */     //   100: swap
/*    */     //   101: invokevirtual mu0 : (II)Z
/*    */     //   104: putfield h1 : Z
/*    */     //   107: getfield aK : I
/*    */     //   110: putfield qk0 : I
/*    */     //   113: getfield gk0 : I
/*    */     //   116: putfield fV : I
/*    */     //   119: invokevirtual Zq0 : ()V
/*    */     //   122: bipush #8
/*    */     //   124: if_icmpne -> 129
/*    */     //   127: iconst_0
/*    */     //   128: ireturn
/*    */     //   129: iload_2
/*    */     //   130: iconst_3
/*    */     //   131: istore_1
/*    */     //   132: bipush #6
/*    */     //   134: if_icmpne -> 168
/*    */     //   137: getstatic f/da.Zu : Z
/*    */     //   140: ifne -> 161
/*    */     //   143: aload_0
/*    */     //   144: getfield Z5 : Z
/*    */     //   147: ifne -> 153
/*    */     //   150: goto -> 161
/*    */     //   153: new java/lang/AssertionError
/*    */     //   156: dup
/*    */     //   157: invokespecial <init> : ()V
/*    */     //   160: athrow
/*    */     //   161: aload_0
/*    */     //   162: iconst_1
/*    */     //   163: putfield Z5 : Z
/*    */     //   166: iconst_1
/*    */     //   167: ireturn
/*    */     //   168: aload_0
/*    */     //   169: getfield lw0 : Lf/GC0;
/*    */     //   172: ifnull -> 222
/*    */     //   175: iload_2
/*    */     //   176: iconst_5
/*    */     //   177: if_icmpeq -> 190
/*    */     //   180: iload_2
/*    */     //   181: iload_1
/*    */     //   182: if_icmpeq -> 190
/*    */     //   185: iload_2
/*    */     //   186: iconst_4
/*    */     //   187: if_icmpne -> 222
/*    */     //   190: aload_0
/*    */     //   191: getfield AU : [Lf/LPt7;
/*    */     //   194: dup
/*    */     //   195: astore_1
/*    */     //   196: ifnull -> 222
/*    */     //   199: aload_1
/*    */     //   200: arraylength
/*    */     //   201: istore_3
/*    */     //   202: iconst_0
/*    */     //   203: istore #4
/*    */     //   205: iload #4
/*    */     //   207: iload_3
/*    */     //   208: if_icmpge -> 222
/*    */     //   211: aload_1
/*    */     //   212: iload #4
/*    */     //   214: aaload
/*    */     //   215: pop
/*    */     //   216: iinc #4, 1
/*    */     //   219: goto -> 205
/*    */     //   222: iload_2
/*    */     //   223: iconst_5
/*    */     //   224: if_icmpne -> 279
/*    */     //   227: aload_0
/*    */     //   228: getfield lw0 : Lf/GC0;
/*    */     //   231: dup
/*    */     //   232: astore_1
/*    */     //   233: ifnull -> 279
/*    */     //   236: aload_1
/*    */     //   237: getfield Gr : Ljava/lang/String;
/*    */     //   240: dup
/*    */     //   241: astore_1
/*    */     //   242: ifnull -> 279
/*    */     //   245: aload_0
/*    */     //   246: getfield AU : [Lf/LPt7;
/*    */     //   249: dup
/*    */     //   250: astore_0
/*    */     //   251: ifnull -> 279
/*    */     //   254: aload_0
/*    */     //   255: arraylength
/*    */     //   256: istore_2
/*    */     //   257: iconst_0
/*    */     //   258: istore_3
/*    */     //   259: iload_3
/*    */     //   260: iload_2
/*    */     //   261: if_icmpge -> 279
/*    */     //   264: aload_0
/*    */     //   265: iload_3
/*    */     //   266: aaload
/*    */     //   267: aload_1
/*    */     //   268: invokeinterface G80 : (Ljava/lang/String;)V
/*    */     //   273: iinc #3, 1
/*    */     //   276: goto -> 259
/*    */     //   279: iconst_1
/*    */     //   280: ireturn
/*    */     //   281: iconst_0
/*    */     //   282: ireturn
/*    */     // Line number table:
/*    */     //   Java source line number -> byte code offset
/*    */     //   #1	-> 11
/*    */     //   #2	-> 23
/*    */     //   #3	-> 50
/*    */     //   #4	-> 54
/*    */     //   #5	-> 59
/*    */     //   #6	-> 62
/*    */     //   #7	-> 65
/*    */     //   #8	-> 68
/*    */     //   #9	-> 71
/*    */     //   #10	-> 74
/*    */     //   #11	-> 92
/*    */     //   #12	-> 96
/*    */     //   #13	-> 101
/*    */     //   #14	-> 104
/*    */     //   #15	-> 107
/*    */     //   #16	-> 110
/*    */     //   #17	-> 113
/*    */     //   #18	-> 116
/*    */     //   #19	-> 137
/*    */   }
/*    */   
/*    */   public final Object t2(int paramInt1, int paramInt2) {
/*    */     xc xc;
/*    */     GC0 gC0;
/*    */     if ((gC0 = this.lw0) != null && xc = gC0.pM instanceof Cp)
/*    */       return ((Cp)xc).EH; 
/*    */     return super.t2(paramInt1, paramInt2);
/*    */   }
/*    */   
/*    */   public final int QE0(cR paramcR, e00 parame00, int paramInt1, int paramInt2) {
/*    */     pe pe1 = null;
/*    */     Ok ok;
/*    */     if (FJ.Qh((ok = (Ok)(paramcR = paramcR.bw0(parame00)).rI(parame00)).hW)) {
/*    */       if (parame00 == e00.FONT_SIZE && (paramcR = paramcR.g8) == null)
/*    */         return 14; 
/*    */       if ((pe1 = VP(paramcR)) == null)
/*    */         return 0; 
/*    */     } 
/*    */     float f = ok.QK0;
/*    */     switch (Zk0.yE(ok.hW)) {
/*    */       case 5:
/*    */         return paramInt2;
/*    */       case 4:
/*    */         f = paramInt1 * 0.01F * f;
/*    */         break;
/*    */       case 3:
/*    */         f *= ((t90)pe1).getEX();
/*    */         break;
/*    */       case 2:
/*    */         f *= ((t90)pe1).getEM();
/*    */         break;
/*    */       case 1:
/*    */         f *= 1.33F;
/*    */         break;
/*    */     } 
/*    */     return (f >= 32767.0F) ? 32767 : ((f <= -32768.0F) ? -32768 : Math.round(f));
/*    */   }
/*    */   
/*    */   public final void t30() {}
/*    */   
/*    */   public final void HK0() {}
/*    */   
/*    */   public final void Dc0(Ap paramAp, String paramString) {
/*    */     if (paramString != null) {
/*    */       if (paramAp.fr0 == null) {
/*    */         if (!this.Ca.containsKey(paramString) && !this.bm0.containsKey(paramString)) {
/*    */           if (!this.Ca.containsValue(paramAp)) {
/*    */             this.Ca.put(paramString, paramAp);
/*    */             return;
/*    */           } 
/*    */           throw new IllegalArgumentException("widget already registered");
/*    */         } 
/*    */         throw new IllegalArgumentException("widget name already in registered");
/*    */       } 
/*    */       throw new IllegalArgumentException("Widget must not have a parent");
/*    */     } 
/*    */     throw new NullPointerException("name");
/*    */   } }


/* Location:              /Users/vnnsnnt/Documents/Codespace/JavaWorkspace/RedTrainer/src/main/java/org/trainer/client/PokeMMO.jar!/f/da.class
 * Java compiler version: 8 (52.0)
 * JD-Core Version:       1.1.3
 */