/* 1 */ package f;public final class DD implements Runnable { private void Ug0(pA parampA, j40 paramj40) { parampA
/* 2 */       .Um(paramj40.Jg); JG0 jG0;
/* 3 */     if (km.XU() && (jG0 = this.C0.FX) != null && this
/* 4 */       .dP && this
/* 5 */       .kN)
/* 6 */       VA0.c90(this);  }
/*   */ 
/*   */   
/*   */   public DD(M60 paramM60, WD paramWD, boolean paramBoolean, j40 paramj40, Fy0[] paramArrayOfFy0, int paramInt, pA parampA) {}
/*   */   
/*   */   public final void run() {
/*   */     // Byte code:
/*   */     //   0: aload_0
/*   */     //   1: getfield EL : Lf/WD;
/*   */     //   4: getfield HA : S
/*   */     //   7: aload_0
/*   */     //   8: getfield HX : Z
/*   */     //   11: invokestatic CE0 : (SZ)Z
/*   */     //   14: ifeq -> 92
/*   */     //   17: aload_0
/*   */     //   18: getstatic f/js.vu0 : Lf/js;
/*   */     //   21: astore_1
/*   */     //   22: getfield C0 : Lf/M60;
/*   */     //   25: aload_1
/*   */     //   26: aload_0
/*   */     //   27: dup
/*   */     //   28: dup
/*   */     //   29: dup2
/*   */     //   30: getfield w20 : Lf/j40;
/*   */     //   33: astore_1
/*   */     //   34: getfield EL : Lf/WD;
/*   */     //   37: getfield HA : S
/*   */     //   40: istore_2
/*   */     //   41: getfield QW : [Lf/Fy0;
/*   */     //   44: aload_0
/*   */     //   45: getfield P1 : I
/*   */     //   48: aaload
/*   */     //   49: dup
/*   */     //   50: dup
/*   */     //   51: astore_0
/*   */     //   52: getfield Kd : I
/*   */     //   55: aload_0
/*   */     //   56: getfield xY : I
/*   */     //   59: iadd
/*   */     //   60: istore_0
/*   */     //   61: getfield er0 : I
/*   */     //   64: istore_3
/*   */     //   65: getfield c4 : Lf/pA;
/*   */     //   68: aload_1
/*   */     //   69: <illegal opcode> run : (Lf/DD;Lf/pA;Lf/j40;)Ljava/lang/Runnable;
/*   */     //   74: astore #4
/*   */     //   76: invokevirtual getClass : ()Ljava/lang/Class;
/*   */     //   79: pop
/*   */     //   80: aload_1
/*   */     //   81: iload_2
/*   */     //   82: iload_0
/*   */     //   83: iload_3
/*   */     //   84: aload #4
/*   */     //   86: invokestatic yC0 : (Lf/JG0;Lf/j40;SIILjava/lang/Runnable;)V
/*   */     //   89: goto -> 225
/*   */     //   92: aload_0
/*   */     //   93: dup
/*   */     //   94: getstatic f/km.u4 : Lf/R8;
/*   */     //   97: astore_1
/*   */     //   98: getfield w20 : Lf/j40;
/*   */     //   101: getfield Jg : I
/*   */     //   104: istore_2
/*   */     //   105: getfield EL : Lf/WD;
/*   */     //   108: getfield HA : S
/*   */     //   111: dup
/*   */     //   112: istore_3
/*   */     //   113: iconst_0
/*   */     //   114: istore #4
/*   */     //   116: iconst_0
/*   */     //   117: istore #5
/*   */     //   119: bipush #19
/*   */     //   121: if_icmpne -> 154
/*   */     //   124: aload_1
/*   */     //   125: dup
/*   */     //   126: invokevirtual getClass : ()Ljava/lang/Class;
/*   */     //   129: pop
/*   */     //   130: iconst_1
/*   */     //   131: istore_1
/*   */     //   132: aconst_null
/*   */     //   133: astore_2
/*   */     //   134: getfield YG0 : Lf/js;
/*   */     //   137: getfield MH0 : Lf/pA;
/*   */     //   140: dup
/*   */     //   141: astore_3
/*   */     //   142: ifnull -> 174
/*   */     //   145: aload_3
/*   */     //   146: iload_1
/*   */     //   147: aload_2
/*   */     //   148: invokevirtual U10 : (ZLf/R2;)V
/*   */     //   151: goto -> 174
/*   */     //   154: aload_1
/*   */     //   155: getfield e20 : Lf/c4;
/*   */     //   158: new f/NH
/*   */     //   161: dup
/*   */     //   162: iload_2
/*   */     //   163: iload #4
/*   */     //   165: iload #5
/*   */     //   167: iload_3
/*   */     //   168: invokespecial <init> : (IIIS)V
/*   */     //   171: invokevirtual W3 : (Lf/Bi;)V
/*   */     //   174: invokestatic XU : ()Z
/*   */     //   177: ifeq -> 225
/*   */     //   180: aload_0
/*   */     //   181: dup
/*   */     //   182: getfield c4 : Lf/pA;
/*   */     //   185: aload_0
/*   */     //   186: getfield w20 : Lf/j40;
/*   */     //   189: getfield Jg : I
/*   */     //   192: invokevirtual Um : (I)V
/*   */     //   195: getfield C0 : Lf/M60;
/*   */     //   198: getfield FX : Lf/JG0;
/*   */     //   201: dup
/*   */     //   202: astore_0
/*   */     //   203: ifnull -> 225
/*   */     //   206: aload_0
/*   */     //   207: getfield dP : Z
/*   */     //   210: ifeq -> 225
/*   */     //   213: aload_0
/*   */     //   214: getfield kN : Z
/*   */     //   217: ifeq -> 225
/*   */     //   220: aload_0
/*   */     //   221: invokestatic c90 : (Lf/JG0;)Z
/*   */     //   224: pop
/*   */     //   225: return
/*   */     // Line number table:
/*   */     //   Java source line number -> byte code offset
/*   */     //   #1	-> 4
/*   */     //   #2	-> 8
/*   */     //   #3	-> 18
/*   */     //   #4	-> 22
/*   */     //   #5	-> 37
/*   */     //   #6	-> 41
/*   */     //   #7	-> 52
/*   */     //   #8	-> 56
/*   */     //   #9	-> 61
/*   */     //   #10	-> 65
/*   */     //   #11	-> 101
/*   */     //   #12	-> 105
/*   */     //   #13	-> 108
/*   */     //   #14	-> 126
/*   */     //   #15	-> 134
/*   */     //   #16	-> 137
/*   */     //   #17	-> 148
/*   */     //   #18	-> 155
/*   */     //   #19	-> 158
/*   */     //   #20	-> 174
/*   */     //   #21	-> 189
/*   */     //   #22	-> 192
/*   */     //   #23	-> 198
/*   */     //   #24	-> 207
/*   */     //   #25	-> 214
/*   */     //   #26	-> 221
/*   */   } }


/* Location:              /Users/vnnsnnt/Documents/Codespace/JavaWorkspace/RedTrainer/src/main/java/org/trainer/client/PokeMMO.jar!/f/DD.class
 * Java compiler version: 8 (52.0)
 * JD-Core Version:       1.1.3
 */