/*  1 */ package f;public final class Dk extends Ip implements r60 { public final Bf az0; public int cOn; public int Wj; public Un[] M30; public final Ip bp; public static boolean Ws(hm0 paramhm0, j40 paramj40) { return 
/*    */ 
/*    */       
/*  4 */       (paramj40.Jg == paramhm0.K0.ta.q10); }
/*    */   public vT[] aF0;
/*    */   public final dQ Dm; public p30 UH; public Dk(Bf paramBf, LPT3 paramLPT3, int paramInt, boolean paramBoolean) { // Byte code:
/*    */     //   0: aload_1
/*    */     //   1: aload_0
/*    */     //   2: aload_1
/*    */     //   3: aload_0
/*    */     //   4: dup
/*    */     //   5: dup
/*    */     //   6: invokespecial <init> : ()V
/*    */     //   9: iconst_0
/*    */     //   10: putfield Wj : I
/*    */     //   13: iconst_0
/*    */     //   14: anewarray f/Un
/*    */     //   17: putfield M30 : [Lf/Un;
/*    */     //   20: putfield az0 : Lf/Bf;
/*    */     //   23: invokeinterface sU : ()Z
/*    */     //   28: ifeq -> 38
/*    */     //   31: ldc 'battle-panel-dark'
/*    */     //   33: astore #5
/*    */     //   35: goto -> 42
/*    */     //   38: ldc 'hud-panel-invis'
/*    */     //   40: astore #5
/*    */     //   42: iload #4
/*    */     //   44: aload_0
/*    */     //   45: aload #5
/*    */     //   47: invokevirtual Xu : (Ljava/lang/String;)V
/*    */     //   50: new f/dQ
/*    */     //   53: astore #5
/*    */     //   55: getstatic f/F40.ef0 : Lf/F40;
/*    */     //   58: astore #6
/*    */     //   60: sipush #157
/*    */     //   63: istore #7
/*    */     //   65: ifeq -> 75
/*    */     //   68: bipush #12
/*    */     //   70: istore #8
/*    */     //   72: goto -> 79
/*    */     //   75: bipush #13
/*    */     //   77: istore #8
/*    */     //   79: aload_0
/*    */     //   80: dup
/*    */     //   81: dup
/*    */     //   82: aload #5
/*    */     //   84: dup
/*    */     //   85: aload #6
/*    */     //   87: iload #7
/*    */     //   89: iload #8
/*    */     //   91: invokestatic Qf0 : (Lf/F40;II)Ljava/lang/String;
/*    */     //   94: invokespecial <init> : (Ljava/lang/String;)V
/*    */     //   97: putfield Dm : Lf/dQ;
/*    */     //   100: new f/Ip
/*    */     //   103: dup
/*    */     //   104: invokespecial <init> : ()V
/*    */     //   107: putfield bp : Lf/Ip;
/*    */     //   110: bipush #6
/*    */     //   112: anewarray f/vT
/*    */     //   115: putfield aF0 : [Lf/vT;
/*    */     //   118: new java/util/ArrayList
/*    */     //   121: dup
/*    */     //   122: astore #5
/*    */     //   124: invokespecial <init> : ()V
/*    */     //   127: iconst_0
/*    */     //   128: istore #6
/*    */     //   130: getstatic f/km.MR : Lf/Gp0;
/*    */     //   133: dup
/*    */     //   134: astore #7
/*    */     //   136: ifnull -> 146
/*    */     //   139: aload #7
/*    */     //   141: invokevirtual hG0 : ()B
/*    */     //   144: istore #6
/*    */     //   146: aload_2
/*    */     //   147: aload_1
/*    */     //   148: getstatic f/km.u4 : Lf/R8;
/*    */     //   151: invokevirtual dl0 : ()Lf/Uc0;
/*    */     //   154: astore #8
/*    */     //   156: invokeinterface sU : ()Z
/*    */     //   161: invokevirtual default : (Z)Lf/dv;
/*    */     //   164: invokevirtual ordinal : ()I
/*    */     //   167: dup
/*    */     //   168: istore #9
/*    */     //   170: iconst_5
/*    */     //   171: if_icmpeq -> 421
/*    */     //   174: iload #9
/*    */     //   176: bipush #6
/*    */     //   178: if_icmpeq -> 344
/*    */     //   181: iconst_0
/*    */     //   182: istore #9
/*    */     //   184: iload #9
/*    */     //   186: bipush #6
/*    */     //   188: if_icmpge -> 223
/*    */     //   191: aload #8
/*    */     //   193: iload #9
/*    */     //   195: i2s
/*    */     //   196: invokevirtual ky : (S)Lf/j40;
/*    */     //   199: dup
/*    */     //   200: astore #10
/*    */     //   202: ifnull -> 213
/*    */     //   205: aload #5
/*    */     //   207: aload #10
/*    */     //   209: invokevirtual add : (Ljava/lang/Object;)Z
/*    */     //   212: pop
/*    */     //   213: iload #9
/*    */     //   215: iconst_1
/*    */     //   216: iadd
/*    */     //   217: i2b
/*    */     //   218: istore #9
/*    */     //   220: goto -> 184
/*    */     //   223: aload_1
/*    */     //   224: invokeinterface sU : ()Z
/*    */     //   229: ifeq -> 504
/*    */     //   232: aload #7
/*    */     //   234: ifnull -> 504
/*    */     //   237: aload #7
/*    */     //   239: iload #6
/*    */     //   241: invokevirtual wB : (B)Lf/QZ;
/*    */     //   244: instanceof f/X10
/*    */     //   247: ifeq -> 504
/*    */     //   250: aload #7
/*    */     //   252: iload #6
/*    */     //   254: invokevirtual S10 : (B)[Lf/hm0;
/*    */     //   257: dup
/*    */     //   258: astore #6
/*    */     //   260: arraylength
/*    */     //   261: istore #7
/*    */     //   263: iconst_0
/*    */     //   264: istore #8
/*    */     //   266: iload #8
/*    */     //   268: iload #7
/*    */     //   270: if_icmpge -> 504
/*    */     //   273: aload #6
/*    */     //   275: iload #8
/*    */     //   277: aaload
/*    */     //   278: dup
/*    */     //   279: astore #9
/*    */     //   281: ifnull -> 338
/*    */     //   284: aload #9
/*    */     //   286: invokevirtual wh0 : ()Z
/*    */     //   289: ifeq -> 295
/*    */     //   292: goto -> 338
/*    */     //   295: aload #5
/*    */     //   297: invokeinterface stream : ()Ljava/util/stream/Stream;
/*    */     //   302: aload #9
/*    */     //   304: <illegal opcode> test : (Lf/hm0;)Ljava/util/function/Predicate;
/*    */     //   309: invokeinterface noneMatch : (Ljava/util/function/Predicate;)Z
/*    */     //   314: ifeq -> 338
/*    */     //   317: aload #5
/*    */     //   319: new f/j40
/*    */     //   322: dup
/*    */     //   323: aload #9
/*    */     //   325: invokevirtual k6 : ()Lf/jd0;
/*    */     //   328: invokevirtual w70 : ()Lf/Q90;
/*    */     //   331: invokespecial <init> : (Lf/Q90;)V
/*    */     //   334: invokevirtual add : (Ljava/lang/Object;)Z
/*    */     //   337: pop
/*    */     //   338: iinc #8, 1
/*    */     //   341: goto -> 266
/*    */     //   344: aload #7
/*    */     //   346: ifnonnull -> 352
/*    */     //   349: goto -> 504
/*    */     //   352: aload #7
/*    */     //   354: invokevirtual N00 : ()Lf/mJ;
/*    */     //   357: dup
/*    */     //   358: astore #6
/*    */     //   360: ifnonnull -> 366
/*    */     //   363: goto -> 504
/*    */     //   366: aload #7
/*    */     //   368: aload #6
/*    */     //   370: dup
/*    */     //   371: invokevirtual aR : ()B
/*    */     //   374: istore #6
/*    */     //   376: invokevirtual F90 : ()B
/*    */     //   379: iload #6
/*    */     //   381: swap
/*    */     //   382: invokevirtual N0 : (BB)Lf/hm0;
/*    */     //   385: dup
/*    */     //   386: astore #6
/*    */     //   388: ifnonnull -> 394
/*    */     //   391: goto -> 504
/*    */     //   394: aload #8
/*    */     //   396: aload #6
/*    */     //   398: invokevirtual ih : ()I
/*    */     //   401: invokevirtual de0 : (I)Lf/j40;
/*    */     //   404: dup
/*    */     //   405: astore #6
/*    */     //   407: ifnull -> 504
/*    */     //   410: aload #5
/*    */     //   412: aload #6
/*    */     //   414: invokevirtual add : (Ljava/lang/Object;)Z
/*    */     //   417: pop
/*    */     //   418: goto -> 504
/*    */     //   421: aload #7
/*    */     //   423: ifnonnull -> 429
/*    */     //   426: goto -> 504
/*    */     //   429: aload #7
/*    */     //   431: iload #6
/*    */     //   433: invokevirtual S10 : (B)[Lf/hm0;
/*    */     //   436: dup
/*    */     //   437: astore #6
/*    */     //   439: arraylength
/*    */     //   440: istore #7
/*    */     //   442: iconst_0
/*    */     //   443: istore #9
/*    */     //   445: iload #9
/*    */     //   447: iload #7
/*    */     //   449: if_icmpge -> 504
/*    */     //   452: aload #6
/*    */     //   454: iload #9
/*    */     //   456: aaload
/*    */     //   457: dup
/*    */     //   458: astore #10
/*    */     //   460: ifnull -> 498
/*    */     //   463: aload #10
/*    */     //   465: invokevirtual wh0 : ()Z
/*    */     //   468: ifeq -> 474
/*    */     //   471: goto -> 498
/*    */     //   474: aload #8
/*    */     //   476: aload #10
/*    */     //   478: invokevirtual ih : ()I
/*    */     //   481: invokevirtual de0 : (I)Lf/j40;
/*    */     //   484: dup
/*    */     //   485: astore #10
/*    */     //   487: ifnull -> 498
/*    */     //   490: aload #5
/*    */     //   492: aload #10
/*    */     //   494: invokevirtual add : (Ljava/lang/Object;)Z
/*    */     //   497: pop
/*    */     //   498: iinc #9, 1
/*    */     //   501: goto -> 445
/*    */     //   504: iconst_0
/*    */     //   505: istore #6
/*    */     //   507: iload #6
/*    */     //   509: aload_0
/*    */     //   510: getfield aF0 : [Lf/vT;
/*    */     //   513: dup
/*    */     //   514: astore #7
/*    */     //   516: arraylength
/*    */     //   517: if_icmpge -> 626
/*    */     //   520: new f/MI0
/*    */     //   523: astore #8
/*    */     //   525: invokestatic XU : ()Z
/*    */     //   528: ifeq -> 539
/*    */     //   531: sipush #300
/*    */     //   534: istore #9
/*    */     //   536: goto -> 544
/*    */     //   539: sipush #209
/*    */     //   542: istore #9
/*    */     //   544: invokestatic XU : ()Z
/*    */     //   547: ifeq -> 557
/*    */     //   550: bipush #80
/*    */     //   552: istore #10
/*    */     //   554: goto -> 561
/*    */     //   557: bipush #52
/*    */     //   559: istore #10
/*    */     //   561: iload #6
/*    */     //   563: aload_0
/*    */     //   564: dup
/*    */     //   565: dup
/*    */     //   566: aload #7
/*    */     //   568: iload #6
/*    */     //   570: aload #8
/*    */     //   572: aload_0
/*    */     //   573: iload #9
/*    */     //   575: iload #10
/*    */     //   577: iload #6
/*    */     //   579: invokespecial <init> : (Lf/Dk;III)V
/*    */     //   582: aload #8
/*    */     //   584: aastore
/*    */     //   585: getfield aF0 : [Lf/vT;
/*    */     //   588: iload #6
/*    */     //   590: aaload
/*    */     //   591: iconst_0
/*    */     //   592: invokevirtual sk0 : (Z)V
/*    */     //   595: getfield aF0 : [Lf/vT;
/*    */     //   598: iload #6
/*    */     //   600: aaload
/*    */     //   601: ldc 'battle-button'
/*    */     //   603: invokevirtual Xu : (Ljava/lang/String;)V
/*    */     //   606: getfield aF0 : [Lf/vT;
/*    */     //   609: iload #6
/*    */     //   611: aaload
/*    */     //   612: getstatic f/et.COM2 : Lf/et;
/*    */     //   615: invokevirtual C70 : (Lf/et;)V
/*    */     //   618: iconst_1
/*    */     //   619: iadd
/*    */     //   620: i2s
/*    */     //   621: istore #6
/*    */     //   623: goto -> 507
/*    */     //   626: aload #5
/*    */     //   628: invokevirtual iterator : ()Ljava/util/Iterator;
/*    */     //   631: astore #6
/*    */     //   633: aload #6
/*    */     //   635: invokeinterface hasNext : ()Z
/*    */     //   640: ifeq -> 765
/*    */     //   643: aload #5
/*    */     //   645: aload #6
/*    */     //   647: invokeinterface next : ()Ljava/lang/Object;
/*    */     //   652: checkcast f/j40
/*    */     //   655: dup
/*    */     //   656: astore #7
/*    */     //   658: invokevirtual indexOf : (Ljava/lang/Object;)I
/*    */     //   661: dup
/*    */     //   662: istore #8
/*    */     //   664: aload_0
/*    */     //   665: getfield aF0 : [Lf/vT;
/*    */     //   668: dup
/*    */     //   669: astore #9
/*    */     //   671: arraylength
/*    */     //   672: if_icmplt -> 678
/*    */     //   675: goto -> 633
/*    */     //   678: aload #7
/*    */     //   680: aload_0
/*    */     //   681: aload #9
/*    */     //   683: iload #8
/*    */     //   685: aaload
/*    */     //   686: aload #7
/*    */     //   688: invokevirtual EG0 : (Lf/j40;)V
/*    */     //   691: getfield aF0 : [Lf/vT;
/*    */     //   694: iload #8
/*    */     //   696: aaload
/*    */     //   697: astore #9
/*    */     //   699: ifnull -> 730
/*    */     //   702: aload_2
/*    */     //   703: invokevirtual co0 : ()Z
/*    */     //   706: ifeq -> 724
/*    */     //   709: aload #7
/*    */     //   711: invokevirtual Ek : ()Lf/UD0;
/*    */     //   714: aload_2
/*    */     //   715: invokevirtual gJ0 : ()[Lf/UD0;
/*    */     //   718: invokestatic Gw0 : (Ljava/lang/Object;[Ljava/lang/Object;)Z
/*    */     //   721: ifeq -> 730
/*    */     //   724: iconst_1
/*    */     //   725: istore #10
/*    */     //   727: goto -> 733
/*    */     //   730: iconst_0
/*    */     //   731: istore #10
/*    */     //   733: aload_0
/*    */     //   734: aload #9
/*    */     //   736: iload #10
/*    */     //   738: invokevirtual sk0 : (Z)V
/*    */     //   741: getfield aF0 : [Lf/vT;
/*    */     //   744: iload #8
/*    */     //   746: aaload
/*    */     //   747: aload_1
/*    */     //   748: aload #7
/*    */     //   750: iload #4
/*    */     //   752: aload_2
/*    */     //   753: iload_3
/*    */     //   754: <illegal opcode> run : (Lf/Bf;Lf/j40;ZLf/LPT3;I)Ljava/lang/Runnable;
/*    */     //   759: invokevirtual tW : (Ljava/lang/Runnable;)V
/*    */     //   762: goto -> 633
/*    */     //   765: aload_1
/*    */     //   766: invokeinterface sU : ()Z
/*    */     //   771: ifeq -> 1031
/*    */     //   774: invokestatic XU : ()Z
/*    */     //   777: ifeq -> 783
/*    */     //   780: goto -> 1031
/*    */     //   783: aload_0
/*    */     //   784: dup
/*    */     //   785: getfield bp : Lf/Ip;
/*    */     //   788: dup
/*    */     //   789: invokevirtual d7 : ()Lf/cr0;
/*    */     //   792: iconst_2
/*    */     //   793: anewarray f/U90
/*    */     //   796: dup
/*    */     //   797: dup
/*    */     //   798: aload_0
/*    */     //   799: swap
/*    */     //   800: aload_0
/*    */     //   801: getfield bp : Lf/Ip;
/*    */     //   804: invokevirtual mE0 : ()Lf/g0;
/*    */     //   807: iconst_3
/*    */     //   808: anewarray f/JG0
/*    */     //   811: dup
/*    */     //   812: dup
/*    */     //   813: astore_2
/*    */     //   814: aload_0
/*    */     //   815: getfield aF0 : [Lf/vT;
/*    */     //   818: dup
/*    */     //   819: astore_3
/*    */     //   820: aload_2
/*    */     //   821: aload_3
/*    */     //   822: aload_2
/*    */     //   823: aload_3
/*    */     //   824: iconst_0
/*    */     //   825: aaload
/*    */     //   826: iconst_0
/*    */     //   827: swap
/*    */     //   828: aastore
/*    */     //   829: iconst_1
/*    */     //   830: aaload
/*    */     //   831: iconst_1
/*    */     //   832: swap
/*    */     //   833: aastore
/*    */     //   834: iconst_2
/*    */     //   835: aaload
/*    */     //   836: iconst_2
/*    */     //   837: swap
/*    */     //   838: aastore
/*    */     //   839: invokevirtual Mg : ([Lf/JG0;)Lf/U90;
/*    */     //   842: iconst_0
/*    */     //   843: swap
/*    */     //   844: aastore
/*    */     //   845: getfield bp : Lf/Ip;
/*    */     //   848: invokevirtual mE0 : ()Lf/g0;
/*    */     //   851: iconst_3
/*    */     //   852: anewarray f/JG0
/*    */     //   855: dup
/*    */     //   856: dup
/*    */     //   857: astore_2
/*    */     //   858: aload_0
/*    */     //   859: getfield aF0 : [Lf/vT;
/*    */     //   862: dup
/*    */     //   863: astore_3
/*    */     //   864: aload_2
/*    */     //   865: aload_3
/*    */     //   866: aload_2
/*    */     //   867: aload_3
/*    */     //   868: iconst_3
/*    */     //   869: aaload
/*    */     //   870: iconst_0
/*    */     //   871: swap
/*    */     //   872: aastore
/*    */     //   873: iconst_4
/*    */     //   874: aaload
/*    */     //   875: iconst_1
/*    */     //   876: swap
/*    */     //   877: aastore
/*    */     //   878: iconst_5
/*    */     //   879: aaload
/*    */     //   880: iconst_2
/*    */     //   881: swap
/*    */     //   882: aastore
/*    */     //   883: invokevirtual Mg : ([Lf/JG0;)Lf/U90;
/*    */     //   886: iconst_1
/*    */     //   887: swap
/*    */     //   888: aastore
/*    */     //   889: invokevirtual cOM8 : ([Lf/U90;)Lf/U90;
/*    */     //   892: invokevirtual WN : (Lf/U90;)V
/*    */     //   895: getfield bp : Lf/Ip;
/*    */     //   898: dup
/*    */     //   899: invokevirtual d7 : ()Lf/cr0;
/*    */     //   902: iconst_3
/*    */     //   903: anewarray f/U90
/*    */     //   906: dup
/*    */     //   907: dup
/*    */     //   908: astore_2
/*    */     //   909: aload_0
/*    */     //   910: aload_2
/*    */     //   911: aload_0
/*    */     //   912: aload_2
/*    */     //   913: aload_0
/*    */     //   914: getfield bp : Lf/Ip;
/*    */     //   917: invokevirtual mE0 : ()Lf/g0;
/*    */     //   920: iconst_2
/*    */     //   921: anewarray f/JG0
/*    */     //   924: dup
/*    */     //   925: dup
/*    */     //   926: astore_2
/*    */     //   927: aload_0
/*    */     //   928: getfield aF0 : [Lf/vT;
/*    */     //   931: dup
/*    */     //   932: aload_2
/*    */     //   933: swap
/*    */     //   934: iconst_0
/*    */     //   935: aaload
/*    */     //   936: iconst_0
/*    */     //   937: swap
/*    */     //   938: aastore
/*    */     //   939: iconst_3
/*    */     //   940: aaload
/*    */     //   941: iconst_1
/*    */     //   942: swap
/*    */     //   943: aastore
/*    */     //   944: invokevirtual Mg : ([Lf/JG0;)Lf/U90;
/*    */     //   947: iconst_0
/*    */     //   948: swap
/*    */     //   949: aastore
/*    */     //   950: getfield bp : Lf/Ip;
/*    */     //   953: invokevirtual mE0 : ()Lf/g0;
/*    */     //   956: iconst_2
/*    */     //   957: anewarray f/JG0
/*    */     //   960: dup
/*    */     //   961: dup
/*    */     //   962: astore_2
/*    */     //   963: aload_0
/*    */     //   964: getfield aF0 : [Lf/vT;
/*    */     //   967: dup
/*    */     //   968: aload_2
/*    */     //   969: swap
/*    */     //   970: iconst_1
/*    */     //   971: aaload
/*    */     //   972: iconst_0
/*    */     //   973: swap
/*    */     //   974: aastore
/*    */     //   975: iconst_4
/*    */     //   976: aaload
/*    */     //   977: iconst_1
/*    */     //   978: swap
/*    */     //   979: aastore
/*    */     //   980: invokevirtual Mg : ([Lf/JG0;)Lf/U90;
/*    */     //   983: iconst_1
/*    */     //   984: swap
/*    */     //   985: aastore
/*    */     //   986: getfield bp : Lf/Ip;
/*    */     //   989: invokevirtual mE0 : ()Lf/g0;
/*    */     //   992: iconst_2
/*    */     //   993: anewarray f/JG0
/*    */     //   996: dup
/*    */     //   997: dup
/*    */     //   998: astore_2
/*    */     //   999: aload_0
/*    */     //   1000: getfield aF0 : [Lf/vT;
/*    */     //   1003: dup
/*    */     //   1004: aload_2
/*    */     //   1005: swap
/*    */     //   1006: iconst_2
/*    */     //   1007: aaload
/*    */     //   1008: iconst_0
/*    */     //   1009: swap
/*    */     //   1010: aastore
/*    */     //   1011: iconst_5
/*    */     //   1012: aaload
/*    */     //   1013: iconst_1
/*    */     //   1014: swap
/*    */     //   1015: aastore
/*    */     //   1016: invokevirtual Mg : ([Lf/JG0;)Lf/U90;
/*    */     //   1019: iconst_2
/*    */     //   1020: swap
/*    */     //   1021: aastore
/*    */     //   1022: invokevirtual cOM8 : ([Lf/U90;)Lf/U90;
/*    */     //   1025: invokevirtual rK0 : (Lf/U90;)V
/*    */     //   1028: goto -> 1281
/*    */     //   1031: aload_0
/*    */     //   1032: dup
/*    */     //   1033: getfield bp : Lf/Ip;
/*    */     //   1036: dup
/*    */     //   1037: invokevirtual d7 : ()Lf/cr0;
/*    */     //   1040: bipush #18
/*    */     //   1042: invokevirtual Aq : (I)Lf/U90;
/*    */     //   1045: iconst_3
/*    */     //   1046: anewarray f/U90
/*    */     //   1049: dup
/*    */     //   1050: dup
/*    */     //   1051: astore_2
/*    */     //   1052: aload_0
/*    */     //   1053: aload_2
/*    */     //   1054: aload_0
/*    */     //   1055: aload_2
/*    */     //   1056: aload_0
/*    */     //   1057: getfield bp : Lf/Ip;
/*    */     //   1060: invokevirtual mE0 : ()Lf/g0;
/*    */     //   1063: iconst_2
/*    */     //   1064: anewarray f/JG0
/*    */     //   1067: dup
/*    */     //   1068: dup
/*    */     //   1069: astore_2
/*    */     //   1070: aload_0
/*    */     //   1071: getfield aF0 : [Lf/vT;
/*    */     //   1074: dup
/*    */     //   1075: aload_2
/*    */     //   1076: swap
/*    */     //   1077: iconst_0
/*    */     //   1078: aaload
/*    */     //   1079: iconst_0
/*    */     //   1080: swap
/*    */     //   1081: aastore
/*    */     //   1082: iconst_1
/*    */     //   1083: aaload
/*    */     //   1084: iconst_1
/*    */     //   1085: swap
/*    */     //   1086: aastore
/*    */     //   1087: invokevirtual Mg : ([Lf/JG0;)Lf/U90;
/*    */     //   1090: iconst_0
/*    */     //   1091: swap
/*    */     //   1092: aastore
/*    */     //   1093: getfield bp : Lf/Ip;
/*    */     //   1096: invokevirtual mE0 : ()Lf/g0;
/*    */     //   1099: iconst_2
/*    */     //   1100: anewarray f/JG0
/*    */     //   1103: dup
/*    */     //   1104: dup
/*    */     //   1105: astore_2
/*    */     //   1106: aload_0
/*    */     //   1107: getfield aF0 : [Lf/vT;
/*    */     //   1110: dup
/*    */     //   1111: aload_2
/*    */     //   1112: swap
/*    */     //   1113: iconst_2
/*    */     //   1114: aaload
/*    */     //   1115: iconst_0
/*    */     //   1116: swap
/*    */     //   1117: aastore
/*    */     //   1118: iconst_3
/*    */     //   1119: aaload
/*    */     //   1120: iconst_1
/*    */     //   1121: swap
/*    */     //   1122: aastore
/*    */     //   1123: invokevirtual Mg : ([Lf/JG0;)Lf/U90;
/*    */     //   1126: iconst_1
/*    */     //   1127: swap
/*    */     //   1128: aastore
/*    */     //   1129: getfield bp : Lf/Ip;
/*    */     //   1132: invokevirtual mE0 : ()Lf/g0;
/*    */     //   1135: iconst_2
/*    */     //   1136: anewarray f/JG0
/*    */     //   1139: dup
/*    */     //   1140: dup
/*    */     //   1141: astore_2
/*    */     //   1142: aload_0
/*    */     //   1143: getfield aF0 : [Lf/vT;
/*    */     //   1146: dup
/*    */     //   1147: aload_2
/*    */     //   1148: swap
/*    */     //   1149: iconst_4
/*    */     //   1150: aaload
/*    */     //   1151: iconst_0
/*    */     //   1152: swap
/*    */     //   1153: aastore
/*    */     //   1154: iconst_5
/*    */     //   1155: aaload
/*    */     //   1156: iconst_1
/*    */     //   1157: swap
/*    */     //   1158: aastore
/*    */     //   1159: invokevirtual Mg : ([Lf/JG0;)Lf/U90;
/*    */     //   1162: iconst_2
/*    */     //   1163: swap
/*    */     //   1164: aastore
/*    */     //   1165: invokevirtual cOM8 : ([Lf/U90;)Lf/U90;
/*    */     //   1168: invokevirtual WN : (Lf/U90;)V
/*    */     //   1171: getfield bp : Lf/Ip;
/*    */     //   1174: dup
/*    */     //   1175: invokevirtual d7 : ()Lf/cr0;
/*    */     //   1178: iconst_2
/*    */     //   1179: anewarray f/U90
/*    */     //   1182: dup
/*    */     //   1183: dup
/*    */     //   1184: aload_0
/*    */     //   1185: swap
/*    */     //   1186: aload_0
/*    */     //   1187: getfield bp : Lf/Ip;
/*    */     //   1190: invokevirtual mE0 : ()Lf/g0;
/*    */     //   1193: iconst_3
/*    */     //   1194: anewarray f/JG0
/*    */     //   1197: dup
/*    */     //   1198: dup
/*    */     //   1199: astore_2
/*    */     //   1200: aload_0
/*    */     //   1201: getfield aF0 : [Lf/vT;
/*    */     //   1204: dup
/*    */     //   1205: astore_3
/*    */     //   1206: aload_2
/*    */     //   1207: aload_3
/*    */     //   1208: aload_2
/*    */     //   1209: aload_3
/*    */     //   1210: iconst_0
/*    */     //   1211: aaload
/*    */     //   1212: iconst_0
/*    */     //   1213: swap
/*    */     //   1214: aastore
/*    */     //   1215: iconst_2
/*    */     //   1216: aaload
/*    */     //   1217: iconst_1
/*    */     //   1218: swap
/*    */     //   1219: aastore
/*    */     //   1220: iconst_4
/*    */     //   1221: aaload
/*    */     //   1222: iconst_2
/*    */     //   1223: swap
/*    */     //   1224: aastore
/*    */     //   1225: invokevirtual Mg : ([Lf/JG0;)Lf/U90;
/*    */     //   1228: iconst_0
/*    */     //   1229: swap
/*    */     //   1230: aastore
/*    */     //   1231: getfield bp : Lf/Ip;
/*    */     //   1234: invokevirtual mE0 : ()Lf/g0;
/*    */     //   1237: iconst_3
/*    */     //   1238: anewarray f/JG0
/*    */     //   1241: dup
/*    */     //   1242: dup
/*    */     //   1243: astore_2
/*    */     //   1244: aload_0
/*    */     //   1245: getfield aF0 : [Lf/vT;
/*    */     //   1248: dup
/*    */     //   1249: astore_3
/*    */     //   1250: aload_2
/*    */     //   1251: aload_3
/*    */     //   1252: aload_2
/*    */     //   1253: aload_3
/*    */     //   1254: iconst_1
/*    */     //   1255: aaload
/*    */     //   1256: iconst_0
/*    */     //   1257: swap
/*    */     //   1258: aastore
/*    */     //   1259: iconst_3
/*    */     //   1260: aaload
/*    */     //   1261: iconst_1
/*    */     //   1262: swap
/*    */     //   1263: aastore
/*    */     //   1264: iconst_5
/*    */     //   1265: aaload
/*    */     //   1266: iconst_2
/*    */     //   1267: swap
/*    */     //   1268: aastore
/*    */     //   1269: invokevirtual Mg : ([Lf/JG0;)Lf/U90;
/*    */     //   1272: iconst_1
/*    */     //   1273: swap
/*    */     //   1274: aastore
/*    */     //   1275: invokevirtual cOM8 : ([Lf/U90;)Lf/U90;
/*    */     //   1278: invokevirtual rK0 : (Lf/U90;)V
/*    */     //   1281: aload_1
/*    */     //   1282: aload_0
/*    */     //   1283: dup
/*    */     //   1284: getfield bp : Lf/Ip;
/*    */     //   1287: invokevirtual J8 : (Lf/JG0;)V
/*    */     //   1290: invokeinterface sU : ()Z
/*    */     //   1295: ifeq -> 1309
/*    */     //   1298: aload_0
/*    */     //   1299: dup
/*    */     //   1300: getfield Dm : Lf/dQ;
/*    */     //   1303: invokevirtual J8 : (Lf/JG0;)V
/*    */     //   1306: goto -> 1355
/*    */     //   1309: aload_0
/*    */     //   1310: dup
/*    */     //   1311: dup
/*    */     //   1312: new f/p30
/*    */     //   1315: dup
/*    */     //   1316: astore_2
/*    */     //   1317: aload_1
/*    */     //   1318: aload_0
/*    */     //   1319: aload_2
/*    */     //   1320: dup
/*    */     //   1321: bipush #53
/*    */     //   1323: invokestatic OH0 : (I)Ljava/lang/String;
/*    */     //   1326: invokespecial <init> : (Ljava/lang/String;)V
/*    */     //   1329: putfield UH : Lf/p30;
/*    */     //   1332: <illegal opcode> run : (Lf/Bf;)Ljava/lang/Runnable;
/*    */     //   1337: invokevirtual tW : (Ljava/lang/Runnable;)V
/*    */     //   1340: getfield UH : Lf/p30;
/*    */     //   1343: ldc_w 'battle-button-return'
/*    */     //   1346: invokevirtual Xu : (Ljava/lang/String;)V
/*    */     //   1349: getfield UH : Lf/p30;
/*    */     //   1352: invokevirtual J8 : (Lf/JG0;)V
/*    */     //   1355: aload_1
/*    */     //   1356: aload_0
/*    */     //   1357: getfield aF0 : [Lf/vT;
/*    */     //   1360: astore_1
/*    */     //   1361: invokeinterface sU : ()Z
/*    */     //   1366: ifeq -> 1383
/*    */     //   1369: invokestatic XU : ()Z
/*    */     //   1372: ifeq -> 1378
/*    */     //   1375: goto -> 1383
/*    */     //   1378: iconst_3
/*    */     //   1379: istore_2
/*    */     //   1380: goto -> 1385
/*    */     //   1383: iconst_2
/*    */     //   1384: istore_2
/*    */     //   1385: aload_0
/*    */     //   1386: aload_1
/*    */     //   1387: iload_2
/*    */     //   1388: invokevirtual iC : ([Lf/Un;I)V
/*    */     //   1391: return } public static void sG0(Bf paramBf, j40 paramj40, boolean paramBoolean, LPT3 paramLPT3, int paramInt) { // Byte code:
/*    */     //   0: aload_1
/*    */     //   1: aload_0
/*    */     //   2: invokeinterface kJ : ()V
/*    */     //   7: ifnonnull -> 11
/*    */     //   10: return
/*    */     //   11: iload_2
/*    */     //   12: ifeq -> 33
/*    */     //   15: aload_0
/*    */     //   16: aload_1
/*    */     //   17: aload_3
/*    */     //   18: getfield bj0 : S
/*    */     //   21: istore_0
/*    */     //   22: getfield Zs : Lf/Q90;
/*    */     //   25: iload_0
/*    */     //   26: swap
/*    */     //   27: invokeinterface uV : (SLf/Q90;)V
/*    */     //   32: return
/*    */     //   33: aload_3
/*    */     //   34: aload_0
/*    */     //   35: invokeinterface sU : ()Z
/*    */     //   40: invokevirtual default : (Z)Lf/dv;
/*    */     //   43: getstatic f/dv.Vx0 : Lf/dv;
/*    */     //   46: if_acmpne -> 62
/*    */     //   49: aload_0
/*    */     //   50: aload_3
/*    */     //   51: iload #4
/*    */     //   53: aload_1
/*    */     //   54: invokeinterface yL0 : (Lf/LPT3;ILf/j40;)V
/*    */     //   59: goto -> 114
/*    */     //   62: aload_3
/*    */     //   63: getfield EA : Z
/*    */     //   66: ifeq -> 92
/*    */     //   69: aload_0
/*    */     //   70: invokeinterface sU : ()Z
/*    */     //   75: ifne -> 92
/*    */     //   78: getstatic f/pA.Dg0 : Lf/pA;
/*    */     //   81: aload_0
/*    */     //   82: iload #4
/*    */     //   84: aload_1
/*    */     //   85: iconst_m1
/*    */     //   86: invokevirtual Nr : (Lf/Bf;ILf/j40;B)V
/*    */     //   89: goto -> 114
/*    */     //   92: aload_0
/*    */     //   93: aload_1
/*    */     //   94: aload_3
/*    */     //   95: getfield bj0 : S
/*    */     //   98: istore_0
/*    */     //   99: getfield Jg : I
/*    */     //   102: istore_1
/*    */     //   103: iload_0
/*    */     //   104: iload #4
/*    */     //   106: iload_1
/*    */     //   107: iconst_1
/*    */     //   108: iconst_m1
/*    */     //   109: invokeinterface ZN : (SIISB)V
/*    */     //   114: return
/*    */     // Line number table:
/*    */     //   Java source line number -> byte code offset
/*    */     //   #1	-> 18
/*    */     //   #2	-> 22
/*    */     //   #3	-> 27
/*    */     //   #4	-> 63
/*    */     //   #5	-> 70
/*    */     //   #6	-> 78
/*    */     //   #7	-> 86
/*    */     //   #8	-> 95
/*    */     //   #9	-> 99
/*  6 */     //   #10	-> 109 } public final void LM(throws paramthrows) { this.k1 = false; VA0.c90(y()); } public final void tH0(oa0 paramoa0) { Un un; int i; if (h1.J20(paramoa0.GG0, BM.bC)) { if ((un = y()) != null && this.kN) hm.Fz0(this.TG0.oh0);  return; }  if (((Dk)super)
/*  7 */       .UH != null && 
/*    */       
/*  9 */       h1.J20(paramoa0.GG0, BM.lc))
/*    */     {
/*    */       
/* 12 */       hm.Fz0(((Dk)super).UH.TG0.oh0);
/*    */     }
/* 14 */     if (h1.J20(paramoa0.GG0, BM.M8)) { if ((i = ((Dk)super).cOn + 1) % ((Dk)super).Wj == 0)
/*    */       {
/*    */ 
/*    */ 
/*    */ 
/*    */         
/* 20 */         VA0.c90(super.y()); }  } else { if (h1.J20(i.GG0, BM.Oq)) { if (((i = ((Dk)super).cOn) + 1) % ((Dk)super).Wj != 1) ((Dk)super).cOn = i - 1;  } else { if (h1.J20(i.GG0, BM.ni) ? ((i = ((Dk)super).cOn - ((Dk)super).Wj) < 0) : (!h1.J20(i.GG0, BM.N70) || (i = ((Dk)super).cOn + ((Dk)super).Wj) >= ((Dk)super).M30.length)) VA0.c90(super.y());  ((Dk)super).cOn = i; }  VA0.c90(super.y()); }
/*    */     
/*    */     ((Dk)super).cOn = i; }
/*    */ 
/*    */   
/*    */   public final boolean i2(oa0 paramoa0) {
/*    */     if (B8.Wm0(paramoa0.cz0) && paramoa0.oO()) {
/*    */       tH0(paramoa0);
/*    */       return true;
/*    */     } 
/*    */     return super.i2(paramoa0);
/*    */   }
/*    */   
/*    */   public final Un y() {
/*    */     Un[] arrayOfUn;
/*    */     int i;
/*    */     return ((i = this.cOn) < 0 || i >= (arrayOfUn = this.M30).length) ? null : this[i];
/*    */   }
/*    */   
/*    */   public final void d40() {
/*    */     // Byte code:
/*    */     //   0: aload_0
/*    */     //   1: getfield fr0 : Lf/JG0;
/*    */     //   4: dup
/*    */     //   5: astore_1
/*    */     //   6: ifnonnull -> 10
/*    */     //   9: return
/*    */     //   10: aload_0
/*    */     //   11: getfield az0 : Lf/Bf;
/*    */     //   14: invokeinterface sU : ()Z
/*    */     //   19: ifeq -> 206
/*    */     //   22: invokestatic XU : ()Z
/*    */     //   25: ifeq -> 31
/*    */     //   28: goto -> 206
/*    */     //   31: aload_1
/*    */     //   32: aload_0
/*    */     //   33: dup
/*    */     //   34: aload_1
/*    */     //   35: dup
/*    */     //   36: invokevirtual qF : ()I
/*    */     //   39: istore_2
/*    */     //   40: invokevirtual Hy : ()I
/*    */     //   43: istore_3
/*    */     //   44: getfield Kd : I
/*    */     //   47: istore #4
/*    */     //   49: getfield er0 : I
/*    */     //   52: istore #5
/*    */     //   54: instanceof f/ia0
/*    */     //   57: ifeq -> 118
/*    */     //   60: aload_1
/*    */     //   61: checkcast f/ia0
/*    */     //   64: dup
/*    */     //   65: dup
/*    */     //   66: astore_1
/*    */     //   67: aload_0
/*    */     //   68: dup
/*    */     //   69: aload_1
/*    */     //   70: dup
/*    */     //   71: dup2
/*    */     //   72: getfield coM7 : I
/*    */     //   75: istore_2
/*    */     //   76: getfield Ds0 : I
/*    */     //   79: istore_3
/*    */     //   80: getfield Kc : I
/*    */     //   83: istore #4
/*    */     //   85: getfield gA0 : I
/*    */     //   88: istore #5
/*    */     //   90: iload_2
/*    */     //   91: iload_3
/*    */     //   92: invokevirtual Tm : (II)Z
/*    */     //   95: pop
/*    */     //   96: iload #4
/*    */     //   98: iload #5
/*    */     //   100: invokevirtual ME : (II)Z
/*    */     //   103: pop
/*    */     //   104: iload_2
/*    */     //   105: iload_3
/*    */     //   106: invokevirtual Tm : (II)Z
/*    */     //   109: pop
/*    */     //   110: iload #4
/*    */     //   112: iload #5
/*    */     //   114: invokevirtual ME : (II)Z
/*    */     //   117: pop
/*    */     //   118: aload_0
/*    */     //   119: dup
/*    */     //   120: dup2
/*    */     //   121: getfield Dm : Lf/dQ;
/*    */     //   124: aload_0
/*    */     //   125: getfield Kd : I
/*    */     //   128: sipush #650
/*    */     //   131: iadd
/*    */     //   132: aload_0
/*    */     //   133: getfield er0 : I
/*    */     //   136: bipush #30
/*    */     //   138: iadd
/*    */     //   139: invokevirtual ME : (II)Z
/*    */     //   142: pop
/*    */     //   143: getfield bp : Lf/Ip;
/*    */     //   146: iload_2
/*    */     //   147: iload_3
/*    */     //   148: invokevirtual Tm : (II)Z
/*    */     //   151: pop
/*    */     //   152: getfield bp : Lf/Ip;
/*    */     //   155: iconst_5
/*    */     //   156: bipush #8
/*    */     //   158: iconst_5
/*    */     //   159: bipush #8
/*    */     //   161: invokevirtual kN : (IIII)Z
/*    */     //   164: pop
/*    */     //   165: getfield bp : Lf/Ip;
/*    */     //   168: iload #4
/*    */     //   170: iload #5
/*    */     //   172: invokevirtual ME : (II)Z
/*    */     //   175: pop
/*    */     //   176: iconst_0
/*    */     //   177: istore_1
/*    */     //   178: iload_1
/*    */     //   179: aload_0
/*    */     //   180: getfield aF0 : [Lf/vT;
/*    */     //   183: dup
/*    */     //   184: astore_2
/*    */     //   185: arraylength
/*    */     //   186: if_icmpge -> 495
/*    */     //   189: aload_2
/*    */     //   190: iload_1
/*    */     //   191: aaload
/*    */     //   192: sipush #200
/*    */     //   195: bipush #48
/*    */     //   197: invokevirtual uh0 : (II)V
/*    */     //   200: iinc #1, 1
/*    */     //   203: goto -> 178
/*    */     //   206: invokestatic Nr : ()Z
/*    */     //   209: ifeq -> 344
/*    */     //   212: aload_0
/*    */     //   213: getfield UH : Lf/p30;
/*    */     //   216: dup
/*    */     //   217: astore_2
/*    */     //   218: ifnull -> 262
/*    */     //   221: aload_0
/*    */     //   222: aload_2
/*    */     //   223: invokevirtual mM : ()V
/*    */     //   226: getfield UH : Lf/p30;
/*    */     //   229: aload_1
/*    */     //   230: invokevirtual m40 : ()I
/*    */     //   233: aload_0
/*    */     //   234: getfield UH : Lf/p30;
/*    */     //   237: getfield xY : I
/*    */     //   240: isub
/*    */     //   241: iconst_5
/*    */     //   242: isub
/*    */     //   243: aload_1
/*    */     //   244: invokevirtual mD : ()I
/*    */     //   247: aload_0
/*    */     //   248: getfield UH : Lf/p30;
/*    */     //   251: getfield HC : I
/*    */     //   254: isub
/*    */     //   255: bipush #6
/*    */     //   257: isub
/*    */     //   258: invokevirtual ME : (II)Z
/*    */     //   261: pop
/*    */     //   262: aload_0
/*    */     //   263: dup
/*    */     //   264: dup
/*    */     //   265: getfield bp : Lf/Ip;
/*    */     //   268: aload_1
/*    */     //   269: dup
/*    */     //   270: invokevirtual qF : ()I
/*    */     //   273: istore_2
/*    */     //   274: invokevirtual Hy : ()I
/*    */     //   277: iload_2
/*    */     //   278: swap
/*    */     //   279: invokevirtual Tm : (II)Z
/*    */     //   282: pop
/*    */     //   283: getfield bp : Lf/Ip;
/*    */     //   286: aload_1
/*    */     //   287: invokevirtual RS : ()I
/*    */     //   290: aload_1
/*    */     //   291: invokevirtual e3 : ()I
/*    */     //   294: bipush #50
/*    */     //   296: iadd
/*    */     //   297: invokevirtual ME : (II)Z
/*    */     //   300: pop
/*    */     //   301: getfield bp : Lf/Ip;
/*    */     //   304: iconst_5
/*    */     //   305: bipush #8
/*    */     //   307: iconst_5
/*    */     //   308: bipush #8
/*    */     //   310: invokevirtual kN : (IIII)Z
/*    */     //   313: pop
/*    */     //   314: iconst_0
/*    */     //   315: istore_1
/*    */     //   316: iload_1
/*    */     //   317: aload_0
/*    */     //   318: getfield aF0 : [Lf/vT;
/*    */     //   321: dup
/*    */     //   322: astore_2
/*    */     //   323: arraylength
/*    */     //   324: if_icmpge -> 495
/*    */     //   327: aload_2
/*    */     //   328: iload_1
/*    */     //   329: aaload
/*    */     //   330: sipush #186
/*    */     //   333: bipush #42
/*    */     //   335: invokevirtual uh0 : (II)V
/*    */     //   338: iinc #1, 1
/*    */     //   341: goto -> 316
/*    */     //   344: aload_0
/*    */     //   345: dup
/*    */     //   346: dup2
/*    */     //   347: invokevirtual mM : ()V
/*    */     //   350: getfield bp : Lf/Ip;
/*    */     //   353: sipush #630
/*    */     //   356: sipush #350
/*    */     //   359: invokevirtual Tm : (II)Z
/*    */     //   362: pop
/*    */     //   363: getfield bp : Lf/Ip;
/*    */     //   366: aload_1
/*    */     //   367: invokevirtual RS : ()I
/*    */     //   370: aload_1
/*    */     //   371: invokevirtual e3 : ()I
/*    */     //   374: bipush #50
/*    */     //   376: iadd
/*    */     //   377: invokevirtual ME : (II)Z
/*    */     //   380: pop
/*    */     //   381: getfield bp : Lf/Ip;
/*    */     //   384: iconst_5
/*    */     //   385: bipush #8
/*    */     //   387: iconst_5
/*    */     //   388: bipush #8
/*    */     //   390: invokevirtual kN : (IIII)Z
/*    */     //   393: pop
/*    */     //   394: iconst_0
/*    */     //   395: istore_1
/*    */     //   396: iload_1
/*    */     //   397: aload_0
/*    */     //   398: getfield aF0 : [Lf/vT;
/*    */     //   401: dup
/*    */     //   402: astore_2
/*    */     //   403: arraylength
/*    */     //   404: if_icmpge -> 424
/*    */     //   407: aload_2
/*    */     //   408: iload_1
/*    */     //   409: aaload
/*    */     //   410: sipush #300
/*    */     //   413: bipush #80
/*    */     //   415: invokevirtual Xg0 : (II)V
/*    */     //   418: iinc #1, 1
/*    */     //   421: goto -> 396
/*    */     //   424: aload_0
/*    */     //   425: getfield UH : Lf/p30;
/*    */     //   428: dup
/*    */     //   429: astore_1
/*    */     //   430: ifnull -> 474
/*    */     //   433: aload_1
/*    */     //   434: aload_0
/*    */     //   435: aload_1
/*    */     //   436: dup
/*    */     //   437: sipush #180
/*    */     //   440: bipush #56
/*    */     //   442: istore_1
/*    */     //   443: putfield go0 : I
/*    */     //   446: iload_1
/*    */     //   447: putfield Bo : I
/*    */     //   450: getfield bp : Lf/Ip;
/*    */     //   453: invokevirtual Xq : ()I
/*    */     //   456: sipush #195
/*    */     //   459: isub
/*    */     //   460: aload_0
/*    */     //   461: getfield bp : Lf/Ip;
/*    */     //   464: getfield HC : I
/*    */     //   467: bipush #30
/*    */     //   469: isub
/*    */     //   470: invokevirtual ME : (II)Z
/*    */     //   473: pop
/*    */     //   474: aload_0
/*    */     //   475: getfield Dm : Lf/dQ;
/*    */     //   478: dup
/*    */     //   479: dup
/*    */     //   480: astore_0
/*    */     //   481: getfield Kd : I
/*    */     //   484: aload_0
/*    */     //   485: invokevirtual yR : ()I
/*    */     //   488: bipush #10
/*    */     //   490: iadd
/*    */     //   491: invokevirtual ME : (II)Z
/*    */     //   494: pop
/*    */     //   495: return
/*    */     // Line number table:
/*    */     //   Java source line number -> byte code offset
/*    */     //   #1	-> 1
/*    */     //   #2	-> 11
/*    */     //   #3	-> 44
/*    */     //   #4	-> 49
/*    */     //   #5	-> 54
/*    */     //   #6	-> 72
/*    */     //   #7	-> 76
/*    */     //   #8	-> 80
/*    */     //   #9	-> 85
/*    */     //   #10	-> 92
/*    */     //   #11	-> 100
/*    */     //   #12	-> 106
/*    */     //   #13	-> 114
/*    */     //   #14	-> 121
/*    */     //   #15	-> 125
/*    */     //   #16	-> 133
/*    */     //   #17	-> 139
/*    */     //   #18	-> 143
/*    */     //   #19	-> 161
/*    */     //   #20	-> 165
/*    */     //   #21	-> 172
/*    */     //   #22	-> 180
/*    */     //   #23	-> 237
/*    */     //   #24	-> 244
/*    */     //   #25	-> 251
/*    */     //   #26	-> 258
/*    */     //   #27	-> 265
/*    */     //   #28	-> 297
/*    */     //   #29	-> 301
/*    */     //   #30	-> 310
/*    */     //   #31	-> 318
/*    */     //   #32	-> 377
/*    */     //   #33	-> 381
/*    */     //   #34	-> 390
/*    */     //   #35	-> 398
/*    */     //   #36	-> 443
/*    */     //   #37	-> 450
/*    */     //   #38	-> 464
/*    */     //   #39	-> 470
/*    */     //   #40	-> 475
/*    */     //   #41	-> 481
/*    */     //   #42	-> 485
/*    */     //   #43	-> 491
/*    */   }
/*    */   
/*    */   public final void iC(Un[] paramArrayOfUn, int paramInt) {
/*    */     this.cOn = 0;
/*    */     this.Wj = paramInt;
/*    */     this.M30 = paramArrayOfUn;
/*    */     if (paramArrayOfUn.length == 0)
/*    */       return; 
/*    */     VA0.c90(paramArrayOfUn[0]);
/*    */   } }


/* Location:              /Users/vnnsnnt/Documents/Codespace/JavaWorkspace/RedTrainer/src/main/java/org/trainer/client/PokeMMO.jar!/f/Dk.class
 * Java compiler version: 8 (52.0)
 * JD-Core Version:       1.1.3
 */