/*  1 */ package f;public final class DL extends fZ { public final boolean i2() { if (zm0.u20 - this
/*  2 */       .BC > 1000L) { (this.NuL.default())
/*  3 */         .Bm0
/*  4 */         .gL(); if (this.J80) if (this.NuL.Pf()) { km.u4
/*  5 */             .jF((byte)3, false, false);
/*  6 */           if (this.NuL == km.a3
/*  7 */             .Ct)
/*  8 */             km.u4.TA0(false);  } else { this.NuL
/*  9 */             .pm
/*    */             
/* 11 */             .vE(nl.Dz0, false); }   return true; }  return false; }
/*    */ 
/*    */   
/*    */   public final long BC = zm0.zg();
/*    */   public final xr0 gq;
/*    */   public final tc NuL;
/*    */   public final boolean po0;
/*    */   public final boolean J80;
/*    */   public short[][][] SJ;
/*    */   public short[][][] Vo;
/*    */   public short[][][] im0;
/*    */   public short[][][] MI;
/*    */   
/*    */   public DL(xr0 paramxr0, tc paramtc, boolean paramBoolean1, boolean paramBoolean2) {
/*    */     short[] arrayOfShort1;
/*    */     (arrayOfShort1 = new short[2])[0] = 720;
/*    */     (new short[2])[1] = 721;
/*    */     short[][] arrayOfShort;
/*    */     (arrayOfShort = new short[3][])[0] = arrayOfShort1;
/*    */     (arrayOfShort1 = new short[2])[0] = 728;
/*    */     (new short[2])[1] = 729;
/*    */     (new short[3][])[1] = arrayOfShort1;
/*    */     (arrayOfShort1 = new short[2])[0] = 736;
/*    */     (new short[2])[1] = 737;
/*    */     (new short[3][])[2] = arrayOfShort1;
/*    */     (new short[3][][])[0] = arrayOfShort;
/*    */     (arrayOfShort1 = new short[2])[0] = 778;
/*    */     (new short[2])[1] = 779;
/*    */     (arrayOfShort = new short[3][])[0] = arrayOfShort1;
/*    */     (arrayOfShort1 = new short[2])[0] = 786;
/*    */     (new short[2])[1] = 787;
/*    */     (new short[3][])[1] = arrayOfShort1;
/*    */     (arrayOfShort1 = new short[2])[0] = 794;
/*    */     (new short[2])[1] = 795;
/*    */     (new short[3][])[2] = arrayOfShort1;
/*    */     (new short[3][][])[1] = arrayOfShort;
/*    */     (arrayOfShort1 = new short[2])[0] = 776;
/*    */     (new short[2])[1] = 777;
/*    */     (arrayOfShort = new short[3][])[0] = arrayOfShort1;
/*    */     (arrayOfShort1 = new short[2])[0] = 784;
/*    */     (new short[2])[1] = 785;
/*    */     (new short[3][])[1] = arrayOfShort1;
/*    */     (arrayOfShort1 = new short[2])[0] = 792;
/*    */     (new short[2])[1] = 793;
/*    */     (new short[3][])[2] = arrayOfShort1;
/*    */     this.SJ = new short[][][] { null, null, arrayOfShort };
/*    */     (arrayOfShort1 = new short[2])[0] = 731;
/*    */     (new short[2])[1] = 732;
/*    */     (arrayOfShort = new short[3][])[0] = arrayOfShort1;
/*    */     (arrayOfShort1 = new short[2])[0] = 739;
/*    */     (new short[2])[1] = 740;
/*    */     (new short[3][])[1] = arrayOfShort1;
/*    */     (arrayOfShort1 = new short[2])[0] = 747;
/*    */     (new short[2])[1] = 748;
/*    */     (new short[3][])[2] = arrayOfShort1;
/*    */     (new short[3][][])[0] = arrayOfShort;
/*    */     (arrayOfShort1 = new short[2])[0] = 782;
/*    */     (new short[2])[1] = 783;
/*    */     (arrayOfShort = new short[3][])[0] = arrayOfShort1;
/*    */     (arrayOfShort1 = new short[2])[0] = 790;
/*    */     (new short[2])[1] = 791;
/*    */     (new short[3][])[1] = arrayOfShort1;
/*    */     (arrayOfShort1 = new short[2])[0] = 798;
/*    */     (new short[2])[1] = 799;
/*    */     (new short[3][])[2] = arrayOfShort1;
/*    */     (new short[3][][])[1] = arrayOfShort;
/*    */     (arrayOfShort1 = new short[2])[0] = 780;
/*    */     (new short[2])[1] = 781;
/*    */     (arrayOfShort = new short[3][])[0] = arrayOfShort1;
/*    */     (arrayOfShort1 = new short[2])[0] = 788;
/*    */     (new short[2])[1] = 789;
/*    */     (new short[3][])[1] = arrayOfShort1;
/*    */     (arrayOfShort1 = new short[2])[0] = 796;
/*    */     (new short[2])[1] = 797;
/*    */     (new short[3][])[2] = arrayOfShort1;
/*    */     this.Vo = new short[][][] { null, null, arrayOfShort };
/*    */     (arrayOfShort1 = new short[2])[0] = 640;
/*    */     (new short[2])[1] = 641;
/*    */     (arrayOfShort = new short[3][])[0] = arrayOfShort1;
/*    */     (arrayOfShort1 = new short[2])[0] = 648;
/*    */     (new short[2])[1] = 649;
/*    */     (new short[3][])[1] = arrayOfShort1;
/*    */     (arrayOfShort1 = new short[2])[0] = 656;
/*    */     (new short[2])[1] = 657;
/*    */     (new short[3][])[2] = arrayOfShort1;
/*    */     (new short[3][][])[0] = arrayOfShort;
/*    */     (arrayOfShort1 = new short[2])[0] = 642;
/*    */     (new short[2])[1] = 643;
/*    */     (arrayOfShort = new short[3][])[0] = arrayOfShort1;
/*    */     (arrayOfShort1 = new short[2])[0] = 650;
/*    */     (new short[2])[1] = 651;
/*    */     (new short[3][])[1] = arrayOfShort1;
/*    */     (arrayOfShort1 = new short[2])[0] = 658;
/*    */     (new short[2])[1] = 659;
/*    */     (new short[3][])[2] = arrayOfShort1;
/*    */     (new short[3][][])[1] = arrayOfShort;
/*    */     (arrayOfShort1 = new short[2])[0] = 644;
/*    */     (new short[2])[1] = 645;
/*    */     (arrayOfShort = new short[3][])[0] = arrayOfShort1;
/*    */     (arrayOfShort1 = new short[2])[0] = 652;
/*    */     (new short[2])[1] = 653;
/*    */     (new short[3][])[1] = arrayOfShort1;
/*    */     (arrayOfShort1 = new short[2])[0] = 660;
/*    */     (new short[2])[1] = 661;
/*    */     (new short[3][])[2] = arrayOfShort1;
/*    */     this.im0 = new short[][][] { null, null, arrayOfShort };
/*    */     (arrayOfShort1 = new short[2])[0] = 664;
/*    */     (new short[2])[1] = 665;
/*    */     (arrayOfShort = new short[3][])[0] = arrayOfShort1;
/*    */     (arrayOfShort1 = new short[2])[0] = 672;
/*    */     (new short[2])[1] = 673;
/*    */     (new short[3][])[1] = arrayOfShort1;
/*    */     (arrayOfShort1 = new short[2])[0] = 680;
/*    */     (new short[2])[1] = 681;
/*    */     (new short[3][])[2] = arrayOfShort1;
/*    */     (new short[3][][])[0] = arrayOfShort;
/*    */     (arrayOfShort1 = new short[2])[0] = 666;
/*    */     (new short[2])[1] = 667;
/*    */     (arrayOfShort = new short[3][])[0] = arrayOfShort1;
/*    */     (arrayOfShort1 = new short[2])[0] = 674;
/*    */     (new short[2])[1] = 675;
/*    */     (new short[3][])[1] = arrayOfShort1;
/*    */     (arrayOfShort1 = new short[2])[0] = 682;
/*    */     (new short[2])[1] = 683;
/*    */     (new short[3][])[2] = arrayOfShort1;
/*    */     (new short[3][][])[1] = arrayOfShort;
/*    */     (arrayOfShort1 = new short[2])[0] = 668;
/*    */     (new short[2])[1] = 669;
/*    */     (arrayOfShort = new short[3][])[0] = arrayOfShort1;
/*    */     (arrayOfShort1 = new short[2])[0] = 676;
/*    */     (new short[2])[1] = 677;
/*    */     (new short[3][])[1] = arrayOfShort1;
/*    */     (arrayOfShort1 = new short[2])[0] = 684;
/*    */     (new short[2])[1] = 685;
/*    */     (new short[3][])[2] = arrayOfShort1;
/*    */     this.MI = new short[][][] { null, null, arrayOfShort };
/*    */     this.gq = paramxr0;
/*    */     this.NuL = paramtc;
/*    */     this.po0 = paramBoolean1;
/*    */     this.J80 = paramBoolean2;
/*    */     if (paramBoolean2)
/*    */       Gh(0L); 
/*    */     if (paramtc.Pf())
/*    */       km.u4.TA0(true); 
/*    */   }
/*    */   
/*    */   public final void tU(tH paramtH, int paramInt1, int paramInt2, int paramInt3) {
/*    */     // Byte code:
/*    */     //   0: iload_2
/*    */     //   1: ifeq -> 5
/*    */     //   4: return
/*    */     //   5: getstatic f/zm0.u20 : J
/*    */     //   8: aload_0
/*    */     //   9: getfield BC : J
/*    */     //   12: lsub
/*    */     //   13: dup2
/*    */     //   14: lstore_1
/*    */     //   15: iconst_0
/*    */     //   16: istore_3
/*    */     //   17: getstatic f/NI.Ov0 : I
/*    */     //   20: i2l
/*    */     //   21: lcmp
/*    */     //   22: ifge -> 35
/*    */     //   25: aload_0
/*    */     //   26: getfield J80 : Z
/*    */     //   29: ifeq -> 63
/*    */     //   32: goto -> 68
/*    */     //   35: lload_1
/*    */     //   36: ldc2_w 500
/*    */     //   39: lcmp
/*    */     //   40: ifge -> 48
/*    */     //   43: iconst_1
/*    */     //   44: istore_3
/*    */     //   45: goto -> 70
/*    */     //   48: lload_1
/*    */     //   49: ldc2_w 750
/*    */     //   52: lcmp
/*    */     //   53: ifge -> 70
/*    */     //   56: aload_0
/*    */     //   57: getfield J80 : Z
/*    */     //   60: ifeq -> 68
/*    */     //   63: iconst_0
/*    */     //   64: istore_3
/*    */     //   65: goto -> 70
/*    */     //   68: iconst_2
/*    */     //   69: istore_3
/*    */     //   70: aload_0
/*    */     //   71: dup
/*    */     //   72: lload_1
/*    */     //   73: invokevirtual Gh : (J)V
/*    */     //   76: getfield gq : Lf/xr0;
/*    */     //   79: invokevirtual Q4 : ()Lf/KI;
/*    */     //   82: getfield E10 : B
/*    */     //   85: iconst_1
/*    */     //   86: if_icmpne -> 93
/*    */     //   89: iconst_1
/*    */     //   90: goto -> 94
/*    */     //   93: iconst_0
/*    */     //   94: ifeq -> 137
/*    */     //   97: aload_0
/*    */     //   98: getfield po0 : Z
/*    */     //   101: ifeq -> 114
/*    */     //   104: aload_0
/*    */     //   105: getfield J80 : Z
/*    */     //   108: ifeq -> 121
/*    */     //   111: goto -> 129
/*    */     //   114: aload_0
/*    */     //   115: getfield J80 : Z
/*    */     //   118: ifeq -> 129
/*    */     //   121: aload_0
/*    */     //   122: getfield im0 : [[[S
/*    */     //   125: astore_1
/*    */     //   126: goto -> 174
/*    */     //   129: aload_0
/*    */     //   130: getfield MI : [[[S
/*    */     //   133: astore_1
/*    */     //   134: goto -> 174
/*    */     //   137: aload_0
/*    */     //   138: getfield po0 : Z
/*    */     //   141: ifeq -> 154
/*    */     //   144: aload_0
/*    */     //   145: getfield J80 : Z
/*    */     //   148: ifeq -> 161
/*    */     //   151: goto -> 169
/*    */     //   154: aload_0
/*    */     //   155: getfield J80 : Z
/*    */     //   158: ifeq -> 169
/*    */     //   161: aload_0
/*    */     //   162: getfield SJ : [[[S
/*    */     //   165: astore_1
/*    */     //   166: goto -> 174
/*    */     //   169: aload_0
/*    */     //   170: getfield Vo : [[[S
/*    */     //   173: astore_1
/*    */     //   174: iconst_m1
/*    */     //   175: istore_2
/*    */     //   176: iload_2
/*    */     //   177: iconst_1
/*    */     //   178: if_icmpge -> 266
/*    */     //   181: iconst_m1
/*    */     //   182: istore #4
/*    */     //   184: iload #4
/*    */     //   186: iconst_2
/*    */     //   187: if_icmpge -> 260
/*    */     //   190: aload_0
/*    */     //   191: getfield gq : Lf/xr0;
/*    */     //   194: invokevirtual Q4 : ()Lf/KI;
/*    */     //   197: aload_0
/*    */     //   198: getfield gq : Lf/xr0;
/*    */     //   201: invokevirtual Ka : ()S
/*    */     //   204: iload_2
/*    */     //   205: iadd
/*    */     //   206: aload_0
/*    */     //   207: getfield gq : Lf/xr0;
/*    */     //   210: invokevirtual hA0 : ()S
/*    */     //   213: iload #4
/*    */     //   215: iadd
/*    */     //   216: iconst_0
/*    */     //   217: invokevirtual v50 : (III)Lf/xr0;
/*    */     //   220: dup
/*    */     //   221: astore #5
/*    */     //   223: aload_1
/*    */     //   224: iload_3
/*    */     //   225: aaload
/*    */     //   226: iload #4
/*    */     //   228: iconst_1
/*    */     //   229: iadd
/*    */     //   230: dup
/*    */     //   231: istore #4
/*    */     //   233: aaload
/*    */     //   234: iload_2
/*    */     //   235: iconst_1
/*    */     //   236: iadd
/*    */     //   237: saload
/*    */     //   238: istore #6
/*    */     //   240: ifnonnull -> 246
/*    */     //   243: goto -> 184
/*    */     //   246: aload #5
/*    */     //   248: dup
/*    */     //   249: invokevirtual F80 : ()B
/*    */     //   252: iload #6
/*    */     //   254: invokevirtual z0 : (BS)V
/*    */     //   257: goto -> 184
/*    */     //   260: iinc #2, 1
/*    */     //   263: goto -> 176
/*    */     //   266: return
/*    */     // Line number table:
/*    */     //   Java source line number -> byte code offset
/*    */     //   #1	-> 5
/*    */     //   #2	-> 9
/*    */     //   #3	-> 76
/*    */     //   #4	-> 82
/*    */     //   #5	-> 98
/*    */     //   #6	-> 217
/*    */     //   #7	-> 225
/*    */     //   #8	-> 249
/*    */   }
/*    */   
/*    */   public final void Gh(long paramLong) {
/*    */     // Byte code:
/*    */     //   0: lload_1
/*    */     //   1: getstatic f/NI.Ov0 : I
/*    */     //   4: dup
/*    */     //   5: istore_3
/*    */     //   6: i2l
/*    */     //   7: lcmp
/*    */     //   8: ifgt -> 18
/*    */     //   11: aload_0
/*    */     //   12: getfield J80 : Z
/*    */     //   15: ifeq -> 132
/*    */     //   18: aload_0
/*    */     //   19: getfield J80 : Z
/*    */     //   22: dup
/*    */     //   23: istore #4
/*    */     //   25: ifne -> 33
/*    */     //   28: lload_1
/*    */     //   29: iload_3
/*    */     //   30: i2l
/*    */     //   31: lsub
/*    */     //   32: lstore_1
/*    */     //   33: iload #4
/*    */     //   35: lload_1
/*    */     //   36: dup2
/*    */     //   37: ldc2_w 50
/*    */     //   40: ldiv
/*    */     //   41: l2i
/*    */     //   42: istore_1
/*    */     //   43: ldc2_w 80
/*    */     //   46: ldiv
/*    */     //   47: l2i
/*    */     //   48: istore_2
/*    */     //   49: ifeq -> 83
/*    */     //   52: aload_0
/*    */     //   53: dup
/*    */     //   54: getfield NuL : Lf/tc;
/*    */     //   57: getfield HW : Lf/G5;
/*    */     //   60: iconst_3
/*    */     //   61: putfield g50 : B
/*    */     //   64: iinc #1, -20
/*    */     //   67: iinc #2, -12
/*    */     //   70: getfield po0 : Z
/*    */     //   73: ifeq -> 110
/*    */     //   76: iload_2
/*    */     //   77: iconst_m1
/*    */     //   78: imul
/*    */     //   79: istore_2
/*    */     //   80: goto -> 110
/*    */     //   83: iload_2
/*    */     //   84: iconst_2
/*    */     //   85: if_icmpge -> 93
/*    */     //   88: iconst_0
/*    */     //   89: istore_2
/*    */     //   90: goto -> 96
/*    */     //   93: iinc #2, -2
/*    */     //   96: aload_0
/*    */     //   97: iload_1
/*    */     //   98: iconst_m1
/*    */     //   99: imul
/*    */     //   100: istore_1
/*    */     //   101: getfield po0 : Z
/*    */     //   104: ifeq -> 110
/*    */     //   107: goto -> 76
/*    */     //   110: aload_0
/*    */     //   111: getfield NuL : Lf/tc;
/*    */     //   114: invokevirtual default : ()Lf/static;
/*    */     //   117: getfield Bm0 : Lf/eo;
/*    */     //   120: iload_2
/*    */     //   121: iload_1
/*    */     //   122: i2f
/*    */     //   123: fstore_0
/*    */     //   124: i2f
/*    */     //   125: fload_0
/*    */     //   126: swap
/*    */     //   127: fconst_0
/*    */     //   128: invokevirtual TG0 : (FFF)Lf/eo;
/*    */     //   131: pop
/*    */     //   132: return
/*    */     // Line number table:
/*    */     //   Java source line number -> byte code offset
/*    */     //   #1	-> 57
/*    */     //   #2	-> 61
/*    */     //   #3	-> 70
/*    */     //   #4	-> 117
/*    */     //   #5	-> 128
/*    */   } }


/* Location:              /Users/vnnsnnt/Documents/Codespace/JavaWorkspace/RedTrainer/src/main/java/org/trainer/client/PokeMMO.jar!/f/DL.class
 * Java compiler version: 8 (52.0)
 * JD-Core Version:       1.1.3
 */