/*  1 */ package f;public final class dS { public static final HashMap O10; public static final Object Z3; public final q80 ld0; public final VI Lpt5; public li0 W40; public final bn0 Kd; public final HashMap cOm1; public oF0 d70; public final HashMap ah; public final HashMap At; public final Em oc0; public pe hS; public final q80 ro; static { O10 = new HashMap<>(); pb0(et.class, "alignment"); pb0(je0.class, "direction"); pb0(Mv.class, "tabposition"); Z3 = new Object(); } public dS(VI paramVI, li0 paramli0) { q80 q801; this.d70 = null; this(this, null); this.ld0 = new q80(); this.Lpt5 = paramVI; this.W40 = paramli0; this.Kd = new bn0(q801, paramVI); this.cOm1 = new HashMap<>(); this.ah = new HashMap<>(); this.At = new HashMap<>(); this.ro = new q80(this, null); this
/*  2 */       .oc0 = new Em(this); } public static void pb0(Class<?> paramClass, String paramString) { if (paramClass.isEnum()) { HashMap<?, Class<?>> hashMap; Class clazz; if ((clazz = (hashMap = O10).get(paramString)) == null || clazz == paramClass) { hashMap.put(paramString, paramClass); return; }  throw new IllegalArgumentException("Enum type name \"" + paramString + "\" is already in use by " + clazz); }  throw new IllegalArgumentException("not an enum class"); } public static eL gh0(int paramInt, String paramString) { if ((paramInt = gd0.rB(paramString, paramInt, paramString.length())) >= paramString.length()) return null;  int i;
/*  3 */     if ((i = paramString.indexOf(',', paramInt)) < 0) i = paramString.length(); 
/*  4 */     String str = gd0.PJ0(paramString, paramInt, i); return new eL(str, gh0(i + 1, paramString)); } public static void zD(xS paramxS, L00 paramL00) { String str; if ((str = paramxS.S3("ref")) != null) { if (str.endsWith("*")) { if ((str = str.substring(0, str.length() - 1)).length() <= 0 || str.endsWith(".")) { paramL00.w10 = str; paramxS.LX(); return; }  throw paramxS.s70("Wildcard must end with \".*\" or be \"*\""); }  throw paramxS.s70("Wildcard reference must end with '*'"); }  throw paramxS.s70("Reference required for wildcard theme"); } public static dS W00(URL paramURL, VI paramVI, li0 paramli0, HashMap paramHashMap) { if (paramVI != null) try { dS dS1; ((tw)paramVI).Ls(paramli0); this(paramVI, paramli0); (new dS()).ld0.J10(Integer.valueOf(-1), "SINGLE_COLUMN"); (new dS()).ld0.J10(Short.valueOf('翿'), "MAX"); if (!paramHashMap.isEmpty()) { q80 q801; (q801 = dS1.ld0).getClass(); for (Iterator<Map.Entry> iterator = paramHashMap.entrySet().iterator(); iterator.hasNext(); ) { String str = (String)((Map.Entry)iterator.next()).getKey(); q801.J10(((Map.Entry)iterator.next()).getValue(), str); }  }  dS1
/*  5 */           .uq(paramURL); return dS1; } catch (XmlPullParserException xmlPullParserException) { throw (IOException)(new IOException()).initCause(xmlPullParserException); }   throw new IllegalArgumentException("renderer is null"); } public final nY GK(String paramString, boolean paramBoolean1, boolean paramBoolean2) { int j; if ((j = paramString.indexOf('.', 0)) < 0) j = paramString.length();  nY nY; if ((nY = (nY)this.ah.get(paramString.substring(0, j))) == null && (nY = (nY)this.ah.get("*")) != null) { if (!paramBoolean2) return null;  lI.wb().getClass(); lI.u4.warning("Selected fallback theme for missing theme \"" + paramString + "\""); }  int i; while (nY != null && (i = j + 1) < paramString.length()) { int k; if ((k = paramString.indexOf('.', i)) < 0) { j = k = paramString.length(); } else { j = k; }
/*  6 */        String str = paramString.substring(i, j);
/*  7 */       nY = ((L00)nY).mn0(this, true); }  if (nY == null && paramBoolean1)
/*  8 */     { lI.wb().getClass();
/*  9 */       lI.u4.warning("Could not find theme: " + paramString); }  return nY; } public final void uq(URL paramURL) { try { xS xS; this(paramURL); try { xS.WJ0 = dS.class.getName(); boolean bool = false; String str1 = null, str2 = null; xS.bb.require(bool, str1, str2); xS.LX(); return; } finally { this = null; xS.close(); }  } catch (XmlPullParserException xmlPullParserException) { String str = getMessage(); int i = getLineNumber(), j = getColumnNumber(); throw new TD(str, paramURL, i, j, this); } catch (TD tD) { throw null; } catch (Exception exception) { throw (IOException)(new IOException("while parsing Theme XML: " + paramURL)).initCause(this); }  } public final void Ol0(xS paramxS, URL paramURL) { // Byte code:
/*    */     //   0: aload_1
/*    */     //   1: getfield bb : Lorg/xmlpull/v1/XmlPullParser;
/*    */     //   4: iconst_2
/*    */     //   5: aconst_null
/*    */     //   6: ldc_w 'themes'
/*    */     //   9: invokeinterface require : (ILjava/lang/String;Ljava/lang/String;)V
/*    */     //   14: aload_1
/*    */     //   15: dup
/*    */     //   16: invokevirtual LX : ()V
/*    */     //   19: invokevirtual aM : ()Z
/*    */     //   22: ifne -> 1261
/*    */     //   25: aload_1
/*    */     //   26: dup
/*    */     //   27: getfield bb : Lorg/xmlpull/v1/XmlPullParser;
/*    */     //   30: iconst_2
/*    */     //   31: aconst_null
/*    */     //   32: aconst_null
/*    */     //   33: invokeinterface require : (ILjava/lang/String;Ljava/lang/String;)V
/*    */     //   38: getfield bb : Lorg/xmlpull/v1/XmlPullParser;
/*    */     //   41: invokeinterface getName : ()Ljava/lang/String;
/*    */     //   46: astore_3
/*    */     //   47: ldc_w 'images'
/*    */     //   50: aload_3
/*    */     //   51: invokevirtual equals : (Ljava/lang/Object;)Z
/*    */     //   54: ifne -> 949
/*    */     //   57: ldc_w 'textures'
/*    */     //   60: aload_3
/*    */     //   61: invokevirtual equals : (Ljava/lang/Object;)Z
/*    */     //   64: ifeq -> 70
/*    */     //   67: goto -> 949
/*    */     //   70: ldc_w 'include'
/*    */     //   73: aload_3
/*    */     //   74: invokevirtual equals : (Ljava/lang/Object;)Z
/*    */     //   77: ifeq -> 174
/*    */     //   80: aload_0
/*    */     //   81: aload_1
/*    */     //   82: ldc_w 'filename'
/*    */     //   85: invokevirtual Jg0 : (Ljava/lang/String;)Ljava/lang/String;
/*    */     //   88: astore #4
/*    */     //   90: new java/net/URL
/*    */     //   93: dup
/*    */     //   94: astore #5
/*    */     //   96: aload_2
/*    */     //   97: aload #4
/*    */     //   99: invokespecial <init> : (Ljava/net/URL;Ljava/lang/String;)V
/*    */     //   102: aload #5
/*    */     //   104: invokevirtual uq : (Ljava/net/URL;)V
/*    */     //   107: goto -> 368
/*    */     //   110: astore_0
/*    */     //   111: aload_0
/*    */     //   112: aload_1
/*    */     //   113: dup
/*    */     //   114: getfield bb : Lorg/xmlpull/v1/XmlPullParser;
/*    */     //   117: invokeinterface getLineNumber : ()I
/*    */     //   122: istore_1
/*    */     //   123: getfield bb : Lorg/xmlpull/v1/XmlPullParser;
/*    */     //   126: invokeinterface getColumnNumber : ()I
/*    */     //   131: istore_3
/*    */     //   132: getfield pI0 : Lf/uH;
/*    */     //   135: astore #4
/*    */     //   137: aload #4
/*    */     //   139: getfield d : Lf/uH;
/*    */     //   142: dup
/*    */     //   143: astore #5
/*    */     //   145: ifnull -> 155
/*    */     //   148: aload #5
/*    */     //   150: astore #4
/*    */     //   152: goto -> 137
/*    */     //   155: aload_0
/*    */     //   156: aload #4
/*    */     //   158: new f/uH
/*    */     //   161: dup
/*    */     //   162: astore_0
/*    */     //   163: aload_2
/*    */     //   164: iload_1
/*    */     //   165: iload_3
/*    */     //   166: invokespecial <init> : (Ljava/net/URL;II)V
/*    */     //   169: aload_0
/*    */     //   170: putfield d : Lf/uH;
/*    */     //   173: athrow
/*    */     //   174: ldc_w 'fontGen'
/*    */     //   177: aload_3
/*    */     //   178: invokevirtual equals : (Ljava/lang/Object;)Z
/*    */     //   181: ifeq -> 375
/*    */     //   184: aload_0
/*    */     //   185: invokestatic currentTimeMillis : ()J
/*    */     //   188: lstore #4
/*    */     //   190: ldc f/dS
/*    */     //   192: invokevirtual getName : ()Ljava/lang/String;
/*    */     //   195: invokestatic getLogger : (Ljava/lang/String;)Ljava/util/logging/Logger;
/*    */     //   198: ldc_w 'Generating Fonts...'
/*    */     //   201: invokevirtual info : (Ljava/lang/String;)V
/*    */     //   204: getfield cOm1 : Ljava/util/HashMap;
/*    */     //   207: invokevirtual values : ()Ljava/util/Collection;
/*    */     //   210: invokeinterface iterator : ()Ljava/util/Iterator;
/*    */     //   215: astore #6
/*    */     //   217: aload #6
/*    */     //   219: invokeinterface hasNext : ()Z
/*    */     //   224: ifeq -> 247
/*    */     //   227: aload #6
/*    */     //   229: invokeinterface next : ()Ljava/lang/Object;
/*    */     //   234: checkcast f/pe
/*    */     //   237: checkcast f/t90
/*    */     //   240: aload_0
/*    */     //   241: invokevirtual init : (Lf/dS;)V
/*    */     //   244: goto -> 217
/*    */     //   247: aload_0
/*    */     //   248: ldc f/dS
/*    */     //   250: invokevirtual getName : ()Ljava/lang/String;
/*    */     //   253: invokestatic getLogger : (Ljava/lang/String;)Ljava/util/logging/Logger;
/*    */     //   256: astore #6
/*    */     //   258: ldc_w 'Default font to ''
/*    */     //   261: invokestatic df : (Ljava/lang/String;)Ljava/lang/StringBuilder;
/*    */     //   264: astore #7
/*    */     //   266: getfield hS : Lf/pe;
/*    */     //   269: dup
/*    */     //   270: astore #8
/*    */     //   272: ifnonnull -> 283
/*    */     //   275: ldc_w 'null'
/*    */     //   278: astore #8
/*    */     //   280: goto -> 293
/*    */     //   283: aload #8
/*    */     //   285: checkcast f/t90
/*    */     //   288: invokevirtual getName : ()Ljava/lang/String;
/*    */     //   291: astore #8
/*    */     //   293: aload_0
/*    */     //   294: aload #6
/*    */     //   296: aload #7
/*    */     //   298: aload #8
/*    */     //   300: invokevirtual append : (Ljava/lang/String;)Ljava/lang/StringBuilder;
/*    */     //   303: ldc_w '''
/*    */     //   306: invokevirtual append : (Ljava/lang/String;)Ljava/lang/StringBuilder;
/*    */     //   309: invokevirtual toString : ()Ljava/lang/String;
/*    */     //   312: invokevirtual info : (Ljava/lang/String;)V
/*    */     //   315: getfield hS : Lf/pe;
/*    */     //   318: dup
/*    */     //   319: astore #6
/*    */     //   321: ifnull -> 333
/*    */     //   324: aload #6
/*    */     //   326: checkcast f/t90
/*    */     //   329: aload_0
/*    */     //   330: invokevirtual init : (Lf/dS;)V
/*    */     //   333: ldc f/dS
/*    */     //   335: invokevirtual getName : ()Ljava/lang/String;
/*    */     //   338: invokestatic getLogger : (Ljava/lang/String;)Ljava/util/logging/Logger;
/*    */     //   341: ldc_w 'Generated fonts in '
/*    */     //   344: invokestatic df : (Ljava/lang/String;)Ljava/lang/StringBuilder;
/*    */     //   347: invokestatic currentTimeMillis : ()J
/*    */     //   350: lload #4
/*    */     //   352: lsub
/*    */     //   353: invokevirtual append : (J)Ljava/lang/StringBuilder;
/*    */     //   356: ldc_w ' ms.'
/*    */     //   359: invokevirtual append : (Ljava/lang/String;)Ljava/lang/StringBuilder;
/*    */     //   362: invokevirtual toString : ()Ljava/lang/String;
/*    */     //   365: invokevirtual info : (Ljava/lang/String;)V
/*    */     //   368: aload_1
/*    */     //   369: invokevirtual LX : ()V
/*    */     //   372: goto -> 1239
/*    */     //   375: aload_1
/*    */     //   376: ldc_w 'name'
/*    */     //   379: invokevirtual Jg0 : (Ljava/lang/String;)Ljava/lang/String;
/*    */     //   382: astore #4
/*    */     //   384: ldc_w 'theme'
/*    */     //   387: aload_3
/*    */     //   388: invokevirtual equals : (Ljava/lang/Object;)Z
/*    */     //   391: ifeq -> 469
/*    */     //   394: aload_0
/*    */     //   395: getfield ah : Ljava/util/HashMap;
/*    */     //   398: aload #4
/*    */     //   400: invokevirtual containsKey : (Ljava/lang/Object;)Z
/*    */     //   403: ifeq -> 443
/*    */     //   406: aload_1
/*    */     //   407: ldc_w 'overwrite'
/*    */     //   410: iconst_0
/*    */     //   411: invokevirtual GC : (Ljava/lang/String;Z)Z
/*    */     //   414: ifne -> 443
/*    */     //   417: aload_0
/*    */     //   418: dup
/*    */     //   419: getfield ah : Ljava/util/HashMap;
/*    */     //   422: aload #4
/*    */     //   424: invokevirtual get : (Ljava/lang/Object;)Ljava/lang/Object;
/*    */     //   427: checkcast f/L00
/*    */     //   430: aload_1
/*    */     //   431: aload #4
/*    */     //   433: aconst_null
/*    */     //   434: aload_2
/*    */     //   435: invokevirtual FF : (Lf/L00;Lf/xS;Ljava/lang/String;Lf/L00;Ljava/net/URL;)Lf/L00;
/*    */     //   438: astore #5
/*    */     //   440: goto -> 454
/*    */     //   443: aload_0
/*    */     //   444: aconst_null
/*    */     //   445: aload_1
/*    */     //   446: aload #4
/*    */     //   448: aload_2
/*    */     //   449: invokevirtual be : (Lf/L00;Lf/xS;Ljava/lang/String;Ljava/net/URL;)Lf/L00;
/*    */     //   452: astore #5
/*    */     //   454: aload_0
/*    */     //   455: getfield ah : Ljava/util/HashMap;
/*    */     //   458: aload #4
/*    */     //   460: aload #5
/*    */     //   462: invokevirtual put : (Ljava/lang/Object;Ljava/lang/Object;)Ljava/lang/Object;
/*    */     //   465: pop
/*    */     //   466: goto -> 1239
/*    */     //   469: ldc_w 'inputMapDef'
/*    */     //   472: aload_3
/*    */     //   473: invokevirtual equals : (Ljava/lang/Object;)Z
/*    */     //   476: ifeq -> 544
/*    */     //   479: aload_0
/*    */     //   480: getfield At : Ljava/util/HashMap;
/*    */     //   483: aload #4
/*    */     //   485: invokevirtual containsKey : (Ljava/lang/Object;)Z
/*    */     //   488: ifne -> 512
/*    */     //   491: aload_0
/*    */     //   492: getfield At : Ljava/util/HashMap;
/*    */     //   495: aload #4
/*    */     //   497: aload_0
/*    */     //   498: aload_1
/*    */     //   499: aload #4
/*    */     //   501: aconst_null
/*    */     //   502: invokevirtual A4 : (Lf/xS;Ljava/lang/String;Lf/L00;)Lf/dH;
/*    */     //   505: invokevirtual put : (Ljava/lang/Object;Ljava/lang/Object;)Ljava/lang/Object;
/*    */     //   508: pop
/*    */     //   509: goto -> 1239
/*    */     //   512: aload_1
/*    */     //   513: new java/lang/StringBuilder
/*    */     //   516: dup
/*    */     //   517: invokespecial <init> : ()V
/*    */     //   520: ldc_w 'inputMap "'
/*    */     //   523: invokevirtual append : (Ljava/lang/String;)Ljava/lang/StringBuilder;
/*    */     //   526: aload #4
/*    */     //   528: invokevirtual append : (Ljava/lang/String;)Ljava/lang/StringBuilder;
/*    */     //   531: ldc_w '" already defined'
/*    */     //   534: invokevirtual append : (Ljava/lang/String;)Ljava/lang/StringBuilder;
/*    */     //   537: invokevirtual toString : ()Ljava/lang/String;
/*    */     //   540: invokevirtual s70 : (Ljava/lang/String;)Lorg/xmlpull/v1/XmlPullParserException;
/*    */     //   543: athrow
/*    */     //   544: ldc_w 'fontDef'
/*    */     //   547: aload_3
/*    */     //   548: invokevirtual equals : (Ljava/lang/Object;)Z
/*    */     //   551: ifeq -> 913
/*    */     //   554: aload_1
/*    */     //   555: dup
/*    */     //   556: ldc_w 'default'
/*    */     //   559: iconst_0
/*    */     //   560: invokevirtual GC : (Ljava/lang/String;Z)Z
/*    */     //   563: istore #5
/*    */     //   565: ldc 'ref'
/*    */     //   567: invokevirtual S3 : (Ljava/lang/String;)Ljava/lang/String;
/*    */     //   570: ifnull -> 835
/*    */     //   573: aload_0
/*    */     //   574: aload_1
/*    */     //   575: dup
/*    */     //   576: ldc_w 'name'
/*    */     //   579: invokevirtual Jg0 : (Ljava/lang/String;)Ljava/lang/String;
/*    */     //   582: astore #6
/*    */     //   584: ldc 'ref'
/*    */     //   586: invokevirtual S3 : (Ljava/lang/String;)Ljava/lang/String;
/*    */     //   589: astore #7
/*    */     //   591: getfield cOm1 : Ljava/util/HashMap;
/*    */     //   594: aload #7
/*    */     //   596: invokevirtual containsKey : (Ljava/lang/Object;)Z
/*    */     //   599: ifeq -> 809
/*    */     //   602: aload_1
/*    */     //   603: aload_0
/*    */     //   604: aload_1
/*    */     //   605: new f/dt
/*    */     //   608: dup
/*    */     //   609: astore #8
/*    */     //   611: invokespecial <init> : ()V
/*    */     //   614: aload #8
/*    */     //   616: invokevirtual U1 : (Lf/xS;Lf/dt;)V
/*    */     //   619: new java/util/ArrayList
/*    */     //   622: dup
/*    */     //   623: astore #9
/*    */     //   625: invokespecial <init> : ()V
/*    */     //   628: new java/util/ArrayList
/*    */     //   631: dup
/*    */     //   632: astore #10
/*    */     //   634: invokespecial <init> : ()V
/*    */     //   637: invokevirtual LX : ()V
/*    */     //   640: aload_1
/*    */     //   641: invokevirtual aM : ()Z
/*    */     //   644: ifne -> 738
/*    */     //   647: aload_1
/*    */     //   648: dup
/*    */     //   649: getfield bb : Lorg/xmlpull/v1/XmlPullParser;
/*    */     //   652: iconst_2
/*    */     //   653: aconst_null
/*    */     //   654: ldc_w 'fontParam'
/*    */     //   657: invokeinterface require : (ILjava/lang/String;Ljava/lang/String;)V
/*    */     //   662: invokestatic A10 : (Lf/xS;)Lf/Nm0;
/*    */     //   665: dup
/*    */     //   666: astore #11
/*    */     //   668: ifnull -> 730
/*    */     //   671: aload_1
/*    */     //   672: dup
/*    */     //   673: dup
/*    */     //   674: aload #9
/*    */     //   676: aload_0
/*    */     //   677: aload_1
/*    */     //   678: aload #10
/*    */     //   680: aload #11
/*    */     //   682: invokevirtual add : (Ljava/lang/Object;)Z
/*    */     //   685: pop
/*    */     //   686: new f/dt
/*    */     //   689: dup
/*    */     //   690: astore #11
/*    */     //   692: aload #8
/*    */     //   694: invokespecial <init> : (Lf/dt;)V
/*    */     //   697: aload #11
/*    */     //   699: invokevirtual U1 : (Lf/xS;Lf/dt;)V
/*    */     //   702: aload #11
/*    */     //   704: invokevirtual add : (Ljava/lang/Object;)Z
/*    */     //   707: pop
/*    */     //   708: invokevirtual LX : ()V
/*    */     //   711: getfield bb : Lorg/xmlpull/v1/XmlPullParser;
/*    */     //   714: iconst_3
/*    */     //   715: aconst_null
/*    */     //   716: ldc_w 'fontParam'
/*    */     //   719: invokeinterface require : (ILjava/lang/String;Ljava/lang/String;)V
/*    */     //   724: invokevirtual LX : ()V
/*    */     //   727: goto -> 640
/*    */     //   730: aload_1
/*    */     //   731: ldc_w 'Condition required'
/*    */     //   734: invokevirtual s70 : (Ljava/lang/String;)Lorg/xmlpull/v1/XmlPullParserException;
/*    */     //   737: athrow
/*    */     //   738: aload_0
/*    */     //   739: aload #9
/*    */     //   741: dup
/*    */     //   742: aload #8
/*    */     //   744: invokevirtual add : (Ljava/lang/Object;)Z
/*    */     //   747: pop
/*    */     //   748: new f/vc
/*    */     //   751: dup
/*    */     //   752: astore #8
/*    */     //   754: aload #10
/*    */     //   756: iconst_0
/*    */     //   757: anewarray f/Nm0
/*    */     //   760: invokevirtual toArray : ([Ljava/lang/Object;)[Ljava/lang/Object;
/*    */     //   763: checkcast [Lf/Nm0;
/*    */     //   766: invokespecial <init> : ([Lf/Nm0;)V
/*    */     //   769: iconst_0
/*    */     //   770: anewarray f/dt
/*    */     //   773: invokevirtual toArray : ([Ljava/lang/Object;)[Ljava/lang/Object;
/*    */     //   776: checkcast [Lf/dt;
/*    */     //   779: astore #9
/*    */     //   781: getfield cOm1 : Ljava/util/HashMap;
/*    */     //   784: aload #7
/*    */     //   786: invokevirtual get : (Ljava/lang/Object;)Ljava/lang/Object;
/*    */     //   789: checkcast f/pe
/*    */     //   792: checkcast f/t90
/*    */     //   795: aload #6
/*    */     //   797: aload #8
/*    */     //   799: aload #9
/*    */     //   801: invokevirtual clone : (Ljava/lang/String;Lf/vc;[Lf/dt;)Lf/pe;
/*    */     //   804: astore #6
/*    */     //   806: goto -> 843
/*    */     //   809: aload_1
/*    */     //   810: new java/lang/StringBuilder
/*    */     //   813: dup
/*    */     //   814: invokespecial <init> : ()V
/*    */     //   817: ldc_w 'Can't find referenced font '
/*    */     //   820: invokevirtual append : (Ljava/lang/String;)Ljava/lang/StringBuilder;
/*    */     //   823: aload #7
/*    */     //   825: invokevirtual append : (Ljava/lang/String;)Ljava/lang/StringBuilder;
/*    */     //   828: invokevirtual toString : ()Ljava/lang/String;
/*    */     //   831: invokevirtual s70 : (Ljava/lang/String;)Lorg/xmlpull/v1/XmlPullParserException;
/*    */     //   834: athrow
/*    */     //   835: aload_0
/*    */     //   836: aload_1
/*    */     //   837: aload_2
/*    */     //   838: invokevirtual Jd0 : (Lf/xS;Ljava/net/URL;)Lf/t90;
/*    */     //   841: astore #6
/*    */     //   843: aload #6
/*    */     //   845: ifnull -> 881
/*    */     //   848: iload #5
/*    */     //   850: aload_0
/*    */     //   851: getfield cOm1 : Ljava/util/HashMap;
/*    */     //   854: aload #4
/*    */     //   856: aload #6
/*    */     //   858: invokevirtual put : (Ljava/lang/Object;Ljava/lang/Object;)Ljava/lang/Object;
/*    */     //   861: pop
/*    */     //   862: ifne -> 872
/*    */     //   865: aload_0
/*    */     //   866: getfield hS : Lf/pe;
/*    */     //   869: ifnonnull -> 1239
/*    */     //   872: aload_0
/*    */     //   873: aload #6
/*    */     //   875: putfield hS : Lf/pe;
/*    */     //   878: goto -> 1239
/*    */     //   881: aload_1
/*    */     //   882: new java/lang/StringBuilder
/*    */     //   885: dup
/*    */     //   886: invokespecial <init> : ()V
/*    */     //   889: ldc_w 'unable to load font "'
/*    */     //   892: invokevirtual append : (Ljava/lang/String;)Ljava/lang/StringBuilder;
/*    */     //   895: aload #4
/*    */     //   897: invokevirtual append : (Ljava/lang/String;)Ljava/lang/StringBuilder;
/*    */     //   900: ldc_w '"'
/*    */     //   903: invokevirtual append : (Ljava/lang/String;)Ljava/lang/StringBuilder;
/*    */     //   906: invokevirtual toString : ()Ljava/lang/String;
/*    */     //   909: invokevirtual s70 : (Ljava/lang/String;)Lorg/xmlpull/v1/XmlPullParserException;
/*    */     //   912: athrow
/*    */     //   913: ldc_w 'constantDef'
/*    */     //   916: aload_3
/*    */     //   917: invokevirtual equals : (Ljava/lang/Object;)Z
/*    */     //   920: ifeq -> 944
/*    */     //   923: aload_0
/*    */     //   924: dup
/*    */     //   925: getfield ld0 : Lf/q80;
/*    */     //   928: astore #4
/*    */     //   930: aload_1
/*    */     //   931: aload_2
/*    */     //   932: ldc_w 'constantDef'
/*    */     //   935: aconst_null
/*    */     //   936: aload #4
/*    */     //   938: invokevirtual Rc0 : (Lf/xS;Ljava/net/URL;Ljava/lang/String;Lf/L00;Lf/q80;)V
/*    */     //   941: goto -> 1239
/*    */     //   944: aload_1
/*    */     //   945: invokevirtual Zl0 : ()Lorg/xmlpull/v1/XmlPullParserException;
/*    */     //   948: athrow
/*    */     //   949: aload_1
/*    */     //   950: dup
/*    */     //   951: aload_0
/*    */     //   952: getfield Kd : Lf/bn0;
/*    */     //   955: dup
/*    */     //   956: astore #4
/*    */     //   958: invokevirtual getClass : ()Ljava/lang/Class;
/*    */     //   961: pop
/*    */     //   962: getfield bb : Lorg/xmlpull/v1/XmlPullParser;
/*    */     //   965: iconst_2
/*    */     //   966: aconst_null
/*    */     //   967: aconst_null
/*    */     //   968: invokeinterface require : (ILjava/lang/String;Ljava/lang/String;)V
/*    */     //   973: aconst_null
/*    */     //   974: astore #5
/*    */     //   976: ldc_w 'file'
/*    */     //   979: invokevirtual S3 : (Ljava/lang/String;)Ljava/lang/String;
/*    */     //   982: dup
/*    */     //   983: astore #6
/*    */     //   985: ifnull -> 1115
/*    */     //   988: aload #4
/*    */     //   990: getfield WK : Lf/q80;
/*    */     //   993: aload #6
/*    */     //   995: iconst_0
/*    */     //   996: ldc java/lang/String
/*    */     //   998: aconst_null
/*    */     //   999: invokevirtual Yz0 : (Ljava/lang/String;ZLjava/lang/Class;Ljava/lang/Object;)Ljava/lang/Object;
/*    */     //   1002: checkcast java/lang/String
/*    */     //   1005: dup
/*    */     //   1006: astore #5
/*    */     //   1008: ifnull -> 1015
/*    */     //   1011: aload #5
/*    */     //   1013: astore #6
/*    */     //   1015: aload #4
/*    */     //   1017: aload_1
/*    */     //   1018: dup
/*    */     //   1019: dup
/*    */     //   1020: ldc_w 'format'
/*    */     //   1023: invokevirtual S3 : (Ljava/lang/String;)Ljava/lang/String;
/*    */     //   1026: pop
/*    */     //   1027: ldc_w 'filter'
/*    */     //   1030: invokevirtual S3 : (Ljava/lang/String;)Ljava/lang/String;
/*    */     //   1033: astore #5
/*    */     //   1035: ldc_w 'comment'
/*    */     //   1038: invokevirtual S3 : (Ljava/lang/String;)Ljava/lang/String;
/*    */     //   1041: pop
/*    */     //   1042: getfield tJ0 : Lf/VI;
/*    */     //   1045: new java/net/URL
/*    */     //   1048: dup
/*    */     //   1049: astore #7
/*    */     //   1051: aload_2
/*    */     //   1052: aload #6
/*    */     //   1054: invokespecial <init> : (Ljava/net/URL;Ljava/lang/String;)V
/*    */     //   1057: checkcast f/tw
/*    */     //   1060: aload #7
/*    */     //   1062: aload #5
/*    */     //   1064: invokevirtual z10 : (Ljava/net/URL;Ljava/lang/String;)Lf/nK;
/*    */     //   1067: dup
/*    */     //   1068: astore #5
/*    */     //   1070: ifnull -> 1076
/*    */     //   1073: goto -> 1115
/*    */     //   1076: new java/lang/NullPointerException
/*    */     //   1079: dup
/*    */     //   1080: ldc_w 'loadTexture returned null'
/*    */     //   1083: invokespecial <init> : (Ljava/lang/String;)V
/*    */     //   1086: athrow
/*    */     //   1087: astore_0
/*    */     //   1088: aload_1
/*    */     //   1089: new java/lang/StringBuilder
/*    */     //   1092: dup
/*    */     //   1093: invokespecial <init> : ()V
/*    */     //   1096: ldc_w 'Unable to load image file: '
/*    */     //   1099: invokevirtual append : (Ljava/lang/String;)Ljava/lang/StringBuilder;
/*    */     //   1102: aload #6
/*    */     //   1104: invokevirtual append : (Ljava/lang/String;)Ljava/lang/StringBuilder;
/*    */     //   1107: invokevirtual toString : ()Ljava/lang/String;
/*    */     //   1110: aload_0
/*    */     //   1111: invokevirtual q70 : (Ljava/lang/String;Ljava/lang/Throwable;)Lorg/xmlpull/v1/XmlPullParserException;
/*    */     //   1114: athrow
/*    */     //   1115: aload #4
/*    */     //   1117: aload #5
/*    */     //   1119: putfield J : Lf/nK;
/*    */     //   1122: aload_1
/*    */     //   1123: dup
/*    */     //   1124: invokevirtual LX : ()V
/*    */     //   1127: invokevirtual aM : ()Z
/*    */     //   1130: ifne -> 1233
/*    */     //   1133: aload_1
/*    */     //   1134: dup
/*    */     //   1135: dup
/*    */     //   1136: ldc_w 'name'
/*    */     //   1139: invokevirtual Jg0 : (Ljava/lang/String;)Ljava/lang/String;
/*    */     //   1142: dup
/*    */     //   1143: astore #5
/*    */     //   1145: invokestatic n8 : (Lf/xS;Ljava/lang/String;)V
/*    */     //   1148: getfield bb : Lorg/xmlpull/v1/XmlPullParser;
/*    */     //   1151: invokeinterface getName : ()Ljava/lang/String;
/*    */     //   1156: astore #6
/*    */     //   1158: ldc_w 'cursor'
/*    */     //   1161: aload_1
/*    */     //   1162: getfield bb : Lorg/xmlpull/v1/XmlPullParser;
/*    */     //   1165: invokeinterface getName : ()Ljava/lang/String;
/*    */     //   1170: invokevirtual equals : (Ljava/lang/Object;)Z
/*    */     //   1173: ifeq -> 1187
/*    */     //   1176: aload #4
/*    */     //   1178: aload_1
/*    */     //   1179: aload #5
/*    */     //   1181: invokevirtual Mn : (Lf/xS;Ljava/lang/String;)V
/*    */     //   1184: goto -> 1209
/*    */     //   1187: aload #4
/*    */     //   1189: dup
/*    */     //   1190: aload_1
/*    */     //   1191: aload #6
/*    */     //   1193: invokevirtual B30 : (Lf/xS;Ljava/lang/String;)Lf/mX;
/*    */     //   1196: astore #7
/*    */     //   1198: getfield Bd0 : Ljava/util/TreeMap;
/*    */     //   1201: aload #5
/*    */     //   1203: aload #7
/*    */     //   1205: invokevirtual put : (Ljava/lang/Object;Ljava/lang/Object;)Ljava/lang/Object;
/*    */     //   1208: pop
/*    */     //   1209: aload_1
/*    */     //   1210: iconst_3
/*    */     //   1211: istore #5
/*    */     //   1213: aconst_null
/*    */     //   1214: astore #7
/*    */     //   1216: getfield bb : Lorg/xmlpull/v1/XmlPullParser;
/*    */     //   1219: iload #5
/*    */     //   1221: aload #7
/*    */     //   1223: aload #6
/*    */     //   1225: invokeinterface require : (ILjava/lang/String;Ljava/lang/String;)V
/*    */     //   1230: goto -> 1122
/*    */     //   1233: aload #4
/*    */     //   1235: aconst_null
/*    */     //   1236: putfield J : Lf/nK;
/*    */     //   1239: aload_1
/*    */     //   1240: getfield bb : Lorg/xmlpull/v1/XmlPullParser;
/*    */     //   1243: iconst_3
/*    */     //   1244: aconst_null
/*    */     //   1245: aload_3
/*    */     //   1246: invokeinterface require : (ILjava/lang/String;Ljava/lang/String;)V
/*    */     //   1251: goto -> 14
/*    */     //   1254: aload #4
/*    */     //   1256: aconst_null
/*    */     //   1257: putfield J : Lf/nK;
/*    */     //   1260: athrow
/*    */     //   1261: aload_1
/*    */     //   1262: getfield bb : Lorg/xmlpull/v1/XmlPullParser;
/*    */     //   1265: iconst_3
/*    */     //   1266: aconst_null
/*    */     //   1267: ldc_w 'themes'
/*    */     //   1270: invokeinterface require : (ILjava/lang/String;Ljava/lang/String;)V
/*    */     //   1275: return
/*    */     // Line number table:
/*    */     //   Java source line number -> byte code offset
/*    */     //   #1	-> 1
/*    */     //   #2	-> 6
/*    */     //   #3	-> 16
/*    */     //   #4	-> 27
/*    */     //   #5	-> 38
/*    */     //   #6	-> 47
/*    */     //   #7	-> 114
/*    */     //   #8	-> 123
/*    */     //   #9	-> 132
/*    */     //   #10	-> 173
/*    */     //   #11	-> 185
/*    */     //   #12	-> 258
/*    */     //   #13	-> 266
/*    */     //   #14	-> 341
/*    */     //   #15	-> 347
/*    */     //   #16	-> 369
/*    */     //   #17	-> 576
/*    */     //   #18	-> 649
/*    */     //   #19	-> 662
/*    */     //   #20	-> 711
/*    */     //   #21	-> 724
/*    */     //   #22	-> 757
/*    */     //   #23	-> 770
/*    */     //   #24	-> 838
/*    */     //   #25	-> 962
/*    */     //   #26	-> 968
/*    */     //   #27	-> 976
/*    */     //   #28	-> 996
/*    */     //   #29	-> 1002
/*    */     //   #30	-> 1145
/*    */     //   #31	-> 1148
/*    */     //   #32	-> 1158
/*    */     //   #33	-> 1162
/*    */     //   #34	-> 1170
/*    */     //   #35	-> 1216
/*    */     //   #36	-> 1236
/*    */     //   #37	-> 1240
/*    */     //   #38	-> 1257
/*    */     //   #39	-> 1262
/*    */     // Exception table:
/*    */     //   from	to	target	type
/*    */     //   90	93	110	f/TD
/*    */     //   96	110	110	f/TD
/*    */     //   1042	1048	1087	java/io/IOException
/*    */     //   1051	1067	1087	java/io/IOException
/*    */     //   1076	1087	1087	java/io/IOException
/*    */     //   1122	1130	1254	finally
/*    */     //   1133	1142	1254	finally
/*    */     //   1145	1156	1254	finally
/*    */     //   1158	1173	1254	finally
/*    */     //   1176	1196	1254	finally
/*    */     //   1198	1208	1254	finally
/*  9 */     //   1216	1233	1254	finally } public final dH A4(xS paramxS, String paramString, L00 paramL00) { dH dH = dH.TB; if (paramxS.GC("merge", false)) if (paramL00 != null) { Object object; if (object = paramL00.Fy.VV(paramString) instanceof dH) { dH = (dH)object; } else if (object != null) { throw paramxS.s70(B40.df("Can only merge with inputMap - found a ").append(object.getClass().getSimpleName()).toString()); }  } else { throw paramxS.s70("Can't merge on top level"); }   if ((paramString = paramxS.S3("ref")) != null) { dH dH2; dH dH1; if ((dH1 = (dH)this.At.get(paramString)) != null) { dH.getClass(); if (this != dH && this.Sg.length != 0) if (dH.Sg.length == 0) { dH = this; } else { LinkedHashSet linkedHashSet1; this(Arrays.asList((E[])this.Sg)); int j; if ((j = (new LinkedHashSet()).size()) != 0) { int k; dY[] arrayOfDY1; linkedHashSet1.toArray((Object[])(arrayOfDY1 = new dY[k = dH.Sg.length + j])); dY[] arrayOfDY2; int m; byte b; for (m = (arrayOfDY2 = dH.Sg).length, b = 0; b < m; ) { dY dY; if (!linkedHashSet1.contains(dY = arrayOfDY2[b])) { int n = j + 1; arrayOfDY1[j] = dY; j = n; }  b++; }  dH2 = new dH(); if (j != k) { arrayOfDY1 = new dY[j]; System.arraycopy(arrayOfDY1, 0, arrayOfDY1, 0, j); }
/* 10 */                this(arrayOfDY1); dH = dH2; }  }   } else { throw paramxS
/* 11 */           .s70("Undefined input map: " + dH2); }  }  paramxS
/* 12 */       .LX();
/* 13 */     this(); LinkedHashSet linkedHashSet; while (!paramxS.aM()) { paramxS
/* 14 */         .bb.require(2, null, "action");
/* 15 */       paramString = paramxS.Jg0("name");
/* 16 */       paramxS.V60(); 
/* 17 */       try { dY dY; if (!add((E)(dY = dY.IF0(paramxS.bb.nextText(), paramString)))) { Level level = Level.WARNING; String str1 = "Duplicate key stroke: {0}", str2 = dY.bk(); Logger.getLogger(dH.class.getName()).log(level, str1, str2); }  paramxS
/* 18 */           .bb.require(3, null, "action");
/* 19 */         paramxS.LX(); } catch (IllegalArgumentException illegalArgumentException) { throw paramxS.q70("can't parse Keystroke", this); }  }  dH
/* 20 */       .getClass(); int i;
/* 21 */     if ((i = size()) != 0) { int j; dY[] arrayOfDY1; toArray(arrayOfDY1 = new dY[j = dH.Sg.length + i]); dY[] arrayOfDY2; int k; byte b; for (k = (arrayOfDY2 = dH.Sg).length, b = 0; b < k; ) { dY dY; if (!contains(dY = arrayOfDY2[b])) { int m = i + 1; arrayOfDY1[i] = dY; i = m; }  b++; }  dH = new dH(); if (i != j) {
/* 22 */         arrayOfDY1 = new dY[i]; System.arraycopy(arrayOfDY1, 0, arrayOfDY1, 0, i);
/* 23 */       }  this(arrayOfDY1); }  return dH; } public final void U1(xS paramxS, dt paramdt) { byte b = 0; for (int i = paramxS.bb.getAttributeCount(); b < i; ) { if (paramxS.wJ0.get(b)) { HashMap<?, v2> hashMap; boolean bool; String str = paramxS.bb.getAttributeName(b); /* monitor enter ClassFileLocalVariableReferenceExpression{type=ObjectType{java/util/HashMap}, name=null} */ try {  } finally { this = null; /* monitor exit ClassFileLocalVariableReferenceExpression{type=PrimitiveType{primitive=maybe_boolean}, name=null} */ }  }  b++; }  } public final void Rc0(xS paramxS, URL paramURL, String paramString, L00 paramL00, q80 paramq80) { byte b = 2; String str = null; try { Iterator<Map.Entry<K, V>> iterator; paramxS.bb.require(b, str, paramString); String str1 = paramxS.Jg0("name"); paramxS.LX(); Object object = Cb(paramxS, str = paramxS.bb.getName(), this, paramURL, paramL00); byte b2 = 3; String str3 = null; paramxS.bb.require(b2, str3, str); paramxS.LX(); byte b1 = 3; String str2 = null; paramxS.bb.require(b1, str2, paramString); if (object instanceof Map) { Map map = (Map)object; if (paramL00 != null || size() == 1) { paramq80.getClass(); for (iterator = entrySet().iterator(); hasNext(); ) { object = ((Map.Entry)next()).getKey(); paramq80.J10(((Map.Entry)next()).getValue(), (String)object); }  return; }  throw paramxS.s70("constant definitions must define exactly 1 value"); }  VN.n8(paramxS, (String)this); paramq80.J10(object, (String)this); return; } catch (NumberFormatException numberFormatException) { throw paramxS.q70("unable to parse value", this); }  } public final Object Cb(xS paramxS, String paramString1, String paramString2, URL paramURL, L00 paramL00) { // Byte code:
/*    */     //   0: ldc_w 'list'
/*    */     //   3: aload_2
/*    */     //   4: invokevirtual equals : (Ljava/lang/Object;)Z
/*    */     //   7: ifeq -> 111
/*    */     //   10: aload_1
/*    */     //   11: new f/q1
/*    */     //   14: dup
/*    */     //   15: astore_2
/*    */     //   16: aload_0
/*    */     //   17: aload #5
/*    */     //   19: invokespecial <init> : (Lf/dS;Lf/L00;)V
/*    */     //   22: invokevirtual LX : ()V
/*    */     //   25: aload_1
/*    */     //   26: getfield bb : Lorg/xmlpull/v1/XmlPullParser;
/*    */     //   29: invokeinterface getEventType : ()I
/*    */     //   34: iconst_2
/*    */     //   35: if_icmpne -> 43
/*    */     //   38: iconst_1
/*    */     //   39: istore_3
/*    */     //   40: goto -> 45
/*    */     //   43: iconst_0
/*    */     //   44: istore_3
/*    */     //   45: iload_3
/*    */     //   46: ifeq -> 109
/*    */     //   49: aload_1
/*    */     //   50: aload_2
/*    */     //   51: aload_1
/*    */     //   52: aload_0
/*    */     //   53: aload_1
/*    */     //   54: dup
/*    */     //   55: getfield bb : Lorg/xmlpull/v1/XmlPullParser;
/*    */     //   58: invokeinterface getName : ()Ljava/lang/String;
/*    */     //   63: dup
/*    */     //   64: astore_3
/*    */     //   65: aconst_null
/*    */     //   66: aload #4
/*    */     //   68: aload #5
/*    */     //   70: invokevirtual Cb : (Lf/xS;Ljava/lang/String;Ljava/lang/String;Ljava/net/URL;Lf/L00;)Ljava/lang/Object;
/*    */     //   73: astore #6
/*    */     //   75: iconst_3
/*    */     //   76: istore #7
/*    */     //   78: aconst_null
/*    */     //   79: astore #8
/*    */     //   81: getfield bb : Lorg/xmlpull/v1/XmlPullParser;
/*    */     //   84: iload #7
/*    */     //   86: aload #8
/*    */     //   88: aload_3
/*    */     //   89: invokeinterface require : (ILjava/lang/String;Ljava/lang/String;)V
/*    */     //   94: getfield fr0 : Ljava/util/ArrayList;
/*    */     //   97: aload #6
/*    */     //   99: invokevirtual add : (Ljava/lang/Object;)Z
/*    */     //   102: pop
/*    */     //   103: invokevirtual LX : ()V
/*    */     //   106: goto -> 25
/*    */     //   109: aload_2
/*    */     //   110: areturn
/*    */     //   111: ldc_w 'map'
/*    */     //   114: aload_2
/*    */     //   115: invokevirtual equals : (Ljava/lang/Object;)Z
/*    */     //   118: ifeq -> 132
/*    */     //   121: aload_0
/*    */     //   122: aload #5
/*    */     //   124: aload_1
/*    */     //   125: aload_3
/*    */     //   126: aload #4
/*    */     //   128: invokevirtual VX : (Lf/L00;Lf/xS;Ljava/lang/String;Ljava/net/URL;)Lf/q80;
/*    */     //   131: areturn
/*    */     //   132: ldc_w 'inputMapDef'
/*    */     //   135: aload_2
/*    */     //   136: invokevirtual equals : (Ljava/lang/Object;)Z
/*    */     //   139: ifeq -> 151
/*    */     //   142: aload_0
/*    */     //   143: aload_1
/*    */     //   144: aload_3
/*    */     //   145: aload #5
/*    */     //   147: invokevirtual A4 : (Lf/xS;Ljava/lang/String;Lf/L00;)Lf/dH;
/*    */     //   150: areturn
/*    */     //   151: ldc_w 'fontDef'
/*    */     //   154: aload_2
/*    */     //   155: invokevirtual equals : (Ljava/lang/Object;)Z
/*    */     //   158: ifeq -> 169
/*    */     //   161: aload_0
/*    */     //   162: aload_1
/*    */     //   163: aload #4
/*    */     //   165: invokevirtual Jd0 : (Lf/xS;Ljava/net/URL;)Lf/t90;
/*    */     //   168: areturn
/*    */     //   169: ldc_w 'enum'
/*    */     //   172: aload_2
/*    */     //   173: invokevirtual equals : (Ljava/lang/Object;)Z
/*    */     //   176: ifeq -> 252
/*    */     //   179: aload_1
/*    */     //   180: ldc_w 'type'
/*    */     //   183: invokevirtual Jg0 : (Ljava/lang/String;)Ljava/lang/String;
/*    */     //   186: astore_0
/*    */     //   187: getstatic f/dS.O10 : Ljava/util/HashMap;
/*    */     //   190: aload_0
/*    */     //   191: invokevirtual get : (Ljava/lang/Object;)Ljava/lang/Object;
/*    */     //   194: checkcast java/lang/Class
/*    */     //   197: dup
/*    */     //   198: astore_2
/*    */     //   199: ifnull -> 221
/*    */     //   202: aload_1
/*    */     //   203: aload_2
/*    */     //   204: aload_1
/*    */     //   205: dup
/*    */     //   206: invokevirtual V60 : ()V
/*    */     //   209: getfield bb : Lorg/xmlpull/v1/XmlPullParser;
/*    */     //   212: invokeinterface nextText : ()Ljava/lang/String;
/*    */     //   217: invokevirtual dj : (Ljava/lang/Class;Ljava/lang/String;)Ljava/lang/Enum;
/*    */     //   220: areturn
/*    */     //   221: aload_1
/*    */     //   222: new java/lang/StringBuilder
/*    */     //   225: dup
/*    */     //   226: invokespecial <init> : ()V
/*    */     //   229: ldc_w 'enum type "'
/*    */     //   232: invokevirtual append : (Ljava/lang/String;)Ljava/lang/StringBuilder;
/*    */     //   235: aload_0
/*    */     //   236: invokevirtual append : (Ljava/lang/String;)Ljava/lang/StringBuilder;
/*    */     //   239: ldc_w '" not registered'
/*    */     //   242: invokevirtual append : (Ljava/lang/String;)Ljava/lang/StringBuilder;
/*    */     //   245: invokevirtual toString : ()Ljava/lang/String;
/*    */     //   248: invokevirtual s70 : (Ljava/lang/String;)Lorg/xmlpull/v1/XmlPullParserException;
/*    */     //   251: athrow
/*    */     //   252: ldc_w 'bool'
/*    */     //   255: aload_2
/*    */     //   256: invokevirtual equals : (Ljava/lang/Object;)Z
/*    */     //   259: ifeq -> 325
/*    */     //   262: aload_1
/*    */     //   263: dup
/*    */     //   264: invokevirtual V60 : ()V
/*    */     //   267: getfield bb : Lorg/xmlpull/v1/XmlPullParser;
/*    */     //   270: invokeinterface nextText : ()Ljava/lang/String;
/*    */     //   275: astore_0
/*    */     //   276: ldc_w 'true'
/*    */     //   279: aload_0
/*    */     //   280: invokevirtual equals : (Ljava/lang/Object;)Z
/*    */     //   283: ifeq -> 291
/*    */     //   286: iconst_1
/*    */     //   287: istore_0
/*    */     //   288: goto -> 303
/*    */     //   291: ldc_w 'false'
/*    */     //   294: aload_0
/*    */     //   295: invokevirtual equals : (Ljava/lang/Object;)Z
/*    */     //   298: ifeq -> 308
/*    */     //   301: iconst_0
/*    */     //   302: istore_0
/*    */     //   303: iload_0
/*    */     //   304: invokestatic valueOf : (Z)Ljava/lang/Boolean;
/*    */     //   307: areturn
/*    */     //   308: new org/xmlpull/v1/XmlPullParserException
/*    */     //   311: dup
/*    */     //   312: aload_1
/*    */     //   313: getfield bb : Lorg/xmlpull/v1/XmlPullParser;
/*    */     //   316: ldc_w 'boolean value must be 'true' or 'false''
/*    */     //   319: swap
/*    */     //   320: aconst_null
/*    */     //   321: invokespecial <init> : (Ljava/lang/String;Lorg/xmlpull/v1/XmlPullParser;Ljava/lang/Throwable;)V
/*    */     //   324: athrow
/*    */     //   325: aload_1
/*    */     //   326: dup
/*    */     //   327: invokevirtual V60 : ()V
/*    */     //   330: getfield bb : Lorg/xmlpull/v1/XmlPullParser;
/*    */     //   333: invokeinterface nextText : ()Ljava/lang/String;
/*    */     //   338: astore #4
/*    */     //   340: ldc_w 'color'
/*    */     //   343: aload_2
/*    */     //   344: invokevirtual equals : (Ljava/lang/Object;)Z
/*    */     //   347: ifeq -> 361
/*    */     //   350: aload_1
/*    */     //   351: aload #4
/*    */     //   353: aload_0
/*    */     //   354: getfield ld0 : Lf/q80;
/*    */     //   357: invokestatic qs : (Lf/xS;Ljava/lang/String;Lf/q80;)Lf/pRn;
/*    */     //   360: areturn
/*    */     //   361: ldc_w 'float'
/*    */     //   364: aload_2
/*    */     //   365: invokevirtual equals : (Ljava/lang/Object;)Z
/*    */     //   368: ifeq -> 385
/*    */     //   371: aload_0
/*    */     //   372: aload_1
/*    */     //   373: aload #4
/*    */     //   375: invokevirtual Hj : (Lf/xS;Ljava/lang/String;)Ljava/lang/Number;
/*    */     //   378: invokevirtual floatValue : ()F
/*    */     //   381: invokestatic valueOf : (F)Ljava/lang/Float;
/*    */     //   384: areturn
/*    */     //   385: ldc_w 'int'
/*    */     //   388: aload_2
/*    */     //   389: invokevirtual equals : (Ljava/lang/Object;)Z
/*    */     //   392: ifeq -> 409
/*    */     //   395: aload_0
/*    */     //   396: aload_1
/*    */     //   397: aload #4
/*    */     //   399: invokevirtual Hj : (Lf/xS;Ljava/lang/String;)Ljava/lang/Number;
/*    */     //   402: invokevirtual intValue : ()I
/*    */     //   405: invokestatic valueOf : (I)Ljava/lang/Integer;
/*    */     //   408: areturn
/*    */     //   409: ldc_w 'string'
/*    */     //   412: aload_2
/*    */     //   413: invokevirtual equals : (Ljava/lang/Object;)Z
/*    */     //   416: ifeq -> 422
/*    */     //   419: aload #4
/*    */     //   421: areturn
/*    */     //   422: ldc_w 'font'
/*    */     //   425: aload_2
/*    */     //   426: invokevirtual equals : (Ljava/lang/Object;)Z
/*    */     //   429: ifeq -> 483
/*    */     //   432: aload_0
/*    */     //   433: getfield cOm1 : Ljava/util/HashMap;
/*    */     //   436: aload #4
/*    */     //   438: invokevirtual get : (Ljava/lang/Object;)Ljava/lang/Object;
/*    */     //   441: checkcast f/pe
/*    */     //   444: dup
/*    */     //   445: astore_0
/*    */     //   446: ifnull -> 451
/*    */     //   449: aload_0
/*    */     //   450: areturn
/*    */     //   451: aload_1
/*    */     //   452: new java/lang/StringBuilder
/*    */     //   455: dup
/*    */     //   456: invokespecial <init> : ()V
/*    */     //   459: ldc_w 'Font "'
/*    */     //   462: invokevirtual append : (Ljava/lang/String;)Ljava/lang/StringBuilder;
/*    */     //   465: aload #4
/*    */     //   467: invokevirtual append : (Ljava/lang/String;)Ljava/lang/StringBuilder;
/*    */     //   470: ldc_w '" not found'
/*    */     //   473: invokevirtual append : (Ljava/lang/String;)Ljava/lang/StringBuilder;
/*    */     //   476: invokevirtual toString : ()Ljava/lang/String;
/*    */     //   479: invokevirtual s70 : (Ljava/lang/String;)Lorg/xmlpull/v1/XmlPullParserException;
/*    */     //   482: athrow
/*    */     //   483: ldc_w 'border'
/*    */     //   486: aload_2
/*    */     //   487: invokevirtual equals : (Ljava/lang/Object;)Z
/*    */     //   490: ifeq -> 532
/*    */     //   493: aload_0
/*    */     //   494: ldc_w f/uE0
/*    */     //   497: astore_0
/*    */     //   498: getfield oc0 : Lf/Em;
/*    */     //   501: aload_0
/*    */     //   502: aload #4
/*    */     //   504: invokevirtual gt0 : (Ljava/lang/Class;Ljava/lang/String;)Ljava/lang/Object;
/*    */     //   507: areturn
/*    */     //   508: astore_0
/*    */     //   509: aload_0
/*    */     //   510: ldc_w 'unable to evaluate'
/*    */     //   513: astore_2
/*    */     //   514: invokevirtual getCause : ()Ljava/lang/Throwable;
/*    */     //   517: ifnull -> 525
/*    */     //   520: aload_0
/*    */     //   521: invokevirtual getCause : ()Ljava/lang/Throwable;
/*    */     //   524: astore_0
/*    */     //   525: aload_1
/*    */     //   526: aload_2
/*    */     //   527: aload_0
/*    */     //   528: invokevirtual q70 : (Ljava/lang/String;Ljava/lang/Throwable;)Lorg/xmlpull/v1/XmlPullParserException;
/*    */     //   531: athrow
/*    */     //   532: ldc_w 'dimension'
/*    */     //   535: aload_2
/*    */     //   536: invokevirtual equals : (Ljava/lang/Object;)Z
/*    */     //   539: ifeq -> 581
/*    */     //   542: aload_0
/*    */     //   543: ldc_w f/db
/*    */     //   546: astore_0
/*    */     //   547: getfield oc0 : Lf/Em;
/*    */     //   550: aload_0
/*    */     //   551: aload #4
/*    */     //   553: invokevirtual gt0 : (Ljava/lang/Class;Ljava/lang/String;)Ljava/lang/Object;
/*    */     //   556: areturn
/*    */     //   557: astore_0
/*    */     //   558: aload_0
/*    */     //   559: ldc_w 'unable to evaluate'
/*    */     //   562: astore_2
/*    */     //   563: invokevirtual getCause : ()Ljava/lang/Throwable;
/*    */     //   566: ifnull -> 574
/*    */     //   569: aload_0
/*    */     //   570: invokevirtual getCause : ()Ljava/lang/Throwable;
/*    */     //   573: astore_0
/*    */     //   574: aload_1
/*    */     //   575: aload_2
/*    */     //   576: aload_0
/*    */     //   577: invokevirtual q70 : (Ljava/lang/String;Ljava/lang/Throwable;)Lorg/xmlpull/v1/XmlPullParserException;
/*    */     //   580: athrow
/*    */     //   581: ldc_w 'gap'
/*    */     //   584: aload_2
/*    */     //   585: invokevirtual equals : (Ljava/lang/Object;)Z
/*    */     //   588: ifne -> 934
/*    */     //   591: ldc_w 'size'
/*    */     //   594: aload_2
/*    */     //   595: invokevirtual equals : (Ljava/lang/Object;)Z
/*    */     //   598: ifeq -> 604
/*    */     //   601: goto -> 934
/*    */     //   604: ldc_w 'constant'
/*    */     //   607: aload_2
/*    */     //   608: invokevirtual equals : (Ljava/lang/Object;)Z
/*    */     //   611: ifeq -> 668
/*    */     //   614: aload_0
/*    */     //   615: getfield ld0 : Lf/q80;
/*    */     //   618: getfield Fy : Lf/XR;
/*    */     //   621: aload #4
/*    */     //   623: invokevirtual VV : (Ljava/lang/Object;)Ljava/lang/Object;
/*    */     //   626: dup
/*    */     //   627: astore_0
/*    */     //   628: ifnull -> 642
/*    */     //   631: aload_0
/*    */     //   632: getstatic f/dS.Z3 : Ljava/lang/Object;
/*    */     //   635: if_acmpne -> 640
/*    */     //   638: aconst_null
/*    */     //   639: astore_0
/*    */     //   640: aload_0
/*    */     //   641: areturn
/*    */     //   642: aload_1
/*    */     //   643: new java/lang/StringBuilder
/*    */     //   646: dup
/*    */     //   647: invokespecial <init> : ()V
/*    */     //   650: ldc_w 'Unknown constant: '
/*    */     //   653: invokevirtual append : (Ljava/lang/String;)Ljava/lang/StringBuilder;
/*    */     //   656: aload #4
/*    */     //   658: invokevirtual append : (Ljava/lang/String;)Ljava/lang/StringBuilder;
/*    */     //   661: invokevirtual toString : ()Ljava/lang/String;
/*    */     //   664: invokevirtual s70 : (Ljava/lang/String;)Lorg/xmlpull/v1/XmlPullParserException;
/*    */     //   667: athrow
/*    */     //   668: ldc_w 'image'
/*    */     //   671: aload_2
/*    */     //   672: invokevirtual equals : (Ljava/lang/Object;)Z
/*    */     //   675: ifeq -> 731
/*    */     //   678: aload #4
/*    */     //   680: ldc_w '.*'
/*    */     //   683: invokevirtual endsWith : (Ljava/lang/String;)Z
/*    */     //   686: ifeq -> 720
/*    */     //   689: aload_3
/*    */     //   690: ifnull -> 709
/*    */     //   693: aload_0
/*    */     //   694: getfield Kd : Lf/bn0;
/*    */     //   697: getfield Bd0 : Ljava/util/TreeMap;
/*    */     //   700: aload #4
/*    */     //   702: aconst_null
/*    */     //   703: aload_3
/*    */     //   704: swap
/*    */     //   705: invokestatic W9 : (Ljava/util/TreeMap;Ljava/lang/String;Ljava/lang/String;Lf/JB;)Ljava/util/Map;
/*    */     //   708: areturn
/*    */     //   709: new java/lang/IllegalArgumentException
/*    */     //   712: dup
/*    */     //   713: ldc_w 'Wildcard's not allowed'
/*    */     //   716: invokespecial <init> : (Ljava/lang/String;)V
/*    */     //   719: athrow
/*    */     //   720: aload_0
/*    */     //   721: getfield Kd : Lf/bn0;
/*    */     //   724: aload_1
/*    */     //   725: aload #4
/*    */     //   727: invokevirtual Mi0 : (Lf/xS;Ljava/lang/String;)Lf/mX;
/*    */     //   730: areturn
/*    */     //   731: ldc_w 'cursor'
/*    */     //   734: aload_2
/*    */     //   735: invokevirtual equals : (Ljava/lang/Object;)Z
/*    */     //   738: ifeq -> 848
/*    */     //   741: aload #4
/*    */     //   743: ldc_w '.*'
/*    */     //   746: invokevirtual endsWith : (Ljava/lang/String;)Z
/*    */     //   749: ifeq -> 785
/*    */     //   752: aload_3
/*    */     //   753: ifnull -> 774
/*    */     //   756: aload_0
/*    */     //   757: getfield Kd : Lf/bn0;
/*    */     //   760: getfield js0 : Ljava/util/TreeMap;
/*    */     //   763: aload #4
/*    */     //   765: getstatic f/bn0.mq0 : Lf/JB;
/*    */     //   768: aload_3
/*    */     //   769: swap
/*    */     //   770: invokestatic W9 : (Ljava/util/TreeMap;Ljava/lang/String;Ljava/lang/String;Lf/JB;)Ljava/util/Map;
/*    */     //   773: areturn
/*    */     //   774: new java/lang/IllegalArgumentException
/*    */     //   777: dup
/*    */     //   778: ldc_w 'Wildcard's not allowed'
/*    */     //   781: invokespecial <init> : (Ljava/lang/String;)V
/*    */     //   784: athrow
/*    */     //   785: aload_0
/*    */     //   786: getfield Kd : Lf/bn0;
/*    */     //   789: getfield js0 : Ljava/util/TreeMap;
/*    */     //   792: aload #4
/*    */     //   794: invokevirtual get : (Ljava/lang/Object;)Ljava/lang/Object;
/*    */     //   797: checkcast f/JE0
/*    */     //   800: dup
/*    */     //   801: astore_0
/*    */     //   802: ifnull -> 816
/*    */     //   805: aload_0
/*    */     //   806: getstatic f/bn0.mq0 : Lf/JB;
/*    */     //   809: if_acmpne -> 814
/*    */     //   812: aconst_null
/*    */     //   813: astore_0
/*    */     //   814: aload_0
/*    */     //   815: areturn
/*    */     //   816: aload_1
/*    */     //   817: new java/lang/StringBuilder
/*    */     //   820: dup
/*    */     //   821: invokespecial <init> : ()V
/*    */     //   824: ldc_w 'referenced cursor "'
/*    */     //   827: invokevirtual append : (Ljava/lang/String;)Ljava/lang/StringBuilder;
/*    */     //   830: aload #4
/*    */     //   832: invokevirtual append : (Ljava/lang/String;)Ljava/lang/StringBuilder;
/*    */     //   835: ldc_w '" not found'
/*    */     //   838: invokevirtual append : (Ljava/lang/String;)Ljava/lang/StringBuilder;
/*    */     //   841: invokevirtual toString : ()Ljava/lang/String;
/*    */     //   844: invokevirtual s70 : (Ljava/lang/String;)Lorg/xmlpull/v1/XmlPullParserException;
/*    */     //   847: athrow
/*    */     //   848: ldc_w 'inputMap'
/*    */     //   851: aload_2
/*    */     //   852: invokevirtual equals : (Ljava/lang/Object;)Z
/*    */     //   855: ifeq -> 903
/*    */     //   858: aload_0
/*    */     //   859: getfield At : Ljava/util/HashMap;
/*    */     //   862: aload #4
/*    */     //   864: invokevirtual get : (Ljava/lang/Object;)Ljava/lang/Object;
/*    */     //   867: checkcast f/dH
/*    */     //   870: dup
/*    */     //   871: astore_0
/*    */     //   872: ifnull -> 877
/*    */     //   875: aload_0
/*    */     //   876: areturn
/*    */     //   877: aload_1
/*    */     //   878: new java/lang/StringBuilder
/*    */     //   881: dup
/*    */     //   882: invokespecial <init> : ()V
/*    */     //   885: ldc_w 'Undefined input map: '
/*    */     //   888: invokevirtual append : (Ljava/lang/String;)Ljava/lang/StringBuilder;
/*    */     //   891: aload #4
/*    */     //   893: invokevirtual append : (Ljava/lang/String;)Ljava/lang/StringBuilder;
/*    */     //   896: invokevirtual toString : ()Ljava/lang/String;
/*    */     //   899: invokevirtual s70 : (Ljava/lang/String;)Lorg/xmlpull/v1/XmlPullParserException;
/*    */     //   902: athrow
/*    */     //   903: aload_1
/*    */     //   904: new java/lang/StringBuilder
/*    */     //   907: dup
/*    */     //   908: invokespecial <init> : ()V
/*    */     //   911: ldc_w 'Unknown type "'
/*    */     //   914: invokevirtual append : (Ljava/lang/String;)Ljava/lang/StringBuilder;
/*    */     //   917: aload_2
/*    */     //   918: invokevirtual append : (Ljava/lang/String;)Ljava/lang/StringBuilder;
/*    */     //   921: ldc_w '" specified'
/*    */     //   924: invokevirtual append : (Ljava/lang/String;)Ljava/lang/StringBuilder;
/*    */     //   927: invokevirtual toString : ()Ljava/lang/String;
/*    */     //   930: invokevirtual s70 : (Ljava/lang/String;)Lorg/xmlpull/v1/XmlPullParserException;
/*    */     //   933: athrow
/*    */     //   934: aload_0
/*    */     //   935: ldc_w f/TI0
/*    */     //   938: astore_0
/*    */     //   939: getfield oc0 : Lf/Em;
/*    */     //   942: aload_0
/*    */     //   943: aload #4
/*    */     //   945: invokevirtual gt0 : (Ljava/lang/Class;Ljava/lang/String;)Ljava/lang/Object;
/*    */     //   948: areturn
/*    */     //   949: astore_0
/*    */     //   950: aload_0
/*    */     //   951: ldc_w 'unable to evaluate'
/*    */     //   954: astore_2
/*    */     //   955: invokevirtual getCause : ()Ljava/lang/Throwable;
/*    */     //   958: ifnull -> 966
/*    */     //   961: aload_0
/*    */     //   962: invokevirtual getCause : ()Ljava/lang/Throwable;
/*    */     //   965: astore_0
/*    */     //   966: aload_1
/*    */     //   967: aload_2
/*    */     //   968: aload_0
/*    */     //   969: invokevirtual q70 : (Ljava/lang/String;Ljava/lang/Throwable;)Lorg/xmlpull/v1/XmlPullParserException;
/*    */     //   972: athrow
/*    */     //   973: astore_0
/*    */     //   974: aload_1
/*    */     //   975: ldc_w 'unable to parse value'
/*    */     //   978: aload_0
/*    */     //   979: invokevirtual q70 : (Ljava/lang/String;Ljava/lang/Throwable;)Lorg/xmlpull/v1/XmlPullParserException;
/*    */     //   982: athrow
/*    */     // Line number table:
/*    */     //   Java source line number -> byte code offset
/*    */     //   #1	-> 11
/*    */     //   #2	-> 26
/*    */     //   #3	-> 55
/*    */     //   #4	-> 70
/*    */     //   #5	-> 81
/*    */     //   #6	-> 94
/*    */     //   #7	-> 111
/*    */     //   #8	-> 206
/*    */     //   #9	-> 217
/*    */     //   #10	-> 222
/*    */     //   #11	-> 264
/*    */     //   #12	-> 276
/*    */     //   #13	-> 304
/*    */     //   #14	-> 308
/*    */     //   #15	-> 327
/*    */     //   #16	-> 340
/*    */     //   #17	-> 498
/*    */     //   #18	-> 514
/*    */     //   #19	-> 528
/*    */     //   #20	-> 532
/*    */     //   #21	-> 547
/*    */     //   #22	-> 563
/*    */     //   #23	-> 577
/*    */     //   #24	-> 581
/*    */     //   #25	-> 618
/*    */     //   #26	-> 623
/*    */     //   #27	-> 632
/*    */     //   #28	-> 697
/*    */     //   #29	-> 705
/*    */     //   #30	-> 709
/*    */     //   #31	-> 760
/*    */     //   #32	-> 765
/*    */     //   #33	-> 774
/*    */     //   #34	-> 789
/*    */     //   #35	-> 794
/*    */     //   #36	-> 806
/*    */     //   #37	-> 817
/*    */     //   #38	-> 848
/*    */     //   #39	-> 859
/*    */     //   #40	-> 904
/*    */     //   #41	-> 939
/*    */     //   #42	-> 955
/*    */     //   #43	-> 969
/*    */     //   #44	-> 975
/*    */     // Exception table:
/*    */     //   from	to	target	type
/*    */     //   0	7	973	java/lang/NumberFormatException
/*    */     //   10	14	973	java/lang/NumberFormatException
/*    */     //   16	34	973	java/lang/NumberFormatException
/*    */     //   49	63	973	java/lang/NumberFormatException
/*    */     //   65	73	973	java/lang/NumberFormatException
/*    */     //   81	102	973	java/lang/NumberFormatException
/*    */     //   103	109	973	java/lang/NumberFormatException
/*    */     //   111	118	973	java/lang/NumberFormatException
/*    */     //   121	131	973	java/lang/NumberFormatException
/*    */     //   132	139	973	java/lang/NumberFormatException
/*    */     //   142	150	973	java/lang/NumberFormatException
/*    */     //   151	158	973	java/lang/NumberFormatException
/*    */     //   161	168	973	java/lang/NumberFormatException
/*    */     //   169	176	973	java/lang/NumberFormatException
/*    */     //   179	186	973	java/lang/NumberFormatException
/*    */     //   187	197	973	java/lang/NumberFormatException
/*    */     //   202	220	973	java/lang/NumberFormatException
/*    */     //   221	259	973	java/lang/NumberFormatException
/*    */     //   262	275	973	java/lang/NumberFormatException
/*    */     //   276	283	973	java/lang/NumberFormatException
/*    */     //   291	298	973	java/lang/NumberFormatException
/*    */     //   303	307	973	java/lang/NumberFormatException
/*    */     //   308	338	973	java/lang/NumberFormatException
/*    */     //   340	347	973	java/lang/NumberFormatException
/*    */     //   350	360	973	java/lang/NumberFormatException
/*    */     //   361	368	973	java/lang/NumberFormatException
/*    */     //   371	384	973	java/lang/NumberFormatException
/*    */     //   385	392	973	java/lang/NumberFormatException
/*    */     //   395	408	973	java/lang/NumberFormatException
/*    */     //   409	416	973	java/lang/NumberFormatException
/*    */     //   422	429	973	java/lang/NumberFormatException
/*    */     //   432	444	973	java/lang/NumberFormatException
/*    */     //   451	490	973	java/lang/NumberFormatException
/*    */     //   493	497	973	java/lang/NumberFormatException
/*    */     //   498	507	508	java/text/ParseException
/*    */     //   498	507	973	java/lang/NumberFormatException
/*    */     //   509	513	973	java/lang/NumberFormatException
/*    */     //   514	517	973	java/lang/NumberFormatException
/*    */     //   520	524	973	java/lang/NumberFormatException
/*    */     //   525	539	973	java/lang/NumberFormatException
/*    */     //   542	546	973	java/lang/NumberFormatException
/*    */     //   547	556	557	java/text/ParseException
/*    */     //   547	556	973	java/lang/NumberFormatException
/*    */     //   558	562	973	java/lang/NumberFormatException
/*    */     //   563	566	973	java/lang/NumberFormatException
/*    */     //   569	573	973	java/lang/NumberFormatException
/*    */     //   574	588	973	java/lang/NumberFormatException
/*    */     //   591	598	973	java/lang/NumberFormatException
/*    */     //   604	611	973	java/lang/NumberFormatException
/*    */     //   614	626	973	java/lang/NumberFormatException
/*    */     //   631	635	973	java/lang/NumberFormatException
/*    */     //   642	675	973	java/lang/NumberFormatException
/*    */     //   678	686	973	java/lang/NumberFormatException
/*    */     //   693	700	973	java/lang/NumberFormatException
/*    */     //   703	708	973	java/lang/NumberFormatException
/*    */     //   709	730	973	java/lang/NumberFormatException
/*    */     //   731	738	973	java/lang/NumberFormatException
/*    */     //   741	749	973	java/lang/NumberFormatException
/*    */     //   756	773	973	java/lang/NumberFormatException
/*    */     //   774	800	973	java/lang/NumberFormatException
/*    */     //   805	809	973	java/lang/NumberFormatException
/*    */     //   816	855	973	java/lang/NumberFormatException
/*    */     //   858	870	973	java/lang/NumberFormatException
/*    */     //   877	938	973	java/lang/NumberFormatException
/*    */     //   939	948	949	java/text/ParseException
/*    */     //   939	948	973	java/lang/NumberFormatException
/*    */     //   950	954	973	java/lang/NumberFormatException
/*    */     //   955	958	973	java/lang/NumberFormatException
/*    */     //   961	965	973	java/lang/NumberFormatException
/* 23 */     //   966	973	973	java/lang/NumberFormatException } public final L00 FF(L00 paramL001, xS paramxS, String paramString, L00 paramL002, URL paramURL) { VN.n8(paramxS, paramString); if ((paramString.equals("*") && paramL002 == null) || paramString.indexOf('.') < 0) { L00 l001; this(this, paramString, paramL002); L00 l002 = this.oc0.D50; this.oc0.D50 = l001; try { if (paramxS.GC("merge", false)) if (paramL002 != null) { L00 l00; if ((l00 = paramL002.XC0(paramString)) != null) { l001.Fy.Xd0(l00.Fy); l001.Tf.Xd0(l00.Tf); l001.w10 = l00.w10; }  } else { throw paramxS.s70("Can't merge on top level"); }   paramxS.S3("ref"); if (paramL001 != null) { l001.Fy.Xd0(paramL001.Fy); l001.Tf.Xd0(paramL001.Tf); l001.w10 = paramL001.w10; }  l001.a00 = paramxS.GC("allowWildcard", true); paramxS.LX(); while (!paramxS.aM()) { byte b1 = 2; paramString = null; paramL002 = null; paramxS.bb.require(b1, paramString, (String)paramL002); String str = paramxS.bb.getName(); paramString = paramxS.Jg0("name"); if ("param".equals(str)) { paramString = "param"; Rc0(paramxS, paramURL, paramString, l001, l001); } else if ("theme".equals(str)) { if (paramString.length() == 0) { zD(paramxS, l001); } else { paramL002 = be(l001, paramxS, paramString, paramURL); paramL002 = FF(l001.XC0(paramString), paramxS, paramString, l001, paramURL); XR xR = ((l001.XC0(paramString) == null || paramxS.GC("overwrite", false)) ? l001 : l001).Tf; xR.HC(paramString, paramL002); }  } else { throw paramxS.Zl0(); }  byte b2 = 3; paramL002 = null; paramxS.bb.require(b2, (String)paramL002, str); }  return l001; } finally { this.oc0.D50 = l002; }  }  throw paramxS.s70("'.' is not allowed in names"); } public final Number Hj(xS paramxS, String paramString) { try { Em em; (em = this.oc0).rk.clear(); (new SB(paramString, this)).Id(false); if (this.oc0.rk.size() == 1) return tp();  throw new IllegalStateException("Expected one return value on the stack"); } catch (ParseException null) { Throwable throwable; paramString = "unable to evaluate"; if (getCause() != null) throwable = getCause();  throw paramxS.q70(paramString, this); }  } public final void Ka0() { for (Iterator<t90> iterator = this.cOm1.values().iterator(); iterator.hasNext(); ((t90)iterator.next()).destroy()); pe pe1; if ((pe1 = this.hS) != null) { ((t90)pe1).destroy(); this.hS = null; }  this.cOm1.clear(); oF0 oF01; if ((oF01 = this.d70) != null) { for (Hc0 hc0 = oF01.dA.r30(); hc0.hasNext();) ((jk0)hc0.next()).MO.dispose();  this.d70.dispose(); this.d70 = null; }  this.W40.destroy(); } public final L00 be(L00 paramL00, xS paramxS, String paramString, URL paramURL) { VN.n8(paramxS, paramString); if ((paramString.equals("*") && paramL00 == null) || paramString.indexOf('.') < 0) { L00 l001; this(this, paramString, paramL00); L00 l002 = this.oc0.D50; this.oc0.D50 = l001; try { if (paramxS.GC("merge", false)) if (paramL00 != null) { L00 l00; if ((l00 = paramL00.XC0(paramString)) != null) { l001.Fy.Xd0(l00.Fy); l001.Tf.Xd0(l00.Tf); l001.w10 = l00.w10; }  } else { throw paramxS.s70("Can't merge on top level"); }   paramxS.S3("overwrite"); if ((paramString = paramxS.S3("ref")) != null) { L00 l00 = null; if (paramL00 != null) l00 = paramL00.XC0(paramString);  if (l00 == null) l00 = (L00)GK(paramString, true, true);  if (l00 != null) { l001.Fy.Xd0(l00.Fy); l001.Tf.Xd0(l00.Tf); l001.w10 = l00.w10; } else { throw paramxS.s70("referenced theme info not found: " + paramString); }  }  l001.a00 = paramxS.GC("allowWildcard", true); paramxS.LX(); while (!paramxS.aM()) { byte b1 = 2; paramString = null; String str2 = null; paramxS.bb.require(b1, paramString, str2); String str1 = paramxS.bb.getName(); paramString = paramxS.Jg0("name"); if ("param".equals(str1)) { paramString = "param"; Rc0(paramxS, paramURL, paramString, l001, l001); } else if ("theme".equals(str1)) { if (paramString.length() == 0) { zD(paramxS, l001); } else { L00 l00 = be(l001, paramxS, paramString, paramURL); l001.Tf.HC(paramString, l00); }  } else { throw paramxS.Zl0(); }  byte b2 = 3; str2 = null; paramxS.bb.require(b2, str2, str1); }  return l001; } finally { this.oc0.D50 = l002; }  }  throw paramxS.s70("'.' is not allowed in names"); } public final t90 Jd0(xS paramxS, URL paramURL) { String str1 = paramxS.Jg0("name"); String str2; if ((str2 = paramxS.S3("filename")) != null) { URL uRL; this(paramURL, str2); paramURL = uRL; }  if ((str2 = paramxS.S3("families")) != null) { eL eL = gh0(0, str2); } else { str2 = null; }  if (str2 != null) { Hj(paramxS, paramxS.Jg0("size")).intValue(); String str; if ((str = paramxS.S3("style")) != null) { eL eL = gh0(0, str); } else { str = null; }  while (str != null) { if (!"bold".equalsIgnoreCase(((eL)str).F2)) "italic".equalsIgnoreCase(((eL)str).F2);  eL eL = ((eL)str).aF; }  }  this(); vc vc; dt dt; ArrayList<dt> arrayList; ArrayList<Nm0> arrayList1; U1(paramxS, dt); this(); this(); paramxS.LX(); while (!paramxS.aM()) { paramxS.bb.require(2, null, "fontParam"); Nm0 nm0; if ((nm0 = VN.A10(paramxS)) != null) { dt dt1; arrayList1.add(nm0); this(dt); U1(paramxS, dt1); arrayList.add(dt1); paramxS.LX(); paramxS.bb.require(3, null, "fontParam"); paramxS.LX(); continue; }  throw paramxS.s70("Condition required"); }  arrayList.add(dt); Nm0[] arrayOfNm0; this(arrayOfNm0 = arrayList1.toArray(new Nm0[0])); dt[] arrayOfDt = arrayList.<dt>toArray(new dt[0]); if (str2 != null) this.Lpt5.getClass();  tw tw; (tw = (tw)this.Lpt5).getClass(); if (arrayOfDt != null) { if (arrayOfNm0.length + 1 == arrayOfDt.length) { t90 t90; G g; this(); String[] arrayOfString; boolean bool1, bool2; int i; byte b; for ((new G()).mV = true, (new G()).Io = pD0.El0, arrayOfString = new String[0], bool1 = false, bool2 = false, i = arrayOfDt.length, b = 0; b < i; ) { g.gJ = ((Boolean)dt1.xD(dt.cL0)).booleanValue(); g.A = ((Integer)dt1.xD(dt.Zn0)).intValue(); int j = ((Integer)dt1.xD(dt.l80)).intValue(); g.Iz0 = ((Boolean)dt1.xD(dt.Ym)).booleanValue(); g.Io = (pD0)dt1.xD(dt.CL0); pD0 pD0 = (pD0)dt1.xD(dt.AT); g.ic = ((Float)dt1.xD(dt.qQ)).floatValue(); g.Ma = ((Integer)dt1.xD(dt.S50)).intValue(); g.hj = ((Float)dt1.xD(dt.lo)).floatValue(); pRn pRn = (pRn)dt1.xD(dt.R7); this(); color.a = pRn.Zg0(); color.r = pRn.pT(); color.g = pRn.bf(); Color color; (color = new Color()).b = pRn.x3(); g.eh = new Color(); g.qH0 = ((Boolean)dt1.xD(dt.oz0)).booleanValue(); g.lx = ((Float)dt1.xD(dt.iN)).floatValue(); g.Lp = ((Integer)dt1.xD(dt.M80)).intValue(); g.YA = ((Integer)dt1.xD(dt.Nl0)).intValue(); pRn = (pRn)dt1.xD(dt.Rf0); this(); color.a = pRn.Zg0(); color.r = pRn.pT(); color.g = pRn.bf(); (color = new Color()).b = pRn.x3(); g.m5 = new Color(); g.Q60 = ((Integer)dt1.xD(dt.Wy0)).intValue(); g.XJ = ((Integer)dt1.xD(dt.rK0)).intValue(); g.Bd = ((Boolean)dt1.xD(dt.pW)).booleanValue(); g.uX = (cu0)dt1.xD(dt.vw); g.IS = (cu0)dt1.xD(dt.CN); pRn = (pRn)dt1.xD(dt.kC0); this(); color.a = pRn.Zg0(); color.r = pRn.pT(); color.g = pRn.bf(); (color = new Color()).b = pRn.x3(); g.Wh = new Color(); g.u5 = (String)dt1.xD(dt.j10); dt dt1; String[] arrayOfString1 = ((String)(dt1 = arrayOfDt[b]).xD(dt.Or)).split(","); boolean bool3 = ((Boolean)arrayOfDt[b].xD(dt.pc0)).booleanValue(), bool4 = ((Boolean)arrayOfDt[b].xD(dt.jj0)).booleanValue(); if (t90.bigCJKFontSizes()) { if (j > 0) g.A = j;  if (pD0 != pD0.Gh0) g.Io = pD0;  }  b++; bool2 = bool4; bool1 = bool3; arrayOfString = arrayOfString1; }  RD0 rD0 = null; try { rD0 = (RD0)paramURL.getContent(); } catch (IOException iOException) { null.printStackTrace(); }  if (rD0 == null || !rD0.L0())
/* 24 */         { Logger.getLogger(tw.class.getName())
/*    */ 
/*    */             
/* 27 */             .log(Level.WARNING, B40.df("Couldn't locate font file: ").append(paramURL.getPath()).append(" fh = ").append(rD0).toString()); return null; }  hK0 hK0 = this.FF; this(str1, this, rD0, g, vc, arrayOfString, bool1, bool2, hK0, arrayOfDt); return t90; }  throw new IllegalArgumentException("select.getNumExpressions() + 1 != parameterList.length"); }  throw new NullPointerException("parameterList"); }
/*    */ 
/*    */   
/*    */   public final q80 VX(L00 paramL00, xS paramxS, String paramString, URL paramURL) {
/*    */     this(this, paramL00);
/*    */     q80 q801;
/*    */     if (paramxS.GC("merge", false))
/*    */       if (paramL00 != null) {
/*    */         Object object;
/*    */         if (object = paramL00.Fy.VV(paramString) instanceof q80) {
/*    */           object = object;
/*    */           q801.Fy.Xd0(((q80)object).Fy);
/*    */         } else if (object != null) {
/*    */           throw paramxS.s70(B40.df("Can only merge with map - found a ").append(object.getClass().getSimpleName()).toString());
/*    */         } 
/*    */       } else {
/*    */         throw paramxS.s70("Can't merge on top level");
/*    */       }  
/*    */     if ((paramString = paramxS.S3("ref")) != null) {
/*    */       q80 q802;
/*    */       Object object;
/*    */       if ((object = paramL00.Fy.VV(paramString)) != null || (object = this.ld0.Fy.VV(paramString)) != null) {
/*    */         if (object instanceof q80) {
/*    */           q802 = (q80)object;
/*    */           q801.Fy.Xd0(q802.Fy);
/*    */         } else {
/*    */           throw new IOException(B40.df("Expected a map got a ").append(object.getClass().getSimpleName()).toString());
/*    */         } 
/*    */       } else {
/*    */         throw new IOException(m0.tF0("Referenced map not found: ", q802));
/*    */       } 
/*    */     } 
/*    */     paramxS.LX();
/*    */     while ((paramxS.bb.getEventType() == 2)) {
/*    */       paramString = paramxS.bb.getName();
/*    */       Rc0(paramxS, paramURL, "param", paramL00, q801);
/*    */       paramxS.bb.require(3, null, paramString);
/*    */       paramxS.LX();
/*    */     } 
/*    */     return q801;
/*    */   } }


/* Location:              /Users/vnnsnnt/Documents/Codespace/JavaWorkspace/RedTrainer/src/main/java/org/trainer/client/PokeMMO.jar!/f/dS.class
 * Java compiler version: 8 (52.0)
 * JD-Core Version:       1.1.3
 */