/* 1 */ package f;public final class Du { public final int ua(int paramInt) { int k; short[] arrayOfShort = this.qw; if (paramInt == 0) { k = this.Hw; } else { k = paramInt; }
/* 2 */      paramInt = arrayOfShort[k - 1] * 2; int j = arrayOfShort[paramInt] * 2;
/*   */     
/* 4 */     int i = arrayOfShort[(paramInt + 1) % this.Hw] * 2; float f2 = arrayOfFloat[paramInt], f3 = arrayOfFloat[paramInt + 1], f4 = arrayOfFloat[j], f1 = arrayOfFloat[i]; f2 = NUL.df(f3, arrayOfFloat[i + 1], f4, (arrayOfFloat[i + 1] - f5) * f2); float arrayOfFloat[], f5;
/* 5 */     return (int)Math.signum(((f5 = (arrayOfFloat = this.xd)[j + 1]) - f3) * f1 + f2); }
/*   */ 
/*   */   
/*   */   public final Wk0 Dc0;
/*   */   public short[] qw;
/*   */   public float[] xd;
/*   */   public int Hw;
/*   */   public final o0 Ek0;
/*   */   public final Wk0 jh0;
/*   */   
/*   */   public Du() {
/*   */     Wk0 wk02;
/*   */     o0 o01;
/*   */     Wk0 wk01;
/*   */     this();
/*   */     this.Dc0 = this;
/*   */     this();
/*   */     this.Ek0 = this;
/*   */     this();
/*   */     this.jh0 = this;
/*   */   }
/*   */   
/*   */   public final Wk0 C5(float[] paramArrayOffloat) {
/*   */     // Byte code:
/*   */     //   0: aload_1
/*   */     //   1: iconst_0
/*   */     //   2: istore_2
/*   */     //   3: arraylength
/*   */     //   4: dup
/*   */     //   5: istore_3
/*   */     //   6: aload_0
/*   */     //   7: dup
/*   */     //   8: dup
/*   */     //   9: iload_3
/*   */     //   10: aload_0
/*   */     //   11: aload_1
/*   */     //   12: putfield xd : [F
/*   */     //   15: iconst_2
/*   */     //   16: idiv
/*   */     //   17: dup
/*   */     //   18: istore #4
/*   */     //   20: putfield Hw : I
/*   */     //   23: iconst_0
/*   */     //   24: istore #5
/*   */     //   26: getfield Dc0 : Lf/Wk0;
/*   */     //   29: dup
/*   */     //   30: dup2
/*   */     //   31: iconst_0
/*   */     //   32: putfield AK0 : I
/*   */     //   35: iload #4
/*   */     //   37: invokevirtual JA0 : (I)V
/*   */     //   40: iload #4
/*   */     //   42: putfield AK0 : I
/*   */     //   45: getfield YJ0 : [S
/*   */     //   48: dup
/*   */     //   49: astore #6
/*   */     //   51: putfield qw : [S
/*   */     //   54: getstatic f/Go0.P30 : I
/*   */     //   57: pop
/*   */     //   58: iconst_2
/*   */     //   59: if_icmpgt -> 65
/*   */     //   62: goto -> 138
/*   */     //   65: aload_1
/*   */     //   66: iload_3
/*   */     //   67: iload_2
/*   */     //   68: fconst_0
/*   */     //   69: fstore_3
/*   */     //   70: iadd
/*   */     //   71: iconst_2
/*   */     //   72: isub
/*   */     //   73: dup
/*   */     //   74: istore #7
/*   */     //   76: aload_1
/*   */     //   77: iload #7
/*   */     //   79: faload
/*   */     //   80: fstore #8
/*   */     //   82: iconst_1
/*   */     //   83: iadd
/*   */     //   84: faload
/*   */     //   85: fstore #9
/*   */     //   87: iload_2
/*   */     //   88: iload #7
/*   */     //   90: if_icmpgt -> 128
/*   */     //   93: fload #8
/*   */     //   95: aload_1
/*   */     //   96: iload_2
/*   */     //   97: aload_1
/*   */     //   98: iload_2
/*   */     //   99: faload
/*   */     //   100: fstore #8
/*   */     //   102: iconst_1
/*   */     //   103: iadd
/*   */     //   104: faload
/*   */     //   105: dup
/*   */     //   106: fstore #10
/*   */     //   108: fmul
/*   */     //   109: fload #8
/*   */     //   111: fload #9
/*   */     //   113: fmul
/*   */     //   114: fsub
/*   */     //   115: fload_3
/*   */     //   116: fadd
/*   */     //   117: fstore_3
/*   */     //   118: iinc #2, 2
/*   */     //   121: fload #10
/*   */     //   123: fstore #9
/*   */     //   125: goto -> 87
/*   */     //   128: fload_3
/*   */     //   129: fconst_0
/*   */     //   130: fcmpg
/*   */     //   131: ifge -> 138
/*   */     //   134: iconst_1
/*   */     //   135: goto -> 139
/*   */     //   138: iconst_0
/*   */     //   139: ifeq -> 167
/*   */     //   142: iconst_0
/*   */     //   143: istore_1
/*   */     //   144: iload_1
/*   */     //   145: iload #4
/*   */     //   147: if_icmpge -> 197
/*   */     //   150: iload_1
/*   */     //   151: aload #6
/*   */     //   153: iload_1
/*   */     //   154: iload #5
/*   */     //   156: iload_1
/*   */     //   157: iadd
/*   */     //   158: i2s
/*   */     //   159: sastore
/*   */     //   160: iconst_1
/*   */     //   161: iadd
/*   */     //   162: i2s
/*   */     //   163: istore_1
/*   */     //   164: goto -> 144
/*   */     //   167: iload #4
/*   */     //   169: iconst_0
/*   */     //   170: istore_1
/*   */     //   171: iconst_1
/*   */     //   172: isub
/*   */     //   173: istore_2
/*   */     //   174: iload_1
/*   */     //   175: iload #4
/*   */     //   177: if_icmpge -> 197
/*   */     //   180: aload #6
/*   */     //   182: iload_1
/*   */     //   183: iload #5
/*   */     //   185: iload_2
/*   */     //   186: iadd
/*   */     //   187: iload_1
/*   */     //   188: isub
/*   */     //   189: i2s
/*   */     //   190: sastore
/*   */     //   191: iinc #1, 1
/*   */     //   194: goto -> 174
/*   */     //   197: iload #4
/*   */     //   199: aload_0
/*   */     //   200: getfield Ek0 : Lf/o0;
/*   */     //   203: dup
/*   */     //   204: astore_1
/*   */     //   205: iconst_0
/*   */     //   206: dup
/*   */     //   207: istore_2
/*   */     //   208: putfield mG0 : I
/*   */     //   211: iflt -> 985
/*   */     //   214: iload #4
/*   */     //   216: iload_2
/*   */     //   217: iadd
/*   */     //   218: dup
/*   */     //   219: istore_2
/*   */     //   220: aload_1
/*   */     //   221: getfield Ky : [I
/*   */     //   224: arraylength
/*   */     //   225: if_icmple -> 251
/*   */     //   228: aload_1
/*   */     //   229: bipush #8
/*   */     //   231: iload_2
/*   */     //   232: invokestatic max : (II)I
/*   */     //   235: aload_1
/*   */     //   236: getfield mG0 : I
/*   */     //   239: i2f
/*   */     //   240: ldc 1.75
/*   */     //   242: fmul
/*   */     //   243: f2i
/*   */     //   244: invokestatic max : (II)I
/*   */     //   247: invokevirtual YK0 : (I)[I
/*   */     //   250: pop
/*   */     //   251: iconst_0
/*   */     //   252: istore_2
/*   */     //   253: iload_2
/*   */     //   254: iload #4
/*   */     //   256: if_icmpge -> 274
/*   */     //   259: aload_1
/*   */     //   260: aload_0
/*   */     //   261: iload_2
/*   */     //   262: invokevirtual ua : (I)I
/*   */     //   265: invokevirtual oU : (I)V
/*   */     //   268: iinc #2, 1
/*   */     //   271: goto -> 253
/*   */     //   274: aload_0
/*   */     //   275: dup
/*   */     //   276: getfield jh0 : Lf/Wk0;
/*   */     //   279: dup
/*   */     //   280: astore_1
/*   */     //   281: iload #4
/*   */     //   283: aload_1
/*   */     //   284: iconst_0
/*   */     //   285: putfield AK0 : I
/*   */     //   288: iconst_2
/*   */     //   289: isub
/*   */     //   290: iconst_0
/*   */     //   291: swap
/*   */     //   292: invokestatic max : (II)I
/*   */     //   295: iconst_3
/*   */     //   296: imul
/*   */     //   297: invokevirtual JA0 : (I)V
/*   */     //   300: getfield Ek0 : Lf/o0;
/*   */     //   303: getfield Ky : [I
/*   */     //   306: astore_2
/*   */     //   307: aload_0
/*   */     //   308: getfield Hw : I
/*   */     //   311: dup
/*   */     //   312: istore_3
/*   */     //   313: iconst_3
/*   */     //   314: if_icmple -> 947
/*   */     //   317: iconst_0
/*   */     //   318: istore #4
/*   */     //   320: iload #4
/*   */     //   322: iload_3
/*   */     //   323: if_icmpge -> 652
/*   */     //   326: aload_0
/*   */     //   327: getfield Ek0 : Lf/o0;
/*   */     //   330: getfield Ky : [I
/*   */     //   333: dup
/*   */     //   334: astore #5
/*   */     //   336: iload #4
/*   */     //   338: iaload
/*   */     //   339: iconst_m1
/*   */     //   340: if_icmpne -> 346
/*   */     //   343: goto -> 621
/*   */     //   346: iload #4
/*   */     //   348: ifne -> 360
/*   */     //   351: aload_0
/*   */     //   352: getfield Hw : I
/*   */     //   355: istore #6
/*   */     //   357: goto -> 364
/*   */     //   360: iload #4
/*   */     //   362: istore #6
/*   */     //   364: iload #4
/*   */     //   366: iload #6
/*   */     //   368: iconst_1
/*   */     //   369: isub
/*   */     //   370: istore #6
/*   */     //   372: iconst_1
/*   */     //   373: iadd
/*   */     //   374: aload_0
/*   */     //   375: getfield Hw : I
/*   */     //   378: dup
/*   */     //   379: istore #7
/*   */     //   381: irem
/*   */     //   382: dup
/*   */     //   383: istore #8
/*   */     //   385: aload_0
/*   */     //   386: dup
/*   */     //   387: getfield qw : [S
/*   */     //   390: dup
/*   */     //   391: astore #9
/*   */     //   393: iload #8
/*   */     //   395: aload #9
/*   */     //   397: iload #4
/*   */     //   399: aload #9
/*   */     //   401: iload #6
/*   */     //   403: saload
/*   */     //   404: iconst_2
/*   */     //   405: imul
/*   */     //   406: istore #8
/*   */     //   408: saload
/*   */     //   409: iconst_2
/*   */     //   410: imul
/*   */     //   411: istore #10
/*   */     //   413: saload
/*   */     //   414: iconst_2
/*   */     //   415: imul
/*   */     //   416: istore #11
/*   */     //   418: getfield xd : [F
/*   */     //   421: dup
/*   */     //   422: astore #12
/*   */     //   424: iload #11
/*   */     //   426: aload #12
/*   */     //   428: iload #11
/*   */     //   430: aload #12
/*   */     //   432: iload #10
/*   */     //   434: aload #12
/*   */     //   436: iload #10
/*   */     //   438: aload #12
/*   */     //   440: iload #8
/*   */     //   442: aload #12
/*   */     //   444: iload #8
/*   */     //   446: faload
/*   */     //   447: fstore #8
/*   */     //   449: iconst_1
/*   */     //   450: iadd
/*   */     //   451: faload
/*   */     //   452: fstore #10
/*   */     //   454: faload
/*   */     //   455: fstore #11
/*   */     //   457: iconst_1
/*   */     //   458: iadd
/*   */     //   459: faload
/*   */     //   460: fstore #13
/*   */     //   462: faload
/*   */     //   463: fstore #14
/*   */     //   465: iconst_1
/*   */     //   466: iadd
/*   */     //   467: faload
/*   */     //   468: fstore #15
/*   */     //   470: iconst_1
/*   */     //   471: iadd
/*   */     //   472: iload #7
/*   */     //   474: irem
/*   */     //   475: istore #7
/*   */     //   477: iload #7
/*   */     //   479: iload #6
/*   */     //   481: if_icmpeq -> 639
/*   */     //   484: aload #5
/*   */     //   486: iload #7
/*   */     //   488: iaload
/*   */     //   489: iconst_1
/*   */     //   490: if_icmpeq -> 625
/*   */     //   493: fload #10
/*   */     //   495: fload #15
/*   */     //   497: dup
/*   */     //   498: aload #12
/*   */     //   500: aload #9
/*   */     //   502: iload #7
/*   */     //   504: saload
/*   */     //   505: iconst_2
/*   */     //   506: imul
/*   */     //   507: dup
/*   */     //   508: aload #12
/*   */     //   510: swap
/*   */     //   511: faload
/*   */     //   512: fstore #16
/*   */     //   514: iconst_1
/*   */     //   515: iadd
/*   */     //   516: faload
/*   */     //   517: dup
/*   */     //   518: dup
/*   */     //   519: fstore #17
/*   */     //   521: fload #10
/*   */     //   523: fsub
/*   */     //   524: fload #14
/*   */     //   526: fmul
/*   */     //   527: fload #8
/*   */     //   529: swap
/*   */     //   530: invokestatic df : (FFFF)F
/*   */     //   533: fstore #18
/*   */     //   535: fsub
/*   */     //   536: fload #16
/*   */     //   538: fmul
/*   */     //   539: fload #18
/*   */     //   541: fadd
/*   */     //   542: invokestatic signum : (F)F
/*   */     //   545: f2i
/*   */     //   546: iflt -> 625
/*   */     //   549: fload #13
/*   */     //   551: fload #10
/*   */     //   553: dup
/*   */     //   554: fload #17
/*   */     //   556: dup
/*   */     //   557: fload #13
/*   */     //   559: fsub
/*   */     //   560: fload #8
/*   */     //   562: fmul
/*   */     //   563: fload #11
/*   */     //   565: swap
/*   */     //   566: invokestatic df : (FFFF)F
/*   */     //   569: fstore #18
/*   */     //   571: fsub
/*   */     //   572: fload #16
/*   */     //   574: fmul
/*   */     //   575: fload #18
/*   */     //   577: fadd
/*   */     //   578: invokestatic signum : (F)F
/*   */     //   581: f2i
/*   */     //   582: iflt -> 625
/*   */     //   585: fload #15
/*   */     //   587: fload #13
/*   */     //   589: dup
/*   */     //   590: fload #17
/*   */     //   592: dup
/*   */     //   593: fload #15
/*   */     //   595: fsub
/*   */     //   596: fload #11
/*   */     //   598: fmul
/*   */     //   599: fload #14
/*   */     //   601: swap
/*   */     //   602: invokestatic df : (FFFF)F
/*   */     //   605: fstore #17
/*   */     //   607: fsub
/*   */     //   608: fload #16
/*   */     //   610: fmul
/*   */     //   611: fload #17
/*   */     //   613: fadd
/*   */     //   614: invokestatic signum : (F)F
/*   */     //   617: f2i
/*   */     //   618: iflt -> 625
/*   */     //   621: iconst_0
/*   */     //   622: goto -> 640
/*   */     //   625: iload #7
/*   */     //   627: iconst_1
/*   */     //   628: iadd
/*   */     //   629: aload_0
/*   */     //   630: getfield Hw : I
/*   */     //   633: irem
/*   */     //   634: istore #7
/*   */     //   636: goto -> 477
/*   */     //   639: iconst_1
/*   */     //   640: ifeq -> 646
/*   */     //   643: goto -> 695
/*   */     //   646: iinc #4, 1
/*   */     //   649: goto -> 320
/*   */     //   652: aload_0
/*   */     //   653: getfield Ek0 : Lf/o0;
/*   */     //   656: getfield Ky : [I
/*   */     //   659: astore #4
/*   */     //   661: iconst_0
/*   */     //   662: istore #5
/*   */     //   664: iload #5
/*   */     //   666: iload_3
/*   */     //   667: if_icmpge -> 692
/*   */     //   670: aload #4
/*   */     //   672: iload #5
/*   */     //   674: iaload
/*   */     //   675: iconst_m1
/*   */     //   676: if_icmpeq -> 686
/*   */     //   679: iload #5
/*   */     //   681: istore #4
/*   */     //   683: goto -> 695
/*   */     //   686: iinc #5, 1
/*   */     //   689: goto -> 664
/*   */     //   692: iconst_0
/*   */     //   693: istore #4
/*   */     //   695: iload #4
/*   */     //   697: aload_0
/*   */     //   698: dup
/*   */     //   699: getfield qw : [S
/*   */     //   702: astore_3
/*   */     //   703: getfield jh0 : Lf/Wk0;
/*   */     //   706: astore #5
/*   */     //   708: ifne -> 720
/*   */     //   711: aload_0
/*   */     //   712: getfield Hw : I
/*   */     //   715: istore #6
/*   */     //   717: goto -> 724
/*   */     //   720: iload #4
/*   */     //   722: istore #6
/*   */     //   724: iload #4
/*   */     //   726: aload_0
/*   */     //   727: aload #5
/*   */     //   729: aload_3
/*   */     //   730: aload #5
/*   */     //   732: aload_3
/*   */     //   733: iload #4
/*   */     //   735: aload #5
/*   */     //   737: aload_3
/*   */     //   738: iload #6
/*   */     //   740: iconst_1
/*   */     //   741: isub
/*   */     //   742: saload
/*   */     //   743: invokevirtual GG0 : (S)V
/*   */     //   746: saload
/*   */     //   747: invokevirtual GG0 : (S)V
/*   */     //   750: iload #4
/*   */     //   752: iconst_1
/*   */     //   753: iadd
/*   */     //   754: dup
/*   */     //   755: istore_3
/*   */     //   756: aload_0
/*   */     //   757: getfield Hw : I
/*   */     //   760: irem
/*   */     //   761: saload
/*   */     //   762: invokevirtual GG0 : (S)V
/*   */     //   765: getfield Dc0 : Lf/Wk0;
/*   */     //   768: dup
/*   */     //   769: astore #5
/*   */     //   771: getfield AK0 : I
/*   */     //   774: dup
/*   */     //   775: istore #6
/*   */     //   777: if_icmpge -> 919
/*   */     //   780: aload #5
/*   */     //   782: dup
/*   */     //   783: iload #6
/*   */     //   785: aload #5
/*   */     //   787: getfield YJ0 : [S
/*   */     //   790: dup
/*   */     //   791: astore #5
/*   */     //   793: iload #4
/*   */     //   795: saload
/*   */     //   796: pop
/*   */     //   797: iconst_1
/*   */     //   798: isub
/*   */     //   799: dup
/*   */     //   800: istore #6
/*   */     //   802: putfield AK0 : I
/*   */     //   805: getfield Zv : Z
/*   */     //   808: ifeq -> 833
/*   */     //   811: aload #5
/*   */     //   813: iload #6
/*   */     //   815: iload #4
/*   */     //   817: isub
/*   */     //   818: istore #6
/*   */     //   820: iload_3
/*   */     //   821: aload #5
/*   */     //   823: iload #4
/*   */     //   825: iload #6
/*   */     //   827: invokestatic arraycopy : (Ljava/lang/Object;ILjava/lang/Object;II)V
/*   */     //   830: goto -> 843
/*   */     //   833: aload #5
/*   */     //   835: dup
/*   */     //   836: iload #6
/*   */     //   838: saload
/*   */     //   839: iload #4
/*   */     //   841: swap
/*   */     //   842: sastore
/*   */     //   843: iload #4
/*   */     //   845: aload_0
/*   */     //   846: dup
/*   */     //   847: dup
/*   */     //   848: getfield Ek0 : Lf/o0;
/*   */     //   851: iload #4
/*   */     //   853: invokevirtual Yv0 : (I)V
/*   */     //   856: getfield Hw : I
/*   */     //   859: iconst_1
/*   */     //   860: isub
/*   */     //   861: dup
/*   */     //   862: istore_3
/*   */     //   863: putfield Hw : I
/*   */     //   866: ifne -> 875
/*   */     //   869: iload_3
/*   */     //   870: istore #5
/*   */     //   872: goto -> 879
/*   */     //   875: iload #4
/*   */     //   877: istore #5
/*   */     //   879: iload #4
/*   */     //   881: iload #5
/*   */     //   883: iconst_1
/*   */     //   884: isub
/*   */     //   885: istore #5
/*   */     //   887: iload_3
/*   */     //   888: if_icmpne -> 894
/*   */     //   891: iconst_0
/*   */     //   892: istore #4
/*   */     //   894: aload_2
/*   */     //   895: aload_0
/*   */     //   896: aload_2
/*   */     //   897: aload_0
/*   */     //   898: iload #5
/*   */     //   900: invokevirtual ua : (I)I
/*   */     //   903: iload #5
/*   */     //   905: swap
/*   */     //   906: iastore
/*   */     //   907: iload #4
/*   */     //   909: invokevirtual ua : (I)I
/*   */     //   912: iload #4
/*   */     //   914: swap
/*   */     //   915: iastore
/*   */     //   916: goto -> 307
/*   */     //   919: new java/lang/IndexOutOfBoundsException
/*   */     //   922: dup
/*   */     //   923: ldc 'index can't be >= size: '
/*   */     //   925: iload #4
/*   */     //   927: ldc ' >= '
/*   */     //   929: invokestatic DH0 : (Ljava/lang/String;ILjava/lang/String;)Ljava/lang/StringBuilder;
/*   */     //   932: aload #5
/*   */     //   934: getfield AK0 : I
/*   */     //   937: invokevirtual append : (I)Ljava/lang/StringBuilder;
/*   */     //   940: invokevirtual toString : ()Ljava/lang/String;
/*   */     //   943: invokespecial <init> : (Ljava/lang/String;)V
/*   */     //   946: athrow
/*   */     //   947: iload_3
/*   */     //   948: iconst_3
/*   */     //   949: if_icmpne -> 983
/*   */     //   952: aload_0
/*   */     //   953: getfield jh0 : Lf/Wk0;
/*   */     //   956: dup
/*   */     //   957: astore_2
/*   */     //   958: aload_0
/*   */     //   959: getfield qw : [S
/*   */     //   962: dup
/*   */     //   963: astore_0
/*   */     //   964: aload_2
/*   */     //   965: aload_0
/*   */     //   966: aload_2
/*   */     //   967: aload_0
/*   */     //   968: iconst_0
/*   */     //   969: saload
/*   */     //   970: invokevirtual GG0 : (S)V
/*   */     //   973: iconst_1
/*   */     //   974: saload
/*   */     //   975: invokevirtual GG0 : (S)V
/*   */     //   978: iconst_2
/*   */     //   979: saload
/*   */     //   980: invokevirtual GG0 : (S)V
/*   */     //   983: aload_1
/*   */     //   984: areturn
/*   */     //   985: new java/lang/IllegalArgumentException
/*   */     //   988: dup
/*   */     //   989: ldc 'additionalCapacity must be >= 0: '
/*   */     //   991: iload #4
/*   */     //   993: invokestatic SD0 : (Ljava/lang/String;I)Ljava/lang/String;
/*   */     //   996: invokespecial <init> : (Ljava/lang/String;)V
/*   */     //   999: athrow
/*   */     // Line number table:
/*   */     //   Java source line number -> byte code offset
/*   */     //   #1	-> 12
/*   */     //   #2	-> 32
/*   */     //   #3	-> 37
/*   */     //   #4	-> 79
/*   */     //   #5	-> 159
/*   */     //   #6	-> 208
/*   */     //   #7	-> 221
/*   */     //   #8	-> 262
/*   */     //   #9	-> 285
/*   */     //   #10	-> 292
/*   */     //   #11	-> 300
/*   */     //   #12	-> 327
/*   */     //   #13	-> 352
/*   */     //   #14	-> 375
/*   */     //   #15	-> 387
/*   */     //   #16	-> 474
/*   */     //   #17	-> 488
/*   */     //   #18	-> 542
/*   */     //   #19	-> 630
/*   */     //   #20	-> 653
/*   */     //   #21	-> 699
/*   */     //   #22	-> 712
/*   */     //   #23	-> 742
/*   */     //   #24	-> 757
/*   */     //   #25	-> 761
/*   */     //   #26	-> 771
/*   */     //   #27	-> 787
/*   */     //   #28	-> 848
/*   */     //   #29	-> 900
/*   */     //   #30	-> 919
/*   */     //   #31	-> 923
/*   */     //   #32	-> 934
/*   */     //   #33	-> 953
/*   */     //   #34	-> 985
/*   */     //   #35	-> 989
/*   */     //   #36	-> 996
/*   */   } }


/* Location:              /Users/vnnsnnt/Documents/Codespace/JavaWorkspace/RedTrainer/src/main/java/org/trainer/client/PokeMMO.jar!/f/Du.class
 * Java compiler version: 7 (51.0)
 * JD-Core Version:       1.1.3
 */