/*  1 */ package f;public final class EB extends Xi { public static eo Sh = new eo(); public static eo Ti = new eo(); public IF0 CR; public float gi0; public boolean ms; public SI Dg0; public SI Db0; public Tm PF; public final void QE(int paramInt1, int paramInt2) { this.gi0 = x0(); this(); this.PF = tm; this.R8 = paramInt1; this.by0 = paramInt2; float f = paramInt1; Tm tm; (tm = new Tm()).Wt(f, paramInt2, true); this.PF.nUl = 1.0F / this.gi0; this.PF.UX(true); this
/*  2 */       .zU.d60(this.PF.VD0); } public Eb oj; public tH zU; public RS C70; public int R8; public int by0; public fQ tq0; public EB() { Eb eb; RS rS; fQ fQ1; this.CR = null; this.gi0 = 4.0F; this.ms = false; this.Dg0 = null; this.Db0 = null; this(); this.oj = this; this(); this.C70 = this; this.R8 = 1; this.by0 = 1; this(); this.tq0 = this; this.wN = null; dK(); } public final float x0() { if (this.ms) return this.gi0;  if (km.XU()) { int i; if ((i = h1.b40) > 2) return i;  if ((i = UB0.M60.fG0() + 10) < 1152) {  } else { if (i < 1920); if (i < 2560); if (i < 3840); }  } else { int i; if ((i = h1.b40) > 3) return i;  if ((i = UB0.M60.fG0() - 10) <= 1920); if (i < 2560); if (i < 3840); }  return 8.0F; } public final void Xv0() { this.ms = false; } public final void Ap0() { // Byte code:
/*    */     //   0: getstatic f/km.a3 : Lf/vh0;
/*    */     //   3: dup
/*    */     //   4: astore_1
/*    */     //   5: ifnonnull -> 14
/*    */     //   8: aload_0
/*    */     //   9: iconst_0
/*    */     //   10: putfield w6 : Z
/*    */     //   13: return
/*    */     //   14: aload_1
/*    */     //   15: aload_0
/*    */     //   16: iconst_0
/*    */     //   17: putfield Com2 : Z
/*    */     //   20: invokevirtual Jr0 : ()Lf/KI;
/*    */     //   23: astore_1
/*    */     //   24: getstatic f/km.a3 : Lf/vh0;
/*    */     //   27: getfield Ct : Lf/Jo;
/*    */     //   30: dup
/*    */     //   31: astore_2
/*    */     //   32: ifnull -> 4297
/*    */     //   35: getstatic f/km.u4 : Lf/R8;
/*    */     //   38: getfield sU : Z
/*    */     //   41: ifeq -> 4297
/*    */     //   44: aload_1
/*    */     //   45: instanceof f/IF0
/*    */     //   48: ifeq -> 4297
/*    */     //   51: aload_1
/*    */     //   52: checkcast f/IF0
/*    */     //   55: astore_1
/*    */     //   56: getstatic f/h1.gt0 : Z
/*    */     //   59: ifeq -> 1260
/*    */     //   62: aload_0
/*    */     //   63: getfield C70 : Lf/RS;
/*    */     //   66: dup
/*    */     //   67: astore_3
/*    */     //   68: aload_1
/*    */     //   69: invokevirtual getClass : ()Ljava/lang/Class;
/*    */     //   72: pop
/*    */     //   73: getfield zy0 : Lf/Y00;
/*    */     //   76: dup
/*    */     //   77: astore #4
/*    */     //   79: ifnull -> 103
/*    */     //   82: aload_3
/*    */     //   83: getfield bv : Lf/IF0;
/*    */     //   86: aload_1
/*    */     //   87: if_acmpeq -> 93
/*    */     //   90: goto -> 103
/*    */     //   93: aload_3
/*    */     //   94: getfield lpT5 : Z
/*    */     //   97: ifne -> 980
/*    */     //   100: goto -> 1260
/*    */     //   103: aload #4
/*    */     //   105: ifnull -> 112
/*    */     //   108: aload_3
/*    */     //   109: invokevirtual dispose : ()V
/*    */     //   112: aload_1
/*    */     //   113: aload_3
/*    */     //   114: dup
/*    */     //   115: aload_1
/*    */     //   116: putfield bv : Lf/IF0;
/*    */     //   119: new f/JX
/*    */     //   122: dup
/*    */     //   123: astore #4
/*    */     //   125: invokespecial <init> : ()V
/*    */     //   128: aload #4
/*    */     //   130: putfield Xh : Lf/JX;
/*    */     //   133: new f/Tm
/*    */     //   136: dup
/*    */     //   137: astore #4
/*    */     //   139: invokespecial <init> : ()V
/*    */     //   142: getfield Lq0 : Lf/pB0;
/*    */     //   145: dup
/*    */     //   146: astore #5
/*    */     //   148: ifnull -> 759
/*    */     //   151: aload #5
/*    */     //   153: getfield nK0 : Lf/y9;
/*    */     //   156: ldc '0'
/*    */     //   158: astore #5
/*    */     //   160: ldc 'border_width'
/*    */     //   162: astore #6
/*    */     //   164: getfield un : Lf/f7;
/*    */     //   167: aload #6
/*    */     //   169: invokevirtual pd0 : (Ljava/lang/Object;)Ljava/lang/Object;
/*    */     //   172: dup
/*    */     //   173: astore #6
/*    */     //   175: ifnonnull -> 181
/*    */     //   178: goto -> 185
/*    */     //   181: aload #6
/*    */     //   183: astore #5
/*    */     //   185: aload_1
/*    */     //   186: dup
/*    */     //   187: aload #5
/*    */     //   189: checkcast java/lang/String
/*    */     //   192: invokestatic parseInt : (Ljava/lang/String;)I
/*    */     //   195: putfield Jf : I
/*    */     //   198: getfield Lq0 : Lf/pB0;
/*    */     //   201: getfield nK0 : Lf/y9;
/*    */     //   204: ldc '0'
/*    */     //   206: astore #5
/*    */     //   208: ldc 'border_height'
/*    */     //   210: astore #6
/*    */     //   212: getfield un : Lf/f7;
/*    */     //   215: aload #6
/*    */     //   217: invokevirtual pd0 : (Ljava/lang/Object;)Ljava/lang/Object;
/*    */     //   220: dup
/*    */     //   221: astore #6
/*    */     //   223: ifnonnull -> 229
/*    */     //   226: goto -> 233
/*    */     //   229: aload #6
/*    */     //   231: astore #5
/*    */     //   233: aload_1
/*    */     //   234: dup
/*    */     //   235: aload #5
/*    */     //   237: checkcast java/lang/String
/*    */     //   240: invokestatic parseInt : (Ljava/lang/String;)I
/*    */     //   243: dup
/*    */     //   244: istore #5
/*    */     //   246: putfield kZ : I
/*    */     //   249: getfield Jf : I
/*    */     //   252: iconst_1
/*    */     //   253: if_icmplt -> 1260
/*    */     //   256: iload #5
/*    */     //   258: iconst_1
/*    */     //   259: if_icmpge -> 265
/*    */     //   262: goto -> 1260
/*    */     //   265: aload_1
/*    */     //   266: iconst_2
/*    */     //   267: anewarray java/lang/String
/*    */     //   270: astore #5
/*    */     //   272: getfield Lq0 : Lf/pB0;
/*    */     //   275: getfield nK0 : Lf/y9;
/*    */     //   278: ldc ''
/*    */     //   280: astore #6
/*    */     //   282: ldc 'border_bottom'
/*    */     //   284: astore #7
/*    */     //   286: getfield un : Lf/f7;
/*    */     //   289: aload #7
/*    */     //   291: invokevirtual pd0 : (Ljava/lang/Object;)Ljava/lang/Object;
/*    */     //   294: dup
/*    */     //   295: astore #7
/*    */     //   297: ifnonnull -> 303
/*    */     //   300: goto -> 307
/*    */     //   303: aload #7
/*    */     //   305: astore #6
/*    */     //   307: aload_1
/*    */     //   308: aload #5
/*    */     //   310: aload #6
/*    */     //   312: checkcast java/lang/String
/*    */     //   315: iconst_0
/*    */     //   316: swap
/*    */     //   317: aastore
/*    */     //   318: getfield Lq0 : Lf/pB0;
/*    */     //   321: getfield nK0 : Lf/y9;
/*    */     //   324: ldc ''
/*    */     //   326: astore #6
/*    */     //   328: ldc 'border_top'
/*    */     //   330: astore #7
/*    */     //   332: getfield un : Lf/f7;
/*    */     //   335: aload #7
/*    */     //   337: invokevirtual pd0 : (Ljava/lang/Object;)Ljava/lang/Object;
/*    */     //   340: dup
/*    */     //   341: astore #7
/*    */     //   343: ifnonnull -> 349
/*    */     //   346: goto -> 353
/*    */     //   349: aload #7
/*    */     //   351: astore #6
/*    */     //   353: aload_1
/*    */     //   354: aload #5
/*    */     //   356: aload #6
/*    */     //   358: checkcast java/lang/String
/*    */     //   361: iconst_1
/*    */     //   362: swap
/*    */     //   363: aastore
/*    */     //   364: iconst_2
/*    */     //   365: anewarray [Lf/else;
/*    */     //   368: putfield rE : [[Lf/else;
/*    */     //   371: iconst_0
/*    */     //   372: istore #6
/*    */     //   374: iconst_0
/*    */     //   375: istore #7
/*    */     //   377: iconst_0
/*    */     //   378: istore #8
/*    */     //   380: iload #8
/*    */     //   382: iconst_2
/*    */     //   383: if_icmpge -> 649
/*    */     //   386: aload #5
/*    */     //   388: iload #8
/*    */     //   390: aaload
/*    */     //   391: ldc_w ','
/*    */     //   394: invokevirtual split : (Ljava/lang/String;)[Ljava/lang/String;
/*    */     //   397: dup
/*    */     //   398: astore #9
/*    */     //   400: arraylength
/*    */     //   401: aload_1
/*    */     //   402: getfield kZ : I
/*    */     //   405: dup
/*    */     //   406: imul
/*    */     //   407: if_icmpeq -> 423
/*    */     //   410: aload_1
/*    */     //   411: dup
/*    */     //   412: iconst_0
/*    */     //   413: putfield Jf : I
/*    */     //   416: iconst_0
/*    */     //   417: putfield kZ : I
/*    */     //   420: goto -> 1260
/*    */     //   423: aload_1
/*    */     //   424: getfield rE : [[Lf/else;
/*    */     //   427: iload #8
/*    */     //   429: aload #9
/*    */     //   431: arraylength
/*    */     //   432: anewarray f/else
/*    */     //   435: aastore
/*    */     //   436: iconst_0
/*    */     //   437: istore #10
/*    */     //   439: iload #10
/*    */     //   441: aload #9
/*    */     //   443: arraylength
/*    */     //   444: if_icmpge -> 643
/*    */     //   447: aload_1
/*    */     //   448: dup
/*    */     //   449: aload #9
/*    */     //   451: iload #10
/*    */     //   453: aaload
/*    */     //   454: invokestatic parseInt : (Ljava/lang/String;)I
/*    */     //   457: istore #11
/*    */     //   459: getfield rE : [[Lf/else;
/*    */     //   462: iload #8
/*    */     //   464: aaload
/*    */     //   465: astore #12
/*    */     //   467: getfield Lq0 : Lf/pB0;
/*    */     //   470: getfield f8 : Lf/bR;
/*    */     //   473: dup
/*    */     //   474: astore #13
/*    */     //   476: getfield GO : Lf/fQ;
/*    */     //   479: getfield Z8 : I
/*    */     //   482: iconst_1
/*    */     //   483: isub
/*    */     //   484: istore #14
/*    */     //   486: iload #14
/*    */     //   488: iflt -> 530
/*    */     //   491: aload #13
/*    */     //   493: getfield GO : Lf/fQ;
/*    */     //   496: iload #14
/*    */     //   498: invokevirtual get : (I)Ljava/lang/Object;
/*    */     //   501: checkcast f/tv
/*    */     //   504: getfield m0 : Lf/y10;
/*    */     //   507: iload #11
/*    */     //   509: invokevirtual get : (I)Ljava/lang/Object;
/*    */     //   512: checkcast f/else
/*    */     //   515: dup
/*    */     //   516: astore #15
/*    */     //   518: ifnull -> 524
/*    */     //   521: goto -> 533
/*    */     //   524: iinc #14, -1
/*    */     //   527: goto -> 486
/*    */     //   530: aconst_null
/*    */     //   531: astore #15
/*    */     //   533: aload_1
/*    */     //   534: aload #12
/*    */     //   536: iload #10
/*    */     //   538: aload #15
/*    */     //   540: aastore
/*    */     //   541: getfield rE : [[Lf/else;
/*    */     //   544: iload #8
/*    */     //   546: aaload
/*    */     //   547: iload #10
/*    */     //   549: aaload
/*    */     //   550: dup
/*    */     //   551: astore #11
/*    */     //   553: ifnonnull -> 559
/*    */     //   556: goto -> 1260
/*    */     //   559: aload #11
/*    */     //   561: invokeinterface LPT8 : ()Lf/pe0;
/*    */     //   566: getfield H0 : I
/*    */     //   569: iload #6
/*    */     //   571: if_icmple -> 594
/*    */     //   574: aload_1
/*    */     //   575: getfield rE : [[Lf/else;
/*    */     //   578: iload #8
/*    */     //   580: aaload
/*    */     //   581: iload #10
/*    */     //   583: aaload
/*    */     //   584: invokeinterface LPT8 : ()Lf/pe0;
/*    */     //   589: getfield H0 : I
/*    */     //   592: istore #6
/*    */     //   594: aload_1
/*    */     //   595: getfield rE : [[Lf/else;
/*    */     //   598: iload #8
/*    */     //   600: aaload
/*    */     //   601: iload #10
/*    */     //   603: aaload
/*    */     //   604: invokeinterface LPT8 : ()Lf/pe0;
/*    */     //   609: getfield Vn0 : I
/*    */     //   612: iload #7
/*    */     //   614: if_icmple -> 637
/*    */     //   617: aload_1
/*    */     //   618: getfield rE : [[Lf/else;
/*    */     //   621: iload #8
/*    */     //   623: aaload
/*    */     //   624: iload #10
/*    */     //   626: aaload
/*    */     //   627: invokeinterface LPT8 : ()Lf/pe0;
/*    */     //   632: getfield Vn0 : I
/*    */     //   635: istore #7
/*    */     //   637: iinc #10, 1
/*    */     //   640: goto -> 439
/*    */     //   643: iinc #8, 1
/*    */     //   646: goto -> 380
/*    */     //   649: aload_3
/*    */     //   650: dup
/*    */     //   651: dup2
/*    */     //   652: aload #4
/*    */     //   654: aload_1
/*    */     //   655: getfield Jf : I
/*    */     //   658: iload #6
/*    */     //   660: imul
/*    */     //   661: i2f
/*    */     //   662: aload_1
/*    */     //   663: getfield kZ : I
/*    */     //   666: iload #7
/*    */     //   668: imul
/*    */     //   669: i2f
/*    */     //   670: iconst_0
/*    */     //   671: invokevirtual Wt : (FFZ)V
/*    */     //   674: getfield Xh : Lf/JX;
/*    */     //   677: aload #4
/*    */     //   679: getfield VD0 : Lcom/badlogic/gdx/math/Matrix4;
/*    */     //   682: invokevirtual d60 : (Lcom/badlogic/gdx/math/Matrix4;)V
/*    */     //   685: new f/Y00
/*    */     //   688: dup
/*    */     //   689: dup
/*    */     //   690: astore #4
/*    */     //   692: getstatic f/Uc.xi0 : Lf/Uc;
/*    */     //   695: aload_1
/*    */     //   696: dup
/*    */     //   697: getfield Jf : I
/*    */     //   700: bipush #16
/*    */     //   702: imul
/*    */     //   703: istore #5
/*    */     //   705: getfield kZ : I
/*    */     //   708: bipush #16
/*    */     //   710: imul
/*    */     //   711: iload #5
/*    */     //   713: swap
/*    */     //   714: iconst_0
/*    */     //   715: invokespecial <init> : (Lf/Uc;IIZ)V
/*    */     //   718: putfield zy0 : Lf/Y00;
/*    */     //   721: aload #4
/*    */     //   723: invokevirtual P10 : ()Lf/zp;
/*    */     //   726: checkcast com/badlogic/gdx/graphics/Texture
/*    */     //   729: dup
/*    */     //   730: aload_3
/*    */     //   731: swap
/*    */     //   732: putfield RE0 : Lcom/badlogic/gdx/graphics/Texture;
/*    */     //   735: getstatic f/cu0.Fh : Lf/cu0;
/*    */     //   738: dup
/*    */     //   739: invokevirtual setFilter : (Lf/cu0;Lf/cu0;)V
/*    */     //   742: getfield RE0 : Lcom/badlogic/gdx/graphics/Texture;
/*    */     //   745: getstatic f/A00.OW : Lf/A00;
/*    */     //   748: dup
/*    */     //   749: invokevirtual setWrap : (Lf/A00;Lf/A00;)V
/*    */     //   752: iconst_0
/*    */     //   753: putfield lpT5 : Z
/*    */     //   756: goto -> 980
/*    */     //   759: aload_3
/*    */     //   760: dup
/*    */     //   761: dup
/*    */     //   762: aload #4
/*    */     //   764: aload_1
/*    */     //   765: getfield Jf : I
/*    */     //   768: bipush #16
/*    */     //   770: imul
/*    */     //   771: i2f
/*    */     //   772: aload_1
/*    */     //   773: getfield kZ : I
/*    */     //   776: bipush #16
/*    */     //   778: imul
/*    */     //   779: i2f
/*    */     //   780: iconst_0
/*    */     //   781: invokevirtual Wt : (FFZ)V
/*    */     //   784: getfield Xh : Lf/JX;
/*    */     //   787: aload #4
/*    */     //   789: getfield VD0 : Lcom/badlogic/gdx/math/Matrix4;
/*    */     //   792: invokevirtual d60 : (Lcom/badlogic/gdx/math/Matrix4;)V
/*    */     //   795: new f/Y00
/*    */     //   798: dup
/*    */     //   799: dup
/*    */     //   800: astore #4
/*    */     //   802: getstatic f/Uc.xi0 : Lf/Uc;
/*    */     //   805: aload_1
/*    */     //   806: dup
/*    */     //   807: getfield Jf : I
/*    */     //   810: bipush #16
/*    */     //   812: imul
/*    */     //   813: istore #5
/*    */     //   815: getfield kZ : I
/*    */     //   818: bipush #16
/*    */     //   820: imul
/*    */     //   821: iload #5
/*    */     //   823: swap
/*    */     //   824: iconst_0
/*    */     //   825: invokespecial <init> : (Lf/Uc;IIZ)V
/*    */     //   828: putfield zy0 : Lf/Y00;
/*    */     //   831: aload #4
/*    */     //   833: invokevirtual P10 : ()Lf/zp;
/*    */     //   836: checkcast com/badlogic/gdx/graphics/Texture
/*    */     //   839: dup
/*    */     //   840: aload_3
/*    */     //   841: swap
/*    */     //   842: putfield RE0 : Lcom/badlogic/gdx/graphics/Texture;
/*    */     //   845: getstatic f/cu0.Fh : Lf/cu0;
/*    */     //   848: dup
/*    */     //   849: invokevirtual setFilter : (Lf/cu0;Lf/cu0;)V
/*    */     //   852: getfield RE0 : Lcom/badlogic/gdx/graphics/Texture;
/*    */     //   855: getstatic f/A00.OW : Lf/A00;
/*    */     //   858: dup
/*    */     //   859: invokevirtual setWrap : (Lf/A00;Lf/A00;)V
/*    */     //   862: iconst_0
/*    */     //   863: istore #4
/*    */     //   865: iconst_0
/*    */     //   866: istore #5
/*    */     //   868: iload #5
/*    */     //   870: aload_1
/*    */     //   871: getfield kZ : I
/*    */     //   874: if_icmpge -> 974
/*    */     //   877: iconst_0
/*    */     //   878: istore #6
/*    */     //   880: iload #6
/*    */     //   882: aload_1
/*    */     //   883: getfield Jf : I
/*    */     //   886: if_icmpge -> 964
/*    */     //   889: iconst_0
/*    */     //   890: istore #7
/*    */     //   892: iload #7
/*    */     //   894: iconst_2
/*    */     //   895: if_icmpge -> 954
/*    */     //   898: aload_1
/*    */     //   899: getfield pM : [[Lf/xW;
/*    */     //   902: iload #6
/*    */     //   904: aaload
/*    */     //   905: iload #5
/*    */     //   907: aaload
/*    */     //   908: getfield lS : Lf/a4;
/*    */     //   911: getfield W6 : [I
/*    */     //   914: dup
/*    */     //   915: astore #8
/*    */     //   917: ifnull -> 934
/*    */     //   920: aload #8
/*    */     //   922: iload #7
/*    */     //   924: iaload
/*    */     //   925: ifle -> 934
/*    */     //   928: iconst_1
/*    */     //   929: istore #8
/*    */     //   931: goto -> 937
/*    */     //   934: iconst_0
/*    */     //   935: istore #8
/*    */     //   937: iload #7
/*    */     //   939: iload #4
/*    */     //   941: iload #8
/*    */     //   943: ior
/*    */     //   944: istore #4
/*    */     //   946: iconst_1
/*    */     //   947: iadd
/*    */     //   948: i2s
/*    */     //   949: istore #7
/*    */     //   951: goto -> 892
/*    */     //   954: iload #6
/*    */     //   956: iconst_1
/*    */     //   957: iadd
/*    */     //   958: i2s
/*    */     //   959: istore #6
/*    */     //   961: goto -> 880
/*    */     //   964: iload #5
/*    */     //   966: iconst_1
/*    */     //   967: iadd
/*    */     //   968: i2s
/*    */     //   969: istore #5
/*    */     //   971: goto -> 868
/*    */     //   974: aload_3
/*    */     //   975: iload #4
/*    */     //   977: putfield lpT5 : Z
/*    */     //   980: aload_3
/*    */     //   981: dup
/*    */     //   982: getfield zy0 : Lf/Y00;
/*    */     //   985: astore #4
/*    */     //   987: getstatic f/UB0.re0 : Lf/hj0;
/*    */     //   990: aload #4
/*    */     //   992: getfield EE0 : I
/*    */     //   995: ldc_w 36160
/*    */     //   998: swap
/*    */     //   999: invokeinterface glBindFramebuffer : (II)V
/*    */     //   1004: getstatic f/UB0.re0 : Lf/hj0;
/*    */     //   1007: aload #4
/*    */     //   1009: getfield E80 : Lf/wl0;
/*    */     //   1012: dup
/*    */     //   1013: getfield rS : I
/*    */     //   1016: istore #4
/*    */     //   1018: getfield Z : I
/*    */     //   1021: istore #5
/*    */     //   1023: iconst_0
/*    */     //   1024: iconst_0
/*    */     //   1025: iload #4
/*    */     //   1027: iload #5
/*    */     //   1029: invokeinterface glViewport : (IIII)V
/*    */     //   1034: getstatic f/UB0.go : Lf/hj0;
/*    */     //   1037: fconst_0
/*    */     //   1038: fconst_0
/*    */     //   1039: fconst_0
/*    */     //   1040: fconst_0
/*    */     //   1041: invokeinterface glClearColor : (FFFF)V
/*    */     //   1046: getstatic f/UB0.go : Lf/hj0;
/*    */     //   1049: sipush #16384
/*    */     //   1052: invokeinterface glClear : (I)V
/*    */     //   1057: getfield Xh : Lf/JX;
/*    */     //   1060: invokevirtual Tx : ()V
/*    */     //   1063: iconst_0
/*    */     //   1064: istore #4
/*    */     //   1066: iload #4
/*    */     //   1068: aload_1
/*    */     //   1069: getfield kZ : I
/*    */     //   1072: if_icmpge -> 1246
/*    */     //   1075: iconst_0
/*    */     //   1076: istore #5
/*    */     //   1078: iload #5
/*    */     //   1080: aload_1
/*    */     //   1081: getfield Jf : I
/*    */     //   1084: if_icmpge -> 1236
/*    */     //   1087: iconst_0
/*    */     //   1088: istore #6
/*    */     //   1090: iload #6
/*    */     //   1092: iconst_2
/*    */     //   1093: if_icmpge -> 1226
/*    */     //   1096: aload_1
/*    */     //   1097: getfield rE : [[Lf/else;
/*    */     //   1100: dup
/*    */     //   1101: astore #7
/*    */     //   1103: ifnull -> 1132
/*    */     //   1106: aload #7
/*    */     //   1108: iload #6
/*    */     //   1110: aaload
/*    */     //   1111: iload #4
/*    */     //   1113: aload_1
/*    */     //   1114: getfield kZ : I
/*    */     //   1117: imul
/*    */     //   1118: iload #5
/*    */     //   1120: iadd
/*    */     //   1121: aaload
/*    */     //   1122: invokeinterface LPT8 : ()Lf/pe0;
/*    */     //   1127: astore #7
/*    */     //   1129: goto -> 1152
/*    */     //   1132: aload_1
/*    */     //   1133: getfield pM : [[Lf/xW;
/*    */     //   1136: iload #5
/*    */     //   1138: aaload
/*    */     //   1139: iload #4
/*    */     //   1141: aaload
/*    */     //   1142: getfield lS : Lf/a4;
/*    */     //   1145: iload #6
/*    */     //   1147: invokevirtual GC0 : (I)Lf/pe0;
/*    */     //   1150: astore #7
/*    */     //   1152: aload #7
/*    */     //   1154: ifnonnull -> 1160
/*    */     //   1157: goto -> 1216
/*    */     //   1160: aload_3
/*    */     //   1161: getfield Xh : Lf/JX;
/*    */     //   1164: dup
/*    */     //   1165: astore #8
/*    */     //   1167: aload #7
/*    */     //   1169: dup
/*    */     //   1170: dup
/*    */     //   1171: aload #8
/*    */     //   1173: iload #4
/*    */     //   1175: iload #5
/*    */     //   1177: bipush #16
/*    */     //   1179: imul
/*    */     //   1180: i2f
/*    */     //   1181: fstore #7
/*    */     //   1183: bipush #16
/*    */     //   1185: imul
/*    */     //   1186: i2f
/*    */     //   1187: fstore #8
/*    */     //   1189: invokevirtual getClass : ()Ljava/lang/Class;
/*    */     //   1192: pop
/*    */     //   1193: getfield H0 : I
/*    */     //   1196: i2f
/*    */     //   1197: fstore #9
/*    */     //   1199: getfield Vn0 : I
/*    */     //   1202: i2f
/*    */     //   1203: fstore #10
/*    */     //   1205: fload #7
/*    */     //   1207: fload #8
/*    */     //   1209: fload #9
/*    */     //   1211: fload #10
/*    */     //   1213: invokevirtual Yo0 : (Lf/pe0;FFFF)V
/*    */     //   1216: iload #6
/*    */     //   1218: iconst_1
/*    */     //   1219: iadd
/*    */     //   1220: i2s
/*    */     //   1221: istore #6
/*    */     //   1223: goto -> 1090
/*    */     //   1226: iload #5
/*    */     //   1228: iconst_1
/*    */     //   1229: iadd
/*    */     //   1230: i2s
/*    */     //   1231: istore #5
/*    */     //   1233: goto -> 1078
/*    */     //   1236: iload #4
/*    */     //   1238: iconst_1
/*    */     //   1239: iadd
/*    */     //   1240: i2s
/*    */     //   1241: istore #4
/*    */     //   1243: goto -> 1066
/*    */     //   1246: aload_3
/*    */     //   1247: dup
/*    */     //   1248: getfield Xh : Lf/JX;
/*    */     //   1251: invokevirtual end : ()V
/*    */     //   1254: getfield zy0 : Lf/Y00;
/*    */     //   1257: invokevirtual end : ()V
/*    */     //   1260: aload_0
/*    */     //   1261: dup
/*    */     //   1262: getfield zU : Lf/tH;
/*    */     //   1265: invokevirtual getClass : ()Ljava/lang/Class;
/*    */     //   1268: pop
/*    */     //   1269: getfield zU : Lf/tH;
/*    */     //   1272: invokevirtual Tx : ()V
/*    */     //   1275: getstatic f/km.u4 : Lf/R8;
/*    */     //   1278: invokevirtual x00 : ()Z
/*    */     //   1281: iconst_1
/*    */     //   1282: ixor
/*    */     //   1283: dup
/*    */     //   1284: aload_0
/*    */     //   1285: swap
/*    */     //   1286: putfield w6 : Z
/*    */     //   1289: ifne -> 1308
/*    */     //   1292: getstatic f/km.u4 : Lf/R8;
/*    */     //   1295: invokevirtual D80 : ()V
/*    */     //   1298: invokestatic Bp : ()Lf/ud;
/*    */     //   1301: sipush #500
/*    */     //   1304: iconst_0
/*    */     //   1305: invokevirtual Xk : (IZ)V
/*    */     //   1308: aload_0
/*    */     //   1309: dup
/*    */     //   1310: dup
/*    */     //   1311: aload_2
/*    */     //   1312: aload_0
/*    */     //   1313: dup
/*    */     //   1314: dup
/*    */     //   1315: aload_2
/*    */     //   1316: getfield pm : Lf/d7;
/*    */     //   1319: getfield cOm3 : Lf/eo;
/*    */     //   1322: astore_3
/*    */     //   1323: getfield PF : Lf/Tm;
/*    */     //   1326: getfield H : Lf/eo;
/*    */     //   1329: aload_3
/*    */     //   1330: invokevirtual JL : (Lf/eo;)Lf/eo;
/*    */     //   1333: ldc_w 16.0
/*    */     //   1336: invokevirtual uu : (F)Lf/eo;
/*    */     //   1339: pop
/*    */     //   1340: getfield PF : Lf/Tm;
/*    */     //   1343: getfield H : Lf/eo;
/*    */     //   1346: dup
/*    */     //   1347: getfield x : F
/*    */     //   1350: aload_2
/*    */     //   1351: getfield J : Lf/static;
/*    */     //   1354: invokevirtual zv : ()I
/*    */     //   1357: iconst_2
/*    */     //   1358: idiv
/*    */     //   1359: i2f
/*    */     //   1360: fadd
/*    */     //   1361: putfield x : F
/*    */     //   1364: getfield PF : Lf/Tm;
/*    */     //   1367: getfield H : Lf/eo;
/*    */     //   1370: dup
/*    */     //   1371: getfield y : F
/*    */     //   1374: aload_2
/*    */     //   1375: getfield J : Lf/static;
/*    */     //   1378: invokevirtual e60 : ()I
/*    */     //   1381: iconst_2
/*    */     //   1382: idiv
/*    */     //   1383: i2f
/*    */     //   1384: fadd
/*    */     //   1385: putfield y : F
/*    */     //   1388: getfield HW : Lf/G5;
/*    */     //   1391: dup
/*    */     //   1392: astore_3
/*    */     //   1393: invokevirtual getClass : ()Ljava/lang/Class;
/*    */     //   1396: pop
/*    */     //   1397: getstatic f/km.a3 : Lf/vh0;
/*    */     //   1400: aload_3
/*    */     //   1401: dup
/*    */     //   1402: dup
/*    */     //   1403: getfield FB : B
/*    */     //   1406: istore_3
/*    */     //   1407: getfield kD0 : B
/*    */     //   1410: istore #4
/*    */     //   1412: getfield vu0 : B
/*    */     //   1415: istore #5
/*    */     //   1417: iload_3
/*    */     //   1418: iload #4
/*    */     //   1420: iload #5
/*    */     //   1422: invokevirtual COm8 : (BBB)Lf/KI;
/*    */     //   1425: astore_3
/*    */     //   1426: getfield PF : Lf/Tm;
/*    */     //   1429: getfield H : Lf/eo;
/*    */     //   1432: dup
/*    */     //   1433: getfield x : F
/*    */     //   1436: aload_3
/*    */     //   1437: invokevirtual cp0 : ()I
/*    */     //   1440: i2f
/*    */     //   1441: fadd
/*    */     //   1442: putfield x : F
/*    */     //   1445: getfield PF : Lf/Tm;
/*    */     //   1448: getfield H : Lf/eo;
/*    */     //   1451: dup
/*    */     //   1452: getfield y : F
/*    */     //   1455: aload_3
/*    */     //   1456: invokevirtual kf0 : ()I
/*    */     //   1459: i2f
/*    */     //   1460: fadd
/*    */     //   1461: putfield y : F
/*    */     //   1464: getfield PF : Lf/Tm;
/*    */     //   1467: getfield H : Lf/eo;
/*    */     //   1470: dup
/*    */     //   1471: dup2
/*    */     //   1472: getfield x : F
/*    */     //   1475: f2i
/*    */     //   1476: i2f
/*    */     //   1477: putfield x : F
/*    */     //   1480: getfield y : F
/*    */     //   1483: f2i
/*    */     //   1484: i2f
/*    */     //   1485: putfield y : F
/*    */     //   1488: getstatic f/tr.Jv : Lf/tr;
/*    */     //   1491: dup
/*    */     //   1492: astore_3
/*    */     //   1493: aload_0
/*    */     //   1494: aload_3
/*    */     //   1495: invokevirtual WR : ()V
/*    */     //   1498: getfield PF : Lf/Tm;
/*    */     //   1501: getfield H : Lf/eo;
/*    */     //   1504: dup
/*    */     //   1505: astore #4
/*    */     //   1507: getfield x : F
/*    */     //   1510: fstore #5
/*    */     //   1512: getfield hn0 : I
/*    */     //   1515: dup
/*    */     //   1516: istore #6
/*    */     //   1518: iconst_2
/*    */     //   1519: irem
/*    */     //   1520: ifne -> 1532
/*    */     //   1523: aload_3
/*    */     //   1524: getfield fm : I
/*    */     //   1527: istore #7
/*    */     //   1529: goto -> 1539
/*    */     //   1532: aload_3
/*    */     //   1533: getfield fm : I
/*    */     //   1536: ineg
/*    */     //   1537: istore #7
/*    */     //   1539: iload #6
/*    */     //   1541: aload #4
/*    */     //   1543: dup
/*    */     //   1544: fload #5
/*    */     //   1546: iload #7
/*    */     //   1548: i2f
/*    */     //   1549: fsub
/*    */     //   1550: putfield x : F
/*    */     //   1553: getfield y : F
/*    */     //   1556: fstore #5
/*    */     //   1558: iconst_2
/*    */     //   1559: irem
/*    */     //   1560: ifne -> 1571
/*    */     //   1563: aload_3
/*    */     //   1564: getfield Am : I
/*    */     //   1567: istore_3
/*    */     //   1568: goto -> 1577
/*    */     //   1571: aload_3
/*    */     //   1572: getfield Am : I
/*    */     //   1575: ineg
/*    */     //   1576: istore_3
/*    */     //   1577: aload #4
/*    */     //   1579: fload #5
/*    */     //   1581: iload_3
/*    */     //   1582: i2f
/*    */     //   1583: fsub
/*    */     //   1584: putfield y : F
/*    */     //   1587: getstatic f/wJ0.Nf0 : Lf/wJ0;
/*    */     //   1590: dup
/*    */     //   1591: astore_3
/*    */     //   1592: getfield NuL : J
/*    */     //   1595: getstatic f/zm0.u20 : J
/*    */     //   1598: dup2
/*    */     //   1599: lstore #4
/*    */     //   1601: lcmp
/*    */     //   1602: ifle -> 1608
/*    */     //   1605: goto -> 1642
/*    */     //   1608: lload #4
/*    */     //   1610: aload_3
/*    */     //   1611: getfield rs : J
/*    */     //   1614: lsub
/*    */     //   1615: aload_3
/*    */     //   1616: getfield Gb : I
/*    */     //   1619: i2l
/*    */     //   1620: lcmp
/*    */     //   1621: ifle -> 1642
/*    */     //   1624: lload #4
/*    */     //   1626: aload_3
/*    */     //   1627: getfield vM : J
/*    */     //   1630: lsub
/*    */     //   1631: bipush #100
/*    */     //   1633: i2l
/*    */     //   1634: lcmp
/*    */     //   1635: ifle -> 1642
/*    */     //   1638: iconst_1
/*    */     //   1639: goto -> 1643
/*    */     //   1642: iconst_0
/*    */     //   1643: ifeq -> 1688
/*    */     //   1646: aload_3
/*    */     //   1647: dup
/*    */     //   1648: getfield FE0 : Ljava/util/LinkedList;
/*    */     //   1651: dup
/*    */     //   1652: astore #4
/*    */     //   1654: monitorenter
/*    */     //   1655: getfield FE0 : Ljava/util/LinkedList;
/*    */     //   1658: invokevirtual poll : ()Ljava/lang/Object;
/*    */     //   1661: checkcast f/nl
/*    */     //   1664: dup
/*    */     //   1665: astore #5
/*    */     //   1667: ifnull -> 1676
/*    */     //   1670: aload_3
/*    */     //   1671: aload #5
/*    */     //   1673: invokevirtual ZP : (Lf/nl;)V
/*    */     //   1676: aload #4
/*    */     //   1678: monitorexit
/*    */     //   1679: goto -> 1688
/*    */     //   1682: astore_0
/*    */     //   1683: aload_0
/*    */     //   1684: aload #4
/*    */     //   1686: monitorexit
/*    */     //   1687: athrow
/*    */     //   1688: aload_1
/*    */     //   1689: aload_0
/*    */     //   1690: dup
/*    */     //   1691: aload_1
/*    */     //   1692: aload_0
/*    */     //   1693: dup
/*    */     //   1694: dup
/*    */     //   1695: dup2
/*    */     //   1696: getfield PF : Lf/Tm;
/*    */     //   1699: getfield H : Lf/eo;
/*    */     //   1702: dup
/*    */     //   1703: getfield x : F
/*    */     //   1706: aload_3
/*    */     //   1707: invokevirtual LE : ()I
/*    */     //   1710: i2f
/*    */     //   1711: fadd
/*    */     //   1712: putfield x : F
/*    */     //   1715: getfield PF : Lf/Tm;
/*    */     //   1718: getfield H : Lf/eo;
/*    */     //   1721: dup
/*    */     //   1722: getfield y : F
/*    */     //   1725: aload_3
/*    */     //   1726: invokevirtual Lh : ()I
/*    */     //   1729: i2f
/*    */     //   1730: fadd
/*    */     //   1731: putfield y : F
/*    */     //   1734: getfield PF : Lf/Tm;
/*    */     //   1737: dup
/*    */     //   1738: getfield H : Lf/eo;
/*    */     //   1741: dup
/*    */     //   1742: astore_3
/*    */     //   1743: aload_0
/*    */     //   1744: aload_3
/*    */     //   1745: dup
/*    */     //   1746: aload_0
/*    */     //   1747: aload_3
/*    */     //   1748: getfield x : F
/*    */     //   1751: fstore_3
/*    */     //   1752: getfield R8 : I
/*    */     //   1755: iconst_1
/*    */     //   1756: iand
/*    */     //   1757: i2f
/*    */     //   1758: aload_0
/*    */     //   1759: getfield gi0 : F
/*    */     //   1762: dup
/*    */     //   1763: fstore #4
/*    */     //   1765: fdiv
/*    */     //   1766: ldc_w 0.5
/*    */     //   1769: fmul
/*    */     //   1770: fload_3
/*    */     //   1771: fadd
/*    */     //   1772: putfield x : F
/*    */     //   1775: getfield y : F
/*    */     //   1778: fstore_3
/*    */     //   1779: getfield by0 : I
/*    */     //   1782: iconst_1
/*    */     //   1783: iand
/*    */     //   1784: i2f
/*    */     //   1785: fload #4
/*    */     //   1787: fdiv
/*    */     //   1788: ldc_w 0.5
/*    */     //   1791: fmul
/*    */     //   1792: fload_3
/*    */     //   1793: fadd
/*    */     //   1794: putfield y : F
/*    */     //   1797: iconst_1
/*    */     //   1798: invokevirtual UX : (Z)V
/*    */     //   1801: getfield zU : Lf/tH;
/*    */     //   1804: aload_0
/*    */     //   1805: getfield PF : Lf/Tm;
/*    */     //   1808: getfield VD0 : Lcom/badlogic/gdx/math/Matrix4;
/*    */     //   1811: invokevirtual d60 : (Lcom/badlogic/gdx/math/Matrix4;)V
/*    */     //   1814: getstatic f/EB.Sh : Lf/eo;
/*    */     //   1817: aload_0
/*    */     //   1818: getfield PF : Lf/Tm;
/*    */     //   1821: getfield H : Lf/eo;
/*    */     //   1824: invokevirtual JL : (Lf/eo;)Lf/eo;
/*    */     //   1827: aload_0
/*    */     //   1828: getfield R8 : I
/*    */     //   1831: i2f
/*    */     //   1832: aload_0
/*    */     //   1833: getfield gi0 : F
/*    */     //   1836: dup
/*    */     //   1837: fstore_3
/*    */     //   1838: fdiv
/*    */     //   1839: fconst_2
/*    */     //   1840: fdiv
/*    */     //   1841: ldc_w 16.0
/*    */     //   1844: fadd
/*    */     //   1845: aload_0
/*    */     //   1846: getfield by0 : I
/*    */     //   1849: i2f
/*    */     //   1850: fload_3
/*    */     //   1851: fdiv
/*    */     //   1852: fconst_2
/*    */     //   1853: fdiv
/*    */     //   1854: ldc_w 16.0
/*    */     //   1857: fadd
/*    */     //   1858: fconst_0
/*    */     //   1859: invokevirtual uD : (FFF)Lf/eo;
/*    */     //   1862: pop
/*    */     //   1863: getstatic f/EB.Ti : Lf/eo;
/*    */     //   1866: aload_0
/*    */     //   1867: getfield PF : Lf/Tm;
/*    */     //   1870: getfield H : Lf/eo;
/*    */     //   1873: invokevirtual JL : (Lf/eo;)Lf/eo;
/*    */     //   1876: aload_0
/*    */     //   1877: getfield R8 : I
/*    */     //   1880: i2f
/*    */     //   1881: aload_0
/*    */     //   1882: getfield gi0 : F
/*    */     //   1885: dup
/*    */     //   1886: fstore_3
/*    */     //   1887: fdiv
/*    */     //   1888: fconst_2
/*    */     //   1889: fdiv
/*    */     //   1890: ldc_w 16.0
/*    */     //   1893: fadd
/*    */     //   1894: aload_0
/*    */     //   1895: getfield by0 : I
/*    */     //   1898: i2f
/*    */     //   1899: fload_3
/*    */     //   1900: fdiv
/*    */     //   1901: fconst_2
/*    */     //   1902: fdiv
/*    */     //   1903: ldc_w 16.0
/*    */     //   1906: fadd
/*    */     //   1907: fconst_0
/*    */     //   1908: invokevirtual Tz : (FFF)Lf/eo;
/*    */     //   1911: pop
/*    */     //   1912: getfield oj : Lf/Eb;
/*    */     //   1915: getstatic f/EB.Sh : Lf/eo;
/*    */     //   1918: getstatic f/EB.Ti : Lf/eo;
/*    */     //   1921: invokevirtual kX : (Lf/eo;Lf/eo;)Lf/Eb;
/*    */     //   1924: pop
/*    */     //   1925: getfield Cd : Lf/yE0;
/*    */     //   1928: aload_0
/*    */     //   1929: getfield w6 : Z
/*    */     //   1932: iconst_1
/*    */     //   1933: ixor
/*    */     //   1934: invokevirtual Gt : (Lf/yE0;Z)V
/*    */     //   1937: getfield CR : Lf/IF0;
/*    */     //   1940: if_acmpeq -> 2037
/*    */     //   1943: getstatic f/km.MR : Lf/Gp0;
/*    */     //   1946: ifnonnull -> 2037
/*    */     //   1949: aload_2
/*    */     //   1950: invokevirtual UG : ()Z
/*    */     //   1953: ifeq -> 2009
/*    */     //   1956: aload_2
/*    */     //   1957: invokevirtual VO : ()Z
/*    */     //   1960: ifne -> 2009
/*    */     //   1963: aload_2
/*    */     //   1964: getfield HW : Lf/G5;
/*    */     //   1967: getfield FB : B
/*    */     //   1970: dup
/*    */     //   1971: istore_2
/*    */     //   1972: ifeq -> 1996
/*    */     //   1975: iload_2
/*    */     //   1976: iconst_1
/*    */     //   1977: if_icmpeq -> 1983
/*    */     //   1980: goto -> 2026
/*    */     //   1983: getstatic f/km.pm0 : Lf/VD0;
/*    */     //   1986: iconst_1
/*    */     //   1987: sipush #365
/*    */     //   1990: invokevirtual Wk0 : (BS)V
/*    */     //   1993: goto -> 2026
/*    */     //   1996: getstatic f/km.pm0 : Lf/VD0;
/*    */     //   1999: iconst_0
/*    */     //   2000: sipush #305
/*    */     //   2003: invokevirtual Wk0 : (BS)V
/*    */     //   2006: goto -> 2026
/*    */     //   2009: getstatic f/km.pm0 : Lf/VD0;
/*    */     //   2012: aload_1
/*    */     //   2013: dup
/*    */     //   2014: getfield E10 : B
/*    */     //   2017: istore_2
/*    */     //   2018: getfield ar : S
/*    */     //   2021: iload_2
/*    */     //   2022: swap
/*    */     //   2023: invokevirtual Wk0 : (BS)V
/*    */     //   2026: aload_0
/*    */     //   2027: aload_1
/*    */     //   2028: putfield CR : Lf/IF0;
/*    */     //   2031: getstatic f/km.iE0 : Lf/r9;
/*    */     //   2034: invokevirtual Hf0 : ()V
/*    */     //   2037: aload_1
/*    */     //   2038: getstatic f/km.xn : Lf/Xc0;
/*    */     //   2041: astore_2
/*    */     //   2042: getfield UZ : Lf/vF;
/*    */     //   2045: dup
/*    */     //   2046: astore_3
/*    */     //   2047: aload_2
/*    */     //   2048: invokevirtual getClass : ()Ljava/lang/Class;
/*    */     //   2051: pop
/*    */     //   2052: getstatic f/vF.Cv0 : Lf/vF;
/*    */     //   2055: if_acmpne -> 2070
/*    */     //   2058: aload_2
/*    */     //   2059: iconst_0
/*    */     //   2060: invokevirtual G80 : (I)V
/*    */     //   2063: iconst_1
/*    */     //   2064: invokestatic yu : (Z)V
/*    */     //   2067: goto -> 2237
/*    */     //   2070: aload_3
/*    */     //   2071: getstatic f/vF.ud0 : Lf/vF;
/*    */     //   2074: if_acmpeq -> 2232
/*    */     //   2077: aload_3
/*    */     //   2078: getstatic f/vF.ai : Lf/vF;
/*    */     //   2081: if_acmpeq -> 2232
/*    */     //   2084: aload_3
/*    */     //   2085: getstatic f/vF.Ed0 : Lf/vF;
/*    */     //   2088: if_acmpne -> 2094
/*    */     //   2091: goto -> 2232
/*    */     //   2094: getstatic f/Xc0.B70 : Z
/*    */     //   2097: ifeq -> 2104
/*    */     //   2100: iconst_0
/*    */     //   2101: invokestatic yu : (Z)V
/*    */     //   2104: getstatic f/L70.gq : Lf/L70;
/*    */     //   2107: dup
/*    */     //   2108: astore_3
/*    */     //   2109: invokevirtual Rr0 : ()I
/*    */     //   2112: bipush #100
/*    */     //   2114: imul
/*    */     //   2115: aload_3
/*    */     //   2116: invokevirtual Zi0 : ()I
/*    */     //   2119: sipush #3600
/*    */     //   2122: irem
/*    */     //   2123: bipush #60
/*    */     //   2125: idiv
/*    */     //   2126: i2d
/*    */     //   2127: ldc2_w 1.65
/*    */     //   2130: dmul
/*    */     //   2131: d2i
/*    */     //   2132: iadd
/*    */     //   2133: dup
/*    */     //   2134: istore_3
/*    */     //   2135: sipush #1400
/*    */     //   2138: if_icmple -> 2151
/*    */     //   2141: iload_3
/*    */     //   2142: sipush #2000
/*    */     //   2145: if_icmpgt -> 2151
/*    */     //   2148: goto -> 2232
/*    */     //   2151: iload_3
/*    */     //   2152: sipush #700
/*    */     //   2155: if_icmplt -> 2165
/*    */     //   2158: iload_3
/*    */     //   2159: sipush #2000
/*    */     //   2162: if_icmple -> 2232
/*    */     //   2165: iload_3
/*    */     //   2166: sipush #2000
/*    */     //   2169: if_icmple -> 2191
/*    */     //   2172: iload_3
/*    */     //   2173: sipush #2255
/*    */     //   2176: if_icmpge -> 2191
/*    */     //   2179: aload_2
/*    */     //   2180: iload_3
/*    */     //   2181: sipush #2000
/*    */     //   2184: isub
/*    */     //   2185: invokevirtual G80 : (I)V
/*    */     //   2188: goto -> 2237
/*    */     //   2191: iload_3
/*    */     //   2192: sipush #445
/*    */     //   2195: if_icmple -> 2222
/*    */     //   2198: iload_3
/*    */     //   2199: sipush #700
/*    */     //   2202: if_icmpge -> 2222
/*    */     //   2205: aload_2
/*    */     //   2206: iload_3
/*    */     //   2207: sipush #445
/*    */     //   2210: isub
/*    */     //   2211: sipush #255
/*    */     //   2214: swap
/*    */     //   2215: isub
/*    */     //   2216: invokevirtual G80 : (I)V
/*    */     //   2219: goto -> 2237
/*    */     //   2222: aload_2
/*    */     //   2223: sipush #255
/*    */     //   2226: invokevirtual G80 : (I)V
/*    */     //   2229: goto -> 2237
/*    */     //   2232: aload_2
/*    */     //   2233: iconst_0
/*    */     //   2234: invokevirtual G80 : (I)V
/*    */     //   2237: getstatic f/h1.gt0 : Z
/*    */     //   2240: ifeq -> 2391
/*    */     //   2243: aload_1
/*    */     //   2244: aload_0
/*    */     //   2245: dup
/*    */     //   2246: getfield zU : Lf/tH;
/*    */     //   2249: astore_2
/*    */     //   2250: getfield C70 : Lf/RS;
/*    */     //   2253: astore_3
/*    */     //   2254: getfield Jf : I
/*    */     //   2257: iconst_1
/*    */     //   2258: if_icmplt -> 2391
/*    */     //   2261: aload_1
/*    */     //   2262: getfield kZ : I
/*    */     //   2265: iconst_1
/*    */     //   2266: if_icmpge -> 2272
/*    */     //   2269: goto -> 2391
/*    */     //   2272: aload_2
/*    */     //   2273: aload_3
/*    */     //   2274: aload_2
/*    */     //   2275: getstatic f/Xc0.Nn0 : F
/*    */     //   2278: invokevirtual og0 : (F)V
/*    */     //   2281: getstatic f/km.wI0 : Lf/Pw;
/*    */     //   2284: getfield iJ0 : Lf/Xi;
/*    */     //   2287: invokevirtual vD : ()Lf/Eb;
/*    */     //   2290: dup
/*    */     //   2291: aload_1
/*    */     //   2292: swap
/*    */     //   2293: getfield LW : Lf/eo;
/*    */     //   2296: dup
/*    */     //   2297: aload_1
/*    */     //   2298: swap
/*    */     //   2299: getfield x : F
/*    */     //   2302: f2i
/*    */     //   2303: istore_2
/*    */     //   2304: getfield Jf : I
/*    */     //   2307: bipush #16
/*    */     //   2309: imul
/*    */     //   2310: dup
/*    */     //   2311: istore_3
/*    */     //   2312: iconst_2
/*    */     //   2313: imul
/*    */     //   2314: iload_2
/*    */     //   2315: iadd
/*    */     //   2316: istore_2
/*    */     //   2317: getfield y : F
/*    */     //   2320: f2i
/*    */     //   2321: istore #4
/*    */     //   2323: getfield kZ : I
/*    */     //   2326: dup
/*    */     //   2327: istore #5
/*    */     //   2329: bipush #16
/*    */     //   2331: imul
/*    */     //   2332: dup
/*    */     //   2333: istore #6
/*    */     //   2335: iconst_2
/*    */     //   2336: imul
/*    */     //   2337: iload #4
/*    */     //   2339: iadd
/*    */     //   2340: istore #4
/*    */     //   2342: getfield pp0 : Lf/eo;
/*    */     //   2345: dup
/*    */     //   2346: getfield x : F
/*    */     //   2349: dup
/*    */     //   2350: iload_3
/*    */     //   2351: i2f
/*    */     //   2352: dup
/*    */     //   2353: fstore_3
/*    */     //   2354: frem
/*    */     //   2355: fsub
/*    */     //   2356: fload_3
/*    */     //   2357: fsub
/*    */     //   2358: fstore_3
/*    */     //   2359: getfield y : F
/*    */     //   2362: dup
/*    */     //   2363: iload #6
/*    */     //   2365: i2f
/*    */     //   2366: frem
/*    */     //   2367: fsub
/*    */     //   2368: iload #5
/*    */     //   2370: bipush #8
/*    */     //   2372: imul
/*    */     //   2373: i2f
/*    */     //   2374: fsub
/*    */     //   2375: fstore #5
/*    */     //   2377: getfield RE0 : Lcom/badlogic/gdx/graphics/Texture;
/*    */     //   2380: fload_3
/*    */     //   2381: fload #5
/*    */     //   2383: iconst_0
/*    */     //   2384: iconst_0
/*    */     //   2385: iload_2
/*    */     //   2386: iload #4
/*    */     //   2388: invokevirtual oS : (Lcom/badlogic/gdx/graphics/Texture;FFIIII)V
/*    */     //   2391: getstatic f/km.a3 : Lf/vh0;
/*    */     //   2394: dup
/*    */     //   2395: astore_2
/*    */     //   2396: ifnonnull -> 2402
/*    */     //   2399: goto -> 3007
/*    */     //   2402: aload_2
/*    */     //   2403: getfield Ct : Lf/Jo;
/*    */     //   2406: dup
/*    */     //   2407: astore_2
/*    */     //   2408: ifnonnull -> 2414
/*    */     //   2411: goto -> 3007
/*    */     //   2414: invokestatic Ek : ()I
/*    */     //   2417: dup
/*    */     //   2418: istore_3
/*    */     //   2419: iconst_1
/*    */     //   2420: if_icmpge -> 2493
/*    */     //   2423: getstatic f/Hk.Ki0 : Z
/*    */     //   2426: ifeq -> 2486
/*    */     //   2429: getstatic f/km.a3 : Lf/vh0;
/*    */     //   2432: invokevirtual iterator : ()Ljava/util/Iterator;
/*    */     //   2435: astore_2
/*    */     //   2436: aload_2
/*    */     //   2437: invokeinterface hasNext : ()Z
/*    */     //   2442: ifeq -> 2479
/*    */     //   2445: aload_2
/*    */     //   2446: invokeinterface next : ()Ljava/lang/Object;
/*    */     //   2451: checkcast f/tc
/*    */     //   2454: dup
/*    */     //   2455: dup
/*    */     //   2456: astore_3
/*    */     //   2457: invokevirtual getClass : ()Ljava/lang/Class;
/*    */     //   2460: pop
/*    */     //   2461: instanceof f/Jo
/*    */     //   2464: ifeq -> 2436
/*    */     //   2467: aload_3
/*    */     //   2468: invokevirtual default : ()Lf/static;
/*    */     //   2471: iconst_0
/*    */     //   2472: iconst_0
/*    */     //   2473: invokevirtual fH : (ZZ)V
/*    */     //   2476: goto -> 2436
/*    */     //   2479: aload_0
/*    */     //   2480: getfield tq0 : Lf/fQ;
/*    */     //   2483: invokevirtual clear : ()V
/*    */     //   2486: iconst_0
/*    */     //   2487: putstatic f/Hk.Ki0 : Z
/*    */     //   2490: goto -> 3007
/*    */     //   2493: aload_2
/*    */     //   2494: iconst_1
/*    */     //   2495: putstatic f/Hk.Ki0 : Z
/*    */     //   2498: getfield HW : Lf/G5;
/*    */     //   2501: dup
/*    */     //   2502: astore #4
/*    */     //   2504: invokevirtual getClass : ()Ljava/lang/Class;
/*    */     //   2507: pop
/*    */     //   2508: getstatic f/km.a3 : Lf/vh0;
/*    */     //   2511: aload #4
/*    */     //   2513: dup
/*    */     //   2514: dup
/*    */     //   2515: getfield FB : B
/*    */     //   2518: istore #4
/*    */     //   2520: getfield kD0 : B
/*    */     //   2523: istore #5
/*    */     //   2525: getfield vu0 : B
/*    */     //   2528: istore #6
/*    */     //   2530: iload #4
/*    */     //   2532: iload #5
/*    */     //   2534: iload #6
/*    */     //   2536: invokevirtual COm8 : (BBB)Lf/KI;
/*    */     //   2539: dup
/*    */     //   2540: astore #4
/*    */     //   2542: getstatic f/EB.Sh : Lf/eo;
/*    */     //   2545: aload_2
/*    */     //   2546: getfield pm : Lf/d7;
/*    */     //   2549: getfield cOm3 : Lf/eo;
/*    */     //   2552: invokevirtual JL : (Lf/eo;)Lf/eo;
/*    */     //   2555: pop
/*    */     //   2556: ifnull -> 2599
/*    */     //   2559: getstatic f/EB.Sh : Lf/eo;
/*    */     //   2562: dup
/*    */     //   2563: getfield x : F
/*    */     //   2566: aload #4
/*    */     //   2568: invokevirtual cp0 : ()I
/*    */     //   2571: bipush #16
/*    */     //   2573: idiv
/*    */     //   2574: i2f
/*    */     //   2575: fadd
/*    */     //   2576: putfield x : F
/*    */     //   2579: getstatic f/EB.Sh : Lf/eo;
/*    */     //   2582: dup
/*    */     //   2583: getfield y : F
/*    */     //   2586: aload #4
/*    */     //   2588: invokevirtual kf0 : ()I
/*    */     //   2591: bipush #16
/*    */     //   2593: idiv
/*    */     //   2594: i2f
/*    */     //   2595: fadd
/*    */     //   2596: putfield y : F
/*    */     //   2599: getstatic f/km.a3 : Lf/vh0;
/*    */     //   2602: invokevirtual iterator : ()Ljava/util/Iterator;
/*    */     //   2605: astore_2
/*    */     //   2606: aload_2
/*    */     //   2607: invokeinterface hasNext : ()Z
/*    */     //   2612: ifeq -> 2774
/*    */     //   2615: aload_2
/*    */     //   2616: invokeinterface next : ()Ljava/lang/Object;
/*    */     //   2621: checkcast f/tc
/*    */     //   2624: dup
/*    */     //   2625: dup
/*    */     //   2626: astore #4
/*    */     //   2628: invokevirtual getClass : ()Ljava/lang/Class;
/*    */     //   2631: pop
/*    */     //   2632: instanceof f/Jo
/*    */     //   2635: ifeq -> 2606
/*    */     //   2638: aload #4
/*    */     //   2640: checkcast f/Jo
/*    */     //   2643: dup
/*    */     //   2644: astore #4
/*    */     //   2646: getfield HW : Lf/G5;
/*    */     //   2649: dup
/*    */     //   2650: astore #5
/*    */     //   2652: invokevirtual getClass : ()Ljava/lang/Class;
/*    */     //   2655: pop
/*    */     //   2656: getstatic f/km.a3 : Lf/vh0;
/*    */     //   2659: aload #5
/*    */     //   2661: dup
/*    */     //   2662: dup
/*    */     //   2663: getfield FB : B
/*    */     //   2666: istore #5
/*    */     //   2668: getfield kD0 : B
/*    */     //   2671: istore #6
/*    */     //   2673: getfield vu0 : B
/*    */     //   2676: istore #7
/*    */     //   2678: iload #5
/*    */     //   2680: iload #6
/*    */     //   2682: iload #7
/*    */     //   2684: invokevirtual COm8 : (BBB)Lf/KI;
/*    */     //   2687: dup
/*    */     //   2688: astore #5
/*    */     //   2690: getstatic f/EB.Ti : Lf/eo;
/*    */     //   2693: aload #4
/*    */     //   2695: getfield pm : Lf/d7;
/*    */     //   2698: getfield cOm3 : Lf/eo;
/*    */     //   2701: invokevirtual JL : (Lf/eo;)Lf/eo;
/*    */     //   2704: pop
/*    */     //   2705: ifnull -> 2748
/*    */     //   2708: getstatic f/EB.Ti : Lf/eo;
/*    */     //   2711: dup
/*    */     //   2712: getfield x : F
/*    */     //   2715: aload #5
/*    */     //   2717: invokevirtual cp0 : ()I
/*    */     //   2720: bipush #16
/*    */     //   2722: idiv
/*    */     //   2723: i2f
/*    */     //   2724: fadd
/*    */     //   2725: putfield x : F
/*    */     //   2728: getstatic f/EB.Ti : Lf/eo;
/*    */     //   2731: dup
/*    */     //   2732: getfield y : F
/*    */     //   2735: aload #5
/*    */     //   2737: invokevirtual kf0 : ()I
/*    */     //   2740: bipush #16
/*    */     //   2742: idiv
/*    */     //   2743: i2f
/*    */     //   2744: fadd
/*    */     //   2745: putfield y : F
/*    */     //   2748: aload_0
/*    */     //   2749: aload #4
/*    */     //   2751: getstatic f/EB.Sh : Lf/eo;
/*    */     //   2754: getstatic f/EB.Ti : Lf/eo;
/*    */     //   2757: invokevirtual u50 : (Lf/eo;)F
/*    */     //   2760: putfield xc : F
/*    */     //   2763: getfield tq0 : Lf/fQ;
/*    */     //   2766: aload #4
/*    */     //   2768: invokevirtual Com3 : (Ljava/lang/Object;)V
/*    */     //   2771: goto -> 2606
/*    */     //   2774: aload_0
/*    */     //   2775: dup
/*    */     //   2776: getfield tq0 : Lf/fQ;
/*    */     //   2779: getstatic f/Jo.of : Lf/Fz0;
/*    */     //   2782: invokevirtual sort : (Ljava/util/Comparator;)V
/*    */     //   2785: new f/V6
/*    */     //   2788: dup
/*    */     //   2789: astore_2
/*    */     //   2790: invokespecial <init> : ()V
/*    */     //   2793: new f/V6
/*    */     //   2796: dup
/*    */     //   2797: astore #4
/*    */     //   2799: invokespecial <init> : ()V
/*    */     //   2802: iconst_0
/*    */     //   2803: istore #5
/*    */     //   2805: getfield tq0 : Lf/fQ;
/*    */     //   2808: getfield Z8 : I
/*    */     //   2811: istore #6
/*    */     //   2813: iload #5
/*    */     //   2815: iload #6
/*    */     //   2817: if_icmpge -> 2901
/*    */     //   2820: aload_0
/*    */     //   2821: getfield tq0 : Lf/fQ;
/*    */     //   2824: iload #5
/*    */     //   2826: invokevirtual get : (I)Ljava/lang/Object;
/*    */     //   2829: checkcast f/Jo
/*    */     //   2832: dup
/*    */     //   2833: astore #7
/*    */     //   2835: getfield pm : Lf/d7;
/*    */     //   2838: getfield n3 : Z
/*    */     //   2841: ifeq -> 2847
/*    */     //   2844: goto -> 2895
/*    */     //   2847: aload_2
/*    */     //   2848: aload #7
/*    */     //   2850: getfield HW : Lf/G5;
/*    */     //   2853: dup
/*    */     //   2854: astore #8
/*    */     //   2856: getfield mm : S
/*    */     //   2859: aload #8
/*    */     //   2861: getfield Yu0 : S
/*    */     //   2864: bipush #16
/*    */     //   2866: ishl
/*    */     //   2867: ior
/*    */     //   2868: dup
/*    */     //   2869: istore #8
/*    */     //   2871: invokevirtual return : (I)Z
/*    */     //   2874: ifne -> 2895
/*    */     //   2877: aload #4
/*    */     //   2879: aload #7
/*    */     //   2881: aload_2
/*    */     //   2882: iload #8
/*    */     //   2884: invokevirtual uX : (I)Z
/*    */     //   2887: pop
/*    */     //   2888: getfield Jg : I
/*    */     //   2891: invokevirtual uX : (I)Z
/*    */     //   2894: pop
/*    */     //   2895: iinc #5, 1
/*    */     //   2898: goto -> 2813
/*    */     //   2901: iconst_0
/*    */     //   2902: istore_2
/*    */     //   2903: iconst_0
/*    */     //   2904: istore #5
/*    */     //   2906: iload #5
/*    */     //   2908: iload #6
/*    */     //   2910: if_icmpge -> 3000
/*    */     //   2913: aload_0
/*    */     //   2914: getfield tq0 : Lf/fQ;
/*    */     //   2917: iload #6
/*    */     //   2919: iload #5
/*    */     //   2921: isub
/*    */     //   2922: iconst_1
/*    */     //   2923: isub
/*    */     //   2924: invokevirtual get : (I)Ljava/lang/Object;
/*    */     //   2927: checkcast f/Jo
/*    */     //   2930: dup
/*    */     //   2931: astore #7
/*    */     //   2933: iconst_0
/*    */     //   2934: istore #8
/*    */     //   2936: iconst_1
/*    */     //   2937: istore #9
/*    */     //   2939: getfield pm : Lf/d7;
/*    */     //   2942: getfield n3 : Z
/*    */     //   2945: ifne -> 2970
/*    */     //   2948: aload #4
/*    */     //   2950: aload #7
/*    */     //   2952: getfield Jg : I
/*    */     //   2955: invokevirtual return : (I)Z
/*    */     //   2958: ifne -> 2970
/*    */     //   2961: iconst_1
/*    */     //   2962: istore #8
/*    */     //   2964: iconst_0
/*    */     //   2965: istore #9
/*    */     //   2967: goto -> 2982
/*    */     //   2970: iload_2
/*    */     //   2971: iconst_1
/*    */     //   2972: iadd
/*    */     //   2973: dup
/*    */     //   2974: istore_2
/*    */     //   2975: iload_3
/*    */     //   2976: if_icmple -> 2982
/*    */     //   2979: iconst_1
/*    */     //   2980: istore #8
/*    */     //   2982: aload #7
/*    */     //   2984: getfield J : Lf/static;
/*    */     //   2987: iload #8
/*    */     //   2989: iload #9
/*    */     //   2991: invokevirtual fH : (ZZ)V
/*    */     //   2994: iinc #5, 1
/*    */     //   2997: goto -> 2906
/*    */     //   3000: aload_0
/*    */     //   3001: getfield tq0 : Lf/fQ;
/*    */     //   3004: invokevirtual clear : ()V
/*    */     //   3007: iconst_0
/*    */     //   3008: istore_2
/*    */     //   3009: iload_2
/*    */     //   3010: iconst_3
/*    */     //   3011: if_icmpge -> 3310
/*    */     //   3014: aload_1
/*    */     //   3015: getfield r4 : [Lf/Rw0;
/*    */     //   3018: dup
/*    */     //   3019: astore_3
/*    */     //   3020: arraylength
/*    */     //   3021: istore #4
/*    */     //   3023: iconst_0
/*    */     //   3024: istore #5
/*    */     //   3026: iload #5
/*    */     //   3028: iload #4
/*    */     //   3030: if_icmpge -> 3138
/*    */     //   3033: aload_3
/*    */     //   3034: iload #5
/*    */     //   3036: aaload
/*    */     //   3037: dup
/*    */     //   3038: astore #6
/*    */     //   3040: invokevirtual getClass : ()Ljava/lang/Class;
/*    */     //   3043: pop
/*    */     //   3044: getstatic f/km.a3 : Lf/vh0;
/*    */     //   3047: aload #6
/*    */     //   3049: dup
/*    */     //   3050: dup
/*    */     //   3051: getfield El0 : B
/*    */     //   3054: istore #7
/*    */     //   3056: getfield uj0 : B
/*    */     //   3059: istore #8
/*    */     //   3061: getfield Wy0 : B
/*    */     //   3064: istore #9
/*    */     //   3066: iload #7
/*    */     //   3068: iload #8
/*    */     //   3070: iload #9
/*    */     //   3072: invokevirtual COm8 : (BBB)Lf/KI;
/*    */     //   3075: checkcast f/IF0
/*    */     //   3078: dup
/*    */     //   3079: astore #7
/*    */     //   3081: ifnonnull -> 3087
/*    */     //   3084: goto -> 3132
/*    */     //   3087: aload #6
/*    */     //   3089: getfield Ac : Lf/c6;
/*    */     //   3092: invokevirtual ordinal : ()I
/*    */     //   3095: iconst_2
/*    */     //   3096: if_icmpeq -> 3102
/*    */     //   3099: goto -> 3132
/*    */     //   3102: aload #7
/*    */     //   3104: aload_0
/*    */     //   3105: dup
/*    */     //   3106: dup
/*    */     //   3107: getfield zU : Lf/tH;
/*    */     //   3110: astore #6
/*    */     //   3112: getfield PF : Lf/Tm;
/*    */     //   3115: astore #7
/*    */     //   3117: getfield oj : Lf/Eb;
/*    */     //   3120: astore #8
/*    */     //   3122: aload #6
/*    */     //   3124: aload #7
/*    */     //   3126: aload #8
/*    */     //   3128: iload_2
/*    */     //   3129: invokevirtual uY : (Lf/tH;Lf/Tm;Lf/Eb;I)V
/*    */     //   3132: iinc #5, 1
/*    */     //   3135: goto -> 3026
/*    */     //   3138: aload_1
/*    */     //   3139: dup
/*    */     //   3140: aload_0
/*    */     //   3141: dup
/*    */     //   3142: dup
/*    */     //   3143: getfield zU : Lf/tH;
/*    */     //   3146: astore_3
/*    */     //   3147: getfield PF : Lf/Tm;
/*    */     //   3150: astore #4
/*    */     //   3152: getfield oj : Lf/Eb;
/*    */     //   3155: astore #5
/*    */     //   3157: aload_3
/*    */     //   3158: aload #4
/*    */     //   3160: aload #5
/*    */     //   3162: iload_2
/*    */     //   3163: invokevirtual uY : (Lf/tH;Lf/Tm;Lf/Eb;I)V
/*    */     //   3166: getfield r4 : [Lf/Rw0;
/*    */     //   3169: dup
/*    */     //   3170: astore_3
/*    */     //   3171: arraylength
/*    */     //   3172: istore #4
/*    */     //   3174: iconst_0
/*    */     //   3175: istore #5
/*    */     //   3177: iload #5
/*    */     //   3179: iload #4
/*    */     //   3181: if_icmpge -> 3304
/*    */     //   3184: aload_3
/*    */     //   3185: iload #5
/*    */     //   3187: aaload
/*    */     //   3188: dup
/*    */     //   3189: astore #6
/*    */     //   3191: invokevirtual getClass : ()Ljava/lang/Class;
/*    */     //   3194: pop
/*    */     //   3195: getstatic f/km.a3 : Lf/vh0;
/*    */     //   3198: aload #6
/*    */     //   3200: dup
/*    */     //   3201: dup
/*    */     //   3202: getfield El0 : B
/*    */     //   3205: istore #7
/*    */     //   3207: getfield uj0 : B
/*    */     //   3210: istore #8
/*    */     //   3212: getfield Wy0 : B
/*    */     //   3215: istore #9
/*    */     //   3217: iload #7
/*    */     //   3219: iload #8
/*    */     //   3221: iload #9
/*    */     //   3223: invokevirtual COm8 : (BBB)Lf/KI;
/*    */     //   3226: checkcast f/IF0
/*    */     //   3229: dup
/*    */     //   3230: astore #7
/*    */     //   3232: ifnonnull -> 3238
/*    */     //   3235: goto -> 3298
/*    */     //   3238: aload #6
/*    */     //   3240: getfield Ac : Lf/c6;
/*    */     //   3243: invokevirtual ordinal : ()I
/*    */     //   3246: dup
/*    */     //   3247: istore #6
/*    */     //   3249: iconst_1
/*    */     //   3250: if_icmpeq -> 3268
/*    */     //   3253: iload #6
/*    */     //   3255: iconst_3
/*    */     //   3256: if_icmpeq -> 3268
/*    */     //   3259: iload #6
/*    */     //   3261: iconst_4
/*    */     //   3262: if_icmpeq -> 3268
/*    */     //   3265: goto -> 3298
/*    */     //   3268: aload #7
/*    */     //   3270: aload_0
/*    */     //   3271: dup
/*    */     //   3272: dup
/*    */     //   3273: getfield zU : Lf/tH;
/*    */     //   3276: astore #6
/*    */     //   3278: getfield PF : Lf/Tm;
/*    */     //   3281: astore #7
/*    */     //   3283: getfield oj : Lf/Eb;
/*    */     //   3286: astore #8
/*    */     //   3288: aload #6
/*    */     //   3290: aload #7
/*    */     //   3292: aload #8
/*    */     //   3294: iload_2
/*    */     //   3295: invokevirtual uY : (Lf/tH;Lf/Tm;Lf/Eb;I)V
/*    */     //   3298: iinc #5, 1
/*    */     //   3301: goto -> 3177
/*    */     //   3304: iinc #2, 1
/*    */     //   3307: goto -> 3009
/*    */     //   3310: getstatic f/km.a3 : Lf/vh0;
/*    */     //   3313: ifnonnull -> 3319
/*    */     //   3316: goto -> 3735
/*    */     //   3319: aload_0
/*    */     //   3320: getfield Db0 : Lf/SI;
/*    */     //   3323: dup
/*    */     //   3324: astore_1
/*    */     //   3325: ifnull -> 3354
/*    */     //   3328: aload_1
/*    */     //   3329: aload_0
/*    */     //   3330: getfield zU : Lf/tH;
/*    */     //   3333: astore_2
/*    */     //   3334: getfield while : Z
/*    */     //   3337: ifne -> 3349
/*    */     //   3340: aload_1
/*    */     //   3341: dup
/*    */     //   3342: invokevirtual Zq : ()V
/*    */     //   3345: iconst_1
/*    */     //   3346: putfield while : Z
/*    */     //   3349: aload_1
/*    */     //   3350: aload_2
/*    */     //   3351: invokevirtual IA : (Lf/tH;)V
/*    */     //   3354: aload_0
/*    */     //   3355: getfield Dg0 : Lf/SI;
/*    */     //   3358: dup
/*    */     //   3359: astore_1
/*    */     //   3360: ifnull -> 3389
/*    */     //   3363: aload_1
/*    */     //   3364: aload_0
/*    */     //   3365: getfield zU : Lf/tH;
/*    */     //   3368: astore_2
/*    */     //   3369: getfield while : Z
/*    */     //   3372: ifne -> 3384
/*    */     //   3375: aload_1
/*    */     //   3376: dup
/*    */     //   3377: invokevirtual Zq : ()V
/*    */     //   3380: iconst_1
/*    */     //   3381: putfield while : Z
/*    */     //   3384: aload_1
/*    */     //   3385: aload_2
/*    */     //   3386: invokevirtual IA : (Lf/tH;)V
/*    */     //   3389: getstatic f/km.a3 : Lf/vh0;
/*    */     //   3392: invokevirtual Jr0 : ()Lf/KI;
/*    */     //   3395: dup
/*    */     //   3396: astore_1
/*    */     //   3397: ifnonnull -> 3403
/*    */     //   3400: goto -> 3735
/*    */     //   3403: getstatic f/km.a3 : Lf/vh0;
/*    */     //   3406: getfield Ct : Lf/Jo;
/*    */     //   3409: ifnull -> 3735
/*    */     //   3412: aload_1
/*    */     //   3413: aload_0
/*    */     //   3414: aload_1
/*    */     //   3415: invokevirtual dr0 : (Lf/KI;)V
/*    */     //   3418: getfield Eo : Lf/xm;
/*    */     //   3421: getstatic f/xm.jQ : Lf/xm;
/*    */     //   3424: if_acmpne -> 3434
/*    */     //   3427: aload_1
/*    */     //   3428: getfield lpT1 : Z
/*    */     //   3431: ifeq -> 3735
/*    */     //   3434: getstatic f/km.u4 : Lf/R8;
/*    */     //   3437: getfield Ta0 : I
/*    */     //   3440: bipush #7
/*    */     //   3442: if_icmpeq -> 3735
/*    */     //   3445: aload_0
/*    */     //   3446: dup
/*    */     //   3447: dup
/*    */     //   3448: dup2
/*    */     //   3449: dup2
/*    */     //   3450: getfield Bu0 : F
/*    */     //   3453: ldc_w 10.0
/*    */     //   3456: fmul
/*    */     //   3457: invokestatic round : (F)I
/*    */     //   3460: i2f
/*    */     //   3461: ldc_w 10.0
/*    */     //   3464: fdiv
/*    */     //   3465: bipush #49
/*    */     //   3467: i2f
/*    */     //   3468: fstore_1
/*    */     //   3469: bipush #24
/*    */     //   3471: i2f
/*    */     //   3472: fmul
/*    */     //   3473: fload_1
/*    */     //   3474: fadd
/*    */     //   3475: f2i
/*    */     //   3476: istore_1
/*    */     //   3477: getfield oj : Lf/Eb;
/*    */     //   3480: dup
/*    */     //   3481: getfield LW : Lf/eo;
/*    */     //   3484: dup
/*    */     //   3485: getfield x : F
/*    */     //   3488: fstore_2
/*    */     //   3489: getfield y : F
/*    */     //   3492: fstore_3
/*    */     //   3493: getfield pp0 : Lf/eo;
/*    */     //   3496: dup
/*    */     //   3497: getfield x : F
/*    */     //   3500: f2i
/*    */     //   3501: istore #4
/*    */     //   3503: getfield y : F
/*    */     //   3506: f2i
/*    */     //   3507: dup
/*    */     //   3508: istore #5
/*    */     //   3510: fload_3
/*    */     //   3511: iload #4
/*    */     //   3513: fload_2
/*    */     //   3514: fconst_2
/*    */     //   3515: fdiv
/*    */     //   3516: f2i
/*    */     //   3517: iadd
/*    */     //   3518: iload_1
/*    */     //   3519: iconst_2
/*    */     //   3520: idiv
/*    */     //   3521: dup
/*    */     //   3522: istore #6
/*    */     //   3524: isub
/*    */     //   3525: istore #7
/*    */     //   3527: fconst_2
/*    */     //   3528: fdiv
/*    */     //   3529: f2i
/*    */     //   3530: iadd
/*    */     //   3531: iload #6
/*    */     //   3533: isub
/*    */     //   3534: bipush #-10
/*    */     //   3536: iadd
/*    */     //   3537: istore #6
/*    */     //   3539: getfield zU : Lf/tH;
/*    */     //   3542: iload_1
/*    */     //   3543: iload #6
/*    */     //   3545: iload #7
/*    */     //   3547: invokestatic ZZ : ()Lf/interface;
/*    */     //   3550: getfield d5 : [Lcom/badlogic/gdx/graphics/Texture;
/*    */     //   3553: iconst_0
/*    */     //   3554: aaload
/*    */     //   3555: astore #8
/*    */     //   3557: i2f
/*    */     //   3558: fstore #9
/*    */     //   3560: i2f
/*    */     //   3561: fstore #10
/*    */     //   3563: i2f
/*    */     //   3564: fstore #11
/*    */     //   3566: aload #8
/*    */     //   3568: fload #9
/*    */     //   3570: fload #10
/*    */     //   3572: fload #11
/*    */     //   3574: dup
/*    */     //   3575: invokevirtual Ap0 : (Lcom/badlogic/gdx/graphics/Texture;FFFF)V
/*    */     //   3578: getfield zU : Lf/tH;
/*    */     //   3581: iload #6
/*    */     //   3583: iload #5
/*    */     //   3585: iload #4
/*    */     //   3587: invokestatic ZZ : ()Lf/interface;
/*    */     //   3590: getfield kO : Lcom/badlogic/gdx/graphics/Texture;
/*    */     //   3593: astore #8
/*    */     //   3595: i2f
/*    */     //   3596: fstore #9
/*    */     //   3598: i2f
/*    */     //   3599: fstore #10
/*    */     //   3601: iconst_2
/*    */     //   3602: iadd
/*    */     //   3603: iload #5
/*    */     //   3605: ineg
/*    */     //   3606: iadd
/*    */     //   3607: i2f
/*    */     //   3608: fstore #5
/*    */     //   3610: aload #8
/*    */     //   3612: fload #9
/*    */     //   3614: fload #10
/*    */     //   3616: fload_2
/*    */     //   3617: fload #5
/*    */     //   3619: invokevirtual Ap0 : (Lcom/badlogic/gdx/graphics/Texture;FFFF)V
/*    */     //   3622: getfield zU : Lf/tH;
/*    */     //   3625: fload_3
/*    */     //   3626: iload #6
/*    */     //   3628: iload_1
/*    */     //   3629: invokestatic ZZ : ()Lf/interface;
/*    */     //   3632: getfield kO : Lcom/badlogic/gdx/graphics/Texture;
/*    */     //   3635: astore_3
/*    */     //   3636: iadd
/*    */     //   3637: iconst_2
/*    */     //   3638: isub
/*    */     //   3639: i2f
/*    */     //   3640: fstore #5
/*    */     //   3642: f2i
/*    */     //   3643: istore #6
/*    */     //   3645: aload_3
/*    */     //   3646: iload #6
/*    */     //   3648: iconst_4
/*    */     //   3649: iadd
/*    */     //   3650: i2f
/*    */     //   3651: fstore_3
/*    */     //   3652: fload #9
/*    */     //   3654: fload #5
/*    */     //   3656: fload_2
/*    */     //   3657: fload_3
/*    */     //   3658: invokevirtual Ap0 : (Lcom/badlogic/gdx/graphics/Texture;FFFF)V
/*    */     //   3661: getfield zU : Lf/tH;
/*    */     //   3664: iload #6
/*    */     //   3666: iload #7
/*    */     //   3668: invokestatic ZZ : ()Lf/interface;
/*    */     //   3671: getfield kO : Lcom/badlogic/gdx/graphics/Texture;
/*    */     //   3674: astore_3
/*    */     //   3675: iconst_2
/*    */     //   3676: iadd
/*    */     //   3677: iload #4
/*    */     //   3679: ineg
/*    */     //   3680: iadd
/*    */     //   3681: i2f
/*    */     //   3682: fstore #4
/*    */     //   3684: i2f
/*    */     //   3685: fstore #5
/*    */     //   3687: aload_3
/*    */     //   3688: fload #9
/*    */     //   3690: fload #10
/*    */     //   3692: fload #4
/*    */     //   3694: fload #5
/*    */     //   3696: invokevirtual Ap0 : (Lcom/badlogic/gdx/graphics/Texture;FFFF)V
/*    */     //   3699: getfield zU : Lf/tH;
/*    */     //   3702: iload #7
/*    */     //   3704: iload_1
/*    */     //   3705: invokestatic ZZ : ()Lf/interface;
/*    */     //   3708: getfield kO : Lcom/badlogic/gdx/graphics/Texture;
/*    */     //   3711: astore_1
/*    */     //   3712: iadd
/*    */     //   3713: iconst_2
/*    */     //   3714: isub
/*    */     //   3715: i2f
/*    */     //   3716: fstore_3
/*    */     //   3717: aload_1
/*    */     //   3718: fload_2
/*    */     //   3719: f2i
/*    */     //   3720: iconst_2
/*    */     //   3721: idiv
/*    */     //   3722: iconst_4
/*    */     //   3723: iadd
/*    */     //   3724: i2f
/*    */     //   3725: fstore_1
/*    */     //   3726: fload_3
/*    */     //   3727: fload #10
/*    */     //   3729: fload_1
/*    */     //   3730: fload #5
/*    */     //   3732: invokevirtual Ap0 : (Lcom/badlogic/gdx/graphics/Texture;FFFF)V
/*    */     //   3735: getstatic f/km.a3 : Lf/vh0;
/*    */     //   3738: ifnull -> 4287
/*    */     //   3741: getstatic f/ro.l10 : B
/*    */     //   3744: ifle -> 4287
/*    */     //   3747: getstatic f/wJ0.Nf0 : Lf/wJ0;
/*    */     //   3750: dup
/*    */     //   3751: invokevirtual LE : ()I
/*    */     //   3754: getstatic f/km.a3 : Lf/vh0;
/*    */     //   3757: getfield Ct : Lf/Jo;
/*    */     //   3760: getfield HW : Lf/G5;
/*    */     //   3763: getfield mm : S
/*    */     //   3766: bipush #16
/*    */     //   3768: imul
/*    */     //   3769: swap
/*    */     //   3770: iadd
/*    */     //   3771: istore_1
/*    */     //   3772: invokevirtual Lh : ()I
/*    */     //   3775: getstatic f/km.a3 : Lf/vh0;
/*    */     //   3778: getfield Ct : Lf/Jo;
/*    */     //   3781: getfield HW : Lf/G5;
/*    */     //   3784: getfield Yu0 : S
/*    */     //   3787: bipush #16
/*    */     //   3789: imul
/*    */     //   3790: swap
/*    */     //   3791: iadd
/*    */     //   3792: istore_2
/*    */     //   3793: getstatic f/ro.l10 : B
/*    */     //   3796: dup
/*    */     //   3797: istore_3
/*    */     //   3798: iconst_1
/*    */     //   3799: if_icmpne -> 4240
/*    */     //   3802: getstatic f/HQ.Z90 : Lf/HQ;
/*    */     //   3805: getstatic f/ro.eL : S
/*    */     //   3808: invokevirtual Qe : (S)Lf/lj0;
/*    */     //   3811: dup
/*    */     //   3812: astore_3
/*    */     //   3813: getfield iC0 : B
/*    */     //   3816: iconst_4
/*    */     //   3817: if_icmpeq -> 4072
/*    */     //   3820: aload_3
/*    */     //   3821: getfield pf0 : Z
/*    */     //   3824: ifeq -> 3830
/*    */     //   3827: goto -> 4072
/*    */     //   3830: getstatic f/km.a3 : Lf/vh0;
/*    */     //   3833: invokevirtual Jr0 : ()Lf/KI;
/*    */     //   3836: dup
/*    */     //   3837: astore #4
/*    */     //   3839: instanceof f/IF0
/*    */     //   3842: ifne -> 3848
/*    */     //   3845: goto -> 4287
/*    */     //   3848: aload #4
/*    */     //   3850: checkcast f/IF0
/*    */     //   3853: astore #4
/*    */     //   3855: iconst_0
/*    */     //   3856: istore #5
/*    */     //   3858: aload_3
/*    */     //   3859: getfield wW : B
/*    */     //   3862: tableswitch default -> 3916, 0 -> 3940, 1 -> 3940, 2 -> 3916, 3 -> 3934, 4 -> 3934, 5 -> 3934, 6 -> 3916, 7 -> 3928, 8 -> 3922, 9 -> 3934
/*    */     //   3916: iconst_0
/*    */     //   3917: istore #6
/*    */     //   3919: goto -> 3943
/*    */     //   3922: iconst_3
/*    */     //   3923: istore #6
/*    */     //   3925: goto -> 3943
/*    */     //   3928: iconst_4
/*    */     //   3929: istore #6
/*    */     //   3931: goto -> 3943
/*    */     //   3934: iconst_2
/*    */     //   3935: istore #6
/*    */     //   3937: goto -> 3943
/*    */     //   3940: iconst_1
/*    */     //   3941: istore #6
/*    */     //   3943: iload #5
/*    */     //   3945: iload #6
/*    */     //   3947: if_icmpge -> 4287
/*    */     //   3950: iconst_0
/*    */     //   3951: istore #6
/*    */     //   3953: iload #6
/*    */     //   3955: aload_3
/*    */     //   3956: invokevirtual js0 : ()I
/*    */     //   3959: if_icmpge -> 4066
/*    */     //   3962: aload #4
/*    */     //   3964: getfield hz0 : Lf/AC0;
/*    */     //   3967: aload_3
/*    */     //   3968: getfield tJ : [S
/*    */     //   3971: aload_3
/*    */     //   3972: invokevirtual js0 : ()I
/*    */     //   3975: iload #5
/*    */     //   3977: imul
/*    */     //   3978: iload #6
/*    */     //   3980: iadd
/*    */     //   3981: saload
/*    */     //   3982: sipush #512
/*    */     //   3985: iadd
/*    */     //   3986: istore #7
/*    */     //   3988: getfield KL : [Lf/a4;
/*    */     //   3991: iload #7
/*    */     //   3993: aaload
/*    */     //   3994: dup
/*    */     //   3995: astore #7
/*    */     //   3997: ifnonnull -> 4003
/*    */     //   4000: goto -> 4287
/*    */     //   4003: invokestatic nanoTime : ()J
/*    */     //   4006: ldc2_w 300000000
/*    */     //   4009: ldiv
/*    */     //   4010: ldc2_w 2
/*    */     //   4013: lrem
/*    */     //   4014: lconst_1
/*    */     //   4015: lcmp
/*    */     //   4016: ifne -> 4060
/*    */     //   4019: aload_0
/*    */     //   4020: getfield zU : Lf/tH;
/*    */     //   4023: iload #5
/*    */     //   4025: iload #6
/*    */     //   4027: aload #7
/*    */     //   4029: iconst_1
/*    */     //   4030: invokevirtual GC0 : (I)Lf/pe0;
/*    */     //   4033: astore #7
/*    */     //   4035: bipush #16
/*    */     //   4037: imul
/*    */     //   4038: iload_1
/*    */     //   4039: iadd
/*    */     //   4040: i2f
/*    */     //   4041: fstore #8
/*    */     //   4043: bipush #16
/*    */     //   4045: imul
/*    */     //   4046: iload_2
/*    */     //   4047: iadd
/*    */     //   4048: i2f
/*    */     //   4049: fstore #9
/*    */     //   4051: aload #7
/*    */     //   4053: fload #8
/*    */     //   4055: fload #9
/*    */     //   4057: invokevirtual TB : (Lf/pe0;FF)V
/*    */     //   4060: iinc #6, 1
/*    */     //   4063: goto -> 3953
/*    */     //   4066: iinc #5, 1
/*    */     //   4069: goto -> 3858
/*    */     //   4072: aload_3
/*    */     //   4073: invokevirtual x5 : ()S
/*    */     //   4076: dup
/*    */     //   4077: istore #4
/*    */     //   4079: getstatic f/G00.Av0 : Lf/G00;
/*    */     //   4082: aload_3
/*    */     //   4083: getfield interface : B
/*    */     //   4086: iload #4
/*    */     //   4088: iconst_0
/*    */     //   4089: invokevirtual Cx0 : (BIZ)Lf/LJ;
/*    */     //   4092: iconst_0
/*    */     //   4093: invokevirtual LT : (I)Lf/U70;
/*    */     //   4096: dup
/*    */     //   4097: dup2
/*    */     //   4098: astore_3
/*    */     //   4099: invokevirtual HA0 : ()Lcom/badlogic/gdx/graphics/Texture;
/*    */     //   4102: pop
/*    */     //   4103: getfield mv : I
/*    */     //   4106: istore #5
/*    */     //   4108: getfield s7 : I
/*    */     //   4111: istore #6
/*    */     //   4113: sipush #200
/*    */     //   4116: if_icmplt -> 4154
/*    */     //   4119: iload #4
/*    */     //   4121: sipush #300
/*    */     //   4124: if_icmpge -> 4154
/*    */     //   4127: iload #4
/*    */     //   4129: sipush #211
/*    */     //   4132: if_icmpne -> 4146
/*    */     //   4135: bipush #24
/*    */     //   4137: istore #5
/*    */     //   4139: bipush #36
/*    */     //   4141: istore #6
/*    */     //   4143: goto -> 4154
/*    */     //   4146: bipush #24
/*    */     //   4148: istore #5
/*    */     //   4150: bipush #24
/*    */     //   4152: istore #6
/*    */     //   4154: iload #5
/*    */     //   4156: bipush #16
/*    */     //   4158: if_icmple -> 4171
/*    */     //   4161: iload_1
/*    */     //   4162: iload #5
/*    */     //   4164: bipush #16
/*    */     //   4166: isub
/*    */     //   4167: iconst_2
/*    */     //   4168: idiv
/*    */     //   4169: isub
/*    */     //   4170: istore_1
/*    */     //   4171: iload #6
/*    */     //   4173: bipush #16
/*    */     //   4175: if_icmple -> 4186
/*    */     //   4178: iload_2
/*    */     //   4179: iload #6
/*    */     //   4181: bipush #16
/*    */     //   4183: isub
/*    */     //   4184: isub
/*    */     //   4185: istore_2
/*    */     //   4186: invokestatic nanoTime : ()J
/*    */     //   4189: ldc2_w 300000000
/*    */     //   4192: ldiv
/*    */     //   4193: ldc2_w 2
/*    */     //   4196: lrem
/*    */     //   4197: lconst_1
/*    */     //   4198: lcmp
/*    */     //   4199: ifne -> 4287
/*    */     //   4202: aload_0
/*    */     //   4203: getfield zU : Lf/tH;
/*    */     //   4206: iload #6
/*    */     //   4208: iload #5
/*    */     //   4210: iload_2
/*    */     //   4211: iload_1
/*    */     //   4212: aload_3
/*    */     //   4213: invokevirtual HA0 : ()Lcom/badlogic/gdx/graphics/Texture;
/*    */     //   4216: astore_1
/*    */     //   4217: i2f
/*    */     //   4218: fstore_2
/*    */     //   4219: i2f
/*    */     //   4220: fstore_3
/*    */     //   4221: i2f
/*    */     //   4222: fstore #4
/*    */     //   4224: i2f
/*    */     //   4225: fstore #5
/*    */     //   4227: aload_1
/*    */     //   4228: fload_2
/*    */     //   4229: fload_3
/*    */     //   4230: fload #4
/*    */     //   4232: fload #5
/*    */     //   4234: invokevirtual Ap0 : (Lcom/badlogic/gdx/graphics/Texture;FFFF)V
/*    */     //   4237: goto -> 4287
/*    */     //   4240: iload_3
/*    */     //   4241: iconst_2
/*    */     //   4242: if_icmpne -> 4287
/*    */     //   4245: invokestatic nanoTime : ()J
/*    */     //   4248: ldc2_w 300000000
/*    */     //   4251: ldiv
/*    */     //   4252: ldc2_w 2
/*    */     //   4255: lrem
/*    */     //   4256: lconst_1
/*    */     //   4257: lcmp
/*    */     //   4258: ifne -> 4287
/*    */     //   4261: aload_0
/*    */     //   4262: getfield zU : Lf/tH;
/*    */     //   4265: iload_2
/*    */     //   4266: iload_1
/*    */     //   4267: invokestatic Kw0 : ()Lf/h90;
/*    */     //   4270: getfield yH : Lf/U70;
/*    */     //   4273: invokevirtual HA0 : ()Lcom/badlogic/gdx/graphics/Texture;
/*    */     //   4276: astore_1
/*    */     //   4277: i2f
/*    */     //   4278: fstore_2
/*    */     //   4279: i2f
/*    */     //   4280: fstore_3
/*    */     //   4281: aload_1
/*    */     //   4282: fload_2
/*    */     //   4283: fload_3
/*    */     //   4284: invokevirtual VI : (Lcom/badlogic/gdx/graphics/Texture;FF)V
/*    */     //   4287: aload_0
/*    */     //   4288: getfield zU : Lf/tH;
/*    */     //   4291: invokevirtual end : ()V
/*    */     //   4294: goto -> 4302
/*    */     //   4297: aload_0
/*    */     //   4298: iconst_0
/*    */     //   4299: putfield w6 : Z
/*    */     //   4302: return
/*    */     // Line number table:
/*    */     //   Java source line number -> byte code offset
/*    */     //   #1	-> 17
/*    */     //   #2	-> 20
/*    */     //   #3	-> 27
/*    */     //   #4	-> 35
/*    */     //   #5	-> 38
/*    */     //   #6	-> 45
/*    */     //   #7	-> 73
/*    */     //   #8	-> 153
/*    */     //   #9	-> 156
/*    */     //   #10	-> 164
/*    */     //   #11	-> 169
/*    */     //   #12	-> 189
/*    */     //   #13	-> 201
/*    */     //   #14	-> 204
/*    */     //   #15	-> 212
/*    */     //   #16	-> 217
/*    */     //   #17	-> 237
/*    */     //   #18	-> 275
/*    */     //   #19	-> 278
/*    */     //   #20	-> 286
/*    */     //   #21	-> 291
/*    */     //   #22	-> 312
/*    */     //   #23	-> 321
/*    */     //   #24	-> 324
/*    */     //   #25	-> 332
/*    */     //   #26	-> 337
/*    */     //   #27	-> 358
/*    */     //   #28	-> 470
/*    */     //   #29	-> 476
/*    */     //   #30	-> 479
/*    */     //   #31	-> 504
/*    */     //   #32	-> 509
/*    */     //   #33	-> 540
/*    */     //   #34	-> 566
/*    */     //   #35	-> 575
/*    */     //   #36	-> 589
/*    */     //   #37	-> 595
/*    */     //   #38	-> 609
/*    */     //   #39	-> 618
/*    */     //   #40	-> 632
/*    */     //   #41	-> 655
/*    */     //   #42	-> 908
/*    */     //   #43	-> 911
/*    */     //   #44	-> 924
/*    */     //   #45	-> 977
/*    */     //   #46	-> 987
/*    */     //   #47	-> 992
/*    */     //   #48	-> 999
/*    */     //   #49	-> 1004
/*    */     //   #50	-> 1034
/*    */     //   #51	-> 1142
/*    */     //   #52	-> 1147
/*    */     //   #53	-> 1193
/*    */     //   #54	-> 1199
/*    */     //   #55	-> 1213
/*    */     //   #56	-> 1248
/*    */     //   #57	-> 1262
/*    */     //   #58	-> 1305
/*    */     //   #59	-> 1316
/*    */     //   #60	-> 1319
/*    */     //   #61	-> 1323
/*    */     //   #62	-> 1351
/*    */     //   #63	-> 1354
/*    */     //   #64	-> 1375
/*    */     //   #65	-> 1378
/*    */     //   #66	-> 1388
/*    */     //   #67	-> 1393
/*    */     //   #68	-> 1397
/*    */     //   #69	-> 1403
/*    */     //   #70	-> 1407
/*    */     //   #71	-> 1412
/*    */     //   #72	-> 1422
/*    */     //   #73	-> 1426
/*    */     //   #74	-> 1512
/*    */     //   #75	-> 1550
/*    */     //   #76	-> 1559
/*    */     //   #77	-> 1584
/*    */     //   #78	-> 1587
/*    */     //   #79	-> 1592
/*    */     //   #80	-> 1595
/*    */     //   #81	-> 1611
/*    */     //   #82	-> 1648
/*    */     //   #83	-> 1696
/*    */     //   #84	-> 1798
/*    */     //   #85	-> 1801
/*    */     //   #86	-> 1925
/*    */     //   #87	-> 1929
/*    */     //   #88	-> 1964
/*    */     //   #89	-> 1967
/*    */     //   #90	-> 1983
/*    */     //   #91	-> 2014
/*    */     //   #92	-> 2018
/*    */     //   #93	-> 2023
/*    */     //   #94	-> 2042
/*    */     //   #95	-> 2048
/*    */     //   #96	-> 2052
/*    */     //   #97	-> 2104
/*    */     //   #98	-> 2109
/*    */     //   #99	-> 2116
/*    */     //   #100	-> 2185
/*    */     //   #101	-> 2237
/*    */     //   #102	-> 2254
/*    */     //   #103	-> 2284
/*    */     //   #104	-> 2287
/*    */     //   #105	-> 2293
/*    */     //   #106	-> 2299
/*    */     //   #107	-> 2304
/*    */     //   #108	-> 2317
/*    */     //   #109	-> 2323
/*    */     //   #110	-> 2391
/*    */     //   #111	-> 2403
/*    */     //   #112	-> 2414
/*    */     //   #113	-> 2461
/*    */     //   #114	-> 2468
/*    */     //   #115	-> 2498
/*    */     //   #116	-> 2504
/*    */     //   #117	-> 2508
/*    */     //   #118	-> 2515
/*    */     //   #119	-> 2520
/*    */     //   #120	-> 2525
/*    */     //   #121	-> 2536
/*    */     //   #122	-> 2542
/*    */     //   #123	-> 2546
/*    */     //   #124	-> 2549
/*    */     //   #125	-> 2552
/*    */     //   #126	-> 2632
/*    */     //   #127	-> 2640
/*    */     //   #128	-> 2646
/*    */     //   #129	-> 2652
/*    */     //   #130	-> 2656
/*    */     //   #131	-> 2663
/*    */     //   #132	-> 2668
/*    */     //   #133	-> 2673
/*    */     //   #134	-> 2684
/*    */     //   #135	-> 2690
/*    */     //   #136	-> 2695
/*    */     //   #137	-> 2698
/*    */     //   #138	-> 2701
/*    */     //   #139	-> 2760
/*    */     //   #140	-> 2763
/*    */     //   #141	-> 2835
/*    */     //   #142	-> 2838
/*    */     //   #143	-> 2850
/*    */     //   #144	-> 2856
/*    */     //   #145	-> 2861
/*    */     //   #146	-> 2871
/*    */     //   #147	-> 2888
/*    */     //   #148	-> 2891
/*    */     //   #149	-> 2939
/*    */     //   #150	-> 2942
/*    */     //   #151	-> 2952
/*    */     //   #152	-> 2955
/*    */     //   #153	-> 2984
/*    */     //   #154	-> 2991
/*    */     //   #155	-> 3015
/*    */     //   #156	-> 3020
/*    */     //   #157	-> 3044
/*    */     //   #158	-> 3089
/*    */     //   #159	-> 3092
/*    */     //   #160	-> 3166
/*    */     //   #161	-> 3171
/*    */     //   #162	-> 3195
/*    */     //   #163	-> 3240
/*    */     //   #164	-> 3243
/*    */     //   #165	-> 3310
/*    */     //   #166	-> 3334
/*    */     //   #167	-> 3355
/*    */     //   #168	-> 3369
/*    */     //   #169	-> 3389
/*    */     //   #170	-> 3406
/*    */     //   #171	-> 3415
/*    */     //   #172	-> 3418
/*    */     //   #173	-> 3421
/*    */     //   #174	-> 3428
/*    */     //   #175	-> 3434
/*    */     //   #176	-> 3437
/*    */     //   #177	-> 3450
/*    */     //   #178	-> 3481
/*    */     //   #179	-> 3485
/*    */     //   #180	-> 3489
/*    */     //   #181	-> 3493
/*    */     //   #182	-> 3550
/*    */     //   #183	-> 3554
/*    */     //   #184	-> 3575
/*    */     //   #185	-> 3590
/*    */     //   #186	-> 3619
/*    */     //   #187	-> 3632
/*    */     //   #188	-> 3658
/*    */     //   #189	-> 3671
/*    */     //   #190	-> 3696
/*    */     //   #191	-> 3708
/*    */     //   #192	-> 3721
/*    */     //   #193	-> 3735
/*    */     //   #194	-> 3747
/*    */     //   #195	-> 3751
/*    */     //   #196	-> 3757
/*    */     //   #197	-> 3760
/*    */     //   #198	-> 3763
/*    */     //   #199	-> 3772
/*    */     //   #200	-> 3778
/*    */     //   #201	-> 3781
/*    */     //   #202	-> 3784
/*    */     //   #203	-> 3793
/*    */     //   #204	-> 3802
/*    */     //   #205	-> 3805
/*    */     //   #206	-> 3813
/*    */     //   #207	-> 3821
/*    */     //   #208	-> 3830
/*    */     //   #209	-> 3859
/*    */     //   #210	-> 3956
/*    */     //   #211	-> 3964
/*    */     //   #212	-> 3968
/*    */     //   #213	-> 3972
/*    */     //   #214	-> 3988
/*    */     //   #215	-> 3993
/*    */     //   #216	-> 4003
/*    */     //   #217	-> 4079
/*    */     //   #218	-> 4083
/*    */     //   #219	-> 4089
/*    */     //   #220	-> 4093
/*    */     //   #221	-> 4103
/*    */     //   #222	-> 4108
/*    */     //   #223	-> 4168
/*    */     //   #224	-> 4270
/*    */     //   #225	-> 4273
/*    */     //   #226	-> 4288
/*    */     // Exception table:
/*    */     //   from	to	target	type
/*    */     //   1655	1664	1682	finally
/*    */     //   1670	1682	1682	finally
/*  2 */     //   1683	1687	1682	finally } public final void ek() { this.ms = true; this.gi0++; QE(UB0.M60.fG0(), UB0.M60.dL()); } public final void k0() { this.ms = true; if (--this.gi0 < 1.0F) this.gi0 = 1.0F;  QE(UB0.M60.fG0(), UB0.M60.dL()); } public final void CH(double paramDouble) { this.ms = true; if ((this.gi0 = (float)(this.gi0 - paramDouble)) < 1.0F) this.gi0 = 1.0F;  QE(UB0.M60.fG0(), UB0.M60.dL()); } public final void BJ0(float paramFloat) { this.gi0 = paramFloat; if (paramFloat < 1.0F) this.gi0 = 1.0F;  QE(UB0.M60.fG0(), UB0.M60.dL()); } public final String XX() { return B40.df("\nMap Render Calls: ").append(this.zU.G20).toString(); } public final void dispose() { Xc0 xc0; if ((xc0 = km.xn) != null) { xc0.dispose(); km.xn = null; }  this.zU.dispose(); this.C70.dispose(); } public final ny UB0() { return this.PF; } public final Eb vD() { return this.oj; } public final void LB(tc paramtc, p10 paramp10, ArrayList<tc> paramArrayList) { if (paramtc == null) return;  G5 g5; (g5 = paramtc.HW).getClass();
/*    */     
/*  4 */     byte b1 = this.FB;
/*  5 */     byte b2 = this.kD0;
/*  6 */     byte b3 = this.vu0;
/*  7 */     if (km.a3.COm8(b1, b2, b3) == null)
/*  8 */       return;  Sh
/*    */       
/* 10 */       .JL((paramtc.default()).lpt8); Sh.x += 8.0F; this(16.0F, 32.0F, 100.0F); eo eo1; if (Y4.jJ0(paramp10, Sh, this)) paramArrayList.add(paramtc);  }
/*    */ 
/*    */   
/*    */   public final void Iy(qo paramqo) {
/*    */     KI kI;
/*    */     if ((kI = km.a3.Jr0()) == null)
/*    */       return; 
/*    */     vF vF;
/*    */     if ((vF = this.UZ) == vF.ud0 || this == vF.ai || this == vF.Cv0 || this == vF.Ed0) {
/*    */       paramqo.vF0.set(1.0F, 1.0F, 1.0F, 1.0F);
/*    */       return;
/*    */     } 
/*    */     int i;
/*    */     L70 l70;
/*    */     if ((i = (l70 = L70.gq).Rr0() * 100 + (int)((Zi0() % 3600 / 60) * 1.65D)) > 1400 && i <= 2000) {
/*    */       paramqo.vF0.set(1.0F, 1.0F, 1.0F, 1.0F);
/*    */     } else {
/*    */       float f;
/*    */       if (i < 700 || i > 2000) {
/*    */         float f1;
/*    */         if (i > 2000 && i < 2255) {
/*    */           f1 = (2255 - i) / 255.0F;
/*    */           f1 = f1 * 0.71F + 0.29F;
/*    */           f = f1 * 0.5F + 0.5F;
/*    */           float f2 = f1 * 0.25F + 0.75F;
/*    */           paramqo.vF0.set(f1, f1, f, f2);
/*    */         } else if (f1 > 445 && f1 < 700) {
/*    */           f1 = (f1 - 445) / 255.0F;
/*    */           f1 = f1 * 0.71F + 0.29F;
/*    */           f = f1 * 0.5F + 0.5F;
/*    */           f.vF0.set(f1, f1, f, f);
/*    */         } else {
/*    */           f.vF0.set(0.29F, 0.29F, 0.5F, 0.5F);
/*    */         } 
/*    */         return;
/*    */       } 
/*    */       f.vF0.set(1.0F, 1.0F, 1.0F, 0.75F);
/*    */     } 
/*    */   }
/*    */   
/*    */   public final void LB0(boolean paramBoolean) {
/*    */     this.E4 = paramBoolean;
/*    */     if (!paramBoolean)
/*    */       Gt(yE0.ne, true); 
/*    */   }
/*    */   
/*    */   public final void dK() {
/*    */     this.zU = new tH();
/*    */     QE(UB0.M60.fG0(), UB0.M60.dL());
/*    */     if (km.xn == null)
/*    */       km.xn = new Xc0(); 
/*    */   }
/*    */   
/*    */   public final void Gt(yE0 paramyE0, boolean paramBoolean) {
/*    */     if ((!Bz.WZ && (Bz.fn || km.D70(8))) || !this.E4)
/*    */       paramyE0 = yE0.ne; 
/*    */     SI sI;
/*    */     if ((sI = this.Dg0) == null || sI.LPT7 != paramyE0) {
/*    */       if (sI != null)
/*    */         if (paramBoolean) {
/*    */           this.Db0 = null;
/*    */         } else {
/*    */           this.Db0 = sI;
/*    */           sI.y00 = true;
/*    */         }  
/*    */       switch (paramyE0.ordinal()) {
/*    */         default:
/*    */           this.Dg0 = null;
/*    */           break;
/*    */         case 17:
/*    */           super(paramyE0, paramBoolean);
/*    */           this.Dg0 = sI;
/*    */           break;
/*    */         case 7:
/*    */           super(paramyE0, paramBoolean);
/*    */           this.Dg0 = sI;
/*    */           break;
/*    */         case 6:
/*    */           super(paramyE0, paramBoolean);
/*    */           this.Dg0 = sI;
/*    */           break;
/*    */         case 8:
/*    */           super(paramyE0, paramBoolean);
/*    */           this.Dg0 = sI;
/*    */           break;
/*    */         case 3:
/*    */         case 5:
/*    */         case 13:
/*    */         case 15:
/*    */           super(paramyE0, paramBoolean);
/*    */           this.Dg0 = sI;
/*    */           break;
/*    */         case 11:
/*    */           super(paramyE0, paramBoolean);
/*    */           this.Dg0 = sI;
/*    */           break;
/*    */       } 
/*    */       KI kI;
/*    */       if ((kI = km.a3.Jr0()) != null && kI.UZ == vF.Cv0) {
/*    */         xF xF;
/*    */         this(paramyE0, paramBoolean);
/*    */         this.Dg0 = this;
/*    */       } 
/*    */     } 
/*    */   } }


/* Location:              /Users/vnnsnnt/Documents/Codespace/JavaWorkspace/RedTrainer/src/main/java/org/trainer/client/PokeMMO.jar!/f/EB.class
 * Java compiler version: 8 (52.0)
 * JD-Core Version:       1.1.3
 */