package f;

public final class EE extends TF0 {
  public EE(RD0 paramRD0, Mw paramMw) {}
  
  public final Object COm7(It paramIt, bM0 parambM0) {
    // Byte code:
    //   0: aload_2
    //   1: aload_1
    //   2: aload_2
    //   3: ldc 'file'
    //   5: ldc java/lang/String
    //   7: aconst_null
    //   8: invokestatic aD0 : (Lf/It;Lf/bM0;Ljava/lang/String;Ljava/lang/Class;Ljava/lang/Class;)Ljava/lang/Object;
    //   11: checkcast java/lang/String
    //   14: astore_3
    //   15: getstatic java/lang/Integer.TYPE : Ljava/lang/Class;
    //   18: astore #4
    //   20: iconst_m1
    //   21: invokestatic valueOf : (I)Ljava/lang/Integer;
    //   24: astore #5
    //   26: ldc 'scaledSize'
    //   28: invokevirtual Jb : (Ljava/lang/String;)Lf/bM0;
    //   31: dup
    //   32: astore #6
    //   34: ifnonnull -> 40
    //   37: goto -> 51
    //   40: aload_1
    //   41: aload #4
    //   43: aconst_null
    //   44: aload #6
    //   46: invokevirtual Uj0 : (Ljava/lang/Class;Ljava/lang/Class;Lf/bM0;)Ljava/lang/Object;
    //   49: astore #5
    //   51: aload_2
    //   52: aload #5
    //   54: checkcast java/lang/Integer
    //   57: invokevirtual intValue : ()I
    //   60: istore #4
    //   62: ldc java/lang/Boolean
    //   64: astore #5
    //   66: getstatic java/lang/Boolean.FALSE : Ljava/lang/Boolean;
    //   69: astore #6
    //   71: ldc 'flip'
    //   73: invokevirtual Jb : (Ljava/lang/String;)Lf/bM0;
    //   76: dup
    //   77: astore #7
    //   79: ifnonnull -> 89
    //   82: aload #6
    //   84: astore #5
    //   86: goto -> 100
    //   89: aload_1
    //   90: aload #5
    //   92: aconst_null
    //   93: aload #7
    //   95: invokevirtual Uj0 : (Ljava/lang/Class;Ljava/lang/Class;Lf/bM0;)Ljava/lang/Object;
    //   98: astore #5
    //   100: aload_2
    //   101: aload #5
    //   103: checkcast java/lang/Boolean
    //   106: astore_2
    //   107: ldc java/lang/Boolean
    //   109: astore #5
    //   111: ldc 'markupEnabled'
    //   113: invokevirtual Jb : (Ljava/lang/String;)Lf/bM0;
    //   116: dup
    //   117: astore #7
    //   119: ifnonnull -> 125
    //   122: goto -> 136
    //   125: aload_1
    //   126: aload #5
    //   128: aconst_null
    //   129: aload #7
    //   131: invokevirtual Uj0 : (Ljava/lang/Class;Ljava/lang/Class;Lf/bM0;)Ljava/lang/Object;
    //   134: astore #6
    //   136: aload_0
    //   137: aload #6
    //   139: checkcast java/lang/Boolean
    //   142: astore_1
    //   143: getfield dp0 : Lf/RD0;
    //   146: invokevirtual wT : ()Lf/RD0;
    //   149: aload_3
    //   150: invokevirtual f0 : (Ljava/lang/String;)Lf/RD0;
    //   153: dup
    //   154: astore #5
    //   156: invokevirtual L0 : ()Z
    //   159: ifne -> 171
    //   162: getstatic f/UB0.vj0 : Lf/XG;
    //   165: aload_3
    //   166: invokevirtual aP : (Ljava/lang/String;)Lf/hZ;
    //   169: astore #5
    //   171: aload #5
    //   173: invokevirtual L0 : ()Z
    //   176: ifeq -> 405
    //   179: aload_0
    //   180: aload #5
    //   182: invokevirtual k6 : ()Ljava/lang/String;
    //   185: astore_3
    //   186: getfield cR : Lf/Mw;
    //   189: aload_3
    //   190: invokevirtual Lp : (Ljava/lang/String;)Lf/fQ;
    //   193: dup
    //   194: astore #6
    //   196: ifnull -> 229
    //   199: new f/Me
    //   202: dup
    //   203: astore_0
    //   204: new f/vQ
    //   207: dup
    //   208: astore_3
    //   209: aload_2
    //   210: invokevirtual booleanValue : ()Z
    //   213: aload #5
    //   215: swap
    //   216: invokespecial <init> : (Lf/RD0;Z)V
    //   219: aload_3
    //   220: aload #6
    //   222: iconst_1
    //   223: invokespecial <init> : (Lf/vQ;Lf/fQ;Z)V
    //   226: goto -> 340
    //   229: aload_0
    //   230: getfield cR : Lf/Mw;
    //   233: ldc f/pe0
    //   235: aload_3
    //   236: invokevirtual QH : (Ljava/lang/Class;Ljava/lang/String;)Ljava/lang/Object;
    //   239: checkcast f/pe0
    //   242: dup
    //   243: astore_0
    //   244: ifnull -> 269
    //   247: new f/Me
    //   250: dup
    //   251: astore_3
    //   252: aload_2
    //   253: invokevirtual booleanValue : ()Z
    //   256: istore_2
    //   257: aload #5
    //   259: aload_0
    //   260: iload_2
    //   261: invokespecial <init> : (Lf/RD0;Lf/pe0;Z)V
    //   264: aload_3
    //   265: astore_0
    //   266: goto -> 340
    //   269: aload #5
    //   271: invokevirtual wT : ()Lf/RD0;
    //   274: new java/lang/StringBuilder
    //   277: dup
    //   278: aload_3
    //   279: swap
    //   280: invokespecial <init> : ()V
    //   283: invokevirtual append : (Ljava/lang/String;)Ljava/lang/StringBuilder;
    //   286: ldc '.png'
    //   288: invokevirtual append : (Ljava/lang/String;)Ljava/lang/StringBuilder;
    //   291: invokevirtual toString : ()Ljava/lang/String;
    //   294: invokevirtual f0 : (Ljava/lang/String;)Lf/RD0;
    //   297: dup
    //   298: astore_0
    //   299: invokevirtual L0 : ()Z
    //   302: ifeq -> 325
    //   305: new f/Me
    //   308: dup
    //   309: astore_3
    //   310: aload_2
    //   311: invokevirtual booleanValue : ()Z
    //   314: istore_2
    //   315: aload #5
    //   317: aload_0
    //   318: iload_2
    //   319: invokespecial <init> : (Lf/RD0;Lf/RD0;Z)V
    //   322: goto -> 264
    //   325: new f/Me
    //   328: dup
    //   329: astore_0
    //   330: aload_2
    //   331: invokevirtual booleanValue : ()Z
    //   334: aload #5
    //   336: swap
    //   337: invokespecial <init> : (Lf/RD0;Z)V
    //   340: iload #4
    //   342: aload_0
    //   343: getfield XO : Lf/vQ;
    //   346: aload_1
    //   347: invokevirtual booleanValue : ()Z
    //   350: putfield Zp : Z
    //   353: iconst_m1
    //   354: if_icmpeq -> 373
    //   357: aload_0
    //   358: getfield XO : Lf/vQ;
    //   361: dup
    //   362: iload #4
    //   364: i2f
    //   365: swap
    //   366: getfield Y5 : F
    //   369: fdiv
    //   370: invokevirtual rM : (F)V
    //   373: aload_0
    //   374: areturn
    //   375: astore_0
    //   376: new f/kN
    //   379: dup
    //   380: new java/lang/StringBuilder
    //   383: dup
    //   384: invokespecial <init> : ()V
    //   387: ldc 'Error loading bitmap font: '
    //   389: invokevirtual append : (Ljava/lang/String;)Ljava/lang/StringBuilder;
    //   392: aload #5
    //   394: invokevirtual append : (Ljava/lang/Object;)Ljava/lang/StringBuilder;
    //   397: invokevirtual toString : ()Ljava/lang/String;
    //   400: aload_0
    //   401: invokespecial <init> : (Ljava/lang/String;Ljava/lang/Throwable;)V
    //   404: athrow
    //   405: new f/kN
    //   408: dup
    //   409: new java/lang/StringBuilder
    //   412: dup
    //   413: invokespecial <init> : ()V
    //   416: ldc 'Font file not found: '
    //   418: invokevirtual append : (Ljava/lang/String;)Ljava/lang/StringBuilder;
    //   421: aload #5
    //   423: invokevirtual append : (Ljava/lang/Object;)Ljava/lang/StringBuilder;
    //   426: invokevirtual toString : ()Ljava/lang/String;
    //   429: invokespecial <init> : (Ljava/lang/String;)V
    //   432: athrow
    // Line number table:
    //   Java source line number -> byte code offset
    //   #1	-> 3
    //   #2	-> 11
    //   #3	-> 26
    //   #4	-> 54
    //   #5	-> 71
    //   #6	-> 103
    //   #7	-> 111
    //   #8	-> 139
    //   #9	-> 343
    //   #10	-> 347
    //   #11	-> 358
    //   #12	-> 366
    //   #13	-> 370
    // Exception table:
    //   from	to	target	type
    //   186	193	375	java/lang/RuntimeException
    //   199	202	375	java/lang/RuntimeException
    //   204	207	375	java/lang/RuntimeException
    //   209	242	375	java/lang/RuntimeException
    //   247	250	375	java/lang/RuntimeException
    //   252	256	375	java/lang/RuntimeException
    //   257	264	375	java/lang/RuntimeException
    //   269	277	375	java/lang/RuntimeException
    //   278	297	375	java/lang/RuntimeException
    //   299	302	375	java/lang/RuntimeException
    //   305	308	375	java/lang/RuntimeException
    //   310	314	375	java/lang/RuntimeException
    //   315	328	375	java/lang/RuntimeException
    //   330	353	375	java/lang/RuntimeException
    //   357	361	375	java/lang/RuntimeException
    //   365	369	375	java/lang/RuntimeException
    //   370	373	375	java/lang/RuntimeException
  }
}


/* Location:              /Users/vnnsnnt/Documents/Codespace/JavaWorkspace/RedTrainer/src/main/java/org/trainer/client/PokeMMO.jar!/f/EE.class
 * Java compiler version: 7 (51.0)
 * JD-Core Version:       1.1.3
 */