/*  1 */ package f;public final class eI { public static final eo Pp = new eo(); public static final Matrix4 GB0 = new Matrix4(); public static final Matrix4 vC0 = new Matrix4(); public static final ik zi = C00.gd(eI.class); public static final eo UL0 = new eo(); public static eI Sr0; public static lpt1 Yp0(byte paramByte, int paramInt, boolean paramBoolean) { Q1 q1 = null; fn fn = null; if (paramByte != 3) { if (paramByte == 4) { q1 = km.mI0.yE.sM(paramBoolean).vn0(paramInt); fn = km.mI0.yE.sM(paramBoolean).jw(paramInt); }  }
/*  2 */     else { q1 = km.mI0.MT.EI0.vn0(paramInt);
/*    */       
/*  4 */       fn = km.mI0.MT.EI0.jw(paramInt); }  if (q1 == null || fn == null)
/*    */     {
/*    */ 
/*    */ 
/*    */ 
/*    */       
/* 10 */       return null; }  hC hC = q1.Nt[0]; this(paramByte, hC, q1.Qo0); Iq iq; lpt1 lpt1; hC = null; if (h1.Pm) if (paramByte != 3) { if (paramByte == 4) { VV vV; IZ iZ = km.ln.dh0[4]; if (paramBoolean) { vV = VV.i60; } else { vV = VV.transient; }  lpt1 = iZ.oL0(vV, paramInt, iq); }  } else { lpt1 = km.ln.dh0[3].TA(paramInt, iq); }   if (lpt1 == null) { DG0(q1.Nt[0], q1.Qo0); eI eI1 = Lj(); Wd wd = q1.Qo0; fQ fQ = fn.ok0; eI1.getClass(); lpt1 = Q9(q1.Nt[0], iq, wd, fQ, 1.0F, false, false); }  if (fn.ok0.Z8 > 0) { Wd wd = q1.Qo0; fQ fQ = fn.ok0; Lj().getClass(); aI(lpt1, wd, iq, fQ); }  return lpt1; } public static is0 cR; public eI() { hd0 hd0; this(); (new hd0()).dl = false; cR = new is0(); } public static eI Lj() { if (Sr0 == null) Sr0 = new eI();  return Sr0; } public static void DG0(hC paramhC, Wd paramWd) { // Byte code:
/*    */     //   0: aload_0
/*    */     //   1: ifnull -> 151
/*    */     //   4: aload_1
/*    */     //   5: ifnonnull -> 11
/*    */     //   8: goto -> 151
/*    */     //   11: iconst_0
/*    */     //   12: istore_2
/*    */     //   13: iload_2
/*    */     //   14: aload_0
/*    */     //   15: getfield p3 : Lf/fQ;
/*    */     //   18: dup
/*    */     //   19: astore_3
/*    */     //   20: getfield Z8 : I
/*    */     //   23: if_icmpge -> 150
/*    */     //   26: aload_3
/*    */     //   27: iload_2
/*    */     //   28: invokevirtual get : (I)Ljava/lang/Object;
/*    */     //   31: checkcast f/tC
/*    */     //   34: dup
/*    */     //   35: astore_3
/*    */     //   36: getfield Ih : Ljava/lang/String;
/*    */     //   39: ifnull -> 137
/*    */     //   42: aload_3
/*    */     //   43: getfield JZ : Ljava/lang/String;
/*    */     //   46: dup
/*    */     //   47: astore #4
/*    */     //   49: ifnonnull -> 55
/*    */     //   52: goto -> 137
/*    */     //   55: aload_1
/*    */     //   56: getfield as0 : Z
/*    */     //   59: ifeq -> 144
/*    */     //   62: aload_1
/*    */     //   63: getfield TE : Lf/Yy0;
/*    */     //   66: getfield ai0 : Lf/fQ;
/*    */     //   69: getfield Z8 : I
/*    */     //   72: ifne -> 78
/*    */     //   75: goto -> 144
/*    */     //   78: aload_1
/*    */     //   79: getfield K5 : Lf/Nn;
/*    */     //   82: aload #4
/*    */     //   84: invokevirtual pd0 : (Ljava/lang/Object;)Ljava/lang/Object;
/*    */     //   87: checkcast java/lang/Integer
/*    */     //   90: dup
/*    */     //   91: astore #4
/*    */     //   93: ifnonnull -> 99
/*    */     //   96: goto -> 137
/*    */     //   99: aload_3
/*    */     //   100: dup
/*    */     //   101: aload_1
/*    */     //   102: getfield TE : Lf/Yy0;
/*    */     //   105: aload #4
/*    */     //   107: invokevirtual intValue : ()I
/*    */     //   110: invokevirtual yO : (I)Lf/vO;
/*    */     //   113: checkcast f/fk0
/*    */     //   116: dup
/*    */     //   117: astore_3
/*    */     //   118: getfield b70 : Lf/f20;
/*    */     //   121: getfield Io0 : B
/*    */     //   124: putfield T1 : I
/*    */     //   127: aload_3
/*    */     //   128: getfield rW : B
/*    */     //   131: putfield SS : I
/*    */     //   134: goto -> 144
/*    */     //   137: getstatic f/eI.zi : Lf/ik;
/*    */     //   140: invokevirtual getClass : ()Ljava/lang/Class;
/*    */     //   143: pop
/*    */     //   144: iinc #2, 1
/*    */     //   147: goto -> 13
/*    */     //   150: return
/*    */     //   151: getstatic f/eI.zi : Lf/ik;
/*    */     //   154: invokevirtual getClass : ()Ljava/lang/Class;
/*    */     //   157: pop
/*    */     //   158: return
/*    */     // Line number table:
/*    */     //   Java source line number -> byte code offset
/*    */     //   #1	-> 66
/*    */     //   #2	-> 69
/*    */     //   #3	-> 79 } public static void C90(HI paramHI, lpt1 paramlpt1, hC paramhC, Ew paramEw) { // Byte code:
/*    */     //   0: getstatic f/km.ln : Lf/ei;
/*    */     //   3: dup
/*    */     //   4: astore #4
/*    */     //   6: ifnull -> 23
/*    */     //   9: aload #4
/*    */     //   11: getfield tn : Lf/fQ;
/*    */     //   14: invokevirtual isEmpty : ()Z
/*    */     //   17: iconst_1
/*    */     //   18: ixor
/*    */     //   19: ifeq -> 23
/*    */     //   22: return
/*    */     //   23: aload_0
/*    */     //   24: getfield aB0 : Lf/V60;
/*    */     //   27: dup
/*    */     //   28: astore #4
/*    */     //   30: getfield K2 : Lf/fQ;
/*    */     //   33: getfield Z8 : I
/*    */     //   36: ifne -> 786
/*    */     //   39: aload #4
/*    */     //   41: getfield uo : Lf/HI;
/*    */     //   44: invokevirtual bO : ()B
/*    */     //   47: iconst_2
/*    */     //   48: if_icmpne -> 412
/*    */     //   51: aload #4
/*    */     //   53: getfield uo : Lf/HI;
/*    */     //   56: getfield TI : Lf/RD;
/*    */     //   59: ldc '/a/0/6/9'
/*    */     //   61: invokevirtual B8 : (Ljava/lang/String;)Lf/T7;
/*    */     //   64: dup
/*    */     //   65: dup
/*    */     //   66: astore #5
/*    */     //   68: invokestatic Mx0 : ()V
/*    */     //   71: getfield db : Ljava/lang/String;
/*    */     //   74: pop
/*    */     //   75: getfield bP : Lf/HI;
/*    */     //   78: dup
/*    */     //   79: astore #6
/*    */     //   81: invokevirtual GA0 : ()Ljava/nio/ByteBuffer;
/*    */     //   84: dup
/*    */     //   85: astore #7
/*    */     //   87: aload #5
/*    */     //   89: getfield XL : I
/*    */     //   92: invokestatic cL0 : (Ljava/nio/ByteBuffer;I)I
/*    */     //   95: dup
/*    */     //   96: istore #5
/*    */     //   98: ldc 1129464142
/*    */     //   100: dup
/*    */     //   101: istore #8
/*    */     //   103: if_icmpne -> 391
/*    */     //   106: aload #7
/*    */     //   108: dup
/*    */     //   109: dup
/*    */     //   110: invokestatic Lx0 : (Ljava/nio/ByteBuffer;)I
/*    */     //   113: istore #5
/*    */     //   115: invokevirtual getInt : ()I
/*    */     //   118: dup
/*    */     //   119: istore #8
/*    */     //   121: aload #7
/*    */     //   123: invokevirtual position : ()I
/*    */     //   126: bipush #8
/*    */     //   128: swap
/*    */     //   129: aload #7
/*    */     //   131: invokestatic TG0 : (IIILjava/nio/ByteBuffer;)I
/*    */     //   134: istore #9
/*    */     //   136: invokevirtual position : ()I
/*    */     //   139: iload #9
/*    */     //   141: iadd
/*    */     //   142: istore #9
/*    */     //   144: iconst_0
/*    */     //   145: istore #10
/*    */     //   147: iload #10
/*    */     //   149: iload #8
/*    */     //   151: if_icmpge -> 786
/*    */     //   154: iload #10
/*    */     //   156: iload #5
/*    */     //   158: bipush #12
/*    */     //   160: iadd
/*    */     //   161: dup
/*    */     //   162: aload #7
/*    */     //   164: swap
/*    */     //   165: iload #10
/*    */     //   167: bipush #8
/*    */     //   169: imul
/*    */     //   170: dup
/*    */     //   171: istore #11
/*    */     //   173: iadd
/*    */     //   174: invokevirtual getInt : (I)I
/*    */     //   177: istore #12
/*    */     //   179: iconst_4
/*    */     //   180: iload #11
/*    */     //   182: aload #7
/*    */     //   184: invokestatic iy0 : (IIILjava/nio/ByteBuffer;)I
/*    */     //   187: iload #12
/*    */     //   189: dup
/*    */     //   190: iload #9
/*    */     //   192: iadd
/*    */     //   193: istore #11
/*    */     //   195: isub
/*    */     //   196: istore #12
/*    */     //   198: getstatic f/nN.Wj : [Ljava/lang/String;
/*    */     //   201: astore #13
/*    */     //   203: sipush #400
/*    */     //   206: if_icmpge -> 218
/*    */     //   209: aload #13
/*    */     //   211: iload #10
/*    */     //   213: aaload
/*    */     //   214: pop
/*    */     //   215: goto -> 224
/*    */     //   218: iload #10
/*    */     //   220: invokestatic toString : (I)Ljava/lang/String;
/*    */     //   223: pop
/*    */     //   224: iload #12
/*    */     //   226: aload #6
/*    */     //   228: invokevirtual GA0 : ()Ljava/nio/ByteBuffer;
/*    */     //   231: dup
/*    */     //   232: astore #13
/*    */     //   234: iload #11
/*    */     //   236: invokevirtual position : (I)Ljava/nio/Buffer;
/*    */     //   239: pop
/*    */     //   240: ifle -> 258
/*    */     //   243: iload #11
/*    */     //   245: aload #13
/*    */     //   247: invokevirtual limit : ()I
/*    */     //   250: iload #12
/*    */     //   252: swap
/*    */     //   253: aload #13
/*    */     //   255: invokestatic Pp0 : (IIILjava/nio/ByteBuffer;)V
/*    */     //   258: aload #13
/*    */     //   260: invokevirtual slice : ()Ljava/nio/ByteBuffer;
/*    */     //   263: getstatic java/nio/ByteOrder.LITTLE_ENDIAN : Ljava/nio/ByteOrder;
/*    */     //   266: invokevirtual order : (Ljava/nio/ByteOrder;)Ljava/nio/ByteBuffer;
/*    */     //   269: invokestatic vb0 : (Ljava/nio/ByteBuffer;)Lf/uv;
/*    */     //   272: getfield v9 : Lf/fQ;
/*    */     //   275: invokevirtual r30 : ()Lf/Hc0;
/*    */     //   278: astore #11
/*    */     //   280: aload #11
/*    */     //   282: invokevirtual hasNext : ()Z
/*    */     //   285: ifeq -> 385
/*    */     //   288: aload #11
/*    */     //   290: invokevirtual next : ()Ljava/lang/Object;
/*    */     //   293: checkcast f/xe
/*    */     //   296: dup
/*    */     //   297: astore #12
/*    */     //   299: getfield w4 : Lf/fQ;
/*    */     //   302: invokevirtual r30 : ()Lf/Hc0;
/*    */     //   305: astore #13
/*    */     //   307: aload #13
/*    */     //   309: invokevirtual hasNext : ()Z
/*    */     //   312: ifeq -> 280
/*    */     //   315: aload #4
/*    */     //   317: aload #13
/*    */     //   319: invokevirtual next : ()Ljava/lang/Object;
/*    */     //   322: checkcast f/yn
/*    */     //   325: astore #14
/*    */     //   327: new f/VF
/*    */     //   330: dup
/*    */     //   331: astore #15
/*    */     //   333: aload #12
/*    */     //   335: dup
/*    */     //   336: aload #15
/*    */     //   338: invokespecial <init> : ()V
/*    */     //   341: getfield Ih : Ljava/lang/String;
/*    */     //   344: astore #16
/*    */     //   346: getfield EF0 : I
/*    */     //   349: aload #14
/*    */     //   351: aload #15
/*    */     //   353: aload #14
/*    */     //   355: aload #15
/*    */     //   357: aload #16
/*    */     //   359: putfield Cg0 : Ljava/lang/String;
/*    */     //   362: getfield Ih : Ljava/lang/String;
/*    */     //   365: putfield xI0 : Ljava/lang/String;
/*    */     //   368: invokestatic FC : (ILf/yn;)[Lf/Z30;
/*    */     //   371: putfield qD0 : [Lf/Z30;
/*    */     //   374: getfield K2 : Lf/fQ;
/*    */     //   377: aload #15
/*    */     //   379: invokevirtual Com3 : (Ljava/lang/Object;)V
/*    */     //   382: goto -> 307
/*    */     //   385: iinc #10, 1
/*    */     //   388: goto -> 147
/*    */     //   391: new java/lang/RuntimeException
/*    */     //   394: dup
/*    */     //   395: ldc_w 'Header magic mismatch = '
/*    */     //   398: iload #5
/*    */     //   400: ldc_w ' vs expected '
/*    */     //   403: iload #8
/*    */     //   405: invokestatic KK : (Ljava/lang/String;ILjava/lang/String;I)Ljava/lang/String;
/*    */     //   408: invokespecial <init> : (Ljava/lang/String;)V
/*    */     //   411: athrow
/*    */     //   412: aload #4
/*    */     //   414: getfield uo : Lf/HI;
/*    */     //   417: invokevirtual bO : ()B
/*    */     //   420: iconst_4
/*    */     //   421: if_icmpne -> 786
/*    */     //   424: aload #4
/*    */     //   426: getfield uo : Lf/HI;
/*    */     //   429: getfield TI : Lf/RD;
/*    */     //   432: ldc_w '/a/1/4/0'
/*    */     //   435: invokevirtual B8 : (Ljava/lang/String;)Lf/T7;
/*    */     //   438: dup
/*    */     //   439: dup
/*    */     //   440: astore #5
/*    */     //   442: invokestatic Mx0 : ()V
/*    */     //   445: getfield db : Ljava/lang/String;
/*    */     //   448: pop
/*    */     //   449: getfield bP : Lf/HI;
/*    */     //   452: dup
/*    */     //   453: astore #6
/*    */     //   455: invokevirtual GA0 : ()Ljava/nio/ByteBuffer;
/*    */     //   458: dup
/*    */     //   459: astore #7
/*    */     //   461: aload #5
/*    */     //   463: getfield XL : I
/*    */     //   466: invokestatic cL0 : (Ljava/nio/ByteBuffer;I)I
/*    */     //   469: dup
/*    */     //   470: istore #5
/*    */     //   472: ldc 1129464142
/*    */     //   474: dup
/*    */     //   475: istore #8
/*    */     //   477: if_icmpne -> 765
/*    */     //   480: aload #7
/*    */     //   482: dup
/*    */     //   483: dup
/*    */     //   484: invokestatic Lx0 : (Ljava/nio/ByteBuffer;)I
/*    */     //   487: istore #5
/*    */     //   489: invokevirtual getInt : ()I
/*    */     //   492: dup
/*    */     //   493: istore #8
/*    */     //   495: aload #7
/*    */     //   497: invokevirtual position : ()I
/*    */     //   500: bipush #8
/*    */     //   502: swap
/*    */     //   503: aload #7
/*    */     //   505: invokestatic TG0 : (IIILjava/nio/ByteBuffer;)I
/*    */     //   508: istore #9
/*    */     //   510: invokevirtual position : ()I
/*    */     //   513: iload #9
/*    */     //   515: iadd
/*    */     //   516: istore #9
/*    */     //   518: iconst_0
/*    */     //   519: istore #10
/*    */     //   521: iload #10
/*    */     //   523: iload #8
/*    */     //   525: if_icmpge -> 786
/*    */     //   528: iload #10
/*    */     //   530: iload #5
/*    */     //   532: bipush #12
/*    */     //   534: iadd
/*    */     //   535: dup
/*    */     //   536: aload #7
/*    */     //   538: swap
/*    */     //   539: iload #10
/*    */     //   541: bipush #8
/*    */     //   543: imul
/*    */     //   544: dup
/*    */     //   545: istore #11
/*    */     //   547: iadd
/*    */     //   548: invokevirtual getInt : (I)I
/*    */     //   551: istore #12
/*    */     //   553: iconst_4
/*    */     //   554: iload #11
/*    */     //   556: aload #7
/*    */     //   558: invokestatic iy0 : (IIILjava/nio/ByteBuffer;)I
/*    */     //   561: iload #12
/*    */     //   563: dup
/*    */     //   564: iload #9
/*    */     //   566: iadd
/*    */     //   567: istore #11
/*    */     //   569: isub
/*    */     //   570: istore #12
/*    */     //   572: getstatic f/nN.Wj : [Ljava/lang/String;
/*    */     //   575: astore #13
/*    */     //   577: sipush #400
/*    */     //   580: if_icmpge -> 592
/*    */     //   583: aload #13
/*    */     //   585: iload #10
/*    */     //   587: aaload
/*    */     //   588: pop
/*    */     //   589: goto -> 598
/*    */     //   592: iload #10
/*    */     //   594: invokestatic toString : (I)Ljava/lang/String;
/*    */     //   597: pop
/*    */     //   598: iload #12
/*    */     //   600: aload #6
/*    */     //   602: invokevirtual GA0 : ()Ljava/nio/ByteBuffer;
/*    */     //   605: dup
/*    */     //   606: astore #13
/*    */     //   608: iload #11
/*    */     //   610: invokevirtual position : (I)Ljava/nio/Buffer;
/*    */     //   613: pop
/*    */     //   614: ifle -> 632
/*    */     //   617: iload #11
/*    */     //   619: aload #13
/*    */     //   621: invokevirtual limit : ()I
/*    */     //   624: iload #12
/*    */     //   626: swap
/*    */     //   627: aload #13
/*    */     //   629: invokestatic Pp0 : (IIILjava/nio/ByteBuffer;)V
/*    */     //   632: aload #13
/*    */     //   634: invokevirtual slice : ()Ljava/nio/ByteBuffer;
/*    */     //   637: getstatic java/nio/ByteOrder.LITTLE_ENDIAN : Ljava/nio/ByteOrder;
/*    */     //   640: invokevirtual order : (Ljava/nio/ByteOrder;)Ljava/nio/ByteBuffer;
/*    */     //   643: invokestatic vb0 : (Ljava/nio/ByteBuffer;)Lf/uv;
/*    */     //   646: getfield v9 : Lf/fQ;
/*    */     //   649: invokevirtual r30 : ()Lf/Hc0;
/*    */     //   652: astore #11
/*    */     //   654: aload #11
/*    */     //   656: invokevirtual hasNext : ()Z
/*    */     //   659: ifeq -> 759
/*    */     //   662: aload #11
/*    */     //   664: invokevirtual next : ()Ljava/lang/Object;
/*    */     //   667: checkcast f/xe
/*    */     //   670: dup
/*    */     //   671: astore #12
/*    */     //   673: getfield w4 : Lf/fQ;
/*    */     //   676: invokevirtual r30 : ()Lf/Hc0;
/*    */     //   679: astore #13
/*    */     //   681: aload #13
/*    */     //   683: invokevirtual hasNext : ()Z
/*    */     //   686: ifeq -> 654
/*    */     //   689: aload #4
/*    */     //   691: aload #13
/*    */     //   693: invokevirtual next : ()Ljava/lang/Object;
/*    */     //   696: checkcast f/yn
/*    */     //   699: astore #14
/*    */     //   701: new f/VF
/*    */     //   704: dup
/*    */     //   705: astore #15
/*    */     //   707: aload #12
/*    */     //   709: dup
/*    */     //   710: aload #15
/*    */     //   712: invokespecial <init> : ()V
/*    */     //   715: getfield Ih : Ljava/lang/String;
/*    */     //   718: astore #16
/*    */     //   720: getfield EF0 : I
/*    */     //   723: aload #14
/*    */     //   725: aload #15
/*    */     //   727: aload #14
/*    */     //   729: aload #15
/*    */     //   731: aload #16
/*    */     //   733: putfield Cg0 : Ljava/lang/String;
/*    */     //   736: getfield Ih : Ljava/lang/String;
/*    */     //   739: putfield xI0 : Ljava/lang/String;
/*    */     //   742: invokestatic FC : (ILf/yn;)[Lf/Z30;
/*    */     //   745: putfield qD0 : [Lf/Z30;
/*    */     //   748: getfield K2 : Lf/fQ;
/*    */     //   751: aload #15
/*    */     //   753: invokevirtual Com3 : (Ljava/lang/Object;)V
/*    */     //   756: goto -> 681
/*    */     //   759: iinc #10, 1
/*    */     //   762: goto -> 521
/*    */     //   765: new java/lang/RuntimeException
/*    */     //   768: dup
/*    */     //   769: ldc_w 'Header magic mismatch = '
/*    */     //   772: iload #5
/*    */     //   774: ldc_w ' vs expected '
/*    */     //   777: iload #8
/*    */     //   779: invokestatic KK : (Ljava/lang/String;ILjava/lang/String;I)Ljava/lang/String;
/*    */     //   782: invokespecial <init> : (Ljava/lang/String;)V
/*    */     //   785: athrow
/*    */     //   786: aload #4
/*    */     //   788: getfield K2 : Lf/fQ;
/*    */     //   791: invokevirtual r30 : ()Lf/Hc0;
/*    */     //   794: astore #4
/*    */     //   796: aload #4
/*    */     //   798: invokevirtual hasNext : ()Z
/*    */     //   801: ifeq -> 1082
/*    */     //   804: aload_1
/*    */     //   805: aload #4
/*    */     //   807: invokevirtual next : ()Ljava/lang/Object;
/*    */     //   810: checkcast f/VF
/*    */     //   813: astore #5
/*    */     //   815: getfield Zl0 : Ljava/lang/String;
/*    */     //   818: ldc_w 'm_dun17'
/*    */     //   821: invokevirtual contains : (Ljava/lang/CharSequence;)Z
/*    */     //   824: ifeq -> 844
/*    */     //   827: aload #5
/*    */     //   829: getfield Cg0 : Ljava/lang/String;
/*    */     //   832: ldc_w 'in31_08gym'
/*    */     //   835: invokevirtual contains : (Ljava/lang/CharSequence;)Z
/*    */     //   838: ifeq -> 844
/*    */     //   841: goto -> 796
/*    */     //   844: aload_0
/*    */     //   845: invokevirtual bO : ()B
/*    */     //   848: iconst_2
/*    */     //   849: if_icmpne -> 1051
/*    */     //   852: aload #5
/*    */     //   854: getfield xI0 : Ljava/lang/String;
/*    */     //   857: ldc_w 'ice_s_02_1'
/*    */     //   860: invokevirtual contains : (Ljava/lang/CharSequence;)Z
/*    */     //   863: ifeq -> 892
/*    */     //   866: aload_1
/*    */     //   867: aload #5
/*    */     //   869: getfield qD0 : [Lf/Z30;
/*    */     //   872: astore #5
/*    */     //   874: ldc_w 'ow'
/*    */     //   877: ldc_w 'lambert3'
/*    */     //   880: ldc_w 0.05
/*    */     //   883: aload #5
/*    */     //   885: iconst_1
/*    */     //   886: invokevirtual dA : (Ljava/lang/String;Ljava/lang/String;F[Lf/Z30;Z)V
/*    */     //   889: goto -> 796
/*    */     //   892: aload #5
/*    */     //   894: getfield xI0 : Ljava/lang/String;
/*    */     //   897: ldc_w 'c36_foun'
/*    */     //   900: invokevirtual contains : (Ljava/lang/CharSequence;)Z
/*    */     //   903: ifeq -> 946
/*    */     //   906: aload_1
/*    */     //   907: aload #5
/*    */     //   909: dup
/*    */     //   910: getfield xI0 : Ljava/lang/String;
/*    */     //   913: ldc_w 'c36_'
/*    */     //   916: ldc_w 'c07_'
/*    */     //   919: invokevirtual replace : (Ljava/lang/CharSequence;Ljava/lang/CharSequence;)Ljava/lang/String;
/*    */     //   922: astore #5
/*    */     //   924: getfield qD0 : [Lf/Z30;
/*    */     //   927: astore #6
/*    */     //   929: ldc_w 'ow'
/*    */     //   932: aload #5
/*    */     //   934: ldc_w 0.05
/*    */     //   937: aload #6
/*    */     //   939: iconst_1
/*    */     //   940: invokevirtual dA : (Ljava/lang/String;Ljava/lang/String;F[Lf/Z30;Z)V
/*    */     //   943: goto -> 796
/*    */     //   946: aload #5
/*    */     //   948: getfield xI0 : Ljava/lang/String;
/*    */     //   951: ldc_w 'n_water_a_1'
/*    */     //   954: invokevirtual equalsIgnoreCase : (Ljava/lang/String;)Z
/*    */     //   957: ifeq -> 1051
/*    */     //   960: bipush #120
/*    */     //   962: dup
/*    */     //   963: istore #6
/*    */     //   965: anewarray f/Z30
/*    */     //   968: astore #7
/*    */     //   970: iconst_0
/*    */     //   971: istore #8
/*    */     //   973: iload #8
/*    */     //   975: iload #6
/*    */     //   977: if_icmpge -> 1029
/*    */     //   980: aload #7
/*    */     //   982: iload #8
/*    */     //   984: new f/Z30
/*    */     //   987: dup
/*    */     //   988: astore #9
/*    */     //   990: iload #8
/*    */     //   992: i2f
/*    */     //   993: dup
/*    */     //   994: fconst_1
/*    */     //   995: fmul
/*    */     //   996: iload #6
/*    */     //   998: i2f
/*    */     //   999: dup
/*    */     //   1000: fstore #10
/*    */     //   1002: fdiv
/*    */     //   1003: fstore #11
/*    */     //   1005: ldc_w -1.0
/*    */     //   1008: fmul
/*    */     //   1009: fload #10
/*    */     //   1011: fdiv
/*    */     //   1012: fload #11
/*    */     //   1014: swap
/*    */     //   1015: fconst_1
/*    */     //   1016: fconst_1
/*    */     //   1017: invokespecial <init> : (FFFF)V
/*    */     //   1020: aload #9
/*    */     //   1022: aastore
/*    */     //   1023: iinc #8, 1
/*    */     //   1026: goto -> 973
/*    */     //   1029: aload_1
/*    */     //   1030: aload #5
/*    */     //   1032: getfield xI0 : Ljava/lang/String;
/*    */     //   1035: ldc_w 'ow'
/*    */     //   1038: swap
/*    */     //   1039: ldc_w 0.1
/*    */     //   1042: aload #7
/*    */     //   1044: iconst_1
/*    */     //   1045: invokevirtual dA : (Ljava/lang/String;Ljava/lang/String;F[Lf/Z30;Z)V
/*    */     //   1048: goto -> 796
/*    */     //   1051: aload_1
/*    */     //   1052: aload #5
/*    */     //   1054: dup
/*    */     //   1055: getfield xI0 : Ljava/lang/String;
/*    */     //   1058: astore #5
/*    */     //   1060: getfield qD0 : [Lf/Z30;
/*    */     //   1063: astore #6
/*    */     //   1065: ldc_w 'ow'
/*    */     //   1068: aload #5
/*    */     //   1070: ldc_w 0.0333
/*    */     //   1073: aload #6
/*    */     //   1075: iconst_1
/*    */     //   1076: invokevirtual dA : (Ljava/lang/String;Ljava/lang/String;F[Lf/Z30;Z)V
/*    */     //   1079: goto -> 796
/*    */     //   1082: aload_0
/*    */     //   1083: new f/fQ
/*    */     //   1086: dup
/*    */     //   1087: astore #4
/*    */     //   1089: iconst_1
/*    */     //   1090: invokespecial <init> : (I)V
/*    */     //   1093: getfield aB0 : Lf/V60;
/*    */     //   1096: dup
/*    */     //   1097: astore #5
/*    */     //   1099: getfield Wa0 : Lf/fQ;
/*    */     //   1102: getfield Z8 : I
/*    */     //   1105: ifne -> 2149
/*    */     //   1108: aload #5
/*    */     //   1110: getfield uo : Lf/HI;
/*    */     //   1113: invokevirtual bO : ()B
/*    */     //   1116: iconst_2
/*    */     //   1117: if_icmpne -> 1915
/*    */     //   1120: aload #5
/*    */     //   1122: getfield uo : Lf/HI;
/*    */     //   1125: getfield TI : Lf/RD;
/*    */     //   1128: ldc_w '/a/0/7/0'
/*    */     //   1131: invokevirtual B8 : (Ljava/lang/String;)Lf/T7;
/*    */     //   1134: dup
/*    */     //   1135: dup
/*    */     //   1136: astore #6
/*    */     //   1138: invokestatic Mx0 : ()V
/*    */     //   1141: getfield db : Ljava/lang/String;
/*    */     //   1144: pop
/*    */     //   1145: getfield bP : Lf/HI;
/*    */     //   1148: dup
/*    */     //   1149: astore #7
/*    */     //   1151: invokevirtual GA0 : ()Ljava/nio/ByteBuffer;
/*    */     //   1154: dup
/*    */     //   1155: astore #8
/*    */     //   1157: aload #6
/*    */     //   1159: getfield XL : I
/*    */     //   1162: invokestatic cL0 : (Ljava/nio/ByteBuffer;I)I
/*    */     //   1165: dup
/*    */     //   1166: istore #6
/*    */     //   1168: ldc 1129464142
/*    */     //   1170: dup
/*    */     //   1171: istore #9
/*    */     //   1173: if_icmpne -> 1894
/*    */     //   1176: aload #8
/*    */     //   1178: dup
/*    */     //   1179: dup
/*    */     //   1180: invokestatic Lx0 : (Ljava/nio/ByteBuffer;)I
/*    */     //   1183: istore #6
/*    */     //   1185: invokevirtual getInt : ()I
/*    */     //   1188: dup
/*    */     //   1189: istore #9
/*    */     //   1191: aload #8
/*    */     //   1193: invokevirtual position : ()I
/*    */     //   1196: bipush #8
/*    */     //   1198: swap
/*    */     //   1199: aload #8
/*    */     //   1201: invokestatic TG0 : (IIILjava/nio/ByteBuffer;)I
/*    */     //   1204: istore #10
/*    */     //   1206: invokevirtual position : ()I
/*    */     //   1209: iload #10
/*    */     //   1211: iadd
/*    */     //   1212: istore #10
/*    */     //   1214: iconst_0
/*    */     //   1215: istore #11
/*    */     //   1217: iload #11
/*    */     //   1219: iload #9
/*    */     //   1221: if_icmpge -> 2149
/*    */     //   1224: iload #11
/*    */     //   1226: iload #6
/*    */     //   1228: bipush #12
/*    */     //   1230: iadd
/*    */     //   1231: dup
/*    */     //   1232: aload #8
/*    */     //   1234: swap
/*    */     //   1235: iload #11
/*    */     //   1237: bipush #8
/*    */     //   1239: imul
/*    */     //   1240: dup
/*    */     //   1241: istore #12
/*    */     //   1243: iadd
/*    */     //   1244: invokevirtual getInt : (I)I
/*    */     //   1247: istore #13
/*    */     //   1249: iconst_4
/*    */     //   1250: iload #12
/*    */     //   1252: aload #8
/*    */     //   1254: invokestatic iy0 : (IIILjava/nio/ByteBuffer;)I
/*    */     //   1257: iload #13
/*    */     //   1259: dup
/*    */     //   1260: iload #10
/*    */     //   1262: iadd
/*    */     //   1263: istore #12
/*    */     //   1265: isub
/*    */     //   1266: istore #13
/*    */     //   1268: getstatic f/nN.Wj : [Ljava/lang/String;
/*    */     //   1271: astore #14
/*    */     //   1273: sipush #400
/*    */     //   1276: if_icmpge -> 1288
/*    */     //   1279: aload #14
/*    */     //   1281: iload #11
/*    */     //   1283: aaload
/*    */     //   1284: pop
/*    */     //   1285: goto -> 1294
/*    */     //   1288: iload #11
/*    */     //   1290: invokestatic toString : (I)Ljava/lang/String;
/*    */     //   1293: pop
/*    */     //   1294: iload #13
/*    */     //   1296: aload #7
/*    */     //   1298: invokevirtual GA0 : ()Ljava/nio/ByteBuffer;
/*    */     //   1301: dup
/*    */     //   1302: astore #14
/*    */     //   1304: iload #12
/*    */     //   1306: invokevirtual position : (I)Ljava/nio/Buffer;
/*    */     //   1309: pop
/*    */     //   1310: ifle -> 1328
/*    */     //   1313: iload #12
/*    */     //   1315: aload #14
/*    */     //   1317: invokevirtual limit : ()I
/*    */     //   1320: iload #13
/*    */     //   1322: swap
/*    */     //   1323: aload #14
/*    */     //   1325: invokestatic Pp0 : (IIILjava/nio/ByteBuffer;)V
/*    */     //   1328: aload #14
/*    */     //   1330: invokevirtual slice : ()Ljava/nio/ByteBuffer;
/*    */     //   1333: getstatic java/nio/ByteOrder.LITTLE_ENDIAN : Ljava/nio/ByteOrder;
/*    */     //   1336: invokevirtual order : (Ljava/nio/ByteOrder;)Ljava/nio/ByteBuffer;
/*    */     //   1339: dup
/*    */     //   1340: astore #12
/*    */     //   1342: invokevirtual getInt : ()I
/*    */     //   1345: dup
/*    */     //   1346: dup
/*    */     //   1347: istore #13
/*    */     //   1349: newarray int
/*    */     //   1351: astore #14
/*    */     //   1353: newarray int
/*    */     //   1355: astore #15
/*    */     //   1357: iconst_0
/*    */     //   1358: istore #16
/*    */     //   1360: iload #16
/*    */     //   1362: iload #13
/*    */     //   1364: if_icmpge -> 1395
/*    */     //   1367: aload #15
/*    */     //   1369: aload #12
/*    */     //   1371: aload #14
/*    */     //   1373: aload #12
/*    */     //   1375: invokevirtual getInt : ()I
/*    */     //   1378: iload #16
/*    */     //   1380: swap
/*    */     //   1381: iastore
/*    */     //   1382: invokevirtual getInt : ()I
/*    */     //   1385: iload #16
/*    */     //   1387: swap
/*    */     //   1388: iastore
/*    */     //   1389: iinc #16, 1
/*    */     //   1392: goto -> 1360
/*    */     //   1395: aload #12
/*    */     //   1397: invokevirtual getInt : ()I
/*    */     //   1400: pop
/*    */     //   1401: iconst_0
/*    */     //   1402: istore #16
/*    */     //   1404: iload #16
/*    */     //   1406: iload #13
/*    */     //   1408: if_icmpge -> 1888
/*    */     //   1411: aload #12
/*    */     //   1413: aload #15
/*    */     //   1415: iload #16
/*    */     //   1417: iaload
/*    */     //   1418: bipush #20
/*    */     //   1420: iadd
/*    */     //   1421: invokevirtual position : (I)Ljava/nio/Buffer;
/*    */     //   1424: pop
/*    */     //   1425: aconst_null
/*    */     //   1426: astore #17
/*    */     //   1428: new f/C20
/*    */     //   1431: dup
/*    */     //   1432: astore #18
/*    */     //   1434: aload #12
/*    */     //   1436: iconst_0
/*    */     //   1437: iconst_1
/*    */     //   1438: invokespecial <init> : (Ljava/nio/ByteBuffer;ZZ)V
/*    */     //   1441: aload #18
/*    */     //   1443: astore #17
/*    */     //   1445: goto -> 1451
/*    */     //   1448: invokevirtual printStackTrace : ()V
/*    */     //   1451: aload #17
/*    */     //   1453: ifnull -> 1882
/*    */     //   1456: aload #12
/*    */     //   1458: dup
/*    */     //   1459: aload #14
/*    */     //   1461: iload #16
/*    */     //   1463: iaload
/*    */     //   1464: invokevirtual position : (I)Ljava/nio/Buffer;
/*    */     //   1467: pop
/*    */     //   1468: invokevirtual getInt : ()I
/*    */     //   1471: istore #18
/*    */     //   1473: iconst_0
/*    */     //   1474: istore #19
/*    */     //   1476: bipush #16
/*    */     //   1478: dup
/*    */     //   1479: istore #20
/*    */     //   1481: newarray int
/*    */     //   1483: astore #21
/*    */     //   1485: new f/fQ
/*    */     //   1488: dup
/*    */     //   1489: astore #22
/*    */     //   1491: invokespecial <init> : ()V
/*    */     //   1494: iconst_0
/*    */     //   1495: istore #23
/*    */     //   1497: iload #23
/*    */     //   1499: iload #18
/*    */     //   1501: if_icmpge -> 1526
/*    */     //   1504: aload #22
/*    */     //   1506: new f/Gc0
/*    */     //   1509: dup
/*    */     //   1510: astore #24
/*    */     //   1512: invokespecial <init> : ()V
/*    */     //   1515: aload #24
/*    */     //   1517: invokevirtual Com3 : (Ljava/lang/Object;)V
/*    */     //   1520: iinc #23, 1
/*    */     //   1523: goto -> 1497
/*    */     //   1526: iconst_0
/*    */     //   1527: istore #23
/*    */     //   1529: iload #23
/*    */     //   1531: iload #18
/*    */     //   1533: if_icmpge -> 1586
/*    */     //   1536: iload #23
/*    */     //   1538: aload #22
/*    */     //   1540: iload #23
/*    */     //   1542: aload #12
/*    */     //   1544: invokevirtual getShort : ()S
/*    */     //   1547: istore #24
/*    */     //   1549: invokevirtual get : (I)Ljava/lang/Object;
/*    */     //   1552: checkcast f/Gc0
/*    */     //   1555: iload #24
/*    */     //   1557: putfield LB : S
/*    */     //   1560: ifle -> 1580
/*    */     //   1563: iload #24
/*    */     //   1565: ifne -> 1580
/*    */     //   1568: aload #21
/*    */     //   1570: iload #19
/*    */     //   1572: iconst_1
/*    */     //   1573: iadd
/*    */     //   1574: dup
/*    */     //   1575: istore #19
/*    */     //   1577: iload #23
/*    */     //   1579: iastore
/*    */     //   1580: iinc #23, 1
/*    */     //   1583: goto -> 1529
/*    */     //   1586: iload #18
/*    */     //   1588: sipush #151
/*    */     //   1591: if_icmpeq -> 1606
/*    */     //   1594: iload #18
/*    */     //   1596: iconst_3
/*    */     //   1597: if_icmpeq -> 1606
/*    */     //   1600: iload #18
/*    */     //   1602: iconst_5
/*    */     //   1603: if_icmpne -> 1612
/*    */     //   1606: aload #12
/*    */     //   1608: invokevirtual getShort : ()S
/*    */     //   1611: pop
/*    */     //   1612: iconst_0
/*    */     //   1613: istore #19
/*    */     //   1615: iload #19
/*    */     //   1617: iload #18
/*    */     //   1619: if_icmpge -> 1650
/*    */     //   1622: aload #22
/*    */     //   1624: iload #19
/*    */     //   1626: aload #12
/*    */     //   1628: invokevirtual get : ()B
/*    */     //   1631: istore #23
/*    */     //   1633: invokevirtual get : (I)Ljava/lang/Object;
/*    */     //   1636: checkcast f/Gc0
/*    */     //   1639: iload #23
/*    */     //   1641: putfield oz0 : B
/*    */     //   1644: iinc #19, 1
/*    */     //   1647: goto -> 1615
/*    */     //   1650: iload #18
/*    */     //   1652: sipush #151
/*    */     //   1655: if_icmpeq -> 1670
/*    */     //   1658: iload #18
/*    */     //   1660: iconst_3
/*    */     //   1661: if_icmpeq -> 1670
/*    */     //   1664: iload #18
/*    */     //   1666: iconst_5
/*    */     //   1667: if_icmpne -> 1688
/*    */     //   1670: iload #18
/*    */     //   1672: aload #12
/*    */     //   1674: invokevirtual get : ()B
/*    */     //   1677: pop
/*    */     //   1678: iconst_5
/*    */     //   1679: if_icmpne -> 1688
/*    */     //   1682: aload #12
/*    */     //   1684: invokevirtual getShort : ()S
/*    */     //   1687: pop
/*    */     //   1688: iconst_0
/*    */     //   1689: istore #19
/*    */     //   1691: iload #19
/*    */     //   1693: iload #18
/*    */     //   1695: if_icmpge -> 1726
/*    */     //   1698: aload #22
/*    */     //   1700: iload #19
/*    */     //   1702: aload #12
/*    */     //   1704: invokevirtual get : ()B
/*    */     //   1707: istore #23
/*    */     //   1709: invokevirtual get : (I)Ljava/lang/Object;
/*    */     //   1712: checkcast f/Gc0
/*    */     //   1715: iload #23
/*    */     //   1717: putfield Wq : B
/*    */     //   1720: iinc #19, 1
/*    */     //   1723: goto -> 1691
/*    */     //   1726: aload #12
/*    */     //   1728: aload #15
/*    */     //   1730: iload #16
/*    */     //   1732: iaload
/*    */     //   1733: iconst_4
/*    */     //   1734: isub
/*    */     //   1735: invokevirtual getInt : (I)I
/*    */     //   1738: istore #18
/*    */     //   1740: iconst_0
/*    */     //   1741: istore #19
/*    */     //   1743: iload #19
/*    */     //   1745: iload #20
/*    */     //   1747: if_icmpge -> 1882
/*    */     //   1750: iload #19
/*    */     //   1752: aload #21
/*    */     //   1754: new f/fQ
/*    */     //   1757: dup
/*    */     //   1758: astore #23
/*    */     //   1760: invokespecial <init> : ()V
/*    */     //   1763: iload #19
/*    */     //   1765: iaload
/*    */     //   1766: istore #24
/*    */     //   1768: ifle -> 1779
/*    */     //   1771: iload #24
/*    */     //   1773: ifne -> 1779
/*    */     //   1776: goto -> 1876
/*    */     //   1779: iload #19
/*    */     //   1781: aload #22
/*    */     //   1783: getfield Z8 : I
/*    */     //   1786: istore #25
/*    */     //   1788: bipush #15
/*    */     //   1790: if_icmpeq -> 1810
/*    */     //   1793: aload #21
/*    */     //   1795: iload #19
/*    */     //   1797: iconst_1
/*    */     //   1798: iadd
/*    */     //   1799: iaload
/*    */     //   1800: dup
/*    */     //   1801: istore #26
/*    */     //   1803: ifle -> 1810
/*    */     //   1806: iload #26
/*    */     //   1808: istore #25
/*    */     //   1810: iload #24
/*    */     //   1812: iload #25
/*    */     //   1814: if_icmpge -> 1835
/*    */     //   1817: aload #23
/*    */     //   1819: aload #22
/*    */     //   1821: iload #24
/*    */     //   1823: invokevirtual get : (I)Ljava/lang/Object;
/*    */     //   1826: invokevirtual Com3 : (Ljava/lang/Object;)V
/*    */     //   1829: iinc #24, 1
/*    */     //   1832: goto -> 1810
/*    */     //   1835: aload #5
/*    */     //   1837: aload #23
/*    */     //   1839: invokevirtual peek : ()Ljava/lang/Object;
/*    */     //   1842: checkcast f/Gc0
/*    */     //   1845: dup
/*    */     //   1846: getfield LB : S
/*    */     //   1849: iload #18
/*    */     //   1851: iadd
/*    */     //   1852: i2s
/*    */     //   1853: putfield LB : S
/*    */     //   1856: getfield Wa0 : Lf/fQ;
/*    */     //   1859: new f/hz
/*    */     //   1862: dup
/*    */     //   1863: aload #17
/*    */     //   1865: getfield bl : Lf/Wd;
/*    */     //   1868: aload #23
/*    */     //   1870: invokespecial <init> : (Lf/Wd;Lf/fQ;)V
/*    */     //   1873: invokevirtual Com3 : (Ljava/lang/Object;)V
/*    */     //   1876: iinc #19, 1
/*    */     //   1879: goto -> 1743
/*    */     //   1882: iinc #16, 1
/*    */     //   1885: goto -> 1404
/*    */     //   1888: iinc #11, 1
/*    */     //   1891: goto -> 1217
/*    */     //   1894: new java/lang/RuntimeException
/*    */     //   1897: dup
/*    */     //   1898: ldc_w 'Header magic mismatch = '
/*    */     //   1901: iload #6
/*    */     //   1903: ldc_w ' vs expected '
/*    */     //   1906: iload #9
/*    */     //   1908: invokestatic KK : (Ljava/lang/String;ILjava/lang/String;I)Ljava/lang/String;
/*    */     //   1911: invokespecial <init> : (Ljava/lang/String;)V
/*    */     //   1914: athrow
/*    */     //   1915: aload #5
/*    */     //   1917: getfield uo : Lf/HI;
/*    */     //   1920: invokevirtual bO : ()B
/*    */     //   1923: iconst_3
/*    */     //   1924: if_icmpne -> 2001
/*    */     //   1927: aload #5
/*    */     //   1929: dup
/*    */     //   1930: dup
/*    */     //   1931: dup2
/*    */     //   1932: dup2
/*    */     //   1933: dup2
/*    */     //   1934: dup2
/*    */     //   1935: invokevirtual m20 : ()V
/*    */     //   1938: getfield Wa0 : Lf/fQ;
/*    */     //   1941: ldc_w '/data/t3_fl_b.nsbtx'
/*    */     //   1944: ldc_w 't3_fl_b'
/*    */     //   1947: invokevirtual Sc : (Lf/fQ;Ljava/lang/String;Ljava/lang/String;)V
/*    */     //   1950: getfield Wa0 : Lf/fQ;
/*    */     //   1953: ldc_w '/data/t3_fl_p.nsbtx'
/*    */     //   1956: ldc_w 't3_fl_p'
/*    */     //   1959: invokevirtual Sc : (Lf/fQ;Ljava/lang/String;Ljava/lang/String;)V
/*    */     //   1962: getfield Wa0 : Lf/fQ;
/*    */     //   1965: ldc_w '/data/t3_fl_r.nsbtx'
/*    */     //   1968: ldc_w 't3_fl_r'
/*    */     //   1971: invokevirtual Sc : (Lf/fQ;Ljava/lang/String;Ljava/lang/String;)V
/*    */     //   1974: getfield Wa0 : Lf/fQ;
/*    */     //   1977: ldc_w '/data/t3_fl_y.nsbtx'
/*    */     //   1980: ldc_w 't3_fl_y'
/*    */     //   1983: invokevirtual Sc : (Lf/fQ;Ljava/lang/String;Ljava/lang/String;)V
/*    */     //   1986: getfield Wa0 : Lf/fQ;
/*    */     //   1989: ldc_w '/data/lake_anim.nsbtx'
/*    */     //   1992: ldc_w 'lakep'
/*    */     //   1995: invokevirtual Sc : (Lf/fQ;Ljava/lang/String;Ljava/lang/String;)V
/*    */     //   1998: goto -> 2149
/*    */     //   2001: aload #5
/*    */     //   2003: getfield uo : Lf/HI;
/*    */     //   2006: invokevirtual bO : ()B
/*    */     //   2009: iconst_4
/*    */     //   2010: if_icmpne -> 2149
/*    */     //   2013: aload #5
/*    */     //   2015: dup
/*    */     //   2016: dup
/*    */     //   2017: dup2
/*    */     //   2018: dup2
/*    */     //   2019: dup2
/*    */     //   2020: dup2
/*    */     //   2021: dup2
/*    */     //   2022: dup2
/*    */     //   2023: dup2
/*    */     //   2024: dup2
/*    */     //   2025: dup2
/*    */     //   2026: getfield Wa0 : Lf/fQ;
/*    */     //   2029: ldc_w '/data/t3_fl_b.nsbtx'
/*    */     //   2032: ldc_w 't3_fl_b'
/*    */     //   2035: invokevirtual Sc : (Lf/fQ;Ljava/lang/String;Ljava/lang/String;)V
/*    */     //   2038: getfield Wa0 : Lf/fQ;
/*    */     //   2041: ldc_w '/data/t3_fl_p.nsbtx'
/*    */     //   2044: ldc_w 't3_fl_p'
/*    */     //   2047: invokevirtual Sc : (Lf/fQ;Ljava/lang/String;Ljava/lang/String;)V
/*    */     //   2050: getfield Wa0 : Lf/fQ;
/*    */     //   2053: ldc_w '/data/t3_fl_r.nsbtx'
/*    */     //   2056: ldc_w 't3_fl_r'
/*    */     //   2059: invokevirtual Sc : (Lf/fQ;Ljava/lang/String;Ljava/lang/String;)V
/*    */     //   2062: getfield Wa0 : Lf/fQ;
/*    */     //   2065: ldc_w '/data/t3_fl_y.nsbtx'
/*    */     //   2068: ldc_w 't3_fl_y'
/*    */     //   2071: invokevirtual Sc : (Lf/fQ;Ljava/lang/String;Ljava/lang/String;)V
/*    */     //   2074: getfield Wa0 : Lf/fQ;
/*    */     //   2077: ldc_w '/data/lake_anim.nsbtx'
/*    */     //   2080: ldc_w 'lakep'
/*    */     //   2083: invokevirtual Sc : (Lf/fQ;Ljava/lang/String;Ljava/lang/String;)V
/*    */     //   2086: getfield Wa0 : Lf/fQ;
/*    */     //   2089: ldc_w '/data/miniasahamabe.nsbtx'
/*    */     //   2092: ldc_w 'asahamabe'
/*    */     //   2095: invokevirtual Sc : (Lf/fQ;Ljava/lang/String;Ljava/lang/String;)V
/*    */     //   2098: getfield Wa0 : Lf/fQ;
/*    */     //   2101: ldc_w '/data/miniasasea.nsbtx'
/*    */     //   2104: ldc_w 'asasea'
/*    */     //   2107: invokevirtual Sc : (Lf/fQ;Ljava/lang/String;Ljava/lang/String;)V
/*    */     //   2110: getfield Wa0 : Lf/fQ;
/*    */     //   2113: ldc_w '/data/minihamabe.nsbtx'
/*    */     //   2116: ldc_w 'hamabe'
/*    */     //   2119: invokevirtual Sc : (Lf/fQ;Ljava/lang/String;Ljava/lang/String;)V
/*    */     //   2122: getfield Wa0 : Lf/fQ;
/*    */     //   2125: ldc_w '/data/minimum.nsbtx'
/*    */     //   2128: ldc_w 'sea'
/*    */     //   2131: invokevirtual Sc : (Lf/fQ;Ljava/lang/String;Ljava/lang/String;)V
/*    */     //   2134: getfield Wa0 : Lf/fQ;
/*    */     //   2137: ldc_w '/data/minirhana.nsbtx'
/*    */     //   2140: ldc_w 'rhana'
/*    */     //   2143: invokevirtual Sc : (Lf/fQ;Ljava/lang/String;Ljava/lang/String;)V
/*    */     //   2146: invokevirtual m20 : ()V
/*    */     //   2149: aload #5
/*    */     //   2151: getfield Wa0 : Lf/fQ;
/*    */     //   2154: invokevirtual r30 : ()Lf/Hc0;
/*    */     //   2157: astore #5
/*    */     //   2159: aload #5
/*    */     //   2161: invokevirtual hasNext : ()Z
/*    */     //   2164: ifeq -> 4033
/*    */     //   2167: aload #5
/*    */     //   2169: invokevirtual next : ()Ljava/lang/Object;
/*    */     //   2172: checkcast f/hz
/*    */     //   2175: dup
/*    */     //   2176: dup
/*    */     //   2177: astore #6
/*    */     //   2179: getfield QE0 : F
/*    */     //   2182: fstore #7
/*    */     //   2184: getfield GG0 : Lf/eM;
/*    */     //   2187: invokevirtual iC : ()Lf/qA0;
/*    */     //   2190: dup
/*    */     //   2191: astore #8
/*    */     //   2193: invokevirtual getClass : ()Ljava/lang/Class;
/*    */     //   2196: pop
/*    */     //   2197: aload #8
/*    */     //   2199: invokevirtual hasNext : ()Z
/*    */     //   2202: ifeq -> 2159
/*    */     //   2205: aload_0
/*    */     //   2206: aload #8
/*    */     //   2208: invokevirtual next : ()Ljava/lang/Object;
/*    */     //   2211: checkcast f/ai
/*    */     //   2214: dup
/*    */     //   2215: astore #9
/*    */     //   2217: aload #4
/*    */     //   2219: invokevirtual clear : ()V
/*    */     //   2222: getfield aH : Ljava/lang/String;
/*    */     //   2225: astore #10
/*    */     //   2227: invokevirtual bO : ()B
/*    */     //   2230: iconst_3
/*    */     //   2231: if_icmpne -> 3420
/*    */     //   2234: aload_1
/*    */     //   2235: getfield Zl0 : Ljava/lang/String;
/*    */     //   2238: ldc_w 'm_gym0503_00_00c'
/*    */     //   2241: invokevirtual equalsIgnoreCase : (Ljava/lang/String;)Z
/*    */     //   2244: ifne -> 2955
/*    */     //   2247: aload_1
/*    */     //   2248: getfield Zl0 : Ljava/lang/String;
/*    */     //   2251: ldc_w 'm_gym0502_00_00c'
/*    */     //   2254: invokevirtual equalsIgnoreCase : (Ljava/lang/String;)Z
/*    */     //   2257: ifeq -> 2263
/*    */     //   2260: goto -> 2955
/*    */     //   2263: aload_1
/*    */     //   2264: getfield Zl0 : Ljava/lang/String;
/*    */     //   2267: ldc_w 'm_wifi02_00_00c'
/*    */     //   2270: invokevirtual equalsIgnoreCase : (Ljava/lang/String;)Z
/*    */     //   2273: ifeq -> 2304
/*    */     //   2276: aload #10
/*    */     //   2278: ldc_w 'wtk_kabe2'
/*    */     //   2281: invokevirtual equalsIgnoreCase : (Ljava/lang/String;)Z
/*    */     //   2284: ifeq -> 2290
/*    */     //   2287: goto -> 2385
/*    */     //   2290: aload #10
/*    */     //   2292: ldc_w 'wtk_kabe12.0'
/*    */     //   2295: invokevirtual equalsIgnoreCase : (Ljava/lang/String;)Z
/*    */     //   2298: ifeq -> 3039
/*    */     //   2301: goto -> 2350
/*    */     //   2304: aload_1
/*    */     //   2305: getfield Zl0 : Ljava/lang/String;
/*    */     //   2308: ldc_w 'm_wifi01_00_00c'
/*    */     //   2311: invokevirtual equalsIgnoreCase : (Ljava/lang/String;)Z
/*    */     //   2314: ifeq -> 2361
/*    */     //   2317: aload #10
/*    */     //   2319: ldc_w 'wtk_kabe1'
/*    */     //   2322: invokevirtual equalsIgnoreCase : (Ljava/lang/String;)Z
/*    */     //   2325: ifeq -> 2339
/*    */     //   2328: aload #4
/*    */     //   2330: ldc_w 'kabe2'
/*    */     //   2333: invokevirtual Com3 : (Ljava/lang/Object;)V
/*    */     //   2336: goto -> 3039
/*    */     //   2339: aload #10
/*    */     //   2341: ldc_w 'wtk_kabe11.0'
/*    */     //   2344: invokevirtual equalsIgnoreCase : (Ljava/lang/String;)Z
/*    */     //   2347: ifeq -> 3039
/*    */     //   2350: aload #4
/*    */     //   2352: ldc_w 'kabe_anm'
/*    */     //   2355: invokevirtual Com3 : (Ljava/lang/Object;)V
/*    */     //   2358: goto -> 3039
/*    */     //   2361: aload_1
/*    */     //   2362: getfield Zl0 : Ljava/lang/String;
/*    */     //   2365: ldc_w 'm_wifi03_00_00c'
/*    */     //   2368: invokevirtual equalsIgnoreCase : (Ljava/lang/String;)Z
/*    */     //   2371: ifeq -> 2418
/*    */     //   2374: aload #10
/*    */     //   2376: ldc_w 'wtk_kabe3'
/*    */     //   2379: invokevirtual equalsIgnoreCase : (Ljava/lang/String;)Z
/*    */     //   2382: ifeq -> 2396
/*    */     //   2385: aload #4
/*    */     //   2387: ldc_w 'wifi_r2'
/*    */     //   2390: invokevirtual Com3 : (Ljava/lang/Object;)V
/*    */     //   2393: goto -> 3039
/*    */     //   2396: aload #10
/*    */     //   2398: ldc_w 'wtk_kabe13.0'
/*    */     //   2401: invokevirtual equalsIgnoreCase : (Ljava/lang/String;)Z
/*    */     //   2404: ifeq -> 3039
/*    */     //   2407: aload #4
/*    */     //   2409: ldc_w 'lambert9'
/*    */     //   2412: invokevirtual Com3 : (Ljava/lang/Object;)V
/*    */     //   2415: goto -> 3039
/*    */     //   2418: aload_1
/*    */     //   2419: getfield Zl0 : Ljava/lang/String;
/*    */     //   2422: ldc_w 'm_siten03_00_00c'
/*    */     //   2425: invokevirtual equalsIgnoreCase : (Ljava/lang/String;)Z
/*    */     //   2428: ifeq -> 2450
/*    */     //   2431: aload #10
/*    */     //   2433: ldc_w 'm_4ten_hi'
/*    */     //   2436: invokevirtual startsWith : (Ljava/lang/String;)Z
/*    */     //   2439: ifeq -> 3039
/*    */     //   2442: ldc_w 0.1
/*    */     //   2445: fstore #7
/*    */     //   2447: goto -> 3039
/*    */     //   2450: aload_1
/*    */     //   2451: getfield Zl0 : Ljava/lang/String;
/*    */     //   2454: ldc_w 'm_dun0101_00_00c'
/*    */     //   2457: invokevirtual equalsIgnoreCase : (Ljava/lang/String;)Z
/*    */     //   2460: ifeq -> 2482
/*    */     //   2463: aload #10
/*    */     //   2465: ldc_w 'c3_s03b'
/*    */     //   2468: invokevirtual startsWith : (Ljava/lang/String;)Z
/*    */     //   2471: ifeq -> 3039
/*    */     //   2474: ldc_w 0.05
/*    */     //   2477: fstore #7
/*    */     //   2479: goto -> 3039
/*    */     //   2482: aload_1
/*    */     //   2483: getfield Zl0 : Ljava/lang/String;
/*    */     //   2486: ldc_w 'm_dun0602_01_01c'
/*    */     //   2489: invokevirtual equalsIgnoreCase : (Ljava/lang/String;)Z
/*    */     //   2492: ifne -> 2560
/*    */     //   2495: aload_1
/*    */     //   2496: getfield Zl0 : Ljava/lang/String;
/*    */     //   2499: ldc_w 'm_dun0602_01_02c'
/*    */     //   2502: invokevirtual equalsIgnoreCase : (Ljava/lang/String;)Z
/*    */     //   2505: ifne -> 2560
/*    */     //   2508: aload_1
/*    */     //   2509: getfield Zl0 : Ljava/lang/String;
/*    */     //   2512: ldc_w 'm_dun0602_01_03c'
/*    */     //   2515: invokevirtual equalsIgnoreCase : (Ljava/lang/String;)Z
/*    */     //   2518: ifne -> 2560
/*    */     //   2521: aload_1
/*    */     //   2522: getfield Zl0 : Ljava/lang/String;
/*    */     //   2525: ldc_w 'm_dun0602_02_01c'
/*    */     //   2528: invokevirtual equalsIgnoreCase : (Ljava/lang/String;)Z
/*    */     //   2531: ifne -> 2560
/*    */     //   2534: aload_1
/*    */     //   2535: getfield Zl0 : Ljava/lang/String;
/*    */     //   2538: ldc_w 'm_dun0602_02_02c'
/*    */     //   2541: invokevirtual equalsIgnoreCase : (Ljava/lang/String;)Z
/*    */     //   2544: ifne -> 2560
/*    */     //   2547: aload_1
/*    */     //   2548: getfield Zl0 : Ljava/lang/String;
/*    */     //   2551: ldc_w 'm_dun0602_02_03c'
/*    */     //   2554: invokevirtual equalsIgnoreCase : (Ljava/lang/String;)Z
/*    */     //   2557: ifeq -> 3039
/*    */     //   2560: aload #10
/*    */     //   2562: ldc_w 'numa_f1b'
/*    */     //   2565: invokevirtual equalsIgnoreCase : (Ljava/lang/String;)Z
/*    */     //   2568: ifeq -> 2689
/*    */     //   2571: aload_1
/*    */     //   2572: dup
/*    */     //   2573: aload #6
/*    */     //   2575: dup
/*    */     //   2576: getfield bz : Lf/Wd;
/*    */     //   2579: aload #9
/*    */     //   2581: dup
/*    */     //   2582: getfield ZP : Lf/fQ;
/*    */     //   2585: astore #10
/*    */     //   2587: getfield ej : Lf/fQ;
/*    */     //   2590: aload #10
/*    */     //   2592: swap
/*    */     //   2593: aconst_null
/*    */     //   2594: aconst_null
/*    */     //   2595: aload_3
/*    */     //   2596: iconst_0
/*    */     //   2597: invokestatic qY : (Lf/Wd;Lf/fQ;Lf/fQ;Lf/fQ;Lf/fQ;Lf/Ew;Z)[Lf/pe0;
/*    */     //   2600: astore #10
/*    */     //   2602: getfield bz : Lf/Wd;
/*    */     //   2605: aload #9
/*    */     //   2607: getfield ZP : Lf/fQ;
/*    */     //   2610: dup
/*    */     //   2611: bipush #6
/*    */     //   2613: newarray int
/*    */     //   2615: dup
/*    */     //   2616: dup
/*    */     //   2617: dup2
/*    */     //   2618: dup2
/*    */     //   2619: astore #9
/*    */     //   2621: iconst_0
/*    */     //   2622: ldc_w -12558248
/*    */     //   2625: iastore
/*    */     //   2626: iconst_1
/*    */     //   2627: ldc_w -12556192
/*    */     //   2630: iastore
/*    */     //   2631: iconst_2
/*    */     //   2632: iconst_0
/*    */     //   2633: iastore
/*    */     //   2634: iconst_3
/*    */     //   2635: iconst_0
/*    */     //   2636: iastore
/*    */     //   2637: iconst_4
/*    */     //   2638: iconst_0
/*    */     //   2639: iastore
/*    */     //   2640: iconst_5
/*    */     //   2641: iconst_0
/*    */     //   2642: iastore
/*    */     //   2643: getfield Z8 : I
/*    */     //   2646: aload #9
/*    */     //   2648: swap
/*    */     //   2649: aload_3
/*    */     //   2650: iconst_0
/*    */     //   2651: invokestatic Mf0 : (Lf/Wd;Lf/fQ;[IILf/Ew;Z)[Lf/pe0;
/*    */     //   2654: astore #9
/*    */     //   2656: ldc_w 'ow'
/*    */     //   2659: ldc_w 'numa_b_lm1'
/*    */     //   2662: ldc_w 0.25
/*    */     //   2665: aload #10
/*    */     //   2667: iconst_1
/*    */     //   2668: invokevirtual rq : (Ljava/lang/String;Ljava/lang/String;F[Lf/pe0;Z)V
/*    */     //   2671: ldc_w 'ow'
/*    */     //   2674: ldc_w 'lambert37'
/*    */     //   2677: ldc_w 0.25
/*    */     //   2680: aload #9
/*    */     //   2682: iconst_1
/*    */     //   2683: invokevirtual rq : (Ljava/lang/String;Ljava/lang/String;F[Lf/pe0;Z)V
/*    */     //   2686: goto -> 2197
/*    */     //   2689: aload #10
/*    */     //   2691: ldc_w 'numa_f1de'
/*    */     //   2694: invokevirtual equalsIgnoreCase : (Ljava/lang/String;)Z
/*    */     //   2697: ifeq -> 2933
/*    */     //   2700: aload_1
/*    */     //   2701: dup
/*    */     //   2702: aload #6
/*    */     //   2704: dup
/*    */     //   2705: aload_1
/*    */     //   2706: dup
/*    */     //   2707: aload #6
/*    */     //   2709: dup
/*    */     //   2710: getfield bz : Lf/Wd;
/*    */     //   2713: aload #9
/*    */     //   2715: dup
/*    */     //   2716: getfield ZP : Lf/fQ;
/*    */     //   2719: astore #10
/*    */     //   2721: getfield ej : Lf/fQ;
/*    */     //   2724: aload #10
/*    */     //   2726: swap
/*    */     //   2727: aconst_null
/*    */     //   2728: aconst_null
/*    */     //   2729: aload_3
/*    */     //   2730: iconst_0
/*    */     //   2731: invokestatic qY : (Lf/Wd;Lf/fQ;Lf/fQ;Lf/fQ;Lf/fQ;Lf/Ew;Z)[Lf/pe0;
/*    */     //   2734: astore #10
/*    */     //   2736: getfield bz : Lf/Wd;
/*    */     //   2739: aload #9
/*    */     //   2741: dup
/*    */     //   2742: getfield ZP : Lf/fQ;
/*    */     //   2745: astore #11
/*    */     //   2747: getfield ej : Lf/fQ;
/*    */     //   2750: aload #11
/*    */     //   2752: swap
/*    */     //   2753: aconst_null
/*    */     //   2754: aconst_null
/*    */     //   2755: aload_3
/*    */     //   2756: iconst_1
/*    */     //   2757: invokestatic qY : (Lf/Wd;Lf/fQ;Lf/fQ;Lf/fQ;Lf/fQ;Lf/Ew;Z)[Lf/pe0;
/*    */     //   2760: astore #11
/*    */     //   2762: ldc_w 'ow'
/*    */     //   2765: ldc_w 'numa_d_lm27'
/*    */     //   2768: ldc_w 0.25
/*    */     //   2771: aload #10
/*    */     //   2773: iconst_1
/*    */     //   2774: invokevirtual rq : (Ljava/lang/String;Ljava/lang/String;F[Lf/pe0;Z)V
/*    */     //   2777: ldc_w 'ow'
/*    */     //   2780: ldc_w 'numa_e_lm25'
/*    */     //   2783: ldc_w 0.25
/*    */     //   2786: aload #11
/*    */     //   2788: iconst_1
/*    */     //   2789: invokevirtual rq : (Ljava/lang/String;Ljava/lang/String;F[Lf/pe0;Z)V
/*    */     //   2792: getfield bz : Lf/Wd;
/*    */     //   2795: aload #9
/*    */     //   2797: getfield ZP : Lf/fQ;
/*    */     //   2800: dup
/*    */     //   2801: bipush #6
/*    */     //   2803: newarray int
/*    */     //   2805: dup
/*    */     //   2806: dup
/*    */     //   2807: dup2
/*    */     //   2808: dup2
/*    */     //   2809: astore #10
/*    */     //   2811: iconst_0
/*    */     //   2812: ldc_w -12558248
/*    */     //   2815: iastore
/*    */     //   2816: iconst_1
/*    */     //   2817: ldc_w -12556192
/*    */     //   2820: iastore
/*    */     //   2821: iconst_2
/*    */     //   2822: iconst_0
/*    */     //   2823: iastore
/*    */     //   2824: iconst_3
/*    */     //   2825: iconst_0
/*    */     //   2826: iastore
/*    */     //   2827: iconst_4
/*    */     //   2828: iconst_0
/*    */     //   2829: iastore
/*    */     //   2830: iconst_5
/*    */     //   2831: iconst_0
/*    */     //   2832: iastore
/*    */     //   2833: getfield Z8 : I
/*    */     //   2836: aload #10
/*    */     //   2838: swap
/*    */     //   2839: aload_3
/*    */     //   2840: iconst_0
/*    */     //   2841: invokestatic Mf0 : (Lf/Wd;Lf/fQ;[IILf/Ew;Z)[Lf/pe0;
/*    */     //   2844: astore #10
/*    */     //   2846: getfield bz : Lf/Wd;
/*    */     //   2849: aload #9
/*    */     //   2851: getfield ZP : Lf/fQ;
/*    */     //   2854: dup
/*    */     //   2855: bipush #6
/*    */     //   2857: newarray int
/*    */     //   2859: dup
/*    */     //   2860: dup
/*    */     //   2861: dup2
/*    */     //   2862: dup2
/*    */     //   2863: astore #9
/*    */     //   2865: iconst_0
/*    */     //   2866: ldc_w -12558248
/*    */     //   2869: iastore
/*    */     //   2870: iconst_1
/*    */     //   2871: ldc_w -12556192
/*    */     //   2874: iastore
/*    */     //   2875: iconst_2
/*    */     //   2876: iconst_0
/*    */     //   2877: iastore
/*    */     //   2878: iconst_3
/*    */     //   2879: iconst_0
/*    */     //   2880: iastore
/*    */     //   2881: iconst_4
/*    */     //   2882: iconst_0
/*    */     //   2883: iastore
/*    */     //   2884: iconst_5
/*    */     //   2885: iconst_0
/*    */     //   2886: iastore
/*    */     //   2887: getfield Z8 : I
/*    */     //   2890: aload #9
/*    */     //   2892: swap
/*    */     //   2893: aload_3
/*    */     //   2894: iconst_1
/*    */     //   2895: invokestatic Mf0 : (Lf/Wd;Lf/fQ;[IILf/Ew;Z)[Lf/pe0;
/*    */     //   2898: astore #9
/*    */     //   2900: ldc_w 'ow'
/*    */     //   2903: ldc_w 'lambert40'
/*    */     //   2906: ldc_w 0.25
/*    */     //   2909: aload #9
/*    */     //   2911: iconst_1
/*    */     //   2912: invokevirtual rq : (Ljava/lang/String;Ljava/lang/String;F[Lf/pe0;Z)V
/*    */     //   2915: ldc_w 'ow'
/*    */     //   2918: ldc_w 'lambert39'
/*    */     //   2921: ldc_w 0.25
/*    */     //   2924: aload #10
/*    */     //   2926: iconst_1
/*    */     //   2927: invokevirtual rq : (Ljava/lang/String;Ljava/lang/String;F[Lf/pe0;Z)V
/*    */     //   2930: goto -> 2197
/*    */     //   2933: aload #10
/*    */     //   2935: ldc_w 'numa_f1c'
/*    */     //   2938: invokevirtual equalsIgnoreCase : (Ljava/lang/String;)Z
/*    */     //   2941: ifeq -> 3039
/*    */     //   2944: aload #4
/*    */     //   2946: ldc_w 'numa_c_lm1'
/*    */     //   2949: invokevirtual Com3 : (Ljava/lang/Object;)V
/*    */     //   2952: goto -> 3039
/*    */     //   2955: aload_1
/*    */     //   2956: getfield xl0 : Lf/fQ;
/*    */     //   2959: invokevirtual r30 : ()Lf/Hc0;
/*    */     //   2962: astore #11
/*    */     //   2964: aload #11
/*    */     //   2966: invokevirtual hasNext : ()Z
/*    */     //   2969: ifeq -> 3039
/*    */     //   2972: aload #11
/*    */     //   2974: invokevirtual next : ()Ljava/lang/Object;
/*    */     //   2977: checkcast f/T0
/*    */     //   2980: dup
/*    */     //   2981: astore #12
/*    */     //   2983: getfield Xy0 : Ljava/lang/String;
/*    */     //   2986: ldc_w 'yomawaru_eye'
/*    */     //   2989: invokevirtual contains : (Ljava/lang/CharSequence;)Z
/*    */     //   2992: ifeq -> 2964
/*    */     //   2995: aload #9
/*    */     //   2997: getfield aH : Ljava/lang/String;
/*    */     //   3000: ldc_w 'yomawaru'
/*    */     //   3003: invokevirtual contains : (Ljava/lang/CharSequence;)Z
/*    */     //   3006: ifeq -> 2964
/*    */     //   3009: aload #4
/*    */     //   3011: aload #12
/*    */     //   3013: dup
/*    */     //   3014: new f/qo
/*    */     //   3017: dup
/*    */     //   3018: getstatic f/qo.cu0 : J
/*    */     //   3021: getstatic com/badlogic/gdx/graphics/Color.DARK_GRAY : Lcom/badlogic/gdx/graphics/Color;
/*    */     //   3024: invokespecial <init> : (JLcom/badlogic/gdx/graphics/Color;)V
/*    */     //   3027: invokevirtual Tz0 : (Lf/dj;)V
/*    */     //   3030: getfield Xy0 : Ljava/lang/String;
/*    */     //   3033: invokevirtual Com3 : (Ljava/lang/Object;)V
/*    */     //   3036: goto -> 2964
/*    */     //   3039: aload #10
/*    */     //   3041: ldc_w 'rhana'
/*    */     //   3044: invokevirtual contains : (Ljava/lang/CharSequence;)Z
/*    */     //   3047: ifne -> 3087
/*    */     //   3050: aload #10
/*    */     //   3052: ldc_w 'numa_'
/*    */     //   3055: invokevirtual startsWith : (Ljava/lang/String;)Z
/*    */     //   3058: ifeq -> 3075
/*    */     //   3061: aload #10
/*    */     //   3063: ldc_w 'numa_f'
/*    */     //   3066: invokevirtual startsWith : (Ljava/lang/String;)Z
/*    */     //   3069: ifne -> 3075
/*    */     //   3072: goto -> 3087
/*    */     //   3075: aload #6
/*    */     //   3077: getfield bz : Lf/Wd;
/*    */     //   3080: aconst_null
/*    */     //   3081: putfield jt : [I
/*    */     //   3084: goto -> 3293
/*    */     //   3087: aload_1
/*    */     //   3088: bipush #12
/*    */     //   3090: istore #11
/*    */     //   3092: bipush #41
/*    */     //   3094: istore #12
/*    */     //   3096: bipush #38
/*    */     //   3098: istore #13
/*    */     //   3100: getfield Zl0 : Ljava/lang/String;
/*    */     //   3103: ldc_w 'm_dun0301'
/*    */     //   3106: invokevirtual startsWith : (Ljava/lang/String;)Z
/*    */     //   3109: ifeq -> 3138
/*    */     //   3112: aload #10
/*    */     //   3114: ldc_w 'rhana'
/*    */     //   3117: invokevirtual contains : (Ljava/lang/CharSequence;)Z
/*    */     //   3120: ifeq -> 3138
/*    */     //   3123: bipush #53
/*    */     //   3125: istore #11
/*    */     //   3127: bipush #45
/*    */     //   3129: istore #12
/*    */     //   3131: bipush #47
/*    */     //   3133: istore #13
/*    */     //   3135: goto -> 3223
/*    */     //   3138: aload #10
/*    */     //   3140: ldc_w 'numa_b'
/*    */     //   3143: invokevirtual startsWith : (Ljava/lang/String;)Z
/*    */     //   3146: ifeq -> 3160
/*    */     //   3149: bipush #69
/*    */     //   3151: istore #12
/*    */     //   3153: bipush #66
/*    */     //   3155: istore #13
/*    */     //   3157: goto -> 3223
/*    */     //   3160: aload #10
/*    */     //   3162: ldc_w 'numa_c'
/*    */     //   3165: invokevirtual startsWith : (Ljava/lang/String;)Z
/*    */     //   3168: ifeq -> 3182
/*    */     //   3171: bipush #71
/*    */     //   3173: istore #12
/*    */     //   3175: bipush #68
/*    */     //   3177: istore #13
/*    */     //   3179: goto -> 3223
/*    */     //   3182: aload #10
/*    */     //   3184: ldc_w 'numa_d'
/*    */     //   3187: invokevirtual startsWith : (Ljava/lang/String;)Z
/*    */     //   3190: ifeq -> 3204
/*    */     //   3193: bipush #73
/*    */     //   3195: istore #12
/*    */     //   3197: bipush #70
/*    */     //   3199: istore #13
/*    */     //   3201: goto -> 3223
/*    */     //   3204: aload #10
/*    */     //   3206: ldc_w 'numa_e'
/*    */     //   3209: invokevirtual startsWith : (Ljava/lang/String;)Z
/*    */     //   3212: ifeq -> 3223
/*    */     //   3215: bipush #75
/*    */     //   3217: istore #12
/*    */     //   3219: bipush #72
/*    */     //   3221: istore #13
/*    */     //   3223: aload #6
/*    */     //   3225: aload_0
/*    */     //   3226: getstatic f/km.mI0 : Lf/P1;
/*    */     //   3229: getfield MT : Lf/gD;
/*    */     //   3232: getstatic f/VV.Dv0 : Lf/VV;
/*    */     //   3235: iload #11
/*    */     //   3237: invokevirtual oB : (Lf/VV;I)Lf/Wd;
/*    */     //   3240: astore #10
/*    */     //   3242: invokevirtual bO : ()B
/*    */     //   3245: aload #10
/*    */     //   3247: dup
/*    */     //   3248: getstatic f/L70.gq : Lf/L70;
/*    */     //   3251: invokevirtual fu : ()B
/*    */     //   3254: istore #10
/*    */     //   3256: getfield Va0 : Lf/Yy0;
/*    */     //   3259: iload #13
/*    */     //   3261: invokevirtual yO : (I)Lf/vO;
/*    */     //   3264: checkcast f/ZA0
/*    */     //   3267: getfield Vk : I
/*    */     //   3270: istore #13
/*    */     //   3272: iload #10
/*    */     //   3274: iload #11
/*    */     //   3276: iload #12
/*    */     //   3278: iload #13
/*    */     //   3280: invokestatic Ks0 : (BLf/Wd;IIII)[I
/*    */     //   3283: astore #10
/*    */     //   3285: getfield bz : Lf/Wd;
/*    */     //   3288: aload #10
/*    */     //   3290: putfield jt : [I
/*    */     //   3293: aload #4
/*    */     //   3295: invokevirtual isEmpty : ()Z
/*    */     //   3298: ifeq -> 3409
/*    */     //   3301: aload_1
/*    */     //   3302: getfield xl0 : Lf/fQ;
/*    */     //   3305: invokevirtual r30 : ()Lf/Hc0;
/*    */     //   3308: astore #10
/*    */     //   3310: aload #10
/*    */     //   3312: invokevirtual hasNext : ()Z
/*    */     //   3315: ifeq -> 3409
/*    */     //   3318: aload #10
/*    */     //   3320: invokevirtual next : ()Ljava/lang/Object;
/*    */     //   3323: checkcast f/T0
/*    */     //   3326: dup
/*    */     //   3327: astore #11
/*    */     //   3329: getfield Xy0 : Ljava/lang/String;
/*    */     //   3332: ldc_w '_'
/*    */     //   3335: invokevirtual split : (Ljava/lang/String;)[Ljava/lang/String;
/*    */     //   3338: dup
/*    */     //   3339: dup
/*    */     //   3340: astore #12
/*    */     //   3342: iconst_0
/*    */     //   3343: aaload
/*    */     //   3344: astore #13
/*    */     //   3346: arraylength
/*    */     //   3347: iconst_2
/*    */     //   3348: if_icmple -> 3380
/*    */     //   3351: aload #11
/*    */     //   3353: getfield Xy0 : Ljava/lang/String;
/*    */     //   3356: dup
/*    */     //   3357: invokevirtual length : ()I
/*    */     //   3360: aload #12
/*    */     //   3362: dup
/*    */     //   3363: arraylength
/*    */     //   3364: iconst_1
/*    */     //   3365: isub
/*    */     //   3366: aaload
/*    */     //   3367: invokevirtual length : ()I
/*    */     //   3370: isub
/*    */     //   3371: iconst_1
/*    */     //   3372: isub
/*    */     //   3373: iconst_0
/*    */     //   3374: swap
/*    */     //   3375: invokevirtual substring : (II)Ljava/lang/String;
/*    */     //   3378: astore #13
/*    */     //   3380: aload #13
/*    */     //   3382: aload #9
/*    */     //   3384: getfield aH : Ljava/lang/String;
/*    */     //   3387: invokevirtual equalsIgnoreCase : (Ljava/lang/String;)Z
/*    */     //   3390: ifne -> 3396
/*    */     //   3393: goto -> 3310
/*    */     //   3396: aload #4
/*    */     //   3398: aload #11
/*    */     //   3400: getfield Xy0 : Ljava/lang/String;
/*    */     //   3403: invokevirtual Com3 : (Ljava/lang/Object;)V
/*    */     //   3406: goto -> 3310
/*    */     //   3409: aload #4
/*    */     //   3411: invokevirtual isEmpty : ()Z
/*    */     //   3414: ifeq -> 3913
/*    */     //   3417: goto -> 2197
/*    */     //   3420: aload_0
/*    */     //   3421: invokevirtual bO : ()B
/*    */     //   3424: iconst_4
/*    */     //   3425: if_icmpne -> 3795
/*    */     //   3428: aload #10
/*    */     //   3430: ldc_w 'flower0'
/*    */     //   3433: invokevirtual startsWith : (Ljava/lang/String;)Z
/*    */     //   3436: ifeq -> 3567
/*    */     //   3439: getstatic f/L70.gq : Lf/L70;
/*    */     //   3442: dup
/*    */     //   3443: astore #11
/*    */     //   3445: invokevirtual fu : ()B
/*    */     //   3448: iconst_1
/*    */     //   3449: if_icmpeq -> 3555
/*    */     //   3452: aload #10
/*    */     //   3454: bipush #10
/*    */     //   3456: istore #10
/*    */     //   3458: bipush #26
/*    */     //   3460: istore #12
/*    */     //   3462: bipush #25
/*    */     //   3464: istore #13
/*    */     //   3466: ldc_w 'flower02'
/*    */     //   3469: invokevirtual equalsIgnoreCase : (Ljava/lang/String;)Z
/*    */     //   3472: ifeq -> 3483
/*    */     //   3475: bipush #27
/*    */     //   3477: istore #12
/*    */     //   3479: bipush #26
/*    */     //   3481: istore #13
/*    */     //   3483: aload #6
/*    */     //   3485: aload_0
/*    */     //   3486: getstatic f/km.mI0 : Lf/P1;
/*    */     //   3489: getfield yE : Lf/BE;
/*    */     //   3492: getstatic f/VV.Dv0 : Lf/VV;
/*    */     //   3495: iload #10
/*    */     //   3497: invokevirtual oB : (Lf/VV;I)Lf/Wd;
/*    */     //   3500: astore #10
/*    */     //   3502: invokevirtual bO : ()B
/*    */     //   3505: aload #10
/*    */     //   3507: dup
/*    */     //   3508: aload #11
/*    */     //   3510: invokevirtual fu : ()B
/*    */     //   3513: istore #10
/*    */     //   3515: getfield Va0 : Lf/Yy0;
/*    */     //   3518: iload #13
/*    */     //   3520: invokevirtual yO : (I)Lf/vO;
/*    */     //   3523: checkcast f/ZA0
/*    */     //   3526: getfield Vk : I
/*    */     //   3529: istore #11
/*    */     //   3531: iload #10
/*    */     //   3533: bipush #10
/*    */     //   3535: iload #12
/*    */     //   3537: iload #11
/*    */     //   3539: invokestatic Ks0 : (BLf/Wd;IIII)[I
/*    */     //   3542: astore #10
/*    */     //   3544: getfield bz : Lf/Wd;
/*    */     //   3547: aload #10
/*    */     //   3549: putfield jt : [I
/*    */     //   3552: goto -> 3659
/*    */     //   3555: aload #6
/*    */     //   3557: getfield bz : Lf/Wd;
/*    */     //   3560: aconst_null
/*    */     //   3561: putfield jt : [I
/*    */     //   3564: goto -> 3659
/*    */     //   3567: aload #10
/*    */     //   3569: ldc_w 'sea_rock'
/*    */     //   3572: invokevirtual equalsIgnoreCase : (Ljava/lang/String;)Z
/*    */     //   3575: ifeq -> 3659
/*    */     //   3578: aload_1
/*    */     //   3579: getfield xl0 : Lf/fQ;
/*    */     //   3582: invokevirtual r30 : ()Lf/Hc0;
/*    */     //   3585: astore #10
/*    */     //   3587: aload #10
/*    */     //   3589: invokevirtual hasNext : ()Z
/*    */     //   3592: ifeq -> 3659
/*    */     //   3595: aload #10
/*    */     //   3597: invokevirtual next : ()Ljava/lang/Object;
/*    */     //   3600: checkcast f/T0
/*    */     //   3603: dup
/*    */     //   3604: astore #11
/*    */     //   3606: getfield Xy0 : Ljava/lang/String;
/*    */     //   3609: ldc_w 'sea_rock'
/*    */     //   3612: invokevirtual equalsIgnoreCase : (Ljava/lang/String;)Z
/*    */     //   3615: ifne -> 3646
/*    */     //   3618: aload #11
/*    */     //   3620: getfield Xy0 : Ljava/lang/String;
/*    */     //   3623: ldc_w 'sea_rock_lm'
/*    */     //   3626: invokevirtual startsWith : (Ljava/lang/String;)Z
/*    */     //   3629: ifne -> 3646
/*    */     //   3632: aload #11
/*    */     //   3634: getfield Xy0 : Ljava/lang/String;
/*    */     //   3637: ldc_w 'dsea_rock'
/*    */     //   3640: invokevirtual equalsIgnoreCase : (Ljava/lang/String;)Z
/*    */     //   3643: ifeq -> 3587
/*    */     //   3646: aload #4
/*    */     //   3648: aload #11
/*    */     //   3650: getfield Xy0 : Ljava/lang/String;
/*    */     //   3653: invokevirtual Com3 : (Ljava/lang/Object;)V
/*    */     //   3656: goto -> 3587
/*    */     //   3659: aload #4
/*    */     //   3661: invokevirtual isEmpty : ()Z
/*    */     //   3664: ifeq -> 3913
/*    */     //   3667: aload_1
/*    */     //   3668: getfield xl0 : Lf/fQ;
/*    */     //   3671: invokevirtual r30 : ()Lf/Hc0;
/*    */     //   3674: astore #10
/*    */     //   3676: aload #10
/*    */     //   3678: invokevirtual hasNext : ()Z
/*    */     //   3681: ifeq -> 3913
/*    */     //   3684: aload #10
/*    */     //   3686: invokevirtual next : ()Ljava/lang/Object;
/*    */     //   3689: checkcast f/T0
/*    */     //   3692: dup
/*    */     //   3693: astore #11
/*    */     //   3695: getfield Xy0 : Ljava/lang/String;
/*    */     //   3698: aload #9
/*    */     //   3700: getfield aH : Ljava/lang/String;
/*    */     //   3703: invokevirtual equalsIgnoreCase : (Ljava/lang/String;)Z
/*    */     //   3706: ifeq -> 3712
/*    */     //   3709: goto -> 3782
/*    */     //   3712: aload #11
/*    */     //   3714: getfield Xy0 : Ljava/lang/String;
/*    */     //   3717: ldc_w '_'
/*    */     //   3720: invokevirtual split : (Ljava/lang/String;)[Ljava/lang/String;
/*    */     //   3723: dup
/*    */     //   3724: dup
/*    */     //   3725: astore #12
/*    */     //   3727: iconst_0
/*    */     //   3728: aaload
/*    */     //   3729: pop
/*    */     //   3730: arraylength
/*    */     //   3731: iconst_2
/*    */     //   3732: if_icmple -> 3763
/*    */     //   3735: aload #11
/*    */     //   3737: getfield Xy0 : Ljava/lang/String;
/*    */     //   3740: dup
/*    */     //   3741: invokevirtual length : ()I
/*    */     //   3744: aload #12
/*    */     //   3746: dup
/*    */     //   3747: arraylength
/*    */     //   3748: iconst_1
/*    */     //   3749: isub
/*    */     //   3750: aaload
/*    */     //   3751: invokevirtual length : ()I
/*    */     //   3754: isub
/*    */     //   3755: iconst_1
/*    */     //   3756: isub
/*    */     //   3757: iconst_0
/*    */     //   3758: swap
/*    */     //   3759: invokevirtual substring : (II)Ljava/lang/String;
/*    */     //   3762: pop
/*    */     //   3763: aload #11
/*    */     //   3765: getfield Xy0 : Ljava/lang/String;
/*    */     //   3768: aload #9
/*    */     //   3770: getfield aH : Ljava/lang/String;
/*    */     //   3773: invokevirtual equalsIgnoreCase : (Ljava/lang/String;)Z
/*    */     //   3776: ifne -> 3782
/*    */     //   3779: goto -> 3676
/*    */     //   3782: aload #4
/*    */     //   3784: aload #11
/*    */     //   3786: getfield Xy0 : Ljava/lang/String;
/*    */     //   3789: invokevirtual Com3 : (Ljava/lang/Object;)V
/*    */     //   3792: goto -> 3676
/*    */     //   3795: iconst_0
/*    */     //   3796: istore #11
/*    */     //   3798: iload #11
/*    */     //   3800: aload_2
/*    */     //   3801: getfield p3 : Lf/fQ;
/*    */     //   3804: dup
/*    */     //   3805: astore #12
/*    */     //   3807: getfield Z8 : I
/*    */     //   3810: if_icmpge -> 3874
/*    */     //   3813: aload #12
/*    */     //   3815: iload #11
/*    */     //   3817: invokevirtual get : (I)Ljava/lang/Object;
/*    */     //   3820: checkcast f/tC
/*    */     //   3823: dup
/*    */     //   3824: astore #12
/*    */     //   3826: getfield JZ : Ljava/lang/String;
/*    */     //   3829: dup
/*    */     //   3830: astore #13
/*    */     //   3832: ifnonnull -> 3838
/*    */     //   3835: goto -> 3868
/*    */     //   3838: aload #13
/*    */     //   3840: aload #10
/*    */     //   3842: invokevirtual contains : (Ljava/lang/CharSequence;)Z
/*    */     //   3845: ifeq -> 3868
/*    */     //   3848: aload #12
/*    */     //   3850: aload #4
/*    */     //   3852: aload #12
/*    */     //   3854: getfield Ih : Ljava/lang/String;
/*    */     //   3857: invokevirtual Com3 : (Ljava/lang/Object;)V
/*    */     //   3860: getfield JZ : Ljava/lang/String;
/*    */     //   3863: astore #10
/*    */     //   3865: goto -> 3874
/*    */     //   3868: iinc #11, 1
/*    */     //   3871: goto -> 3798
/*    */     //   3874: ldc_w 'sea_simi'
/*    */     //   3877: aload #10
/*    */     //   3879: invokevirtual contains : (Ljava/lang/CharSequence;)Z
/*    */     //   3882: ifne -> 2197
/*    */     //   3885: aload #10
/*    */     //   3887: aload #6
/*    */     //   3889: getfield bz : Lf/Wd;
/*    */     //   3892: getfield K5 : Lf/Nn;
/*    */     //   3895: invokevirtual W5 : ()Lf/Q70;
/*    */     //   3898: invokevirtual next : ()Ljava/lang/Object;
/*    */     //   3901: checkcast java/lang/CharSequence
/*    */     //   3904: invokevirtual contains : (Ljava/lang/CharSequence;)Z
/*    */     //   3907: ifne -> 3913
/*    */     //   3910: goto -> 2197
/*    */     //   3913: aload_0
/*    */     //   3914: invokevirtual bO : ()B
/*    */     //   3917: iconst_2
/*    */     //   3918: if_icmpne -> 3948
/*    */     //   3921: aload #4
/*    */     //   3923: getfield Z8 : I
/*    */     //   3926: ifle -> 3948
/*    */     //   3929: aload #9
/*    */     //   3931: getfield fc0 : I
/*    */     //   3934: ldc_w 1552476462
/*    */     //   3937: if_icmpne -> 3948
/*    */     //   3940: aload #4
/*    */     //   3942: ldc_w 'denki_2'
/*    */     //   3945: invokevirtual Com3 : (Ljava/lang/Object;)V
/*    */     //   3948: aload #4
/*    */     //   3950: aload #6
/*    */     //   3952: getfield bz : Lf/Wd;
/*    */     //   3955: aload #6
/*    */     //   3957: dup
/*    */     //   3958: aload #9
/*    */     //   3960: dup
/*    */     //   3961: getfield ZP : Lf/fQ;
/*    */     //   3964: astore #9
/*    */     //   3966: getfield ej : Lf/fQ;
/*    */     //   3969: astore #10
/*    */     //   3971: getfield EB0 : Lf/fQ;
/*    */     //   3974: astore #11
/*    */     //   3976: getfield wr : Lf/fQ;
/*    */     //   3979: astore #12
/*    */     //   3981: aload #9
/*    */     //   3983: aload #10
/*    */     //   3985: aload #11
/*    */     //   3987: aload #12
/*    */     //   3989: aload_3
/*    */     //   3990: iconst_0
/*    */     //   3991: invokestatic qY : (Lf/Wd;Lf/fQ;Lf/fQ;Lf/fQ;Lf/fQ;Lf/Ew;Z)[Lf/pe0;
/*    */     //   3994: astore #9
/*    */     //   3996: invokevirtual r30 : ()Lf/Hc0;
/*    */     //   3999: astore #10
/*    */     //   4001: aload #10
/*    */     //   4003: invokevirtual hasNext : ()Z
/*    */     //   4006: ifeq -> 2197
/*    */     //   4009: aload_1
/*    */     //   4010: aload #10
/*    */     //   4012: invokevirtual next : ()Ljava/lang/Object;
/*    */     //   4015: checkcast java/lang/String
/*    */     //   4018: ldc_w 'ow'
/*    */     //   4021: swap
/*    */     //   4022: fload #7
/*    */     //   4024: aload #9
/*    */     //   4026: iconst_1
/*    */     //   4027: invokevirtual rq : (Ljava/lang/String;Ljava/lang/String;F[Lf/pe0;Z)V
/*    */     //   4030: goto -> 4001
/*    */     //   4033: return
/*    */     // Line number table:
/*    */     //   Java source line number -> byte code offset
/*    */     //   #1	-> 11
/*    */     //   #2	-> 24
/*    */     //   #3	-> 30
/*    */     //   #4	-> 33
/*    */     //   #5	-> 56
/*    */     //   #6	-> 59
/*    */     //   #7	-> 68
/*    */     //   #8	-> 71
/*    */     //   #9	-> 75
/*    */     //   #10	-> 81
/*    */     //   #11	-> 92
/*    */     //   #12	-> 110
/*    */     //   #13	-> 115
/*    */     //   #14	-> 131
/*    */     //   #15	-> 136
/*    */     //   #16	-> 174
/*    */     //   #17	-> 184
/*    */     //   #18	-> 198
/*    */     //   #19	-> 228
/*    */     //   #20	-> 255
/*    */     //   #21	-> 260
/*    */     //   #22	-> 269
/*    */     //   #23	-> 359
/*    */     //   #24	-> 374
/*    */     //   #25	-> 391
/*    */     //   #26	-> 395
/*    */     //   #27	-> 408
/*    */     //   #28	-> 414
/*    */     //   #29	-> 429
/*    */     //   #30	-> 432
/*    */     //   #31	-> 442
/*    */     //   #32	-> 445
/*    */     //   #33	-> 449
/*    */     //   #34	-> 455
/*    */     //   #35	-> 466
/*    */     //   #36	-> 484
/*    */     //   #37	-> 489
/*    */     //   #38	-> 505
/*    */     //   #39	-> 510
/*    */     //   #40	-> 548
/*    */     //   #41	-> 558
/*    */     //   #42	-> 572
/*    */     //   #43	-> 602
/*    */     //   #44	-> 629
/*    */     //   #45	-> 634
/*    */     //   #46	-> 643
/*    */     //   #47	-> 733
/*    */     //   #48	-> 748
/*    */     //   #49	-> 765
/*    */     //   #50	-> 769
/*    */     //   #51	-> 782
/*    */     //   #52	-> 788
/*    */     //   #53	-> 791
/*    */     //   #54	-> 1093
/*    */     //   #55	-> 1099
/*    */     //   #56	-> 1102
/*    */     //   #57	-> 1125
/*    */     //   #58	-> 1128
/*    */     //   #59	-> 1138
/*    */     //   #60	-> 1141
/*    */     //   #61	-> 1145
/*    */     //   #62	-> 1151
/*    */     //   #63	-> 1162
/*    */     //   #64	-> 1180
/*    */     //   #65	-> 1185
/*    */     //   #66	-> 1201
/*    */     //   #67	-> 1206
/*    */     //   #68	-> 1244
/*    */     //   #69	-> 1254
/*    */     //   #70	-> 1268
/*    */     //   #71	-> 1298
/*    */     //   #72	-> 1325
/*    */     //   #73	-> 1330
/*    */     //   #74	-> 1342
/*    */     //   #75	-> 1894
/*    */     //   #76	-> 1898
/*    */     //   #77	-> 1911
/*    */     //   #78	-> 1917
/*    */     //   #79	-> 2154
/*    */     //   #80	-> 3081
/*    */     //   #81	-> 3100
/*    */     //   #82	-> 3248
/*    */     //   #83	-> 3251
/*    */     //   #84	-> 3290
/*    */     //   #85	-> 3295
/*    */     //   #86	-> 3439
/*    */     //   #87	-> 3445
/*    */     //   #88	-> 3549
/*    */     //   #89	-> 3557
/*    */     //   #90	-> 3561
/*    */     //   #91	-> 3569
/*    */     // Exception table:
/*    */     //   from	to	target	type
/*    */     //   1428	1431	1448	java/lang/Exception
/*    */     //   1434	1441	1448	java/lang/Exception } public static ZH ok0(Wd paramWd, String paramString1, String paramString2) { Integer integer1 = (Integer)paramWd.K5.pd0(paramString1); Integer integer2; if ((integer2 = (Integer)paramWd.zg0.pd0(paramString2)) == null || integer1 == null) { zi.error("Couldn't find " + paramString1 + " or " + paramString2); return null; }  int i = integer1.intValue(); return paramWd.bI(i, integer2.intValue()); } public static pe0[] qY(Wd paramWd, fQ paramfQ1, fQ paramfQ2, fQ paramfQ3, fQ paramfQ4, Ew paramEw, boolean paramBoolean) { // Byte code:
/*    */     //   0: aload #4
/*    */     //   2: ifnonnull -> 311
/*    */     //   5: new java/util/HashMap
/*    */     //   8: dup
/*    */     //   9: astore #4
/*    */     //   11: invokespecial <init> : ()V
/*    */     //   14: iconst_0
/*    */     //   15: istore #7
/*    */     //   17: iload #7
/*    */     //   19: aload_1
/*    */     //   20: getfield Z8 : I
/*    */     //   23: dup
/*    */     //   24: istore #8
/*    */     //   26: if_icmpge -> 243
/*    */     //   29: aload_2
/*    */     //   30: getfield Z8 : I
/*    */     //   33: iload #8
/*    */     //   35: if_icmpne -> 45
/*    */     //   38: iload #7
/*    */     //   40: istore #8
/*    */     //   42: goto -> 48
/*    */     //   45: iconst_0
/*    */     //   46: istore #8
/*    */     //   48: aload_0
/*    */     //   49: aload_1
/*    */     //   50: iload #7
/*    */     //   52: aload_2
/*    */     //   53: iload #8
/*    */     //   55: invokevirtual get : (I)Ljava/lang/Object;
/*    */     //   58: checkcast java/lang/String
/*    */     //   61: astore #8
/*    */     //   63: invokevirtual get : (I)Ljava/lang/Object;
/*    */     //   66: checkcast java/lang/String
/*    */     //   69: dup
/*    */     //   70: astore #9
/*    */     //   72: aload #8
/*    */     //   74: invokestatic ok0 : (Lf/Wd;Ljava/lang/String;Ljava/lang/String;)Lf/ZH;
/*    */     //   77: dup
/*    */     //   78: astore #10
/*    */     //   80: ifnonnull -> 128
/*    */     //   83: getstatic f/eI.zi : Lf/ik;
/*    */     //   86: new java/lang/StringBuilder
/*    */     //   89: dup
/*    */     //   90: invokespecial <init> : ()V
/*    */     //   93: ldc_w 'Couldn't create simple animation pixmap from '
/*    */     //   96: invokevirtual append : (Ljava/lang/String;)Ljava/lang/StringBuilder;
/*    */     //   99: aload #9
/*    */     //   101: invokevirtual append : (Ljava/lang/String;)Ljava/lang/StringBuilder;
/*    */     //   104: ldc_w ' / '
/*    */     //   107: invokevirtual append : (Ljava/lang/String;)Ljava/lang/StringBuilder;
/*    */     //   110: aload #8
/*    */     //   112: invokevirtual append : (Ljava/lang/String;)Ljava/lang/StringBuilder;
/*    */     //   115: invokevirtual toString : ()Ljava/lang/String;
/*    */     //   118: invokeinterface error : (Ljava/lang/String;)V
/*    */     //   123: aconst_null
/*    */     //   124: astore_0
/*    */     //   125: goto -> 309
/*    */     //   128: iload #6
/*    */     //   130: ifeq -> 144
/*    */     //   133: aload #10
/*    */     //   135: dup
/*    */     //   136: invokestatic hY : (Lf/ZH;)Lf/ZH;
/*    */     //   139: astore #10
/*    */     //   141: invokevirtual dispose : ()V
/*    */     //   144: aload #5
/*    */     //   146: new com/badlogic/gdx/graphics/Texture
/*    */     //   149: dup
/*    */     //   150: dup
/*    */     //   151: astore #8
/*    */     //   153: new f/AB
/*    */     //   156: dup
/*    */     //   157: aload #10
/*    */     //   159: aconst_null
/*    */     //   160: iconst_0
/*    */     //   161: iconst_0
/*    */     //   162: iconst_0
/*    */     //   163: invokespecial <init> : (Lf/ZH;Lf/Uc;ZZZ)V
/*    */     //   166: invokespecial <init> : (Lf/Bu0;)V
/*    */     //   169: getstatic f/cu0.Fh : Lf/cu0;
/*    */     //   172: dup
/*    */     //   173: invokevirtual setFilter : (Lf/cu0;Lf/cu0;)V
/*    */     //   176: getfield Ro : Lf/fQ;
/*    */     //   179: ifnonnull -> 198
/*    */     //   182: aload #5
/*    */     //   184: new f/fQ
/*    */     //   187: dup
/*    */     //   188: astore #9
/*    */     //   190: invokespecial <init> : ()V
/*    */     //   193: aload #9
/*    */     //   195: putfield Ro : Lf/fQ;
/*    */     //   198: iload #7
/*    */     //   200: aload #10
/*    */     //   202: aload #4
/*    */     //   204: iload #7
/*    */     //   206: aload #5
/*    */     //   208: getfield Ro : Lf/fQ;
/*    */     //   211: aload #8
/*    */     //   213: invokevirtual Com3 : (Ljava/lang/Object;)V
/*    */     //   216: invokestatic valueOf : (B)Ljava/lang/Byte;
/*    */     //   219: new f/pe0
/*    */     //   222: dup
/*    */     //   223: aload #8
/*    */     //   225: invokespecial <init> : (Lcom/badlogic/gdx/graphics/Texture;)V
/*    */     //   228: invokevirtual put : (Ljava/lang/Object;Ljava/lang/Object;)Ljava/lang/Object;
/*    */     //   231: pop
/*    */     //   232: invokevirtual dispose : ()V
/*    */     //   235: iconst_1
/*    */     //   236: iadd
/*    */     //   237: i2b
/*    */     //   238: istore #7
/*    */     //   240: goto -> 17
/*    */     //   243: aload_3
/*    */     //   244: ifnonnull -> 268
/*    */     //   247: aload #4
/*    */     //   249: invokevirtual values : ()Ljava/util/Collection;
/*    */     //   252: iconst_0
/*    */     //   253: anewarray f/pe0
/*    */     //   256: invokeinterface toArray : ([Ljava/lang/Object;)[Ljava/lang/Object;
/*    */     //   261: checkcast [Lf/pe0;
/*    */     //   264: astore_0
/*    */     //   265: goto -> 309
/*    */     //   268: aload_3
/*    */     //   269: getfield Z8 : I
/*    */     //   272: dup
/*    */     //   273: istore_0
/*    */     //   274: anewarray f/pe0
/*    */     //   277: astore_1
/*    */     //   278: iconst_0
/*    */     //   279: istore_2
/*    */     //   280: iload_2
/*    */     //   281: iload_0
/*    */     //   282: if_icmpge -> 307
/*    */     //   285: aload_1
/*    */     //   286: iload_2
/*    */     //   287: aload #4
/*    */     //   289: aload_3
/*    */     //   290: iload_2
/*    */     //   291: invokevirtual get : (I)Ljava/lang/Object;
/*    */     //   294: invokevirtual get : (Ljava/lang/Object;)Ljava/lang/Object;
/*    */     //   297: checkcast f/pe0
/*    */     //   300: aastore
/*    */     //   301: iinc #2, 1
/*    */     //   304: goto -> 280
/*    */     //   307: aload_1
/*    */     //   308: astore_0
/*    */     //   309: aload_0
/*    */     //   310: areturn
/*    */     //   311: aload #4
/*    */     //   313: new java/util/HashMap
/*    */     //   316: dup
/*    */     //   317: astore_3
/*    */     //   318: invokespecial <init> : ()V
/*    */     //   321: invokevirtual r30 : ()Lf/Hc0;
/*    */     //   324: astore #7
/*    */     //   326: aload #7
/*    */     //   328: invokevirtual hasNext : ()Z
/*    */     //   331: ifeq -> 537
/*    */     //   334: aload_0
/*    */     //   335: aload_2
/*    */     //   336: aload_1
/*    */     //   337: aload #7
/*    */     //   339: invokevirtual next : ()Ljava/lang/Object;
/*    */     //   342: checkcast f/Gc0
/*    */     //   345: dup
/*    */     //   346: astore #8
/*    */     //   348: getfield oz0 : B
/*    */     //   351: invokevirtual get : (I)Ljava/lang/Object;
/*    */     //   354: checkcast java/lang/String
/*    */     //   357: astore #9
/*    */     //   359: aload #8
/*    */     //   361: getfield Wq : B
/*    */     //   364: invokevirtual get : (I)Ljava/lang/Object;
/*    */     //   367: checkcast java/lang/String
/*    */     //   370: astore #10
/*    */     //   372: aload #9
/*    */     //   374: aload #10
/*    */     //   376: invokestatic ok0 : (Lf/Wd;Ljava/lang/String;Ljava/lang/String;)Lf/ZH;
/*    */     //   379: dup
/*    */     //   380: astore #11
/*    */     //   382: ifnonnull -> 427
/*    */     //   385: getstatic f/eI.zi : Lf/ik;
/*    */     //   388: new java/lang/StringBuilder
/*    */     //   391: dup
/*    */     //   392: invokespecial <init> : ()V
/*    */     //   395: ldc_w 'Couldn't create texture animation pixmap from '
/*    */     //   398: invokevirtual append : (Ljava/lang/String;)Ljava/lang/StringBuilder;
/*    */     //   401: aload #9
/*    */     //   403: invokevirtual append : (Ljava/lang/String;)Ljava/lang/StringBuilder;
/*    */     //   406: ldc_w ' / '
/*    */     //   409: invokevirtual append : (Ljava/lang/String;)Ljava/lang/StringBuilder;
/*    */     //   412: aload #10
/*    */     //   414: invokevirtual append : (Ljava/lang/String;)Ljava/lang/StringBuilder;
/*    */     //   417: invokevirtual toString : ()Ljava/lang/String;
/*    */     //   420: invokeinterface error : (Ljava/lang/String;)V
/*    */     //   425: aconst_null
/*    */     //   426: areturn
/*    */     //   427: iload #6
/*    */     //   429: ifeq -> 443
/*    */     //   432: aload #11
/*    */     //   434: dup
/*    */     //   435: invokestatic hY : (Lf/ZH;)Lf/ZH;
/*    */     //   438: astore #11
/*    */     //   440: invokevirtual dispose : ()V
/*    */     //   443: aload #5
/*    */     //   445: new com/badlogic/gdx/graphics/Texture
/*    */     //   448: dup
/*    */     //   449: dup
/*    */     //   450: astore #9
/*    */     //   452: new f/AB
/*    */     //   455: dup
/*    */     //   456: aload #11
/*    */     //   458: aconst_null
/*    */     //   459: iconst_0
/*    */     //   460: iconst_0
/*    */     //   461: iconst_0
/*    */     //   462: invokespecial <init> : (Lf/ZH;Lf/Uc;ZZZ)V
/*    */     //   465: invokespecial <init> : (Lf/Bu0;)V
/*    */     //   468: getstatic f/cu0.Fh : Lf/cu0;
/*    */     //   471: dup
/*    */     //   472: invokevirtual setFilter : (Lf/cu0;Lf/cu0;)V
/*    */     //   475: getfield Ro : Lf/fQ;
/*    */     //   478: ifnonnull -> 497
/*    */     //   481: aload #5
/*    */     //   483: new f/fQ
/*    */     //   486: dup
/*    */     //   487: astore #10
/*    */     //   489: invokespecial <init> : ()V
/*    */     //   492: aload #10
/*    */     //   494: putfield Ro : Lf/fQ;
/*    */     //   497: aload #11
/*    */     //   499: aload_3
/*    */     //   500: aload #8
/*    */     //   502: aload #5
/*    */     //   504: getfield Ro : Lf/fQ;
/*    */     //   507: aload #9
/*    */     //   509: invokevirtual Com3 : (Ljava/lang/Object;)V
/*    */     //   512: getfield oz0 : B
/*    */     //   515: invokestatic valueOf : (B)Ljava/lang/Byte;
/*    */     //   518: new f/pe0
/*    */     //   521: dup
/*    */     //   522: aload #9
/*    */     //   524: invokespecial <init> : (Lcom/badlogic/gdx/graphics/Texture;)V
/*    */     //   527: invokevirtual put : (Ljava/lang/Object;Ljava/lang/Object;)Ljava/lang/Object;
/*    */     //   530: pop
/*    */     //   531: invokevirtual dispose : ()V
/*    */     //   534: goto -> 326
/*    */     //   537: aload #4
/*    */     //   539: new f/fQ
/*    */     //   542: dup
/*    */     //   543: astore_0
/*    */     //   544: invokespecial <init> : ()V
/*    */     //   547: iconst_0
/*    */     //   548: istore_1
/*    */     //   549: invokevirtual r30 : ()Lf/Hc0;
/*    */     //   552: astore_2
/*    */     //   553: aload_2
/*    */     //   554: invokevirtual hasNext : ()Z
/*    */     //   557: ifeq -> 609
/*    */     //   560: aload_2
/*    */     //   561: invokevirtual next : ()Ljava/lang/Object;
/*    */     //   564: checkcast f/Gc0
/*    */     //   567: astore #4
/*    */     //   569: iload_1
/*    */     //   570: aload #4
/*    */     //   572: getfield LB : S
/*    */     //   575: dup
/*    */     //   576: istore #5
/*    */     //   578: if_icmpgt -> 603
/*    */     //   581: aload_0
/*    */     //   582: aload_3
/*    */     //   583: aload #4
/*    */     //   585: getfield oz0 : B
/*    */     //   588: invokestatic valueOf : (B)Ljava/lang/Byte;
/*    */     //   591: invokevirtual get : (Ljava/lang/Object;)Ljava/lang/Object;
/*    */     //   594: invokevirtual Com3 : (Ljava/lang/Object;)V
/*    */     //   597: iinc #1, 1
/*    */     //   600: goto -> 569
/*    */     //   603: iload #5
/*    */     //   605: istore_1
/*    */     //   606: goto -> 553
/*    */     //   609: aload_0
/*    */     //   610: ldc_w f/pe0
/*    */     //   613: invokevirtual Ib : (Ljava/lang/Class;)[Ljava/lang/Object;
/*    */     //   616: checkcast [Lf/pe0;
/*    */     //   619: areturn
/*    */     // Line number table:
/*    */     //   Java source line number -> byte code offset
/*    */     //   #1	-> 5
/*    */     //   #2	-> 146
/*    */     //   #3	-> 176
/*    */     //   #4	-> 184
/*    */     //   #5	-> 216
/*    */     //   #6	-> 313
/*    */     //   #7	-> 445
/*    */     //   #8	-> 475
/*    */     //   #9	-> 483
/* 10 */     //   #10	-> 512 } public static lpt1 L4(S paramS, int paramInt, int... paramVarArgs) { return QO(paramS, paramInt, true, false, false, paramVarArgs); } public static void aI(lpt1 paramlpt1, Wd paramWd, Ew paramEw, fQ paramfQ) { ei ei; if (paramfQ != null && ((ei = km.ln) == null || (ei.tn.isEmpty() ^ true) == 0)) for (Hc0 hc0 = paramfQ.r30(); hc0.hasNext(); ) { IK0 iK0; (iK0 = (IK0)hc0.next()).getClass(); if ((IK0)hc0.next() instanceof eB) for (Hc0 hc01 = ((eB)iK0).tW.r30(); hc01.hasNext();) { label135: for (hc02 = (iG = (iG)hc01.next()).Uj0.r30(); hc02.hasNext(); ) { HashMap<Object, Object> hashMap; fQ fQ2; Sh sh = (Sh)hc02.next(); L70 l70; int i; if (!(((l70 = L70.gq).fu() == 1) ? 1 : 0) && ((i = paramlpt1.YZ) == 1778373671 || i == 1778373672 || i == 1778373673 || i == 1778403462 || i == 1778403463 || i == 1778403464) && iG.Ih.equalsIgnoreCase("ushadow_ani")) { i = paramEw.td0; int n = sh.Ih.hashCode(); byte b2 = -1, b3 = -1; int i1; switch (i1 = paramlpt1.YZ) { default: switch (i1) { default: break;case 1778403462: case 1778403463: case 1778403464: break; } case 1778373672: if (n != -1644313926 && n != -1644313895) { switch (n) { default: break;case -1854157706: case -1854157705: case -1854157704: case -1854157703: case -1854157702: case -1854157701: break; }  b2 = 1; b3 = 4; break; }  b2 = 11; b3 = 2; break;case 1778373671: switch (n) { default: break;case -1644313957: case -1644313926: case -1644313895: case -1644313833: b2 = 17; b3 = 6; break;case -1854157706: case -1854157705: case -1854157704: case -1854157703: case -1854157701: break; }  b2 = 1; b3 = 8; break;case 1778373673: switch (n) { default: break;case -1854157706: case -1854157705: case -1854157704: case -1854157703: case -1854157702: case -1854157701: break; }  b2 = 3; b3 = 2; break; }
/* 11 */                  byte b1 = l70.fu(); Yy0 yy0;
/* 12 */                 if (b2 > 0 && b3 < (yy0 = paramWd.Va0).ai0
/* 13 */                   .Z8 && b2 < 
/*    */                   
/* 15 */                   paramWd.TE.ai0
/* 16 */                   .Z8)
/* 17 */                 { int i2 = (yy0.yO(b3)).Vk; if (IW.jF((byte)4, b1, i, i2)) { i2 = (paramWd.Va0.yO(b3)).Vk; paramWd
/* 18 */                       .jt = IW.Ks0((byte)4, paramWd, b1, i, b2, i2); }  }  }
/* 19 */                String str = sh.Ih;
/* 20 */               this(); fQ fQ1; for (Hc0 hc03 = (fQ1 = sh.VD).r30(); hc03.hasNext(); ) { Texture texture; Gc0 gc0 = (Gc0)hc03.next(); String str1, str2; ZH zH; if ((zH = ok0(paramWd, str1 = (String)iG.Ba0.get(gc0.oz0), str2 = (String)iG.rn.get(gc0.Wq))) == null) { zi.error("Couldn't create texture animation pixmap from " + str1 + " / " + str2); fQ1 = null; continue label135; }
/* 21 */                  this(new AB(zH, null, false, false, false)); (new Texture()).setFilter(cu0.Fh, cu0.Fh);
/* 22 */                 if (paramEw.Ro == null)
/* 23 */                 { fQ fQ3; this(); paramEw.Ro = fQ3; }  paramEw.Ro.Com3(texture); hashMap
/* 24 */                   .put(Byte.valueOf(gc0.oz0), new pe0(texture)); zH.dispose(); }  int j = 0; this(); int k = iG.oO; if (fQ1.Z8 > 1) k = ((Gc0)fQ1.get(1)).LB;  int m; for (byte b = 0; b < (m = iG.oO); ) { if (b >= k) if ((k = ++j + 1) < fQ1.Z8) { k = ((Gc0)fQ1.get(k)).LB; } else { k = m; }   if (j >= fQ1.Z8) { zi.error("out of bounds for fv data animation"); break; }  fQ2.Com3(hashMap.get(Byte.valueOf(((Gc0)fQ1.get(j)).oz0))); b++; }  pe0[] arrayOfPe0 = (pe0[])fQ2.Ib(pe0.class); paramlpt1
/* 25 */                 .rq(iG.Ih, str, 0.033333335F, arrayOfPe0, false); }  }   if (iK0 instanceof uv)
/*    */         {
/* 27 */           for (Hc0 hc01 = ((uv)iK0).v9.r30(); hc01.hasNext();) { for (Hc0 hc02 = (xe = (xe)hc01.next()).w4.r30(); hc02.hasNext(); ) { yn yn; String str = (yn = (yn)hc02.next()).Ih; Z30[] arrayOfZ30 = Z30.FC(xe.EF0, yn); paramlpt1.dA(xe.Ih, str, 0.05F, arrayOfZ30, false); }  }  }  if (iK0 instanceof tq0)
/*    */         {
/* 29 */           for (Hc0 hc01 = ((tq0)iK0).D2.r30(); hc01.hasNext(); ) { String str = ((VH0)hc01.next()).Ih; int i = ((VH0)hc01.next()).IC0; fQ fQ1 = ((VH0)hc01.next()).X20; if (paramlpt1
/* 30 */               .hI == null)
/* 31 */             { HashMap<Object, Object> hashMap; this(); paramlpt1.hI = hashMap; }  if (fQ1 == null) continue;  if (paramlpt1.hI.get(str) == null) { NY nY; this(); paramlpt1.hI.put(str, nY); paramlpt1.lz.Com3(str); }  for (Hc0 hc02 = fQ1.r30(); hc02.hasNext(); ) { xX xX; Dw dw; Yf0[] arrayOfYf0; byte b; for (dw = (Dw)hc02.next(), arrayOfYf0 = new Yf0[i], b = 0; b < i; )
/* 32 */               { long l1 = dw.lt;
/* 33 */                 int[] arrayOfInt1 = dw.Ck0;
/* 34 */                 long l2 = dw.UW; int arrayOfInt2[] = dw.uh, k = Dw.ge(dw.Nn, b, l2, arrayOfInt2);
/* 35 */                 long l3 = dw.II; int arrayOfInt3[] = dw.lPT3, m = Dw.ge(dw.RF0, b, l3, arrayOfInt3);
/* 36 */                 long l4 = dw.G0; int arrayOfInt4[] = dw.sL, n = Dw.ge(dw.T00, b, l4, arrayOfInt4);
/* 37 */                 Yf0 yf0 = new Yf0();
/* 38 */                 long l5 = dw.ow0; int arrayOfInt5[] = dw.Yv0, i1 = Dw.ge(dw.XB0, b, l5, arrayOfInt5); int j; if ((j = Dw.ge(dw.p00, b, l1, arrayOfInt1)) != -1)
/* 39 */                 { j = dL.AC0(j); } else { j = -1; }  if (k != -1) { k = dL.AC0(k); } else { k = -1; }  if (m != -1) { m = dL.AC0(m); } else { m = -1; }  if (n != -1) { n = dL.AC0(n); } else { n = -1; }  this(i1, j, k, m, n); arrayOfYf0[b] = yf0; b++; }  this(dw.Ih, arrayOfYf0); ((NY)paramlpt1.hI.get(str)).x7.Com3(xX); }
/*    */              }
/*    */            }  }
/*    */         }
/*    */ 
/*    */   
/*    */   public static lpt1 QO(S paramS, int paramInt, boolean paramBoolean1, boolean paramBoolean2, boolean paramBoolean3, int... paramVarArgs) {
/*    */     try {
/*    */       fQ fQ;
/*    */       Q1 q1 = Q1.tB(paramS.Em0(paramInt).rb(false));
/*    */       this(1);
/*    */       if (paramVarArgs != null) {
/*    */         int i;
/*    */         byte b;
/*    */         for (i = paramVarArgs.length, b = 0; b < i; ) {
/*    */           IK0 iK0;
/*    */           int j;
/*    */           if ((j = paramVarArgs[b]) >= 0 && j < paramS.size() && (iK0 = IK0.qB0(paramS.Em0(j).rb(false))) != null)
/*    */             fQ.Com3(iK0); 
/*    */           b++;
/*    */         } 
/*    */       } 
/*    */       eI eI1 = Lj();
/*    */       Wd wd = q1.Qo0;
/*    */       float f = 1.0F;
/*    */       eI1.getClass();
/*    */       return Gy(q1.Nt[0], wd, fQ, f, paramBoolean1, paramBoolean3, paramBoolean2);
/*    */     } catch (Exception exception) {
/*    */       zi.error("convert error", exception);
/*    */       return null;
/*    */     } 
/*    */   }
/*    */   
/*    */   public static lpt1 Jc(hC paramhC, Wd paramWd, fQ paramfQ) {
/*    */     return Gy(paramhC, paramWd, paramfQ, 1.0F, true, false, false);
/*    */   }
/*    */   
/*    */   public static lpt1 T40(hC paramhC, KB0 paramKB0, boolean paramBoolean) {
/*    */     DG0(paramhC, paramKB0.Ag);
/*    */     paramKB0.QI0(paramhC);
/*    */     Ew ew = paramKB0.Db0;
/*    */     return Q9(paramhC, ew, paramKB0.Ag, null, 1.0F, paramBoolean, false);
/*    */   }
/*    */   
/*    */   public static lpt1 Gy(hC paramhC, Wd paramWd, fQ paramfQ, float paramFloat, boolean paramBoolean1, boolean paramBoolean2, boolean paramBoolean3) {
/*    */     this((byte)-1, paramhC, paramWd);
/*    */     Iq iq;
/*    */     DG0(paramhC, paramWd);
/*    */     return Q9(paramhC, iq, paramWd, paramfQ, paramFloat, paramBoolean1, paramBoolean3);
/*    */   }
/*    */   
/*    */   public static lpt1 Q9(hC paramhC, Ew paramEw, Wd paramWd, fQ paramfQ, float paramFloat, boolean paramBoolean1, boolean paramBoolean2) {
/*    */     // Byte code:
/*    */     //   0: getstatic f/eI.cR : Lf/is0;
/*    */     //   3: dup
/*    */     //   4: dup
/*    */     //   5: astore #4
/*    */     //   7: getfield pm : Lf/gv0;
/*    */     //   10: invokevirtual WU : ()Lcom/badlogic/gdx/math/Matrix4;
/*    */     //   13: pop
/*    */     //   14: getfield pm : Lf/gv0;
/*    */     //   17: dup
/*    */     //   18: iconst_0
/*    */     //   19: putfield Jb : I
/*    */     //   22: getfield Yo : Lf/fQ;
/*    */     //   25: invokevirtual clear : ()V
/*    */     //   28: iconst_0
/*    */     //   29: istore #7
/*    */     //   31: iload #7
/*    */     //   33: aload #4
/*    */     //   35: getfield kK0 : [Lf/gv0;
/*    */     //   38: dup
/*    */     //   39: astore #8
/*    */     //   41: arraylength
/*    */     //   42: if_icmpge -> 79
/*    */     //   45: aload #4
/*    */     //   47: aload #8
/*    */     //   49: iload #7
/*    */     //   51: aaload
/*    */     //   52: invokevirtual WU : ()Lcom/badlogic/gdx/math/Matrix4;
/*    */     //   55: pop
/*    */     //   56: getfield kK0 : [Lf/gv0;
/*    */     //   59: iload #7
/*    */     //   61: aaload
/*    */     //   62: dup
/*    */     //   63: iconst_0
/*    */     //   64: putfield Jb : I
/*    */     //   67: getfield Yo : Lf/fQ;
/*    */     //   70: invokevirtual clear : ()V
/*    */     //   73: iinc #7, 1
/*    */     //   76: goto -> 31
/*    */     //   79: iload #6
/*    */     //   81: ifne -> 341
/*    */     //   84: aload_0
/*    */     //   85: getfield oI0 : Ljava/nio/ByteBuffer;
/*    */     //   88: dup
/*    */     //   89: astore #4
/*    */     //   91: iconst_0
/*    */     //   92: invokevirtual position : (I)Ljava/nio/Buffer;
/*    */     //   95: pop
/*    */     //   96: aload #4
/*    */     //   98: invokevirtual hasRemaining : ()Z
/*    */     //   101: ifeq -> 314
/*    */     //   104: aload #4
/*    */     //   106: invokevirtual get : ()B
/*    */     //   109: dup
/*    */     //   110: istore #6
/*    */     //   112: bipush #15
/*    */     //   114: iand
/*    */     //   115: tableswitch default -> 176, 2 -> 300, 3 -> 291, 4 -> 291, 5 -> 291, 6 -> 248, 7 -> 212, 8 -> 212, 9 -> 179, 10 -> 176, 11 -> 176, 12 -> 300, 13 -> 300
/*    */     //   176: goto -> 96
/*    */     //   179: aload #4
/*    */     //   181: dup
/*    */     //   182: dup
/*    */     //   183: invokevirtual get : ()B
/*    */     //   186: pop
/*    */     //   187: invokevirtual get : ()B
/*    */     //   190: aload #4
/*    */     //   192: invokevirtual position : ()I
/*    */     //   195: istore #4
/*    */     //   197: iconst_3
/*    */     //   198: imul
/*    */     //   199: iload #4
/*    */     //   201: iadd
/*    */     //   202: invokevirtual position : (I)Ljava/nio/Buffer;
/*    */     //   205: pop
/*    */     //   206: iconst_1
/*    */     //   207: istore #4
/*    */     //   209: goto -> 317
/*    */     //   212: iload #6
/*    */     //   214: aload #4
/*    */     //   216: invokevirtual get : ()B
/*    */     //   219: pop
/*    */     //   220: iconst_5
/*    */     //   221: ishr
/*    */     //   222: iconst_1
/*    */     //   223: iand
/*    */     //   224: iconst_1
/*    */     //   225: if_icmpne -> 234
/*    */     //   228: aload #4
/*    */     //   230: invokevirtual get : ()B
/*    */     //   233: pop
/*    */     //   234: iload #6
/*    */     //   236: bipush #6
/*    */     //   238: ishr
/*    */     //   239: iconst_1
/*    */     //   240: iand
/*    */     //   241: iconst_1
/*    */     //   242: if_icmpne -> 96
/*    */     //   245: goto -> 291
/*    */     //   248: iload #6
/*    */     //   250: aload #4
/*    */     //   252: dup
/*    */     //   253: dup
/*    */     //   254: invokevirtual get : ()B
/*    */     //   257: pop
/*    */     //   258: invokevirtual get : ()B
/*    */     //   261: pop
/*    */     //   262: invokevirtual get : ()B
/*    */     //   265: pop
/*    */     //   266: iconst_5
/*    */     //   267: ishr
/*    */     //   268: iconst_1
/*    */     //   269: iand
/*    */     //   270: iconst_1
/*    */     //   271: if_icmpne -> 280
/*    */     //   274: aload #4
/*    */     //   276: invokevirtual get : ()B
/*    */     //   279: pop
/*    */     //   280: iload #6
/*    */     //   282: bipush #6
/*    */     //   284: ishr
/*    */     //   285: iconst_1
/*    */     //   286: iand
/*    */     //   287: iconst_1
/*    */     //   288: if_icmpne -> 96
/*    */     //   291: aload #4
/*    */     //   293: invokevirtual get : ()B
/*    */     //   296: pop
/*    */     //   297: goto -> 96
/*    */     //   300: aload #4
/*    */     //   302: dup
/*    */     //   303: invokevirtual get : ()B
/*    */     //   306: pop
/*    */     //   307: invokevirtual get : ()B
/*    */     //   310: pop
/*    */     //   311: goto -> 96
/*    */     //   314: iconst_0
/*    */     //   315: istore #4
/*    */     //   317: aload_0
/*    */     //   318: getfield ck0 : Lf/TJ0;
/*    */     //   321: ifnonnull -> 338
/*    */     //   324: iload #4
/*    */     //   326: ifeq -> 332
/*    */     //   329: goto -> 338
/*    */     //   332: iconst_0
/*    */     //   333: istore #6
/*    */     //   335: goto -> 341
/*    */     //   338: iconst_1
/*    */     //   339: istore #6
/*    */     //   341: aload_0
/*    */     //   342: new f/fQ
/*    */     //   345: dup
/*    */     //   346: astore #4
/*    */     //   348: invokespecial <init> : ()V
/*    */     //   351: getstatic f/eI.cR : Lf/is0;
/*    */     //   354: astore #7
/*    */     //   356: getfield oI0 : Ljava/nio/ByteBuffer;
/*    */     //   359: dup
/*    */     //   360: astore #8
/*    */     //   362: iconst_0
/*    */     //   363: invokevirtual position : (I)Ljava/nio/Buffer;
/*    */     //   366: pop
/*    */     //   367: iconst_0
/*    */     //   368: istore #9
/*    */     //   370: iconst_0
/*    */     //   371: istore #10
/*    */     //   373: aload #8
/*    */     //   375: invokevirtual hasRemaining : ()Z
/*    */     //   378: ifeq -> 3804
/*    */     //   381: aload #8
/*    */     //   383: invokevirtual get : ()B
/*    */     //   386: dup
/*    */     //   387: istore #11
/*    */     //   389: bipush #15
/*    */     //   391: iand
/*    */     //   392: tableswitch default -> 456, 2 -> 3790, 3 -> 3720, 4 -> 3710, 5 -> 1177, 6 -> 894, 7 -> 852, 8 -> 852, 9 -> 568, 10 -> 456, 11 -> 459, 12 -> 3790, 13 -> 3790
/*    */     //   456: goto -> 373
/*    */     //   459: iload #11
/*    */     //   461: iconst_5
/*    */     //   462: ishr
/*    */     //   463: iconst_1
/*    */     //   464: iand
/*    */     //   465: ifne -> 518
/*    */     //   468: aload #7
/*    */     //   470: getfield pm : Lf/gv0;
/*    */     //   473: getstatic f/eI.GB0 : Lcom/badlogic/gdx/math/Matrix4;
/*    */     //   476: dup
/*    */     //   477: aload_0
/*    */     //   478: getfield Sw : F
/*    */     //   481: fstore #11
/*    */     //   483: invokevirtual WU : ()Lcom/badlogic/gdx/math/Matrix4;
/*    */     //   486: pop
/*    */     //   487: getfield Z0 : [F
/*    */     //   490: dup
/*    */     //   491: dup2
/*    */     //   492: astore #12
/*    */     //   494: iconst_0
/*    */     //   495: fload #11
/*    */     //   497: fastore
/*    */     //   498: iconst_5
/*    */     //   499: fload #11
/*    */     //   501: fastore
/*    */     //   502: bipush #10
/*    */     //   504: fload #11
/*    */     //   506: fastore
/*    */     //   507: getfield Z0 : [F
/*    */     //   510: aload #12
/*    */     //   512: invokestatic jq : ([F[F)V
/*    */     //   515: goto -> 373
/*    */     //   518: aload #7
/*    */     //   520: getfield pm : Lf/gv0;
/*    */     //   523: getstatic f/eI.GB0 : Lcom/badlogic/gdx/math/Matrix4;
/*    */     //   526: dup
/*    */     //   527: aload_0
/*    */     //   528: getfield KD : F
/*    */     //   531: fstore #11
/*    */     //   533: invokevirtual WU : ()Lcom/badlogic/gdx/math/Matrix4;
/*    */     //   536: pop
/*    */     //   537: getfield Z0 : [F
/*    */     //   540: dup
/*    */     //   541: dup2
/*    */     //   542: astore #12
/*    */     //   544: iconst_0
/*    */     //   545: fload #11
/*    */     //   547: fastore
/*    */     //   548: iconst_5
/*    */     //   549: fload #11
/*    */     //   551: fastore
/*    */     //   552: bipush #10
/*    */     //   554: fload #11
/*    */     //   556: fastore
/*    */     //   557: getfield Z0 : [F
/*    */     //   560: aload #12
/*    */     //   562: invokestatic jq : ([F[F)V
/*    */     //   565: goto -> 373
/*    */     //   568: aload #8
/*    */     //   570: dup
/*    */     //   571: getstatic f/eI.vC0 : Lcom/badlogic/gdx/math/Matrix4;
/*    */     //   574: dup
/*    */     //   575: astore #11
/*    */     //   577: getfield Z0 : [F
/*    */     //   580: fconst_0
/*    */     //   581: invokestatic fill : ([FF)V
/*    */     //   584: invokevirtual get : ()B
/*    */     //   587: istore #12
/*    */     //   589: invokevirtual get : ()B
/*    */     //   592: istore #13
/*    */     //   594: iconst_0
/*    */     //   595: istore #14
/*    */     //   597: iload #14
/*    */     //   599: iload #13
/*    */     //   601: if_icmpge -> 770
/*    */     //   604: aload #8
/*    */     //   606: dup
/*    */     //   607: dup
/*    */     //   608: invokevirtual get : ()B
/*    */     //   611: istore #15
/*    */     //   613: invokevirtual get : ()B
/*    */     //   616: istore #16
/*    */     //   618: invokevirtual get : ()B
/*    */     //   621: sipush #255
/*    */     //   624: iand
/*    */     //   625: i2f
/*    */     //   626: ldc_w 256.0
/*    */     //   629: fdiv
/*    */     //   630: fstore #17
/*    */     //   632: getstatic f/eI.GB0 : Lcom/badlogic/gdx/math/Matrix4;
/*    */     //   635: dup
/*    */     //   636: astore #18
/*    */     //   638: aload_0
/*    */     //   639: aload #18
/*    */     //   641: dup
/*    */     //   642: aload #7
/*    */     //   644: getfield kK0 : [Lf/gv0;
/*    */     //   647: iload #15
/*    */     //   649: aaload
/*    */     //   650: astore #15
/*    */     //   652: invokevirtual getClass : ()Ljava/lang/Class;
/*    */     //   655: pop
/*    */     //   656: aload #15
/*    */     //   658: getfield Z0 : [F
/*    */     //   661: invokevirtual Qw : ([F)Lcom/badlogic/gdx/math/Matrix4;
/*    */     //   664: pop
/*    */     //   665: getfield ck0 : Lf/TJ0;
/*    */     //   668: getfield nO : [Lf/Ot0;
/*    */     //   671: iload #16
/*    */     //   673: aaload
/*    */     //   674: getfield cy0 : Lcom/badlogic/gdx/math/Matrix4;
/*    */     //   677: invokevirtual lU : (Lcom/badlogic/gdx/math/Matrix4;)Lcom/badlogic/gdx/math/Matrix4;
/*    */     //   680: pop
/*    */     //   681: iconst_0
/*    */     //   682: istore #15
/*    */     //   684: iload #15
/*    */     //   686: aload #18
/*    */     //   688: getfield Z0 : [F
/*    */     //   691: dup
/*    */     //   692: astore #16
/*    */     //   694: arraylength
/*    */     //   695: if_icmpge -> 717
/*    */     //   698: aload #16
/*    */     //   700: iload #15
/*    */     //   702: aload #16
/*    */     //   704: iload #15
/*    */     //   706: faload
/*    */     //   707: fload #17
/*    */     //   709: fmul
/*    */     //   710: fastore
/*    */     //   711: iinc #15, 1
/*    */     //   714: goto -> 684
/*    */     //   717: getstatic f/eI.GB0 : Lcom/badlogic/gdx/math/Matrix4;
/*    */     //   720: astore #15
/*    */     //   722: iconst_0
/*    */     //   723: istore #16
/*    */     //   725: iload #16
/*    */     //   727: aload #11
/*    */     //   729: getfield Z0 : [F
/*    */     //   732: dup
/*    */     //   733: astore #17
/*    */     //   735: arraylength
/*    */     //   736: if_icmpge -> 764
/*    */     //   739: aload #17
/*    */     //   741: iload #16
/*    */     //   743: aload #17
/*    */     //   745: iload #16
/*    */     //   747: faload
/*    */     //   748: aload #15
/*    */     //   750: getfield Z0 : [F
/*    */     //   753: iload #16
/*    */     //   755: faload
/*    */     //   756: fadd
/*    */     //   757: fastore
/*    */     //   758: iinc #16, 1
/*    */     //   761: goto -> 725
/*    */     //   764: iinc #14, 1
/*    */     //   767: goto -> 597
/*    */     //   770: aload #7
/*    */     //   772: dup
/*    */     //   773: getfield pm : Lf/gv0;
/*    */     //   776: dup
/*    */     //   777: aload #11
/*    */     //   779: swap
/*    */     //   780: invokevirtual getClass : ()Ljava/lang/Class;
/*    */     //   783: pop
/*    */     //   784: getfield Z0 : [F
/*    */     //   787: invokevirtual Qw : ([F)Lcom/badlogic/gdx/math/Matrix4;
/*    */     //   790: pop
/*    */     //   791: getfield kK0 : [Lf/gv0;
/*    */     //   794: iload #12
/*    */     //   796: aaload
/*    */     //   797: dup
/*    */     //   798: dup2
/*    */     //   799: astore #11
/*    */     //   801: aload #7
/*    */     //   803: getfield pm : Lf/gv0;
/*    */     //   806: astore #12
/*    */     //   808: invokevirtual getClass : ()Ljava/lang/Class;
/*    */     //   811: pop
/*    */     //   812: aload #12
/*    */     //   814: getfield Jb : I
/*    */     //   817: putfield Jb : I
/*    */     //   820: aload #12
/*    */     //   822: aload #11
/*    */     //   824: dup
/*    */     //   825: getfield Yo : Lf/fQ;
/*    */     //   828: invokevirtual clear : ()V
/*    */     //   831: getfield Yo : Lf/fQ;
/*    */     //   834: aload #12
/*    */     //   836: getfield Yo : Lf/fQ;
/*    */     //   839: invokevirtual OG0 : (Lf/fQ;)V
/*    */     //   842: getfield Z0 : [F
/*    */     //   845: invokevirtual Qw : ([F)Lcom/badlogic/gdx/math/Matrix4;
/*    */     //   848: pop
/*    */     //   849: goto -> 373
/*    */     //   852: iload #11
/*    */     //   854: aload #8
/*    */     //   856: invokevirtual get : ()B
/*    */     //   859: pop
/*    */     //   860: iconst_5
/*    */     //   861: ishr
/*    */     //   862: iconst_1
/*    */     //   863: iand
/*    */     //   864: iconst_1
/*    */     //   865: if_icmpne -> 874
/*    */     //   868: aload #8
/*    */     //   870: invokevirtual get : ()B
/*    */     //   873: pop
/*    */     //   874: iload #11
/*    */     //   876: bipush #6
/*    */     //   878: ishr
/*    */     //   879: iconst_1
/*    */     //   880: iand
/*    */     //   881: iconst_1
/*    */     //   882: if_icmpne -> 373
/*    */     //   885: aload #8
/*    */     //   887: invokevirtual get : ()B
/*    */     //   890: pop
/*    */     //   891: goto -> 373
/*    */     //   894: iload #11
/*    */     //   896: aload #8
/*    */     //   898: dup
/*    */     //   899: dup
/*    */     //   900: invokevirtual get : ()B
/*    */     //   903: istore #12
/*    */     //   905: invokevirtual get : ()B
/*    */     //   908: pop
/*    */     //   909: invokevirtual get : ()B
/*    */     //   912: pop
/*    */     //   913: iconst_5
/*    */     //   914: ishr
/*    */     //   915: iconst_1
/*    */     //   916: iand
/*    */     //   917: iconst_1
/*    */     //   918: if_icmpne -> 927
/*    */     //   921: iconst_1
/*    */     //   922: istore #13
/*    */     //   924: goto -> 930
/*    */     //   927: iconst_0
/*    */     //   928: istore #13
/*    */     //   930: iload #11
/*    */     //   932: bipush #6
/*    */     //   934: ishr
/*    */     //   935: iconst_1
/*    */     //   936: iand
/*    */     //   937: iconst_1
/*    */     //   938: if_icmpne -> 947
/*    */     //   941: iconst_1
/*    */     //   942: istore #11
/*    */     //   944: goto -> 950
/*    */     //   947: iconst_0
/*    */     //   948: istore #11
/*    */     //   950: iload #13
/*    */     //   952: ifeq -> 965
/*    */     //   955: aload #8
/*    */     //   957: invokevirtual get : ()B
/*    */     //   960: istore #14
/*    */     //   962: goto -> 968
/*    */     //   965: iconst_m1
/*    */     //   966: istore #14
/*    */     //   968: iload #11
/*    */     //   970: ifeq -> 983
/*    */     //   973: aload #8
/*    */     //   975: invokevirtual get : ()B
/*    */     //   978: istore #15
/*    */     //   980: goto -> 986
/*    */     //   983: iconst_m1
/*    */     //   984: istore #15
/*    */     //   986: iload #11
/*    */     //   988: ifeq -> 1051
/*    */     //   991: aload #7
/*    */     //   993: getfield pm : Lf/gv0;
/*    */     //   996: dup
/*    */     //   997: dup2
/*    */     //   998: astore #11
/*    */     //   1000: aload #7
/*    */     //   1002: getfield kK0 : [Lf/gv0;
/*    */     //   1005: iload #15
/*    */     //   1007: aaload
/*    */     //   1008: astore #15
/*    */     //   1010: invokevirtual getClass : ()Ljava/lang/Class;
/*    */     //   1013: pop
/*    */     //   1014: aload #15
/*    */     //   1016: getfield Jb : I
/*    */     //   1019: putfield Jb : I
/*    */     //   1022: aload #15
/*    */     //   1024: aload #11
/*    */     //   1026: dup
/*    */     //   1027: getfield Yo : Lf/fQ;
/*    */     //   1030: invokevirtual clear : ()V
/*    */     //   1033: getfield Yo : Lf/fQ;
/*    */     //   1036: aload #15
/*    */     //   1038: getfield Yo : Lf/fQ;
/*    */     //   1041: invokevirtual OG0 : (Lf/fQ;)V
/*    */     //   1044: getfield Z0 : [F
/*    */     //   1047: invokevirtual Qw : ([F)Lcom/badlogic/gdx/math/Matrix4;
/*    */     //   1050: pop
/*    */     //   1051: iload #13
/*    */     //   1053: aload_0
/*    */     //   1054: aload #7
/*    */     //   1056: getfield pm : Lf/gv0;
/*    */     //   1059: dup
/*    */     //   1060: iload #12
/*    */     //   1062: putfield Jb : I
/*    */     //   1065: getfield Yo : Lf/fQ;
/*    */     //   1068: iload #12
/*    */     //   1070: invokestatic valueOf : (I)Ljava/lang/Integer;
/*    */     //   1073: invokevirtual Com3 : (Ljava/lang/Object;)V
/*    */     //   1076: getfield Os0 : Lf/fQ;
/*    */     //   1079: iload #12
/*    */     //   1081: invokevirtual get : (I)Ljava/lang/Object;
/*    */     //   1084: checkcast f/vY
/*    */     //   1087: getfield qX : Lcom/badlogic/gdx/math/Matrix4;
/*    */     //   1090: dup
/*    */     //   1091: aload #7
/*    */     //   1093: getfield pm : Lf/gv0;
/*    */     //   1096: astore #11
/*    */     //   1098: invokevirtual getClass : ()Ljava/lang/Class;
/*    */     //   1101: pop
/*    */     //   1102: aload #11
/*    */     //   1104: getfield Z0 : [F
/*    */     //   1107: invokevirtual Qw : ([F)Lcom/badlogic/gdx/math/Matrix4;
/*    */     //   1110: pop
/*    */     //   1111: ifeq -> 373
/*    */     //   1114: aload #7
/*    */     //   1116: getfield kK0 : [Lf/gv0;
/*    */     //   1119: iload #14
/*    */     //   1121: aaload
/*    */     //   1122: dup
/*    */     //   1123: dup2
/*    */     //   1124: astore #11
/*    */     //   1126: aload #7
/*    */     //   1128: getfield pm : Lf/gv0;
/*    */     //   1131: astore #12
/*    */     //   1133: invokevirtual getClass : ()Ljava/lang/Class;
/*    */     //   1136: pop
/*    */     //   1137: aload #12
/*    */     //   1139: getfield Jb : I
/*    */     //   1142: putfield Jb : I
/*    */     //   1145: aload #12
/*    */     //   1147: aload #11
/*    */     //   1149: dup
/*    */     //   1150: getfield Yo : Lf/fQ;
/*    */     //   1153: invokevirtual clear : ()V
/*    */     //   1156: getfield Yo : Lf/fQ;
/*    */     //   1159: aload #12
/*    */     //   1161: getfield Yo : Lf/fQ;
/*    */     //   1164: invokevirtual OG0 : (Lf/fQ;)V
/*    */     //   1167: getfield Z0 : [F
/*    */     //   1170: invokevirtual Qw : ([F)Lcom/badlogic/gdx/math/Matrix4;
/*    */     //   1173: pop
/*    */     //   1174: goto -> 373
/*    */     //   1177: aload_0
/*    */     //   1178: dup
/*    */     //   1179: aload #8
/*    */     //   1181: invokevirtual get : ()B
/*    */     //   1184: istore #11
/*    */     //   1186: getfield rt : Lf/fQ;
/*    */     //   1189: iload #11
/*    */     //   1191: invokevirtual get : (I)Ljava/lang/Object;
/*    */     //   1194: checkcast f/qL0
/*    */     //   1197: dup
/*    */     //   1198: astore #12
/*    */     //   1200: aload #7
/*    */     //   1202: getfield pm : Lf/gv0;
/*    */     //   1205: getfield Jb : I
/*    */     //   1208: putfield h30 : I
/*    */     //   1211: getfield p3 : Lf/fQ;
/*    */     //   1214: iload #10
/*    */     //   1216: invokevirtual get : (I)Ljava/lang/Object;
/*    */     //   1219: checkcast f/tC
/*    */     //   1222: dup
/*    */     //   1223: astore #13
/*    */     //   1225: getfield MC : Z
/*    */     //   1228: ifne -> 1242
/*    */     //   1231: iload #5
/*    */     //   1233: ifeq -> 1242
/*    */     //   1236: iconst_1
/*    */     //   1237: istore #14
/*    */     //   1239: goto -> 1245
/*    */     //   1242: iconst_0
/*    */     //   1243: istore #14
/*    */     //   1245: iload #6
/*    */     //   1247: new f/Ns
/*    */     //   1250: dup
/*    */     //   1251: astore #15
/*    */     //   1253: invokespecial <init> : ()V
/*    */     //   1256: ifeq -> 1298
/*    */     //   1259: aload #15
/*    */     //   1261: dup
/*    */     //   1262: aload #7
/*    */     //   1264: getfield pm : Lf/gv0;
/*    */     //   1267: dup
/*    */     //   1268: getfield Jb : I
/*    */     //   1271: i2f
/*    */     //   1272: fstore #16
/*    */     //   1274: getfield Fu : F
/*    */     //   1277: fstore #17
/*    */     //   1279: getfield ii : Lf/NC0;
/*    */     //   1282: dup
/*    */     //   1283: fload #17
/*    */     //   1285: swap
/*    */     //   1286: fload #16
/*    */     //   1288: putfield x : F
/*    */     //   1291: putfield y : F
/*    */     //   1294: iconst_1
/*    */     //   1295: putfield tO : Z
/*    */     //   1298: aload #12
/*    */     //   1300: getfield rh : I
/*    */     //   1303: ifge -> 1309
/*    */     //   1306: goto -> 1464
/*    */     //   1309: aload #12
/*    */     //   1311: new f/c50
/*    */     //   1314: dup
/*    */     //   1315: astore #16
/*    */     //   1317: aload_0
/*    */     //   1318: dup
/*    */     //   1319: aload #16
/*    */     //   1321: aload #12
/*    */     //   1323: aload #16
/*    */     //   1325: ldc_w 'polygon'
/*    */     //   1328: iload #11
/*    */     //   1330: ldc_w '_'
/*    */     //   1333: invokestatic DH0 : (Ljava/lang/String;ILjava/lang/String;)Ljava/lang/StringBuilder;
/*    */     //   1336: aload_0
/*    */     //   1337: getfield p3 : Lf/fQ;
/*    */     //   1340: aload #12
/*    */     //   1342: getfield rh : I
/*    */     //   1345: invokevirtual get : (I)Ljava/lang/Object;
/*    */     //   1348: checkcast f/tC
/*    */     //   1351: getfield Ih : Ljava/lang/String;
/*    */     //   1354: invokevirtual append : (Ljava/lang/String;)Ljava/lang/StringBuilder;
/*    */     //   1357: invokevirtual toString : ()Ljava/lang/String;
/*    */     //   1360: invokespecial <init> : (Ljava/lang/String;)V
/*    */     //   1363: getfield h30 : I
/*    */     //   1366: dup
/*    */     //   1367: istore #11
/*    */     //   1369: putfield s3 : I
/*    */     //   1372: getfield Os0 : Lf/fQ;
/*    */     //   1375: iload #11
/*    */     //   1377: invokevirtual get : (I)Ljava/lang/Object;
/*    */     //   1380: checkcast f/vY
/*    */     //   1383: pop
/*    */     //   1384: getfield p3 : Lf/fQ;
/*    */     //   1387: aload #12
/*    */     //   1389: getfield rh : I
/*    */     //   1392: invokevirtual get : (I)Ljava/lang/Object;
/*    */     //   1395: checkcast f/tC
/*    */     //   1398: putfield mR : Lf/tC;
/*    */     //   1401: getfield aL : [B
/*    */     //   1404: dup
/*    */     //   1405: astore #11
/*    */     //   1407: ifnonnull -> 1416
/*    */     //   1410: aconst_null
/*    */     //   1411: astore #11
/*    */     //   1413: goto -> 1456
/*    */     //   1416: aload #12
/*    */     //   1418: getfield zb : Ljava/nio/ByteBuffer;
/*    */     //   1421: ifnonnull -> 1440
/*    */     //   1424: aload #12
/*    */     //   1426: aload #11
/*    */     //   1428: invokestatic wrap : ([B)Ljava/nio/ByteBuffer;
/*    */     //   1431: getstatic java/nio/ByteOrder.LITTLE_ENDIAN : Ljava/nio/ByteOrder;
/*    */     //   1434: invokevirtual order : (Ljava/nio/ByteOrder;)Ljava/nio/ByteBuffer;
/*    */     //   1437: putfield zb : Ljava/nio/ByteBuffer;
/*    */     //   1440: aload #12
/*    */     //   1442: dup
/*    */     //   1443: getfield zb : Ljava/nio/ByteBuffer;
/*    */     //   1446: iconst_0
/*    */     //   1447: invokevirtual position : (I)Ljava/nio/Buffer;
/*    */     //   1450: pop
/*    */     //   1451: getfield zb : Ljava/nio/ByteBuffer;
/*    */     //   1454: astore #11
/*    */     //   1456: aload #11
/*    */     //   1458: iconst_m1
/*    */     //   1459: istore #17
/*    */     //   1461: ifnonnull -> 1470
/*    */     //   1464: aconst_null
/*    */     //   1465: astore #16
/*    */     //   1467: goto -> 3678
/*    */     //   1470: aload #11
/*    */     //   1472: iconst_0
/*    */     //   1473: istore #18
/*    */     //   1475: invokevirtual limit : ()I
/*    */     //   1478: istore #19
/*    */     //   1480: iconst_4
/*    */     //   1481: newarray int
/*    */     //   1483: astore #20
/*    */     //   1485: getstatic f/eI.UL0 : Lf/eo;
/*    */     //   1488: invokevirtual gL : ()Lf/eo;
/*    */     //   1491: pop
/*    */     //   1492: iload #18
/*    */     //   1494: iload #19
/*    */     //   1496: if_icmpge -> 3678
/*    */     //   1499: iconst_0
/*    */     //   1500: istore #21
/*    */     //   1502: iload #21
/*    */     //   1504: iconst_4
/*    */     //   1505: if_icmpge -> 1548
/*    */     //   1508: iload #18
/*    */     //   1510: iload #19
/*    */     //   1512: if_icmplt -> 1526
/*    */     //   1515: aload #20
/*    */     //   1517: iload #21
/*    */     //   1519: sipush #255
/*    */     //   1522: iastore
/*    */     //   1523: goto -> 1542
/*    */     //   1526: aload #20
/*    */     //   1528: aload #11
/*    */     //   1530: iload #18
/*    */     //   1532: invokevirtual get : (I)B
/*    */     //   1535: iload #21
/*    */     //   1537: swap
/*    */     //   1538: iastore
/*    */     //   1539: iinc #18, 1
/*    */     //   1542: iinc #21, 1
/*    */     //   1545: goto -> 1502
/*    */     //   1548: iconst_0
/*    */     //   1549: istore #21
/*    */     //   1551: iload #21
/*    */     //   1553: iconst_4
/*    */     //   1554: if_icmpge -> 1492
/*    */     //   1557: iload #18
/*    */     //   1559: iload #19
/*    */     //   1561: if_icmpge -> 1492
/*    */     //   1564: aload #20
/*    */     //   1566: iload #21
/*    */     //   1568: iaload
/*    */     //   1569: dup
/*    */     //   1570: istore #22
/*    */     //   1572: ifeq -> 3672
/*    */     //   1575: iload #22
/*    */     //   1577: bipush #80
/*    */     //   1579: if_icmpeq -> 3669
/*    */     //   1582: iload #22
/*    */     //   1584: bipush #96
/*    */     //   1586: if_icmpeq -> 3669
/*    */     //   1589: iload #22
/*    */     //   1591: bipush #64
/*    */     //   1593: if_icmpeq -> 3654
/*    */     //   1596: iload #22
/*    */     //   1598: bipush #65
/*    */     //   1600: if_icmpeq -> 3495
/*    */     //   1603: iload #22
/*    */     //   1605: tableswitch default -> 1672, 16 -> 3438, 17 -> 3672, 18 -> 3669, 19 -> 3669, 20 -> 2311, 21 -> 2299, 22 -> 2253, 23 -> 2188, 24 -> 2122, 25 -> 2052, 26 -> 1982, 27 -> 1894, 28 -> 1817
/*    */     //   1672: iload #22
/*    */     //   1674: tableswitch default -> 1736, 32 -> 3335, 33 -> 3243, 34 -> 3054, 35 -> 2903, 36 -> 2802, 37 -> 2726, 38 -> 2650, 39 -> 2574, 40 -> 2433, 41 -> 3438, 42 -> 3669, 43 -> 3669
/*    */     //   1736: iload #22
/*    */     //   1738: tableswitch default -> 1772, 48 -> 3669, 49 -> 3669, 50 -> 3669, 51 -> 3438, 52 -> 3427
/*    */     //   1772: iload #22
/*    */     //   1774: tableswitch default -> 1800, 112 -> 3458, 113 -> 3452, 114 -> 3669
/*    */     //   1800: getstatic java/lang/System.out : Ljava/io/PrintStream;
/*    */     //   1803: ldc_w 'UNK COMMAND '
/*    */     //   1806: invokestatic df : (Ljava/lang/String;)Ljava/lang/StringBuilder;
/*    */     //   1809: aload #20
/*    */     //   1811: iload #21
/*    */     //   1813: iaload
/*    */     //   1814: goto -> 3464
/*    */     //   1817: aload #7
/*    */     //   1819: aload #11
/*    */     //   1821: iload #18
/*    */     //   1823: aload #11
/*    */     //   1825: iload #18
/*    */     //   1827: aload #11
/*    */     //   1829: iload #18
/*    */     //   1831: invokevirtual getInt : (I)I
/*    */     //   1834: invokestatic T50 : (I)F
/*    */     //   1837: fstore #22
/*    */     //   1839: iconst_4
/*    */     //   1840: iadd
/*    */     //   1841: invokevirtual getInt : (I)I
/*    */     //   1844: invokestatic T50 : (I)F
/*    */     //   1847: fstore #23
/*    */     //   1849: bipush #8
/*    */     //   1851: iadd
/*    */     //   1852: invokevirtual getInt : (I)I
/*    */     //   1855: invokestatic T50 : (I)F
/*    */     //   1858: fstore #24
/*    */     //   1860: iinc #18, 12
/*    */     //   1863: getfield pm : Lf/gv0;
/*    */     //   1866: getstatic f/eI.GB0 : Lcom/badlogic/gdx/math/Matrix4;
/*    */     //   1869: fload #22
/*    */     //   1871: fload #23
/*    */     //   1873: fload #24
/*    */     //   1875: invokevirtual gv0 : (FFF)Lcom/badlogic/gdx/math/Matrix4;
/*    */     //   1878: astore #22
/*    */     //   1880: getfield Z0 : [F
/*    */     //   1883: aload #22
/*    */     //   1885: getfield Z0 : [F
/*    */     //   1888: invokestatic jq : ([F[F)V
/*    */     //   1891: goto -> 3672
/*    */     //   1894: aload #7
/*    */     //   1896: aload #11
/*    */     //   1898: iload #18
/*    */     //   1900: aload #11
/*    */     //   1902: iload #18
/*    */     //   1904: aload #11
/*    */     //   1906: iload #18
/*    */     //   1908: invokevirtual getInt : (I)I
/*    */     //   1911: invokestatic T50 : (I)F
/*    */     //   1914: fstore #22
/*    */     //   1916: iconst_4
/*    */     //   1917: iadd
/*    */     //   1918: invokevirtual getInt : (I)I
/*    */     //   1921: invokestatic T50 : (I)F
/*    */     //   1924: fstore #23
/*    */     //   1926: bipush #8
/*    */     //   1928: iadd
/*    */     //   1929: invokevirtual getInt : (I)I
/*    */     //   1932: invokestatic Jd0 : (I)F
/*    */     //   1935: fstore #24
/*    */     //   1937: iinc #18, 12
/*    */     //   1940: getfield pm : Lf/gv0;
/*    */     //   1943: getstatic f/eI.GB0 : Lcom/badlogic/gdx/math/Matrix4;
/*    */     //   1946: dup
/*    */     //   1947: invokevirtual WU : ()Lcom/badlogic/gdx/math/Matrix4;
/*    */     //   1950: pop
/*    */     //   1951: getfield Z0 : [F
/*    */     //   1954: dup
/*    */     //   1955: dup2
/*    */     //   1956: astore #25
/*    */     //   1958: iconst_0
/*    */     //   1959: fload #22
/*    */     //   1961: fastore
/*    */     //   1962: iconst_5
/*    */     //   1963: fload #23
/*    */     //   1965: fastore
/*    */     //   1966: bipush #10
/*    */     //   1968: fload #24
/*    */     //   1970: fastore
/*    */     //   1971: getfield Z0 : [F
/*    */     //   1974: aload #25
/*    */     //   1976: invokestatic jq : ([F[F)V
/*    */     //   1979: goto -> 3672
/*    */     //   1982: aload #11
/*    */     //   1984: iload #18
/*    */     //   1986: getstatic f/eI.GB0 : Lcom/badlogic/gdx/math/Matrix4;
/*    */     //   1989: invokevirtual WU : ()Lcom/badlogic/gdx/math/Matrix4;
/*    */     //   1992: pop
/*    */     //   1993: invokevirtual position : (I)Ljava/nio/Buffer;
/*    */     //   1996: pop
/*    */     //   1997: iconst_0
/*    */     //   1998: istore #22
/*    */     //   2000: iload #22
/*    */     //   2002: iconst_3
/*    */     //   2003: if_icmpge -> 2173
/*    */     //   2006: iconst_0
/*    */     //   2007: istore #23
/*    */     //   2009: iload #23
/*    */     //   2011: iconst_3
/*    */     //   2012: if_icmpge -> 2046
/*    */     //   2015: getstatic f/eI.GB0 : Lcom/badlogic/gdx/math/Matrix4;
/*    */     //   2018: getfield Z0 : [F
/*    */     //   2021: iload #22
/*    */     //   2023: iconst_4
/*    */     //   2024: imul
/*    */     //   2025: iload #23
/*    */     //   2027: iadd
/*    */     //   2028: aload #11
/*    */     //   2030: invokevirtual getInt : ()I
/*    */     //   2033: invokestatic T50 : (I)F
/*    */     //   2036: fastore
/*    */     //   2037: iinc #18, 4
/*    */     //   2040: iinc #23, 1
/*    */     //   2043: goto -> 2009
/*    */     //   2046: iinc #22, 1
/*    */     //   2049: goto -> 2000
/*    */     //   2052: aload #11
/*    */     //   2054: iload #18
/*    */     //   2056: invokevirtual position : (I)Ljava/nio/Buffer;
/*    */     //   2059: pop
/*    */     //   2060: getstatic f/eI.GB0 : Lcom/badlogic/gdx/math/Matrix4;
/*    */     //   2063: invokevirtual WU : ()Lcom/badlogic/gdx/math/Matrix4;
/*    */     //   2066: pop
/*    */     //   2067: iconst_0
/*    */     //   2068: istore #22
/*    */     //   2070: iload #22
/*    */     //   2072: iconst_4
/*    */     //   2073: if_icmpge -> 2173
/*    */     //   2076: iconst_0
/*    */     //   2077: istore #23
/*    */     //   2079: iload #23
/*    */     //   2081: iconst_3
/*    */     //   2082: if_icmpge -> 2116
/*    */     //   2085: getstatic f/eI.GB0 : Lcom/badlogic/gdx/math/Matrix4;
/*    */     //   2088: getfield Z0 : [F
/*    */     //   2091: iload #22
/*    */     //   2093: iconst_4
/*    */     //   2094: imul
/*    */     //   2095: iload #23
/*    */     //   2097: iadd
/*    */     //   2098: aload #11
/*    */     //   2100: invokevirtual getInt : ()I
/*    */     //   2103: invokestatic T50 : (I)F
/*    */     //   2106: fastore
/*    */     //   2107: iinc #18, 4
/*    */     //   2110: iinc #23, 1
/*    */     //   2113: goto -> 2079
/*    */     //   2116: iinc #22, 1
/*    */     //   2119: goto -> 2070
/*    */     //   2122: aload #11
/*    */     //   2124: iload #18
/*    */     //   2126: invokevirtual position : (I)Ljava/nio/Buffer;
/*    */     //   2129: pop
/*    */     //   2130: getstatic f/eI.GB0 : Lcom/badlogic/gdx/math/Matrix4;
/*    */     //   2133: invokevirtual WU : ()Lcom/badlogic/gdx/math/Matrix4;
/*    */     //   2136: pop
/*    */     //   2137: iconst_0
/*    */     //   2138: istore #22
/*    */     //   2140: iload #22
/*    */     //   2142: bipush #16
/*    */     //   2144: if_icmpge -> 2173
/*    */     //   2147: getstatic f/eI.GB0 : Lcom/badlogic/gdx/math/Matrix4;
/*    */     //   2150: getfield Z0 : [F
/*    */     //   2153: iload #22
/*    */     //   2155: aload #11
/*    */     //   2157: invokevirtual getInt : ()I
/*    */     //   2160: invokestatic T50 : (I)F
/*    */     //   2163: fastore
/*    */     //   2164: iinc #18, 4
/*    */     //   2167: iinc #22, 1
/*    */     //   2170: goto -> 2140
/*    */     //   2173: aload #7
/*    */     //   2175: getfield pm : Lf/gv0;
/*    */     //   2178: getstatic f/eI.GB0 : Lcom/badlogic/gdx/math/Matrix4;
/*    */     //   2181: invokevirtual lU : (Lcom/badlogic/gdx/math/Matrix4;)Lcom/badlogic/gdx/math/Matrix4;
/*    */     //   2184: pop
/*    */     //   2185: goto -> 3672
/*    */     //   2188: aload #11
/*    */     //   2190: iload #18
/*    */     //   2192: invokevirtual position : (I)Ljava/nio/Buffer;
/*    */     //   2195: pop
/*    */     //   2196: iconst_0
/*    */     //   2197: istore #22
/*    */     //   2199: iload #22
/*    */     //   2201: iconst_4
/*    */     //   2202: if_icmpge -> 3672
/*    */     //   2205: iconst_0
/*    */     //   2206: istore #23
/*    */     //   2208: iload #23
/*    */     //   2210: iconst_3
/*    */     //   2211: if_icmpge -> 2247
/*    */     //   2214: aload #7
/*    */     //   2216: getfield pm : Lf/gv0;
/*    */     //   2219: getfield Z0 : [F
/*    */     //   2222: iload #22
/*    */     //   2224: iconst_4
/*    */     //   2225: imul
/*    */     //   2226: iload #23
/*    */     //   2228: iadd
/*    */     //   2229: aload #11
/*    */     //   2231: invokevirtual getInt : ()I
/*    */     //   2234: invokestatic T50 : (I)F
/*    */     //   2237: fastore
/*    */     //   2238: iinc #18, 4
/*    */     //   2241: iinc #23, 1
/*    */     //   2244: goto -> 2208
/*    */     //   2247: iinc #22, 1
/*    */     //   2250: goto -> 2199
/*    */     //   2253: aload #11
/*    */     //   2255: iload #18
/*    */     //   2257: invokevirtual position : (I)Ljava/nio/Buffer;
/*    */     //   2260: pop
/*    */     //   2261: iconst_0
/*    */     //   2262: istore #22
/*    */     //   2264: iload #22
/*    */     //   2266: bipush #16
/*    */     //   2268: if_icmpge -> 3672
/*    */     //   2271: aload #7
/*    */     //   2273: getfield pm : Lf/gv0;
/*    */     //   2276: getfield Z0 : [F
/*    */     //   2279: iload #22
/*    */     //   2281: aload #11
/*    */     //   2283: invokevirtual getInt : ()I
/*    */     //   2286: invokestatic T50 : (I)F
/*    */     //   2289: fastore
/*    */     //   2290: iinc #18, 4
/*    */     //   2293: iinc #22, 1
/*    */     //   2296: goto -> 2264
/*    */     //   2299: aload #7
/*    */     //   2301: getfield pm : Lf/gv0;
/*    */     //   2304: invokevirtual WU : ()Lcom/badlogic/gdx/math/Matrix4;
/*    */     //   2307: pop
/*    */     //   2308: goto -> 3672
/*    */     //   2311: iload #6
/*    */     //   2313: aload #7
/*    */     //   2315: aload #11
/*    */     //   2317: iload #18
/*    */     //   2319: invokevirtual getInt : (I)I
/*    */     //   2322: bipush #31
/*    */     //   2324: iand
/*    */     //   2325: istore #22
/*    */     //   2327: iinc #18, 4
/*    */     //   2330: getfield pm : Lf/gv0;
/*    */     //   2333: dup
/*    */     //   2334: dup2
/*    */     //   2335: astore #23
/*    */     //   2337: aload #7
/*    */     //   2339: getfield kK0 : [Lf/gv0;
/*    */     //   2342: iload #22
/*    */     //   2344: aaload
/*    */     //   2345: astore #22
/*    */     //   2347: invokevirtual getClass : ()Ljava/lang/Class;
/*    */     //   2350: pop
/*    */     //   2351: aload #22
/*    */     //   2353: getfield Jb : I
/*    */     //   2356: putfield Jb : I
/*    */     //   2359: aload #22
/*    */     //   2361: aload #23
/*    */     //   2363: dup
/*    */     //   2364: getfield Yo : Lf/fQ;
/*    */     //   2367: invokevirtual clear : ()V
/*    */     //   2370: getfield Yo : Lf/fQ;
/*    */     //   2373: aload #22
/*    */     //   2375: getfield Yo : Lf/fQ;
/*    */     //   2378: invokevirtual OG0 : (Lf/fQ;)V
/*    */     //   2381: getfield Z0 : [F
/*    */     //   2384: invokevirtual Qw : ([F)Lcom/badlogic/gdx/math/Matrix4;
/*    */     //   2387: pop
/*    */     //   2388: ifeq -> 3672
/*    */     //   2391: aload #15
/*    */     //   2393: dup
/*    */     //   2394: aload #7
/*    */     //   2396: getfield pm : Lf/gv0;
/*    */     //   2399: dup
/*    */     //   2400: getfield Jb : I
/*    */     //   2403: i2f
/*    */     //   2404: fstore #22
/*    */     //   2406: getfield Fu : F
/*    */     //   2409: fstore #23
/*    */     //   2411: getfield ii : Lf/NC0;
/*    */     //   2414: dup
/*    */     //   2415: fload #23
/*    */     //   2417: swap
/*    */     //   2418: fload #22
/*    */     //   2420: putfield x : F
/*    */     //   2423: putfield y : F
/*    */     //   2426: iconst_1
/*    */     //   2427: putfield tO : Z
/*    */     //   2430: goto -> 3672
/*    */     //   2433: aload #11
/*    */     //   2435: iload #18
/*    */     //   2437: invokevirtual getInt : (I)I
/*    */     //   2440: istore #22
/*    */     //   2442: iinc #18, 4
/*    */     //   2445: getstatic f/eI.UL0 : Lf/eo;
/*    */     //   2448: dup
/*    */     //   2449: astore #23
/*    */     //   2451: iload #22
/*    */     //   2453: aload #23
/*    */     //   2455: dup
/*    */     //   2456: iload #22
/*    */     //   2458: aload #23
/*    */     //   2460: dup
/*    */     //   2461: iload #22
/*    */     //   2463: aload #23
/*    */     //   2465: getfield x : F
/*    */     //   2468: fstore #22
/*    */     //   2470: sipush #1023
/*    */     //   2473: iand
/*    */     //   2474: i2s
/*    */     //   2475: istore #24
/*    */     //   2477: iconst_0
/*    */     //   2478: bipush #9
/*    */     //   2480: iload #24
/*    */     //   2482: invokestatic cOm4 : (IIS)F
/*    */     //   2485: ldc_w 8.0
/*    */     //   2488: fdiv
/*    */     //   2489: fload #22
/*    */     //   2491: fadd
/*    */     //   2492: putfield x : F
/*    */     //   2495: getfield y : F
/*    */     //   2498: fstore #22
/*    */     //   2500: bipush #10
/*    */     //   2502: ishr
/*    */     //   2503: sipush #1023
/*    */     //   2506: iand
/*    */     //   2507: i2s
/*    */     //   2508: istore #24
/*    */     //   2510: iconst_0
/*    */     //   2511: bipush #9
/*    */     //   2513: iload #24
/*    */     //   2515: invokestatic cOm4 : (IIS)F
/*    */     //   2518: ldc_w 8.0
/*    */     //   2521: fdiv
/*    */     //   2522: fload #22
/*    */     //   2524: fadd
/*    */     //   2525: putfield y : F
/*    */     //   2528: getfield z : F
/*    */     //   2531: fstore #22
/*    */     //   2533: bipush #20
/*    */     //   2535: ishr
/*    */     //   2536: sipush #1023
/*    */     //   2539: iand
/*    */     //   2540: i2s
/*    */     //   2541: istore #24
/*    */     //   2543: iconst_0
/*    */     //   2544: bipush #9
/*    */     //   2546: iload #24
/*    */     //   2548: invokestatic cOm4 : (IIS)F
/*    */     //   2551: ldc_w 8.0
/*    */     //   2554: fdiv
/*    */     //   2555: fload #22
/*    */     //   2557: fadd
/*    */     //   2558: putfield z : F
/*    */     //   2561: getstatic f/eI.Pp : Lf/eo;
/*    */     //   2564: dup
/*    */     //   2565: astore #22
/*    */     //   2567: invokevirtual getClass : ()Ljava/lang/Class;
/*    */     //   2570: pop
/*    */     //   2571: goto -> 3013
/*    */     //   2574: aload #11
/*    */     //   2576: iload #18
/*    */     //   2578: invokevirtual getInt : (I)I
/*    */     //   2581: istore #22
/*    */     //   2583: iinc #18, 4
/*    */     //   2586: getstatic f/eI.UL0 : Lf/eo;
/*    */     //   2589: dup
/*    */     //   2590: astore #23
/*    */     //   2592: iload #22
/*    */     //   2594: aload #23
/*    */     //   2596: iload #22
/*    */     //   2598: ldc_w 65535
/*    */     //   2601: iand
/*    */     //   2602: i2s
/*    */     //   2603: istore #22
/*    */     //   2605: iconst_3
/*    */     //   2606: bipush #12
/*    */     //   2608: iload #22
/*    */     //   2610: invokestatic cOm4 : (IIS)F
/*    */     //   2613: putfield y : F
/*    */     //   2616: bipush #16
/*    */     //   2618: ishr
/*    */     //   2619: ldc_w 65535
/*    */     //   2622: iand
/*    */     //   2623: i2s
/*    */     //   2624: istore #22
/*    */     //   2626: iconst_3
/*    */     //   2627: bipush #12
/*    */     //   2629: iload #22
/*    */     //   2631: invokestatic cOm4 : (IIS)F
/*    */     //   2634: putfield z : F
/*    */     //   2637: getstatic f/eI.Pp : Lf/eo;
/*    */     //   2640: dup
/*    */     //   2641: astore #22
/*    */     //   2643: invokevirtual getClass : ()Ljava/lang/Class;
/*    */     //   2646: pop
/*    */     //   2647: goto -> 3013
/*    */     //   2650: aload #11
/*    */     //   2652: iload #18
/*    */     //   2654: invokevirtual getInt : (I)I
/*    */     //   2657: istore #22
/*    */     //   2659: iinc #18, 4
/*    */     //   2662: getstatic f/eI.UL0 : Lf/eo;
/*    */     //   2665: dup
/*    */     //   2666: astore #23
/*    */     //   2668: iload #22
/*    */     //   2670: aload #23
/*    */     //   2672: iload #22
/*    */     //   2674: ldc_w 65535
/*    */     //   2677: iand
/*    */     //   2678: i2s
/*    */     //   2679: istore #22
/*    */     //   2681: iconst_3
/*    */     //   2682: bipush #12
/*    */     //   2684: iload #22
/*    */     //   2686: invokestatic cOm4 : (IIS)F
/*    */     //   2689: putfield x : F
/*    */     //   2692: bipush #16
/*    */     //   2694: ishr
/*    */     //   2695: ldc_w 65535
/*    */     //   2698: iand
/*    */     //   2699: i2s
/*    */     //   2700: istore #22
/*    */     //   2702: iconst_3
/*    */     //   2703: bipush #12
/*    */     //   2705: iload #22
/*    */     //   2707: invokestatic cOm4 : (IIS)F
/*    */     //   2710: putfield z : F
/*    */     //   2713: getstatic f/eI.Pp : Lf/eo;
/*    */     //   2716: dup
/*    */     //   2717: astore #22
/*    */     //   2719: invokevirtual getClass : ()Ljava/lang/Class;
/*    */     //   2722: pop
/*    */     //   2723: goto -> 3013
/*    */     //   2726: aload #11
/*    */     //   2728: iload #18
/*    */     //   2730: invokevirtual getInt : (I)I
/*    */     //   2733: istore #22
/*    */     //   2735: iinc #18, 4
/*    */     //   2738: getstatic f/eI.UL0 : Lf/eo;
/*    */     //   2741: dup
/*    */     //   2742: astore #23
/*    */     //   2744: iload #22
/*    */     //   2746: aload #23
/*    */     //   2748: iload #22
/*    */     //   2750: ldc_w 65535
/*    */     //   2753: iand
/*    */     //   2754: i2s
/*    */     //   2755: istore #22
/*    */     //   2757: iconst_3
/*    */     //   2758: bipush #12
/*    */     //   2760: iload #22
/*    */     //   2762: invokestatic cOm4 : (IIS)F
/*    */     //   2765: putfield x : F
/*    */     //   2768: bipush #16
/*    */     //   2770: ishr
/*    */     //   2771: ldc_w 65535
/*    */     //   2774: iand
/*    */     //   2775: i2s
/*    */     //   2776: istore #22
/*    */     //   2778: iconst_3
/*    */     //   2779: bipush #12
/*    */     //   2781: iload #22
/*    */     //   2783: invokestatic cOm4 : (IIS)F
/*    */     //   2786: putfield y : F
/*    */     //   2789: getstatic f/eI.Pp : Lf/eo;
/*    */     //   2792: dup
/*    */     //   2793: astore #22
/*    */     //   2795: invokevirtual getClass : ()Ljava/lang/Class;
/*    */     //   2798: pop
/*    */     //   2799: goto -> 3013
/*    */     //   2802: aload #11
/*    */     //   2804: iload #18
/*    */     //   2806: invokevirtual getInt : (I)I
/*    */     //   2809: istore #22
/*    */     //   2811: iinc #18, 4
/*    */     //   2814: getstatic f/eI.UL0 : Lf/eo;
/*    */     //   2817: dup
/*    */     //   2818: astore #23
/*    */     //   2820: iload #22
/*    */     //   2822: aload #23
/*    */     //   2824: iload #22
/*    */     //   2826: aload #23
/*    */     //   2828: iload #22
/*    */     //   2830: sipush #1023
/*    */     //   2833: iand
/*    */     //   2834: i2s
/*    */     //   2835: istore #22
/*    */     //   2837: iconst_3
/*    */     //   2838: bipush #6
/*    */     //   2840: iload #22
/*    */     //   2842: invokestatic cOm4 : (IIS)F
/*    */     //   2845: putfield x : F
/*    */     //   2848: bipush #10
/*    */     //   2850: ishr
/*    */     //   2851: sipush #1023
/*    */     //   2854: iand
/*    */     //   2855: i2s
/*    */     //   2856: istore #22
/*    */     //   2858: iconst_3
/*    */     //   2859: bipush #6
/*    */     //   2861: iload #22
/*    */     //   2863: invokestatic cOm4 : (IIS)F
/*    */     //   2866: putfield y : F
/*    */     //   2869: bipush #20
/*    */     //   2871: ishr
/*    */     //   2872: sipush #1023
/*    */     //   2875: iand
/*    */     //   2876: i2s
/*    */     //   2877: istore #22
/*    */     //   2879: iconst_3
/*    */     //   2880: bipush #6
/*    */     //   2882: iload #22
/*    */     //   2884: invokestatic cOm4 : (IIS)F
/*    */     //   2887: putfield z : F
/*    */     //   2890: getstatic f/eI.Pp : Lf/eo;
/*    */     //   2893: dup
/*    */     //   2894: astore #22
/*    */     //   2896: invokevirtual getClass : ()Ljava/lang/Class;
/*    */     //   2899: pop
/*    */     //   2900: goto -> 3013
/*    */     //   2903: aload #11
/*    */     //   2905: iload #18
/*    */     //   2907: aload #11
/*    */     //   2909: iload #18
/*    */     //   2911: invokevirtual getInt : (I)I
/*    */     //   2914: istore #22
/*    */     //   2916: iconst_4
/*    */     //   2917: iadd
/*    */     //   2918: invokevirtual getInt : (I)I
/*    */     //   2921: istore #23
/*    */     //   2923: iinc #18, 8
/*    */     //   2926: getstatic f/eI.UL0 : Lf/eo;
/*    */     //   2929: dup
/*    */     //   2930: astore #24
/*    */     //   2932: iload #23
/*    */     //   2934: aload #24
/*    */     //   2936: iload #22
/*    */     //   2938: aload #24
/*    */     //   2940: iload #22
/*    */     //   2942: ldc_w 65535
/*    */     //   2945: iand
/*    */     //   2946: i2s
/*    */     //   2947: istore #22
/*    */     //   2949: iconst_3
/*    */     //   2950: bipush #12
/*    */     //   2952: iload #22
/*    */     //   2954: invokestatic cOm4 : (IIS)F
/*    */     //   2957: putfield x : F
/*    */     //   2960: bipush #16
/*    */     //   2962: ishr
/*    */     //   2963: ldc_w 65535
/*    */     //   2966: iand
/*    */     //   2967: i2s
/*    */     //   2968: istore #22
/*    */     //   2970: iconst_3
/*    */     //   2971: bipush #12
/*    */     //   2973: iload #22
/*    */     //   2975: invokestatic cOm4 : (IIS)F
/*    */     //   2978: putfield y : F
/*    */     //   2981: ldc_w 65535
/*    */     //   2984: iand
/*    */     //   2985: i2s
/*    */     //   2986: istore #22
/*    */     //   2988: iconst_3
/*    */     //   2989: bipush #12
/*    */     //   2991: iload #22
/*    */     //   2993: invokestatic cOm4 : (IIS)F
/*    */     //   2996: putfield z : F
/*    */     //   2999: getstatic f/eI.Pp : Lf/eo;
/*    */     //   3002: dup
/*    */     //   3003: astore #22
/*    */     //   3005: invokevirtual getClass : ()Ljava/lang/Class;
/*    */     //   3008: pop
/*    */     //   3009: aload #24
/*    */     //   3011: astore #23
/*    */     //   3013: aload #15
/*    */     //   3015: aload #22
/*    */     //   3017: aload #23
/*    */     //   3019: dup
/*    */     //   3020: dup
/*    */     //   3021: getfield x : F
/*    */     //   3024: fstore #22
/*    */     //   3026: getfield y : F
/*    */     //   3029: fstore #23
/*    */     //   3031: getfield z : F
/*    */     //   3034: fstore #24
/*    */     //   3036: fload #22
/*    */     //   3038: fload #23
/*    */     //   3040: fload #24
/*    */     //   3042: invokevirtual TG0 : (FFF)Lf/eo;
/*    */     //   3045: aload #7
/*    */     //   3047: swap
/*    */     //   3048: invokevirtual W70 : (Lf/is0;Lf/eo;)V
/*    */     //   3051: goto -> 3672
/*    */     //   3054: aload #13
/*    */     //   3056: aload #11
/*    */     //   3058: iload #18
/*    */     //   3060: aload #11
/*    */     //   3062: iload #18
/*    */     //   3064: invokevirtual getShort : (I)S
/*    */     //   3067: istore #22
/*    */     //   3069: bipush #11
/*    */     //   3071: iconst_4
/*    */     //   3072: iload #22
/*    */     //   3074: invokestatic cOm4 : (IIS)F
/*    */     //   3077: fstore #22
/*    */     //   3079: iconst_2
/*    */     //   3080: iadd
/*    */     //   3081: invokevirtual getShort : (I)S
/*    */     //   3084: istore #23
/*    */     //   3086: bipush #11
/*    */     //   3088: iconst_4
/*    */     //   3089: iload #23
/*    */     //   3091: invokestatic cOm4 : (IIS)F
/*    */     //   3094: fstore #23
/*    */     //   3096: iinc #18, 4
/*    */     //   3099: getfield hh0 : F
/*    */     //   3102: dup
/*    */     //   3103: fstore #24
/*    */     //   3105: fconst_0
/*    */     //   3106: fcmpl
/*    */     //   3107: ifle -> 3173
/*    */     //   3110: aload #13
/*    */     //   3112: getfield mc0 : F
/*    */     //   3115: dup
/*    */     //   3116: fstore #25
/*    */     //   3118: fconst_0
/*    */     //   3119: fcmpl
/*    */     //   3120: ifle -> 3173
/*    */     //   3123: fload #25
/*    */     //   3125: aload #13
/*    */     //   3127: fload #24
/*    */     //   3129: aload #13
/*    */     //   3131: getfield jw0 : I
/*    */     //   3134: i2f
/*    */     //   3135: fdiv
/*    */     //   3136: fload #22
/*    */     //   3138: fmul
/*    */     //   3139: aload #13
/*    */     //   3141: getfield Go : I
/*    */     //   3144: i2f
/*    */     //   3145: fconst_1
/*    */     //   3146: fadd
/*    */     //   3147: fdiv
/*    */     //   3148: fstore #22
/*    */     //   3150: getfield lpt6 : I
/*    */     //   3153: i2f
/*    */     //   3154: fdiv
/*    */     //   3155: fneg
/*    */     //   3156: fload #23
/*    */     //   3158: fmul
/*    */     //   3159: aload #13
/*    */     //   3161: getfield aB0 : I
/*    */     //   3164: i2f
/*    */     //   3165: fconst_1
/*    */     //   3166: fadd
/*    */     //   3167: fdiv
/*    */     //   3168: fstore #23
/*    */     //   3170: goto -> 3219
/*    */     //   3173: aload #13
/*    */     //   3175: dup
/*    */     //   3176: getfield jw0 : I
/*    */     //   3179: i2f
/*    */     //   3180: fconst_1
/*    */     //   3181: swap
/*    */     //   3182: fdiv
/*    */     //   3183: fload #22
/*    */     //   3185: fmul
/*    */     //   3186: aload #13
/*    */     //   3188: getfield Go : I
/*    */     //   3191: i2f
/*    */     //   3192: fconst_1
/*    */     //   3193: fadd
/*    */     //   3194: fdiv
/*    */     //   3195: fstore #22
/*    */     //   3197: getfield lpt6 : I
/*    */     //   3200: i2f
/*    */     //   3201: fconst_1
/*    */     //   3202: swap
/*    */     //   3203: fdiv
/*    */     //   3204: fneg
/*    */     //   3205: fload #23
/*    */     //   3207: fmul
/*    */     //   3208: aload #13
/*    */     //   3210: getfield aB0 : I
/*    */     //   3213: i2f
/*    */     //   3214: fconst_1
/*    */     //   3215: fadd
/*    */     //   3216: fdiv
/*    */     //   3217: fstore #23
/*    */     //   3219: aload #15
/*    */     //   3221: dup
/*    */     //   3222: getfield iG0 : Lf/NC0;
/*    */     //   3225: dup
/*    */     //   3226: fload #22
/*    */     //   3228: putfield x : F
/*    */     //   3231: fload #23
/*    */     //   3233: putfield y : F
/*    */     //   3236: iconst_1
/*    */     //   3237: putfield BK0 : Z
/*    */     //   3240: goto -> 3672
/*    */     //   3243: aload #15
/*    */     //   3245: dup
/*    */     //   3246: aload #11
/*    */     //   3248: iload #18
/*    */     //   3250: invokevirtual getInt : (I)I
/*    */     //   3253: dup
/*    */     //   3254: dup
/*    */     //   3255: iinc #18, 4
/*    */     //   3258: sipush #1023
/*    */     //   3261: iand
/*    */     //   3262: i2s
/*    */     //   3263: istore #22
/*    */     //   3265: iconst_0
/*    */     //   3266: bipush #9
/*    */     //   3268: iload #22
/*    */     //   3270: invokestatic cOm4 : (IIS)F
/*    */     //   3273: fstore #22
/*    */     //   3275: bipush #10
/*    */     //   3277: ishr
/*    */     //   3278: sipush #1023
/*    */     //   3281: iand
/*    */     //   3282: i2s
/*    */     //   3283: istore #23
/*    */     //   3285: iconst_0
/*    */     //   3286: bipush #9
/*    */     //   3288: iload #23
/*    */     //   3290: invokestatic cOm4 : (IIS)F
/*    */     //   3293: fstore #23
/*    */     //   3295: bipush #20
/*    */     //   3297: ishr
/*    */     //   3298: sipush #1023
/*    */     //   3301: iand
/*    */     //   3302: i2s
/*    */     //   3303: istore #24
/*    */     //   3305: iconst_0
/*    */     //   3306: bipush #9
/*    */     //   3308: iload #24
/*    */     //   3310: invokestatic cOm4 : (IIS)F
/*    */     //   3313: fstore #24
/*    */     //   3315: getfield Zo0 : Lf/eo;
/*    */     //   3318: fload #22
/*    */     //   3320: fload #23
/*    */     //   3322: fload #24
/*    */     //   3324: invokevirtual TG0 : (FFF)Lf/eo;
/*    */     //   3327: pop
/*    */     //   3328: iconst_1
/*    */     //   3329: putfield w6 : Z
/*    */     //   3332: goto -> 3672
/*    */     //   3335: iload #14
/*    */     //   3337: aload #11
/*    */     //   3339: iload #18
/*    */     //   3341: invokevirtual getInt : (I)I
/*    */     //   3344: i2l
/*    */     //   3345: lstore #22
/*    */     //   3347: iinc #18, 4
/*    */     //   3350: ifeq -> 3672
/*    */     //   3353: aload #15
/*    */     //   3355: dup
/*    */     //   3356: lload #22
/*    */     //   3358: dup2
/*    */     //   3359: dup2
/*    */     //   3360: ldc2_w 31
/*    */     //   3363: land
/*    */     //   3364: lstore #22
/*    */     //   3366: iconst_5
/*    */     //   3367: lshr
/*    */     //   3368: ldc2_w 31
/*    */     //   3371: land
/*    */     //   3372: lstore #24
/*    */     //   3374: bipush #10
/*    */     //   3376: lshr
/*    */     //   3377: ldc2_w 31
/*    */     //   3380: land
/*    */     //   3381: lload #24
/*    */     //   3383: lload #22
/*    */     //   3385: l2f
/*    */     //   3386: ldc_w 31.0
/*    */     //   3389: fdiv
/*    */     //   3390: fstore #22
/*    */     //   3392: l2f
/*    */     //   3393: ldc_w 31.0
/*    */     //   3396: fdiv
/*    */     //   3397: fstore #23
/*    */     //   3399: l2f
/*    */     //   3400: ldc_w 31.0
/*    */     //   3403: fdiv
/*    */     //   3404: fstore #24
/*    */     //   3406: getfield Qq0 : Lcom/badlogic/gdx/graphics/Color;
/*    */     //   3409: fload #22
/*    */     //   3411: fload #23
/*    */     //   3413: fload #24
/*    */     //   3415: fconst_1
/*    */     //   3416: invokevirtual set : (FFFF)Lcom/badlogic/gdx/graphics/Color;
/*    */     //   3419: pop
/*    */     //   3420: iconst_1
/*    */     //   3421: putfield K70 : Z
/*    */     //   3424: goto -> 3672
/*    */     //   3427: iload #18
/*    */     //   3429: sipush #128
/*    */     //   3432: iadd
/*    */     //   3433: istore #18
/*    */     //   3435: goto -> 3672
/*    */     //   3438: aload #11
/*    */     //   3440: iload #18
/*    */     //   3442: invokevirtual getInt : (I)I
/*    */     //   3445: pop
/*    */     //   3446: iinc #18, 4
/*    */     //   3449: goto -> 3672
/*    */     //   3452: iinc #18, 8
/*    */     //   3455: goto -> 3672
/*    */     //   3458: iinc #18, 12
/*    */     //   3461: goto -> 3672
/*    */     //   3464: ldc_w '0x'
/*    */     //   3467: invokestatic df : (Ljava/lang/String;)Ljava/lang/StringBuilder;
/*    */     //   3470: swap
/*    */     //   3471: invokestatic toHexString : (I)Ljava/lang/String;
/*    */     //   3474: invokevirtual toUpperCase : ()Ljava/lang/String;
/*    */     //   3477: invokevirtual append : (Ljava/lang/String;)Ljava/lang/StringBuilder;
/*    */     //   3480: invokevirtual toString : ()Ljava/lang/String;
/*    */     //   3483: invokevirtual append : (Ljava/lang/String;)Ljava/lang/StringBuilder;
/*    */     //   3486: invokevirtual toString : ()Ljava/lang/String;
/*    */     //   3489: invokevirtual println : (Ljava/lang/String;)V
/*    */     //   3492: goto -> 3672
/*    */     //   3495: aload #16
/*    */     //   3497: aload #15
/*    */     //   3499: dup
/*    */     //   3500: aload #16
/*    */     //   3502: dup
/*    */     //   3503: aload #15
/*    */     //   3505: aload #16
/*    */     //   3507: aload #15
/*    */     //   3509: aload #16
/*    */     //   3511: aload #15
/*    */     //   3513: aload #16
/*    */     //   3515: aload #15
/*    */     //   3517: aload #16
/*    */     //   3519: dup
/*    */     //   3520: dup
/*    */     //   3521: iconst_4
/*    */     //   3522: invokestatic s6 : (I)[I
/*    */     //   3525: iload #17
/*    */     //   3527: iaload
/*    */     //   3528: istore #22
/*    */     //   3530: getfield e60 : I
/*    */     //   3533: aload #15
/*    */     //   3535: getfield ud0 : I
/*    */     //   3538: iadd
/*    */     //   3539: putfield e60 : I
/*    */     //   3542: getfield fK : Lf/G3;
/*    */     //   3545: dup
/*    */     //   3546: astore #23
/*    */     //   3548: aload #15
/*    */     //   3550: getfield ax0 : Lf/G3;
/*    */     //   3553: dup
/*    */     //   3554: aload #23
/*    */     //   3556: invokevirtual getClass : ()Ljava/lang/Class;
/*    */     //   3559: pop
/*    */     //   3560: getfield By0 : [F
/*    */     //   3563: astore #23
/*    */     //   3565: getfield NB0 : I
/*    */     //   3568: iconst_0
/*    */     //   3569: swap
/*    */     //   3570: aload #23
/*    */     //   3572: invokevirtual p : (II[F)V
/*    */     //   3575: getfield tO : Z
/*    */     //   3578: putfield hJ : Z
/*    */     //   3581: getfield K70 : Z
/*    */     //   3584: putfield Um : Z
/*    */     //   3587: getfield w6 : Z
/*    */     //   3590: putfield Do0 : Z
/*    */     //   3593: getfield BK0 : Z
/*    */     //   3596: putfield Cf : Z
/*    */     //   3599: getfield Tm : Lf/fQ;
/*    */     //   3602: new f/tB0
/*    */     //   3605: dup
/*    */     //   3606: iload #22
/*    */     //   3608: aload #15
/*    */     //   3610: getfield ud0 : I
/*    */     //   3613: invokespecial <init> : (II)V
/*    */     //   3616: invokevirtual Com3 : (Ljava/lang/Object;)V
/*    */     //   3619: iconst_0
/*    */     //   3620: putfield ud0 : I
/*    */     //   3623: getfield ax0 : Lf/G3;
/*    */     //   3626: iconst_0
/*    */     //   3627: putfield NB0 : I
/*    */     //   3630: getfield eH : I
/*    */     //   3633: aload #12
/*    */     //   3635: getfield Pw : I
/*    */     //   3638: dup
/*    */     //   3639: istore #22
/*    */     //   3641: if_icmpge -> 3672
/*    */     //   3644: aload #16
/*    */     //   3646: iload #22
/*    */     //   3648: putfield eH : I
/*    */     //   3651: goto -> 3672
/*    */     //   3654: aload #11
/*    */     //   3656: iload #18
/*    */     //   3658: invokevirtual getInt : (I)I
/*    */     //   3661: istore #17
/*    */     //   3663: iinc #18, 4
/*    */     //   3666: goto -> 3672
/*    */     //   3669: iinc #18, 4
/*    */     //   3672: iinc #21, 1
/*    */     //   3675: goto -> 1551
/*    */     //   3678: aload #16
/*    */     //   3680: aload #12
/*    */     //   3682: iload #9
/*    */     //   3684: iconst_1
/*    */     //   3685: iadd
/*    */     //   3686: istore #11
/*    */     //   3688: iload #9
/*    */     //   3690: putfield Pw : I
/*    */     //   3693: ifnull -> 3703
/*    */     //   3696: aload #4
/*    */     //   3698: aload #16
/*    */     //   3700: invokevirtual Com3 : (Ljava/lang/Object;)V
/*    */     //   3703: iload #11
/*    */     //   3705: istore #9
/*    */     //   3707: goto -> 373
/*    */     //   3710: aload #8
/*    */     //   3712: invokevirtual get : ()B
/*    */     //   3715: istore #10
/*    */     //   3717: goto -> 373
/*    */     //   3720: aload #7
/*    */     //   3722: aload #8
/*    */     //   3724: invokevirtual get : ()B
/*    */     //   3727: istore #11
/*    */     //   3729: getfield pm : Lf/gv0;
/*    */     //   3732: dup
/*    */     //   3733: dup2
/*    */     //   3734: astore #12
/*    */     //   3736: aload #7
/*    */     //   3738: getfield kK0 : [Lf/gv0;
/*    */     //   3741: iload #11
/*    */     //   3743: aaload
/*    */     //   3744: astore #11
/*    */     //   3746: invokevirtual getClass : ()Ljava/lang/Class;
/*    */     //   3749: pop
/*    */     //   3750: aload #11
/*    */     //   3752: getfield Jb : I
/*    */     //   3755: putfield Jb : I
/*    */     //   3758: aload #11
/*    */     //   3760: aload #12
/*    */     //   3762: dup
/*    */     //   3763: getfield Yo : Lf/fQ;
/*    */     //   3766: invokevirtual clear : ()V
/*    */     //   3769: getfield Yo : Lf/fQ;
/*    */     //   3772: aload #11
/*    */     //   3774: getfield Yo : Lf/fQ;
/*    */     //   3777: invokevirtual OG0 : (Lf/fQ;)V
/*    */     //   3780: getfield Z0 : [F
/*    */     //   3783: invokevirtual Qw : ([F)Lcom/badlogic/gdx/math/Matrix4;
/*    */     //   3786: pop
/*    */     //   3787: goto -> 373
/*    */     //   3790: aload #8
/*    */     //   3792: dup
/*    */     //   3793: invokevirtual get : ()B
/*    */     //   3796: pop
/*    */     //   3797: invokevirtual get : ()B
/*    */     //   3800: pop
/*    */     //   3801: goto -> 373
/*    */     //   3804: aload_0
/*    */     //   3805: dup
/*    */     //   3806: aload #4
/*    */     //   3808: iload #6
/*    */     //   3810: invokestatic ct : (Lf/hC;Lf/fQ;Z)Lf/YW;
/*    */     //   3813: aload_1
/*    */     //   3814: aload #4
/*    */     //   3816: aload_3
/*    */     //   3817: invokestatic oe : (Lf/hC;Lf/YW;Lf/vf0;Lf/fQ;Lf/fQ;)Lf/cf0;
/*    */     //   3820: astore #4
/*    */     //   3822: new f/lpt1
/*    */     //   3825: dup
/*    */     //   3826: dup2
/*    */     //   3827: aload_2
/*    */     //   3828: swap
/*    */     //   3829: aload #4
/*    */     //   3831: aload_0
/*    */     //   3832: dup
/*    */     //   3833: getfield Ih : Ljava/lang/String;
/*    */     //   3836: astore_0
/*    */     //   3837: getfield Sw : F
/*    */     //   3840: aload_0
/*    */     //   3841: swap
/*    */     //   3842: aload_1
/*    */     //   3843: invokespecial <init> : (Lf/cf0;Ljava/lang/String;FLf/Ew;)V
/*    */     //   3846: aload_1
/*    */     //   3847: aload_3
/*    */     //   3848: invokestatic aI : (Lf/lpt1;Lf/Wd;Lf/Ew;Lf/fQ;)V
/*    */     //   3851: invokevirtual kg0 : ()V
/*    */     //   3854: areturn
/*    */     //   3855: astore_0
/*    */     //   3856: getstatic f/eI.cR : Lf/is0;
/*    */     //   3859: dup
/*    */     //   3860: dup
/*    */     //   3861: astore_1
/*    */     //   3862: getfield pm : Lf/gv0;
/*    */     //   3865: invokevirtual WU : ()Lcom/badlogic/gdx/math/Matrix4;
/*    */     //   3868: pop
/*    */     //   3869: getfield pm : Lf/gv0;
/*    */     //   3872: dup
/*    */     //   3873: iconst_0
/*    */     //   3874: putfield Jb : I
/*    */     //   3877: getfield Yo : Lf/fQ;
/*    */     //   3880: invokevirtual clear : ()V
/*    */     //   3883: iconst_0
/*    */     //   3884: istore_2
/*    */     //   3885: iload_2
/*    */     //   3886: aload_1
/*    */     //   3887: getfield kK0 : [Lf/gv0;
/*    */     //   3890: dup
/*    */     //   3891: astore_3
/*    */     //   3892: arraylength
/*    */     //   3893: if_icmpge -> 3926
/*    */     //   3896: aload_1
/*    */     //   3897: aload_3
/*    */     //   3898: iload_2
/*    */     //   3899: aaload
/*    */     //   3900: invokevirtual WU : ()Lcom/badlogic/gdx/math/Matrix4;
/*    */     //   3903: pop
/*    */     //   3904: getfield kK0 : [Lf/gv0;
/*    */     //   3907: iload_2
/*    */     //   3908: aaload
/*    */     //   3909: dup
/*    */     //   3910: iconst_0
/*    */     //   3911: putfield Jb : I
/*    */     //   3914: getfield Yo : Lf/fQ;
/*    */     //   3917: invokevirtual clear : ()V
/*    */     //   3920: iinc #2, 1
/*    */     //   3923: goto -> 3885
/*    */     //   3926: aload_0
/*    */     //   3927: athrow
/*    */     // Line number table:
/*    */     //   Java source line number -> byte code offset
/*    */     //   #1	-> 7
/*    */     //   #2	-> 10
/*    */     //   #3	-> 85
/*    */     //   #4	-> 318
/*    */     //   #5	-> 342
/*    */     //   #6	-> 483
/*    */     //   #7	-> 487
/*    */     //   #8	-> 507
/*    */     //   #9	-> 512
/*    */     //   #10	-> 520
/*    */     //   #11	-> 533
/*    */     //   #12	-> 537
/*    */     //   #13	-> 557
/*    */     //   #14	-> 562
/*    */     //   #15	-> 571
/*    */     //   #16	-> 577
/*    */     //   #17	-> 584
/*    */     //   #18	-> 658
/*    */     //   #19	-> 665
/*    */     //   #20	-> 688
/*    */     //   #21	-> 717
/*    */     //   #22	-> 729
/*    */     //   #23	-> 773
/*    */     //   #24	-> 784
/*    */     //   #25	-> 791
/*    */     //   #26	-> 814
/*    */     //   #27	-> 856
/*    */     //   #28	-> 993
/*    */     //   #29	-> 1002
/*    */     //   #30	-> 1016
/*    */     //   #31	-> 1056
/*    */     //   #32	-> 1104
/*    */     //   #33	-> 1116
/*    */     //   #34	-> 1139
/*    */     //   #35	-> 1181
/*    */     //   #36	-> 1208
/*    */     //   #37	-> 1211
/*    */     //   #38	-> 1247
/*    */     //   #39	-> 1279
/*    */     //   #40	-> 1288
/*    */     //   #41	-> 1291
/*    */     //   #42	-> 1295
/*    */     //   #43	-> 1300
/*    */     //   #44	-> 1311
/*    */     //   #45	-> 1325
/*    */     //   #46	-> 1337
/*    */     //   #47	-> 1342
/*    */     //   #48	-> 1345
/*    */     //   #49	-> 1363
/*    */     //   #50	-> 1369
/*    */     //   #51	-> 1389
/*    */     //   #52	-> 1392
/*    */     //   #53	-> 1401
/*    */     //   #54	-> 1475
/*    */     //   #55	-> 1803
/*    */     //   #56	-> 1813
/*    */     //   #57	-> 1880
/*    */     //   #58	-> 1885
/*    */     //   #59	-> 1908
/*    */     //   #60	-> 1947
/*    */     //   #61	-> 1951
/*    */     //   #62	-> 1971
/*    */     //   #63	-> 1976
/*    */     //   #64	-> 1986
/*    */     //   #65	-> 2330
/*    */     //   #66	-> 2353
/*    */     //   #67	-> 2396
/*    */     //   #68	-> 2411
/*    */     //   #69	-> 2420
/*    */     //   #70	-> 2423
/*    */     //   #71	-> 2427
/*    */     //   #72	-> 2437
/*    */     //   #73	-> 3021
/*    */     //   #74	-> 3048
/*    */     //   #75	-> 3222
/*    */     //   #76	-> 3228
/*    */     //   #77	-> 3233
/*    */     //   #78	-> 3237
/*    */     //   #79	-> 3250
/*    */     //   #80	-> 3315
/*    */     //   #81	-> 3341
/*    */     //   #82	-> 3406
/*    */     //   #83	-> 3442
/*    */     //   #84	-> 3464
/*    */     //   #85	-> 3471
/*    */     //   #86	-> 3483
/*    */     //   #87	-> 3522
/*    */     //   #88	-> 3527
/*    */     //   #89	-> 3530
/*    */     //   #90	-> 3560
/*    */     //   #91	-> 3575
/*    */     //   #92	-> 3578
/*    */     //   #93	-> 3581
/*    */     //   #94	-> 3584
/*    */     //   #95	-> 3587
/*    */     //   #96	-> 3590
/*    */     //   #97	-> 3593
/*    */     //   #98	-> 3596
/*    */     //   #99	-> 3620
/*    */     //   #100	-> 3627
/*    */     //   #101	-> 3630
/*    */     //   #102	-> 3690
/*    */     //   #103	-> 3729
/*    */     //   #104	-> 3738
/*    */     //   #105	-> 3752
/*    */     //   #106	-> 3793
/*    */     //   #107	-> 3810
/*    */     //   #108	-> 3862
/*    */     //   #109	-> 3865
/*    */     //   #110	-> 3927
/*    */     // Exception table:
/*    */     //   from	to	target	type
/*    */     //   3813	3820	3855	java/lang/Exception
/*    */   }
/*    */   
/*    */   public static pe0[] Mf0(Wd paramWd, fQ paramfQ, int[] paramArrayOfint, int paramInt, Ew paramEw, boolean paramBoolean) {
/*    */     this();
/*    */     HashMap<Object, Object> hashMap1, hashMap2;
/*    */     this();
/*    */     byte b;
/*    */     Hc0 hc0;
/*    */     for (b = 0, hc0 = paramfQ.r30(); hc0.hasNext(); ) {
/*    */       String str = (String)hc0.next();
/*    */       byte b2 = (byte)(b + 1);
/*    */       hashMap1.put(Byte.valueOf(b), str);
/*    */       byte b1 = b2;
/*    */     } 
/*    */     for (Iterator<Map.Entry> iterator = hashMap1.entrySet().iterator(); iterator.hasNext(); ) {
/*    */       ZH zH;
/*    */       Texture texture;
/*    */       Map.Entry<?, String> entry;
/*    */       String str = (entry = iterator.next()).getValue();
/*    */       Integer integer;
/*    */       if ((integer = (Integer)paramWd.K5.pd0(str)) != null) {
/*    */         zH = Wd.IV((fk0)paramWd.TE.yO(integer.intValue()), paramArrayOfint);
/*    */       } else {
/*    */         zi.error("Couldn't find " + zH);
/*    */         zH = null;
/*    */       } 
/*    */       if (zH == null) {
/*    */         zi.error(B40.df("Couldn't create pixmap from ").append(entry.getValue()).toString());
/*    */         return null;
/*    */       } 
/*    */       if (paramBoolean) {
/*    */         zH = FX.hY(zH);
/*    */         zH.dispose();
/*    */       } 
/*    */       this(new AB(zH, null, false, false, false));
/*    */       (new Texture()).setFilter(cu0.Fh, cu0.Fh);
/*    */       if (paramEw.Ro == null) {
/*    */         fQ fQ1;
/*    */         this();
/*    */         paramEw.Ro = fQ1;
/*    */       } 
/*    */       paramEw.Ro.Com3(texture);
/*    */       hashMap2.put(entry.getKey(), new pe0(texture));
/*    */       zH.dispose();
/*    */     } 
/*    */     return (pe0[])hashMap2.values().toArray((Object[])new pe0[0]);
/*    */   }
/*    */   
/*    */   public static cf0 oe(hC paramhC, YW paramYW, vf0 paramvf0, fQ paramfQ1, fQ paramfQ2) {
/*    */     // Byte code:
/*    */     //   0: aload_3
/*    */     //   1: new f/cf0
/*    */     //   4: dup
/*    */     //   5: astore #5
/*    */     //   7: aload_1
/*    */     //   8: aload_2
/*    */     //   9: invokespecial <init> : (Lf/YW;Lf/vf0;)V
/*    */     //   12: new f/fQ
/*    */     //   15: invokespecial <init> : ()V
/*    */     //   18: invokevirtual r30 : ()Lf/Hc0;
/*    */     //   21: astore_1
/*    */     //   22: aload_1
/*    */     //   23: invokevirtual hasNext : ()Z
/*    */     //   26: ifeq -> 138
/*    */     //   29: aload #5
/*    */     //   31: aload_0
/*    */     //   32: aload #5
/*    */     //   34: dup
/*    */     //   35: aload_1
/*    */     //   36: invokevirtual next : ()Ljava/lang/Object;
/*    */     //   39: checkcast f/c50
/*    */     //   42: dup
/*    */     //   43: astore_2
/*    */     //   44: getfield Ar : Ljava/lang/String;
/*    */     //   47: astore #6
/*    */     //   49: iconst_1
/*    */     //   50: istore #7
/*    */     //   52: getfield O0 : Lf/fQ;
/*    */     //   55: aload #6
/*    */     //   57: iload #7
/*    */     //   59: invokestatic le0 : (Lf/fQ;Ljava/lang/String;Z)Lf/zP;
/*    */     //   62: astore #6
/*    */     //   64: getfield O0 : Lf/fQ;
/*    */     //   67: aload #6
/*    */     //   69: iconst_1
/*    */     //   70: invokevirtual Ct : (Ljava/lang/Object;Z)Z
/*    */     //   73: pop
/*    */     //   74: getfield Os0 : Lf/fQ;
/*    */     //   77: aload_2
/*    */     //   78: getfield s3 : I
/*    */     //   81: invokevirtual get : (I)Ljava/lang/Object;
/*    */     //   84: checkcast f/vY
/*    */     //   87: getfield Ih : Ljava/lang/String;
/*    */     //   90: astore_2
/*    */     //   91: iconst_1
/*    */     //   92: istore #7
/*    */     //   94: getfield O0 : Lf/fQ;
/*    */     //   97: aload_2
/*    */     //   98: iload #7
/*    */     //   100: invokestatic le0 : (Lf/fQ;Ljava/lang/String;Z)Lf/zP;
/*    */     //   103: ifnonnull -> 116
/*    */     //   106: getstatic f/eI.zi : Lf/ik;
/*    */     //   109: invokevirtual getClass : ()Ljava/lang/Class;
/*    */     //   112: pop
/*    */     //   113: goto -> 22
/*    */     //   116: aload #5
/*    */     //   118: iconst_1
/*    */     //   119: istore #7
/*    */     //   121: getfield O0 : Lf/fQ;
/*    */     //   124: aload_2
/*    */     //   125: iload #7
/*    */     //   127: invokestatic le0 : (Lf/fQ;Ljava/lang/String;Z)Lf/zP;
/*    */     //   130: aload #6
/*    */     //   132: invokevirtual V0 : (Lf/zP;)V
/*    */     //   135: goto -> 22
/*    */     //   138: aload #4
/*    */     //   140: aload #5
/*    */     //   142: getfield O0 : Lf/fQ;
/*    */     //   145: iconst_0
/*    */     //   146: invokevirtual get : (I)Ljava/lang/Object;
/*    */     //   149: checkcast f/zP
/*    */     //   152: getfield nH : Lf/eo;
/*    */     //   155: aload_0
/*    */     //   156: getfield Sw : F
/*    */     //   159: fconst_1
/*    */     //   160: swap
/*    */     //   161: fdiv
/*    */     //   162: invokevirtual uu : (F)Lf/eo;
/*    */     //   165: pop
/*    */     //   166: ifnull -> 1065
/*    */     //   169: aload #5
/*    */     //   171: getfield cs : Lf/fQ;
/*    */     //   174: getfield Z8 : I
/*    */     //   177: ifne -> 1065
/*    */     //   180: aload #4
/*    */     //   182: invokevirtual r30 : ()Lf/Hc0;
/*    */     //   185: astore_1
/*    */     //   186: aload_1
/*    */     //   187: invokevirtual hasNext : ()Z
/*    */     //   190: ifeq -> 1065
/*    */     //   193: aload_1
/*    */     //   194: invokevirtual next : ()Ljava/lang/Object;
/*    */     //   197: checkcast f/IK0
/*    */     //   200: dup
/*    */     //   201: dup
/*    */     //   202: astore_2
/*    */     //   203: invokevirtual getClass : ()Ljava/lang/Class;
/*    */     //   206: pop
/*    */     //   207: instanceof f/PK
/*    */     //   210: ifeq -> 186
/*    */     //   213: aload_0
/*    */     //   214: aload_2
/*    */     //   215: aload #5
/*    */     //   217: getfield cs : Lf/fQ;
/*    */     //   220: astore_2
/*    */     //   221: checkcast f/PK
/*    */     //   224: astore #4
/*    */     //   226: new f/d4
/*    */     //   229: dup
/*    */     //   230: astore #6
/*    */     //   232: aload #4
/*    */     //   234: aload #6
/*    */     //   236: aload #4
/*    */     //   238: aload #6
/*    */     //   240: invokespecial <init> : ()V
/*    */     //   243: getfield Kc : Ljava/lang/String;
/*    */     //   246: putfield Ge : Ljava/lang/String;
/*    */     //   249: getfield GF0 : Lf/Yy0;
/*    */     //   252: getfield ai0 : Lf/fQ;
/*    */     //   255: invokevirtual first : ()Ljava/lang/Object;
/*    */     //   258: checkcast f/vO
/*    */     //   261: checkcast f/Lw0
/*    */     //   264: getfield Zz0 : I
/*    */     //   267: iconst_1
/*    */     //   268: isub
/*    */     //   269: i2f
/*    */     //   270: ldc_w 0.033333335
/*    */     //   273: fmul
/*    */     //   274: putfield Cd0 : F
/*    */     //   277: new f/fQ
/*    */     //   280: dup
/*    */     //   281: astore #7
/*    */     //   283: invokespecial <init> : ()V
/*    */     //   286: getfield Os0 : Lf/fQ;
/*    */     //   289: invokevirtual r30 : ()Lf/Hc0;
/*    */     //   292: astore #8
/*    */     //   294: aload #8
/*    */     //   296: invokevirtual hasNext : ()Z
/*    */     //   299: ifeq -> 338
/*    */     //   302: aload #7
/*    */     //   304: aload #5
/*    */     //   306: aload #8
/*    */     //   308: invokevirtual next : ()Ljava/lang/Object;
/*    */     //   311: checkcast f/vY
/*    */     //   314: getfield Ih : Ljava/lang/String;
/*    */     //   317: astore #9
/*    */     //   319: iconst_1
/*    */     //   320: istore #10
/*    */     //   322: getfield O0 : Lf/fQ;
/*    */     //   325: aload #9
/*    */     //   327: iload #10
/*    */     //   329: invokestatic le0 : (Lf/fQ;Ljava/lang/String;Z)Lf/zP;
/*    */     //   332: invokevirtual Com3 : (Ljava/lang/Object;)V
/*    */     //   335: goto -> 294
/*    */     //   338: aload #4
/*    */     //   340: getfield GF0 : Lf/Yy0;
/*    */     //   343: getfield ai0 : Lf/fQ;
/*    */     //   346: invokevirtual first : ()Ljava/lang/Object;
/*    */     //   349: checkcast f/vO
/*    */     //   352: checkcast f/Lw0
/*    */     //   355: getfield zJ : [Lf/tf0;
/*    */     //   358: astore #4
/*    */     //   360: iconst_0
/*    */     //   361: istore #7
/*    */     //   363: iload #7
/*    */     //   365: aload_0
/*    */     //   366: getfield Os0 : Lf/fQ;
/*    */     //   369: dup
/*    */     //   370: astore #8
/*    */     //   372: getfield Z8 : I
/*    */     //   375: if_icmpge -> 1056
/*    */     //   378: aload #4
/*    */     //   380: arraylength
/*    */     //   381: iload #7
/*    */     //   383: if_icmpgt -> 396
/*    */     //   386: getstatic f/eI.zi : Lf/ik;
/*    */     //   389: invokevirtual getClass : ()Ljava/lang/Class;
/*    */     //   392: pop
/*    */     //   393: goto -> 1050
/*    */     //   396: aload #4
/*    */     //   398: iload #7
/*    */     //   400: aload #8
/*    */     //   402: iload #7
/*    */     //   404: invokevirtual get : (I)Ljava/lang/Object;
/*    */     //   407: checkcast f/vY
/*    */     //   410: astore #8
/*    */     //   412: aaload
/*    */     //   413: dup
/*    */     //   414: dup
/*    */     //   415: astore #9
/*    */     //   417: invokevirtual getClass : ()Ljava/lang/Class;
/*    */     //   420: pop
/*    */     //   421: new f/Kj0
/*    */     //   424: dup
/*    */     //   425: astore #10
/*    */     //   427: invokespecial <init> : ()V
/*    */     //   430: invokevirtual Qp0 : ()Z
/*    */     //   433: ifeq -> 639
/*    */     //   436: aload #9
/*    */     //   438: aload #10
/*    */     //   440: new f/fQ
/*    */     //   443: dup
/*    */     //   444: dup
/*    */     //   445: astore #11
/*    */     //   447: invokespecial <init> : ()V
/*    */     //   450: putfield gc : Lf/fQ;
/*    */     //   453: getfield qf : I
/*    */     //   456: i2l
/*    */     //   457: dup2
/*    */     //   458: lstore #12
/*    */     //   460: ldc2_w 8
/*    */     //   463: land
/*    */     //   464: lconst_0
/*    */     //   465: lcmp
/*    */     //   466: ifeq -> 495
/*    */     //   469: lload #12
/*    */     //   471: ldc2_w 16
/*    */     //   474: land
/*    */     //   475: lconst_0
/*    */     //   476: lcmp
/*    */     //   477: ifeq -> 495
/*    */     //   480: lload #12
/*    */     //   482: ldc2_w 32
/*    */     //   485: land
/*    */     //   486: lconst_0
/*    */     //   487: lcmp
/*    */     //   488: ifeq -> 495
/*    */     //   491: iconst_1
/*    */     //   492: goto -> 496
/*    */     //   495: iconst_0
/*    */     //   496: ifeq -> 557
/*    */     //   499: aload #11
/*    */     //   501: new f/w6
/*    */     //   504: dup
/*    */     //   505: new f/eo
/*    */     //   508: dup
/*    */     //   509: astore #11
/*    */     //   511: aload #9
/*    */     //   513: getfield iu0 : Lf/SK;
/*    */     //   516: iconst_0
/*    */     //   517: invokevirtual Xs : (I)F
/*    */     //   520: aload #9
/*    */     //   522: dup
/*    */     //   523: getfield T : Lf/SK;
/*    */     //   526: iconst_0
/*    */     //   527: invokevirtual Xs : (I)F
/*    */     //   530: fstore #12
/*    */     //   532: getfield YE : Lf/SK;
/*    */     //   535: iconst_0
/*    */     //   536: invokevirtual Xs : (I)F
/*    */     //   539: fload #12
/*    */     //   541: swap
/*    */     //   542: invokespecial <init> : (FFF)V
/*    */     //   545: fconst_0
/*    */     //   546: aload #11
/*    */     //   548: invokespecial <init> : (FLjava/lang/Object;)V
/*    */     //   551: invokevirtual Com3 : (Ljava/lang/Object;)V
/*    */     //   554: goto -> 639
/*    */     //   557: iconst_0
/*    */     //   558: istore #11
/*    */     //   560: iload #11
/*    */     //   562: aload #9
/*    */     //   564: getfield nJ : I
/*    */     //   567: if_icmpge -> 639
/*    */     //   570: aload #10
/*    */     //   572: getfield gc : Lf/fQ;
/*    */     //   575: new f/w6
/*    */     //   578: dup
/*    */     //   579: iload #11
/*    */     //   581: i2f
/*    */     //   582: ldc_w 0.033333335
/*    */     //   585: fmul
/*    */     //   586: new f/eo
/*    */     //   589: dup
/*    */     //   590: aload #9
/*    */     //   592: getfield iu0 : Lf/SK;
/*    */     //   595: iload #11
/*    */     //   597: invokevirtual Xs : (I)F
/*    */     //   600: aload #9
/*    */     //   602: dup
/*    */     //   603: getfield T : Lf/SK;
/*    */     //   606: iload #11
/*    */     //   608: invokevirtual Xs : (I)F
/*    */     //   611: fstore #12
/*    */     //   613: getfield YE : Lf/SK;
/*    */     //   616: iload #11
/*    */     //   618: invokevirtual Xs : (I)F
/*    */     //   621: fload #12
/*    */     //   623: swap
/*    */     //   624: invokespecial <init> : (FFF)V
/*    */     //   627: invokespecial <init> : (FLjava/lang/Object;)V
/*    */     //   630: invokevirtual Com3 : (Ljava/lang/Object;)V
/*    */     //   633: iinc #11, 1
/*    */     //   636: goto -> 560
/*    */     //   639: aload #9
/*    */     //   641: invokevirtual Lx0 : ()Z
/*    */     //   644: ifeq -> 773
/*    */     //   647: aload #9
/*    */     //   649: aload #10
/*    */     //   651: new f/fQ
/*    */     //   654: dup
/*    */     //   655: invokespecial <init> : ()V
/*    */     //   658: putfield I9 : Lf/fQ;
/*    */     //   661: invokevirtual Id : ()Z
/*    */     //   664: ifeq -> 709
/*    */     //   667: aload #10
/*    */     //   669: getfield I9 : Lf/fQ;
/*    */     //   672: new f/w6
/*    */     //   675: dup
/*    */     //   676: new f/TG0
/*    */     //   679: dup
/*    */     //   680: aload #9
/*    */     //   682: swap
/*    */     //   683: invokespecial <init> : ()V
/*    */     //   686: getfield Zt0 : Lf/U1;
/*    */     //   689: iconst_0
/*    */     //   690: invokevirtual tG : (I)Lcom/badlogic/gdx/math/Matrix4;
/*    */     //   693: iconst_1
/*    */     //   694: swap
/*    */     //   695: invokevirtual dJ : (ZLcom/badlogic/gdx/math/Matrix4;)Lf/TG0;
/*    */     //   698: fconst_0
/*    */     //   699: swap
/*    */     //   700: invokespecial <init> : (FLjava/lang/Object;)V
/*    */     //   703: invokevirtual Com3 : (Ljava/lang/Object;)V
/*    */     //   706: goto -> 773
/*    */     //   709: iconst_0
/*    */     //   710: istore #11
/*    */     //   712: iload #11
/*    */     //   714: aload #9
/*    */     //   716: getfield nJ : I
/*    */     //   719: if_icmpge -> 773
/*    */     //   722: aload #10
/*    */     //   724: getfield I9 : Lf/fQ;
/*    */     //   727: new f/w6
/*    */     //   730: dup
/*    */     //   731: iload #11
/*    */     //   733: i2f
/*    */     //   734: ldc_w 0.033333335
/*    */     //   737: fmul
/*    */     //   738: new f/TG0
/*    */     //   741: dup
/*    */     //   742: aload #9
/*    */     //   744: swap
/*    */     //   745: invokespecial <init> : ()V
/*    */     //   748: getfield Zt0 : Lf/U1;
/*    */     //   751: iload #11
/*    */     //   753: invokevirtual tG : (I)Lcom/badlogic/gdx/math/Matrix4;
/*    */     //   756: iconst_1
/*    */     //   757: swap
/*    */     //   758: invokevirtual dJ : (ZLcom/badlogic/gdx/math/Matrix4;)Lf/TG0;
/*    */     //   761: invokespecial <init> : (FLjava/lang/Object;)V
/*    */     //   764: invokevirtual Com3 : (Ljava/lang/Object;)V
/*    */     //   767: iinc #11, 1
/*    */     //   770: goto -> 712
/*    */     //   773: aload #9
/*    */     //   775: invokevirtual LL0 : ()Z
/*    */     //   778: ifeq -> 984
/*    */     //   781: aload #9
/*    */     //   783: aload #10
/*    */     //   785: new f/fQ
/*    */     //   788: dup
/*    */     //   789: dup
/*    */     //   790: astore #11
/*    */     //   792: invokespecial <init> : ()V
/*    */     //   795: putfield lp : Lf/fQ;
/*    */     //   798: getfield qf : I
/*    */     //   801: i2l
/*    */     //   802: dup2
/*    */     //   803: lstore #12
/*    */     //   805: ldc2_w 2048
/*    */     //   808: land
/*    */     //   809: lconst_0
/*    */     //   810: lcmp
/*    */     //   811: ifeq -> 840
/*    */     //   814: lload #12
/*    */     //   816: ldc2_w 4096
/*    */     //   819: land
/*    */     //   820: lconst_0
/*    */     //   821: lcmp
/*    */     //   822: ifeq -> 840
/*    */     //   825: lload #12
/*    */     //   827: ldc2_w 8192
/*    */     //   830: land
/*    */     //   831: lconst_0
/*    */     //   832: lcmp
/*    */     //   833: ifeq -> 840
/*    */     //   836: iconst_1
/*    */     //   837: goto -> 841
/*    */     //   840: iconst_0
/*    */     //   841: ifeq -> 902
/*    */     //   844: aload #11
/*    */     //   846: new f/w6
/*    */     //   849: dup
/*    */     //   850: new f/eo
/*    */     //   853: dup
/*    */     //   854: astore #11
/*    */     //   856: aload #9
/*    */     //   858: getfield Gt0 : Lf/Jw0;
/*    */     //   861: iconst_0
/*    */     //   862: invokevirtual wg0 : (I)F
/*    */     //   865: aload #9
/*    */     //   867: dup
/*    */     //   868: getfield Ye : Lf/Jw0;
/*    */     //   871: iconst_0
/*    */     //   872: invokevirtual wg0 : (I)F
/*    */     //   875: fstore #9
/*    */     //   877: getfield ED0 : Lf/Jw0;
/*    */     //   880: iconst_0
/*    */     //   881: invokevirtual wg0 : (I)F
/*    */     //   884: fload #9
/*    */     //   886: swap
/*    */     //   887: invokespecial <init> : (FFF)V
/*    */     //   890: fconst_0
/*    */     //   891: aload #11
/*    */     //   893: invokespecial <init> : (FLjava/lang/Object;)V
/*    */     //   896: invokevirtual Com3 : (Ljava/lang/Object;)V
/*    */     //   899: goto -> 984
/*    */     //   902: iconst_0
/*    */     //   903: istore #11
/*    */     //   905: iload #11
/*    */     //   907: aload #9
/*    */     //   909: getfield nJ : I
/*    */     //   912: if_icmpge -> 984
/*    */     //   915: aload #10
/*    */     //   917: getfield lp : Lf/fQ;
/*    */     //   920: new f/w6
/*    */     //   923: dup
/*    */     //   924: iload #11
/*    */     //   926: i2f
/*    */     //   927: ldc_w 0.033333335
/*    */     //   930: fmul
/*    */     //   931: new f/eo
/*    */     //   934: dup
/*    */     //   935: aload #9
/*    */     //   937: getfield Gt0 : Lf/Jw0;
/*    */     //   940: iload #11
/*    */     //   942: invokevirtual wg0 : (I)F
/*    */     //   945: aload #9
/*    */     //   947: dup
/*    */     //   948: getfield Ye : Lf/Jw0;
/*    */     //   951: iload #11
/*    */     //   953: invokevirtual wg0 : (I)F
/*    */     //   956: fstore #12
/*    */     //   958: getfield ED0 : Lf/Jw0;
/*    */     //   961: iload #11
/*    */     //   963: invokevirtual wg0 : (I)F
/*    */     //   966: fload #12
/*    */     //   968: swap
/*    */     //   969: invokespecial <init> : (FFF)V
/*    */     //   972: invokespecial <init> : (FLjava/lang/Object;)V
/*    */     //   975: invokevirtual Com3 : (Ljava/lang/Object;)V
/*    */     //   978: iinc #11, 1
/*    */     //   981: goto -> 905
/*    */     //   984: aload #5
/*    */     //   986: aload #8
/*    */     //   988: getfield Ih : Ljava/lang/String;
/*    */     //   991: astore #8
/*    */     //   993: iconst_1
/*    */     //   994: istore #9
/*    */     //   996: getfield O0 : Lf/fQ;
/*    */     //   999: aload #8
/*    */     //   1001: iload #9
/*    */     //   1003: invokestatic le0 : (Lf/fQ;Ljava/lang/String;Z)Lf/zP;
/*    */     //   1006: dup
/*    */     //   1007: aload #10
/*    */     //   1009: swap
/*    */     //   1010: putfield WW : Lf/zP;
/*    */     //   1013: ifnull -> 1050
/*    */     //   1016: aload #10
/*    */     //   1018: getfield I9 : Lf/fQ;
/*    */     //   1021: ifnonnull -> 1040
/*    */     //   1024: aload #10
/*    */     //   1026: getfield lp : Lf/fQ;
/*    */     //   1029: ifnonnull -> 1040
/*    */     //   1032: aload #10
/*    */     //   1034: getfield gc : Lf/fQ;
/*    */     //   1037: ifnull -> 1050
/*    */     //   1040: aload #6
/*    */     //   1042: getfield Jg : Lf/fQ;
/*    */     //   1045: aload #10
/*    */     //   1047: invokevirtual Com3 : (Ljava/lang/Object;)V
/*    */     //   1050: iinc #7, 1
/*    */     //   1053: goto -> 363
/*    */     //   1056: aload_2
/*    */     //   1057: aload #6
/*    */     //   1059: invokevirtual Com3 : (Ljava/lang/Object;)V
/*    */     //   1062: goto -> 186
/*    */     //   1065: aload_3
/*    */     //   1066: invokevirtual r30 : ()Lf/Hc0;
/*    */     //   1069: astore_1
/*    */     //   1070: aload_1
/*    */     //   1071: invokevirtual hasNext : ()Z
/*    */     //   1074: ifeq -> 1598
/*    */     //   1077: aload #5
/*    */     //   1079: aload_1
/*    */     //   1080: invokevirtual next : ()Ljava/lang/Object;
/*    */     //   1083: checkcast f/c50
/*    */     //   1086: dup
/*    */     //   1087: astore_2
/*    */     //   1088: getfield mR : Lf/tC;
/*    */     //   1091: dup
/*    */     //   1092: astore_3
/*    */     //   1093: getfield Ih : Ljava/lang/String;
/*    */     //   1096: astore #4
/*    */     //   1098: getfield s30 : Lf/fQ;
/*    */     //   1101: getfield Z8 : I
/*    */     //   1104: istore #6
/*    */     //   1106: iconst_0
/*    */     //   1107: istore #7
/*    */     //   1109: iload #7
/*    */     //   1111: iload #6
/*    */     //   1113: if_icmpge -> 1152
/*    */     //   1116: aload #5
/*    */     //   1118: getfield s30 : Lf/fQ;
/*    */     //   1121: iload #7
/*    */     //   1123: invokevirtual get : (I)Ljava/lang/Object;
/*    */     //   1126: checkcast f/T0
/*    */     //   1129: dup
/*    */     //   1130: astore #8
/*    */     //   1132: getfield Xy0 : Ljava/lang/String;
/*    */     //   1135: aload #4
/*    */     //   1137: invokevirtual equalsIgnoreCase : (Ljava/lang/String;)Z
/*    */     //   1140: ifeq -> 1146
/*    */     //   1143: goto -> 1155
/*    */     //   1146: iinc #7, 1
/*    */     //   1149: goto -> 1109
/*    */     //   1152: aconst_null
/*    */     //   1153: astore #8
/*    */     //   1155: aload_3
/*    */     //   1156: aload #8
/*    */     //   1158: dup
/*    */     //   1159: new f/Xf0
/*    */     //   1162: dup
/*    */     //   1163: aload_3
/*    */     //   1164: getstatic f/Xf0.xZ : J
/*    */     //   1167: lstore #6
/*    */     //   1169: getfield LpT7 : I
/*    */     //   1172: istore #4
/*    */     //   1174: lload #6
/*    */     //   1176: iload #4
/*    */     //   1178: invokespecial <init> : (JI)V
/*    */     //   1181: invokevirtual Tz0 : (Lf/dj;)V
/*    */     //   1184: new f/IF
/*    */     //   1187: dup
/*    */     //   1188: aload_3
/*    */     //   1189: getfield gw : I
/*    */     //   1192: iconst_1
/*    */     //   1193: invokespecial <init> : (IZ)V
/*    */     //   1196: invokevirtual Tz0 : (Lf/dj;)V
/*    */     //   1199: getfield kI : Z
/*    */     //   1202: ifeq -> 1275
/*    */     //   1205: aload_3
/*    */     //   1206: getfield nA : Lcom/badlogic/gdx/graphics/Color;
/*    */     //   1209: dup
/*    */     //   1210: astore #4
/*    */     //   1212: getfield r : F
/*    */     //   1215: ldc_w 0.25
/*    */     //   1218: fcmpl
/*    */     //   1219: ifle -> 1275
/*    */     //   1222: aload #4
/*    */     //   1224: getfield g : F
/*    */     //   1227: ldc_w 0.25
/*    */     //   1230: fcmpl
/*    */     //   1231: ifle -> 1275
/*    */     //   1234: aload #4
/*    */     //   1236: getfield b : F
/*    */     //   1239: ldc_w 0.25
/*    */     //   1242: fcmpl
/*    */     //   1243: ifle -> 1275
/*    */     //   1246: aload #8
/*    */     //   1248: new f/qo
/*    */     //   1251: dup
/*    */     //   1252: astore #4
/*    */     //   1254: aload_3
/*    */     //   1255: getstatic f/qo.iu0 : J
/*    */     //   1258: lstore #6
/*    */     //   1260: getfield nA : Lcom/badlogic/gdx/graphics/Color;
/*    */     //   1263: astore_3
/*    */     //   1264: lload #6
/*    */     //   1266: aload_3
/*    */     //   1267: invokespecial <init> : (JLcom/badlogic/gdx/graphics/Color;)V
/*    */     //   1270: aload #4
/*    */     //   1272: invokevirtual Tz0 : (Lf/dj;)V
/*    */     //   1275: aload #8
/*    */     //   1277: getfield Xy0 : Ljava/lang/String;
/*    */     //   1280: ldc_w 'c4g_arch1_lm2'
/*    */     //   1283: invokevirtual equals : (Ljava/lang/Object;)Z
/*    */     //   1286: ifne -> 1317
/*    */     //   1289: aload #8
/*    */     //   1291: getfield Xy0 : Ljava/lang/String;
/*    */     //   1294: ldc_w 'sh'
/*    */     //   1297: invokevirtual equals : (Ljava/lang/Object;)Z
/*    */     //   1300: ifne -> 1317
/*    */     //   1303: aload #8
/*    */     //   1305: getfield Xy0 : Ljava/lang/String;
/*    */     //   1308: ldc_w 't3_fl_'
/*    */     //   1311: invokevirtual startsWith : (Ljava/lang/String;)Z
/*    */     //   1314: ifeq -> 1326
/*    */     //   1317: aload_2
/*    */     //   1318: getfield mR : Lf/tC;
/*    */     //   1321: bipush #6
/*    */     //   1323: putfield T1 : I
/*    */     //   1326: aload_2
/*    */     //   1327: getfield mR : Lf/tC;
/*    */     //   1330: getfield T1 : I
/*    */     //   1333: dup
/*    */     //   1334: istore_3
/*    */     //   1335: bipush #6
/*    */     //   1337: if_icmpeq -> 1353
/*    */     //   1340: iload_3
/*    */     //   1341: iconst_1
/*    */     //   1342: if_icmpne -> 1348
/*    */     //   1345: goto -> 1353
/*    */     //   1348: iconst_0
/*    */     //   1349: istore_3
/*    */     //   1350: goto -> 1355
/*    */     //   1353: iconst_1
/*    */     //   1354: istore_3
/*    */     //   1355: iload_3
/*    */     //   1356: ifeq -> 1381
/*    */     //   1359: aload #8
/*    */     //   1361: new f/Ra
/*    */     //   1364: dup
/*    */     //   1365: getstatic f/Ra.SG0 : J
/*    */     //   1368: aload_2
/*    */     //   1369: getfield mR : Lf/tC;
/*    */     //   1372: getfield T1 : I
/*    */     //   1375: invokespecial <init> : (JI)V
/*    */     //   1378: invokevirtual Tz0 : (Lf/dj;)V
/*    */     //   1381: iload_3
/*    */     //   1382: ifne -> 1407
/*    */     //   1385: aload_2
/*    */     //   1386: getfield mR : Lf/tC;
/*    */     //   1389: dup
/*    */     //   1390: astore_3
/*    */     //   1391: getfield g30 : F
/*    */     //   1394: fconst_1
/*    */     //   1395: fcmpg
/*    */     //   1396: iflt -> 1407
/*    */     //   1399: aload_3
/*    */     //   1400: getfield SS : I
/*    */     //   1403: iconst_1
/*    */     //   1404: if_icmpne -> 1443
/*    */     //   1407: aload #8
/*    */     //   1409: dup
/*    */     //   1410: new f/zc
/*    */     //   1413: dup
/*    */     //   1414: aload_2
/*    */     //   1415: getfield mR : Lf/tC;
/*    */     //   1418: getfield g30 : F
/*    */     //   1421: invokespecial <init> : (F)V
/*    */     //   1424: invokevirtual Tz0 : (Lf/dj;)V
/*    */     //   1427: new f/LPT9
/*    */     //   1430: dup
/*    */     //   1431: getstatic f/LPT9.It0 : J
/*    */     //   1434: ldc_w 0.01
/*    */     //   1437: invokespecial <init> : (JF)V
/*    */     //   1440: invokevirtual Tz0 : (Lf/dj;)V
/*    */     //   1443: aload_0
/*    */     //   1444: getfield Ih : Ljava/lang/String;
/*    */     //   1447: ldc_w 'm_gift01_00_00c'
/*    */     //   1450: invokevirtual equalsIgnoreCase : (Ljava/lang/String;)Z
/*    */     //   1453: ifeq -> 1490
/*    */     //   1456: aload #8
/*    */     //   1458: getfield Xy0 : Ljava/lang/String;
/*    */     //   1461: ldc_w 'lambert8'
/*    */     //   1464: invokevirtual equalsIgnoreCase : (Ljava/lang/String;)Z
/*    */     //   1467: ifeq -> 1490
/*    */     //   1470: aload #8
/*    */     //   1472: new f/zc
/*    */     //   1475: dup
/*    */     //   1476: astore_2
/*    */     //   1477: ldc_w 0.45
/*    */     //   1480: invokespecial <init> : (F)V
/*    */     //   1483: aload_2
/*    */     //   1484: invokevirtual Tz0 : (Lf/dj;)V
/*    */     //   1487: goto -> 1070
/*    */     //   1490: aload_0
/*    */     //   1491: getfield Ih : Ljava/lang/String;
/*    */     //   1494: ldc_w 'c1_s03'
/*    */     //   1497: invokevirtual equalsIgnoreCase : (Ljava/lang/String;)Z
/*    */     //   1500: ifeq -> 1537
/*    */     //   1503: aload #8
/*    */     //   1505: getfield Xy0 : Ljava/lang/String;
/*    */     //   1508: ldc_w 'lambert7'
/*    */     //   1511: invokevirtual equalsIgnoreCase : (Ljava/lang/String;)Z
/*    */     //   1514: ifeq -> 1537
/*    */     //   1517: aload #8
/*    */     //   1519: new f/zc
/*    */     //   1522: dup
/*    */     //   1523: astore_2
/*    */     //   1524: ldc_w 0.75
/*    */     //   1527: invokespecial <init> : (F)V
/*    */     //   1530: aload_2
/*    */     //   1531: invokevirtual Tz0 : (Lf/dj;)V
/*    */     //   1534: goto -> 1070
/*    */     //   1537: aload_0
/*    */     //   1538: getfield Ih : Ljava/lang/String;
/*    */     //   1541: ldc_w 'm_dun'
/*    */     //   1544: invokevirtual startsWith : (Ljava/lang/String;)Z
/*    */     //   1547: ifeq -> 1070
/*    */     //   1550: aload #8
/*    */     //   1552: getfield Xy0 : Ljava/lang/String;
/*    */     //   1555: ldc_w 'light_lm1'
/*    */     //   1558: invokevirtual equalsIgnoreCase : (Ljava/lang/String;)Z
/*    */     //   1561: ifne -> 1578
/*    */     //   1564: aload #8
/*    */     //   1566: getfield Xy0 : Ljava/lang/String;
/*    */     //   1569: ldc_w 'd_light'
/*    */     //   1572: invokevirtual equalsIgnoreCase : (Ljava/lang/String;)Z
/*    */     //   1575: ifeq -> 1070
/*    */     //   1578: aload #8
/*    */     //   1580: new f/zc
/*    */     //   1583: dup
/*    */     //   1584: astore_2
/*    */     //   1585: ldc_w 0.99
/*    */     //   1588: invokespecial <init> : (F)V
/*    */     //   1591: aload_2
/*    */     //   1592: invokevirtual Tz0 : (Lf/dj;)V
/*    */     //   1595: goto -> 1070
/*    */     //   1598: aload #5
/*    */     //   1600: areturn
/*    */     // Line number table:
/*    */     //   Java source line number -> byte code offset
/*    */     //   #1	-> 52
/*    */     //   #2	-> 64
/*    */     //   #3	-> 94
/*    */     //   #4	-> 106
/*    */     //   #5	-> 121
/*    */     //   #6	-> 132
/*    */     //   #7	-> 207
/*    */     //   #8	-> 217
/*    */     //   #9	-> 226
/*    */     //   #10	-> 249
/*    */     //   #11	-> 252
/*    */     //   #12	-> 255
/*    */     //   #13	-> 261
/*    */     //   #14	-> 264
/*    */     //   #15	-> 322
/*    */     //   #16	-> 332
/*    */     //   #17	-> 340
/*    */     //   #18	-> 343
/*    */     //   #19	-> 346
/*    */     //   #20	-> 352
/*    */     //   #21	-> 355
/*    */     //   #22	-> 366
/*    */     //   #23	-> 421
/*    */     //   #24	-> 453
/*    */     //   #25	-> 501
/*    */     //   #26	-> 798
/*    */     //   #27	-> 846
/*    */     //   #28	-> 988
/*    */     //   #29	-> 996
/*    */     //   #30	-> 1010
/*    */     //   #31	-> 1059
/*    */     //   #32	-> 1098
/*    */     //   #33	-> 1159
/*    */   }
/*    */   
/*    */   public static YW ct(hC paramhC, fQ paramfQ, boolean paramBoolean) {
/*    */     this();
/*    */     YW yW;
/*    */     Jp jp;
/*    */     this();
/*    */     (new Jp()).Qk0 = "Aramature";
/*    */     (new Jp()).pB = new eo(1.0F, 1.0F, 1.0F);
/*    */     jp.JX = arrayOfJp;
/*    */     Jp[] arrayOfJp;
/*    */     (arrayOfJp = new Jp[1])[0] = hF(paramhC, (vY)paramhC.Os0.get(0));
/*    */     (new YW()).nG0.Com3(jp);
/*    */     int i;
/*    */     Hc0 hc0;
/*    */     for (i = 0, hc0 = paramfQ.r30(); hc0.hasNext(); ) {
/*    */       String str2;
/*    */       fQ fQ1;
/*    */       byte b;
/*    */       mZ mZ;
/*    */       fQ fQ2;
/*    */       String str1 = Integer.toString(++i);
/*    */       c50 c50;
/*    */       if ("default".equals((c50 = (c50)hc0.next()).Ar)) {
/*    */         str2 = m0.tF0("node", str1);
/*    */       } else {
/*    */         str2 = c50.Ar;
/*    */       } 
/*    */       "default".equals(c50.Ar);
/*    */       if ("default".equals(c50.Ar)) {
/*    */         str1 = m0.tF0("part", str1);
/*    */       } else {
/*    */         str1 = c50.Ar;
/*    */       } 
/*    */       f7 f7 = null;
/*    */       int j = 3;
/*    */       j = (c50.Do0 ? 3 : 0) + j;
/*    */       if (c50.Um) {
/*    */         b = 4;
/*    */       } else {
/*    */         b = 0;
/*    */       } 
/*    */       j += b;
/*    */       if (c50.Cf) {
/*    */         b = 2;
/*    */       } else {
/*    */         b = 0;
/*    */       } 
/*    */       j += b;
/*    */       if (paramBoolean) {
/*    */         this();
/*    */         for (b = 0; b < c50.e60; ) {
/*    */           vY vY = (vY)paramhC.Os0.get((int)c50.fK.cON((j + 2) * b + j));
/*    */           f7.X00(Integer.valueOf((int)c50.fK.cON((j + 2) * b + j)), vY);
/*    */           b++;
/*    */         } 
/*    */         fQ1 = f7.W5().sk0();
/*    */       } 
/*    */       for (Hc0 hc01 = c50.Tm.r30(); hc01.hasNext(); ) {
/*    */         int i2, n = ((tB0)hc01.next()).xz;
/*    */         switch (Zk0.yE(((tB0)hc01.next()).aq)) {
/*    */           default:
/*    */             continue;
/*    */           case 3:
/*    */             for (i1 = 0; (i2 = i1 + 2) < n; ) {
/*    */               c50.o1.X3(c50.R3(c50.Y7 + i1, c50.e60));
/*    */               c50.o1.X3(c50.R3(c50.Y7 + i1 + 1, c50.e60));
/*    */               c50.o1.X3(c50.R3(c50.Y7 + i1 + 2, c50.e60));
/*    */               if (i1 + 3 < n) {
/*    */                 c50.o1.X3(c50.R3(c50.Y7 + i1 + 1, c50.e60));
/*    */                 c50.o1.X3(c50.R3(c50.Y7 + i1 + 3, c50.e60));
/*    */                 c50.o1.X3(c50.R3(c50.Y7 + i1 + 2, c50.e60));
/*    */               } 
/*    */               i1 = i2;
/*    */             } 
/*    */             c50.Y7 += n;
/*    */             continue;
/*    */           case 2:
/*    */             for (i1 = 0; (i2 = i1 + 2) < n; ) {
/*    */               c50.o1.X3(c50.R3(c50.Y7 + i1, c50.e60));
/*    */               c50.o1.X3(c50.R3(c50.Y7 + i1 + 1, c50.e60));
/*    */               c50.o1.X3(c50.R3(c50.Y7 + i1 + 2, c50.e60));
/*    */               if (i1 + 3 < n) {
/*    */                 c50.o1.X3(c50.R3(c50.Y7 + i1 + 1, c50.e60));
/*    */                 c50.o1.X3(c50.R3(c50.Y7 + i1 + 3, c50.e60));
/*    */                 c50.o1.X3(c50.R3(c50.Y7 + i1 + 2, c50.e60));
/*    */               } 
/*    */               i1 = i2;
/*    */             } 
/*    */             c50.Y7 += n;
/*    */             continue;
/*    */           case 1:
/*    */             for (i1 = 0; i1 < n; ) {
/*    */               c50.o1.X3(c50.R3(c50.Y7, c50.e60));
/*    */               c50.o1.X3(c50.R3(c50.Y7 + 1, c50.e60));
/*    */               c50.o1.X3(c50.R3(c50.Y7 + 2, c50.e60));
/*    */               c50.o1.X3(c50.R3(c50.Y7, c50.e60));
/*    */               c50.o1.X3(c50.R3(c50.Y7 + 2, c50.e60));
/*    */               c50.o1.X3(c50.R3(c50.Y7 + 3, c50.e60));
/*    */               c50.Y7 += 4;
/*    */               i1 += 4;
/*    */             } 
/*    */             continue;
/*    */           case 0:
/*    */             break;
/*    */         } 
/*    */         for (int i1 = 0; i1 < n; ) {
/*    */           c50.o1.X3(c50.R3(c50.Y7, c50.e60));
/*    */           c50.o1.X3(c50.R3(c50.Y7 + 1, c50.e60));
/*    */           c50.o1.X3(c50.R3(c50.Y7 + 2, c50.e60));
/*    */           c50.Y7 += 3;
/*    */           i1 += 3;
/*    */         } 
/*    */       } 
/*    */       this();
/*    */       this();
/*    */       (new fQ()).Com3(new lw0(1, 3, "a_position"));
/*    */       if (c50.Do0) {
/*    */         lw0 lw0;
/*    */         this(8, 3, "a_normal");
/*    */         fQ2.Com3(lw0);
/*    */       } 
/*    */       if (c50.Um) {
/*    */         lw0 lw0;
/*    */         this(2, 4, 5126, false, "a_color");
/*    */         fQ2.Com3(lw0);
/*    */       } 
/*    */       if (c50.Cf) {
/*    */         lw0 lw0;
/*    */         this(16, 2, "a_texCoord0");
/*    */         fQ2.Com3(lw0);
/*    */       } 
/*    */       if (c50.hJ) {
/*    */         lw0 lw0;
/*    */         this(64, 2, "a_boneWeight0");
/*    */         fQ2.Com3(lw0);
/*    */       } 
/*    */       mZ.e7 = (lw0[])fQ2.Ib(lw0.class);
/*    */       System.arraycopy(g3.By0, 0, arrayOfFloat, 0, k);
/*    */       G3 g3;
/*    */       int k;
/*    */       float[] arrayOfFloat = new float[k = (g3 = c50.fK).NB0];
/*    */       this();
/*    */       ow0.Qp0 = str1;
/*    */       System.arraycopy(wk0.YJ0, 0, arrayOfShort, 0, m);
/*    */       ow0 ow0;
/*    */       Wk0 wk0;
/*    */       int m;
/*    */       short[] arrayOfShort = new short[m = (wk0 = c50.o1).AK0];
/*    */       (new ow0()).Ff0 = 4;
/*    */       mZ.i2 = new ow0[] { ow0 };
/*    */       if (paramBoolean) {
/*    */         byte b1 = 0;
/*    */         while (b1 < c50.e60) {
/*    */           int n = (j + 2) * b1 + j;
/*    */           float[] arrayOfFloat1;
/*    */           (arrayOfFloat1 = mZ.qL0)[n] = fQ1.JF0(Integer.valueOf((int)arrayOfFloat1[n]), false);
/*    */           b1++;
/*    */         } 
/*    */       } 
/*    */       yW.Lg.Com3(mZ);
/*    */       this();
/*    */       Jp jp1;
/*    */       (jp1 = new Jp()).Qk0 = str2;
/*    */       (new Jp()).XD0 = new eo();
/*    */       (new Jp()).Ea0 = new TG0();
/*    */       (new Jp()).pB = new eo(1.0F, 1.0F, 1.0F);
/*    */       this();
/*    */       bj0.E00 = str1;
/*    */       bj0 bj0;
/*    */       (bj0 = new bj0()).const = c50.mR.Ih;
/*    */       if (c50.hJ && paramBoolean) {
/*    */         eM eM;
/*    */         this(true, paramfQ.Z8, String.class, Matrix4.class);
/*    */         Hc0 hc02;
/*    */         label120: for (bj0.fu = eM, hc02 = fQ1.r30(); hc02.hasNext(); ) {
/*    */           Matrix4 matrix42;
/*    */           int n = ((Integer)hc02.next()).intValue();
/*    */           vY vY;
/*    */           Matrix4 matrix41;
/*    */           (matrix41 = (vY = (vY)paramhC.Os0.get(n)).qX).getClass();
/*    */           this(matrix41);
/*    */           if ((new Matrix4()).eA() == 0.0F) {
/*    */             this();
/*    */             float[] arrayOfFloat1;
/*    */             byte b1;
/*    */             for ((arrayOfFloat1 = new float[m = 4])[0] = 1.0E-6F, (new float[m = 4])[1] = 1.0E-5F, (new float[m = 4])[2] = 1.0E-4F, (new float[m = 4])[3] = 0.001F, b1 = 0; b1 < m; ) {
/*    */               float f = arrayOfFloat1[b1];
/*    */               matrix41.WU();
/*    */               matrix41.Z0[0] = f;
/*    */               matrix41.Z0[5] = f;
/*    */               matrix41.Z0[10] = f;
/*    */               byte b2 = 0;
/*    */               float[] arrayOfFloat2;
/*    */               while (b2 < (arrayOfFloat2 = matrix42.Z0).length) {
/*    */                 arrayOfFloat2[b2] = arrayOfFloat2[b2] + matrix41.Z0[b2];
/*    */                 b2++;
/*    */               } 
/*    */               if (matrix42.eA() != 0.0F) {
/*    */                 matrix41 = matrix42;
/*    */                 continue label120;
/*    */               } 
/*    */               b1++;
/*    */             } 
/*    */             if (matrix42.eA() == 0.0F)
/*    */               matrix41 = null; 
/*    */             if (matrix41 == null) {
/*    */               matrix42.toString();
/*    */               zi.getClass();
/*    */               matrix42.Jo(vY.G8);
/*    */             } 
/*    */           } 
/*    */           bj0.fu.Ed0(((vY)paramhC.Os0.get(n)).Ih, matrix42);
/*    */         } 
/*    */       } 
/*    */       jp1.Sz = new bj0[] { bj0 };
/*    */       yW.nG0.Com3(jp1);
/*    */       this();
/*    */       QD qD;
/*    */       (qD = new QD()).KJ0 = c50.mR.Ih;
/*    */       this();
/*    */       ri0.kH = 2;
/*    */       Ri0 ri0;
/*    */       (ri0 = new Ri0()).i0 = c50.mR.Ih;
/*    */       if ((new QD()).Oi0 == null) {
/*    */         fQ fQ3;
/*    */         this(1);
/*    */         qD.Oi0 = fQ3;
/*    */       } 
/*    */       qD.Oi0.Com3(ri0);
/*    */       yW.ID.Com3(qD);
/*    */     } 
/*    */     return yW;
/*    */   }
/*    */   
/*    */   public static Jp hF(hC paramhC, vY paramvY) {
/*    */     this();
/*    */     jp.Qk0 = paramvY.Ih;
/*    */     jp.XD0 = paramvY.G8;
/*    */     jp.pB = paramvY.cJ;
/*    */     jp.Ea0 = paramvY.z30;
/*    */     Jp jp;
/*    */     (jp = new Jp()).JX = new Jp[paramvY.D30.Z8];
/*    */     for (byte b = 0; b < jp.JX.length; b++) {
/*    */       int i = ((Integer)paramvY.D30.get(b)).intValue();
/*    */       jp.JX[b] = hF(paramhC, (vY)paramhC.Os0.get(i));
/*    */     } 
/*    */     return jp;
/*    */   }
/*    */   
/*    */   public static lpt1 Gp(int paramInt) {
/*    */     return Yp0((byte)3, paramInt, true);
/*    */   } }


/* Location:              /Users/vnnsnnt/Documents/Codespace/JavaWorkspace/RedTrainer/src/main/java/org/trainer/client/PokeMMO.jar!/f/eI.class
 * Java compiler version: 8 (52.0)
 * JD-Core Version:       1.1.3
 */