package f;

public final class eq0 {
  public static final ik LPT9 = C00.gd(eq0.class);
  
  public int QE = 0;
  
  public boolean wm0 = false;
  
  public int F70 = -1;
  
  public int n8;
  
  public int tI0 = 0;
  
  public final int re() {
    // Byte code:
    //   0: aload_0
    //   1: getfield wm0 : Z
    //   4: ifeq -> 50
    //   7: aload_0
    //   8: getfield QE : I
    //   11: invokestatic currentTimeMillis : ()J
    //   14: ldc2_w 1000
    //   17: ldiv
    //   18: l2i
    //   19: aload_0
    //   20: getfield n8 : I
    //   23: isub
    //   24: isub
    //   25: dup
    //   26: istore_1
    //   27: ifge -> 32
    //   30: iconst_0
    //   31: istore_1
    //   32: aload_0
    //   33: getfield F70 : I
    //   36: dup
    //   37: istore_0
    //   38: ifle -> 48
    //   41: iload_1
    //   42: iload_0
    //   43: if_icmple -> 48
    //   46: iload_0
    //   47: istore_1
    //   48: iload_1
    //   49: ireturn
    //   50: aload_0
    //   51: getfield QE : I
    //   54: dup
    //   55: istore_0
    //   56: ifge -> 61
    //   59: iconst_0
    //   60: ireturn
    //   61: iload_0
    //   62: ireturn
  }
}


/* Location:              /Users/vnnsnnt/Documents/Codespace/JavaWorkspace/RedTrainer/src/main/java/org/trainer/client/PokeMMO.jar!/f/eq0.class
 * Java compiler version: 8 (52.0)
 * JD-Core Version:       1.1.3
 */