/*  1 */ package f;public final class ex extends Ip implements r60 { public final Bf XO; public int aJ; public int nV; public Un[] Tn; public Ip Kz; private void F4(LPT3 paramLPT3, Bf paramBf, int paramInt, j40 paramj40, byte paramByte) { if (paramLPT3.EA && this
/*  2 */       .ZI == 1)
/*  3 */     { pA.Dg0
/*  4 */         .Nr(paramBf, paramInt, paramj40, paramByte); } else { System.out.println(paramBf.getClass());
/*  5 */       short s = paramLPT3.bj0;
/*  6 */       int i = paramj40.Jg;
/*  7 */       paramBf.ZN(s, paramInt, i, (short)1, paramByte); }  } public mc[] tH; public dQ k7; public p30 nB0; public final int ZI; public ex(Bf paramBf, LPT3 paramLPT3, int paramInt, j40 paramj40) { // Byte code:
/*    */     //   0: aload_1
/*    */     //   1: aload_0
/*    */     //   2: aload_1
/*    */     //   3: aload_0
/*    */     //   4: dup
/*    */     //   5: dup
/*    */     //   6: invokespecial <init> : ()V
/*    */     //   9: iconst_2
/*    */     //   10: putfield nV : I
/*    */     //   13: iconst_0
/*    */     //   14: anewarray f/Un
/*    */     //   17: putfield Tn : [Lf/Un;
/*    */     //   20: putfield XO : Lf/Bf;
/*    */     //   23: instanceof f/wg0
/*    */     //   26: ifeq -> 37
/*    */     //   29: aload_0
/*    */     //   30: iconst_1
/*    */     //   31: putfield ZI : I
/*    */     //   34: goto -> 42
/*    */     //   37: aload_0
/*    */     //   38: iconst_2
/*    */     //   39: putfield ZI : I
/*    */     //   42: aload_0
/*    */     //   43: getfield ZI : I
/*    */     //   46: iconst_1
/*    */     //   47: if_icmpne -> 59
/*    */     //   50: aload_0
/*    */     //   51: ldc 'hud-panel-invis'
/*    */     //   53: invokevirtual Xu : (Ljava/lang/String;)V
/*    */     //   56: goto -> 65
/*    */     //   59: aload_0
/*    */     //   60: ldc 'battle-panel-dark'
/*    */     //   62: invokevirtual Xu : (Ljava/lang/String;)V
/*    */     //   65: aload_2
/*    */     //   66: aload #4
/*    */     //   68: invokevirtual eC : ()Lf/Q90;
/*    */     //   71: astore #5
/*    */     //   73: invokevirtual Ue0 : ()B
/*    */     //   76: iconst_1
/*    */     //   77: if_icmpge -> 84
/*    */     //   80: iconst_1
/*    */     //   81: goto -> 85
/*    */     //   84: iconst_0
/*    */     //   85: new f/dQ
/*    */     //   88: astore #6
/*    */     //   90: getstatic f/F40.ef0 : Lf/F40;
/*    */     //   93: astore #7
/*    */     //   95: sipush #157
/*    */     //   98: istore #8
/*    */     //   100: ifeq -> 110
/*    */     //   103: bipush #22
/*    */     //   105: istore #9
/*    */     //   107: goto -> 114
/*    */     //   110: bipush #21
/*    */     //   112: istore #9
/*    */     //   114: aload_0
/*    */     //   115: dup
/*    */     //   116: dup
/*    */     //   117: aload #6
/*    */     //   119: dup
/*    */     //   120: aload #7
/*    */     //   122: iload #8
/*    */     //   124: iload #9
/*    */     //   126: invokestatic Qf0 : (Lf/F40;II)Ljava/lang/String;
/*    */     //   129: invokespecial <init> : (Ljava/lang/String;)V
/*    */     //   132: putfield k7 : Lf/dQ;
/*    */     //   135: new f/Ip
/*    */     //   138: dup
/*    */     //   139: invokespecial <init> : ()V
/*    */     //   142: putfield Kz : Lf/Ip;
/*    */     //   145: iconst_4
/*    */     //   146: anewarray f/mc
/*    */     //   149: putfield tH : [Lf/mc;
/*    */     //   152: iconst_0
/*    */     //   153: istore #6
/*    */     //   155: iload #6
/*    */     //   157: iconst_4
/*    */     //   158: if_icmpge -> 540
/*    */     //   161: aload #5
/*    */     //   163: iload #6
/*    */     //   165: aload_0
/*    */     //   166: dup
/*    */     //   167: getfield tH : [Lf/mc;
/*    */     //   170: iload #6
/*    */     //   172: new f/Dg0
/*    */     //   175: dup
/*    */     //   176: astore #7
/*    */     //   178: aload_0
/*    */     //   179: iload #6
/*    */     //   181: invokespecial <init> : (Lf/ex;I)V
/*    */     //   184: aload #7
/*    */     //   186: aastore
/*    */     //   187: getfield tH : [Lf/mc;
/*    */     //   190: iload #6
/*    */     //   192: aaload
/*    */     //   193: ldc 'item-move-dialog-button'
/*    */     //   195: invokevirtual Xu : (Ljava/lang/String;)V
/*    */     //   198: invokestatic cw : ()Lf/yk0;
/*    */     //   201: aload #5
/*    */     //   203: iload #6
/*    */     //   205: invokevirtual Fp0 : (I)S
/*    */     //   208: invokevirtual mP : (S)Lf/WD;
/*    */     //   211: astore #7
/*    */     //   213: invokevirtual Fp0 : (I)S
/*    */     //   216: ifne -> 302
/*    */     //   219: aload_0
/*    */     //   220: dup
/*    */     //   221: dup
/*    */     //   222: dup2
/*    */     //   223: getfield tH : [Lf/mc;
/*    */     //   226: iload #6
/*    */     //   228: aaload
/*    */     //   229: ldc '-'
/*    */     //   231: invokevirtual s6 : (Ljava/lang/String;)V
/*    */     //   234: getfield tH : [Lf/mc;
/*    */     //   237: iload #6
/*    */     //   239: aaload
/*    */     //   240: new java/lang/StringBuilder
/*    */     //   243: dup
/*    */     //   244: invokespecial <init> : ()V
/*    */     //   247: sipush #1852
/*    */     //   250: invokestatic OH0 : (I)Ljava/lang/String;
/*    */     //   253: invokevirtual append : (Ljava/lang/String;)Ljava/lang/StringBuilder;
/*    */     //   256: ldc ' - / -'
/*    */     //   258: invokevirtual append : (Ljava/lang/String;)Ljava/lang/StringBuilder;
/*    */     //   261: invokevirtual toString : ()Ljava/lang/String;
/*    */     //   264: invokevirtual Ep0 : (Ljava/lang/String;)V
/*    */     //   267: getfield tH : [Lf/mc;
/*    */     //   270: iload #6
/*    */     //   272: aaload
/*    */     //   273: iconst_0
/*    */     //   274: invokevirtual sk0 : (Z)V
/*    */     //   277: getfield tH : [Lf/mc;
/*    */     //   280: iload #6
/*    */     //   282: aaload
/*    */     //   283: invokevirtual CW : ()Lf/rH;
/*    */     //   286: invokevirtual H : ()V
/*    */     //   289: getfield tH : [Lf/mc;
/*    */     //   292: iload #6
/*    */     //   294: aaload
/*    */     //   295: aconst_null
/*    */     //   296: invokevirtual Gq0 : (Ljava/lang/Object;)V
/*    */     //   299: goto -> 507
/*    */     //   302: aload_0
/*    */     //   303: dup
/*    */     //   304: aload #7
/*    */     //   306: aload #5
/*    */     //   308: aload_0
/*    */     //   309: dup
/*    */     //   310: dup
/*    */     //   311: getfield tH : [Lf/mc;
/*    */     //   314: iload #6
/*    */     //   316: aaload
/*    */     //   317: iconst_1
/*    */     //   318: invokevirtual sk0 : (Z)V
/*    */     //   321: getfield tH : [Lf/mc;
/*    */     //   324: iload #6
/*    */     //   326: aaload
/*    */     //   327: aload #7
/*    */     //   329: aload #4
/*    */     //   331: invokestatic Ii0 : (Lf/WD;Lf/j40;)Lf/Ip;
/*    */     //   334: invokevirtual Gq0 : (Ljava/lang/Object;)V
/*    */     //   337: getfield tH : [Lf/mc;
/*    */     //   340: iload #6
/*    */     //   342: aaload
/*    */     //   343: new java/lang/StringBuilder
/*    */     //   346: dup
/*    */     //   347: astore #8
/*    */     //   349: invokespecial <init> : ()V
/*    */     //   352: sipush #1852
/*    */     //   355: aload #8
/*    */     //   357: ldc ' '
/*    */     //   359: invokestatic X9 : (ILjava/lang/StringBuilder;Ljava/lang/String;)Ljava/lang/StringBuilder;
/*    */     //   362: aload #5
/*    */     //   364: iload #6
/*    */     //   366: invokevirtual vC : (I)B
/*    */     //   369: invokevirtual append : (I)Ljava/lang/StringBuilder;
/*    */     //   372: ldc ' / '
/*    */     //   374: invokevirtual append : (Ljava/lang/String;)Ljava/lang/StringBuilder;
/*    */     //   377: aload #5
/*    */     //   379: iload #6
/*    */     //   381: aload #7
/*    */     //   383: invokevirtual Ot : ()B
/*    */     //   386: invokevirtual Vk0 : (IB)B
/*    */     //   389: invokevirtual append : (I)Ljava/lang/StringBuilder;
/*    */     //   392: invokevirtual toString : ()Ljava/lang/String;
/*    */     //   395: invokevirtual Ep0 : (Ljava/lang/String;)V
/*    */     //   398: invokevirtual Fn : (Lf/Q90;)Lf/Ht0;
/*    */     //   401: astore #8
/*    */     //   403: getfield tH : [Lf/mc;
/*    */     //   406: iload #6
/*    */     //   408: aaload
/*    */     //   409: invokevirtual CW : ()Lf/rH;
/*    */     //   412: iconst_1
/*    */     //   413: anewarray f/pe0
/*    */     //   416: dup
/*    */     //   417: invokestatic ZZ : ()Lf/interface;
/*    */     //   420: aload #8
/*    */     //   422: invokevirtual oI : ()B
/*    */     //   425: invokevirtual xk0 : (I)Lf/pe0;
/*    */     //   428: iconst_0
/*    */     //   429: swap
/*    */     //   430: aastore
/*    */     //   431: invokevirtual Pn : ([Lf/pe0;)Lf/JG0;
/*    */     //   434: pop
/*    */     //   435: getfield tH : [Lf/mc;
/*    */     //   438: iload #6
/*    */     //   440: aaload
/*    */     //   441: invokevirtual CW : ()Lf/rH;
/*    */     //   444: sipush #153
/*    */     //   447: bipush #9
/*    */     //   449: invokevirtual zT : (II)Lf/JG0;
/*    */     //   452: pop
/*    */     //   453: invokestatic XU : ()Z
/*    */     //   456: ifeq -> 492
/*    */     //   459: aload_0
/*    */     //   460: dup
/*    */     //   461: getfield tH : [Lf/mc;
/*    */     //   464: iload #6
/*    */     //   466: aaload
/*    */     //   467: invokevirtual CW : ()Lf/rH;
/*    */     //   470: sipush #153
/*    */     //   473: bipush #14
/*    */     //   475: invokevirtual zT : (II)Lf/JG0;
/*    */     //   478: pop
/*    */     //   479: getfield tH : [Lf/mc;
/*    */     //   482: iload #6
/*    */     //   484: aaload
/*    */     //   485: invokevirtual CW : ()Lf/rH;
/*    */     //   488: fconst_2
/*    */     //   489: invokevirtual Ii0 : (F)V
/*    */     //   492: aload_0
/*    */     //   493: getfield tH : [Lf/mc;
/*    */     //   496: iload #6
/*    */     //   498: aaload
/*    */     //   499: aload #7
/*    */     //   501: invokevirtual cW : ()Ljava/lang/String;
/*    */     //   504: invokevirtual s6 : (Ljava/lang/String;)V
/*    */     //   507: iload #6
/*    */     //   509: aload_0
/*    */     //   510: getfield tH : [Lf/mc;
/*    */     //   513: iload #6
/*    */     //   515: aaload
/*    */     //   516: aload_0
/*    */     //   517: aload_2
/*    */     //   518: aload_1
/*    */     //   519: iload_3
/*    */     //   520: aload #4
/*    */     //   522: iload #6
/*    */     //   524: <illegal opcode> run : (Lf/ex;Lf/LPT3;Lf/Bf;ILf/j40;B)Ljava/lang/Runnable;
/*    */     //   529: invokevirtual tW : (Ljava/lang/Runnable;)V
/*    */     //   532: iconst_1
/*    */     //   533: iadd
/*    */     //   534: i2b
/*    */     //   535: istore #6
/*    */     //   537: goto -> 155
/*    */     //   540: aload_0
/*    */     //   541: getfield ZI : I
/*    */     //   544: iconst_2
/*    */     //   545: dup
/*    */     //   546: istore_2
/*    */     //   547: if_icmpeq -> 748
/*    */     //   550: aload_0
/*    */     //   551: dup
/*    */     //   552: getfield Kz : Lf/Ip;
/*    */     //   555: dup
/*    */     //   556: invokevirtual d7 : ()Lf/cr0;
/*    */     //   559: bipush #18
/*    */     //   561: invokevirtual Aq : (I)Lf/U90;
/*    */     //   564: iconst_2
/*    */     //   565: anewarray f/U90
/*    */     //   568: dup
/*    */     //   569: dup
/*    */     //   570: aload_0
/*    */     //   571: swap
/*    */     //   572: aload_0
/*    */     //   573: getfield Kz : Lf/Ip;
/*    */     //   576: invokevirtual mE0 : ()Lf/g0;
/*    */     //   579: iconst_2
/*    */     //   580: anewarray f/JG0
/*    */     //   583: dup
/*    */     //   584: dup
/*    */     //   585: astore_3
/*    */     //   586: aload_0
/*    */     //   587: getfield tH : [Lf/mc;
/*    */     //   590: dup
/*    */     //   591: aload_3
/*    */     //   592: swap
/*    */     //   593: iconst_0
/*    */     //   594: aaload
/*    */     //   595: iconst_0
/*    */     //   596: swap
/*    */     //   597: aastore
/*    */     //   598: iconst_1
/*    */     //   599: aaload
/*    */     //   600: iconst_1
/*    */     //   601: swap
/*    */     //   602: aastore
/*    */     //   603: invokevirtual Mg : ([Lf/JG0;)Lf/U90;
/*    */     //   606: iconst_0
/*    */     //   607: swap
/*    */     //   608: aastore
/*    */     //   609: getfield Kz : Lf/Ip;
/*    */     //   612: invokevirtual mE0 : ()Lf/g0;
/*    */     //   615: iconst_2
/*    */     //   616: anewarray f/JG0
/*    */     //   619: dup
/*    */     //   620: dup
/*    */     //   621: astore_3
/*    */     //   622: aload_0
/*    */     //   623: getfield tH : [Lf/mc;
/*    */     //   626: dup
/*    */     //   627: aload_3
/*    */     //   628: swap
/*    */     //   629: iconst_2
/*    */     //   630: aaload
/*    */     //   631: iconst_0
/*    */     //   632: swap
/*    */     //   633: aastore
/*    */     //   634: iconst_3
/*    */     //   635: aaload
/*    */     //   636: iconst_1
/*    */     //   637: swap
/*    */     //   638: aastore
/*    */     //   639: invokevirtual Mg : ([Lf/JG0;)Lf/U90;
/*    */     //   642: iconst_1
/*    */     //   643: swap
/*    */     //   644: aastore
/*    */     //   645: invokevirtual cOM8 : ([Lf/U90;)Lf/U90;
/*    */     //   648: invokevirtual WN : (Lf/U90;)V
/*    */     //   651: getfield Kz : Lf/Ip;
/*    */     //   654: dup
/*    */     //   655: invokevirtual d7 : ()Lf/cr0;
/*    */     //   658: iconst_2
/*    */     //   659: anewarray f/U90
/*    */     //   662: dup
/*    */     //   663: dup
/*    */     //   664: aload_0
/*    */     //   665: swap
/*    */     //   666: aload_0
/*    */     //   667: getfield Kz : Lf/Ip;
/*    */     //   670: invokevirtual mE0 : ()Lf/g0;
/*    */     //   673: iconst_2
/*    */     //   674: anewarray f/JG0
/*    */     //   677: dup
/*    */     //   678: dup
/*    */     //   679: astore_3
/*    */     //   680: aload_0
/*    */     //   681: getfield tH : [Lf/mc;
/*    */     //   684: dup
/*    */     //   685: aload_3
/*    */     //   686: swap
/*    */     //   687: iconst_0
/*    */     //   688: aaload
/*    */     //   689: iconst_0
/*    */     //   690: swap
/*    */     //   691: aastore
/*    */     //   692: iconst_2
/*    */     //   693: aaload
/*    */     //   694: iconst_1
/*    */     //   695: swap
/*    */     //   696: aastore
/*    */     //   697: invokevirtual Mg : ([Lf/JG0;)Lf/U90;
/*    */     //   700: iconst_0
/*    */     //   701: swap
/*    */     //   702: aastore
/*    */     //   703: getfield Kz : Lf/Ip;
/*    */     //   706: invokevirtual mE0 : ()Lf/g0;
/*    */     //   709: iconst_2
/*    */     //   710: anewarray f/JG0
/*    */     //   713: dup
/*    */     //   714: dup
/*    */     //   715: astore_3
/*    */     //   716: aload_0
/*    */     //   717: getfield tH : [Lf/mc;
/*    */     //   720: dup
/*    */     //   721: aload_3
/*    */     //   722: swap
/*    */     //   723: iconst_1
/*    */     //   724: aaload
/*    */     //   725: iconst_0
/*    */     //   726: swap
/*    */     //   727: aastore
/*    */     //   728: iconst_3
/*    */     //   729: aaload
/*    */     //   730: iconst_1
/*    */     //   731: swap
/*    */     //   732: aastore
/*    */     //   733: invokevirtual Mg : ([Lf/JG0;)Lf/U90;
/*    */     //   736: iconst_1
/*    */     //   737: swap
/*    */     //   738: aastore
/*    */     //   739: invokevirtual cOM8 : ([Lf/U90;)Lf/U90;
/*    */     //   742: invokevirtual rK0 : (Lf/U90;)V
/*    */     //   745: goto -> 938
/*    */     //   748: aload_0
/*    */     //   749: dup
/*    */     //   750: getfield Kz : Lf/Ip;
/*    */     //   753: dup
/*    */     //   754: invokevirtual d7 : ()Lf/cr0;
/*    */     //   757: iconst_2
/*    */     //   758: anewarray f/U90
/*    */     //   761: dup
/*    */     //   762: dup
/*    */     //   763: aload_0
/*    */     //   764: swap
/*    */     //   765: aload_0
/*    */     //   766: getfield Kz : Lf/Ip;
/*    */     //   769: invokevirtual mE0 : ()Lf/g0;
/*    */     //   772: iconst_2
/*    */     //   773: anewarray f/JG0
/*    */     //   776: dup
/*    */     //   777: dup
/*    */     //   778: astore_3
/*    */     //   779: aload_0
/*    */     //   780: getfield tH : [Lf/mc;
/*    */     //   783: dup
/*    */     //   784: aload_3
/*    */     //   785: swap
/*    */     //   786: iconst_0
/*    */     //   787: aaload
/*    */     //   788: iconst_0
/*    */     //   789: swap
/*    */     //   790: aastore
/*    */     //   791: iconst_1
/*    */     //   792: aaload
/*    */     //   793: iconst_1
/*    */     //   794: swap
/*    */     //   795: aastore
/*    */     //   796: invokevirtual Mg : ([Lf/JG0;)Lf/U90;
/*    */     //   799: iconst_0
/*    */     //   800: swap
/*    */     //   801: aastore
/*    */     //   802: getfield Kz : Lf/Ip;
/*    */     //   805: invokevirtual mE0 : ()Lf/g0;
/*    */     //   808: iconst_2
/*    */     //   809: anewarray f/JG0
/*    */     //   812: dup
/*    */     //   813: dup
/*    */     //   814: astore_3
/*    */     //   815: aload_0
/*    */     //   816: getfield tH : [Lf/mc;
/*    */     //   819: dup
/*    */     //   820: aload_3
/*    */     //   821: swap
/*    */     //   822: iconst_2
/*    */     //   823: aaload
/*    */     //   824: iconst_0
/*    */     //   825: swap
/*    */     //   826: aastore
/*    */     //   827: iconst_3
/*    */     //   828: aaload
/*    */     //   829: iconst_1
/*    */     //   830: swap
/*    */     //   831: aastore
/*    */     //   832: invokevirtual Mg : ([Lf/JG0;)Lf/U90;
/*    */     //   835: iconst_1
/*    */     //   836: swap
/*    */     //   837: aastore
/*    */     //   838: invokevirtual cOM8 : ([Lf/U90;)Lf/U90;
/*    */     //   841: invokevirtual WN : (Lf/U90;)V
/*    */     //   844: getfield Kz : Lf/Ip;
/*    */     //   847: dup
/*    */     //   848: invokevirtual d7 : ()Lf/cr0;
/*    */     //   851: iconst_2
/*    */     //   852: anewarray f/U90
/*    */     //   855: dup
/*    */     //   856: dup
/*    */     //   857: aload_0
/*    */     //   858: swap
/*    */     //   859: aload_0
/*    */     //   860: getfield Kz : Lf/Ip;
/*    */     //   863: invokevirtual mE0 : ()Lf/g0;
/*    */     //   866: iconst_2
/*    */     //   867: anewarray f/JG0
/*    */     //   870: dup
/*    */     //   871: dup
/*    */     //   872: astore_3
/*    */     //   873: aload_0
/*    */     //   874: getfield tH : [Lf/mc;
/*    */     //   877: dup
/*    */     //   878: aload_3
/*    */     //   879: swap
/*    */     //   880: iconst_0
/*    */     //   881: aaload
/*    */     //   882: iconst_0
/*    */     //   883: swap
/*    */     //   884: aastore
/*    */     //   885: iconst_2
/*    */     //   886: aaload
/*    */     //   887: iconst_1
/*    */     //   888: swap
/*    */     //   889: aastore
/*    */     //   890: invokevirtual Mg : ([Lf/JG0;)Lf/U90;
/*    */     //   893: iconst_0
/*    */     //   894: swap
/*    */     //   895: aastore
/*    */     //   896: getfield Kz : Lf/Ip;
/*    */     //   899: invokevirtual mE0 : ()Lf/g0;
/*    */     //   902: iconst_2
/*    */     //   903: anewarray f/JG0
/*    */     //   906: dup
/*    */     //   907: dup
/*    */     //   908: astore_3
/*    */     //   909: aload_0
/*    */     //   910: getfield tH : [Lf/mc;
/*    */     //   913: dup
/*    */     //   914: aload_3
/*    */     //   915: swap
/*    */     //   916: iconst_1
/*    */     //   917: aaload
/*    */     //   918: iconst_0
/*    */     //   919: swap
/*    */     //   920: aastore
/*    */     //   921: iconst_3
/*    */     //   922: aaload
/*    */     //   923: iconst_1
/*    */     //   924: swap
/*    */     //   925: aastore
/*    */     //   926: invokevirtual Mg : ([Lf/JG0;)Lf/U90;
/*    */     //   929: iconst_1
/*    */     //   930: swap
/*    */     //   931: aastore
/*    */     //   932: invokevirtual cOM8 : ([Lf/U90;)Lf/U90;
/*    */     //   935: invokevirtual rK0 : (Lf/U90;)V
/*    */     //   938: aload_0
/*    */     //   939: dup
/*    */     //   940: dup
/*    */     //   941: getfield Kz : Lf/Ip;
/*    */     //   944: invokevirtual J8 : (Lf/JG0;)V
/*    */     //   947: getfield ZI : I
/*    */     //   950: iload_2
/*    */     //   951: if_icmpne -> 962
/*    */     //   954: aload_0
/*    */     //   955: dup
/*    */     //   956: getfield k7 : Lf/dQ;
/*    */     //   959: invokevirtual J8 : (Lf/JG0;)V
/*    */     //   962: aload_0
/*    */     //   963: getfield ZI : I
/*    */     //   966: iload_2
/*    */     //   967: if_icmpeq -> 1024
/*    */     //   970: aload_0
/*    */     //   971: dup
/*    */     //   972: dup
/*    */     //   973: new f/p30
/*    */     //   976: dup
/*    */     //   977: aload_0
/*    */     //   978: swap
/*    */     //   979: dup
/*    */     //   980: bipush #53
/*    */     //   982: invokestatic OH0 : (I)Ljava/lang/String;
/*    */     //   985: bipush #96
/*    */     //   987: bipush #30
/*    */     //   989: invokespecial <init> : (Ljava/lang/String;II)V
/*    */     //   992: putfield nB0 : Lf/p30;
/*    */     //   995: ldc_w 'battle-button-return'
/*    */     //   998: invokevirtual Xu : (Ljava/lang/String;)V
/*    */     //   1001: getfield nB0 : Lf/p30;
/*    */     //   1004: aload_1
/*    */     //   1005: dup
/*    */     //   1006: invokevirtual getClass : ()Ljava/lang/Class;
/*    */     //   1009: pop
/*    */     //   1010: <illegal opcode> run : (Lf/Bf;)Ljava/lang/Runnable;
/*    */     //   1015: invokevirtual tW : (Ljava/lang/Runnable;)V
/*    */     //   1018: getfield nB0 : Lf/p30;
/*    */     //   1021: invokevirtual J8 : (Lf/JG0;)V
/*    */     //   1024: aload_0
/*    */     //   1025: dup
/*    */     //   1026: getfield tH : [Lf/mc;
/*    */     //   1029: iconst_2
/*    */     //   1030: invokevirtual aI : ([Lf/Un;I)V
/*    */     //   1033: return
/*    */     // Line number table:
/*    */     //   Java source line number -> byte code offset
/*    */     //   #1	-> 357
/*  7 */     //   #2	-> 366 } public final void LM(throws paramthrows) { this.k1 = false; Un[] arrayOfUn; int i; if ((i = this.aJ) >= 0 && i < (arrayOfUn = this.Tn).length) VA0.c90(this[i]);  } public final void d40() { if (this.ZI == 1) { this.nB0.Tm(40, 40); this.nB0.ME(this.fr0.m40() - this.nB0.xY - 60, this.fr0.mD() - this.nB0.HC + 4);
/*  8 */       this.Kz.Tm(((wg0)this.XO).qF(), ((wg0)this.XO).Hy()); this.Kz
/*  9 */         .ME(((wg0)this.XO).RS(), ((wg0)this.XO).e3() + 50);
/* 10 */       this.Kz
/* 11 */         .kN(5, 8, 5, 8); }
/* 12 */     else { if (km.XU()) { this.k7
/*    */ 
/*    */           
/* 15 */           .ME(this.Kd + 10, this.er0 + 30);
/* 16 */         this.Kz
/*    */ 
/*    */ 
/*    */           
/* 20 */           .Tm(this.fr0.qF(), this.fr0.Hy()); }
/*    */       else
/*    */       { Bf bf;
/*    */         
/* 24 */         if (bf = this.XO instanceof ia0)
/* 25 */         { int i = ((ia0)bf).coM7;
/* 26 */           int j = ((ia0)bf).Ds0;
/* 27 */           int k = ((ia0)bf).Kc;
/* 28 */           int m = ((ia0)bf).gA0;
/* 29 */           Tm(i, j);
/* 30 */           ME(k, m);
/* 31 */           (bf = bf).Tm(i, j);
/* 32 */           ((ia0)bf).ME(k, m); }  this
/* 33 */           .k7
/*    */ 
/*    */           
/* 36 */           .ME(this.Kd + 450, this.er0 + 30);
/* 37 */         this.Kz
/*    */ 
/*    */ 
/*    */           
/* 41 */           .Tm(this.fr0.qF(), this.fr0.Hy()); }  this.Kz.ME(this
/* 42 */           .Kd + 5, this
/* 43 */           .er0 + 5); }
/*    */      }
/*    */ 
/*    */   
/*    */   public final boolean i2(oa0 paramoa0) {
/*    */     if (B8.Wm0(paramoa0.cz0) && paramoa0.oO()) {
/*    */       rn(paramoa0);
/*    */       return true;
/*    */     } 
/*    */     return super.i2(paramoa0);
/*    */   }
/*    */   
/*    */   public final void rn(oa0 paramoa0) {
/*    */     // Byte code:
/*    */     //   0: aload_1
/*    */     //   1: getfield GG0 : I
/*    */     //   4: getstatic f/BM.bC : Lf/BM;
/*    */     //   7: invokestatic J20 : (ILf/BM;)Z
/*    */     //   10: ifeq -> 41
/*    */     //   13: aload_0
/*    */     //   14: getfield Tn : [Lf/Un;
/*    */     //   17: aload_0
/*    */     //   18: getfield aJ : I
/*    */     //   21: aaload
/*    */     //   22: dup
/*    */     //   23: astore_0
/*    */     //   24: getfield kN : Z
/*    */     //   27: ifeq -> 40
/*    */     //   30: aload_0
/*    */     //   31: getfield TG0 : Lf/protected;
/*    */     //   34: getfield oh0 : [Ljava/lang/Runnable;
/*    */     //   37: invokestatic Fz0 : ([Ljava/lang/Runnable;)V
/*    */     //   40: return
/*    */     //   41: aload_0
/*    */     //   42: getfield nB0 : Lf/p30;
/*    */     //   45: ifnull -> 74
/*    */     //   48: aload_1
/*    */     //   49: getfield GG0 : I
/*    */     //   52: getstatic f/BM.lc : Lf/BM;
/*    */     //   55: invokestatic J20 : (ILf/BM;)Z
/*    */     //   58: ifeq -> 74
/*    */     //   61: aload_0
/*    */     //   62: getfield nB0 : Lf/p30;
/*    */     //   65: getfield TG0 : Lf/protected;
/*    */     //   68: getfield oh0 : [Ljava/lang/Runnable;
/*    */     //   71: invokestatic Fz0 : ([Ljava/lang/Runnable;)V
/*    */     //   74: aload_1
/*    */     //   75: getfield GG0 : I
/*    */     //   78: getstatic f/BM.M8 : Lf/BM;
/*    */     //   81: invokestatic J20 : (ILf/BM;)Z
/*    */     //   84: ifeq -> 114
/*    */     //   87: aload_0
/*    */     //   88: getfield aJ : I
/*    */     //   91: iconst_1
/*    */     //   92: iadd
/*    */     //   93: dup
/*    */     //   94: istore_1
/*    */     //   95: aload_0
/*    */     //   96: getfield nV : I
/*    */     //   99: irem
/*    */     //   100: ifne -> 106
/*    */     //   103: goto -> 219
/*    */     //   106: aload_0
/*    */     //   107: iload_1
/*    */     //   108: putfield aJ : I
/*    */     //   111: goto -> 219
/*    */     //   114: aload_1
/*    */     //   115: getfield GG0 : I
/*    */     //   118: getstatic f/BM.Oq : Lf/BM;
/*    */     //   121: invokestatic J20 : (ILf/BM;)Z
/*    */     //   124: ifeq -> 157
/*    */     //   127: aload_0
/*    */     //   128: getfield aJ : I
/*    */     //   131: dup
/*    */     //   132: istore_1
/*    */     //   133: iconst_1
/*    */     //   134: iadd
/*    */     //   135: aload_0
/*    */     //   136: getfield nV : I
/*    */     //   139: irem
/*    */     //   140: iconst_1
/*    */     //   141: if_icmpne -> 147
/*    */     //   144: goto -> 219
/*    */     //   147: aload_0
/*    */     //   148: iload_1
/*    */     //   149: iconst_1
/*    */     //   150: isub
/*    */     //   151: putfield aJ : I
/*    */     //   154: goto -> 219
/*    */     //   157: aload_1
/*    */     //   158: getfield GG0 : I
/*    */     //   161: getstatic f/BM.ni : Lf/BM;
/*    */     //   164: invokestatic J20 : (ILf/BM;)Z
/*    */     //   167: ifeq -> 187
/*    */     //   170: aload_0
/*    */     //   171: getfield aJ : I
/*    */     //   174: aload_0
/*    */     //   175: getfield nV : I
/*    */     //   178: isub
/*    */     //   179: dup
/*    */     //   180: istore_1
/*    */     //   181: ifge -> 106
/*    */     //   184: goto -> 219
/*    */     //   187: aload_1
/*    */     //   188: getfield GG0 : I
/*    */     //   191: getstatic f/BM.N70 : Lf/BM;
/*    */     //   194: invokestatic J20 : (ILf/BM;)Z
/*    */     //   197: ifeq -> 219
/*    */     //   200: aload_0
/*    */     //   201: getfield aJ : I
/*    */     //   204: aload_0
/*    */     //   205: getfield nV : I
/*    */     //   208: iadd
/*    */     //   209: dup
/*    */     //   210: istore_1
/*    */     //   211: aload_0
/*    */     //   212: getfield Tn : [Lf/Un;
/*    */     //   215: arraylength
/*    */     //   216: if_icmplt -> 106
/*    */     //   219: aload_0
/*    */     //   220: getfield aJ : I
/*    */     //   223: dup
/*    */     //   224: istore_1
/*    */     //   225: iflt -> 246
/*    */     //   228: iload_1
/*    */     //   229: aload_0
/*    */     //   230: getfield Tn : [Lf/Un;
/*    */     //   233: dup
/*    */     //   234: astore_0
/*    */     //   235: arraylength
/*    */     //   236: if_icmpge -> 246
/*    */     //   239: aload_0
/*    */     //   240: iload_1
/*    */     //   241: aaload
/*    */     //   242: invokestatic c90 : (Lf/JG0;)Z
/*    */     //   245: pop
/*    */     //   246: return
/*    */     // Line number table:
/*    */     //   Java source line number -> byte code offset
/*    */     //   #1	-> 1
/*    */     //   #2	-> 4
/*    */     //   #3	-> 24
/*    */     //   #4	-> 31
/*    */     //   #5	-> 34
/*    */     //   #6	-> 37
/*    */     //   #7	-> 42
/*    */     //   #8	-> 49
/*    */     //   #9	-> 52
/*    */     //   #10	-> 65
/*    */     //   #11	-> 68
/*    */     //   #12	-> 71
/*    */     //   #13	-> 75
/*    */     //   #14	-> 78
/*    */     //   #15	-> 115
/*    */     //   #16	-> 118
/*    */     //   #17	-> 158
/*    */     //   #18	-> 161
/*    */     //   #19	-> 188
/*    */     //   #20	-> 191
/*    */   }
/*    */   
/*    */   public final void aI(Un[] paramArrayOfUn, int paramInt) {
/*    */     this.aJ = 0;
/*    */     this.nV = 2;
/*    */     this.Tn = paramArrayOfUn;
/*    */     if (paramArrayOfUn.length == 0)
/*    */       return; 
/*    */     VA0.c90(paramArrayOfUn[0]);
/*    */   } }


/* Location:              /Users/vnnsnnt/Documents/Codespace/JavaWorkspace/RedTrainer/src/main/java/org/trainer/client/PokeMMO.jar!/f/ex.class
 * Java compiler version: 8 (52.0)
 * JD-Core Version:       1.1.3
 */