/*  1 */ package f;public abstract class f9 extends JG0 { public static void an(yD paramyD, xc paramxc, jT paramjT, Gj paramGj, Sx0 paramSx0) { boolean bool; if (paramGj != Gj.FC0) { bool = true; } else { bool = false; }  paramyD.OE0(false); if ((bool || paramSx0 != Sx0.z00) && !bool) { paramyD.t0 = paramyD.NC0(paramjT.X90); ArrayList<?> arrayList; int j;
/*  2 */       for (j = (arrayList = paramyD.o4).size(); j-- > 0;) { if (((jT)arrayList.get(j)).Ia() <= paramyD.t0) arrayList.remove(j);  }
/*    */       
/*  4 */       for (j = (arrayList = paramyD.A60).size(); j-- > 0;) { if (((jT)arrayList.get(j)).Ia() <= paramyD.t0) arrayList.remove(j);  }  paramyD
/*  5 */         .lo(); }
/*  6 */      int i = paramjT.iw0; short s1 = paramjT.ZW, s2 = paramjT.li; paramyD.pr(i, s1, s2); if (paramjT.iw0 > (i = paramyD.tl)) paramjT.iw0 = i;  if (bool) { if (paramGj == Gj.Df) { paramjT.mx = paramyD.CQ(paramjT.li) - paramjT.iw0; paramyD.A60.add(paramjT); } else { paramjT.mx = paramyD.o70(paramjT.ZW); paramyD.o4.add(paramjT); }  } else { int j; if (paramSx0 == Sx0.z00) { if (paramyD.sL() < paramjT.iw0 && !paramyD.zs0()) paramyD.OE0(false);  j = paramjT.iw0; int k; paramyD
/*  7 */           .gC0 = (k = paramyD.gC0) + j;
/*  8 */         paramjT.mx = k; }
/*    */       else
/*    */       { int k;
/*    */         
/*    */         e00 e00;
/* 13 */         if ((k = ((AuX)j.X10.bw0(e00 = e00.HORIZONTAL_ALIGNMENT).rI(e00)).ordinal()) != 1) { if (k != 2 && k != 3) { paramjT.mx = paramyD.o70(paramjT.ZW); } else { k = paramyD.VN; paramjT
/*    */               
/* 15 */               .mx = JO.Se0(paramyD.tl, paramjT.iw0, 2, k); }  } else { paramjT.mx = paramyD.CQ(paramjT.li) - paramjT.iw0; }  }  }  paramyD.pb0.add(paramjT); if (bool) { if (bK0 || paramyD.xu0 == paramyD.pb0.size() - 1) { paramyD.xu0++; paramjT.dF = paramyD.NC0(paramjT.X90); paramyD.lo(); return; }  throw new AssertionError(); }  if (paramSx0 != Sx0.z00) { int j = Math.max(0, paramyD.tl - paramjT.iw0); paramyD
/* 16 */         .SF = Math.min(paramyD.SF, j);
/* 17 */       paramyD.OE0(false); }
/*    */      }
/*    */ 
/*    */   
/*    */   public static final Ll Gz;
/*    */   public static final char[] F00;
/*    */   public static final vc wd;
/*    */   public final HashMap Y3 = new HashMap<>();
/*    */   public final HashMap ii0 = new HashMap<>();
/*    */   public final HashMap vf0 = new HashMap<>();
/*    */   public final ArrayList Fw = new ArrayList();
/*    */   public final TJ Rf = new TJ(this);
/*    */   public final tJ gD = new tJ(this);
/*    */   public Zq0 wy;
/*    */   public nW y50;
/*    */   public nW Wy0;
/*    */   public pe xF0;
/*    */   public Cs0[] Cv;
/*    */   public JE0 ey;
/*    */   public JE0 Z30;
/*    */   public final fM pW = new fM(null);
/*    */   public final ArrayList Ze0 = new ArrayList();
/*    */   public final Pj aA = new Pj(cOm7());
/*    */   public boolean gW;
/*    */   public boolean Tv0;
/*    */   public boolean X2;
/*    */   public db cj0;
/*    */   public int th;
/*    */   public int qj;
/*    */   public boolean Kw0;
/*    */   public boolean yV;
/*    */   public jT Zk;
/*    */   public HashMap dG0 = new HashMap<>();
/*    */   
/*    */   public f9() {}
/*    */   
/*    */   static {
/*    */     Ll ll = Ll.F10("hover");
/*    */     F00 = new char[0];
/*    */     this(ll);
/*    */     x2 x2;
/*    */     wd = new vc(new Nm0[] { x2 });
/*    */   }
/*    */   
/*    */   public f9(wH0 paramwH0) {
/*    */     this();
/*    */     pb0(paramwH0);
/*    */   }
/*    */   
/*    */   public final void Ae0() {
/*    */     int i = -1, j = -1;
/*    */     if (this.wy == null) {
/*    */       i = 0;
/*    */       j = 0;
/*    */     } else {
/*    */       int k = Ho();
/*    */       int m = Math.max(0, this.fu - k);
/*    */       if (this.fu > 0 && Math.max(0, AW() - k) < m) {
/*    */         fM fM1;
/*    */         this(null);
/*    */         throws throws;
/*    */         if ((throws = this.Bo0) != null)
/*    */           throws.IB0.getClass(); 
/*    */         try {
/*    */           fM1.iw0 = m;
/*    */           this(this, fM1, 0, 0, 0, false);
/*    */           Sz(yD, this.wy);
/*    */           yD yD;
/*    */           (yD = new yD()).T1();
/*    */           i = Math.max(0, m - yD.SF);
/*    */           j = (new yD()).t0;
/*    */         } finally {}
/*    */       } 
/*    */     } 
/*    */     this(i, j);
/*    */     db db1;
/*    */     this.cj0 = this;
/*    */   }
/*    */   
/*    */   public final void FC0() {
/*    */     jT jT1 = null;
/*    */     if (this.Kw0)
/*    */       jT1 = this.pW.zz(this.th - RS(), this.qj - e3()); 
/*    */     if (this.Zk != jT1) {
/*    */       this.Zk = jT1;
/*    */       this.pW.NUl(jT1);
/*    */       Ll ll1;
/*    */       this.aA.Vx.Ym0(ll1 = Gz);
/*    */       this.aA.mV.Ym0(ll1);
/*    */       zn();
/*    */     } 
/*    */     if (jT1 != null && jT1.bw != null) {
/*    */     
/*    */     } else {
/*    */     
/*    */     } 
/*    */     this.v10 = this.ey;
/*    */     Ll ll = Gz;
/*    */     this.O.gf0(this, this.Kw0);
/*    */   }
/*    */   
/*    */   public final void Sz(yD paramyD, Iterable paramIterable) {
/*    */     Iterator<xc> iterator = paramIterable.iterator();
/*    */     while (iterator.hasNext())
/*    */       pt(paramyD, iterator.next()); 
/*    */   }
/*    */   
/*    */   public final void pt(yD paramyD, xc paramxc) {
/*    */     // Byte code:
/*    */     //   0: aload_2
/*    */     //   1: aload_1
/*    */     //   2: aload_2
/*    */     //   3: getfield X10 : Lf/cR;
/*    */     //   6: getstatic f/e00.CLEAR : Lf/e00;
/*    */     //   9: dup
/*    */     //   10: astore_3
/*    */     //   11: invokevirtual bw0 : (Lf/e00;)Lf/cR;
/*    */     //   14: aload_3
/*    */     //   15: invokevirtual rI : (Lf/e00;)Ljava/lang/Object;
/*    */     //   18: checkcast f/UG
/*    */     //   21: invokevirtual yM : (Lf/UG;)V
/*    */     //   24: instanceof f/qn0
/*    */     //   27: ifeq -> 2183
/*    */     //   30: aload_0
/*    */     //   31: aload_2
/*    */     //   32: checkcast f/qn0
/*    */     //   35: astore_2
/*    */     //   36: getfield dG0 : Ljava/util/HashMap;
/*    */     //   39: aload_2
/*    */     //   40: invokevirtual hashCode : ()I
/*    */     //   43: invokestatic valueOf : (I)Ljava/lang/Integer;
/*    */     //   46: invokevirtual get : (Ljava/lang/Object;)Ljava/lang/Object;
/*    */     //   49: checkcast f/coM4
/*    */     //   52: dup
/*    */     //   53: astore_3
/*    */     //   54: ifnull -> 248
/*    */     //   57: aload_1
/*    */     //   58: dup
/*    */     //   59: aload_3
/*    */     //   60: aload_1
/*    */     //   61: aload_3
/*    */     //   62: aload_1
/*    */     //   63: aload_3
/*    */     //   64: aload_1
/*    */     //   65: aload_3
/*    */     //   66: aload_1
/*    */     //   67: aload_3
/*    */     //   68: aload_1
/*    */     //   69: aload_3
/*    */     //   70: aload_1
/*    */     //   71: aload_3
/*    */     //   72: aload_1
/*    */     //   73: aload_3
/*    */     //   74: aload_1
/*    */     //   75: aload_3
/*    */     //   76: aload_1
/*    */     //   77: aload_3
/*    */     //   78: aload_1
/*    */     //   79: aload_3
/*    */     //   80: aload_1
/*    */     //   81: aload_3
/*    */     //   82: aload_1
/*    */     //   83: aload_3
/*    */     //   84: aload_1
/*    */     //   85: aload_3
/*    */     //   86: aload_1
/*    */     //   87: aload_3
/*    */     //   88: aload_1
/*    */     //   89: aload_3
/*    */     //   90: aload_1
/*    */     //   91: aload_3
/*    */     //   92: aload_1
/*    */     //   93: aload_3
/*    */     //   94: aload_1
/*    */     //   95: aload_3
/*    */     //   96: aload_1
/*    */     //   97: aload_3
/*    */     //   98: aload_1
/*    */     //   99: aload_3
/*    */     //   100: aload_1
/*    */     //   101: aload_3
/*    */     //   102: getfield oZ : I
/*    */     //   105: putfield t0 : I
/*    */     //   108: getfield DP : I
/*    */     //   111: putfield gC0 : I
/*    */     //   114: getfield rg : I
/*    */     //   117: putfield xu0 : I
/*    */     //   120: getfield L : I
/*    */     //   123: putfield Xb0 : I
/*    */     //   126: getfield eT : I
/*    */     //   129: putfield Ta : I
/*    */     //   132: getfield Rw : I
/*    */     //   135: putfield qL : I
/*    */     //   138: getfield yf : I
/*    */     //   141: putfield ML : I
/*    */     //   144: getfield Y3 : I
/*    */     //   147: putfield jy : I
/*    */     //   150: getfield COM3 : I
/*    */     //   153: putfield Fq : I
/*    */     //   156: getfield break : I
/*    */     //   159: putfield VN : I
/*    */     //   162: getfield zc : I
/*    */     //   165: putfield tl : I
/*    */     //   168: getfield OE0 : I
/*    */     //   171: putfield kj : I
/*    */     //   174: getfield mz0 : I
/*    */     //   177: putfield pn : I
/*    */     //   180: getfield Ob : I
/*    */     //   183: putfield St0 : I
/*    */     //   186: getfield x60 : I
/*    */     //   189: putfield dd0 : I
/*    */     //   192: getfield Wr : I
/*    */     //   195: putfield SF : I
/*    */     //   198: getfield ha : Z
/*    */     //   201: putfield eS : Z
/*    */     //   204: getfield HH0 : Z
/*    */     //   207: putfield Oo : Z
/*    */     //   210: getfield jp : Z
/*    */     //   213: putfield m00 : Z
/*    */     //   216: getfield KI : Lf/AuX;
/*    */     //   219: putfield YP : Lf/AuX;
/*    */     //   222: getfield Ea : Ljava/lang/String;
/*    */     //   225: putfield WM : Ljava/lang/String;
/*    */     //   228: getfield hB0 : Lf/cR;
/*    */     //   231: putfield LT : Lf/cR;
/*    */     //   234: getfield pb0 : Ljava/util/ArrayList;
/*    */     //   237: aload_3
/*    */     //   238: getfield RQ : Ljava/util/ArrayList;
/*    */     //   241: invokevirtual addAll : (Ljava/util/Collection;)Z
/*    */     //   244: pop
/*    */     //   245: goto -> 5733
/*    */     //   248: aload_0
/*    */     //   249: aload_2
/*    */     //   250: dup
/*    */     //   251: new f/coM4
/*    */     //   254: dup
/*    */     //   255: astore_3
/*    */     //   256: invokespecial <init> : ()V
/*    */     //   259: getfield j5 : Ljava/lang/String;
/*    */     //   262: astore #4
/*    */     //   264: getfield X10 : Lf/cR;
/*    */     //   267: dup
/*    */     //   268: astore #5
/*    */     //   270: invokevirtual Nz0 : (Lf/cR;)Lf/pe;
/*    */     //   273: dup
/*    */     //   274: astore #6
/*    */     //   276: ifnonnull -> 285
/*    */     //   279: aconst_null
/*    */     //   280: astore #6
/*    */     //   282: goto -> 342
/*    */     //   285: new f/PS
/*    */     //   288: dup
/*    */     //   289: astore #7
/*    */     //   291: aload #6
/*    */     //   293: aload #5
/*    */     //   295: dup
/*    */     //   296: getstatic f/e00.COLOR : Lf/e00;
/*    */     //   299: dup
/*    */     //   300: astore #6
/*    */     //   302: invokevirtual bw0 : (Lf/e00;)Lf/cR;
/*    */     //   305: aload #6
/*    */     //   307: invokevirtual rI : (Lf/e00;)Ljava/lang/Object;
/*    */     //   310: checkcast f/pRn
/*    */     //   313: astore #6
/*    */     //   315: getstatic f/e00.COLOR_HOVER : Lf/e00;
/*    */     //   318: dup
/*    */     //   319: astore #8
/*    */     //   321: invokevirtual bw0 : (Lf/e00;)Lf/cR;
/*    */     //   324: aload #8
/*    */     //   326: invokevirtual rI : (Lf/e00;)Ljava/lang/Object;
/*    */     //   329: checkcast f/pRn
/*    */     //   332: aload #6
/*    */     //   334: swap
/*    */     //   335: invokespecial <init> : (Lf/pe;Lf/pRn;Lf/pRn;)V
/*    */     //   338: aload #7
/*    */     //   340: astore #6
/*    */     //   342: aload #6
/*    */     //   344: aload #5
/*    */     //   346: getstatic f/e00.PREFORMATTED : Lf/e00;
/*    */     //   349: dup
/*    */     //   350: astore #7
/*    */     //   352: invokevirtual bw0 : (Lf/e00;)Lf/cR;
/*    */     //   355: aload #7
/*    */     //   357: invokevirtual rI : (Lf/e00;)Ljava/lang/Object;
/*    */     //   360: checkcast java/lang/Boolean
/*    */     //   363: invokevirtual booleanValue : ()Z
/*    */     //   366: istore #7
/*    */     //   368: ifnonnull -> 374
/*    */     //   371: goto -> 5733
/*    */     //   374: aload #5
/*    */     //   376: getstatic f/e00.INHERIT_HOVER : Lf/e00;
/*    */     //   379: dup
/*    */     //   380: astore #8
/*    */     //   382: invokevirtual bw0 : (Lf/e00;)Lf/cR;
/*    */     //   385: aload #8
/*    */     //   387: getfield x10 : I
/*    */     //   390: istore #9
/*    */     //   392: getfield LPt1 : [Ljava/lang/Object;
/*    */     //   395: dup
/*    */     //   396: astore #10
/*    */     //   398: ifnull -> 411
/*    */     //   401: aload #10
/*    */     //   403: iload #9
/*    */     //   405: aaload
/*    */     //   406: astore #9
/*    */     //   408: goto -> 414
/*    */     //   411: aconst_null
/*    */     //   412: astore #9
/*    */     //   414: aload #8
/*    */     //   416: getfield Tw0 : Ljava/lang/Class;
/*    */     //   419: aload #9
/*    */     //   421: invokevirtual cast : (Ljava/lang/Object;)Ljava/lang/Object;
/*    */     //   424: checkcast java/lang/Boolean
/*    */     //   427: dup
/*    */     //   428: astore #8
/*    */     //   430: ifnull -> 443
/*    */     //   433: aload #8
/*    */     //   435: invokevirtual booleanValue : ()Z
/*    */     //   438: istore #8
/*    */     //   440: goto -> 472
/*    */     //   443: aload_1
/*    */     //   444: getfield LT : Lf/cR;
/*    */     //   447: dup
/*    */     //   448: astore #8
/*    */     //   450: ifnull -> 469
/*    */     //   453: aload #8
/*    */     //   455: aload #5
/*    */     //   457: getfield g8 : Lf/cR;
/*    */     //   460: if_acmpne -> 469
/*    */     //   463: iconst_1
/*    */     //   464: istore #8
/*    */     //   466: goto -> 472
/*    */     //   469: iconst_0
/*    */     //   470: istore #8
/*    */     //   472: iload #7
/*    */     //   474: aload_1
/*    */     //   475: aload #6
/*    */     //   477: getfield ZU : Lf/pe;
/*    */     //   480: aload #5
/*    */     //   482: swap
/*    */     //   483: iconst_0
/*    */     //   484: invokevirtual LpT2 : (Lf/cR;Lf/pe;Z)V
/*    */     //   487: ifeq -> 503
/*    */     //   490: aload_1
/*    */     //   491: getfield m00 : Z
/*    */     //   494: ifne -> 503
/*    */     //   497: aload_1
/*    */     //   498: iconst_0
/*    */     //   499: invokevirtual OE0 : (Z)Z
/*    */     //   502: pop
/*    */     //   503: iload #7
/*    */     //   505: ifeq -> 985
/*    */     //   508: iconst_0
/*    */     //   509: istore #5
/*    */     //   511: iload #5
/*    */     //   513: aload #4
/*    */     //   515: invokevirtual length : ()I
/*    */     //   518: if_icmpge -> 1982
/*    */     //   521: aload #4
/*    */     //   523: bipush #10
/*    */     //   525: iload #5
/*    */     //   527: invokevirtual indexOf : (II)I
/*    */     //   530: dup
/*    */     //   531: istore #9
/*    */     //   533: ifge -> 543
/*    */     //   536: aload #4
/*    */     //   538: invokevirtual length : ()I
/*    */     //   541: istore #9
/*    */     //   543: aload #6
/*    */     //   545: getfield ZU : Lf/pe;
/*    */     //   548: astore #10
/*    */     //   550: iload #5
/*    */     //   552: iload #9
/*    */     //   554: if_icmpge -> 925
/*    */     //   557: aload #4
/*    */     //   559: iload #5
/*    */     //   561: invokevirtual charAt : (I)C
/*    */     //   564: bipush #9
/*    */     //   566: if_icmpne -> 730
/*    */     //   569: aload_2
/*    */     //   570: iinc #5, 1
/*    */     //   573: getfield X10 : Lf/cR;
/*    */     //   576: aload #10
/*    */     //   578: checkcast f/t90
/*    */     //   581: dup
/*    */     //   582: astore #11
/*    */     //   584: invokevirtual getEM : ()I
/*    */     //   587: istore #12
/*    */     //   589: getstatic f/e00.TAB_SIZE : Lf/e00;
/*    */     //   592: dup
/*    */     //   593: astore #13
/*    */     //   595: aload_1
/*    */     //   596: getfield Kf : Lf/f9;
/*    */     //   599: invokevirtual getClass : ()Ljava/lang/Class;
/*    */     //   602: pop
/*    */     //   603: invokevirtual bw0 : (Lf/e00;)Lf/cR;
/*    */     //   606: aload #13
/*    */     //   608: invokevirtual rI : (Lf/e00;)Ljava/lang/Object;
/*    */     //   611: checkcast java/lang/Integer
/*    */     //   614: invokevirtual intValue : ()I
/*    */     //   617: dup
/*    */     //   618: istore #13
/*    */     //   620: ifle -> 686
/*    */     //   623: iload #12
/*    */     //   625: ifgt -> 631
/*    */     //   628: goto -> 686
/*    */     //   631: aload_1
/*    */     //   632: aload #11
/*    */     //   634: aload_1
/*    */     //   635: iload #13
/*    */     //   637: sipush #32767
/*    */     //   640: iload #12
/*    */     //   642: idiv
/*    */     //   643: invokestatic min : (II)I
/*    */     //   646: iload #12
/*    */     //   648: imul
/*    */     //   649: istore #11
/*    */     //   651: getfield gC0 : I
/*    */     //   654: aload_1
/*    */     //   655: getfield VN : I
/*    */     //   658: isub
/*    */     //   659: istore #12
/*    */     //   661: invokevirtual getSpaceWidth : ()I
/*    */     //   664: iload #12
/*    */     //   666: iadd
/*    */     //   667: istore #12
/*    */     //   669: getfield gC0 : I
/*    */     //   672: iload #11
/*    */     //   674: iadd
/*    */     //   675: iload #12
/*    */     //   677: iload #11
/*    */     //   679: irem
/*    */     //   680: isub
/*    */     //   681: istore #11
/*    */     //   683: goto -> 702
/*    */     //   686: aload #11
/*    */     //   688: aload_1
/*    */     //   689: getfield gC0 : I
/*    */     //   692: istore #11
/*    */     //   694: invokevirtual getSpaceWidth : ()I
/*    */     //   697: iload #11
/*    */     //   699: iadd
/*    */     //   700: istore #11
/*    */     //   702: iload #11
/*    */     //   704: aload_1
/*    */     //   705: getfield tl : I
/*    */     //   708: if_icmpge -> 720
/*    */     //   711: aload_1
/*    */     //   712: iload #11
/*    */     //   714: putfield gC0 : I
/*    */     //   717: goto -> 730
/*    */     //   720: aload_1
/*    */     //   721: invokevirtual zs0 : ()Z
/*    */     //   724: ifne -> 730
/*    */     //   727: goto -> 925
/*    */     //   730: aload #4
/*    */     //   732: bipush #9
/*    */     //   734: iload #5
/*    */     //   736: invokevirtual indexOf : (II)I
/*    */     //   739: dup
/*    */     //   740: istore #11
/*    */     //   742: iflt -> 755
/*    */     //   745: iload #11
/*    */     //   747: iload #9
/*    */     //   749: if_icmpge -> 755
/*    */     //   752: goto -> 759
/*    */     //   755: iload #9
/*    */     //   757: istore #11
/*    */     //   759: iload #11
/*    */     //   761: iload #5
/*    */     //   763: if_icmple -> 918
/*    */     //   766: aload #10
/*    */     //   768: aload_1
/*    */     //   769: invokevirtual sL : ()I
/*    */     //   772: istore #12
/*    */     //   774: checkcast f/t90
/*    */     //   777: aload #4
/*    */     //   779: iload #5
/*    */     //   781: iload #11
/*    */     //   783: iload #12
/*    */     //   785: invokevirtual computeVisibleGlpyhs : (Ljava/lang/CharSequence;III)I
/*    */     //   788: dup
/*    */     //   789: istore #11
/*    */     //   791: ifne -> 804
/*    */     //   794: aload_1
/*    */     //   795: invokevirtual zs0 : ()Z
/*    */     //   798: ifne -> 804
/*    */     //   801: goto -> 925
/*    */     //   804: aload_3
/*    */     //   805: iconst_1
/*    */     //   806: iload #11
/*    */     //   808: invokestatic max : (II)I
/*    */     //   811: iload #5
/*    */     //   813: iadd
/*    */     //   814: istore #11
/*    */     //   816: new f/vB
/*    */     //   819: dup
/*    */     //   820: astore #12
/*    */     //   822: aload_1
/*    */     //   823: aload #12
/*    */     //   825: iload #8
/*    */     //   827: aload #12
/*    */     //   829: aload_1
/*    */     //   830: aload #12
/*    */     //   832: aload_1
/*    */     //   833: dup
/*    */     //   834: aload #12
/*    */     //   836: dup
/*    */     //   837: aload_2
/*    */     //   838: aload_1
/*    */     //   839: getfield Q10 : Z
/*    */     //   842: istore #13
/*    */     //   844: aload #6
/*    */     //   846: aload #4
/*    */     //   848: iload #5
/*    */     //   850: iload #11
/*    */     //   852: iload #13
/*    */     //   854: invokespecial <init> : (Lf/xc;Lf/PS;Ljava/lang/String;IIZ)V
/*    */     //   857: getfield iw0 : I
/*    */     //   860: istore #5
/*    */     //   862: getfield gC0 : I
/*    */     //   865: dup
/*    */     //   866: istore #13
/*    */     //   868: iload #5
/*    */     //   870: iadd
/*    */     //   871: putfield gC0 : I
/*    */     //   874: iload #13
/*    */     //   876: putfield mx : I
/*    */     //   879: getfield Ta : I
/*    */     //   882: i2s
/*    */     //   883: putfield X90 : S
/*    */     //   886: putfield rH : Z
/*    */     //   889: getfield pb0 : Ljava/util/ArrayList;
/*    */     //   892: aload #12
/*    */     //   894: invokevirtual add : (Ljava/lang/Object;)Z
/*    */     //   897: pop
/*    */     //   898: iconst_1
/*    */     //   899: putfield Et0 : Z
/*    */     //   902: getfield RQ : Ljava/util/ArrayList;
/*    */     //   905: aload #12
/*    */     //   907: invokevirtual add : (Ljava/lang/Object;)Z
/*    */     //   910: pop
/*    */     //   911: iload #11
/*    */     //   913: istore #5
/*    */     //   915: goto -> 550
/*    */     //   918: iload #11
/*    */     //   920: istore #5
/*    */     //   922: goto -> 550
/*    */     //   925: iload #5
/*    */     //   927: iload #9
/*    */     //   929: if_icmplt -> 976
/*    */     //   932: iload #9
/*    */     //   934: aload #4
/*    */     //   936: invokevirtual length : ()I
/*    */     //   939: if_icmpge -> 969
/*    */     //   942: aload #4
/*    */     //   944: iload #9
/*    */     //   946: invokevirtual charAt : (I)C
/*    */     //   949: bipush #10
/*    */     //   951: if_icmpne -> 969
/*    */     //   954: aload_1
/*    */     //   955: iload #9
/*    */     //   957: iconst_1
/*    */     //   958: iadd
/*    */     //   959: istore #5
/*    */     //   961: iconst_1
/*    */     //   962: invokevirtual OE0 : (Z)Z
/*    */     //   965: pop
/*    */     //   966: goto -> 511
/*    */     //   969: iload #9
/*    */     //   971: istore #5
/*    */     //   973: goto -> 511
/*    */     //   976: aload_1
/*    */     //   977: iconst_0
/*    */     //   978: invokevirtual OE0 : (Z)Z
/*    */     //   981: pop
/*    */     //   982: goto -> 550
/*    */     //   985: aload #4
/*    */     //   987: iconst_0
/*    */     //   988: istore #5
/*    */     //   990: invokevirtual length : ()I
/*    */     //   993: istore #9
/*    */     //   995: iload #5
/*    */     //   997: iload #9
/*    */     //   999: if_icmpge -> 1021
/*    */     //   1002: aload #4
/*    */     //   1004: iload #5
/*    */     //   1006: invokevirtual charAt : (I)C
/*    */     //   1009: invokestatic isWhitespace : (C)Z
/*    */     //   1012: ifeq -> 1021
/*    */     //   1015: iinc #5, 1
/*    */     //   1018: goto -> 995
/*    */     //   1021: iconst_0
/*    */     //   1022: istore #10
/*    */     //   1024: iload #9
/*    */     //   1026: iload #5
/*    */     //   1028: if_icmple -> 1055
/*    */     //   1031: aload #4
/*    */     //   1033: iload #9
/*    */     //   1035: iconst_1
/*    */     //   1036: isub
/*    */     //   1037: invokevirtual charAt : (I)C
/*    */     //   1040: invokestatic isWhitespace : (C)Z
/*    */     //   1043: ifeq -> 1055
/*    */     //   1046: iconst_1
/*    */     //   1047: istore #10
/*    */     //   1049: iinc #9, -1
/*    */     //   1052: goto -> 1024
/*    */     //   1055: iload #5
/*    */     //   1057: aload #6
/*    */     //   1059: getfield ZU : Lf/pe;
/*    */     //   1062: astore #11
/*    */     //   1064: ifle -> 1166
/*    */     //   1067: aload_1
/*    */     //   1068: dup
/*    */     //   1069: getfield pb0 : Ljava/util/ArrayList;
/*    */     //   1072: invokevirtual size : ()I
/*    */     //   1075: istore #12
/*    */     //   1077: getfield xu0 : I
/*    */     //   1080: iload #12
/*    */     //   1082: if_icmpge -> 1141
/*    */     //   1085: aload_1
/*    */     //   1086: getfield pb0 : Ljava/util/ArrayList;
/*    */     //   1089: iload #12
/*    */     //   1091: iconst_1
/*    */     //   1092: isub
/*    */     //   1093: invokevirtual get : (I)Ljava/lang/Object;
/*    */     //   1096: checkcast f/jT
/*    */     //   1099: dup
/*    */     //   1100: astore #12
/*    */     //   1102: instanceof f/vB
/*    */     //   1105: ifeq -> 1137
/*    */     //   1108: aload #12
/*    */     //   1110: checkcast f/vB
/*    */     //   1113: dup
/*    */     //   1114: astore #12
/*    */     //   1116: getfield X20 : Ljava/lang/String;
/*    */     //   1119: aload #12
/*    */     //   1121: getfield Nh0 : I
/*    */     //   1124: iconst_1
/*    */     //   1125: isub
/*    */     //   1126: invokevirtual charAt : (I)C
/*    */     //   1129: invokestatic isWhitespace : (C)Z
/*    */     //   1132: iconst_1
/*    */     //   1133: ixor
/*    */     //   1134: goto -> 1142
/*    */     //   1137: iconst_1
/*    */     //   1138: goto -> 1142
/*    */     //   1141: iconst_0
/*    */     //   1142: ifeq -> 1166
/*    */     //   1145: aload_1
/*    */     //   1146: aload #11
/*    */     //   1148: aload_1
/*    */     //   1149: getfield gC0 : I
/*    */     //   1152: istore #12
/*    */     //   1154: checkcast f/t90
/*    */     //   1157: invokevirtual getSpaceWidth : ()I
/*    */     //   1160: iload #12
/*    */     //   1162: iadd
/*    */     //   1163: putfield gC0 : I
/*    */     //   1166: aconst_null
/*    */     //   1167: astore #12
/*    */     //   1169: iload #5
/*    */     //   1171: iload #9
/*    */     //   1173: if_icmpge -> 1949
/*    */     //   1176: getstatic f/f9.bK0 : Z
/*    */     //   1179: ifne -> 1206
/*    */     //   1182: aload #4
/*    */     //   1184: iload #5
/*    */     //   1186: invokevirtual charAt : (I)C
/*    */     //   1189: invokestatic isWhitespace : (C)Z
/*    */     //   1192: ifne -> 1198
/*    */     //   1195: goto -> 1206
/*    */     //   1198: new java/lang/AssertionError
/*    */     //   1201: dup
/*    */     //   1202: invokespecial <init> : ()V
/*    */     //   1205: athrow
/*    */     //   1206: aload_1
/*    */     //   1207: getfield YP : Lf/AuX;
/*    */     //   1210: getstatic f/AuX.Ce0 : Lf/AuX;
/*    */     //   1213: if_acmpeq -> 1480
/*    */     //   1216: aload #11
/*    */     //   1218: aload_1
/*    */     //   1219: invokevirtual sL : ()I
/*    */     //   1222: istore #13
/*    */     //   1224: checkcast f/t90
/*    */     //   1227: aload #4
/*    */     //   1229: iload #5
/*    */     //   1231: iload #9
/*    */     //   1233: iload #13
/*    */     //   1235: invokevirtual computeVisibleGlpyhs : (Ljava/lang/CharSequence;III)I
/*    */     //   1238: iload #5
/*    */     //   1240: iadd
/*    */     //   1241: dup
/*    */     //   1242: istore #13
/*    */     //   1244: iload #9
/*    */     //   1246: if_icmpge -> 1448
/*    */     //   1249: iload #13
/*    */     //   1251: istore #14
/*    */     //   1253: iload #14
/*    */     //   1255: iload #5
/*    */     //   1257: if_icmple -> 1297
/*    */     //   1260: aload #4
/*    */     //   1262: iload #14
/*    */     //   1264: invokevirtual charAt : (I)C
/*    */     //   1267: ldc_w ':;,.-!?'
/*    */     //   1270: swap
/*    */     //   1271: invokevirtual indexOf : (I)I
/*    */     //   1274: iflt -> 1283
/*    */     //   1277: iconst_1
/*    */     //   1278: istore #15
/*    */     //   1280: goto -> 1286
/*    */     //   1283: iconst_0
/*    */     //   1284: istore #15
/*    */     //   1286: iload #15
/*    */     //   1288: ifeq -> 1297
/*    */     //   1291: iinc #14, -1
/*    */     //   1294: goto -> 1253
/*    */     //   1297: aload #4
/*    */     //   1299: iload #14
/*    */     //   1301: invokevirtual charAt : (I)C
/*    */     //   1304: dup
/*    */     //   1305: istore #15
/*    */     //   1307: invokestatic isWhitespace : (C)Z
/*    */     //   1310: ifne -> 1357
/*    */     //   1313: ldc_w ':;,.-!?'
/*    */     //   1316: iload #15
/*    */     //   1318: invokevirtual indexOf : (I)I
/*    */     //   1321: iflt -> 1328
/*    */     //   1324: iconst_1
/*    */     //   1325: goto -> 1329
/*    */     //   1328: iconst_0
/*    */     //   1329: ifne -> 1357
/*    */     //   1332: iload #15
/*    */     //   1334: sipush #12289
/*    */     //   1337: if_icmpeq -> 1357
/*    */     //   1340: iload #15
/*    */     //   1342: sipush #12290
/*    */     //   1345: if_icmpne -> 1351
/*    */     //   1348: goto -> 1357
/*    */     //   1351: iconst_0
/*    */     //   1352: istore #15
/*    */     //   1354: goto -> 1360
/*    */     //   1357: iconst_1
/*    */     //   1358: istore #15
/*    */     //   1360: iload #15
/*    */     //   1362: ifne -> 1452
/*    */     //   1365: iload #14
/*    */     //   1367: iload #5
/*    */     //   1369: if_icmple -> 1452
/*    */     //   1372: aload #4
/*    */     //   1374: iload #14
/*    */     //   1376: iconst_1
/*    */     //   1377: isub
/*    */     //   1378: invokevirtual charAt : (I)C
/*    */     //   1381: dup
/*    */     //   1382: istore #15
/*    */     //   1384: invokestatic isWhitespace : (C)Z
/*    */     //   1387: ifne -> 1434
/*    */     //   1390: ldc_w ':;,.-!?'
/*    */     //   1393: iload #15
/*    */     //   1395: invokevirtual indexOf : (I)I
/*    */     //   1398: iflt -> 1405
/*    */     //   1401: iconst_1
/*    */     //   1402: goto -> 1406
/*    */     //   1405: iconst_0
/*    */     //   1406: ifne -> 1434
/*    */     //   1409: iload #15
/*    */     //   1411: sipush #12289
/*    */     //   1414: if_icmpeq -> 1434
/*    */     //   1417: iload #15
/*    */     //   1419: sipush #12290
/*    */     //   1422: if_icmpne -> 1428
/*    */     //   1425: goto -> 1434
/*    */     //   1428: iconst_0
/*    */     //   1429: istore #15
/*    */     //   1431: goto -> 1437
/*    */     //   1434: iconst_1
/*    */     //   1435: istore #15
/*    */     //   1437: iload #15
/*    */     //   1439: ifne -> 1452
/*    */     //   1442: iinc #14, -1
/*    */     //   1445: goto -> 1365
/*    */     //   1448: iload #13
/*    */     //   1450: istore #14
/*    */     //   1452: iload #14
/*    */     //   1454: iload #5
/*    */     //   1456: if_icmple -> 1488
/*    */     //   1459: aload #4
/*    */     //   1461: iload #14
/*    */     //   1463: iconst_1
/*    */     //   1464: isub
/*    */     //   1465: invokevirtual charAt : (I)C
/*    */     //   1468: invokestatic isWhitespace : (C)Z
/*    */     //   1471: ifeq -> 1488
/*    */     //   1474: iinc #14, -1
/*    */     //   1477: goto -> 1452
/*    */     //   1480: iload #5
/*    */     //   1482: iload #5
/*    */     //   1484: istore #13
/*    */     //   1486: istore #14
/*    */     //   1488: iload #14
/*    */     //   1490: iconst_0
/*    */     //   1491: istore #15
/*    */     //   1493: iload #5
/*    */     //   1495: if_icmpne -> 1711
/*    */     //   1498: aload_1
/*    */     //   1499: getfield YP : Lf/AuX;
/*    */     //   1502: getstatic f/AuX.Ce0 : Lf/AuX;
/*    */     //   1505: if_acmpeq -> 1519
/*    */     //   1508: aload_1
/*    */     //   1509: iconst_0
/*    */     //   1510: invokevirtual OE0 : (Z)Z
/*    */     //   1513: ifeq -> 1519
/*    */     //   1516: goto -> 1169
/*    */     //   1519: aload #12
/*    */     //   1521: ifnonnull -> 1547
/*    */     //   1524: aload_2
/*    */     //   1525: getfield X10 : Lf/cR;
/*    */     //   1528: getstatic f/e00.BREAKWORD : Lf/e00;
/*    */     //   1531: dup
/*    */     //   1532: astore #12
/*    */     //   1534: invokevirtual bw0 : (Lf/e00;)Lf/cR;
/*    */     //   1537: aload #12
/*    */     //   1539: invokevirtual rI : (Lf/e00;)Ljava/lang/Object;
/*    */     //   1542: checkcast java/lang/Boolean
/*    */     //   1545: astore #12
/*    */     //   1547: aload #12
/*    */     //   1549: invokevirtual booleanValue : ()Z
/*    */     //   1552: ifeq -> 1575
/*    */     //   1555: iload #13
/*    */     //   1557: iload #5
/*    */     //   1559: if_icmpne -> 1704
/*    */     //   1562: iload #5
/*    */     //   1564: iconst_1
/*    */     //   1565: iadd
/*    */     //   1566: istore #13
/*    */     //   1568: iload #13
/*    */     //   1570: istore #14
/*    */     //   1572: goto -> 1708
/*    */     //   1575: iload #14
/*    */     //   1577: iload #9
/*    */     //   1579: if_icmpge -> 1656
/*    */     //   1582: aload #4
/*    */     //   1584: iload #14
/*    */     //   1586: invokevirtual charAt : (I)C
/*    */     //   1589: dup
/*    */     //   1590: istore #13
/*    */     //   1592: invokestatic isWhitespace : (C)Z
/*    */     //   1595: ifne -> 1642
/*    */     //   1598: ldc_w ':;,.-!?'
/*    */     //   1601: iload #13
/*    */     //   1603: invokevirtual indexOf : (I)I
/*    */     //   1606: iflt -> 1613
/*    */     //   1609: iconst_1
/*    */     //   1610: goto -> 1614
/*    */     //   1613: iconst_0
/*    */     //   1614: ifne -> 1642
/*    */     //   1617: iload #13
/*    */     //   1619: sipush #12289
/*    */     //   1622: if_icmpeq -> 1642
/*    */     //   1625: iload #13
/*    */     //   1627: sipush #12290
/*    */     //   1630: if_icmpne -> 1636
/*    */     //   1633: goto -> 1642
/*    */     //   1636: iconst_0
/*    */     //   1637: istore #13
/*    */     //   1639: goto -> 1645
/*    */     //   1642: iconst_1
/*    */     //   1643: istore #13
/*    */     //   1645: iload #13
/*    */     //   1647: ifne -> 1656
/*    */     //   1650: iinc #14, 1
/*    */     //   1653: goto -> 1575
/*    */     //   1656: iload #14
/*    */     //   1658: istore #13
/*    */     //   1660: iload #13
/*    */     //   1662: iload #9
/*    */     //   1664: if_icmpge -> 1704
/*    */     //   1667: aload #4
/*    */     //   1669: iload #13
/*    */     //   1671: invokevirtual charAt : (I)C
/*    */     //   1674: ldc_w ':;,.-!?'
/*    */     //   1677: swap
/*    */     //   1678: invokevirtual indexOf : (I)I
/*    */     //   1681: iflt -> 1690
/*    */     //   1684: iconst_1
/*    */     //   1685: istore #14
/*    */     //   1687: goto -> 1693
/*    */     //   1690: iconst_0
/*    */     //   1691: istore #14
/*    */     //   1693: iload #14
/*    */     //   1695: ifeq -> 1704
/*    */     //   1698: iinc #13, 1
/*    */     //   1701: goto -> 1660
/*    */     //   1704: iload #13
/*    */     //   1706: istore #14
/*    */     //   1708: iconst_1
/*    */     //   1709: istore #15
/*    */     //   1711: iload #5
/*    */     //   1713: iload #14
/*    */     //   1715: if_icmpge -> 1919
/*    */     //   1718: iload #15
/*    */     //   1720: new f/vB
/*    */     //   1723: dup
/*    */     //   1724: astore #13
/*    */     //   1726: aload_1
/*    */     //   1727: getfield Q10 : Z
/*    */     //   1730: istore #15
/*    */     //   1732: aload_2
/*    */     //   1733: aload #6
/*    */     //   1735: aload #4
/*    */     //   1737: iload #5
/*    */     //   1739: iload #14
/*    */     //   1741: iload #15
/*    */     //   1743: invokespecial <init> : (Lf/xc;Lf/PS;Ljava/lang/String;IIZ)V
/*    */     //   1746: ifeq -> 1778
/*    */     //   1749: aload_1
/*    */     //   1750: dup
/*    */     //   1751: dup
/*    */     //   1752: aload #13
/*    */     //   1754: getfield iw0 : I
/*    */     //   1757: istore #5
/*    */     //   1759: getfield qL : I
/*    */     //   1762: istore #15
/*    */     //   1764: getfield ML : I
/*    */     //   1767: istore #16
/*    */     //   1769: iload #5
/*    */     //   1771: iload #15
/*    */     //   1773: iload #16
/*    */     //   1775: invokevirtual pr : (III)V
/*    */     //   1778: aload_1
/*    */     //   1779: getfield YP : Lf/AuX;
/*    */     //   1782: getstatic f/AuX.Ce0 : Lf/AuX;
/*    */     //   1785: if_acmpne -> 1806
/*    */     //   1788: aload_1
/*    */     //   1789: invokevirtual sL : ()I
/*    */     //   1792: aload #13
/*    */     //   1794: getfield iw0 : I
/*    */     //   1797: if_icmpge -> 1806
/*    */     //   1800: aload_1
/*    */     //   1801: iconst_0
/*    */     //   1802: invokevirtual OE0 : (Z)Z
/*    */     //   1805: pop
/*    */     //   1806: iload #14
/*    */     //   1808: aload #13
/*    */     //   1810: getfield iw0 : I
/*    */     //   1813: istore #5
/*    */     //   1815: iload #9
/*    */     //   1817: if_icmpge -> 1846
/*    */     //   1820: aload #4
/*    */     //   1822: iload #14
/*    */     //   1824: invokevirtual charAt : (I)C
/*    */     //   1827: invokestatic isWhitespace : (C)Z
/*    */     //   1830: ifeq -> 1846
/*    */     //   1833: aload #11
/*    */     //   1835: checkcast f/t90
/*    */     //   1838: invokevirtual getSpaceWidth : ()I
/*    */     //   1841: iload #5
/*    */     //   1843: iadd
/*    */     //   1844: istore #5
/*    */     //   1846: aload_3
/*    */     //   1847: aload #13
/*    */     //   1849: aload_1
/*    */     //   1850: aload #13
/*    */     //   1852: iload #8
/*    */     //   1854: aload #13
/*    */     //   1856: aload_1
/*    */     //   1857: aload #13
/*    */     //   1859: aload_1
/*    */     //   1860: aload #13
/*    */     //   1862: aload_1
/*    */     //   1863: dup
/*    */     //   1864: getfield gC0 : I
/*    */     //   1867: dup
/*    */     //   1868: istore #15
/*    */     //   1870: iload #5
/*    */     //   1872: iadd
/*    */     //   1873: putfield gC0 : I
/*    */     //   1876: iload #15
/*    */     //   1878: putfield mx : I
/*    */     //   1881: getfield Ta : I
/*    */     //   1884: i2s
/*    */     //   1885: putfield X90 : S
/*    */     //   1888: getfield WM : Ljava/lang/String;
/*    */     //   1891: putfield bw : Ljava/lang/String;
/*    */     //   1894: putfield rH : Z
/*    */     //   1897: getfield pb0 : Ljava/util/ArrayList;
/*    */     //   1900: aload #13
/*    */     //   1902: invokevirtual add : (Ljava/lang/Object;)Z
/*    */     //   1905: pop
/*    */     //   1906: iconst_1
/*    */     //   1907: putfield Et0 : Z
/*    */     //   1910: getfield RQ : Ljava/util/ArrayList;
/*    */     //   1913: aload #13
/*    */     //   1915: invokevirtual add : (Ljava/lang/Object;)Z
/*    */     //   1918: pop
/*    */     //   1919: iload #14
/*    */     //   1921: istore #5
/*    */     //   1923: iload #5
/*    */     //   1925: iload #9
/*    */     //   1927: if_icmpge -> 1169
/*    */     //   1930: aload #4
/*    */     //   1932: iload #5
/*    */     //   1934: invokevirtual charAt : (I)C
/*    */     //   1937: invokestatic isWhitespace : (C)Z
/*    */     //   1940: ifeq -> 1169
/*    */     //   1943: iinc #5, 1
/*    */     //   1946: goto -> 1923
/*    */     //   1949: aload_1
/*    */     //   1950: invokevirtual zs0 : ()Z
/*    */     //   1953: ifne -> 1982
/*    */     //   1956: iload #10
/*    */     //   1958: ifeq -> 1982
/*    */     //   1961: aload_1
/*    */     //   1962: aload #11
/*    */     //   1964: aload_1
/*    */     //   1965: getfield gC0 : I
/*    */     //   1968: istore #4
/*    */     //   1970: checkcast f/t90
/*    */     //   1973: invokevirtual getSpaceWidth : ()I
/*    */     //   1976: iload #4
/*    */     //   1978: iadd
/*    */     //   1979: putfield gC0 : I
/*    */     //   1982: aload_0
/*    */     //   1983: aload_3
/*    */     //   1984: aload_1
/*    */     //   1985: aload_3
/*    */     //   1986: aload_1
/*    */     //   1987: aload_3
/*    */     //   1988: aload_1
/*    */     //   1989: aload_3
/*    */     //   1990: aload_1
/*    */     //   1991: aload_3
/*    */     //   1992: aload_1
/*    */     //   1993: aload_3
/*    */     //   1994: aload_1
/*    */     //   1995: aload_3
/*    */     //   1996: aload_1
/*    */     //   1997: aload_3
/*    */     //   1998: aload_1
/*    */     //   1999: aload_3
/*    */     //   2000: aload_1
/*    */     //   2001: aload_3
/*    */     //   2002: aload_1
/*    */     //   2003: aload_3
/*    */     //   2004: aload_1
/*    */     //   2005: aload_3
/*    */     //   2006: aload_1
/*    */     //   2007: aload_3
/*    */     //   2008: aload_1
/*    */     //   2009: aload_3
/*    */     //   2010: aload_1
/*    */     //   2011: aload_3
/*    */     //   2012: aload_1
/*    */     //   2013: aload_3
/*    */     //   2014: aload_1
/*    */     //   2015: aload_3
/*    */     //   2016: aload_1
/*    */     //   2017: aload_3
/*    */     //   2018: aload_1
/*    */     //   2019: aload_3
/*    */     //   2020: aload_1
/*    */     //   2021: aload_3
/*    */     //   2022: aload_1
/*    */     //   2023: aload_3
/*    */     //   2024: aload_1
/*    */     //   2025: aload_3
/*    */     //   2026: aload_1
/*    */     //   2027: dup
/*    */     //   2028: iload #7
/*    */     //   2030: putfield m00 : Z
/*    */     //   2033: getfield t0 : I
/*    */     //   2036: putfield oZ : I
/*    */     //   2039: getfield gC0 : I
/*    */     //   2042: putfield DP : I
/*    */     //   2045: getfield xu0 : I
/*    */     //   2048: putfield rg : I
/*    */     //   2051: getfield Xb0 : I
/*    */     //   2054: putfield L : I
/*    */     //   2057: getfield Ta : I
/*    */     //   2060: putfield eT : I
/*    */     //   2063: getfield qL : I
/*    */     //   2066: putfield Rw : I
/*    */     //   2069: getfield ML : I
/*    */     //   2072: putfield yf : I
/*    */     //   2075: getfield jy : I
/*    */     //   2078: putfield Y3 : I
/*    */     //   2081: getfield Fq : I
/*    */     //   2084: putfield COM3 : I
/*    */     //   2087: getfield VN : I
/*    */     //   2090: putfield break : I
/*    */     //   2093: getfield tl : I
/*    */     //   2096: putfield zc : I
/*    */     //   2099: getfield kj : I
/*    */     //   2102: putfield OE0 : I
/*    */     //   2105: getfield pn : I
/*    */     //   2108: putfield mz0 : I
/*    */     //   2111: getfield St0 : I
/*    */     //   2114: putfield Ob : I
/*    */     //   2117: getfield dd0 : I
/*    */     //   2120: putfield x60 : I
/*    */     //   2123: getfield SF : I
/*    */     //   2126: putfield Wr : I
/*    */     //   2129: getfield eS : Z
/*    */     //   2132: putfield ha : Z
/*    */     //   2135: getfield Oo : Z
/*    */     //   2138: putfield HH0 : Z
/*    */     //   2141: getfield m00 : Z
/*    */     //   2144: putfield jp : Z
/*    */     //   2147: getfield YP : Lf/AuX;
/*    */     //   2150: putfield KI : Lf/AuX;
/*    */     //   2153: getfield WM : Ljava/lang/String;
/*    */     //   2156: putfield Ea : Ljava/lang/String;
/*    */     //   2159: getfield LT : Lf/cR;
/*    */     //   2162: putfield hB0 : Lf/cR;
/*    */     //   2165: getfield dG0 : Ljava/util/HashMap;
/*    */     //   2168: aload_2
/*    */     //   2169: invokevirtual hashCode : ()I
/*    */     //   2172: invokestatic valueOf : (I)Ljava/lang/Integer;
/*    */     //   2175: aload_3
/*    */     //   2176: invokevirtual put : (Ljava/lang/Object;Ljava/lang/Object;)Ljava/lang/Object;
/*    */     //   2179: pop
/*    */     //   2180: goto -> 5733
/*    */     //   2183: aload_2
/*    */     //   2184: instanceof f/XA0
/*    */     //   2187: ifeq -> 2199
/*    */     //   2190: aload_1
/*    */     //   2191: iconst_1
/*    */     //   2192: invokevirtual OE0 : (Z)Z
/*    */     //   2195: pop
/*    */     //   2196: goto -> 5733
/*    */     //   2199: aload_1
/*    */     //   2200: getfield m00 : Z
/*    */     //   2203: ifeq -> 2217
/*    */     //   2206: aload_1
/*    */     //   2207: dup
/*    */     //   2208: iconst_0
/*    */     //   2209: invokevirtual OE0 : (Z)Z
/*    */     //   2212: pop
/*    */     //   2213: iconst_0
/*    */     //   2214: putfield m00 : Z
/*    */     //   2217: aload_2
/*    */     //   2218: instanceof f/ft
/*    */     //   2221: ifeq -> 2320
/*    */     //   2224: aload_1
/*    */     //   2225: aload_0
/*    */     //   2226: aload_1
/*    */     //   2227: dup
/*    */     //   2228: dup
/*    */     //   2229: aload_0
/*    */     //   2230: aload_1
/*    */     //   2231: aload_0
/*    */     //   2232: aload_2
/*    */     //   2233: checkcast f/ft
/*    */     //   2236: dup
/*    */     //   2237: astore_2
/*    */     //   2238: getfield X10 : Lf/cR;
/*    */     //   2241: dup
/*    */     //   2242: astore_3
/*    */     //   2243: invokevirtual Nz0 : (Lf/cR;)Lf/pe;
/*    */     //   2246: astore #4
/*    */     //   2248: aload_3
/*    */     //   2249: invokevirtual Si : (Lf/yD;Lf/cR;)V
/*    */     //   2252: aload_2
/*    */     //   2253: invokevirtual FF : (Lf/xc;)Lf/jT;
/*    */     //   2256: astore #5
/*    */     //   2258: aload_3
/*    */     //   2259: aload #4
/*    */     //   2261: iconst_1
/*    */     //   2262: invokevirtual LpT2 : (Lf/cR;Lf/pe;Z)V
/*    */     //   2265: aload_2
/*    */     //   2266: invokevirtual Sz : (Lf/yD;Ljava/lang/Iterable;)V
/*    */     //   2269: getfield YP : Lf/AuX;
/*    */     //   2272: getstatic f/AuX.Ce0 : Lf/AuX;
/*    */     //   2275: if_acmpne -> 2285
/*    */     //   2278: aload_1
/*    */     //   2279: getstatic f/AuX.XT : Lf/AuX;
/*    */     //   2282: putfield YP : Lf/AuX;
/*    */     //   2285: aload_0
/*    */     //   2286: aload_1
/*    */     //   2287: aload #5
/*    */     //   2289: aload_1
/*    */     //   2290: dup
/*    */     //   2291: dup
/*    */     //   2292: iconst_0
/*    */     //   2293: invokevirtual OE0 : (Z)Z
/*    */     //   2296: pop
/*    */     //   2297: iconst_0
/*    */     //   2298: putfield eS : Z
/*    */     //   2301: getfield t0 : I
/*    */     //   2304: aload #5
/*    */     //   2306: getfield dF : I
/*    */     //   2309: isub
/*    */     //   2310: putfield RA0 : I
/*    */     //   2313: aload_3
/*    */     //   2314: invokevirtual PE : (Lf/yD;Lf/cR;)V
/*    */     //   2317: goto -> 5733
/*    */     //   2320: aload_2
/*    */     //   2321: instanceof f/Cp
/*    */     //   2324: ifeq -> 2376
/*    */     //   2327: aload_0
/*    */     //   2328: aload_2
/*    */     //   2329: checkcast f/Cp
/*    */     //   2332: dup
/*    */     //   2333: astore_2
/*    */     //   2334: getfield mR : Ljava/lang/String;
/*    */     //   2337: invokevirtual Ca0 : (Ljava/lang/String;)Lf/mX;
/*    */     //   2340: dup
/*    */     //   2341: astore_3
/*    */     //   2342: ifnonnull -> 2348
/*    */     //   2345: goto -> 5733
/*    */     //   2348: aload_0
/*    */     //   2349: aload_1
/*    */     //   2350: new f/dK
/*    */     //   2353: dup
/*    */     //   2354: astore_0
/*    */     //   2355: aload_1
/*    */     //   2356: aload_0
/*    */     //   2357: aload_2
/*    */     //   2358: aload_3
/*    */     //   2359: invokespecial <init> : (Lf/xc;Lf/mX;)V
/*    */     //   2362: getfield WM : Ljava/lang/String;
/*    */     //   2365: putfield bw : Ljava/lang/String;
/*    */     //   2368: aload_2
/*    */     //   2369: aload_0
/*    */     //   2370: invokevirtual o0 : (Lf/yD;Lf/xc;Lf/jT;)V
/*    */     //   2373: goto -> 5733
/*    */     //   2376: aload_2
/*    */     //   2377: instanceof f/ga
/*    */     //   2380: ifeq -> 2539
/*    */     //   2383: aload_0
/*    */     //   2384: aload_2
/*    */     //   2385: checkcast f/ga
/*    */     //   2388: astore_2
/*    */     //   2389: getfield Y3 : Ljava/util/HashMap;
/*    */     //   2392: aload_2
/*    */     //   2393: getfield Ap : Ljava/lang/String;
/*    */     //   2396: invokevirtual get : (Ljava/lang/Object;)Ljava/lang/Object;
/*    */     //   2399: checkcast f/JG0
/*    */     //   2402: dup
/*    */     //   2403: astore_3
/*    */     //   2404: ifnonnull -> 2462
/*    */     //   2407: aload_0
/*    */     //   2408: getfield ii0 : Ljava/util/HashMap;
/*    */     //   2411: aload_2
/*    */     //   2412: getfield Ap : Ljava/lang/String;
/*    */     //   2415: invokevirtual get : (Ljava/lang/Object;)Ljava/lang/Object;
/*    */     //   2418: checkcast f/aF0
/*    */     //   2421: dup
/*    */     //   2422: astore #4
/*    */     //   2424: ifnull -> 2455
/*    */     //   2427: aload_2
/*    */     //   2428: getfield T50 : Ljava/lang/String;
/*    */     //   2431: astore_3
/*    */     //   2432: new f/cX
/*    */     //   2435: dup
/*    */     //   2436: dup
/*    */     //   2437: astore #5
/*    */     //   2439: aload #4
/*    */     //   2441: aload_3
/*    */     //   2442: dup
/*    */     //   2443: invokespecial <init> : (Lf/aF0;Ljava/lang/String;Ljava/lang/String;)V
/*    */     //   2446: ldc_w 'chat-playername'
/*    */     //   2449: invokevirtual Xu : (Ljava/lang/String;)V
/*    */     //   2452: aload #5
/*    */     //   2454: astore_3
/*    */     //   2455: aload_3
/*    */     //   2456: ifnonnull -> 2462
/*    */     //   2459: goto -> 5733
/*    */     //   2462: aload_3
/*    */     //   2463: getfield fr0 : Lf/JG0;
/*    */     //   2466: ifnull -> 2490
/*    */     //   2469: ldc f/f9
/*    */     //   2471: invokevirtual getName : ()Ljava/lang/String;
/*    */     //   2474: invokestatic getLogger : (Ljava/lang/String;)Ljava/util/logging/Logger;
/*    */     //   2477: getstatic java/util/logging/Level.SEVERE : Ljava/util/logging/Level;
/*    */     //   2480: ldc_w 'Widget already added: {0}'
/*    */     //   2483: aload_3
/*    */     //   2484: invokevirtual log : (Ljava/util/logging/Level;Ljava/lang/String;Ljava/lang/Object;)V
/*    */     //   2487: goto -> 5733
/*    */     //   2490: aload_0
/*    */     //   2491: aload_1
/*    */     //   2492: aload_2
/*    */     //   2493: aload_3
/*    */     //   2494: aload_0
/*    */     //   2495: aload_3
/*    */     //   2496: aload_0
/*    */     //   2497: invokevirtual Ub : ()I
/*    */     //   2500: invokespecial si : (Lf/JG0;I)V
/*    */     //   2503: invokevirtual mM : ()V
/*    */     //   2506: new f/Fv0
/*    */     //   2509: dup
/*    */     //   2510: astore_0
/*    */     //   2511: aload_3
/*    */     //   2512: aload_0
/*    */     //   2513: aload_3
/*    */     //   2514: aload_0
/*    */     //   2515: aload_2
/*    */     //   2516: aload_3
/*    */     //   2517: invokespecial <init> : (Lf/xc;Lf/JG0;)V
/*    */     //   2520: getfield xY : I
/*    */     //   2523: putfield iw0 : I
/*    */     //   2526: getfield HC : I
/*    */     //   2529: putfield RA0 : I
/*    */     //   2532: aload_0
/*    */     //   2533: invokevirtual o0 : (Lf/yD;Lf/xc;Lf/jT;)V
/*    */     //   2536: goto -> 5733
/*    */     //   2539: aload_2
/*    */     //   2540: instanceof f/Zc0
/*    */     //   2543: ifeq -> 2858
/*    */     //   2546: aload_2
/*    */     //   2547: checkcast f/Zc0
/*    */     //   2550: dup
/*    */     //   2551: astore_2
/*    */     //   2552: getfield X10 : Lf/cR;
/*    */     //   2555: dup
/*    */     //   2556: astore_3
/*    */     //   2557: aload_0
/*    */     //   2558: aload_1
/*    */     //   2559: aload_3
/*    */     //   2560: invokevirtual Si : (Lf/yD;Lf/cR;)V
/*    */     //   2563: getstatic f/e00.LIST_STYLE_IMAGE : Lf/e00;
/*    */     //   2566: dup
/*    */     //   2567: astore #4
/*    */     //   2569: invokevirtual bw0 : (Lf/e00;)Lf/cR;
/*    */     //   2572: aload #4
/*    */     //   2574: invokevirtual rI : (Lf/e00;)Ljava/lang/Object;
/*    */     //   2577: checkcast java/lang/String
/*    */     //   2580: dup
/*    */     //   2581: astore #4
/*    */     //   2583: ifnull -> 2597
/*    */     //   2586: aload_0
/*    */     //   2587: aload #4
/*    */     //   2589: invokevirtual Ca0 : (Ljava/lang/String;)Lf/mX;
/*    */     //   2592: astore #4
/*    */     //   2594: goto -> 2600
/*    */     //   2597: aconst_null
/*    */     //   2598: astore #4
/*    */     //   2600: aload #4
/*    */     //   2602: ifnull -> 2837
/*    */     //   2605: new f/dK
/*    */     //   2608: dup
/*    */     //   2609: astore #5
/*    */     //   2611: aload_1
/*    */     //   2612: aload #5
/*    */     //   2614: aload_0
/*    */     //   2615: aload_1
/*    */     //   2616: aload #5
/*    */     //   2618: dup
/*    */     //   2619: aload_1
/*    */     //   2620: aload_2
/*    */     //   2621: aload #5
/*    */     //   2623: aload_0
/*    */     //   2624: aload_3
/*    */     //   2625: aload_1
/*    */     //   2626: aload #5
/*    */     //   2628: aload_2
/*    */     //   2629: aload #4
/*    */     //   2631: invokespecial <init> : (Lf/xc;Lf/mX;)V
/*    */     //   2634: getstatic f/e00.PADDING_LEFT : Lf/e00;
/*    */     //   2637: astore #4
/*    */     //   2639: getfield qR : I
/*    */     //   2642: aload #4
/*    */     //   2644: swap
/*    */     //   2645: iconst_0
/*    */     //   2646: invokevirtual Gf : (Lf/cR;Lf/e00;II)I
/*    */     //   2649: iconst_0
/*    */     //   2650: swap
/*    */     //   2651: invokestatic max : (II)I
/*    */     //   2654: i2s
/*    */     //   2655: putfield li : S
/*    */     //   2658: getstatic f/Gj.Og0 : Lf/Gj;
/*    */     //   2661: getstatic f/Sx0.nI0 : Lf/Sx0;
/*    */     //   2664: astore #4
/*    */     //   2666: aload #5
/*    */     //   2668: swap
/*    */     //   2669: aload #4
/*    */     //   2671: invokestatic an : (Lf/yD;Lf/xc;Lf/jT;Lf/Gj;Lf/Sx0;)V
/*    */     //   2674: getfield RA0 : I
/*    */     //   2677: istore #4
/*    */     //   2679: sipush #32767
/*    */     //   2682: putfield RA0 : I
/*    */     //   2685: aload_2
/*    */     //   2686: invokevirtual Sz : (Lf/yD;Ljava/lang/Iterable;)V
/*    */     //   2689: iload #4
/*    */     //   2691: putfield RA0 : I
/*    */     //   2694: getfield o4 : Ljava/util/ArrayList;
/*    */     //   2697: aload #5
/*    */     //   2699: invokevirtual remove : (Ljava/lang/Object;)Z
/*    */     //   2702: pop
/*    */     //   2703: invokevirtual Ia : ()I
/*    */     //   2706: dup
/*    */     //   2707: istore_2
/*    */     //   2708: aload_1
/*    */     //   2709: dup
/*    */     //   2710: iconst_0
/*    */     //   2711: invokevirtual OE0 : (Z)Z
/*    */     //   2714: pop
/*    */     //   2715: getfield t0 : I
/*    */     //   2718: if_icmple -> 2830
/*    */     //   2721: aload_1
/*    */     //   2722: dup
/*    */     //   2723: iload_2
/*    */     //   2724: putfield t0 : I
/*    */     //   2727: getfield o4 : Ljava/util/ArrayList;
/*    */     //   2730: dup
/*    */     //   2731: astore_2
/*    */     //   2732: invokevirtual size : ()I
/*    */     //   2735: istore #4
/*    */     //   2737: iload #4
/*    */     //   2739: dup
/*    */     //   2740: iconst_m1
/*    */     //   2741: iadd
/*    */     //   2742: istore #4
/*    */     //   2744: ifle -> 2776
/*    */     //   2747: aload_2
/*    */     //   2748: iload #4
/*    */     //   2750: invokevirtual get : (I)Ljava/lang/Object;
/*    */     //   2753: checkcast f/jT
/*    */     //   2756: invokevirtual Ia : ()I
/*    */     //   2759: aload_1
/*    */     //   2760: getfield t0 : I
/*    */     //   2763: if_icmpgt -> 2737
/*    */     //   2766: aload_2
/*    */     //   2767: iload #4
/*    */     //   2769: invokevirtual remove : (I)Ljava/lang/Object;
/*    */     //   2772: pop
/*    */     //   2773: goto -> 2737
/*    */     //   2776: aload_1
/*    */     //   2777: getfield A60 : Ljava/util/ArrayList;
/*    */     //   2780: dup
/*    */     //   2781: astore_2
/*    */     //   2782: invokevirtual size : ()I
/*    */     //   2785: istore #4
/*    */     //   2787: iload #4
/*    */     //   2789: dup
/*    */     //   2790: iconst_m1
/*    */     //   2791: iadd
/*    */     //   2792: istore #4
/*    */     //   2794: ifle -> 2826
/*    */     //   2797: aload_2
/*    */     //   2798: iload #4
/*    */     //   2800: invokevirtual get : (I)Ljava/lang/Object;
/*    */     //   2803: checkcast f/jT
/*    */     //   2806: invokevirtual Ia : ()I
/*    */     //   2809: aload_1
/*    */     //   2810: getfield t0 : I
/*    */     //   2813: if_icmpgt -> 2787
/*    */     //   2816: aload_2
/*    */     //   2817: iload #4
/*    */     //   2819: invokevirtual remove : (I)Ljava/lang/Object;
/*    */     //   2822: pop
/*    */     //   2823: goto -> 2787
/*    */     //   2826: aload_1
/*    */     //   2827: invokevirtual lo : ()V
/*    */     //   2830: aload_1
/*    */     //   2831: invokevirtual lo : ()V
/*    */     //   2834: goto -> 2849
/*    */     //   2837: aload_1
/*    */     //   2838: aload_0
/*    */     //   2839: aload_1
/*    */     //   2840: aload_2
/*    */     //   2841: invokevirtual Sz : (Lf/yD;Ljava/lang/Iterable;)V
/*    */     //   2844: iconst_0
/*    */     //   2845: invokevirtual OE0 : (Z)Z
/*    */     //   2848: pop
/*    */     //   2849: aload_0
/*    */     //   2850: aload_1
/*    */     //   2851: aload_3
/*    */     //   2852: invokevirtual PE : (Lf/yD;Lf/cR;)V
/*    */     //   2855: goto -> 5733
/*    */     //   2858: aload_2
/*    */     //   2859: instanceof f/iv0
/*    */     //   2862: ifeq -> 3471
/*    */     //   2865: aload_0
/*    */     //   2866: aload_2
/*    */     //   2867: checkcast f/iv0
/*    */     //   2870: dup
/*    */     //   2871: astore_2
/*    */     //   2872: getfield X10 : Lf/cR;
/*    */     //   2875: dup
/*    */     //   2876: astore_3
/*    */     //   2877: invokevirtual Nz0 : (Lf/cR;)Lf/pe;
/*    */     //   2880: dup
/*    */     //   2881: astore #4
/*    */     //   2883: ifnonnull -> 2892
/*    */     //   2886: aconst_null
/*    */     //   2887: astore #4
/*    */     //   2889: goto -> 2948
/*    */     //   2892: new f/PS
/*    */     //   2895: dup
/*    */     //   2896: astore #5
/*    */     //   2898: aload #4
/*    */     //   2900: aload_3
/*    */     //   2901: dup
/*    */     //   2902: getstatic f/e00.COLOR : Lf/e00;
/*    */     //   2905: dup
/*    */     //   2906: astore #4
/*    */     //   2908: invokevirtual bw0 : (Lf/e00;)Lf/cR;
/*    */     //   2911: aload #4
/*    */     //   2913: invokevirtual rI : (Lf/e00;)Ljava/lang/Object;
/*    */     //   2916: checkcast f/pRn
/*    */     //   2919: astore #4
/*    */     //   2921: getstatic f/e00.COLOR_HOVER : Lf/e00;
/*    */     //   2924: dup
/*    */     //   2925: astore #6
/*    */     //   2927: invokevirtual bw0 : (Lf/e00;)Lf/cR;
/*    */     //   2930: aload #6
/*    */     //   2932: invokevirtual rI : (Lf/e00;)Ljava/lang/Object;
/*    */     //   2935: checkcast f/pRn
/*    */     //   2938: aload #4
/*    */     //   2940: swap
/*    */     //   2941: invokespecial <init> : (Lf/pe;Lf/pRn;Lf/pRn;)V
/*    */     //   2944: aload #5
/*    */     //   2946: astore #4
/*    */     //   2948: aload #4
/*    */     //   2950: ifnonnull -> 2956
/*    */     //   2953: goto -> 5733
/*    */     //   2956: aload_0
/*    */     //   2957: aload_3
/*    */     //   2958: aload_1
/*    */     //   2959: aload_2
/*    */     //   2960: dup
/*    */     //   2961: aload_1
/*    */     //   2962: aload_2
/*    */     //   2963: aload_0
/*    */     //   2964: aload_1
/*    */     //   2965: aload_3
/*    */     //   2966: invokevirtual Si : (Lf/yD;Lf/cR;)V
/*    */     //   2969: invokevirtual FF : (Lf/xc;)Lf/jT;
/*    */     //   2972: astore #5
/*    */     //   2974: getfield ZF : I
/*    */     //   2977: iconst_1
/*    */     //   2978: swap
/*    */     //   2979: invokestatic max : (II)I
/*    */     //   2982: istore #6
/*    */     //   2984: getfield k60 : Ljava/util/ArrayList;
/*    */     //   2987: invokevirtual size : ()I
/*    */     //   2990: dup
/*    */     //   2991: istore #7
/*    */     //   2993: aload_3
/*    */     //   2994: getstatic f/e00.LIST_STYLE_TYPE : Lf/e00;
/*    */     //   2997: dup
/*    */     //   2998: astore #8
/*    */     //   3000: invokevirtual bw0 : (Lf/e00;)Lf/cR;
/*    */     //   3003: aload #8
/*    */     //   3005: invokevirtual rI : (Lf/e00;)Ljava/lang/Object;
/*    */     //   3008: checkcast f/au
/*    */     //   3011: astore #8
/*    */     //   3013: anewarray java/lang/String
/*    */     //   3016: astore #9
/*    */     //   3018: getstatic f/e00.PADDING_LEFT : Lf/e00;
/*    */     //   3021: astore #10
/*    */     //   3023: getfield qR : I
/*    */     //   3026: aload #10
/*    */     //   3028: swap
/*    */     //   3029: iconst_0
/*    */     //   3030: invokevirtual Gf : (Lf/cR;Lf/e00;II)I
/*    */     //   3033: iconst_0
/*    */     //   3034: swap
/*    */     //   3035: invokestatic max : (II)I
/*    */     //   3038: istore #10
/*    */     //   3040: iconst_0
/*    */     //   3041: istore #11
/*    */     //   3043: iload #11
/*    */     //   3045: iload #7
/*    */     //   3047: if_icmpge -> 3100
/*    */     //   3050: iload #10
/*    */     //   3052: aload #4
/*    */     //   3054: aload #9
/*    */     //   3056: iload #11
/*    */     //   3058: aload #8
/*    */     //   3060: iload #6
/*    */     //   3062: iload #11
/*    */     //   3064: iadd
/*    */     //   3065: invokevirtual kq0 : (I)Ljava/lang/String;
/*    */     //   3068: ldc_w '. '
/*    */     //   3071: invokevirtual concat : (Ljava/lang/String;)Ljava/lang/String;
/*    */     //   3074: dup
/*    */     //   3075: astore #10
/*    */     //   3077: aastore
/*    */     //   3078: getfield ZU : Lf/pe;
/*    */     //   3081: checkcast f/t90
/*    */     //   3084: aload #10
/*    */     //   3086: invokevirtual computeTextWidth : (Ljava/lang/CharSequence;)I
/*    */     //   3089: invokestatic max : (II)I
/*    */     //   3092: istore #10
/*    */     //   3094: iinc #11, 1
/*    */     //   3097: goto -> 3043
/*    */     //   3100: iconst_0
/*    */     //   3101: istore #6
/*    */     //   3103: iload #6
/*    */     //   3105: iload #7
/*    */     //   3107: if_icmpge -> 3447
/*    */     //   3110: aload_0
/*    */     //   3111: aload_1
/*    */     //   3112: aload_2
/*    */     //   3113: aload #9
/*    */     //   3115: iload #6
/*    */     //   3117: aaload
/*    */     //   3118: astore #8
/*    */     //   3120: getfield k60 : Ljava/util/ArrayList;
/*    */     //   3123: iload #6
/*    */     //   3125: invokevirtual get : (I)Ljava/lang/Object;
/*    */     //   3128: checkcast f/xc
/*    */     //   3131: dup
/*    */     //   3132: astore #11
/*    */     //   3134: getfield X10 : Lf/cR;
/*    */     //   3137: dup
/*    */     //   3138: astore #12
/*    */     //   3140: invokevirtual Si : (Lf/yD;Lf/cR;)V
/*    */     //   3143: new f/vB
/*    */     //   3146: dup
/*    */     //   3147: astore #13
/*    */     //   3149: aload_1
/*    */     //   3150: aload #13
/*    */     //   3152: aload_0
/*    */     //   3153: aload_1
/*    */     //   3154: aload #13
/*    */     //   3156: dup
/*    */     //   3157: iload #10
/*    */     //   3159: aload #13
/*    */     //   3161: aload_1
/*    */     //   3162: aload_2
/*    */     //   3163: aload #13
/*    */     //   3165: aload_0
/*    */     //   3166: aload #12
/*    */     //   3168: aload_1
/*    */     //   3169: aload #13
/*    */     //   3171: dup
/*    */     //   3172: dup
/*    */     //   3173: aload_2
/*    */     //   3174: aload_1
/*    */     //   3175: aload #8
/*    */     //   3177: invokevirtual length : ()I
/*    */     //   3180: istore #14
/*    */     //   3182: getfield Q10 : Z
/*    */     //   3185: istore #15
/*    */     //   3187: aload #4
/*    */     //   3189: aload #8
/*    */     //   3191: iconst_0
/*    */     //   3192: iload #14
/*    */     //   3194: iload #15
/*    */     //   3196: invokespecial <init> : (Lf/xc;Lf/PS;Ljava/lang/String;IIZ)V
/*    */     //   3199: getfield iw0 : I
/*    */     //   3202: istore #8
/*    */     //   3204: getfield RA0 : I
/*    */     //   3207: istore #14
/*    */     //   3209: getstatic f/e00.PADDING_LEFT : Lf/e00;
/*    */     //   3212: astore #15
/*    */     //   3214: getfield qR : I
/*    */     //   3217: aload #15
/*    */     //   3219: swap
/*    */     //   3220: iconst_0
/*    */     //   3221: invokevirtual Gf : (Lf/cR;Lf/e00;II)I
/*    */     //   3224: iconst_0
/*    */     //   3225: swap
/*    */     //   3226: invokestatic max : (II)I
/*    */     //   3229: iload #8
/*    */     //   3231: iadd
/*    */     //   3232: putfield iw0 : I
/*    */     //   3235: getstatic f/Gj.Og0 : Lf/Gj;
/*    */     //   3238: getstatic f/Sx0.nI0 : Lf/Sx0;
/*    */     //   3241: astore #15
/*    */     //   3243: aload #13
/*    */     //   3245: swap
/*    */     //   3246: aload #15
/*    */     //   3248: invokestatic an : (Lf/yD;Lf/xc;Lf/jT;Lf/Gj;Lf/Sx0;)V
/*    */     //   3251: getfield mx : I
/*    */     //   3254: istore #15
/*    */     //   3256: iload #8
/*    */     //   3258: isub
/*    */     //   3259: iconst_0
/*    */     //   3260: swap
/*    */     //   3261: invokestatic max : (II)I
/*    */     //   3264: iload #15
/*    */     //   3266: iadd
/*    */     //   3267: putfield mx : I
/*    */     //   3270: sipush #32767
/*    */     //   3273: putfield RA0 : I
/*    */     //   3276: aload #11
/*    */     //   3278: invokevirtual pt : (Lf/yD;Lf/xc;)V
/*    */     //   3281: iload #14
/*    */     //   3283: putfield RA0 : I
/*    */     //   3286: getfield o4 : Ljava/util/ArrayList;
/*    */     //   3289: aload #13
/*    */     //   3291: invokevirtual remove : (Ljava/lang/Object;)Z
/*    */     //   3294: pop
/*    */     //   3295: invokevirtual Ia : ()I
/*    */     //   3298: dup
/*    */     //   3299: istore #8
/*    */     //   3301: aload_1
/*    */     //   3302: dup
/*    */     //   3303: iconst_0
/*    */     //   3304: invokevirtual OE0 : (Z)Z
/*    */     //   3307: pop
/*    */     //   3308: getfield t0 : I
/*    */     //   3311: if_icmple -> 3430
/*    */     //   3314: aload_1
/*    */     //   3315: dup
/*    */     //   3316: iload #8
/*    */     //   3318: putfield t0 : I
/*    */     //   3321: getfield o4 : Ljava/util/ArrayList;
/*    */     //   3324: dup
/*    */     //   3325: astore #8
/*    */     //   3327: invokevirtual size : ()I
/*    */     //   3330: istore #11
/*    */     //   3332: iload #11
/*    */     //   3334: dup
/*    */     //   3335: iconst_m1
/*    */     //   3336: iadd
/*    */     //   3337: istore #11
/*    */     //   3339: ifle -> 3373
/*    */     //   3342: aload #8
/*    */     //   3344: iload #11
/*    */     //   3346: invokevirtual get : (I)Ljava/lang/Object;
/*    */     //   3349: checkcast f/jT
/*    */     //   3352: invokevirtual Ia : ()I
/*    */     //   3355: aload_1
/*    */     //   3356: getfield t0 : I
/*    */     //   3359: if_icmpgt -> 3332
/*    */     //   3362: aload #8
/*    */     //   3364: iload #11
/*    */     //   3366: invokevirtual remove : (I)Ljava/lang/Object;
/*    */     //   3369: pop
/*    */     //   3370: goto -> 3332
/*    */     //   3373: aload_1
/*    */     //   3374: getfield A60 : Ljava/util/ArrayList;
/*    */     //   3377: dup
/*    */     //   3378: astore #8
/*    */     //   3380: invokevirtual size : ()I
/*    */     //   3383: istore #11
/*    */     //   3385: iload #11
/*    */     //   3387: dup
/*    */     //   3388: iconst_m1
/*    */     //   3389: iadd
/*    */     //   3390: istore #11
/*    */     //   3392: ifle -> 3426
/*    */     //   3395: aload #8
/*    */     //   3397: iload #11
/*    */     //   3399: invokevirtual get : (I)Ljava/lang/Object;
/*    */     //   3402: checkcast f/jT
/*    */     //   3405: invokevirtual Ia : ()I
/*    */     //   3408: aload_1
/*    */     //   3409: getfield t0 : I
/*    */     //   3412: if_icmpgt -> 3385
/*    */     //   3415: aload #8
/*    */     //   3417: iload #11
/*    */     //   3419: invokevirtual remove : (I)Ljava/lang/Object;
/*    */     //   3422: pop
/*    */     //   3423: goto -> 3385
/*    */     //   3426: aload_1
/*    */     //   3427: invokevirtual lo : ()V
/*    */     //   3430: aload_0
/*    */     //   3431: aload_1
/*    */     //   3432: invokevirtual lo : ()V
/*    */     //   3435: aload_1
/*    */     //   3436: aload #12
/*    */     //   3438: invokevirtual PE : (Lf/yD;Lf/cR;)V
/*    */     //   3441: iinc #6, 1
/*    */     //   3444: goto -> 3103
/*    */     //   3447: aload_0
/*    */     //   3448: aload_1
/*    */     //   3449: aload #5
/*    */     //   3451: aload_1
/*    */     //   3452: getfield t0 : I
/*    */     //   3455: aload #5
/*    */     //   3457: getfield dF : I
/*    */     //   3460: isub
/*    */     //   3461: putfield RA0 : I
/*    */     //   3464: aload_3
/*    */     //   3465: invokevirtual PE : (Lf/yD;Lf/cR;)V
/*    */     //   3468: goto -> 5733
/*    */     //   3471: aload_2
/*    */     //   3472: instanceof f/jr
/*    */     //   3475: ifeq -> 3491
/*    */     //   3478: aload_0
/*    */     //   3479: aload_2
/*    */     //   3480: checkcast f/jr
/*    */     //   3483: aload_1
/*    */     //   3484: swap
/*    */     //   3485: invokevirtual vq0 : (Lf/yD;Lf/Ct;)V
/*    */     //   3488: goto -> 5733
/*    */     //   3491: aload_2
/*    */     //   3492: instanceof f/KN
/*    */     //   3495: ifeq -> 5566
/*    */     //   3498: aload_2
/*    */     //   3499: checkcast f/KN
/*    */     //   3502: dup
/*    */     //   3503: astore_2
/*    */     //   3504: getfield g50 : I
/*    */     //   3507: dup
/*    */     //   3508: istore_3
/*    */     //   3509: aload_2
/*    */     //   3510: dup
/*    */     //   3511: dup2
/*    */     //   3512: getfield bD : I
/*    */     //   3515: istore #4
/*    */     //   3517: getfield Qi : I
/*    */     //   3520: istore #5
/*    */     //   3522: getfield mE0 : I
/*    */     //   3525: istore #6
/*    */     //   3527: getfield X10 : Lf/cR;
/*    */     //   3530: astore #7
/*    */     //   3532: ifeq -> 5733
/*    */     //   3535: iload #4
/*    */     //   3537: ifne -> 3543
/*    */     //   3540: goto -> 5733
/*    */     //   3543: aload_1
/*    */     //   3544: aload_0
/*    */     //   3545: aload #7
/*    */     //   3547: aload_1
/*    */     //   3548: dup
/*    */     //   3549: aload_0
/*    */     //   3550: aload #7
/*    */     //   3552: aload_1
/*    */     //   3553: dup
/*    */     //   3554: aload_2
/*    */     //   3555: aload_0
/*    */     //   3556: aload_1
/*    */     //   3557: aload #7
/*    */     //   3559: invokevirtual Si : (Lf/yD;Lf/cR;)V
/*    */     //   3562: invokevirtual FF : (Lf/xc;)Lf/jT;
/*    */     //   3565: astore #8
/*    */     //   3567: getstatic f/e00.MARGIN_LEFT : Lf/e00;
/*    */     //   3570: astore #9
/*    */     //   3572: getfield qR : I
/*    */     //   3575: aload #9
/*    */     //   3577: swap
/*    */     //   3578: iconst_0
/*    */     //   3579: invokevirtual Gf : (Lf/cR;Lf/e00;II)I
/*    */     //   3582: iconst_0
/*    */     //   3583: swap
/*    */     //   3584: invokestatic max : (II)I
/*    */     //   3587: invokevirtual o70 : (I)I
/*    */     //   3590: istore #9
/*    */     //   3592: getstatic f/e00.MARGIN_RIGHT : Lf/e00;
/*    */     //   3595: astore #10
/*    */     //   3597: getfield qR : I
/*    */     //   3600: aload #10
/*    */     //   3602: swap
/*    */     //   3603: iconst_0
/*    */     //   3604: invokevirtual Gf : (Lf/cR;Lf/e00;II)I
/*    */     //   3607: iconst_0
/*    */     //   3608: swap
/*    */     //   3609: invokestatic max : (II)I
/*    */     //   3612: invokevirtual CQ : (I)I
/*    */     //   3615: iload #9
/*    */     //   3617: isub
/*    */     //   3618: iconst_0
/*    */     //   3619: swap
/*    */     //   3620: invokestatic max : (II)I
/*    */     //   3623: dup
/*    */     //   3624: istore #10
/*    */     //   3626: aload_0
/*    */     //   3627: aload #7
/*    */     //   3629: aload_1
/*    */     //   3630: getstatic f/e00.WIDTH : Lf/e00;
/*    */     //   3633: astore #11
/*    */     //   3635: getfield qR : I
/*    */     //   3638: aload #11
/*    */     //   3640: swap
/*    */     //   3641: ldc_w -2147483648
/*    */     //   3644: invokevirtual Gf : (Lf/cR;Lf/e00;II)I
/*    */     //   3647: invokestatic min : (II)I
/*    */     //   3650: dup
/*    */     //   3651: istore #11
/*    */     //   3653: ldc_w -2147483648
/*    */     //   3656: if_icmpne -> 3665
/*    */     //   3659: iconst_1
/*    */     //   3660: istore #12
/*    */     //   3662: goto -> 3668
/*    */     //   3665: iconst_0
/*    */     //   3666: istore #12
/*    */     //   3668: iload #11
/*    */     //   3670: ifgt -> 3677
/*    */     //   3673: iload #10
/*    */     //   3675: istore #11
/*    */     //   3677: aload_2
/*    */     //   3678: dup
/*    */     //   3679: dup2
/*    */     //   3680: iload_3
/*    */     //   3681: newarray int
/*    */     //   3683: astore #13
/*    */     //   3685: iload_3
/*    */     //   3686: iconst_1
/*    */     //   3687: iadd
/*    */     //   3688: dup
/*    */     //   3689: istore #14
/*    */     //   3691: newarray int
/*    */     //   3693: dup
/*    */     //   3694: astore #15
/*    */     //   3696: iload #5
/*    */     //   3698: aload_0
/*    */     //   3699: aload #7
/*    */     //   3701: aload_1
/*    */     //   3702: iload_3
/*    */     //   3703: newarray boolean
/*    */     //   3705: astore #16
/*    */     //   3707: getstatic f/e00.PADDING_LEFT : Lf/e00;
/*    */     //   3710: astore #17
/*    */     //   3712: getfield qR : I
/*    */     //   3715: aload #17
/*    */     //   3717: swap
/*    */     //   3718: iconst_0
/*    */     //   3719: invokevirtual Gf : (Lf/cR;Lf/e00;II)I
/*    */     //   3722: iconst_0
/*    */     //   3723: swap
/*    */     //   3724: invokestatic max : (II)I
/*    */     //   3727: invokestatic max : (II)I
/*    */     //   3730: iconst_0
/*    */     //   3731: swap
/*    */     //   3732: iastore
/*    */     //   3733: getfield g50 : I
/*    */     //   3736: istore #17
/*    */     //   3738: getfield bD : I
/*    */     //   3741: istore #18
/*    */     //   3743: getfield Qi : I
/*    */     //   3746: istore #19
/*    */     //   3748: getfield mE0 : I
/*    */     //   3751: istore #20
/*    */     //   3753: aconst_null
/*    */     //   3754: astore #21
/*    */     //   3756: iconst_0
/*    */     //   3757: istore #22
/*    */     //   3759: iload #22
/*    */     //   3761: iload #17
/*    */     //   3763: if_icmpge -> 4146
/*    */     //   3766: iconst_0
/*    */     //   3767: istore #23
/*    */     //   3769: iconst_0
/*    */     //   3770: istore #24
/*    */     //   3772: iconst_0
/*    */     //   3773: istore #25
/*    */     //   3775: iconst_0
/*    */     //   3776: istore #26
/*    */     //   3778: iconst_0
/*    */     //   3779: istore #27
/*    */     //   3781: iload #27
/*    */     //   3783: iload #18
/*    */     //   3785: if_icmpge -> 4098
/*    */     //   3788: aload_2
/*    */     //   3789: iload #27
/*    */     //   3791: iload #22
/*    */     //   3793: invokevirtual nF : (II)Lf/bJ;
/*    */     //   3796: dup
/*    */     //   3797: astore #28
/*    */     //   3799: ifnull -> 4092
/*    */     //   3802: aload_0
/*    */     //   3803: aload #28
/*    */     //   3805: dup
/*    */     //   3806: getfield X10 : Lf/cR;
/*    */     //   3809: astore #29
/*    */     //   3811: getfield zd : I
/*    */     //   3814: istore #30
/*    */     //   3816: getstatic f/e00.WIDTH : Lf/e00;
/*    */     //   3819: aload #29
/*    */     //   3821: swap
/*    */     //   3822: iload #11
/*    */     //   3824: ldc_w -2147483648
/*    */     //   3827: invokevirtual Gf : (Lf/cR;Lf/e00;II)I
/*    */     //   3830: dup
/*    */     //   3831: istore #31
/*    */     //   3833: ldc_w -2147483648
/*    */     //   3836: if_icmpne -> 3946
/*    */     //   3839: iload #30
/*    */     //   3841: iconst_1
/*    */     //   3842: if_icmpgt -> 3850
/*    */     //   3845: iload #26
/*    */     //   3847: ifne -> 3946
/*    */     //   3850: iload #11
/*    */     //   3852: aload_0
/*    */     //   3853: iload #20
/*    */     //   3855: aload_0
/*    */     //   3856: aload #29
/*    */     //   3858: iload #20
/*    */     //   3860: aload_0
/*    */     //   3861: aload #29
/*    */     //   3863: getstatic f/e00.PADDING_LEFT : Lf/e00;
/*    */     //   3866: iload #11
/*    */     //   3868: iconst_0
/*    */     //   3869: invokevirtual Gf : (Lf/cR;Lf/e00;II)I
/*    */     //   3872: iconst_0
/*    */     //   3873: swap
/*    */     //   3874: invokestatic max : (II)I
/*    */     //   3877: invokestatic max : (II)I
/*    */     //   3880: istore #31
/*    */     //   3882: getstatic f/e00.PADDING_RIGHT : Lf/e00;
/*    */     //   3885: iload #11
/*    */     //   3887: iconst_0
/*    */     //   3888: invokevirtual Gf : (Lf/cR;Lf/e00;II)I
/*    */     //   3891: iconst_0
/*    */     //   3892: swap
/*    */     //   3893: invokestatic max : (II)I
/*    */     //   3896: invokestatic max : (II)I
/*    */     //   3899: istore #32
/*    */     //   3901: new f/fM
/*    */     //   3904: dup
/*    */     //   3905: astore #33
/*    */     //   3907: iload #11
/*    */     //   3909: aload #33
/*    */     //   3911: iload #11
/*    */     //   3913: aload #33
/*    */     //   3915: aconst_null
/*    */     //   3916: invokespecial <init> : (Lf/xc;)V
/*    */     //   3919: putfield iw0 : I
/*    */     //   3922: iload #31
/*    */     //   3924: iload #32
/*    */     //   3926: aload #28
/*    */     //   3928: aconst_null
/*    */     //   3929: iconst_0
/*    */     //   3930: invokevirtual NF0 : (Lf/fM;IIILf/Ct;Ljava/lang/String;Z)Lf/yD;
/*    */     //   3933: dup
/*    */     //   3934: invokevirtual T1 : ()V
/*    */     //   3937: getfield SF : I
/*    */     //   3940: isub
/*    */     //   3941: istore #31
/*    */     //   3943: goto -> 3960
/*    */     //   3946: iload #30
/*    */     //   3948: iconst_1
/*    */     //   3949: if_icmpne -> 3960
/*    */     //   3952: iload #31
/*    */     //   3954: iflt -> 3960
/*    */     //   3957: iconst_1
/*    */     //   3958: istore #26
/*    */     //   3960: iload #30
/*    */     //   3962: iconst_1
/*    */     //   3963: if_icmple -> 4035
/*    */     //   3966: aload #21
/*    */     //   3968: ifnonnull -> 3980
/*    */     //   3971: new java/util/HashMap
/*    */     //   3974: dup
/*    */     //   3975: astore #21
/*    */     //   3977: invokespecial <init> : ()V
/*    */     //   3980: aload #21
/*    */     //   3982: iload #22
/*    */     //   3984: bipush #16
/*    */     //   3986: ishl
/*    */     //   3987: iload #30
/*    */     //   3989: iadd
/*    */     //   3990: invokestatic valueOf : (I)Ljava/lang/Integer;
/*    */     //   3993: dup
/*    */     //   3994: astore #28
/*    */     //   3996: invokevirtual get : (Ljava/lang/Object;)Ljava/lang/Object;
/*    */     //   3999: checkcast java/lang/Integer
/*    */     //   4002: dup
/*    */     //   4003: astore #29
/*    */     //   4005: ifnull -> 4018
/*    */     //   4008: iload #31
/*    */     //   4010: aload #29
/*    */     //   4012: invokevirtual intValue : ()I
/*    */     //   4015: if_icmple -> 4092
/*    */     //   4018: aload #21
/*    */     //   4020: iload #31
/*    */     //   4022: invokestatic valueOf : (I)Ljava/lang/Integer;
/*    */     //   4025: aload #28
/*    */     //   4027: swap
/*    */     //   4028: invokevirtual put : (Ljava/lang/Object;Ljava/lang/Object;)Ljava/lang/Object;
/*    */     //   4031: pop
/*    */     //   4032: goto -> 4092
/*    */     //   4035: iload #25
/*    */     //   4037: aload_0
/*    */     //   4038: aload #29
/*    */     //   4040: iload #24
/*    */     //   4042: aload_0
/*    */     //   4043: aload #29
/*    */     //   4045: iload #23
/*    */     //   4047: iload #31
/*    */     //   4049: invokestatic max : (II)I
/*    */     //   4052: istore #23
/*    */     //   4054: getstatic f/e00.MARGIN_LEFT : Lf/e00;
/*    */     //   4057: dup
/*    */     //   4058: astore #24
/*    */     //   4060: iload #11
/*    */     //   4062: iconst_0
/*    */     //   4063: invokevirtual Gf : (Lf/cR;Lf/e00;II)I
/*    */     //   4066: invokestatic max : (II)I
/*    */     //   4069: istore #25
/*    */     //   4071: aload #24
/*    */     //   4073: iload #11
/*    */     //   4075: iconst_0
/*    */     //   4076: invokevirtual Gf : (Lf/cR;Lf/e00;II)I
/*    */     //   4079: invokestatic max : (II)I
/*    */     //   4082: istore #24
/*    */     //   4084: iload #25
/*    */     //   4086: iload #24
/*    */     //   4088: istore #25
/*    */     //   4090: istore #24
/*    */     //   4092: iinc #27, 1
/*    */     //   4095: goto -> 3781
/*    */     //   4098: aload #15
/*    */     //   4100: iload #19
/*    */     //   4102: iload #25
/*    */     //   4104: aload #15
/*    */     //   4106: iload #22
/*    */     //   4108: aload #15
/*    */     //   4110: iload #22
/*    */     //   4112: aload #13
/*    */     //   4114: iload #22
/*    */     //   4116: iload #23
/*    */     //   4118: aload #16
/*    */     //   4120: iload #22
/*    */     //   4122: iload #26
/*    */     //   4124: bastore
/*    */     //   4125: iastore
/*    */     //   4126: iaload
/*    */     //   4127: iload #24
/*    */     //   4129: invokestatic max : (II)I
/*    */     //   4132: iastore
/*    */     //   4133: iinc #22, 1
/*    */     //   4136: invokestatic max : (II)I
/*    */     //   4139: iload #22
/*    */     //   4141: swap
/*    */     //   4142: iastore
/*    */     //   4143: goto -> 3759
/*    */     //   4146: aload #21
/*    */     //   4148: ifnull -> 4339
/*    */     //   4151: aload #21
/*    */     //   4153: invokevirtual entrySet : ()Ljava/util/Set;
/*    */     //   4156: invokeinterface iterator : ()Ljava/util/Iterator;
/*    */     //   4161: astore #17
/*    */     //   4163: aload #17
/*    */     //   4165: invokeinterface hasNext : ()Z
/*    */     //   4170: ifeq -> 4339
/*    */     //   4173: aload #17
/*    */     //   4175: invokeinterface next : ()Ljava/lang/Object;
/*    */     //   4180: checkcast java/util/Map$Entry
/*    */     //   4183: dup
/*    */     //   4184: invokeinterface getKey : ()Ljava/lang/Object;
/*    */     //   4189: checkcast java/lang/Integer
/*    */     //   4192: invokevirtual intValue : ()I
/*    */     //   4195: dup
/*    */     //   4196: bipush #16
/*    */     //   4198: iushr
/*    */     //   4199: istore #18
/*    */     //   4201: ldc_w 65535
/*    */     //   4204: iand
/*    */     //   4205: istore #19
/*    */     //   4207: invokeinterface getValue : ()Ljava/lang/Object;
/*    */     //   4212: checkcast java/lang/Integer
/*    */     //   4215: invokevirtual intValue : ()I
/*    */     //   4218: istore #20
/*    */     //   4220: iconst_0
/*    */     //   4221: istore #21
/*    */     //   4223: iload #19
/*    */     //   4225: istore #22
/*    */     //   4227: iload #21
/*    */     //   4229: iload #19
/*    */     //   4231: if_icmpge -> 4267
/*    */     //   4234: aload #16
/*    */     //   4236: iload #18
/*    */     //   4238: iload #21
/*    */     //   4240: iadd
/*    */     //   4241: dup
/*    */     //   4242: istore #23
/*    */     //   4244: baload
/*    */     //   4245: ifeq -> 4261
/*    */     //   4248: iload #20
/*    */     //   4250: aload #13
/*    */     //   4252: iload #23
/*    */     //   4254: iaload
/*    */     //   4255: isub
/*    */     //   4256: istore #20
/*    */     //   4258: iinc #22, -1
/*    */     //   4261: iinc #21, 1
/*    */     //   4264: goto -> 4227
/*    */     //   4267: iload #20
/*    */     //   4269: ifle -> 4163
/*    */     //   4272: iconst_0
/*    */     //   4273: istore #21
/*    */     //   4275: iload #21
/*    */     //   4277: iload #19
/*    */     //   4279: if_icmpge -> 4163
/*    */     //   4282: iload #22
/*    */     //   4284: ifle -> 4163
/*    */     //   4287: aload #16
/*    */     //   4289: iload #18
/*    */     //   4291: iload #21
/*    */     //   4293: iadd
/*    */     //   4294: dup
/*    */     //   4295: istore #23
/*    */     //   4297: baload
/*    */     //   4298: ifne -> 4333
/*    */     //   4301: iload #20
/*    */     //   4303: aload #13
/*    */     //   4305: iload #23
/*    */     //   4307: aload #13
/*    */     //   4309: iload #23
/*    */     //   4311: iload #20
/*    */     //   4313: iload #22
/*    */     //   4315: idiv
/*    */     //   4316: istore #20
/*    */     //   4318: iaload
/*    */     //   4319: iload #20
/*    */     //   4321: invokestatic max : (II)I
/*    */     //   4324: iastore
/*    */     //   4325: iload #20
/*    */     //   4327: isub
/*    */     //   4328: istore #20
/*    */     //   4330: iinc #22, -1
/*    */     //   4333: iinc #21, 1
/*    */     //   4336: goto -> 4275
/*    */     //   4339: aload #15
/*    */     //   4341: iload_3
/*    */     //   4342: aload #15
/*    */     //   4344: iload_3
/*    */     //   4345: iaload
/*    */     //   4346: aload_0
/*    */     //   4347: aload #7
/*    */     //   4349: aload_1
/*    */     //   4350: getstatic f/e00.PADDING_RIGHT : Lf/e00;
/*    */     //   4353: astore #17
/*    */     //   4355: getfield qR : I
/*    */     //   4358: aload #17
/*    */     //   4360: swap
/*    */     //   4361: iconst_0
/*    */     //   4362: invokevirtual Gf : (Lf/cR;Lf/e00;II)I
/*    */     //   4365: iconst_0
/*    */     //   4366: swap
/*    */     //   4367: invokestatic max : (II)I
/*    */     //   4370: invokestatic max : (II)I
/*    */     //   4373: iastore
/*    */     //   4374: iconst_0
/*    */     //   4375: istore #17
/*    */     //   4377: iconst_0
/*    */     //   4378: istore #18
/*    */     //   4380: iload #18
/*    */     //   4382: iload #14
/*    */     //   4384: if_icmpge -> 4403
/*    */     //   4387: iload #17
/*    */     //   4389: aload #15
/*    */     //   4391: iload #18
/*    */     //   4393: iaload
/*    */     //   4394: iadd
/*    */     //   4395: istore #17
/*    */     //   4397: iinc #18, 1
/*    */     //   4400: goto -> 4380
/*    */     //   4403: iconst_0
/*    */     //   4404: istore #14
/*    */     //   4406: iconst_0
/*    */     //   4407: istore #18
/*    */     //   4409: iload #18
/*    */     //   4411: iload_3
/*    */     //   4412: if_icmpge -> 4431
/*    */     //   4415: iload #14
/*    */     //   4417: aload #13
/*    */     //   4419: iload #18
/*    */     //   4421: iaload
/*    */     //   4422: iadd
/*    */     //   4423: istore #14
/*    */     //   4425: iinc #18, 1
/*    */     //   4428: goto -> 4409
/*    */     //   4431: iload #12
/*    */     //   4433: ifeq -> 4448
/*    */     //   4436: iload #10
/*    */     //   4438: iload #14
/*    */     //   4440: iload #17
/*    */     //   4442: iadd
/*    */     //   4443: invokestatic min : (II)I
/*    */     //   4446: istore #11
/*    */     //   4448: iload #11
/*    */     //   4450: iload #17
/*    */     //   4452: isub
/*    */     //   4453: iconst_0
/*    */     //   4454: swap
/*    */     //   4455: invokestatic max : (II)I
/*    */     //   4458: dup
/*    */     //   4459: istore #10
/*    */     //   4461: iload #14
/*    */     //   4463: if_icmpeq -> 4643
/*    */     //   4466: iload #14
/*    */     //   4468: ifle -> 4643
/*    */     //   4471: iconst_0
/*    */     //   4472: istore #12
/*    */     //   4474: iload #10
/*    */     //   4476: iload #14
/*    */     //   4478: iload_3
/*    */     //   4479: istore #19
/*    */     //   4481: istore #18
/*    */     //   4483: istore #17
/*    */     //   4485: iload #12
/*    */     //   4487: iload_3
/*    */     //   4488: if_icmpge -> 4536
/*    */     //   4491: aload #16
/*    */     //   4493: iload #12
/*    */     //   4495: baload
/*    */     //   4496: ifeq -> 4530
/*    */     //   4499: iload #18
/*    */     //   4501: iload #17
/*    */     //   4503: aload #13
/*    */     //   4505: iload #12
/*    */     //   4507: iaload
/*    */     //   4508: dup
/*    */     //   4509: istore #17
/*    */     //   4511: isub
/*    */     //   4512: istore #18
/*    */     //   4514: iload #17
/*    */     //   4516: isub
/*    */     //   4517: istore #17
/*    */     //   4519: iinc #19, -1
/*    */     //   4522: iload #18
/*    */     //   4524: iload #17
/*    */     //   4526: istore #18
/*    */     //   4528: istore #17
/*    */     //   4530: iinc #12, 1
/*    */     //   4533: goto -> 4485
/*    */     //   4536: iload #10
/*    */     //   4538: iconst_0
/*    */     //   4539: istore #12
/*    */     //   4541: ifge -> 4553
/*    */     //   4544: iconst_1
/*    */     //   4545: istore #12
/*    */     //   4547: iload_3
/*    */     //   4548: istore #19
/*    */     //   4550: goto -> 4561
/*    */     //   4553: iload #17
/*    */     //   4555: iload #18
/*    */     //   4557: istore #14
/*    */     //   4559: istore #10
/*    */     //   4561: iconst_0
/*    */     //   4562: istore #17
/*    */     //   4564: iload #17
/*    */     //   4566: iload_3
/*    */     //   4567: if_icmpge -> 4643
/*    */     //   4570: iload #19
/*    */     //   4572: ifle -> 4643
/*    */     //   4575: iload #12
/*    */     //   4577: ifne -> 4588
/*    */     //   4580: aload #16
/*    */     //   4582: iload #17
/*    */     //   4584: baload
/*    */     //   4585: ifne -> 4637
/*    */     //   4588: iload #14
/*    */     //   4590: aload #13
/*    */     //   4592: iload #17
/*    */     //   4594: iaload
/*    */     //   4595: istore #18
/*    */     //   4597: ifle -> 4613
/*    */     //   4600: iload #18
/*    */     //   4602: iload #10
/*    */     //   4604: imul
/*    */     //   4605: iload #14
/*    */     //   4607: idiv
/*    */     //   4608: istore #20
/*    */     //   4610: goto -> 4616
/*    */     //   4613: iconst_0
/*    */     //   4614: istore #20
/*    */     //   4616: iload #14
/*    */     //   4618: iload #10
/*    */     //   4620: aload #13
/*    */     //   4622: iload #17
/*    */     //   4624: iload #20
/*    */     //   4626: iastore
/*    */     //   4627: iload #20
/*    */     //   4629: isub
/*    */     //   4630: istore #10
/*    */     //   4632: iload #18
/*    */     //   4634: isub
/*    */     //   4635: istore #14
/*    */     //   4637: iinc #17, 1
/*    */     //   4640: goto -> 4564
/*    */     //   4643: iload_3
/*    */     //   4644: aload_1
/*    */     //   4645: iload #5
/*    */     //   4647: aload_0
/*    */     //   4648: aload #7
/*    */     //   4650: aload_1
/*    */     //   4651: dup
/*    */     //   4652: dup
/*    */     //   4653: aload_0
/*    */     //   4654: aload_1
/*    */     //   4655: aload_2
/*    */     //   4656: invokevirtual mk0 : (Lf/yD;Lf/xc;)Lf/dK;
/*    */     //   4659: astore #10
/*    */     //   4661: getstatic f/AuX.XT : Lf/AuX;
/*    */     //   4664: putfield YP : Lf/AuX;
/*    */     //   4667: getfield t0 : I
/*    */     //   4670: istore #12
/*    */     //   4672: getstatic f/e00.PADDING_TOP : Lf/e00;
/*    */     //   4675: astore #14
/*    */     //   4677: getfield qR : I
/*    */     //   4680: aload #14
/*    */     //   4682: swap
/*    */     //   4683: iconst_0
/*    */     //   4684: invokevirtual Gf : (Lf/cR;Lf/e00;II)I
/*    */     //   4687: iconst_0
/*    */     //   4688: swap
/*    */     //   4689: invokestatic max : (II)I
/*    */     //   4692: invokestatic max : (II)I
/*    */     //   4695: iload #12
/*    */     //   4697: iadd
/*    */     //   4698: putfield t0 : I
/*    */     //   4701: anewarray f/dK
/*    */     //   4704: astore #12
/*    */     //   4706: iconst_0
/*    */     //   4707: istore #14
/*    */     //   4709: iload #14
/*    */     //   4711: iload #4
/*    */     //   4713: if_icmpge -> 5337
/*    */     //   4716: iload #14
/*    */     //   4718: ifle -> 4732
/*    */     //   4721: aload_1
/*    */     //   4722: dup
/*    */     //   4723: getfield t0 : I
/*    */     //   4726: iload #5
/*    */     //   4728: iadd
/*    */     //   4729: putfield t0 : I
/*    */     //   4732: aload_2
/*    */     //   4733: aconst_null
/*    */     //   4734: astore #16
/*    */     //   4736: getfield nx0 : [Lf/cR;
/*    */     //   4739: iload #14
/*    */     //   4741: aaload
/*    */     //   4742: dup
/*    */     //   4743: astore #17
/*    */     //   4745: ifnull -> 4916
/*    */     //   4748: aload #17
/*    */     //   4750: aload_1
/*    */     //   4751: dup
/*    */     //   4752: aload_0
/*    */     //   4753: aload #17
/*    */     //   4755: getstatic f/e00.MARGIN_TOP : Lf/e00;
/*    */     //   4758: iload #11
/*    */     //   4760: iconst_0
/*    */     //   4761: invokevirtual Gf : (Lf/cR;Lf/e00;II)I
/*    */     //   4764: iconst_0
/*    */     //   4765: swap
/*    */     //   4766: invokestatic max : (II)I
/*    */     //   4769: invokevirtual NC0 : (I)I
/*    */     //   4772: putfield t0 : I
/*    */     //   4775: getstatic f/e00.BACKGROUND_IMAGE : Lf/e00;
/*    */     //   4778: dup
/*    */     //   4779: astore #18
/*    */     //   4781: invokevirtual bw0 : (Lf/e00;)Lf/cR;
/*    */     //   4784: aload #18
/*    */     //   4786: invokevirtual rI : (Lf/e00;)Ljava/lang/Object;
/*    */     //   4789: checkcast java/lang/String
/*    */     //   4792: dup
/*    */     //   4793: astore #18
/*    */     //   4795: ifnull -> 4809
/*    */     //   4798: aload_0
/*    */     //   4799: aload #18
/*    */     //   4801: invokevirtual Ca0 : (Ljava/lang/String;)Lf/mX;
/*    */     //   4804: astore #18
/*    */     //   4806: goto -> 4812
/*    */     //   4809: aconst_null
/*    */     //   4810: astore #18
/*    */     //   4812: aload #18
/*    */     //   4814: ifnull -> 4865
/*    */     //   4817: aload_1
/*    */     //   4818: new f/dK
/*    */     //   4821: dup
/*    */     //   4822: astore #16
/*    */     //   4824: iload #11
/*    */     //   4826: aload #16
/*    */     //   4828: iload #9
/*    */     //   4830: aload #16
/*    */     //   4832: aload_1
/*    */     //   4833: aload #16
/*    */     //   4835: aload_2
/*    */     //   4836: aload #18
/*    */     //   4838: invokespecial <init> : (Lf/xc;Lf/mX;)V
/*    */     //   4841: getfield t0 : I
/*    */     //   4844: putfield dF : I
/*    */     //   4847: putfield mx : I
/*    */     //   4850: putfield iw0 : I
/*    */     //   4853: getfield ST : Lf/fM;
/*    */     //   4856: getfield Xf0 : Ljava/util/ArrayList;
/*    */     //   4859: aload #16
/*    */     //   4861: invokevirtual add : (Ljava/lang/Object;)Z
/*    */     //   4864: pop
/*    */     //   4865: aload_1
/*    */     //   4866: aload_0
/*    */     //   4867: aload #17
/*    */     //   4869: aload_1
/*    */     //   4870: aload_0
/*    */     //   4871: aload #17
/*    */     //   4873: aload_1
/*    */     //   4874: getfield t0 : I
/*    */     //   4877: istore #18
/*    */     //   4879: getstatic f/e00.PADDING_TOP : Lf/e00;
/*    */     //   4882: iload #11
/*    */     //   4884: iconst_0
/*    */     //   4885: invokevirtual Gf : (Lf/cR;Lf/e00;II)I
/*    */     //   4888: iconst_0
/*    */     //   4889: swap
/*    */     //   4890: invokestatic max : (II)I
/*    */     //   4893: iload #18
/*    */     //   4895: iadd
/*    */     //   4896: putfield t0 : I
/*    */     //   4899: getstatic f/e00.HEIGHT : Lf/e00;
/*    */     //   4902: iload #11
/*    */     //   4904: iconst_0
/*    */     //   4905: invokevirtual Gf : (Lf/cR;Lf/e00;II)I
/*    */     //   4908: iconst_0
/*    */     //   4909: swap
/*    */     //   4910: invokestatic max : (II)I
/*    */     //   4913: putfield pn : I
/*    */     //   4916: iconst_0
/*    */     //   4917: istore #18
/*    */     //   4919: iload #9
/*    */     //   4921: istore #19
/*    */     //   4923: iload #18
/*    */     //   4925: iload_3
/*    */     //   4926: if_icmpge -> 5215
/*    */     //   4929: aload_2
/*    */     //   4930: iload #14
/*    */     //   4932: iload #19
/*    */     //   4934: aload #15
/*    */     //   4936: iload #18
/*    */     //   4938: iaload
/*    */     //   4939: iadd
/*    */     //   4940: istore #19
/*    */     //   4942: iload #18
/*    */     //   4944: invokevirtual nF : (II)Lf/bJ;
/*    */     //   4947: dup
/*    */     //   4948: astore #20
/*    */     //   4950: aload #13
/*    */     //   4952: iload #18
/*    */     //   4954: iaload
/*    */     //   4955: istore #21
/*    */     //   4957: ifnull -> 5202
/*    */     //   4960: iconst_1
/*    */     //   4961: istore #22
/*    */     //   4963: iload #22
/*    */     //   4965: aload #20
/*    */     //   4967: getfield zd : I
/*    */     //   4970: if_icmpge -> 5001
/*    */     //   4973: aload #15
/*    */     //   4975: iload #18
/*    */     //   4977: iload #22
/*    */     //   4979: iadd
/*    */     //   4980: dup
/*    */     //   4981: istore #23
/*    */     //   4983: iaload
/*    */     //   4984: aload #13
/*    */     //   4986: iload #23
/*    */     //   4988: iaload
/*    */     //   4989: iadd
/*    */     //   4990: iload #21
/*    */     //   4992: iadd
/*    */     //   4993: istore #21
/*    */     //   4995: iinc #22, 1
/*    */     //   4998: goto -> 4963
/*    */     //   5001: aload_0
/*    */     //   5002: aload_1
/*    */     //   5003: aload #20
/*    */     //   5005: iload #6
/*    */     //   5007: aload_0
/*    */     //   5008: iload #6
/*    */     //   5010: aload_0
/*    */     //   5011: aload #20
/*    */     //   5013: getfield X10 : Lf/cR;
/*    */     //   5016: dup
/*    */     //   5017: astore #22
/*    */     //   5019: getstatic f/e00.PADDING_LEFT : Lf/e00;
/*    */     //   5022: iload #11
/*    */     //   5024: iconst_0
/*    */     //   5025: invokevirtual Gf : (Lf/cR;Lf/e00;II)I
/*    */     //   5028: iconst_0
/*    */     //   5029: swap
/*    */     //   5030: invokestatic max : (II)I
/*    */     //   5033: invokestatic max : (II)I
/*    */     //   5036: istore #23
/*    */     //   5038: aload #22
/*    */     //   5040: getstatic f/e00.PADDING_RIGHT : Lf/e00;
/*    */     //   5043: iload #11
/*    */     //   5045: iconst_0
/*    */     //   5046: invokevirtual Gf : (Lf/cR;Lf/e00;II)I
/*    */     //   5049: iconst_0
/*    */     //   5050: swap
/*    */     //   5051: invokestatic max : (II)I
/*    */     //   5054: invokestatic max : (II)I
/*    */     //   5057: istore #24
/*    */     //   5059: new f/fM
/*    */     //   5062: dup
/*    */     //   5063: astore #25
/*    */     //   5065: aload #20
/*    */     //   5067: invokespecial <init> : (Lf/xc;)V
/*    */     //   5070: invokevirtual mk0 : (Lf/yD;Lf/xc;)Lf/dK;
/*    */     //   5073: dup
/*    */     //   5074: astore #26
/*    */     //   5076: ifnull -> 5105
/*    */     //   5079: aload #12
/*    */     //   5081: aload #26
/*    */     //   5083: dup
/*    */     //   5084: dup
/*    */     //   5085: iload #19
/*    */     //   5087: putfield mx : I
/*    */     //   5090: iload #21
/*    */     //   5092: putfield iw0 : I
/*    */     //   5095: aload #25
/*    */     //   5097: putfield PRN : Lf/jT;
/*    */     //   5100: iload #18
/*    */     //   5102: aload #26
/*    */     //   5104: aastore
/*    */     //   5105: aload #20
/*    */     //   5107: aload_0
/*    */     //   5108: aload #25
/*    */     //   5110: iload #11
/*    */     //   5112: aload_1
/*    */     //   5113: dup
/*    */     //   5114: aload #25
/*    */     //   5116: aload_0
/*    */     //   5117: aload #22
/*    */     //   5119: aload #25
/*    */     //   5121: iload #21
/*    */     //   5123: aload #25
/*    */     //   5125: aload_1
/*    */     //   5126: aload #25
/*    */     //   5128: iload #19
/*    */     //   5130: putfield mx : I
/*    */     //   5133: getfield t0 : I
/*    */     //   5136: putfield dF : I
/*    */     //   5139: putfield iw0 : I
/*    */     //   5142: getstatic f/e00.MARGIN_TOP : Lf/e00;
/*    */     //   5145: iload #11
/*    */     //   5147: iconst_0
/*    */     //   5148: invokevirtual Gf : (Lf/cR;Lf/e00;II)I
/*    */     //   5151: iconst_0
/*    */     //   5152: swap
/*    */     //   5153: invokestatic max : (II)I
/*    */     //   5156: i2s
/*    */     //   5157: putfield X90 : S
/*    */     //   5160: getfield pb0 : Ljava/util/ArrayList;
/*    */     //   5163: aload #25
/*    */     //   5165: invokevirtual add : (Ljava/lang/Object;)Z
/*    */     //   5168: pop
/*    */     //   5169: getfield Q10 : Z
/*    */     //   5172: istore #22
/*    */     //   5174: iload #23
/*    */     //   5176: iload #24
/*    */     //   5178: aload #20
/*    */     //   5180: aconst_null
/*    */     //   5181: iload #22
/*    */     //   5183: invokevirtual NF0 : (Lf/fM;IIILf/Ct;Ljava/lang/String;Z)Lf/yD;
/*    */     //   5186: pop
/*    */     //   5187: getfield zd : I
/*    */     //   5190: iconst_1
/*    */     //   5191: isub
/*    */     //   5192: iconst_0
/*    */     //   5193: swap
/*    */     //   5194: invokestatic max : (II)I
/*    */     //   5197: iload #18
/*    */     //   5199: iadd
/*    */     //   5200: istore #18
/*    */     //   5202: iload #19
/*    */     //   5204: iload #21
/*    */     //   5206: iadd
/*    */     //   5207: istore #19
/*    */     //   5209: iinc #18, 1
/*    */     //   5212: goto -> 4923
/*    */     //   5215: aload_1
/*    */     //   5216: iconst_0
/*    */     //   5217: invokevirtual OE0 : (Z)Z
/*    */     //   5220: pop
/*    */     //   5221: iconst_0
/*    */     //   5222: istore #18
/*    */     //   5224: iload #18
/*    */     //   5226: iload_3
/*    */     //   5227: if_icmpge -> 5268
/*    */     //   5230: aload #12
/*    */     //   5232: iload #18
/*    */     //   5234: aaload
/*    */     //   5235: dup
/*    */     //   5236: astore #19
/*    */     //   5238: ifnull -> 5262
/*    */     //   5241: aload #12
/*    */     //   5243: iload #18
/*    */     //   5245: aload #19
/*    */     //   5247: aload_1
/*    */     //   5248: getfield t0 : I
/*    */     //   5251: aload #19
/*    */     //   5253: getfield dF : I
/*    */     //   5256: isub
/*    */     //   5257: putfield RA0 : I
/*    */     //   5260: aconst_null
/*    */     //   5261: aastore
/*    */     //   5262: iinc #18, 1
/*    */     //   5265: goto -> 5224
/*    */     //   5268: aload #17
/*    */     //   5270: ifnull -> 5331
/*    */     //   5273: aload #16
/*    */     //   5275: aload_1
/*    */     //   5276: aload_0
/*    */     //   5277: aload #17
/*    */     //   5279: aload_1
/*    */     //   5280: getfield t0 : I
/*    */     //   5283: istore #18
/*    */     //   5285: getstatic f/e00.PADDING_BOTTOM : Lf/e00;
/*    */     //   5288: iload #11
/*    */     //   5290: iconst_0
/*    */     //   5291: invokevirtual Gf : (Lf/cR;Lf/e00;II)I
/*    */     //   5294: iconst_0
/*    */     //   5295: swap
/*    */     //   5296: invokestatic max : (II)I
/*    */     //   5299: iload #18
/*    */     //   5301: iadd
/*    */     //   5302: dup
/*    */     //   5303: istore #18
/*    */     //   5305: putfield t0 : I
/*    */     //   5308: ifnull -> 5324
/*    */     //   5311: aload #16
/*    */     //   5313: iload #18
/*    */     //   5315: aload #16
/*    */     //   5317: getfield dF : I
/*    */     //   5320: isub
/*    */     //   5321: putfield RA0 : I
/*    */     //   5324: aload_0
/*    */     //   5325: aload_1
/*    */     //   5326: aload #17
/*    */     //   5328: invokevirtual PE : (Lf/yD;Lf/cR;)V
/*    */     //   5331: iinc #14, 1
/*    */     //   5334: goto -> 4709
/*    */     //   5337: aload_1
/*    */     //   5338: dup
/*    */     //   5339: iload #5
/*    */     //   5341: aload_0
/*    */     //   5342: aload #7
/*    */     //   5344: aload_1
/*    */     //   5345: dup
/*    */     //   5346: getfield t0 : I
/*    */     //   5349: istore_2
/*    */     //   5350: getstatic f/e00.PADDING_BOTTOM : Lf/e00;
/*    */     //   5353: astore_3
/*    */     //   5354: getfield qR : I
/*    */     //   5357: aload_3
/*    */     //   5358: swap
/*    */     //   5359: iconst_0
/*    */     //   5360: invokevirtual Gf : (Lf/cR;Lf/e00;II)I
/*    */     //   5363: iconst_0
/*    */     //   5364: swap
/*    */     //   5365: invokestatic max : (II)I
/*    */     //   5368: invokestatic max : (II)I
/*    */     //   5371: iload_2
/*    */     //   5372: iadd
/*    */     //   5373: putfield t0 : I
/*    */     //   5376: getfield o4 : Ljava/util/ArrayList;
/*    */     //   5379: dup
/*    */     //   5380: astore_2
/*    */     //   5381: invokevirtual size : ()I
/*    */     //   5384: istore_3
/*    */     //   5385: iload_3
/*    */     //   5386: dup
/*    */     //   5387: iconst_m1
/*    */     //   5388: iadd
/*    */     //   5389: istore_3
/*    */     //   5390: ifle -> 5420
/*    */     //   5393: aload_2
/*    */     //   5394: iload_3
/*    */     //   5395: invokevirtual get : (I)Ljava/lang/Object;
/*    */     //   5398: checkcast f/jT
/*    */     //   5401: invokevirtual Ia : ()I
/*    */     //   5404: aload_1
/*    */     //   5405: getfield t0 : I
/*    */     //   5408: if_icmpgt -> 5385
/*    */     //   5411: aload_2
/*    */     //   5412: iload_3
/*    */     //   5413: invokevirtual remove : (I)Ljava/lang/Object;
/*    */     //   5416: pop
/*    */     //   5417: goto -> 5385
/*    */     //   5420: aload_1
/*    */     //   5421: getfield A60 : Ljava/util/ArrayList;
/*    */     //   5424: dup
/*    */     //   5425: astore_2
/*    */     //   5426: invokevirtual size : ()I
/*    */     //   5429: istore_3
/*    */     //   5430: iload_3
/*    */     //   5431: dup
/*    */     //   5432: iconst_m1
/*    */     //   5433: iadd
/*    */     //   5434: istore_3
/*    */     //   5435: ifle -> 5465
/*    */     //   5438: aload_2
/*    */     //   5439: iload_3
/*    */     //   5440: invokevirtual get : (I)Ljava/lang/Object;
/*    */     //   5443: checkcast f/jT
/*    */     //   5446: invokevirtual Ia : ()I
/*    */     //   5449: aload_1
/*    */     //   5450: getfield t0 : I
/*    */     //   5453: if_icmpgt -> 5430
/*    */     //   5456: aload_2
/*    */     //   5457: iload_3
/*    */     //   5458: invokevirtual remove : (I)Ljava/lang/Object;
/*    */     //   5461: pop
/*    */     //   5462: goto -> 5430
/*    */     //   5465: aload #10
/*    */     //   5467: aload_1
/*    */     //   5468: dup
/*    */     //   5469: dup2
/*    */     //   5470: invokevirtual lo : ()V
/*    */     //   5473: getfield tl : I
/*    */     //   5476: iload #11
/*    */     //   5478: isub
/*    */     //   5479: iconst_0
/*    */     //   5480: swap
/*    */     //   5481: invokestatic max : (II)I
/*    */     //   5484: istore_2
/*    */     //   5485: getfield SF : I
/*    */     //   5488: iload_2
/*    */     //   5489: invokestatic min : (II)I
/*    */     //   5492: putfield SF : I
/*    */     //   5495: ifnull -> 5527
/*    */     //   5498: aload #10
/*    */     //   5500: iload #11
/*    */     //   5502: aload #10
/*    */     //   5504: iload #9
/*    */     //   5506: aload #10
/*    */     //   5508: aload_1
/*    */     //   5509: getfield t0 : I
/*    */     //   5512: aload #10
/*    */     //   5514: getfield dF : I
/*    */     //   5517: isub
/*    */     //   5518: putfield RA0 : I
/*    */     //   5521: putfield mx : I
/*    */     //   5524: putfield iw0 : I
/*    */     //   5527: aload_0
/*    */     //   5528: aload_1
/*    */     //   5529: aload #8
/*    */     //   5531: aload_1
/*    */     //   5532: aload #8
/*    */     //   5534: iload #11
/*    */     //   5536: aload #8
/*    */     //   5538: iload #9
/*    */     //   5540: putfield mx : I
/*    */     //   5543: putfield iw0 : I
/*    */     //   5546: getfield t0 : I
/*    */     //   5549: aload #8
/*    */     //   5551: getfield dF : I
/*    */     //   5554: isub
/*    */     //   5555: putfield RA0 : I
/*    */     //   5558: aload #7
/*    */     //   5560: invokevirtual PE : (Lf/yD;Lf/cR;)V
/*    */     //   5563: goto -> 5733
/*    */     //   5566: aload_2
/*    */     //   5567: instanceof f/Cq0
/*    */     //   5570: ifeq -> 5664
/*    */     //   5573: aload_1
/*    */     //   5574: dup
/*    */     //   5575: aload_2
/*    */     //   5576: checkcast f/Cq0
/*    */     //   5579: astore_2
/*    */     //   5580: getfield WM : Ljava/lang/String;
/*    */     //   5583: astore_3
/*    */     //   5584: aload_2
/*    */     //   5585: getfield RC0 : Ljava/lang/String;
/*    */     //   5588: putfield WM : Ljava/lang/String;
/*    */     //   5591: aload_2
/*    */     //   5592: getfield X10 : Lf/cR;
/*    */     //   5595: getstatic f/e00.DISPLAY : Lf/e00;
/*    */     //   5598: dup
/*    */     //   5599: astore #4
/*    */     //   5601: invokevirtual bw0 : (Lf/e00;)Lf/cR;
/*    */     //   5604: aload #4
/*    */     //   5606: invokevirtual rI : (Lf/e00;)Ljava/lang/Object;
/*    */     //   5609: checkcast f/Sx0
/*    */     //   5612: getstatic f/Sx0.nI0 : Lf/Sx0;
/*    */     //   5615: if_acmpne -> 5627
/*    */     //   5618: aload_0
/*    */     //   5619: aload_1
/*    */     //   5620: aload_2
/*    */     //   5621: invokevirtual vq0 : (Lf/yD;Lf/Ct;)V
/*    */     //   5624: goto -> 5656
/*    */     //   5627: aload_0
/*    */     //   5628: dup
/*    */     //   5629: aload_1
/*    */     //   5630: aload_0
/*    */     //   5631: aload_2
/*    */     //   5632: getfield X10 : Lf/cR;
/*    */     //   5635: astore_0
/*    */     //   5636: aload_1
/*    */     //   5637: aload_0
/*    */     //   5638: invokevirtual Si : (Lf/yD;Lf/cR;)V
/*    */     //   5641: aload_2
/*    */     //   5642: invokevirtual FF : (Lf/xc;)Lf/jT;
/*    */     //   5645: pop
/*    */     //   5646: aload_1
/*    */     //   5647: aload_2
/*    */     //   5648: invokevirtual Sz : (Lf/yD;Ljava/lang/Iterable;)V
/*    */     //   5651: aload_1
/*    */     //   5652: aload_0
/*    */     //   5653: invokevirtual PE : (Lf/yD;Lf/cR;)V
/*    */     //   5656: aload_1
/*    */     //   5657: aload_3
/*    */     //   5658: putfield WM : Ljava/lang/String;
/*    */     //   5661: goto -> 5733
/*    */     //   5664: aload_2
/*    */     //   5665: instanceof f/Ct
/*    */     //   5668: ifeq -> 5708
/*    */     //   5671: aload_0
/*    */     //   5672: dup
/*    */     //   5673: aload_1
/*    */     //   5674: aload_0
/*    */     //   5675: aload_2
/*    */     //   5676: checkcast f/Ct
/*    */     //   5679: dup
/*    */     //   5680: astore_0
/*    */     //   5681: getfield X10 : Lf/cR;
/*    */     //   5684: astore_2
/*    */     //   5685: aload_1
/*    */     //   5686: aload_2
/*    */     //   5687: invokevirtual Si : (Lf/yD;Lf/cR;)V
/*    */     //   5690: aload_0
/*    */     //   5691: invokevirtual FF : (Lf/xc;)Lf/jT;
/*    */     //   5694: pop
/*    */     //   5695: aload_1
/*    */     //   5696: aload_0
/*    */     //   5697: invokevirtual Sz : (Lf/yD;Ljava/lang/Iterable;)V
/*    */     //   5700: aload_1
/*    */     //   5701: aload_2
/*    */     //   5702: invokevirtual PE : (Lf/yD;Lf/cR;)V
/*    */     //   5705: goto -> 5733
/*    */     //   5708: ldc f/f9
/*    */     //   5710: invokevirtual getName : ()Ljava/lang/String;
/*    */     //   5713: invokestatic getLogger : (Ljava/lang/String;)Ljava/util/logging/Logger;
/*    */     //   5716: aload_2
/*    */     //   5717: getstatic java/util/logging/Level.SEVERE : Ljava/util/logging/Level;
/*    */     //   5720: astore_0
/*    */     //   5721: invokevirtual getClass : ()Ljava/lang/Class;
/*    */     //   5724: astore_1
/*    */     //   5725: aload_0
/*    */     //   5726: ldc_w 'Unknown Element subclass: {0}'
/*    */     //   5729: aload_1
/*    */     //   5730: invokevirtual log : (Ljava/util/logging/Level;Ljava/lang/String;Ljava/lang/Object;)V
/*    */     //   5733: return
/*    */     // Line number table:
/*    */     //   Java source line number -> byte code offset
/*    */     //   #1	-> 3
/*    */     //   #2	-> 6
/*    */     //   #3	-> 11
/*    */     //   #4	-> 15
/*    */     //   #5	-> 18
/*    */     //   #6	-> 36
/*    */     //   #7	-> 102
/*    */     //   #8	-> 251
/*    */     //   #9	-> 259
/*    */     //   #10	-> 264
/*    */     //   #11	-> 270
/*    */     //   #12	-> 302
/*    */     //   #13	-> 310
/*    */     //   #14	-> 321
/*    */     //   #15	-> 329
/*    */     //   #16	-> 346
/*    */     //   #17	-> 352
/*    */     //   #18	-> 360
/*    */     //   #19	-> 387
/*    */     //   #20	-> 392
/*    */     //   #21	-> 416
/*    */     //   #22	-> 421
/*    */     //   #23	-> 424
/*    */     //   #24	-> 457
/*    */     //   #25	-> 477
/*    */     //   #26	-> 527
/*    */     //   #27	-> 545
/*    */     //   #28	-> 573
/*    */     //   #29	-> 578
/*    */     //   #30	-> 603
/*    */     //   #31	-> 608
/*    */     //   #32	-> 611
/*    */     //   #33	-> 705
/*    */     //   #34	-> 862
/*    */     //   #35	-> 876
/*    */     //   #36	-> 899
/*    */     //   #37	-> 936
/*    */     //   #38	-> 978
/*    */     //   #39	-> 990
/*    */     //   #40	-> 1006
/*    */     //   #41	-> 1009
/*    */     //   #42	-> 1037
/*    */     //   #43	-> 1040
/*    */     //   #44	-> 1059
/*    */     //   #45	-> 1069
/*    */     //   #46	-> 1072
/*    */     //   #47	-> 1129
/*    */     //   #48	-> 1149
/*    */     //   #49	-> 1189
/*    */     //   #50	-> 1198
/*    */     //   #51	-> 1267
/*    */     //   #52	-> 1301
/*    */     //   #53	-> 1307
/*    */     //   #54	-> 1313
/*    */     //   #55	-> 1378
/*    */     //   #56	-> 1384
/*    */     //   #57	-> 1390
/*    */     //   #58	-> 1465
/*    */     //   #59	-> 1468
/*    */     //   #60	-> 1499
/*    */     //   #61	-> 1525
/*    */     //   #62	-> 1528
/*    */     //   #63	-> 1534
/*    */     //   #64	-> 1539
/*    */     //   #65	-> 1542
/*    */     //   #66	-> 1592
/*    */     //   #67	-> 1598
/*    */     //   #68	-> 1671
/*    */     //   #69	-> 1674
/*    */     //   #70	-> 1720
/*    */     //   #71	-> 1827
/*    */     //   #72	-> 1835
/*    */     //   #73	-> 1864
/*    */     //   #74	-> 1878
/*    */     //   #75	-> 1907
/*    */     //   #76	-> 1934
/*    */     //   #77	-> 1937
/*    */     //   #78	-> 1950
/*    */     //   #79	-> 2030
/*    */     //   #80	-> 2033
/*    */     //   #81	-> 2165
/*    */     //   #82	-> 2184
/*    */     //   #83	-> 2238
/*    */     //   #84	-> 2243
/*    */     //   #85	-> 2321
/*    */     //   #86	-> 2334
/*    */     //   #87	-> 2337
/*    */     //   #88	-> 2377
/*    */     //   #89	-> 2389
/*    */     //   #90	-> 2393
/*    */     //   #91	-> 2396
/*    */     //   #92	-> 2412
/*    */     //   #93	-> 2415
/*    */     //   #94	-> 2428
/*    */     //   #95	-> 2432
/*    */     //   #96	-> 2463
/*    */     //   #97	-> 2469
/*    */     //   #98	-> 2520
/*    */     //   #99	-> 2523
/*    */     //   #100	-> 2526
/*    */     //   #101	-> 2529
/*    */     //   #102	-> 2540
/*    */     //   #103	-> 2552
/*    */     //   #104	-> 2560
/*    */     //   #105	-> 2569
/*    */     //   #106	-> 2574
/*    */     //   #107	-> 2577
/*    */     //   #108	-> 2605
/*    */     //   #109	-> 2646
/*    */     //   #110	-> 2655
/*    */     //   #111	-> 2711
/*    */     //   #112	-> 2727
/*    */     //   #113	-> 2732
/*    */     //   #114	-> 2777
/*    */     //   #115	-> 2782
/*    */     //   #116	-> 2827
/*    */     //   #117	-> 2831
/*    */     //   #118	-> 2859
/*    */     //   #119	-> 2872
/*    */     //   #120	-> 2877
/*    */     //   #121	-> 2908
/*    */     //   #122	-> 2916
/*    */     //   #123	-> 2927
/*    */     //   #124	-> 2935
/*    */     //   #125	-> 2966
/*    */     //   #126	-> 2974
/*    */     //   #127	-> 2979
/*    */     //   #128	-> 2984
/*    */     //   #129	-> 2994
/*    */     //   #130	-> 3000
/*    */     //   #131	-> 3008
/*    */     //   #132	-> 3030
/*    */     //   #133	-> 3065
/*    */     //   #134	-> 3120
/*    */     //   #135	-> 3134
/*    */     //   #136	-> 3140
/*    */     //   #137	-> 3221
/*    */     //   #138	-> 3232
/*    */     //   #139	-> 3304
/*    */     //   #140	-> 3321
/*    */     //   #141	-> 3327
/*    */     //   #142	-> 3374
/*    */     //   #143	-> 3380
/*    */     //   #144	-> 3427
/*    */     //   #145	-> 3432
/*    */     //   #146	-> 3472
/*    */     //   #147	-> 3504
/*    */     //   #148	-> 3512
/*    */     //   #149	-> 3517
/*    */     //   #150	-> 3522
/*    */     //   #151	-> 3527
/*    */     //   #152	-> 3559
/*    */     //   #153	-> 3579
/*    */     //   #154	-> 3587
/*    */     //   #155	-> 3604
/*    */     //   #156	-> 3612
/*    */     //   #157	-> 3719
/*    */     //   #158	-> 3727
/*    */     //   #159	-> 3733
/*    */     //   #160	-> 3738
/*    */     //   #161	-> 3743
/*    */     //   #162	-> 3748
/*    */     //   #163	-> 3793
/*    */     //   #164	-> 3806
/*    */     //   #165	-> 3811
/*    */     //   #166	-> 3816
/*    */     //   #167	-> 3869
/*    */     //   #168	-> 3877
/*    */     //   #169	-> 3888
/*    */     //   #170	-> 3896
/*    */     //   #171	-> 4345
/*    */     //   #172	-> 4362
/*    */     //   #173	-> 4370
/*    */     //   #174	-> 4684
/*    */     //   #175	-> 4692
/*    */     //   #176	-> 4736
/*    */     //   #177	-> 4755
/*    */     //   #178	-> 4761
/*    */     //   #179	-> 4769
/*    */     //   #180	-> 4781
/*    */     //   #181	-> 4786
/*    */     //   #182	-> 4789
/*    */     //   #183	-> 4818
/*    */     //   #184	-> 4885
/*    */     //   #185	-> 4896
/*    */     //   #186	-> 4905
/*    */     //   #187	-> 4913
/*    */     //   #188	-> 4967
/*    */     //   #189	-> 4983
/*    */     //   #190	-> 5013
/*    */     //   #191	-> 5019
/*    */     //   #192	-> 5025
/*    */     //   #193	-> 5033
/*    */     //   #194	-> 5046
/*    */     //   #195	-> 5054
/*    */     //   #196	-> 5148
/*    */     //   #197	-> 5157
/*    */     //   #198	-> 5187
/*    */     //   #199	-> 5194
/*    */     //   #200	-> 5291
/*    */     //   #201	-> 5305
/*    */     //   #202	-> 5360
/*    */     //   #203	-> 5368
/*    */     //   #204	-> 5376
/*    */     //   #205	-> 5381
/*    */     //   #206	-> 5421
/*    */     //   #207	-> 5426
/*    */     //   #208	-> 5470
/*    */     //   #209	-> 5473
/*    */     //   #210	-> 5485
/*    */     //   #211	-> 5509
/*    */     //   #212	-> 5567
/*    */     //   #213	-> 5580
/*    */     //   #214	-> 5585
/*    */     //   #215	-> 5588
/*    */     //   #216	-> 5592
/*    */     //   #217	-> 5595
/*    */     //   #218	-> 5601
/*    */     //   #219	-> 5606
/*    */     //   #220	-> 5609
/*    */     //   #221	-> 5632
/*    */     //   #222	-> 5638
/*    */     //   #223	-> 5658
/*    */     //   #224	-> 5665
/*    */     //   #225	-> 5681
/*    */     //   #226	-> 5687
/*    */     //   #227	-> 5708
/*    */   }
/*    */   
/*    */   public final void o0(yD paramyD, xc paramxc, jT paramjT) {
/*    */     cR cR;
/*    */     e00 e002;
/*    */     Gj gj = (Gj)(cR = paramxc.X10).bw0(e002 = e00.FLOAT_POSITION).rI(e002);
/*    */     e00 e003;
/*    */     Sx0 sx0 = (Sx0)paramxc.X10.bw0(e003 = e00.DISPLAY).rI(e003);
/*    */     e00 e004 = e00.MARGIN_TOP;
/*    */     int m = paramyD.qR;
/*    */     paramjT.X90 = (short)Math.max(0, Gf(cR, e004, m, 0));
/*    */     e004 = e00.MARGIN_LEFT;
/*    */     m = paramyD.qR;
/*    */     paramjT.ZW = (short)Math.max(0, Gf(cR, e004, m, 0));
/*    */     e004 = e00.MARGIN_RIGHT;
/*    */     m = paramyD.qR;
/*    */     paramjT.li = (short)Math.max(0, Gf(cR, e004, m, 0));
/*    */     e004 = e00.MARGIN_BOTTOM;
/*    */     m = paramyD.qR;
/*    */     paramjT.N8 = (short)Math.max(0, Gf(cR, e004, m, 0));
/*    */     int j = paramjT.RA0;
/*    */     e00 e005 = e00.WIDTH;
/*    */     int n = paramyD.qR, i1 = paramjT.iw0;
/*    */     int k;
/*    */     if ((k = Gf(cR, e005, n, i1)) > 0) {
/*    */       if ((n = paramjT.iw0) > 0)
/*    */         j = k * paramjT.RA0 / n; 
/*    */       paramjT.iw0 = k;
/*    */     } 
/*    */     e00 e001 = e00.HEIGHT;
/*    */     k = paramjT.RA0;
/*    */     int i;
/*    */     if ((i = Gf(cR, this, k, j)) > 0)
/*    */       paramjT.RA0 = i; 
/*    */     an(paramyD, paramxc, paramjT, gj, sx0);
/*    */   }
/*    */   
/*    */   public final pe Nz0(cR paramcR) {
/*    */     e00 e00;
/*    */     eL eL;
/*    */     if ((eL = (eL)paramcR.bw0(e00 = e00.FONT_FAMILIES).rI(e00)) != null && this.y50 != null)
/*    */       do {
/*    */         nW nW1 = this.y50;
/*    */         pe pe1;
/*    */         if ((pe1 = ((q80)nW1).aa0(eL.F2)) != null)
/*    */           return pe1; 
/*    */       } while ((eL = eL.aF) != null); 
/*    */     return this.xF0;
/*    */   }
/*    */   
/*    */   public final mX Ca0(String paramString) {
/*    */     mX mX;
/*    */     if ((mX = (mX)this.vf0.get(paramString)) != null)
/*    */       return mX; 
/*    */     for (byte b = 0; b < this.Fw.size(); b++) {
/*    */       mX mX1;
/*    */       if ((mX1 = ((Dt0)this.Fw.get(b)).HM()) != null)
/*    */         return mX1; 
/*    */     } 
/*    */     nW nW1;
/*    */     return ((nW1 = this.Wy0) != null) ? ((q80)this).w2(paramString) : null;
/*    */   }
/*    */   
/*    */   public final void Si(yD paramyD, cR paramcR) {
/*    */     e00 e00 = e00.MARGIN_TOP;
/*    */     int i = Math.max(0, Gf(paramcR, this, paramyD.qR, 0));
/*    */     paramyD.OE0(false);
/*    */     paramyD.OE0(false);
/*    */     if ((i = paramyD.NC0(i)) > paramyD.t0) {
/*    */       paramyD.t0 = i;
/*    */       ArrayList<?> arrayList;
/*    */       int j;
/*    */       for (j = (arrayList = paramyD.o4).size(); j-- > 0;) {
/*    */         if (((jT)get(j)).Ia() <= paramyD.t0)
/*    */           remove(j); 
/*    */       } 
/*    */       for (j = (arrayList = paramyD.A60).size(); j-- > 0;) {
/*    */         if (((jT)get(j)).Ia() <= paramyD.t0)
/*    */           remove(j); 
/*    */       } 
/*    */       paramyD.lo();
/*    */     } 
/*    */   }
/*    */   
/*    */   public final void PE(yD paramyD, cR paramcR) {
/*    */     e00 e00 = e00.MARGIN_BOTTOM;
/*    */     int i = Math.max(0, Gf(paramcR, this, paramyD.qR, 0));
/*    */     if (paramyD.zs0()) {
/*    */       paramyD.jy = Math.max(paramyD.jy, paramyD.t0 + i);
/*    */     } else {
/*    */       paramyD.Fq = Math.max(paramyD.Fq, i);
/*    */     } 
/*    */   }
/*    */   
/*    */   public final yD NF0(fM paramfM, int paramInt1, int paramInt2, int paramInt3, Ct paramCt, String paramString, boolean paramBoolean) {
/*    */     // Byte code:
/*    */     //   0: aload_0
/*    */     //   1: dup
/*    */     //   2: dup
/*    */     //   3: aload #5
/*    */     //   5: getfield X10 : Lf/cR;
/*    */     //   8: dup
/*    */     //   9: astore #8
/*    */     //   11: getstatic f/e00.PADDING_TOP : Lf/e00;
/*    */     //   14: iload_2
/*    */     //   15: iconst_0
/*    */     //   16: invokevirtual Gf : (Lf/cR;Lf/e00;II)I
/*    */     //   19: istore #9
/*    */     //   21: aload #8
/*    */     //   23: iconst_0
/*    */     //   24: iload #9
/*    */     //   26: invokestatic max : (II)I
/*    */     //   29: istore #9
/*    */     //   31: getstatic f/e00.PADDING_BOTTOM : Lf/e00;
/*    */     //   34: iload_2
/*    */     //   35: iconst_0
/*    */     //   36: invokevirtual Gf : (Lf/cR;Lf/e00;II)I
/*    */     //   39: istore #10
/*    */     //   41: aload #8
/*    */     //   43: iconst_0
/*    */     //   44: iload #10
/*    */     //   46: invokestatic max : (II)I
/*    */     //   49: istore #10
/*    */     //   51: getstatic f/e00.MARGIN_BOTTOM : Lf/e00;
/*    */     //   54: iload_2
/*    */     //   55: iconst_0
/*    */     //   56: invokevirtual Gf : (Lf/cR;Lf/e00;II)I
/*    */     //   59: iconst_0
/*    */     //   60: swap
/*    */     //   61: invokestatic max : (II)I
/*    */     //   64: istore_2
/*    */     //   65: new f/yD
/*    */     //   68: dup
/*    */     //   69: dup
/*    */     //   70: astore #11
/*    */     //   72: aload_0
/*    */     //   73: aload #11
/*    */     //   75: aload #5
/*    */     //   77: aload #11
/*    */     //   79: aload #8
/*    */     //   81: aload #11
/*    */     //   83: aload #6
/*    */     //   85: aload #11
/*    */     //   87: aload_0
/*    */     //   88: aload_1
/*    */     //   89: iload_3
/*    */     //   90: iload #4
/*    */     //   92: iload #9
/*    */     //   94: iload #7
/*    */     //   96: invokespecial <init> : (Lf/f9;Lf/fM;IIIZ)V
/*    */     //   99: putfield WM : Ljava/lang/String;
/*    */     //   102: putfield LT : Lf/cR;
/*    */     //   105: invokevirtual Sz : (Lf/yD;Ljava/lang/Iterable;)V
/*    */     //   108: invokevirtual T1 : ()V
/*    */     //   111: getfield t0 : I
/*    */     //   114: iload #10
/*    */     //   116: iadd
/*    */     //   117: dup
/*    */     //   118: istore_3
/*    */     //   119: aload_0
/*    */     //   120: aload #8
/*    */     //   122: getstatic f/e00.HEIGHT : Lf/e00;
/*    */     //   125: iload_3
/*    */     //   126: dup
/*    */     //   127: invokevirtual Gf : (Lf/cR;Lf/e00;II)I
/*    */     //   130: invokestatic max : (II)I
/*    */     //   133: dup
/*    */     //   134: istore_0
/*    */     //   135: iload_3
/*    */     //   136: if_icmple -> 373
/*    */     //   139: aload #8
/*    */     //   141: iconst_0
/*    */     //   142: istore #4
/*    */     //   144: getstatic f/e00.VERTICAL_ALIGNMENT : Lf/e00;
/*    */     //   147: dup
/*    */     //   148: astore #5
/*    */     //   150: invokevirtual bw0 : (Lf/e00;)Lf/cR;
/*    */     //   153: aload #5
/*    */     //   155: invokevirtual rI : (Lf/e00;)Ljava/lang/Object;
/*    */     //   158: checkcast f/Om0
/*    */     //   161: invokevirtual ordinal : ()I
/*    */     //   164: dup
/*    */     //   165: istore #5
/*    */     //   167: iconst_1
/*    */     //   168: if_icmpeq -> 194
/*    */     //   171: iload #5
/*    */     //   173: iconst_2
/*    */     //   174: if_icmpeq -> 186
/*    */     //   177: iload #5
/*    */     //   179: iconst_3
/*    */     //   180: if_icmpeq -> 194
/*    */     //   183: goto -> 201
/*    */     //   186: iload_0
/*    */     //   187: iload_3
/*    */     //   188: isub
/*    */     //   189: istore #4
/*    */     //   191: goto -> 201
/*    */     //   194: iload_0
/*    */     //   195: iload_3
/*    */     //   196: isub
/*    */     //   197: iconst_2
/*    */     //   198: idiv
/*    */     //   199: istore #4
/*    */     //   201: iload #4
/*    */     //   203: ifle -> 373
/*    */     //   206: aload_1
/*    */     //   207: iconst_0
/*    */     //   208: istore_3
/*    */     //   209: getfield nA0 : Ljava/util/ArrayList;
/*    */     //   212: invokevirtual size : ()I
/*    */     //   215: istore #5
/*    */     //   217: iload_3
/*    */     //   218: iload #5
/*    */     //   220: if_icmpge -> 250
/*    */     //   223: aload_1
/*    */     //   224: getfield nA0 : Ljava/util/ArrayList;
/*    */     //   227: iload_3
/*    */     //   228: invokevirtual get : (I)Ljava/lang/Object;
/*    */     //   231: checkcast f/jT
/*    */     //   234: dup
/*    */     //   235: getfield dF : I
/*    */     //   238: iload #4
/*    */     //   240: iadd
/*    */     //   241: putfield dF : I
/*    */     //   244: iinc #3, 1
/*    */     //   247: goto -> 217
/*    */     //   250: aload_1
/*    */     //   251: getfield Pe0 : [C
/*    */     //   254: dup
/*    */     //   255: astore_3
/*    */     //   256: arraylength
/*    */     //   257: ifle -> 373
/*    */     //   260: aload_3
/*    */     //   261: iconst_1
/*    */     //   262: caload
/*    */     //   263: ifne -> 280
/*    */     //   266: aload_3
/*    */     //   267: dup
/*    */     //   268: iconst_0
/*    */     //   269: caload
/*    */     //   270: iload #4
/*    */     //   272: iadd
/*    */     //   273: i2c
/*    */     //   274: iconst_0
/*    */     //   275: swap
/*    */     //   276: castore
/*    */     //   277: goto -> 373
/*    */     //   280: aload_3
/*    */     //   281: arraylength
/*    */     //   282: dup
/*    */     //   283: istore_3
/*    */     //   284: iconst_2
/*    */     //   285: iadd
/*    */     //   286: newarray char
/*    */     //   288: dup
/*    */     //   289: astore #5
/*    */     //   291: iload #4
/*    */     //   293: i2c
/*    */     //   294: iconst_0
/*    */     //   295: swap
/*    */     //   296: castore
/*    */     //   297: iconst_0
/*    */     //   298: istore #6
/*    */     //   300: iload #6
/*    */     //   302: iload_3
/*    */     //   303: if_icmpge -> 367
/*    */     //   306: aload_1
/*    */     //   307: getfield Pe0 : [C
/*    */     //   310: dup
/*    */     //   311: astore #7
/*    */     //   313: iload #6
/*    */     //   315: caload
/*    */     //   316: dup
/*    */     //   317: istore #8
/*    */     //   319: ifle -> 329
/*    */     //   322: iload #8
/*    */     //   324: iload #4
/*    */     //   326: iadd
/*    */     //   327: istore #8
/*    */     //   329: aload #5
/*    */     //   331: aload #7
/*    */     //   333: iload #6
/*    */     //   335: aload #5
/*    */     //   337: iload #8
/*    */     //   339: iload #6
/*    */     //   341: iconst_2
/*    */     //   342: iadd
/*    */     //   343: istore #7
/*    */     //   345: i2c
/*    */     //   346: iload #7
/*    */     //   348: swap
/*    */     //   349: castore
/*    */     //   350: iinc #6, 3
/*    */     //   353: iconst_1
/*    */     //   354: iadd
/*    */     //   355: caload
/*    */     //   356: iload #6
/*    */     //   358: swap
/*    */     //   359: castore
/*    */     //   360: iload #7
/*    */     //   362: istore #6
/*    */     //   364: goto -> 300
/*    */     //   367: aload_1
/*    */     //   368: aload #5
/*    */     //   370: putfield Pe0 : [C
/*    */     //   373: aload #11
/*    */     //   375: aload_1
/*    */     //   376: iload_2
/*    */     //   377: aload #11
/*    */     //   379: aload_1
/*    */     //   380: iload_0
/*    */     //   381: putfield RA0 : I
/*    */     //   384: getfield jy : I
/*    */     //   387: aload #11
/*    */     //   389: getfield t0 : I
/*    */     //   392: isub
/*    */     //   393: invokestatic max : (II)I
/*    */     //   396: i2s
/*    */     //   397: putfield N8 : S
/*    */     //   400: areturn
/*    */     // Line number table:
/*    */     //   Java source line number -> byte code offset
/*    */     //   #1	-> 5
/*    */     //   #2	-> 11
/*    */     //   #3	-> 16
/*    */     //   #4	-> 31
/*    */     //   #5	-> 36
/*    */     //   #6	-> 51
/*    */     //   #7	-> 56
/*    */     //   #8	-> 65
/*    */     //   #9	-> 150
/*    */     //   #10	-> 158
/*    */     //   #11	-> 209
/*    */     //   #12	-> 381
/*    */   }
/*    */   
/*    */   public final void vq0(yD paramyD, Ct paramCt) {
/*    */     // Byte code:
/*    */     //   0: aload_2
/*    */     //   1: aload_1
/*    */     //   2: iconst_0
/*    */     //   3: invokevirtual OE0 : (Z)Z
/*    */     //   6: pop
/*    */     //   7: getfield X10 : Lf/cR;
/*    */     //   10: dup
/*    */     //   11: astore_3
/*    */     //   12: getstatic f/e00.FLOAT_POSITION : Lf/e00;
/*    */     //   15: dup
/*    */     //   16: astore #4
/*    */     //   18: invokevirtual bw0 : (Lf/e00;)Lf/cR;
/*    */     //   21: aload #4
/*    */     //   23: invokevirtual rI : (Lf/e00;)Ljava/lang/Object;
/*    */     //   26: checkcast f/Gj
/*    */     //   29: dup
/*    */     //   30: astore #4
/*    */     //   32: aload_0
/*    */     //   33: aload_3
/*    */     //   34: aload_1
/*    */     //   35: aload_0
/*    */     //   36: aload_3
/*    */     //   37: aload_1
/*    */     //   38: dup
/*    */     //   39: dup2
/*    */     //   40: aload_0
/*    */     //   41: aload_3
/*    */     //   42: aload_1
/*    */     //   43: aload_0
/*    */     //   44: aload_3
/*    */     //   45: aload_1
/*    */     //   46: aload_0
/*    */     //   47: aload_3
/*    */     //   48: aload_1
/*    */     //   49: aload_0
/*    */     //   50: aload_1
/*    */     //   51: aload_2
/*    */     //   52: invokevirtual mk0 : (Lf/yD;Lf/xc;)Lf/dK;
/*    */     //   55: astore #5
/*    */     //   57: getstatic f/e00.MARGIN_TOP : Lf/e00;
/*    */     //   60: astore #6
/*    */     //   62: getfield qR : I
/*    */     //   65: aload #6
/*    */     //   67: swap
/*    */     //   68: iconst_0
/*    */     //   69: invokevirtual Gf : (Lf/cR;Lf/e00;II)I
/*    */     //   72: iconst_0
/*    */     //   73: swap
/*    */     //   74: invokestatic max : (II)I
/*    */     //   77: istore #6
/*    */     //   79: getstatic f/e00.MARGIN_LEFT : Lf/e00;
/*    */     //   82: astore #7
/*    */     //   84: getfield qR : I
/*    */     //   87: aload #7
/*    */     //   89: swap
/*    */     //   90: iconst_0
/*    */     //   91: invokevirtual Gf : (Lf/cR;Lf/e00;II)I
/*    */     //   94: iconst_0
/*    */     //   95: swap
/*    */     //   96: invokestatic max : (II)I
/*    */     //   99: istore #7
/*    */     //   101: getstatic f/e00.MARGIN_RIGHT : Lf/e00;
/*    */     //   104: astore #8
/*    */     //   106: getfield qR : I
/*    */     //   109: aload #8
/*    */     //   111: swap
/*    */     //   112: iconst_0
/*    */     //   113: invokevirtual Gf : (Lf/cR;Lf/e00;II)I
/*    */     //   116: istore #8
/*    */     //   118: iload #7
/*    */     //   120: iconst_0
/*    */     //   121: iload #8
/*    */     //   123: invokestatic max : (II)I
/*    */     //   126: istore #8
/*    */     //   128: invokevirtual o70 : (I)I
/*    */     //   131: istore #9
/*    */     //   133: iload #6
/*    */     //   135: invokevirtual NC0 : (I)I
/*    */     //   138: istore #6
/*    */     //   140: iload #8
/*    */     //   142: invokevirtual CQ : (I)I
/*    */     //   145: iload #9
/*    */     //   147: isub
/*    */     //   148: iconst_0
/*    */     //   149: swap
/*    */     //   150: invokestatic max : (II)I
/*    */     //   153: istore #10
/*    */     //   155: getstatic f/e00.PADDING_LEFT : Lf/e00;
/*    */     //   158: astore #11
/*    */     //   160: getfield qR : I
/*    */     //   163: aload #11
/*    */     //   165: swap
/*    */     //   166: iconst_0
/*    */     //   167: invokevirtual Gf : (Lf/cR;Lf/e00;II)I
/*    */     //   170: iconst_0
/*    */     //   171: swap
/*    */     //   172: invokestatic max : (II)I
/*    */     //   175: istore #11
/*    */     //   177: getstatic f/e00.PADDING_RIGHT : Lf/e00;
/*    */     //   180: astore #12
/*    */     //   182: getfield qR : I
/*    */     //   185: aload #12
/*    */     //   187: swap
/*    */     //   188: iconst_0
/*    */     //   189: invokevirtual Gf : (Lf/cR;Lf/e00;II)I
/*    */     //   192: iconst_0
/*    */     //   193: swap
/*    */     //   194: invokestatic max : (II)I
/*    */     //   197: istore #12
/*    */     //   199: getstatic f/Gj.FC0 : Lf/Gj;
/*    */     //   202: dup
/*    */     //   203: astore #13
/*    */     //   205: if_acmpne -> 224
/*    */     //   208: aload_0
/*    */     //   209: getstatic f/e00.WIDTH : Lf/e00;
/*    */     //   212: aload_3
/*    */     //   213: swap
/*    */     //   214: iload #10
/*    */     //   216: dup
/*    */     //   217: invokevirtual Gf : (Lf/cR;Lf/e00;II)I
/*    */     //   220: istore_3
/*    */     //   221: goto -> 325
/*    */     //   224: aload_0
/*    */     //   225: aload_1
/*    */     //   226: getstatic f/e00.WIDTH : Lf/e00;
/*    */     //   229: astore #14
/*    */     //   231: getfield qR : I
/*    */     //   234: istore #15
/*    */     //   236: aload_3
/*    */     //   237: aload #14
/*    */     //   239: iload #15
/*    */     //   241: ldc_w -2147483648
/*    */     //   244: invokevirtual Gf : (Lf/cR;Lf/e00;II)I
/*    */     //   247: dup
/*    */     //   248: istore_3
/*    */     //   249: ldc_w -2147483648
/*    */     //   252: if_icmpne -> 325
/*    */     //   255: aload_0
/*    */     //   256: aload_1
/*    */     //   257: new f/fM
/*    */     //   260: dup
/*    */     //   261: astore_3
/*    */     //   262: aload_1
/*    */     //   263: aload_3
/*    */     //   264: aconst_null
/*    */     //   265: invokespecial <init> : (Lf/xc;)V
/*    */     //   268: getfield tl : I
/*    */     //   271: iload #11
/*    */     //   273: isub
/*    */     //   274: iload #12
/*    */     //   276: isub
/*    */     //   277: iconst_0
/*    */     //   278: swap
/*    */     //   279: invokestatic max : (II)I
/*    */     //   282: putfield iw0 : I
/*    */     //   285: getfield qR : I
/*    */     //   288: aload_3
/*    */     //   289: swap
/*    */     //   290: iload #11
/*    */     //   292: iload #12
/*    */     //   294: aload_2
/*    */     //   295: aconst_null
/*    */     //   296: iconst_0
/*    */     //   297: invokevirtual NF0 : (Lf/fM;IIILf/Ct;Ljava/lang/String;Z)Lf/yD;
/*    */     //   300: astore #14
/*    */     //   302: aload_3
/*    */     //   303: aload #14
/*    */     //   305: iconst_0
/*    */     //   306: invokevirtual OE0 : (Z)Z
/*    */     //   309: pop
/*    */     //   310: getfield iw0 : I
/*    */     //   313: aload #14
/*    */     //   315: getfield SF : I
/*    */     //   318: isub
/*    */     //   319: iconst_0
/*    */     //   320: swap
/*    */     //   321: invokestatic max : (II)I
/*    */     //   324: istore_3
/*    */     //   325: aload #4
/*    */     //   327: aload #13
/*    */     //   329: iconst_0
/*    */     //   330: iload_3
/*    */     //   331: invokestatic max : (II)I
/*    */     //   334: iload #11
/*    */     //   336: iadd
/*    */     //   337: iload #12
/*    */     //   339: iadd
/*    */     //   340: istore_3
/*    */     //   341: if_acmpeq -> 388
/*    */     //   344: aload_1
/*    */     //   345: iload #8
/*    */     //   347: iload #6
/*    */     //   349: aload_1
/*    */     //   350: dup
/*    */     //   351: iload #7
/*    */     //   353: aload_1
/*    */     //   354: iload_3
/*    */     //   355: iload #7
/*    */     //   357: iload #8
/*    */     //   359: invokevirtual pr : (III)V
/*    */     //   362: invokevirtual o70 : (I)I
/*    */     //   365: istore #9
/*    */     //   367: getfield t0 : I
/*    */     //   370: invokestatic max : (II)I
/*    */     //   373: istore #6
/*    */     //   375: invokevirtual CQ : (I)I
/*    */     //   378: iload #9
/*    */     //   380: isub
/*    */     //   381: iconst_0
/*    */     //   382: swap
/*    */     //   383: invokestatic max : (II)I
/*    */     //   386: istore #10
/*    */     //   388: aload #4
/*    */     //   390: iload_3
/*    */     //   391: iload #10
/*    */     //   393: invokestatic min : (II)I
/*    */     //   396: istore_3
/*    */     //   397: getstatic f/Gj.Df : Lf/Gj;
/*    */     //   400: dup
/*    */     //   401: astore #10
/*    */     //   403: if_acmpne -> 416
/*    */     //   406: aload_1
/*    */     //   407: iload #8
/*    */     //   409: invokevirtual CQ : (I)I
/*    */     //   412: iload_3
/*    */     //   413: isub
/*    */     //   414: istore #9
/*    */     //   416: aload #4
/*    */     //   418: aload #13
/*    */     //   420: aload_1
/*    */     //   421: dup
/*    */     //   422: aload_0
/*    */     //   423: aload_1
/*    */     //   424: dup
/*    */     //   425: dup2
/*    */     //   426: new f/fM
/*    */     //   429: dup
/*    */     //   430: astore_0
/*    */     //   431: aload_1
/*    */     //   432: aload_0
/*    */     //   433: iload #8
/*    */     //   435: aload_0
/*    */     //   436: iload #7
/*    */     //   438: aload_0
/*    */     //   439: iload_3
/*    */     //   440: aload_0
/*    */     //   441: iload #6
/*    */     //   443: aload_0
/*    */     //   444: iload #9
/*    */     //   446: aload_0
/*    */     //   447: aload_2
/*    */     //   448: invokespecial <init> : (Lf/xc;)V
/*    */     //   451: putfield mx : I
/*    */     //   454: putfield dF : I
/*    */     //   457: putfield iw0 : I
/*    */     //   460: i2s
/*    */     //   461: putfield ZW : S
/*    */     //   464: i2s
/*    */     //   465: putfield li : S
/*    */     //   468: getfield WM : Ljava/lang/String;
/*    */     //   471: putfield bw : Ljava/lang/String;
/*    */     //   474: getfield pb0 : Ljava/util/ArrayList;
/*    */     //   477: aload_0
/*    */     //   478: invokevirtual add : (Ljava/lang/Object;)Z
/*    */     //   481: pop
/*    */     //   482: getfield qR : I
/*    */     //   485: istore #7
/*    */     //   487: getfield WM : Ljava/lang/String;
/*    */     //   490: astore #8
/*    */     //   492: getfield Q10 : Z
/*    */     //   495: istore #13
/*    */     //   497: aload_0
/*    */     //   498: iload #7
/*    */     //   500: iload #11
/*    */     //   502: iload #12
/*    */     //   504: aload_2
/*    */     //   505: aload #8
/*    */     //   507: iload #13
/*    */     //   509: invokevirtual NF0 : (Lf/fM;IIILf/Ct;Ljava/lang/String;Z)Lf/yD;
/*    */     //   512: astore_2
/*    */     //   513: getfield pb0 : Ljava/util/ArrayList;
/*    */     //   516: invokevirtual size : ()I
/*    */     //   519: putfield xu0 : I
/*    */     //   522: if_acmpne -> 731
/*    */     //   525: iload #6
/*    */     //   527: aload_0
/*    */     //   528: getfield RA0 : I
/*    */     //   531: iadd
/*    */     //   532: dup
/*    */     //   533: istore #4
/*    */     //   535: aload_1
/*    */     //   536: dup
/*    */     //   537: iconst_0
/*    */     //   538: invokevirtual OE0 : (Z)Z
/*    */     //   541: pop
/*    */     //   542: getfield t0 : I
/*    */     //   545: if_icmple -> 664
/*    */     //   548: aload_1
/*    */     //   549: dup
/*    */     //   550: iload #4
/*    */     //   552: putfield t0 : I
/*    */     //   555: getfield o4 : Ljava/util/ArrayList;
/*    */     //   558: dup
/*    */     //   559: astore #4
/*    */     //   561: invokevirtual size : ()I
/*    */     //   564: istore #7
/*    */     //   566: iload #7
/*    */     //   568: dup
/*    */     //   569: iconst_m1
/*    */     //   570: iadd
/*    */     //   571: istore #7
/*    */     //   573: ifle -> 607
/*    */     //   576: aload #4
/*    */     //   578: iload #7
/*    */     //   580: invokevirtual get : (I)Ljava/lang/Object;
/*    */     //   583: checkcast f/jT
/*    */     //   586: invokevirtual Ia : ()I
/*    */     //   589: aload_1
/*    */     //   590: getfield t0 : I
/*    */     //   593: if_icmpgt -> 566
/*    */     //   596: aload #4
/*    */     //   598: iload #7
/*    */     //   600: invokevirtual remove : (I)Ljava/lang/Object;
/*    */     //   603: pop
/*    */     //   604: goto -> 566
/*    */     //   607: aload_1
/*    */     //   608: getfield A60 : Ljava/util/ArrayList;
/*    */     //   611: dup
/*    */     //   612: astore #4
/*    */     //   614: invokevirtual size : ()I
/*    */     //   617: istore #7
/*    */     //   619: iload #7
/*    */     //   621: dup
/*    */     //   622: iconst_m1
/*    */     //   623: iadd
/*    */     //   624: istore #7
/*    */     //   626: ifle -> 660
/*    */     //   629: aload #4
/*    */     //   631: iload #7
/*    */     //   633: invokevirtual get : (I)Ljava/lang/Object;
/*    */     //   636: checkcast f/jT
/*    */     //   639: invokevirtual Ia : ()I
/*    */     //   642: aload_1
/*    */     //   643: getfield t0 : I
/*    */     //   646: if_icmpgt -> 619
/*    */     //   649: aload #4
/*    */     //   651: iload #7
/*    */     //   653: invokevirtual remove : (I)Ljava/lang/Object;
/*    */     //   656: pop
/*    */     //   657: goto -> 619
/*    */     //   660: aload_1
/*    */     //   661: invokevirtual lo : ()V
/*    */     //   664: aload_1
/*    */     //   665: aload_0
/*    */     //   666: getfield N8 : S
/*    */     //   669: istore #4
/*    */     //   671: invokevirtual zs0 : ()Z
/*    */     //   674: ifeq -> 698
/*    */     //   677: aload_1
/*    */     //   678: dup
/*    */     //   679: getfield jy : I
/*    */     //   682: aload_1
/*    */     //   683: getfield t0 : I
/*    */     //   686: iload #4
/*    */     //   688: iadd
/*    */     //   689: invokestatic max : (II)I
/*    */     //   692: putfield jy : I
/*    */     //   695: goto -> 711
/*    */     //   698: aload_1
/*    */     //   699: dup
/*    */     //   700: getfield Fq : I
/*    */     //   703: iload #4
/*    */     //   705: invokestatic max : (II)I
/*    */     //   708: putfield Fq : I
/*    */     //   711: aload_1
/*    */     //   712: dup
/*    */     //   713: aload_2
/*    */     //   714: getfield SF : I
/*    */     //   717: istore_1
/*    */     //   718: getfield SF : I
/*    */     //   721: iload_1
/*    */     //   722: invokestatic min : (II)I
/*    */     //   725: putfield SF : I
/*    */     //   728: goto -> 763
/*    */     //   731: aload #4
/*    */     //   733: aload #10
/*    */     //   735: if_acmpne -> 750
/*    */     //   738: aload_1
/*    */     //   739: getfield A60 : Ljava/util/ArrayList;
/*    */     //   742: aload_0
/*    */     //   743: invokevirtual add : (Ljava/lang/Object;)Z
/*    */     //   746: pop
/*    */     //   747: goto -> 759
/*    */     //   750: aload_1
/*    */     //   751: getfield o4 : Ljava/util/ArrayList;
/*    */     //   754: aload_0
/*    */     //   755: invokevirtual add : (Ljava/lang/Object;)Z
/*    */     //   758: pop
/*    */     //   759: aload_1
/*    */     //   760: invokevirtual lo : ()V
/*    */     //   763: aload #5
/*    */     //   765: ifnull -> 803
/*    */     //   768: aload #5
/*    */     //   770: aload_0
/*    */     //   771: aload #5
/*    */     //   773: aload_0
/*    */     //   774: aload #5
/*    */     //   776: iload_3
/*    */     //   777: aload #5
/*    */     //   779: iload #6
/*    */     //   781: aload #5
/*    */     //   783: iload #9
/*    */     //   785: putfield mx : I
/*    */     //   788: putfield dF : I
/*    */     //   791: putfield iw0 : I
/*    */     //   794: getfield RA0 : I
/*    */     //   797: putfield RA0 : I
/*    */     //   800: putfield PRN : Lf/jT;
/*    */     //   803: return
/*    */     // Line number table:
/*    */     //   Java source line number -> byte code offset
/*    */     //   #1	-> 7
/*    */     //   #2	-> 12
/*    */     //   #3	-> 18
/*    */     //   #4	-> 23
/*    */     //   #5	-> 26
/*    */     //   #6	-> 69
/*    */     //   #7	-> 79
/*    */     //   #8	-> 91
/*    */     //   #9	-> 101
/*    */     //   #10	-> 113
/*    */     //   #11	-> 128
/*    */     //   #12	-> 167
/*    */     //   #13	-> 177
/*    */     //   #14	-> 189
/*    */     //   #15	-> 199
/*    */     //   #16	-> 538
/*    */     //   #17	-> 555
/*    */     //   #18	-> 561
/*    */     //   #19	-> 608
/*    */     //   #20	-> 614
/*    */     //   #21	-> 661
/*    */     //   #22	-> 666
/*    */     //   #23	-> 671
/*    */     //   #24	-> 714
/*    */     //   #25	-> 718
/*    */     //   #26	-> 739
/*    */   }
/*    */   
/*    */   public final dK mk0(yD paramyD, xc paramxc) {
/*    */     pRn pRn;
/*    */     cR cR;
/*    */     String str;
/*    */     e00 e00;
/*    */     if ((str = (String)(cR = paramxc.X10).bw0(e00 = e00.BACKGROUND_IMAGE).rI(e00)) != null) {
/*    */       mX mX = Ca0(str);
/*    */     } else {
/*    */       str = null;
/*    */     } 
/*    */     if (str == null) {
/*    */       mX mX;
/*    */       e00 e001;
/*    */       if ((pRn = (pRn)cR.bw0(e001 = e00.BACKGROUND_COLOR).rI(e001)).cj() != 0 && (mX = Ca0("white")) != null) {
/*    */         mX mX1 = rv0(pRn);
/*    */         pRn pRn1;
/*    */         e00 e002;
/*    */         if ((pRn1 = (pRn)cR.bw0(e002 = e00.BACKGROUND_COLOR_HOVER).rI(e002)) != null) {
/*    */           Sv0 sv0;
/*    */           vc vc1 = wd;
/*    */           mX[] arrayOfMX;
/*    */           (arrayOfMX = new mX[2])[0] = rv0(pRn1);
/*    */           (new mX[2])[1] = mX1;
/*    */           this(vc1, null, arrayOfMX);
/*    */           mX1 = sv0;
/*    */         } 
/*    */       } else {
/*    */         pRn = null;
/*    */       } 
/*    */     } 
/*    */     if (pRn != null) {
/*    */       this(paramxc, (mX)pRn);
/*    */       this.dF = paramyD.t0;
/*    */       paramyD.ST.Xf0.add(this);
/*    */       dK dK;
/*    */       return dK = new dK();
/*    */     } 
/*    */     return null;
/*    */   }
/*    */   
/*    */   public final void pb0(Zq0 paramZq0) {
/*    */     Zq0 zq02;
/*    */     if ((zq02 = this.wy) != null) {
/*    */       TJ tJ2 = this.Rf;
/*    */       ((zA)zq02).nq0(tJ2);
/*    */     } 
/*    */     this.wy = paramZq0;
/*    */     TJ tJ1 = this.Rf;
/*    */     ((zA)paramZq0).Ac0(tJ1);
/*    */     Zq0 zq01;
/*    */     if (zq01 = this.wy instanceof wH0)
/*    */       ((wH0)zq01).HW = null; 
/*    */     this.wy = paramZq0;
/*    */     ((wH0)paramZq0).HW = this.gD;
/*    */     Ru(true);
/*    */   }
/*    */   
/*    */   public final void Q90() {
/*    */     this.Y3.clear();
/*    */     super.gx();
/*    */     Ru(true);
/*    */   }
/*    */   
/*    */   public final void e80(Cs0 paramCs0) {
/*    */     this.Cv = (Cs0[])hm.LpT6((Object[])this.Cv, paramCs0, Cs0.class);
/*    */   }
/*    */   
/*    */   public final void Xw(nY paramnY) {
/*    */     super.Xw(paramnY);
/*    */     this.y50 = q80.Uz("fonts");
/*    */     this.Wy0 = q80.Uz("images");
/*    */     this.xF0 = q80.aa0("font");
/*    */     this.ey = q80.sL("mouseCursor");
/*    */     q80 q80;
/*    */     this.Z30 = (q80 = (q80)paramnY).sL("mouseCursor.link");
/*    */     Ru(true);
/*    */   }
/*    */   
/*    */   public final void LM(throws paramthrows) {
/*    */     this.aA.Vx.lg0(paramthrows);
/*    */     this.aA.mV.lg0(paramthrows);
/*    */   }
/*    */   
/*    */   public final void si(JG0 paramJG0, int paramInt) {
/*    */     throw new UnsupportedOperationException("use registerWidget");
/*    */   }
/*    */   
/*    */   public final void gx() {
/*    */     throw new UnsupportedOperationException("use registerWidget");
/*    */   }
/*    */   
/*    */   public final JG0 fG0(int paramInt) {
/*    */     throw new UnsupportedOperationException("use registerWidget");
/*    */   }
/*    */   
/*    */   public final int R80() {
/*    */     if (this.cj0 == null)
/*    */       Ae0(); 
/*    */     int i;
/*    */     if ((i = this.cj0.PO) >= 0)
/*    */       return i; 
/*    */     return qF();
/*    */   }
/*    */   
/*    */   public final int tJ0() {
/*    */     if (qF() == 0) {
/*    */       if (this.cj0 == null)
/*    */         Ae0(); 
/*    */       int i;
/*    */       if ((i = this.cj0.bJ0) >= 0)
/*    */         return i; 
/*    */     } 
/*    */     uW();
/*    */     return this.pW.RA0;
/*    */   }
/*    */   
/*    */   public final int J50() {
/*    */     short s = this.fu;
/*    */     return JG0.Fr(AW(), super.J50(), s);
/*    */   }
/*    */   
/*    */   public final void RI(int paramInt1, int paramInt2) {
/*    */     if (paramInt1 != this.fu) {
/*    */       this.cj0 = null;
/*    */       MJ0();
/*    */     } 
/*    */     super.RI(paramInt1, paramInt2);
/*    */   }
/*    */   
/*    */   public final void uh0(int paramInt1, int paramInt2) {
/*    */     if (paramInt1 != AW()) {
/*    */       this.cj0 = null;
/*    */       MJ0();
/*    */     } 
/*    */     super.uh0(paramInt1, paramInt2);
/*    */   }
/*    */   
/*    */   public final void d40() {
/*    */     int i = qF();
/*    */     int j;
/*    */     if ((j = this.pW.iw0) != i || this.Tv0) {
/*    */       if (this.X2 || j != i) {
/*    */         Iterator iterator;
/*    */         for (this.X2 = false, iterator = this.dG0.values().iterator(); iterator.hasNext(); ) {
/*    */           for (Iterator<jT> iterator1 = ((coM4)iterator.next()).RQ.iterator(); iterator1.hasNext(); ) {
/*    */             jT jT1;
/*    */             if (jT1 = iterator1.next() instanceof vB)
/*    */               ((vB)jT1).Et0 = false; 
/*    */             jT1.LpT1();
/*    */           } 
/*    */           iterator.remove();
/*    */         } 
/*    */       } 
/*    */       this.pW.iw0 = i;
/*    */       this.gW = true;
/*    */       this.Tv0 = false;
/*    */       if ((null = this.Bo0) != null)
/*    */         null.IB0.getClass(); 
/*    */       try {
/*    */         yD yD;
/*    */         fM fM1;
/*    */         this.pW.LpT1();
/*    */         this.Ze0.clear();
/*    */         super.gx();
/*    */         this(this, this.pW, 0, 0, 0, true);
/*    */         Zq0 zq0;
/*    */         if ((zq0 = this.wy) != null) {
/*    */           Sz(yD, zq0);
/*    */           yD.T1();
/*    */           int m = RS();
/*    */           this.pW.nv(m, e3());
/*    */           m = 0;
/*    */           boolean bool = false;
/*    */           ArrayList arrayList = this.Ze0;
/*    */           this.pW.xe0(m, bool, arrayList);
/*    */         } 
/*    */         FC0();
/*    */         int k = yD.t0;
/*    */         this.gW = false;
/*    */         fM1.RA0 = k;
/*    */         return;
/*    */       } finally {
/*    */         this.gW = false;
/*    */       } 
/*    */     } 
/*    */   }
/*    */   
/*    */   public final void J00(throws paramthrows) {
/*    */     pj.Vm = RS();
/*    */     pj.nH = e3();
/*    */     byte b;
/*    */     ArrayList<?> arrayList;
/*    */     Pj pj;
/*    */     int i;
/*    */     for ((pj = this.aA).f20 = paramthrows.IB0, b = 0, i = (arrayList = this.Ze0).size(); b < i; ) {
/*    */       ((dK)arrayList.get(b)).in0(pj);
/*    */       b++;
/*    */     } 
/*    */     this.pW.in0(pj);
/*    */   }
/*    */   
/*    */   public final void Gu() {
/*    */     if (!this.gW)
/*    */       MJ0(); 
/*    */   }
/*    */   
/*    */   public final void zE() {}
/*    */   
/*    */   public final void jA0() {
/*    */     super.jA0();
/*    */     this.pW.LpT1();
/*    */     this.Ze0.clear();
/*    */     super.gx();
/*    */     Ru(true);
/*    */   }
/*    */   
/*    */   public boolean i2(oa0 paramoa0) {
/*    */     // Byte code:
/*    */     //   0: aload_0
/*    */     //   1: aload_1
/*    */     //   2: invokespecial i2 : (Lf/oa0;)Z
/*    */     //   5: ifeq -> 10
/*    */     //   8: iconst_1
/*    */     //   9: ireturn
/*    */     //   10: aload_1
/*    */     //   11: getfield cz0 : I
/*    */     //   14: dup
/*    */     //   15: istore_2
/*    */     //   16: invokestatic Pg : (I)Z
/*    */     //   19: ifeq -> 316
/*    */     //   22: aload_0
/*    */     //   23: getfield yV : Z
/*    */     //   26: ifeq -> 82
/*    */     //   29: aload_1
/*    */     //   30: invokevirtual Ud : ()Z
/*    */     //   33: ifeq -> 80
/*    */     //   36: aload_0
/*    */     //   37: dup
/*    */     //   38: aload_1
/*    */     //   39: aload_0
/*    */     //   40: aload_1
/*    */     //   41: aload_0
/*    */     //   42: dup
/*    */     //   43: aload_1
/*    */     //   44: dup
/*    */     //   45: aload_0
/*    */     //   46: iconst_0
/*    */     //   47: putfield yV : Z
/*    */     //   50: getfield aK : I
/*    */     //   53: istore_0
/*    */     //   54: getfield gk0 : I
/*    */     //   57: iload_0
/*    */     //   58: swap
/*    */     //   59: invokevirtual mu0 : (II)Z
/*    */     //   62: putfield Kw0 : Z
/*    */     //   65: getfield aK : I
/*    */     //   68: putfield th : I
/*    */     //   71: getfield gk0 : I
/*    */     //   74: putfield qj : I
/*    */     //   77: invokevirtual FC0 : ()V
/*    */     //   80: iconst_1
/*    */     //   81: ireturn
/*    */     //   82: iload_2
/*    */     //   83: aload_0
/*    */     //   84: dup
/*    */     //   85: aload_1
/*    */     //   86: aload_0
/*    */     //   87: aload_1
/*    */     //   88: aload_0
/*    */     //   89: dup
/*    */     //   90: aload_1
/*    */     //   91: dup
/*    */     //   92: getfield aK : I
/*    */     //   95: istore_3
/*    */     //   96: getfield gk0 : I
/*    */     //   99: iload_3
/*    */     //   100: swap
/*    */     //   101: invokevirtual mu0 : (II)Z
/*    */     //   104: putfield Kw0 : Z
/*    */     //   107: getfield aK : I
/*    */     //   110: putfield th : I
/*    */     //   113: getfield gk0 : I
/*    */     //   116: putfield qj : I
/*    */     //   119: invokevirtual FC0 : ()V
/*    */     //   122: bipush #8
/*    */     //   124: if_icmpne -> 129
/*    */     //   127: iconst_0
/*    */     //   128: ireturn
/*    */     //   129: iload_2
/*    */     //   130: iconst_3
/*    */     //   131: istore_3
/*    */     //   132: bipush #6
/*    */     //   134: if_icmpne -> 168
/*    */     //   137: getstatic f/f9.bK0 : Z
/*    */     //   140: ifne -> 161
/*    */     //   143: aload_0
/*    */     //   144: getfield yV : Z
/*    */     //   147: ifne -> 153
/*    */     //   150: goto -> 161
/*    */     //   153: new java/lang/AssertionError
/*    */     //   156: dup
/*    */     //   157: invokespecial <init> : ()V
/*    */     //   160: athrow
/*    */     //   161: aload_0
/*    */     //   162: iconst_1
/*    */     //   163: putfield yV : Z
/*    */     //   166: iconst_1
/*    */     //   167: ireturn
/*    */     //   168: aload_0
/*    */     //   169: getfield Zk : Lf/jT;
/*    */     //   172: dup
/*    */     //   173: astore #4
/*    */     //   175: ifnull -> 257
/*    */     //   178: iload_2
/*    */     //   179: iconst_5
/*    */     //   180: if_icmpeq -> 193
/*    */     //   183: iload_2
/*    */     //   184: iload_3
/*    */     //   185: if_icmpeq -> 193
/*    */     //   188: iload_2
/*    */     //   189: iconst_4
/*    */     //   190: if_icmpne -> 257
/*    */     //   193: aload_0
/*    */     //   194: aload #4
/*    */     //   196: getfield dM : Lf/xc;
/*    */     //   199: astore_3
/*    */     //   200: getfield Cv : [Lf/Cs0;
/*    */     //   203: dup
/*    */     //   204: astore #4
/*    */     //   206: ifnull -> 257
/*    */     //   209: aload #4
/*    */     //   211: arraylength
/*    */     //   212: istore #5
/*    */     //   214: iconst_0
/*    */     //   215: istore #6
/*    */     //   217: iload #6
/*    */     //   219: iload #5
/*    */     //   221: if_icmpge -> 257
/*    */     //   224: aload #4
/*    */     //   226: iload #6
/*    */     //   228: aaload
/*    */     //   229: dup
/*    */     //   230: astore #7
/*    */     //   232: instanceof f/m1
/*    */     //   235: ifeq -> 251
/*    */     //   238: aload #7
/*    */     //   240: checkcast f/m1
/*    */     //   243: getfield Gs0 : Lf/wu;
/*    */     //   246: aload_1
/*    */     //   247: aload_3
/*    */     //   248: invokevirtual e20 : (Lf/oa0;Lf/xc;)V
/*    */     //   251: iinc #6, 1
/*    */     //   254: goto -> 217
/*    */     //   257: iload_2
/*    */     //   258: iconst_5
/*    */     //   259: if_icmpne -> 314
/*    */     //   262: aload_0
/*    */     //   263: getfield Zk : Lf/jT;
/*    */     //   266: dup
/*    */     //   267: astore_1
/*    */     //   268: ifnull -> 314
/*    */     //   271: aload_1
/*    */     //   272: getfield bw : Ljava/lang/String;
/*    */     //   275: dup
/*    */     //   276: astore_1
/*    */     //   277: ifnull -> 314
/*    */     //   280: aload_0
/*    */     //   281: getfield Cv : [Lf/Cs0;
/*    */     //   284: dup
/*    */     //   285: astore_0
/*    */     //   286: ifnull -> 314
/*    */     //   289: aload_0
/*    */     //   290: arraylength
/*    */     //   291: istore_2
/*    */     //   292: iconst_0
/*    */     //   293: istore_3
/*    */     //   294: iload_3
/*    */     //   295: iload_2
/*    */     //   296: if_icmpge -> 314
/*    */     //   299: aload_0
/*    */     //   300: iload_3
/*    */     //   301: aaload
/*    */     //   302: aload_1
/*    */     //   303: invokeinterface G80 : (Ljava/lang/String;)V
/*    */     //   308: iinc #3, 1
/*    */     //   311: goto -> 294
/*    */     //   314: iconst_1
/*    */     //   315: ireturn
/*    */     //   316: iconst_0
/*    */     //   317: ireturn
/*    */     // Line number table:
/*    */     //   Java source line number -> byte code offset
/*    */     //   #1	-> 11
/*    */     //   #2	-> 23
/*    */     //   #3	-> 50
/*    */     //   #4	-> 54
/*    */     //   #5	-> 59
/*    */     //   #6	-> 62
/*    */     //   #7	-> 65
/*    */     //   #8	-> 68
/*    */     //   #9	-> 71
/*    */     //   #10	-> 74
/*    */     //   #11	-> 92
/*    */     //   #12	-> 96
/*    */     //   #13	-> 101
/*    */     //   #14	-> 104
/*    */     //   #15	-> 107
/*    */     //   #16	-> 110
/*    */     //   #17	-> 113
/*    */     //   #18	-> 116
/*    */     //   #19	-> 137
/*    */     //   #20	-> 243
/*    */     //   #21	-> 248
/*    */     //   #22	-> 263
/*    */   }
/*    */   
/*    */   public final Object t2(int paramInt1, int paramInt2) {
/*    */     jT jT1;
/*    */     xc xc;
/*    */     if ((jT1 = this.Zk) != null && xc = jT1.dM instanceof Cp)
/*    */       return ((Cp)xc).EH; 
/*    */     return super.t2(paramInt1, paramInt2);
/*    */   }
/*    */   
/*    */   public final void Ru(boolean paramBoolean) {
/*    */     if (paramBoolean)
/*    */       this.X2 = true; 
/*    */     this.Tv0 = true;
/*    */     this.cj0 = null;
/*    */     MJ0();
/*    */   }
/*    */   
/*    */   public final int Gf(cR paramcR, e00 parame00, int paramInt1, int paramInt2) {
/*    */     pe pe1 = null;
/*    */     Ok ok;
/*    */     if (FJ.Qh((ok = (Ok)(paramcR = paramcR.bw0(parame00)).rI(parame00)).hW)) {
/*    */       if (parame00 == e00.FONT_SIZE && (paramcR = paramcR.g8) == null)
/*    */         return 14; 
/*    */       if ((pe1 = Nz0(paramcR)) == null)
/*    */         return 0; 
/*    */     } 
/*    */     float f = ok.QK0;
/*    */     switch (Zk0.yE(ok.hW)) {
/*    */       case 5:
/*    */         return paramInt2;
/*    */       case 4:
/*    */         f = paramInt1 * 0.01F * f;
/*    */         break;
/*    */       case 3:
/*    */         f *= ((t90)pe1).getEX();
/*    */         break;
/*    */       case 2:
/*    */         f *= ((t90)pe1).getEM();
/*    */         break;
/*    */       case 1:
/*    */         f *= 1.33F;
/*    */         break;
/*    */     } 
/*    */     return (f >= 32767.0F) ? 32767 : ((f <= -32768.0F) ? -32768 : Math.round(f));
/*    */   }
/*    */   
/*    */   public final void t30() {}
/*    */   
/*    */   public final void HK0() {}
/*    */   
/*    */   public final void QK0(aF0 paramaF0) {
/*    */     String str = "player";
/*    */     if (!this.Y3.containsKey(str) && !this.ii0.containsKey(str)) {
/*    */       this.ii0.put(str, paramaF0);
/*    */       return;
/*    */     } 
/*    */     throw new IllegalArgumentException("widget name already in registered");
/*    */   }
/*    */   
/*    */   public final void JM(Ap paramAp, String paramString) {
/*    */     if (paramString != null) {
/*    */       if (paramAp.fr0 == null) {
/*    */         if (!this.Y3.containsKey(paramString) && !this.ii0.containsKey(paramString)) {
/*    */           if (!this.Y3.containsValue(paramAp)) {
/*    */             this.Y3.put(paramString, paramAp);
/*    */             return;
/*    */           } 
/*    */           throw new IllegalArgumentException("widget already registered");
/*    */         } 
/*    */         throw new IllegalArgumentException("widget name already in registered");
/*    */       } 
/*    */       throw new IllegalArgumentException("Widget must not have a parent");
/*    */     } 
/*    */     throw new NullPointerException("name");
/*    */   } }


/* Location:              /Users/vnnsnnt/Documents/Codespace/JavaWorkspace/RedTrainer/src/main/java/org/trainer/client/PokeMMO.jar!/f/f9.class
 * Java compiler version: 8 (52.0)
 * JD-Core Version:       1.1.3
 */