/*  1 */ package f;public final class Fd0 implements ab0 { public final void qm(Qv0 paramQv0, oa0 paramoa0) { gO gO; if (this.qa0 && (gO = this.N70.dk0) != null) { gO
/*  2 */         .class(paramQv0, Collections.emptyList()); return; }  NR nR; (nR = this.cs).getClass();
/*    */ 
/*    */     
/*  5 */     this
/*  6 */       .Hd = paramQv0; int i = 1;
/*    */     
/*  8 */     paramQv0.O
/*  9 */       .gf0(Qv0.MZ, i);
/* 10 */     if (!paramQv0.As.AX() && paramQv0.ZF && this.Hd != null) {
/* 11 */       i = paramoa0.aK;
/*    */       
/*    */       JG0 jG0;
/* 14 */       if (!(jG0 = this.Zw0.Va0(i, paramoa0.gk0) instanceof Qv0)) {
/* 15 */         jG0 = jG0.fr0;
/*    */       }
/*    */       
/* 18 */       Vp((Qv0)jG0); Vp(null); if (!((jG0 instanceof Qv0 && ((Qv0)(jG0 = jG0)).ZF) ? 1 : 0)) {
/* 19 */         int j = paramoa0.aK;
/*    */         
/*    */         JG0 jG01;
/* 22 */         if (!(jG01 = Va0(j, paramoa0.gk0) instanceof Qv0))
/* 23 */           jG01 = jG01.fr0;  if (jG01 instanceof Qv0 && 
/* 24 */           ((Qv0)(jG01 = jG01))
/* 25 */           .ZF)
/* 26 */         { Vp((Qv0)jG01); } else { Vp(null); }
/*    */       
/*    */       } 
/*    */     }  }
/*    */ 
/*    */   
/*    */   public Fd0(NR paramNR, boolean paramBoolean, pA parampA) {}
/*    */   
/*    */   public final void pN(Qv0 paramQv0, oa0 paramoa0) {
/*    */     // Byte code:
/*    */     //   0: aload_0
/*    */     //   1: getfield qa0 : Z
/*    */     //   4: ifeq -> 35
/*    */     //   7: aload_0
/*    */     //   8: getfield N70 : Lf/pA;
/*    */     //   11: getfield dk0 : Lf/gO;
/*    */     //   14: dup
/*    */     //   15: astore_1
/*    */     //   16: ifnull -> 35
/*    */     //   19: aload_1
/*    */     //   20: aload_2
/*    */     //   21: dup
/*    */     //   22: getfield aK : I
/*    */     //   25: istore_0
/*    */     //   26: getfield gk0 : I
/*    */     //   29: iload_0
/*    */     //   30: swap
/*    */     //   31: invokevirtual lf0 : (II)V
/*    */     //   34: return
/*    */     //   35: aload_0
/*    */     //   36: getfield cs : Lf/NR;
/*    */     //   39: dup
/*    */     //   40: astore_0
/*    */     //   41: getfield Hd : Lf/Qv0;
/*    */     //   44: ifnull -> 178
/*    */     //   47: aload_0
/*    */     //   48: getfield Zw0 : Lf/pA;
/*    */     //   51: aload_2
/*    */     //   52: dup
/*    */     //   53: getfield aK : I
/*    */     //   56: istore_1
/*    */     //   57: getfield gk0 : I
/*    */     //   60: iload_1
/*    */     //   61: swap
/*    */     //   62: invokevirtual Va0 : (II)Lf/JG0;
/*    */     //   65: dup
/*    */     //   66: astore_1
/*    */     //   67: instanceof f/Qv0
/*    */     //   70: ifne -> 78
/*    */     //   73: aload_1
/*    */     //   74: getfield fr0 : Lf/JG0;
/*    */     //   77: astore_1
/*    */     //   78: aload_1
/*    */     //   79: instanceof f/Qv0
/*    */     //   82: ifeq -> 106
/*    */     //   85: aload_1
/*    */     //   86: checkcast f/Qv0
/*    */     //   89: dup
/*    */     //   90: astore_1
/*    */     //   91: getfield ZF : Z
/*    */     //   94: ifeq -> 106
/*    */     //   97: aload_0
/*    */     //   98: aload_1
/*    */     //   99: invokevirtual Vp : (Lf/Qv0;)V
/*    */     //   102: iconst_1
/*    */     //   103: goto -> 112
/*    */     //   106: aload_0
/*    */     //   107: aconst_null
/*    */     //   108: invokevirtual Vp : (Lf/Qv0;)V
/*    */     //   111: iconst_0
/*    */     //   112: ifeq -> 118
/*    */     //   115: goto -> 178
/*    */     //   118: aload_0
/*    */     //   119: aload_2
/*    */     //   120: dup
/*    */     //   121: getfield aK : I
/*    */     //   124: istore_1
/*    */     //   125: getfield gk0 : I
/*    */     //   128: iload_1
/*    */     //   129: swap
/*    */     //   130: invokevirtual Va0 : (II)Lf/JG0;
/*    */     //   133: dup
/*    */     //   134: astore_1
/*    */     //   135: instanceof f/Qv0
/*    */     //   138: ifne -> 146
/*    */     //   141: aload_1
/*    */     //   142: getfield fr0 : Lf/JG0;
/*    */     //   145: astore_1
/*    */     //   146: aload_1
/*    */     //   147: instanceof f/Qv0
/*    */     //   150: ifeq -> 173
/*    */     //   153: aload_1
/*    */     //   154: checkcast f/Qv0
/*    */     //   157: dup
/*    */     //   158: astore_1
/*    */     //   159: getfield ZF : Z
/*    */     //   162: ifeq -> 173
/*    */     //   165: aload_0
/*    */     //   166: aload_1
/*    */     //   167: invokevirtual Vp : (Lf/Qv0;)V
/*    */     //   170: goto -> 178
/*    */     //   173: aload_0
/*    */     //   174: aconst_null
/*    */     //   175: invokevirtual Vp : (Lf/Qv0;)V
/*    */     //   178: return
/*    */     // Line number table:
/*    */     //   Java source line number -> byte code offset
/*    */     //   #1	-> 11
/*    */     //   #2	-> 22
/*    */     //   #3	-> 26
/*    */     //   #4	-> 31
/*    */     //   #5	-> 41
/*    */     //   #6	-> 48
/*    */     //   #7	-> 53
/*    */     //   #8	-> 57
/*    */     //   #9	-> 62
/*    */     //   #10	-> 67
/*    */     //   #11	-> 74
/*    */     //   #12	-> 79
/*    */     //   #13	-> 91
/*    */     //   #14	-> 99
/*    */     //   #15	-> 121
/*    */     //   #16	-> 125
/*    */     //   #17	-> 130
/*    */     //   #18	-> 135
/*    */     //   #19	-> 142
/*    */     //   #20	-> 147
/*    */     //   #21	-> 159
/*    */     //   #22	-> 167
/*    */   }
/*    */   
/*    */   public final void Cj0(Qv0 paramQv0, oa0 paramoa0) {
/*    */     // Byte code:
/*    */     //   0: aload_0
/*    */     //   1: getfield qa0 : Z
/*    */     //   4: ifeq -> 35
/*    */     //   7: aload_0
/*    */     //   8: getfield N70 : Lf/pA;
/*    */     //   11: getfield dk0 : Lf/gO;
/*    */     //   14: dup
/*    */     //   15: astore_1
/*    */     //   16: ifnull -> 35
/*    */     //   19: aload_1
/*    */     //   20: aload_2
/*    */     //   21: dup
/*    */     //   22: getfield aK : I
/*    */     //   25: istore_0
/*    */     //   26: getfield gk0 : I
/*    */     //   29: iload_0
/*    */     //   30: swap
/*    */     //   31: invokevirtual wL0 : (II)V
/*    */     //   34: return
/*    */     //   35: aload_0
/*    */     //   36: getfield cs : Lf/NR;
/*    */     //   39: dup
/*    */     //   40: astore_0
/*    */     //   41: getfield Hd : Lf/Qv0;
/*    */     //   44: dup
/*    */     //   45: astore_1
/*    */     //   46: ifnull -> 563
/*    */     //   49: aload_1
/*    */     //   50: getfield ZF : Z
/*    */     //   53: ifeq -> 563
/*    */     //   56: aload_1
/*    */     //   57: ifnull -> 191
/*    */     //   60: aload_0
/*    */     //   61: getfield Zw0 : Lf/pA;
/*    */     //   64: aload_2
/*    */     //   65: dup
/*    */     //   66: getfield aK : I
/*    */     //   69: istore_1
/*    */     //   70: getfield gk0 : I
/*    */     //   73: iload_1
/*    */     //   74: swap
/*    */     //   75: invokevirtual Va0 : (II)Lf/JG0;
/*    */     //   78: dup
/*    */     //   79: astore_1
/*    */     //   80: instanceof f/Qv0
/*    */     //   83: ifne -> 91
/*    */     //   86: aload_1
/*    */     //   87: getfield fr0 : Lf/JG0;
/*    */     //   90: astore_1
/*    */     //   91: aload_1
/*    */     //   92: instanceof f/Qv0
/*    */     //   95: ifeq -> 119
/*    */     //   98: aload_1
/*    */     //   99: checkcast f/Qv0
/*    */     //   102: dup
/*    */     //   103: astore_1
/*    */     //   104: getfield ZF : Z
/*    */     //   107: ifeq -> 119
/*    */     //   110: aload_0
/*    */     //   111: aload_1
/*    */     //   112: invokevirtual Vp : (Lf/Qv0;)V
/*    */     //   115: iconst_1
/*    */     //   116: goto -> 125
/*    */     //   119: aload_0
/*    */     //   120: aconst_null
/*    */     //   121: invokevirtual Vp : (Lf/Qv0;)V
/*    */     //   124: iconst_0
/*    */     //   125: ifeq -> 131
/*    */     //   128: goto -> 191
/*    */     //   131: aload_0
/*    */     //   132: aload_2
/*    */     //   133: dup
/*    */     //   134: getfield aK : I
/*    */     //   137: istore_1
/*    */     //   138: getfield gk0 : I
/*    */     //   141: iload_1
/*    */     //   142: swap
/*    */     //   143: invokevirtual Va0 : (II)Lf/JG0;
/*    */     //   146: dup
/*    */     //   147: astore_1
/*    */     //   148: instanceof f/Qv0
/*    */     //   151: ifne -> 159
/*    */     //   154: aload_1
/*    */     //   155: getfield fr0 : Lf/JG0;
/*    */     //   158: astore_1
/*    */     //   159: aload_1
/*    */     //   160: instanceof f/Qv0
/*    */     //   163: ifeq -> 186
/*    */     //   166: aload_1
/*    */     //   167: checkcast f/Qv0
/*    */     //   170: dup
/*    */     //   171: astore_1
/*    */     //   172: getfield ZF : Z
/*    */     //   175: ifeq -> 186
/*    */     //   178: aload_0
/*    */     //   179: aload_1
/*    */     //   180: invokevirtual Vp : (Lf/Qv0;)V
/*    */     //   183: goto -> 191
/*    */     //   186: aload_0
/*    */     //   187: aconst_null
/*    */     //   188: invokevirtual Vp : (Lf/Qv0;)V
/*    */     //   191: aload_0
/*    */     //   192: getfield k9 : Lf/Qv0;
/*    */     //   195: dup
/*    */     //   196: astore_1
/*    */     //   197: ifnull -> 340
/*    */     //   200: aload_1
/*    */     //   201: aload_0
/*    */     //   202: getfield Hd : Lf/Qv0;
/*    */     //   205: if_acmpeq -> 340
/*    */     //   208: aload_1
/*    */     //   209: getfield ZF : Z
/*    */     //   212: ifeq -> 340
/*    */     //   215: aload_1
/*    */     //   216: invokevirtual y1 : ()Z
/*    */     //   219: ifeq -> 239
/*    */     //   222: aload_0
/*    */     //   223: getfield k9 : Lf/Qv0;
/*    */     //   226: aload_0
/*    */     //   227: getfield Hd : Lf/Qv0;
/*    */     //   230: invokevirtual public : ()Lf/j40;
/*    */     //   233: invokevirtual zf : (Lf/j40;)V
/*    */     //   236: goto -> 563
/*    */     //   239: aload_0
/*    */     //   240: getfield Zw0 : Lf/pA;
/*    */     //   243: getfield cl : Lf/GV;
/*    */     //   246: dup
/*    */     //   247: astore_1
/*    */     //   248: ifnull -> 314
/*    */     //   251: aload_0
/*    */     //   252: getfield k9 : Lf/Qv0;
/*    */     //   255: dup
/*    */     //   256: astore_2
/*    */     //   257: instanceof f/G9
/*    */     //   260: ifeq -> 314
/*    */     //   263: aload_2
/*    */     //   264: aload_1
/*    */     //   265: invokevirtual Ji0 : (Lf/JG0;)Z
/*    */     //   268: ifeq -> 314
/*    */     //   271: aload_1
/*    */     //   272: aload_0
/*    */     //   273: dup
/*    */     //   274: getfield Hd : Lf/Qv0;
/*    */     //   277: invokevirtual public : ()Lf/j40;
/*    */     //   280: astore_2
/*    */     //   281: getfield k9 : Lf/Qv0;
/*    */     //   284: invokevirtual fH0 : ()S
/*    */     //   287: dup
/*    */     //   288: istore_3
/*    */     //   289: iconst_1
/*    */     //   290: aload_2
/*    */     //   291: invokevirtual Cb : (SZLf/j40;)Z
/*    */     //   294: ifeq -> 563
/*    */     //   297: aload_1
/*    */     //   298: dup
/*    */     //   299: getfield TG0 : [Lf/Qv0;
/*    */     //   302: iload_3
/*    */     //   303: aaload
/*    */     //   304: aload_2
/*    */     //   305: invokevirtual zf : (Lf/j40;)V
/*    */     //   308: invokevirtual update : ()V
/*    */     //   311: goto -> 563
/*    */     //   314: getstatic f/km.MR : Lf/Gp0;
/*    */     //   317: ifnonnull -> 563
/*    */     //   320: getstatic f/km.u4 : Lf/R8;
/*    */     //   323: aload_0
/*    */     //   324: dup
/*    */     //   325: getfield Hd : Lf/Qv0;
/*    */     //   328: astore_1
/*    */     //   329: getfield k9 : Lf/Qv0;
/*    */     //   332: aload_1
/*    */     //   333: swap
/*    */     //   334: invokevirtual lO : (Lf/Qv0;Lf/Qv0;)V
/*    */     //   337: goto -> 563
/*    */     //   340: getstatic f/js.vu0 : Lf/js;
/*    */     //   343: aload_2
/*    */     //   344: dup
/*    */     //   345: getfield aK : I
/*    */     //   348: istore_1
/*    */     //   349: getfield gk0 : I
/*    */     //   352: iload_1
/*    */     //   353: swap
/*    */     //   354: invokevirtual Va0 : (II)Lf/JG0;
/*    */     //   357: dup
/*    */     //   358: astore_1
/*    */     //   359: iconst_0
/*    */     //   360: istore_3
/*    */     //   361: ifnull -> 403
/*    */     //   364: aload_0
/*    */     //   365: getfield Zw0 : Lf/pA;
/*    */     //   368: getfield TF : Lf/wu;
/*    */     //   371: dup
/*    */     //   372: astore #4
/*    */     //   374: ifnull -> 403
/*    */     //   377: aload #4
/*    */     //   379: getfield b00 : Lf/of;
/*    */     //   382: aload_1
/*    */     //   383: getfield fr0 : Lf/JG0;
/*    */     //   386: if_acmpne -> 403
/*    */     //   389: aload #4
/*    */     //   391: aload_0
/*    */     //   392: getfield Hd : Lf/Qv0;
/*    */     //   395: invokevirtual public : ()Lf/j40;
/*    */     //   398: invokevirtual Rd0 : (Lf/j40;)V
/*    */     //   401: iconst_1
/*    */     //   402: istore_3
/*    */     //   403: iload_3
/*    */     //   404: ifne -> 505
/*    */     //   407: aload_1
/*    */     //   408: ifnull -> 505
/*    */     //   411: aload_0
/*    */     //   412: aload_1
/*    */     //   413: invokevirtual fG : (Lf/JG0;)Lf/kC0;
/*    */     //   416: dup
/*    */     //   417: astore_1
/*    */     //   418: ifnull -> 505
/*    */     //   421: aload_0
/*    */     //   422: getfield Hd : Lf/Qv0;
/*    */     //   425: invokevirtual public : ()Lf/j40;
/*    */     //   428: dup
/*    */     //   429: astore_3
/*    */     //   430: ifnull -> 503
/*    */     //   433: aload_3
/*    */     //   434: getfield Zs : Lf/Q90;
/*    */     //   437: invokevirtual YC : ()Z
/*    */     //   440: ifeq -> 446
/*    */     //   443: goto -> 503
/*    */     //   446: aload_1
/*    */     //   447: dup
/*    */     //   448: getfield cv0 : Lf/of;
/*    */     //   451: new java/lang/StringBuilder
/*    */     //   454: dup
/*    */     //   455: aload_1
/*    */     //   456: swap
/*    */     //   457: invokespecial <init> : ()V
/*    */     //   460: getfield cv0 : Lf/of;
/*    */     //   463: getfield F2 : Lf/ak0;
/*    */     //   466: invokevirtual toString : ()Ljava/lang/String;
/*    */     //   469: invokevirtual append : (Ljava/lang/String;)Ljava/lang/StringBuilder;
/*    */     //   472: ldc '{M:'
/*    */     //   474: invokevirtual append : (Ljava/lang/String;)Ljava/lang/StringBuilder;
/*    */     //   477: aload_3
/*    */     //   478: getfield Jg : I
/*    */     //   481: invokevirtual append : (I)Ljava/lang/StringBuilder;
/*    */     //   484: ldc '}'
/*    */     //   486: invokevirtual append : (Ljava/lang/String;)Ljava/lang/StringBuilder;
/*    */     //   489: invokevirtual toString : ()Ljava/lang/String;
/*    */     //   492: iconst_0
/*    */     //   493: invokevirtual Be0 : (Ljava/lang/String;Z)V
/*    */     //   496: getfield cv0 : Lf/of;
/*    */     //   499: invokestatic c90 : (Lf/JG0;)Z
/*    */     //   502: pop
/*    */     //   503: iconst_1
/*    */     //   504: istore_3
/*    */     //   505: iload_3
/*    */     //   506: ifne -> 563
/*    */     //   509: aload_0
/*    */     //   510: aload_2
/*    */     //   511: dup
/*    */     //   512: getfield aK : I
/*    */     //   515: istore_1
/*    */     //   516: getfield gk0 : I
/*    */     //   519: iload_1
/*    */     //   520: swap
/*    */     //   521: invokevirtual Va0 : (II)Lf/JG0;
/*    */     //   524: instanceof f/NR
/*    */     //   527: ifeq -> 563
/*    */     //   530: aload_0
/*    */     //   531: getfield Hd : Lf/Qv0;
/*    */     //   534: dup
/*    */     //   535: astore_1
/*    */     //   536: ifnull -> 563
/*    */     //   539: aload_1
/*    */     //   540: invokevirtual public : ()Lf/j40;
/*    */     //   543: ifnull -> 563
/*    */     //   546: getstatic f/km.u4 : Lf/R8;
/*    */     //   549: aload_0
/*    */     //   550: getfield Hd : Lf/Qv0;
/*    */     //   553: invokevirtual public : ()Lf/j40;
/*    */     //   556: getfield Jg : I
/*    */     //   559: iconst_1
/*    */     //   560: invokevirtual bA0 : (IB)V
/*    */     //   563: aload_0
/*    */     //   564: dup
/*    */     //   565: aconst_null
/*    */     //   566: invokevirtual Vp : (Lf/Qv0;)V
/*    */     //   569: getfield Hd : Lf/Qv0;
/*    */     //   572: dup
/*    */     //   573: astore_1
/*    */     //   574: ifnull -> 595
/*    */     //   577: aload_1
/*    */     //   578: dup
/*    */     //   579: iconst_0
/*    */     //   580: dup
/*    */     //   581: istore_1
/*    */     //   582: putfield I20 : Z
/*    */     //   585: getfield O : Lf/Sa0;
/*    */     //   588: getstatic f/Qv0.MZ : Lf/Ll;
/*    */     //   591: iload_1
/*    */     //   592: invokevirtual gf0 : (Lf/Ll;Z)V
/*    */     //   595: aload_0
/*    */     //   596: aconst_null
/*    */     //   597: putfield Hd : Lf/Qv0;
/*    */     //   600: return
/*    */     // Line number table:
/*    */     //   Java source line number -> byte code offset
/*    */     //   #1	-> 11
/*    */     //   #2	-> 22
/*    */     //   #3	-> 26
/*    */     //   #4	-> 31
/*    */     //   #5	-> 41
/*    */     //   #6	-> 50
/*    */     //   #7	-> 61
/*    */     //   #8	-> 66
/*    */     //   #9	-> 70
/*    */     //   #10	-> 75
/*    */     //   #11	-> 80
/*    */     //   #12	-> 87
/*    */     //   #13	-> 92
/*    */     //   #14	-> 104
/*    */     //   #15	-> 112
/*    */     //   #16	-> 134
/*    */     //   #17	-> 138
/*    */     //   #18	-> 143
/*    */     //   #19	-> 148
/*    */     //   #20	-> 155
/*    */     //   #21	-> 160
/*    */     //   #22	-> 172
/*    */     //   #23	-> 180
/*    */     //   #24	-> 192
/*    */     //   #25	-> 209
/*    */     //   #26	-> 216
/*    */     //   #27	-> 243
/*    */     //   #28	-> 252
/*    */     //   #29	-> 291
/*    */     //   #30	-> 314
/*    */     //   #31	-> 340
/*    */     //   #32	-> 345
/*    */     //   #33	-> 349
/*    */     //   #34	-> 354
/*    */     //   #35	-> 368
/*    */     //   #36	-> 379
/*    */     //   #37	-> 383
/*    */     //   #38	-> 392
/*    */     //   #39	-> 434
/*    */     //   #40	-> 448
/*    */     //   #41	-> 463
/*    */     //   #42	-> 466
/*    */     //   #43	-> 469
/*    */     //   #44	-> 478
/*    */     //   #45	-> 481
/*    */     //   #46	-> 493
/*    */     //   #47	-> 496
/*    */     //   #48	-> 512
/*    */     //   #49	-> 516
/*    */     //   #50	-> 521
/*    */     //   #51	-> 556
/*    */     //   #52	-> 560
/*    */     //   #53	-> 582
/*    */     //   #54	-> 585
/*    */     //   #55	-> 588
/*    */     //   #56	-> 597
/*    */   } }


/* Location:              /Users/vnnsnnt/Documents/Codespace/JavaWorkspace/RedTrainer/src/main/java/org/trainer/client/PokeMMO.jar!/f/Fd0.class
 * Java compiler version: 8 (52.0)
 * JD-Core Version:       1.1.3
 */