/*    */ package f;public final class fr extends Qa0 implements r60 { public pA Zu; public final Runnable XM; public final Ip C0; public final Fy0 Aj0; public final Fy0 Np0; public vF0 Iy; public final Q20 ul; public final Q20 Ez; public final dQ Kk; public final dQ zy; public final dQ WB0; public final VP aD; public final Fy0 GL; public final vF0 BY; public final vF0 Vn; public final dQ Ze; public C6 Yf; public sN com1; public int wt; public int Vp0; public int lX; public int CJ; public int tr; public int j8; public int iG; public int Z50; public int Rh; public float PD0; public float aq; public int tg; public int fX; public int rq0; public int J1; public final ArrayList RH0; public final ArrayList n5; public final ArrayList QQ; public boolean F; public int Rt; public int od; public final o10 z40; public boolean xv; public long En; public List mn0; public fr(pA parampA, R2 paramR2) { // Byte code:
/*    */     //   0: aload_0
/*    */     //   1: dup
/*    */     //   2: dup2
/*    */     //   3: dup2
/*    */     //   4: dup2
/*    */     //   5: dup2
/*    */     //   6: dup2
/*    */     //   7: dup2
/*    */     //   8: dup2
/*    */     //   9: dup2
/*    */     //   10: dup2
/*    */     //   11: dup2
/*    */     //   12: dup2
/*    */     //   13: dup2
/*    */     //   14: invokestatic XU : ()Z
/*    */     //   17: invokespecial <init> : (Z)V
/*    */     //   20: aconst_null
/*    */     //   21: putfield Yf : Lf/C6;
/*    */     //   24: aconst_null
/*    */     //   25: putfield com1 : Lf/sN;
/*    */     //   28: iconst_0
/*    */     //   29: putfield wt : I
/*    */     //   32: iconst_0
/*    */     //   33: putfield Vp0 : I
/*    */     //   36: iconst_m1
/*    */     //   37: putfield lX : I
/*    */     //   40: iconst_m1
/*    */     //   41: putfield CJ : I
/*    */     //   44: iconst_0
/*    */     //   45: putfield tr : I
/*    */     //   48: iconst_0
/*    */     //   49: putfield j8 : I
/*    */     //   52: iconst_0
/*    */     //   53: putfield iG : I
/*    */     //   56: iconst_0
/*    */     //   57: putfield Z50 : I
/*    */     //   60: iconst_0
/*    */     //   61: putfield Rh : I
/*    */     //   64: fconst_0
/*    */     //   65: putfield PD0 : F
/*    */     //   68: fconst_0
/*    */     //   69: putfield aq : F
/*    */     //   72: bipush #8
/*    */     //   74: putfield tg : I
/*    */     //   77: iconst_0
/*    */     //   78: putfield fX : I
/*    */     //   81: iconst_0
/*    */     //   82: putfield rq0 : I
/*    */     //   85: bipush #8
/*    */     //   87: putfield J1 : I
/*    */     //   90: new java/util/ArrayList
/*    */     //   93: dup
/*    */     //   94: invokespecial <init> : ()V
/*    */     //   97: putfield RH0 : Ljava/util/ArrayList;
/*    */     //   100: new java/util/ArrayList
/*    */     //   103: dup
/*    */     //   104: invokespecial <init> : ()V
/*    */     //   107: putfield n5 : Ljava/util/ArrayList;
/*    */     //   110: new java/util/ArrayList
/*    */     //   113: dup
/*    */     //   114: invokespecial <init> : ()V
/*    */     //   117: putfield QQ : Ljava/util/ArrayList;
/*    */     //   120: iconst_1
/*    */     //   121: putfield F : Z
/*    */     //   124: iconst_3
/*    */     //   125: putfield Rt : I
/*    */     //   128: iconst_1
/*    */     //   129: putfield od : I
/*    */     //   132: iconst_0
/*    */     //   133: putfield xv : Z
/*    */     //   136: invokestatic currentTimeMillis : ()J
/*    */     //   139: putfield En : J
/*    */     //   142: invokestatic LS : ()B
/*    */     //   145: dup
/*    */     //   146: istore_3
/*    */     //   147: invokestatic n80 : (B)Z
/*    */     //   150: ifeq -> 161
/*    */     //   153: aload_0
/*    */     //   154: iload_3
/*    */     //   155: invokestatic jn0 : (B)Ljava/util/List;
/*    */     //   158: putfield mn0 : Ljava/util/List;
/*    */     //   161: invokestatic XU : ()Z
/*    */     //   164: ifeq -> 172
/*    */     //   167: iconst_4
/*    */     //   168: istore_3
/*    */     //   169: goto -> 174
/*    */     //   172: iconst_3
/*    */     //   173: istore_3
/*    */     //   174: aload_0
/*    */     //   175: dup
/*    */     //   176: dup
/*    */     //   177: dup2
/*    */     //   178: aload_1
/*    */     //   179: aload_0
/*    */     //   180: aload_2
/*    */     //   181: aload_0
/*    */     //   182: aload_1
/*    */     //   183: aload_0
/*    */     //   184: iload_3
/*    */     //   185: aload_0
/*    */     //   186: iload_3
/*    */     //   187: putfield Rt : I
/*    */     //   190: i2f
/*    */     //   191: ldc 0.75
/*    */     //   193: fmul
/*    */     //   194: f2d
/*    */     //   195: invokestatic floor : (D)D
/*    */     //   198: d2i
/*    */     //   199: putfield od : I
/*    */     //   202: putfield Zu : Lf/pA;
/*    */     //   205: putfield XM : Ljava/lang/Runnable;
/*    */     //   208: <illegal opcode> run : (Lf/pA;)Ljava/lang/Runnable;
/*    */     //   213: invokevirtual TG0 : (Ljava/lang/Runnable;)V
/*    */     //   216: new f/I
/*    */     //   219: dup
/*    */     //   220: aload_0
/*    */     //   221: new f/pRn
/*    */     //   224: dup
/*    */     //   225: astore_1
/*    */     //   226: iconst_m1
/*    */     //   227: iconst_m1
/*    */     //   228: iconst_m1
/*    */     //   229: iconst_m1
/*    */     //   230: invokespecial <init> : (BBBB)V
/*    */     //   233: aload_1
/*    */     //   234: invokespecial <init> : (Lf/JG0;Lf/pRn;)V
/*    */     //   237: invokevirtual Vo0 : (Lf/I;)V
/*    */     //   240: ldc 'town-map'
/*    */     //   242: invokevirtual Xu : (Ljava/lang/String;)V
/*    */     //   245: invokestatic b20 : ()Lf/Of;
/*    */     //   248: sipush #5442
/*    */     //   251: invokevirtual On0 : (S)Lf/LPT3;
/*    */     //   254: invokevirtual getName : ()Ljava/lang/String;
/*    */     //   257: invokevirtual Lo : (Ljava/lang/String;)V
/*    */     //   260: new f/Ip
/*    */     //   263: dup
/*    */     //   264: invokespecial <init> : ()V
/*    */     //   267: putfield C0 : Lf/Ip;
/*    */     //   270: new f/VP
/*    */     //   273: dup
/*    */     //   274: astore_1
/*    */     //   275: aload_0
/*    */     //   276: aload_1
/*    */     //   277: aload_0
/*    */     //   278: aload_1
/*    */     //   279: dup
/*    */     //   280: aconst_null
/*    */     //   281: invokespecial <init> : (Lf/Jo;)V
/*    */     //   284: putfield aD : Lf/VP;
/*    */     //   287: iconst_0
/*    */     //   288: invokevirtual wI0 : (Z)V
/*    */     //   291: getfield od : I
/*    */     //   294: invokevirtual yB0 : (I)V
/*    */     //   297: new f/Fy0
/*    */     //   300: dup
/*    */     //   301: dup
/*    */     //   302: astore_2
/*    */     //   303: aload_0
/*    */     //   304: aload_2
/*    */     //   305: dup
/*    */     //   306: aload_0
/*    */     //   307: getfield Rt : I
/*    */     //   310: bipush #12
/*    */     //   312: imul
/*    */     //   313: ldc_w ''
/*    */     //   316: swap
/*    */     //   317: dup
/*    */     //   318: invokespecial <init> : (Ljava/lang/String;II)V
/*    */     //   321: putfield Aj0 : Lf/Fy0;
/*    */     //   324: ldc_w 'townmap-cursor'
/*    */     //   327: invokevirtual Xu : (Ljava/lang/String;)V
/*    */     //   330: iconst_0
/*    */     //   331: invokevirtual Zf0 : (Z)V
/*    */     //   334: invokestatic LS : ()B
/*    */     //   337: iconst_2
/*    */     //   338: if_icmpne -> 422
/*    */     //   341: aload_1
/*    */     //   342: aload_0
/*    */     //   343: aload_2
/*    */     //   344: dup
/*    */     //   345: dup
/*    */     //   346: invokevirtual zY : ()Lf/rH;
/*    */     //   349: iconst_1
/*    */     //   350: anewarray f/U70
/*    */     //   353: dup
/*    */     //   354: getstatic f/km.mI0 : Lf/P1;
/*    */     //   357: getfield AN : Lf/Wo;
/*    */     //   360: getfield Xo : [Lf/U70;
/*    */     //   363: bipush #7
/*    */     //   365: aaload
/*    */     //   366: iconst_0
/*    */     //   367: swap
/*    */     //   368: aastore
/*    */     //   369: invokevirtual qt : ([Lf/U70;)Lf/JG0;
/*    */     //   372: pop
/*    */     //   373: invokevirtual zY : ()Lf/rH;
/*    */     //   376: aload_0
/*    */     //   377: getfield Rt : I
/*    */     //   380: bipush #16
/*    */     //   382: imul
/*    */     //   383: dup
/*    */     //   384: invokevirtual tL : (II)V
/*    */     //   387: invokevirtual zY : ()Lf/rH;
/*    */     //   390: aload_0
/*    */     //   391: getfield Rt : I
/*    */     //   394: bipush #-16
/*    */     //   396: imul
/*    */     //   397: iconst_0
/*    */     //   398: swap
/*    */     //   399: invokevirtual zT : (II)Lf/JG0;
/*    */     //   402: pop
/*    */     //   403: getfield od : I
/*    */     //   406: dup
/*    */     //   407: bipush #-17
/*    */     //   409: imul
/*    */     //   410: istore_1
/*    */     //   411: bipush #-14
/*    */     //   413: imul
/*    */     //   414: iload_1
/*    */     //   415: swap
/*    */     //   416: invokevirtual nx : (II)V
/*    */     //   419: goto -> 648
/*    */     //   422: invokestatic LS : ()B
/*    */     //   425: iconst_3
/*    */     //   426: if_icmpne -> 501
/*    */     //   429: aload_1
/*    */     //   430: aload_0
/*    */     //   431: aload_2
/*    */     //   432: dup
/*    */     //   433: dup2
/*    */     //   434: invokevirtual zY : ()Lf/rH;
/*    */     //   437: getstatic f/km.mI0 : Lf/P1;
/*    */     //   440: getfield MT : Lf/gD;
/*    */     //   443: getfield ls : [Lf/U70;
/*    */     //   446: invokevirtual qt : ([Lf/U70;)Lf/JG0;
/*    */     //   449: pop
/*    */     //   450: invokevirtual zY : ()Lf/rH;
/*    */     //   453: aload_0
/*    */     //   454: getfield Rt : I
/*    */     //   457: i2f
/*    */     //   458: invokevirtual Ii0 : (F)V
/*    */     //   461: invokevirtual zY : ()Lf/rH;
/*    */     //   464: aload_0
/*    */     //   465: getfield Rt : I
/*    */     //   468: bipush #-4
/*    */     //   470: imul
/*    */     //   471: dup
/*    */     //   472: invokevirtual zT : (II)Lf/JG0;
/*    */     //   475: pop
/*    */     //   476: invokevirtual zY : ()Lf/rH;
/*    */     //   479: invokevirtual HY : ()V
/*    */     //   482: getfield od : I
/*    */     //   485: dup
/*    */     //   486: bipush #-23
/*    */     //   488: imul
/*    */     //   489: istore_1
/*    */     //   490: bipush #-22
/*    */     //   492: imul
/*    */     //   493: iload_1
/*    */     //   494: swap
/*    */     //   495: invokevirtual nx : (II)V
/*    */     //   498: goto -> 648
/*    */     //   501: invokestatic LS : ()B
/*    */     //   504: iconst_4
/*    */     //   505: if_icmpne -> 580
/*    */     //   508: aload_1
/*    */     //   509: aload_0
/*    */     //   510: aload_2
/*    */     //   511: dup
/*    */     //   512: dup2
/*    */     //   513: invokevirtual zY : ()Lf/rH;
/*    */     //   516: getstatic f/km.mI0 : Lf/P1;
/*    */     //   519: getfield yE : Lf/BE;
/*    */     //   522: getfield cOm4 : [Lf/U70;
/*    */     //   525: invokevirtual qt : ([Lf/U70;)Lf/JG0;
/*    */     //   528: pop
/*    */     //   529: invokevirtual zY : ()Lf/rH;
/*    */     //   532: aload_0
/*    */     //   533: getfield Rt : I
/*    */     //   536: i2f
/*    */     //   537: invokevirtual Ii0 : (F)V
/*    */     //   540: invokevirtual zY : ()Lf/rH;
/*    */     //   543: aload_0
/*    */     //   544: getfield Rt : I
/*    */     //   547: bipush #-4
/*    */     //   549: imul
/*    */     //   550: dup
/*    */     //   551: invokevirtual zT : (II)Lf/JG0;
/*    */     //   554: pop
/*    */     //   555: invokevirtual zY : ()Lf/rH;
/*    */     //   558: invokevirtual HY : ()V
/*    */     //   561: getfield od : I
/*    */     //   564: dup
/*    */     //   565: bipush #-23
/*    */     //   567: imul
/*    */     //   568: istore_1
/*    */     //   569: bipush #-22
/*    */     //   571: imul
/*    */     //   572: iload_1
/*    */     //   573: swap
/*    */     //   574: invokevirtual nx : (II)V
/*    */     //   577: goto -> 648
/*    */     //   580: aload_1
/*    */     //   581: aload_0
/*    */     //   582: aload_2
/*    */     //   583: dup
/*    */     //   584: dup2
/*    */     //   585: invokevirtual zY : ()Lf/rH;
/*    */     //   588: invokestatic ds0 : ()Lf/NL;
/*    */     //   591: invokevirtual hu0 : ()[Lf/zh0;
/*    */     //   594: invokevirtual sm : ([Lf/zh0;)V
/*    */     //   597: invokevirtual zY : ()Lf/rH;
/*    */     //   600: aload_0
/*    */     //   601: getfield Rt : I
/*    */     //   604: bipush #12
/*    */     //   606: imul
/*    */     //   607: dup
/*    */     //   608: invokevirtual tL : (II)V
/*    */     //   611: invokevirtual zY : ()Lf/rH;
/*    */     //   614: aload_0
/*    */     //   615: getfield Rt : I
/*    */     //   618: bipush #-2
/*    */     //   620: imul
/*    */     //   621: dup
/*    */     //   622: invokevirtual zT : (II)Lf/JG0;
/*    */     //   625: pop
/*    */     //   626: invokevirtual zY : ()Lf/rH;
/*    */     //   629: invokevirtual HY : ()V
/*    */     //   632: getfield od : I
/*    */     //   635: dup
/*    */     //   636: bipush #-23
/*    */     //   638: imul
/*    */     //   639: istore_1
/*    */     //   640: bipush #-21
/*    */     //   642: imul
/*    */     //   643: iload_1
/*    */     //   644: swap
/*    */     //   645: invokevirtual nx : (II)V
/*    */     //   648: aload_2
/*    */     //   649: aload_0
/*    */     //   650: <illegal opcode> run : (Lf/fr;)Ljava/lang/Runnable;
/*    */     //   655: invokevirtual tW : (Ljava/lang/Runnable;)V
/*    */     //   658: bipush #6
/*    */     //   660: anewarray f/U70
/*    */     //   663: astore_1
/*    */     //   664: iconst_0
/*    */     //   665: istore_2
/*    */     //   666: iload_2
/*    */     //   667: bipush #6
/*    */     //   669: if_icmpge -> 695
/*    */     //   672: aload_1
/*    */     //   673: iload_2
/*    */     //   674: getstatic f/km.mI0 : Lf/P1;
/*    */     //   677: getfield AN : Lf/Wo;
/*    */     //   680: getfield Xo : [Lf/U70;
/*    */     //   683: bipush #14
/*    */     //   685: iload_2
/*    */     //   686: isub
/*    */     //   687: aaload
/*    */     //   688: aastore
/*    */     //   689: iinc #2, 1
/*    */     //   692: goto -> 666
/*    */     //   695: aload_0
/*    */     //   696: dup
/*    */     //   697: dup
/*    */     //   698: dup2
/*    */     //   699: new f/Fy0
/*    */     //   702: dup
/*    */     //   703: astore_2
/*    */     //   704: aload_0
/*    */     //   705: aload_2
/*    */     //   706: dup
/*    */     //   707: dup2
/*    */     //   708: dup2
/*    */     //   709: dup2
/*    */     //   710: aload_0
/*    */     //   711: aload_2
/*    */     //   712: dup
/*    */     //   713: ldc_w ''
/*    */     //   716: iconst_0
/*    */     //   717: iconst_0
/*    */     //   718: invokespecial <init> : (Ljava/lang/String;II)V
/*    */     //   721: putfield Np0 : Lf/Fy0;
/*    */     //   724: ldc_w 'townmap-cursor'
/*    */     //   727: invokevirtual Xu : (Ljava/lang/String;)V
/*    */     //   730: iconst_0
/*    */     //   731: invokevirtual Zf0 : (Z)V
/*    */     //   734: invokevirtual zY : ()Lf/rH;
/*    */     //   737: aload_1
/*    */     //   738: invokevirtual qt : ([Lf/U70;)Lf/JG0;
/*    */     //   741: pop
/*    */     //   742: invokevirtual zY : ()Lf/rH;
/*    */     //   745: aload_1
/*    */     //   746: dup
/*    */     //   747: iconst_0
/*    */     //   748: aaload
/*    */     //   749: invokevirtual Zz : ()I
/*    */     //   752: aload_0
/*    */     //   753: getfield Rt : I
/*    */     //   756: imul
/*    */     //   757: istore_1
/*    */     //   758: iconst_0
/*    */     //   759: aaload
/*    */     //   760: invokevirtual eh0 : ()I
/*    */     //   763: aload_0
/*    */     //   764: getfield Rt : I
/*    */     //   767: imul
/*    */     //   768: iload_1
/*    */     //   769: swap
/*    */     //   770: invokevirtual tL : (II)V
/*    */     //   773: invokevirtual zY : ()Lf/rH;
/*    */     //   776: invokevirtual Ef : ()V
/*    */     //   779: invokevirtual zY : ()Lf/rH;
/*    */     //   782: bipush #125
/*    */     //   784: invokevirtual EV : (I)V
/*    */     //   787: invokevirtual zY : ()Lf/rH;
/*    */     //   790: invokevirtual HY : ()V
/*    */     //   793: iconst_0
/*    */     //   794: invokevirtual wI0 : (Z)V
/*    */     //   797: <illegal opcode> run : (Lf/fr;)Ljava/lang/Runnable;
/*    */     //   802: invokevirtual tW : (Ljava/lang/Runnable;)V
/*    */     //   805: new f/Q20
/*    */     //   808: dup
/*    */     //   809: dup2
/*    */     //   810: astore_1
/*    */     //   811: aload_0
/*    */     //   812: dup
/*    */     //   813: dup
/*    */     //   814: aload_1
/*    */     //   815: aload_0
/*    */     //   816: aload_1
/*    */     //   817: dup
/*    */     //   818: iconst_2
/*    */     //   819: invokespecial <init> : (I)V
/*    */     //   822: putfield ul : Lf/Q20;
/*    */     //   825: getstatic f/et.c5 : Lf/et;
/*    */     //   828: dup
/*    */     //   829: astore_1
/*    */     //   830: invokevirtual Ei0 : (Lf/et;)V
/*    */     //   833: new f/dQ
/*    */     //   836: dup
/*    */     //   837: dup
/*    */     //   838: astore_2
/*    */     //   839: ldc_w ''
/*    */     //   842: invokespecial <init> : (Ljava/lang/String;)V
/*    */     //   845: putfield Kk : Lf/dQ;
/*    */     //   848: new f/dQ
/*    */     //   851: dup
/*    */     //   852: dup
/*    */     //   853: astore_3
/*    */     //   854: ldc_w ''
/*    */     //   857: invokespecial <init> : (Ljava/lang/String;)V
/*    */     //   860: putfield zy : Lf/dQ;
/*    */     //   863: new f/dQ
/*    */     //   866: dup
/*    */     //   867: dup
/*    */     //   868: astore #4
/*    */     //   870: ldc_w ''
/*    */     //   873: invokespecial <init> : (Ljava/lang/String;)V
/*    */     //   876: putfield WB0 : Lf/dQ;
/*    */     //   879: aload_2
/*    */     //   880: invokevirtual J8 : (Lf/JG0;)V
/*    */     //   883: aload_3
/*    */     //   884: invokevirtual J8 : (Lf/JG0;)V
/*    */     //   887: aload #4
/*    */     //   889: invokevirtual J8 : (Lf/JG0;)V
/*    */     //   892: new f/Q20
/*    */     //   895: dup
/*    */     //   896: dup
/*    */     //   897: astore_2
/*    */     //   898: aload_0
/*    */     //   899: aload_2
/*    */     //   900: dup
/*    */     //   901: aload_1
/*    */     //   902: aload_0
/*    */     //   903: aload_2
/*    */     //   904: dup
/*    */     //   905: iconst_1
/*    */     //   906: invokespecial <init> : (I)V
/*    */     //   909: putfield Ez : Lf/Q20;
/*    */     //   912: invokevirtual Ei0 : (Lf/et;)V
/*    */     //   915: ldc_w 'townmap-swarm-indicator'
/*    */     //   918: invokevirtual Xu : (Ljava/lang/String;)V
/*    */     //   921: new f/vF0
/*    */     //   924: dup
/*    */     //   925: dup
/*    */     //   926: astore_1
/*    */     //   927: bipush #32
/*    */     //   929: bipush #32
/*    */     //   931: iconst_0
/*    */     //   932: invokespecial <init> : (III)V
/*    */     //   935: putfield Vn : Lf/vF0;
/*    */     //   938: aload_1
/*    */     //   939: dup
/*    */     //   940: invokevirtual ZH0 : ()Lf/rH;
/*    */     //   943: iconst_3
/*    */     //   944: bipush #-5
/*    */     //   946: invokevirtual zT : (II)Lf/JG0;
/*    */     //   949: pop
/*    */     //   950: new f/dQ
/*    */     //   953: dup
/*    */     //   954: astore_1
/*    */     //   955: aload_0
/*    */     //   956: aload_1
/*    */     //   957: dup
/*    */     //   958: ldc_w ''
/*    */     //   961: invokespecial <init> : (Ljava/lang/String;)V
/*    */     //   964: putfield Ze : Lf/dQ;
/*    */     //   967: ldc_w 'townmap-label'
/*    */     //   970: invokevirtual Xu : (Ljava/lang/String;)V
/*    */     //   973: invokevirtual J8 : (Lf/JG0;)V
/*    */     //   976: aload_1
/*    */     //   977: invokevirtual J8 : (Lf/JG0;)V
/*    */     //   980: new f/Fy0
/*    */     //   983: dup
/*    */     //   984: astore_1
/*    */     //   985: aload_0
/*    */     //   986: aload_1
/*    */     //   987: aload_0
/*    */     //   988: aload_1
/*    */     //   989: dup
/*    */     //   990: aload_0
/*    */     //   991: getfield Rt : I
/*    */     //   994: bipush #16
/*    */     //   996: imul
/*    */     //   997: ldc_w ''
/*    */     //   1000: swap
/*    */     //   1001: dup
/*    */     //   1002: invokespecial <init> : (Ljava/lang/String;II)V
/*    */     //   1005: putfield GL : Lf/Fy0;
/*    */     //   1008: ldc_w 'switch-map'
/*    */     //   1011: invokevirtual Xu : (Ljava/lang/String;)V
/*    */     //   1014: <illegal opcode> run : (Lf/fr;)Ljava/lang/Runnable;
/*    */     //   1019: invokevirtual tW : (Ljava/lang/Runnable;)V
/*    */     //   1022: invokestatic lpT7 : ()Lf/JC0;
/*    */     //   1025: invokestatic LS : ()B
/*    */     //   1028: invokevirtual nC0 : (B)Lf/o10;
/*    */     //   1031: putfield z40 : Lf/o10;
/*    */     //   1034: new f/vF0
/*    */     //   1037: dup
/*    */     //   1038: iconst_1
/*    */     //   1039: iconst_1
/*    */     //   1040: iconst_0
/*    */     //   1041: invokespecial <init> : (III)V
/*    */     //   1044: putfield BY : Lf/vF0;
/*    */     //   1047: getfield C0 : Lf/Ip;
/*    */     //   1050: invokevirtual J8 : (Lf/JG0;)V
/*    */     //   1053: invokestatic LS : ()B
/*    */     //   1056: invokestatic d70 : ()I
/*    */     //   1059: swap
/*    */     //   1060: invokevirtual J2 : (IB)V
/*  1 */     //   1063: return } private void vu0() { sN sN1; if ((sN1 = this.com1) != null)
/*    */     {
/*  3 */       hm.Fz0(this.TG0.oh0); }  } private void jq0() { sN sN1; if ((sN1 = this.com1) != null) { hm.Fz0(sN1.TG0.oh0); return; }
/*  4 */      D80(this.Yf); } public static void do0(pA parampA) { parampA.U10(false, null); } public static byte LS() { vh0 vh0; return ((vh0 = km.a3) == null || vh0.Jr0() == null) ? 2 : (km.a3.Jr0()).E10; } public static int d70() { byte b = g5.kD0; WL0 wL0;
/*    */     G5 g5;
/*  6 */     if (LS() == 0 && km.mI0.UG0 != null && (wL0 = Mm0.gt0(Qx.Zg0((g5 = km.a3.Ct.HW).FB, b, g5.vu0))) != null)
/*  7 */       return wL0.A8;  return 0; }
/*    */    public final boolean Com5() {
/*    */     return false;
/*    */   } public final void WQ(sN paramsN) {
/*    */     // Byte code:
/*    */     //   0: aload_1
/*    */     //   1: aload_0
/*    */     //   2: getfield com1 : Lf/sN;
/*    */     //   5: dup
/*    */     //   6: astore_2
/*    */     //   7: if_acmpne -> 11
/*    */     //   10: return
/*    */     //   11: aload_2
/*    */     //   12: aload_0
/*    */     //   13: aload_1
/*    */     //   14: putfield com1 : Lf/sN;
/*    */     //   17: ifnull -> 32
/*    */     //   20: aload_2
/*    */     //   21: dup
/*    */     //   22: getfield As : Lf/rH;
/*    */     //   25: iconst_0
/*    */     //   26: putfield w70 : Z
/*    */     //   29: invokevirtual nB0 : ()V
/*    */     //   32: aload_1
/*    */     //   33: ifnull -> 274
/*    */     //   36: aload_1
/*    */     //   37: getfield bs : Z
/*    */     //   40: ifeq -> 61
/*    */     //   43: aload_1
/*    */     //   44: getfield Pe : Lf/j60;
/*    */     //   47: getfield RE0 : Z
/*    */     //   50: ifeq -> 61
/*    */     //   53: aload_1
/*    */     //   54: getfield As : Lf/rH;
/*    */     //   57: iconst_1
/*    */     //   58: putfield w70 : Z
/*    */     //   61: aload_1
/*    */     //   62: aload_0
/*    */     //   63: aload_1
/*    */     //   64: invokevirtual nB0 : ()V
/*    */     //   67: getfield Np0 : Lf/Fy0;
/*    */     //   70: aload_1
/*    */     //   71: dup
/*    */     //   72: dup
/*    */     //   73: getfield Kd : I
/*    */     //   76: istore_2
/*    */     //   77: getfield xY : I
/*    */     //   80: iconst_2
/*    */     //   81: idiv
/*    */     //   82: iload_2
/*    */     //   83: iadd
/*    */     //   84: istore_2
/*    */     //   85: getfield er0 : I
/*    */     //   88: istore_3
/*    */     //   89: iload_2
/*    */     //   90: aload_1
/*    */     //   91: getfield HC : I
/*    */     //   94: iconst_2
/*    */     //   95: idiv
/*    */     //   96: iload_3
/*    */     //   97: iadd
/*    */     //   98: invokevirtual ME : (II)Z
/*    */     //   101: pop
/*    */     //   102: getfield Pe : Lf/j60;
/*    */     //   105: dup
/*    */     //   106: astore_2
/*    */     //   107: getfield ka : B
/*    */     //   110: dup
/*    */     //   111: istore_3
/*    */     //   112: iconst_2
/*    */     //   113: if_icmpne -> 174
/*    */     //   116: aload_0
/*    */     //   117: dup
/*    */     //   118: dup
/*    */     //   119: aload_2
/*    */     //   120: aload_0
/*    */     //   121: aload_2
/*    */     //   122: getfield p20 : S
/*    */     //   125: putfield lX : I
/*    */     //   128: getfield LK : S
/*    */     //   131: putfield CJ : I
/*    */     //   134: invokevirtual d40 : ()V
/*    */     //   137: getfield Kk : Lf/dQ;
/*    */     //   140: getstatic f/km.mI0 : Lf/P1;
/*    */     //   143: getfield AN : Lf/Wo;
/*    */     //   146: aload_1
/*    */     //   147: getfield Pe : Lf/j60;
/*    */     //   150: getfield bQ : S
/*    */     //   153: istore_2
/*    */     //   154: getfield YP : Lf/TA0;
/*    */     //   157: getfield Z6 : [Lf/Ws0;
/*    */     //   160: iload_2
/*    */     //   161: aaload
/*    */     //   162: checkcast f/gb
/*    */     //   165: invokevirtual getName : ()Ljava/lang/String;
/*    */     //   168: invokevirtual E1 : (Ljava/lang/String;)V
/*    */     //   171: goto -> 284
/*    */     //   174: iload_3
/*    */     //   175: iconst_3
/*    */     //   176: if_icmpne -> 213
/*    */     //   179: aload_0
/*    */     //   180: dup
/*    */     //   181: dup
/*    */     //   182: aload_2
/*    */     //   183: aload_0
/*    */     //   184: aload_2
/*    */     //   185: getfield p20 : S
/*    */     //   188: putfield wt : I
/*    */     //   191: getfield LK : S
/*    */     //   194: putfield Vp0 : I
/*    */     //   197: getfield Kk : Lf/dQ;
/*    */     //   200: aload_2
/*    */     //   201: invokevirtual j00 : ()Ljava/lang/String;
/*    */     //   204: invokevirtual E1 : (Ljava/lang/String;)V
/*    */     //   207: invokevirtual MJ0 : ()V
/*    */     //   210: goto -> 284
/*    */     //   213: iload_3
/*    */     //   214: iconst_4
/*    */     //   215: if_icmpne -> 284
/*    */     //   218: aload_0
/*    */     //   219: dup
/*    */     //   220: dup
/*    */     //   221: aload_2
/*    */     //   222: aload_0
/*    */     //   223: aload_2
/*    */     //   224: getfield p20 : S
/*    */     //   227: putfield wt : I
/*    */     //   230: getfield LK : S
/*    */     //   233: putfield Vp0 : I
/*    */     //   236: getfield Kk : Lf/dQ;
/*    */     //   239: aload_2
/*    */     //   240: getstatic f/km.mI0 : Lf/P1;
/*    */     //   243: getfield yE : Lf/BE;
/*    */     //   246: astore_2
/*    */     //   247: getfield bQ : S
/*    */     //   250: aload_2
/*    */     //   251: getfield qN : Lf/Fg0;
/*    */     //   254: getfield Z6 : [Lf/Ws0;
/*    */     //   257: swap
/*    */     //   258: aaload
/*    */     //   259: checkcast f/iy0
/*    */     //   262: invokevirtual getName : ()Ljava/lang/String;
/*    */     //   265: invokevirtual E1 : (Ljava/lang/String;)V
/*    */     //   268: invokevirtual MJ0 : ()V
/*    */     //   271: goto -> 284
/*    */     //   274: aload_0
/*    */     //   275: getfield Kk : Lf/dQ;
/*    */     //   278: ldc_w ''
/*    */     //   281: invokevirtual E1 : (Ljava/lang/String;)V
/*    */     //   284: invokestatic LS : ()B
/*    */     //   287: iconst_2
/*    */     //   288: if_icmpne -> 312
/*    */     //   291: aload_1
/*    */     //   292: aload_0
/*    */     //   293: getfield Np0 : Lf/Fy0;
/*    */     //   296: astore_1
/*    */     //   297: ifnull -> 305
/*    */     //   300: iconst_1
/*    */     //   301: istore_2
/*    */     //   302: goto -> 307
/*    */     //   305: iconst_0
/*    */     //   306: istore_2
/*    */     //   307: aload_1
/*    */     //   308: iload_2
/*    */     //   309: invokevirtual wI0 : (Z)V
/*    */     //   312: aload_0
/*    */     //   313: invokevirtual k80 : ()V
/*    */     //   316: return
/*    */     // Line number table:
/*    */     //   Java source line number -> byte code offset
/*    */     //   #1	-> 22
/*    */     //   #2	-> 26
/*    */     //   #3	-> 29
/*    */     //   #4	-> 37
/*    */     //   #5	-> 54
/*    */     //   #6	-> 58
/*    */     //   #7	-> 64
/*    */     //   #8	-> 73
/*    */     //   #9	-> 77
/*    */     //   #10	-> 81
/*    */     //   #11	-> 85
/*    */     //   #12	-> 91
/*    */     //   #13	-> 95
/*    */     //   #14	-> 98
/*    */     //   #15	-> 102
/*    */     //   #16	-> 154
/*    */     //   #17	-> 157
/*    */     //   #18	-> 161
/*    */     //   #19	-> 162
/*    */     //   #20	-> 165
/*    */     //   #21	-> 251
/*    */     //   #22	-> 254
/*    */     //   #23	-> 258
/*    */     //   #24	-> 259
/*    */     //   #25	-> 262
/*    */   } public final void IG0() {
/*    */     VA0.c90(this);
/*    */   } public final void LM(throws paramthrows) {
/*    */     super.LM(paramthrows);
/*    */     d40();
/*    */     qB0(et.Wi0);
/*    */     VA0.c90(this);
/*    */   } public final boolean i2(oa0 paramoa0) {
/*    */     // Byte code:
/*    */     //   0: aload_1
/*    */     //   1: getfield cz0 : I
/*    */     //   4: invokestatic Wm0 : (I)Z
/*    */     //   7: ifeq -> 180
/*    */     //   10: aload_1
/*    */     //   11: invokevirtual oO : ()Z
/*    */     //   14: ifeq -> 180
/*    */     //   17: aload_1
/*    */     //   18: getfield GG0 : I
/*    */     //   21: dup
/*    */     //   22: istore_2
/*    */     //   23: getstatic f/BM.bC : Lf/BM;
/*    */     //   26: invokestatic J20 : (ILf/BM;)Z
/*    */     //   29: ifeq -> 117
/*    */     //   32: aload_0
/*    */     //   33: getfield com1 : Lf/sN;
/*    */     //   36: dup
/*    */     //   37: astore_1
/*    */     //   38: ifnull -> 53
/*    */     //   41: aload_1
/*    */     //   42: getfield TG0 : Lf/protected;
/*    */     //   45: getfield oh0 : [Ljava/lang/Runnable;
/*    */     //   48: invokestatic Fz0 : ([Ljava/lang/Runnable;)V
/*    */     //   51: iconst_1
/*    */     //   52: ireturn
/*    */     //   53: aload_0
/*    */     //   54: getfield wt : I
/*    */     //   57: bipush #21
/*    */     //   59: if_icmpne -> 107
/*    */     //   62: aload_0
/*    */     //   63: getfield Vp0 : I
/*    */     //   66: bipush #13
/*    */     //   68: if_icmpne -> 107
/*    */     //   71: invokestatic LS : ()B
/*    */     //   74: ifne -> 107
/*    */     //   77: aload_0
/*    */     //   78: getfield tr : I
/*    */     //   81: iconst_3
/*    */     //   82: if_icmpne -> 90
/*    */     //   85: aload_0
/*    */     //   86: iconst_m1
/*    */     //   87: putfield tr : I
/*    */     //   90: aload_0
/*    */     //   91: dup
/*    */     //   92: invokestatic LS : ()B
/*    */     //   95: istore_0
/*    */     //   96: getfield tr : I
/*    */     //   99: iconst_1
/*    */     //   100: iadd
/*    */     //   101: iload_0
/*    */     //   102: invokevirtual J2 : (IB)V
/*    */     //   105: iconst_1
/*    */     //   106: ireturn
/*    */     //   107: aload_0
/*    */     //   108: dup
/*    */     //   109: getfield Yf : Lf/C6;
/*    */     //   112: invokevirtual D80 : (Lf/C6;)V
/*    */     //   115: iconst_1
/*    */     //   116: ireturn
/*    */     //   117: iload_2
/*    */     //   118: getstatic f/BM.lc : Lf/BM;
/*    */     //   121: invokestatic J20 : (ILf/BM;)Z
/*    */     //   124: ifeq -> 138
/*    */     //   127: aload_0
/*    */     //   128: getfield Zu : Lf/pA;
/*    */     //   131: iconst_0
/*    */     //   132: aconst_null
/*    */     //   133: invokevirtual U10 : (ZLf/R2;)V
/*    */     //   136: iconst_1
/*    */     //   137: ireturn
/*    */     //   138: iload_2
/*    */     //   139: bipush #66
/*    */     //   141: if_icmpne -> 180
/*    */     //   144: invokestatic LS : ()B
/*    */     //   147: ifne -> 180
/*    */     //   150: aload_0
/*    */     //   151: getfield tr : I
/*    */     //   154: iconst_3
/*    */     //   155: if_icmpne -> 163
/*    */     //   158: aload_0
/*    */     //   159: iconst_m1
/*    */     //   160: putfield tr : I
/*    */     //   163: aload_0
/*    */     //   164: dup
/*    */     //   165: invokestatic LS : ()B
/*    */     //   168: istore_0
/*    */     //   169: getfield tr : I
/*    */     //   172: iconst_1
/*    */     //   173: iadd
/*    */     //   174: iload_0
/*    */     //   175: invokevirtual J2 : (IB)V
/*    */     //   178: iconst_1
/*    */     //   179: ireturn
/*    */     //   180: aload_0
/*    */     //   181: aload_1
/*    */     //   182: invokespecial i2 : (Lf/oa0;)Z
/*    */     //   185: ireturn
/*    */     // Line number table:
/*    */     //   Java source line number -> byte code offset
/*    */     //   #1	-> 1
/*    */     //   #2	-> 4
/*    */     //   #3	-> 11
/*    */     //   #4	-> 18
/*    */     //   #5	-> 23
/*    */     //   #6	-> 42
/*    */     //   #7	-> 45
/*    */     //   #8	-> 48
/*    */     //   #9	-> 54
/*    */     //   #10	-> 133
/*    */     //   #11	-> 144
/*    */   } public final void nh(int paramInt1, int paramInt2) {
/*    */     if (paramInt1 == -1 || paramInt2 == -1)
/* 23 */     { this.Kk.E1(Ml0.OH0(7912)); this.zy.E1(""); return; }  if (LS() == 0) { if ((NL.ds0()).il0[this.tr][paramInt2][paramInt1] == 0) { this.Kk.E1(""); } else { this.Kk.E1(Ml0.la(((NL.ds0()).il0[this.tr][paramInt2][paramInt1] & 0xFF) + 140000 - 88, "")); }  if ((NL.ds0()).N30[this.tr][paramInt2][paramInt1] == 0) k80();  this.zy.E1(Ml0.la(((NL.ds0()).N30[this.tr][paramInt2][paramInt1] & 0xFF) + 140000 - 88, "")); } else { if (LS() == 1) { if ((NL.ds0()).Vz[paramInt2][paramInt1] == -1) { this.Kk.E1(""); } else { this.Kk.E1(Ml0.la(((NL.ds0()).Vz[paramInt2][paramInt1] & 0xFF) + 141000, "")); }  } else { if (LS() == 3) { this.zy.E1(""); JG0 jG0; Iterator<JG0> iterator; for (jG0 = null, iterator = this.QQ.iterator(); iterator.hasNext();) { if (jG01 = iterator.next() instanceof sN && (j60 = ((sN)(jG01 = jG01)).Pe).p20 == this.wt && j60.LK == this.Vp0) jG0 = jG01;  }  if (jG0 != null && jG0 != this.com1) { WQ((sN)jG0); this.En = System.currentTimeMillis() + 150L; return; }  } else if (LS() == 4) { this.zy.E1(""); JG0 jG0; Iterator<JG0> iterator; for (jG0 = null, iterator = this.QQ.iterator(); iterator.hasNext();) { if (jG01 = iterator.next() instanceof sN && (j60 = ((sN)(jG01 = jG01)).Pe).mE0 != 0 && j60.p20 == this.wt && j60.LK == this.Vp0) jG0 = jG01;  }  if (jG0 != null && jG0 != this.com1) { WQ((sN)jG0); this.En = System.currentTimeMillis() + 150L; return; }  } else { if (LS() == 2) { this.zy.E1(""); paramInt1 = this.Aj0.Kd; paramInt2 = this.Aj0.er0; double d = 11110.0D; JG0 jG0 = null; for (Iterator<JG0> iterator = this.QQ.iterator(); iterator.hasNext(); ) { JG0 jG01; int i = (jG01 = jG01).Kd; i = jG01.xY / 2 + i; int j = jG01.er0; long l = (i - paramInt1); l *= l; double d1; if (jG01 = iterator.next() instanceof sN && (d1 = Math.sqrt(((jG01.HC / 2 + j - paramInt2) * (jG01.HC / 2 + j - paramInt2) + l))) < d) { d = d1; jG0 = jG01; }  }  if (jG0 != null && d <= (this.Rt * 8) && jG0 != this.com1) { WQ((sN)jG0); this.En = System.currentTimeMillis() + 150L; } else if (d > (this.Rt * 8)) { WQ(null); }  }  return; }  WQ(null); }
/*    */       
/*    */       k80(); }
/*    */   
/*    */   }
/*    */   
/*    */   public final void FW(int paramInt1, int paramInt2) {
/*    */     // Byte code:
/*    */     //   0: iconst_0
/*    */     //   1: istore_3
/*    */     //   2: bipush #21
/*    */     //   4: istore #4
/*    */     //   6: bipush #14
/*    */     //   8: istore #5
/*    */     //   10: invokestatic LS : ()B
/*    */     //   13: iconst_1
/*    */     //   14: if_icmpne -> 30
/*    */     //   17: iconst_0
/*    */     //   18: istore_3
/*    */     //   19: bipush #27
/*    */     //   21: istore #4
/*    */     //   23: bipush #14
/*    */     //   25: istore #5
/*    */     //   27: goto -> 118
/*    */     //   30: invokestatic LS : ()B
/*    */     //   33: iconst_2
/*    */     //   34: if_icmpne -> 57
/*    */     //   37: aload_0
/*    */     //   38: iconst_0
/*    */     //   39: istore_3
/*    */     //   40: getfield J1 : I
/*    */     //   43: dup
/*    */     //   44: bipush #31
/*    */     //   46: imul
/*    */     //   47: istore #4
/*    */     //   49: bipush #21
/*    */     //   51: imul
/*    */     //   52: istore #5
/*    */     //   54: goto -> 118
/*    */     //   57: invokestatic LS : ()B
/*    */     //   60: iconst_3
/*    */     //   61: if_icmpne -> 78
/*    */     //   64: bipush #6
/*    */     //   66: istore_3
/*    */     //   67: bipush #28
/*    */     //   69: istore #4
/*    */     //   71: bipush #28
/*    */     //   73: istore #5
/*    */     //   75: goto -> 118
/*    */     //   78: invokestatic LS : ()B
/*    */     //   81: iconst_4
/*    */     //   82: if_icmpne -> 118
/*    */     //   85: iconst_0
/*    */     //   86: istore_3
/*    */     //   87: getstatic f/km.u4 : Lf/R8;
/*    */     //   90: getfield fF0 : Lf/BF;
/*    */     //   93: iconst_4
/*    */     //   94: sipush #1490
/*    */     //   97: invokevirtual y5 : (BS)Z
/*    */     //   100: ifeq -> 110
/*    */     //   103: bipush #31
/*    */     //   105: istore #4
/*    */     //   107: goto -> 114
/*    */     //   110: bipush #27
/*    */     //   112: istore #4
/*    */     //   114: bipush #19
/*    */     //   116: istore #5
/*    */     //   118: aload_0
/*    */     //   119: getfield lX : I
/*    */     //   122: dup
/*    */     //   123: istore #6
/*    */     //   125: ifle -> 198
/*    */     //   128: iload #6
/*    */     //   130: aload_0
/*    */     //   131: getfield tg : I
/*    */     //   134: iconst_2
/*    */     //   135: idiv
/*    */     //   136: dup
/*    */     //   137: iload_2
/*    */     //   138: swap
/*    */     //   139: iload_1
/*    */     //   140: imul
/*    */     //   141: istore_1
/*    */     //   142: imul
/*    */     //   143: istore_2
/*    */     //   144: iload_1
/*    */     //   145: iadd
/*    */     //   146: dup
/*    */     //   147: istore_1
/*    */     //   148: iload #4
/*    */     //   150: if_icmple -> 154
/*    */     //   153: return
/*    */     //   154: aload_0
/*    */     //   155: getfield CJ : I
/*    */     //   158: iload_2
/*    */     //   159: iadd
/*    */     //   160: dup
/*    */     //   161: istore_2
/*    */     //   162: iload #5
/*    */     //   164: if_icmple -> 168
/*    */     //   167: return
/*    */     //   168: iload_1
/*    */     //   169: ifge -> 173
/*    */     //   172: return
/*    */     //   173: iload_2
/*    */     //   174: iload_3
/*    */     //   175: if_icmpge -> 179
/*    */     //   178: return
/*    */     //   179: aload_0
/*    */     //   180: dup
/*    */     //   181: dup
/*    */     //   182: iload_1
/*    */     //   183: putfield lX : I
/*    */     //   186: iload_2
/*    */     //   187: putfield CJ : I
/*    */     //   190: iload_1
/*    */     //   191: iload_2
/*    */     //   192: invokevirtual nh : (II)V
/*    */     //   195: goto -> 385
/*    */     //   198: aload_0
/*    */     //   199: getfield wt : I
/*    */     //   202: iload_1
/*    */     //   203: iadd
/*    */     //   204: dup
/*    */     //   205: istore_1
/*    */     //   206: iload #4
/*    */     //   208: if_icmple -> 212
/*    */     //   211: return
/*    */     //   212: aload_0
/*    */     //   213: getfield Vp0 : I
/*    */     //   216: iload_2
/*    */     //   217: iadd
/*    */     //   218: dup
/*    */     //   219: istore_2
/*    */     //   220: iload #5
/*    */     //   222: if_icmple -> 226
/*    */     //   225: return
/*    */     //   226: iload_1
/*    */     //   227: ifge -> 231
/*    */     //   230: return
/*    */     //   231: iload_2
/*    */     //   232: iload_3
/*    */     //   233: if_icmpge -> 237
/*    */     //   236: return
/*    */     //   237: aload_0
/*    */     //   238: dup
/*    */     //   239: dup
/*    */     //   240: dup2
/*    */     //   241: dup2
/*    */     //   242: iload_1
/*    */     //   243: putfield wt : I
/*    */     //   246: iload_2
/*    */     //   247: putfield Vp0 : I
/*    */     //   250: iload_1
/*    */     //   251: iload_2
/*    */     //   252: invokevirtual nh : (II)V
/*    */     //   255: getfield tr : I
/*    */     //   258: istore_1
/*    */     //   259: getfield wt : I
/*    */     //   262: istore_2
/*    */     //   263: getfield Vp0 : I
/*    */     //   266: istore_3
/*    */     //   267: getfield mn0 : Ljava/util/List;
/*    */     //   270: dup
/*    */     //   271: astore #4
/*    */     //   273: ifnonnull -> 279
/*    */     //   276: goto -> 376
/*    */     //   279: aload #4
/*    */     //   281: invokeinterface iterator : ()Ljava/util/Iterator;
/*    */     //   286: astore #4
/*    */     //   288: aload #4
/*    */     //   290: invokeinterface hasNext : ()Z
/*    */     //   295: ifeq -> 376
/*    */     //   298: aload #4
/*    */     //   300: invokeinterface next : ()Ljava/lang/Object;
/*    */     //   305: checkcast f/C6
/*    */     //   308: dup
/*    */     //   309: astore #5
/*    */     //   311: getfield co : B
/*    */     //   314: invokestatic LS : ()B
/*    */     //   317: if_icmpne -> 288
/*    */     //   320: aload #5
/*    */     //   322: getfield cV : I
/*    */     //   325: iload_1
/*    */     //   326: if_icmpne -> 288
/*    */     //   329: aload #5
/*    */     //   331: getfield ci : S
/*    */     //   334: iload_2
/*    */     //   335: if_icmpne -> 288
/*    */     //   338: aload #5
/*    */     //   340: getfield MG : S
/*    */     //   343: iload_3
/*    */     //   344: if_icmpne -> 288
/*    */     //   347: getstatic f/km.u4 : Lf/R8;
/*    */     //   350: getfield fF0 : Lf/BF;
/*    */     //   353: aload #5
/*    */     //   355: dup
/*    */     //   356: getfield co : B
/*    */     //   359: istore #6
/*    */     //   361: getfield NZ : S
/*    */     //   364: iload #6
/*    */     //   366: swap
/*    */     //   367: invokevirtual y5 : (BS)Z
/*    */     //   370: ifeq -> 288
/*    */     //   373: goto -> 379
/*    */     //   376: aconst_null
/*    */     //   377: astore #5
/*    */     //   379: aload_0
/*    */     //   380: aload #5
/*    */     //   382: putfield Yf : Lf/C6;
/*    */     //   385: aload_0
/*    */     //   386: invokevirtual MJ0 : ()V
/*    */     //   389: invokestatic currentTimeMillis : ()J
/*    */     //   392: lstore_1
/*    */     //   393: invokestatic LS : ()B
/*    */     //   396: iconst_2
/*    */     //   397: if_icmpne -> 405
/*    */     //   400: bipush #50
/*    */     //   402: goto -> 407
/*    */     //   405: bipush #100
/*    */     //   407: i2l
/*    */     //   408: lstore_3
/*    */     //   409: aload_0
/*    */     //   410: lload_1
/*    */     //   411: lload_3
/*    */     //   412: ladd
/*    */     //   413: putfield En : J
/*    */     //   416: return
/*    */     // Line number table:
/*    */     //   Java source line number -> byte code offset
/*    */     //   #1	-> 90
/*    */     //   #2	-> 97
/*    */     //   #3	-> 267
/*    */     //   #4	-> 350
/*    */     //   #5	-> 356
/*    */     //   #6	-> 382
/*    */   }
/*    */   
/*    */   public final void V90(throws paramthrows) {
/*    */     if (p3()) {
/*    */       boolean bool = true;
/*    */       JP jP;
/*    */       if (System.currentTimeMillis() >= this.En && (jP = km.Lpt1) != null) {
/*    */         if (jP.bn0(BM.M8))
/*    */           FW(bool, 0); 
/*    */         if (km.Lpt1.bn0(BM.Oq))
/*    */           FW(-1, 0); 
/*    */         if (km.Lpt1.bn0(BM.ni))
/*    */           FW(0, -1); 
/*    */         if (km.Lpt1.bn0(BM.N70))
/*    */           FW(0, bool); 
/*    */       } 
/*    */     } 
/*    */     if (this.z40 != null) {
/*    */       Ll ll;
/*    */       this.BY.O.gf0(ll = Ap.b00, true);
/*    */       this.Vn.O.gf0(ll, true);
/*    */     } 
/*    */     super.V90(paramthrows);
/*    */   }
/*    */   
/*    */   public final void d40() {
/*    */     // Byte code:
/*    */     //   0: invokestatic XU : ()Z
/*    */     //   3: ifeq -> 20
/*    */     //   6: aload_0
/*    */     //   7: getfield Bo0 : Lf/throws;
/*    */     //   10: ifnull -> 58
/*    */     //   13: aload_0
/*    */     //   14: invokevirtual QI : ()V
/*    */     //   17: goto -> 58
/*    */     //   20: aload_0
/*    */     //   21: dup
/*    */     //   22: dup
/*    */     //   23: getfield Iy : Lf/vF0;
/*    */     //   26: getfield xY : I
/*    */     //   29: istore_1
/*    */     //   30: getfield C0 : Lf/Ip;
/*    */     //   33: invokevirtual Ho : ()I
/*    */     //   36: iload_1
/*    */     //   37: iadd
/*    */     //   38: aload_0
/*    */     //   39: dup
/*    */     //   40: getfield Iy : Lf/vF0;
/*    */     //   43: getfield HC : I
/*    */     //   46: istore_1
/*    */     //   47: getfield C0 : Lf/Ip;
/*    */     //   50: invokevirtual Et : ()I
/*    */     //   53: iload_1
/*    */     //   54: iadd
/*    */     //   55: invokevirtual yN : (II)V
/*    */     //   58: aload_0
/*    */     //   59: getfield lX : I
/*    */     //   62: ifle -> 112
/*    */     //   65: aload_0
/*    */     //   66: dup
/*    */     //   67: dup
/*    */     //   68: dup2
/*    */     //   69: getfield Aj0 : Lf/Fy0;
/*    */     //   72: astore_1
/*    */     //   73: getfield C0 : Lf/Ip;
/*    */     //   76: invokevirtual RS : ()I
/*    */     //   79: istore_2
/*    */     //   80: getfield lX : I
/*    */     //   83: aload_0
/*    */     //   84: getfield Rt : I
/*    */     //   87: imul
/*    */     //   88: iload_2
/*    */     //   89: iadd
/*    */     //   90: istore_2
/*    */     //   91: getfield C0 : Lf/Ip;
/*    */     //   94: invokevirtual e3 : ()I
/*    */     //   97: istore_3
/*    */     //   98: getfield CJ : I
/*    */     //   101: aload_0
/*    */     //   102: getfield Rt : I
/*    */     //   105: imul
/*    */     //   106: iload_3
/*    */     //   107: iadd
/*    */     //   108: istore_3
/*    */     //   109: goto -> 166
/*    */     //   112: aload_0
/*    */     //   113: dup
/*    */     //   114: dup
/*    */     //   115: dup2
/*    */     //   116: getfield Aj0 : Lf/Fy0;
/*    */     //   119: astore_1
/*    */     //   120: getfield C0 : Lf/Ip;
/*    */     //   123: invokevirtual RS : ()I
/*    */     //   126: istore_2
/*    */     //   127: getfield wt : I
/*    */     //   130: aload_0
/*    */     //   131: getfield J1 : I
/*    */     //   134: imul
/*    */     //   135: iload_2
/*    */     //   136: iadd
/*    */     //   137: aload_0
/*    */     //   138: getfield fX : I
/*    */     //   141: iadd
/*    */     //   142: istore_2
/*    */     //   143: getfield C0 : Lf/Ip;
/*    */     //   146: invokevirtual e3 : ()I
/*    */     //   149: istore_3
/*    */     //   150: getfield Vp0 : I
/*    */     //   153: aload_0
/*    */     //   154: getfield J1 : I
/*    */     //   157: imul
/*    */     //   158: iload_3
/*    */     //   159: iadd
/*    */     //   160: aload_0
/*    */     //   161: getfield rq0 : I
/*    */     //   164: iadd
/*    */     //   165: istore_3
/*    */     //   166: aload_0
/*    */     //   167: dup
/*    */     //   168: aload_1
/*    */     //   169: iload_2
/*    */     //   170: iload_3
/*    */     //   171: invokevirtual ME : (II)Z
/*    */     //   174: pop
/*    */     //   175: getfield aD : Lf/VP;
/*    */     //   178: aload_0
/*    */     //   179: dup
/*    */     //   180: getfield C0 : Lf/Ip;
/*    */     //   183: invokevirtual RS : ()I
/*    */     //   186: istore_1
/*    */     //   187: getfield j8 : I
/*    */     //   190: aload_0
/*    */     //   191: getfield J1 : I
/*    */     //   194: imul
/*    */     //   195: iload_1
/*    */     //   196: iadd
/*    */     //   197: aload_0
/*    */     //   198: getfield fX : I
/*    */     //   201: iadd
/*    */     //   202: aload_0
/*    */     //   203: dup
/*    */     //   204: getfield C0 : Lf/Ip;
/*    */     //   207: invokevirtual e3 : ()I
/*    */     //   210: istore_1
/*    */     //   211: getfield iG : I
/*    */     //   214: aload_0
/*    */     //   215: getfield J1 : I
/*    */     //   218: imul
/*    */     //   219: iload_1
/*    */     //   220: iadd
/*    */     //   221: aload_0
/*    */     //   222: getfield rq0 : I
/*    */     //   225: iadd
/*    */     //   226: invokevirtual ME : (II)Z
/*    */     //   229: pop
/*    */     //   230: getfield BY : Lf/vF0;
/*    */     //   233: getfield TS : Lf/rH;
/*    */     //   236: invokevirtual AX : ()Z
/*    */     //   239: ifne -> 298
/*    */     //   242: aload_0
/*    */     //   243: getfield BY : Lf/vF0;
/*    */     //   246: aload_0
/*    */     //   247: dup
/*    */     //   248: getfield C0 : Lf/Ip;
/*    */     //   251: invokevirtual RS : ()I
/*    */     //   254: istore_1
/*    */     //   255: getfield Z50 : I
/*    */     //   258: aload_0
/*    */     //   259: getfield J1 : I
/*    */     //   262: imul
/*    */     //   263: iload_1
/*    */     //   264: iadd
/*    */     //   265: aload_0
/*    */     //   266: getfield fX : I
/*    */     //   269: iadd
/*    */     //   270: aload_0
/*    */     //   271: dup
/*    */     //   272: getfield C0 : Lf/Ip;
/*    */     //   275: invokevirtual e3 : ()I
/*    */     //   278: istore_1
/*    */     //   279: getfield Rh : I
/*    */     //   282: aload_0
/*    */     //   283: getfield J1 : I
/*    */     //   286: imul
/*    */     //   287: iload_1
/*    */     //   288: iadd
/*    */     //   289: aload_0
/*    */     //   290: getfield rq0 : I
/*    */     //   293: iadd
/*    */     //   294: invokevirtual ME : (II)Z
/*    */     //   297: pop
/*    */     //   298: invokestatic LS : ()B
/*    */     //   301: ifne -> 359
/*    */     //   304: aload_0
/*    */     //   305: dup
/*    */     //   306: dup
/*    */     //   307: getfield ul : Lf/Q20;
/*    */     //   310: astore_1
/*    */     //   311: getfield C0 : Lf/Ip;
/*    */     //   314: invokevirtual RS : ()I
/*    */     //   317: bipush #22
/*    */     //   319: iadd
/*    */     //   320: istore_2
/*    */     //   321: getfield C0 : Lf/Ip;
/*    */     //   324: invokevirtual e3 : ()I
/*    */     //   327: istore_3
/*    */     //   328: invokestatic XU : ()Z
/*    */     //   331: ifeq -> 341
/*    */     //   334: bipush #45
/*    */     //   336: istore #4
/*    */     //   338: goto -> 345
/*    */     //   341: bipush #30
/*    */     //   343: istore #4
/*    */     //   345: aload_1
/*    */     //   346: iload_3
/*    */     //   347: iload #4
/*    */     //   349: iadd
/*    */     //   350: iload_2
/*    */     //   351: swap
/*    */     //   352: invokevirtual ME : (II)Z
/*    */     //   355: pop
/*    */     //   356: goto -> 521
/*    */     //   359: invokestatic LS : ()B
/*    */     //   362: iconst_3
/*    */     //   363: if_icmpne -> 415
/*    */     //   366: aload_0
/*    */     //   367: dup
/*    */     //   368: getfield ul : Lf/Q20;
/*    */     //   371: astore_1
/*    */     //   372: getfield C0 : Lf/Ip;
/*    */     //   375: invokevirtual RS : ()I
/*    */     //   378: istore_2
/*    */     //   379: invokestatic XU : ()Z
/*    */     //   382: ifeq -> 391
/*    */     //   385: bipush #110
/*    */     //   387: istore_3
/*    */     //   388: goto -> 394
/*    */     //   391: bipush #80
/*    */     //   393: istore_3
/*    */     //   394: aload_0
/*    */     //   395: iload_2
/*    */     //   396: iload_3
/*    */     //   397: iadd
/*    */     //   398: istore_2
/*    */     //   399: getfield C0 : Lf/Ip;
/*    */     //   402: invokevirtual e3 : ()I
/*    */     //   405: istore_3
/*    */     //   406: invokestatic XU : ()Z
/*    */     //   409: ifeq -> 503
/*    */     //   412: goto -> 452
/*    */     //   415: invokestatic LS : ()B
/*    */     //   418: iconst_2
/*    */     //   419: if_icmpne -> 466
/*    */     //   422: aload_0
/*    */     //   423: dup
/*    */     //   424: dup
/*    */     //   425: getfield ul : Lf/Q20;
/*    */     //   428: astore_1
/*    */     //   429: getfield C0 : Lf/Ip;
/*    */     //   432: invokevirtual RS : ()I
/*    */     //   435: bipush #22
/*    */     //   437: iadd
/*    */     //   438: istore_2
/*    */     //   439: getfield C0 : Lf/Ip;
/*    */     //   442: invokevirtual e3 : ()I
/*    */     //   445: istore_3
/*    */     //   446: invokestatic XU : ()Z
/*    */     //   449: ifeq -> 459
/*    */     //   452: bipush #12
/*    */     //   454: istore #4
/*    */     //   456: goto -> 506
/*    */     //   459: bipush #8
/*    */     //   461: istore #4
/*    */     //   463: goto -> 506
/*    */     //   466: aload_0
/*    */     //   467: dup
/*    */     //   468: dup
/*    */     //   469: getfield ul : Lf/Q20;
/*    */     //   472: astore_1
/*    */     //   473: getfield C0 : Lf/Ip;
/*    */     //   476: invokevirtual RS : ()I
/*    */     //   479: bipush #22
/*    */     //   481: iadd
/*    */     //   482: istore_2
/*    */     //   483: getfield C0 : Lf/Ip;
/*    */     //   486: invokevirtual e3 : ()I
/*    */     //   489: istore_3
/*    */     //   490: invokestatic XU : ()Z
/*    */     //   493: ifeq -> 503
/*    */     //   496: bipush #7
/*    */     //   498: istore #4
/*    */     //   500: goto -> 506
/*    */     //   503: iconst_4
/*    */     //   504: istore #4
/*    */     //   506: aload_1
/*    */     //   507: iload_2
/*    */     //   508: iload #4
/*    */     //   510: aload_0
/*    */     //   511: getfield Rt : I
/*    */     //   514: imul
/*    */     //   515: iload_3
/*    */     //   516: iadd
/*    */     //   517: invokevirtual ME : (II)Z
/*    */     //   520: pop
/*    */     //   521: invokestatic Nr : ()Z
/*    */     //   524: ifeq -> 549
/*    */     //   527: aload_0
/*    */     //   528: getfield Ez : Lf/Q20;
/*    */     //   531: aload_0
/*    */     //   532: getfield C0 : Lf/Ip;
/*    */     //   535: invokevirtual RS : ()I
/*    */     //   538: aload_0
/*    */     //   539: getfield C0 : Lf/Ip;
/*    */     //   542: invokevirtual yR : ()I
/*    */     //   545: invokevirtual ME : (II)Z
/*    */     //   548: pop
/*    */     //   549: aload_0
/*    */     //   550: dup
/*    */     //   551: getfield GL : Lf/Fy0;
/*    */     //   554: aload_0
/*    */     //   555: getfield C0 : Lf/Ip;
/*    */     //   558: invokevirtual RS : ()I
/*    */     //   561: aload_0
/*    */     //   562: getfield Rt : I
/*    */     //   565: i2f
/*    */     //   566: ldc_w 172.0
/*    */     //   569: fmul
/*    */     //   570: f2i
/*    */     //   571: iadd
/*    */     //   572: aload_0
/*    */     //   573: getfield C0 : Lf/Ip;
/*    */     //   576: invokevirtual e3 : ()I
/*    */     //   579: aload_0
/*    */     //   580: getfield Rt : I
/*    */     //   583: i2f
/*    */     //   584: ldc_w 116.0
/*    */     //   587: fmul
/*    */     //   588: f2i
/*    */     //   589: iadd
/*    */     //   590: invokevirtual ME : (II)Z
/*    */     //   593: pop
/*    */     //   594: invokespecial d40 : ()V
/*    */     //   597: invokestatic XU : ()Z
/*    */     //   600: ifeq -> 644
/*    */     //   603: aload_0
/*    */     //   604: dup
/*    */     //   605: getfield C0 : Lf/Ip;
/*    */     //   608: aload_0
/*    */     //   609: getfield Iy : Lf/vF0;
/*    */     //   612: dup
/*    */     //   613: getfield xY : I
/*    */     //   616: istore_1
/*    */     //   617: getfield HC : I
/*    */     //   620: iload_1
/*    */     //   621: swap
/*    */     //   622: invokevirtual Tm : (II)Z
/*    */     //   625: pop
/*    */     //   626: getfield C0 : Lf/Ip;
/*    */     //   629: aload_0
/*    */     //   630: getstatic f/et.kL0 : Lf/et;
/*    */     //   633: astore_0
/*    */     //   634: getfield X20 : S
/*    */     //   637: istore_1
/*    */     //   638: aload_0
/*    */     //   639: iconst_0
/*    */     //   640: iload_1
/*    */     //   641: invokevirtual QJ0 : (Lf/et;II)V
/*    */     //   644: return
/*    */     // Line number table:
/*    */     //   Java source line number -> byte code offset
/*    */     //   #1	-> 7
/*    */     //   #2	-> 14
/*    */     //   #3	-> 26
/*    */     //   #4	-> 30
/*    */     //   #5	-> 43
/*    */     //   #6	-> 47
/*    */     //   #7	-> 171
/*    */     //   #8	-> 175
/*    */     //   #9	-> 226
/*    */     //   #10	-> 230
/*    */     //   #11	-> 233
/*    */     //   #12	-> 236
/*    */     //   #13	-> 294
/*    */     //   #14	-> 298
/*    */     //   #15	-> 352
/*    */     //   #16	-> 359
/*    */     //   #17	-> 517
/*    */     //   #18	-> 521
/*    */     //   #19	-> 545
/*    */     //   #20	-> 551
/*    */     //   #21	-> 590
/*    */     //   #22	-> 594
/*    */     //   #23	-> 613
/*    */     //   #24	-> 617
/*    */     //   #25	-> 622
/*    */     //   #26	-> 634
/*    */     //   #27	-> 641
/*    */   }
/*    */   
/*    */   public final void D80(C6 paramC6) {
/*    */     // Byte code:
/*    */     //   0: aload_1
/*    */     //   1: ifnull -> 106
/*    */     //   4: aload_0
/*    */     //   5: getfield F : Z
/*    */     //   8: ifeq -> 106
/*    */     //   11: aload_1
/*    */     //   12: aload_0
/*    */     //   13: getfield Yf : Lf/C6;
/*    */     //   16: if_acmpeq -> 24
/*    */     //   19: iconst_1
/*    */     //   20: istore_2
/*    */     //   21: goto -> 26
/*    */     //   24: iconst_0
/*    */     //   25: istore_2
/*    */     //   26: aload_0
/*    */     //   27: aload_1
/*    */     //   28: putfield Yf : Lf/C6;
/*    */     //   31: invokestatic XU : ()Z
/*    */     //   34: ifeq -> 72
/*    */     //   37: iload_2
/*    */     //   38: ifeq -> 72
/*    */     //   41: aload_0
/*    */     //   42: dup
/*    */     //   43: dup
/*    */     //   44: getfield Yf : Lf/C6;
/*    */     //   47: dup
/*    */     //   48: aload_0
/*    */     //   49: swap
/*    */     //   50: getfield ci : S
/*    */     //   53: dup
/*    */     //   54: istore_0
/*    */     //   55: putfield wt : I
/*    */     //   58: getfield MG : S
/*    */     //   61: dup
/*    */     //   62: istore_1
/*    */     //   63: putfield Vp0 : I
/*    */     //   66: iload_0
/*    */     //   67: iload_1
/*    */     //   68: invokevirtual nh : (II)V
/*    */     //   71: return
/*    */     //   72: aload_0
/*    */     //   73: getstatic f/km.u4 : Lf/R8;
/*    */     //   76: aload_0
/*    */     //   77: getfield Yf : Lf/C6;
/*    */     //   80: getfield ie : B
/*    */     //   83: istore_0
/*    */     //   84: getfield e20 : Lf/c4;
/*    */     //   87: new f/pK0
/*    */     //   90: dup
/*    */     //   91: iload_0
/*    */     //   92: invokespecial <init> : (B)V
/*    */     //   95: invokevirtual W3 : (Lf/Bi;)V
/*    */     //   98: getfield Zu : Lf/pA;
/*    */     //   101: iconst_0
/*    */     //   102: aconst_null
/*    */     //   103: invokevirtual U10 : (ZLf/R2;)V
/*    */     //   106: return
/*    */     // Line number table:
/*    */     //   Java source line number -> byte code offset
/*    */     //   #1	-> 84
/*    */     //   #2	-> 87
/*    */     //   #3	-> 98
/*    */     //   #4	-> 103
/*    */   }
/*    */   
/*    */   public final void J2(int paramInt, byte paramByte) {
/*    */     // Byte code:
/*    */     //   0: iconst_0
/*    */     //   1: istore_3
/*    */     //   2: getstatic f/km.u4 : Lf/R8;
/*    */     //   5: getstatic f/aq0.LI : Lf/aq0;
/*    */     //   8: invokevirtual s40 : (Lf/aq0;)Lf/Uc0;
/*    */     //   11: invokevirtual lPt3 : ()[Lf/j40;
/*    */     //   14: dup
/*    */     //   15: astore #4
/*    */     //   17: arraylength
/*    */     //   18: istore #5
/*    */     //   20: iconst_0
/*    */     //   21: istore #6
/*    */     //   23: iload #6
/*    */     //   25: iload #5
/*    */     //   27: if_icmpge -> 73
/*    */     //   30: aload #4
/*    */     //   32: iload #6
/*    */     //   34: aaload
/*    */     //   35: dup
/*    */     //   36: astore #7
/*    */     //   38: ifnull -> 67
/*    */     //   41: aload #7
/*    */     //   43: getfield Zs : Lf/Q90;
/*    */     //   46: invokevirtual YC : ()Z
/*    */     //   49: ifne -> 67
/*    */     //   52: aload #7
/*    */     //   54: getfield Zs : Lf/Q90;
/*    */     //   57: bipush #19
/*    */     //   59: invokevirtual Xj : (S)Z
/*    */     //   62: ifeq -> 67
/*    */     //   65: iconst_1
/*    */     //   66: istore_3
/*    */     //   67: iinc #6, 1
/*    */     //   70: goto -> 23
/*    */     //   73: getstatic f/km.u4 : Lf/R8;
/*    */     //   76: getstatic f/yM.r4 : Lf/yM;
/*    */     //   79: pop
/*    */     //   80: getfield Fe : [Lf/zr0;
/*    */     //   83: iconst_1
/*    */     //   84: aaload
/*    */     //   85: iconst_m1
/*    */     //   86: sipush #1181
/*    */     //   89: iconst_1
/*    */     //   90: invokevirtual vH0 : (BSS)Z
/*    */     //   93: ifeq -> 98
/*    */     //   96: iconst_1
/*    */     //   97: istore_3
/*    */     //   98: invokestatic LS : ()B
/*    */     //   101: tableswitch default -> 136, 0 -> 215, 1 -> 196, 2 -> 177, 3 -> 158, 4 -> 139
/*    */     //   136: goto -> 233
/*    */     //   139: getstatic f/km.u4 : Lf/R8;
/*    */     //   142: getfield fF0 : Lf/BF;
/*    */     //   145: iconst_4
/*    */     //   146: sipush #1365
/*    */     //   149: invokevirtual y5 : (BS)Z
/*    */     //   152: ifne -> 233
/*    */     //   155: goto -> 231
/*    */     //   158: getstatic f/km.u4 : Lf/R8;
/*    */     //   161: getfield fF0 : Lf/BF;
/*    */     //   164: iconst_3
/*    */     //   165: sipush #1363
/*    */     //   168: invokevirtual y5 : (BS)Z
/*    */     //   171: ifne -> 233
/*    */     //   174: goto -> 231
/*    */     //   177: getstatic f/km.u4 : Lf/R8;
/*    */     //   180: getfield fF0 : Lf/BF;
/*    */     //   183: iconst_2
/*    */     //   184: sipush #1525
/*    */     //   187: invokevirtual y5 : (BS)Z
/*    */     //   190: ifne -> 233
/*    */     //   193: goto -> 231
/*    */     //   196: getstatic f/km.u4 : Lf/R8;
/*    */     //   199: getfield fF0 : Lf/BF;
/*    */     //   202: iconst_1
/*    */     //   203: sipush #2156
/*    */     //   206: invokevirtual y5 : (BS)Z
/*    */     //   209: ifne -> 233
/*    */     //   212: goto -> 231
/*    */     //   215: getstatic f/km.u4 : Lf/R8;
/*    */     //   218: getfield fF0 : Lf/BF;
/*    */     //   221: iconst_0
/*    */     //   222: sipush #2082
/*    */     //   225: invokevirtual y5 : (BS)Z
/*    */     //   228: ifne -> 233
/*    */     //   231: iconst_0
/*    */     //   232: istore_3
/*    */     //   233: iload_1
/*    */     //   234: aload_0
/*    */     //   235: iload_3
/*    */     //   236: putfield F : Z
/*    */     //   239: iflt -> 4237
/*    */     //   242: iload_2
/*    */     //   243: ifne -> 260
/*    */     //   246: iload_1
/*    */     //   247: invokestatic ds0 : ()Lf/NL;
/*    */     //   250: getfield il0 : [[[B
/*    */     //   253: arraylength
/*    */     //   254: if_icmplt -> 260
/*    */     //   257: goto -> 4237
/*    */     //   260: iload_2
/*    */     //   261: aload_0
/*    */     //   262: dup
/*    */     //   263: fconst_0
/*    */     //   264: putfield PD0 : F
/*    */     //   267: fconst_0
/*    */     //   268: putfield aq : F
/*    */     //   271: iconst_1
/*    */     //   272: if_icmpeq -> 279
/*    */     //   275: iload_2
/*    */     //   276: ifne -> 293
/*    */     //   279: aload_0
/*    */     //   280: dup
/*    */     //   281: ldc_w 8.0
/*    */     //   284: putfield PD0 : F
/*    */     //   287: ldc_w 16.0
/*    */     //   290: putfield aq : F
/*    */     //   293: iload_2
/*    */     //   294: aload_0
/*    */     //   295: iload_1
/*    */     //   296: aload_0
/*    */     //   297: dup
/*    */     //   298: dup2
/*    */     //   299: getfield C0 : Lf/Ip;
/*    */     //   302: invokevirtual gx : ()V
/*    */     //   305: getfield QQ : Ljava/util/ArrayList;
/*    */     //   308: invokevirtual clear : ()V
/*    */     //   311: getfield RH0 : Ljava/util/ArrayList;
/*    */     //   314: invokevirtual clear : ()V
/*    */     //   317: getfield n5 : Ljava/util/ArrayList;
/*    */     //   320: invokevirtual clear : ()V
/*    */     //   323: putfield tr : I
/*    */     //   326: iconst_1
/*    */     //   327: if_icmpne -> 367
/*    */     //   330: invokestatic ds0 : ()Lf/NL;
/*    */     //   333: getfield s5 : Lf/U70;
/*    */     //   336: dup
/*    */     //   337: astore_3
/*    */     //   338: invokevirtual getClass : ()Ljava/lang/Class;
/*    */     //   341: pop
/*    */     //   342: new f/aF
/*    */     //   345: dup
/*    */     //   346: dup
/*    */     //   347: astore #4
/*    */     //   349: aload_3
/*    */     //   350: invokespecial <init> : (Lf/U70;)V
/*    */     //   353: iconst_0
/*    */     //   354: iconst_0
/*    */     //   355: sipush #256
/*    */     //   358: sipush #160
/*    */     //   361: invokevirtual Y9 : (IIII)V
/*    */     //   364: goto -> 579
/*    */     //   367: iload_2
/*    */     //   368: ifne -> 415
/*    */     //   371: invokestatic ds0 : ()Lf/NL;
/*    */     //   374: getfield TO : [Lf/U70;
/*    */     //   377: aload_0
/*    */     //   378: getfield tr : I
/*    */     //   381: aaload
/*    */     //   382: dup
/*    */     //   383: astore_3
/*    */     //   384: invokevirtual getClass : ()Ljava/lang/Class;
/*    */     //   387: pop
/*    */     //   388: new f/aF
/*    */     //   391: dup
/*    */     //   392: dup
/*    */     //   393: astore #4
/*    */     //   395: aload_3
/*    */     //   396: invokespecial <init> : (Lf/U70;)V
/*    */     //   399: bipush #24
/*    */     //   401: bipush #16
/*    */     //   403: sipush #192
/*    */     //   406: sipush #144
/*    */     //   409: invokevirtual Y9 : (IIII)V
/*    */     //   412: goto -> 579
/*    */     //   415: iload_2
/*    */     //   416: iconst_3
/*    */     //   417: if_icmpne -> 468
/*    */     //   420: aload_0
/*    */     //   421: dup
/*    */     //   422: dup
/*    */     //   423: getstatic f/km.mI0 : Lf/P1;
/*    */     //   426: getfield MT : Lf/gD;
/*    */     //   429: getfield wU : Lf/U70;
/*    */     //   432: dup
/*    */     //   433: astore_3
/*    */     //   434: invokevirtual getClass : ()Ljava/lang/Class;
/*    */     //   437: pop
/*    */     //   438: new f/aF
/*    */     //   441: dup
/*    */     //   442: astore #4
/*    */     //   444: aload_3
/*    */     //   445: invokespecial <init> : (Lf/U70;)V
/*    */     //   448: ldc_w 21.0
/*    */     //   451: putfield PD0 : F
/*    */     //   454: ldc_w -39.0
/*    */     //   457: putfield aq : F
/*    */     //   460: bipush #7
/*    */     //   462: putfield tg : I
/*    */     //   465: goto -> 579
/*    */     //   468: iload_2
/*    */     //   469: iconst_4
/*    */     //   470: if_icmpne -> 554
/*    */     //   473: getstatic f/km.mI0 : Lf/P1;
/*    */     //   476: getfield yE : Lf/BE;
/*    */     //   479: getfield pm0 : Lf/U70;
/*    */     //   482: astore_3
/*    */     //   483: new f/zh0
/*    */     //   486: astore #4
/*    */     //   488: iconst_0
/*    */     //   489: istore #5
/*    */     //   491: iconst_0
/*    */     //   492: istore #6
/*    */     //   494: getstatic f/km.u4 : Lf/R8;
/*    */     //   497: getfield fF0 : Lf/BF;
/*    */     //   500: iconst_4
/*    */     //   501: sipush #1490
/*    */     //   504: invokevirtual y5 : (BS)Z
/*    */     //   507: ifeq -> 518
/*    */     //   510: sipush #256
/*    */     //   513: istore #7
/*    */     //   515: goto -> 523
/*    */     //   518: sipush #224
/*    */     //   521: istore #7
/*    */     //   523: aload #4
/*    */     //   525: aload_3
/*    */     //   526: iload #5
/*    */     //   528: iload #6
/*    */     //   530: iload #7
/*    */     //   532: sipush #160
/*    */     //   535: invokespecial <init> : (Lf/U70;IIII)V
/*    */     //   538: new f/aF
/*    */     //   541: dup
/*    */     //   542: astore_3
/*    */     //   543: aload #4
/*    */     //   545: invokespecial <init> : (Lf/zh0;)V
/*    */     //   548: aload_3
/*    */     //   549: astore #4
/*    */     //   551: goto -> 579
/*    */     //   554: getstatic f/km.mI0 : Lf/P1;
/*    */     //   557: getfield AN : Lf/Wo;
/*    */     //   560: getfield oP : Lf/U70;
/*    */     //   563: dup
/*    */     //   564: astore_3
/*    */     //   565: invokevirtual getClass : ()Ljava/lang/Class;
/*    */     //   568: pop
/*    */     //   569: new f/aF
/*    */     //   572: dup
/*    */     //   573: astore #4
/*    */     //   575: aload_3
/*    */     //   576: invokespecial <init> : (Lf/U70;)V
/*    */     //   579: aload_0
/*    */     //   580: dup
/*    */     //   581: dup2
/*    */     //   582: dup2
/*    */     //   583: dup2
/*    */     //   584: dup2
/*    */     //   585: dup2
/*    */     //   586: dup2
/*    */     //   587: getfield tg : I
/*    */     //   590: aload_0
/*    */     //   591: getfield Rt : I
/*    */     //   594: dup
/*    */     //   595: istore_3
/*    */     //   596: imul
/*    */     //   597: putfield J1 : I
/*    */     //   600: getfield PD0 : F
/*    */     //   603: iload_3
/*    */     //   604: i2f
/*    */     //   605: dup
/*    */     //   606: fstore_3
/*    */     //   607: fmul
/*    */     //   608: f2i
/*    */     //   609: putfield fX : I
/*    */     //   612: getfield aq : F
/*    */     //   615: fload_3
/*    */     //   616: fmul
/*    */     //   617: f2i
/*    */     //   618: putfield rq0 : I
/*    */     //   621: new f/vF0
/*    */     //   624: dup
/*    */     //   625: dup
/*    */     //   626: astore_3
/*    */     //   627: aload #4
/*    */     //   629: getfield H0 : I
/*    */     //   632: aload_0
/*    */     //   633: getfield Rt : I
/*    */     //   636: dup
/*    */     //   637: istore #5
/*    */     //   639: imul
/*    */     //   640: aload #4
/*    */     //   642: getfield Vn0 : I
/*    */     //   645: iload #5
/*    */     //   647: imul
/*    */     //   648: iconst_0
/*    */     //   649: invokespecial <init> : (III)V
/*    */     //   652: putfield Iy : Lf/vF0;
/*    */     //   655: aload_3
/*    */     //   656: getfield TS : Lf/rH;
/*    */     //   659: iconst_1
/*    */     //   660: anewarray f/pe0
/*    */     //   663: dup
/*    */     //   664: iconst_0
/*    */     //   665: aload #4
/*    */     //   667: aastore
/*    */     //   668: invokevirtual Pn : ([Lf/pe0;)Lf/JG0;
/*    */     //   671: pop
/*    */     //   672: getfield Iy : Lf/vF0;
/*    */     //   675: getfield TS : Lf/rH;
/*    */     //   678: iconst_0
/*    */     //   679: iconst_0
/*    */     //   680: invokevirtual zT : (II)Lf/JG0;
/*    */     //   683: pop
/*    */     //   684: getfield Iy : Lf/vF0;
/*    */     //   687: getfield TS : Lf/rH;
/*    */     //   690: aload #4
/*    */     //   692: getfield H0 : I
/*    */     //   695: aload_0
/*    */     //   696: getfield Rt : I
/*    */     //   699: dup
/*    */     //   700: istore_3
/*    */     //   701: imul
/*    */     //   702: aload #4
/*    */     //   704: getfield Vn0 : I
/*    */     //   707: iload_3
/*    */     //   708: imul
/*    */     //   709: invokevirtual tL : (II)V
/*    */     //   712: getfield C0 : Lf/Ip;
/*    */     //   715: dup
/*    */     //   716: aload_0
/*    */     //   717: getfield Iy : Lf/vF0;
/*    */     //   720: astore_3
/*    */     //   721: invokevirtual Ub : ()I
/*    */     //   724: aload_3
/*    */     //   725: swap
/*    */     //   726: invokevirtual si : (Lf/JG0;I)V
/*    */     //   729: getfield Rt : I
/*    */     //   732: dup
/*    */     //   733: aload_0
/*    */     //   734: swap
/*    */     //   735: bipush #16
/*    */     //   737: imul
/*    */     //   738: putfield j8 : I
/*    */     //   741: bipush #24
/*    */     //   743: imul
/*    */     //   744: putfield iG : I
/*    */     //   747: getfield aD : Lf/VP;
/*    */     //   750: iconst_0
/*    */     //   751: invokevirtual wI0 : (Z)V
/*    */     //   754: iconst_0
/*    */     //   755: istore_3
/*    */     //   756: iconst_0
/*    */     //   757: istore #4
/*    */     //   759: getfield z40 : Lf/o10;
/*    */     //   762: dup
/*    */     //   763: astore #5
/*    */     //   765: ifnull -> 940
/*    */     //   768: aload #5
/*    */     //   770: getfield kT : Z
/*    */     //   773: ifeq -> 841
/*    */     //   776: aload #5
/*    */     //   778: getfield GS : S
/*    */     //   781: dup
/*    */     //   782: istore #5
/*    */     //   784: ifle -> 810
/*    */     //   787: aload_0
/*    */     //   788: getfield BY : Lf/vF0;
/*    */     //   791: getfield TS : Lf/rH;
/*    */     //   794: getstatic f/um0.Kt0 : Lf/um0;
/*    */     //   797: iload #5
/*    */     //   799: iconst_1
/*    */     //   800: iconst_m1
/*    */     //   801: invokevirtual lb : (SZB)[Lf/zh0;
/*    */     //   804: invokevirtual sm : ([Lf/zh0;)V
/*    */     //   807: goto -> 864
/*    */     //   810: aload_0
/*    */     //   811: getfield BY : Lf/vF0;
/*    */     //   814: getfield TS : Lf/rH;
/*    */     //   817: iconst_1
/*    */     //   818: anewarray f/pe0
/*    */     //   821: dup
/*    */     //   822: invokestatic ZZ : ()Lf/interface;
/*    */     //   825: getfield i00 : Lf/pe0;
/*    */     //   828: iconst_0
/*    */     //   829: swap
/*    */     //   830: aastore
/*    */     //   831: invokevirtual Pn : ([Lf/pe0;)Lf/JG0;
/*    */     //   834: pop
/*    */     //   835: iconst_1
/*    */     //   836: istore #4
/*    */     //   838: goto -> 864
/*    */     //   841: aload_0
/*    */     //   842: getfield BY : Lf/vF0;
/*    */     //   845: getfield TS : Lf/rH;
/*    */     //   848: getstatic f/um0.Kt0 : Lf/um0;
/*    */     //   851: aload #5
/*    */     //   853: getfield GS : S
/*    */     //   856: iconst_0
/*    */     //   857: iconst_m1
/*    */     //   858: invokevirtual lb : (SZB)[Lf/zh0;
/*    */     //   861: invokevirtual sm : ([Lf/zh0;)V
/*    */     //   864: iload #4
/*    */     //   866: aload_0
/*    */     //   867: getfield BY : Lf/vF0;
/*    */     //   870: getfield TS : Lf/rH;
/*    */     //   873: dup
/*    */     //   874: astore #4
/*    */     //   876: fconst_2
/*    */     //   877: putfield V1 : F
/*    */     //   880: ifeq -> 896
/*    */     //   883: aload #4
/*    */     //   885: bipush #-10
/*    */     //   887: bipush #-16
/*    */     //   889: invokevirtual zT : (II)Lf/JG0;
/*    */     //   892: pop
/*    */     //   893: goto -> 958
/*    */     //   896: aload_0
/*    */     //   897: getfield z40 : Lf/o10;
/*    */     //   900: getfield RB : Lf/Ws0;
/*    */     //   903: ifnull -> 910
/*    */     //   906: iconst_1
/*    */     //   907: goto -> 911
/*    */     //   910: iconst_0
/*    */     //   911: ifeq -> 927
/*    */     //   914: aload #4
/*    */     //   916: bipush #-18
/*    */     //   918: bipush #-30
/*    */     //   920: invokevirtual zT : (II)Lf/JG0;
/*    */     //   923: pop
/*    */     //   924: goto -> 958
/*    */     //   927: aload #4
/*    */     //   929: bipush #-22
/*    */     //   931: bipush #-32
/*    */     //   933: invokevirtual zT : (II)Lf/JG0;
/*    */     //   936: pop
/*    */     //   937: goto -> 958
/*    */     //   940: aload_0
/*    */     //   941: dup
/*    */     //   942: getfield BY : Lf/vF0;
/*    */     //   945: getfield TS : Lf/rH;
/*    */     //   948: invokevirtual H : ()V
/*    */     //   951: getfield BY : Lf/vF0;
/*    */     //   954: iconst_0
/*    */     //   955: invokevirtual wI0 : (Z)V
/*    */     //   958: iload_2
/*    */     //   959: ifne -> 1522
/*    */     //   962: aload_0
/*    */     //   963: getfield C0 : Lf/Ip;
/*    */     //   966: dup
/*    */     //   967: aload_0
/*    */     //   968: getfield GL : Lf/Fy0;
/*    */     //   971: astore #4
/*    */     //   973: invokevirtual Ub : ()I
/*    */     //   976: aload #4
/*    */     //   978: swap
/*    */     //   979: invokevirtual si : (Lf/JG0;I)V
/*    */     //   982: iconst_0
/*    */     //   983: istore #4
/*    */     //   985: iload #4
/*    */     //   987: bipush #22
/*    */     //   989: if_icmpge -> 1249
/*    */     //   992: iconst_0
/*    */     //   993: istore #5
/*    */     //   995: iload #5
/*    */     //   997: bipush #15
/*    */     //   999: if_icmpge -> 1243
/*    */     //   1002: invokestatic ds0 : ()Lf/NL;
/*    */     //   1005: getfield N30 : [[[B
/*    */     //   1008: aload_0
/*    */     //   1009: getfield tr : I
/*    */     //   1012: aaload
/*    */     //   1013: iload #5
/*    */     //   1015: aaload
/*    */     //   1016: iload #4
/*    */     //   1018: baload
/*    */     //   1019: ifeq -> 1237
/*    */     //   1022: aload_0
/*    */     //   1023: iconst_0
/*    */     //   1024: istore #6
/*    */     //   1026: getfield mn0 : Ljava/util/List;
/*    */     //   1029: invokeinterface iterator : ()Ljava/util/Iterator;
/*    */     //   1034: astore #7
/*    */     //   1036: aload #7
/*    */     //   1038: invokeinterface hasNext : ()Z
/*    */     //   1043: ifeq -> 1080
/*    */     //   1046: aload #7
/*    */     //   1048: invokeinterface next : ()Ljava/lang/Object;
/*    */     //   1053: checkcast f/C6
/*    */     //   1056: dup
/*    */     //   1057: astore #8
/*    */     //   1059: getfield ci : S
/*    */     //   1062: iload #4
/*    */     //   1064: if_icmpne -> 1036
/*    */     //   1067: aload #8
/*    */     //   1069: getfield MG : S
/*    */     //   1072: iload #5
/*    */     //   1074: if_icmpne -> 1036
/*    */     //   1077: iconst_1
/*    */     //   1078: istore #6
/*    */     //   1080: iload #6
/*    */     //   1082: new f/Fy0
/*    */     //   1085: dup
/*    */     //   1086: dup2
/*    */     //   1087: astore #7
/*    */     //   1089: aload_0
/*    */     //   1090: getfield Rt : I
/*    */     //   1093: bipush #8
/*    */     //   1095: imul
/*    */     //   1096: ldc_w ''
/*    */     //   1099: swap
/*    */     //   1100: dup
/*    */     //   1101: invokespecial <init> : (Ljava/lang/String;II)V
/*    */     //   1104: getfield As : Lf/rH;
/*    */     //   1107: iconst_1
/*    */     //   1108: anewarray f/U70
/*    */     //   1111: dup
/*    */     //   1112: invokestatic ds0 : ()Lf/NL;
/*    */     //   1115: getfield qa : Lf/U70;
/*    */     //   1118: iconst_0
/*    */     //   1119: swap
/*    */     //   1120: aastore
/*    */     //   1121: invokevirtual qt : ([Lf/U70;)Lf/JG0;
/*    */     //   1124: pop
/*    */     //   1125: getfield As : Lf/rH;
/*    */     //   1128: astore #8
/*    */     //   1130: ifeq -> 1140
/*    */     //   1133: bipush #7
/*    */     //   1135: istore #9
/*    */     //   1137: goto -> 1143
/*    */     //   1140: iconst_0
/*    */     //   1141: istore #9
/*    */     //   1143: iload #6
/*    */     //   1145: ifeq -> 1155
/*    */     //   1148: bipush #7
/*    */     //   1150: istore #6
/*    */     //   1152: goto -> 1158
/*    */     //   1155: iconst_0
/*    */     //   1156: istore #6
/*    */     //   1158: aload_0
/*    */     //   1159: aload #7
/*    */     //   1161: iload #5
/*    */     //   1163: iload #4
/*    */     //   1165: aload_0
/*    */     //   1166: aload #7
/*    */     //   1168: dup
/*    */     //   1169: aload #8
/*    */     //   1171: iload #9
/*    */     //   1173: iload #6
/*    */     //   1175: invokevirtual zT : (II)Lf/JG0;
/*    */     //   1178: pop
/*    */     //   1179: getfield As : Lf/rH;
/*    */     //   1182: aload_0
/*    */     //   1183: getfield Rt : I
/*    */     //   1186: bipush #8
/*    */     //   1188: imul
/*    */     //   1189: dup
/*    */     //   1190: invokevirtual tL : (II)V
/*    */     //   1193: ldc_w 'townmap-cursor'
/*    */     //   1196: invokevirtual Xu : (Ljava/lang/String;)V
/*    */     //   1199: getfield J1 : I
/*    */     //   1202: dup
/*    */     //   1203: istore #6
/*    */     //   1205: imul
/*    */     //   1206: aload_0
/*    */     //   1207: getfield fX : I
/*    */     //   1210: iadd
/*    */     //   1211: istore #8
/*    */     //   1213: iload #6
/*    */     //   1215: imul
/*    */     //   1216: aload_0
/*    */     //   1217: getfield rq0 : I
/*    */     //   1220: iadd
/*    */     //   1221: iload #8
/*    */     //   1223: swap
/*    */     //   1224: invokevirtual ME : (II)Z
/*    */     //   1227: pop
/*    */     //   1228: getfield RH0 : Ljava/util/ArrayList;
/*    */     //   1231: aload #7
/*    */     //   1233: invokevirtual add : (Ljava/lang/Object;)Z
/*    */     //   1236: pop
/*    */     //   1237: iinc #5, 1
/*    */     //   1240: goto -> 995
/*    */     //   1243: iinc #4, 1
/*    */     //   1246: goto -> 985
/*    */     //   1249: getstatic f/km.a3 : Lf/vh0;
/*    */     //   1252: getfield Ct : Lf/Jo;
/*    */     //   1255: getfield HW : Lf/G5;
/*    */     //   1258: dup
/*    */     //   1259: astore #4
/*    */     //   1261: getfield FB : B
/*    */     //   1264: aload #4
/*    */     //   1266: dup
/*    */     //   1267: getfield kD0 : B
/*    */     //   1270: istore #5
/*    */     //   1272: getfield vu0 : B
/*    */     //   1275: iload #5
/*    */     //   1277: swap
/*    */     //   1278: invokestatic Zg0 : (BBB)I
/*    */     //   1281: invokestatic gt0 : (I)Lf/WL0;
/*    */     //   1284: dup
/*    */     //   1285: astore #5
/*    */     //   1287: iconst_m1
/*    */     //   1288: istore #6
/*    */     //   1290: iconst_m1
/*    */     //   1291: istore #7
/*    */     //   1293: getstatic f/Mm0.i7 : Lf/WL0;
/*    */     //   1296: dup
/*    */     //   1297: astore #8
/*    */     //   1299: if_acmpeq -> 1410
/*    */     //   1302: aload #5
/*    */     //   1304: getfield A8 : B
/*    */     //   1307: iload_1
/*    */     //   1308: if_icmpne -> 1410
/*    */     //   1311: aload #5
/*    */     //   1313: aload_0
/*    */     //   1314: dup
/*    */     //   1315: dup
/*    */     //   1316: dup2
/*    */     //   1317: aload #5
/*    */     //   1319: aload #4
/*    */     //   1321: aload #5
/*    */     //   1323: aload #4
/*    */     //   1325: dup
/*    */     //   1326: getfield mm : S
/*    */     //   1329: istore #4
/*    */     //   1331: getfield Yu0 : S
/*    */     //   1334: iload #4
/*    */     //   1336: swap
/*    */     //   1337: getstatic f/km.a3 : Lf/vh0;
/*    */     //   1340: getfield rK : I
/*    */     //   1343: invokevirtual z30 : (III)B
/*    */     //   1346: istore #6
/*    */     //   1348: getfield Yu0 : S
/*    */     //   1351: getstatic f/km.a3 : Lf/vh0;
/*    */     //   1354: getfield rK : I
/*    */     //   1357: invokevirtual tL : (II)B
/*    */     //   1360: istore #7
/*    */     //   1362: iload #6
/*    */     //   1364: putfield wt : I
/*    */     //   1367: iload #7
/*    */     //   1369: putfield Vp0 : I
/*    */     //   1372: iload #6
/*    */     //   1374: putfield j8 : I
/*    */     //   1377: iload #7
/*    */     //   1379: putfield iG : I
/*    */     //   1382: getfield aD : Lf/VP;
/*    */     //   1385: astore #4
/*    */     //   1387: getfield A8 : B
/*    */     //   1390: iload_1
/*    */     //   1391: if_icmpne -> 1400
/*    */     //   1394: iconst_1
/*    */     //   1395: istore #9
/*    */     //   1397: goto -> 1403
/*    */     //   1400: iconst_0
/*    */     //   1401: istore #9
/*    */     //   1403: aload #4
/*    */     //   1405: iload #9
/*    */     //   1407: invokevirtual wI0 : (Z)V
/*    */     //   1410: aload_0
/*    */     //   1411: getfield z40 : Lf/o10;
/*    */     //   1414: dup
/*    */     //   1415: astore #4
/*    */     //   1417: ifnull -> 1511
/*    */     //   1420: aload #5
/*    */     //   1422: aload #8
/*    */     //   1424: aload #4
/*    */     //   1426: getfield hn : B
/*    */     //   1429: aload #4
/*    */     //   1431: dup
/*    */     //   1432: getfield vw0 : B
/*    */     //   1435: istore #4
/*    */     //   1437: getfield m3 : B
/*    */     //   1440: iload #4
/*    */     //   1442: swap
/*    */     //   1443: invokestatic Zg0 : (BBB)I
/*    */     //   1446: invokestatic gt0 : (I)Lf/WL0;
/*    */     //   1449: astore #4
/*    */     //   1451: if_acmpeq -> 1511
/*    */     //   1454: aload #4
/*    */     //   1456: getfield A8 : B
/*    */     //   1459: iload_1
/*    */     //   1460: if_icmpne -> 1511
/*    */     //   1463: aload_0
/*    */     //   1464: aload #4
/*    */     //   1466: aload_0
/*    */     //   1467: dup
/*    */     //   1468: aload #4
/*    */     //   1470: aload_0
/*    */     //   1471: getfield z40 : Lf/o10;
/*    */     //   1474: dup
/*    */     //   1475: getfield lPT1 : S
/*    */     //   1478: istore_3
/*    */     //   1479: getfield wH : S
/*    */     //   1482: iload_3
/*    */     //   1483: swap
/*    */     //   1484: iconst_m1
/*    */     //   1485: invokevirtual z30 : (III)B
/*    */     //   1488: putfield Z50 : I
/*    */     //   1491: getfield z40 : Lf/o10;
/*    */     //   1494: dup
/*    */     //   1495: getfield lPT1 : S
/*    */     //   1498: pop
/*    */     //   1499: getfield wH : S
/*    */     //   1502: iconst_m1
/*    */     //   1503: invokevirtual tL : (II)B
/*    */     //   1506: putfield Rh : I
/*    */     //   1509: iconst_1
/*    */     //   1510: istore_3
/*    */     //   1511: aload_0
/*    */     //   1512: iload #6
/*    */     //   1514: iload #7
/*    */     //   1516: invokevirtual nh : (II)V
/*    */     //   1519: goto -> 3463
/*    */     //   1522: iload_2
/*    */     //   1523: iconst_1
/*    */     //   1524: if_icmpne -> 1759
/*    */     //   1527: getstatic f/km.a3 : Lf/vh0;
/*    */     //   1530: getfield Ct : Lf/Jo;
/*    */     //   1533: getfield HW : Lf/G5;
/*    */     //   1536: dup
/*    */     //   1537: astore #4
/*    */     //   1539: getfield FB : B
/*    */     //   1542: aload #4
/*    */     //   1544: dup
/*    */     //   1545: getfield kD0 : B
/*    */     //   1548: istore #5
/*    */     //   1550: getfield vu0 : B
/*    */     //   1553: iload #5
/*    */     //   1555: swap
/*    */     //   1556: invokestatic Zg0 : (BBB)I
/*    */     //   1559: invokestatic gt0 : (I)Lf/WL0;
/*    */     //   1562: dup
/*    */     //   1563: astore #5
/*    */     //   1565: iconst_m1
/*    */     //   1566: istore #6
/*    */     //   1568: iconst_m1
/*    */     //   1569: istore #7
/*    */     //   1571: getstatic f/Mm0.i7 : Lf/WL0;
/*    */     //   1574: dup
/*    */     //   1575: astore #8
/*    */     //   1577: if_acmpeq -> 1656
/*    */     //   1580: aload_0
/*    */     //   1581: dup
/*    */     //   1582: dup
/*    */     //   1583: dup2
/*    */     //   1584: aload #5
/*    */     //   1586: aload #4
/*    */     //   1588: aload #5
/*    */     //   1590: aload #4
/*    */     //   1592: dup
/*    */     //   1593: getfield mm : S
/*    */     //   1596: istore #4
/*    */     //   1598: getfield Yu0 : S
/*    */     //   1601: iload #4
/*    */     //   1603: swap
/*    */     //   1604: getstatic f/km.a3 : Lf/vh0;
/*    */     //   1607: getfield rK : I
/*    */     //   1610: invokevirtual z30 : (III)B
/*    */     //   1613: istore #6
/*    */     //   1615: getfield Yu0 : S
/*    */     //   1618: getstatic f/km.a3 : Lf/vh0;
/*    */     //   1621: getfield rK : I
/*    */     //   1624: invokevirtual tL : (II)B
/*    */     //   1627: istore #7
/*    */     //   1629: iload #6
/*    */     //   1631: putfield wt : I
/*    */     //   1634: iload #7
/*    */     //   1636: putfield Vp0 : I
/*    */     //   1639: iload #6
/*    */     //   1641: putfield j8 : I
/*    */     //   1644: iload #7
/*    */     //   1646: putfield iG : I
/*    */     //   1649: getfield aD : Lf/VP;
/*    */     //   1652: iconst_1
/*    */     //   1653: invokevirtual wI0 : (Z)V
/*    */     //   1656: aload_0
/*    */     //   1657: dup
/*    */     //   1658: iload #6
/*    */     //   1660: iload #7
/*    */     //   1662: invokevirtual nh : (II)V
/*    */     //   1665: getfield z40 : Lf/o10;
/*    */     //   1668: dup
/*    */     //   1669: astore #4
/*    */     //   1671: ifnull -> 3463
/*    */     //   1674: aload #5
/*    */     //   1676: aload #8
/*    */     //   1678: aload #4
/*    */     //   1680: getfield hn : B
/*    */     //   1683: aload #4
/*    */     //   1685: dup
/*    */     //   1686: getfield vw0 : B
/*    */     //   1689: istore #4
/*    */     //   1691: getfield m3 : B
/*    */     //   1694: iload #4
/*    */     //   1696: swap
/*    */     //   1697: invokestatic Zg0 : (BBB)I
/*    */     //   1700: invokestatic gt0 : (I)Lf/WL0;
/*    */     //   1703: astore #4
/*    */     //   1705: if_acmpeq -> 3463
/*    */     //   1708: aload_0
/*    */     //   1709: aload #4
/*    */     //   1711: aload_0
/*    */     //   1712: dup
/*    */     //   1713: aload #4
/*    */     //   1715: aload_0
/*    */     //   1716: getfield z40 : Lf/o10;
/*    */     //   1719: dup
/*    */     //   1720: getfield lPT1 : S
/*    */     //   1723: istore_3
/*    */     //   1724: getfield wH : S
/*    */     //   1727: iload_3
/*    */     //   1728: swap
/*    */     //   1729: iconst_m1
/*    */     //   1730: invokevirtual z30 : (III)B
/*    */     //   1733: putfield Z50 : I
/*    */     //   1736: getfield z40 : Lf/o10;
/*    */     //   1739: dup
/*    */     //   1740: getfield lPT1 : S
/*    */     //   1743: pop
/*    */     //   1744: getfield wH : S
/*    */     //   1747: iconst_m1
/*    */     //   1748: invokevirtual tL : (II)B
/*    */     //   1751: putfield Rh : I
/*    */     //   1754: iconst_1
/*    */     //   1755: istore_3
/*    */     //   1756: goto -> 3463
/*    */     //   1759: iload_2
/*    */     //   1760: iconst_3
/*    */     //   1761: if_icmpne -> 2478
/*    */     //   1764: getstatic f/km.mI0 : Lf/P1;
/*    */     //   1767: getfield MT : Lf/gD;
/*    */     //   1770: ifnull -> 3463
/*    */     //   1773: getstatic f/km.a3 : Lf/vh0;
/*    */     //   1776: invokevirtual Jr0 : ()Lf/KI;
/*    */     //   1779: dup
/*    */     //   1780: astore #4
/*    */     //   1782: instanceof f/Cy
/*    */     //   1785: ifeq -> 1804
/*    */     //   1788: aload #4
/*    */     //   1790: checkcast f/Cy
/*    */     //   1793: getfield br0 : Lf/Ws0;
/*    */     //   1796: getfield d8 : B
/*    */     //   1799: istore #5
/*    */     //   1801: goto -> 1807
/*    */     //   1804: iconst_m1
/*    */     //   1805: istore #5
/*    */     //   1807: getstatic f/km.a3 : Lf/vh0;
/*    */     //   1810: getfield Ct : Lf/Jo;
/*    */     //   1813: getfield HW : Lf/G5;
/*    */     //   1816: dup
/*    */     //   1817: getfield mm : S
/*    */     //   1820: bipush #32
/*    */     //   1822: idiv
/*    */     //   1823: istore #6
/*    */     //   1825: getfield Yu0 : S
/*    */     //   1828: bipush #32
/*    */     //   1830: idiv
/*    */     //   1831: istore #7
/*    */     //   1833: iconst_0
/*    */     //   1834: istore #8
/*    */     //   1836: iconst_0
/*    */     //   1837: istore #9
/*    */     //   1839: getstatic f/km.mI0 : Lf/P1;
/*    */     //   1842: getfield MT : Lf/gD;
/*    */     //   1845: dup
/*    */     //   1846: astore #10
/*    */     //   1848: getfield Do : Lf/oD;
/*    */     //   1851: ifnonnull -> 1872
/*    */     //   1854: aload #10
/*    */     //   1856: new f/oD
/*    */     //   1859: dup
/*    */     //   1860: astore #11
/*    */     //   1862: aload #10
/*    */     //   1864: invokespecial <init> : (Lf/gD;)V
/*    */     //   1867: aload #11
/*    */     //   1869: putfield Do : Lf/oD;
/*    */     //   1872: aload #10
/*    */     //   1874: getfield Do : Lf/oD;
/*    */     //   1877: getfield W90 : [Lf/LPT7;
/*    */     //   1880: dup
/*    */     //   1881: astore #10
/*    */     //   1883: arraylength
/*    */     //   1884: istore #11
/*    */     //   1886: iconst_0
/*    */     //   1887: istore #12
/*    */     //   1889: iload #12
/*    */     //   1891: iload #11
/*    */     //   1893: if_icmpge -> 2119
/*    */     //   1896: aload_0
/*    */     //   1897: dup
/*    */     //   1898: aload #10
/*    */     //   1900: iload #12
/*    */     //   1902: aaload
/*    */     //   1903: astore #13
/*    */     //   1905: new f/sN
/*    */     //   1908: dup
/*    */     //   1909: astore #14
/*    */     //   1911: aload_0
/*    */     //   1912: aload #13
/*    */     //   1914: invokespecial <init> : (Lf/fr;Lf/LPT7;)V
/*    */     //   1917: getfield QQ : Ljava/util/ArrayList;
/*    */     //   1920: aload #14
/*    */     //   1922: invokevirtual add : (Ljava/lang/Object;)Z
/*    */     //   1925: pop
/*    */     //   1926: getfield z40 : Lf/o10;
/*    */     //   1929: dup
/*    */     //   1930: astore #15
/*    */     //   1932: ifnull -> 2003
/*    */     //   1935: aload #13
/*    */     //   1937: getfield bQ : S
/*    */     //   1940: dup
/*    */     //   1941: istore #16
/*    */     //   1943: aload #15
/*    */     //   1945: getfield RB : Lf/Ws0;
/*    */     //   1948: dup
/*    */     //   1949: astore #15
/*    */     //   1951: getfield Ga : S
/*    */     //   1954: if_icmpeq -> 1980
/*    */     //   1957: iload #16
/*    */     //   1959: aload #15
/*    */     //   1961: getfield f10 : S
/*    */     //   1964: if_icmpeq -> 1980
/*    */     //   1967: aload #13
/*    */     //   1969: getfield p20 : S
/*    */     //   1972: aload #15
/*    */     //   1974: getfield d8 : B
/*    */     //   1977: if_icmpne -> 2003
/*    */     //   1980: aload_0
/*    */     //   1981: aload #13
/*    */     //   1983: aload_0
/*    */     //   1984: aload #13
/*    */     //   1986: getfield p20 : S
/*    */     //   1989: putfield Z50 : I
/*    */     //   1992: getfield LK : S
/*    */     //   1995: putfield Rh : I
/*    */     //   1998: iconst_1
/*    */     //   1999: istore_3
/*    */     //   2000: iconst_1
/*    */     //   2001: istore #9
/*    */     //   2003: aload #4
/*    */     //   2005: ifnull -> 2113
/*    */     //   2008: aload #13
/*    */     //   2010: getfield bQ : S
/*    */     //   2013: aload #4
/*    */     //   2015: invokevirtual Xg0 : ()S
/*    */     //   2018: if_icmpeq -> 2043
/*    */     //   2021: iload #5
/*    */     //   2023: getstatic f/km.mI0 : Lf/P1;
/*    */     //   2026: getfield MT : Lf/gD;
/*    */     //   2029: aload #13
/*    */     //   2031: getfield bQ : S
/*    */     //   2034: invokevirtual U40 : (I)Lf/iy0;
/*    */     //   2037: getfield d8 : B
/*    */     //   2040: if_icmpne -> 2113
/*    */     //   2043: aload #13
/*    */     //   2045: getfield p20 : S
/*    */     //   2048: dup
/*    */     //   2049: istore #15
/*    */     //   2051: iload #6
/*    */     //   2053: if_icmpne -> 2070
/*    */     //   2056: aload #13
/*    */     //   2058: getfield LK : S
/*    */     //   2061: iload #7
/*    */     //   2063: if_icmpne -> 2070
/*    */     //   2066: iconst_1
/*    */     //   2067: goto -> 2071
/*    */     //   2070: iconst_0
/*    */     //   2071: ifne -> 2081
/*    */     //   2074: aload_0
/*    */     //   2075: getfield com1 : Lf/sN;
/*    */     //   2078: ifnonnull -> 2113
/*    */     //   2081: aload_0
/*    */     //   2082: aload #14
/*    */     //   2084: aload_0
/*    */     //   2085: dup
/*    */     //   2086: aload #13
/*    */     //   2088: aload_0
/*    */     //   2089: iload #15
/*    */     //   2091: putfield j8 : I
/*    */     //   2094: getfield LK : S
/*    */     //   2097: putfield iG : I
/*    */     //   2100: getfield aD : Lf/VP;
/*    */     //   2103: iconst_1
/*    */     //   2104: invokevirtual wI0 : (Z)V
/*    */     //   2107: invokevirtual WQ : (Lf/sN;)V
/*    */     //   2110: iconst_1
/*    */     //   2111: istore #8
/*    */     //   2113: iinc #12, 1
/*    */     //   2116: goto -> 1889
/*    */     //   2119: aload_0
/*    */     //   2120: getfield z40 : Lf/o10;
/*    */     //   2123: dup
/*    */     //   2124: astore #4
/*    */     //   2126: ifnull -> 2216
/*    */     //   2129: iload #9
/*    */     //   2131: ifne -> 2216
/*    */     //   2134: aload #4
/*    */     //   2136: getfield hn : B
/*    */     //   2139: aload #4
/*    */     //   2141: dup
/*    */     //   2142: getfield vw0 : B
/*    */     //   2145: istore #4
/*    */     //   2147: getfield m3 : B
/*    */     //   2150: iload #4
/*    */     //   2152: swap
/*    */     //   2153: invokestatic Zg0 : (BBB)I
/*    */     //   2156: invokestatic gt0 : (I)Lf/WL0;
/*    */     //   2159: dup
/*    */     //   2160: astore #4
/*    */     //   2162: getstatic f/Mm0.i7 : Lf/WL0;
/*    */     //   2165: if_acmpeq -> 2216
/*    */     //   2168: aload_0
/*    */     //   2169: aload #4
/*    */     //   2171: aload_0
/*    */     //   2172: dup
/*    */     //   2173: aload #4
/*    */     //   2175: aload_0
/*    */     //   2176: getfield z40 : Lf/o10;
/*    */     //   2179: dup
/*    */     //   2180: getfield lPT1 : S
/*    */     //   2183: istore_3
/*    */     //   2184: getfield wH : S
/*    */     //   2187: iload_3
/*    */     //   2188: swap
/*    */     //   2189: iconst_m1
/*    */     //   2190: invokevirtual z30 : (III)B
/*    */     //   2193: putfield Z50 : I
/*    */     //   2196: getfield z40 : Lf/o10;
/*    */     //   2199: dup
/*    */     //   2200: getfield lPT1 : S
/*    */     //   2203: pop
/*    */     //   2204: getfield wH : S
/*    */     //   2207: iconst_m1
/*    */     //   2208: invokevirtual tL : (II)B
/*    */     //   2211: putfield Rh : I
/*    */     //   2214: iconst_1
/*    */     //   2215: istore_3
/*    */     //   2216: iload #8
/*    */     //   2218: ifne -> 2456
/*    */     //   2221: getstatic f/km.a3 : Lf/vh0;
/*    */     //   2224: getfield Ct : Lf/Jo;
/*    */     //   2227: getfield HW : Lf/G5;
/*    */     //   2230: dup
/*    */     //   2231: astore #4
/*    */     //   2233: getfield FB : B
/*    */     //   2236: aload #4
/*    */     //   2238: dup
/*    */     //   2239: getfield kD0 : B
/*    */     //   2242: istore #5
/*    */     //   2244: getfield vu0 : B
/*    */     //   2247: iload #5
/*    */     //   2249: swap
/*    */     //   2250: invokestatic Zg0 : (BBB)I
/*    */     //   2253: invokestatic gt0 : (I)Lf/WL0;
/*    */     //   2256: dup
/*    */     //   2257: astore #5
/*    */     //   2259: getstatic f/Mm0.i7 : Lf/WL0;
/*    */     //   2262: if_acmpeq -> 2456
/*    */     //   2265: aload #5
/*    */     //   2267: aload #4
/*    */     //   2269: aload #5
/*    */     //   2271: aload #4
/*    */     //   2273: dup
/*    */     //   2274: getfield mm : S
/*    */     //   2277: istore #4
/*    */     //   2279: getfield Yu0 : S
/*    */     //   2282: iload #4
/*    */     //   2284: swap
/*    */     //   2285: getstatic f/km.a3 : Lf/vh0;
/*    */     //   2288: getfield rK : I
/*    */     //   2291: invokevirtual z30 : (III)B
/*    */     //   2294: istore #4
/*    */     //   2296: getfield Yu0 : S
/*    */     //   2299: getstatic f/km.a3 : Lf/vh0;
/*    */     //   2302: getfield rK : I
/*    */     //   2305: invokevirtual tL : (II)B
/*    */     //   2308: istore #5
/*    */     //   2310: getstatic f/km.mI0 : Lf/P1;
/*    */     //   2313: getfield MT : Lf/gD;
/*    */     //   2316: dup
/*    */     //   2317: astore #6
/*    */     //   2319: getfield Do : Lf/oD;
/*    */     //   2322: ifnonnull -> 2343
/*    */     //   2325: aload #6
/*    */     //   2327: new f/oD
/*    */     //   2330: dup
/*    */     //   2331: astore #7
/*    */     //   2333: aload #6
/*    */     //   2335: invokespecial <init> : (Lf/gD;)V
/*    */     //   2338: aload #7
/*    */     //   2340: putfield Do : Lf/oD;
/*    */     //   2343: aload #6
/*    */     //   2345: getfield Do : Lf/oD;
/*    */     //   2348: getfield W90 : [Lf/LPT7;
/*    */     //   2351: dup
/*    */     //   2352: astore #6
/*    */     //   2354: arraylength
/*    */     //   2355: istore #7
/*    */     //   2357: iconst_0
/*    */     //   2358: istore #8
/*    */     //   2360: iload #8
/*    */     //   2362: iload #7
/*    */     //   2364: if_icmpge -> 2456
/*    */     //   2367: aload #6
/*    */     //   2369: iload #8
/*    */     //   2371: aaload
/*    */     //   2372: dup
/*    */     //   2373: astore #9
/*    */     //   2375: getfield p20 : S
/*    */     //   2378: iload #4
/*    */     //   2380: if_icmpne -> 2450
/*    */     //   2383: aload #9
/*    */     //   2385: getfield LK : S
/*    */     //   2388: iload #5
/*    */     //   2390: if_icmpne -> 2450
/*    */     //   2393: aload_0
/*    */     //   2394: dup
/*    */     //   2395: aload #9
/*    */     //   2397: aload_0
/*    */     //   2398: aload #9
/*    */     //   2400: aload_0
/*    */     //   2401: new f/sN
/*    */     //   2404: dup
/*    */     //   2405: astore #4
/*    */     //   2407: aload_0
/*    */     //   2408: aload #9
/*    */     //   2410: invokespecial <init> : (Lf/fr;Lf/LPT7;)V
/*    */     //   2413: getfield QQ : Ljava/util/ArrayList;
/*    */     //   2416: aload #4
/*    */     //   2418: invokevirtual add : (Ljava/lang/Object;)Z
/*    */     //   2421: pop
/*    */     //   2422: getfield p20 : S
/*    */     //   2425: putfield j8 : I
/*    */     //   2428: getfield LK : S
/*    */     //   2431: putfield iG : I
/*    */     //   2434: aload #4
/*    */     //   2436: aload_0
/*    */     //   2437: getfield aD : Lf/VP;
/*    */     //   2440: iconst_1
/*    */     //   2441: invokevirtual wI0 : (Z)V
/*    */     //   2444: invokevirtual WQ : (Lf/sN;)V
/*    */     //   2447: goto -> 2456
/*    */     //   2450: iinc #8, 1
/*    */     //   2453: goto -> 2360
/*    */     //   2456: aload_0
/*    */     //   2457: getfield com1 : Lf/sN;
/*    */     //   2460: ifnonnull -> 3463
/*    */     //   2463: aload_0
/*    */     //   2464: dup
/*    */     //   2465: bipush #14
/*    */     //   2467: putfield wt : I
/*    */     //   2470: bipush #18
/*    */     //   2472: putfield Vp0 : I
/*    */     //   2475: goto -> 3463
/*    */     //   2478: iload_2
/*    */     //   2479: iconst_4
/*    */     //   2480: if_icmpne -> 3170
/*    */     //   2483: getstatic f/km.mI0 : Lf/P1;
/*    */     //   2486: getfield yE : Lf/BE;
/*    */     //   2489: ifnull -> 3463
/*    */     //   2492: getstatic f/km.a3 : Lf/vh0;
/*    */     //   2495: invokevirtual Jr0 : ()Lf/KI;
/*    */     //   2498: dup
/*    */     //   2499: astore #4
/*    */     //   2501: instanceof f/Cy
/*    */     //   2504: ifeq -> 2523
/*    */     //   2507: aload #4
/*    */     //   2509: checkcast f/Cy
/*    */     //   2512: getfield br0 : Lf/Ws0;
/*    */     //   2515: getfield d8 : B
/*    */     //   2518: istore #5
/*    */     //   2520: goto -> 2526
/*    */     //   2523: iconst_m1
/*    */     //   2524: istore #5
/*    */     //   2526: getstatic f/km.a3 : Lf/vh0;
/*    */     //   2529: getfield Ct : Lf/Jo;
/*    */     //   2532: getfield HW : Lf/G5;
/*    */     //   2535: dup
/*    */     //   2536: getfield mm : S
/*    */     //   2539: bipush #32
/*    */     //   2541: idiv
/*    */     //   2542: istore #6
/*    */     //   2544: getfield Yu0 : S
/*    */     //   2547: bipush #32
/*    */     //   2549: idiv
/*    */     //   2550: iconst_2
/*    */     //   2551: iadd
/*    */     //   2552: istore #7
/*    */     //   2554: iconst_0
/*    */     //   2555: istore #8
/*    */     //   2557: iconst_0
/*    */     //   2558: istore #9
/*    */     //   2560: invokestatic XB : ()Ljava/util/ArrayList;
/*    */     //   2563: invokevirtual iterator : ()Ljava/util/Iterator;
/*    */     //   2566: astore #10
/*    */     //   2568: aload #10
/*    */     //   2570: invokeinterface hasNext : ()Z
/*    */     //   2575: ifeq -> 2854
/*    */     //   2578: aload #10
/*    */     //   2580: invokeinterface next : ()Ljava/lang/Object;
/*    */     //   2585: checkcast f/T6
/*    */     //   2588: dup
/*    */     //   2589: astore #11
/*    */     //   2591: getfield zj : S
/*    */     //   2594: dup
/*    */     //   2595: istore #12
/*    */     //   2597: iconst_m1
/*    */     //   2598: if_icmpeq -> 2627
/*    */     //   2601: getstatic f/km.u4 : Lf/R8;
/*    */     //   2604: getfield fF0 : Lf/BF;
/*    */     //   2607: aload #11
/*    */     //   2609: getfield ka : B
/*    */     //   2612: iload #12
/*    */     //   2614: invokevirtual y5 : (BS)Z
/*    */     //   2617: ifeq -> 2623
/*    */     //   2620: goto -> 2627
/*    */     //   2623: iconst_0
/*    */     //   2624: goto -> 2628
/*    */     //   2627: iconst_1
/*    */     //   2628: ifne -> 2634
/*    */     //   2631: goto -> 2568
/*    */     //   2634: aload_0
/*    */     //   2635: dup
/*    */     //   2636: new f/sN
/*    */     //   2639: dup
/*    */     //   2640: astore #12
/*    */     //   2642: aload_0
/*    */     //   2643: aload #11
/*    */     //   2645: invokespecial <init> : (Lf/fr;Lf/T6;)V
/*    */     //   2648: getfield QQ : Ljava/util/ArrayList;
/*    */     //   2651: aload #12
/*    */     //   2653: invokevirtual add : (Ljava/lang/Object;)Z
/*    */     //   2656: pop
/*    */     //   2657: getfield z40 : Lf/o10;
/*    */     //   2660: dup
/*    */     //   2661: astore #13
/*    */     //   2663: ifnull -> 2729
/*    */     //   2666: aload #11
/*    */     //   2668: getfield bQ : S
/*    */     //   2671: dup
/*    */     //   2672: istore #14
/*    */     //   2674: aload #13
/*    */     //   2676: getfield RB : Lf/Ws0;
/*    */     //   2679: dup
/*    */     //   2680: astore #13
/*    */     //   2682: getfield Ga : S
/*    */     //   2685: if_icmpeq -> 2706
/*    */     //   2688: aload #13
/*    */     //   2690: getfield f10 : S
/*    */     //   2693: dup
/*    */     //   2694: istore #13
/*    */     //   2696: ifeq -> 2729
/*    */     //   2699: iload #14
/*    */     //   2701: iload #13
/*    */     //   2703: if_icmpne -> 2729
/*    */     //   2706: aload_0
/*    */     //   2707: aload #11
/*    */     //   2709: aload_0
/*    */     //   2710: aload #11
/*    */     //   2712: getfield p20 : S
/*    */     //   2715: putfield Z50 : I
/*    */     //   2718: getfield LK : S
/*    */     //   2721: putfield Rh : I
/*    */     //   2724: iconst_1
/*    */     //   2725: istore_3
/*    */     //   2726: iconst_1
/*    */     //   2727: istore #9
/*    */     //   2729: aload #4
/*    */     //   2731: ifnull -> 2568
/*    */     //   2734: aload #11
/*    */     //   2736: getfield bQ : S
/*    */     //   2739: aload #4
/*    */     //   2741: invokevirtual Xg0 : ()S
/*    */     //   2744: if_icmpeq -> 2781
/*    */     //   2747: iload #5
/*    */     //   2749: aload #11
/*    */     //   2751: getstatic f/km.mI0 : Lf/P1;
/*    */     //   2754: getfield yE : Lf/BE;
/*    */     //   2757: astore #13
/*    */     //   2759: getfield bQ : S
/*    */     //   2762: aload #13
/*    */     //   2764: getfield qN : Lf/Fg0;
/*    */     //   2767: getfield Z6 : [Lf/Ws0;
/*    */     //   2770: swap
/*    */     //   2771: aaload
/*    */     //   2772: checkcast f/iy0
/*    */     //   2775: getfield d8 : B
/*    */     //   2778: if_icmpne -> 2568
/*    */     //   2781: aload #11
/*    */     //   2783: getfield p20 : S
/*    */     //   2786: dup
/*    */     //   2787: istore #13
/*    */     //   2789: iload #6
/*    */     //   2791: if_icmpne -> 2808
/*    */     //   2794: aload #11
/*    */     //   2796: getfield LK : S
/*    */     //   2799: iload #7
/*    */     //   2801: if_icmpne -> 2808
/*    */     //   2804: iconst_1
/*    */     //   2805: goto -> 2809
/*    */     //   2808: iconst_0
/*    */     //   2809: ifne -> 2819
/*    */     //   2812: aload_0
/*    */     //   2813: getfield com1 : Lf/sN;
/*    */     //   2816: ifnonnull -> 2568
/*    */     //   2819: aload_0
/*    */     //   2820: aload #12
/*    */     //   2822: aload_0
/*    */     //   2823: dup
/*    */     //   2824: aload #11
/*    */     //   2826: aload_0
/*    */     //   2827: iload #13
/*    */     //   2829: putfield j8 : I
/*    */     //   2832: getfield LK : S
/*    */     //   2835: putfield iG : I
/*    */     //   2838: getfield aD : Lf/VP;
/*    */     //   2841: iconst_1
/*    */     //   2842: invokevirtual wI0 : (Z)V
/*    */     //   2845: invokevirtual WQ : (Lf/sN;)V
/*    */     //   2848: iconst_1
/*    */     //   2849: istore #8
/*    */     //   2851: goto -> 2568
/*    */     //   2854: aload_0
/*    */     //   2855: getfield z40 : Lf/o10;
/*    */     //   2858: dup
/*    */     //   2859: astore #4
/*    */     //   2861: ifnull -> 2951
/*    */     //   2864: iload #9
/*    */     //   2866: ifne -> 2951
/*    */     //   2869: aload #4
/*    */     //   2871: getfield hn : B
/*    */     //   2874: aload #4
/*    */     //   2876: dup
/*    */     //   2877: getfield vw0 : B
/*    */     //   2880: istore #4
/*    */     //   2882: getfield m3 : B
/*    */     //   2885: iload #4
/*    */     //   2887: swap
/*    */     //   2888: invokestatic Zg0 : (BBB)I
/*    */     //   2891: invokestatic gt0 : (I)Lf/WL0;
/*    */     //   2894: dup
/*    */     //   2895: astore #4
/*    */     //   2897: getstatic f/Mm0.i7 : Lf/WL0;
/*    */     //   2900: if_acmpeq -> 2951
/*    */     //   2903: aload_0
/*    */     //   2904: aload #4
/*    */     //   2906: aload_0
/*    */     //   2907: dup
/*    */     //   2908: aload #4
/*    */     //   2910: aload_0
/*    */     //   2911: getfield z40 : Lf/o10;
/*    */     //   2914: dup
/*    */     //   2915: getfield lPT1 : S
/*    */     //   2918: istore_3
/*    */     //   2919: getfield wH : S
/*    */     //   2922: iload_3
/*    */     //   2923: swap
/*    */     //   2924: iconst_m1
/*    */     //   2925: invokevirtual z30 : (III)B
/*    */     //   2928: putfield Z50 : I
/*    */     //   2931: getfield z40 : Lf/o10;
/*    */     //   2934: dup
/*    */     //   2935: getfield lPT1 : S
/*    */     //   2938: pop
/*    */     //   2939: getfield wH : S
/*    */     //   2942: iconst_m1
/*    */     //   2943: invokevirtual tL : (II)B
/*    */     //   2946: putfield Rh : I
/*    */     //   2949: iconst_1
/*    */     //   2950: istore_3
/*    */     //   2951: iload #8
/*    */     //   2953: ifne -> 3148
/*    */     //   2956: getstatic f/km.a3 : Lf/vh0;
/*    */     //   2959: getfield Ct : Lf/Jo;
/*    */     //   2962: getfield HW : Lf/G5;
/*    */     //   2965: dup
/*    */     //   2966: astore #4
/*    */     //   2968: getfield FB : B
/*    */     //   2971: aload #4
/*    */     //   2973: dup
/*    */     //   2974: getfield kD0 : B
/*    */     //   2977: istore #5
/*    */     //   2979: getfield vu0 : B
/*    */     //   2982: iload #5
/*    */     //   2984: swap
/*    */     //   2985: invokestatic Zg0 : (BBB)I
/*    */     //   2988: invokestatic gt0 : (I)Lf/WL0;
/*    */     //   2991: dup
/*    */     //   2992: astore #5
/*    */     //   2994: getstatic f/Mm0.i7 : Lf/WL0;
/*    */     //   2997: if_acmpeq -> 3148
/*    */     //   3000: aload #5
/*    */     //   3002: aload #4
/*    */     //   3004: aload #5
/*    */     //   3006: aload #4
/*    */     //   3008: dup
/*    */     //   3009: getfield mm : S
/*    */     //   3012: istore #4
/*    */     //   3014: getfield Yu0 : S
/*    */     //   3017: iload #4
/*    */     //   3019: swap
/*    */     //   3020: getstatic f/km.a3 : Lf/vh0;
/*    */     //   3023: getfield rK : I
/*    */     //   3026: invokevirtual z30 : (III)B
/*    */     //   3029: istore #4
/*    */     //   3031: getfield Yu0 : S
/*    */     //   3034: getstatic f/km.a3 : Lf/vh0;
/*    */     //   3037: getfield rK : I
/*    */     //   3040: invokevirtual tL : (II)B
/*    */     //   3043: istore #5
/*    */     //   3045: invokestatic XB : ()Ljava/util/ArrayList;
/*    */     //   3048: invokevirtual iterator : ()Ljava/util/Iterator;
/*    */     //   3051: astore #6
/*    */     //   3053: aload #6
/*    */     //   3055: invokeinterface hasNext : ()Z
/*    */     //   3060: ifeq -> 3148
/*    */     //   3063: aload #6
/*    */     //   3065: invokeinterface next : ()Ljava/lang/Object;
/*    */     //   3070: checkcast f/T6
/*    */     //   3073: dup
/*    */     //   3074: astore #7
/*    */     //   3076: getfield p20 : S
/*    */     //   3079: iload #4
/*    */     //   3081: if_icmpne -> 3053
/*    */     //   3084: aload #7
/*    */     //   3086: getfield LK : S
/*    */     //   3089: iload #5
/*    */     //   3091: if_icmpne -> 3053
/*    */     //   3094: aload_0
/*    */     //   3095: dup
/*    */     //   3096: aload #7
/*    */     //   3098: aload_0
/*    */     //   3099: aload #7
/*    */     //   3101: aload_0
/*    */     //   3102: new f/sN
/*    */     //   3105: dup
/*    */     //   3106: astore #4
/*    */     //   3108: aload_0
/*    */     //   3109: aload #7
/*    */     //   3111: invokespecial <init> : (Lf/fr;Lf/T6;)V
/*    */     //   3114: getfield QQ : Ljava/util/ArrayList;
/*    */     //   3117: aload #4
/*    */     //   3119: invokevirtual add : (Ljava/lang/Object;)Z
/*    */     //   3122: pop
/*    */     //   3123: getfield p20 : S
/*    */     //   3126: putfield j8 : I
/*    */     //   3129: getfield LK : S
/*    */     //   3132: putfield iG : I
/*    */     //   3135: aload #4
/*    */     //   3137: aload_0
/*    */     //   3138: getfield aD : Lf/VP;
/*    */     //   3141: iconst_1
/*    */     //   3142: invokevirtual wI0 : (Z)V
/*    */     //   3145: invokevirtual WQ : (Lf/sN;)V
/*    */     //   3148: aload_0
/*    */     //   3149: getfield com1 : Lf/sN;
/*    */     //   3152: ifnonnull -> 3463
/*    */     //   3155: aload_0
/*    */     //   3156: dup
/*    */     //   3157: bipush #21
/*    */     //   3159: putfield wt : I
/*    */     //   3162: bipush #14
/*    */     //   3164: putfield Vp0 : I
/*    */     //   3167: goto -> 3463
/*    */     //   3170: iload_2
/*    */     //   3171: iconst_2
/*    */     //   3172: if_icmpne -> 3463
/*    */     //   3175: getstatic f/km.mI0 : Lf/P1;
/*    */     //   3178: getfield AN : Lf/Wo;
/*    */     //   3181: ifnull -> 3463
/*    */     //   3184: getstatic f/km.a3 : Lf/vh0;
/*    */     //   3187: invokevirtual Jr0 : ()Lf/KI;
/*    */     //   3190: astore #4
/*    */     //   3192: getstatic f/km.mI0 : Lf/P1;
/*    */     //   3195: getfield AN : Lf/Wo;
/*    */     //   3198: invokevirtual Da : ()[Lf/x4;
/*    */     //   3201: dup
/*    */     //   3202: astore #5
/*    */     //   3204: arraylength
/*    */     //   3205: istore #6
/*    */     //   3207: iconst_0
/*    */     //   3208: istore #7
/*    */     //   3210: iload #7
/*    */     //   3212: iload #6
/*    */     //   3214: if_icmpge -> 3463
/*    */     //   3217: aload_0
/*    */     //   3218: dup
/*    */     //   3219: aload #5
/*    */     //   3221: iload #7
/*    */     //   3223: aaload
/*    */     //   3224: astore #8
/*    */     //   3226: new f/sN
/*    */     //   3229: dup
/*    */     //   3230: astore #9
/*    */     //   3232: aload_0
/*    */     //   3233: aload #8
/*    */     //   3235: invokespecial <init> : (Lf/fr;Lf/x4;)V
/*    */     //   3238: getfield QQ : Ljava/util/ArrayList;
/*    */     //   3241: aload #9
/*    */     //   3243: invokevirtual add : (Ljava/lang/Object;)Z
/*    */     //   3246: pop
/*    */     //   3247: getfield z40 : Lf/o10;
/*    */     //   3250: dup
/*    */     //   3251: astore #10
/*    */     //   3253: ifnull -> 3358
/*    */     //   3256: aload #8
/*    */     //   3258: getstatic f/km.mI0 : Lf/P1;
/*    */     //   3261: getfield AN : Lf/Wo;
/*    */     //   3264: astore #11
/*    */     //   3266: getfield bQ : S
/*    */     //   3269: dup
/*    */     //   3270: istore #12
/*    */     //   3272: aload #10
/*    */     //   3274: aload #11
/*    */     //   3276: getfield YP : Lf/TA0;
/*    */     //   3279: getfield Z6 : [Lf/Ws0;
/*    */     //   3282: iload #12
/*    */     //   3284: aaload
/*    */     //   3285: checkcast f/gb
/*    */     //   3288: astore #10
/*    */     //   3290: getfield RB : Lf/Ws0;
/*    */     //   3293: dup
/*    */     //   3294: astore #11
/*    */     //   3296: getfield Ga : S
/*    */     //   3299: if_icmpeq -> 3325
/*    */     //   3302: iload #12
/*    */     //   3304: aload #11
/*    */     //   3306: getfield f10 : S
/*    */     //   3309: if_icmpeq -> 3325
/*    */     //   3312: aload #10
/*    */     //   3314: getfield d8 : B
/*    */     //   3317: aload #11
/*    */     //   3319: getfield d8 : B
/*    */     //   3322: if_icmpne -> 3358
/*    */     //   3325: aload_0
/*    */     //   3326: aload #9
/*    */     //   3328: aload_0
/*    */     //   3329: aload #9
/*    */     //   3331: getfield Kd : I
/*    */     //   3334: aload_0
/*    */     //   3335: getfield od : I
/*    */     //   3338: dup
/*    */     //   3339: istore_3
/*    */     //   3340: iconst_3
/*    */     //   3341: imul
/*    */     //   3342: isub
/*    */     //   3343: putfield Z50 : I
/*    */     //   3346: getfield er0 : I
/*    */     //   3349: iload_3
/*    */     //   3350: iconst_4
/*    */     //   3351: imul
/*    */     //   3352: isub
/*    */     //   3353: putfield Rh : I
/*    */     //   3356: iconst_1
/*    */     //   3357: istore_3
/*    */     //   3358: aload_0
/*    */     //   3359: getfield com1 : Lf/sN;
/*    */     //   3362: ifnonnull -> 3457
/*    */     //   3365: aload #4
/*    */     //   3367: ifnull -> 3383
/*    */     //   3370: aload #8
/*    */     //   3372: getfield bQ : S
/*    */     //   3375: aload #4
/*    */     //   3377: invokevirtual Xg0 : ()S
/*    */     //   3380: if_icmpeq -> 3410
/*    */     //   3383: aload #4
/*    */     //   3385: instanceof f/Cy
/*    */     //   3388: ifeq -> 3457
/*    */     //   3391: aload #4
/*    */     //   3393: checkcast f/Cy
/*    */     //   3396: getfield br0 : Lf/Ws0;
/*    */     //   3399: getfield f10 : S
/*    */     //   3402: aload #8
/*    */     //   3404: getfield bQ : S
/*    */     //   3407: if_icmpne -> 3457
/*    */     //   3410: aload_0
/*    */     //   3411: aload #9
/*    */     //   3413: aload_0
/*    */     //   3414: dup
/*    */     //   3415: aload #9
/*    */     //   3417: aload_0
/*    */     //   3418: aload #9
/*    */     //   3420: getfield Kd : I
/*    */     //   3423: aload_0
/*    */     //   3424: getfield od : I
/*    */     //   3427: dup
/*    */     //   3428: istore #8
/*    */     //   3430: iconst_3
/*    */     //   3431: imul
/*    */     //   3432: isub
/*    */     //   3433: putfield j8 : I
/*    */     //   3436: getfield er0 : I
/*    */     //   3439: iload #8
/*    */     //   3441: iconst_4
/*    */     //   3442: imul
/*    */     //   3443: isub
/*    */     //   3444: putfield iG : I
/*    */     //   3447: getfield aD : Lf/VP;
/*    */     //   3450: iconst_1
/*    */     //   3451: invokevirtual wI0 : (Z)V
/*    */     //   3454: invokevirtual WQ : (Lf/sN;)V
/*    */     //   3457: iinc #7, 1
/*    */     //   3460: goto -> 3210
/*    */     //   3463: iload_3
/*    */     //   3464: ifeq -> 3478
/*    */     //   3467: aload_0
/*    */     //   3468: getfield BY : Lf/vF0;
/*    */     //   3471: iconst_1
/*    */     //   3472: invokevirtual wI0 : (Z)V
/*    */     //   3475: goto -> 3496
/*    */     //   3478: aload_0
/*    */     //   3479: dup
/*    */     //   3480: dup
/*    */     //   3481: getfield BY : Lf/vF0;
/*    */     //   3484: iconst_0
/*    */     //   3485: invokevirtual wI0 : (Z)V
/*    */     //   3488: iconst_0
/*    */     //   3489: putfield Z50 : I
/*    */     //   3492: iconst_0
/*    */     //   3493: putfield Rh : I
/*    */     //   3496: aload_0
/*    */     //   3497: getfield F : Z
/*    */     //   3500: ifeq -> 3746
/*    */     //   3503: aload_0
/*    */     //   3504: getfield mn0 : Ljava/util/List;
/*    */     //   3507: dup
/*    */     //   3508: astore_3
/*    */     //   3509: ifnull -> 3746
/*    */     //   3512: aload_3
/*    */     //   3513: invokeinterface iterator : ()Ljava/util/Iterator;
/*    */     //   3518: astore_3
/*    */     //   3519: aload_3
/*    */     //   3520: invokeinterface hasNext : ()Z
/*    */     //   3525: ifeq -> 3746
/*    */     //   3528: aload_3
/*    */     //   3529: invokeinterface next : ()Ljava/lang/Object;
/*    */     //   3534: checkcast f/C6
/*    */     //   3537: dup
/*    */     //   3538: astore #4
/*    */     //   3540: getfield co : B
/*    */     //   3543: dup
/*    */     //   3544: istore #5
/*    */     //   3546: iload_2
/*    */     //   3547: if_icmpne -> 3519
/*    */     //   3550: aload #4
/*    */     //   3552: getfield cV : I
/*    */     //   3555: iload_1
/*    */     //   3556: if_icmpeq -> 3562
/*    */     //   3559: goto -> 3519
/*    */     //   3562: aload #4
/*    */     //   3564: getfield NZ : S
/*    */     //   3567: dup
/*    */     //   3568: istore #6
/*    */     //   3570: ifeq -> 3589
/*    */     //   3573: getstatic f/km.u4 : Lf/R8;
/*    */     //   3576: getfield fF0 : Lf/BF;
/*    */     //   3579: iload #5
/*    */     //   3581: iload #6
/*    */     //   3583: invokevirtual y5 : (BS)Z
/*    */     //   3586: ifeq -> 3519
/*    */     //   3589: aload #4
/*    */     //   3591: getstatic f/km.a3 : Lf/vh0;
/*    */     //   3594: getfield Ct : Lf/Jo;
/*    */     //   3597: getfield Eh0 : B
/*    */     //   3600: istore #5
/*    */     //   3602: getfield DG : B
/*    */     //   3605: dup
/*    */     //   3606: istore #6
/*    */     //   3608: iconst_m1
/*    */     //   3609: if_icmple -> 3626
/*    */     //   3612: iload #5
/*    */     //   3614: iload #6
/*    */     //   3616: if_icmpne -> 3622
/*    */     //   3619: goto -> 3626
/*    */     //   3622: iconst_0
/*    */     //   3623: goto -> 3627
/*    */     //   3626: iconst_1
/*    */     //   3627: ifeq -> 3519
/*    */     //   3630: iload_2
/*    */     //   3631: new f/Cf0
/*    */     //   3634: dup
/*    */     //   3635: astore #5
/*    */     //   3637: aload_0
/*    */     //   3638: dup
/*    */     //   3639: getfield Rt : I
/*    */     //   3642: i2f
/*    */     //   3643: ldc_w 0.66
/*    */     //   3646: fmul
/*    */     //   3647: f2d
/*    */     //   3648: invokestatic ceil : (D)D
/*    */     //   3651: d2i
/*    */     //   3652: aload #4
/*    */     //   3654: swap
/*    */     //   3655: invokespecial <init> : (Lf/fr;Lf/C6;I)V
/*    */     //   3658: iconst_2
/*    */     //   3659: if_icmpne -> 3689
/*    */     //   3662: aload #4
/*    */     //   3664: dup
/*    */     //   3665: getfield ci : S
/*    */     //   3668: aload_0
/*    */     //   3669: getfield Rt : I
/*    */     //   3672: dup
/*    */     //   3673: istore #4
/*    */     //   3675: imul
/*    */     //   3676: istore #6
/*    */     //   3678: getfield MG : S
/*    */     //   3681: iload #4
/*    */     //   3683: imul
/*    */     //   3684: istore #4
/*    */     //   3686: goto -> 3723
/*    */     //   3689: aload #4
/*    */     //   3691: dup
/*    */     //   3692: getfield ci : S
/*    */     //   3695: aload_0
/*    */     //   3696: getfield J1 : I
/*    */     //   3699: dup
/*    */     //   3700: istore #4
/*    */     //   3702: imul
/*    */     //   3703: aload_0
/*    */     //   3704: getfield fX : I
/*    */     //   3707: iadd
/*    */     //   3708: istore #6
/*    */     //   3710: getfield MG : S
/*    */     //   3713: iload #4
/*    */     //   3715: imul
/*    */     //   3716: aload_0
/*    */     //   3717: getfield rq0 : I
/*    */     //   3720: iadd
/*    */     //   3721: istore #4
/*    */     //   3723: aload_0
/*    */     //   3724: aload #5
/*    */     //   3726: iload #6
/*    */     //   3728: iload #4
/*    */     //   3730: invokevirtual ME : (II)Z
/*    */     //   3733: pop
/*    */     //   3734: getfield n5 : Ljava/util/ArrayList;
/*    */     //   3737: aload #5
/*    */     //   3739: invokevirtual add : (Ljava/lang/Object;)Z
/*    */     //   3742: pop
/*    */     //   3743: goto -> 3519
/*    */     //   3746: aload_0
/*    */     //   3747: getfield wt : I
/*    */     //   3750: ifne -> 3817
/*    */     //   3753: invokestatic LS : ()B
/*    */     //   3756: iconst_2
/*    */     //   3757: if_icmpne -> 3777
/*    */     //   3760: aload_0
/*    */     //   3761: dup
/*    */     //   3762: sipush #446
/*    */     //   3765: putfield wt : I
/*    */     //   3768: sipush #298
/*    */     //   3771: putfield Vp0 : I
/*    */     //   3774: goto -> 3817
/*    */     //   3777: invokestatic LS : ()B
/*    */     //   3780: iconst_3
/*    */     //   3781: if_icmpne -> 3798
/*    */     //   3784: aload_0
/*    */     //   3785: dup
/*    */     //   3786: iconst_4
/*    */     //   3787: putfield wt : I
/*    */     //   3790: bipush #23
/*    */     //   3792: putfield Vp0 : I
/*    */     //   3795: goto -> 3817
/*    */     //   3798: invokestatic LS : ()B
/*    */     //   3801: iconst_4
/*    */     //   3802: if_icmpne -> 3817
/*    */     //   3805: aload_0
/*    */     //   3806: dup
/*    */     //   3807: bipush #21
/*    */     //   3809: putfield wt : I
/*    */     //   3812: bipush #14
/*    */     //   3814: putfield Vp0 : I
/*    */     //   3817: aload_0
/*    */     //   3818: dup
/*    */     //   3819: dup2
/*    */     //   3820: getfield Kk : Lf/dQ;
/*    */     //   3823: ldc_w 'townmap-label'
/*    */     //   3826: invokevirtual Xu : (Ljava/lang/String;)V
/*    */     //   3829: getfield zy : Lf/dQ;
/*    */     //   3832: ldc_w 'townmap-label'
/*    */     //   3835: invokevirtual Xu : (Ljava/lang/String;)V
/*    */     //   3838: getfield WB0 : Lf/dQ;
/*    */     //   3841: ldc_w 'townmap-label'
/*    */     //   3844: invokevirtual Xu : (Ljava/lang/String;)V
/*    */     //   3847: getfield QQ : Ljava/util/ArrayList;
/*    */     //   3850: invokevirtual iterator : ()Ljava/util/Iterator;
/*    */     //   3853: astore_1
/*    */     //   3854: aload_1
/*    */     //   3855: invokeinterface hasNext : ()Z
/*    */     //   3860: ifeq -> 3889
/*    */     //   3863: aload_0
/*    */     //   3864: aload_1
/*    */     //   3865: invokeinterface next : ()Ljava/lang/Object;
/*    */     //   3870: checkcast f/JG0
/*    */     //   3873: astore_2
/*    */     //   3874: getfield C0 : Lf/Ip;
/*    */     //   3877: dup
/*    */     //   3878: aload_2
/*    */     //   3879: swap
/*    */     //   3880: invokevirtual Ub : ()I
/*    */     //   3883: invokevirtual si : (Lf/JG0;I)V
/*    */     //   3886: goto -> 3854
/*    */     //   3889: aload_0
/*    */     //   3890: getfield RH0 : Ljava/util/ArrayList;
/*    */     //   3893: invokevirtual iterator : ()Ljava/util/Iterator;
/*    */     //   3896: astore_1
/*    */     //   3897: aload_1
/*    */     //   3898: invokeinterface hasNext : ()Z
/*    */     //   3903: ifeq -> 3932
/*    */     //   3906: aload_0
/*    */     //   3907: aload_1
/*    */     //   3908: invokeinterface next : ()Ljava/lang/Object;
/*    */     //   3913: checkcast f/JG0
/*    */     //   3916: astore_2
/*    */     //   3917: getfield C0 : Lf/Ip;
/*    */     //   3920: dup
/*    */     //   3921: aload_2
/*    */     //   3922: swap
/*    */     //   3923: invokevirtual Ub : ()I
/*    */     //   3926: invokevirtual si : (Lf/JG0;I)V
/*    */     //   3929: goto -> 3897
/*    */     //   3932: aload_0
/*    */     //   3933: getfield n5 : Ljava/util/ArrayList;
/*    */     //   3936: invokevirtual iterator : ()Ljava/util/Iterator;
/*    */     //   3939: astore_1
/*    */     //   3940: aload_1
/*    */     //   3941: invokeinterface hasNext : ()Z
/*    */     //   3946: ifeq -> 3975
/*    */     //   3949: aload_0
/*    */     //   3950: aload_1
/*    */     //   3951: invokeinterface next : ()Ljava/lang/Object;
/*    */     //   3956: checkcast f/JG0
/*    */     //   3959: astore_2
/*    */     //   3960: getfield C0 : Lf/Ip;
/*    */     //   3963: dup
/*    */     //   3964: aload_2
/*    */     //   3965: swap
/*    */     //   3966: invokevirtual Ub : ()I
/*    */     //   3969: invokevirtual si : (Lf/JG0;I)V
/*    */     //   3972: goto -> 3940
/*    */     //   3975: aload_0
/*    */     //   3976: dup
/*    */     //   3977: dup2
/*    */     //   3978: dup2
/*    */     //   3979: getfield C0 : Lf/Ip;
/*    */     //   3982: dup
/*    */     //   3983: aload_0
/*    */     //   3984: getfield Np0 : Lf/Fy0;
/*    */     //   3987: astore_1
/*    */     //   3988: invokevirtual Ub : ()I
/*    */     //   3991: aload_1
/*    */     //   3992: swap
/*    */     //   3993: invokevirtual si : (Lf/JG0;I)V
/*    */     //   3996: getfield C0 : Lf/Ip;
/*    */     //   3999: dup
/*    */     //   4000: aload_0
/*    */     //   4001: getfield Aj0 : Lf/Fy0;
/*    */     //   4004: astore_1
/*    */     //   4005: invokevirtual Ub : ()I
/*    */     //   4008: aload_1
/*    */     //   4009: swap
/*    */     //   4010: invokevirtual si : (Lf/JG0;I)V
/*    */     //   4013: getfield C0 : Lf/Ip;
/*    */     //   4016: dup
/*    */     //   4017: aload_0
/*    */     //   4018: getfield ul : Lf/Q20;
/*    */     //   4021: astore_1
/*    */     //   4022: invokevirtual Ub : ()I
/*    */     //   4025: aload_1
/*    */     //   4026: swap
/*    */     //   4027: invokevirtual si : (Lf/JG0;I)V
/*    */     //   4030: getfield C0 : Lf/Ip;
/*    */     //   4033: dup
/*    */     //   4034: aload_0
/*    */     //   4035: getfield BY : Lf/vF0;
/*    */     //   4038: astore_1
/*    */     //   4039: invokevirtual Ub : ()I
/*    */     //   4042: aload_1
/*    */     //   4043: swap
/*    */     //   4044: invokevirtual si : (Lf/JG0;I)V
/*    */     //   4047: getfield C0 : Lf/Ip;
/*    */     //   4050: dup
/*    */     //   4051: aload_0
/*    */     //   4052: getfield Ez : Lf/Q20;
/*    */     //   4055: astore_1
/*    */     //   4056: invokevirtual Ub : ()I
/*    */     //   4059: aload_1
/*    */     //   4060: swap
/*    */     //   4061: invokevirtual si : (Lf/JG0;I)V
/*    */     //   4064: getfield C0 : Lf/Ip;
/*    */     //   4067: dup
/*    */     //   4068: aload_0
/*    */     //   4069: getfield aD : Lf/VP;
/*    */     //   4072: astore_1
/*    */     //   4073: invokevirtual Ub : ()I
/*    */     //   4076: aload_1
/*    */     //   4077: swap
/*    */     //   4078: invokevirtual si : (Lf/JG0;I)V
/*    */     //   4081: invokestatic LS : ()B
/*    */     //   4084: iconst_2
/*    */     //   4085: if_icmpeq -> 4108
/*    */     //   4088: invokestatic LS : ()B
/*    */     //   4091: iconst_3
/*    */     //   4092: if_icmpeq -> 4108
/*    */     //   4095: invokestatic LS : ()B
/*    */     //   4098: iconst_4
/*    */     //   4099: if_icmpeq -> 4108
/*    */     //   4102: aload_0
/*    */     //   4103: iconst_0
/*    */     //   4104: iconst_0
/*    */     //   4105: invokevirtual FW : (II)V
/*    */     //   4108: aload_0
/*    */     //   4109: dup
/*    */     //   4110: getfield Ez : Lf/Q20;
/*    */     //   4113: aload_0
/*    */     //   4114: getfield Iy : Lf/vF0;
/*    */     //   4117: getfield xY : I
/*    */     //   4120: bipush #35
/*    */     //   4122: invokevirtual Tm : (II)Z
/*    */     //   4125: pop
/*    */     //   4126: getfield z40 : Lf/o10;
/*    */     //   4129: ifnull -> 4228
/*    */     //   4132: aload_0
/*    */     //   4133: dup
/*    */     //   4134: getfield Ez : Lf/Q20;
/*    */     //   4137: iconst_1
/*    */     //   4138: invokevirtual wI0 : (Z)V
/*    */     //   4141: invokevirtual jm0 : ()Ljava/lang/String;
/*    */     //   4144: dup
/*    */     //   4145: astore_1
/*    */     //   4146: invokevirtual isEmpty : ()Z
/*    */     //   4149: ifne -> 4236
/*    */     //   4152: aload_0
/*    */     //   4153: getfield xv : Z
/*    */     //   4156: ifne -> 4236
/*    */     //   4159: aload_0
/*    */     //   4160: dup
/*    */     //   4161: dup2
/*    */     //   4162: iconst_1
/*    */     //   4163: putfield xv : Z
/*    */     //   4166: getfield Ze : Lf/dQ;
/*    */     //   4169: aload_1
/*    */     //   4170: invokevirtual E1 : (Ljava/lang/String;)V
/*    */     //   4173: getfield Vn : Lf/vF0;
/*    */     //   4176: getfield TS : Lf/rH;
/*    */     //   4179: astore_0
/*    */     //   4180: getstatic f/um0.Kt0 : Lf/um0;
/*    */     //   4183: astore_1
/*    */     //   4184: getfield z40 : Lf/o10;
/*    */     //   4187: dup
/*    */     //   4188: getfield GS : S
/*    */     //   4191: istore_2
/*    */     //   4192: iconst_m1
/*    */     //   4193: istore_3
/*    */     //   4194: getfield kT : Z
/*    */     //   4197: ifeq -> 4210
/*    */     //   4200: iload_2
/*    */     //   4201: ifle -> 4210
/*    */     //   4204: iconst_1
/*    */     //   4205: istore #4
/*    */     //   4207: goto -> 4213
/*    */     //   4210: iconst_0
/*    */     //   4211: istore #4
/*    */     //   4213: aload_0
/*    */     //   4214: aload_1
/*    */     //   4215: iload_2
/*    */     //   4216: iload #4
/*    */     //   4218: iload_3
/*    */     //   4219: invokevirtual lb : (SZB)[Lf/zh0;
/*    */     //   4222: invokevirtual sm : ([Lf/zh0;)V
/*    */     //   4225: goto -> 4236
/*    */     //   4228: aload_0
/*    */     //   4229: getfield Ez : Lf/Q20;
/*    */     //   4232: iconst_0
/*    */     //   4233: invokevirtual wI0 : (Z)V
/*    */     //   4236: return
/*    */     //   4237: return
/*    */     // Line number table:
/*    */     //   Java source line number -> byte code offset
/*    */     //   #1	-> 2
/*    */     //   #2	-> 43
/*    */     //   #3	-> 54
/*    */     //   #4	-> 59
/*    */     //   #5	-> 80
/*    */     //   #6	-> 84
/*    */     //   #7	-> 90
/*    */     //   #8	-> 98
/*    */     //   #9	-> 142
/*    */     //   #10	-> 149
/*    */     //   #11	-> 161
/*    */     //   #12	-> 168
/*    */     //   #13	-> 180
/*    */     //   #14	-> 187
/*    */     //   #15	-> 199
/*    */     //   #16	-> 206
/*    */     //   #17	-> 218
/*    */     //   #18	-> 225
/*    */     //   #19	-> 247
/*    */     //   #20	-> 250
/*    */     //   #21	-> 253
/*    */     //   #22	-> 333
/*    */     //   #23	-> 338
/*    */     //   #24	-> 342
/*    */     //   #25	-> 361
/*    */     //   #26	-> 374
/*    */     //   #27	-> 378
/*    */     //   #28	-> 388
/*    */     //   #29	-> 409
/*    */     //   #30	-> 438
/*    */     //   #31	-> 451
/*    */     //   #32	-> 497
/*    */     //   #33	-> 504
/*    */     //   #34	-> 569
/*    */     //   #35	-> 587
/*    */     //   #36	-> 629
/*    */     //   #37	-> 633
/*    */     //   #38	-> 642
/*    */     //   #39	-> 649
/*    */     //   #40	-> 652
/*    */     //   #41	-> 656
/*    */     //   #42	-> 660
/*    */     //   #43	-> 675
/*    */     //   #44	-> 680
/*    */     //   #45	-> 687
/*    */     //   #46	-> 692
/*    */     //   #47	-> 696
/*    */     //   #48	-> 704
/*    */     //   #49	-> 709
/*    */     //   #50	-> 721
/*    */     //   #51	-> 726
/*    */     //   #52	-> 729
/*    */     //   #53	-> 791
/*    */     //   #54	-> 794
/*    */     //   #55	-> 801
/*    */     //   #56	-> 814
/*    */     //   #57	-> 818
/*    */     //   #58	-> 825
/*    */     //   #59	-> 830
/*    */     //   #60	-> 845
/*    */     //   #61	-> 848
/*    */     //   #62	-> 853
/*    */     //   #63	-> 870
/*    */     //   #64	-> 877
/*    */     //   #65	-> 889
/*    */     //   #66	-> 900
/*    */     //   #67	-> 920
/*    */     //   #68	-> 945
/*    */     //   #69	-> 948
/*    */     //   #70	-> 973
/*    */     //   #71	-> 979
/*    */     //   #72	-> 1002
/*    */     //   #73	-> 1005
/*    */     //   #74	-> 1009
/*    */     //   #75	-> 1104
/*    */     //   #76	-> 1108
/*    */     //   #77	-> 1115
/*    */     //   #78	-> 1120
/*    */     //   #79	-> 1125
/*    */     //   #80	-> 1175
/*    */     //   #81	-> 1179
/*    */     //   #82	-> 1183
/*    */     //   #83	-> 1224
/*    */     //   #84	-> 1228
/*    */     //   #85	-> 1252
/*    */     //   #86	-> 1255
/*    */     //   #87	-> 1261
/*    */     //   #88	-> 1267
/*    */     //   #89	-> 1272
/*    */     //   #90	-> 1278
/*    */     //   #91	-> 1304
/*    */     //   #92	-> 1326
/*    */     //   #93	-> 1331
/*    */     //   #94	-> 1337
/*    */     //   #95	-> 1340
/*    */     //   #96	-> 1343
/*    */     //   #97	-> 1348
/*    */     //   #98	-> 1351
/*    */     //   #99	-> 1354
/*    */     //   #100	-> 1357
/*    */     //   #101	-> 1387
/*    */     //   #102	-> 1407
/*    */     //   #103	-> 1456
/*    */     //   #104	-> 1471
/*    */     //   #105	-> 1530
/*    */     //   #106	-> 1533
/*    */     //   #107	-> 1539
/*    */     //   #108	-> 1545
/*    */     //   #109	-> 1550
/*    */     //   #110	-> 1556
/*    */     //   #111	-> 1593
/*    */     //   #112	-> 1598
/*    */     //   #113	-> 1604
/*    */     //   #114	-> 1607
/*    */     //   #115	-> 1610
/*    */     //   #116	-> 1615
/*    */     //   #117	-> 1618
/*    */     //   #118	-> 1621
/*    */     //   #119	-> 1624
/*    */     //   #120	-> 1793
/*    */     //   #121	-> 1796
/*    */     //   #122	-> 1810
/*    */     //   #123	-> 1813
/*    */     //   #124	-> 1817
/*    */     //   #125	-> 1822
/*    */     //   #126	-> 1825
/*    */     //   #127	-> 1830
/*    */     //   #128	-> 1848
/*    */     //   #129	-> 1856
/*    */     //   #130	-> 1877
/*    */     //   #131	-> 1883
/*    */     //   #132	-> 1969
/*    */     //   #133	-> 1974
/*    */     //   #134	-> 2224
/*    */     //   #135	-> 2227
/*    */     //   #136	-> 2233
/*    */     //   #137	-> 2239
/*    */     //   #138	-> 2244
/*    */     //   #139	-> 2250
/*    */     //   #140	-> 2274
/*    */     //   #141	-> 2279
/*    */     //   #142	-> 2285
/*    */     //   #143	-> 2288
/*    */     //   #144	-> 2291
/*    */     //   #145	-> 2296
/*    */     //   #146	-> 2299
/*    */     //   #147	-> 2302
/*    */     //   #148	-> 2305
/*    */     //   #149	-> 2319
/*    */     //   #150	-> 2327
/*    */     //   #151	-> 2348
/*    */     //   #152	-> 2354
/*    */     //   #153	-> 2512
/*    */     //   #154	-> 2515
/*    */     //   #155	-> 2529
/*    */     //   #156	-> 2532
/*    */     //   #157	-> 2536
/*    */     //   #158	-> 2541
/*    */     //   #159	-> 2544
/*    */     //   #160	-> 2549
/*    */     //   #161	-> 2604
/*    */     //   #162	-> 2609
/*    */     //   #163	-> 2764
/*    */     //   #164	-> 2767
/*    */     //   #165	-> 2771
/*    */     //   #166	-> 2772
/*    */     //   #167	-> 2775
/*    */     //   #168	-> 2959
/*    */     //   #169	-> 2962
/*    */     //   #170	-> 2968
/*    */     //   #171	-> 2974
/*    */     //   #172	-> 2979
/*    */     //   #173	-> 2985
/*    */     //   #174	-> 3009
/*    */     //   #175	-> 3014
/*    */     //   #176	-> 3020
/*    */     //   #177	-> 3023
/*    */     //   #178	-> 3026
/*    */     //   #179	-> 3031
/*    */     //   #180	-> 3034
/*    */     //   #181	-> 3037
/*    */     //   #182	-> 3040
/*    */     //   #183	-> 3276
/*    */     //   #184	-> 3279
/*    */     //   #185	-> 3284
/*    */     //   #186	-> 3285
/*    */     //   #187	-> 3290
/*    */     //   #188	-> 3331
/*    */     //   #189	-> 3335
/*    */     //   #190	-> 3346
/*    */     //   #191	-> 3353
/*    */     //   #192	-> 3396
/*    */     //   #193	-> 3399
/*    */     //   #194	-> 3420
/*    */     //   #195	-> 3424
/*    */     //   #196	-> 3436
/*    */     //   #197	-> 3444
/*    */     //   #198	-> 3576
/*    */     //   #199	-> 3583
/*    */     //   #200	-> 3594
/*    */     //   #201	-> 3597
/*    */     //   #202	-> 3602
/*    */     //   #203	-> 3631
/*    */     //   #204	-> 3730
/*    */     //   #205	-> 3734
/*    */     //   #206	-> 3880
/*    */     //   #207	-> 3883
/*    */     //   #208	-> 3890
/*    */     //   #209	-> 3923
/*    */     //   #210	-> 3926
/*    */     //   #211	-> 3933
/*    */     //   #212	-> 3966
/*    */     //   #213	-> 3969
/*    */     //   #214	-> 3979
/*    */     //   #215	-> 3988
/*    */     //   #216	-> 3993
/*    */     //   #217	-> 3996
/*    */     //   #218	-> 4005
/*    */     //   #219	-> 4010
/*    */     //   #220	-> 4013
/*    */     //   #221	-> 4022
/*    */     //   #222	-> 4027
/*    */     //   #223	-> 4030
/*    */     //   #224	-> 4039
/*    */     //   #225	-> 4044
/*    */     //   #226	-> 4047
/*    */     //   #227	-> 4056
/*    */     //   #228	-> 4061
/*    */     //   #229	-> 4064
/*    */     //   #230	-> 4073
/*    */     //   #231	-> 4078
/*    */     //   #232	-> 4081
/*    */     //   #233	-> 4117
/*    */     //   #234	-> 4122
/*    */     //   #235	-> 4176
/*    */     //   #236	-> 4180
/*    */     //   #237	-> 4184
/*    */   }
/*    */   
/*    */   public final String jm0() {
/*    */     String str = "";
/*    */     o10 o101;
/*    */     if ((o101 = this.z40) != null) {
/*    */       byte b;
/*    */       if ((b = o101.hn) != 0) {
/*    */         if (b != 1) {
/*    */           str = o101.RB.getName();
/*    */         } else {
/*    */           str = Ml0.la((o101.lPt1 & 0xFF) + 141000, "");
/*    */         } 
/*    */       } else {
/*    */         str = Ml0.la((o101.lPt1 & 0xFF) + 140000 - 88, "");
/*    */       } 
/*    */       o10 o102;
/*    */       if ((o102 = this.z40).kT) {
/*    */         String[] arrayOfString;
/*    */         (arrayOfString = new String[2])[0] = Ml0.OH0(this.GS + 150000);
/*    */         (new String[2])[1] = str;
/*    */         str = Ml0.sB(16777247, arrayOfString);
/*    */       } else {
/*    */         String[] arrayOfString;
/*    */         (arrayOfString = new String[2])[0] = Ml0.OH0(this.GS + 150000);
/*    */         (new String[2])[1] = str;
/*    */         str = Ml0.sB(16777246, arrayOfString);
/*    */       } 
/*    */     } 
/*    */     return str;
/*    */   }
/*    */   
/*    */   public final void k80() {
/*    */     vh0 vh0;
/*    */     if ((vh0 = km.a3) == null || vh0.Jr0() == null) {
/*    */       this.zy.E1("");
/*    */       return;
/*    */     } 
/*    */     String str = km.a3.Jr0().xc0();
/*    */     if (!this.Kk.wL.toString().isEmpty() && !str.isEmpty() && !str.equalsIgnoreCase("???") && this.j8 == this.wt && this.iG == this.Vp0 && !this.Kk.wL.toString().equalsIgnoreCase(str)) {
/*    */       this.zy.E1(str);
/*    */     } else {
/*    */       this.zy.E1("");
/*    */     } 
/*    */   } }


/* Location:              /Users/vnnsnnt/Documents/Codespace/JavaWorkspace/RedTrainer/src/main/java/org/trainer/client/PokeMMO.jar!/f/fr.class
 * Java compiler version: 8 (52.0)
 * JD-Core Version:       1.1.3
 */