/*  1 */ package f;public final class fw0 { public static final ik Z40 = C00.gd(fw0.class); public RandomAccessFile zj0; public MappedByteBuffer Og; public S4 ZM = new S4(); public Ws0[] Wb0; public int bu = 0; public int KN = 0; public int FK0 = 0; public final boolean xp(KB0 paramKB0, VV paramVV, Bs paramBs) { int i = this.Og.position(); try { boolean bool; Q1 q1 = Q1.tB(paramBs.qq()); if (paramBs.rM.bO() == 4 && paramBs
/*  2 */         .MV == 225)
/*  3 */         S9.vS(q1.Nt[0]);  eI eI = eI.Lj(); hC hC = q1.Nt[0]; if (paramVV == VV.transient) { bool = true; } else { bool = false; }  eI.getClass(); this.Og
/*    */         
/*  5 */         .putInt(paramBs.MV); int k = this.Og.position(); this.Og.putInt(-1); int j = this.Og.position(); this.Og.putInt(k, j - k - 4); lpt1 lpt1; (lpt1 = eI.T40(hC, paramKB0, bool)).Ea0(); return true; } catch (Exception exception) { Z40
/*    */ 
/*    */         
/*  8 */         .error(B40.df("could not write map cache model ").append(paramBs.MV).toString(), exception); this.Og.position(i); return false; }  }
/*    */   public int UD = -1; public int XJ0 = -1; public ig e10 = null; public boolean rK = false; public boolean Nul = false; public byte KG0; public fw0(byte paramByte, hZ paramhZ, int paramInt) { this.KG0 = paramByte; paramhZ.wT().iz0(); this(paramhZ.bo(), "rw"); this.zj0 = randomAccessFile; long l; RandomAccessFile randomAccessFile; (randomAccessFile = new RandomAccessFile()).setLength(l = paramInt); (this.Og = this.zj0.getChannel().map(FileChannel.MapMode.READ_WRITE, 0L, l)).order(ByteOrder.nativeOrder()); this.Og.putInt(-1); this.Og.putInt(0); this.Wb0 = km.mI0.LpT7(paramByte).I80().IT(); } public final boolean Qm() { // Byte code:
/*    */     //   0: aload_0
/*    */     //   1: getfield Og : Ljava/nio/MappedByteBuffer;
/*    */     //   4: ifnonnull -> 9
/*    */     //   7: iconst_1
/*    */     //   8: ireturn
/*    */     //   9: aload_0
/*    */     //   10: getfield rK : Z
/*    */     //   13: ifne -> 1480
/*    */     //   16: aload_0
/*    */     //   17: getfield KG0 : B
/*    */     //   20: dup
/*    */     //   21: istore_1
/*    */     //   22: iconst_2
/*    */     //   23: if_icmpeq -> 868
/*    */     //   26: iload_1
/*    */     //   27: iconst_3
/*    */     //   28: if_icmpeq -> 382
/*    */     //   31: iload_1
/*    */     //   32: iconst_4
/*    */     //   33: if_icmpeq -> 39
/*    */     //   36: goto -> 1478
/*    */     //   39: aload_0
/*    */     //   40: getfield KN : I
/*    */     //   43: bipush #10
/*    */     //   45: iadd
/*    */     //   46: istore_1
/*    */     //   47: aload_0
/*    */     //   48: getfield KN : I
/*    */     //   51: dup
/*    */     //   52: istore_2
/*    */     //   53: iload_1
/*    */     //   54: if_icmpge -> 351
/*    */     //   57: iload_2
/*    */     //   58: aload_0
/*    */     //   59: getfield Wb0 : [Lf/Ws0;
/*    */     //   62: dup
/*    */     //   63: astore_3
/*    */     //   64: arraylength
/*    */     //   65: if_icmpge -> 351
/*    */     //   68: aload_3
/*    */     //   69: iload_2
/*    */     //   70: aaload
/*    */     //   71: dup
/*    */     //   72: astore_2
/*    */     //   73: getfield P2 : Lf/uz0;
/*    */     //   76: dup
/*    */     //   77: astore_3
/*    */     //   78: ifnonnull -> 89
/*    */     //   81: aload_2
/*    */     //   82: getfield COm4 : S
/*    */     //   85: istore_3
/*    */     //   86: goto -> 94
/*    */     //   89: aload_3
/*    */     //   90: getfield DG : S
/*    */     //   93: istore_3
/*    */     //   94: aload_2
/*    */     //   95: invokevirtual hG0 : ()Z
/*    */     //   98: ifeq -> 109
/*    */     //   101: getstatic f/VV.transient : Lf/VV;
/*    */     //   104: astore #4
/*    */     //   106: goto -> 114
/*    */     //   109: getstatic f/VV.i60 : Lf/VV;
/*    */     //   112: astore #4
/*    */     //   114: aload_2
/*    */     //   115: getstatic f/km.mI0 : Lf/P1;
/*    */     //   118: getfield yE : Lf/BE;
/*    */     //   121: getfield aB0 : Lf/V60;
/*    */     //   124: iload_3
/*    */     //   125: invokevirtual eD : (I)Lf/KB0;
/*    */     //   128: astore_2
/*    */     //   129: getstatic f/km.mI0 : Lf/P1;
/*    */     //   132: getfield yE : Lf/BE;
/*    */     //   135: astore_3
/*    */     //   136: getfield F70 : S
/*    */     //   139: dup
/*    */     //   140: istore #5
/*    */     //   142: aload_3
/*    */     //   143: getfield uF : [Lf/lF0;
/*    */     //   146: dup
/*    */     //   147: astore_3
/*    */     //   148: arraylength
/*    */     //   149: if_icmplt -> 157
/*    */     //   152: aconst_null
/*    */     //   153: astore_3
/*    */     //   154: goto -> 165
/*    */     //   157: aload_3
/*    */     //   158: iload #5
/*    */     //   160: aaload
/*    */     //   161: checkcast f/mF
/*    */     //   164: astore_3
/*    */     //   165: iconst_0
/*    */     //   166: istore #5
/*    */     //   168: iload #5
/*    */     //   170: aload_3
/*    */     //   171: getfield X7 : S
/*    */     //   174: if_icmpge -> 326
/*    */     //   177: iconst_0
/*    */     //   178: istore #6
/*    */     //   180: iload #6
/*    */     //   182: aload_3
/*    */     //   183: getfield cB0 : S
/*    */     //   186: if_icmpge -> 320
/*    */     //   189: aload_3
/*    */     //   190: dup
/*    */     //   191: getfield U1 : [[I
/*    */     //   194: iload #5
/*    */     //   196: aaload
/*    */     //   197: iload #6
/*    */     //   199: iaload
/*    */     //   200: i2s
/*    */     //   201: istore #7
/*    */     //   203: getfield H80 : [[I
/*    */     //   206: dup
/*    */     //   207: astore #8
/*    */     //   209: ifnull -> 240
/*    */     //   212: aload #8
/*    */     //   214: iload #5
/*    */     //   216: aaload
/*    */     //   217: iload #6
/*    */     //   219: iaload
/*    */     //   220: i2s
/*    */     //   221: dup
/*    */     //   222: istore #8
/*    */     //   224: iconst_m1
/*    */     //   225: if_icmpeq -> 314
/*    */     //   228: iload #8
/*    */     //   230: aload_0
/*    */     //   231: getfield KN : I
/*    */     //   234: if_icmpeq -> 240
/*    */     //   237: goto -> 314
/*    */     //   240: iload #7
/*    */     //   242: iflt -> 314
/*    */     //   245: aload_0
/*    */     //   246: getstatic f/km.mI0 : Lf/P1;
/*    */     //   249: getfield yE : Lf/BE;
/*    */     //   252: iload #7
/*    */     //   254: invokevirtual Ea0 : (I)Lf/Bs;
/*    */     //   257: checkcast f/yU
/*    */     //   260: astore #8
/*    */     //   262: getfield ZM : Lf/S4;
/*    */     //   265: iload #7
/*    */     //   267: invokevirtual MN : (I)Z
/*    */     //   270: ifne -> 307
/*    */     //   273: aload_0
/*    */     //   274: aload_2
/*    */     //   275: aload_0
/*    */     //   276: getfield ZM : Lf/S4;
/*    */     //   279: iload #7
/*    */     //   281: invokevirtual V9 : (I)V
/*    */     //   284: aload #4
/*    */     //   286: aload #8
/*    */     //   288: invokevirtual xp : (Lf/KB0;Lf/VV;Lf/Bs;)Z
/*    */     //   291: ifeq -> 314
/*    */     //   294: aload_0
/*    */     //   295: dup
/*    */     //   296: getfield bu : I
/*    */     //   299: iconst_1
/*    */     //   300: iadd
/*    */     //   301: putfield bu : I
/*    */     //   304: goto -> 314
/*    */     //   307: getstatic f/fw0.Z40 : Lf/ik;
/*    */     //   310: invokevirtual getClass : ()Ljava/lang/Class;
/*    */     //   313: pop
/*    */     //   314: iinc #6, 1
/*    */     //   317: goto -> 180
/*    */     //   320: iinc #5, 1
/*    */     //   323: goto -> 168
/*    */     //   326: aload_0
/*    */     //   327: dup
/*    */     //   328: getstatic f/km.mI0 : Lf/P1;
/*    */     //   331: getfield yE : Lf/BE;
/*    */     //   334: getfield aB0 : Lf/V60;
/*    */     //   337: invokevirtual vO : ()V
/*    */     //   340: getfield KN : I
/*    */     //   343: iconst_1
/*    */     //   344: iadd
/*    */     //   345: putfield KN : I
/*    */     //   348: goto -> 47
/*    */     //   351: iload_2
/*    */     //   352: aload_0
/*    */     //   353: getfield Wb0 : [Lf/Ws0;
/*    */     //   356: arraylength
/*    */     //   357: if_icmplt -> 1478
/*    */     //   360: aload_0
/*    */     //   361: dup
/*    */     //   362: iconst_1
/*    */     //   363: putfield rK : Z
/*    */     //   366: getfield Og : Ljava/nio/MappedByteBuffer;
/*    */     //   369: aload_0
/*    */     //   370: getfield bu : I
/*    */     //   373: iconst_4
/*    */     //   374: swap
/*    */     //   375: invokevirtual putInt : (II)Ljava/nio/ByteBuffer;
/*    */     //   378: pop
/*    */     //   379: goto -> 1478
/*    */     //   382: aload_0
/*    */     //   383: getfield KN : I
/*    */     //   386: bipush #10
/*    */     //   388: iadd
/*    */     //   389: istore_1
/*    */     //   390: aload_0
/*    */     //   391: getfield KN : I
/*    */     //   394: dup
/*    */     //   395: istore_2
/*    */     //   396: iload_1
/*    */     //   397: if_icmpge -> 837
/*    */     //   400: iload_2
/*    */     //   401: aload_0
/*    */     //   402: getfield Wb0 : [Lf/Ws0;
/*    */     //   405: dup
/*    */     //   406: astore_3
/*    */     //   407: arraylength
/*    */     //   408: if_icmpge -> 837
/*    */     //   411: aload_3
/*    */     //   412: iload_2
/*    */     //   413: aaload
/*    */     //   414: dup
/*    */     //   415: astore_2
/*    */     //   416: getfield P2 : Lf/uz0;
/*    */     //   419: dup
/*    */     //   420: astore_3
/*    */     //   421: ifnonnull -> 432
/*    */     //   424: aload_2
/*    */     //   425: getfield COm4 : S
/*    */     //   428: istore_3
/*    */     //   429: goto -> 437
/*    */     //   432: aload_3
/*    */     //   433: getfield DG : S
/*    */     //   436: istore_3
/*    */     //   437: aload_2
/*    */     //   438: invokevirtual hG0 : ()Z
/*    */     //   441: ifeq -> 452
/*    */     //   444: getstatic f/VV.transient : Lf/VV;
/*    */     //   447: astore #4
/*    */     //   449: goto -> 457
/*    */     //   452: getstatic f/VV.i60 : Lf/VV;
/*    */     //   455: astore #4
/*    */     //   457: aload_2
/*    */     //   458: getstatic f/km.mI0 : Lf/P1;
/*    */     //   461: getfield MT : Lf/gD;
/*    */     //   464: getfield aB0 : Lf/V60;
/*    */     //   467: iload_3
/*    */     //   468: invokevirtual eD : (I)Lf/KB0;
/*    */     //   471: astore_2
/*    */     //   472: getstatic f/km.mI0 : Lf/P1;
/*    */     //   475: getfield MT : Lf/gD;
/*    */     //   478: astore #5
/*    */     //   480: getfield F70 : S
/*    */     //   483: dup
/*    */     //   484: istore #6
/*    */     //   486: aload #5
/*    */     //   488: getfield uF : [Lf/lF0;
/*    */     //   491: dup
/*    */     //   492: astore #5
/*    */     //   494: arraylength
/*    */     //   495: if_icmplt -> 504
/*    */     //   498: aconst_null
/*    */     //   499: astore #5
/*    */     //   501: goto -> 514
/*    */     //   504: aload #5
/*    */     //   506: iload #6
/*    */     //   508: aaload
/*    */     //   509: checkcast f/mF
/*    */     //   512: astore #5
/*    */     //   514: iconst_0
/*    */     //   515: istore #6
/*    */     //   517: iload #6
/*    */     //   519: aload #5
/*    */     //   521: getfield X7 : S
/*    */     //   524: if_icmpge -> 812
/*    */     //   527: iconst_0
/*    */     //   528: istore #7
/*    */     //   530: iload #7
/*    */     //   532: aload #5
/*    */     //   534: getfield cB0 : S
/*    */     //   537: if_icmpge -> 806
/*    */     //   540: aload #5
/*    */     //   542: dup
/*    */     //   543: getfield U1 : [[I
/*    */     //   546: iload #6
/*    */     //   548: aaload
/*    */     //   549: iload #7
/*    */     //   551: iaload
/*    */     //   552: i2s
/*    */     //   553: istore #8
/*    */     //   555: getfield H80 : [[I
/*    */     //   558: dup
/*    */     //   559: astore #9
/*    */     //   561: ifnull -> 592
/*    */     //   564: aload #9
/*    */     //   566: iload #6
/*    */     //   568: aaload
/*    */     //   569: iload #7
/*    */     //   571: iaload
/*    */     //   572: i2s
/*    */     //   573: dup
/*    */     //   574: istore #9
/*    */     //   576: iconst_m1
/*    */     //   577: if_icmpeq -> 800
/*    */     //   580: iload #9
/*    */     //   582: aload_0
/*    */     //   583: getfield KN : I
/*    */     //   586: if_icmpeq -> 592
/*    */     //   589: goto -> 800
/*    */     //   592: iload #8
/*    */     //   594: iflt -> 800
/*    */     //   597: aload_0
/*    */     //   598: getstatic f/km.mI0 : Lf/P1;
/*    */     //   601: getfield MT : Lf/gD;
/*    */     //   604: iload #8
/*    */     //   606: invokevirtual Ea0 : (I)Lf/Bs;
/*    */     //   609: checkcast f/yU
/*    */     //   612: astore #9
/*    */     //   614: getfield ZM : Lf/S4;
/*    */     //   617: iload #8
/*    */     //   619: invokevirtual MN : (I)Z
/*    */     //   622: ifne -> 793
/*    */     //   625: iload #8
/*    */     //   627: sipush #173
/*    */     //   630: if_icmplt -> 759
/*    */     //   633: iload #8
/*    */     //   635: sipush #180
/*    */     //   638: if_icmpge -> 759
/*    */     //   641: iload #8
/*    */     //   643: sipush #177
/*    */     //   646: if_icmpeq -> 740
/*    */     //   649: iload #8
/*    */     //   651: sipush #178
/*    */     //   654: if_icmpne -> 660
/*    */     //   657: goto -> 740
/*    */     //   660: iload #8
/*    */     //   662: sipush #173
/*    */     //   665: if_icmpne -> 676
/*    */     //   668: bipush #6
/*    */     //   670: istore_2
/*    */     //   671: iload_2
/*    */     //   672: istore_3
/*    */     //   673: goto -> 745
/*    */     //   676: iload #8
/*    */     //   678: sipush #174
/*    */     //   681: if_icmpne -> 692
/*    */     //   684: bipush #15
/*    */     //   686: istore_2
/*    */     //   687: iload_2
/*    */     //   688: istore_3
/*    */     //   689: goto -> 745
/*    */     //   692: iload #8
/*    */     //   694: sipush #175
/*    */     //   697: if_icmpne -> 708
/*    */     //   700: bipush #7
/*    */     //   702: istore_2
/*    */     //   703: iload_2
/*    */     //   704: istore_3
/*    */     //   705: goto -> 745
/*    */     //   708: iload #8
/*    */     //   710: sipush #176
/*    */     //   713: if_icmpne -> 724
/*    */     //   716: bipush #12
/*    */     //   718: istore_2
/*    */     //   719: iload_2
/*    */     //   720: istore_3
/*    */     //   721: goto -> 745
/*    */     //   724: iload #8
/*    */     //   726: sipush #179
/*    */     //   729: if_icmpne -> 745
/*    */     //   732: bipush #19
/*    */     //   734: istore_2
/*    */     //   735: iload_2
/*    */     //   736: istore_3
/*    */     //   737: goto -> 745
/*    */     //   740: bipush #14
/*    */     //   742: istore_2
/*    */     //   743: iload_2
/*    */     //   744: istore_3
/*    */     //   745: getstatic f/km.mI0 : Lf/P1;
/*    */     //   748: getfield MT : Lf/gD;
/*    */     //   751: getfield aB0 : Lf/V60;
/*    */     //   754: iload_3
/*    */     //   755: invokevirtual eD : (I)Lf/KB0;
/*    */     //   758: astore_2
/*    */     //   759: aload_0
/*    */     //   760: aload_2
/*    */     //   761: aload_0
/*    */     //   762: getfield ZM : Lf/S4;
/*    */     //   765: iload #8
/*    */     //   767: invokevirtual V9 : (I)V
/*    */     //   770: aload #4
/*    */     //   772: aload #9
/*    */     //   774: invokevirtual xp : (Lf/KB0;Lf/VV;Lf/Bs;)Z
/*    */     //   777: ifeq -> 800
/*    */     //   780: aload_0
/*    */     //   781: dup
/*    */     //   782: getfield bu : I
/*    */     //   785: iconst_1
/*    */     //   786: iadd
/*    */     //   787: putfield bu : I
/*    */     //   790: goto -> 800
/*    */     //   793: getstatic f/fw0.Z40 : Lf/ik;
/*    */     //   796: invokevirtual getClass : ()Ljava/lang/Class;
/*    */     //   799: pop
/*    */     //   800: iinc #7, 1
/*    */     //   803: goto -> 530
/*    */     //   806: iinc #6, 1
/*    */     //   809: goto -> 517
/*    */     //   812: aload_0
/*    */     //   813: dup
/*    */     //   814: getstatic f/km.mI0 : Lf/P1;
/*    */     //   817: getfield MT : Lf/gD;
/*    */     //   820: getfield aB0 : Lf/V60;
/*    */     //   823: invokevirtual vO : ()V
/*    */     //   826: getfield KN : I
/*    */     //   829: iconst_1
/*    */     //   830: iadd
/*    */     //   831: putfield KN : I
/*    */     //   834: goto -> 390
/*    */     //   837: iload_2
/*    */     //   838: aload_0
/*    */     //   839: getfield Wb0 : [Lf/Ws0;
/*    */     //   842: arraylength
/*    */     //   843: if_icmplt -> 1478
/*    */     //   846: aload_0
/*    */     //   847: dup
/*    */     //   848: iconst_1
/*    */     //   849: putfield rK : Z
/*    */     //   852: getfield Og : Ljava/nio/MappedByteBuffer;
/*    */     //   855: aload_0
/*    */     //   856: getfield bu : I
/*    */     //   859: iconst_4
/*    */     //   860: swap
/*    */     //   861: invokevirtual putInt : (II)Ljava/nio/ByteBuffer;
/*    */     //   864: pop
/*    */     //   865: goto -> 1478
/*    */     //   868: aload_0
/*    */     //   869: getfield KN : I
/*    */     //   872: bipush #10
/*    */     //   874: iadd
/*    */     //   875: istore_1
/*    */     //   876: aload_0
/*    */     //   877: getfield KN : I
/*    */     //   880: dup
/*    */     //   881: istore_2
/*    */     //   882: iload_1
/*    */     //   883: if_icmpge -> 1450
/*    */     //   886: iload_2
/*    */     //   887: aload_0
/*    */     //   888: getfield Wb0 : [Lf/Ws0;
/*    */     //   891: dup
/*    */     //   892: astore_3
/*    */     //   893: arraylength
/*    */     //   894: if_icmpge -> 1450
/*    */     //   897: aload_3
/*    */     //   898: iload_2
/*    */     //   899: aaload
/*    */     //   900: dup
/*    */     //   901: dup
/*    */     //   902: astore_2
/*    */     //   903: getfield P2 : Lf/uz0;
/*    */     //   906: getfield DG : S
/*    */     //   909: istore_3
/*    */     //   910: invokevirtual hG0 : ()Z
/*    */     //   913: ifeq -> 924
/*    */     //   916: getstatic f/VV.transient : Lf/VV;
/*    */     //   919: astore #4
/*    */     //   921: goto -> 929
/*    */     //   924: getstatic f/VV.i60 : Lf/VV;
/*    */     //   927: astore #4
/*    */     //   929: getstatic f/km.mI0 : Lf/P1;
/*    */     //   932: getfield AN : Lf/Wo;
/*    */     //   935: getfield aB0 : Lf/V60;
/*    */     //   938: iload_3
/*    */     //   939: invokevirtual eD : (I)Lf/KB0;
/*    */     //   942: astore_3
/*    */     //   943: getstatic f/km.mI0 : Lf/P1;
/*    */     //   946: getfield AN : Lf/Wo;
/*    */     //   949: aload_2
/*    */     //   950: getfield F70 : S
/*    */     //   953: invokevirtual Sk : (I)Lf/lF0;
/*    */     //   956: astore_2
/*    */     //   957: iconst_0
/*    */     //   958: istore #5
/*    */     //   960: iload #5
/*    */     //   962: aload_2
/*    */     //   963: getfield X7 : S
/*    */     //   966: if_icmpge -> 1118
/*    */     //   969: iconst_0
/*    */     //   970: istore #6
/*    */     //   972: iload #6
/*    */     //   974: aload_2
/*    */     //   975: getfield cB0 : S
/*    */     //   978: if_icmpge -> 1112
/*    */     //   981: aload_2
/*    */     //   982: dup
/*    */     //   983: getfield U1 : [[I
/*    */     //   986: iload #5
/*    */     //   988: aaload
/*    */     //   989: iload #6
/*    */     //   991: iaload
/*    */     //   992: i2s
/*    */     //   993: istore #7
/*    */     //   995: getfield H80 : [[I
/*    */     //   998: dup
/*    */     //   999: astore #8
/*    */     //   1001: ifnull -> 1032
/*    */     //   1004: aload #8
/*    */     //   1006: iload #5
/*    */     //   1008: aaload
/*    */     //   1009: iload #6
/*    */     //   1011: iaload
/*    */     //   1012: i2s
/*    */     //   1013: dup
/*    */     //   1014: istore #8
/*    */     //   1016: iconst_m1
/*    */     //   1017: if_icmpeq -> 1106
/*    */     //   1020: iload #8
/*    */     //   1022: aload_0
/*    */     //   1023: getfield KN : I
/*    */     //   1026: if_icmpeq -> 1032
/*    */     //   1029: goto -> 1106
/*    */     //   1032: iload #7
/*    */     //   1034: iflt -> 1106
/*    */     //   1037: aload_0
/*    */     //   1038: getstatic f/km.mI0 : Lf/P1;
/*    */     //   1041: getfield AN : Lf/Wo;
/*    */     //   1044: iload #7
/*    */     //   1046: invokevirtual Ea0 : (I)Lf/Bs;
/*    */     //   1049: checkcast f/LW
/*    */     //   1052: astore #8
/*    */     //   1054: getfield ZM : Lf/S4;
/*    */     //   1057: iload #7
/*    */     //   1059: invokevirtual MN : (I)Z
/*    */     //   1062: ifne -> 1099
/*    */     //   1065: aload_0
/*    */     //   1066: aload_3
/*    */     //   1067: aload_0
/*    */     //   1068: getfield ZM : Lf/S4;
/*    */     //   1071: iload #7
/*    */     //   1073: invokevirtual V9 : (I)V
/*    */     //   1076: aload #4
/*    */     //   1078: aload #8
/*    */     //   1080: invokevirtual xp : (Lf/KB0;Lf/VV;Lf/Bs;)Z
/*    */     //   1083: ifeq -> 1106
/*    */     //   1086: aload_0
/*    */     //   1087: dup
/*    */     //   1088: getfield bu : I
/*    */     //   1091: iconst_1
/*    */     //   1092: iadd
/*    */     //   1093: putfield bu : I
/*    */     //   1096: goto -> 1106
/*    */     //   1099: getstatic f/fw0.Z40 : Lf/ik;
/*    */     //   1102: invokevirtual getClass : ()Ljava/lang/Class;
/*    */     //   1105: pop
/*    */     //   1106: iinc #6, 1
/*    */     //   1109: goto -> 972
/*    */     //   1112: iinc #5, 1
/*    */     //   1115: goto -> 960
/*    */     //   1118: aload_0
/*    */     //   1119: getfield KN : I
/*    */     //   1122: dup
/*    */     //   1123: istore_2
/*    */     //   1124: bipush #16
/*    */     //   1126: if_icmpne -> 1178
/*    */     //   1129: aload_0
/*    */     //   1130: bipush #104
/*    */     //   1132: istore_2
/*    */     //   1133: getfield ZM : Lf/S4;
/*    */     //   1136: iload_2
/*    */     //   1137: invokevirtual MN : (I)Z
/*    */     //   1140: ifne -> 1425
/*    */     //   1143: aload_0
/*    */     //   1144: aload_3
/*    */     //   1145: aload_0
/*    */     //   1146: getfield ZM : Lf/S4;
/*    */     //   1149: iload_2
/*    */     //   1150: invokevirtual V9 : (I)V
/*    */     //   1153: getstatic f/km.mI0 : Lf/P1;
/*    */     //   1156: getfield AN : Lf/Wo;
/*    */     //   1159: iload_2
/*    */     //   1160: invokevirtual Ea0 : (I)Lf/Bs;
/*    */     //   1163: checkcast f/LW
/*    */     //   1166: aload #4
/*    */     //   1168: swap
/*    */     //   1169: invokevirtual xp : (Lf/KB0;Lf/VV;Lf/Bs;)Z
/*    */     //   1172: ifeq -> 1425
/*    */     //   1175: goto -> 1415
/*    */     //   1178: iload_2
/*    */     //   1179: bipush #96
/*    */     //   1181: if_icmpne -> 1290
/*    */     //   1184: aload_0
/*    */     //   1185: sipush #204
/*    */     //   1188: istore_2
/*    */     //   1189: getfield ZM : Lf/S4;
/*    */     //   1192: iload_2
/*    */     //   1193: invokevirtual MN : (I)Z
/*    */     //   1196: ifne -> 1241
/*    */     //   1199: aload_0
/*    */     //   1200: aload_3
/*    */     //   1201: aload_0
/*    */     //   1202: getfield ZM : Lf/S4;
/*    */     //   1205: iload_2
/*    */     //   1206: invokevirtual V9 : (I)V
/*    */     //   1209: getstatic f/km.mI0 : Lf/P1;
/*    */     //   1212: getfield AN : Lf/Wo;
/*    */     //   1215: iload_2
/*    */     //   1216: invokevirtual Ea0 : (I)Lf/Bs;
/*    */     //   1219: checkcast f/LW
/*    */     //   1222: aload #4
/*    */     //   1224: swap
/*    */     //   1225: invokevirtual xp : (Lf/KB0;Lf/VV;Lf/Bs;)Z
/*    */     //   1228: ifeq -> 1241
/*    */     //   1231: aload_0
/*    */     //   1232: dup
/*    */     //   1233: getfield bu : I
/*    */     //   1236: iconst_1
/*    */     //   1237: iadd
/*    */     //   1238: putfield bu : I
/*    */     //   1241: aload_0
/*    */     //   1242: bipush #106
/*    */     //   1244: istore_2
/*    */     //   1245: getfield ZM : Lf/S4;
/*    */     //   1248: iload_2
/*    */     //   1249: invokevirtual MN : (I)Z
/*    */     //   1252: ifne -> 1425
/*    */     //   1255: aload_0
/*    */     //   1256: aload_3
/*    */     //   1257: aload_0
/*    */     //   1258: getfield ZM : Lf/S4;
/*    */     //   1261: iload_2
/*    */     //   1262: invokevirtual V9 : (I)V
/*    */     //   1265: getstatic f/km.mI0 : Lf/P1;
/*    */     //   1268: getfield AN : Lf/Wo;
/*    */     //   1271: iload_2
/*    */     //   1272: invokevirtual Ea0 : (I)Lf/Bs;
/*    */     //   1275: checkcast f/LW
/*    */     //   1278: aload #4
/*    */     //   1280: swap
/*    */     //   1281: invokevirtual xp : (Lf/KB0;Lf/VV;Lf/Bs;)Z
/*    */     //   1284: ifeq -> 1425
/*    */     //   1287: goto -> 1415
/*    */     //   1290: iload_2
/*    */     //   1291: bipush #120
/*    */     //   1293: if_icmpne -> 1425
/*    */     //   1296: sipush #200
/*    */     //   1299: istore_2
/*    */     //   1300: iload_2
/*    */     //   1301: sipush #204
/*    */     //   1304: if_icmpgt -> 1368
/*    */     //   1307: aload_0
/*    */     //   1308: getfield ZM : Lf/S4;
/*    */     //   1311: iload_2
/*    */     //   1312: invokevirtual MN : (I)Z
/*    */     //   1315: ifne -> 1360
/*    */     //   1318: aload_0
/*    */     //   1319: aload_3
/*    */     //   1320: aload_0
/*    */     //   1321: getfield ZM : Lf/S4;
/*    */     //   1324: iload_2
/*    */     //   1325: invokevirtual V9 : (I)V
/*    */     //   1328: getstatic f/km.mI0 : Lf/P1;
/*    */     //   1331: getfield AN : Lf/Wo;
/*    */     //   1334: iload_2
/*    */     //   1335: invokevirtual Ea0 : (I)Lf/Bs;
/*    */     //   1338: checkcast f/LW
/*    */     //   1341: aload #4
/*    */     //   1343: swap
/*    */     //   1344: invokevirtual xp : (Lf/KB0;Lf/VV;Lf/Bs;)Z
/*    */     //   1347: ifeq -> 1360
/*    */     //   1350: aload_0
/*    */     //   1351: dup
/*    */     //   1352: getfield bu : I
/*    */     //   1355: iconst_1
/*    */     //   1356: iadd
/*    */     //   1357: putfield bu : I
/*    */     //   1360: iload_2
/*    */     //   1361: iconst_1
/*    */     //   1362: iadd
/*    */     //   1363: i2s
/*    */     //   1364: istore_2
/*    */     //   1365: goto -> 1300
/*    */     //   1368: aload_0
/*    */     //   1369: sipush #253
/*    */     //   1372: istore_2
/*    */     //   1373: getfield ZM : Lf/S4;
/*    */     //   1376: iload_2
/*    */     //   1377: invokevirtual MN : (I)Z
/*    */     //   1380: ifne -> 1425
/*    */     //   1383: aload_0
/*    */     //   1384: aload_3
/*    */     //   1385: aload_0
/*    */     //   1386: getfield ZM : Lf/S4;
/*    */     //   1389: iload_2
/*    */     //   1390: invokevirtual V9 : (I)V
/*    */     //   1393: getstatic f/km.mI0 : Lf/P1;
/*    */     //   1396: getfield AN : Lf/Wo;
/*    */     //   1399: iload_2
/*    */     //   1400: invokevirtual Ea0 : (I)Lf/Bs;
/*    */     //   1403: checkcast f/LW
/*    */     //   1406: aload #4
/*    */     //   1408: swap
/*    */     //   1409: invokevirtual xp : (Lf/KB0;Lf/VV;Lf/Bs;)Z
/*    */     //   1412: ifeq -> 1425
/*    */     //   1415: aload_0
/*    */     //   1416: dup
/*    */     //   1417: getfield bu : I
/*    */     //   1420: iconst_1
/*    */     //   1421: iadd
/*    */     //   1422: putfield bu : I
/*    */     //   1425: aload_0
/*    */     //   1426: dup
/*    */     //   1427: getstatic f/km.mI0 : Lf/P1;
/*    */     //   1430: getfield AN : Lf/Wo;
/*    */     //   1433: getfield aB0 : Lf/V60;
/*    */     //   1436: invokevirtual vO : ()V
/*    */     //   1439: getfield KN : I
/*    */     //   1442: iconst_1
/*    */     //   1443: iadd
/*    */     //   1444: putfield KN : I
/*    */     //   1447: goto -> 876
/*    */     //   1450: iload_2
/*    */     //   1451: aload_0
/*    */     //   1452: getfield Wb0 : [Lf/Ws0;
/*    */     //   1455: arraylength
/*    */     //   1456: if_icmplt -> 1478
/*    */     //   1459: aload_0
/*    */     //   1460: dup
/*    */     //   1461: iconst_1
/*    */     //   1462: putfield rK : Z
/*    */     //   1465: getfield Og : Ljava/nio/MappedByteBuffer;
/*    */     //   1468: aload_0
/*    */     //   1469: getfield bu : I
/*    */     //   1472: iconst_4
/*    */     //   1473: swap
/*    */     //   1474: invokevirtual putInt : (II)Ljava/nio/ByteBuffer;
/*    */     //   1477: pop
/*    */     //   1478: iconst_0
/*    */     //   1479: ireturn
/*    */     //   1480: aload_0
/*    */     //   1481: getfield Nul : Z
/*    */     //   1484: ifne -> 1580
/*    */     //   1487: aload_0
/*    */     //   1488: getfield KG0 : B
/*    */     //   1491: dup
/*    */     //   1492: istore_1
/*    */     //   1493: iconst_2
/*    */     //   1494: if_icmpeq -> 1546
/*    */     //   1497: iload_1
/*    */     //   1498: iconst_3
/*    */     //   1499: if_icmpeq -> 1538
/*    */     //   1502: iload_1
/*    */     //   1503: iconst_4
/*    */     //   1504: if_icmpeq -> 1510
/*    */     //   1507: goto -> 1578
/*    */     //   1510: aload_0
/*    */     //   1511: getfield FK0 : I
/*    */     //   1514: dup
/*    */     //   1515: istore_1
/*    */     //   1516: ifne -> 1526
/*    */     //   1519: aload_0
/*    */     //   1520: iconst_0
/*    */     //   1521: invokevirtual in0 : (Z)V
/*    */     //   1524: iconst_0
/*    */     //   1525: ireturn
/*    */     //   1526: iload_1
/*    */     //   1527: iconst_1
/*    */     //   1528: if_icmpne -> 1578
/*    */     //   1531: aload_0
/*    */     //   1532: iconst_1
/*    */     //   1533: invokevirtual in0 : (Z)V
/*    */     //   1536: iconst_0
/*    */     //   1537: ireturn
/*    */     //   1538: aload_0
/*    */     //   1539: iconst_1
/*    */     //   1540: invokevirtual in0 : (Z)V
/*    */     //   1543: goto -> 1578
/*    */     //   1546: aload_0
/*    */     //   1547: getfield FK0 : I
/*    */     //   1550: dup
/*    */     //   1551: istore_1
/*    */     //   1552: ifne -> 1564
/*    */     //   1555: aload_0
/*    */     //   1556: getstatic f/VV.i60 : Lf/VV;
/*    */     //   1559: invokevirtual As : (Lf/VV;)V
/*    */     //   1562: iconst_0
/*    */     //   1563: ireturn
/*    */     //   1564: iload_1
/*    */     //   1565: iconst_1
/*    */     //   1566: if_icmpne -> 1578
/*    */     //   1569: aload_0
/*    */     //   1570: getstatic f/VV.transient : Lf/VV;
/*    */     //   1573: invokevirtual As : (Lf/VV;)V
/*    */     //   1576: iconst_0
/*    */     //   1577: ireturn
/*    */     //   1578: iconst_0
/*    */     //   1579: ireturn
/*    */     //   1580: getstatic f/km.mI0 : Lf/P1;
/*    */     //   1583: getfield AN : Lf/Wo;
/*    */     //   1586: dup
/*    */     //   1587: astore_1
/*    */     //   1588: ifnull -> 1598
/*    */     //   1591: aload_1
/*    */     //   1592: getfield aB0 : Lf/V60;
/*    */     //   1595: invokevirtual vO : ()V
/*    */     //   1598: getstatic f/km.mI0 : Lf/P1;
/*    */     //   1601: getfield MT : Lf/gD;
/*    */     //   1604: dup
/*    */     //   1605: astore_1
/*    */     //   1606: ifnull -> 1616
/*    */     //   1609: aload_1
/*    */     //   1610: getfield aB0 : Lf/V60;
/*    */     //   1613: invokevirtual vO : ()V
/*    */     //   1616: getstatic f/km.mI0 : Lf/P1;
/*    */     //   1619: getfield yE : Lf/BE;
/*    */     //   1622: dup
/*    */     //   1623: astore_1
/*    */     //   1624: ifnull -> 1634
/*    */     //   1627: aload_1
/*    */     //   1628: getfield aB0 : Lf/V60;
/*    */     //   1631: invokevirtual vO : ()V
/*    */     //   1634: aload_0
/*    */     //   1635: iconst_m1
/*    */     //   1636: istore_1
/*    */     //   1637: getfield KG0 : B
/*    */     //   1640: dup
/*    */     //   1641: istore_2
/*    */     //   1642: iconst_2
/*    */     //   1643: if_icmpeq -> 1671
/*    */     //   1646: iload_2
/*    */     //   1647: iconst_3
/*    */     //   1648: if_icmpeq -> 1665
/*    */     //   1651: iload_2
/*    */     //   1652: iconst_4
/*    */     //   1653: if_icmpeq -> 1659
/*    */     //   1656: goto -> 1673
/*    */     //   1659: bipush #9
/*    */     //   1661: istore_1
/*    */     //   1662: goto -> 1673
/*    */     //   1665: bipush #8
/*    */     //   1667: istore_1
/*    */     //   1668: goto -> 1673
/*    */     //   1671: iconst_3
/*    */     //   1672: istore_1
/*    */     //   1673: aload_0
/*    */     //   1674: dup
/*    */     //   1675: dup2
/*    */     //   1676: getstatic f/fw0.Z40 : Lf/ik;
/*    */     //   1679: dup
/*    */     //   1680: astore_2
/*    */     //   1681: ldc_w 'Starting cache save for region '
/*    */     //   1684: invokestatic df : (Ljava/lang/String;)Ljava/lang/StringBuilder;
/*    */     //   1687: aload_0
/*    */     //   1688: getfield KG0 : B
/*    */     //   1691: invokevirtual append : (I)Ljava/lang/StringBuilder;
/*    */     //   1694: invokevirtual toString : ()Ljava/lang/String;
/*    */     //   1697: invokeinterface info : (Ljava/lang/String;)V
/*    */     //   1702: getfield Og : Ljava/nio/MappedByteBuffer;
/*    */     //   1705: invokevirtual flip : ()Ljava/nio/Buffer;
/*    */     //   1708: pop
/*    */     //   1709: getfield Og : Ljava/nio/MappedByteBuffer;
/*    */     //   1712: iload_1
/*    */     //   1713: invokevirtual putInt : (I)Ljava/nio/ByteBuffer;
/*    */     //   1716: pop
/*    */     //   1717: getfield Og : Ljava/nio/MappedByteBuffer;
/*    */     //   1720: invokevirtual limit : ()I
/*    */     //   1723: istore_1
/*    */     //   1724: getfield Og : Ljava/nio/MappedByteBuffer;
/*    */     //   1727: dup
/*    */     //   1728: aload_0
/*    */     //   1729: aconst_null
/*    */     //   1730: putfield Og : Ljava/nio/MappedByteBuffer;
/*    */     //   1733: invokevirtual force : ()Ljava/nio/MappedByteBuffer;
/*    */     //   1736: pop
/*    */     //   1737: invokestatic El0 : (Ljava/nio/Buffer;)Z
/*    */     //   1740: ifeq -> 1755
/*    */     //   1743: aload_2
/*    */     //   1744: ldc_w 'Released buffer'
/*    */     //   1747: invokeinterface info : (Ljava/lang/String;)V
/*    */     //   1752: goto -> 1767
/*    */     //   1755: aload_2
/*    */     //   1756: ldc_w 'Attempting forced GC'
/*    */     //   1759: invokeinterface info : (Ljava/lang/String;)V
/*    */     //   1764: invokestatic gc : ()V
/*    */     //   1767: aload_0
/*    */     //   1768: getfield zj0 : Ljava/io/RandomAccessFile;
/*    */     //   1771: iload_1
/*    */     //   1772: i2l
/*    */     //   1773: invokevirtual setLength : (J)V
/*    */     //   1776: goto -> 1792
/*    */     //   1779: astore_1
/*    */     //   1780: getstatic f/fw0.Z40 : Lf/ik;
/*    */     //   1783: ldc_w ''
/*    */     //   1786: aload_1
/*    */     //   1787: invokeinterface warn : (Ljava/lang/String;Ljava/lang/Throwable;)V
/*    */     //   1792: aload_0
/*    */     //   1793: getfield zj0 : Ljava/io/RandomAccessFile;
/*    */     //   1796: invokevirtual close : ()V
/*    */     //   1799: getstatic f/fw0.Z40 : Lf/ik;
/*    */     //   1802: new java/lang/StringBuilder
/*    */     //   1805: dup
/*    */     //   1806: invokespecial <init> : ()V
/*    */     //   1809: ldc_w 'Finished cache save for region '
/*    */     //   1812: invokevirtual append : (Ljava/lang/String;)Ljava/lang/StringBuilder;
/*    */     //   1815: aload_0
/*    */     //   1816: getfield KG0 : B
/*    */     //   1819: invokevirtual append : (I)Ljava/lang/StringBuilder;
/*    */     //   1822: invokevirtual toString : ()Ljava/lang/String;
/*    */     //   1825: invokeinterface info : (Ljava/lang/String;)V
/*    */     //   1830: iconst_1
/*    */     //   1831: goto -> 1848
/*    */     //   1834: astore_0
/*    */     //   1835: getstatic f/fw0.Z40 : Lf/ik;
/*    */     //   1838: ldc_w 'Could not save cache '
/*    */     //   1841: aload_0
/*    */     //   1842: invokeinterface error : (Ljava/lang/String;Ljava/lang/Throwable;)V
/*    */     //   1847: iconst_0
/*    */     //   1848: ireturn
/*    */     // Line number table:
/*    */     //   Java source line number -> byte code offset
/*    */     //   #1	-> 40
/*    */     //   #2	-> 73
/*    */     //   #3	-> 82
/*    */     //   #4	-> 90
/*    */     //   #5	-> 95
/*    */     //   #6	-> 121
/*    */     //   #7	-> 125
/*    */     //   #8	-> 143
/*    */     //   #9	-> 148
/*    */     //   #10	-> 171
/*    */     //   #11	-> 254
/*    */     //   #12	-> 257
/*    */     //   #13	-> 262
/*    */     //   #14	-> 334
/*    */     //   #15	-> 337
/*    */     //   #16	-> 383
/*    */     //   #17	-> 416
/*    */     //   #18	-> 425
/*    */     //   #19	-> 433
/*    */     //   #20	-> 438
/*    */     //   #21	-> 464
/*    */     //   #22	-> 468
/*    */     //   #23	-> 488
/*    */     //   #24	-> 494
/*    */     //   #25	-> 521
/*    */     //   #26	-> 606
/*    */     //   #27	-> 609
/*    */     //   #28	-> 614
/*    */     //   #29	-> 751
/*    */     //   #30	-> 755
/*    */     //   #31	-> 820
/*    */     //   #32	-> 823
/*    */     //   #33	-> 869
/*    */     //   #34	-> 903
/*    */     //   #35	-> 906
/*    */     //   #36	-> 910
/*    */     //   #37	-> 935
/*    */     //   #38	-> 939
/*    */     //   #39	-> 1046
/*    */     //   #40	-> 1049
/*    */     //   #41	-> 1054
/*    */     //   #42	-> 1160
/*    */     //   #43	-> 1163
/*    */     //   #44	-> 1169
/*    */     //   #45	-> 1216
/*    */     //   #46	-> 1219
/*    */     //   #47	-> 1225
/*    */     //   #48	-> 1272
/*    */     //   #49	-> 1275
/*    */     //   #50	-> 1281
/*    */     //   #51	-> 1335
/*    */     //   #52	-> 1338
/*    */     //   #53	-> 1344
/*    */     //   #54	-> 1400
/*    */     //   #55	-> 1403
/*    */     //   #56	-> 1409
/*    */     //   #57	-> 1433
/*    */     //   #58	-> 1436
/*    */     //   #59	-> 1481
/*    */     //   #60	-> 1592
/*    */     //   #61	-> 1595
/*    */     //   #62	-> 1610
/*    */     //   #63	-> 1613
/*    */     //   #64	-> 1628
/*    */     //   #65	-> 1631
/*    */     //   #66	-> 1676
/*    */     //   #67	-> 1681
/*    */     //   #68	-> 1688
/*    */     // Exception table:
/*    */     //   from	to	target	type
/*    */     //   1702	1708	1834	java/lang/Exception
/*    */     //   1709	1716	1834	java/lang/Exception
/*    */     //   1717	1723	1834	java/lang/Exception
/*    */     //   1724	1736	1834	java/lang/Exception
/*    */     //   1737	1740	1779	finally
/*    */     //   1743	1771	1779	finally
/*    */     //   1773	1779	1779	finally
/*    */     //   1780	1830	1834	java/lang/Exception } public final void in0(boolean paramBoolean) { // Byte code:
/*    */     //   0: aload_0
/*    */     //   1: getfield UD : I
/*    */     //   4: iconst_m1
/*    */     //   5: if_icmpne -> 137
/*    */     //   8: aload_0
/*    */     //   9: getfield KG0 : B
/*    */     //   12: dup
/*    */     //   13: istore_2
/*    */     //   14: iconst_3
/*    */     //   15: if_icmpeq -> 75
/*    */     //   18: iload_2
/*    */     //   19: iconst_4
/*    */     //   20: if_icmpeq -> 26
/*    */     //   23: goto -> 101
/*    */     //   26: iload_1
/*    */     //   27: new f/ig
/*    */     //   30: astore_2
/*    */     //   31: getstatic f/km.mI0 : Lf/P1;
/*    */     //   34: getfield yE : Lf/BE;
/*    */     //   37: getfield TI : Lf/RD;
/*    */     //   40: astore_3
/*    */     //   41: ifeq -> 52
/*    */     //   44: ldc_w '/a/0/4/0'
/*    */     //   47: astore #4
/*    */     //   49: goto -> 57
/*    */     //   52: ldc_w '/a/1/4/8'
/*    */     //   55: astore #4
/*    */     //   57: aload_0
/*    */     //   58: aload_2
/*    */     //   59: dup
/*    */     //   60: aload_3
/*    */     //   61: aload #4
/*    */     //   63: invokevirtual B8 : (Ljava/lang/String;)Lf/T7;
/*    */     //   66: invokespecial <init> : (Lf/T7;)V
/*    */     //   69: putfield e10 : Lf/ig;
/*    */     //   72: goto -> 101
/*    */     //   75: aload_0
/*    */     //   76: new f/ig
/*    */     //   79: dup
/*    */     //   80: getstatic f/km.mI0 : Lf/P1;
/*    */     //   83: getfield MT : Lf/gD;
/*    */     //   86: getfield TI : Lf/RD;
/*    */     //   89: ldc_w '/fielddata/build_model/build_model.narc'
/*    */     //   92: invokevirtual B8 : (Ljava/lang/String;)Lf/T7;
/*    */     //   95: invokespecial <init> : (Lf/T7;)V
/*    */     //   98: putfield e10 : Lf/ig;
/*    */     //   101: aload_0
/*    */     //   102: dup
/*    */     //   103: dup2
/*    */     //   104: getfield Og : Ljava/nio/MappedByteBuffer;
/*    */     //   107: aload_0
/*    */     //   108: getfield e10 : Lf/ig;
/*    */     //   111: getfield Pd : Lf/E60;
/*    */     //   114: getfield dh0 : I
/*    */     //   117: invokevirtual putInt : (I)Ljava/nio/ByteBuffer;
/*    */     //   120: pop
/*    */     //   121: iconst_0
/*    */     //   122: putfield UD : I
/*    */     //   125: getfield e10 : Lf/ig;
/*    */     //   128: getfield Pd : Lf/E60;
/*    */     //   131: getfield dh0 : I
/*    */     //   134: putfield XJ0 : I
/*    */     //   137: aload_0
/*    */     //   138: getfield UD : I
/*    */     //   141: bipush #10
/*    */     //   143: iadd
/*    */     //   144: istore_2
/*    */     //   145: aload_0
/*    */     //   146: getfield UD : I
/*    */     //   149: dup
/*    */     //   150: istore_3
/*    */     //   151: iload_2
/*    */     //   152: if_icmpge -> 492
/*    */     //   155: iload_3
/*    */     //   156: aload_0
/*    */     //   157: getfield XJ0 : I
/*    */     //   160: if_icmpge -> 492
/*    */     //   163: aload_0
/*    */     //   164: aconst_null
/*    */     //   165: astore #4
/*    */     //   167: aconst_null
/*    */     //   168: astore #5
/*    */     //   170: getfield KG0 : B
/*    */     //   173: dup
/*    */     //   174: istore #6
/*    */     //   176: iconst_3
/*    */     //   177: if_icmpeq -> 230
/*    */     //   180: iload #6
/*    */     //   182: iconst_4
/*    */     //   183: if_icmpeq -> 189
/*    */     //   186: goto -> 263
/*    */     //   189: getstatic f/km.mI0 : Lf/P1;
/*    */     //   192: getfield yE : Lf/BE;
/*    */     //   195: iload_1
/*    */     //   196: invokevirtual sM : (Z)Lf/Jj;
/*    */     //   199: aload_0
/*    */     //   200: getfield UD : I
/*    */     //   203: invokevirtual vn0 : (I)Lf/Q1;
/*    */     //   206: astore #4
/*    */     //   208: getstatic f/km.mI0 : Lf/P1;
/*    */     //   211: getfield yE : Lf/BE;
/*    */     //   214: iload_1
/*    */     //   215: invokevirtual sM : (Z)Lf/Jj;
/*    */     //   218: aload_0
/*    */     //   219: getfield UD : I
/*    */     //   222: invokevirtual jw : (I)Lf/fn;
/*    */     //   225: astore #5
/*    */     //   227: goto -> 263
/*    */     //   230: getstatic f/km.mI0 : Lf/P1;
/*    */     //   233: getfield MT : Lf/gD;
/*    */     //   236: getfield EI0 : Lf/Jj;
/*    */     //   239: iload_3
/*    */     //   240: invokevirtual vn0 : (I)Lf/Q1;
/*    */     //   243: astore #4
/*    */     //   245: getstatic f/km.mI0 : Lf/P1;
/*    */     //   248: getfield MT : Lf/gD;
/*    */     //   251: getfield EI0 : Lf/Jj;
/*    */     //   254: aload_0
/*    */     //   255: getfield UD : I
/*    */     //   258: invokevirtual jw : (I)Lf/fn;
/*    */     //   261: astore #5
/*    */     //   263: aload_0
/*    */     //   264: iload_1
/*    */     //   265: iconst_0
/*    */     //   266: istore_3
/*    */     //   267: iconst_1
/*    */     //   268: ixor
/*    */     //   269: istore #6
/*    */     //   271: getfield KG0 : B
/*    */     //   274: iconst_4
/*    */     //   275: if_icmpne -> 367
/*    */     //   278: iload_1
/*    */     //   279: ifne -> 321
/*    */     //   282: aload_0
/*    */     //   283: getfield UD : I
/*    */     //   286: dup
/*    */     //   287: istore #7
/*    */     //   289: sipush #146
/*    */     //   292: if_icmpeq -> 319
/*    */     //   295: iload #7
/*    */     //   297: sipush #147
/*    */     //   300: if_icmpeq -> 319
/*    */     //   303: iload #7
/*    */     //   305: sipush #173
/*    */     //   308: if_icmpeq -> 319
/*    */     //   311: iload #7
/*    */     //   313: sipush #174
/*    */     //   316: if_icmpne -> 321
/*    */     //   319: iconst_1
/*    */     //   320: istore_3
/*    */     //   321: iload_1
/*    */     //   322: ifeq -> 370
/*    */     //   325: aload_0
/*    */     //   326: getfield UD : I
/*    */     //   329: dup
/*    */     //   330: istore #7
/*    */     //   332: bipush #117
/*    */     //   334: if_icmpeq -> 367
/*    */     //   337: iload #7
/*    */     //   339: sipush #169
/*    */     //   342: if_icmpeq -> 367
/*    */     //   345: iload #7
/*    */     //   347: sipush #186
/*    */     //   350: if_icmpeq -> 367
/*    */     //   353: iload #7
/*    */     //   355: bipush #64
/*    */     //   357: if_icmplt -> 370
/*    */     //   360: iload #7
/*    */     //   362: bipush #70
/*    */     //   364: if_icmpgt -> 370
/*    */     //   367: iconst_1
/*    */     //   368: istore #6
/*    */     //   370: aload_0
/*    */     //   371: dup
/*    */     //   372: aload #4
/*    */     //   374: invokestatic Lj : ()Lf/eI;
/*    */     //   377: astore #7
/*    */     //   379: getfield Nt : [Lf/hC;
/*    */     //   382: iconst_0
/*    */     //   383: aaload
/*    */     //   384: dup
/*    */     //   385: aload #7
/*    */     //   387: swap
/*    */     //   388: aload #5
/*    */     //   390: aload #4
/*    */     //   392: getfield Qo0 : Lf/Wd;
/*    */     //   395: astore #4
/*    */     //   397: getfield ok0 : Lf/fQ;
/*    */     //   400: astore #5
/*    */     //   402: getfield Sw : F
/*    */     //   405: fstore #7
/*    */     //   407: invokevirtual getClass : ()Ljava/lang/Class;
/*    */     //   410: pop
/*    */     //   411: aload #4
/*    */     //   413: aload #5
/*    */     //   415: fload #7
/*    */     //   417: iload #6
/*    */     //   419: iconst_0
/*    */     //   420: iload_3
/*    */     //   421: invokestatic Gy : (Lf/hC;Lf/Wd;Lf/fQ;FZZZ)Lf/lpt1;
/*    */     //   424: dup
/*    */     //   425: astore_3
/*    */     //   426: aload_0
/*    */     //   427: dup
/*    */     //   428: dup2
/*    */     //   429: getfield Og : Ljava/nio/MappedByteBuffer;
/*    */     //   432: invokevirtual position : ()I
/*    */     //   435: istore #4
/*    */     //   437: getfield Og : Ljava/nio/MappedByteBuffer;
/*    */     //   440: iconst_m1
/*    */     //   441: invokevirtual putInt : (I)Ljava/nio/ByteBuffer;
/*    */     //   444: pop
/*    */     //   445: new f/iR
/*    */     //   448: aload_0
/*    */     //   449: getfield Og : Ljava/nio/MappedByteBuffer;
/*    */     //   452: aload_3
/*    */     //   453: invokespecial <init> : (Ljava/nio/MappedByteBuffer;Lf/lpt1;)V
/*    */     //   456: getfield Og : Ljava/nio/MappedByteBuffer;
/*    */     //   459: invokevirtual position : ()I
/*    */     //   462: istore_3
/*    */     //   463: getfield Og : Ljava/nio/MappedByteBuffer;
/*    */     //   466: iload #4
/*    */     //   468: iload_3
/*    */     //   469: iload #4
/*    */     //   471: isub
/*    */     //   472: iconst_4
/*    */     //   473: isub
/*    */     //   474: invokevirtual putInt : (II)Ljava/nio/ByteBuffer;
/*    */     //   477: pop
/*    */     //   478: invokevirtual Ea0 : ()V
/*    */     //   481: getfield UD : I
/*    */     //   484: iconst_1
/*    */     //   485: iadd
/*    */     //   486: putfield UD : I
/*    */     //   489: goto -> 145
/*    */     //   492: iload_3
/*    */     //   493: aload_0
/*    */     //   494: getfield XJ0 : I
/*    */     //   497: if_icmplt -> 524
/*    */     //   500: iload_1
/*    */     //   501: aload_0
/*    */     //   502: dup
/*    */     //   503: dup
/*    */     //   504: getfield FK0 : I
/*    */     //   507: iconst_1
/*    */     //   508: iadd
/*    */     //   509: putfield FK0 : I
/*    */     //   512: iconst_m1
/*    */     //   513: putfield UD : I
/*    */     //   516: ifeq -> 524
/*    */     //   519: aload_0
/*    */     //   520: iconst_1
/*    */     //   521: putfield Nul : Z
/*    */     //   524: return
/*    */     // Line number table:
/*    */     //   Java source line number -> byte code offset
/*    */     //   #1	-> 37
/*    */     //   #2	-> 44
/*    */     //   #3	-> 86
/*    */     //   #4	-> 89
/*    */     //   #5	-> 111
/*    */     //   #6	-> 114
/*    */     //   #7	-> 117
/*    */     //   #8	-> 128
/*    */     //   #9	-> 131
/*    */     //   #10	-> 134
/*    */     //   #11	-> 236
/*    */     //   #12	-> 240
/*    */     //   #13	-> 251
/*    */     //   #14	-> 255
/*    */     //   #15	-> 429
/*  9 */     //   #16	-> 478 } public final void As(VV paramVV) { if (this.UD == -1) { ig ig2; T7 t7 = null; int m; if ((m = paramVV.ordinal()) != 1) { if (m == 2) t7 = km.mI0.AN.TI.B8("/a/2/3/0");  } else { t7 = km.mI0.AN.TI.B8("/a/2/2/9"); }  this(t7); this.e10 = new ig(); this.Og.putInt(ig2.Pd.dh0); this.UD = 0; this.XJ0 = this.e10.Pd.dh0; }  int j = 0; int k; ig ig1; while ((k = this.UD) < 
/* 10 */       (ig1 = this.e10).Pd
/* 11 */       .dh0)
/*    */     
/*    */     { 
/* 14 */       Wd wd = km.mI0.AN.oB(paramVV, this.UD); S0 s0; int m = (s0 = S0.qy(ig1.zz(k).rb(false))).Of0.size(); this.Og.putInt(m); for (byte b = 0; b < m; ) { boolean bool; Mh0 mh0; (mh0 = s0.Of0.get(b)).DI0(); eI eI = eI.Lj(); fQ fQ = mh0.Fe0; hC hC; float f = (hC = (s0.Of0.get(b)).sD.Nt[0]).Sw; if (paramVV == VV.transient) { bool = true; } else { bool = false; }  eI
/* 15 */           .getClass();
/*    */         
/* 17 */         int n = this.Og.position(); this.Og.putInt(-1); int i1 = this.Og.position(); this.Og.putInt(n, i1 - n - 4);
/* 18 */         mh0.sD = null; mh0.Fe0.clear(); mh0.kR = false; lpt1 lpt1;
/* 19 */         (lpt1 = eI.Gy(hC, wd, fQ, f, bool, false, false)).Ea0(); b++; }  this.UD++; if (++j > 5) return;  }  this.FK0 = i; this.UD = -1; int i; if ((i = this.FK0 + 1) == 2) this.Nul = true;  }
/*    */    }


/* Location:              /Users/vnnsnnt/Documents/Codespace/JavaWorkspace/RedTrainer/src/main/java/org/trainer/client/PokeMMO.jar!/f/fw0.class
 * Java compiler version: 8 (52.0)
 * JD-Core Version:       1.1.3
 */