/*  1 */ package f;public class Ga extends JG0 { public static final x9[] h10; public static final NC0 OA0; public final w1 Db0; public final Ja qz0; public x9[] y00; public cQ my; public int fG0; public int uu; public boolean vn; public boolean Om; public boolean Jv; public int LPt1; public int rI0; public final void zy0(int paramInt, boolean paramBoolean, RJ paramRJ) { if (paramInt >= -1 && paramInt < this.nN) { if (paramBoolean) { uW(); if (paramInt == -1) { hq(0); } else { int i; int j; if ((j = (i = this.Zb0) - paramInt) > 0)
/*  2 */           { hq(i - (j + (i = this.rI0) - 1) / i * i); }
/*  3 */           else if ((j = paramInt - i + this.y00.length - 1) > 0)
/*  4 */           { hq((j + (j = this.rI0) - 1) / j * j + i); }  }  }  if (this.go != paramInt) { this.go = paramInt; this.Pe = true;
/*  5 */         hm.c50(this.Un0, paramRJ); } else if (paramRJ
/*  6 */         .Ye0 || paramRJ == 
/*  7 */         RJ.kf)
/*  8 */       { hm.c50(this.Un0, paramRJ); }  return; }
/*  9 */      throw new IllegalArgumentException(); } public int Zb0; public int go; public int nN; public boolean Pe; public tC0[] Un0; public YG Kt0; public cx0 TN; public float pB0; public Ga() { w1 w11; this.fG0 = 20; this.uu = -1; this.vn = true; this.LPt1 = 1; this.rI0 = 1; this.go = -1; this.TN = new cx0(); this.pB0 = 0.0F; this(this, 0); this.Db0 = new w1(); this(); this.qz0 = ja; Ja ja; (ja = new Ja()).XI0(w11); this.y00 = h10; super.si(ja, 0); Tm(200, 300); Zf0(true); fk(); } static { h10 = new x9[0]; OA0 = new NC0(); } public Ga(LK0 paramLK0) { this(); UN(paramLK0); } public String TI() { return "listbox"; } public final void rS(tC0 paramtC0) { this.Un0 = (tC0[])hm.LpT6((Object[])this.Un0, paramtC0, tC0.class); } public final void hq(int paramInt) { paramInt = Math.max(0, Math.min(paramInt, this.nN - 1)); if (this.Zb0 != paramInt) { this.Zb0 = paramInt; this.qz0.Fk0(paramInt / this.rI0, false); this.Pe = true; }  } public final JG0 Va0(int paramInt1, int paramInt2) { return this; } public final void si(JG0 paramJG0, int paramInt) { throw new UnsupportedOperationException(); } public final void gx() { throw new UnsupportedOperationException(); } public final JG0 fG0(int paramInt) { throw new UnsupportedOperationException(); } public final void Xw(nY paramnY) { super.Xw(paramnY); q80 q80; int i; if ((i = (q80 = (q80)paramnY).Km(20, "cellHeight")) >= 1) { this.fG0 = i; if ((i = q80.Km(-1, "cellWidth")) >= 1 || i == -1) { this.uu = i; this.vn = q80.Mw0("rowMajor", true); this.Om = q80.Mw0("fixedCellWidth", false); this.Jv = q80.Mw0("fixedCellHeight", false);
/* 10 */         this.LPt1 = q80.Km(1, "minDisplayedRows"); return; }  throw new IllegalArgumentException("cellWidth < 1"); }
/* 11 */      throw new IllegalArgumentException("cellHeight < 1"); } public final void pm() { boolean bool = true; x9[] arrayOfX9; int i; if ((i = this.go - this.Zb0) >= 0 && i < (arrayOfX9 = this.y00).length) ((xK0)this[i]).O.gf0(JG0.e30, bool);  } public final void GD() { boolean bool = false; x9[] arrayOfX9; int i; if ((i = this.go - this.Zb0) >= 0 && i < (arrayOfX9 = this.y00).length) ((xK0)this[i]).O.gf0(JG0.e30, bool);  } public final boolean i2(oa0 paramoa0) { // Byte code:
/*    */     //   0: aload_1
/*    */     //   1: getfield cz0 : I
/*    */     //   4: invokestatic yE : (I)I
/*    */     //   7: tableswitch default -> 32, 7 -> 633, 8 -> 116, 9 -> 42
/*    */     //   32: aload_0
/*    */     //   33: aload_1
/*    */     //   34: invokespecial i2 : (Lf/oa0;)Z
/*    */     //   37: ifeq -> 680
/*    */     //   40: iconst_1
/*    */     //   41: ireturn
/*    */     //   42: aload_1
/*    */     //   43: getfield GG0 : I
/*    */     //   46: invokestatic Nk : (I)I
/*    */     //   49: dup
/*    */     //   50: istore_0
/*    */     //   51: iconst_3
/*    */     //   52: if_icmpeq -> 114
/*    */     //   55: iload_0
/*    */     //   56: bipush #66
/*    */     //   58: if_icmpeq -> 114
/*    */     //   61: iload_0
/*    */     //   62: bipush #123
/*    */     //   64: if_icmpeq -> 114
/*    */     //   67: iload_0
/*    */     //   68: bipush #92
/*    */     //   70: if_icmpeq -> 114
/*    */     //   73: iload_0
/*    */     //   74: bipush #93
/*    */     //   76: if_icmpeq -> 114
/*    */     //   79: iload_0
/*    */     //   80: tableswitch default -> 112, 19 -> 114, 20 -> 114, 21 -> 114, 22 -> 114
/*    */     //   112: iconst_0
/*    */     //   113: ireturn
/*    */     //   114: iconst_1
/*    */     //   115: ireturn
/*    */     //   116: aload_1
/*    */     //   117: getfield GG0 : I
/*    */     //   120: invokestatic Nk : (I)I
/*    */     //   123: dup
/*    */     //   124: istore_2
/*    */     //   125: iconst_3
/*    */     //   126: if_icmpeq -> 613
/*    */     //   129: iload_2
/*    */     //   130: bipush #66
/*    */     //   132: if_icmpeq -> 594
/*    */     //   135: iload_2
/*    */     //   136: bipush #123
/*    */     //   138: if_icmpeq -> 576
/*    */     //   141: iload_2
/*    */     //   142: bipush #92
/*    */     //   144: if_icmpeq -> 542
/*    */     //   147: iload_2
/*    */     //   148: bipush #93
/*    */     //   150: if_icmpeq -> 511
/*    */     //   153: iload_2
/*    */     //   154: tableswitch default -> 184, 19 -> 273, 20 -> 246, 21 -> 222, 22 -> 187
/*    */     //   184: goto -> 301
/*    */     //   187: aload_0
/*    */     //   188: iconst_1
/*    */     //   189: istore_1
/*    */     //   190: getfield go : I
/*    */     //   193: iload_1
/*    */     //   194: iadd
/*    */     //   195: dup
/*    */     //   196: istore_1
/*    */     //   197: iflt -> 631
/*    */     //   200: iload_1
/*    */     //   201: aload_0
/*    */     //   202: getfield nN : I
/*    */     //   205: if_icmpge -> 631
/*    */     //   208: aload_0
/*    */     //   209: getstatic f/RJ.J80 : Lf/RJ;
/*    */     //   212: astore_0
/*    */     //   213: iload_1
/*    */     //   214: iconst_1
/*    */     //   215: aload_0
/*    */     //   216: invokevirtual zy0 : (IZLf/RJ;)V
/*    */     //   219: goto -> 631
/*    */     //   222: aload_0
/*    */     //   223: iconst_m1
/*    */     //   224: istore_1
/*    */     //   225: getfield go : I
/*    */     //   228: iload_1
/*    */     //   229: iadd
/*    */     //   230: dup
/*    */     //   231: istore_1
/*    */     //   232: iflt -> 631
/*    */     //   235: iload_1
/*    */     //   236: aload_0
/*    */     //   237: getfield nN : I
/*    */     //   240: if_icmpge -> 631
/*    */     //   243: goto -> 208
/*    */     //   246: aload_0
/*    */     //   247: dup
/*    */     //   248: getfield rI0 : I
/*    */     //   251: istore_1
/*    */     //   252: getfield go : I
/*    */     //   255: iload_1
/*    */     //   256: iadd
/*    */     //   257: dup
/*    */     //   258: istore_1
/*    */     //   259: iflt -> 631
/*    */     //   262: iload_1
/*    */     //   263: aload_0
/*    */     //   264: getfield nN : I
/*    */     //   267: if_icmpge -> 631
/*    */     //   270: goto -> 208
/*    */     //   273: aload_0
/*    */     //   274: dup
/*    */     //   275: getfield rI0 : I
/*    */     //   278: ineg
/*    */     //   279: istore_1
/*    */     //   280: getfield go : I
/*    */     //   283: iload_1
/*    */     //   284: iadd
/*    */     //   285: dup
/*    */     //   286: istore_1
/*    */     //   287: iflt -> 631
/*    */     //   290: iload_1
/*    */     //   291: aload_0
/*    */     //   292: getfield nN : I
/*    */     //   295: if_icmpge -> 631
/*    */     //   298: goto -> 208
/*    */     //   301: aload_1
/*    */     //   302: getfield cz0 : I
/*    */     //   305: bipush #9
/*    */     //   307: if_icmpne -> 322
/*    */     //   310: aload_1
/*    */     //   311: getfield Z9 : C
/*    */     //   314: ifeq -> 322
/*    */     //   317: iconst_1
/*    */     //   318: istore_2
/*    */     //   319: goto -> 324
/*    */     //   322: iconst_0
/*    */     //   323: istore_2
/*    */     //   324: iload_2
/*    */     //   325: ifeq -> 509
/*    */     //   328: aload_1
/*    */     //   329: getfield Z9 : C
/*    */     //   332: dup
/*    */     //   333: istore_2
/*    */     //   334: ifeq -> 348
/*    */     //   337: iload_2
/*    */     //   338: invokestatic isLetterOrDigit : (C)Z
/*    */     //   341: ifeq -> 348
/*    */     //   344: iconst_1
/*    */     //   345: goto -> 349
/*    */     //   348: iconst_0
/*    */     //   349: ifeq -> 509
/*    */     //   352: aload_0
/*    */     //   353: aload_1
/*    */     //   354: getfield Z9 : C
/*    */     //   357: invokestatic toString : (C)Ljava/lang/String;
/*    */     //   360: astore_1
/*    */     //   361: getfield go : I
/*    */     //   364: iconst_1
/*    */     //   365: iadd
/*    */     //   366: istore_2
/*    */     //   367: iload_2
/*    */     //   368: aload_0
/*    */     //   369: getfield nN : I
/*    */     //   372: if_icmpge -> 427
/*    */     //   375: aload_0
/*    */     //   376: getfield my : Lf/cQ;
/*    */     //   379: checkcast f/LK0
/*    */     //   382: iload_2
/*    */     //   383: invokevirtual c90 : (I)Ljava/lang/Object;
/*    */     //   386: dup
/*    */     //   387: astore_3
/*    */     //   388: ifnull -> 412
/*    */     //   391: aload_3
/*    */     //   392: invokevirtual toString : ()Ljava/lang/String;
/*    */     //   395: aload_1
/*    */     //   396: invokevirtual length : ()I
/*    */     //   399: istore_3
/*    */     //   400: iconst_1
/*    */     //   401: iconst_0
/*    */     //   402: aload_1
/*    */     //   403: iconst_0
/*    */     //   404: iload_3
/*    */     //   405: invokevirtual regionMatches : (ZILjava/lang/String;II)Z
/*    */     //   408: istore_3
/*    */     //   409: goto -> 414
/*    */     //   412: iconst_0
/*    */     //   413: istore_3
/*    */     //   414: iload_3
/*    */     //   415: ifeq -> 421
/*    */     //   418: goto -> 491
/*    */     //   421: iinc #2, 1
/*    */     //   424: goto -> 367
/*    */     //   427: iconst_0
/*    */     //   428: istore_2
/*    */     //   429: iload_2
/*    */     //   430: aload_0
/*    */     //   431: getfield go : I
/*    */     //   434: if_icmpge -> 489
/*    */     //   437: aload_0
/*    */     //   438: getfield my : Lf/cQ;
/*    */     //   441: checkcast f/LK0
/*    */     //   444: iload_2
/*    */     //   445: invokevirtual c90 : (I)Ljava/lang/Object;
/*    */     //   448: dup
/*    */     //   449: astore_3
/*    */     //   450: ifnull -> 474
/*    */     //   453: aload_3
/*    */     //   454: invokevirtual toString : ()Ljava/lang/String;
/*    */     //   457: aload_1
/*    */     //   458: invokevirtual length : ()I
/*    */     //   461: istore_3
/*    */     //   462: iconst_1
/*    */     //   463: iconst_0
/*    */     //   464: aload_1
/*    */     //   465: iconst_0
/*    */     //   466: iload_3
/*    */     //   467: invokevirtual regionMatches : (ZILjava/lang/String;II)Z
/*    */     //   470: istore_3
/*    */     //   471: goto -> 476
/*    */     //   474: iconst_0
/*    */     //   475: istore_3
/*    */     //   476: iload_3
/*    */     //   477: ifeq -> 483
/*    */     //   480: goto -> 491
/*    */     //   483: iinc #2, 1
/*    */     //   486: goto -> 429
/*    */     //   489: iconst_m1
/*    */     //   490: istore_2
/*    */     //   491: iload_2
/*    */     //   492: iconst_m1
/*    */     //   493: if_icmpeq -> 507
/*    */     //   496: aload_0
/*    */     //   497: getstatic f/RJ.J80 : Lf/RJ;
/*    */     //   500: astore_0
/*    */     //   501: iload_2
/*    */     //   502: iconst_1
/*    */     //   503: aload_0
/*    */     //   504: invokevirtual zy0 : (IZLf/RJ;)V
/*    */     //   507: iconst_1
/*    */     //   508: ireturn
/*    */     //   509: iconst_0
/*    */     //   510: ireturn
/*    */     //   511: aload_0
/*    */     //   512: dup
/*    */     //   513: getfield nN : I
/*    */     //   516: iconst_1
/*    */     //   517: isub
/*    */     //   518: aload_0
/*    */     //   519: getfield go : I
/*    */     //   522: aload_0
/*    */     //   523: getfield y00 : [Lf/x9;
/*    */     //   526: arraylength
/*    */     //   527: iadd
/*    */     //   528: invokestatic min : (II)I
/*    */     //   531: getstatic f/RJ.J80 : Lf/RJ;
/*    */     //   534: iconst_1
/*    */     //   535: swap
/*    */     //   536: invokevirtual zy0 : (IZLf/RJ;)V
/*    */     //   539: goto -> 631
/*    */     //   542: aload_0
/*    */     //   543: getfield nN : I
/*    */     //   546: ifle -> 631
/*    */     //   549: aload_0
/*    */     //   550: dup
/*    */     //   551: getfield go : I
/*    */     //   554: aload_0
/*    */     //   555: getfield y00 : [Lf/x9;
/*    */     //   558: arraylength
/*    */     //   559: isub
/*    */     //   560: iconst_0
/*    */     //   561: swap
/*    */     //   562: invokestatic max : (II)I
/*    */     //   565: getstatic f/RJ.J80 : Lf/RJ;
/*    */     //   568: iconst_1
/*    */     //   569: swap
/*    */     //   570: invokevirtual zy0 : (IZLf/RJ;)V
/*    */     //   573: goto -> 631
/*    */     //   576: aload_0
/*    */     //   577: dup
/*    */     //   578: getfield nN : I
/*    */     //   581: iconst_1
/*    */     //   582: isub
/*    */     //   583: getstatic f/RJ.J80 : Lf/RJ;
/*    */     //   586: iconst_1
/*    */     //   587: swap
/*    */     //   588: invokevirtual zy0 : (IZLf/RJ;)V
/*    */     //   591: goto -> 631
/*    */     //   594: aload_0
/*    */     //   595: dup
/*    */     //   596: getfield go : I
/*    */     //   599: istore_0
/*    */     //   600: getstatic f/RJ.sx : Lf/RJ;
/*    */     //   603: astore_1
/*    */     //   604: iload_0
/*    */     //   605: iconst_0
/*    */     //   606: aload_1
/*    */     //   607: invokevirtual zy0 : (IZLf/RJ;)V
/*    */     //   610: goto -> 631
/*    */     //   613: aload_0
/*    */     //   614: getfield nN : I
/*    */     //   617: ifle -> 631
/*    */     //   620: aload_0
/*    */     //   621: getstatic f/RJ.J80 : Lf/RJ;
/*    */     //   624: astore_0
/*    */     //   625: iconst_0
/*    */     //   626: iconst_1
/*    */     //   627: aload_0
/*    */     //   628: invokevirtual zy0 : (IZLf/RJ;)V
/*    */     //   631: iconst_1
/*    */     //   632: ireturn
/*    */     //   633: aload_0
/*    */     //   634: getfield qz0 : Lf/Ja;
/*    */     //   637: dup
/*    */     //   638: astore_0
/*    */     //   639: aload_1
/*    */     //   640: getfield kB0 : I
/*    */     //   643: ineg
/*    */     //   644: istore_1
/*    */     //   645: getfield mz0 : I
/*    */     //   648: aload_0
/*    */     //   649: getfield sy : I
/*    */     //   652: if_icmpge -> 665
/*    */     //   655: aload_0
/*    */     //   656: getfield Ny0 : I
/*    */     //   659: iload_1
/*    */     //   660: iadd
/*    */     //   661: istore_1
/*    */     //   662: goto -> 672
/*    */     //   665: aload_0
/*    */     //   666: getfield Ny0 : I
/*    */     //   669: iload_1
/*    */     //   670: isub
/*    */     //   671: istore_1
/*    */     //   672: aload_0
/*    */     //   673: iload_1
/*    */     //   674: iconst_1
/*    */     //   675: invokevirtual Fk0 : (IZ)V
/*    */     //   678: iconst_1
/*    */     //   679: ireturn
/*    */     //   680: aload_1
/*    */     //   681: getfield cz0 : I
/*    */     //   684: invokestatic Pg : (I)Z
/*    */     //   687: ireturn
/*    */     // Line number table:
/*    */     //   Java source line number -> byte code offset
/*    */     //   #1	-> 1
/*    */     //   #2	-> 4
/*    */     //   #3	-> 43
/*    */     //   #4	-> 46
/*    */     //   #5	-> 117
/*    */     //   #6	-> 120
/*    */     //   #7	-> 190
/*    */     //   #8	-> 225
/*    */     //   #9	-> 248
/*    */     //   #10	-> 252
/*    */     //   #11	-> 275
/*    */     //   #12	-> 280
/*    */     //   #13	-> 302
/*    */     //   #14	-> 329
/*    */     //   #15	-> 338
/*    */     //   #16	-> 354
/*    */     //   #17	-> 357
/*    */     //   #18	-> 361
/*    */     //   #19	-> 383
/*    */     //   #20	-> 392
/*    */     //   #21	-> 431
/*    */     //   #22	-> 445
/*    */     //   #23	-> 454
/*    */     //   #24	-> 497
/*    */     //   #25	-> 640
/*    */     //   #26	-> 645
/*    */     //   #27	-> 649
/*    */     //   #28	-> 666
/*    */     //   #29	-> 675
/* 11 */     //   #30	-> 681 } public final void V90(throws paramthrows) { if (this.Pe) { this.Pe = false; int j; if (this.go >= (j = this.nN)) this.go = -1;  j = (Math.max(0, j - this.y00.length) + (j = this.rI0) - 1) / j * j; if (this.Zb0 > j) this.Zb0 = Math.max(0, j);  boolean bool; byte b; x9[] arrayOfX9; for (bool = p3(), b = 0; b < (arrayOfX9 = this.y00).length; ) { boolean bool1; x9 x91 = arrayOfX9[b]; int k; if ((k = b + this.Zb0) < this.nN) { String str; boolean bool2; xK0 xK0 = (xK0)x91; Object object; if ((object = this.my.c90(k)) == null) { str = ""; } else { xK0.getClass(); str = object.toString(); }  xK0.HC(str); object = xK0.O; Ll ll = xK0.RQ; if (object == null) { bool2 = true; } else { bool2 = false; }  object.gf0(ll, bool2); this.my.getClass(); xK0.z4 = null; xK0.zn(); } else { ((xK0)x91)
/*    */ 
/*    */             
/* 14 */             .HC("");
/* 15 */           ((xK0)x91).O
/* 16 */             .gf0(xK0.RQ, true);
/* 17 */           ((xK0)x91).z4 = null; ((xK0)x91).zn(); }  if (k == this
/* 18 */           .go) { bool1 = true; } else { bool1 = false; }  if (((xK0)(x91 = x91))
/* 19 */           .dv != bool1) { ((xK0)x91)
/* 20 */             .dv = bool1;
/* 21 */           ((JG0)x91).O
/* 22 */             .gf0(xK0.qG0, bool1); }  if (k == this
/* 23 */           .go && bool) { k = 1; } else { k = 0; }  ((JG0)x91)
/* 24 */           .O
/* 25 */           .gf0(JG0.e30, k); b++; }  }
/* 26 */      int i = (Math.max(0, this.nN - this.y00.length) + (i = this.rI0) - 1) / i;
/* 27 */     this.qz0.mE0(i); this.qz0.Fk0(this.Zb0 / this.rI0, false); super.V90(paramthrows); }
/*    */ 
/*    */   
/*    */   public final int AW() {
/*    */     return Math.max(super.AW(), this.qz0.AW());
/*    */   }
/*    */   
/*    */   public final int HY() {
/*    */     int i = Math.max(super.HY(), this.qz0.HY());
/*    */     if (this.LPt1 > 0) {
/*    */       i = Et();
/*    */       i = Math.max(i, Math.min(this.nN, this.LPt1) * this.fG0 + i);
/*    */     } 
/*    */     return i;
/*    */   }
/*    */   
/*    */   public final int R80() {
/*    */     return Math.max(super.R80(), this.qz0.AW());
/*    */   }
/*    */   
/*    */   public final int tJ0() {
/*    */     int i;
/*    */     return Math.max((this.nN + (i = this.rI0) - 1) / i * this.fG0, this.qz0.HY());
/*    */   }
/*    */   
/*    */   public final void d40() {
/*    */     // Byte code:
/*    */     //   0: aload_0
/*    */     //   1: dup
/*    */     //   2: dup2
/*    */     //   3: getfield qz0 : Lf/Ja;
/*    */     //   6: dup
/*    */     //   7: aload_0
/*    */     //   8: swap
/*    */     //   9: invokevirtual AW : ()I
/*    */     //   12: istore_1
/*    */     //   13: invokevirtual Hy : ()I
/*    */     //   16: iload_1
/*    */     //   17: swap
/*    */     //   18: invokevirtual Tm : (II)Z
/*    */     //   21: pop
/*    */     //   22: getfield qz0 : Lf/Ja;
/*    */     //   25: aload_0
/*    */     //   26: dup
/*    */     //   27: invokevirtual m40 : ()I
/*    */     //   30: aload_0
/*    */     //   31: getfield qz0 : Lf/Ja;
/*    */     //   34: getfield xY : I
/*    */     //   37: isub
/*    */     //   38: istore_1
/*    */     //   39: invokevirtual e3 : ()I
/*    */     //   42: iload_1
/*    */     //   43: swap
/*    */     //   44: invokevirtual ME : (II)Z
/*    */     //   47: pop
/*    */     //   48: invokevirtual Hy : ()I
/*    */     //   51: aload_0
/*    */     //   52: getfield fG0 : I
/*    */     //   55: idiv
/*    */     //   56: iconst_1
/*    */     //   57: swap
/*    */     //   58: invokestatic max : (II)I
/*    */     //   61: istore_1
/*    */     //   62: getfield uu : I
/*    */     //   65: iconst_m1
/*    */     //   66: if_icmpeq -> 98
/*    */     //   69: aload_0
/*    */     //   70: dup
/*    */     //   71: getfield qz0 : Lf/Ja;
/*    */     //   74: getfield Kd : I
/*    */     //   77: aload_0
/*    */     //   78: invokevirtual RS : ()I
/*    */     //   81: isub
/*    */     //   82: aload_0
/*    */     //   83: getfield uu : I
/*    */     //   86: idiv
/*    */     //   87: iconst_1
/*    */     //   88: swap
/*    */     //   89: invokestatic max : (II)I
/*    */     //   92: putfield rI0 : I
/*    */     //   95: goto -> 103
/*    */     //   98: aload_0
/*    */     //   99: iconst_1
/*    */     //   100: putfield rI0 : I
/*    */     //   103: iload_1
/*    */     //   104: aload_0
/*    */     //   105: getfield rI0 : I
/*    */     //   108: imul
/*    */     //   109: istore_2
/*    */     //   110: getstatic f/Ga.mc0 : Z
/*    */     //   113: ifne -> 132
/*    */     //   116: iload_2
/*    */     //   117: iconst_1
/*    */     //   118: if_icmplt -> 124
/*    */     //   121: goto -> 132
/*    */     //   124: new java/lang/AssertionError
/*    */     //   127: dup
/*    */     //   128: invokespecial <init> : ()V
/*    */     //   131: athrow
/*    */     //   132: iload_2
/*    */     //   133: aload_0
/*    */     //   134: getfield qz0 : Lf/Ja;
/*    */     //   137: astore_3
/*    */     //   138: iconst_1
/*    */     //   139: if_icmplt -> 527
/*    */     //   142: aload_3
/*    */     //   143: dup
/*    */     //   144: iload_2
/*    */     //   145: putfield x10 : I
/*    */     //   148: getfield zm0 : Z
/*    */     //   151: ifeq -> 158
/*    */     //   154: aload_3
/*    */     //   155: invokevirtual ve : ()V
/*    */     //   158: aload_0
/*    */     //   159: getfield y00 : [Lf/x9;
/*    */     //   162: arraylength
/*    */     //   163: istore_3
/*    */     //   164: iload_3
/*    */     //   165: istore #4
/*    */     //   167: iload #4
/*    */     //   169: dup
/*    */     //   170: iconst_m1
/*    */     //   171: iadd
/*    */     //   172: istore #4
/*    */     //   174: iload_2
/*    */     //   175: if_icmple -> 190
/*    */     //   178: aload_0
/*    */     //   179: iload #4
/*    */     //   181: iconst_1
/*    */     //   182: iadd
/*    */     //   183: invokespecial fG0 : (I)Lf/JG0;
/*    */     //   186: pop
/*    */     //   187: goto -> 167
/*    */     //   190: aload_0
/*    */     //   191: dup
/*    */     //   192: iload_2
/*    */     //   193: anewarray f/x9
/*    */     //   196: astore #4
/*    */     //   198: getfield y00 : [Lf/x9;
/*    */     //   201: astore #5
/*    */     //   203: aload #4
/*    */     //   205: aload #5
/*    */     //   207: iload_2
/*    */     //   208: aload #5
/*    */     //   210: arraylength
/*    */     //   211: invokestatic min : (II)I
/*    */     //   214: istore #5
/*    */     //   216: iconst_0
/*    */     //   217: aload #4
/*    */     //   219: iconst_0
/*    */     //   220: iload #5
/*    */     //   222: invokestatic arraycopy : (Ljava/lang/Object;ILjava/lang/Object;II)V
/*    */     //   225: putfield y00 : [Lf/x9;
/*    */     //   228: iload_3
/*    */     //   229: iload_2
/*    */     //   230: if_icmpge -> 296
/*    */     //   233: aload_0
/*    */     //   234: dup
/*    */     //   235: dup
/*    */     //   236: invokevirtual sa0 : ()Lf/x9;
/*    */     //   239: dup
/*    */     //   240: astore #4
/*    */     //   242: new f/Lo
/*    */     //   245: dup
/*    */     //   246: astore #5
/*    */     //   248: aload_0
/*    */     //   249: iload_3
/*    */     //   250: invokespecial <init> : (Lf/Ga;I)V
/*    */     //   253: checkcast f/xK0
/*    */     //   256: dup
/*    */     //   257: dup
/*    */     //   258: getfield Dq0 : [Lf/tC0;
/*    */     //   261: aload #5
/*    */     //   263: ldc f/tC0
/*    */     //   265: invokestatic LpT6 : ([Ljava/lang/Object;Ljava/lang/Object;Ljava/lang/Class;)[Ljava/lang/Object;
/*    */     //   268: checkcast [Lf/tC0;
/*    */     //   271: putfield Dq0 : [Lf/tC0;
/*    */     //   274: iload_3
/*    */     //   275: iconst_1
/*    */     //   276: iadd
/*    */     //   277: dup
/*    */     //   278: istore #5
/*    */     //   280: invokespecial si : (Lf/JG0;I)V
/*    */     //   283: getfield y00 : [Lf/x9;
/*    */     //   286: iload_3
/*    */     //   287: aload #4
/*    */     //   289: aastore
/*    */     //   290: iload #5
/*    */     //   292: istore_3
/*    */     //   293: goto -> 228
/*    */     //   296: aload_0
/*    */     //   297: dup
/*    */     //   298: getfield qz0 : Lf/Ja;
/*    */     //   301: getfield Kd : I
/*    */     //   304: aload_0
/*    */     //   305: invokevirtual RS : ()I
/*    */     //   308: isub
/*    */     //   309: istore_3
/*    */     //   310: invokevirtual Hy : ()I
/*    */     //   313: istore #4
/*    */     //   315: iconst_0
/*    */     //   316: istore #5
/*    */     //   318: iload #5
/*    */     //   320: iload_2
/*    */     //   321: if_icmpge -> 521
/*    */     //   324: aload_0
/*    */     //   325: getfield vn : Z
/*    */     //   328: ifeq -> 352
/*    */     //   331: iload #5
/*    */     //   333: dup
/*    */     //   334: aload_0
/*    */     //   335: getfield rI0 : I
/*    */     //   338: dup
/*    */     //   339: istore #6
/*    */     //   341: idiv
/*    */     //   342: istore #7
/*    */     //   344: iload #6
/*    */     //   346: irem
/*    */     //   347: istore #6
/*    */     //   349: goto -> 363
/*    */     //   352: iload #5
/*    */     //   354: dup
/*    */     //   355: iload_1
/*    */     //   356: irem
/*    */     //   357: istore #7
/*    */     //   359: iload_1
/*    */     //   360: idiv
/*    */     //   361: istore #6
/*    */     //   363: aload_0
/*    */     //   364: getfield Jv : Z
/*    */     //   367: ifeq -> 385
/*    */     //   370: iload #7
/*    */     //   372: aload_0
/*    */     //   373: getfield fG0 : I
/*    */     //   376: dup
/*    */     //   377: istore #7
/*    */     //   379: imul
/*    */     //   380: istore #8
/*    */     //   382: goto -> 407
/*    */     //   385: iload #7
/*    */     //   387: dup
/*    */     //   388: iload #4
/*    */     //   390: imul
/*    */     //   391: iload_1
/*    */     //   392: idiv
/*    */     //   393: istore #8
/*    */     //   395: iconst_1
/*    */     //   396: iadd
/*    */     //   397: iload #4
/*    */     //   399: imul
/*    */     //   400: iload_1
/*    */     //   401: idiv
/*    */     //   402: iload #8
/*    */     //   404: isub
/*    */     //   405: istore #7
/*    */     //   407: aload_0
/*    */     //   408: getfield Om : Z
/*    */     //   411: ifeq -> 435
/*    */     //   414: aload_0
/*    */     //   415: getfield uu : I
/*    */     //   418: dup
/*    */     //   419: istore #9
/*    */     //   421: iconst_m1
/*    */     //   422: if_icmpeq -> 435
/*    */     //   425: iload #6
/*    */     //   427: iload #9
/*    */     //   429: imul
/*    */     //   430: istore #6
/*    */     //   432: goto -> 470
/*    */     //   435: iload #6
/*    */     //   437: dup
/*    */     //   438: iload_3
/*    */     //   439: imul
/*    */     //   440: aload_0
/*    */     //   441: getfield rI0 : I
/*    */     //   444: dup
/*    */     //   445: istore #6
/*    */     //   447: idiv
/*    */     //   448: istore #9
/*    */     //   450: iconst_1
/*    */     //   451: iadd
/*    */     //   452: iload_3
/*    */     //   453: imul
/*    */     //   454: iload #6
/*    */     //   456: idiv
/*    */     //   457: iload #9
/*    */     //   459: isub
/*    */     //   460: istore #6
/*    */     //   462: iload #6
/*    */     //   464: iload #9
/*    */     //   466: istore #6
/*    */     //   468: istore #9
/*    */     //   470: aload_0
/*    */     //   471: getfield y00 : [Lf/x9;
/*    */     //   474: iload #5
/*    */     //   476: aaload
/*    */     //   477: checkcast f/JG0
/*    */     //   480: dup
/*    */     //   481: aload_0
/*    */     //   482: swap
/*    */     //   483: iconst_0
/*    */     //   484: iload #9
/*    */     //   486: invokestatic max : (II)I
/*    */     //   489: iconst_0
/*    */     //   490: iload #7
/*    */     //   492: invokestatic max : (II)I
/*    */     //   495: invokevirtual Tm : (II)Z
/*    */     //   498: pop
/*    */     //   499: invokevirtual RS : ()I
/*    */     //   502: iload #6
/*    */     //   504: iadd
/*    */     //   505: aload_0
/*    */     //   506: invokevirtual e3 : ()I
/*    */     //   509: iload #8
/*    */     //   511: iadd
/*    */     //   512: invokevirtual Ol0 : (II)V
/*    */     //   515: iinc #5, 1
/*    */     //   518: goto -> 318
/*    */     //   521: aload_0
/*    */     //   522: iconst_1
/*    */     //   523: putfield Pe : Z
/*    */     //   526: return
/*    */     //   527: aload_3
/*    */     //   528: invokevirtual getClass : ()Ljava/lang/Class;
/*    */     //   531: pop
/*    */     //   532: new java/lang/IllegalArgumentException
/*    */     //   535: dup
/*    */     //   536: ldc_w 'pageSize < 1'
/*    */     //   539: invokespecial <init> : (Ljava/lang/String;)V
/*    */     //   542: athrow
/*    */     // Line number table:
/*    */     //   Java source line number -> byte code offset
/*    */     //   #1	-> 9
/*    */     //   #2	-> 13
/*    */     //   #3	-> 34
/*    */     //   #4	-> 39
/*    */     //   #5	-> 44
/*    */     //   #6	-> 48
/*    */     //   #7	-> 74
/*    */     //   #8	-> 78
/*    */     //   #9	-> 105
/*    */     //   #10	-> 145
/*    */     //   #11	-> 148
/*    */     //   #12	-> 159
/*    */     //   #13	-> 258
/*    */     //   #14	-> 263
/*    */     //   #15	-> 280
/*    */     //   #16	-> 301
/*    */     //   #17	-> 305
/*    */     //   #18	-> 523
/*    */     //   #19	-> 528
/*    */     //   #20	-> 532
/*    */   }
/*    */   
/*    */   public x9 sa0() {
/*    */     return new xK0();
/*    */   }
/*    */   
/*    */   public final void LM(throws paramthrows) {
/*    */     this(new C10(this));
/*    */     YG yG;
/*    */     this.Kt0 = new YG();
/*    */     paramthrows.xr.K90(yG);
/*    */   }
/*    */   
/*    */   public final void ED0(throws paramthrows) {
/*    */     paramthrows.xr.Sh0(this.Kt0);
/*    */   }
/*    */   
/*    */   public final void UN(cQ paramcQ) {
/*    */     cQ cQ1;
/*    */     if ((cQ1 = this.my) != paramcQ) {
/*    */       if (cQ1 != null)
/*    */         cQ1.rw = (MQ[])hm.LL0(this.Db0, (Object[])cQ1.rw); 
/*    */       this.my = paramcQ;
/*    */       if (paramcQ != null) {
/*    */         w1 w11 = this.Db0;
/*    */         paramcQ.rw = (MQ[])hm.LpT6((Object[])paramcQ.rw, w11, MQ.class);
/*    */       } 
/*    */       this.Db0.kR();
/*    */     } 
/*    */   } }


/* Location:              /Users/vnnsnnt/Documents/Codespace/JavaWorkspace/RedTrainer/src/main/java/org/trainer/client/PokeMMO.jar!/f/Ga.class
 * Java compiler version: 8 (52.0)
 * JD-Core Version:       1.1.3
 */