/*    */ package f;public final class gO extends Qa0 implements r60 { public YA0 DQ; public n3[] Gu0; public final Iq0 LPt7; public NR oP; public nJ0[] fH; public Fp default; public YA0 Ve; public YA0 WG0; public ZE M50; public of ok0; public rS Uj; public vF0 lS; public k4 gD; public vF0 lD; public vF0 c30; public vF0 Dr; public vF0 tr; public vF0 cB0; public ge0 lp0; public ge0 ek; public mX a2; public kg0 sK0; public boolean At0; public j40 ub; public UA0 NV; public boolean D1; public dQ Oj; public dQ Yk; public vF0 ON; public dQ J70; public dQ XI0; public dQ Yr; public dQ YL; public dQ Dp; public dQ eF0; public vF0 Fq; public vF0[] Vj; public dQ[] e0; public dQ ER; public vF0 YI; public dQ Es0; public dQ VK0; public int s5; public Qv0 U40; public final HashSet Lpt8; public gf PP; public Yw0 oq; public sM ob; public sM UN; public boolean Sv0; public dQ FM; public Ip Bq0; public rS AF0; public cx0 xI0; public cx0 me; public final fQ V3; public boolean iE0; public gO(Iq0 paramIq0) { super(km.XU()); YA0 yA01; pRn pRn; YA0 yA02; this.At0 = false; this.Lpt8 = new HashSet(); this.ob = null; this.UN = null; this.Sv0 = false; this.xI0 = new cx0(); this.me = new cx0(); this.V3 = new fQ(); this.iE0 = false; this.LPt7 = paramIq0; this(); if (km.XU()) yA01.oU();  this((byte)-1, (byte)-1, (byte)-1, (byte)-1); Vo0(new I(this, pRn)); Xu("pc-frame"); Lo(Ml0.OH0(1118)); EP(1); if (km.u4.s40(aq0.XJ0) == null) { km.u4.Am(new Cg0(km.a3.wQ().VC())); js.N2().ln0(Ml0.OH0(2312)); return; }  (this.sK0 = new kg0(km.wI0.cF)).fA0(km.mI0.AN); TG0(this::close); this.default = new Fp(); if (km.XU()) { YA0 yA0 = jt(); yA01.try(yA0).fu().Ig0(290.0F).sV().fa0(60.0F); } else { float f; YA0 yA0 = jt(); nJ0 nJ01 = yA01.try(yA0).fu(); if (t90.bigCJKFontSizes()) { f = 320.0F; } else { f = 275.0F; }  nJ01 = nJ01.Ig0(f); nJ01.fJ((t90.bigCJKFontSizes() ? 'ɝ' : 'Ȱ')).sV(); }  this(pA.Wd(), true); this.oP = nR; NR nR; (nR = new NR()).To(this::ee); this(); if (km.XU()) { yA02.try(lK0()).fa0(5.0F).zm0(); yA02.try(wF()).fa0(3.0F).J80(2.0F).K4().zm0(); (new YA0()).Dv0.S7(this.default).J80(10.0F).fu().K4(); (new YA0()).Dv0.S7(this.oP).ti0().sg(5.0F); yA02.try(new YA0()).DJ().sV().sg(5.0F).fa0(10.0F); } else { yA02.try(lK0()).fJ(60.0F).Xs0().zm0(); yA02.try(wF()).K4().sg(5.0F).zm0(); (new YA0()).Dv0.S7(this.default).J80(0.0F).K4(); (new YA0()).Dv0.S7(this.oP).Xs0().fa0(5.0F); yA02.try(new YA0()).Ig0(700.0F).sV().fa0(2.0F).sg(5.0F).zm0(); yA02.try(JU()).J80(5.0F).NT().Kw().AuX(4.0F).sg(5.0F); }  if (km.XU()) { this.DQ = new YA0(); yA01.try(yA02).LPT7(); this.DQ.try(yA01).LPT7(); this.DQ.ZE(); this.DQ.try(JU()).Kw(); Xg0(km.wI0.dG(), km.wI0.k1()); } else { yA01.try(yA02).LPT7(); this.oP.mM(); this.oP.uW(); this.DQ = yA01; }  J8(this.DQ); XH0(0); }
/*  2 */   public static void po0(JG0 paramJG0, j40 paramj40) { (paramJG0 = paramJG0.fr0.fr0).getClass();
/*  3 */     if (paramj40 != null && !paramj40.Zs.YC()) { ((kC0)paramJG0)
/*  4 */         .cv0
/*    */ 
/*    */ 
/*    */ 
/*    */ 
/*    */         
/* 10 */         .Be0(((kC0)paramJG0).cv0.F2.toString() + "{M:" + paramj40.Jg + "}", false);
/* 11 */       VA0.c90(((kC0)paramJG0).cv0); }  } public static void XK(JG0 paramJG0, j40 paramj40) { ((wu)paramJG0.fr0.fr0.fr0).Rd0(paramj40); } public static int SK(Qv0 paramQv01, Qv0 paramQv02) { if (paramQv01 == paramQv02) return 0;  if (paramQv01.Ba0.public() == null) return -1;  if (paramQv02.Ba0.public() == null) return 1;  return (paramQv01.fH0() - paramQv01.Ba0.fH0() > 0) ? Integer.compare(paramQv01.fH0(), paramQv02.fH0()) : Integer.compare(paramQv02.fH0(), paramQv01.fH0()); } public static boolean Oj0(Qv0 paramQv0) { Qv0 qv0; if ((qv0 = paramQv0.Ba0) == null) return false;  if (qv0 == paramQv0) return false;  if (paramQv0.public() == null) return false;  return paramQv0.Ba0.y1() ^ true; } private void Uy() { Ip ip; if (!this.Sv0) { this.FM.E1(Ml0.OH0(55)); km.u4.e20.W3(new ri()); return; }  if (this.Bq0 != null) { ArrayList<kK> arrayList; this(); if (this.ob != null) arrayList.add(new kK(this.ob, true));  if (this.UN != null) arrayList.add(new kK(this.UN, true));  kK[] arrayOfKK; if ((arrayOfKK = arrayList.<kK>toArray(new kK[0])).length > 0) { this.Bq0.gx(); (ip = this.Bq0).getClass(); this.Bq0.rK0((new g0(this)).Mg((JG0[])arrayOfKK)); (ip = this.Bq0).getClass(); this.Bq0.WN((new cr0(this)).Em0().Mg((JG0[])arrayOfKK).Em0()); return; }  }  ((gO)super).FM.E1(Ml0.OH0(3004)); } private void gy0(gf paramgf) { XH0(paramgf.Ba0); paramgf.V0.H0(0); } private void sz0(gf paramgf) { XH0(paramgf.Ba0); paramgf.V0.H0(0); } private void Oz0(bv parambv) { // Byte code:
/*    */     //   0: aload_1
/*    */     //   1: getstatic f/bv.Gg : Lf/bv;
/*    */     //   4: if_acmpne -> 99
/*    */     //   7: aload_0
/*    */     //   8: getfield fH : [Lf/nJ0;
/*    */     //   11: aload_0
/*    */     //   12: getfield s5 : I
/*    */     //   15: aaload
/*    */     //   16: getfield ZX : Ljava/lang/Object;
/*    */     //   19: checkcast f/gf
/*    */     //   22: astore_1
/*    */     //   23: new f/VH
/*    */     //   26: dup
/*    */     //   27: dup
/*    */     //   28: astore_2
/*    */     //   29: aload_0
/*    */     //   30: aload_2
/*    */     //   31: aload_0
/*    */     //   32: aload_1
/*    */     //   33: <illegal opcode> Bn : (Lf/gO;Lf/gf;)Lf/Tx;
/*    */     //   38: astore_0
/*    */     //   39: sipush #7004
/*    */     //   42: invokestatic OH0 : (I)Ljava/lang/String;
/*    */     //   45: bipush #20
/*    */     //   47: aload_0
/*    */     //   48: invokespecial <init> : (Ljava/lang/String;ILf/Tx;)V
/*    */     //   51: getfield LPt7 : Lf/Iq0;
/*    */     //   54: aload_1
/*    */     //   55: getfield Ki0 : I
/*    */     //   58: i2b
/*    */     //   59: invokevirtual Kg : (B)Ljava/lang/String;
/*    */     //   62: astore_0
/*    */     //   63: getfield Hl : Lf/of;
/*    */     //   66: aload_0
/*    */     //   67: iconst_0
/*    */     //   68: invokevirtual Be0 : (Ljava/lang/String;Z)V
/*    */     //   71: getfield Hl : Lf/of;
/*    */     //   74: ldc_w '[ |\p{L}|\p{N}|\p{P}]{1,20}'
/*    */     //   77: invokevirtual Lpt5 : (Ljava/lang/String;)V
/*    */     //   80: getstatic f/pA.Dg0 : Lf/pA;
/*    */     //   83: aload_2
/*    */     //   84: invokevirtual J8 : (Lf/JG0;)V
/*    */     //   87: getstatic f/UB0.Kg0 : Lf/Q50;
/*    */     //   90: aload_2
/*    */     //   91: <illegal opcode> run : (Lf/VH;)Ljava/lang/Runnable;
/*    */     //   96: invokevirtual fN : (Ljava/lang/Runnable;)V
/*    */     //   99: return
/*    */     // Line number table:
/*    */     //   Java source line number -> byte code offset
/*    */     //   #1	-> 16
/*    */     //   #2	-> 19
/*    */     //   #3	-> 42
/*    */     //   #4	-> 51
/*    */     //   #5	-> 55
/*    */     //   #6	-> 59
/*    */     //   #7	-> 63
/*    */     //   #8	-> 68
/*    */     //   #9	-> 71
/*    */     //   #10	-> 74
/*    */     //   #11	-> 80
/* 11 */     //   #12	-> 84 } public final void d40() { super.d40(); NR nR; if ((nR = this.oP) != null) nR.mM();  int i = this.lS.TS.e00(); byte b = 0; j40 j401; if (!this.D1 && (j401 = this.ub) != null) { short s; if ((s = j401.Zs.Cw0) != 3) { if (s == 130) b = -40;  } else { b = -20; }  }  rH rH; k4 k41; (rH = this.lS.TS).zT((k41 = this.gD).xY / 2 - i / 2 + b, k41.HC / 2 + -10 - rH.cA() / 2); if (km.XU()) { this.tr
/* 12 */         .TS
/*    */ 
/*    */ 
/*    */ 
/*    */ 
/*    */ 
/*    */         
/* 19 */         .zT(this.gD.xY - this.tr.TS.e00() - 5, this.gD.HC - this.tr.TS.cA() + 18); i = 5; if (this.ub != null) { this.c30
/* 20 */           .TS
/* 21 */           .zT(5, i); if (this.ub
/* 22 */           .Zs
/* 23 */           .tm0())
/*    */         {
/*    */           
/* 26 */           i = this.c30.TS.cA() + i; }  this.Dr
/* 27 */           .TS
/* 28 */           .zT(5, i); }  this.lD
/* 29 */         .TS
/*    */ 
/*    */         
/* 32 */         .zT(1, this.gD.HC - this.lD.TS.cA() + 32 - 20); this.cB0
/* 33 */         .TS
/*    */ 
/*    */         
/* 36 */         .zT(1, this.gD.HC - this.cB0.TS.cA() * 2 + 29 - 20); } else { this.tr
/* 37 */         .TS
/*    */ 
/*    */ 
/*    */ 
/*    */ 
/*    */ 
/*    */         
/* 44 */         .zT(this.gD.xY - this.tr.TS.e00() - 5, this.gD.HC - this.tr.TS.cA() + 35); i = -28; if (this.ub != null) { this.c30
/* 45 */           .TS
/* 46 */           .zT(5, i); if (this.ub
/* 47 */           .Zs
/* 48 */           .tm0()) i = -8; 
/* 49 */         this.Dr
/* 50 */           .TS
/* 51 */           .zT(5, i); }
/*    */ 
/*    */ 
/*    */       
/* 55 */       int j = this.gD.xY - this.lD.TS.e00() - 5; this.lD
/* 56 */         .TS
/* 57 */         .zT(j, -28); this.cB0
/* 58 */         .TS
/* 59 */         .zT(j, this.cB0.TS.cA() + -28 + 2); }  } private void h60(gf paramgf, String paramString) { if (!Iq0.rb.reset(paramString).matches()) paramString = "";  byte b2 = (byte)paramgf.Ki0; this.LPt7.kq(b2, paramString); byte b1 = (byte)paramgf.Ki0; km.u4.e20.W3(new DQ(b1, paramString)); String str; paramgf.s6(str = this.LPt7.Kg(b2)); this.VK0.E1(str); UB0.Kg0.fN(() -> VA0.c90(e8().M50())); } private void l50(Un paramUn) { // Byte code:
/*    */     //   0: new f/B3
/*    */     //   3: dup
/*    */     //   4: astore_2
/*    */     //   5: aload_1
/*    */     //   6: dup
/*    */     //   7: dup
/*    */     //   8: aload_2
/*    */     //   9: dup
/*    */     //   10: dup2
/*    */     //   11: dup2
/*    */     //   12: dup2
/*    */     //   13: dup2
/*    */     //   14: invokespecial <init> : ()V
/*    */     //   17: new f/zz
/*    */     //   20: dup
/*    */     //   21: astore_1
/*    */     //   22: iconst_0
/*    */     //   23: invokespecial <init> : (I)V
/*    */     //   26: new f/wT
/*    */     //   29: dup
/*    */     //   30: astore_2
/*    */     //   31: sipush #2330
/*    */     //   34: invokestatic OH0 : (I)Ljava/lang/String;
/*    */     //   37: aload_1
/*    */     //   38: invokespecial <init> : (Ljava/lang/String;Lf/zz;)V
/*    */     //   41: new f/zz
/*    */     //   44: dup
/*    */     //   45: astore_3
/*    */     //   46: iconst_0
/*    */     //   47: invokespecial <init> : (I)V
/*    */     //   50: new f/wT
/*    */     //   53: dup
/*    */     //   54: astore #4
/*    */     //   56: new java/lang/StringBuilder
/*    */     //   59: dup
/*    */     //   60: astore #5
/*    */     //   62: invokespecial <init> : ()V
/*    */     //   65: iconst_1
/*    */     //   66: aload #5
/*    */     //   68: ldc_w ' '
/*    */     //   71: invokestatic X9 : (ILjava/lang/StringBuilder;Ljava/lang/String;)Ljava/lang/StringBuilder;
/*    */     //   74: sipush #2331
/*    */     //   77: invokestatic OH0 : (I)Ljava/lang/String;
/*    */     //   80: invokevirtual append : (Ljava/lang/String;)Ljava/lang/StringBuilder;
/*    */     //   83: invokevirtual toString : ()Ljava/lang/String;
/*    */     //   86: aload_3
/*    */     //   87: invokespecial <init> : (Ljava/lang/String;Lf/zz;)V
/*    */     //   90: new f/zz
/*    */     //   93: dup
/*    */     //   94: astore #5
/*    */     //   96: iconst_0
/*    */     //   97: invokespecial <init> : (I)V
/*    */     //   100: new f/wT
/*    */     //   103: dup
/*    */     //   104: astore #6
/*    */     //   106: sipush #2332
/*    */     //   109: invokestatic OH0 : (I)Ljava/lang/String;
/*    */     //   112: aload #5
/*    */     //   114: invokespecial <init> : (Ljava/lang/String;Lf/zz;)V
/*    */     //   117: new f/zz
/*    */     //   120: dup
/*    */     //   121: astore #7
/*    */     //   123: iconst_0
/*    */     //   124: invokespecial <init> : (I)V
/*    */     //   127: new f/wT
/*    */     //   130: dup
/*    */     //   131: astore #8
/*    */     //   133: sipush #2333
/*    */     //   136: invokestatic OH0 : (I)Ljava/lang/String;
/*    */     //   139: aload #7
/*    */     //   141: invokespecial <init> : (Ljava/lang/String;Lf/zz;)V
/*    */     //   144: new f/zz
/*    */     //   147: dup
/*    */     //   148: astore #9
/*    */     //   150: iconst_0
/*    */     //   151: invokespecial <init> : (I)V
/*    */     //   154: new f/wT
/*    */     //   157: dup
/*    */     //   158: astore #10
/*    */     //   160: sipush #8100
/*    */     //   163: invokestatic OH0 : (I)Ljava/lang/String;
/*    */     //   166: aload #9
/*    */     //   168: invokespecial <init> : (Ljava/lang/String;Lf/zz;)V
/*    */     //   171: new f/zz
/*    */     //   174: dup
/*    */     //   175: astore #11
/*    */     //   177: iconst_0
/*    */     //   178: invokespecial <init> : (I)V
/*    */     //   181: new f/wT
/*    */     //   184: dup
/*    */     //   185: astore #12
/*    */     //   187: sipush #2334
/*    */     //   190: invokestatic OH0 : (I)Ljava/lang/String;
/*    */     //   193: aload #11
/*    */     //   195: invokespecial <init> : (Ljava/lang/String;Lf/zz;)V
/*    */     //   198: new f/zz
/*    */     //   201: dup
/*    */     //   202: astore #13
/*    */     //   204: iconst_0
/*    */     //   205: invokespecial <init> : (I)V
/*    */     //   208: new f/wT
/*    */     //   211: dup
/*    */     //   212: astore #14
/*    */     //   214: sipush #2329
/*    */     //   217: invokestatic OH0 : (I)Ljava/lang/String;
/*    */     //   220: aload #13
/*    */     //   222: invokespecial <init> : (Ljava/lang/String;Lf/zz;)V
/*    */     //   225: new f/Hk0
/*    */     //   228: dup
/*    */     //   229: astore #15
/*    */     //   231: aload_0
/*    */     //   232: aload_1
/*    */     //   233: aload #15
/*    */     //   235: sipush #2335
/*    */     //   238: invokestatic OH0 : (I)Ljava/lang/String;
/*    */     //   241: invokespecial <init> : (Ljava/lang/String;)V
/*    */     //   244: aload_3
/*    */     //   245: aload #11
/*    */     //   247: aload #5
/*    */     //   249: aload #7
/*    */     //   251: aload #9
/*    */     //   253: aload #13
/*    */     //   255: <illegal opcode> run : (Lf/gO;Lf/qs;Lf/qs;Lf/qs;Lf/qs;Lf/qs;Lf/qs;Lf/qs;)Ljava/lang/Runnable;
/*    */     //   260: putfield rv : Ljava/lang/Runnable;
/*    */     //   263: getfield aV : Ljava/util/ArrayList;
/*    */     //   266: aload_2
/*    */     //   267: invokevirtual add : (Ljava/lang/Object;)Z
/*    */     //   270: pop
/*    */     //   271: getfield aV : Ljava/util/ArrayList;
/*    */     //   274: aload #4
/*    */     //   276: invokevirtual add : (Ljava/lang/Object;)Z
/*    */     //   279: pop
/*    */     //   280: getfield aV : Ljava/util/ArrayList;
/*    */     //   283: aload #14
/*    */     //   285: invokevirtual add : (Ljava/lang/Object;)Z
/*    */     //   288: pop
/*    */     //   289: getfield aV : Ljava/util/ArrayList;
/*    */     //   292: aload #12
/*    */     //   294: invokevirtual add : (Ljava/lang/Object;)Z
/*    */     //   297: pop
/*    */     //   298: getfield aV : Ljava/util/ArrayList;
/*    */     //   301: aload #10
/*    */     //   303: invokevirtual add : (Ljava/lang/Object;)Z
/*    */     //   306: pop
/*    */     //   307: getfield aV : Ljava/util/ArrayList;
/*    */     //   310: aload #6
/*    */     //   312: invokevirtual add : (Ljava/lang/Object;)Z
/*    */     //   315: pop
/*    */     //   316: getfield aV : Ljava/util/ArrayList;
/*    */     //   319: aload #8
/*    */     //   321: invokevirtual add : (Ljava/lang/Object;)Z
/*    */     //   324: pop
/*    */     //   325: new f/Hk0
/*    */     //   328: dup
/*    */     //   329: astore_0
/*    */     //   330: invokespecial <init> : ()V
/*    */     //   333: getfield aV : Ljava/util/ArrayList;
/*    */     //   336: aload_0
/*    */     //   337: invokevirtual add : (Ljava/lang/Object;)Z
/*    */     //   340: pop
/*    */     //   341: getfield aV : Ljava/util/ArrayList;
/*    */     //   344: aload #15
/*    */     //   346: invokevirtual add : (Ljava/lang/Object;)Z
/*    */     //   349: pop
/*    */     //   350: getfield Kd : I
/*    */     //   353: istore_0
/*    */     //   354: getfield er0 : I
/*    */     //   357: iload_0
/*    */     //   358: swap
/*    */     //   359: invokestatic T1 : (Lf/hu;Lf/JG0;II)V
/*    */     //   362: return
/*    */     // Line number table:
/*    */     //   Java source line number -> byte code offset
/*    */     //   #1	-> 23
/*    */     //   #2	-> 26
/*    */     //   #3	-> 47
/*    */     //   #4	-> 50
/*    */     //   #5	-> 68
/*    */     //   #6	-> 77
/*    */     //   #7	-> 97
/*    */     //   #8	-> 100
/*    */     //   #9	-> 124
/*    */     //   #10	-> 127
/*    */     //   #11	-> 151
/*    */     //   #12	-> 154
/*    */     //   #13	-> 178
/*    */     //   #14	-> 181
/*    */     //   #15	-> 205
/*    */     //   #16	-> 208
/*    */     //   #17	-> 260
/*    */     //   #18	-> 263
/*    */     //   #19	-> 325
/*    */     //   #20	-> 333
/*    */     //   #21	-> 350
/*    */     //   #22	-> 354
/* 59 */     //   #23	-> 359 } private void final(qs paramqs1, qs paramqs2, qs paramqs3, qs paramqs4, qs paramqs5, qs paramqs6, qs paramqs7) { byte b = 0; if (paramqs1.getValue()) b = (byte)1;  if (paramqs2.getValue()) b = (byte)(b | 0x2);  if (paramqs3.getValue()) b = (byte)(b | 0x4);  if (paramqs4.getValue()) b = (byte)(b | 0x8);  if (paramqs5.getValue()) b = (byte)(b | 0x10);  if (paramqs6.getValue()) b = (byte)(b | 0x20);  if (paramqs7.getValue()) b = (byte)((byte)(b | 0x40) | 0x4);  int[] arrayOfInt; (arrayOfInt = new int[1])[0] = (e8()).Zb; km.u4.e20.W3(new yN(b, arrayOfInt)); } private void Ft0() { this.WG0 = null; this.V3.clear(); this.ok0.Be0("", false); Fw(false); } public static vy SI0(Ap paramAp, dQ paramdQ) { JG0[] arrayOfJG0; (arrayOfJG0 = new JG0[2])[0] = paramAp; (new JG0[2])[1] = paramdQ; (new vy(arrayOfJG0)).sh0 = 5.0F; return new vy(arrayOfJG0); } public final void Jj(boolean paramBoolean) { if (paramBoolean) { this.WG0 = null; this.V3.clear(); }  gx(); Un un = this.Ki; si(this, Ub()); YA0 yA0 = this.DQ; si(this, Ub()); Fw(false); e8().H0((e8()).Gg0); this.iE0 = false; } public final void IG0() { e8().H0(0); mX mX1; j40 j401; if ((mX1 = this.a2) != null && (j401 = this.ub) != null) this.gD.td0 = mX1.rv0((pRn)Rs.OS.get(j401.rG()));  } public final YA0 jt() { this(); YA0 yA0; Ln ln; byte b3; (new YA0()).Xu("preview-frame"); (new YA0()).Dv0.RT.getClass(); this(2.0F); (new YA0()).Dv0.RT.x90 = new Ln(); (new YA0()).Dv0.RT.gL = ln; (new YA0()).Dv0.RT.Ph = ln; (new YA0()).Dv0.RT.B5 = ln; (new YA0()).Dv0.RT.Xs0().fu(); this.lS = new vF0(); if (km.XU()) { this.lS.Cu0(280, 200); this.lS.RI(280, 200); } else { this.lS.Cu0(280, 100); this.lS.RI(280, 100); }  this.lD = new vF0(); this.cB0 = new vF0(); this.c30 = new vF0(); this.Dr = new vF0(); this.tr = new vF0(); (this.Oj = new dQ()).Xu("monster-name-label"); (this.Yk = new dQ()).Xu("monster-name-label"); this.ON = new vF0(16, 16, 0); this.J70 = new dQ(); this.XI0 = new dQ(); (this.Yr = new dQ()).Xu("label-markup"); this.YL = new dQ(); this.Dp = new dQ(); this.eF0 = new dQ(); vF0 vF02 = new vF0(); if (km.XU()) { b3 = 24; } else { b3 = 16; }  this(b3, 16, 0); this.Fq = vF02; vF02.TS.xB0 = 1; byte b1; vF0[] arrayOfVF0; for (this.Vj = new vF0[4], this.e0 = new dQ[4], b1 = 0; b1 < (arrayOfVF0 = this.Vj).length; ) { vF0 vF03; dQ dQ1; this(); arrayOfVF0[b1] = vF03; if (km.XU()) (this.Vj[b1]).TS.V1 = 2.0F;  this(); this.e0[b1] = dQ1; b1++; }  this.ER = new dQ(); this.YI = new vF0(16, 16, 0); this.Es0 = new dQ(); this.ON.TS.V1 = 2.0F; if (km.Nr()) this.ON.TS.zT(-8, 2);  if (km.XU()) { this.lD.TS.V1 = 2.0F; this.cB0.TS.V1 = 2.0F; this.c30.TS.V1 = 2.0F; this.Dr.TS.V1 = 2.0F; this.tr.TS.V1 = 2.0F; this.YI.TS.V1 = 2.0F; }  this(this); this.gD = k41; vF0 vF01 = this.lS; k4 k41; (new k4()).si(vF01, (k41 = new k4()).Ub()); vF01 = this.c30; this.gD.si(vF01, this.gD.Ub()); vF01 = this.Dr; this.gD.si(vF01, this.gD.Ub()); vF01 = this.tr; this.gD.si(vF01, this.gD.Ub()); vF01 = this.lD; this.gD.si(vF01, this.gD.Ub()); vF01 = this.cB0; this.gD.si(vF01, this.gD.Ub()); this.gD.Xu("border-container"); SA sA = yA0.Dv0; vy vy2 = SI0(this.Oj, this.ON); if (km.XU()) { vy2.uh0(32, 50); } else { byte b5, b4 = 32; if (t90.bigCJKFontSizes()) { b5 = 45; } else { b5 = 38; }  vy2.uh0(b4, b5); }  (sA.S7(this.Yk).R7()).ss = Integer.valueOf(2);
/* 60 */     (sA.S7(this.Yk).R7()).Ox.wP();
/* 61 */     (sA.S7(this.gD))
/* 62 */       .ss = Integer.valueOf(2);
/* 63 */     sA.S7(this.gD).Kw(); sA.S7(this.gD).x70();
/* 64 */     (sA.S7(this.gD).Ig0(250.0F).fJ(180.0F).fu())
/* 65 */       .Ox.wP();
/* 66 */     (sA.S7(vy2).R7())
/* 67 */       .ss = Integer.valueOf(2);
/* 68 */     (sA.S7(vy2).R7()).Ox.wP();
/* 69 */     nJ0 nJ01 = sA.SB(2318, "label-title").R7().Kw(); nJ01
/* 70 */       .Ox.S7(this.XI0)
/* 71 */       .Kw(); nJ01.Ox.S7(this.XI0).x70();
/* 72 */     (nJ01.Ox.S7(this.XI0)).Ox.wP();
/* 73 */     nJ01 = sA.SB(1849, "label-title").R7().Kw();
/* 74 */     (nJ01.Ox.S7(this.Yr))
/* 75 */       .Ox.wP();
/* 76 */     nJ01 = sA.SB(1800, "label-title").R7().Kw();
/* 77 */     (nJ01.Ox.S7(this.YL))
/* 78 */       .Ox.wP();
/* 79 */     nJ01 = sA.SB(1805, "label-title").R7().Kw();
/* 80 */     (nJ01.Ox.S7(this.Dp))
/* 81 */       .Ox.wP();
/* 82 */     vy vy1 = SI0(this.ER, this.YI);
/* 83 */     ((sA.SB(1824, "label-title").R7().Kw()).Ox.S7(vy1))
/* 84 */       .Ox.wP();
/* 85 */     vy1 = SI0(this.eF0, this.Fq);
/* 86 */     ((sA.SB(1842, "label-title").R7().Kw()).Ox.S7(vy1))
/* 87 */       .Ox.wP(); for (byte b2 = 0; b2 < 4; )
/* 88 */     { (sA.S7(SI0(this.Vj[b2], this.e0[b2])).J80(5.0F))
/* 89 */         .ss = Integer.valueOf(2);
/* 90 */       (sA.S7(SI0(this.Vj[b2], this.e0[b2])).J80(5.0F)).Ox.wP(); b2++; }  yA0
/* 91 */       .wI0(false);
/*    */     return yA0; }
/*    */ 
/*    */   
/*    */   public final void ee(j40 paramj40) {
/*    */     // Byte code:
/*    */     //   0: aload_0
/*    */     //   1: getfield ub : Lf/j40;
/*    */     //   4: aload_1
/*    */     //   5: if_acmpne -> 9
/*    */     //   8: return
/*    */     //   9: aload_0
/*    */     //   10: dup
/*    */     //   11: aload_1
/*    */     //   12: putfield ub : Lf/j40;
/*    */     //   15: getfield NV : Lf/UA0;
/*    */     //   18: dup
/*    */     //   19: astore_2
/*    */     //   20: ifnull -> 27
/*    */     //   23: aload_2
/*    */     //   24: invokevirtual dispose : ()V
/*    */     //   27: aload_1
/*    */     //   28: aload_0
/*    */     //   29: aconst_null
/*    */     //   30: putfield NV : Lf/UA0;
/*    */     //   33: ifnonnull -> 262
/*    */     //   36: aload_0
/*    */     //   37: dup
/*    */     //   38: dup2
/*    */     //   39: dup2
/*    */     //   40: dup2
/*    */     //   41: dup2
/*    */     //   42: dup2
/*    */     //   43: dup2
/*    */     //   44: dup2
/*    */     //   45: getfield lS : Lf/vF0;
/*    */     //   48: getfield TS : Lf/rH;
/*    */     //   51: invokevirtual H : ()V
/*    */     //   54: getfield gD : Lf/k4;
/*    */     //   57: iconst_0
/*    */     //   58: invokevirtual wI0 : (Z)V
/*    */     //   61: getfield Oj : Lf/dQ;
/*    */     //   64: ldc_w ''
/*    */     //   67: invokevirtual E1 : (Ljava/lang/String;)V
/*    */     //   70: getfield ON : Lf/vF0;
/*    */     //   73: getfield TS : Lf/rH;
/*    */     //   76: invokevirtual H : ()V
/*    */     //   79: getfield lD : Lf/vF0;
/*    */     //   82: getfield TS : Lf/rH;
/*    */     //   85: invokevirtual H : ()V
/*    */     //   88: getfield cB0 : Lf/vF0;
/*    */     //   91: getfield TS : Lf/rH;
/*    */     //   94: invokevirtual H : ()V
/*    */     //   97: getfield c30 : Lf/vF0;
/*    */     //   100: getfield TS : Lf/rH;
/*    */     //   103: invokevirtual H : ()V
/*    */     //   106: getfield Dr : Lf/vF0;
/*    */     //   109: getfield TS : Lf/rH;
/*    */     //   112: invokevirtual H : ()V
/*    */     //   115: getfield tr : Lf/vF0;
/*    */     //   118: getfield TS : Lf/rH;
/*    */     //   121: invokevirtual H : ()V
/*    */     //   124: getfield J70 : Lf/dQ;
/*    */     //   127: ldc_w ''
/*    */     //   130: invokevirtual E1 : (Ljava/lang/String;)V
/*    */     //   133: getfield XI0 : Lf/dQ;
/*    */     //   136: ldc_w ''
/*    */     //   139: invokevirtual E1 : (Ljava/lang/String;)V
/*    */     //   142: getfield Yr : Lf/dQ;
/*    */     //   145: ldc_w ''
/*    */     //   148: invokevirtual E1 : (Ljava/lang/String;)V
/*    */     //   151: getfield YL : Lf/dQ;
/*    */     //   154: ldc_w ''
/*    */     //   157: invokevirtual E1 : (Ljava/lang/String;)V
/*    */     //   160: getfield Dp : Lf/dQ;
/*    */     //   163: ldc_w ''
/*    */     //   166: invokevirtual E1 : (Ljava/lang/String;)V
/*    */     //   169: getfield eF0 : Lf/dQ;
/*    */     //   172: ldc_w ''
/*    */     //   175: invokevirtual E1 : (Ljava/lang/String;)V
/*    */     //   178: getfield Fq : Lf/vF0;
/*    */     //   181: getfield TS : Lf/rH;
/*    */     //   184: invokevirtual H : ()V
/*    */     //   187: iconst_0
/*    */     //   188: istore_1
/*    */     //   189: iload_1
/*    */     //   190: iconst_4
/*    */     //   191: if_icmpge -> 224
/*    */     //   194: aload_0
/*    */     //   195: dup
/*    */     //   196: getfield Vj : [Lf/vF0;
/*    */     //   199: iload_1
/*    */     //   200: aaload
/*    */     //   201: getfield TS : Lf/rH;
/*    */     //   204: invokevirtual H : ()V
/*    */     //   207: getfield e0 : [Lf/dQ;
/*    */     //   210: iload_1
/*    */     //   211: aaload
/*    */     //   212: ldc_w ''
/*    */     //   215: invokevirtual E1 : (Ljava/lang/String;)V
/*    */     //   218: iinc #1, 1
/*    */     //   221: goto -> 189
/*    */     //   224: aload_0
/*    */     //   225: dup
/*    */     //   226: dup2
/*    */     //   227: getfield ER : Lf/dQ;
/*    */     //   230: ldc_w ''
/*    */     //   233: invokevirtual E1 : (Ljava/lang/String;)V
/*    */     //   236: getfield YI : Lf/vF0;
/*    */     //   239: getfield TS : Lf/rH;
/*    */     //   242: invokevirtual H : ()V
/*    */     //   245: getfield Es0 : Lf/dQ;
/*    */     //   248: ldc_w ''
/*    */     //   251: invokevirtual E1 : (Ljava/lang/String;)V
/*    */     //   254: getfield Ve : Lf/YA0;
/*    */     //   257: iconst_0
/*    */     //   258: invokevirtual wI0 : (Z)V
/*    */     //   261: return
/*    */     //   262: aload_0
/*    */     //   263: dup
/*    */     //   264: getfield Ve : Lf/YA0;
/*    */     //   267: iconst_1
/*    */     //   268: invokevirtual wI0 : (Z)V
/*    */     //   271: getfield lS : Lf/vF0;
/*    */     //   274: getfield TS : Lf/rH;
/*    */     //   277: astore_2
/*    */     //   278: getstatic f/um0.Kt0 : Lf/um0;
/*    */     //   281: aload_1
/*    */     //   282: getfield Zs : Lf/Q90;
/*    */     //   285: getfield Cw0 : S
/*    */     //   288: istore_3
/*    */     //   289: getfield da : [Lf/Uf0;
/*    */     //   292: iconst_2
/*    */     //   293: aaload
/*    */     //   294: dup
/*    */     //   295: astore #4
/*    */     //   297: ifnonnull -> 305
/*    */     //   300: fconst_0
/*    */     //   301: fstore_3
/*    */     //   302: goto -> 312
/*    */     //   305: aload #4
/*    */     //   307: iload_3
/*    */     //   308: invokevirtual Sp : (S)F
/*    */     //   311: fstore_3
/*    */     //   312: aload_1
/*    */     //   313: aload_2
/*    */     //   314: aload_0
/*    */     //   315: fconst_1
/*    */     //   316: fstore #4
/*    */     //   318: getstatic f/um0.Kt0 : Lf/um0;
/*    */     //   321: aload_1
/*    */     //   322: dup
/*    */     //   323: getfield Zs : Lf/Q90;
/*    */     //   326: invokevirtual Vf0 : ()S
/*    */     //   329: istore #5
/*    */     //   331: invokevirtual s5 : ()B
/*    */     //   334: iload #5
/*    */     //   336: aload_1
/*    */     //   337: getfield Zs : Lf/Q90;
/*    */     //   340: invokevirtual tm0 : ()Z
/*    */     //   343: iconst_0
/*    */     //   344: swap
/*    */     //   345: invokevirtual rE0 : (BSZZ)Z
/*    */     //   348: putfield D1 : Z
/*    */     //   351: fconst_1
/*    */     //   352: putfield V1 : F
/*    */     //   355: getfield Zs : Lf/Q90;
/*    */     //   358: invokevirtual da : ()Z
/*    */     //   361: ifeq -> 420
/*    */     //   364: aload_1
/*    */     //   365: getfield Zs : Lf/Q90;
/*    */     //   368: invokevirtual tm0 : ()Z
/*    */     //   371: ifeq -> 387
/*    */     //   374: aload_2
/*    */     //   375: getstatic f/dM.d10 : Lcom/badlogic/gdx/graphics/Color;
/*    */     //   378: putfield bG0 : Lcom/badlogic/gdx/graphics/Color;
/*    */     //   381: fconst_1
/*    */     //   382: fstore #4
/*    */     //   384: goto -> 399
/*    */     //   387: aload_2
/*    */     //   388: getstatic f/dM.N1 : Lcom/badlogic/gdx/graphics/Color;
/*    */     //   391: putfield bG0 : Lcom/badlogic/gdx/graphics/Color;
/*    */     //   394: ldc_w 0.8
/*    */     //   397: fstore #4
/*    */     //   399: aload_2
/*    */     //   400: dup
/*    */     //   401: fload #4
/*    */     //   403: putfield is : F
/*    */     //   406: ldc_w 1.5
/*    */     //   409: putfield Vy : F
/*    */     //   412: ldc_w 1.15
/*    */     //   415: fstore #4
/*    */     //   417: goto -> 425
/*    */     //   420: aload_2
/*    */     //   421: fconst_0
/*    */     //   422: putfield is : F
/*    */     //   425: getstatic f/um0.Kt0 : Lf/um0;
/*    */     //   428: aload_1
/*    */     //   429: dup
/*    */     //   430: getfield Zs : Lf/Q90;
/*    */     //   433: invokevirtual Vf0 : ()S
/*    */     //   436: istore #5
/*    */     //   438: invokevirtual s5 : ()B
/*    */     //   441: iload #5
/*    */     //   443: aload_1
/*    */     //   444: getfield Zs : Lf/Q90;
/*    */     //   447: invokevirtual tm0 : ()Z
/*    */     //   450: iconst_0
/*    */     //   451: swap
/*    */     //   452: invokevirtual H9 : (BSZZ)[Lf/zh0;
/*    */     //   455: astore #5
/*    */     //   457: aconst_null
/*    */     //   458: astore #6
/*    */     //   460: getstatic f/um0.Kt0 : Lf/um0;
/*    */     //   463: aload_1
/*    */     //   464: dup
/*    */     //   465: getfield Zs : Lf/Q90;
/*    */     //   468: invokevirtual Vf0 : ()S
/*    */     //   471: istore #7
/*    */     //   473: invokevirtual s5 : ()B
/*    */     //   476: iload #7
/*    */     //   478: aload_1
/*    */     //   479: getfield Zs : Lf/Q90;
/*    */     //   482: invokevirtual tm0 : ()Z
/*    */     //   485: iconst_0
/*    */     //   486: swap
/*    */     //   487: invokevirtual F7 : (BSZZ)Z
/*    */     //   490: ifeq -> 525
/*    */     //   493: getstatic f/um0.Kt0 : Lf/um0;
/*    */     //   496: aload_1
/*    */     //   497: dup
/*    */     //   498: getfield Zs : Lf/Q90;
/*    */     //   501: invokevirtual Vf0 : ()S
/*    */     //   504: istore #6
/*    */     //   506: invokevirtual s5 : ()B
/*    */     //   509: iload #6
/*    */     //   511: aload_1
/*    */     //   512: getfield Zs : Lf/Q90;
/*    */     //   515: invokevirtual tm0 : ()Z
/*    */     //   518: iconst_0
/*    */     //   519: swap
/*    */     //   520: invokevirtual Hr : (BSZZ)[I
/*    */     //   523: astore #6
/*    */     //   525: getstatic f/um0.Kt0 : Lf/um0;
/*    */     //   528: aload_1
/*    */     //   529: dup
/*    */     //   530: getfield Zs : Lf/Q90;
/*    */     //   533: invokevirtual Vf0 : ()S
/*    */     //   536: istore #7
/*    */     //   538: invokevirtual s5 : ()B
/*    */     //   541: iload #7
/*    */     //   543: aload_1
/*    */     //   544: getfield Zs : Lf/Q90;
/*    */     //   547: invokevirtual tm0 : ()Z
/*    */     //   550: iconst_0
/*    */     //   551: swap
/*    */     //   552: invokevirtual rE0 : (BSZZ)Z
/*    */     //   555: ifne -> 604
/*    */     //   558: getstatic f/um0.Kt0 : Lf/um0;
/*    */     //   561: aload_1
/*    */     //   562: dup
/*    */     //   563: getfield Zs : Lf/Q90;
/*    */     //   566: invokevirtual Vf0 : ()S
/*    */     //   569: istore #7
/*    */     //   571: invokevirtual s5 : ()B
/*    */     //   574: iload #7
/*    */     //   576: aload_1
/*    */     //   577: getfield Zs : Lf/Q90;
/*    */     //   580: invokevirtual tm0 : ()Z
/*    */     //   583: iconst_0
/*    */     //   584: swap
/*    */     //   585: invokevirtual vt : (BSZZ)Lf/UA0;
/*    */     //   588: dup
/*    */     //   589: astore #7
/*    */     //   591: fload #4
/*    */     //   593: aload_0
/*    */     //   594: aload #7
/*    */     //   596: putfield NV : Lf/UA0;
/*    */     //   599: fconst_2
/*    */     //   600: fmul
/*    */     //   601: invokevirtual Zz : (F)V
/*    */     //   604: aload #5
/*    */     //   606: ifnull -> 641
/*    */     //   609: aload #5
/*    */     //   611: arraylength
/*    */     //   612: iconst_2
/*    */     //   613: if_icmple -> 641
/*    */     //   616: aload #6
/*    */     //   618: ifnull -> 641
/*    */     //   621: aload_2
/*    */     //   622: dup
/*    */     //   623: dup
/*    */     //   624: aload #5
/*    */     //   626: invokevirtual sm : ([Lf/zh0;)V
/*    */     //   629: aload #6
/*    */     //   631: invokevirtual s8 : ([I)V
/*    */     //   634: iconst_1
/*    */     //   635: putfield vU : Z
/*    */     //   638: goto -> 707
/*    */     //   641: aload_0
/*    */     //   642: getfield NV : Lf/UA0;
/*    */     //   645: dup
/*    */     //   646: astore #6
/*    */     //   648: ifnull -> 701
/*    */     //   651: aload_1
/*    */     //   652: aload_0
/*    */     //   653: aload_2
/*    */     //   654: iconst_1
/*    */     //   655: anewarray f/UA0
/*    */     //   658: dup
/*    */     //   659: iconst_0
/*    */     //   660: aload #6
/*    */     //   662: aastore
/*    */     //   663: invokevirtual fc0 : ([Lf/UA0;)V
/*    */     //   666: getfield NV : Lf/UA0;
/*    */     //   669: astore #5
/*    */     //   671: getfield Zs : Lf/Q90;
/*    */     //   674: invokevirtual da : ()Z
/*    */     //   677: ifeq -> 688
/*    */     //   680: ldc_w 0.9
/*    */     //   683: fstore #6
/*    */     //   685: goto -> 691
/*    */     //   688: fconst_1
/*    */     //   689: fstore #6
/*    */     //   691: aload #5
/*    */     //   693: fload #6
/*    */     //   695: putfield rS : F
/*    */     //   698: goto -> 707
/*    */     //   701: aload_2
/*    */     //   702: aload #5
/*    */     //   704: invokevirtual sm : ([Lf/zh0;)V
/*    */     //   707: fload_3
/*    */     //   708: aload_2
/*    */     //   709: invokevirtual cA : ()I
/*    */     //   712: istore #5
/*    */     //   714: fconst_0
/*    */     //   715: invokestatic JC0 : (FF)Z
/*    */     //   718: ifeq -> 729
/*    */     //   721: fload #4
/*    */     //   723: fconst_2
/*    */     //   724: fmul
/*    */     //   725: fstore_3
/*    */     //   726: goto -> 742
/*    */     //   729: fload_3
/*    */     //   730: fload #4
/*    */     //   732: fmul
/*    */     //   733: ldc_w 164.0
/*    */     //   736: fmul
/*    */     //   737: iload #5
/*    */     //   739: i2f
/*    */     //   740: fdiv
/*    */     //   741: fstore_3
/*    */     //   742: aload_0
/*    */     //   743: getfield NV : Lf/UA0;
/*    */     //   746: ifnonnull -> 754
/*    */     //   749: aload_2
/*    */     //   750: fload_3
/*    */     //   751: putfield V1 : F
/*    */     //   754: aload_0
/*    */     //   755: dup
/*    */     //   756: getfield gD : Lf/k4;
/*    */     //   759: iconst_1
/*    */     //   760: invokevirtual wI0 : (Z)V
/*    */     //   763: getfield a2 : Lf/mX;
/*    */     //   766: dup
/*    */     //   767: astore_2
/*    */     //   768: ifnull -> 798
/*    */     //   771: aload_0
/*    */     //   772: getfield gD : Lf/k4;
/*    */     //   775: aload_2
/*    */     //   776: aload_1
/*    */     //   777: invokevirtual rG : ()Lf/Ht0;
/*    */     //   780: getstatic f/Rs.OS : Ljava/util/EnumMap;
/*    */     //   783: swap
/*    */     //   784: invokevirtual get : (Ljava/lang/Object;)Ljava/lang/Object;
/*    */     //   787: checkcast f/pRn
/*    */     //   790: invokeinterface rv0 : (Lf/pRn;)Lf/mX;
/*    */     //   795: putfield td0 : Lf/mX;
/*    */     //   798: aload_1
/*    */     //   799: getfield Zs : Lf/Q90;
/*    */     //   802: invokevirtual YC : ()Z
/*    */     //   805: ifne -> 1102
/*    */     //   808: aload_1
/*    */     //   809: getfield Zs : Lf/Q90;
/*    */     //   812: getfield xH : Lf/mA;
/*    */     //   815: getfield WF : B
/*    */     //   818: ifle -> 866
/*    */     //   821: aload_0
/*    */     //   822: getfield tr : Lf/vF0;
/*    */     //   825: getfield TS : Lf/rH;
/*    */     //   828: iconst_1
/*    */     //   829: anewarray f/pe0
/*    */     //   832: dup
/*    */     //   833: invokestatic ZZ : ()Lf/interface;
/*    */     //   836: aload_1
/*    */     //   837: getfield Zs : Lf/Q90;
/*    */     //   840: dup
/*    */     //   841: getfield xH : Lf/mA;
/*    */     //   844: getfield WF : B
/*    */     //   847: istore_2
/*    */     //   848: invokevirtual Gf : ()Z
/*    */     //   851: iload_2
/*    */     //   852: swap
/*    */     //   853: invokevirtual kK : (IZ)Lf/pe0;
/*    */     //   856: iconst_0
/*    */     //   857: swap
/*    */     //   858: aastore
/*    */     //   859: invokevirtual Pn : ([Lf/pe0;)Lf/JG0;
/*    */     //   862: pop
/*    */     //   863: goto -> 876
/*    */     //   866: aload_0
/*    */     //   867: getfield tr : Lf/vF0;
/*    */     //   870: getfield TS : Lf/rH;
/*    */     //   873: invokevirtual H : ()V
/*    */     //   876: aload_1
/*    */     //   877: invokevirtual rG : ()Lf/Ht0;
/*    */     //   880: getfield zm0 : B
/*    */     //   883: aload_1
/*    */     //   884: invokevirtual OH : ()Lf/Ht0;
/*    */     //   887: getfield zm0 : B
/*    */     //   890: if_icmpeq -> 960
/*    */     //   893: aload_0
/*    */     //   894: dup
/*    */     //   895: getfield lD : Lf/vF0;
/*    */     //   898: getfield TS : Lf/rH;
/*    */     //   901: iconst_1
/*    */     //   902: anewarray f/pe0
/*    */     //   905: dup
/*    */     //   906: invokestatic ZZ : ()Lf/interface;
/*    */     //   909: aload_1
/*    */     //   910: invokevirtual rG : ()Lf/Ht0;
/*    */     //   913: getfield zm0 : B
/*    */     //   916: invokevirtual xk0 : (I)Lf/pe0;
/*    */     //   919: iconst_0
/*    */     //   920: swap
/*    */     //   921: aastore
/*    */     //   922: invokevirtual Pn : ([Lf/pe0;)Lf/JG0;
/*    */     //   925: pop
/*    */     //   926: getfield cB0 : Lf/vF0;
/*    */     //   929: getfield TS : Lf/rH;
/*    */     //   932: iconst_1
/*    */     //   933: anewarray f/pe0
/*    */     //   936: dup
/*    */     //   937: invokestatic ZZ : ()Lf/interface;
/*    */     //   940: aload_1
/*    */     //   941: invokevirtual OH : ()Lf/Ht0;
/*    */     //   944: getfield zm0 : B
/*    */     //   947: invokevirtual xk0 : (I)Lf/pe0;
/*    */     //   950: iconst_0
/*    */     //   951: swap
/*    */     //   952: aastore
/*    */     //   953: invokevirtual Pn : ([Lf/pe0;)Lf/JG0;
/*    */     //   956: pop
/*    */     //   957: goto -> 1002
/*    */     //   960: aload_0
/*    */     //   961: dup
/*    */     //   962: getfield lD : Lf/vF0;
/*    */     //   965: getfield TS : Lf/rH;
/*    */     //   968: iconst_1
/*    */     //   969: anewarray f/pe0
/*    */     //   972: dup
/*    */     //   973: invokestatic ZZ : ()Lf/interface;
/*    */     //   976: aload_1
/*    */     //   977: invokevirtual rG : ()Lf/Ht0;
/*    */     //   980: getfield zm0 : B
/*    */     //   983: invokevirtual xk0 : (I)Lf/pe0;
/*    */     //   986: iconst_0
/*    */     //   987: swap
/*    */     //   988: aastore
/*    */     //   989: invokevirtual Pn : ([Lf/pe0;)Lf/JG0;
/*    */     //   992: pop
/*    */     //   993: getfield cB0 : Lf/vF0;
/*    */     //   996: getfield TS : Lf/rH;
/*    */     //   999: invokevirtual H : ()V
/*    */     //   1002: aload_1
/*    */     //   1003: getfield Zs : Lf/Q90;
/*    */     //   1006: invokevirtual tm0 : ()Z
/*    */     //   1009: ifeq -> 1047
/*    */     //   1012: aload_0
/*    */     //   1013: getfield c30 : Lf/vF0;
/*    */     //   1016: getfield TS : Lf/rH;
/*    */     //   1019: iconst_1
/*    */     //   1020: anewarray f/pe0
/*    */     //   1023: dup
/*    */     //   1024: invokestatic ZZ : ()Lf/interface;
/*    */     //   1027: aload_1
/*    */     //   1028: getfield Zs : Lf/Q90;
/*    */     //   1031: invokevirtual Gf : ()Z
/*    */     //   1034: invokevirtual gj0 : (Z)Lf/pe0;
/*    */     //   1037: iconst_0
/*    */     //   1038: swap
/*    */     //   1039: aastore
/*    */     //   1040: invokevirtual Pn : ([Lf/pe0;)Lf/JG0;
/*    */     //   1043: pop
/*    */     //   1044: goto -> 1057
/*    */     //   1047: aload_0
/*    */     //   1048: getfield c30 : Lf/vF0;
/*    */     //   1051: getfield TS : Lf/rH;
/*    */     //   1054: invokevirtual H : ()V
/*    */     //   1057: aload_1
/*    */     //   1058: getfield Zs : Lf/Q90;
/*    */     //   1061: invokevirtual da : ()Z
/*    */     //   1064: ifeq -> 1095
/*    */     //   1067: aload_0
/*    */     //   1068: getfield Dr : Lf/vF0;
/*    */     //   1071: getfield TS : Lf/rH;
/*    */     //   1074: iconst_1
/*    */     //   1075: anewarray f/pe0
/*    */     //   1078: dup
/*    */     //   1079: invokestatic ZZ : ()Lf/interface;
/*    */     //   1082: getfield i00 : Lf/pe0;
/*    */     //   1085: iconst_0
/*    */     //   1086: swap
/*    */     //   1087: aastore
/*    */     //   1088: invokevirtual Pn : ([Lf/pe0;)Lf/JG0;
/*    */     //   1091: pop
/*    */     //   1092: goto -> 1151
/*    */     //   1095: aload_0
/*    */     //   1096: getfield Dr : Lf/vF0;
/*    */     //   1099: goto -> 1145
/*    */     //   1102: aload_0
/*    */     //   1103: dup
/*    */     //   1104: dup
/*    */     //   1105: dup2
/*    */     //   1106: getfield lD : Lf/vF0;
/*    */     //   1109: getfield TS : Lf/rH;
/*    */     //   1112: invokevirtual H : ()V
/*    */     //   1115: getfield cB0 : Lf/vF0;
/*    */     //   1118: getfield TS : Lf/rH;
/*    */     //   1121: invokevirtual H : ()V
/*    */     //   1124: getfield c30 : Lf/vF0;
/*    */     //   1127: getfield TS : Lf/rH;
/*    */     //   1130: invokevirtual H : ()V
/*    */     //   1133: getfield Dr : Lf/vF0;
/*    */     //   1136: getfield TS : Lf/rH;
/*    */     //   1139: invokevirtual H : ()V
/*    */     //   1142: getfield tr : Lf/vF0;
/*    */     //   1145: getfield TS : Lf/rH;
/*    */     //   1148: invokevirtual H : ()V
/*    */     //   1151: aload_0
/*    */     //   1152: getfield sK0 : Lf/kg0;
/*    */     //   1155: dup
/*    */     //   1156: astore_2
/*    */     //   1157: ifnull -> 1164
/*    */     //   1160: aload_2
/*    */     //   1161: invokevirtual pf0 : ()V
/*    */     //   1164: aload_0
/*    */     //   1165: getfield sK0 : Lf/kg0;
/*    */     //   1168: ifnull -> 1288
/*    */     //   1171: getstatic f/h1.qu0 : Z
/*    */     //   1174: ifeq -> 1288
/*    */     //   1177: aload_1
/*    */     //   1178: invokevirtual rG : ()Lf/Ht0;
/*    */     //   1181: dup
/*    */     //   1182: astore_2
/*    */     //   1183: getstatic f/Ht0.Ku : Lf/Ht0;
/*    */     //   1186: if_acmpne -> 1202
/*    */     //   1189: aload_2
/*    */     //   1190: aload_1
/*    */     //   1191: invokevirtual OH : ()Lf/Ht0;
/*    */     //   1194: if_acmpeq -> 1202
/*    */     //   1197: aload_1
/*    */     //   1198: invokevirtual OH : ()Lf/Ht0;
/*    */     //   1201: astore_2
/*    */     //   1202: aload_2
/*    */     //   1203: getstatic f/Ht0.ki0 : Lf/Ht0;
/*    */     //   1206: if_acmpeq -> 1231
/*    */     //   1209: aload_2
/*    */     //   1210: getstatic f/Ht0.Bo : Lf/Ht0;
/*    */     //   1213: if_acmpeq -> 1231
/*    */     //   1216: aload_2
/*    */     //   1217: getstatic f/Ht0.xj0 : Lf/Ht0;
/*    */     //   1220: if_acmpne -> 1226
/*    */     //   1223: goto -> 1231
/*    */     //   1226: iconst_0
/*    */     //   1227: istore_3
/*    */     //   1228: goto -> 1233
/*    */     //   1231: iconst_1
/*    */     //   1232: istore_3
/*    */     //   1233: aload_2
/*    */     //   1234: aload_0
/*    */     //   1235: iload_3
/*    */     //   1236: putfield At0 : Z
/*    */     //   1239: getstatic f/Ht0.P00 : Lf/Ht0;
/*    */     //   1242: if_acmpeq -> 1288
/*    */     //   1245: aload_2
/*    */     //   1246: getstatic f/Ht0.CW : Lf/Ht0;
/*    */     //   1249: if_acmpeq -> 1288
/*    */     //   1252: aload_0
/*    */     //   1253: dup
/*    */     //   1254: getfield sK0 : Lf/kg0;
/*    */     //   1257: ldc_w 'special/type_'
/*    */     //   1260: invokestatic df : (Ljava/lang/String;)Ljava/lang/StringBuilder;
/*    */     //   1263: aload_2
/*    */     //   1264: getfield zm0 : B
/*    */     //   1267: invokevirtual append : (I)Ljava/lang/StringBuilder;
/*    */     //   1270: invokevirtual toString : ()Ljava/lang/String;
/*    */     //   1273: invokevirtual gi0 : (Ljava/lang/String;)Lcom/badlogic/gdx/graphics/g3d/particles/ParticleEffectExt;
/*    */     //   1276: dup
/*    */     //   1277: astore_2
/*    */     //   1278: invokevirtual start : ()V
/*    */     //   1281: getfield sK0 : Lf/kg0;
/*    */     //   1284: aload_2
/*    */     //   1285: invokevirtual L40 : (Lcom/badlogic/gdx/graphics/g3d/particles/ParticleEffectExt;)V
/*    */     //   1288: aload_1
/*    */     //   1289: ldc_w '???'
/*    */     //   1292: astore_2
/*    */     //   1293: getfield Zs : Lf/Q90;
/*    */     //   1296: invokevirtual YC : ()Z
/*    */     //   1299: ifne -> 1313
/*    */     //   1302: aload_1
/*    */     //   1303: getfield Zs : Lf/Q90;
/*    */     //   1306: getfield od : B
/*    */     //   1309: invokestatic valueOf : (I)Ljava/lang/String;
/*    */     //   1312: astore_2
/*    */     //   1313: aload_1
/*    */     //   1314: getfield Zs : Lf/Q90;
/*    */     //   1317: invokevirtual xt : ()Z
/*    */     //   1320: ifeq -> 1337
/*    */     //   1323: aload_0
/*    */     //   1324: getfield Yk : Lf/dQ;
/*    */     //   1327: aload_1
/*    */     //   1328: invokevirtual m : ()Ljava/lang/String;
/*    */     //   1331: invokevirtual E1 : (Ljava/lang/String;)V
/*    */     //   1334: goto -> 1347
/*    */     //   1337: aload_0
/*    */     //   1338: getfield Yk : Lf/dQ;
/*    */     //   1341: ldc_w ' '
/*    */     //   1344: invokevirtual E1 : (Ljava/lang/String;)V
/*    */     //   1347: aload_1
/*    */     //   1348: aload_0
/*    */     //   1349: getfield Oj : Lf/dQ;
/*    */     //   1352: new java/lang/StringBuilder
/*    */     //   1355: dup
/*    */     //   1356: invokespecial <init> : ()V
/*    */     //   1359: sipush #1731
/*    */     //   1362: aload_2
/*    */     //   1363: invokestatic Go : (ILjava/lang/String;)Ljava/lang/String;
/*    */     //   1366: invokevirtual append : (Ljava/lang/String;)Ljava/lang/StringBuilder;
/*    */     //   1369: ldc_w ' '
/*    */     //   1372: invokevirtual append : (Ljava/lang/String;)Ljava/lang/StringBuilder;
/*    */     //   1375: aload_1
/*    */     //   1376: invokevirtual Hn : ()Ljava/lang/String;
/*    */     //   1379: invokevirtual append : (Ljava/lang/String;)Ljava/lang/StringBuilder;
/*    */     //   1382: invokevirtual toString : ()Ljava/lang/String;
/*    */     //   1385: invokevirtual E1 : (Ljava/lang/String;)V
/*    */     //   1388: invokevirtual s5 : ()B
/*    */     //   1391: iflt -> 1463
/*    */     //   1394: aload_1
/*    */     //   1395: getfield Zs : Lf/Q90;
/*    */     //   1398: invokevirtual YC : ()Z
/*    */     //   1401: ifne -> 1463
/*    */     //   1404: aload_0
/*    */     //   1405: dup
/*    */     //   1406: getfield ON : Lf/vF0;
/*    */     //   1409: getfield TS : Lf/rH;
/*    */     //   1412: iconst_1
/*    */     //   1413: anewarray f/pe0
/*    */     //   1416: dup
/*    */     //   1417: aload_1
/*    */     //   1418: invokestatic ZZ : ()Lf/interface;
/*    */     //   1421: astore_2
/*    */     //   1422: invokevirtual s5 : ()B
/*    */     //   1425: aload_2
/*    */     //   1426: getfield ar0 : [Lf/pe0;
/*    */     //   1429: swap
/*    */     //   1430: aaload
/*    */     //   1431: iconst_0
/*    */     //   1432: swap
/*    */     //   1433: aastore
/*    */     //   1434: invokevirtual Pn : ([Lf/pe0;)Lf/JG0;
/*    */     //   1437: pop
/*    */     //   1438: getfield ON : Lf/vF0;
/*    */     //   1441: dup
/*    */     //   1442: dup
/*    */     //   1443: astore_2
/*    */     //   1444: getfield TS : Lf/rH;
/*    */     //   1447: invokevirtual e00 : ()I
/*    */     //   1450: aload_2
/*    */     //   1451: getfield TS : Lf/rH;
/*    */     //   1454: invokevirtual cA : ()I
/*    */     //   1457: invokevirtual Cu0 : (II)V
/*    */     //   1460: goto -> 1473
/*    */     //   1463: aload_0
/*    */     //   1464: getfield ON : Lf/vF0;
/*    */     //   1467: getfield TS : Lf/rH;
/*    */     //   1470: invokevirtual H : ()V
/*    */     //   1473: aload_1
/*    */     //   1474: aload_0
/*    */     //   1475: getfield J70 : Lf/dQ;
/*    */     //   1478: new java/lang/StringBuilder
/*    */     //   1481: dup
/*    */     //   1482: astore_2
/*    */     //   1483: invokespecial <init> : ()V
/*    */     //   1486: sipush #2319
/*    */     //   1489: aload_2
/*    */     //   1490: ldc_w ' '
/*    */     //   1493: invokestatic X9 : (ILjava/lang/StringBuilder;Ljava/lang/String;)Ljava/lang/StringBuilder;
/*    */     //   1496: aload_1
/*    */     //   1497: getfield Zs : Lf/Q90;
/*    */     //   1500: getfield Tl0 : S
/*    */     //   1503: invokevirtual append : (I)Ljava/lang/StringBuilder;
/*    */     //   1506: ldc_w ' ('
/*    */     //   1509: invokevirtual append : (Ljava/lang/String;)Ljava/lang/StringBuilder;
/*    */     //   1512: aload_0
/*    */     //   1513: getfield VK0 : Lf/dQ;
/*    */     //   1516: getfield wL : Ljava/lang/CharSequence;
/*    */     //   1519: invokeinterface toString : ()Ljava/lang/String;
/*    */     //   1524: invokevirtual append : (Ljava/lang/String;)Ljava/lang/StringBuilder;
/*    */     //   1527: ldc_w ')'
/*    */     //   1530: invokevirtual append : (Ljava/lang/String;)Ljava/lang/StringBuilder;
/*    */     //   1533: invokevirtual toString : ()Ljava/lang/String;
/*    */     //   1536: invokevirtual E1 : (Ljava/lang/String;)V
/*    */     //   1539: getfield Zs : Lf/Q90;
/*    */     //   1542: invokevirtual YC : ()Z
/*    */     //   1545: ifne -> 1976
/*    */     //   1548: aload_0
/*    */     //   1549: dup
/*    */     //   1550: dup2
/*    */     //   1551: getfield XI0 : Lf/dQ;
/*    */     //   1554: new java/lang/StringBuilder
/*    */     //   1557: dup
/*    */     //   1558: aload_1
/*    */     //   1559: swap
/*    */     //   1560: invokespecial <init> : ()V
/*    */     //   1563: getfield Fq0 : Lf/Sf;
/*    */     //   1566: getstatic f/hR.Gg : Lf/hR;
/*    */     //   1569: dup
/*    */     //   1570: astore_2
/*    */     //   1571: invokevirtual Mm : (Lf/hR;)S
/*    */     //   1574: invokevirtual append : (I)Ljava/lang/StringBuilder;
/*    */     //   1577: ldc_w '/'
/*    */     //   1580: invokevirtual append : (Ljava/lang/String;)Ljava/lang/StringBuilder;
/*    */     //   1583: aload_1
/*    */     //   1584: getfield Fq0 : Lf/Sf;
/*    */     //   1587: getstatic f/hR.zh : Lf/hR;
/*    */     //   1590: dup
/*    */     //   1591: astore_3
/*    */     //   1592: invokevirtual Mm : (Lf/hR;)S
/*    */     //   1595: invokevirtual append : (I)Ljava/lang/StringBuilder;
/*    */     //   1598: ldc_w '/'
/*    */     //   1601: invokevirtual append : (Ljava/lang/String;)Ljava/lang/StringBuilder;
/*    */     //   1604: aload_1
/*    */     //   1605: getfield Fq0 : Lf/Sf;
/*    */     //   1608: getstatic f/hR.kq : Lf/hR;
/*    */     //   1611: dup
/*    */     //   1612: astore #4
/*    */     //   1614: invokevirtual Mm : (Lf/hR;)S
/*    */     //   1617: invokevirtual append : (I)Ljava/lang/StringBuilder;
/*    */     //   1620: ldc_w '/'
/*    */     //   1623: invokevirtual append : (Ljava/lang/String;)Ljava/lang/StringBuilder;
/*    */     //   1626: aload_1
/*    */     //   1627: getfield Fq0 : Lf/Sf;
/*    */     //   1630: getstatic f/hR.Xx : Lf/hR;
/*    */     //   1633: dup
/*    */     //   1634: astore #5
/*    */     //   1636: invokevirtual Mm : (Lf/hR;)S
/*    */     //   1639: invokevirtual append : (I)Ljava/lang/StringBuilder;
/*    */     //   1642: ldc_w '/'
/*    */     //   1645: invokevirtual append : (Ljava/lang/String;)Ljava/lang/StringBuilder;
/*    */     //   1648: aload_1
/*    */     //   1649: getfield Fq0 : Lf/Sf;
/*    */     //   1652: getstatic f/hR.PE0 : Lf/hR;
/*    */     //   1655: dup
/*    */     //   1656: astore #6
/*    */     //   1658: invokevirtual Mm : (Lf/hR;)S
/*    */     //   1661: invokevirtual append : (I)Ljava/lang/StringBuilder;
/*    */     //   1664: ldc_w '/'
/*    */     //   1667: invokevirtual append : (Ljava/lang/String;)Ljava/lang/StringBuilder;
/*    */     //   1670: aload_1
/*    */     //   1671: getfield Fq0 : Lf/Sf;
/*    */     //   1674: getstatic f/hR.s5 : Lf/hR;
/*    */     //   1677: dup
/*    */     //   1678: astore #7
/*    */     //   1680: invokevirtual Mm : (Lf/hR;)S
/*    */     //   1683: invokevirtual append : (I)Ljava/lang/StringBuilder;
/*    */     //   1686: invokevirtual toString : ()Ljava/lang/String;
/*    */     //   1689: invokevirtual E1 : (Ljava/lang/String;)V
/*    */     //   1692: getfield Yr : Lf/dQ;
/*    */     //   1695: new java/lang/StringBuilder
/*    */     //   1698: dup
/*    */     //   1699: aload_1
/*    */     //   1700: swap
/*    */     //   1701: invokespecial <init> : ()V
/*    */     //   1704: getfield Zs : Lf/Q90;
/*    */     //   1707: aload_2
/*    */     //   1708: invokevirtual Hc : (Lf/hR;)B
/*    */     //   1711: invokevirtual append : (I)Ljava/lang/StringBuilder;
/*    */     //   1714: ldc_w '/'
/*    */     //   1717: invokevirtual append : (Ljava/lang/String;)Ljava/lang/StringBuilder;
/*    */     //   1720: aload_1
/*    */     //   1721: getfield Zs : Lf/Q90;
/*    */     //   1724: aload_3
/*    */     //   1725: invokevirtual Hc : (Lf/hR;)B
/*    */     //   1728: invokevirtual append : (I)Ljava/lang/StringBuilder;
/*    */     //   1731: ldc_w '/'
/*    */     //   1734: invokevirtual append : (Ljava/lang/String;)Ljava/lang/StringBuilder;
/*    */     //   1737: aload_1
/*    */     //   1738: getfield Zs : Lf/Q90;
/*    */     //   1741: aload #4
/*    */     //   1743: invokevirtual Hc : (Lf/hR;)B
/*    */     //   1746: invokevirtual append : (I)Ljava/lang/StringBuilder;
/*    */     //   1749: ldc_w '/'
/*    */     //   1752: invokevirtual append : (Ljava/lang/String;)Ljava/lang/StringBuilder;
/*    */     //   1755: aload_1
/*    */     //   1756: getfield Zs : Lf/Q90;
/*    */     //   1759: aload #5
/*    */     //   1761: invokevirtual Hc : (Lf/hR;)B
/*    */     //   1764: invokevirtual append : (I)Ljava/lang/StringBuilder;
/*    */     //   1767: ldc_w '/'
/*    */     //   1770: invokevirtual append : (Ljava/lang/String;)Ljava/lang/StringBuilder;
/*    */     //   1773: aload_1
/*    */     //   1774: getfield Zs : Lf/Q90;
/*    */     //   1777: aload #6
/*    */     //   1779: invokevirtual Hc : (Lf/hR;)B
/*    */     //   1782: invokevirtual append : (I)Ljava/lang/StringBuilder;
/*    */     //   1785: ldc_w '/'
/*    */     //   1788: invokevirtual append : (Ljava/lang/String;)Ljava/lang/StringBuilder;
/*    */     //   1791: aload_1
/*    */     //   1792: getfield Zs : Lf/Q90;
/*    */     //   1795: aload #7
/*    */     //   1797: invokevirtual Hc : (Lf/hR;)B
/*    */     //   1800: invokevirtual append : (I)Ljava/lang/StringBuilder;
/*    */     //   1803: invokevirtual toString : ()Ljava/lang/String;
/*    */     //   1806: getstatic f/rG0.J2 : Ljava/text/DecimalFormat;
/*    */     //   1809: pop
/*    */     //   1810: ldc_w '31'
/*    */     //   1813: ldc_w '[#6fb76f]31[]'
/*    */     //   1816: invokevirtual replace : (Ljava/lang/CharSequence;Ljava/lang/CharSequence;)Ljava/lang/String;
/*    */     //   1819: ldc_w '([^0-9])0'
/*    */     //   1822: ldc_w '$1[#ff6666]0[]'
/*    */     //   1825: invokevirtual replaceAll : (Ljava/lang/String;Ljava/lang/String;)Ljava/lang/String;
/*    */     //   1828: ldc_w '^0/'
/*    */     //   1831: ldc_w '[#ff6666]0[]/'
/*    */     //   1834: invokevirtual replaceAll : (Ljava/lang/String;Ljava/lang/String;)Ljava/lang/String;
/*    */     //   1837: invokevirtual E1 : (Ljava/lang/String;)V
/*    */     //   1840: getfield YL : Lf/dQ;
/*    */     //   1843: new java/lang/StringBuilder
/*    */     //   1846: dup
/*    */     //   1847: aload_1
/*    */     //   1848: swap
/*    */     //   1849: invokespecial <init> : ()V
/*    */     //   1852: getfield Zs : Lf/Q90;
/*    */     //   1855: aload_2
/*    */     //   1856: invokevirtual Uu0 : (Lf/hR;)S
/*    */     //   1859: invokevirtual append : (I)Ljava/lang/StringBuilder;
/*    */     //   1862: ldc_w '/'
/*    */     //   1865: invokevirtual append : (Ljava/lang/String;)Ljava/lang/StringBuilder;
/*    */     //   1868: aload_1
/*    */     //   1869: getfield Zs : Lf/Q90;
/*    */     //   1872: aload_3
/*    */     //   1873: invokevirtual Uu0 : (Lf/hR;)S
/*    */     //   1876: invokevirtual append : (I)Ljava/lang/StringBuilder;
/*    */     //   1879: ldc_w '/'
/*    */     //   1882: invokevirtual append : (Ljava/lang/String;)Ljava/lang/StringBuilder;
/*    */     //   1885: aload_1
/*    */     //   1886: getfield Zs : Lf/Q90;
/*    */     //   1889: aload #4
/*    */     //   1891: invokevirtual Uu0 : (Lf/hR;)S
/*    */     //   1894: invokevirtual append : (I)Ljava/lang/StringBuilder;
/*    */     //   1897: ldc_w '/'
/*    */     //   1900: invokevirtual append : (Ljava/lang/String;)Ljava/lang/StringBuilder;
/*    */     //   1903: aload_1
/*    */     //   1904: getfield Zs : Lf/Q90;
/*    */     //   1907: aload #5
/*    */     //   1909: invokevirtual Uu0 : (Lf/hR;)S
/*    */     //   1912: invokevirtual append : (I)Ljava/lang/StringBuilder;
/*    */     //   1915: ldc_w '/'
/*    */     //   1918: invokevirtual append : (Ljava/lang/String;)Ljava/lang/StringBuilder;
/*    */     //   1921: aload_1
/*    */     //   1922: getfield Zs : Lf/Q90;
/*    */     //   1925: aload #6
/*    */     //   1927: invokevirtual Uu0 : (Lf/hR;)S
/*    */     //   1930: invokevirtual append : (I)Ljava/lang/StringBuilder;
/*    */     //   1933: ldc_w '/'
/*    */     //   1936: invokevirtual append : (Ljava/lang/String;)Ljava/lang/StringBuilder;
/*    */     //   1939: aload_1
/*    */     //   1940: getfield Zs : Lf/Q90;
/*    */     //   1943: aload #7
/*    */     //   1945: invokevirtual Uu0 : (Lf/hR;)S
/*    */     //   1948: invokevirtual append : (I)Ljava/lang/StringBuilder;
/*    */     //   1951: invokevirtual toString : ()Ljava/lang/String;
/*    */     //   1954: invokevirtual E1 : (Ljava/lang/String;)V
/*    */     //   1957: getfield Dp : Lf/dQ;
/*    */     //   1960: aload_1
/*    */     //   1961: getfield Zs : Lf/Q90;
/*    */     //   1964: getfield k0 : Lf/nV;
/*    */     //   1967: invokevirtual cK0 : ()Ljava/lang/String;
/*    */     //   1970: invokevirtual E1 : (Ljava/lang/String;)V
/*    */     //   1973: goto -> 2015
/*    */     //   1976: aload_0
/*    */     //   1977: dup
/*    */     //   1978: dup2
/*    */     //   1979: getfield XI0 : Lf/dQ;
/*    */     //   1982: ldc_w '???'
/*    */     //   1985: invokevirtual E1 : (Ljava/lang/String;)V
/*    */     //   1988: getfield Yr : Lf/dQ;
/*    */     //   1991: ldc_w '???'
/*    */     //   1994: invokevirtual E1 : (Ljava/lang/String;)V
/*    */     //   1997: getfield YL : Lf/dQ;
/*    */     //   2000: ldc_w '???'
/*    */     //   2003: invokevirtual E1 : (Ljava/lang/String;)V
/*    */     //   2006: getfield Dp : Lf/dQ;
/*    */     //   2009: ldc_w '???'
/*    */     //   2012: invokevirtual E1 : (Ljava/lang/String;)V
/*    */     //   2015: aload_1
/*    */     //   2016: aload_0
/*    */     //   2017: getstatic f/Of.eH : Lf/Of;
/*    */     //   2020: aload_1
/*    */     //   2021: getfield Zs : Lf/Q90;
/*    */     //   2024: invokevirtual p10 : ()S
/*    */     //   2027: invokevirtual On0 : (S)Lf/LPT3;
/*    */     //   2030: astore_2
/*    */     //   2031: getfield Dp : Lf/dQ;
/*    */     //   2034: iconst_0
/*    */     //   2035: putfield jl : I
/*    */     //   2038: getfield Zs : Lf/Q90;
/*    */     //   2041: invokevirtual YC : ()Z
/*    */     //   2044: ifeq -> 2062
/*    */     //   2047: aload_0
/*    */     //   2048: getfield Dp : Lf/dQ;
/*    */     //   2051: dup
/*    */     //   2052: aconst_null
/*    */     //   2053: putfield z4 : Ljava/lang/Object;
/*    */     //   2056: invokevirtual zn : ()V
/*    */     //   2059: goto -> 2114
/*    */     //   2062: aload_1
/*    */     //   2063: getfield Zs : Lf/Q90;
/*    */     //   2066: getfield k0 : Lf/nV;
/*    */     //   2069: dup
/*    */     //   2070: astore_3
/*    */     //   2071: getfield Qc0 : Lf/hR;
/*    */     //   2074: ifnonnull -> 2093
/*    */     //   2077: aload_0
/*    */     //   2078: getfield Dp : Lf/dQ;
/*    */     //   2081: astore_3
/*    */     //   2082: sipush #1806
/*    */     //   2085: invokestatic OH0 : (I)Ljava/lang/String;
/*    */     //   2088: astore #4
/*    */     //   2090: goto -> 2104
/*    */     //   2093: aload_3
/*    */     //   2094: aload_0
/*    */     //   2095: getfield Dp : Lf/dQ;
/*    */     //   2098: astore_3
/*    */     //   2099: invokestatic Em0 : (Lf/nV;)Ljava/lang/String;
/*    */     //   2102: astore #4
/*    */     //   2104: aload_3
/*    */     //   2105: dup
/*    */     //   2106: aload #4
/*    */     //   2108: putfield z4 : Ljava/lang/Object;
/*    */     //   2111: invokevirtual zn : ()V
/*    */     //   2114: aload_1
/*    */     //   2115: getfield Zs : Lf/Q90;
/*    */     //   2118: invokevirtual p10 : ()S
/*    */     //   2121: ifle -> 2188
/*    */     //   2124: aload_0
/*    */     //   2125: dup
/*    */     //   2126: dup
/*    */     //   2127: getfield Fq : Lf/vF0;
/*    */     //   2130: getfield TS : Lf/rH;
/*    */     //   2133: iconst_1
/*    */     //   2134: anewarray f/U70
/*    */     //   2137: dup
/*    */     //   2138: getstatic f/wm0.y0 : Lf/wm0;
/*    */     //   2141: aload_1
/*    */     //   2142: getfield Zs : Lf/Q90;
/*    */     //   2145: invokevirtual p10 : ()S
/*    */     //   2148: iconst_0
/*    */     //   2149: invokevirtual SJ0 : (SZ)Lf/U70;
/*    */     //   2152: iconst_0
/*    */     //   2153: swap
/*    */     //   2154: aastore
/*    */     //   2155: invokevirtual qt : ([Lf/U70;)Lf/JG0;
/*    */     //   2158: pop
/*    */     //   2159: getfield Fq : Lf/vF0;
/*    */     //   2162: getfield TS : Lf/rH;
/*    */     //   2165: bipush #24
/*    */     //   2167: bipush #24
/*    */     //   2169: invokevirtual tL : (II)V
/*    */     //   2172: getfield eF0 : Lf/dQ;
/*    */     //   2175: aload_2
/*    */     //   2176: getfield Iu : I
/*    */     //   2179: invokestatic OH0 : (I)Ljava/lang/String;
/*    */     //   2182: invokevirtual E1 : (Ljava/lang/String;)V
/*    */     //   2185: goto -> 2210
/*    */     //   2188: aload_0
/*    */     //   2189: dup
/*    */     //   2190: getfield Fq : Lf/vF0;
/*    */     //   2193: getfield TS : Lf/rH;
/*    */     //   2196: invokevirtual H : ()V
/*    */     //   2199: getfield eF0 : Lf/dQ;
/*    */     //   2202: bipush #61
/*    */     //   2204: invokestatic OH0 : (I)Ljava/lang/String;
/*    */     //   2207: invokevirtual E1 : (Ljava/lang/String;)V
/*    */     //   2210: iconst_0
/*    */     //   2211: istore_2
/*    */     //   2212: iload_2
/*    */     //   2213: iconst_4
/*    */     //   2214: if_icmpge -> 2390
/*    */     //   2217: invokestatic cw : ()Lf/yk0;
/*    */     //   2220: aload_1
/*    */     //   2221: getfield Zs : Lf/Q90;
/*    */     //   2224: getfield En0 : [S
/*    */     //   2227: iload_2
/*    */     //   2228: saload
/*    */     //   2229: invokevirtual mP : (S)Lf/WD;
/*    */     //   2232: dup
/*    */     //   2233: astore_3
/*    */     //   2234: ifnull -> 2360
/*    */     //   2237: aload_3
/*    */     //   2238: getfield HA : S
/*    */     //   2241: ifle -> 2360
/*    */     //   2244: aload_0
/*    */     //   2245: dup
/*    */     //   2246: dup2
/*    */     //   2247: getfield Vj : [Lf/vF0;
/*    */     //   2250: iload_2
/*    */     //   2251: aaload
/*    */     //   2252: getfield TS : Lf/rH;
/*    */     //   2255: iconst_1
/*    */     //   2256: anewarray f/pe0
/*    */     //   2259: dup
/*    */     //   2260: invokestatic ZZ : ()Lf/interface;
/*    */     //   2263: aload_3
/*    */     //   2264: aload_1
/*    */     //   2265: getfield Zs : Lf/Q90;
/*    */     //   2268: aconst_null
/*    */     //   2269: invokevirtual Wt : (Lf/Q90;Lf/Mx;)Lf/Ht0;
/*    */     //   2272: getfield zm0 : B
/*    */     //   2275: invokevirtual xk0 : (I)Lf/pe0;
/*    */     //   2278: iconst_0
/*    */     //   2279: swap
/*    */     //   2280: aastore
/*    */     //   2281: invokevirtual Pn : ([Lf/pe0;)Lf/JG0;
/*    */     //   2284: pop
/*    */     //   2285: getfield Vj : [Lf/vF0;
/*    */     //   2288: iload_2
/*    */     //   2289: aaload
/*    */     //   2290: dup
/*    */     //   2291: dup
/*    */     //   2292: astore #4
/*    */     //   2294: getfield TS : Lf/rH;
/*    */     //   2297: invokevirtual e00 : ()I
/*    */     //   2300: aload #4
/*    */     //   2302: getfield TS : Lf/rH;
/*    */     //   2305: invokevirtual cA : ()I
/*    */     //   2308: invokevirtual Cu0 : (II)V
/*    */     //   2311: getfield e0 : [Lf/dQ;
/*    */     //   2314: iload_2
/*    */     //   2315: aaload
/*    */     //   2316: aload_3
/*    */     //   2317: getfield iz : I
/*    */     //   2320: invokestatic OH0 : (I)Ljava/lang/String;
/*    */     //   2323: invokevirtual E1 : (Ljava/lang/String;)V
/*    */     //   2326: getfield e0 : [Lf/dQ;
/*    */     //   2329: iload_2
/*    */     //   2330: aaload
/*    */     //   2331: sipush #200
/*    */     //   2334: putfield jl : I
/*    */     //   2337: invokestatic Nr : ()Z
/*    */     //   2340: ifeq -> 2384
/*    */     //   2343: aload_0
/*    */     //   2344: getfield e0 : [Lf/dQ;
/*    */     //   2347: iload_2
/*    */     //   2348: aaload
/*    */     //   2349: aload_3
/*    */     //   2350: aload_1
/*    */     //   2351: invokestatic Ii0 : (Lf/WD;Lf/j40;)Lf/Ip;
/*    */     //   2354: invokevirtual Gq0 : (Ljava/lang/Object;)V
/*    */     //   2357: goto -> 2384
/*    */     //   2360: aload_0
/*    */     //   2361: dup
/*    */     //   2362: getfield Vj : [Lf/vF0;
/*    */     //   2365: iload_2
/*    */     //   2366: aaload
/*    */     //   2367: getfield TS : Lf/rH;
/*    */     //   2370: invokevirtual H : ()V
/*    */     //   2373: getfield e0 : [Lf/dQ;
/*    */     //   2376: iload_2
/*    */     //   2377: aaload
/*    */     //   2378: ldc_w ' '
/*    */     //   2381: invokevirtual E1 : (Ljava/lang/String;)V
/*    */     //   2384: iinc #2, 1
/*    */     //   2387: goto -> 2212
/*    */     //   2390: aload_1
/*    */     //   2391: getfield Zs : Lf/Q90;
/*    */     //   2394: getfield cC : B
/*    */     //   2397: iconst_2
/*    */     //   2398: if_icmpne -> 2424
/*    */     //   2401: aload_0
/*    */     //   2402: getfield ER : Lf/dQ;
/*    */     //   2405: astore_2
/*    */     //   2406: ldc_w 'label-hidden-ability'
/*    */     //   2409: dup
/*    */     //   2410: astore_3
/*    */     //   2411: aload_2
/*    */     //   2412: getfield cl : Ljava/lang/String;
/*    */     //   2415: invokevirtual equals : (Ljava/lang/Object;)Z
/*    */     //   2418: ifeq -> 2447
/*    */     //   2421: goto -> 2456
/*    */     //   2424: aload_0
/*    */     //   2425: getfield ER : Lf/dQ;
/*    */     //   2428: astore_2
/*    */     //   2429: ldc_w 'label'
/*    */     //   2432: dup
/*    */     //   2433: astore_3
/*    */     //   2434: aload_2
/*    */     //   2435: getfield cl : Ljava/lang/String;
/*    */     //   2438: invokevirtual equals : (Ljava/lang/Object;)Z
/*    */     //   2441: ifeq -> 2447
/*    */     //   2444: goto -> 2456
/*    */     //   2447: aload_2
/*    */     //   2448: dup
/*    */     //   2449: aload_3
/*    */     //   2450: invokevirtual Xu : (Ljava/lang/String;)V
/*    */     //   2453: invokevirtual cZ : ()V
/*    */     //   2456: aload_1
/*    */     //   2457: getfield Zs : Lf/Q90;
/*    */     //   2460: invokevirtual YC : ()Z
/*    */     //   2463: ifeq -> 2479
/*    */     //   2466: aload_0
/*    */     //   2467: getfield ER : Lf/dQ;
/*    */     //   2470: ldc_w '???'
/*    */     //   2473: invokevirtual E1 : (Ljava/lang/String;)V
/*    */     //   2476: goto -> 2497
/*    */     //   2479: aload_0
/*    */     //   2480: getfield ER : Lf/dQ;
/*    */     //   2483: aload_1
/*    */     //   2484: invokevirtual rX : ()S
/*    */     //   2487: ldc_w 210000
/*    */     //   2490: iadd
/*    */     //   2491: invokestatic OH0 : (I)Ljava/lang/String;
/*    */     //   2494: invokevirtual E1 : (Ljava/lang/String;)V
/*    */     //   2497: aload_1
/*    */     //   2498: getfield Zs : Lf/Q90;
/*    */     //   2501: invokevirtual iL : ()Z
/*    */     //   2504: ifeq -> 2558
/*    */     //   2507: aload_0
/*    */     //   2508: dup
/*    */     //   2509: getfield YI : Lf/vF0;
/*    */     //   2512: getfield TS : Lf/rH;
/*    */     //   2515: iconst_1
/*    */     //   2516: anewarray f/pe0
/*    */     //   2519: dup
/*    */     //   2520: invokestatic ZZ : ()Lf/interface;
/*    */     //   2523: getfield n30 : Lf/pe0;
/*    */     //   2526: iconst_0
/*    */     //   2527: swap
/*    */     //   2528: aastore
/*    */     //   2529: invokevirtual Pn : ([Lf/pe0;)Lf/JG0;
/*    */     //   2532: pop
/*    */     //   2533: getfield YI : Lf/vF0;
/*    */     //   2536: dup
/*    */     //   2537: dup
/*    */     //   2538: astore_2
/*    */     //   2539: getfield TS : Lf/rH;
/*    */     //   2542: invokevirtual e00 : ()I
/*    */     //   2545: aload_2
/*    */     //   2546: getfield TS : Lf/rH;
/*    */     //   2549: invokevirtual cA : ()I
/*    */     //   2552: invokevirtual Cu0 : (II)V
/*    */     //   2555: goto -> 2568
/*    */     //   2558: aload_0
/*    */     //   2559: getfield YI : Lf/vF0;
/*    */     //   2562: getfield TS : Lf/rH;
/*    */     //   2565: invokevirtual H : ()V
/*    */     //   2568: aload_0
/*    */     //   2569: dup
/*    */     //   2570: getfield Es0 : Lf/dQ;
/*    */     //   2573: aload_1
/*    */     //   2574: invokevirtual rX : ()S
/*    */     //   2577: ldc_w 220000
/*    */     //   2580: iadd
/*    */     //   2581: invokestatic OH0 : (I)Ljava/lang/String;
/*    */     //   2584: invokevirtual E1 : (Ljava/lang/String;)V
/*    */     //   2587: getfield ER : Lf/dQ;
/*    */     //   2590: dup
/*    */     //   2591: dup
/*    */     //   2592: aload_0
/*    */     //   2593: swap
/*    */     //   2594: iconst_0
/*    */     //   2595: putfield jl : I
/*    */     //   2598: getfield Es0 : Lf/dQ;
/*    */     //   2601: putfield z4 : Ljava/lang/Object;
/*    */     //   2604: invokevirtual zn : ()V
/*    */     //   2607: invokestatic XU : ()Z
/*    */     //   2610: ifeq -> 2767
/*    */     //   2613: aload_0
/*    */     //   2614: getfield Ve : Lf/YA0;
/*    */     //   2617: getfield Bo0 : Lf/throws;
/*    */     //   2620: ifnonnull -> 2656
/*    */     //   2623: getstatic f/km.wI0 : Lf/Pw;
/*    */     //   2626: getfield pY : Lf/Y00;
/*    */     //   2629: dup
/*    */     //   2630: astore_2
/*    */     //   2631: ifnull -> 2644
/*    */     //   2634: aload_2
/*    */     //   2635: getfield E80 : Lf/wl0;
/*    */     //   2638: getfield rS : I
/*    */     //   2641: goto -> 2650
/*    */     //   2644: getstatic f/UB0.M60 : Lf/w70;
/*    */     //   2647: invokevirtual fG0 : ()I
/*    */     //   2650: sipush #1300
/*    */     //   2653: if_icmpgt -> 2767
/*    */     //   2656: aload_0
/*    */     //   2657: getfield Ve : Lf/YA0;
/*    */     //   2660: getfield xY : I
/*    */     //   2663: sipush #300
/*    */     //   2666: if_icmpgt -> 2767
/*    */     //   2669: aload_1
/*    */     //   2670: iconst_0
/*    */     //   2671: istore_1
/*    */     //   2672: getfield Fq0 : Lf/Sf;
/*    */     //   2675: astore_2
/*    */     //   2676: getstatic f/hR.ka : [Lf/hR;
/*    */     //   2679: dup
/*    */     //   2680: astore_3
/*    */     //   2681: arraylength
/*    */     //   2682: istore #4
/*    */     //   2684: iconst_0
/*    */     //   2685: istore #5
/*    */     //   2687: iload #5
/*    */     //   2689: iload #4
/*    */     //   2691: if_icmpge -> 2716
/*    */     //   2694: aload_2
/*    */     //   2695: aload_3
/*    */     //   2696: iload #5
/*    */     //   2698: aaload
/*    */     //   2699: invokevirtual Mm : (Lf/hR;)S
/*    */     //   2702: bipush #100
/*    */     //   2704: if_icmplt -> 2710
/*    */     //   2707: iinc #1, 1
/*    */     //   2710: iinc #5, 1
/*    */     //   2713: goto -> 2687
/*    */     //   2716: iload_1
/*    */     //   2717: iconst_5
/*    */     //   2718: if_icmplt -> 2744
/*    */     //   2721: aload_0
/*    */     //   2722: getfield XI0 : Lf/dQ;
/*    */     //   2725: astore_1
/*    */     //   2726: ldc_w 'label-stats-small'
/*    */     //   2729: dup
/*    */     //   2730: astore_2
/*    */     //   2731: aload_1
/*    */     //   2732: getfield cl : Ljava/lang/String;
/*    */     //   2735: invokevirtual equals : (Ljava/lang/Object;)Z
/*    */     //   2738: ifeq -> 2790
/*    */     //   2741: goto -> 2799
/*    */     //   2744: aload_0
/*    */     //   2745: getfield XI0 : Lf/dQ;
/*    */     //   2748: astore_1
/*    */     //   2749: ldc_w 'label'
/*    */     //   2752: dup
/*    */     //   2753: astore_2
/*    */     //   2754: aload_1
/*    */     //   2755: getfield cl : Ljava/lang/String;
/*    */     //   2758: invokevirtual equals : (Ljava/lang/Object;)Z
/*    */     //   2761: ifeq -> 2790
/*    */     //   2764: goto -> 2799
/*    */     //   2767: aload_0
/*    */     //   2768: getfield XI0 : Lf/dQ;
/*    */     //   2771: astore_1
/*    */     //   2772: ldc_w 'label'
/*    */     //   2775: dup
/*    */     //   2776: astore_2
/*    */     //   2777: aload_1
/*    */     //   2778: getfield cl : Ljava/lang/String;
/*    */     //   2781: invokevirtual equals : (Ljava/lang/Object;)Z
/*    */     //   2784: ifeq -> 2790
/*    */     //   2787: goto -> 2799
/*    */     //   2790: aload_1
/*    */     //   2791: dup
/*    */     //   2792: aload_2
/*    */     //   2793: invokevirtual Xu : (Ljava/lang/String;)V
/*    */     //   2796: invokevirtual cZ : ()V
/*    */     //   2799: aload_0
/*    */     //   2800: invokevirtual MJ0 : ()V
/*    */     //   2803: return
/*    */     // Line number table:
/*    */     //   Java source line number -> byte code offset
/*    */     //   #1	-> 48
/*    */     //   #2	-> 51
/*    */     //   #3	-> 73
/*    */     //   #4	-> 76
/*    */     //   #5	-> 82
/*    */     //   #6	-> 85
/*    */     //   #7	-> 91
/*    */     //   #8	-> 94
/*    */     //   #9	-> 100
/*    */     //   #10	-> 103
/*    */     //   #11	-> 109
/*    */     //   #12	-> 112
/*    */     //   #13	-> 118
/*    */     //   #14	-> 121
/*    */     //   #15	-> 181
/*    */     //   #16	-> 184
/*    */     //   #17	-> 201
/*    */     //   #18	-> 204
/*    */     //   #19	-> 239
/*    */     //   #20	-> 242
/*    */     //   #21	-> 271
/*    */     //   #22	-> 274
/*    */     //   #23	-> 278
/*    */     //   #24	-> 282
/*    */     //   #25	-> 285
/*    */     //   #26	-> 289
/*    */     //   #27	-> 293
/*    */     //   #28	-> 318
/*    */     //   #29	-> 323
/*    */     //   #30	-> 326
/*    */     //   #31	-> 337
/*    */     //   #32	-> 340
/*    */     //   #33	-> 352
/*    */     //   #34	-> 355
/*    */     //   #35	-> 358
/*    */     //   #36	-> 365
/*    */     //   #37	-> 368
/*    */     //   #38	-> 378
/*    */     //   #39	-> 388
/*    */     //   #40	-> 391
/*    */     //   #41	-> 403
/*    */     //   #42	-> 409
/*    */     //   #43	-> 422
/*    */     //   #44	-> 425
/*    */     //   #45	-> 430
/*    */     //   #46	-> 433
/*    */     //   #47	-> 444
/*    */     //   #48	-> 447
/*    */     //   #49	-> 460
/*    */     //   #50	-> 465
/*    */     //   #51	-> 468
/*    */     //   #52	-> 479
/*    */     //   #53	-> 482
/*    */     //   #54	-> 493
/*    */     //   #55	-> 498
/*    */     //   #56	-> 501
/*    */     //   #57	-> 512
/*    */     //   #58	-> 515
/*    */     //   #59	-> 525
/*    */     //   #60	-> 530
/*    */     //   #61	-> 533
/*    */     //   #62	-> 544
/*    */     //   #63	-> 547
/*    */     //   #64	-> 558
/*    */     //   #65	-> 563
/*    */     //   #66	-> 566
/*    */     //   #67	-> 577
/*    */     //   #68	-> 580
/*    */     //   #69	-> 635
/*    */     //   #70	-> 642
/*    */     //   #71	-> 671
/*    */     //   #72	-> 695
/*    */     //   #73	-> 704
/*    */     //   #74	-> 751
/*    */     //   #75	-> 756
/*    */     //   #76	-> 780
/*    */     //   #77	-> 790
/*    */     //   #78	-> 795
/*    */     //   #79	-> 799
/*    */     //   #80	-> 809
/*    */     //   #81	-> 812
/*    */     //   #82	-> 815
/*    */     //   #83	-> 822
/*    */     //   #84	-> 825
/*    */     //   #85	-> 829
/*    */     //   #86	-> 837
/*    */     //   #87	-> 841
/*    */     //   #88	-> 844
/*    */     //   #89	-> 848
/*    */     //   #90	-> 870
/*    */     //   #91	-> 873
/*    */     //   #92	-> 880
/*    */     //   #93	-> 884
/*    */     //   #94	-> 887
/*    */     //   #95	-> 895
/*    */     //   #96	-> 898
/*    */     //   #97	-> 902
/*    */     //   #98	-> 913
/*    */     //   #99	-> 916
/*    */     //   #100	-> 929
/*    */     //   #101	-> 933
/*    */     //   #102	-> 944
/*    */     //   #103	-> 947
/*    */     //   #104	-> 965
/*    */     //   #105	-> 969
/*    */     //   #106	-> 980
/*    */     //   #107	-> 983
/*    */     //   #108	-> 996
/*    */     //   #109	-> 999
/*    */     //   #110	-> 1003
/*    */     //   #111	-> 1013
/*    */     //   #112	-> 1016
/*    */     //   #113	-> 1020
/*    */     //   #114	-> 1028
/*    */     //   #115	-> 1031
/*    */     //   #116	-> 1051
/*    */     //   #117	-> 1054
/*    */     //   #118	-> 1058
/*    */     //   #119	-> 1068
/*    */     //   #120	-> 1071
/*    */     //   #121	-> 1075
/*    */     //   #122	-> 1082
/*    */     //   #123	-> 1087
/*    */     //   #124	-> 1109
/*    */     //   #125	-> 1112
/*    */     //   #126	-> 1118
/*    */     //   #127	-> 1121
/*    */     //   #128	-> 1127
/*    */     //   #129	-> 1130
/*    */     //   #130	-> 1136
/*    */     //   #131	-> 1139
/*    */     //   #132	-> 1145
/*    */     //   #133	-> 1148
/*    */     //   #134	-> 1257
/*    */     //   #135	-> 1264
/*    */     //   #136	-> 1267
/*    */     //   #137	-> 1289
/*    */     //   #138	-> 1293
/*    */     //   #139	-> 1296
/*    */     //   #140	-> 1303
/*    */     //   #141	-> 1306
/*    */     //   #142	-> 1309
/*    */     //   #143	-> 1314
/*    */     //   #144	-> 1317
/*    */     //   #145	-> 1395
/*    */     //   #146	-> 1406
/*    */     //   #147	-> 1409
/*    */     //   #148	-> 1413
/*    */     //   #149	-> 1426
/*    */     //   #150	-> 1430
/*    */     //   #151	-> 1433
/*    */     //   #152	-> 1444
/*    */     //   #153	-> 1447
/*    */     //   #154	-> 1464
/*    */     //   #155	-> 1467
/*    */     //   #156	-> 1470
/*    */     //   #157	-> 1490
/*    */     //   #158	-> 1497
/*    */     //   #159	-> 1500
/*    */     //   #160	-> 1503
/*    */     //   #161	-> 1516
/*    */     //   #162	-> 1519
/*    */     //   #163	-> 1524
/*    */     //   #164	-> 1539
/*    */     //   #165	-> 1551
/*    */     //   #166	-> 1563
/*    */     //   #167	-> 1566
/*    */     //   #168	-> 1584
/*    */     //   #169	-> 1587
/*    */     //   #170	-> 1605
/*    */     //   #171	-> 1608
/*    */     //   #172	-> 1627
/*    */     //   #173	-> 1630
/*    */     //   #174	-> 1649
/*    */     //   #175	-> 1652
/*    */     //   #176	-> 1671
/*    */     //   #177	-> 1674
/*    */     //   #178	-> 1704
/*    */     //   #179	-> 1708
/*    */     //   #180	-> 1721
/*    */     //   #181	-> 1725
/*    */     //   #182	-> 1738
/*    */     //   #183	-> 1743
/*    */     //   #184	-> 1756
/*    */     //   #185	-> 1761
/*    */     //   #186	-> 1774
/*    */     //   #187	-> 1779
/*    */     //   #188	-> 1792
/*    */     //   #189	-> 1797
/*    */     //   #190	-> 1810
/*    */     //   #191	-> 1837
/*    */     //   #192	-> 1852
/*    */     //   #193	-> 1856
/*    */     //   #194	-> 1869
/*    */     //   #195	-> 1873
/*    */     //   #196	-> 1886
/*    */     //   #197	-> 1891
/*    */     //   #198	-> 1904
/*    */     //   #199	-> 1909
/*    */     //   #200	-> 1922
/*    */     //   #201	-> 1927
/*    */     //   #202	-> 1940
/*    */     //   #203	-> 1945
/*    */     //   #204	-> 1961
/*    */     //   #205	-> 1964
/*    */     //   #206	-> 1967
/*    */     //   #207	-> 2017
/*    */     //   #208	-> 2021
/*    */     //   #209	-> 2024
/*    */     //   #210	-> 2035
/*    */     //   #211	-> 2038
/*    */     //   #212	-> 2048
/*    */     //   #213	-> 2053
/*    */     //   #214	-> 2056
/*    */     //   #215	-> 2063
/*    */     //   #216	-> 2066
/*    */     //   #217	-> 2071
/*    */     //   #218	-> 2078
/*    */     //   #219	-> 2108
/*    */     //   #220	-> 2111
/*    */     //   #221	-> 2115
/*    */     //   #222	-> 2118
/*    */     //   #223	-> 2130
/*    */     //   #224	-> 2134
/*    */     //   #225	-> 2138
/*    */     //   #226	-> 2142
/*    */     //   #227	-> 2145
/*    */     //   #228	-> 2149
/*    */     //   #229	-> 2154
/*    */     //   #230	-> 2162
/*    */     //   #231	-> 2169
/*    */     //   #232	-> 2176
/*    */     //   #233	-> 2182
/*    */     //   #234	-> 2193
/*    */     //   #235	-> 2196
/*    */     //   #236	-> 2221
/*    */     //   #237	-> 2224
/*    */     //   #238	-> 2228
/*    */     //   #239	-> 2229
/*    */     //   #240	-> 2238
/*    */     //   #241	-> 2247
/*    */     //   #242	-> 2252
/*    */     //   #243	-> 2256
/*    */     //   #244	-> 2265
/*    */     //   #245	-> 2269
/*    */     //   #246	-> 2272
/*    */     //   #247	-> 2275
/*    */     //   #248	-> 2294
/*    */     //   #249	-> 2297
/*    */     //   #250	-> 2311
/*    */     //   #251	-> 2317
/*    */     //   #252	-> 2323
/*    */     //   #253	-> 2334
/*    */     //   #254	-> 2337
/*    */     //   #255	-> 2367
/*    */     //   #256	-> 2370
/*    */     //   #257	-> 2391
/*    */     //   #258	-> 2394
/*    */     //   #259	-> 2402
/*    */     //   #260	-> 2412
/*    */     //   #261	-> 2415
/*    */     //   #262	-> 2425
/*    */     //   #263	-> 2435
/*    */     //   #264	-> 2438
/*    */     //   #265	-> 2457
/*    */     //   #266	-> 2467
/*    */     //   #267	-> 2498
/*    */     //   #268	-> 2501
/*    */     //   #269	-> 2512
/*    */     //   #270	-> 2516
/*    */     //   #271	-> 2523
/*    */     //   #272	-> 2528
/*    */     //   #273	-> 2539
/*    */     //   #274	-> 2542
/*    */     //   #275	-> 2559
/*    */     //   #276	-> 2562
/*    */     //   #277	-> 2565
/*    */     //   #278	-> 2595
/*    */     //   #279	-> 2598
/*    */     //   #280	-> 2601
/*    */     //   #281	-> 2607
/*    */     //   #282	-> 2617
/*    */     //   #283	-> 2623
/*    */     //   #284	-> 2626
/*    */     //   #285	-> 2635
/*    */     //   #286	-> 2638
/*    */     //   #287	-> 2644
/*    */     //   #288	-> 2657
/*    */     //   #289	-> 2660
/*    */     //   #290	-> 2672
/*    */     //   #291	-> 2676
/*    */     //   #292	-> 2732
/*    */     //   #293	-> 2735
/*    */     //   #294	-> 2745
/*    */     //   #295	-> 2755
/*    */     //   #296	-> 2758
/*    */     //   #297	-> 2768
/*    */     //   #298	-> 2778
/*    */     //   #299	-> 2781
/*    */     //   #300	-> 2800
/*    */   }
/*    */   
/*    */   public final void XH0(int paramInt) {
/*    */     n3 n31;
/*    */     if (paramInt < 0)
/*    */       paramInt = 0; 
/*    */     nJ0[] arrayOfNJ0;
/*    */     if (paramInt >= (arrayOfNJ0 = this.fH).length)
/*    */       paramInt = arrayOfNJ0.length - 1; 
/*    */     this.default.gx();
/*    */     gf gf1;
/*    */     if ((gf1 = (gf)(this.fH[paramInt]).ZX).Ki0 == -1) {
/*    */       rS rS1 = this.Uj;
/*    */     } else {
/*    */       n31 = gf1.V0;
/*    */     } 
/*    */     this.default.si(n31, this.default.Ub());
/*    */     e8().zn0(false);
/*    */     this.VK0.E1(this.LPt7.Kg((byte)gf1.Ki0));
/*    */     gf1.BA();
/*    */     this.s5 = paramInt;
/*    */     Fw(true);
/*    */   }
/*    */   
/*    */   public final YA0 lK0() {
/*    */     this();
/*    */     (this.VK0 = P6.A("BOX")).Xu("box-name");
/*    */     this.VK0.lPt3(this::Oz0);
/*    */     dQ dQ1 = this.VK0;
/*    */     YA0 yA0;
/*    */     (yA0 = new YA0()).Dv0.S7(this);
/*    */     return new YA0();
/*    */   }
/*    */   
/*    */   public final YA0 wF() {
/*    */     // Byte code:
/*    */     //   0: aload_0
/*    */     //   1: dup
/*    */     //   2: new f/YA0
/*    */     //   5: dup
/*    */     //   6: astore_1
/*    */     //   7: invokespecial <init> : ()V
/*    */     //   10: getstatic f/km.u4 : Lf/R8;
/*    */     //   13: getstatic f/aq0.XJ0 : Lf/aq0;
/*    */     //   16: invokevirtual s40 : (Lf/aq0;)Lf/Uc0;
/*    */     //   19: invokevirtual oq : ()I
/*    */     //   22: bipush #60
/*    */     //   24: idiv
/*    */     //   25: dup
/*    */     //   26: istore_2
/*    */     //   27: anewarray f/n3
/*    */     //   30: putfield Gu0 : [Lf/n3;
/*    */     //   33: iload_2
/*    */     //   34: iconst_1
/*    */     //   35: iadd
/*    */     //   36: dup
/*    */     //   37: istore_2
/*    */     //   38: anewarray f/nJ0
/*    */     //   41: putfield fH : [Lf/nJ0;
/*    */     //   44: iconst_0
/*    */     //   45: istore_3
/*    */     //   46: iload_3
/*    */     //   47: aload_0
/*    */     //   48: getfield fH : [Lf/nJ0;
/*    */     //   51: dup
/*    */     //   52: astore #4
/*    */     //   54: arraylength
/*    */     //   55: if_icmpge -> 91
/*    */     //   58: iload_3
/*    */     //   59: bipush #13
/*    */     //   61: irem
/*    */     //   62: ifne -> 73
/*    */     //   65: aload_1
/*    */     //   66: getfield Dv0 : Lf/SA;
/*    */     //   69: invokevirtual wP : ()Lf/nJ0;
/*    */     //   72: pop
/*    */     //   73: aload #4
/*    */     //   75: iload_3
/*    */     //   76: aload_1
/*    */     //   77: getfield Dv0 : Lf/SA;
/*    */     //   80: aconst_null
/*    */     //   81: invokevirtual S7 : (Ljava/lang/Object;)Lf/nJ0;
/*    */     //   84: aastore
/*    */     //   85: iinc #3, 1
/*    */     //   88: goto -> 46
/*    */     //   91: invokestatic XU : ()Z
/*    */     //   94: ifeq -> 103
/*    */     //   97: bipush #74
/*    */     //   99: istore_3
/*    */     //   100: goto -> 106
/*    */     //   103: bipush #52
/*    */     //   105: istore_3
/*    */     //   106: iconst_0
/*    */     //   107: istore #4
/*    */     //   109: iload #4
/*    */     //   111: aload_0
/*    */     //   112: getfield Gu0 : [Lf/n3;
/*    */     //   115: dup
/*    */     //   116: astore #5
/*    */     //   118: arraylength
/*    */     //   119: if_icmpge -> 257
/*    */     //   122: aload_0
/*    */     //   123: dup
/*    */     //   124: aload #5
/*    */     //   126: iload #4
/*    */     //   128: new f/n3
/*    */     //   131: dup
/*    */     //   132: astore #5
/*    */     //   134: aload_0
/*    */     //   135: iload #4
/*    */     //   137: invokespecial <init> : (Lf/gO;I)V
/*    */     //   140: aload #5
/*    */     //   142: aastore
/*    */     //   143: getfield Gu0 : [Lf/n3;
/*    */     //   146: iload #4
/*    */     //   148: aaload
/*    */     //   149: aload_0
/*    */     //   150: <illegal opcode> accept : (Lf/gO;)Ljava/util/function/Consumer;
/*    */     //   155: putfield Qx0 : Ljava/util/function/Consumer;
/*    */     //   158: new f/gf
/*    */     //   161: dup
/*    */     //   162: astore #5
/*    */     //   164: aload_0
/*    */     //   165: aload #5
/*    */     //   167: dup
/*    */     //   168: aload_0
/*    */     //   169: aload #5
/*    */     //   171: dup
/*    */     //   172: dup
/*    */     //   173: aload_0
/*    */     //   174: dup
/*    */     //   175: dup
/*    */     //   176: getfield LPt7 : Lf/Iq0;
/*    */     //   179: astore #6
/*    */     //   181: getfield Gu0 : [Lf/n3;
/*    */     //   184: iload #4
/*    */     //   186: aaload
/*    */     //   187: astore #7
/*    */     //   189: aload #6
/*    */     //   191: aload_1
/*    */     //   192: aload #7
/*    */     //   194: iload #4
/*    */     //   196: invokespecial <init> : (Lf/gO;Lf/Iq0;Lf/YA0;Lf/n3;I)V
/*    */     //   199: iconst_1
/*    */     //   200: invokevirtual wI0 : (Z)V
/*    */     //   203: iconst_1
/*    */     //   204: invokevirtual sk0 : (Z)V
/*    */     //   207: getfield LPt7 : Lf/Iq0;
/*    */     //   210: iload #4
/*    */     //   212: i2b
/*    */     //   213: invokevirtual Kg : (B)Ljava/lang/String;
/*    */     //   216: invokevirtual s6 : (Ljava/lang/String;)V
/*    */     //   219: <illegal opcode> run : (Lf/gO;Lf/gf;)Ljava/lang/Runnable;
/*    */     //   224: invokevirtual tW : (Ljava/lang/Runnable;)V
/*    */     //   227: getfield fH : [Lf/nJ0;
/*    */     //   230: aload_0
/*    */     //   231: getfield LPt7 : Lf/Iq0;
/*    */     //   234: iload #4
/*    */     //   236: invokevirtual cm0 : (I)I
/*    */     //   239: aaload
/*    */     //   240: aload #5
/*    */     //   242: invokevirtual cd : (Lf/JG0;)Lf/nJ0;
/*    */     //   245: iload_3
/*    */     //   246: i2f
/*    */     //   247: invokevirtual dO : (F)Lf/nJ0;
/*    */     //   250: pop
/*    */     //   251: iinc #4, 1
/*    */     //   254: goto -> 109
/*    */     //   257: aload_0
/*    */     //   258: dup
/*    */     //   259: new f/rS
/*    */     //   262: dup
/*    */     //   263: aload_0
/*    */     //   264: swap
/*    */     //   265: dup
/*    */     //   266: aconst_null
/*    */     //   267: invokespecial <init> : (Lf/JG0;)V
/*    */     //   270: putfield Uj : Lf/rS;
/*    */     //   273: iconst_2
/*    */     //   274: invokevirtual zG0 : (I)V
/*    */     //   277: new f/jw0
/*    */     //   280: dup
/*    */     //   281: astore #4
/*    */     //   283: aload_0
/*    */     //   284: aload #4
/*    */     //   286: aload_0
/*    */     //   287: invokespecial <init> : (Lf/gO;)V
/*    */     //   290: <illegal opcode> accept : (Lf/gO;)Ljava/util/function/Consumer;
/*    */     //   295: putfield Qx0 : Ljava/util/function/Consumer;
/*    */     //   298: getfield Uj : Lf/rS;
/*    */     //   301: aload #4
/*    */     //   303: invokevirtual Gz0 : (Lf/JG0;)V
/*    */     //   306: new f/gf
/*    */     //   309: dup
/*    */     //   310: astore #5
/*    */     //   312: aload_0
/*    */     //   313: aload #5
/*    */     //   315: aload_0
/*    */     //   316: aload #5
/*    */     //   318: dup
/*    */     //   319: dup
/*    */     //   320: aload_0
/*    */     //   321: dup
/*    */     //   322: getfield LPt7 : Lf/Iq0;
/*    */     //   325: aload_1
/*    */     //   326: aload #4
/*    */     //   328: iconst_m1
/*    */     //   329: invokespecial <init> : (Lf/gO;Lf/Iq0;Lf/YA0;Lf/n3;I)V
/*    */     //   332: iconst_1
/*    */     //   333: invokevirtual wI0 : (Z)V
/*    */     //   336: iconst_1
/*    */     //   337: invokevirtual sk0 : (Z)V
/*    */     //   340: getfield fH : [Lf/nJ0;
/*    */     //   343: aload_0
/*    */     //   344: getfield Gu0 : [Lf/n3;
/*    */     //   347: arraylength
/*    */     //   348: aaload
/*    */     //   349: aload #5
/*    */     //   351: invokevirtual cd : (Lf/JG0;)Lf/nJ0;
/*    */     //   354: iload_3
/*    */     //   355: i2f
/*    */     //   356: dup
/*    */     //   357: fstore_3
/*    */     //   358: invokevirtual dO : (F)Lf/nJ0;
/*    */     //   361: pop
/*    */     //   362: <illegal opcode> run : (Lf/gO;Lf/gf;)Ljava/lang/Runnable;
/*    */     //   367: invokevirtual tW : (Ljava/lang/Runnable;)V
/*    */     //   370: new f/rS
/*    */     //   373: dup
/*    */     //   374: dup
/*    */     //   375: astore #4
/*    */     //   377: aload_0
/*    */     //   378: dup
/*    */     //   379: dup
/*    */     //   380: dup2
/*    */     //   381: aload #4
/*    */     //   383: dup
/*    */     //   384: aconst_null
/*    */     //   385: invokespecial <init> : (Lf/JG0;)V
/*    */     //   388: iconst_2
/*    */     //   389: invokevirtual zG0 : (I)V
/*    */     //   392: new f/Ip
/*    */     //   395: dup
/*    */     //   396: invokespecial <init> : ()V
/*    */     //   399: putfield Bq0 : Lf/Ip;
/*    */     //   402: new f/dQ
/*    */     //   405: dup
/*    */     //   406: invokespecial <init> : ()V
/*    */     //   409: putfield FM : Lf/dQ;
/*    */     //   412: getfield Bq0 : Lf/Ip;
/*    */     //   415: dup
/*    */     //   416: dup
/*    */     //   417: astore #4
/*    */     //   419: invokevirtual getClass : ()Ljava/lang/Class;
/*    */     //   422: pop
/*    */     //   423: new f/cr0
/*    */     //   426: dup
/*    */     //   427: aload #4
/*    */     //   429: invokespecial <init> : (Lf/Ip;)V
/*    */     //   432: invokevirtual Em0 : ()Lf/U90;
/*    */     //   435: aload_0
/*    */     //   436: getfield FM : Lf/dQ;
/*    */     //   439: invokevirtual Ya : (Lf/JG0;)Lf/U90;
/*    */     //   442: invokevirtual Em0 : ()Lf/U90;
/*    */     //   445: invokevirtual rK0 : (Lf/U90;)V
/*    */     //   448: getfield Bq0 : Lf/Ip;
/*    */     //   451: dup
/*    */     //   452: dup
/*    */     //   453: astore #4
/*    */     //   455: invokevirtual getClass : ()Ljava/lang/Class;
/*    */     //   458: pop
/*    */     //   459: new f/cr0
/*    */     //   462: dup
/*    */     //   463: aload #4
/*    */     //   465: invokespecial <init> : (Lf/Ip;)V
/*    */     //   468: invokevirtual Em0 : ()Lf/U90;
/*    */     //   471: aload_0
/*    */     //   472: getfield FM : Lf/dQ;
/*    */     //   475: invokevirtual Ya : (Lf/JG0;)Lf/U90;
/*    */     //   478: invokevirtual Em0 : ()Lf/U90;
/*    */     //   481: invokevirtual WN : (Lf/U90;)V
/*    */     //   484: getfield Bq0 : Lf/Ip;
/*    */     //   487: invokevirtual Gz0 : (Lf/JG0;)V
/*    */     //   490: putfield AF0 : Lf/rS;
/*    */     //   493: getstatic f/gm.By0 : Z
/*    */     //   496: ifeq -> 583
/*    */     //   499: getstatic f/km.u4 : Lf/R8;
/*    */     //   502: getfield Lz : Lf/fH0;
/*    */     //   505: getfield m4 : B
/*    */     //   508: getstatic f/Bz.Np0 : I
/*    */     //   511: if_icmpge -> 583
/*    */     //   514: iload_2
/*    */     //   515: new f/Un
/*    */     //   518: dup
/*    */     //   519: dup
/*    */     //   520: dup2
/*    */     //   521: astore_2
/*    */     //   522: ldc_w '+'
/*    */     //   525: invokespecial <init> : (Ljava/lang/String;)V
/*    */     //   528: ldc_w 'pc-box-button'
/*    */     //   531: invokevirtual Xu : (Ljava/lang/String;)V
/*    */     //   534: iconst_1
/*    */     //   535: invokevirtual wI0 : (Z)V
/*    */     //   538: iconst_1
/*    */     //   539: invokevirtual sk0 : (Z)V
/*    */     //   542: bipush #13
/*    */     //   544: irem
/*    */     //   545: ifne -> 556
/*    */     //   548: aload_1
/*    */     //   549: getfield Dv0 : Lf/SA;
/*    */     //   552: invokevirtual wP : ()Lf/nJ0;
/*    */     //   555: pop
/*    */     //   556: aload_2
/*    */     //   557: aload_0
/*    */     //   558: aload_1
/*    */     //   559: getfield Dv0 : Lf/SA;
/*    */     //   562: aconst_null
/*    */     //   563: invokevirtual S7 : (Ljava/lang/Object;)Lf/nJ0;
/*    */     //   566: aload_2
/*    */     //   567: invokevirtual cd : (Lf/JG0;)Lf/nJ0;
/*    */     //   570: fload_3
/*    */     //   571: invokevirtual dO : (F)Lf/nJ0;
/*    */     //   574: pop
/*    */     //   575: <illegal opcode> run : (Lf/gO;)Ljava/lang/Runnable;
/*    */     //   580: invokevirtual tW : (Ljava/lang/Runnable;)V
/*    */     //   583: aload_1
/*    */     //   584: areturn
/*    */     // Line number table:
/*    */     //   Java source line number -> byte code offset
/*    */     //   #1	-> 61
/*    */     //   #2	-> 66
/*    */     //   #3	-> 69
/*    */     //   #4	-> 77
/*    */     //   #5	-> 84
/*    */     //   #6	-> 155
/*    */     //   #7	-> 158
/*    */     //   #8	-> 267
/*    */     //   #9	-> 270
/*    */     //   #10	-> 295
/*    */     //   #11	-> 298
/*    */     //   #12	-> 370
/*    */     //   #13	-> 385
/*    */     //   #14	-> 389
/*    */     //   #15	-> 423
/*    */     //   #16	-> 432
/*    */     //   #17	-> 459
/*    */     //   #18	-> 468
/*    */     //   #19	-> 490
/*    */     //   #20	-> 502
/*    */     //   #21	-> 505
/*    */     //   #22	-> 508
/*    */     //   #23	-> 544
/*    */     //   #24	-> 549
/*    */     //   #25	-> 552
/*    */     //   #26	-> 559
/*    */     //   #27	-> 567
/*    */   }
/*    */   
/*    */   public final void H60() {
/*    */     vg();
/*    */     this.default.gx();
/*    */     rS rS1 = this.AF0;
/*    */     this.default.si(this, this.default.Ub());
/*    */   }
/*    */   
/*    */   public final void vg() {
/*    */     UB0.Kg0.fN(this::Uy);
/*    */   }
/*    */   
/*    */   public final n3 e8() {
/*    */     return ((gf)(this.fH[this.s5]).ZX).V0;
/*    */   }
/*    */   
/*    */   public final void Fw(boolean paramBoolean) {
/*    */     NR nR;
/*    */     if ((nR = this.oP) != null)
/*    */       nR.xf0(); 
/*    */     String[] arrayOfString = this.ok0.F2.toString().toLowerCase().split(" ");
/*    */     if (paramBoolean) {
/*    */       int i;
/*    */       n3[] arrayOfN3;
/*    */       if ((i = this.s5) < (arrayOfN3 = this.Gu0).length)
/*    */         arrayOfN3[i].lp0(arrayOfString); 
/*    */     } else {
/*    */       n3[] arrayOfN3;
/*    */       int i;
/*    */       byte b;
/*    */       for (i = (arrayOfN3 = this.Gu0).length, b = 0; b < i; ) {
/*    */         n3 n31;
/*    */         if ((n31 = arrayOfN3[b]) != null)
/*    */           n31.lp0(arrayOfString); 
/*    */         b++;
/*    */       } 
/*    */     } 
/*    */     ((jw0)this.Uj.iR).lp0(null);
/*    */     ee(e8().M50().public());
/*    */   }
/*    */   
/*    */   public final void V90(throws paramthrows) {
/*    */     // Byte code:
/*    */     //   0: getstatic f/km.u4 : Lf/R8;
/*    */     //   3: getstatic f/aq0.LI : Lf/aq0;
/*    */     //   6: invokevirtual s40 : (Lf/aq0;)Lf/Uc0;
/*    */     //   9: astore_2
/*    */     //   10: invokestatic XU : ()Z
/*    */     //   13: ifeq -> 46
/*    */     //   16: aload_2
/*    */     //   17: ifnull -> 46
/*    */     //   20: aload_2
/*    */     //   21: getfield ID0 : Z
/*    */     //   24: ifeq -> 37
/*    */     //   27: aload_2
/*    */     //   28: iconst_0
/*    */     //   29: putfield ID0 : Z
/*    */     //   32: iconst_1
/*    */     //   33: istore_2
/*    */     //   34: goto -> 39
/*    */     //   37: iconst_0
/*    */     //   38: istore_2
/*    */     //   39: iload_2
/*    */     //   40: ifeq -> 46
/*    */     //   43: goto -> 83
/*    */     //   46: getstatic f/km.u4 : Lf/R8;
/*    */     //   49: getstatic f/aq0.XJ0 : Lf/aq0;
/*    */     //   52: invokevirtual s40 : (Lf/aq0;)Lf/Uc0;
/*    */     //   55: dup
/*    */     //   56: astore_2
/*    */     //   57: ifnull -> 87
/*    */     //   60: aload_2
/*    */     //   61: getfield ID0 : Z
/*    */     //   64: ifeq -> 77
/*    */     //   67: aload_2
/*    */     //   68: iconst_0
/*    */     //   69: putfield ID0 : Z
/*    */     //   72: iconst_1
/*    */     //   73: istore_2
/*    */     //   74: goto -> 79
/*    */     //   77: iconst_0
/*    */     //   78: istore_2
/*    */     //   79: iload_2
/*    */     //   80: ifeq -> 87
/*    */     //   83: iconst_1
/*    */     //   84: goto -> 88
/*    */     //   87: iconst_0
/*    */     //   88: ifeq -> 96
/*    */     //   91: aload_0
/*    */     //   92: iconst_0
/*    */     //   93: invokevirtual Fw : (Z)V
/*    */     //   96: aload_0
/*    */     //   97: getfield U40 : Lf/Qv0;
/*    */     //   100: ifnull -> 198
/*    */     //   103: aload_0
/*    */     //   104: invokevirtual e8 : ()Lf/n3;
/*    */     //   107: instanceof f/jw0
/*    */     //   110: ifeq -> 198
/*    */     //   113: aload_0
/*    */     //   114: getfield U40 : Lf/Qv0;
/*    */     //   117: getfield jo : I
/*    */     //   120: aload_0
/*    */     //   121: getfield Uj : Lf/rS;
/*    */     //   124: dup
/*    */     //   125: astore_2
/*    */     //   126: getfield er0 : I
/*    */     //   129: isub
/*    */     //   130: dup
/*    */     //   131: istore_3
/*    */     //   132: aload_2
/*    */     //   133: getfield HC : I
/*    */     //   136: istore #4
/*    */     //   138: ifle -> 198
/*    */     //   141: iload_3
/*    */     //   142: iload #4
/*    */     //   144: if_icmpge -> 198
/*    */     //   147: iload_3
/*    */     //   148: iload #4
/*    */     //   150: bipush #7
/*    */     //   152: idiv
/*    */     //   153: if_icmpge -> 172
/*    */     //   156: aload_2
/*    */     //   157: dup
/*    */     //   158: getfield PB : Lf/Ja;
/*    */     //   161: getfield Ny0 : I
/*    */     //   164: iconst_2
/*    */     //   165: isub
/*    */     //   166: invokevirtual rt : (I)V
/*    */     //   169: goto -> 198
/*    */     //   172: iload_3
/*    */     //   173: i2f
/*    */     //   174: iload #4
/*    */     //   176: i2f
/*    */     //   177: ldc_w 0.85714287
/*    */     //   180: fmul
/*    */     //   181: fcmpl
/*    */     //   182: ifle -> 198
/*    */     //   185: aload_2
/*    */     //   186: dup
/*    */     //   187: getfield PB : Lf/Ja;
/*    */     //   190: getfield Ny0 : I
/*    */     //   193: iconst_2
/*    */     //   194: iadd
/*    */     //   195: invokevirtual rt : (I)V
/*    */     //   198: aload_0
/*    */     //   199: aload_1
/*    */     //   200: invokespecial V90 : (Lf/throws;)V
/*    */     //   203: return
/*    */     // Line number table:
/*    */     //   Java source line number -> byte code offset
/*    */     //   #1	-> 0
/*    */     //   #2	-> 21
/*    */     //   #3	-> 46
/*    */     //   #4	-> 61
/*    */     //   #5	-> 93
/*    */     //   #6	-> 97
/*    */     //   #7	-> 104
/*    */     //   #8	-> 114
/*    */     //   #9	-> 117
/*    */     //   #10	-> 121
/*    */     //   #11	-> 126
/*    */     //   #12	-> 133
/*    */     //   #13	-> 152
/*    */     //   #14	-> 158
/*    */     //   #15	-> 161
/*    */     //   #16	-> 166
/*    */     //   #17	-> 187
/*    */     //   #18	-> 190
/*    */     //   #19	-> 195
/*    */   }
/*    */   
/*    */   public final void R60(throws paramthrows) {
/*    */     super.R60(paramthrows);
/*    */     if (this.U40 != null)
/*    */       for (Iterator iterator = this.Lpt8.iterator(); hasNext(); ) {
/*    */         int i = ((Qv0)next()).r6;
/*    */         ((Qv0)next()).Ve(paramthrows, i, ((Qv0)next()).jo, 0);
/*    */       }  
/*    */   }
/*    */   
/*    */   public final void yV(throws paramthrows) {
/*    */     if (UB0.PU.Ak(129) && UB0.PU.j2(34))
/*    */       this.ok0.BA(); 
/*    */     if (h1.pw) {
/*    */       UB0.M60.getClass();
/*    */       UB0.M60.getClass();
/*    */     } 
/*    */     int i = 0, j = 0;
/*    */     mX mX1;
/*    */     if ((mX1 = this.td0) != null) {
/*    */       Sa0 sa0 = this.O;
/*    */       int k = this.Kd - j;
/*    */       int m = this.er0;
/*    */       i = this.xY + j + i;
/*    */       j = this.HC;
/*    */       mX1.W8(sa0, k, m, i, j);
/*    */     } 
/*    */     UA0 uA0;
/*    */     if ((uA0 = this.NV) != null)
/*    */       UB0.Kg0.fN(this); 
/*    */   }
/*    */   
/*    */   public final boolean i2(oa0 paramoa0) {
/*    */     // Byte code:
/*    */     //   0: aload_1
/*    */     //   1: getfield cz0 : I
/*    */     //   4: invokestatic Wm0 : (I)Z
/*    */     //   7: ifeq -> 513
/*    */     //   10: aload_1
/*    */     //   11: invokevirtual oO : ()Z
/*    */     //   14: ifeq -> 513
/*    */     //   17: aload_0
/*    */     //   18: getfield oP : Lf/NR;
/*    */     //   21: invokevirtual p3 : ()Z
/*    */     //   24: ifeq -> 92
/*    */     //   27: aload_1
/*    */     //   28: getfield GG0 : I
/*    */     //   31: getstatic f/BM.Oq : Lf/BM;
/*    */     //   34: invokestatic J20 : (ILf/BM;)Z
/*    */     //   37: ifeq -> 92
/*    */     //   40: aload_0
/*    */     //   41: dup
/*    */     //   42: dup
/*    */     //   43: invokevirtual e8 : ()Lf/n3;
/*    */     //   46: dup
/*    */     //   47: getfield Gg0 : I
/*    */     //   50: invokevirtual H0 : (I)V
/*    */     //   53: invokevirtual e8 : ()Lf/n3;
/*    */     //   56: invokevirtual M50 : ()Lf/Zq;
/*    */     //   59: dup
/*    */     //   60: dup2
/*    */     //   61: astore_0
/*    */     //   62: invokevirtual RS : ()I
/*    */     //   65: istore_1
/*    */     //   66: invokevirtual qF : ()I
/*    */     //   69: iconst_2
/*    */     //   70: idiv
/*    */     //   71: iload_1
/*    */     //   72: iadd
/*    */     //   73: istore_1
/*    */     //   74: invokevirtual e3 : ()I
/*    */     //   77: istore_2
/*    */     //   78: iload_1
/*    */     //   79: aload_0
/*    */     //   80: invokevirtual Hy : ()I
/*    */     //   83: iconst_2
/*    */     //   84: idiv
/*    */     //   85: iload_2
/*    */     //   86: iadd
/*    */     //   87: invokevirtual lf0 : (II)V
/*    */     //   90: iconst_1
/*    */     //   91: ireturn
/*    */     //   92: aload_1
/*    */     //   93: getfield GG0 : I
/*    */     //   96: getstatic f/BM.cf : Lf/BM;
/*    */     //   99: invokestatic J20 : (ILf/BM;)Z
/*    */     //   102: ifeq -> 132
/*    */     //   105: aload_0
/*    */     //   106: dup
/*    */     //   107: getfield lp0 : Lf/ge0;
/*    */     //   110: dup
/*    */     //   111: getfield TG0 : Lf/protected;
/*    */     //   114: invokevirtual nm0 : ()Z
/*    */     //   117: iconst_1
/*    */     //   118: ixor
/*    */     //   119: istore_0
/*    */     //   120: getfield TG0 : Lf/protected;
/*    */     //   123: iload_0
/*    */     //   124: invokevirtual Fx0 : (Z)V
/*    */     //   127: invokevirtual Xu : ()V
/*    */     //   130: iconst_1
/*    */     //   131: ireturn
/*    */     //   132: aload_1
/*    */     //   133: getfield GG0 : I
/*    */     //   136: getstatic f/BM.PW : Lf/BM;
/*    */     //   139: invokestatic J20 : (ILf/BM;)Z
/*    */     //   142: ifeq -> 179
/*    */     //   145: aload_0
/*    */     //   146: getfield iE0 : Z
/*    */     //   149: ifne -> 179
/*    */     //   152: aload_0
/*    */     //   153: dup
/*    */     //   154: dup2
/*    */     //   155: invokevirtual e8 : ()Lf/n3;
/*    */     //   158: getfield Gg0 : I
/*    */     //   161: istore_0
/*    */     //   162: getfield s5 : I
/*    */     //   165: iconst_1
/*    */     //   166: iadd
/*    */     //   167: invokevirtual XH0 : (I)V
/*    */     //   170: invokevirtual e8 : ()Lf/n3;
/*    */     //   173: iload_0
/*    */     //   174: invokevirtual H0 : (I)V
/*    */     //   177: iconst_1
/*    */     //   178: ireturn
/*    */     //   179: aload_1
/*    */     //   180: getfield GG0 : I
/*    */     //   183: getstatic f/BM.fN : Lf/BM;
/*    */     //   186: invokestatic J20 : (ILf/BM;)Z
/*    */     //   189: ifeq -> 226
/*    */     //   192: aload_0
/*    */     //   193: getfield iE0 : Z
/*    */     //   196: ifne -> 226
/*    */     //   199: aload_0
/*    */     //   200: dup
/*    */     //   201: dup2
/*    */     //   202: invokevirtual e8 : ()Lf/n3;
/*    */     //   205: getfield Gg0 : I
/*    */     //   208: istore_0
/*    */     //   209: getfield s5 : I
/*    */     //   212: iconst_1
/*    */     //   213: isub
/*    */     //   214: invokevirtual XH0 : (I)V
/*    */     //   217: invokevirtual e8 : ()Lf/n3;
/*    */     //   220: iload_0
/*    */     //   221: invokevirtual H0 : (I)V
/*    */     //   224: iconst_1
/*    */     //   225: ireturn
/*    */     //   226: aload_0
/*    */     //   227: getfield U40 : Lf/Qv0;
/*    */     //   230: ifnull -> 454
/*    */     //   233: aload_1
/*    */     //   234: getfield GG0 : I
/*    */     //   237: getstatic f/BM.lc : Lf/BM;
/*    */     //   240: invokestatic J20 : (ILf/BM;)Z
/*    */     //   243: ifeq -> 315
/*    */     //   246: aload_0
/*    */     //   247: getfield Lpt8 : Ljava/util/HashSet;
/*    */     //   250: invokevirtual iterator : ()Ljava/util/Iterator;
/*    */     //   253: astore_1
/*    */     //   254: aload_1
/*    */     //   255: invokeinterface hasNext : ()Z
/*    */     //   260: ifeq -> 301
/*    */     //   263: aload_1
/*    */     //   264: invokeinterface next : ()Ljava/lang/Object;
/*    */     //   269: checkcast f/Qv0
/*    */     //   272: dup
/*    */     //   273: dup2
/*    */     //   274: iconst_0
/*    */     //   275: dup
/*    */     //   276: istore_2
/*    */     //   277: putfield I20 : Z
/*    */     //   280: getfield O : Lf/Sa0;
/*    */     //   283: getstatic f/Qv0.MZ : Lf/Ll;
/*    */     //   286: iload_2
/*    */     //   287: invokevirtual gf0 : (Lf/Ll;Z)V
/*    */     //   290: aconst_null
/*    */     //   291: putfield Ba0 : Lf/Qv0;
/*    */     //   294: iconst_0
/*    */     //   295: invokevirtual Cx0 : (Z)V
/*    */     //   298: goto -> 254
/*    */     //   301: aload_0
/*    */     //   302: dup
/*    */     //   303: aconst_null
/*    */     //   304: putfield U40 : Lf/Qv0;
/*    */     //   307: getfield Lpt8 : Ljava/util/HashSet;
/*    */     //   310: invokevirtual clear : ()V
/*    */     //   313: iconst_1
/*    */     //   314: ireturn
/*    */     //   315: aload_1
/*    */     //   316: getfield GG0 : I
/*    */     //   319: getstatic f/BM.ni : Lf/BM;
/*    */     //   322: invokestatic J20 : (ILf/BM;)Z
/*    */     //   325: ifne -> 380
/*    */     //   328: aload_1
/*    */     //   329: getfield GG0 : I
/*    */     //   332: getstatic f/BM.N70 : Lf/BM;
/*    */     //   335: invokestatic J20 : (ILf/BM;)Z
/*    */     //   338: ifne -> 380
/*    */     //   341: aload_1
/*    */     //   342: getfield GG0 : I
/*    */     //   345: getstatic f/BM.Oq : Lf/BM;
/*    */     //   348: invokestatic J20 : (ILf/BM;)Z
/*    */     //   351: ifne -> 380
/*    */     //   354: aload_1
/*    */     //   355: getfield GG0 : I
/*    */     //   358: getstatic f/BM.M8 : Lf/BM;
/*    */     //   361: invokestatic J20 : (ILf/BM;)Z
/*    */     //   364: ifne -> 380
/*    */     //   367: aload_1
/*    */     //   368: getfield GG0 : I
/*    */     //   371: getstatic f/BM.bC : Lf/BM;
/*    */     //   374: invokestatic J20 : (ILf/BM;)Z
/*    */     //   377: ifeq -> 454
/*    */     //   380: aload_0
/*    */     //   381: dup
/*    */     //   382: aload_1
/*    */     //   383: invokespecial i2 : (Lf/oa0;)Z
/*    */     //   386: pop
/*    */     //   387: getfield U40 : Lf/Qv0;
/*    */     //   390: ifnonnull -> 395
/*    */     //   393: iconst_1
/*    */     //   394: ireturn
/*    */     //   395: aload_0
/*    */     //   396: getfield Bo0 : Lf/throws;
/*    */     //   399: dup
/*    */     //   400: astore_1
/*    */     //   401: ifnonnull -> 406
/*    */     //   404: iconst_1
/*    */     //   405: ireturn
/*    */     //   406: aload_1
/*    */     //   407: getfield LG : Lf/JG0;
/*    */     //   410: dup
/*    */     //   411: astore_2
/*    */     //   412: ifnull -> 420
/*    */     //   415: aload_2
/*    */     //   416: astore_1
/*    */     //   417: goto -> 406
/*    */     //   420: aload_0
/*    */     //   421: aload_1
/*    */     //   422: dup
/*    */     //   423: dup
/*    */     //   424: invokevirtual RS : ()I
/*    */     //   427: istore_0
/*    */     //   428: invokevirtual qF : ()I
/*    */     //   431: iconst_2
/*    */     //   432: idiv
/*    */     //   433: iload_0
/*    */     //   434: iadd
/*    */     //   435: istore_0
/*    */     //   436: invokevirtual e3 : ()I
/*    */     //   439: istore_2
/*    */     //   440: iload_0
/*    */     //   441: aload_1
/*    */     //   442: invokevirtual Hy : ()I
/*    */     //   445: iconst_2
/*    */     //   446: idiv
/*    */     //   447: iload_2
/*    */     //   448: iadd
/*    */     //   449: invokevirtual lf0 : (II)V
/*    */     //   452: iconst_1
/*    */     //   453: ireturn
/*    */     //   454: aload_1
/*    */     //   455: getfield GG0 : I
/*    */     //   458: getstatic f/BM.lc : Lf/BM;
/*    */     //   461: invokestatic J20 : (ILf/BM;)Z
/*    */     //   464: ifeq -> 513
/*    */     //   467: aload_0
/*    */     //   468: invokevirtual e9 : ()Lf/JG0;
/*    */     //   471: instanceof f/of
/*    */     //   474: ifeq -> 499
/*    */     //   477: aload_1
/*    */     //   478: getfield GG0 : I
/*    */     //   481: sipush #256
/*    */     //   484: iand
/*    */     //   485: ifeq -> 493
/*    */     //   488: iconst_1
/*    */     //   489: istore_2
/*    */     //   490: goto -> 495
/*    */     //   493: iconst_0
/*    */     //   494: istore_2
/*    */     //   495: iload_2
/*    */     //   496: ifeq -> 513
/*    */     //   499: aload_0
/*    */     //   500: aload_1
/*    */     //   501: invokespecial i2 : (Lf/oa0;)Z
/*    */     //   504: ifne -> 511
/*    */     //   507: aload_0
/*    */     //   508: invokevirtual close : ()V
/*    */     //   511: iconst_1
/*    */     //   512: ireturn
/*    */     //   513: aload_0
/*    */     //   514: aload_1
/*    */     //   515: invokespecial i2 : (Lf/oa0;)Z
/*    */     //   518: ireturn
/*    */     // Line number table:
/*    */     //   Java source line number -> byte code offset
/*    */     //   #1	-> 1
/*    */     //   #2	-> 4
/*    */     //   #3	-> 11
/*    */     //   #4	-> 28
/*    */     //   #5	-> 31
/*    */     //   #6	-> 47
/*    */     //   #7	-> 50
/*    */     //   #8	-> 53
/*    */     //   #9	-> 93
/*    */     //   #10	-> 96
/*    */     //   #11	-> 111
/*    */     //   #12	-> 114
/*    */     //   #13	-> 120
/*    */     //   #14	-> 124
/*    */     //   #15	-> 127
/*    */     //   #16	-> 133
/*    */     //   #17	-> 136
/*    */     //   #18	-> 158
/*    */     //   #19	-> 162
/*    */     //   #20	-> 180
/*    */     //   #21	-> 183
/*    */     //   #22	-> 205
/*    */     //   #23	-> 209
/*    */     //   #24	-> 234
/*    */     //   #25	-> 237
/*    */     //   #26	-> 247
/*    */     //   #27	-> 277
/*    */     //   #28	-> 280
/*    */     //   #29	-> 283
/*    */     //   #30	-> 291
/*    */     //   #31	-> 295
/*    */     //   #32	-> 304
/*    */     //   #33	-> 307
/*    */     //   #34	-> 316
/*    */     //   #35	-> 319
/*    */     //   #36	-> 329
/*    */     //   #37	-> 332
/*    */     //   #38	-> 342
/*    */     //   #39	-> 345
/*    */     //   #40	-> 355
/*    */     //   #41	-> 358
/*    */     //   #42	-> 368
/*    */     //   #43	-> 371
/*    */     //   #44	-> 396
/*    */     //   #45	-> 407
/*    */     //   #46	-> 424
/*    */     //   #47	-> 455
/*    */     //   #48	-> 458
/*    */     //   #49	-> 478
/*    */     //   #50	-> 501
/*    */   }
/*    */   
/*    */   public final void lf0(int paramInt1, int paramInt2) {
/*    */     if (this.U40 != null) {
/*    */       JG0 jG0;
/*    */       boolean bool;
/*    */       if (!(bool = jG0 = js.vu0.MH0.Va0(paramInt1, paramInt2) instanceof gf))
/*    */         this.PP = null; 
/*    */       Qv0 qv0;
/*    */       paramInt2 = paramInt1 - (qv0 = this.U40).r6;
/*    */       int i = paramInt2 - qv0.jo;
/*    */       for (Iterator<Qv0> iterator = this.Lpt8.iterator(); iterator.hasNext(); ) {
/*    */         Qv0 qv01;
/*    */         int j = (qv01 = iterator.next()).r6 + paramInt2;
/*    */         int k = (iterator.next()).jo + i;
/*    */         JG0 jG01, jG02;
/*    */         if (!(jG01 = js.vu0.MH0.Va0(j, k) instanceof Qv0) && jG02 = jG01.fr0 instanceof Qv0)
/*    */           jG01 = jG02; 
/*    */         if (jG01 instanceof Qv0) {
/*    */           qv01.Ba0 = (Qv0)jG01;
/*    */         } else {
/*    */           if (jG01 instanceof n3)
/*    */             continue; 
/*    */           qv01.Ba0 = null;
/*    */         } 
/*    */         if (qv01.Ba0 != null) {
/*    */           qv01.O.gf0(Qv0.GZ, true);
/*    */           qv01.O.gf0(Qv0.iX, false);
/*    */         } 
/*    */       } 
/*    */       if (bool) {
/*    */         gf gf1 = (gf)jG0;
/*    */         if (this.PP != gf1) {
/*    */           Yw0 yw0;
/*    */           if ((yw0 = this.oq) != null)
/*    */             yw0.uw0(); 
/*    */           this(this, gf1);
/*    */           this.oq = new Yw0();
/*    */           HC.k6().S(yw0, 0.5F);
/*    */         } 
/*    */         Iterator iterator1;
/*    */         for (this.PP = gf1, paramInt2 = 0, iterator1 = this.Lpt8.iterator(); iterator1.hasNext(); ) {
/*    */           ((Qv0)iterator1.next()).Ba0 = lg(gf1.V0.Zb, paramInt2);
/*    */           paramInt2++;
/*    */         } 
/*    */       } 
/*    */     } 
/*    */   }
/*    */   
/*    */   public final void wL0(int paramInt1, int paramInt2) {
/*    */     Yw0 yw0;
/*    */     if ((yw0 = this.oq) != null)
/*    */       yw0.uw0(); 
/*    */     if (this.U40 != null) {
/*    */       lf0(paramInt1, paramInt2);
/*    */       if (km.MR == null) {
/*    */         Qv0 qv0;
/*    */         List<Qv0> list;
/*    */         Iterator<Qv0> iterator1;
/*    */         for (yw0 = null, iterator1 = this.Lpt8.iterator(); iterator1.hasNext();) {
/*    */           if ((qv01 = iterator1.next()).public() != null && qv01.Ba0 != null && (yw0 == null || ((Qv0)yw0).Ba0.fH0() > qv01.Ba0.fH0()))
/*    */             qv0 = qv01; 
/*    */         } 
/*    */         if (this.Lpt8.size() > 1 && qv0 != null && qv0.lK() == aq0.XJ0 && qv0.Ba0.lK() == aq0.LI) {
/*    */           Collections.sort(new ArrayList<>(this.Lpt8));
/*    */           short s = qv0.Ba0.fH0();
/*    */           this();
/*    */           for (Iterator<Comparable> iterator2 = (new ArrayList<>(this.Lpt8)).iterator(); iterator2.hasNext(); ) {
/*    */             Qv0 qv01, qv02;
/*    */             if ((qv02 = (Qv0)iterator2.next()).public() == null || s >= 6)
/*    */               continue; 
/*    */             short s2 = (short)(s + 1);
/*    */             NR nR;
/*    */             (nR = this.oP).getClass();
/*    */             if (s < 0 || s > 6) {
/*    */               qv01 = null;
/*    */             } else {
/*    */               qv01 = nR.FB0[qv01];
/*    */             } 
/*    */             qv02.Ba0 = qv01;
/*    */             list.add(qv02);
/*    */             short s1 = s2;
/*    */           } 
/*    */         } else {
/*    */           list = (List)this.Lpt8.stream().filter(gO::Oj0).sorted(gO::SK).collect(Collectors.toList());
/*    */         } 
/*    */         Qv0[] arrayOfQv01, arrayOfQv02;
/*    */         byte b;
/*    */         for (arrayOfQv01 = new Qv0[list.size()], arrayOfQv02 = new Qv0[list.size()], b = 0; b < list.size(); ) {
/*    */           arrayOfQv01[b] = qv01;
/*    */           Qv0 qv01;
/*    */           arrayOfQv02[b] = (qv01 = list.get(b)).Ba0;
/*    */           b++;
/*    */         } 
/*    */         km.u4.Zt(arrayOfQv01, arrayOfQv02);
/*    */       } 
/*    */       JG0 jG0;
/*    */       if (jG0 = (js.vu0.Va0(paramInt1, paramInt2)).fr0 instanceof of) {
/*    */         JG0 jG01;
/*    */         if ((jG01 = jG0.fr0.fr0).fr0 instanceof wu) {
/*    */           this.Lpt8.stream().map(Qv0::public).forEach(jG0::XK);
/*    */         } else if (jG01 instanceof kC0) {
/*    */           this.Lpt8.stream().map(Qv0::public).forEach(jG0::po0);
/*    */         } 
/*    */       } 
/*    */       for (Iterator<Qv0> iterator = this.Lpt8.iterator(); iterator.hasNext(); ) {
/*    */         Qv0 qv01;
/*    */         boolean bool = false;
/*    */         (iterator.next()).O.gf0(Qv0.MZ, bool);
/*    */         Qv0 qv02;
/*    */         if ((qv02 = (iterator.next()).Ba0) != null && qv02.y1())
/*    */           qv01.Ba0.zf(qv01.public()); 
/*    */         qv01.Ba0 = null;
/*    */       } 
/*    */     } 
/*    */     this.U40 = null;
/*    */     this.Lpt8.clear();
/*    */   }
/*    */   
/*    */   public final nJ0[] ZK0() {
/*    */     return this.fH;
/*    */   }
/*    */   
/*    */   public final boolean gO() {
/*    */     ge0 ge01;
/*    */     if ((ge01 = this.lp0) == null)
/*    */       return false; 
/*    */     return this.TG0.nm0();
/*    */   }
/*    */   
/*    */   public final void Xu() {
/*    */     e8().zn0(false);
/*    */     Zq zq;
/*    */     if ((zq = e8().M50()).p3()) {
/*    */       zq.O.gf0(Qv0.mk0, this.lp0.TG0.nm0());
/*    */       zq.O.gf0(Qv0.Co, false);
/*    */     } 
/*    */   }
/*    */   
/*    */   public final void uq() {
/*    */     if (this.WG0 != null)
/*    */       return; 
/*    */     Runnable runnable1 = () -> Jj(true), runnable2 = () -> Jj(false);
/*    */     lg0 lg0 = T80.N2(this.V3, false, this, runnable2);
/*    */     (new YA0()).Dv0.S7(this).kp0();
/*    */     (new YA0()).Dv0.S7(this).i40();
/*    */     (new YA0()).Dv0.S7(this).Xs0().AuX(7.0F);
/*    */     this.WG0 = new YA0();
/*    */   }
/*    */   
/*    */   public final void close() {
/*    */     if (this.iE0) {
/*    */       Jj(false);
/*    */       return;
/*    */     } 
/*    */     pA pA;
/*    */     if ((pA = js.vu0.MH0).QI0 == null && pA.AL == null)
/*    */       km.u4.e20.W3(new nC()); 
/*    */     js.vu0.KE();
/*    */     boolean bool = false;
/*    */     (pA = js.vu0.MH0).getClass();
/*    */     UB0.Kg0.fN(new NP(pA, bool));
/*    */     UB0.Kg0.fN(() -> {
/*    */           kg0 kg01;
/*    */           if ((kg01 = this.sK0) != null) {
/*    */             kg01.pf0();
/*    */             this.sK0.dispose();
/*    */             this.sK0 = null;
/*    */           } 
/*    */           UA0 uA0;
/*    */           if ((uA0 = this.NV) != null)
/*    */             dispose(); 
/*    */         });
/*    */   }
/*    */   
/*    */   public final void aF0() {
/*    */     uq();
/*    */     gx();
/*    */     Un un = this.Ki;
/*    */     si(this, Ub());
/*    */     YA0 yA0 = this.WG0;
/*    */     si(this, Ub());
/*    */     VA0.c90(this.WG0.lPt3(0).lPt3(3));
/*    */     this.iE0 = true;
/*    */   }
/*    */   
/*    */   public final ZE JU() {
/*    */     // Byte code:
/*    */     //   0: new f/ZE
/*    */     //   3: dup
/*    */     //   4: dup
/*    */     //   5: astore_1
/*    */     //   6: aload_0
/*    */     //   7: invokespecial <init> : (Lf/gO;)V
/*    */     //   10: new f/of
/*    */     //   13: dup
/*    */     //   14: astore_2
/*    */     //   15: aload_0
/*    */     //   16: aload_2
/*    */     //   17: aload_0
/*    */     //   18: aload_2
/*    */     //   19: dup
/*    */     //   20: aconst_null
/*    */     //   21: invokespecial <init> : (Lf/Sa0;)V
/*    */     //   24: putfield ok0 : Lf/of;
/*    */     //   27: iconst_1
/*    */     //   28: putfield n00 : Z
/*    */     //   31: <illegal opcode> SX : (Lf/gO;)Lf/a70;
/*    */     //   36: invokevirtual JD0 : (Lf/a70;)V
/*    */     //   39: new f/Un
/*    */     //   42: dup
/*    */     //   43: astore_2
/*    */     //   44: aload_0
/*    */     //   45: aload_2
/*    */     //   46: dup
/*    */     //   47: dup
/*    */     //   48: dup2
/*    */     //   49: ldc_w '☒'
/*    */     //   52: invokespecial <init> : (Ljava/lang/String;)V
/*    */     //   55: ldc_w 'button-symbol'
/*    */     //   58: invokevirtual Xu : (Ljava/lang/String;)V
/*    */     //   61: sipush #8036
/*    */     //   64: invokestatic OH0 : (I)Ljava/lang/String;
/*    */     //   67: putfield z4 : Ljava/lang/Object;
/*    */     //   70: invokevirtual zn : ()V
/*    */     //   73: bipush #100
/*    */     //   75: putfield jl : I
/*    */     //   78: <illegal opcode> run : (Lf/gO;)Ljava/lang/Runnable;
/*    */     //   83: invokevirtual tW : (Ljava/lang/Runnable;)V
/*    */     //   86: new f/Un
/*    */     //   89: dup
/*    */     //   90: astore_3
/*    */     //   91: aload_0
/*    */     //   92: aload_3
/*    */     //   93: sipush #8010
/*    */     //   96: invokestatic OH0 : (I)Ljava/lang/String;
/*    */     //   99: invokespecial <init> : (Ljava/lang/String;)V
/*    */     //   102: <illegal opcode> run : (Lf/gO;)Ljava/lang/Runnable;
/*    */     //   107: invokevirtual tW : (Ljava/lang/Runnable;)V
/*    */     //   110: new f/ge0
/*    */     //   113: dup
/*    */     //   114: astore #4
/*    */     //   116: aload_0
/*    */     //   117: dup
/*    */     //   118: aload #4
/*    */     //   120: dup
/*    */     //   121: invokespecial <init> : ()V
/*    */     //   124: putfield ek : Lf/ge0;
/*    */     //   127: <illegal opcode> run : (Lf/gO;)Ljava/lang/Runnable;
/*    */     //   132: invokevirtual tW : (Ljava/lang/Runnable;)V
/*    */     //   135: new f/Un
/*    */     //   138: dup
/*    */     //   139: astore #4
/*    */     //   141: aload_0
/*    */     //   142: aload #4
/*    */     //   144: dup
/*    */     //   145: sipush #2315
/*    */     //   148: invokestatic OH0 : (I)Ljava/lang/String;
/*    */     //   151: invokespecial <init> : (Ljava/lang/String;)V
/*    */     //   154: <illegal opcode> run : (Lf/gO;Lf/Un;)Ljava/lang/Runnable;
/*    */     //   159: invokevirtual tW : (Ljava/lang/Runnable;)V
/*    */     //   162: new f/ge0
/*    */     //   165: dup
/*    */     //   166: astore #5
/*    */     //   168: aload_0
/*    */     //   169: dup
/*    */     //   170: aload #5
/*    */     //   172: dup
/*    */     //   173: invokespecial <init> : ()V
/*    */     //   176: putfield lp0 : Lf/ge0;
/*    */     //   179: <illegal opcode> run : (Lf/gO;)Ljava/lang/Runnable;
/*    */     //   184: invokevirtual tW : (Ljava/lang/Runnable;)V
/*    */     //   187: getfield Dv0 : Lf/SA;
/*    */     //   190: astore #5
/*    */     //   192: invokestatic XU : ()Z
/*    */     //   195: ifeq -> 359
/*    */     //   198: aload #5
/*    */     //   200: aload_2
/*    */     //   201: aload #5
/*    */     //   203: aload_0
/*    */     //   204: aload #5
/*    */     //   206: aload_3
/*    */     //   207: aload #5
/*    */     //   209: dup
/*    */     //   210: aload_0
/*    */     //   211: aload #5
/*    */     //   213: aload_0
/*    */     //   214: aload #5
/*    */     //   216: aload #4
/*    */     //   218: invokevirtual S7 : (Ljava/lang/Object;)Lf/nJ0;
/*    */     //   221: invokevirtual fu : ()Lf/nJ0;
/*    */     //   224: ldc_w 10.0
/*    */     //   227: invokevirtual J80 : (F)Lf/nJ0;
/*    */     //   230: ldc_w 10.0
/*    */     //   233: invokevirtual sg : (F)Lf/nJ0;
/*    */     //   236: pop
/*    */     //   237: getfield lp0 : Lf/ge0;
/*    */     //   240: new f/dQ
/*    */     //   243: dup
/*    */     //   244: dup
/*    */     //   245: sipush #2314
/*    */     //   248: invokestatic OH0 : (I)Ljava/lang/String;
/*    */     //   251: astore_2
/*    */     //   252: invokespecial <init> : ()V
/*    */     //   255: aload_2
/*    */     //   256: invokevirtual E1 : (Ljava/lang/String;)V
/*    */     //   259: invokestatic SI0 : (Lf/Ap;Lf/dQ;)Lf/vy;
/*    */     //   262: invokevirtual S7 : (Ljava/lang/Object;)Lf/nJ0;
/*    */     //   265: ldc_w 5.0
/*    */     //   268: invokevirtual sg : (F)Lf/nJ0;
/*    */     //   271: pop
/*    */     //   272: getfield ek : Lf/ge0;
/*    */     //   275: new f/dQ
/*    */     //   278: dup
/*    */     //   279: dup
/*    */     //   280: sipush #2316
/*    */     //   283: invokestatic OH0 : (I)Ljava/lang/String;
/*    */     //   286: astore_2
/*    */     //   287: invokespecial <init> : ()V
/*    */     //   290: aload_2
/*    */     //   291: invokevirtual E1 : (Ljava/lang/String;)V
/*    */     //   294: invokestatic SI0 : (Lf/Ap;Lf/dQ;)Lf/vy;
/*    */     //   297: invokevirtual S7 : (Ljava/lang/Object;)Lf/nJ0;
/*    */     //   300: pop
/*    */     //   301: new f/JG0
/*    */     //   304: dup
/*    */     //   305: invokespecial <init> : ()V
/*    */     //   308: invokevirtual S7 : (Ljava/lang/Object;)Lf/nJ0;
/*    */     //   311: dup
/*    */     //   312: invokevirtual Kw : ()Lf/nJ0;
/*    */     //   315: pop
/*    */     //   316: invokevirtual x70 : ()Lf/nJ0;
/*    */     //   319: pop
/*    */     //   320: invokevirtual S7 : (Ljava/lang/Object;)Lf/nJ0;
/*    */     //   323: ldc_w 10.0
/*    */     //   326: invokevirtual sg : (F)Lf/nJ0;
/*    */     //   329: pop
/*    */     //   330: getfield ok0 : Lf/of;
/*    */     //   333: invokevirtual S7 : (Ljava/lang/Object;)Lf/nJ0;
/*    */     //   336: ldc_w 10.0
/*    */     //   339: invokevirtual sg : (F)Lf/nJ0;
/*    */     //   342: pop
/*    */     //   343: invokevirtual S7 : (Ljava/lang/Object;)Lf/nJ0;
/*    */     //   346: invokevirtual ti0 : ()Lf/nJ0;
/*    */     //   349: ldc_w 10.0
/*    */     //   352: invokevirtual sg : (F)Lf/nJ0;
/*    */     //   355: pop
/*    */     //   356: goto -> 459
/*    */     //   359: aload #5
/*    */     //   361: aload_3
/*    */     //   362: aload #5
/*    */     //   364: aload_2
/*    */     //   365: aload #5
/*    */     //   367: aload_0
/*    */     //   368: aload #5
/*    */     //   370: dup
/*    */     //   371: dup
/*    */     //   372: aload_0
/*    */     //   373: aload #5
/*    */     //   375: dup
/*    */     //   376: aload_0
/*    */     //   377: aload #5
/*    */     //   379: aload #4
/*    */     //   381: aload #5
/*    */     //   383: getfield RT : Lf/nJ0;
/*    */     //   386: ldc_w 5.0
/*    */     //   389: invokevirtual sg : (F)Lf/nJ0;
/*    */     //   392: pop
/*    */     //   393: invokevirtual S7 : (Ljava/lang/Object;)Lf/nJ0;
/*    */     //   396: pop
/*    */     //   397: getfield lp0 : Lf/ge0;
/*    */     //   400: invokevirtual S7 : (Ljava/lang/Object;)Lf/nJ0;
/*    */     //   403: pop
/*    */     //   404: sipush #2314
/*    */     //   407: invokevirtual mv0 : (I)Lf/nJ0;
/*    */     //   410: pop
/*    */     //   411: getfield ek : Lf/ge0;
/*    */     //   414: invokevirtual S7 : (Ljava/lang/Object;)Lf/nJ0;
/*    */     //   417: pop
/*    */     //   418: sipush #2316
/*    */     //   421: invokevirtual mv0 : (I)Lf/nJ0;
/*    */     //   424: pop
/*    */     //   425: new f/JG0
/*    */     //   428: dup
/*    */     //   429: invokespecial <init> : ()V
/*    */     //   432: invokevirtual S7 : (Ljava/lang/Object;)Lf/nJ0;
/*    */     //   435: dup
/*    */     //   436: invokevirtual Kw : ()Lf/nJ0;
/*    */     //   439: pop
/*    */     //   440: invokevirtual x70 : ()Lf/nJ0;
/*    */     //   443: pop
/*    */     //   444: getfield ok0 : Lf/of;
/*    */     //   447: invokevirtual S7 : (Ljava/lang/Object;)Lf/nJ0;
/*    */     //   450: pop
/*    */     //   451: invokevirtual S7 : (Ljava/lang/Object;)Lf/nJ0;
/*    */     //   454: pop
/*    */     //   455: invokevirtual S7 : (Ljava/lang/Object;)Lf/nJ0;
/*    */     //   458: pop
/*    */     //   459: aload_1
/*    */     //   460: aload_0
/*    */     //   461: aload_1
/*    */     //   462: iconst_1
/*    */     //   463: putfield WA0 : Z
/*    */     //   466: aload_1
/*    */     //   467: putfield M50 : Lf/ZE;
/*    */     //   470: areturn
/*    */     // Line number table:
/*    */     //   Java source line number -> byte code offset
/*    */     //   #1	-> 21
/*    */     //   #2	-> 24
/*    */     //   #3	-> 28
/*    */     //   #4	-> 31
/*    */     //   #5	-> 67
/*    */     //   #6	-> 75
/*    */     //   #7	-> 78
/*    */     //   #8	-> 252
/*    */     //   #9	-> 259
/*    */     //   #10	-> 287
/*    */     //   #11	-> 294
/*    */     //   #12	-> 312
/*    */     //   #13	-> 320
/*    */     //   #14	-> 383
/*    */     //   #15	-> 389
/*    */     //   #16	-> 436
/*    */     //   #17	-> 444
/*    */     //   #18	-> 463
/*    */     //   #19	-> 467
/*    */   }
/*    */   
/*    */   public final Zq lg(int paramInt1, int paramInt2) {
/*    */     n3[] arrayOfN3;
/*    */     if (paramInt1 < 0 || paramInt1 > (arrayOfN3 = this.Gu0).length)
/*    */       return null; 
/*    */     byte b1 = 0;
/*    */     Zq[] arrayOfZq;
/*    */     int i = (arrayOfZq = this[paramInt1].MY()).length;
/*    */     for (byte b2 = 0; b2 < i; b2++) {
/*    */       Zq zq;
/*    */       if ((zq = arrayOfZq[b2]).public() == null) {
/*    */         if (paramInt2 == b1)
/*    */           return zq; 
/*    */         b1++;
/*    */       } 
/*    */     } 
/*    */     return null;
/*    */   }
/*    */   
/*    */   public final void class(Qv0 paramQv0, List paramList) {
/*    */     this.Lpt8.addAll(paramList);
/*    */     this.Lpt8.add(paramQv0);
/*    */     for (Iterator iterator = this.Lpt8.iterator(); iterator.hasNext(); ) {
/*    */       boolean bool = true;
/*    */       ((Qv0)iterator.next()).O.gf0(Qv0.MZ, bool);
/*    */       ((Qv0)iterator.next()).r6 = ((Qv0)iterator.next()).Kd;
/*    */       ((Qv0)iterator.next()).jo = ((Qv0)iterator.next()).er0;
/*    */     } 
/*    */     this.U40 = paramQv0;
/*    */     if (this.Lpt8.size() == 1)
/*    */       ee(paramQv0.public()); 
/*    */   } }


/* Location:              /Users/vnnsnnt/Documents/Codespace/JavaWorkspace/RedTrainer/src/main/java/org/trainer/client/PokeMMO.jar!/f/gO.class
 * Java compiler version: 8 (52.0)
 * JD-Core Version:       1.1.3
 */