/*  1 */ package f;public final class GV extends Qa0 implements r60 { public final byte NL0; public final Ip f10; public F7 xb0; public final Qv0[] TG0; public final dQ[] h10; public final vF0[] FD0; public final dQ[][] oD0; public final dQ[][] aS; public final dQ[] Q00; private void G20(hR paramhR) { this.oD0[1][paramhR.It0]
/*  2 */       .cZ(); } public final dQ[][] vs; public final vF0[] TF0; public final dQ[] R90; public Un gZ; public int I80; public int nb0; public final Un[][] xe0; public boolean av; public GV(byte paramByte) { super(km.XU()); Ip ip; this.TG0 = new Qv0[3]; this.h10 = new dQ[3]; this.FD0 = new vF0[3]; this.oD0 = new dQ[3][6]; this.aS = new dQ[3][4]; this.Q00 = new dQ[3]; this.vs = new dQ[3][6]; this.TF0 = new vF0[3]; this.R90 = new dQ[3]; this.I80 = 0; this.nb0 = 0; this.av = false; this.NL0 = paramByte; TG0(this::KG0); Xu("breed-window"); Lo(Ml0.OH0(2525)); EP(1); paramByte = 0; Qv0[] arrayOfQv0; while (paramByte < (arrayOfQv0 = this.TG0).length) { G9 g9; vF0 vF02; xo0 xo03; vF0 vF01; xo0 xo02; xo0 xo01; boolean bool; this(paramByte); arrayOfQv0[paramByte] = g9; this.TG0[paramByte].hC(true); Qv0 qv0 = this.TG0[paramByte]; if (paramByte != 1) { bool = true; } else { bool = false; }  qv0.sk0(bool); if (paramByte != 1) { if (km.XU()) this.TG0[paramByte].tW(() -> lPT5(paramShort));  this.TG0[paramByte].L1(() -> lPT5(paramShort)); }  this(); this.TF0[paramByte] = vF02; this.TF0[paramByte].ZH0().zT(56, 2); this.TF0[paramByte].Xu("held-item"); if (km.XU()) { this.TF0[paramByte].ZH0().Ii0(2.0F); this.TF0[paramByte].ZH0().zT(44, 0); }  this(); this.h10[paramByte] = xo03; this.h10[paramByte].Xu("shared-value"); this(); this.FD0[paramByte] = vF01; this(); this.Q00[paramByte] = xo02; this.Q00[paramByte].Xu("shared-value"); this.Q00[paramByte].Pb0(150); byte b1; dQ[] arrayOfDQ; for (b1 = 0; b1 < (arrayOfDQ = this.oD0[paramByte]).length; b1++) { xo0 xo0; this(); arrayOfDQ[b1] = xo0; this.oD0[paramByte][b1].Xu("iv-value"); this.oD0[paramByte][b1].Pb0(150); }  for (b1 = 0; b1 < (arrayOfDQ = this.aS[paramByte]).length; b1++) { xo0 xo0; this(); arrayOfDQ[b1] = xo0; this.aS[paramByte][b1].Xu("shared-value"); this.aS[paramByte][b1].Pb0(150); }  this(); this.R90[paramByte] = xo01; this.R90[paramByte].Xu("shared-value"); this.R90[paramByte].Pb0(150); short s = (short)(paramByte + 1); }  this(); this.f10 = ip; U90[] arrayOfU901 = new U90[3]; U90[] arrayOfU902 = new U90[3]; for (byte b = 0; b < this.TG0.length; b++) { cr0 cr0 = this.f10.d7(); g0 g0 = this.f10.mE0(); dQ[] arrayOfDQ; for (byte b1 = 0; b1 < (arrayOfDQ = this.vs[b]).length; b1++) { xo0 xo0; byte b2; this(Ml0.OH0(b1 + 1830)); arrayOfDQ[b1] = xo0; this.vs[b][b1].Xu("iv-slot"); cr0.ee0(this.f10.mE0().Mg(new JG0[] { this.vs[b][b1], this.oD0[b][b1] })); cr0 cr01 = this.f10.d7(); if (b == 1) { b2 = 16; } else { b2 = 20; }  g0.ee0(cr01.Aq(b2).Mg(new JG0[] { this.vs[b][b1], this.oD0[b][b1] })); }  U90 u90 = this.f10.d7().ee0(this.f10.mE0().Mg(new JG0[] { this.TG0[b] })).ee0(this.f10.d7().Mg(new JG0[] { this.h10[b], this.FD0[b] })).Aq(7).ee0(cr0).Aq(7).Mg((JG0[])this.aS[b]).Aq(7).Ya(this.Q00[b]).Aq(7).Ya(this.R90[b]); if (b != 1) u90.Aq(7).Ya(this.TF0[b]);  arrayOfU902[b] = u90 = this.f10.mE0().ee0(this.f10.d7().Em0().Mg(new JG0[] { this.TG0[b] }).Em0()).ee0(this.f10.mE0().Mg(new JG0[] { this.h10[b], this.FD0[b] })).ee0(this.f10.d7().Em0().ee0(g0).Em0()).Mg((JG0[])this.aS[b]).Ya(this.Q00[b]).Ya(this.R90[b]); if (b != 1) u90.ee0(this.f10.d7().Em0().Mg(new JG0[] { this.TF0[b] }).Em0());  if (b == 1) { (this.gZ = new Un()).wI0(false); this.gZ.tW(this::lJ0); arrayOfU901[b].l9(7).Ya(this.gZ).Em0(); arrayOfU902[b].Ya(this.gZ); }  }  this.f10.WN(this.f10.mE0().cOM8(arrayOfU901)); this.f10.rK0(this.f10.d7().ee0(arrayOfU902[0]).Aq(30).ee0(arrayOfU902[1]).Aq(30).ee0(arrayOfU902[2])); J8(this.f10); arrayOfUn[0] = this.TG0[0]; Un[] arrayOfUn; (arrayOfUn = new Un[2])[1] = this.TG0[2]; (new Un[2][])[0] = arrayOfUn; (arrayOfUn = new Un[1])[0] = this.gZ; this.xe0 = new Un[][] { null, arrayOfUn }; } private void XS(j40 paramj40, short paramShort) { if (Cb(paramShort, true, paramj40)) { this.TG0[paramShort].zf(paramj40); update(); }  F7 f7; if ((f7 = this.xb0) != null) tp0();  } private void b4() { byte[] arrayOfByte = new byte[2]; j40 j40; if ((j40 = this.TG0[0].public()) == null) { KG0(); return; }  arrayOfByte[0] = (byte)j40.Zs.Tl0;
/*  3 */     if ((j40 = this.TG0[2].public()) == null) { KG0(); return; }  arrayOfByte[
/*    */         
/*  5 */         1] = (byte)j40.Zs.Tl0;
/*  6 */     km.u4.N7(this.NL0, arrayOfByte); pA pA;
/*    */     GV gV;
/*  8 */     if ((gV = (pA = pA.Dg0).cl) != null) { gV
/*  9 */         .ra0(); this.cl = null; }  } public final void pv0() { if (this.TG0[0].public() != null) { this.TG0[2].wI0(true); js.vu0.j90(this.TG0[2], Ml0.OH0(2527), et.F30); UB0.Kg0.fN(() -> sJ(0, 1)); } else { VA0.c90(this.TG0[0]); js.vu0.j90(this.TG0[0], Ml0.OH0(2526), et.F30); }  if (this.TG0[2].public() != null) { js.vu0.KE(); arrayOfInt[0] = (this.TG0[0].public()).Jg; int[] arrayOfInt; (arrayOfInt = new int[2])[1] = (this.TG0[2].public()).Jg;
/*    */       
/* 11 */       km.u4.e20
/* 12 */         .W3(new bq0(arrayOfInt));
/* 13 */       this.TG0[1].zf(null); r10(1, false); }  } public final void XJ(String paramString) { if (paramString == null || paramString.isEmpty()) { this.gZ.s6(Ml0.OH0(2528).trim()); un = this.gZ; if (!(paramString = "button").equals(this.cl)) { Xu(paramString); cZ(); }  return; }  if (km.XU()) paramString = paramString.trim();  ((GV)super).h10[1].E1(paramString); ((GV)super).h10[1].wI0(true); ((GV)super).gZ.s6(""); Un un = ((GV)super).gZ; if (!(paramString = "min-button").equals(this.cl)) { Xu(paramString); cZ(); }  } public final void r10(int paramInt, boolean paramBoolean) { if (paramInt > 0 || paramBoolean) this.TG0[paramInt].wI0(paramBoolean);  this.h10[paramInt].wI0(paramBoolean); this.Q00[paramInt].wI0(paramBoolean); if (!paramBoolean) this.Q00[paramInt].Gq0(null);  this.R90[paramInt].wI0(paramBoolean); if (!paramBoolean) this.R90[paramInt].Gq0(null);  byte b; for (b = 0; b < 6; b++) { this.vs[paramInt][b].wI0(paramBoolean); this.oD0[paramInt][b].wI0(paramBoolean); if (!paramBoolean) this.oD0[paramInt][b].Gq0(null);  }  for (b = 0; b < 4; b++) { this.aS[paramInt][b].wI0(paramBoolean); if (!paramBoolean) this.aS[paramInt][b].Gq0(null);  }  this.TF0[paramInt].wI0(paramBoolean); this.gZ.wI0(paramBoolean); if (paramInt == 1 && paramBoolean) XJ(null);  } public final void KG0() { km.u4.lx0(this.NL0, (byte)0); pA pA; GV gV; if ((gV = (pA = pA.Dg0).cl) != null) { gV.ra0(); this.cl = null; }  } public final void lJ0() { String str; j40 j401 = this.TG0[0].public(), j403 = this.TG0[2].public(); j40 j402; if ((j402 = this.TG0[1].public()) == null || j401 == null || j403 == null) return;  byte b2 = j403.Zs.eH; byte b1; if ((b1 = j402.Zs.eH) != j401.Zs.eH || b1 != b2) { boolean bool1; StringBuilder stringBuilder; boolean bool2; this(); if (!j402.Zs.iL() && (j401.Zs.iL() || j403.Zs.iL())) { b2 = 1; } else { b2 = 0; }
/* 14 */        if (!j402.Zs.da() && (j401
/* 15 */         .Zs.da() || j403
/* 16 */         .Zs.da())) { bool2 = true; } else { bool2 = false; }
/*    */       
/* 18 */       if (!j402.Zs.wl() && (j401
/* 19 */         .Zs
/* 20 */         .wl() || j403
/* 21 */         .Zs
/* 22 */         .wl())) { bool1 = true; } else { bool1 = false; }  if (b2 == 0 && !bool2 && !bool1) { pf(); return; }  if (b2 != 0) stringBuilder.append("- ").append(Ml0.OH0(2521)).append("\n");  if (bool2) stringBuilder.append("- ").append(Ml0.OH0(2522)).append("\n");  if (bool1) stringBuilder.append("- ").append(Ml0.OH0(2523)).append("\n");
/*    */       
/* 24 */       this[0] = j402.m(); String[] arrayOfString; (arrayOfString = new String[2])[1] = stringBuilder.toString(); str = Ml0.sB(2524, this); Runnable runnable = this::pf; Un un = this.gZ; (new h70(this, runnable, un))
/* 25 */         .sD0 = true;
/* 26 */       js.vu0.uh(new h70(this, runnable, un)); return; }  super.pf(); } public final void pf() { String str = Ml0.OH0(16779082); Runnable runnable = this::b4; Un un = this.gZ; js.vu0.uh(new h70(this, runnable, un)); } public final void LM(throws paramthrows) { super.LM(paramthrows); for (byte b = 0; b < this.TG0.length; b++) r10(b, false);  } public final void IG0() { if (this.TG0[0].public() == null) pv0();  } public final void ED0(throws paramthrows) { super.ED0(paramthrows); js.vu0.KE(); } public final void lPT5(short paramShort) { // Byte code:
/*    */     //   0: aload_0
/*    */     //   1: getfield xb0 : Lf/F7;
/*    */     //   4: dup
/*    */     //   5: astore_2
/*    */     //   6: ifnull -> 18
/*    */     //   9: aload_0
/*    */     //   10: aload_2
/*    */     //   11: invokevirtual tp0 : ()V
/*    */     //   14: aconst_null
/*    */     //   15: putfield xb0 : Lf/F7;
/*    */     //   18: new f/B3
/*    */     //   21: dup
/*    */     //   22: astore_2
/*    */     //   23: invokespecial <init> : ()V
/*    */     //   26: iconst_0
/*    */     //   27: istore_3
/*    */     //   28: iload_3
/*    */     //   29: getstatic f/km.u4 : Lf/R8;
/*    */     //   32: getstatic f/aq0.LI : Lf/aq0;
/*    */     //   35: dup
/*    */     //   36: astore #4
/*    */     //   38: invokevirtual s40 : (Lf/aq0;)Lf/Uc0;
/*    */     //   41: invokevirtual oq : ()I
/*    */     //   44: if_icmpge -> 270
/*    */     //   47: getstatic f/km.u4 : Lf/R8;
/*    */     //   50: aload #4
/*    */     //   52: invokevirtual s40 : (Lf/aq0;)Lf/Uc0;
/*    */     //   55: iload_3
/*    */     //   56: invokevirtual ky : (S)Lf/j40;
/*    */     //   59: dup
/*    */     //   60: astore #4
/*    */     //   62: ifnull -> 262
/*    */     //   65: aload_0
/*    */     //   66: iload_1
/*    */     //   67: iconst_0
/*    */     //   68: aload #4
/*    */     //   70: invokevirtual Cb : (SZLf/j40;)Z
/*    */     //   73: ifne -> 79
/*    */     //   76: goto -> 262
/*    */     //   79: iload_1
/*    */     //   80: aload_0
/*    */     //   81: getfield TG0 : [Lf/Qv0;
/*    */     //   84: iconst_0
/*    */     //   85: aaload
/*    */     //   86: invokevirtual public : ()Lf/j40;
/*    */     //   89: astore #5
/*    */     //   91: iconst_2
/*    */     //   92: if_icmpne -> 111
/*    */     //   95: aload #5
/*    */     //   97: getfield Jg : I
/*    */     //   100: aload #4
/*    */     //   102: getfield Jg : I
/*    */     //   105: if_icmpne -> 111
/*    */     //   108: goto -> 262
/*    */     //   111: aload #4
/*    */     //   113: invokevirtual s5 : ()B
/*    */     //   116: iconst_m1
/*    */     //   117: if_icmpeq -> 211
/*    */     //   120: new f/Fy0
/*    */     //   123: dup
/*    */     //   124: dup
/*    */     //   125: astore #5
/*    */     //   127: aload #4
/*    */     //   129: invokevirtual Hn : ()Ljava/lang/String;
/*    */     //   132: iconst_m1
/*    */     //   133: iconst_m1
/*    */     //   134: invokespecial <init> : (Ljava/lang/String;II)V
/*    */     //   137: getfield As : Lf/rH;
/*    */     //   140: iconst_1
/*    */     //   141: anewarray f/pe0
/*    */     //   144: dup
/*    */     //   145: aload #4
/*    */     //   147: invokestatic ZZ : ()Lf/interface;
/*    */     //   150: astore #6
/*    */     //   152: invokevirtual s5 : ()B
/*    */     //   155: aload #6
/*    */     //   157: getfield ar0 : [Lf/pe0;
/*    */     //   160: swap
/*    */     //   161: aaload
/*    */     //   162: iconst_0
/*    */     //   163: swap
/*    */     //   164: aastore
/*    */     //   165: invokevirtual Pn : ([Lf/pe0;)Lf/JG0;
/*    */     //   168: pop
/*    */     //   169: invokestatic XU : ()Z
/*    */     //   172: ifeq -> 196
/*    */     //   175: aload #5
/*    */     //   177: getfield As : Lf/rH;
/*    */     //   180: dup
/*    */     //   181: fconst_2
/*    */     //   182: putfield V1 : F
/*    */     //   185: bipush #-5
/*    */     //   187: bipush #17
/*    */     //   189: invokevirtual zT : (II)Lf/JG0;
/*    */     //   192: pop
/*    */     //   193: goto -> 227
/*    */     //   196: aload #5
/*    */     //   198: getfield As : Lf/rH;
/*    */     //   201: iconst_2
/*    */     //   202: bipush #6
/*    */     //   204: invokevirtual zT : (II)Lf/JG0;
/*    */     //   207: pop
/*    */     //   208: goto -> 227
/*    */     //   211: new f/Fy0
/*    */     //   214: dup
/*    */     //   215: astore #5
/*    */     //   217: aload #4
/*    */     //   219: invokevirtual Hn : ()Ljava/lang/String;
/*    */     //   222: iconst_m1
/*    */     //   223: iconst_m1
/*    */     //   224: invokespecial <init> : (Ljava/lang/String;II)V
/*    */     //   227: aload_2
/*    */     //   228: aload #5
/*    */     //   230: aload_0
/*    */     //   231: aload #4
/*    */     //   233: iload_1
/*    */     //   234: <illegal opcode> run : (Lf/GV;Lf/j40;S)Ljava/lang/Runnable;
/*    */     //   239: invokevirtual tW : (Ljava/lang/Runnable;)V
/*    */     //   242: new f/zq
/*    */     //   245: dup
/*    */     //   246: astore #4
/*    */     //   248: aload #5
/*    */     //   250: invokespecial <init> : (Lf/Fy0;)V
/*    */     //   253: getfield aV : Ljava/util/ArrayList;
/*    */     //   256: aload #4
/*    */     //   258: invokevirtual add : (Ljava/lang/Object;)Z
/*    */     //   261: pop
/*    */     //   262: iload_3
/*    */     //   263: iconst_1
/*    */     //   264: iadd
/*    */     //   265: i2s
/*    */     //   266: istore_3
/*    */     //   267: goto -> 28
/*    */     //   270: aload_2
/*    */     //   271: aload_0
/*    */     //   272: getfield TG0 : [Lf/Qv0;
/*    */     //   275: iload_1
/*    */     //   276: aaload
/*    */     //   277: invokestatic Yo : (Lf/B3;Lf/JG0;)Lf/F7;
/*    */     //   280: dup
/*    */     //   281: astore_1
/*    */     //   282: aload_0
/*    */     //   283: dup
/*    */     //   284: aload_1
/*    */     //   285: putfield xb0 : Lf/F7;
/*    */     //   288: <illegal opcode> run : (Lf/GV;)Ljava/lang/Runnable;
/*    */     //   293: putfield es0 : Ljava/lang/Runnable;
/*    */     //   296: return
/*    */     // Line number table:
/*    */     //   Java source line number -> byte code offset
/*    */     //   #1	-> 97
/*    */     //   #2	-> 102
/*    */     //   #3	-> 113
/*    */     //   #4	-> 137
/*    */     //   #5	-> 141
/*    */     //   #6	-> 157
/*    */     //   #7	-> 161
/*    */     //   #8	-> 164
/*    */     //   #9	-> 177
/*    */     //   #10	-> 182
/*    */     //   #11	-> 189
/*    */     //   #12	-> 198
/*    */     //   #13	-> 204
/*    */     //   #14	-> 253
/*    */     //   #15	-> 272
/*    */     //   #16	-> 293 }
/* 27 */   public final void update() { pv0(); Qv0[] arrayOfQv0; for (byte b = 0; b < (arrayOfQv0 = this.TG0).length; ) { if (b != 1) if (arrayOfQv0[b].public() != null) { j40 j40; if ((j40 = this.TG0[b].public()).Zs.p10() > 0) { LPT3 lPT3 = Of.eH.On0(j40.Zs.p10()); this.TF0[b].E1(Ml0.OH0(lPT3.Iu)); (this.TF0[b]).TS.qt(new U70[] { wm0.y0.HR(lPT3, false) }); (this.TF0[b]).z4 = rG0.kh0(lPT3); this.TF0[b].zn(); (this.TF0[b]).jl = 200; } else { this.TF0[b].E1(""); (this.TF0[b]).z4 = null; this.TF0[b].zn(); (this.TF0[b]).TS.H(); }  this.h10[b].E1(j40.m()); if (j40.s5() != -1) { boolean bool = false; interface interface = interface.ZZ(); byte b3 = j40.s5(); (new pe0[1])[bool] = interface.ar0[b3]; (this.FD0[b]).TS.Pn(new pe0[1]); if (km.XU())
/* 28 */             { (this.FD0[b]).TS
/* 29 */                 .V1 = 2.0F;
/* 30 */               (this.FD0[b]).TS.zT(4, -33); } else { (this.FD0[b])
/* 31 */                 .TS
/* 32 */                 .zT(4, -23); }  } else { (this.FD0[b])
/* 33 */               .TS
/* 34 */               .H(); }  hR[] arrayOfHR; int i; byte b2; for (i = (arrayOfHR = hR.Tt0).length, b2 = 0; b2 < i; )
/* 35 */           { hR hR; if (!(hR = arrayOfHR[b2]).NT) this
/* 36 */                 .oD0[b][hR
/* 37 */                   .It0]
/*    */ 
/*    */                 
/* 40 */                 .E1(j40.Zs.Hc(hR) + "");  b2++; }  for (byte b1 = 0; b1 < 4; )
/* 41 */           { if (j40.Zs
/* 42 */               .En0[b1] == 
/* 43 */               0) { this
/* 44 */                 .aS[b][b1].E1("-"); } else { this.aS[b][b1]
/*    */ 
/*    */ 
/*    */ 
/*    */ 
/*    */ 
/*    */                 
/* 51 */                 .E1(Ml0.OH0((yk0.cw().mP(j40.Zs.En0[b1])).iz)); }  b1++; }  this.Q00[b]
/*    */ 
/*    */             
/* 54 */             .E1(j40.Zs.k0.cK0() + ""); this.R90[b]
/*    */             
/* 56 */             .E1(Ml0.Go(2539, j40.Zs.lG())); r10(b, true); } else { (this.FD0[b])
/* 57 */             .TS
/* 58 */             .H(); (this.TF0[b])
/* 59 */             .z4 = null;
/* 60 */           this.TF0[b].zn(); }   b++; }
/*    */      }
/*    */ 
/*    */   
/*    */   public final void I80(int[] paramArrayOfint, boolean paramBoolean, short paramShort, byte paramByte1, jZ[] paramArrayOfjZ, nV[] paramArrayOfnV, short[] paramArrayOfshort, byte[] paramArrayOfbyte, byte paramByte2, byte paramByte3) {
/*    */     // Byte code:
/*    */     //   0: aload_0
/*    */     //   1: getfield TG0 : [Lf/Qv0;
/*    */     //   4: iconst_0
/*    */     //   5: aaload
/*    */     //   6: invokevirtual public : ()Lf/j40;
/*    */     //   9: ifnull -> 2103
/*    */     //   12: aload_0
/*    */     //   13: getfield TG0 : [Lf/Qv0;
/*    */     //   16: iconst_0
/*    */     //   17: aaload
/*    */     //   18: invokevirtual public : ()Lf/j40;
/*    */     //   21: getfield Jg : I
/*    */     //   24: aload_1
/*    */     //   25: iconst_0
/*    */     //   26: iaload
/*    */     //   27: if_icmpeq -> 33
/*    */     //   30: goto -> 2103
/*    */     //   33: aload_0
/*    */     //   34: getfield TG0 : [Lf/Qv0;
/*    */     //   37: iconst_2
/*    */     //   38: aaload
/*    */     //   39: invokevirtual public : ()Lf/j40;
/*    */     //   42: ifnull -> 2102
/*    */     //   45: aload_0
/*    */     //   46: getfield TG0 : [Lf/Qv0;
/*    */     //   49: iconst_2
/*    */     //   50: aaload
/*    */     //   51: invokevirtual public : ()Lf/j40;
/*    */     //   54: getfield Jg : I
/*    */     //   57: aload_1
/*    */     //   58: iconst_1
/*    */     //   59: iaload
/*    */     //   60: if_icmpeq -> 66
/*    */     //   63: goto -> 2102
/*    */     //   66: iload_2
/*    */     //   67: ifne -> 147
/*    */     //   70: aload_0
/*    */     //   71: dup
/*    */     //   72: dup2
/*    */     //   73: dup2
/*    */     //   74: getfield TG0 : [Lf/Qv0;
/*    */     //   77: iconst_1
/*    */     //   78: aaload
/*    */     //   79: aconst_null
/*    */     //   80: invokevirtual zf : (Lf/j40;)V
/*    */     //   83: iconst_1
/*    */     //   84: iconst_0
/*    */     //   85: invokevirtual r10 : (IZ)V
/*    */     //   88: sipush #2529
/*    */     //   91: invokestatic OH0 : (I)Ljava/lang/String;
/*    */     //   94: invokevirtual XJ : (Ljava/lang/String;)V
/*    */     //   97: getfield h10 : [Lf/dQ;
/*    */     //   100: iconst_1
/*    */     //   101: aaload
/*    */     //   102: iconst_1
/*    */     //   103: invokevirtual wI0 : (Z)V
/*    */     //   106: getfield gZ : Lf/Un;
/*    */     //   109: ldc_w ''
/*    */     //   112: invokevirtual s6 : (Ljava/lang/String;)V
/*    */     //   115: getfield gZ : Lf/Un;
/*    */     //   118: astore_0
/*    */     //   119: ldc_w 'min-button'
/*    */     //   122: dup
/*    */     //   123: astore_1
/*    */     //   124: aload_0
/*    */     //   125: getfield cl : Ljava/lang/String;
/*    */     //   128: invokevirtual equals : (Ljava/lang/Object;)Z
/*    */     //   131: ifeq -> 137
/*    */     //   134: goto -> 146
/*    */     //   137: aload_0
/*    */     //   138: dup
/*    */     //   139: aload_1
/*    */     //   140: invokevirtual Xu : (Ljava/lang/String;)V
/*    */     //   143: invokevirtual cZ : ()V
/*    */     //   146: return
/*    */     //   147: aload_0
/*    */     //   148: getfield TG0 : [Lf/Qv0;
/*    */     //   151: iconst_0
/*    */     //   152: aaload
/*    */     //   153: invokevirtual public : ()Lf/j40;
/*    */     //   156: getfield Zs : Lf/Q90;
/*    */     //   159: invokevirtual tm0 : ()Z
/*    */     //   162: ifeq -> 188
/*    */     //   165: aload_0
/*    */     //   166: getfield TG0 : [Lf/Qv0;
/*    */     //   169: iconst_2
/*    */     //   170: aaload
/*    */     //   171: invokevirtual public : ()Lf/j40;
/*    */     //   174: getfield Zs : Lf/Q90;
/*    */     //   177: invokevirtual tm0 : ()Z
/*    */     //   180: ifeq -> 188
/*    */     //   183: iconst_1
/*    */     //   184: istore_1
/*    */     //   185: goto -> 190
/*    */     //   188: iconst_0
/*    */     //   189: istore_1
/*    */     //   190: iload #4
/*    */     //   192: new f/Q90
/*    */     //   195: dup
/*    */     //   196: dup
/*    */     //   197: astore_2
/*    */     //   198: iconst_0
/*    */     //   199: invokespecial <init> : (I)V
/*    */     //   202: iload_3
/*    */     //   203: putfield Cw0 : S
/*    */     //   206: iconst_m1
/*    */     //   207: if_icmple -> 216
/*    */     //   210: aload_2
/*    */     //   211: iload #4
/*    */     //   213: putfield Vp : B
/*    */     //   216: aload_0
/*    */     //   217: aload_2
/*    */     //   218: iload #10
/*    */     //   220: invokevirtual am : (B)V
/*    */     //   223: getfield TG0 : [Lf/Qv0;
/*    */     //   226: iconst_0
/*    */     //   227: aaload
/*    */     //   228: invokevirtual public : ()Lf/j40;
/*    */     //   231: getfield Zs : Lf/Q90;
/*    */     //   234: invokevirtual tm0 : ()Z
/*    */     //   237: ifeq -> 276
/*    */     //   240: aload_0
/*    */     //   241: getfield TG0 : [Lf/Qv0;
/*    */     //   244: iconst_2
/*    */     //   245: aaload
/*    */     //   246: invokevirtual public : ()Lf/j40;
/*    */     //   249: getfield Zs : Lf/Q90;
/*    */     //   252: invokevirtual tm0 : ()Z
/*    */     //   255: ifeq -> 276
/*    */     //   258: aload_2
/*    */     //   259: dup
/*    */     //   260: dup
/*    */     //   261: getfield eH : B
/*    */     //   264: iconst_1
/*    */     //   265: ior
/*    */     //   266: i2b
/*    */     //   267: putfield eH : B
/*    */     //   270: getstatic f/mA.Wh0 : Lf/mA;
/*    */     //   273: putfield xH : Lf/mA;
/*    */     //   276: aload_0
/*    */     //   277: getfield TG0 : [Lf/Qv0;
/*    */     //   280: iconst_0
/*    */     //   281: aaload
/*    */     //   282: invokevirtual public : ()Lf/j40;
/*    */     //   285: getfield Zs : Lf/Q90;
/*    */     //   288: getfield wH : [Lf/mA;
/*    */     //   291: dup
/*    */     //   292: astore #4
/*    */     //   294: arraylength
/*    */     //   295: istore #10
/*    */     //   297: iconst_0
/*    */     //   298: istore #11
/*    */     //   300: iload #11
/*    */     //   302: iload #10
/*    */     //   304: if_icmpge -> 322
/*    */     //   307: aload_2
/*    */     //   308: aload #4
/*    */     //   310: iload #11
/*    */     //   312: aaload
/*    */     //   313: invokevirtual JS : (Lf/mA;)V
/*    */     //   316: iinc #11, 1
/*    */     //   319: goto -> 300
/*    */     //   322: aload_0
/*    */     //   323: getfield TG0 : [Lf/Qv0;
/*    */     //   326: iconst_2
/*    */     //   327: aaload
/*    */     //   328: invokevirtual public : ()Lf/j40;
/*    */     //   331: getfield Zs : Lf/Q90;
/*    */     //   334: getfield wH : [Lf/mA;
/*    */     //   337: dup
/*    */     //   338: astore #4
/*    */     //   340: arraylength
/*    */     //   341: istore #10
/*    */     //   343: iconst_0
/*    */     //   344: istore #11
/*    */     //   346: iload #11
/*    */     //   348: iload #10
/*    */     //   350: if_icmpge -> 368
/*    */     //   353: aload_2
/*    */     //   354: aload #4
/*    */     //   356: iload #11
/*    */     //   358: aaload
/*    */     //   359: invokevirtual JS : (Lf/mA;)V
/*    */     //   362: iinc #11, 1
/*    */     //   365: goto -> 346
/*    */     //   368: aload_0
/*    */     //   369: getfield TG0 : [Lf/Qv0;
/*    */     //   372: iconst_1
/*    */     //   373: aaload
/*    */     //   374: new f/j40
/*    */     //   377: dup
/*    */     //   378: aload_2
/*    */     //   379: invokespecial <init> : (Lf/Q90;)V
/*    */     //   382: invokevirtual zf : (Lf/j40;)V
/*    */     //   385: invokestatic v30 : ()Lf/On;
/*    */     //   388: iload_3
/*    */     //   389: invokevirtual lpT3 : (S)Lf/UD0;
/*    */     //   392: dup
/*    */     //   393: astore_2
/*    */     //   394: ifnonnull -> 412
/*    */     //   397: aload_0
/*    */     //   398: getfield h10 : [Lf/dQ;
/*    */     //   401: iconst_1
/*    */     //   402: aaload
/*    */     //   403: ldc_w '???'
/*    */     //   406: invokevirtual E1 : (Ljava/lang/String;)V
/*    */     //   409: goto -> 426
/*    */     //   412: aload_0
/*    */     //   413: getfield h10 : [Lf/dQ;
/*    */     //   416: iconst_1
/*    */     //   417: aaload
/*    */     //   418: aload_2
/*    */     //   419: iconst_0
/*    */     //   420: invokevirtual o60 : (Z)Ljava/lang/String;
/*    */     //   423: invokevirtual E1 : (Ljava/lang/String;)V
/*    */     //   426: new java/text/DecimalFormat
/*    */     //   429: dup
/*    */     //   430: astore_2
/*    */     //   431: ldc_w '00.#'
/*    */     //   434: invokespecial <init> : (Ljava/lang/String;)V
/*    */     //   437: new java/text/DecimalFormat
/*    */     //   440: dup
/*    */     //   441: astore_3
/*    */     //   442: ldc_w '#.0'
/*    */     //   445: invokespecial <init> : (Ljava/lang/String;)V
/*    */     //   448: getstatic f/hR.Tm0 : [Lf/hR;
/*    */     //   451: dup
/*    */     //   452: astore #4
/*    */     //   454: arraylength
/*    */     //   455: istore #10
/*    */     //   457: iconst_0
/*    */     //   458: istore #11
/*    */     //   460: iload #11
/*    */     //   462: iload #10
/*    */     //   464: if_icmpge -> 1472
/*    */     //   467: aload #4
/*    */     //   469: iload #11
/*    */     //   471: aaload
/*    */     //   472: dup
/*    */     //   473: astore #12
/*    */     //   475: getfield NT : Z
/*    */     //   478: ifeq -> 484
/*    */     //   481: goto -> 1466
/*    */     //   484: aload #5
/*    */     //   486: aload #12
/*    */     //   488: getfield dL : B
/*    */     //   491: aaload
/*    */     //   492: getfield ZM : Z
/*    */     //   495: ifeq -> 519
/*    */     //   498: aload_0
/*    */     //   499: getfield oD0 : [[Lf/dQ;
/*    */     //   502: iconst_1
/*    */     //   503: aaload
/*    */     //   504: aload #12
/*    */     //   506: getfield It0 : B
/*    */     //   509: aaload
/*    */     //   510: ldc_w 'iv-value-green'
/*    */     //   513: invokevirtual Xu : (Ljava/lang/String;)V
/*    */     //   516: goto -> 536
/*    */     //   519: aload_0
/*    */     //   520: getfield oD0 : [[Lf/dQ;
/*    */     //   523: iconst_1
/*    */     //   524: aaload
/*    */     //   525: aload #12
/*    */     //   527: getfield It0 : B
/*    */     //   530: aaload
/*    */     //   531: ldc 'iv-value'
/*    */     //   533: invokevirtual Xu : (Ljava/lang/String;)V
/*    */     //   536: iload_1
/*    */     //   537: aload #5
/*    */     //   539: aload #12
/*    */     //   541: getstatic f/UB0.Kg0 : Lf/Q50;
/*    */     //   544: aload_0
/*    */     //   545: aload #12
/*    */     //   547: <illegal opcode> run : (Lf/GV;Lf/hR;)Ljava/lang/Runnable;
/*    */     //   552: invokevirtual fN : (Ljava/lang/Runnable;)V
/*    */     //   555: new java/lang/StringBuilder
/*    */     //   558: dup
/*    */     //   559: astore #13
/*    */     //   561: invokespecial <init> : ()V
/*    */     //   564: new java/util/TreeSet
/*    */     //   567: dup
/*    */     //   568: astore #14
/*    */     //   570: invokespecial <init> : ()V
/*    */     //   573: getfield dL : B
/*    */     //   576: aaload
/*    */     //   577: getfield OS : Ljava/util/ArrayList;
/*    */     //   580: dup
/*    */     //   581: astore #15
/*    */     //   583: invokestatic sort : (Ljava/util/List;)V
/*    */     //   586: new f/Zz0
/*    */     //   589: dup
/*    */     //   590: astore #16
/*    */     //   592: invokespecial <init> : ()V
/*    */     //   595: new f/dQ
/*    */     //   598: astore #17
/*    */     //   600: ifeq -> 609
/*    */     //   603: sipush #2548
/*    */     //   606: goto -> 612
/*    */     //   609: sipush #2547
/*    */     //   612: invokestatic OH0 : (I)Ljava/lang/String;
/*    */     //   615: astore #18
/*    */     //   617: aload #15
/*    */     //   619: aload #16
/*    */     //   621: aload #17
/*    */     //   623: dup
/*    */     //   624: invokespecial <init> : ()V
/*    */     //   627: aload #18
/*    */     //   629: invokevirtual E1 : (Ljava/lang/String;)V
/*    */     //   632: iconst_1
/*    */     //   633: anewarray f/JG0
/*    */     //   636: dup
/*    */     //   637: astore #18
/*    */     //   639: iconst_0
/*    */     //   640: aload #17
/*    */     //   642: aastore
/*    */     //   643: aload #18
/*    */     //   645: invokevirtual of0 : ([Lf/JG0;)V
/*    */     //   648: new f/ib0
/*    */     //   651: dup
/*    */     //   652: astore #17
/*    */     //   654: invokespecial <init> : ()V
/*    */     //   657: invokevirtual iterator : ()Ljava/util/Iterator;
/*    */     //   660: astore #18
/*    */     //   662: aload #18
/*    */     //   664: invokeinterface hasNext : ()Z
/*    */     //   669: ifeq -> 768
/*    */     //   672: aload #17
/*    */     //   674: aload #18
/*    */     //   676: invokeinterface next : ()Ljava/lang/Object;
/*    */     //   681: checkcast f/os0
/*    */     //   684: dup
/*    */     //   685: getfield OF : B
/*    */     //   688: istore #19
/*    */     //   690: getfield G1 : F
/*    */     //   693: fstore #20
/*    */     //   695: iload #19
/*    */     //   697: invokevirtual A60 : (I)I
/*    */     //   700: dup
/*    */     //   701: istore #19
/*    */     //   703: ifge -> 733
/*    */     //   706: aload #17
/*    */     //   708: iload #19
/*    */     //   710: ineg
/*    */     //   711: iconst_1
/*    */     //   712: isub
/*    */     //   713: istore #19
/*    */     //   715: getfield BX : [F
/*    */     //   718: dup
/*    */     //   719: iload #19
/*    */     //   721: swap
/*    */     //   722: iload #19
/*    */     //   724: faload
/*    */     //   725: fload #20
/*    */     //   727: fadd
/*    */     //   728: fastore
/*    */     //   729: iconst_0
/*    */     //   730: goto -> 744
/*    */     //   733: aload #17
/*    */     //   735: getfield BX : [F
/*    */     //   738: iload #19
/*    */     //   740: fload #20
/*    */     //   742: fastore
/*    */     //   743: iconst_1
/*    */     //   744: aload #17
/*    */     //   746: getfield JO : [B
/*    */     //   749: iload #19
/*    */     //   751: baload
/*    */     //   752: pop
/*    */     //   753: ifeq -> 662
/*    */     //   756: aload #17
/*    */     //   758: dup
/*    */     //   759: getfield QC0 : Z
/*    */     //   762: invokevirtual xt0 : (Z)V
/*    */     //   765: goto -> 662
/*    */     //   768: aload #17
/*    */     //   770: getfield ir0 : I
/*    */     //   773: aload #15
/*    */     //   775: invokeinterface size : ()I
/*    */     //   780: if_icmpeq -> 789
/*    */     //   783: iconst_1
/*    */     //   784: istore #18
/*    */     //   786: goto -> 792
/*    */     //   789: iconst_0
/*    */     //   790: istore #18
/*    */     //   792: aload #15
/*    */     //   794: invokeinterface iterator : ()Ljava/util/Iterator;
/*    */     //   799: astore #15
/*    */     //   801: aload #15
/*    */     //   803: invokeinterface hasNext : ()Z
/*    */     //   808: ifeq -> 1205
/*    */     //   811: aload #17
/*    */     //   813: aload #15
/*    */     //   815: invokeinterface next : ()Ljava/lang/Object;
/*    */     //   820: checkcast f/os0
/*    */     //   823: dup
/*    */     //   824: astore #19
/*    */     //   826: new f/dQ
/*    */     //   829: dup
/*    */     //   830: dup2
/*    */     //   831: astore #20
/*    */     //   833: aload #19
/*    */     //   835: getfield Ku : I
/*    */     //   838: invokestatic OH0 : (I)Ljava/lang/String;
/*    */     //   841: astore #21
/*    */     //   843: invokespecial <init> : ()V
/*    */     //   846: aload #21
/*    */     //   848: invokevirtual E1 : (Ljava/lang/String;)V
/*    */     //   851: ldc_w 'label-tooltip'
/*    */     //   854: invokevirtual Xu : (Ljava/lang/String;)V
/*    */     //   857: new f/dQ
/*    */     //   860: dup
/*    */     //   861: dup
/*    */     //   862: astore #21
/*    */     //   864: invokespecial <init> : ()V
/*    */     //   867: ldc_w ' | '
/*    */     //   870: invokevirtual E1 : (Ljava/lang/String;)V
/*    */     //   873: getfield OF : B
/*    */     //   876: invokevirtual u10 : (I)I
/*    */     //   879: dup
/*    */     //   880: istore #22
/*    */     //   882: ifge -> 895
/*    */     //   885: aload #17
/*    */     //   887: getfield Mn0 : F
/*    */     //   890: fstore #22
/*    */     //   892: goto -> 905
/*    */     //   895: aload #17
/*    */     //   897: getfield BX : [F
/*    */     //   900: iload #22
/*    */     //   902: faload
/*    */     //   903: fstore #22
/*    */     //   905: fload #22
/*    */     //   907: aload #19
/*    */     //   909: new f/dQ
/*    */     //   912: astore #23
/*    */     //   914: getfield G1 : F
/*    */     //   917: invokestatic JC0 : (FF)Z
/*    */     //   920: ifeq -> 931
/*    */     //   923: ldc_w ''
/*    */     //   926: astore #22
/*    */     //   928: goto -> 958
/*    */     //   931: ldc_w ' (='
/*    */     //   934: invokestatic df : (Ljava/lang/String;)Ljava/lang/StringBuilder;
/*    */     //   937: aload_3
/*    */     //   938: fload #22
/*    */     //   940: f2d
/*    */     //   941: invokevirtual format : (D)Ljava/lang/String;
/*    */     //   944: invokevirtual append : (Ljava/lang/String;)Ljava/lang/StringBuilder;
/*    */     //   947: ldc_w '%)'
/*    */     //   950: invokevirtual append : (Ljava/lang/String;)Ljava/lang/StringBuilder;
/*    */     //   953: invokevirtual toString : ()Ljava/lang/String;
/*    */     //   956: astore #22
/*    */     //   958: iload #18
/*    */     //   960: aload #23
/*    */     //   962: dup
/*    */     //   963: aload #22
/*    */     //   965: aload #23
/*    */     //   967: invokespecial <init> : ()V
/*    */     //   970: invokevirtual E1 : (Ljava/lang/String;)V
/*    */     //   973: ldc_w 'label-tooltip'
/*    */     //   976: invokevirtual Xu : (Ljava/lang/String;)V
/*    */     //   979: new f/dQ
/*    */     //   982: dup
/*    */     //   983: dup
/*    */     //   984: astore #22
/*    */     //   986: iconst_2
/*    */     //   987: anewarray java/lang/String
/*    */     //   990: dup
/*    */     //   991: astore #24
/*    */     //   993: aload_3
/*    */     //   994: aload #19
/*    */     //   996: aload #24
/*    */     //   998: aload_2
/*    */     //   999: aload #19
/*    */     //   1001: getfield OF : B
/*    */     //   1004: i2l
/*    */     //   1005: invokevirtual format : (J)Ljava/lang/String;
/*    */     //   1008: iconst_0
/*    */     //   1009: swap
/*    */     //   1010: aastore
/*    */     //   1011: getfield G1 : F
/*    */     //   1014: f2d
/*    */     //   1015: invokevirtual format : (D)Ljava/lang/String;
/*    */     //   1018: iconst_1
/*    */     //   1019: swap
/*    */     //   1020: aastore
/*    */     //   1021: sipush #2546
/*    */     //   1024: aload #24
/*    */     //   1026: invokestatic sB : (I[Ljava/lang/String;)Ljava/lang/String;
/*    */     //   1029: astore #24
/*    */     //   1031: invokespecial <init> : ()V
/*    */     //   1034: aload #24
/*    */     //   1036: invokevirtual E1 : (Ljava/lang/String;)V
/*    */     //   1039: ifeq -> 1077
/*    */     //   1042: aload #16
/*    */     //   1044: iconst_4
/*    */     //   1045: anewarray f/JG0
/*    */     //   1048: dup
/*    */     //   1049: dup
/*    */     //   1050: dup2
/*    */     //   1051: astore #24
/*    */     //   1053: iconst_0
/*    */     //   1054: aload #20
/*    */     //   1056: aastore
/*    */     //   1057: iconst_1
/*    */     //   1058: aload #21
/*    */     //   1060: aastore
/*    */     //   1061: iconst_2
/*    */     //   1062: aload #22
/*    */     //   1064: aastore
/*    */     //   1065: iconst_3
/*    */     //   1066: aload #23
/*    */     //   1068: aastore
/*    */     //   1069: aload #24
/*    */     //   1071: invokevirtual of0 : ([Lf/JG0;)V
/*    */     //   1074: goto -> 1104
/*    */     //   1077: aload #16
/*    */     //   1079: iconst_3
/*    */     //   1080: anewarray f/JG0
/*    */     //   1083: dup
/*    */     //   1084: dup2
/*    */     //   1085: astore #23
/*    */     //   1087: iconst_0
/*    */     //   1088: aload #20
/*    */     //   1090: aastore
/*    */     //   1091: iconst_1
/*    */     //   1092: aload #21
/*    */     //   1094: aastore
/*    */     //   1095: iconst_2
/*    */     //   1096: aload #22
/*    */     //   1098: aastore
/*    */     //   1099: aload #23
/*    */     //   1101: invokevirtual of0 : ([Lf/JG0;)V
/*    */     //   1104: aload #13
/*    */     //   1106: aload #14
/*    */     //   1108: aload #19
/*    */     //   1110: getfield OF : B
/*    */     //   1113: invokestatic valueOf : (B)Ljava/lang/Byte;
/*    */     //   1116: invokevirtual add : (Ljava/lang/Object;)Z
/*    */     //   1119: pop
/*    */     //   1120: invokevirtual length : ()I
/*    */     //   1123: iconst_1
/*    */     //   1124: if_icmple -> 1136
/*    */     //   1127: aload #13
/*    */     //   1129: ldc_w '\\n'
/*    */     //   1132: invokevirtual append : (Ljava/lang/String;)Ljava/lang/StringBuilder;
/*    */     //   1135: pop
/*    */     //   1136: aload #19
/*    */     //   1138: getfield Ku : I
/*    */     //   1141: dup
/*    */     //   1142: istore #20
/*    */     //   1144: ifle -> 1150
/*    */     //   1147: goto -> 1155
/*    */     //   1150: sipush #2546
/*    */     //   1153: istore #20
/*    */     //   1155: aload #13
/*    */     //   1157: iload #20
/*    */     //   1159: iconst_2
/*    */     //   1160: anewarray java/lang/String
/*    */     //   1163: dup
/*    */     //   1164: dup
/*    */     //   1165: astore #20
/*    */     //   1167: aload_3
/*    */     //   1168: aload #19
/*    */     //   1170: aload #20
/*    */     //   1172: aload_2
/*    */     //   1173: aload #19
/*    */     //   1175: getfield OF : B
/*    */     //   1178: i2l
/*    */     //   1179: invokevirtual format : (J)Ljava/lang/String;
/*    */     //   1182: iconst_0
/*    */     //   1183: swap
/*    */     //   1184: aastore
/*    */     //   1185: getfield G1 : F
/*    */     //   1188: f2d
/*    */     //   1189: invokevirtual format : (D)Ljava/lang/String;
/*    */     //   1192: iconst_1
/*    */     //   1193: swap
/*    */     //   1194: aastore
/*    */     //   1195: invokestatic sB : (I[Ljava/lang/String;)Ljava/lang/String;
/*    */     //   1198: invokevirtual append : (Ljava/lang/String;)Ljava/lang/StringBuilder;
/*    */     //   1201: pop
/*    */     //   1202: goto -> 801
/*    */     //   1205: aload #14
/*    */     //   1207: invokevirtual size : ()I
/*    */     //   1210: iconst_1
/*    */     //   1211: if_icmpne -> 1257
/*    */     //   1214: aload_0
/*    */     //   1215: getfield oD0 : [[Lf/dQ;
/*    */     //   1218: iconst_1
/*    */     //   1219: aaload
/*    */     //   1220: aload #12
/*    */     //   1222: getfield It0 : B
/*    */     //   1225: aaload
/*    */     //   1226: new java/lang/StringBuilder
/*    */     //   1229: dup
/*    */     //   1230: aload #14
/*    */     //   1232: swap
/*    */     //   1233: invokespecial <init> : ()V
/*    */     //   1236: invokevirtual first : ()Ljava/lang/Object;
/*    */     //   1239: invokevirtual append : (Ljava/lang/Object;)Ljava/lang/StringBuilder;
/*    */     //   1242: ldc_w ''
/*    */     //   1245: invokevirtual append : (Ljava/lang/String;)Ljava/lang/StringBuilder;
/*    */     //   1248: invokevirtual toString : ()Ljava/lang/String;
/*    */     //   1251: invokevirtual E1 : (Ljava/lang/String;)V
/*    */     //   1254: goto -> 1335
/*    */     //   1257: aload #14
/*    */     //   1259: invokevirtual size : ()I
/*    */     //   1262: iconst_1
/*    */     //   1263: if_icmple -> 1317
/*    */     //   1266: aload_0
/*    */     //   1267: getfield oD0 : [[Lf/dQ;
/*    */     //   1270: iconst_1
/*    */     //   1271: aaload
/*    */     //   1272: aload #12
/*    */     //   1274: getfield It0 : B
/*    */     //   1277: aaload
/*    */     //   1278: new java/lang/StringBuilder
/*    */     //   1281: dup
/*    */     //   1282: aload #14
/*    */     //   1284: swap
/*    */     //   1285: invokespecial <init> : ()V
/*    */     //   1288: invokevirtual first : ()Ljava/lang/Object;
/*    */     //   1291: invokevirtual append : (Ljava/lang/Object;)Ljava/lang/StringBuilder;
/*    */     //   1294: ldc_w ' - '
/*    */     //   1297: invokevirtual append : (Ljava/lang/String;)Ljava/lang/StringBuilder;
/*    */     //   1300: aload #14
/*    */     //   1302: invokevirtual last : ()Ljava/lang/Object;
/*    */     //   1305: invokevirtual append : (Ljava/lang/Object;)Ljava/lang/StringBuilder;
/*    */     //   1308: invokevirtual toString : ()Ljava/lang/String;
/*    */     //   1311: invokevirtual E1 : (Ljava/lang/String;)V
/*    */     //   1314: goto -> 1335
/*    */     //   1317: aload_0
/*    */     //   1318: getfield oD0 : [[Lf/dQ;
/*    */     //   1321: iconst_1
/*    */     //   1322: aaload
/*    */     //   1323: aload #12
/*    */     //   1325: getfield It0 : B
/*    */     //   1328: aaload
/*    */     //   1329: ldc_w '???'
/*    */     //   1332: invokevirtual E1 : (Ljava/lang/String;)V
/*    */     //   1335: aload #5
/*    */     //   1337: aload #12
/*    */     //   1339: getfield dL : B
/*    */     //   1342: aaload
/*    */     //   1343: getfield d : S
/*    */     //   1346: dup
/*    */     //   1347: istore #14
/*    */     //   1349: ifle -> 1449
/*    */     //   1352: aload #16
/*    */     //   1354: aload #13
/*    */     //   1356: dup
/*    */     //   1357: getstatic f/Of.eH : Lf/Of;
/*    */     //   1360: iload #14
/*    */     //   1362: invokevirtual On0 : (S)Lf/LPT3;
/*    */     //   1365: astore #13
/*    */     //   1367: ldc_w '\\n'
/*    */     //   1370: invokevirtual append : (Ljava/lang/String;)Ljava/lang/StringBuilder;
/*    */     //   1373: pop
/*    */     //   1374: aload #13
/*    */     //   1376: getfield Iu : I
/*    */     //   1379: invokestatic OH0 : (I)Ljava/lang/String;
/*    */     //   1382: sipush #2530
/*    */     //   1385: swap
/*    */     //   1386: invokestatic Go : (ILjava/lang/String;)Ljava/lang/String;
/*    */     //   1389: invokevirtual append : (Ljava/lang/String;)Ljava/lang/StringBuilder;
/*    */     //   1392: pop
/*    */     //   1393: iconst_1
/*    */     //   1394: anewarray f/JG0
/*    */     //   1397: dup
/*    */     //   1398: new f/dQ
/*    */     //   1401: dup
/*    */     //   1402: dup
/*    */     //   1403: astore #14
/*    */     //   1405: ldc_w '\\n'
/*    */     //   1408: invokestatic df : (Ljava/lang/String;)Ljava/lang/StringBuilder;
/*    */     //   1411: aload #13
/*    */     //   1413: getfield Iu : I
/*    */     //   1416: invokestatic OH0 : (I)Ljava/lang/String;
/*    */     //   1419: sipush #2530
/*    */     //   1422: swap
/*    */     //   1423: invokestatic Go : (ILjava/lang/String;)Ljava/lang/String;
/*    */     //   1426: invokevirtual append : (Ljava/lang/String;)Ljava/lang/StringBuilder;
/*    */     //   1429: invokevirtual toString : ()Ljava/lang/String;
/*    */     //   1432: astore #13
/*    */     //   1434: invokespecial <init> : ()V
/*    */     //   1437: aload #13
/*    */     //   1439: invokevirtual E1 : (Ljava/lang/String;)V
/*    */     //   1442: iconst_0
/*    */     //   1443: aload #14
/*    */     //   1445: aastore
/*    */     //   1446: invokevirtual of0 : ([Lf/JG0;)V
/*    */     //   1449: aload_0
/*    */     //   1450: getfield oD0 : [[Lf/dQ;
/*    */     //   1453: iconst_1
/*    */     //   1454: aaload
/*    */     //   1455: aload #12
/*    */     //   1457: getfield It0 : B
/*    */     //   1460: aaload
/*    */     //   1461: aload #16
/*    */     //   1463: invokevirtual Gq0 : (Ljava/lang/Object;)V
/*    */     //   1466: iinc #11, 1
/*    */     //   1469: goto -> 460
/*    */     //   1472: iconst_0
/*    */     //   1473: istore_1
/*    */     //   1474: iload_1
/*    */     //   1475: iconst_4
/*    */     //   1476: if_icmpge -> 1641
/*    */     //   1479: aload #7
/*    */     //   1481: arraylength
/*    */     //   1482: iload_1
/*    */     //   1483: if_icmple -> 1621
/*    */     //   1486: aload #7
/*    */     //   1488: iload_1
/*    */     //   1489: saload
/*    */     //   1490: ifne -> 1496
/*    */     //   1493: goto -> 1621
/*    */     //   1496: invokestatic cw : ()Lf/yk0;
/*    */     //   1499: aload #7
/*    */     //   1501: iload_1
/*    */     //   1502: saload
/*    */     //   1503: invokevirtual mP : (S)Lf/WD;
/*    */     //   1506: dup
/*    */     //   1507: astore_2
/*    */     //   1508: ifnonnull -> 1528
/*    */     //   1511: aload_0
/*    */     //   1512: getfield aS : [[Lf/dQ;
/*    */     //   1515: iconst_1
/*    */     //   1516: aaload
/*    */     //   1517: iload_1
/*    */     //   1518: aaload
/*    */     //   1519: ldc_w '-'
/*    */     //   1522: invokevirtual E1 : (Ljava/lang/String;)V
/*    */     //   1525: goto -> 1635
/*    */     //   1528: aload #8
/*    */     //   1530: iload_1
/*    */     //   1531: aload_0
/*    */     //   1532: getfield aS : [[Lf/dQ;
/*    */     //   1535: iconst_1
/*    */     //   1536: aaload
/*    */     //   1537: iload_1
/*    */     //   1538: aaload
/*    */     //   1539: aload_2
/*    */     //   1540: getfield iz : I
/*    */     //   1543: invokestatic OH0 : (I)Ljava/lang/String;
/*    */     //   1546: invokevirtual E1 : (Ljava/lang/String;)V
/*    */     //   1549: baload
/*    */     //   1550: ifne -> 1569
/*    */     //   1553: aload_0
/*    */     //   1554: getfield aS : [[Lf/dQ;
/*    */     //   1557: iconst_1
/*    */     //   1558: aaload
/*    */     //   1559: iload_1
/*    */     //   1560: aaload
/*    */     //   1561: ldc 'shared-value'
/*    */     //   1563: invokevirtual Xu : (Ljava/lang/String;)V
/*    */     //   1566: goto -> 1583
/*    */     //   1569: aload_0
/*    */     //   1570: getfield aS : [[Lf/dQ;
/*    */     //   1573: iconst_1
/*    */     //   1574: aaload
/*    */     //   1575: iload_1
/*    */     //   1576: aaload
/*    */     //   1577: ldc_w 'shared-value-green'
/*    */     //   1580: invokevirtual Xu : (Ljava/lang/String;)V
/*    */     //   1583: aload_0
/*    */     //   1584: getfield aS : [[Lf/dQ;
/*    */     //   1587: iconst_1
/*    */     //   1588: aaload
/*    */     //   1589: iload_1
/*    */     //   1590: aaload
/*    */     //   1591: aload #8
/*    */     //   1593: iload_1
/*    */     //   1594: baload
/*    */     //   1595: sipush #2533
/*    */     //   1598: iadd
/*    */     //   1599: invokestatic OH0 : (I)Ljava/lang/String;
/*    */     //   1602: invokevirtual Gq0 : (Ljava/lang/Object;)V
/*    */     //   1605: getstatic f/UB0.Kg0 : Lf/Q50;
/*    */     //   1608: aload_0
/*    */     //   1609: iload_1
/*    */     //   1610: <illegal opcode> run : (Lf/GV;I)Ljava/lang/Runnable;
/*    */     //   1615: invokevirtual fN : (Ljava/lang/Runnable;)V
/*    */     //   1618: goto -> 1635
/*    */     //   1621: aload_0
/*    */     //   1622: getfield aS : [[Lf/dQ;
/*    */     //   1625: iconst_1
/*    */     //   1626: aaload
/*    */     //   1627: iload_1
/*    */     //   1628: aaload
/*    */     //   1629: ldc_w '-'
/*    */     //   1632: invokevirtual E1 : (Ljava/lang/String;)V
/*    */     //   1635: iinc #1, 1
/*    */     //   1638: goto -> 1474
/*    */     //   1641: aload #6
/*    */     //   1643: arraylength
/*    */     //   1644: iconst_1
/*    */     //   1645: if_icmpge -> 1689
/*    */     //   1648: aload_0
/*    */     //   1649: dup
/*    */     //   1650: dup
/*    */     //   1651: getfield Q00 : [Lf/dQ;
/*    */     //   1654: iconst_1
/*    */     //   1655: aaload
/*    */     //   1656: ldc_w '???'
/*    */     //   1659: invokevirtual E1 : (Ljava/lang/String;)V
/*    */     //   1662: getfield Q00 : [Lf/dQ;
/*    */     //   1665: iconst_1
/*    */     //   1666: aaload
/*    */     //   1667: sipush #2532
/*    */     //   1670: invokestatic OH0 : (I)Ljava/lang/String;
/*    */     //   1673: invokevirtual Gq0 : (Ljava/lang/Object;)V
/*    */     //   1676: getfield Q00 : [Lf/dQ;
/*    */     //   1679: iconst_1
/*    */     //   1680: aaload
/*    */     //   1681: ldc 'shared-value'
/*    */     //   1683: invokevirtual Xu : (Ljava/lang/String;)V
/*    */     //   1686: goto -> 1912
/*    */     //   1689: new java/lang/StringBuilder
/*    */     //   1692: dup
/*    */     //   1693: astore_1
/*    */     //   1694: invokespecial <init> : ()V
/*    */     //   1697: new java/lang/StringBuilder
/*    */     //   1700: dup
/*    */     //   1701: astore_2
/*    */     //   1702: invokespecial <init> : ()V
/*    */     //   1705: iconst_0
/*    */     //   1706: istore #4
/*    */     //   1708: iload #4
/*    */     //   1710: aload #6
/*    */     //   1712: arraylength
/*    */     //   1713: if_icmpge -> 1819
/*    */     //   1716: iload #4
/*    */     //   1718: ifle -> 1737
/*    */     //   1721: aload_2
/*    */     //   1722: aload_1
/*    */     //   1723: ldc_w ' / '
/*    */     //   1726: invokevirtual append : (Ljava/lang/String;)Ljava/lang/StringBuilder;
/*    */     //   1729: pop
/*    */     //   1730: ldc_w '\\n'
/*    */     //   1733: invokevirtual append : (Ljava/lang/String;)Ljava/lang/StringBuilder;
/*    */     //   1736: pop
/*    */     //   1737: aload_2
/*    */     //   1738: aload_1
/*    */     //   1739: aload #6
/*    */     //   1741: iload #4
/*    */     //   1743: aaload
/*    */     //   1744: invokevirtual cK0 : ()Ljava/lang/String;
/*    */     //   1747: invokevirtual append : (Ljava/lang/String;)Ljava/lang/StringBuilder;
/*    */     //   1750: pop
/*    */     //   1751: new java/lang/StringBuilder
/*    */     //   1754: dup
/*    */     //   1755: astore #5
/*    */     //   1757: aload #6
/*    */     //   1759: iload #4
/*    */     //   1761: aload #5
/*    */     //   1763: invokespecial <init> : ()V
/*    */     //   1766: aaload
/*    */     //   1767: invokevirtual cK0 : ()Ljava/lang/String;
/*    */     //   1770: invokevirtual append : (Ljava/lang/String;)Ljava/lang/StringBuilder;
/*    */     //   1773: ldc_w ' - '
/*    */     //   1776: invokevirtual append : (Ljava/lang/String;)Ljava/lang/StringBuilder;
/*    */     //   1779: aload_3
/*    */     //   1780: aload #6
/*    */     //   1782: arraylength
/*    */     //   1783: i2d
/*    */     //   1784: dstore #7
/*    */     //   1786: dconst_1
/*    */     //   1787: dload #7
/*    */     //   1789: ddiv
/*    */     //   1790: ldc2_w 100.0
/*    */     //   1793: dmul
/*    */     //   1794: invokevirtual format : (D)Ljava/lang/String;
/*    */     //   1797: invokevirtual append : (Ljava/lang/String;)Ljava/lang/StringBuilder;
/*    */     //   1800: ldc_w '%'
/*    */     //   1803: invokevirtual append : (Ljava/lang/String;)Ljava/lang/StringBuilder;
/*    */     //   1806: invokevirtual toString : ()Ljava/lang/String;
/*    */     //   1809: invokevirtual append : (Ljava/lang/String;)Ljava/lang/StringBuilder;
/*    */     //   1812: pop
/*    */     //   1813: iinc #4, 1
/*    */     //   1816: goto -> 1708
/*    */     //   1819: aload #6
/*    */     //   1821: aload_2
/*    */     //   1822: getstatic f/Of.eH : Lf/Of;
/*    */     //   1825: sipush #195
/*    */     //   1828: invokevirtual On0 : (S)Lf/LPT3;
/*    */     //   1831: astore_3
/*    */     //   1832: ldc_w '\\n'
/*    */     //   1835: invokevirtual append : (Ljava/lang/String;)Ljava/lang/StringBuilder;
/*    */     //   1838: pop
/*    */     //   1839: arraylength
/*    */     //   1840: iconst_1
/*    */     //   1841: if_icmple -> 1852
/*    */     //   1844: sipush #2531
/*    */     //   1847: istore #4
/*    */     //   1849: goto -> 1857
/*    */     //   1852: sipush #2530
/*    */     //   1855: istore #4
/*    */     //   1857: aload_0
/*    */     //   1858: dup
/*    */     //   1859: dup
/*    */     //   1860: aload_2
/*    */     //   1861: iload #4
/*    */     //   1863: aload_3
/*    */     //   1864: getfield Iu : I
/*    */     //   1867: invokestatic OH0 : (I)Ljava/lang/String;
/*    */     //   1870: invokestatic Go : (ILjava/lang/String;)Ljava/lang/String;
/*    */     //   1873: invokevirtual append : (Ljava/lang/String;)Ljava/lang/StringBuilder;
/*    */     //   1876: pop
/*    */     //   1877: getfield Q00 : [Lf/dQ;
/*    */     //   1880: iconst_1
/*    */     //   1881: aaload
/*    */     //   1882: aload_1
/*    */     //   1883: invokevirtual toString : ()Ljava/lang/String;
/*    */     //   1886: invokevirtual E1 : (Ljava/lang/String;)V
/*    */     //   1889: getfield Q00 : [Lf/dQ;
/*    */     //   1892: iconst_1
/*    */     //   1893: aaload
/*    */     //   1894: aload_2
/*    */     //   1895: invokevirtual toString : ()Ljava/lang/String;
/*    */     //   1898: invokevirtual Gq0 : (Ljava/lang/Object;)V
/*    */     //   1901: getfield Q00 : [Lf/dQ;
/*    */     //   1904: iconst_1
/*    */     //   1905: aaload
/*    */     //   1906: ldc_w 'shared-value-green'
/*    */     //   1909: invokevirtual Xu : (Ljava/lang/String;)V
/*    */     //   1912: iload #9
/*    */     //   1914: aload_0
/*    */     //   1915: getfield R90 : [Lf/dQ;
/*    */     //   1918: iconst_1
/*    */     //   1919: aaload
/*    */     //   1920: aconst_null
/*    */     //   1921: invokevirtual Gq0 : (Ljava/lang/Object;)V
/*    */     //   1924: ifne -> 1967
/*    */     //   1927: aload_0
/*    */     //   1928: dup
/*    */     //   1929: getfield R90 : [Lf/dQ;
/*    */     //   1932: iconst_1
/*    */     //   1933: aaload
/*    */     //   1934: getstatic f/km.a3 : Lf/vh0;
/*    */     //   1937: getfield Ct : Lf/Jo;
/*    */     //   1940: getfield ED0 : Ljava/lang/String;
/*    */     //   1943: sipush #2539
/*    */     //   1946: swap
/*    */     //   1947: invokestatic Go : (ILjava/lang/String;)Ljava/lang/String;
/*    */     //   1950: invokevirtual E1 : (Ljava/lang/String;)V
/*    */     //   1953: getfield R90 : [Lf/dQ;
/*    */     //   1956: iconst_1
/*    */     //   1957: aaload
/*    */     //   1958: ldc_w 'shared-value-green'
/*    */     //   1961: invokevirtual Xu : (Ljava/lang/String;)V
/*    */     //   1964: goto -> 2083
/*    */     //   1967: iload #9
/*    */     //   1969: iconst_1
/*    */     //   1970: if_icmpne -> 2057
/*    */     //   1973: aload_0
/*    */     //   1974: dup
/*    */     //   1975: dup2
/*    */     //   1976: getfield R90 : [Lf/dQ;
/*    */     //   1979: iconst_1
/*    */     //   1980: aaload
/*    */     //   1981: new java/lang/StringBuilder
/*    */     //   1984: dup
/*    */     //   1985: invokespecial <init> : ()V
/*    */     //   1988: getstatic f/km.a3 : Lf/vh0;
/*    */     //   1991: getfield Ct : Lf/Jo;
/*    */     //   1994: getfield ED0 : Ljava/lang/String;
/*    */     //   1997: invokevirtual append : (Ljava/lang/String;)Ljava/lang/StringBuilder;
/*    */     //   2000: ldc_w ' *'
/*    */     //   2003: invokevirtual append : (Ljava/lang/String;)Ljava/lang/StringBuilder;
/*    */     //   2006: invokevirtual toString : ()Ljava/lang/String;
/*    */     //   2009: sipush #2539
/*    */     //   2012: swap
/*    */     //   2013: invokestatic Go : (ILjava/lang/String;)Ljava/lang/String;
/*    */     //   2016: invokevirtual E1 : (Ljava/lang/String;)V
/*    */     //   2019: getfield R90 : [Lf/dQ;
/*    */     //   2022: iconst_1
/*    */     //   2023: aaload
/*    */     //   2024: ldc 'shared-value'
/*    */     //   2026: invokevirtual Xu : (Ljava/lang/String;)V
/*    */     //   2029: getfield R90 : [Lf/dQ;
/*    */     //   2032: iconst_1
/*    */     //   2033: aaload
/*    */     //   2034: sipush #2538
/*    */     //   2037: invokestatic OH0 : (I)Ljava/lang/String;
/*    */     //   2040: invokevirtual Gq0 : (Ljava/lang/Object;)V
/*    */     //   2043: getfield R90 : [Lf/dQ;
/*    */     //   2046: iconst_1
/*    */     //   2047: aaload
/*    */     //   2048: sipush #150
/*    */     //   2051: putfield jl : I
/*    */     //   2054: goto -> 2083
/*    */     //   2057: aload_0
/*    */     //   2058: dup
/*    */     //   2059: getfield R90 : [Lf/dQ;
/*    */     //   2062: iconst_1
/*    */     //   2063: aaload
/*    */     //   2064: sipush #2540
/*    */     //   2067: invokestatic OH0 : (I)Ljava/lang/String;
/*    */     //   2070: invokevirtual E1 : (Ljava/lang/String;)V
/*    */     //   2073: getfield R90 : [Lf/dQ;
/*    */     //   2076: iconst_1
/*    */     //   2077: aaload
/*    */     //   2078: ldc 'shared-value'
/*    */     //   2080: invokevirtual Xu : (Ljava/lang/String;)V
/*    */     //   2083: aload_0
/*    */     //   2084: getstatic f/UB0.Kg0 : Lf/Q50;
/*    */     //   2087: aload_0
/*    */     //   2088: <illegal opcode> run : (Lf/GV;)Ljava/lang/Runnable;
/*    */     //   2093: invokevirtual fN : (Ljava/lang/Runnable;)V
/*    */     //   2096: iconst_1
/*    */     //   2097: iconst_1
/*    */     //   2098: invokevirtual r10 : (IZ)V
/*    */     //   2101: return
/*    */     //   2102: return
/*    */     //   2103: return
/*    */     // Line number table:
/*    */     //   Java source line number -> byte code offset
/*    */     //   #1	-> 21
/*    */     //   #2	-> 26
/*    */     //   #3	-> 54
/*    */     //   #4	-> 59
/*    */     //   #5	-> 74
/*    */     //   #6	-> 91
/*    */     //   #7	-> 125
/*    */     //   #8	-> 128
/*    */     //   #9	-> 148
/*    */     //   #10	-> 156
/*    */     //   #11	-> 159
/*    */     //   #12	-> 166
/*    */     //   #13	-> 174
/*    */     //   #14	-> 177
/*    */     //   #15	-> 192
/*    */     //   #16	-> 203
/*    */     //   #17	-> 213
/*    */     //   #18	-> 220
/*    */     //   #19	-> 231
/*    */     //   #20	-> 234
/*    */     //   #21	-> 249
/*    */     //   #22	-> 252
/*    */     //   #23	-> 261
/*    */     //   #24	-> 277
/*    */     //   #25	-> 285
/*    */     //   #26	-> 288
/*    */     //   #27	-> 294
/*    */     //   #28	-> 331
/*    */     //   #29	-> 334
/*    */     //   #30	-> 340
/*    */     //   #31	-> 420
/*    */     //   #32	-> 423
/*    */     //   #33	-> 475
/*    */     //   #34	-> 488
/*    */     //   #35	-> 491
/*    */     //   #36	-> 492
/*    */     //   #37	-> 499
/*    */     //   #38	-> 506
/*    */     //   #39	-> 509
/*    */     //   #40	-> 527
/*    */     //   #41	-> 530
/*    */     //   #42	-> 573
/*    */     //   #43	-> 576
/*    */     //   #44	-> 577
/*    */     //   #45	-> 583
/*    */     //   #46	-> 624
/*    */     //   #47	-> 633
/*    */     //   #48	-> 697
/*    */     //   #49	-> 770
/*    */     //   #50	-> 775
/*    */     //   #51	-> 843
/*    */     //   #52	-> 851
/*    */     //   #53	-> 864
/*    */     //   #54	-> 873
/*    */     //   #55	-> 876
/*    */     //   #56	-> 909
/*    */     //   #57	-> 931
/*    */     //   #58	-> 941
/*    */     //   #59	-> 967
/*    */     //   #60	-> 973
/*    */     //   #61	-> 1031
/*    */     //   #62	-> 1045
/*    */     //   #63	-> 1222
/*    */     //   #64	-> 1225
/*    */     //   #65	-> 1274
/*    */     //   #66	-> 1277
/*    */     //   #67	-> 1325
/*    */     //   #68	-> 1328
/*    */     //   #69	-> 1339
/*    */     //   #70	-> 1342
/*    */     //   #71	-> 1343
/*    */     //   #72	-> 1357
/*    */     //   #73	-> 1362
/*    */     //   #74	-> 1376
/*    */     //   #75	-> 1386
/*    */     //   #76	-> 1405
/*    */     //   #77	-> 1413
/*    */     //   #78	-> 1423
/*    */     //   #79	-> 1434
/*    */     //   #80	-> 1445
/*    */     //   #81	-> 1457
/*    */     //   #82	-> 1460
/*    */     //   #83	-> 1540
/*    */     //   #84	-> 1546
/*    */     //   #85	-> 1822
/*    */     //   #86	-> 1828
/*    */     //   #87	-> 1864
/*    */     //   #88	-> 1870
/*    */     //   #89	-> 1937
/*    */     //   #90	-> 1940
/*    */     //   #91	-> 1947
/*    */     //   #92	-> 1991
/*    */     //   #93	-> 1994
/*    */     //   #94	-> 1997
/*    */     //   #95	-> 2051
/*    */     //   #96	-> 2059
/*    */   }
/*    */   
/*    */   public final void sJ(int paramInt1, int paramInt2) {
/*    */     if (paramInt1 < 0)
/*    */       paramInt1 = 0; 
/*    */     Un[][] arrayOfUn;
/*    */     if (paramInt1 >= (arrayOfUn = this.xe0).length)
/*    */       paramInt1 = arrayOfUn.length - 1; 
/*    */     if (paramInt2 < 0)
/*    */       paramInt2 = 0; 
/*    */     Un[] arrayOfUn1;
/*    */     if (paramInt2 >= (arrayOfUn1 = arrayOfUn[paramInt1]).length)
/*    */       paramInt2 = arrayOfUn1.length - 1; 
/*    */     Un un;
/*    */     if (!(un = arrayOfUn1[paramInt2]).dP) {
/*    */       un = null;
/*    */     } else {
/*    */       this.I80 = paramInt2;
/*    */       this.nb0 = paramInt1;
/*    */     } 
/*    */     if (un == null)
/*    */       return; 
/*    */     VA0.c90(arrayOfUn[this.nb0][this.I80]);
/*    */   }
/*    */   
/*    */   public final boolean i2(oa0 paramoa0) {
/*    */     // Byte code:
/*    */     //   0: aload_1
/*    */     //   1: getfield cz0 : I
/*    */     //   4: invokestatic Wm0 : (I)Z
/*    */     //   7: ifeq -> 282
/*    */     //   10: aload_1
/*    */     //   11: invokevirtual oO : ()Z
/*    */     //   14: ifeq -> 282
/*    */     //   17: aload_1
/*    */     //   18: getfield GG0 : I
/*    */     //   21: dup
/*    */     //   22: istore_2
/*    */     //   23: getstatic f/BM.Oq : Lf/BM;
/*    */     //   26: invokestatic J20 : (ILf/BM;)Z
/*    */     //   29: ifeq -> 48
/*    */     //   32: aload_0
/*    */     //   33: dup
/*    */     //   34: getfield nb0 : I
/*    */     //   37: aload_0
/*    */     //   38: getfield I80 : I
/*    */     //   41: iconst_1
/*    */     //   42: isub
/*    */     //   43: invokevirtual sJ : (II)V
/*    */     //   46: iconst_1
/*    */     //   47: ireturn
/*    */     //   48: iload_2
/*    */     //   49: getstatic f/BM.M8 : Lf/BM;
/*    */     //   52: invokestatic J20 : (ILf/BM;)Z
/*    */     //   55: ifeq -> 74
/*    */     //   58: aload_0
/*    */     //   59: dup
/*    */     //   60: getfield nb0 : I
/*    */     //   63: aload_0
/*    */     //   64: getfield I80 : I
/*    */     //   67: iconst_1
/*    */     //   68: iadd
/*    */     //   69: invokevirtual sJ : (II)V
/*    */     //   72: iconst_1
/*    */     //   73: ireturn
/*    */     //   74: iload_2
/*    */     //   75: getstatic f/BM.ni : Lf/BM;
/*    */     //   78: invokestatic J20 : (ILf/BM;)Z
/*    */     //   81: ifeq -> 103
/*    */     //   84: aload_0
/*    */     //   85: dup
/*    */     //   86: dup
/*    */     //   87: getfield nb0 : I
/*    */     //   90: iconst_1
/*    */     //   91: isub
/*    */     //   92: istore_0
/*    */     //   93: getfield I80 : I
/*    */     //   96: iload_0
/*    */     //   97: swap
/*    */     //   98: invokevirtual sJ : (II)V
/*    */     //   101: iconst_1
/*    */     //   102: ireturn
/*    */     //   103: iload_2
/*    */     //   104: getstatic f/BM.N70 : Lf/BM;
/*    */     //   107: invokestatic J20 : (ILf/BM;)Z
/*    */     //   110: ifeq -> 132
/*    */     //   113: aload_0
/*    */     //   114: dup
/*    */     //   115: dup
/*    */     //   116: getfield nb0 : I
/*    */     //   119: iconst_1
/*    */     //   120: iadd
/*    */     //   121: istore_0
/*    */     //   122: getfield I80 : I
/*    */     //   125: iload_0
/*    */     //   126: swap
/*    */     //   127: invokevirtual sJ : (II)V
/*    */     //   130: iconst_1
/*    */     //   131: ireturn
/*    */     //   132: iload_2
/*    */     //   133: getstatic f/BM.bC : Lf/BM;
/*    */     //   136: invokestatic J20 : (ILf/BM;)Z
/*    */     //   139: ifeq -> 173
/*    */     //   142: aload_0
/*    */     //   143: getfield xe0 : [[Lf/Un;
/*    */     //   146: aload_0
/*    */     //   147: getfield nb0 : I
/*    */     //   150: aaload
/*    */     //   151: aload_0
/*    */     //   152: getfield I80 : I
/*    */     //   155: aaload
/*    */     //   156: dup
/*    */     //   157: astore_0
/*    */     //   158: ifnull -> 171
/*    */     //   161: aload_0
/*    */     //   162: getfield TG0 : Lf/protected;
/*    */     //   165: getfield oh0 : [Ljava/lang/Runnable;
/*    */     //   168: invokestatic Fz0 : ([Ljava/lang/Runnable;)V
/*    */     //   171: iconst_1
/*    */     //   172: ireturn
/*    */     //   173: iload_2
/*    */     //   174: getstatic f/BM.lc : Lf/BM;
/*    */     //   177: invokestatic J20 : (ILf/BM;)Z
/*    */     //   180: ifeq -> 282
/*    */     //   183: aload_0
/*    */     //   184: getfield TG0 : [Lf/Qv0;
/*    */     //   187: iconst_2
/*    */     //   188: aaload
/*    */     //   189: invokevirtual public : ()Lf/j40;
/*    */     //   192: ifnull -> 237
/*    */     //   195: aload_0
/*    */     //   196: dup
/*    */     //   197: dup2
/*    */     //   198: dup2
/*    */     //   199: iconst_0
/*    */     //   200: iconst_0
/*    */     //   201: invokevirtual sJ : (II)V
/*    */     //   204: getfield TG0 : [Lf/Qv0;
/*    */     //   207: iconst_1
/*    */     //   208: aaload
/*    */     //   209: aconst_null
/*    */     //   210: invokevirtual zf : (Lf/j40;)V
/*    */     //   213: iconst_1
/*    */     //   214: iconst_0
/*    */     //   215: invokevirtual r10 : (IZ)V
/*    */     //   218: getfield TG0 : [Lf/Qv0;
/*    */     //   221: iconst_2
/*    */     //   222: aaload
/*    */     //   223: aconst_null
/*    */     //   224: invokevirtual zf : (Lf/j40;)V
/*    */     //   227: iconst_2
/*    */     //   228: iconst_0
/*    */     //   229: invokevirtual r10 : (IZ)V
/*    */     //   232: invokevirtual update : ()V
/*    */     //   235: iconst_1
/*    */     //   236: ireturn
/*    */     //   237: aload_0
/*    */     //   238: getfield TG0 : [Lf/Qv0;
/*    */     //   241: iconst_0
/*    */     //   242: aaload
/*    */     //   243: invokevirtual public : ()Lf/j40;
/*    */     //   246: ifnull -> 276
/*    */     //   249: aload_0
/*    */     //   250: dup
/*    */     //   251: dup2
/*    */     //   252: iconst_0
/*    */     //   253: iconst_0
/*    */     //   254: invokevirtual sJ : (II)V
/*    */     //   257: getfield TG0 : [Lf/Qv0;
/*    */     //   260: iconst_0
/*    */     //   261: aaload
/*    */     //   262: aconst_null
/*    */     //   263: invokevirtual zf : (Lf/j40;)V
/*    */     //   266: iconst_0
/*    */     //   267: iconst_0
/*    */     //   268: invokevirtual r10 : (IZ)V
/*    */     //   271: invokevirtual update : ()V
/*    */     //   274: iconst_1
/*    */     //   275: ireturn
/*    */     //   276: aload_0
/*    */     //   277: invokevirtual KG0 : ()V
/*    */     //   280: iconst_1
/*    */     //   281: ireturn
/*    */     //   282: aload_0
/*    */     //   283: aload_1
/*    */     //   284: invokespecial i2 : (Lf/oa0;)Z
/*    */     //   287: ireturn
/*    */     // Line number table:
/*    */     //   Java source line number -> byte code offset
/*    */     //   #1	-> 1
/*    */     //   #2	-> 4
/*    */     //   #3	-> 11
/*    */     //   #4	-> 18
/*    */     //   #5	-> 23
/*    */     //   #6	-> 143
/*    */     //   #7	-> 162
/*    */     //   #8	-> 165
/*    */     //   #9	-> 168
/*    */     //   #10	-> 174
/*    */     //   #11	-> 204
/*    */     //   #12	-> 218
/*    */   }
/*    */   
/*    */   public final void d40() {
/*    */     if (km.XU())
/*    */       QI(); 
/*    */     super.d40();
/*    */     if (!km.XU() && !this.av) {
/*    */       this.av = true;
/*    */       js0(et.Wi0);
/*    */     } 
/*    */   }
/*    */   
/*    */   public final boolean Cb(short paramShort, boolean paramBoolean, j40 paramj40) {
/*    */     if (paramj40 == null)
/*    */       return true; 
/*    */     if (paramj40.Zs.YC())
/*    */       return false; 
/*    */     j40 j401 = this.TG0[0].public(), j402 = this.TG0[2].public();
/*    */     if ((paramShort == 2 && this.Jg == paramj40.Jg) || (paramShort == 0 && j402 != null && j402.Jg == paramj40.Jg)) {
/*    */       if (paramBoolean)
/*    */         js.vu0.Pu(-1, Ml0.OH0(2549)); 
/*    */       return false;
/*    */     } 
/*    */     return true;
/*    */   } }


/* Location:              /Users/vnnsnnt/Documents/Codespace/JavaWorkspace/RedTrainer/src/main/java/org/trainer/client/PokeMMO.jar!/f/GV.class
 * Java compiler version: 8 (52.0)
 * JD-Core Version:       1.1.3
 */