/*  1 */ package f;public final class gx extends JG0 { public final Ip QS; public final dQ Uf0; public final dQ Vd; public final dQ Ug; private void IX(int paramInt) { (this.B[0][paramInt]).TS
/*    */ 
/*    */ 
/*    */       
/*  5 */       .sm(new zh0[] { RP.fB0.Up0[0] }); (this.B[1][paramInt])
/*  6 */       .TS
/*    */ 
/*    */ 
/*    */       
/* 10 */       .sm(new zh0[] { RP.fB0.Up0[2] }); } public final dQ CD0; public final vF0[][] B; public final int[] Uv; public gx(String paramString1, String paramString2) { dQ dQ1; dQ dQ2; dQ dQ3; dQ dQ4; dQ dQ5; this.Uv = new int[2]; Xu("setko-judge"); (this.QS = new Ip()).Xu("setko-judge-dialog"); (new Ip()).Tm(450, 270); Tm(450, 270); this.Uf0 = new dQ(paramString1); this.Vd = new dQ(paramString2); this.Ug = new dQ("0"); this.CD0 = new dQ("0"); this(Ml0.OH0(206101)); this(Ml0.OH0(206103)); this(Ml0.OH0(206104)); this(Ml0.OH0(206105)); byte[] arrayOfByte; (arrayOfByte = new byte[2])[0] = 0; (new byte[2])[1] = 1; String[] arrayOfString; (arrayOfString = new String[2])[0] = ""; (new String[2])[1] = ""; this(Ml0.Nq0(206106, arrayOfByte, arrayOfString)); this.B = new vF0[2][3]; for (byte b2 = 0; b2 < 3; b2++) { vF0 vF01; this(16, 16); this.B[0][b2] = vF01; this(16, 16); this.B[1][b2] = vF01; this.B[0][b2].ZH0().Ii0(2.0F); this.B[1][b2].ZH0().Ii0(2.0F); this.B[0][b2].ZH0().zT(-10, 0); this.B[1][b2].ZH0().zT(-10, 0); }  arrayOfJG02[0] = this.Uf0; arrayOfJG02[1] = arrayOfVF01[0]; arrayOfJG02[2] = arrayOfVF01[1]; vF0[] arrayOfVF01; arrayOfJG02[3] = (arrayOfVF01 = this.B[0])[2]; JG0[] arrayOfJG02; (arrayOfJG02 = new JG0[5])[4] = this.Ug; arrayOfU902[0] = this.QS.mE0().Mg(new JG0[5]); arrayOfU902[1] = this.QS.mE0().Mg(new JG0[] { dQ1, dQ2, dQ3, dQ4, dQ5 }); arrayOfJG02[0] = this.Vd; arrayOfJG02[1] = this.B[1][0]; arrayOfJG02[2] = this.B[1][1]; arrayOfJG02[3] = this.B[1][2]; (arrayOfJG02 = new JG0[5])[4] = this.CD0; U90[] arrayOfU902; (arrayOfU902 = new U90[3])[2] = this.QS.mE0().Mg(new JG0[5]); this.QS.rK0(this.QS.d7().cOM8(new U90[3])); arrayOfU901[0] = this.QS.mE0().Mg(new JG0[] { this.Uf0, dQ1, this.Vd }); arrayOfJG01[0] = arrayOfVF0[0][0]; arrayOfJG01[1] = dQ2; JG0[] arrayOfJG01; vF0[][] arrayOfVF0; (arrayOfJG01 = new JG0[3])[2] = (arrayOfVF0 = this.B)[1][0]; arrayOfU901[1] = this.QS.mE0().Mg(new JG0[3]); arrayOfJG01[0] = arrayOfVF0[0][1]; arrayOfJG01[1] = dQ3; (arrayOfJG01 = new JG0[3])[2] = (arrayOfVF0 = this.B)[1][1]; arrayOfU901[2] = this.QS.mE0().Mg(new JG0[3]); arrayOfJG01[0] = arrayOfVF0[0][2]; arrayOfJG01[1] = dQ4; (arrayOfJG01 = new JG0[3])[2] = (arrayOfVF0 = this.B)[1][2]; arrayOfU901[3] = this.QS.mE0().Mg(new JG0[3]); U90[] arrayOfU901; (arrayOfU901 = new U90[5])[4] = this.QS.mE0().Mg(new JG0[] { this.Ug, dQ5, this.CD0 }); this.QS.WN(this.QS.d7().cOM8(new U90[5])); J8(this.QS); et et; this.QS.hJ0(et = et.kL0, dQ1); this.QS.hJ0(et, dQ2); this.QS.hJ0(et, dQ3); this.QS.hJ0(et, dQ4); this.QS.hJ0(et, dQ5); this.QS.hJ0(et, this.Ug); this.QS.hJ0(et, this.CD0); for (byte b1 = 0; b1 < 3; b1++) { dQ2 = this.B[0][b1]; et et1; this.QS.hJ0(et1 = et.kL0, dQ2); this.QS.hJ0(et1, this.B[1][b1]); }  mM(); } private void vF0(int paramInt) { (this.B[0][paramInt]).TS.sm(new zh0[] { RP.fB0.Up0[2] }); (this.B[1][paramInt]).TS.sm(new zh0[] { RP.fB0.Up0[0] }); } private void va0(int paramInt) { (this.B[0][paramInt]).TS.sm(new zh0[] { RP.fB0.Up0[1] }); (this.B[1][paramInt]).TS.sm(new zh0[] { RP.fB0.Up0[1] }); }
/*    */ 
/*    */   
/*    */   public final void kf0(int paramInt, byte[][] paramArrayOfbyte) {
/*    */     // Byte code:
/*    */     //   0: aload_2
/*    */     //   1: iconst_0
/*    */     //   2: aaload
/*    */     //   3: iload_1
/*    */     //   4: baload
/*    */     //   5: dup
/*    */     //   6: istore_3
/*    */     //   7: aload_2
/*    */     //   8: iconst_1
/*    */     //   9: aaload
/*    */     //   10: iload_1
/*    */     //   11: baload
/*    */     //   12: dup
/*    */     //   13: istore_2
/*    */     //   14: if_icmpne -> 53
/*    */     //   17: aload_0
/*    */     //   18: getfield Uv : [I
/*    */     //   21: dup
/*    */     //   22: dup2
/*    */     //   23: iconst_0
/*    */     //   24: iaload
/*    */     //   25: iconst_1
/*    */     //   26: iadd
/*    */     //   27: iconst_0
/*    */     //   28: swap
/*    */     //   29: iastore
/*    */     //   30: iconst_1
/*    */     //   31: iaload
/*    */     //   32: iconst_1
/*    */     //   33: iadd
/*    */     //   34: iconst_1
/*    */     //   35: swap
/*    */     //   36: iastore
/*    */     //   37: getstatic f/UB0.Kg0 : Lf/Q50;
/*    */     //   40: aload_0
/*    */     //   41: iload_1
/*    */     //   42: <illegal opcode> run : (Lf/gx;I)Ljava/lang/Runnable;
/*    */     //   47: invokevirtual fN : (Ljava/lang/Runnable;)V
/*    */     //   50: goto -> 111
/*    */     //   53: iload_3
/*    */     //   54: iload_2
/*    */     //   55: if_icmple -> 86
/*    */     //   58: aload_0
/*    */     //   59: getfield Uv : [I
/*    */     //   62: dup
/*    */     //   63: iconst_0
/*    */     //   64: iaload
/*    */     //   65: iconst_2
/*    */     //   66: iadd
/*    */     //   67: iconst_0
/*    */     //   68: swap
/*    */     //   69: iastore
/*    */     //   70: getstatic f/UB0.Kg0 : Lf/Q50;
/*    */     //   73: aload_0
/*    */     //   74: iload_1
/*    */     //   75: <illegal opcode> run : (Lf/gx;I)Ljava/lang/Runnable;
/*    */     //   80: invokevirtual fN : (Ljava/lang/Runnable;)V
/*    */     //   83: goto -> 111
/*    */     //   86: aload_0
/*    */     //   87: getfield Uv : [I
/*    */     //   90: dup
/*    */     //   91: iconst_1
/*    */     //   92: iaload
/*    */     //   93: iconst_2
/*    */     //   94: iadd
/*    */     //   95: iconst_1
/*    */     //   96: swap
/*    */     //   97: iastore
/*    */     //   98: getstatic f/UB0.Kg0 : Lf/Q50;
/*    */     //   101: aload_0
/*    */     //   102: iload_1
/*    */     //   103: <illegal opcode> run : (Lf/gx;I)Ljava/lang/Runnable;
/*    */     //   108: invokevirtual fN : (Ljava/lang/Runnable;)V
/*    */     //   111: aload_0
/*    */     //   112: dup
/*    */     //   113: getfield Ug : Lf/dQ;
/*    */     //   116: ldc ''
/*    */     //   118: invokestatic df : (Ljava/lang/String;)Ljava/lang/StringBuilder;
/*    */     //   121: aload_0
/*    */     //   122: getfield Uv : [I
/*    */     //   125: iconst_0
/*    */     //   126: iaload
/*    */     //   127: invokevirtual append : (I)Ljava/lang/StringBuilder;
/*    */     //   130: invokevirtual toString : ()Ljava/lang/String;
/*    */     //   133: invokevirtual E1 : (Ljava/lang/String;)V
/*    */     //   136: getfield CD0 : Lf/dQ;
/*    */     //   139: ldc ''
/*    */     //   141: invokestatic df : (Ljava/lang/String;)Ljava/lang/StringBuilder;
/*    */     //   144: aload_0
/*    */     //   145: getfield Uv : [I
/*    */     //   148: iconst_1
/*    */     //   149: iaload
/*    */     //   150: invokevirtual append : (I)Ljava/lang/StringBuilder;
/*    */     //   153: invokevirtual toString : ()Ljava/lang/String;
/*    */     //   156: invokevirtual E1 : (Ljava/lang/String;)V
/*    */     //   159: return
/*    */     // Line number table:
/*    */     //   Java source line number -> byte code offset
/*    */     //   #1	-> 116
/*    */     //   #2	-> 122
/*    */     //   #3	-> 139
/*    */     //   #4	-> 145
/*    */   }
/*    */   
/*    */   public final void d40() {
/*    */     ME(km.wI0.dG() / 2 - this.xY / 2, km.wI0.k1() / 2 - this.HC / 2 - 100);
/*    */   } }


/* Location:              /Users/vnnsnnt/Documents/Codespace/JavaWorkspace/RedTrainer/src/main/java/org/trainer/client/PokeMMO.jar!/f/gx.class
 * Java compiler version: 8 (52.0)
 * JD-Core Version:       1.1.3
 */