/* 1 */ package f;public final class h00 extends JS { public static void Wu(kf paramkf, hm0 paramhm0) { this(paramhm0); LV lV; Gr0 gr0; mw mw; this((byte)0, mw); paramkf.YP
/* 2 */       .add(lV);
/* 3 */     this(paramhm0, paramkf.oD(paramhm0));
/* 4 */     paramkf.YP.add(gr0); }
/*   */ 
/*   */   
/*   */   public h00(short paramShort) {
/*   */     super(paramShort);
/*   */   }
/*   */   
/*   */   public final byte YG0() {
/*   */     return -26;
/*   */   }
/*   */   
/*   */   public final void Nl(hm0 paramhm01, hm0 paramhm02, boolean paramBoolean1, boolean paramBoolean2, short paramShort, boolean paramBoolean3, kf paramkf, b60 paramb60) {
/*   */     // Byte code:
/*   */     //   0: aload #7
/*   */     //   2: dup
/*   */     //   3: aload_2
/*   */     //   4: dup
/*   */     //   5: dup
/*   */     //   6: aload_0
/*   */     //   7: getfield cOM9 : S
/*   */     //   10: invokevirtual tx : (S)V
/*   */     //   13: invokevirtual coM1 : ()Ljava/lang/String;
/*   */     //   16: ldc 200520
/*   */     //   18: swap
/*   */     //   19: invokestatic Go : (ILjava/lang/String;)Ljava/lang/String;
/*   */     //   22: astore_0
/*   */     //   23: <illegal opcode> run : (Lf/kf;Lf/hm0;)Ljava/lang/Runnable;
/*   */     //   28: astore_1
/*   */     //   29: aload_0
/*   */     //   30: ldc ''
/*   */     //   32: aload_1
/*   */     //   33: invokevirtual r00 : (Ljava/lang/String;Ljava/lang/String;Ljava/lang/Runnable;)V
/*   */     //   36: return
/*   */     // Line number table:
/*   */     //   Java source line number -> byte code offset
/*   */     //   #1	-> 7
/*   */     //   #2	-> 10
/*   */     //   #3	-> 30
/*   */   } }


/* Location:              /Users/vnnsnnt/Documents/Codespace/JavaWorkspace/RedTrainer/src/main/java/org/trainer/client/PokeMMO.jar!/f/h00.class
 * Java compiler version: 8 (52.0)
 * JD-Core Version:       1.1.3
 */