/*  1 */ package f;public class h1 { public static final ik A4 = C00.gd(h1.class); public static final int NU = 0; public static final int OA0 = 1; public static final int ax0 = 2; public static final int coN = -1; @mB0(key = "client.roms.fr", defaultValue = "") public static String Pq = ""; @mB0(key = "client.roms.em", defaultValue = "") public static String Vh = ""; @mB0(key = "client.roms.nds", defaultValue = "") public static String h0 = ""; @mB0(key = "client.roms.nds2", defaultValue = "") public static String yD0 = ""; @mB0(key = "client.roms.nds3", defaultValue = "") public static String Re0 = ""; @mB0(key = "client.graphics.width", defaultValue = "1024") public static int tR; @mB0(key = "client.graphics.height", defaultValue = "768") public static int wd0; @mB0(key = "client.graphics.vsync", defaultValue = "false") public static boolean ru0; @mB0(key = "client.graphics.display_mode", defaultValue = "0") public static byte c20; @mB0(key = "client.graphics.maximized", defaultValue = "true") public static boolean IE0; @mB0(key = "client.graphics.xpos", defaultValue = "-1") public static int XO; @mB0(key = "client.graphics.ypos", defaultValue = "-1") public static int da0; @mB0(key = "client.graphics.desktop.fullscreen_monitor", defaultValue = "") public static String LA0 = ""; @mB0(key = "client.graphics.max_fpx", defaultValue = "60") public static int dB0; @mB0(key = "client.graphics.max_fpx_unfocused", defaultValue = "20") public static int AC0; @mB0(key = "client.graphics.show_fps", defaultValue = "false") public static boolean Lf0; @mB0(key = "client.graphics.graphics_api", defaultValue = "OpenGL") public static String ev; @mB0(key = "client.graphics.msaa_samples", defaultValue = "0") public static int Vu0; @mB0(key = "client.graphics.android.immersive_mode", defaultValue = "true") public static boolean WX; @mB0(key = "client.graphics.max_visible_players", defaultValue = "-1") public static int y00; @mB0(key = "client.graphics.disabled.ow.particles", defaultValue = "false") public static boolean Vy; @mB0(key = "client.graphics.battle.flash.animation", defaultValue = "true") public static boolean SZ; @mB0(key = "client.graphics.gba.zoom_level", defaultValue = "-1") public static int b40; @mB0(key = "client.graphics.nds.reduced_fov", defaultValue = "false") public static boolean hR; @mB0(key = "client.graphics.desktop.macos.enable_low_power_gfx", defaultValue = "false") public static boolean qL; @mB0(key = "client.graphics.nds.hgss_sprites_enabled_in_gba", defaultValue = "true") public static boolean X2; @mB0(key = "client.graphics.shader_quality", defaultValue = "1") public static int YJ; @mB0(key = "client.graphics.battle_sprites.render_scale.front", defaultValue = "2") public static int UD0; @mB0(key = "client.graphics.battle_sprites.render_scale.back", defaultValue = "3") public static int Wx0; @mB0(key = "client.gui.hud.hidden", defaultValue = "false") public static boolean mD0; @mB0(key = "client.gui.hud.chatframe.locked", defaultValue = "false") public static boolean JF; @mB0(key = "client.gui.hud.chatframe.x", defaultValue = "0") public static int S9; @mB0(key = "client.gui.hud.chatframe.y", defaultValue = "0") public static int Ba0; @mB0(key = "client.gui.hud.chatframe.width", defaultValue = "400") public static int Ke0; @mB0(key = "client.gui.hud.chatframe.height", defaultValue = "200") public static int CR; @mB0(key = "client.gui.hud.hotkeybar.x", defaultValue = "250") public static int mG; @mB0(key = "client.gui.hud.hotkeybar.y", defaultValue = "0") public static int yc; @mB0(key = "client.gui.hud.playereffectsframe.x", defaultValue = "244") public static int YV; @mB0(key = "client.gui.hud.playereffectsframe.y", defaultValue = "56") public static int AI; @mB0(key = "client.gui.gm-hud.direction-menu.x", defaultValue = "-1") public static int O40; @mB0(key = "client.gui.gm-hud.direction-menu.y", defaultValue = "-1") public static int EZ; @mB0(key = "client.ui.battle.notification", defaultValue = "true") public static boolean me0; @mB0(key = "client.gui.showchatbubbles", defaultValue = "true") public static boolean bf; @mB0(key = "client.gui.inset.mode", defaultValue = "1") public static int B30; @mB0(key = "client.gui.apply.insets", defaultValue = "true") public static boolean pw; @mB0(key = "client.gui.scale.guiscale", defaultValue = "1") public static float zA0; @mB0(key = "client.gui.scale.hidpifont", defaultValue = "true") public static boolean ho; @mB0(key = "client.gui.scale.cjkfonts", defaultValue = "true") public static boolean VV; @mB0(key = "client.gui.swcursor", defaultValue = "false") public static boolean IC0; @mB0(key = "client.graphics.render.battlebg", defaultValue = "true") public static boolean bp0; @mB0(key = "client.graphics.render_border", defaultValue = "true") public static boolean gt0; @mB0(key = "client.graphics.render.overworld_in_battle", defaultValue = "true") public static boolean zR; @mB0(key = "client.graphics.battle.size", defaultValue = "100") public static int Ju0; @mB0(key = "client.controls.gdx.key_a") public static int o5 = BM.bC.L00; public static void ab() { this(); V6 v6; if (!(new V6()).uX(o5)) o5 = 0;  if (!v6.uX(nUL)) nUL = 0;  if (!v6.uX(Wa0)) Wa0 = 0;  if (!v6.uX(Ll)) Ll = 0;  if (!v6.uX(SJ0)) SJ0 = 0;  if (!v6.uX(wu)) wu = 0;  if (!v6.uX(Qd0)) Qd0 = 0;  if (!v6.uX(Gu)) Gu = 0;  if (!v6.uX(Zj0)) Zj0 = 0;  if (!v6.uX(UC0)) UC0 = 0;  if (!v6.uX(om0)) om0 = 0;  if (!v6.uX(ey)) ey = 0;  if (!v6.uX(g6)) g6 = 0;  if (!v6.uX(c80)) c80 = 0;  if (!v6.uX(WK0)) WK0 = 0;  if (!v6.uX(Sv0)) Sv0 = 0;  if (!v6.uX(Yu0)) Yu0 = 0;  if (!v6.uX(COn)) COn = 0;  if (!v6.uX(lpt4)) lpt4 = 0;  if (!v6.uX(NC)) NC = 0;  if (!v6.uX(Mm0)) Mm0 = 0;  if (!v6.uX(w30)) w30 = 0;  if (!v6.uX(LU)) LU = 0;  if (!v6.uX(TA)) TA = 0;  if (!v6.uX(a3)) a3 = 0;  if (!v6.uX(X4)) X4 = 0;  if (!v6.uX(DB)) DB = 0;  } public static HashSet Jx0() { HashSet hashSet; if ((hashSet = nw) != null) return hashSet;  String[] arrayOfString; short s; byte b; for (arrayOfString = Ri.split(";"), s = 0, nw = new HashSet(), b = 0; b < arrayOfString.length; ) { Xv0 xv0; if (!arrayOfString[b].trim().isEmpty() && (xv0 = Xv0.nS(arrayOfString[b])) != null) { nw.add(xv0); s = (short)(s | xv0.gE); }  b++; }
/*  2 */      while = s; return nw; } public static boolean tz(HashSet<?> paramHashSet) { short s = 0; this(); ArrayList<String> arrayList; StringBuilder stringBuilder; for (null = (nw = paramHashSet).iterator(); null.hasNext(); ) { Xv0 xv0; arrayList.add((xv0 = (Xv0)null.next()).uz0);
/*  3 */       s = (short)(s | xv0.gE); }
/*  4 */      Collections.sort(arrayList); this(); for (String str : arrayList) { if (stringBuilder.length() > 0) stringBuilder.append(";");  stringBuilder.append(str); }  if (Ri.equalsIgnoreCase(stringBuilder.toString())) return false;  Ri = stringBuilder.toString(); while = s; Td(); return true; } public static void cd0(rx0[] paramArrayOfrx0) { this(); StringBuilder stringBuilder; int i; byte b; for (i = paramArrayOfrx0.length, b = 0; b < i; ) { rx0 rx01; if (!(rx01 = paramArrayOfrx0[b]).rc.isEmpty()) { if (stringBuilder.length() > 0)
/*  5 */           stringBuilder.append("|");  stringBuilder.append(rx01.BT);
/*    */         
/*  7 */         for (Iterator<Prn> iterator = rx01.rc.values().iterator(); iterator.hasNext(); ) { Prn prn; if ((prn = iterator.next())
/*  8 */             .dL0 == null || prn
/*  9 */             .f5 == 0) continue;  stringBuilder
/* 10 */             .append(";");
/*    */           
/* 12 */           stringBuilder.append(prn.dL0); stringBuilder.append(",");
/*    */           int j;
/* 14 */           if ((j = Zk0.yE(prn.f5)) != 0) { if (j != 1) continue;  stringBuilder.append("AXIS"); stringBuilder.append(","); stringBuilder
/*    */               
/* 16 */               .append(prn.Com8); stringBuilder.append(",");
/*    */             
/* 18 */             stringBuilder.append(prn.iD0); continue; }  stringBuilder.append("BUTTON"); stringBuilder.append(","); stringBuilder
/*    */             
/* 20 */             .append(prn.wd0); }  }  b++; }  ja0 = stringBuilder.toString(); Td(); } public static ArrayList ls0() { this(); ArrayList<String> arrayList; String[] arrayOfString; int i = (arrayOfString = Na.split("/")).length; for (byte b = 0; b < i; b++) { String str; if (!(str = arrayOfString[b].trim()).isEmpty() && !arrayList.contains(str)) arrayList.add(str);  }  return arrayList; } public static boolean J20(int paramInt, BM paramBM) { return (paramBM == null) ? false : paramBM.U60(paramInt); } public static boolean Td() { this(Bz.CN, "main.properties"); File file; boolean bool; if (bool = Cq.RG0((new File()).getAbsolutePath(), h1.class)) { A4.info(B40.df("Saved config to ").append(file.getAbsolutePath()).toString()); Gh0 = false; } else { A4.error(B40.df("Error saving config to ").append(file.getAbsolutePath()).toString()); }  return bool; } public static Kz a50() { return Kz.valueOf(ev); } public static PJ0 Tu() { if (LA0.isEmpty()) return null;  try { String[] arrayOfString = LA0.split(","); String str = arrayOfString[0]; int i = Integer.parseInt(arrayOfString[1]); int j = Integer.parseInt(arrayOfString[2]); return new PJ0(str, i, j); } catch (Exception exception) { return null; }  } public static int Ek() { int i; if ((i = y00) == -1) { if (km.ER()) { i = 20; } else { i = 0; }  return i; }  return i; } public static ArrayList wL0() { // Byte code:
/*    */     //   0: getstatic f/h1.pB : Ljava/lang/String;
/*    */     //   3: ldc_w ';'
/*    */     //   6: invokevirtual split : (Ljava/lang/String;)[Ljava/lang/String;
/*    */     //   9: astore_0
/*    */     //   10: getstatic f/h1.Rw0 : Ljava/lang/String;
/*    */     //   13: ldc_w ';'
/*    */     //   16: iconst_m1
/*    */     //   17: invokevirtual split : (Ljava/lang/String;I)[Ljava/lang/String;
/*    */     //   20: astore_1
/*    */     //   21: new java/util/ArrayList
/*    */     //   24: dup
/*    */     //   25: astore_2
/*    */     //   26: invokespecial <init> : ()V
/*    */     //   29: iconst_0
/*    */     //   30: istore_3
/*    */     //   31: iload_3
/*    */     //   32: aload_0
/*    */     //   33: arraylength
/*    */     //   34: if_icmpge -> 195
/*    */     //   37: iload_3
/*    */     //   38: aload_1
/*    */     //   39: arraylength
/*    */     //   40: if_icmpge -> 195
/*    */     //   43: aload_1
/*    */     //   44: iload_3
/*    */     //   45: aaload
/*    */     //   46: ldc_w ','
/*    */     //   49: invokevirtual split : (Ljava/lang/String;)[Ljava/lang/String;
/*    */     //   52: astore #4
/*    */     //   54: new java/util/HashSet
/*    */     //   57: dup
/*    */     //   58: astore #5
/*    */     //   60: invokespecial <init> : ()V
/*    */     //   63: iconst_0
/*    */     //   64: istore #6
/*    */     //   66: iload #6
/*    */     //   68: aload #4
/*    */     //   70: arraylength
/*    */     //   71: if_icmpge -> 172
/*    */     //   74: aload #4
/*    */     //   76: iload #6
/*    */     //   78: aaload
/*    */     //   79: invokevirtual trim : ()Ljava/lang/String;
/*    */     //   82: invokevirtual isEmpty : ()Z
/*    */     //   85: ifeq -> 91
/*    */     //   88: goto -> 166
/*    */     //   91: aload #4
/*    */     //   93: iload #6
/*    */     //   95: aaload
/*    */     //   96: getstatic f/ZY.l3 : Lf/ZY;
/*    */     //   99: pop
/*    */     //   100: invokestatic parseInt : (Ljava/lang/String;)I
/*    */     //   103: istore #7
/*    */     //   105: getstatic f/ZY.R70 : [Lf/ZY;
/*    */     //   108: dup
/*    */     //   109: astore #8
/*    */     //   111: arraylength
/*    */     //   112: istore #9
/*    */     //   114: iconst_0
/*    */     //   115: istore #10
/*    */     //   117: iload #10
/*    */     //   119: iload #9
/*    */     //   121: if_icmpge -> 150
/*    */     //   124: aload #8
/*    */     //   126: iload #10
/*    */     //   128: aaload
/*    */     //   129: dup
/*    */     //   130: astore #11
/*    */     //   132: getfield oZ : B
/*    */     //   135: iload #7
/*    */     //   137: if_icmpne -> 143
/*    */     //   140: goto -> 153
/*    */     //   143: iinc #10, 1
/*    */     //   146: goto -> 117
/*    */     //   149: pop
/*    */     //   150: aconst_null
/*    */     //   151: astore #11
/*    */     //   153: aload #11
/*    */     //   155: ifnull -> 166
/*    */     //   158: aload #5
/*    */     //   160: aload #11
/*    */     //   162: invokevirtual add : (Ljava/lang/Object;)Z
/*    */     //   165: pop
/*    */     //   166: iinc #6, 1
/*    */     //   169: goto -> 66
/*    */     //   172: aload_2
/*    */     //   173: new f/uM
/*    */     //   176: dup
/*    */     //   177: aload_0
/*    */     //   178: iload_3
/*    */     //   179: aaload
/*    */     //   180: aload #5
/*    */     //   182: invokespecial <init> : (Ljava/lang/String;Ljava/util/HashSet;)V
/*    */     //   185: invokevirtual add : (Ljava/lang/Object;)Z
/*    */     //   188: pop
/*    */     //   189: iinc #3, 1
/*    */     //   192: goto -> 31
/*    */     //   195: aload_2
/*    */     //   196: areturn
/*    */     // Line number table:
/*    */     //   Java source line number -> byte code offset
/*    */     //   #1	-> 100
/*    */     //   #2	-> 162
/*    */     // Exception table:
/*    */     //   from	to	target	type
/*    */     //   100	103	149	java/lang/NumberFormatException } public static HashMap ib0() { // Byte code:
/*    */     //   0: getstatic f/h1.ja0 : Ljava/lang/String;
/*    */     //   3: ldc_w '\|'
/*    */     //   6: invokevirtual split : (Ljava/lang/String;)[Ljava/lang/String;
/*    */     //   9: astore_0
/*    */     //   10: new java/util/HashMap
/*    */     //   13: dup
/*    */     //   14: astore_1
/*    */     //   15: invokespecial <init> : ()V
/*    */     //   18: iconst_0
/*    */     //   19: istore_2
/*    */     //   20: iload_2
/*    */     //   21: aload_0
/*    */     //   22: arraylength
/*    */     //   23: if_icmpge -> 315
/*    */     //   26: aload_0
/*    */     //   27: iload_2
/*    */     //   28: aaload
/*    */     //   29: invokevirtual trim : ()Ljava/lang/String;
/*    */     //   32: invokevirtual isEmpty : ()Z
/*    */     //   35: ifne -> 309
/*    */     //   38: aload_0
/*    */     //   39: iload_2
/*    */     //   40: aaload
/*    */     //   41: ldc_w ';'
/*    */     //   44: invokevirtual contains : (Ljava/lang/CharSequence;)Z
/*    */     //   47: ifne -> 53
/*    */     //   50: goto -> 309
/*    */     //   53: aload_0
/*    */     //   54: iload_2
/*    */     //   55: aaload
/*    */     //   56: ldc_w ';'
/*    */     //   59: invokevirtual split : (Ljava/lang/String;)[Ljava/lang/String;
/*    */     //   62: dup
/*    */     //   63: astore_3
/*    */     //   64: arraylength
/*    */     //   65: iconst_2
/*    */     //   66: if_icmpge -> 72
/*    */     //   69: goto -> 309
/*    */     //   72: aload_3
/*    */     //   73: iconst_0
/*    */     //   74: aaload
/*    */     //   75: astore #4
/*    */     //   77: new f/rx0
/*    */     //   80: dup
/*    */     //   81: astore #5
/*    */     //   83: aload #4
/*    */     //   85: invokespecial <init> : (Ljava/lang/String;)V
/*    */     //   88: iconst_1
/*    */     //   89: istore #6
/*    */     //   91: iload #6
/*    */     //   93: aload_3
/*    */     //   94: arraylength
/*    */     //   95: if_icmpge -> 294
/*    */     //   98: aload_3
/*    */     //   99: iload #6
/*    */     //   101: aaload
/*    */     //   102: ldc_w ','
/*    */     //   105: invokevirtual split : (Ljava/lang/String;)[Ljava/lang/String;
/*    */     //   108: dup
/*    */     //   109: astore #7
/*    */     //   111: arraylength
/*    */     //   112: iconst_3
/*    */     //   113: if_icmpge -> 119
/*    */     //   116: goto -> 288
/*    */     //   119: aload #7
/*    */     //   121: iconst_0
/*    */     //   122: aaload
/*    */     //   123: astore #8
/*    */     //   125: getstatic f/BM.ba0 : [Lf/BM;
/*    */     //   128: dup
/*    */     //   129: astore #9
/*    */     //   131: arraylength
/*    */     //   132: istore #10
/*    */     //   134: iconst_0
/*    */     //   135: istore #11
/*    */     //   137: iload #11
/*    */     //   139: iload #10
/*    */     //   141: if_icmpge -> 172
/*    */     //   144: aload #9
/*    */     //   146: iload #11
/*    */     //   148: aaload
/*    */     //   149: dup
/*    */     //   150: astore #12
/*    */     //   152: getfield xl0 : Ljava/lang/String;
/*    */     //   155: aload #8
/*    */     //   157: invokevirtual equalsIgnoreCase : (Ljava/lang/String;)Z
/*    */     //   160: ifeq -> 166
/*    */     //   163: goto -> 175
/*    */     //   166: iinc #11, 1
/*    */     //   169: goto -> 137
/*    */     //   172: aconst_null
/*    */     //   173: astore #12
/*    */     //   175: aload #12
/*    */     //   177: ifnonnull -> 183
/*    */     //   180: goto -> 288
/*    */     //   183: aload #7
/*    */     //   185: new f/Prn
/*    */     //   188: dup
/*    */     //   189: astore #8
/*    */     //   191: aload #12
/*    */     //   193: invokespecial <init> : (Lf/BM;)V
/*    */     //   196: iconst_1
/*    */     //   197: aaload
/*    */     //   198: ldc_w 'BUTTON'
/*    */     //   201: invokevirtual equalsIgnoreCase : (Ljava/lang/String;)Z
/*    */     //   204: ifeq -> 223
/*    */     //   207: aload #8
/*    */     //   209: aload #7
/*    */     //   211: iconst_2
/*    */     //   212: aaload
/*    */     //   213: invokestatic parseInt : (Ljava/lang/String;)I
/*    */     //   216: invokevirtual yH0 : (I)Lf/Prn;
/*    */     //   219: pop
/*    */     //   220: goto -> 272
/*    */     //   223: aload #7
/*    */     //   225: iconst_1
/*    */     //   226: aaload
/*    */     //   227: ldc_w 'AXIS'
/*    */     //   230: invokevirtual equalsIgnoreCase : (Ljava/lang/String;)Z
/*    */     //   233: ifeq -> 288
/*    */     //   236: aload #7
/*    */     //   238: arraylength
/*    */     //   239: iconst_4
/*    */     //   240: if_icmpge -> 246
/*    */     //   243: goto -> 288
/*    */     //   246: aload #8
/*    */     //   248: aload #7
/*    */     //   250: dup
/*    */     //   251: iconst_2
/*    */     //   252: aaload
/*    */     //   253: invokestatic parseInt : (Ljava/lang/String;)I
/*    */     //   256: istore #7
/*    */     //   258: iconst_3
/*    */     //   259: aaload
/*    */     //   260: invokestatic parseBoolean : (Ljava/lang/String;)Z
/*    */     //   263: iload #7
/*    */     //   265: swap
/*    */     //   266: invokevirtual nx : (IZ)Lf/Prn;
/*    */     //   269: goto -> 219
/*    */     //   272: aload #5
/*    */     //   274: getfield rc : Ljava/util/HashMap;
/*    */     //   277: aload #8
/*    */     //   279: getfield dL0 : Lf/BM;
/*    */     //   282: aload #8
/*    */     //   284: invokevirtual put : (Ljava/lang/Object;Ljava/lang/Object;)Ljava/lang/Object;
/*    */     //   287: pop
/*    */     //   288: iinc #6, 1
/*    */     //   291: goto -> 91
/*    */     //   294: aload_1
/*    */     //   295: aload #4
/*    */     //   297: aload #5
/*    */     //   299: invokevirtual put : (Ljava/lang/Object;Ljava/lang/Object;)Ljava/lang/Object;
/*    */     //   302: pop
/*    */     //   303: goto -> 309
/*    */     //   306: invokevirtual printStackTrace : ()V
/*    */     //   309: iinc #2, 1
/*    */     //   312: goto -> 20
/*    */     //   315: aload_1
/*    */     //   316: areturn
/*    */     // Line number table:
/*    */     //   Java source line number -> byte code offset
/*    */     //   #1	-> 125
/*    */     //   #2	-> 185
/*    */     //   #3	-> 274
/*    */     //   #4	-> 279
/*    */     //   #5	-> 284
/*    */     //   #6	-> 299
/*    */     // Exception table:
/*    */     //   from	to	target	type
/*    */     //   91	95	306	java/lang/Exception
/*    */     //   98	108	306	java/lang/Exception
/*    */     //   111	112	306	java/lang/Exception
/*    */     //   119	123	306	java/lang/Exception
/*    */     //   125	128	306	java/lang/Exception
/*    */     //   131	132	306	java/lang/Exception
/*    */     //   144	149	306	java/lang/Exception
/*    */     //   152	160	306	java/lang/Exception
/*    */     //   183	188	306	java/lang/Exception
/*    */     //   191	204	306	java/lang/Exception
/*    */     //   207	219	306	java/lang/Exception
/*    */     //   223	233	306	java/lang/Exception
/*    */     //   236	239	306	java/lang/Exception
/*    */     //   246	256	306	java/lang/Exception
/* 20 */     //   258	287	306	java/lang/Exception } public static void m7() { ev = "OpenGL"; } @mB0(key = "client.controls.gdx.hotbar3") public static int Zj0 = BM.lpT3
/* 21 */     .L00;
/* 22 */   static { yl.rh0 = h1::yf0; yl.gc0 = h1::er0; yl.Fa = h1::In; yl.Oi0 = h1::dx0; yl.AR = h1::Um; } @mB0(key = "client.controls.gdx.key_b") public static int nUL = BM.lc.L00; @mB0(key = "client.controls.gdx.key_x") public static int X4 = BM.go0.L00; @mB0(key = "client.controls.gdx.key_y") public static int DB = BM.Nx.L00; @mB0(key = "client.controls.gdx.key_up") public static int Wa0 = BM.ni.L00; @mB0(key = "client.controls.gdx.key_down") public static int Ll = BM.N70.L00; @mB0(key = "client.controls.gdx.key_left") public static int SJ0 = BM.Oq.L00; @mB0(key = "client.controls.gdx.key_right") public static int wu = BM.M8.L00; @mB0(key = "client.controls.gdx.hotbar1") public static int Qd0 = BM.Ul.L00; @mB0(key = "client.controls.gdx.hotbar2") public static int Gu = BM.Vv0.L00; @mB0(key = "client.controls.gdx.hotbar4") public static int UC0 = BM.WN
/* 23 */     .L00; @mB0(key = "client.controls.gdx.hotbar5")
/* 24 */   public static int om0 = BM.Vs
/* 25 */     .L00; @mB0(key = "client.controls.gdx.hotbar6")
/* 26 */   public static int ey = BM.jA
/* 27 */     .L00; @mB0(key = "client.controls.gdx.hotbar7")
/* 28 */   public static int g6 = BM.Um0
/* 29 */     .L00; @mB0(key = "client.controls.gdx.hotbar8")
/* 30 */   public static int c80 = BM.Km
/* 31 */     .L00; @mB0(key = "client.controls.gdx.hotbar9")
/* 32 */   public static int WK0 = BM.Hg
/* 33 */     .L00; @mB0(key = "client.controls.gdx.friendlist")
/* 34 */   public static int Sv0 = BM.Rd
/* 35 */     .L00; @mB0(key = "client.controls.gdx.bag")
/* 36 */   public static int Yu0 = BM.cf
/* 37 */     .L00; @mB0(key = "client.controls.gdx.trainer")
/* 38 */   public static int COn = BM.I0
/* 39 */     .L00; @mB0(key = "client.controls.gdx.codex")
/* 40 */   public static int lpt4 = BM.TC
/* 41 */     .L00; @mB0(key = "client.controls.gdx.gamemenu")
/* 42 */   public static int NC = BM.l30
/* 43 */     .L00; @mB0(key = "client.controls.gdx.hidegui")
/* 44 */   public static int Mm0 = BM.eH0
/* 45 */     .L00; @mB0(key = "client.controls.gdx.faq")
/* 46 */   public static int w30 = BM.W1
/* 47 */     .L00; @mB0(key = "client.controls.gdx.team")
/* 48 */   public static int LU = BM.Ij0
/* 49 */     .L00; @mB0(key = "client.controls.gdx.screenshot")
/* 50 */   public static int TA = BM.i40
/* 51 */     .L00; @mB0(key = "client.controls.gdx.tradelink")
/* 52 */   public static int a3 = BM.EW
/* 53 */     .L00; @mB0(key = "client.controls.controller_input_maps_gdx", defaultValue = "") public static String ja0; @mB0(key = "client.input.controllers.enable_native_support", defaultValue = "true") public static boolean D30; @mB0(key = "client.sound_engine.music_volume", defaultValue = "50")
/* 54 */   public static int Hh0 = 50; @mB0(key = "client.sound_engine.sfx_volume", defaultValue = "50") public static int HF = 50; @mB0(key = "client.sound_engine.system_volume", defaultValue = "50") public static int xP = 50; @mB0(key = "client.sound_engine.output_device", defaultValue = "") public static String PB; @mB0(key = "client.sound_engine.music_mute_when_unfocused", defaultValue = "true") public static boolean VJ0; @mB0(key = "client.sound_engine.battle_sfx.panning", defaultValue = "1") public static float In0; @mB0(key = "client.gameplay.autosprint.enabled", defaultValue = "true") public static boolean sP; @mB0(key = "client.gameplay.follower_bounce", defaultValue = "0") public static int rl0; @mB0(key = "client.gameplay.hatching_animations", defaultValue = "0") public static int ei; @mB0(key = "client.gameplay.mail_attachments_warning_dismissed", defaultValue = "false") public static boolean vj; @mB0(key = "client.ui.chat.word_filter.enabled", defaultValue = "true") public static boolean yA0; @mB0(key = "client.ui.smallhud", defaultValue = "true") public static boolean Eg0; @mB0(key = "client.ui.particles", defaultValue = "true") public static boolean qu0; @mB0(key = "client.ui.chat.name_highlight.enabled", defaultValue = "true") public static boolean Ye0; @mB0(key = "client.ui.chat.whisper_highlight.enabled", defaultValue = "true") public static boolean cOM5; @mB0(key = "client.ui.chat.timestamp.enabled", defaultValue = "false") public static boolean M20; @mB0(key = "client.ui.chat.type_name_display.enabled", defaultValue = "true") public static boolean Po0; @mB0(key = "client.ui.chat.language_name_display.enabled", defaultValue = "true") public static boolean c7; @mB0(key = "client.ui.chat.buffer.size", defaultValue = "2") public static int f0; @mB0(key = "client.ui.string.lang", defaultValue = "en") public static String pB0; @mB0(key = "client.ui.string.lang.selected_manually", defaultValue = "false") public static boolean p0; @mB0(key = "client.ui.japanese.charactermode", defaultValue = "0") public static int zr0; @mB0(key = "client.ui.nameplate.self", defaultValue = "false") public static boolean QP; @mB0(key = "client.ui.chat.transparency", defaultValue = "90") public static int iF0; @mB0(key = "client.ui.chat.tab.names", defaultValue = "Local;Global;Trade;Whispers;Battle") public static String pB; @mB0(key = "client.ui.chat.tab.hidden_chat_types", defaultValue = "6,18,5;7,18,0,3,4,5,9,8,17;7,6,18,0,3,4,9,8,17;7,6,18,0,3,5,9,8;7,16,6,0,3,4,5,9,8,17") public static String Rw0; @mB0(key = "client.ui.chat.tab.currently_active_tab", defaultValue = "Local") public static String LF0 = ""; @mB0(key = "client.ui.chat.linked_images.enabled", defaultValue = "true") public static boolean Iu0; @mB0(key = "client.ui.theme", defaultValue = "default") public static String MW; @mB0(key = "client.ui.last_revision", defaultValue = "0") public static int wT; @mB0(key = "client.mobile.notch", defaultValue = "false") public static boolean fD; @mB0(key = "client.mobile.dpad.scale", defaultValue = "1") public static float b90 = 1.0F; @mB0(key = "client.mobile.dpad.deadzone_radius", defaultValue = "0.2") public static float nR; @mB0(key = "client.mobile.ab.scale", defaultValue = "1") public static float Fg = 1.0F; @mB0(key = "client.mobile.dpad.sticky_directionals_strength", defaultValue = "3") public static int QJ; @mB0(key = "client.mobile.ab.reversed", defaultValue = "false") public static boolean c00 = false; @mB0(key = "client.mobile.hotbar.swap_party", defaultValue = "false") public static boolean Wo = false; @mB0(key = "client.mobile.onscreencontrols.show", defaultValue = "true") public static boolean je; @mB0(key = "client.ui.hud.battle.force_enable_battle_hud", defaultValue = "1") public static int nv; @mB0(key = "client.ui.hud.battle.show_damage_percentage_level", defaultValue = "1") public static int ak0; @mB0(key = "client.ui.hud.battle.replays.enable_instant_replays", defaultValue = "false") public static boolean rn; @mB0(key = "client.cache.model_cache.enable", defaultValue = "true") public static boolean Pm; @mB0(key = "client.cache.model_cache.regenerate", defaultValue = "false") public static boolean A0; @mB0(key = "ipv6.enable", defaultValue = "true") public static boolean FJ; public static boolean x1 = false; @mB0(key = "client.ui.theme.color1", defaultValue = "") public static String Xc0; @mB0(key = "client.ui.chat.notification.word_list", defaultValue = "") public static String in0; public static String[] hx = null; @mB0(key = "client.ui.chat.language.ignored_languages", defaultValue = "") public static String Ri; @mB0(key = "client.ui.chat.language.current_language", defaultValue = "en") public static String qc; @mB0(key = "client.ui.chat.language.current_language.selected_manually", defaultValue = "false") public static boolean Bb; private static HashSet nw = null; public static short while = 0; @mB0(key = "client.gameplay.textspeed", defaultValue = "4") public static int sK0 = 4;
/*    */   @mB0(key = "client.mods.enabled_mods", defaultValue = "")
/*    */   public static String Na;
/*    */   @mB0(key = "client.mods.debugs.verbose.enabled", defaultValue = "false")
/*    */   public static boolean zE;
/*    */   @mB0(key = "client.integrations.discord_rich_presence.enabled", defaultValue = "true")
/*    */   public static boolean PF0;
/*    */   public static boolean Gh0 = false;
/*    */   
/*    */   public static class PJ0 {
/*    */     public final String Ys;
/*    */     public final int Je;
/*    */     public final int LpT7;
/*    */     
/*    */     public PJ0(String param1String, int param1Int1, int param1Int2) {
/*    */       this.Ys = param1String;
/*    */       this.Je = param1Int1;
/*    */       this.LpT7 = param1Int2;
/*    */     }
/*    */   } }


/* Location:              /Users/vnnsnnt/Documents/Codespace/JavaWorkspace/RedTrainer/src/main/java/org/trainer/client/PokeMMO.jar!/f/h1.class
 * Java compiler version: 8 (52.0)
 * JD-Core Version:       1.1.3
 */