package f;

import java.nio.ByteBuffer;

public final class hC extends vO {
  public fQ Os0;
  
  public fQ p3;
  
  public fQ rt;
  
  public final fQ Nj;
  
  public TJ0 ck0;
  
  public ByteBuffer oI0;
  
  public Eb iQ;
  
  public float KD;
  
  public float Sw;
  
  public hC() {
    fQ fQ1;
    this();
    this.Nj = this;
  }
  
  public final void we0(ByteBuffer paramByteBuffer, int... paramVarArgs) {
    this.Vk = paramByteBuffer.getInt();
  }
  
  public final void rf0(ByteBuffer paramByteBuffer) {
    // Byte code:
    //   0: aload_1
    //   1: aload_0
    //   2: aload_1
    //   3: dup
    //   4: dup
    //   5: aload_0
    //   6: aload_1
    //   7: dup
    //   8: dup
    //   9: aload_0
    //   10: dup
    //   11: dup2
    //   12: aload_1
    //   13: dup
    //   14: dup
    //   15: dup2
    //   16: dup2
    //   17: dup2
    //   18: dup2
    //   19: dup2
    //   20: dup2
    //   21: aload_0
    //   22: aload_1
    //   23: aload_0
    //   24: aload_1
    //   25: aload_0
    //   26: aload_1
    //   27: aload_0
    //   28: aload_1
    //   29: aload_0
    //   30: getfield Vk : I
    //   33: istore_2
    //   34: invokevirtual getInt : ()I
    //   37: iload_2
    //   38: iadd
    //   39: istore_2
    //   40: getfield Vk : I
    //   43: istore_3
    //   44: invokevirtual getInt : ()I
    //   47: iload_3
    //   48: iadd
    //   49: istore_3
    //   50: getfield Vk : I
    //   53: istore #4
    //   55: invokevirtual getInt : ()I
    //   58: iload #4
    //   60: iadd
    //   61: istore #4
    //   63: getfield Vk : I
    //   66: istore #5
    //   68: invokevirtual getInt : ()I
    //   71: iload #5
    //   73: iadd
    //   74: istore #5
    //   76: getfield Vk : I
    //   79: istore #6
    //   81: invokevirtual getInt : ()I
    //   84: iload #6
    //   86: iadd
    //   87: istore #6
    //   89: invokevirtual get : ()B
    //   92: pop
    //   93: invokevirtual get : ()B
    //   96: pop
    //   97: invokevirtual get : ()B
    //   100: pop
    //   101: invokevirtual get : ()B
    //   104: pop
    //   105: invokevirtual get : ()B
    //   108: pop
    //   109: invokevirtual get : ()B
    //   112: pop
    //   113: invokevirtual get : ()B
    //   116: pop
    //   117: invokevirtual get : ()B
    //   120: pop
    //   121: invokevirtual getInt : ()I
    //   124: invokestatic Jd0 : (I)F
    //   127: fstore #7
    //   129: invokevirtual getInt : ()I
    //   132: invokestatic Jd0 : (I)F
    //   135: fstore #8
    //   137: invokevirtual getShort : ()S
    //   140: pop
    //   141: invokevirtual getShort : ()S
    //   144: pop
    //   145: invokevirtual getShort : ()S
    //   148: pop
    //   149: invokevirtual getShort : ()S
    //   152: pop
    //   153: fload #7
    //   155: putfield Sw : F
    //   158: fload #8
    //   160: putfield KD : F
    //   163: new f/Eb
    //   166: dup
    //   167: invokespecial <init> : ()V
    //   170: putfield iQ : Lf/Eb;
    //   173: new f/eo
    //   176: dup
    //   177: astore #7
    //   179: aload_1
    //   180: invokevirtual getShort : ()S
    //   183: invokestatic jv0 : (S)F
    //   186: aload_1
    //   187: dup
    //   188: invokevirtual getShort : ()S
    //   191: invokestatic jv0 : (S)F
    //   194: fstore #8
    //   196: invokevirtual getShort : ()S
    //   199: invokestatic jv0 : (S)F
    //   202: fload #8
    //   204: swap
    //   205: invokespecial <init> : (FFF)V
    //   208: new f/eo
    //   211: dup
    //   212: astore #8
    //   214: aload #7
    //   216: dup
    //   217: dup
    //   218: aload #8
    //   220: aload_1
    //   221: invokevirtual getShort : ()S
    //   224: invokestatic jv0 : (S)F
    //   227: aload_1
    //   228: dup
    //   229: invokevirtual getShort : ()S
    //   232: invokestatic jv0 : (S)F
    //   235: fstore #9
    //   237: invokevirtual getShort : ()S
    //   240: invokestatic jv0 : (S)F
    //   243: fload #9
    //   245: swap
    //   246: invokespecial <init> : (FFF)V
    //   249: getfield x : F
    //   252: fstore #9
    //   254: getfield y : F
    //   257: fstore #10
    //   259: getfield z : F
    //   262: fstore #11
    //   264: fload #9
    //   266: fload #10
    //   268: fload #11
    //   270: invokevirtual Tz : (FFF)Lf/eo;
    //   273: pop
    //   274: getfield iQ : Lf/Eb;
    //   277: aload #7
    //   279: aload #8
    //   281: invokevirtual kX : (Lf/eo;Lf/eo;)Lf/Eb;
    //   284: pop
    //   285: invokevirtual getInt : ()I
    //   288: pop
    //   289: invokevirtual getInt : ()I
    //   292: pop
    //   293: invokevirtual position : ()I
    //   296: istore #7
    //   298: new f/Yy0
    //   301: dup
    //   302: aload_1
    //   303: <illegal opcode> get : ()Ljava/util/function/Supplier;
    //   308: iload #7
    //   310: invokespecial <init> : (Ljava/nio/ByteBuffer;Ljava/util/function/Supplier;I)V
    //   313: getfield ai0 : Lf/fQ;
    //   316: putfield Os0 : Lf/fQ;
    //   319: iload #4
    //   321: invokevirtual position : (I)Ljava/nio/Buffer;
    //   324: pop
    //   325: invokevirtual getShort : ()S
    //   328: ldc 65535
    //   330: iand
    //   331: iload #4
    //   333: iadd
    //   334: istore #7
    //   336: invokevirtual getShort : ()S
    //   339: ldc 65535
    //   341: iand
    //   342: iload #4
    //   344: iadd
    //   345: istore #8
    //   347: new f/Yy0
    //   350: dup
    //   351: aload_1
    //   352: <illegal opcode> get : ()Ljava/util/function/Supplier;
    //   357: iload #4
    //   359: invokespecial <init> : (Ljava/nio/ByteBuffer;Ljava/util/function/Supplier;I)V
    //   362: getfield ai0 : Lf/fQ;
    //   365: putfield p3 : Lf/fQ;
    //   368: iload #7
    //   370: invokevirtual position : (I)Ljava/nio/Buffer;
    //   373: pop
    //   374: new f/Yy0
    //   377: dup
    //   378: aload_1
    //   379: <illegal opcode> get : ()Ljava/util/function/Supplier;
    //   384: iload #4
    //   386: invokespecial <init> : (Ljava/nio/ByteBuffer;Ljava/util/function/Supplier;I)V
    //   389: getfield ai0 : Lf/fQ;
    //   392: invokevirtual r30 : ()Lf/Hc0;
    //   395: astore #7
    //   397: aload #7
    //   399: invokevirtual hasNext : ()Z
    //   402: ifeq -> 491
    //   405: aload #7
    //   407: invokevirtual next : ()Ljava/lang/Object;
    //   410: checkcast f/C8
    //   413: dup
    //   414: astore #9
    //   416: aload_0
    //   417: getfield p3 : Lf/fQ;
    //   420: astore #10
    //   422: getfield p20 : [I
    //   425: dup
    //   426: astore #11
    //   428: arraylength
    //   429: istore #12
    //   431: iconst_0
    //   432: istore #13
    //   434: iload #13
    //   436: iload #12
    //   438: if_icmpge -> 397
    //   441: aload #9
    //   443: aload #10
    //   445: aload #11
    //   447: iload #13
    //   449: iaload
    //   450: invokevirtual get : (I)Ljava/lang/Object;
    //   453: checkcast f/tC
    //   456: astore #14
    //   458: getfield Ih : Ljava/lang/String;
    //   461: astore #15
    //   463: aload #14
    //   465: getfield JZ : Ljava/lang/String;
    //   468: ifnull -> 478
    //   471: getstatic f/tC.Sj : Lf/ik;
    //   474: invokevirtual getClass : ()Ljava/lang/Class;
    //   477: pop
    //   478: aload #14
    //   480: aload #15
    //   482: putfield JZ : Ljava/lang/String;
    //   485: iinc #13, 1
    //   488: goto -> 434
    //   491: aload_1
    //   492: iload #8
    //   494: invokevirtual position : (I)Ljava/nio/Buffer;
    //   497: pop
    //   498: new f/Yy0
    //   501: dup
    //   502: aload_1
    //   503: <illegal opcode> get : ()Ljava/util/function/Supplier;
    //   508: iload #4
    //   510: invokespecial <init> : (Ljava/nio/ByteBuffer;Ljava/util/function/Supplier;I)V
    //   513: getfield ai0 : Lf/fQ;
    //   516: invokevirtual r30 : ()Lf/Hc0;
    //   519: astore #7
    //   521: aload #7
    //   523: invokevirtual hasNext : ()Z
    //   526: ifeq -> 615
    //   529: aload #7
    //   531: invokevirtual next : ()Ljava/lang/Object;
    //   534: checkcast f/C8
    //   537: dup
    //   538: astore #8
    //   540: aload_0
    //   541: getfield p3 : Lf/fQ;
    //   544: astore #9
    //   546: getfield p20 : [I
    //   549: dup
    //   550: astore #10
    //   552: arraylength
    //   553: istore #11
    //   555: iconst_0
    //   556: istore #12
    //   558: iload #12
    //   560: iload #11
    //   562: if_icmpge -> 521
    //   565: aload #8
    //   567: aload #9
    //   569: aload #10
    //   571: iload #12
    //   573: iaload
    //   574: invokevirtual get : (I)Ljava/lang/Object;
    //   577: checkcast f/tC
    //   580: astore #13
    //   582: getfield Ih : Ljava/lang/String;
    //   585: astore #14
    //   587: aload #13
    //   589: getfield C0 : Ljava/lang/String;
    //   592: ifnull -> 602
    //   595: getstatic f/tC.Sj : Lf/ik;
    //   598: invokevirtual getClass : ()Ljava/lang/Class;
    //   601: pop
    //   602: aload #13
    //   604: aload #14
    //   606: putfield C0 : Ljava/lang/String;
    //   609: iinc #12, 1
    //   612: goto -> 558
    //   615: aload_1
    //   616: iload_3
    //   617: aload_0
    //   618: aload_1
    //   619: iload #4
    //   621: iload_3
    //   622: aload_1
    //   623: iload_3
    //   624: aload_0
    //   625: aload_1
    //   626: iload #5
    //   628: invokevirtual position : (I)Ljava/nio/Buffer;
    //   631: pop
    //   632: new f/Yy0
    //   635: dup
    //   636: aload_1
    //   637: <illegal opcode> get : ()Ljava/util/function/Supplier;
    //   642: iload #5
    //   644: invokespecial <init> : (Ljava/nio/ByteBuffer;Ljava/util/function/Supplier;I)V
    //   647: getfield ai0 : Lf/fQ;
    //   650: putfield rt : Lf/fQ;
    //   653: invokevirtual position : (I)Ljava/nio/Buffer;
    //   656: pop
    //   657: isub
    //   658: newarray byte
    //   660: dup
    //   661: astore #5
    //   663: invokevirtual get : ([B)Ljava/nio/ByteBuffer;
    //   666: pop
    //   667: aload #5
    //   669: invokestatic wrap : ([B)Ljava/nio/ByteBuffer;
    //   672: getstatic java/nio/ByteOrder.LITTLE_ENDIAN : Ljava/nio/ByteOrder;
    //   675: invokevirtual order : (Ljava/nio/ByteOrder;)Ljava/nio/ByteBuffer;
    //   678: putfield oI0 : Ljava/nio/ByteBuffer;
    //   681: iconst_m1
    //   682: istore #5
    //   684: iconst_m1
    //   685: istore #7
    //   687: invokevirtual position : (I)Ljava/nio/Buffer;
    //   690: pop
    //   691: iload_3
    //   692: iload #4
    //   694: if_icmpge -> 1420
    //   697: aload_1
    //   698: invokevirtual get : ()B
    //   701: dup
    //   702: istore #8
    //   704: bipush #36
    //   706: if_icmpeq -> 1408
    //   709: iload #8
    //   711: bipush #38
    //   713: if_icmpeq -> 1298
    //   716: iload #8
    //   718: bipush #43
    //   720: if_icmpeq -> 1292
    //   723: iload #8
    //   725: bipush #68
    //   727: if_icmpeq -> 1408
    //   730: iload #8
    //   732: bipush #102
    //   734: if_icmpeq -> 1149
    //   737: iload #8
    //   739: bipush #70
    //   741: if_icmpeq -> 1094
    //   744: iload #8
    //   746: bipush #71
    //   748: if_icmpeq -> 1083
    //   751: iload #8
    //   753: tableswitch default -> 808, 0 -> 691, 1 -> 1420, 2 -> 1044, 3 -> 1083, 4 -> 1408, 5 -> 970, 6 -> 925, 7 -> 1083, 8 -> 1083, 9 -> 877
    //   808: iload #8
    //   810: tableswitch default -> 836, 11 -> 1292, 12 -> 1083, 13 -> 1077
    //   836: getstatic java/lang/System.out : Ljava/io/PrintStream;
    //   839: ldc 'unk('
    //   841: iload #8
    //   843: ldc ') definition '
    //   845: invokestatic DH0 : (Ljava/lang/String;ILjava/lang/String;)Ljava/lang/StringBuilder;
    //   848: iload #8
    //   850: bipush #15
    //   852: iand
    //   853: invokevirtual append : (I)Ljava/lang/StringBuilder;
    //   856: ldc ' mod = '
    //   858: invokevirtual append : (Ljava/lang/String;)Ljava/lang/StringBuilder;
    //   861: aload_0
    //   862: getfield Ih : Ljava/lang/String;
    //   865: invokevirtual append : (Ljava/lang/String;)Ljava/lang/StringBuilder;
    //   868: invokevirtual toString : ()Ljava/lang/String;
    //   871: invokevirtual println : (Ljava/lang/String;)V
    //   874: goto -> 1420
    //   877: aload_1
    //   878: dup
    //   879: invokevirtual get : ()B
    //   882: pop
    //   883: invokevirtual get : ()B
    //   886: istore #8
    //   888: iinc #3, 2
    //   891: iconst_0
    //   892: istore #9
    //   894: iload #9
    //   896: iload #8
    //   898: if_icmpge -> 1292
    //   901: aload_1
    //   902: dup
    //   903: dup
    //   904: invokevirtual get : ()B
    //   907: pop
    //   908: invokevirtual get : ()B
    //   911: pop
    //   912: invokevirtual get : ()B
    //   915: pop
    //   916: iinc #3, 3
    //   919: iinc #9, 1
    //   922: goto -> 894
    //   925: aload_1
    //   926: dup
    //   927: invokevirtual get : ()B
    //   930: istore #8
    //   932: invokevirtual get : ()B
    //   935: dup
    //   936: istore #9
    //   938: iload #8
    //   940: aload_0
    //   941: aload_1
    //   942: invokevirtual get : ()B
    //   945: pop
    //   946: iinc #3, 4
    //   949: getfield Os0 : Lf/fQ;
    //   952: iload #8
    //   954: invokevirtual get : (I)Ljava/lang/Object;
    //   957: checkcast f/vY
    //   960: invokevirtual getClass : ()Ljava/lang/Class;
    //   963: pop
    //   964: if_icmpeq -> 1373
    //   967: goto -> 1350
    //   970: aload_0
    //   971: dup
    //   972: aload_1
    //   973: invokevirtual get : ()B
    //   976: istore #8
    //   978: getfield rt : Lf/fQ;
    //   981: iload #8
    //   983: invokevirtual get : (I)Ljava/lang/Object;
    //   986: checkcast f/qL0
    //   989: dup
    //   990: astore #9
    //   992: iload #5
    //   994: aload #9
    //   996: iload #7
    //   998: aload_0
    //   999: getfield Nj : Lf/fQ;
    //   1002: aload #9
    //   1004: invokevirtual Com3 : (Ljava/lang/Object;)V
    //   1007: putfield rh : I
    //   1010: putfield h30 : I
    //   1013: getfield Os0 : Lf/fQ;
    //   1016: iload #5
    //   1018: invokevirtual get : (I)Ljava/lang/Object;
    //   1021: checkcast f/vY
    //   1024: getfield f6 : Lf/fQ;
    //   1027: iload #8
    //   1029: invokestatic valueOf : (I)Ljava/lang/Integer;
    //   1032: invokevirtual Com3 : (Ljava/lang/Object;)V
    //   1035: iconst_m1
    //   1036: istore #7
    //   1038: iinc #3, 2
    //   1041: goto -> 691
    //   1044: aload_0
    //   1045: aload_1
    //   1046: dup
    //   1047: invokevirtual get : ()B
    //   1050: istore #5
    //   1052: invokevirtual get : ()B
    //   1055: pop
    //   1056: getfield Os0 : Lf/fQ;
    //   1059: iload #5
    //   1061: invokevirtual get : (I)Ljava/lang/Object;
    //   1064: checkcast f/vY
    //   1067: invokevirtual getClass : ()Ljava/lang/Class;
    //   1070: pop
    //   1071: iinc #3, 3
    //   1074: goto -> 691
    //   1077: iinc #3, 2
    //   1080: goto -> 691
    //   1083: aload_1
    //   1084: invokevirtual get : ()B
    //   1087: pop
    //   1088: iinc #3, 2
    //   1091: goto -> 691
    //   1094: aload_1
    //   1095: invokevirtual get : ()B
    //   1098: dup
    //   1099: istore #8
    //   1101: aload_1
    //   1102: dup
    //   1103: dup
    //   1104: invokevirtual get : ()B
    //   1107: istore #9
    //   1109: invokevirtual get : ()B
    //   1112: pop
    //   1113: invokevirtual get : ()B
    //   1116: pop
    //   1117: iinc #3, 5
    //   1120: ifeq -> 1139
    //   1123: aload_0
    //   1124: getfield Os0 : Lf/fQ;
    //   1127: iload #8
    //   1129: invokevirtual get : (I)Ljava/lang/Object;
    //   1132: checkcast f/vY
    //   1135: invokevirtual getClass : ()Ljava/lang/Class;
    //   1138: pop
    //   1139: iload #9
    //   1141: iload #8
    //   1143: if_icmpeq -> 1373
    //   1146: goto -> 1350
    //   1149: iload #8
    //   1151: aload_1
    //   1152: dup
    //   1153: dup
    //   1154: invokevirtual get : ()B
    //   1157: istore #9
    //   1159: invokevirtual get : ()B
    //   1162: istore #10
    //   1164: invokevirtual get : ()B
    //   1167: pop
    //   1168: iinc #3, 3
    //   1171: iconst_5
    //   1172: ishr
    //   1173: iconst_1
    //   1174: iand
    //   1175: iconst_1
    //   1176: if_icmpne -> 1187
    //   1179: aload_1
    //   1180: invokevirtual get : ()B
    //   1183: pop
    //   1184: iinc #3, 1
    //   1187: iload #8
    //   1189: bipush #6
    //   1191: ishr
    //   1192: iconst_1
    //   1193: iand
    //   1194: iconst_1
    //   1195: if_icmpne -> 1206
    //   1198: aload_1
    //   1199: invokevirtual get : ()B
    //   1202: pop
    //   1203: iinc #3, 1
    //   1206: iload #9
    //   1208: ifeq -> 1227
    //   1211: aload_0
    //   1212: getfield Os0 : Lf/fQ;
    //   1215: iload #9
    //   1217: invokevirtual get : (I)Ljava/lang/Object;
    //   1220: checkcast f/vY
    //   1223: invokevirtual getClass : ()Ljava/lang/Class;
    //   1226: pop
    //   1227: iload #10
    //   1229: iload #9
    //   1231: if_icmpeq -> 1257
    //   1234: aload_0
    //   1235: getfield Os0 : Lf/fQ;
    //   1238: iload #10
    //   1240: invokevirtual get : (I)Ljava/lang/Object;
    //   1243: checkcast f/vY
    //   1246: getfield D30 : Lf/fQ;
    //   1249: iload #9
    //   1251: invokestatic valueOf : (I)Ljava/lang/Integer;
    //   1254: invokevirtual Com3 : (Ljava/lang/Object;)V
    //   1257: aload_0
    //   1258: dup
    //   1259: getfield Os0 : Lf/fQ;
    //   1262: iload #9
    //   1264: invokevirtual get : (I)Ljava/lang/Object;
    //   1267: checkcast f/vY
    //   1270: invokevirtual getClass : ()Ljava/lang/Class;
    //   1273: pop
    //   1274: getfield Os0 : Lf/fQ;
    //   1277: iload #9
    //   1279: invokevirtual get : (I)Ljava/lang/Object;
    //   1282: checkcast f/vY
    //   1285: invokevirtual getClass : ()Ljava/lang/Class;
    //   1288: pop
    //   1289: goto -> 691
    //   1292: iinc #3, 1
    //   1295: goto -> 691
    //   1298: aload_1
    //   1299: invokevirtual get : ()B
    //   1302: dup
    //   1303: istore #8
    //   1305: aload_1
    //   1306: dup
    //   1307: dup
    //   1308: invokevirtual get : ()B
    //   1311: istore #9
    //   1313: invokevirtual get : ()B
    //   1316: pop
    //   1317: invokevirtual get : ()B
    //   1320: pop
    //   1321: iinc #3, 5
    //   1324: ifeq -> 1343
    //   1327: aload_0
    //   1328: getfield Os0 : Lf/fQ;
    //   1331: iload #8
    //   1333: invokevirtual get : (I)Ljava/lang/Object;
    //   1336: checkcast f/vY
    //   1339: invokevirtual getClass : ()Ljava/lang/Class;
    //   1342: pop
    //   1343: iload #9
    //   1345: iload #8
    //   1347: if_icmpeq -> 1373
    //   1350: aload_0
    //   1351: getfield Os0 : Lf/fQ;
    //   1354: iload #9
    //   1356: invokevirtual get : (I)Ljava/lang/Object;
    //   1359: checkcast f/vY
    //   1362: getfield D30 : Lf/fQ;
    //   1365: iload #8
    //   1367: invokestatic valueOf : (I)Ljava/lang/Integer;
    //   1370: invokevirtual Com3 : (Ljava/lang/Object;)V
    //   1373: aload_0
    //   1374: dup
    //   1375: getfield Os0 : Lf/fQ;
    //   1378: iload #8
    //   1380: invokevirtual get : (I)Ljava/lang/Object;
    //   1383: checkcast f/vY
    //   1386: invokevirtual getClass : ()Ljava/lang/Class;
    //   1389: pop
    //   1390: getfield Os0 : Lf/fQ;
    //   1393: iload #8
    //   1395: invokevirtual get : (I)Ljava/lang/Object;
    //   1398: checkcast f/vY
    //   1401: invokevirtual getClass : ()Ljava/lang/Class;
    //   1404: pop
    //   1405: goto -> 691
    //   1408: aload_1
    //   1409: invokevirtual get : ()B
    //   1412: istore #7
    //   1414: iinc #3, 2
    //   1417: goto -> 691
    //   1420: iload #6
    //   1422: iload_2
    //   1423: if_icmpeq -> 1452
    //   1426: aload_0
    //   1427: aload_1
    //   1428: iload #6
    //   1430: invokevirtual position : (I)Ljava/nio/Buffer;
    //   1433: pop
    //   1434: new f/TJ0
    //   1437: dup
    //   1438: aload_1
    //   1439: aload_0
    //   1440: getfield Os0 : Lf/fQ;
    //   1443: getfield Z8 : I
    //   1446: invokespecial <init> : (Ljava/nio/ByteBuffer;I)V
    //   1449: putfield ck0 : Lf/TJ0;
    //   1452: return
    // Line number table:
    //   Java source line number -> byte code offset
    //   #1	-> 249
    //   #2	-> 274
    //   #3	-> 313
    //   #4	-> 316
    //   #5	-> 362
    //   #6	-> 365
    //   #7	-> 389
    //   #8	-> 392
    //   #9	-> 422
    //   #10	-> 428
    //   #11	-> 465
    //   #12	-> 471
    //   #13	-> 494
    //   #14	-> 513
    //   #15	-> 516
    //   #16	-> 546
    //   #17	-> 552
    //   #18	-> 589
    //   #19	-> 595
    //   #20	-> 628
    //   #21	-> 647
    //   #22	-> 650
    //   #23	-> 687
    //   #24	-> 839
    //   #25	-> 853
    //   #26	-> 1007
    //   #27	-> 1010
    //   #28	-> 1013
    //   #29	-> 1351
    //   #30	-> 1409
    //   #31	-> 1430
  }
}


/* Location:              /Users/vnnsnnt/Documents/Codespace/JavaWorkspace/RedTrainer/src/main/java/org/trainer/client/PokeMMO.jar!/f/hC.class
 * Java compiler version: 8 (52.0)
 * JD-Core Version:       1.1.3
 */