/*  1 */ package f;public class HC0 extends wb { private void t20(eo parameo, int paramInt, sh paramsh) { paramInt = this.hB0.Hk(); byte b1 = this.hB0.hE(), b2 = this.hB0.iQ(), b3 = this.hB0.oi(); this.hB0.ZB0(this.hB0.Jx(), paramInt, "", (byte)1, b1, b2, b3); this.hB0.hn0(this.hB0.Si(), false); this.hB0.K0
/*    */       
/*  3 */       .hp0 = paramInt = this.Vy;
/*  4 */     this.hB0.tx(paramInt); this.hB0
/*  5 */       .K0
/*  6 */       .pO(); SK(this.hB0); So so = So.k60().Wz0(4.0F);
/*  7 */     so
/*  8 */       .L5(); uT[] arrayOfUT; int j; for (j = (arrayOfUT = this.hB0.qf).length, b3 = 0; b3 < j; ) { Color color = Color.BLACK; uT uT; s5 s5;
/*  9 */       if ((s5 = (uT = arrayOfUT[b3]).native) != null) s5
/* 10 */           .lx.set(color); 
/* 11 */       float f1 = parameo.x, f2 = parameo.y - 1.1F, f3 = parameo.z; uT.WQ(f1, f2, f3); f1 = parameo.x; f2 = parameo.y; f3 = parameo.z; so.PL(Wz0.gq(uT, 4, 2.4F).qw0(f1, f2, f3)); b3++; }  so.Kr().Wz0(1.0F).PL(Wz0.OC(this::NE))
/*    */       
/* 13 */       .PL(Wz0.gq(this.hB0.rF0.Os0, 13, 1.0F).a(1.4F)).PL(Wz0.OC((paramInt, paramsh) -> this.hB0.JB0())); for (int i = arrayOfUT.length; j < i; ) { arrayOfFloat[0] = color.r; arrayOfFloat[1] = color.g; arrayOfFloat[2] = color.b; float[] arrayOfFloat; Color color; (arrayOfFloat = new float[4])[3] = (color = Color.CLEAR).a; so.PL(Wz0.gq(arrayOfUT[j], 10, 0.8F).qY(new float[4])); j++; }  hm0 hm02 = this.xS;
/*    */     
/* 15 */     hm02 = this.xS;
/*    */     
/* 17 */     hm02 = this.xS;
/*    */     
/* 19 */     hm0 hm01 = this.xS;
/*    */ 
/*    */     
/* 22 */     eh0.sp0(HC0::XL0, so.L5().PL(Ur0("shiny_star_prebaked")).Zo0(ia0((byte)2, (short)1556, 1, 14, 0.0F, 0.9375F, hm02)).Zo0(ia0((byte)2, (short)1554, 1, 14, 700.0F, 0.859375F, hm02)).Zo0(ia0((byte)2, (short)1556, 1, 14, 0.0F, 0.9375F, hm02)).Zo0(ia0((byte)2, (short)1554, 1, 14, 700.0F, 0.859375F, this)).Kr().Wz0(1.5F), 2.5F)
/* 23 */       .PL(Wz0.OC(HC0::pk));
/*    */ 
/*    */     
/* 26 */     so.mg(this.pb.dr0); }
/*    */ 
/*    */   
/*    */   public final kf V8;
/*    */   public final hm0 hB0;
/*    */   public final short Vy;
/*    */   
/*    */   public HC0(kf paramkf, hm0 paramhm0, short paramShort) {
/*    */     super(paramhm0);
/*    */     SK(paramhm0);
/*    */     this.hB0 = paramhm0;
/*    */     this.V8 = paramkf;
/*    */     this.Vy = paramShort;
/*    */   }
/*    */   
/*    */   private void NE(int paramInt, sh paramsh) {
/*    */     Color color = Color.valueOf("#FF9AA2");
/*    */     float f = 0.0F;
/*    */     this.hB0.rF0.Os0.Tz0(new F4(F4.Qr0, this, f));
/*    */   }
/*    */   
/*    */   public final wb O3() {
/*    */     // Byte code:
/*    */     //   0: aload_0
/*    */     //   1: dup
/*    */     //   2: dup
/*    */     //   3: dup2
/*    */     //   4: getfield hB0 : Lf/hm0;
/*    */     //   7: getfield rF0 : Lf/uT;
/*    */     //   10: getfield He0 : Lf/eo;
/*    */     //   13: dup
/*    */     //   14: invokestatic w3 : (Lf/eo;Lf/eo;)Lf/eo;
/*    */     //   17: astore_1
/*    */     //   18: getfield hB0 : Lf/hm0;
/*    */     //   21: ldc_w 0.75
/*    */     //   24: invokevirtual xy0 : (F)V
/*    */     //   27: invokestatic k60 : ()Lf/So;
/*    */     //   30: dup
/*    */     //   31: astore_2
/*    */     //   32: putfield synchronized : Lf/So;
/*    */     //   35: aload_2
/*    */     //   36: invokevirtual eC : ()Lf/So;
/*    */     //   39: aload_0
/*    */     //   40: getfield hB0 : Lf/hm0;
/*    */     //   43: invokevirtual Jx : ()S
/*    */     //   46: invokestatic BR : (S)I
/*    */     //   49: i2f
/*    */     //   50: ldc_w 1000.0
/*    */     //   53: fdiv
/*    */     //   54: ldc_w 0.25
/*    */     //   57: fadd
/*    */     //   58: invokevirtual Vq : (F)Lf/sh;
/*    */     //   61: checkcast f/So
/*    */     //   64: aload_0
/*    */     //   65: getfield hB0 : Lf/hm0;
/*    */     //   68: invokevirtual Si : ()Z
/*    */     //   71: sipush #1388
/*    */     //   74: swap
/*    */     //   75: invokestatic A50 : (SZ)Lf/Wz0;
/*    */     //   78: invokevirtual PL : (Lf/Wz0;)Lf/So;
/*    */     //   81: pop
/*    */     //   82: getfield synchronized : Lf/So;
/*    */     //   85: invokevirtual L5 : ()Lf/So;
/*    */     //   88: pop
/*    */     //   89: getfield hB0 : Lf/hm0;
/*    */     //   92: dup
/*    */     //   93: astore_2
/*    */     //   94: getfield eq0 : Lf/uT;
/*    */     //   97: ifnull -> 152
/*    */     //   100: getstatic f/um0.Kt0 : Lf/um0;
/*    */     //   103: dup
/*    */     //   104: astore_3
/*    */     //   105: getfield Z2 : Lf/U70;
/*    */     //   108: dup
/*    */     //   109: astore #4
/*    */     //   111: ifnull -> 117
/*    */     //   114: goto -> 144
/*    */     //   117: aload_3
/*    */     //   118: new f/U70
/*    */     //   121: dup
/*    */     //   122: astore #4
/*    */     //   124: new f/iI
/*    */     //   127: dup
/*    */     //   128: astore #5
/*    */     //   130: aload_3
/*    */     //   131: invokespecial <init> : (Lf/um0;)V
/*    */     //   134: aload #5
/*    */     //   136: invokespecial <init> : (Lf/N50;)V
/*    */     //   139: aload #4
/*    */     //   141: putfield Z2 : Lf/U70;
/*    */     //   144: aload #4
/*    */     //   146: getstatic f/zm0.u20 : J
/*    */     //   149: putfield mk : J
/*    */     //   152: aload_2
/*    */     //   153: getfield Xn : [Lf/uT;
/*    */     //   156: dup
/*    */     //   157: astore_2
/*    */     //   158: arraylength
/*    */     //   159: istore_3
/*    */     //   160: iconst_0
/*    */     //   161: istore #4
/*    */     //   163: iload #4
/*    */     //   165: iload_3
/*    */     //   166: if_icmpge -> 228
/*    */     //   169: aload_0
/*    */     //   170: aload_2
/*    */     //   171: iload #4
/*    */     //   173: aaload
/*    */     //   174: astore #5
/*    */     //   176: getfield synchronized : Lf/So;
/*    */     //   179: aload #5
/*    */     //   181: iconst_4
/*    */     //   182: ldc_w 0.2
/*    */     //   185: invokestatic gq : (Ljava/lang/Object;IF)Lf/Wz0;
/*    */     //   188: aload_1
/*    */     //   189: dup
/*    */     //   190: dup
/*    */     //   191: getfield x : F
/*    */     //   194: fstore #5
/*    */     //   196: getfield y : F
/*    */     //   199: ldc 1.1
/*    */     //   201: fsub
/*    */     //   202: fstore #6
/*    */     //   204: getfield z : F
/*    */     //   207: fstore #7
/*    */     //   209: fload #5
/*    */     //   211: fload #6
/*    */     //   213: fload #7
/*    */     //   215: invokevirtual qw0 : (FFF)Lf/Wz0;
/*    */     //   218: invokevirtual PL : (Lf/Wz0;)Lf/So;
/*    */     //   221: pop
/*    */     //   222: iinc #4, 1
/*    */     //   225: goto -> 163
/*    */     //   228: aload_0
/*    */     //   229: dup
/*    */     //   230: dup
/*    */     //   231: dup2
/*    */     //   232: dup2
/*    */     //   233: dup2
/*    */     //   234: dup2
/*    */     //   235: dup2
/*    */     //   236: dup2
/*    */     //   237: getfield synchronized : Lf/So;
/*    */     //   240: aload_0
/*    */     //   241: <illegal opcode> Do : (Lf/HC0;)Lf/hk0;
/*    */     //   246: invokestatic OC : (Lf/hk0;)Lf/Wz0;
/*    */     //   249: invokevirtual PL : (Lf/Wz0;)Lf/So;
/*    */     //   252: pop
/*    */     //   253: getfield synchronized : Lf/So;
/*    */     //   256: aload_0
/*    */     //   257: bipush #18
/*    */     //   259: iconst_1
/*    */     //   260: invokevirtual fu0 : (IZ)Lf/Wz0;
/*    */     //   263: invokevirtual PL : (Lf/Wz0;)Lf/So;
/*    */     //   266: pop
/*    */     //   267: getfield synchronized : Lf/So;
/*    */     //   270: <illegal opcode> Do : ()Lf/hk0;
/*    */     //   275: invokestatic OC : (Lf/hk0;)Lf/Wz0;
/*    */     //   278: invokevirtual PL : (Lf/Wz0;)Lf/So;
/*    */     //   281: pop
/*    */     //   282: getfield synchronized : Lf/So;
/*    */     //   285: invokevirtual Kr : ()Lf/So;
/*    */     //   288: pop
/*    */     //   289: getfield synchronized : Lf/So;
/*    */     //   292: ldc_w 3.0
/*    */     //   295: invokevirtual Wz0 : (F)Lf/So;
/*    */     //   298: pop
/*    */     //   299: getfield synchronized : Lf/So;
/*    */     //   302: aload_0
/*    */     //   303: aload_1
/*    */     //   304: <illegal opcode> Do : (Lf/HC0;Lf/eo;)Lf/hk0;
/*    */     //   309: invokestatic OC : (Lf/hk0;)Lf/Wz0;
/*    */     //   312: invokevirtual PL : (Lf/Wz0;)Lf/So;
/*    */     //   315: pop
/*    */     //   316: getfield synchronized : Lf/So;
/*    */     //   319: aload_0
/*    */     //   320: iconst_4
/*    */     //   321: sipush #8470
/*    */     //   324: fconst_0
/*    */     //   325: ldc_w 0.75
/*    */     //   328: ldc_w 0.1
/*    */     //   331: invokevirtual UA0 : (IIFFF)Lf/So;
/*    */     //   334: invokevirtual Zo0 : (Lf/So;)Lf/So;
/*    */     //   337: aload_0
/*    */     //   338: sipush #8470
/*    */     //   341: invokestatic z2 : (I)Lcom/badlogic/gdx/graphics/Color;
/*    */     //   344: astore_1
/*    */     //   345: bipush #14
/*    */     //   347: ldc_w 0.1
/*    */     //   350: fconst_0
/*    */     //   351: ldc_w 0.75
/*    */     //   354: aload_1
/*    */     //   355: invokevirtual BW : (IFFFLcom/badlogic/gdx/graphics/Color;)Lf/So;
/*    */     //   358: invokevirtual Zo0 : (Lf/So;)Lf/So;
/*    */     //   361: aload_0
/*    */     //   362: sipush #8470
/*    */     //   365: invokestatic z2 : (I)Lcom/badlogic/gdx/graphics/Color;
/*    */     //   368: astore_1
/*    */     //   369: bipush #16
/*    */     //   371: ldc_w 0.1
/*    */     //   374: fconst_0
/*    */     //   375: ldc_w 0.75
/*    */     //   378: aload_1
/*    */     //   379: invokevirtual BW : (IFFFLcom/badlogic/gdx/graphics/Color;)Lf/So;
/*    */     //   382: invokevirtual Zo0 : (Lf/So;)Lf/So;
/*    */     //   385: fconst_1
/*    */     //   386: invokevirtual Wz0 : (F)Lf/So;
/*    */     //   389: invokevirtual L5 : ()Lf/So;
/*    */     //   392: aload_0
/*    */     //   393: dup
/*    */     //   394: getfield xS : Lf/hm0;
/*    */     //   397: astore_1
/*    */     //   398: iconst_2
/*    */     //   399: sipush #1818
/*    */     //   402: iconst_0
/*    */     //   403: bipush #14
/*    */     //   405: fconst_0
/*    */     //   406: ldc_w 0.9921875
/*    */     //   409: aload_1
/*    */     //   410: invokevirtual ia0 : (BSIIFFLf/hm0;)Lf/So;
/*    */     //   413: invokevirtual Zo0 : (Lf/So;)Lf/So;
/*    */     //   416: aload_0
/*    */     //   417: iconst_0
/*    */     //   418: iconst_0
/*    */     //   419: fconst_0
/*    */     //   420: ldc_w 800.0
/*    */     //   423: invokevirtual rF : (IIFF)Lf/So;
/*    */     //   426: invokevirtual Zo0 : (Lf/So;)Lf/So;
/*    */     //   429: aload_0
/*    */     //   430: dup
/*    */     //   431: getfield xS : Lf/hm0;
/*    */     //   434: astore_1
/*    */     //   435: iconst_2
/*    */     //   436: sipush #1376
/*    */     //   439: iconst_0
/*    */     //   440: bipush #14
/*    */     //   442: ldc_w 833.3333
/*    */     //   445: fconst_0
/*    */     //   446: aload_1
/*    */     //   447: invokevirtual ia0 : (BSIIFFLf/hm0;)Lf/So;
/*    */     //   450: invokevirtual Zo0 : (Lf/So;)Lf/So;
/*    */     //   453: aload_0
/*    */     //   454: iconst_1
/*    */     //   455: ldc_w 0.6
/*    */     //   458: invokevirtual vk0 : (IF)Lf/So;
/*    */     //   461: invokevirtual Zo0 : (Lf/So;)Lf/So;
/*    */     //   464: invokevirtual Kr : ()Lf/So;
/*    */     //   467: invokevirtual L5 : ()Lf/So;
/*    */     //   470: aload_0
/*    */     //   471: iconst_2
/*    */     //   472: bipush #31
/*    */     //   474: fconst_0
/*    */     //   475: ldc_w 0.5
/*    */     //   478: ldc_w 0.075
/*    */     //   481: invokevirtual UA0 : (IIFFF)Lf/So;
/*    */     //   484: invokevirtual Zo0 : (Lf/So;)Lf/So;
/*    */     //   487: aload_0
/*    */     //   488: bipush #31
/*    */     //   490: invokestatic z2 : (I)Lcom/badlogic/gdx/graphics/Color;
/*    */     //   493: astore_1
/*    */     //   494: bipush #16
/*    */     //   496: ldc_w 1.25
/*    */     //   499: fconst_0
/*    */     //   500: ldc_w 0.5
/*    */     //   503: aload_1
/*    */     //   504: invokevirtual BW : (IFFFLcom/badlogic/gdx/graphics/Color;)Lf/So;
/*    */     //   507: invokevirtual Zo0 : (Lf/So;)Lf/So;
/*    */     //   510: aload_0
/*    */     //   511: bipush #16
/*    */     //   513: iconst_1
/*    */     //   514: invokevirtual Tt : (II)Lf/So;
/*    */     //   517: invokevirtual Zo0 : (Lf/So;)Lf/So;
/*    */     //   520: aload_0
/*    */     //   521: sipush #719
/*    */     //   524: invokevirtual Ii : (I)Lf/Wz0;
/*    */     //   527: invokevirtual PL : (Lf/Wz0;)Lf/So;
/*    */     //   530: aload_0
/*    */     //   531: sipush #719
/*    */     //   534: iconst_0
/*    */     //   535: bipush #11
/*    */     //   537: bipush #8
/*    */     //   539: ldc_w 0.25
/*    */     //   542: invokevirtual hg : (IIIIF)Lf/So;
/*    */     //   545: invokevirtual Zo0 : (Lf/So;)Lf/So;
/*    */     //   548: aload_0
/*    */     //   549: sipush #719
/*    */     //   552: iconst_2
/*    */     //   553: bipush #11
/*    */     //   555: bipush #8
/*    */     //   557: ldc_w 0.5
/*    */     //   560: invokevirtual hg : (IIIIF)Lf/So;
/*    */     //   563: ldc_w 0.2
/*    */     //   566: invokestatic ZF0 : (Lf/So;Lf/So;F)Lf/So;
/*    */     //   569: aload_0
/*    */     //   570: dup
/*    */     //   571: getfield xS : Lf/hm0;
/*    */     //   574: astore_1
/*    */     //   575: iconst_2
/*    */     //   576: sipush #1561
/*    */     //   579: iconst_1
/*    */     //   580: bipush #14
/*    */     //   582: fconst_0
/*    */     //   583: ldc_w 0.9921875
/*    */     //   586: aload_1
/*    */     //   587: invokevirtual ia0 : (BSIIFFLf/hm0;)Lf/So;
/*    */     //   590: invokevirtual Zo0 : (Lf/So;)Lf/So;
/*    */     //   593: aload_0
/*    */     //   594: dup
/*    */     //   595: getfield xS : Lf/hm0;
/*    */     //   598: astore_1
/*    */     //   599: iconst_2
/*    */     //   600: sipush #1907
/*    */     //   603: iconst_2
/*    */     //   604: bipush #14
/*    */     //   606: fconst_0
/*    */     //   607: ldc_w 0.9921875
/*    */     //   610: aload_1
/*    */     //   611: invokevirtual ia0 : (BSIIFFLf/hm0;)Lf/So;
/*    */     //   614: invokevirtual Zo0 : (Lf/So;)Lf/So;
/*    */     //   617: aload_0
/*    */     //   618: dup
/*    */     //   619: getfield xS : Lf/hm0;
/*    */     //   622: astore_1
/*    */     //   623: iconst_2
/*    */     //   624: sipush #1907
/*    */     //   627: iconst_1
/*    */     //   628: bipush #14
/*    */     //   630: ldc_w 1333.3334
/*    */     //   633: ldc_w 0.9921875
/*    */     //   636: aload_1
/*    */     //   637: invokevirtual ia0 : (BSIIFFLf/hm0;)Lf/So;
/*    */     //   640: invokevirtual Zo0 : (Lf/So;)Lf/So;
/*    */     //   643: aload_0
/*    */     //   644: dup
/*    */     //   645: getfield xS : Lf/hm0;
/*    */     //   648: astore_1
/*    */     //   649: iconst_2
/*    */     //   650: sipush #1907
/*    */     //   653: iconst_3
/*    */     //   654: bipush #14
/*    */     //   656: ldc_w 2600.0
/*    */     //   659: ldc_w 0.9921875
/*    */     //   662: aload_1
/*    */     //   663: invokevirtual ia0 : (BSIIFFLf/hm0;)Lf/So;
/*    */     //   666: invokevirtual Zo0 : (Lf/So;)Lf/So;
/*    */     //   669: aload_0
/*    */     //   670: sipush #719
/*    */     //   673: iconst_1
/*    */     //   674: bipush #11
/*    */     //   676: bipush #8
/*    */     //   678: fconst_0
/*    */     //   679: invokevirtual hg : (IIIIF)Lf/So;
/*    */     //   682: ldc 1.4
/*    */     //   684: invokestatic Ye : (Lf/So;Lf/So;F)Lf/So;
/*    */     //   687: aload_0
/*    */     //   688: bipush #16
/*    */     //   690: iconst_2
/*    */     //   691: bipush #23
/*    */     //   693: fconst_0
/*    */     //   694: ldc_w 0.064
/*    */     //   697: ldc_w 0.100097656
/*    */     //   700: ldc_w -0.100097656
/*    */     //   703: invokevirtual Sn : (IIIFFFF)Lf/So;
/*    */     //   706: invokevirtual Zo0 : (Lf/So;)Lf/So;
/*    */     //   709: aload_0
/*    */     //   710: sipush #719
/*    */     //   713: iconst_2
/*    */     //   714: bipush #11
/*    */     //   716: bipush #8
/*    */     //   718: ldc_w 0.5
/*    */     //   721: invokevirtual hg : (IIIIF)Lf/So;
/*    */     //   724: ldc_w 1.6
/*    */     //   727: invokestatic Ye : (Lf/So;Lf/So;F)Lf/So;
/*    */     //   730: aload_0
/*    */     //   731: sipush #719
/*    */     //   734: iconst_0
/*    */     //   735: bipush #11
/*    */     //   737: bipush #8
/*    */     //   739: fconst_0
/*    */     //   740: invokevirtual hg : (IIIIF)Lf/So;
/*    */     //   743: ldc_w 2.6
/*    */     //   746: invokestatic Ye : (Lf/So;Lf/So;F)Lf/So;
/*    */     //   749: aload_0
/*    */     //   750: sipush #719
/*    */     //   753: iconst_3
/*    */     //   754: bipush #11
/*    */     //   756: bipush #8
/*    */     //   758: ldc_w 0.5
/*    */     //   761: invokevirtual hg : (IIIIF)Lf/So;
/*    */     //   764: invokevirtual Zo0 : (Lf/So;)Lf/So;
/*    */     //   767: aload_0
/*    */     //   768: sipush #719
/*    */     //   771: iconst_1
/*    */     //   772: bipush #11
/*    */     //   774: bipush #8
/*    */     //   776: ldc_w 0.25
/*    */     //   779: invokevirtual hg : (IIIIF)Lf/So;
/*    */     //   782: invokestatic h30 : (Lf/So;Lf/So;)Lf/So;
/*    */     //   785: aload_0
/*    */     //   786: iconst_2
/*    */     //   787: bipush #31
/*    */     //   789: ldc_w 0.5
/*    */     //   792: fconst_0
/*    */     //   793: ldc_w 0.075
/*    */     //   796: invokevirtual UA0 : (IIFFF)Lf/So;
/*    */     //   799: invokevirtual Zo0 : (Lf/So;)Lf/So;
/*    */     //   802: aload_0
/*    */     //   803: bipush #31
/*    */     //   805: invokestatic z2 : (I)Lcom/badlogic/gdx/graphics/Color;
/*    */     //   808: astore_1
/*    */     //   809: bipush #16
/*    */     //   811: ldc_w 0.75
/*    */     //   814: ldc_w 0.5
/*    */     //   817: fconst_0
/*    */     //   818: aload_1
/*    */     //   819: invokevirtual BW : (IFFFLcom/badlogic/gdx/graphics/Color;)Lf/So;
/*    */     //   822: invokevirtual Zo0 : (Lf/So;)Lf/So;
/*    */     //   825: aload_0
/*    */     //   826: bipush #16
/*    */     //   828: iconst_2
/*    */     //   829: iconst_1
/*    */     //   830: fconst_0
/*    */     //   831: ldc_w 0.032
/*    */     //   834: ldc_w 0.100097656
/*    */     //   837: ldc_w -0.100097656
/*    */     //   840: invokevirtual Sn : (IIIFFFF)Lf/So;
/*    */     //   843: invokestatic RU : (Lf/So;Lf/So;)Lf/So;
/*    */     //   846: aload_0
/*    */     //   847: ldc_w 0.4
/*    */     //   850: invokevirtual hp0 : (F)Lf/So;
/*    */     //   853: invokevirtual Zo0 : (Lf/So;)Lf/So;
/*    */     //   856: invokevirtual Kr : ()Lf/So;
/*    */     //   859: pop
/*    */     //   860: getfield synchronized : Lf/So;
/*    */     //   863: aload_0
/*    */     //   864: <illegal opcode> Do : (Lf/HC0;)Lf/hk0;
/*    */     //   869: invokestatic OC : (Lf/hk0;)Lf/Wz0;
/*    */     //   872: invokevirtual PL : (Lf/Wz0;)Lf/So;
/*    */     //   875: pop
/*    */     //   876: getfield synchronized : Lf/So;
/*    */     //   879: aload_0
/*    */     //   880: bipush #18
/*    */     //   882: iconst_0
/*    */     //   883: invokevirtual fu0 : (IZ)Lf/Wz0;
/*    */     //   886: invokevirtual PL : (Lf/Wz0;)Lf/So;
/*    */     //   889: pop
/*    */     //   890: getfield synchronized : Lf/So;
/*    */     //   893: aload_0
/*    */     //   894: ldc_w 0.4
/*    */     //   897: invokevirtual hp0 : (F)Lf/So;
/*    */     //   900: invokevirtual Zo0 : (Lf/So;)Lf/So;
/*    */     //   903: pop
/*    */     //   904: getfield synchronized : Lf/So;
/*    */     //   907: invokevirtual Kr : ()Lf/So;
/*    */     //   910: pop
/*    */     //   911: getfield synchronized : Lf/So;
/*    */     //   914: aload_0
/*    */     //   915: getfield pb : Lf/vH;
/*    */     //   918: getfield dr0 : Lf/G30;
/*    */     //   921: invokevirtual mg : (Lf/G30;)Lf/sh;
/*    */     //   924: pop
/*    */     //   925: getfield pb : Lf/vH;
/*    */     //   928: aload_0
/*    */     //   929: getfield synchronized : Lf/So;
/*    */     //   932: invokevirtual t9 : (Lf/So;)V
/*    */     //   935: invokevirtual tS : ()V
/*    */     //   938: areturn
/*    */     // Line number table:
/*    */     //   Java source line number -> byte code offset
/*    */     //   #1	-> 7
/*    */     //   #2	-> 10
/*    */     //   #3	-> 14
/*    */     //   #4	-> 18
/*    */     //   #5	-> 75
/*    */     //   #6	-> 78
/*    */     //   #7	-> 94
/*    */     //   #8	-> 100
/*    */     //   #9	-> 105
/*    */     //   #10	-> 118
/*    */     //   #11	-> 146
/*    */     //   #12	-> 149
/*    */     //   #13	-> 153
/*    */     //   #14	-> 158
/*    */     //   #15	-> 341
/*    */     //   #16	-> 358
/*    */     //   #17	-> 365
/*    */     //   #18	-> 382
/*    */     //   #19	-> 410
/*    */     //   #20	-> 413
/*    */     //   #21	-> 447
/*    */     //   #22	-> 450
/*    */     //   #23	-> 490
/*    */     //   #24	-> 507
/*    */     //   #25	-> 566
/*    */     //   #26	-> 571
/*    */     //   #27	-> 587
/*    */     //   #28	-> 590
/*    */     //   #29	-> 611
/*    */     //   #30	-> 614
/*    */     //   #31	-> 637
/*    */     //   #32	-> 640
/*    */     //   #33	-> 663
/*    */     //   #34	-> 666
/*    */     //   #35	-> 684
/*    */     //   #36	-> 703
/*    */     //   #37	-> 727
/*    */     //   #38	-> 740
/*    */     //   #39	-> 746
/*    */     //   #40	-> 761
/*    */     //   #41	-> 782
/*    */     //   #42	-> 796
/*    */     //   #43	-> 805
/*    */     //   #44	-> 822
/*    */     //   #45	-> 843
/*    */     //   #46	-> 850
/*    */     //   #47	-> 915
/*    */     //   #48	-> 918
/*    */     //   #49	-> 921
/*    */     //   #50	-> 935
/*    */   }
/*    */   
/*    */   public final boolean tF0(boolean paramBoolean) {
/*    */     return false;
/*    */   } }


/* Location:              /Users/vnnsnnt/Documents/Codespace/JavaWorkspace/RedTrainer/src/main/java/org/trainer/client/PokeMMO.jar!/f/HC0.class
 * Java compiler version: 8 (52.0)
 * JD-Core Version:       1.1.3
 */