/* 1 */ package f;public final class Hd0 extends wb { public static final eo gy0 = new eo(); public final Gp0 X; public hm0 xF0; public boolean mS; private void mG(int paramInt, sh paramsh) { byte b; paramInt = 1549; boolean bool = true; if (this.mS) { b = 14; } else { b = 16; }  float f1 = 250.0F, f2 = 0.8F; hm0 hm01 = this.xF0; ia0((byte)2, paramInt, bool, b, f1, f2, hm01); } public boolean cF0; public ET ae0; public oq K60; public final eo[] Fs; public Hd0(Gp0 paramGp0, hm0 paramhm0, boolean paramBoolean, ET paramET) { super(paramhm0); eo eo1; this.cF0 = true; this.X = paramGp0; this.xF0 = paramhm0; this.mS = paramBoolean; this.ae0 = paramET; this(0.5F, 2.0F, 6.0F); eo[] arrayOfEo; (arrayOfEo = new eo[5])[0] = eo1; this(0.5F, 2.0F, 6.0F); (new eo[5])[1] = eo1; this(1.5F, 4.5F, 4.0F); (new eo[5])[2] = eo1; this(3.0F, 3.5F, 4.0F); (new eo[5])[3] = eo1; this(3.0F, 3.5F, 3.5F); (new eo[5])[4] = eo1; this.Fs = this; } private void P80(int paramInt, sh paramsh) { this.xF0.xy0(1.0F); } public static void h9(eo parameo, int paramInt, sh paramsh) { eo2.getClass(); float f3 = parameo.x, f4 = parameo.y, f5 = parameo.z; eo eo2; (eo2 = q10.Rs).TG0(f3, f4, f5);
/* 2 */     eo1.getClass();
/* 3 */     float f1 = parameo.x, f2 = parameo.y; f4 = parameo.z; eo eo1; (eo1 = q10.HF).TG0(f1, f2, f4); } private void sS(int paramInt, sh paramsh) { if (this.cF0) this.xF0.xy0(1.0F);  vH vH; if ((vH = this.pb) != null) vH.Ji0
/* 4 */         .remove(this.K60);  } private void m(eo parameo, int paramInt, sh paramsh) { parameo.JL(this.K60.PL); } public static eo ML(uT paramuT) { return V1.w3(paramuT.He0, paramuT.He0); } public static void eV(eo parameo, int paramInt, sh paramsh) { eo2.getClass(); float f3 = parameo.x, f4 = parameo.y, f5 = parameo.z; eo eo2; (eo2 = q10.Rs).TG0(f3, f4, f5); eo1.getClass(); float f1 = parameo.x, f2 = parameo.y; f4 = parameo.z; eo eo1; (eo1 = q10.HF).TG0(f1, f2, f4); } private void t00(int paramInt, sh paramsh) { if (this.cF0) this.xF0.xy0(1.0F);  vH vH; if ((vH = this.pb) != null) vH.Ji0.remove(this.K60);  } private void Nv0(eo parameo, int paramInt, sh paramsh) { parameo.JL(this.K60.PL); } public static eo rK(uT paramuT) { return V1.w3(paramuT.He0, paramuT.He0); } public static void iO(eo parameo, int paramInt, sh paramsh) { eo2.getClass(); float f3 = parameo.x, f4 = parameo.y, f5 = parameo.z; eo eo2; (eo2 = q10.Rs).TG0(f3, f4, f5); eo1.getClass(); float f1 = parameo.x, f2 = parameo.y; f4 = parameo.z; eo eo1; (eo1 = q10.HF).TG0(f1, f2, f4); } private void pa(int paramInt, sh paramsh) { if (this.cF0) this.xF0.xy0(1.0F);  vH vH; if ((vH = this.pb) != null) vH.Ji0.remove(this.K60);  } private void Wp0(eo parameo, int paramInt, sh paramsh) { parameo.JL(this.K60.PL); } public static eo dL0(uT paramuT) { return V1.w3(paramuT.He0, paramuT.He0); } public final wb O3() { mW().mg(this.pb.dr0); tS(); return this; } public final So mW() { // Byte code:
/*   */     //   0: aload_0
/*   */     //   1: getfield ae0 : Lf/ET;
/*   */     //   4: getstatic f/ET.gX : Lf/ET;
/*   */     //   7: if_acmpne -> 15
/*   */     //   10: aload_0
/*   */     //   11: invokevirtual yF0 : ()Lf/So;
/*   */     //   14: areturn
/*   */     //   15: aload_0
/*   */     //   16: getfield xF0 : Lf/hm0;
/*   */     //   19: invokevirtual Jx : ()S
/*   */     //   22: aload_0
/*   */     //   23: getfield xF0 : Lf/hm0;
/*   */     //   26: invokevirtual iQ : ()B
/*   */     //   29: istore_1
/*   */     //   30: getstatic f/um0.YA : Lf/eo;
/*   */     //   33: pop
/*   */     //   34: lookupswitch default -> 1356, 12 -> 1363, 15 -> 1363, 17 -> 1363, 22 -> 1363, 41 -> 1363, 42 -> 1363, 49 -> 1363, 63 -> 1363, 70 -> 1363, 71 -> 1363, 72 -> 1363, 73 -> 1363, 81 -> 1363, 82 -> 1363, 90 -> 1363, 91 -> 1363, 92 -> 1363, 93 -> 1363, 109 -> 1363, 110 -> 1363, 116 -> 1363, 117 -> 1363, 118 -> 1363, 119 -> 1363, 120 -> 1363, 121 -> 1363, 129 -> 1363, 130 -> 1363, 137 -> 1363, 138 -> 1363, 139 -> 1363, 140 -> 1363, 142 -> 1363, 145 -> 1363, 146 -> 1363, 151 -> 1363, 166 -> 1363, 169 -> 1363, 170 -> 1363, 171 -> 1363, 174 -> 1363, 187 -> 1363, 188 -> 1363, 189 -> 1363, 193 -> 1363, 200 -> 1363, 201 -> 1363, 211 -> 1363, 223 -> 1363, 226 -> 1363, 230 -> 1363, 233 -> 1363, 249 -> 1363, 250 -> 1363, 251 -> 1363, 267 -> 1363, 269 -> 1363, 270 -> 1363, 278 -> 1363, 279 -> 1363, 284 -> 1363, 291 -> 1363, 292 -> 1363, 307 -> 1363, 313 -> 1363, 314 -> 1363, 318 -> 1363, 319 -> 1363, 320 -> 1363, 321 -> 1363, 330 -> 1363, 333 -> 1363, 337 -> 1363, 338 -> 1363, 339 -> 1363, 340 -> 1363, 344 -> 1363, 347 -> 1363, 349 -> 1363, 351 -> 1363, 353 -> 1363, 355 -> 1363, 358 -> 1363, 362 -> 1363, 367 -> 1363, 368 -> 1363, 369 -> 1363, 370 -> 1363, 374 -> 1363, 375 -> 1363, 380 -> 1363, 381 -> 1363, 382 -> 1363, 384 -> 1363, 385 -> 1363, 412 -> 1363, 413 -> 1363, 414 -> 1363, 415 -> 1363, 416 -> 1363, 425 -> 1363, 426 -> 1363, 429 -> 1363, 433 -> 1363, 436 -> 1363, 437 -> 1363, 455 -> 1363, 456 -> 1363, 457 -> 1363, 458 -> 1363, 462 -> 1363, 468 -> 1363, 469 -> 1363, 472 -> 1363, 474 -> 1363, 476 -> 1363, 477 -> 1363, 478 -> 1363, 479 -> 1363, 480 -> 1363, 481 -> 1363, 482 -> 1363, 487 -> 1373, 488 -> 1363, 489 -> 1363, 491 -> 1363, 517 -> 1363, 518 -> 1363, 527 -> 1363, 528 -> 1363, 550 -> 1363, 561 -> 1363, 562 -> 1363, 563 -> 1363, 564 -> 1363, 567 -> 1363, 577 -> 1363, 578 -> 1363, 579 -> 1363, 582 -> 1363, 583 -> 1363, 584 -> 1363, 587 -> 1363, 589 -> 1363, 592 -> 1363, 593 -> 1363, 594 -> 1363, 598 -> 1363, 599 -> 1363, 601 -> 1363, 602 -> 1363, 605 -> 1363, 606 -> 1363, 608 -> 1363, 609 -> 1363, 615 -> 1363, 618 -> 1363, 628 -> 1363, 635 -> 1363, 637 -> 1363, 641 -> 1363, 642 -> 1363, 645 -> 1363, 648 -> 1359
/*   */     //   1356: goto -> 1368
/*   */     //   1359: iload_1
/*   */     //   1360: ifne -> 1368
/*   */     //   1363: iconst_1
/*   */     //   1364: istore_1
/*   */     //   1365: goto -> 1381
/*   */     //   1368: iconst_0
/*   */     //   1369: istore_1
/*   */     //   1370: goto -> 1381
/*   */     //   1373: iload_1
/*   */     //   1374: iconst_1
/*   */     //   1375: if_icmpne -> 1368
/*   */     //   1378: goto -> 1363
/*   */     //   1381: iload_1
/*   */     //   1382: ifeq -> 1390
/*   */     //   1385: aload_0
/*   */     //   1386: invokevirtual UG : ()Lf/So;
/*   */     //   1389: areturn
/*   */     //   1390: aload_0
/*   */     //   1391: getfield xF0 : Lf/hm0;
/*   */     //   1394: invokevirtual Jx : ()S
/*   */     //   1397: dup
/*   */     //   1398: istore_1
/*   */     //   1399: aload_0
/*   */     //   1400: getfield xF0 : Lf/hm0;
/*   */     //   1403: invokevirtual iQ : ()B
/*   */     //   1406: pop
/*   */     //   1407: bipush #50
/*   */     //   1409: if_icmpeq -> 1423
/*   */     //   1412: iload_1
/*   */     //   1413: bipush #51
/*   */     //   1415: if_icmpeq -> 1423
/*   */     //   1418: iconst_0
/*   */     //   1419: istore_1
/*   */     //   1420: goto -> 1425
/*   */     //   1423: iconst_1
/*   */     //   1424: istore_1
/*   */     //   1425: iload_1
/*   */     //   1426: ifeq -> 1434
/*   */     //   1429: aload_0
/*   */     //   1430: invokevirtual Lpt2 : ()Lf/So;
/*   */     //   1433: areturn
/*   */     //   1434: aload_0
/*   */     //   1435: invokevirtual We0 : ()Lf/So;
/*   */     //   1438: areturn } public final boolean tF0(boolean paramBoolean) { return false; } public final So We0() { // Byte code:
/*   */     //   0: aload_0
/*   */     //   1: dup
/*   */     //   2: dup
/*   */     //   3: getstatic f/km.mI0 : Lf/P1;
/*   */     //   6: getfield AN : Lf/Wo;
/*   */     //   9: getfield Do0 : Lf/yI;
/*   */     //   12: aload_0
/*   */     //   13: dup
/*   */     //   14: dup2
/*   */     //   15: getfield xF0 : Lf/hm0;
/*   */     //   18: invokevirtual t30 : ()V
/*   */     //   21: getfield xF0 : Lf/hm0;
/*   */     //   24: getfield qf : [Lf/uT;
/*   */     //   27: dup
/*   */     //   28: astore_1
/*   */     //   29: invokestatic stream : ([Ljava/lang/Object;)Ljava/util/stream/Stream;
/*   */     //   32: <illegal opcode> apply : ()Ljava/util/function/Function;
/*   */     //   37: invokeinterface map : (Ljava/util/function/Function;)Ljava/util/stream/Stream;
/*   */     //   42: <illegal opcode> apply : ()Ljava/util/function/IntFunction;
/*   */     //   47: invokeinterface toArray : (Ljava/util/function/IntFunction;)[Ljava/lang/Object;
/*   */     //   52: checkcast [Lf/eo;
/*   */     //   55: astore_2
/*   */     //   56: getfield xF0 : Lf/hm0;
/*   */     //   59: getfield rF0 : Lf/uT;
/*   */     //   62: getfield He0 : Lf/eo;
/*   */     //   65: dup
/*   */     //   66: invokestatic w3 : (Lf/eo;Lf/eo;)Lf/eo;
/*   */     //   69: astore_3
/*   */     //   70: getfield xF0 : Lf/hm0;
/*   */     //   73: invokevirtual oi : ()B
/*   */     //   76: iconst_4
/*   */     //   77: swap
/*   */     //   78: invokevirtual o3 : (II)Lf/R30;
/*   */     //   81: invokestatic s2 : (Lf/R30;)Lf/oq;
/*   */     //   84: dup
/*   */     //   85: astore #4
/*   */     //   87: putfield K60 : Lf/oq;
/*   */     //   90: getfield pb : Lf/vH;
/*   */     //   93: getfield Ji0 : Ljava/util/ArrayList;
/*   */     //   96: aload #4
/*   */     //   98: invokevirtual add : (Ljava/lang/Object;)Z
/*   */     //   101: pop
/*   */     //   102: new f/eo
/*   */     //   105: dup
/*   */     //   106: astore #4
/*   */     //   108: invokespecial <init> : ()V
/*   */     //   111: getfield mS : Z
/*   */     //   114: ifeq -> 155
/*   */     //   117: aload_0
/*   */     //   118: getfield K60 : Lf/oq;
/*   */     //   121: aload_3
/*   */     //   122: dup
/*   */     //   123: dup
/*   */     //   124: getfield x : F
/*   */     //   127: ldc 0.5
/*   */     //   129: fsub
/*   */     //   130: fstore_3
/*   */     //   131: getfield y : F
/*   */     //   134: ldc 0.5
/*   */     //   136: fsub
/*   */     //   137: fstore #5
/*   */     //   139: getfield z : F
/*   */     //   142: fstore #6
/*   */     //   144: fload_3
/*   */     //   145: fload #5
/*   */     //   147: fload #6
/*   */     //   149: invokevirtual qf0 : (FFF)V
/*   */     //   152: goto -> 187
/*   */     //   155: aload_0
/*   */     //   156: getfield K60 : Lf/oq;
/*   */     //   159: aload_3
/*   */     //   160: dup
/*   */     //   161: dup
/*   */     //   162: getfield x : F
/*   */     //   165: fstore_3
/*   */     //   166: getfield y : F
/*   */     //   169: ldc 0.5
/*   */     //   171: fadd
/*   */     //   172: fstore #5
/*   */     //   174: getfield z : F
/*   */     //   177: fstore #6
/*   */     //   179: fload_3
/*   */     //   180: fload #5
/*   */     //   182: fload #6
/*   */     //   184: invokevirtual qf0 : (FFF)V
/*   */     //   187: aload_1
/*   */     //   188: invokestatic k60 : ()Lf/So;
/*   */     //   191: dup
/*   */     //   192: aload_0
/*   */     //   193: swap
/*   */     //   194: putfield synchronized : Lf/So;
/*   */     //   197: invokevirtual L5 : ()Lf/So;
/*   */     //   200: pop
/*   */     //   201: arraylength
/*   */     //   202: istore_3
/*   */     //   203: iconst_0
/*   */     //   204: istore #5
/*   */     //   206: iload #5
/*   */     //   208: iload_3
/*   */     //   209: if_icmpge -> 320
/*   */     //   212: aload_0
/*   */     //   213: aload_1
/*   */     //   214: iload #5
/*   */     //   216: aaload
/*   */     //   217: astore #6
/*   */     //   219: getfield synchronized : Lf/So;
/*   */     //   222: bipush #7
/*   */     //   224: aload #6
/*   */     //   226: invokestatic aG : (ILjava/lang/Object;)Lf/Wz0;
/*   */     //   229: fconst_0
/*   */     //   230: fconst_0
/*   */     //   231: invokevirtual n20 : (FF)Lf/Wz0;
/*   */     //   234: invokevirtual PL : (Lf/Wz0;)Lf/So;
/*   */     //   237: bipush #8
/*   */     //   239: aload #6
/*   */     //   241: invokestatic aG : (ILjava/lang/Object;)Lf/Wz0;
/*   */     //   244: iconst_4
/*   */     //   245: newarray float
/*   */     //   247: dup
/*   */     //   248: dup
/*   */     //   249: dup2
/*   */     //   250: iconst_0
/*   */     //   251: fconst_1
/*   */     //   252: fastore
/*   */     //   253: iconst_1
/*   */     //   254: fconst_1
/*   */     //   255: fastore
/*   */     //   256: iconst_2
/*   */     //   257: fconst_1
/*   */     //   258: fastore
/*   */     //   259: iconst_3
/*   */     //   260: fconst_1
/*   */     //   261: fastore
/*   */     //   262: invokevirtual qY : ([F)Lf/Wz0;
/*   */     //   265: invokevirtual PL : (Lf/Wz0;)Lf/So;
/*   */     //   268: bipush #10
/*   */     //   270: aload #6
/*   */     //   272: invokestatic aG : (ILjava/lang/Object;)Lf/Wz0;
/*   */     //   275: iconst_4
/*   */     //   276: newarray float
/*   */     //   278: dup
/*   */     //   279: dup
/*   */     //   280: dup2
/*   */     //   281: iconst_0
/*   */     //   282: fconst_1
/*   */     //   283: fastore
/*   */     //   284: iconst_1
/*   */     //   285: fconst_1
/*   */     //   286: fastore
/*   */     //   287: iconst_2
/*   */     //   288: fconst_1
/*   */     //   289: fastore
/*   */     //   290: iconst_3
/*   */     //   291: fconst_1
/*   */     //   292: fastore
/*   */     //   293: invokevirtual qY : ([F)Lf/Wz0;
/*   */     //   296: invokevirtual PL : (Lf/Wz0;)Lf/So;
/*   */     //   299: aload_0
/*   */     //   300: getfield mS : Z
/*   */     //   303: sipush #1382
/*   */     //   306: swap
/*   */     //   307: invokestatic A50 : (SZ)Lf/Wz0;
/*   */     //   310: invokevirtual PL : (Lf/Wz0;)Lf/So;
/*   */     //   313: pop
/*   */     //   314: iinc #5, 1
/*   */     //   317: goto -> 206
/*   */     //   320: aload_0
/*   */     //   321: dup
/*   */     //   322: getfield synchronized : Lf/So;
/*   */     //   325: invokevirtual Kr : ()Lf/So;
/*   */     //   328: pop
/*   */     //   329: getfield mS : Z
/*   */     //   332: ifeq -> 575
/*   */     //   335: aload_0
/*   */     //   336: dup
/*   */     //   337: dup2
/*   */     //   338: getfield Fs : [Lf/eo;
/*   */     //   341: iconst_2
/*   */     //   342: aaload
/*   */     //   343: aload_0
/*   */     //   344: getfield xF0 : Lf/hm0;
/*   */     //   347: getstatic f/km.MR : Lf/Gp0;
/*   */     //   350: invokevirtual zJ0 : (Lf/Gp0;)F
/*   */     //   353: fconst_0
/*   */     //   354: fconst_0
/*   */     //   355: invokevirtual Tz : (FFF)Lf/eo;
/*   */     //   358: pop
/*   */     //   359: getfield Fs : [Lf/eo;
/*   */     //   362: iconst_3
/*   */     //   363: aaload
/*   */     //   364: aload_0
/*   */     //   365: getfield xF0 : Lf/hm0;
/*   */     //   368: getstatic f/km.MR : Lf/Gp0;
/*   */     //   371: invokevirtual zJ0 : (Lf/Gp0;)F
/*   */     //   374: fconst_0
/*   */     //   375: fconst_0
/*   */     //   376: invokevirtual Tz : (FFF)Lf/eo;
/*   */     //   379: pop
/*   */     //   380: getfield Fs : [Lf/eo;
/*   */     //   383: iconst_4
/*   */     //   384: aaload
/*   */     //   385: aload_0
/*   */     //   386: getfield xF0 : Lf/hm0;
/*   */     //   389: getstatic f/km.MR : Lf/Gp0;
/*   */     //   392: invokevirtual zJ0 : (Lf/Gp0;)F
/*   */     //   395: fconst_0
/*   */     //   396: fconst_0
/*   */     //   397: invokevirtual Tz : (FFF)Lf/eo;
/*   */     //   400: pop
/*   */     //   401: new f/QX
/*   */     //   404: dup
/*   */     //   405: astore_3
/*   */     //   406: aload_0
/*   */     //   407: getfield Fs : [Lf/eo;
/*   */     //   410: iconst_0
/*   */     //   411: invokespecial <init> : ([Lf/Ou0;Z)V
/*   */     //   414: getfield synchronized : Lf/So;
/*   */     //   417: invokevirtual eC : ()Lf/So;
/*   */     //   420: astore #5
/*   */     //   422: fconst_0
/*   */     //   423: fstore #6
/*   */     //   425: fload #6
/*   */     //   427: fconst_1
/*   */     //   428: fcmpg
/*   */     //   429: ifge -> 501
/*   */     //   432: fload #6
/*   */     //   434: aload #5
/*   */     //   436: aload_0
/*   */     //   437: aload_3
/*   */     //   438: getstatic f/Hd0.gy0 : Lf/eo;
/*   */     //   441: dup
/*   */     //   442: astore #7
/*   */     //   444: fload #6
/*   */     //   446: invokevirtual Gc0 : (Lf/Ou0;F)Lf/Ou0;
/*   */     //   449: pop
/*   */     //   450: getfield K60 : Lf/oq;
/*   */     //   453: iconst_4
/*   */     //   454: ldc_w 0.01
/*   */     //   457: invokestatic gq : (Ljava/lang/Object;IF)Lf/Wz0;
/*   */     //   460: aload #7
/*   */     //   462: dup
/*   */     //   463: dup
/*   */     //   464: getfield x : F
/*   */     //   467: fstore #6
/*   */     //   469: getfield y : F
/*   */     //   472: fstore #7
/*   */     //   474: getfield z : F
/*   */     //   477: fstore #8
/*   */     //   479: fload #6
/*   */     //   481: fload #7
/*   */     //   483: fload #8
/*   */     //   485: invokevirtual qw0 : (FFF)Lf/Wz0;
/*   */     //   488: invokevirtual PL : (Lf/Wz0;)Lf/So;
/*   */     //   491: pop
/*   */     //   492: ldc_w 0.01
/*   */     //   495: fadd
/*   */     //   496: fstore #6
/*   */     //   498: goto -> 425
/*   */     //   501: aload_0
/*   */     //   502: dup
/*   */     //   503: dup
/*   */     //   504: aload #5
/*   */     //   506: aload_0
/*   */     //   507: aload #4
/*   */     //   509: aload #5
/*   */     //   511: invokevirtual Kr : ()Lf/So;
/*   */     //   514: pop
/*   */     //   515: <illegal opcode> Do : (Lf/Hd0;Lf/eo;)Lf/hk0;
/*   */     //   520: invokestatic OC : (Lf/hk0;)Lf/Wz0;
/*   */     //   523: invokevirtual PL : (Lf/Wz0;)Lf/So;
/*   */     //   526: pop
/*   */     //   527: getfield Fs : [Lf/eo;
/*   */     //   530: iconst_2
/*   */     //   531: aaload
/*   */     //   532: ldc 1.5
/*   */     //   534: ldc 4.5
/*   */     //   536: ldc 4.0
/*   */     //   538: invokevirtual TG0 : (FFF)Lf/eo;
/*   */     //   541: pop
/*   */     //   542: getfield Fs : [Lf/eo;
/*   */     //   545: iconst_3
/*   */     //   546: aaload
/*   */     //   547: ldc 3.0
/*   */     //   549: ldc 3.5
/*   */     //   551: ldc 4.0
/*   */     //   553: invokevirtual TG0 : (FFF)Lf/eo;
/*   */     //   556: pop
/*   */     //   557: getfield Fs : [Lf/eo;
/*   */     //   560: iconst_4
/*   */     //   561: aaload
/*   */     //   562: ldc 3.0
/*   */     //   564: ldc 3.5
/*   */     //   566: ldc 3.5
/*   */     //   568: invokevirtual TG0 : (FFF)Lf/eo;
/*   */     //   571: pop
/*   */     //   572: goto -> 598
/*   */     //   575: aload #4
/*   */     //   577: aload_0
/*   */     //   578: dup
/*   */     //   579: getfield synchronized : Lf/So;
/*   */     //   582: ldc 0.5
/*   */     //   584: invokevirtual Wz0 : (F)Lf/So;
/*   */     //   587: pop
/*   */     //   588: getfield K60 : Lf/oq;
/*   */     //   591: getfield PL : Lf/eo;
/*   */     //   594: invokevirtual JL : (Lf/eo;)Lf/eo;
/*   */     //   597: pop
/*   */     //   598: aload_0
/*   */     //   599: dup
/*   */     //   600: dup
/*   */     //   601: getfield synchronized : Lf/So;
/*   */     //   604: invokevirtual L5 : ()Lf/So;
/*   */     //   607: pop
/*   */     //   608: getfield synchronized : Lf/So;
/*   */     //   611: invokevirtual eC : ()Lf/So;
/*   */     //   614: aload_0
/*   */     //   615: getfield K60 : Lf/oq;
/*   */     //   618: bipush #9
/*   */     //   620: ldc_w 0.2
/*   */     //   623: invokestatic gq : (Ljava/lang/Object;IF)Lf/Wz0;
/*   */     //   626: fconst_0
/*   */     //   627: invokevirtual a : (F)Lf/Wz0;
/*   */     //   630: invokevirtual PL : (Lf/Wz0;)Lf/So;
/*   */     //   633: aload_0
/*   */     //   634: getfield K60 : Lf/oq;
/*   */     //   637: iconst_4
/*   */     //   638: ldc_w 0.01
/*   */     //   641: invokestatic gq : (Ljava/lang/Object;IF)Lf/Wz0;
/*   */     //   644: fconst_0
/*   */     //   645: fconst_0
/*   */     //   646: fconst_0
/*   */     //   647: invokevirtual qw0 : (FFF)Lf/Wz0;
/*   */     //   650: invokevirtual PL : (Lf/Wz0;)Lf/So;
/*   */     //   653: pop
/*   */     //   654: getfield synchronized : Lf/So;
/*   */     //   657: invokevirtual L5 : ()Lf/So;
/*   */     //   660: pop
/*   */     //   661: iconst_0
/*   */     //   662: istore_3
/*   */     //   663: iload_3
/*   */     //   664: aload_1
/*   */     //   665: arraylength
/*   */     //   666: if_icmpge -> 726
/*   */     //   669: aload_0
/*   */     //   670: getfield synchronized : Lf/So;
/*   */     //   673: aload_1
/*   */     //   674: iload_3
/*   */     //   675: aaload
/*   */     //   676: iconst_4
/*   */     //   677: ldc_w 0.01
/*   */     //   680: invokestatic gq : (Ljava/lang/Object;IF)Lf/Wz0;
/*   */     //   683: aload_2
/*   */     //   684: iload_3
/*   */     //   685: aaload
/*   */     //   686: dup
/*   */     //   687: dup
/*   */     //   688: getfield x : F
/*   */     //   691: fstore #5
/*   */     //   693: getfield y : F
/*   */     //   696: ldc_w 0.55
/*   */     //   699: fadd
/*   */     //   700: fstore #6
/*   */     //   702: getfield z : F
/*   */     //   705: fstore #7
/*   */     //   707: fload #5
/*   */     //   709: fload #6
/*   */     //   711: fload #7
/*   */     //   713: invokevirtual qw0 : (FFF)Lf/Wz0;
/*   */     //   716: invokevirtual PL : (Lf/Wz0;)Lf/So;
/*   */     //   719: pop
/*   */     //   720: iinc #3, 1
/*   */     //   723: goto -> 663
/*   */     //   726: aload_0
/*   */     //   727: dup
/*   */     //   728: dup
/*   */     //   729: getfield synchronized : Lf/So;
/*   */     //   732: invokevirtual Kr : ()Lf/So;
/*   */     //   735: pop
/*   */     //   736: getfield synchronized : Lf/So;
/*   */     //   739: sipush #1383
/*   */     //   742: invokestatic cOM2 : (S)Lf/Wz0;
/*   */     //   745: invokevirtual PL : (Lf/Wz0;)Lf/So;
/*   */     //   748: aload_0
/*   */     //   749: <illegal opcode> Do : (Lf/Hd0;)Lf/hk0;
/*   */     //   754: invokestatic OC : (Lf/hk0;)Lf/Wz0;
/*   */     //   757: invokevirtual PL : (Lf/Wz0;)Lf/So;
/*   */     //   760: aload #4
/*   */     //   762: <illegal opcode> Do : (Lf/eo;)Lf/hk0;
/*   */     //   767: invokestatic OC : (Lf/hk0;)Lf/Wz0;
/*   */     //   770: invokevirtual PL : (Lf/Wz0;)Lf/So;
/*   */     //   773: astore_3
/*   */     //   774: getfield xF0 : Lf/hm0;
/*   */     //   777: invokevirtual oi : ()B
/*   */     //   780: bipush #15
/*   */     //   782: if_icmpne -> 793
/*   */     //   785: ldc_w 'spawn_cherish'
/*   */     //   788: astore #4
/*   */     //   790: goto -> 798
/*   */     //   793: ldc_w 'spawn'
/*   */     //   796: astore #4
/*   */     //   798: aload_0
/*   */     //   799: dup
/*   */     //   800: aload_3
/*   */     //   801: aload_0
/*   */     //   802: aload #4
/*   */     //   804: invokevirtual con : (Ljava/lang/String;)Lf/Wz0;
/*   */     //   807: invokevirtual PL : (Lf/Wz0;)Lf/So;
/*   */     //   810: pop
/*   */     //   811: getfield xF0 : Lf/hm0;
/*   */     //   814: invokevirtual oi : ()B
/*   */     //   817: invokevirtual cON : (B)Lf/Wz0;
/*   */     //   820: dup
/*   */     //   821: astore_3
/*   */     //   822: ifnull -> 834
/*   */     //   825: aload_0
/*   */     //   826: getfield synchronized : Lf/So;
/*   */     //   829: aload_3
/*   */     //   830: invokevirtual PL : (Lf/Wz0;)Lf/So;
/*   */     //   833: pop
/*   */     //   834: aload_1
/*   */     //   835: aload_0
/*   */     //   836: dup
/*   */     //   837: getfield synchronized : Lf/So;
/*   */     //   840: ldc_w 0.4
/*   */     //   843: invokevirtual Wz0 : (F)Lf/So;
/*   */     //   846: pop
/*   */     //   847: getfield synchronized : Lf/So;
/*   */     //   850: invokevirtual L5 : ()Lf/So;
/*   */     //   853: pop
/*   */     //   854: arraylength
/*   */     //   855: istore_3
/*   */     //   856: iconst_0
/*   */     //   857: istore #4
/*   */     //   859: iload #4
/*   */     //   861: iload_3
/*   */     //   862: if_icmpge -> 902
/*   */     //   865: aload_0
/*   */     //   866: aload_1
/*   */     //   867: iload #4
/*   */     //   869: aaload
/*   */     //   870: astore #5
/*   */     //   872: getfield synchronized : Lf/So;
/*   */     //   875: aload #5
/*   */     //   877: bipush #7
/*   */     //   879: fconst_1
/*   */     //   880: invokestatic gq : (Ljava/lang/Object;IF)Lf/Wz0;
/*   */     //   883: ldc_w 1.1
/*   */     //   886: ldc_w 1.1
/*   */     //   889: invokevirtual n20 : (FF)Lf/Wz0;
/*   */     //   892: invokevirtual PL : (Lf/Wz0;)Lf/So;
/*   */     //   895: pop
/*   */     //   896: iinc #4, 1
/*   */     //   899: goto -> 859
/*   */     //   902: aload_0
/*   */     //   903: dup
/*   */     //   904: dup
/*   */     //   905: getfield synchronized : Lf/So;
/*   */     //   908: invokevirtual Kr : ()Lf/So;
/*   */     //   911: pop
/*   */     //   912: getfield synchronized : Lf/So;
/*   */     //   915: invokevirtual eC : ()Lf/So;
/*   */     //   918: pop
/*   */     //   919: getfield synchronized : Lf/So;
/*   */     //   922: invokevirtual L5 : ()Lf/So;
/*   */     //   925: pop
/*   */     //   926: iconst_0
/*   */     //   927: istore_3
/*   */     //   928: iload_3
/*   */     //   929: aload_1
/*   */     //   930: arraylength
/*   */     //   931: if_icmpge -> 1086
/*   */     //   934: aload_0
/*   */     //   935: getfield X : Lf/Gp0;
/*   */     //   938: getfield rx : Lf/ky;
/*   */     //   941: aload_0
/*   */     //   942: getfield xF0 : Lf/hm0;
/*   */     //   945: getfield ws : B
/*   */     //   948: invokevirtual cF : (I)Z
/*   */     //   951: ifeq -> 974
/*   */     //   954: aload_1
/*   */     //   955: iload_3
/*   */     //   956: aaload
/*   */     //   957: bipush #11
/*   */     //   959: ldc_w 0.25
/*   */     //   962: invokestatic gq : (Ljava/lang/Object;IF)Lf/Wz0;
/*   */     //   965: fconst_0
/*   */     //   966: invokevirtual a : (F)Lf/Wz0;
/*   */     //   969: astore #4
/*   */     //   971: goto -> 1010
/*   */     //   974: aload_1
/*   */     //   975: iload_3
/*   */     //   976: aaload
/*   */     //   977: bipush #10
/*   */     //   979: ldc_w 0.25
/*   */     //   982: invokestatic gq : (Ljava/lang/Object;IF)Lf/Wz0;
/*   */     //   985: iconst_4
/*   */     //   986: newarray float
/*   */     //   988: dup
/*   */     //   989: dup
/*   */     //   990: dup2
/*   */     //   991: iconst_0
/*   */     //   992: fconst_0
/*   */     //   993: fastore
/*   */     //   994: iconst_1
/*   */     //   995: fconst_0
/*   */     //   996: fastore
/*   */     //   997: iconst_2
/*   */     //   998: fconst_0
/*   */     //   999: fastore
/*   */     //   1000: iconst_3
/*   */     //   1001: ldc_w 0.6
/*   */     //   1004: fastore
/*   */     //   1005: invokevirtual qY : ([F)Lf/Wz0;
/*   */     //   1008: astore #4
/*   */     //   1010: aload_0
/*   */     //   1011: getfield synchronized : Lf/So;
/*   */     //   1014: aload_1
/*   */     //   1015: iload_3
/*   */     //   1016: aaload
/*   */     //   1017: bipush #7
/*   */     //   1019: ldc_w 0.4
/*   */     //   1022: invokestatic gq : (Ljava/lang/Object;IF)Lf/Wz0;
/*   */     //   1025: fconst_1
/*   */     //   1026: fconst_1
/*   */     //   1027: invokevirtual n20 : (FF)Lf/Wz0;
/*   */     //   1030: invokevirtual PL : (Lf/Wz0;)Lf/So;
/*   */     //   1033: aload #4
/*   */     //   1035: invokevirtual PL : (Lf/Wz0;)Lf/So;
/*   */     //   1038: aload_1
/*   */     //   1039: iload_3
/*   */     //   1040: aaload
/*   */     //   1041: iconst_4
/*   */     //   1042: ldc 0.5
/*   */     //   1044: invokestatic gq : (Ljava/lang/Object;IF)Lf/Wz0;
/*   */     //   1047: aload_2
/*   */     //   1048: iload_3
/*   */     //   1049: aaload
/*   */     //   1050: dup
/*   */     //   1051: dup
/*   */     //   1052: getfield x : F
/*   */     //   1055: fstore #4
/*   */     //   1057: getfield y : F
/*   */     //   1060: fstore #5
/*   */     //   1062: getfield z : F
/*   */     //   1065: fstore #6
/*   */     //   1067: fload #4
/*   */     //   1069: fload #5
/*   */     //   1071: fload #6
/*   */     //   1073: invokevirtual qw0 : (FFF)Lf/Wz0;
/*   */     //   1076: invokevirtual PL : (Lf/Wz0;)Lf/So;
/*   */     //   1079: pop
/*   */     //   1080: iinc #3, 1
/*   */     //   1083: goto -> 928
/*   */     //   1086: aload_0
/*   */     //   1087: dup
/*   */     //   1088: dup
/*   */     //   1089: getfield synchronized : Lf/So;
/*   */     //   1092: invokevirtual Kr : ()Lf/So;
/*   */     //   1095: pop
/*   */     //   1096: getfield synchronized : Lf/So;
/*   */     //   1099: astore_1
/*   */     //   1100: getfield xF0 : Lf/hm0;
/*   */     //   1103: dup
/*   */     //   1104: astore_2
/*   */     //   1105: invokevirtual Jx : ()S
/*   */     //   1108: aload_2
/*   */     //   1109: invokevirtual iQ : ()B
/*   */     //   1112: istore_3
/*   */     //   1113: getstatic f/um0.YA : Lf/eo;
/*   */     //   1116: pop
/*   */     //   1117: lookupswitch default -> 2440, 12 -> 2455, 15 -> 2455, 17 -> 2455, 22 -> 2455, 41 -> 2455, 42 -> 2455, 49 -> 2455, 63 -> 2455, 70 -> 2455, 71 -> 2455, 72 -> 2455, 73 -> 2455, 81 -> 2455, 82 -> 2455, 90 -> 2455, 91 -> 2455, 92 -> 2455, 93 -> 2455, 109 -> 2455, 110 -> 2455, 116 -> 2455, 117 -> 2455, 118 -> 2455, 119 -> 2455, 120 -> 2455, 121 -> 2455, 129 -> 2455, 130 -> 2455, 137 -> 2455, 138 -> 2455, 139 -> 2455, 140 -> 2455, 142 -> 2455, 145 -> 2455, 146 -> 2455, 151 -> 2455, 166 -> 2455, 169 -> 2455, 170 -> 2455, 171 -> 2455, 174 -> 2455, 187 -> 2455, 188 -> 2455, 189 -> 2455, 193 -> 2455, 200 -> 2455, 201 -> 2455, 211 -> 2455, 223 -> 2455, 226 -> 2455, 230 -> 2455, 233 -> 2455, 249 -> 2455, 250 -> 2455, 251 -> 2455, 267 -> 2455, 269 -> 2455, 270 -> 2455, 278 -> 2455, 279 -> 2455, 284 -> 2455, 291 -> 2455, 292 -> 2455, 307 -> 2455, 313 -> 2455, 314 -> 2455, 318 -> 2455, 319 -> 2455, 320 -> 2455, 321 -> 2455, 330 -> 2455, 333 -> 2455, 337 -> 2455, 338 -> 2455, 339 -> 2455, 340 -> 2455, 344 -> 2455, 347 -> 2455, 349 -> 2455, 351 -> 2455, 353 -> 2455, 355 -> 2455, 358 -> 2455, 362 -> 2455, 367 -> 2455, 368 -> 2455, 369 -> 2455, 370 -> 2455, 374 -> 2455, 375 -> 2455, 380 -> 2455, 381 -> 2455, 382 -> 2455, 384 -> 2455, 385 -> 2455, 412 -> 2455, 413 -> 2455, 414 -> 2455, 415 -> 2455, 416 -> 2455, 425 -> 2455, 426 -> 2455, 429 -> 2455, 433 -> 2455, 436 -> 2455, 437 -> 2455, 455 -> 2455, 456 -> 2455, 457 -> 2455, 458 -> 2455, 462 -> 2455, 468 -> 2455, 469 -> 2455, 472 -> 2455, 474 -> 2455, 476 -> 2455, 477 -> 2455, 478 -> 2455, 479 -> 2455, 480 -> 2455, 481 -> 2455, 482 -> 2455, 487 -> 2450, 488 -> 2455, 489 -> 2455, 491 -> 2455, 517 -> 2455, 518 -> 2455, 527 -> 2455, 528 -> 2455, 550 -> 2455, 561 -> 2455, 562 -> 2455, 563 -> 2455, 564 -> 2455, 567 -> 2455, 577 -> 2455, 578 -> 2455, 579 -> 2455, 582 -> 2455, 583 -> 2455, 584 -> 2455, 587 -> 2455, 589 -> 2455, 592 -> 2455, 593 -> 2455, 594 -> 2455, 598 -> 2455, 599 -> 2455, 601 -> 2455, 602 -> 2455, 605 -> 2455, 606 -> 2455, 608 -> 2455, 609 -> 2455, 615 -> 2455, 618 -> 2455, 628 -> 2455, 635 -> 2455, 637 -> 2455, 641 -> 2455, 642 -> 2455, 645 -> 2455, 648 -> 2443
/*   */     //   2440: goto -> 2459
/*   */     //   2443: iload_3
/*   */     //   2444: ifne -> 2459
/*   */     //   2447: goto -> 2455
/*   */     //   2450: iload_3
/*   */     //   2451: iconst_1
/*   */     //   2452: if_icmpne -> 2459
/*   */     //   2455: iconst_1
/*   */     //   2456: goto -> 2460
/*   */     //   2459: iconst_0
/*   */     //   2460: ifeq -> 2470
/*   */     //   2463: sipush #2029
/*   */     //   2466: istore_2
/*   */     //   2467: goto -> 2549
/*   */     //   2470: aload_2
/*   */     //   2471: invokevirtual Jx : ()S
/*   */     //   2474: dup
/*   */     //   2475: istore_3
/*   */     //   2476: aload_2
/*   */     //   2477: invokevirtual iQ : ()B
/*   */     //   2480: pop
/*   */     //   2481: bipush #50
/*   */     //   2483: if_icmpeq -> 2496
/*   */     //   2486: iload_3
/*   */     //   2487: bipush #51
/*   */     //   2489: if_icmpeq -> 2496
/*   */     //   2492: iconst_0
/*   */     //   2493: goto -> 2497
/*   */     //   2496: iconst_1
/*   */     //   2497: ifeq -> 2505
/*   */     //   2500: iconst_0
/*   */     //   2501: istore_2
/*   */     //   2502: goto -> 2549
/*   */     //   2505: aload_2
/*   */     //   2506: invokevirtual xp : ()Lf/UD0;
/*   */     //   2509: getfield fu : S
/*   */     //   2512: sipush #500
/*   */     //   2515: if_icmpge -> 2525
/*   */     //   2518: sipush #1400
/*   */     //   2521: istore_2
/*   */     //   2522: goto -> 2549
/*   */     //   2525: aload_2
/*   */     //   2526: invokevirtual xp : ()Lf/UD0;
/*   */     //   2529: getfield fu : S
/*   */     //   2532: sipush #1500
/*   */     //   2535: if_icmpge -> 2545
/*   */     //   2538: sipush #1399
/*   */     //   2541: istore_2
/*   */     //   2542: goto -> 2549
/*   */     //   2545: sipush #1398
/*   */     //   2548: istore_2
/*   */     //   2549: aload_0
/*   */     //   2550: dup
/*   */     //   2551: dup2
/*   */     //   2552: aload_1
/*   */     //   2553: iload_2
/*   */     //   2554: aload_0
/*   */     //   2555: getfield xF0 : Lf/hm0;
/*   */     //   2558: invokevirtual Si : ()Z
/*   */     //   2561: invokestatic A50 : (SZ)Lf/Wz0;
/*   */     //   2564: invokevirtual PL : (Lf/Wz0;)Lf/So;
/*   */     //   2567: pop
/*   */     //   2568: getfield synchronized : Lf/So;
/*   */     //   2571: invokevirtual Kr : ()Lf/So;
/*   */     //   2574: pop
/*   */     //   2575: getfield synchronized : Lf/So;
/*   */     //   2578: invokevirtual Kr : ()Lf/So;
/*   */     //   2581: pop
/*   */     //   2582: getfield synchronized : Lf/So;
/*   */     //   2585: invokevirtual Kr : ()Lf/So;
/*   */     //   2588: pop
/*   */     //   2589: getfield synchronized : Lf/So;
/*   */     //   2592: areturn
/*   */     // Line number table:
/*   */     //   Java source line number -> byte code offset
/*   */     //   #1	-> 9
/*   */     //   #2	-> 15
/*   */     //   #3	-> 24
/*   */     //   #4	-> 29
/*   */     //   #5	-> 59
/*   */     //   #6	-> 62
/*   */     //   #7	-> 66
/*   */     //   #8	-> 70
/*   */     //   #9	-> 93
/*   */     //   #10	-> 98
/*   */     //   #11	-> 307
/*   */     //   #12	-> 310
/*   */     //   #13	-> 591
/*   */     //   #14	-> 594
/*   */     //   #15	-> 742
/*   */     //   #16	-> 745
/*   */     //   #17	-> 785
/*   */     //   #18	-> 804
/*   */     //   #19	-> 938
/*   */     //   #20	-> 942
/*   */     //   #21	-> 945
/*   */     //   #22	-> 948
/*   */     //   #23	-> 1105
/*   */     //   #24	-> 1109
/*   */     //   #25	-> 2506
/*   */     //   #26	-> 2509
/*   */     //   #27	-> 2526
/*   */     //   #28	-> 2529
/*   */     //   #29	-> 2555 } public final So UG() { // Byte code:
/*   */     //   0: aload_0
/*   */     //   1: dup
/*   */     //   2: dup
/*   */     //   3: getstatic f/km.mI0 : Lf/P1;
/*   */     //   6: getfield AN : Lf/Wo;
/*   */     //   9: getfield Do0 : Lf/yI;
/*   */     //   12: aload_0
/*   */     //   13: dup
/*   */     //   14: dup2
/*   */     //   15: getfield xF0 : Lf/hm0;
/*   */     //   18: invokevirtual t30 : ()V
/*   */     //   21: getfield xF0 : Lf/hm0;
/*   */     //   24: getfield qf : [Lf/uT;
/*   */     //   27: dup
/*   */     //   28: astore_1
/*   */     //   29: invokestatic stream : ([Ljava/lang/Object;)Ljava/util/stream/Stream;
/*   */     //   32: <illegal opcode> apply : ()Ljava/util/function/Function;
/*   */     //   37: invokeinterface map : (Ljava/util/function/Function;)Ljava/util/stream/Stream;
/*   */     //   42: <illegal opcode> apply : ()Ljava/util/function/IntFunction;
/*   */     //   47: invokeinterface toArray : (Ljava/util/function/IntFunction;)[Ljava/lang/Object;
/*   */     //   52: checkcast [Lf/eo;
/*   */     //   55: astore_2
/*   */     //   56: getfield xF0 : Lf/hm0;
/*   */     //   59: getfield rF0 : Lf/uT;
/*   */     //   62: getfield He0 : Lf/eo;
/*   */     //   65: dup
/*   */     //   66: invokestatic w3 : (Lf/eo;Lf/eo;)Lf/eo;
/*   */     //   69: astore_3
/*   */     //   70: getfield xF0 : Lf/hm0;
/*   */     //   73: invokevirtual oi : ()B
/*   */     //   76: iconst_4
/*   */     //   77: swap
/*   */     //   78: invokevirtual o3 : (II)Lf/R30;
/*   */     //   81: invokestatic s2 : (Lf/R30;)Lf/oq;
/*   */     //   84: dup
/*   */     //   85: astore #4
/*   */     //   87: putfield K60 : Lf/oq;
/*   */     //   90: getfield pb : Lf/vH;
/*   */     //   93: getfield Ji0 : Ljava/util/ArrayList;
/*   */     //   96: aload #4
/*   */     //   98: invokevirtual add : (Ljava/lang/Object;)Z
/*   */     //   101: pop
/*   */     //   102: new f/eo
/*   */     //   105: dup
/*   */     //   106: astore #4
/*   */     //   108: invokespecial <init> : ()V
/*   */     //   111: getfield mS : Z
/*   */     //   114: ifeq -> 155
/*   */     //   117: aload_0
/*   */     //   118: getfield K60 : Lf/oq;
/*   */     //   121: aload_3
/*   */     //   122: dup
/*   */     //   123: dup
/*   */     //   124: getfield x : F
/*   */     //   127: ldc 0.5
/*   */     //   129: fsub
/*   */     //   130: fstore_3
/*   */     //   131: getfield y : F
/*   */     //   134: ldc 0.5
/*   */     //   136: fsub
/*   */     //   137: fstore #5
/*   */     //   139: getfield z : F
/*   */     //   142: fstore #6
/*   */     //   144: fload_3
/*   */     //   145: fload #5
/*   */     //   147: fload #6
/*   */     //   149: invokevirtual qf0 : (FFF)V
/*   */     //   152: goto -> 187
/*   */     //   155: aload_0
/*   */     //   156: getfield K60 : Lf/oq;
/*   */     //   159: aload_3
/*   */     //   160: dup
/*   */     //   161: dup
/*   */     //   162: getfield x : F
/*   */     //   165: fstore_3
/*   */     //   166: getfield y : F
/*   */     //   169: ldc 0.5
/*   */     //   171: fadd
/*   */     //   172: fstore #5
/*   */     //   174: getfield z : F
/*   */     //   177: fstore #6
/*   */     //   179: fload_3
/*   */     //   180: fload #5
/*   */     //   182: fload #6
/*   */     //   184: invokevirtual qf0 : (FFF)V
/*   */     //   187: aload_1
/*   */     //   188: invokestatic k60 : ()Lf/So;
/*   */     //   191: dup
/*   */     //   192: aload_0
/*   */     //   193: swap
/*   */     //   194: putfield synchronized : Lf/So;
/*   */     //   197: invokevirtual L5 : ()Lf/So;
/*   */     //   200: pop
/*   */     //   201: arraylength
/*   */     //   202: istore_3
/*   */     //   203: iconst_0
/*   */     //   204: istore #5
/*   */     //   206: iload #5
/*   */     //   208: iload_3
/*   */     //   209: if_icmpge -> 320
/*   */     //   212: aload_0
/*   */     //   213: aload_1
/*   */     //   214: iload #5
/*   */     //   216: aaload
/*   */     //   217: astore #6
/*   */     //   219: getfield synchronized : Lf/So;
/*   */     //   222: bipush #7
/*   */     //   224: aload #6
/*   */     //   226: invokestatic aG : (ILjava/lang/Object;)Lf/Wz0;
/*   */     //   229: fconst_0
/*   */     //   230: fconst_0
/*   */     //   231: invokevirtual n20 : (FF)Lf/Wz0;
/*   */     //   234: invokevirtual PL : (Lf/Wz0;)Lf/So;
/*   */     //   237: bipush #8
/*   */     //   239: aload #6
/*   */     //   241: invokestatic aG : (ILjava/lang/Object;)Lf/Wz0;
/*   */     //   244: iconst_4
/*   */     //   245: newarray float
/*   */     //   247: dup
/*   */     //   248: dup
/*   */     //   249: dup2
/*   */     //   250: iconst_0
/*   */     //   251: fconst_1
/*   */     //   252: fastore
/*   */     //   253: iconst_1
/*   */     //   254: fconst_1
/*   */     //   255: fastore
/*   */     //   256: iconst_2
/*   */     //   257: fconst_1
/*   */     //   258: fastore
/*   */     //   259: iconst_3
/*   */     //   260: fconst_1
/*   */     //   261: fastore
/*   */     //   262: invokevirtual qY : ([F)Lf/Wz0;
/*   */     //   265: invokevirtual PL : (Lf/Wz0;)Lf/So;
/*   */     //   268: bipush #10
/*   */     //   270: aload #6
/*   */     //   272: invokestatic aG : (ILjava/lang/Object;)Lf/Wz0;
/*   */     //   275: iconst_4
/*   */     //   276: newarray float
/*   */     //   278: dup
/*   */     //   279: dup
/*   */     //   280: dup2
/*   */     //   281: iconst_0
/*   */     //   282: fconst_1
/*   */     //   283: fastore
/*   */     //   284: iconst_1
/*   */     //   285: fconst_1
/*   */     //   286: fastore
/*   */     //   287: iconst_2
/*   */     //   288: fconst_1
/*   */     //   289: fastore
/*   */     //   290: iconst_3
/*   */     //   291: fconst_1
/*   */     //   292: fastore
/*   */     //   293: invokevirtual qY : ([F)Lf/Wz0;
/*   */     //   296: invokevirtual PL : (Lf/Wz0;)Lf/So;
/*   */     //   299: aload_0
/*   */     //   300: getfield mS : Z
/*   */     //   303: sipush #1382
/*   */     //   306: swap
/*   */     //   307: invokestatic A50 : (SZ)Lf/Wz0;
/*   */     //   310: invokevirtual PL : (Lf/Wz0;)Lf/So;
/*   */     //   313: pop
/*   */     //   314: iinc #5, 1
/*   */     //   317: goto -> 206
/*   */     //   320: aload_0
/*   */     //   321: dup
/*   */     //   322: getfield synchronized : Lf/So;
/*   */     //   325: invokevirtual Kr : ()Lf/So;
/*   */     //   328: pop
/*   */     //   329: getfield mS : Z
/*   */     //   332: ifeq -> 575
/*   */     //   335: aload_0
/*   */     //   336: dup
/*   */     //   337: dup2
/*   */     //   338: getfield Fs : [Lf/eo;
/*   */     //   341: iconst_2
/*   */     //   342: aaload
/*   */     //   343: aload_0
/*   */     //   344: getfield xF0 : Lf/hm0;
/*   */     //   347: getstatic f/km.MR : Lf/Gp0;
/*   */     //   350: invokevirtual zJ0 : (Lf/Gp0;)F
/*   */     //   353: fconst_0
/*   */     //   354: fconst_0
/*   */     //   355: invokevirtual Tz : (FFF)Lf/eo;
/*   */     //   358: pop
/*   */     //   359: getfield Fs : [Lf/eo;
/*   */     //   362: iconst_3
/*   */     //   363: aaload
/*   */     //   364: aload_0
/*   */     //   365: getfield xF0 : Lf/hm0;
/*   */     //   368: getstatic f/km.MR : Lf/Gp0;
/*   */     //   371: invokevirtual zJ0 : (Lf/Gp0;)F
/*   */     //   374: fconst_0
/*   */     //   375: fconst_0
/*   */     //   376: invokevirtual Tz : (FFF)Lf/eo;
/*   */     //   379: pop
/*   */     //   380: getfield Fs : [Lf/eo;
/*   */     //   383: iconst_4
/*   */     //   384: aaload
/*   */     //   385: aload_0
/*   */     //   386: getfield xF0 : Lf/hm0;
/*   */     //   389: getstatic f/km.MR : Lf/Gp0;
/*   */     //   392: invokevirtual zJ0 : (Lf/Gp0;)F
/*   */     //   395: fconst_0
/*   */     //   396: fconst_0
/*   */     //   397: invokevirtual Tz : (FFF)Lf/eo;
/*   */     //   400: pop
/*   */     //   401: new f/QX
/*   */     //   404: dup
/*   */     //   405: astore_3
/*   */     //   406: aload_0
/*   */     //   407: getfield Fs : [Lf/eo;
/*   */     //   410: iconst_0
/*   */     //   411: invokespecial <init> : ([Lf/Ou0;Z)V
/*   */     //   414: getfield synchronized : Lf/So;
/*   */     //   417: invokevirtual eC : ()Lf/So;
/*   */     //   420: astore #5
/*   */     //   422: fconst_0
/*   */     //   423: fstore #6
/*   */     //   425: fload #6
/*   */     //   427: fconst_1
/*   */     //   428: fcmpg
/*   */     //   429: ifge -> 501
/*   */     //   432: fload #6
/*   */     //   434: aload #5
/*   */     //   436: aload_0
/*   */     //   437: aload_3
/*   */     //   438: getstatic f/Hd0.gy0 : Lf/eo;
/*   */     //   441: dup
/*   */     //   442: astore #7
/*   */     //   444: fload #6
/*   */     //   446: invokevirtual Gc0 : (Lf/Ou0;F)Lf/Ou0;
/*   */     //   449: pop
/*   */     //   450: getfield K60 : Lf/oq;
/*   */     //   453: iconst_4
/*   */     //   454: ldc_w 0.01
/*   */     //   457: invokestatic gq : (Ljava/lang/Object;IF)Lf/Wz0;
/*   */     //   460: aload #7
/*   */     //   462: dup
/*   */     //   463: dup
/*   */     //   464: getfield x : F
/*   */     //   467: fstore #6
/*   */     //   469: getfield y : F
/*   */     //   472: fstore #7
/*   */     //   474: getfield z : F
/*   */     //   477: fstore #8
/*   */     //   479: fload #6
/*   */     //   481: fload #7
/*   */     //   483: fload #8
/*   */     //   485: invokevirtual qw0 : (FFF)Lf/Wz0;
/*   */     //   488: invokevirtual PL : (Lf/Wz0;)Lf/So;
/*   */     //   491: pop
/*   */     //   492: ldc_w 0.01
/*   */     //   495: fadd
/*   */     //   496: fstore #6
/*   */     //   498: goto -> 425
/*   */     //   501: aload_0
/*   */     //   502: dup
/*   */     //   503: dup
/*   */     //   504: aload #5
/*   */     //   506: aload_0
/*   */     //   507: aload #4
/*   */     //   509: aload #5
/*   */     //   511: invokevirtual Kr : ()Lf/So;
/*   */     //   514: pop
/*   */     //   515: <illegal opcode> Do : (Lf/Hd0;Lf/eo;)Lf/hk0;
/*   */     //   520: invokestatic OC : (Lf/hk0;)Lf/Wz0;
/*   */     //   523: invokevirtual PL : (Lf/Wz0;)Lf/So;
/*   */     //   526: pop
/*   */     //   527: getfield Fs : [Lf/eo;
/*   */     //   530: iconst_2
/*   */     //   531: aaload
/*   */     //   532: ldc 1.5
/*   */     //   534: ldc 4.5
/*   */     //   536: ldc 4.0
/*   */     //   538: invokevirtual TG0 : (FFF)Lf/eo;
/*   */     //   541: pop
/*   */     //   542: getfield Fs : [Lf/eo;
/*   */     //   545: iconst_3
/*   */     //   546: aaload
/*   */     //   547: ldc 3.0
/*   */     //   549: ldc 3.5
/*   */     //   551: ldc 4.0
/*   */     //   553: invokevirtual TG0 : (FFF)Lf/eo;
/*   */     //   556: pop
/*   */     //   557: getfield Fs : [Lf/eo;
/*   */     //   560: iconst_4
/*   */     //   561: aaload
/*   */     //   562: ldc 3.0
/*   */     //   564: ldc 3.5
/*   */     //   566: ldc 3.5
/*   */     //   568: invokevirtual TG0 : (FFF)Lf/eo;
/*   */     //   571: pop
/*   */     //   572: goto -> 588
/*   */     //   575: aload #4
/*   */     //   577: aload_0
/*   */     //   578: getfield K60 : Lf/oq;
/*   */     //   581: getfield PL : Lf/eo;
/*   */     //   584: invokevirtual JL : (Lf/eo;)Lf/eo;
/*   */     //   587: pop
/*   */     //   588: aload_0
/*   */     //   589: dup
/*   */     //   590: getfield synchronized : Lf/So;
/*   */     //   593: invokevirtual eC : ()Lf/So;
/*   */     //   596: aload_0
/*   */     //   597: getfield K60 : Lf/oq;
/*   */     //   600: bipush #9
/*   */     //   602: ldc_w 0.2
/*   */     //   605: invokestatic gq : (Ljava/lang/Object;IF)Lf/Wz0;
/*   */     //   608: fconst_0
/*   */     //   609: invokevirtual a : (F)Lf/Wz0;
/*   */     //   612: invokevirtual PL : (Lf/Wz0;)Lf/So;
/*   */     //   615: aload_0
/*   */     //   616: getfield K60 : Lf/oq;
/*   */     //   619: iconst_4
/*   */     //   620: ldc_w 0.01
/*   */     //   623: invokestatic gq : (Ljava/lang/Object;IF)Lf/Wz0;
/*   */     //   626: fconst_0
/*   */     //   627: fconst_0
/*   */     //   628: fconst_0
/*   */     //   629: invokevirtual qw0 : (FFF)Lf/Wz0;
/*   */     //   632: invokevirtual PL : (Lf/Wz0;)Lf/So;
/*   */     //   635: pop
/*   */     //   636: getfield synchronized : Lf/So;
/*   */     //   639: invokevirtual L5 : ()Lf/So;
/*   */     //   642: pop
/*   */     //   643: iconst_0
/*   */     //   644: istore_3
/*   */     //   645: iload_3
/*   */     //   646: aload_1
/*   */     //   647: arraylength
/*   */     //   648: if_icmpge -> 708
/*   */     //   651: aload_0
/*   */     //   652: getfield synchronized : Lf/So;
/*   */     //   655: aload_1
/*   */     //   656: iload_3
/*   */     //   657: aaload
/*   */     //   658: iconst_4
/*   */     //   659: ldc_w 0.01
/*   */     //   662: invokestatic gq : (Ljava/lang/Object;IF)Lf/Wz0;
/*   */     //   665: aload_2
/*   */     //   666: iload_3
/*   */     //   667: aaload
/*   */     //   668: dup
/*   */     //   669: dup
/*   */     //   670: getfield x : F
/*   */     //   673: fstore #5
/*   */     //   675: getfield y : F
/*   */     //   678: ldc_w 0.55
/*   */     //   681: fadd
/*   */     //   682: fstore #6
/*   */     //   684: getfield z : F
/*   */     //   687: fstore #7
/*   */     //   689: fload #5
/*   */     //   691: fload #6
/*   */     //   693: fload #7
/*   */     //   695: invokevirtual qw0 : (FFF)Lf/Wz0;
/*   */     //   698: invokevirtual PL : (Lf/Wz0;)Lf/So;
/*   */     //   701: pop
/*   */     //   702: iinc #3, 1
/*   */     //   705: goto -> 645
/*   */     //   708: aload_0
/*   */     //   709: dup
/*   */     //   710: dup
/*   */     //   711: getfield synchronized : Lf/So;
/*   */     //   714: invokevirtual Kr : ()Lf/So;
/*   */     //   717: pop
/*   */     //   718: getfield synchronized : Lf/So;
/*   */     //   721: sipush #1383
/*   */     //   724: invokestatic cOM2 : (S)Lf/Wz0;
/*   */     //   727: invokevirtual PL : (Lf/Wz0;)Lf/So;
/*   */     //   730: aload_0
/*   */     //   731: <illegal opcode> Do : (Lf/Hd0;)Lf/hk0;
/*   */     //   736: invokestatic OC : (Lf/hk0;)Lf/Wz0;
/*   */     //   739: invokevirtual PL : (Lf/Wz0;)Lf/So;
/*   */     //   742: aload #4
/*   */     //   744: <illegal opcode> Do : (Lf/eo;)Lf/hk0;
/*   */     //   749: invokestatic OC : (Lf/hk0;)Lf/Wz0;
/*   */     //   752: invokevirtual PL : (Lf/Wz0;)Lf/So;
/*   */     //   755: astore_3
/*   */     //   756: getfield xF0 : Lf/hm0;
/*   */     //   759: invokevirtual oi : ()B
/*   */     //   762: bipush #15
/*   */     //   764: if_icmpne -> 775
/*   */     //   767: ldc_w 'spawn_cherish'
/*   */     //   770: astore #4
/*   */     //   772: goto -> 780
/*   */     //   775: ldc_w 'spawn'
/*   */     //   778: astore #4
/*   */     //   780: aload_0
/*   */     //   781: dup
/*   */     //   782: aload_3
/*   */     //   783: aload_0
/*   */     //   784: aload #4
/*   */     //   786: invokevirtual con : (Ljava/lang/String;)Lf/Wz0;
/*   */     //   789: invokevirtual PL : (Lf/Wz0;)Lf/So;
/*   */     //   792: pop
/*   */     //   793: getfield xF0 : Lf/hm0;
/*   */     //   796: invokevirtual oi : ()B
/*   */     //   799: invokevirtual cON : (B)Lf/Wz0;
/*   */     //   802: dup
/*   */     //   803: astore_3
/*   */     //   804: ifnull -> 816
/*   */     //   807: aload_0
/*   */     //   808: getfield synchronized : Lf/So;
/*   */     //   811: aload_3
/*   */     //   812: invokevirtual PL : (Lf/Wz0;)Lf/So;
/*   */     //   815: pop
/*   */     //   816: aload_0
/*   */     //   817: dup
/*   */     //   818: dup
/*   */     //   819: getfield synchronized : Lf/So;
/*   */     //   822: ldc_w 0.4
/*   */     //   825: invokevirtual Wz0 : (F)Lf/So;
/*   */     //   828: pop
/*   */     //   829: getfield synchronized : Lf/So;
/*   */     //   832: astore_3
/*   */     //   833: getfield xF0 : Lf/hm0;
/*   */     //   836: dup
/*   */     //   837: astore #4
/*   */     //   839: invokevirtual Jx : ()S
/*   */     //   842: aload #4
/*   */     //   844: invokevirtual iQ : ()B
/*   */     //   847: istore #5
/*   */     //   849: getstatic f/um0.YA : Lf/eo;
/*   */     //   852: pop
/*   */     //   853: lookupswitch default -> 2176, 12 -> 2193, 15 -> 2193, 17 -> 2193, 22 -> 2193, 41 -> 2193, 42 -> 2193, 49 -> 2193, 63 -> 2193, 70 -> 2193, 71 -> 2193, 72 -> 2193, 73 -> 2193, 81 -> 2193, 82 -> 2193, 90 -> 2193, 91 -> 2193, 92 -> 2193, 93 -> 2193, 109 -> 2193, 110 -> 2193, 116 -> 2193, 117 -> 2193, 118 -> 2193, 119 -> 2193, 120 -> 2193, 121 -> 2193, 129 -> 2193, 130 -> 2193, 137 -> 2193, 138 -> 2193, 139 -> 2193, 140 -> 2193, 142 -> 2193, 145 -> 2193, 146 -> 2193, 151 -> 2193, 166 -> 2193, 169 -> 2193, 170 -> 2193, 171 -> 2193, 174 -> 2193, 187 -> 2193, 188 -> 2193, 189 -> 2193, 193 -> 2193, 200 -> 2193, 201 -> 2193, 211 -> 2193, 223 -> 2193, 226 -> 2193, 230 -> 2193, 233 -> 2193, 249 -> 2193, 250 -> 2193, 251 -> 2193, 267 -> 2193, 269 -> 2193, 270 -> 2193, 278 -> 2193, 279 -> 2193, 284 -> 2193, 291 -> 2193, 292 -> 2193, 307 -> 2193, 313 -> 2193, 314 -> 2193, 318 -> 2193, 319 -> 2193, 320 -> 2193, 321 -> 2193, 330 -> 2193, 333 -> 2193, 337 -> 2193, 338 -> 2193, 339 -> 2193, 340 -> 2193, 344 -> 2193, 347 -> 2193, 349 -> 2193, 351 -> 2193, 353 -> 2193, 355 -> 2193, 358 -> 2193, 362 -> 2193, 367 -> 2193, 368 -> 2193, 369 -> 2193, 370 -> 2193, 374 -> 2193, 375 -> 2193, 380 -> 2193, 381 -> 2193, 382 -> 2193, 384 -> 2193, 385 -> 2193, 412 -> 2193, 413 -> 2193, 414 -> 2193, 415 -> 2193, 416 -> 2193, 425 -> 2193, 426 -> 2193, 429 -> 2193, 433 -> 2193, 436 -> 2193, 437 -> 2193, 455 -> 2193, 456 -> 2193, 457 -> 2193, 458 -> 2193, 462 -> 2193, 468 -> 2193, 469 -> 2193, 472 -> 2193, 474 -> 2193, 476 -> 2193, 477 -> 2193, 478 -> 2193, 479 -> 2193, 480 -> 2193, 481 -> 2193, 482 -> 2193, 487 -> 2187, 488 -> 2193, 489 -> 2193, 491 -> 2193, 517 -> 2193, 518 -> 2193, 527 -> 2193, 528 -> 2193, 550 -> 2193, 561 -> 2193, 562 -> 2193, 563 -> 2193, 564 -> 2193, 567 -> 2193, 577 -> 2193, 578 -> 2193, 579 -> 2193, 582 -> 2193, 583 -> 2193, 584 -> 2193, 587 -> 2193, 589 -> 2193, 592 -> 2193, 593 -> 2193, 594 -> 2193, 598 -> 2193, 599 -> 2193, 601 -> 2193, 602 -> 2193, 605 -> 2193, 606 -> 2193, 608 -> 2193, 609 -> 2193, 615 -> 2193, 618 -> 2193, 628 -> 2193, 635 -> 2193, 637 -> 2193, 641 -> 2193, 642 -> 2193, 645 -> 2193, 648 -> 2179
/*   */     //   2176: goto -> 2197
/*   */     //   2179: iload #5
/*   */     //   2181: ifne -> 2197
/*   */     //   2184: goto -> 2193
/*   */     //   2187: iload #5
/*   */     //   2189: iconst_1
/*   */     //   2190: if_icmpne -> 2197
/*   */     //   2193: iconst_1
/*   */     //   2194: goto -> 2198
/*   */     //   2197: iconst_0
/*   */     //   2198: ifeq -> 2209
/*   */     //   2201: sipush #2029
/*   */     //   2204: istore #4
/*   */     //   2206: goto -> 2298
/*   */     //   2209: aload #4
/*   */     //   2211: invokevirtual Jx : ()S
/*   */     //   2214: dup
/*   */     //   2215: istore #5
/*   */     //   2217: aload #4
/*   */     //   2219: invokevirtual iQ : ()B
/*   */     //   2222: pop
/*   */     //   2223: bipush #50
/*   */     //   2225: if_icmpeq -> 2239
/*   */     //   2228: iload #5
/*   */     //   2230: bipush #51
/*   */     //   2232: if_icmpeq -> 2239
/*   */     //   2235: iconst_0
/*   */     //   2236: goto -> 2240
/*   */     //   2239: iconst_1
/*   */     //   2240: ifeq -> 2249
/*   */     //   2243: iconst_0
/*   */     //   2244: istore #4
/*   */     //   2246: goto -> 2298
/*   */     //   2249: aload #4
/*   */     //   2251: invokevirtual xp : ()Lf/UD0;
/*   */     //   2254: getfield fu : S
/*   */     //   2257: sipush #500
/*   */     //   2260: if_icmpge -> 2271
/*   */     //   2263: sipush #1400
/*   */     //   2266: istore #4
/*   */     //   2268: goto -> 2298
/*   */     //   2271: aload #4
/*   */     //   2273: invokevirtual xp : ()Lf/UD0;
/*   */     //   2276: getfield fu : S
/*   */     //   2279: sipush #1500
/*   */     //   2282: if_icmpge -> 2293
/*   */     //   2285: sipush #1399
/*   */     //   2288: istore #4
/*   */     //   2290: goto -> 2298
/*   */     //   2293: sipush #1398
/*   */     //   2296: istore #4
/*   */     //   2298: aload_0
/*   */     //   2299: aload_3
/*   */     //   2300: iload #4
/*   */     //   2302: aload_0
/*   */     //   2303: getfield xF0 : Lf/hm0;
/*   */     //   2306: invokevirtual Si : ()Z
/*   */     //   2309: invokestatic A50 : (SZ)Lf/Wz0;
/*   */     //   2312: invokevirtual PL : (Lf/Wz0;)Lf/So;
/*   */     //   2315: pop
/*   */     //   2316: getfield synchronized : Lf/So;
/*   */     //   2319: invokevirtual L5 : ()Lf/So;
/*   */     //   2322: pop
/*   */     //   2323: iconst_0
/*   */     //   2324: istore_3
/*   */     //   2325: iload_3
/*   */     //   2326: aload_1
/*   */     //   2327: arraylength
/*   */     //   2328: if_icmpge -> 2414
/*   */     //   2331: aload_0
/*   */     //   2332: dup
/*   */     //   2333: getfield synchronized : Lf/So;
/*   */     //   2336: aload_1
/*   */     //   2337: iload_3
/*   */     //   2338: aaload
/*   */     //   2339: bipush #7
/*   */     //   2341: ldc 0.8
/*   */     //   2343: invokestatic gq : (Ljava/lang/Object;IF)Lf/Wz0;
/*   */     //   2346: ldc_w 1.1
/*   */     //   2349: ldc_w 1.1
/*   */     //   2352: invokevirtual n20 : (FF)Lf/Wz0;
/*   */     //   2355: invokevirtual PL : (Lf/Wz0;)Lf/So;
/*   */     //   2358: pop
/*   */     //   2359: getfield synchronized : Lf/So;
/*   */     //   2362: aload_1
/*   */     //   2363: iload_3
/*   */     //   2364: aaload
/*   */     //   2365: iconst_4
/*   */     //   2366: ldc 0.8
/*   */     //   2368: invokestatic gq : (Ljava/lang/Object;IF)Lf/Wz0;
/*   */     //   2371: aload_2
/*   */     //   2372: iload_3
/*   */     //   2373: aaload
/*   */     //   2374: dup
/*   */     //   2375: dup
/*   */     //   2376: getfield x : F
/*   */     //   2379: fstore #4
/*   */     //   2381: getfield y : F
/*   */     //   2384: ldc_w 0.9
/*   */     //   2387: fadd
/*   */     //   2388: fstore #5
/*   */     //   2390: getfield z : F
/*   */     //   2393: fstore #6
/*   */     //   2395: fload #4
/*   */     //   2397: fload #5
/*   */     //   2399: fload #6
/*   */     //   2401: invokevirtual qw0 : (FFF)Lf/Wz0;
/*   */     //   2404: invokevirtual PL : (Lf/Wz0;)Lf/So;
/*   */     //   2407: pop
/*   */     //   2408: iinc #3, 1
/*   */     //   2411: goto -> 2325
/*   */     //   2414: aload_0
/*   */     //   2415: dup
/*   */     //   2416: getfield synchronized : Lf/So;
/*   */     //   2419: invokevirtual Kr : ()Lf/So;
/*   */     //   2422: pop
/*   */     //   2423: getfield synchronized : Lf/So;
/*   */     //   2426: invokevirtual L5 : ()Lf/So;
/*   */     //   2429: pop
/*   */     //   2430: iconst_0
/*   */     //   2431: istore_3
/*   */     //   2432: iload_3
/*   */     //   2433: aload_1
/*   */     //   2434: arraylength
/*   */     //   2435: if_icmpge -> 2549
/*   */     //   2438: aload_0
/*   */     //   2439: getfield X : Lf/Gp0;
/*   */     //   2442: getfield rx : Lf/ky;
/*   */     //   2445: aload_0
/*   */     //   2446: getfield xF0 : Lf/hm0;
/*   */     //   2449: getfield ws : B
/*   */     //   2452: invokevirtual cF : (I)Z
/*   */     //   2455: ifeq -> 2478
/*   */     //   2458: aload_1
/*   */     //   2459: iload_3
/*   */     //   2460: aaload
/*   */     //   2461: bipush #11
/*   */     //   2463: ldc_w 0.25
/*   */     //   2466: invokestatic gq : (Ljava/lang/Object;IF)Lf/Wz0;
/*   */     //   2469: fconst_0
/*   */     //   2470: invokevirtual a : (F)Lf/Wz0;
/*   */     //   2473: astore #4
/*   */     //   2475: goto -> 2514
/*   */     //   2478: aload_1
/*   */     //   2479: iload_3
/*   */     //   2480: aaload
/*   */     //   2481: bipush #10
/*   */     //   2483: ldc_w 0.25
/*   */     //   2486: invokestatic gq : (Ljava/lang/Object;IF)Lf/Wz0;
/*   */     //   2489: iconst_4
/*   */     //   2490: newarray float
/*   */     //   2492: dup
/*   */     //   2493: dup
/*   */     //   2494: dup2
/*   */     //   2495: iconst_0
/*   */     //   2496: fconst_0
/*   */     //   2497: fastore
/*   */     //   2498: iconst_1
/*   */     //   2499: fconst_0
/*   */     //   2500: fastore
/*   */     //   2501: iconst_2
/*   */     //   2502: fconst_0
/*   */     //   2503: fastore
/*   */     //   2504: iconst_3
/*   */     //   2505: ldc_w 0.6
/*   */     //   2508: fastore
/*   */     //   2509: invokevirtual qY : ([F)Lf/Wz0;
/*   */     //   2512: astore #4
/*   */     //   2514: aload_0
/*   */     //   2515: getfield synchronized : Lf/So;
/*   */     //   2518: aload_1
/*   */     //   2519: iload_3
/*   */     //   2520: aaload
/*   */     //   2521: bipush #7
/*   */     //   2523: ldc_w 0.4
/*   */     //   2526: invokestatic gq : (Ljava/lang/Object;IF)Lf/Wz0;
/*   */     //   2529: fconst_1
/*   */     //   2530: fconst_1
/*   */     //   2531: invokevirtual n20 : (FF)Lf/Wz0;
/*   */     //   2534: invokevirtual PL : (Lf/Wz0;)Lf/So;
/*   */     //   2537: aload #4
/*   */     //   2539: invokevirtual PL : (Lf/Wz0;)Lf/So;
/*   */     //   2542: pop
/*   */     //   2543: iinc #3, 1
/*   */     //   2546: goto -> 2432
/*   */     //   2549: aload_0
/*   */     //   2550: dup
/*   */     //   2551: getfield synchronized : Lf/So;
/*   */     //   2554: invokevirtual Kr : ()Lf/So;
/*   */     //   2557: pop
/*   */     //   2558: getfield synchronized : Lf/So;
/*   */     //   2561: invokevirtual L5 : ()Lf/So;
/*   */     //   2564: pop
/*   */     //   2565: iconst_0
/*   */     //   2566: istore_3
/*   */     //   2567: iload_3
/*   */     //   2568: aload_1
/*   */     //   2569: arraylength
/*   */     //   2570: if_icmpge -> 2626
/*   */     //   2573: aload_0
/*   */     //   2574: getfield synchronized : Lf/So;
/*   */     //   2577: aload_1
/*   */     //   2578: iload_3
/*   */     //   2579: aaload
/*   */     //   2580: iconst_4
/*   */     //   2581: ldc_w 0.6
/*   */     //   2584: invokestatic gq : (Ljava/lang/Object;IF)Lf/Wz0;
/*   */     //   2587: aload_2
/*   */     //   2588: iload_3
/*   */     //   2589: aaload
/*   */     //   2590: dup
/*   */     //   2591: dup
/*   */     //   2592: getfield x : F
/*   */     //   2595: fstore #4
/*   */     //   2597: getfield y : F
/*   */     //   2600: fstore #5
/*   */     //   2602: getfield z : F
/*   */     //   2605: fstore #6
/*   */     //   2607: fload #4
/*   */     //   2609: fload #5
/*   */     //   2611: fload #6
/*   */     //   2613: invokevirtual qw0 : (FFF)Lf/Wz0;
/*   */     //   2616: invokevirtual PL : (Lf/Wz0;)Lf/So;
/*   */     //   2619: pop
/*   */     //   2620: iinc #3, 1
/*   */     //   2623: goto -> 2567
/*   */     //   2626: aload_0
/*   */     //   2627: dup
/*   */     //   2628: getfield synchronized : Lf/So;
/*   */     //   2631: invokevirtual Kr : ()Lf/So;
/*   */     //   2634: invokevirtual Kr : ()Lf/So;
/*   */     //   2637: pop
/*   */     //   2638: getfield synchronized : Lf/So;
/*   */     //   2641: areturn
/*   */     // Line number table:
/*   */     //   Java source line number -> byte code offset
/*   */     //   #1	-> 9
/*   */     //   #2	-> 15
/*   */     //   #3	-> 24
/*   */     //   #4	-> 29
/*   */     //   #5	-> 59
/*   */     //   #6	-> 62
/*   */     //   #7	-> 66
/*   */     //   #8	-> 70
/*   */     //   #9	-> 93
/*   */     //   #10	-> 98
/*   */     //   #11	-> 307
/*   */     //   #12	-> 310
/*   */     //   #13	-> 581
/*   */     //   #14	-> 584
/*   */     //   #15	-> 724
/*   */     //   #16	-> 727
/*   */     //   #17	-> 767
/*   */     //   #18	-> 786
/*   */     //   #19	-> 839
/*   */     //   #20	-> 844
/*   */     //   #21	-> 2251
/*   */     //   #22	-> 2254
/*   */     //   #23	-> 2273
/*   */     //   #24	-> 2276
/*   */     //   #25	-> 2303
/*   */     //   #26	-> 2442
/*   */     //   #27	-> 2446
/*   */     //   #28	-> 2449
/*   */     //   #29	-> 2452 } public final So Lpt2() { // Byte code:
/*   */     //   0: aload_0
/*   */     //   1: dup
/*   */     //   2: dup
/*   */     //   3: getstatic f/km.mI0 : Lf/P1;
/*   */     //   6: getfield AN : Lf/Wo;
/*   */     //   9: getfield Do0 : Lf/yI;
/*   */     //   12: aload_0
/*   */     //   13: dup
/*   */     //   14: dup2
/*   */     //   15: getfield xF0 : Lf/hm0;
/*   */     //   18: invokevirtual t30 : ()V
/*   */     //   21: getfield xF0 : Lf/hm0;
/*   */     //   24: getfield qf : [Lf/uT;
/*   */     //   27: dup
/*   */     //   28: astore_1
/*   */     //   29: invokestatic stream : ([Ljava/lang/Object;)Ljava/util/stream/Stream;
/*   */     //   32: <illegal opcode> apply : ()Ljava/util/function/Function;
/*   */     //   37: invokeinterface map : (Ljava/util/function/Function;)Ljava/util/stream/Stream;
/*   */     //   42: <illegal opcode> apply : ()Ljava/util/function/IntFunction;
/*   */     //   47: invokeinterface toArray : (Ljava/util/function/IntFunction;)[Ljava/lang/Object;
/*   */     //   52: checkcast [Lf/eo;
/*   */     //   55: astore_2
/*   */     //   56: getfield xF0 : Lf/hm0;
/*   */     //   59: getfield rF0 : Lf/uT;
/*   */     //   62: getfield He0 : Lf/eo;
/*   */     //   65: dup
/*   */     //   66: invokestatic w3 : (Lf/eo;Lf/eo;)Lf/eo;
/*   */     //   69: astore_3
/*   */     //   70: getfield xF0 : Lf/hm0;
/*   */     //   73: invokevirtual oi : ()B
/*   */     //   76: iconst_4
/*   */     //   77: swap
/*   */     //   78: invokevirtual o3 : (II)Lf/R30;
/*   */     //   81: invokestatic s2 : (Lf/R30;)Lf/oq;
/*   */     //   84: dup
/*   */     //   85: astore #4
/*   */     //   87: putfield K60 : Lf/oq;
/*   */     //   90: getfield pb : Lf/vH;
/*   */     //   93: getfield Ji0 : Ljava/util/ArrayList;
/*   */     //   96: aload #4
/*   */     //   98: invokevirtual add : (Ljava/lang/Object;)Z
/*   */     //   101: pop
/*   */     //   102: new f/eo
/*   */     //   105: dup
/*   */     //   106: astore #4
/*   */     //   108: invokespecial <init> : ()V
/*   */     //   111: getfield mS : Z
/*   */     //   114: ifeq -> 155
/*   */     //   117: aload_0
/*   */     //   118: getfield K60 : Lf/oq;
/*   */     //   121: aload_3
/*   */     //   122: dup
/*   */     //   123: dup
/*   */     //   124: getfield x : F
/*   */     //   127: ldc 0.5
/*   */     //   129: fsub
/*   */     //   130: fstore_3
/*   */     //   131: getfield y : F
/*   */     //   134: ldc 0.5
/*   */     //   136: fsub
/*   */     //   137: fstore #5
/*   */     //   139: getfield z : F
/*   */     //   142: fstore #6
/*   */     //   144: fload_3
/*   */     //   145: fload #5
/*   */     //   147: fload #6
/*   */     //   149: invokevirtual qf0 : (FFF)V
/*   */     //   152: goto -> 187
/*   */     //   155: aload_0
/*   */     //   156: getfield K60 : Lf/oq;
/*   */     //   159: aload_3
/*   */     //   160: dup
/*   */     //   161: dup
/*   */     //   162: getfield x : F
/*   */     //   165: fstore_3
/*   */     //   166: getfield y : F
/*   */     //   169: ldc 0.5
/*   */     //   171: fadd
/*   */     //   172: fstore #5
/*   */     //   174: getfield z : F
/*   */     //   177: fstore #6
/*   */     //   179: fload_3
/*   */     //   180: fload #5
/*   */     //   182: fload #6
/*   */     //   184: invokevirtual qf0 : (FFF)V
/*   */     //   187: aload_1
/*   */     //   188: invokestatic k60 : ()Lf/So;
/*   */     //   191: dup
/*   */     //   192: aload_0
/*   */     //   193: swap
/*   */     //   194: putfield synchronized : Lf/So;
/*   */     //   197: invokevirtual L5 : ()Lf/So;
/*   */     //   200: pop
/*   */     //   201: arraylength
/*   */     //   202: istore_3
/*   */     //   203: iconst_0
/*   */     //   204: istore #5
/*   */     //   206: iload #5
/*   */     //   208: iload_3
/*   */     //   209: if_icmpge -> 320
/*   */     //   212: aload_0
/*   */     //   213: aload_1
/*   */     //   214: iload #5
/*   */     //   216: aaload
/*   */     //   217: astore #6
/*   */     //   219: getfield synchronized : Lf/So;
/*   */     //   222: bipush #7
/*   */     //   224: aload #6
/*   */     //   226: invokestatic aG : (ILjava/lang/Object;)Lf/Wz0;
/*   */     //   229: fconst_0
/*   */     //   230: fconst_0
/*   */     //   231: invokevirtual n20 : (FF)Lf/Wz0;
/*   */     //   234: invokevirtual PL : (Lf/Wz0;)Lf/So;
/*   */     //   237: bipush #8
/*   */     //   239: aload #6
/*   */     //   241: invokestatic aG : (ILjava/lang/Object;)Lf/Wz0;
/*   */     //   244: iconst_4
/*   */     //   245: newarray float
/*   */     //   247: dup
/*   */     //   248: dup
/*   */     //   249: dup2
/*   */     //   250: iconst_0
/*   */     //   251: fconst_1
/*   */     //   252: fastore
/*   */     //   253: iconst_1
/*   */     //   254: fconst_1
/*   */     //   255: fastore
/*   */     //   256: iconst_2
/*   */     //   257: fconst_1
/*   */     //   258: fastore
/*   */     //   259: iconst_3
/*   */     //   260: fconst_1
/*   */     //   261: fastore
/*   */     //   262: invokevirtual qY : ([F)Lf/Wz0;
/*   */     //   265: invokevirtual PL : (Lf/Wz0;)Lf/So;
/*   */     //   268: bipush #10
/*   */     //   270: aload #6
/*   */     //   272: invokestatic aG : (ILjava/lang/Object;)Lf/Wz0;
/*   */     //   275: iconst_4
/*   */     //   276: newarray float
/*   */     //   278: dup
/*   */     //   279: dup
/*   */     //   280: dup2
/*   */     //   281: iconst_0
/*   */     //   282: fconst_1
/*   */     //   283: fastore
/*   */     //   284: iconst_1
/*   */     //   285: fconst_1
/*   */     //   286: fastore
/*   */     //   287: iconst_2
/*   */     //   288: fconst_1
/*   */     //   289: fastore
/*   */     //   290: iconst_3
/*   */     //   291: fconst_1
/*   */     //   292: fastore
/*   */     //   293: invokevirtual qY : ([F)Lf/Wz0;
/*   */     //   296: invokevirtual PL : (Lf/Wz0;)Lf/So;
/*   */     //   299: aload_0
/*   */     //   300: getfield mS : Z
/*   */     //   303: sipush #1382
/*   */     //   306: swap
/*   */     //   307: invokestatic A50 : (SZ)Lf/Wz0;
/*   */     //   310: invokevirtual PL : (Lf/Wz0;)Lf/So;
/*   */     //   313: pop
/*   */     //   314: iinc #5, 1
/*   */     //   317: goto -> 206
/*   */     //   320: aload_0
/*   */     //   321: dup
/*   */     //   322: getfield synchronized : Lf/So;
/*   */     //   325: invokevirtual Kr : ()Lf/So;
/*   */     //   328: pop
/*   */     //   329: getfield mS : Z
/*   */     //   332: ifeq -> 575
/*   */     //   335: aload_0
/*   */     //   336: dup
/*   */     //   337: dup2
/*   */     //   338: getfield Fs : [Lf/eo;
/*   */     //   341: iconst_2
/*   */     //   342: aaload
/*   */     //   343: aload_0
/*   */     //   344: getfield xF0 : Lf/hm0;
/*   */     //   347: getstatic f/km.MR : Lf/Gp0;
/*   */     //   350: invokevirtual zJ0 : (Lf/Gp0;)F
/*   */     //   353: fconst_0
/*   */     //   354: fconst_0
/*   */     //   355: invokevirtual Tz : (FFF)Lf/eo;
/*   */     //   358: pop
/*   */     //   359: getfield Fs : [Lf/eo;
/*   */     //   362: iconst_3
/*   */     //   363: aaload
/*   */     //   364: aload_0
/*   */     //   365: getfield xF0 : Lf/hm0;
/*   */     //   368: getstatic f/km.MR : Lf/Gp0;
/*   */     //   371: invokevirtual zJ0 : (Lf/Gp0;)F
/*   */     //   374: fconst_0
/*   */     //   375: fconst_0
/*   */     //   376: invokevirtual Tz : (FFF)Lf/eo;
/*   */     //   379: pop
/*   */     //   380: getfield Fs : [Lf/eo;
/*   */     //   383: iconst_4
/*   */     //   384: aaload
/*   */     //   385: aload_0
/*   */     //   386: getfield xF0 : Lf/hm0;
/*   */     //   389: getstatic f/km.MR : Lf/Gp0;
/*   */     //   392: invokevirtual zJ0 : (Lf/Gp0;)F
/*   */     //   395: fconst_0
/*   */     //   396: fconst_0
/*   */     //   397: invokevirtual Tz : (FFF)Lf/eo;
/*   */     //   400: pop
/*   */     //   401: new f/QX
/*   */     //   404: dup
/*   */     //   405: astore_3
/*   */     //   406: aload_0
/*   */     //   407: getfield Fs : [Lf/eo;
/*   */     //   410: iconst_0
/*   */     //   411: invokespecial <init> : ([Lf/Ou0;Z)V
/*   */     //   414: getfield synchronized : Lf/So;
/*   */     //   417: invokevirtual eC : ()Lf/So;
/*   */     //   420: astore #5
/*   */     //   422: fconst_0
/*   */     //   423: fstore #6
/*   */     //   425: fload #6
/*   */     //   427: fconst_1
/*   */     //   428: fcmpg
/*   */     //   429: ifge -> 501
/*   */     //   432: fload #6
/*   */     //   434: aload #5
/*   */     //   436: aload_0
/*   */     //   437: aload_3
/*   */     //   438: getstatic f/Hd0.gy0 : Lf/eo;
/*   */     //   441: dup
/*   */     //   442: astore #7
/*   */     //   444: fload #6
/*   */     //   446: invokevirtual Gc0 : (Lf/Ou0;F)Lf/Ou0;
/*   */     //   449: pop
/*   */     //   450: getfield K60 : Lf/oq;
/*   */     //   453: iconst_4
/*   */     //   454: ldc_w 0.01
/*   */     //   457: invokestatic gq : (Ljava/lang/Object;IF)Lf/Wz0;
/*   */     //   460: aload #7
/*   */     //   462: dup
/*   */     //   463: dup
/*   */     //   464: getfield x : F
/*   */     //   467: fstore #6
/*   */     //   469: getfield y : F
/*   */     //   472: fstore #7
/*   */     //   474: getfield z : F
/*   */     //   477: fstore #8
/*   */     //   479: fload #6
/*   */     //   481: fload #7
/*   */     //   483: fload #8
/*   */     //   485: invokevirtual qw0 : (FFF)Lf/Wz0;
/*   */     //   488: invokevirtual PL : (Lf/Wz0;)Lf/So;
/*   */     //   491: pop
/*   */     //   492: ldc_w 0.01
/*   */     //   495: fadd
/*   */     //   496: fstore #6
/*   */     //   498: goto -> 425
/*   */     //   501: aload_0
/*   */     //   502: dup
/*   */     //   503: dup
/*   */     //   504: aload #5
/*   */     //   506: aload_0
/*   */     //   507: aload #4
/*   */     //   509: aload #5
/*   */     //   511: invokevirtual Kr : ()Lf/So;
/*   */     //   514: pop
/*   */     //   515: <illegal opcode> Do : (Lf/Hd0;Lf/eo;)Lf/hk0;
/*   */     //   520: invokestatic OC : (Lf/hk0;)Lf/Wz0;
/*   */     //   523: invokevirtual PL : (Lf/Wz0;)Lf/So;
/*   */     //   526: pop
/*   */     //   527: getfield Fs : [Lf/eo;
/*   */     //   530: iconst_2
/*   */     //   531: aaload
/*   */     //   532: ldc 1.5
/*   */     //   534: ldc 4.5
/*   */     //   536: ldc 4.0
/*   */     //   538: invokevirtual TG0 : (FFF)Lf/eo;
/*   */     //   541: pop
/*   */     //   542: getfield Fs : [Lf/eo;
/*   */     //   545: iconst_3
/*   */     //   546: aaload
/*   */     //   547: ldc 3.0
/*   */     //   549: ldc 3.5
/*   */     //   551: ldc 4.0
/*   */     //   553: invokevirtual TG0 : (FFF)Lf/eo;
/*   */     //   556: pop
/*   */     //   557: getfield Fs : [Lf/eo;
/*   */     //   560: iconst_4
/*   */     //   561: aaload
/*   */     //   562: ldc 3.0
/*   */     //   564: ldc 3.5
/*   */     //   566: ldc 3.5
/*   */     //   568: invokevirtual TG0 : (FFF)Lf/eo;
/*   */     //   571: pop
/*   */     //   572: goto -> 598
/*   */     //   575: aload #4
/*   */     //   577: aload_0
/*   */     //   578: dup
/*   */     //   579: getfield synchronized : Lf/So;
/*   */     //   582: ldc 0.5
/*   */     //   584: invokevirtual Wz0 : (F)Lf/So;
/*   */     //   587: pop
/*   */     //   588: getfield K60 : Lf/oq;
/*   */     //   591: getfield PL : Lf/eo;
/*   */     //   594: invokevirtual JL : (Lf/eo;)Lf/eo;
/*   */     //   597: pop
/*   */     //   598: aload_0
/*   */     //   599: dup
/*   */     //   600: dup
/*   */     //   601: getfield synchronized : Lf/So;
/*   */     //   604: invokevirtual L5 : ()Lf/So;
/*   */     //   607: pop
/*   */     //   608: getfield synchronized : Lf/So;
/*   */     //   611: invokevirtual eC : ()Lf/So;
/*   */     //   614: aload_0
/*   */     //   615: getfield K60 : Lf/oq;
/*   */     //   618: bipush #9
/*   */     //   620: ldc_w 0.2
/*   */     //   623: invokestatic gq : (Ljava/lang/Object;IF)Lf/Wz0;
/*   */     //   626: fconst_0
/*   */     //   627: invokevirtual a : (F)Lf/Wz0;
/*   */     //   630: invokevirtual PL : (Lf/Wz0;)Lf/So;
/*   */     //   633: aload_0
/*   */     //   634: getfield K60 : Lf/oq;
/*   */     //   637: iconst_4
/*   */     //   638: ldc_w 0.01
/*   */     //   641: invokestatic gq : (Ljava/lang/Object;IF)Lf/Wz0;
/*   */     //   644: fconst_0
/*   */     //   645: fconst_0
/*   */     //   646: fconst_0
/*   */     //   647: invokevirtual qw0 : (FFF)Lf/Wz0;
/*   */     //   650: invokevirtual PL : (Lf/Wz0;)Lf/So;
/*   */     //   653: pop
/*   */     //   654: getfield synchronized : Lf/So;
/*   */     //   657: invokevirtual L5 : ()Lf/So;
/*   */     //   660: pop
/*   */     //   661: iconst_0
/*   */     //   662: istore_3
/*   */     //   663: iload_3
/*   */     //   664: aload_1
/*   */     //   665: arraylength
/*   */     //   666: if_icmpge -> 726
/*   */     //   669: aload_0
/*   */     //   670: getfield synchronized : Lf/So;
/*   */     //   673: aload_1
/*   */     //   674: iload_3
/*   */     //   675: aaload
/*   */     //   676: iconst_4
/*   */     //   677: ldc_w 0.01
/*   */     //   680: invokestatic gq : (Ljava/lang/Object;IF)Lf/Wz0;
/*   */     //   683: aload_2
/*   */     //   684: iload_3
/*   */     //   685: aaload
/*   */     //   686: dup
/*   */     //   687: dup
/*   */     //   688: getfield x : F
/*   */     //   691: fstore #5
/*   */     //   693: getfield y : F
/*   */     //   696: ldc_w 0.4
/*   */     //   699: fsub
/*   */     //   700: fstore #6
/*   */     //   702: getfield z : F
/*   */     //   705: fstore #7
/*   */     //   707: fload #5
/*   */     //   709: fload #6
/*   */     //   711: fload #7
/*   */     //   713: invokevirtual qw0 : (FFF)Lf/Wz0;
/*   */     //   716: invokevirtual PL : (Lf/Wz0;)Lf/So;
/*   */     //   719: pop
/*   */     //   720: iinc #3, 1
/*   */     //   723: goto -> 663
/*   */     //   726: aload_0
/*   */     //   727: dup
/*   */     //   728: dup
/*   */     //   729: getfield synchronized : Lf/So;
/*   */     //   732: invokevirtual Kr : ()Lf/So;
/*   */     //   735: pop
/*   */     //   736: getfield synchronized : Lf/So;
/*   */     //   739: sipush #1383
/*   */     //   742: invokestatic cOM2 : (S)Lf/Wz0;
/*   */     //   745: invokevirtual PL : (Lf/Wz0;)Lf/So;
/*   */     //   748: aload_0
/*   */     //   749: <illegal opcode> Do : (Lf/Hd0;)Lf/hk0;
/*   */     //   754: invokestatic OC : (Lf/hk0;)Lf/Wz0;
/*   */     //   757: invokevirtual PL : (Lf/Wz0;)Lf/So;
/*   */     //   760: aload #4
/*   */     //   762: <illegal opcode> Do : (Lf/eo;)Lf/hk0;
/*   */     //   767: invokestatic OC : (Lf/hk0;)Lf/Wz0;
/*   */     //   770: invokevirtual PL : (Lf/Wz0;)Lf/So;
/*   */     //   773: astore_3
/*   */     //   774: getfield xF0 : Lf/hm0;
/*   */     //   777: invokevirtual oi : ()B
/*   */     //   780: bipush #15
/*   */     //   782: if_icmpne -> 793
/*   */     //   785: ldc_w 'spawn_cherish'
/*   */     //   788: astore #4
/*   */     //   790: goto -> 798
/*   */     //   793: ldc_w 'spawn'
/*   */     //   796: astore #4
/*   */     //   798: aload_0
/*   */     //   799: dup
/*   */     //   800: aload_3
/*   */     //   801: aload_0
/*   */     //   802: aload #4
/*   */     //   804: invokevirtual con : (Ljava/lang/String;)Lf/Wz0;
/*   */     //   807: invokevirtual PL : (Lf/Wz0;)Lf/So;
/*   */     //   810: pop
/*   */     //   811: getfield xF0 : Lf/hm0;
/*   */     //   814: invokevirtual oi : ()B
/*   */     //   817: invokevirtual cON : (B)Lf/Wz0;
/*   */     //   820: dup
/*   */     //   821: astore_3
/*   */     //   822: ifnull -> 834
/*   */     //   825: aload_0
/*   */     //   826: getfield synchronized : Lf/So;
/*   */     //   829: aload_3
/*   */     //   830: invokevirtual PL : (Lf/Wz0;)Lf/So;
/*   */     //   833: pop
/*   */     //   834: aload_0
/*   */     //   835: dup
/*   */     //   836: getfield synchronized : Lf/So;
/*   */     //   839: ldc_w 0.4
/*   */     //   842: invokevirtual Wz0 : (F)Lf/So;
/*   */     //   845: pop
/*   */     //   846: getfield synchronized : Lf/So;
/*   */     //   849: invokevirtual L5 : ()Lf/So;
/*   */     //   852: pop
/*   */     //   853: iconst_0
/*   */     //   854: istore_3
/*   */     //   855: iload_3
/*   */     //   856: aload_1
/*   */     //   857: arraylength
/*   */     //   858: if_icmpge -> 935
/*   */     //   861: aload_0
/*   */     //   862: getfield synchronized : Lf/So;
/*   */     //   865: aload_1
/*   */     //   866: iload_3
/*   */     //   867: aaload
/*   */     //   868: bipush #7
/*   */     //   870: ldc 0.5
/*   */     //   872: invokestatic gq : (Ljava/lang/Object;IF)Lf/Wz0;
/*   */     //   875: ldc_w 1.1
/*   */     //   878: ldc_w 1.1
/*   */     //   881: invokevirtual n20 : (FF)Lf/Wz0;
/*   */     //   884: invokevirtual PL : (Lf/Wz0;)Lf/So;
/*   */     //   887: aload_1
/*   */     //   888: iload_3
/*   */     //   889: aaload
/*   */     //   890: iconst_4
/*   */     //   891: ldc 0.5
/*   */     //   893: invokestatic gq : (Ljava/lang/Object;IF)Lf/Wz0;
/*   */     //   896: aload_2
/*   */     //   897: iload_3
/*   */     //   898: aaload
/*   */     //   899: dup
/*   */     //   900: dup
/*   */     //   901: getfield x : F
/*   */     //   904: fstore #4
/*   */     //   906: getfield y : F
/*   */     //   909: fstore #5
/*   */     //   911: getfield z : F
/*   */     //   914: fstore #6
/*   */     //   916: fload #4
/*   */     //   918: fload #5
/*   */     //   920: fload #6
/*   */     //   922: invokevirtual qw0 : (FFF)Lf/Wz0;
/*   */     //   925: invokevirtual PL : (Lf/Wz0;)Lf/So;
/*   */     //   928: pop
/*   */     //   929: iinc #3, 1
/*   */     //   932: goto -> 855
/*   */     //   935: aload_0
/*   */     //   936: dup
/*   */     //   937: dup
/*   */     //   938: getfield synchronized : Lf/So;
/*   */     //   941: invokevirtual Kr : ()Lf/So;
/*   */     //   944: pop
/*   */     //   945: getfield synchronized : Lf/So;
/*   */     //   948: invokevirtual eC : ()Lf/So;
/*   */     //   951: pop
/*   */     //   952: getfield synchronized : Lf/So;
/*   */     //   955: invokevirtual L5 : ()Lf/So;
/*   */     //   958: pop
/*   */     //   959: iconst_0
/*   */     //   960: istore_2
/*   */     //   961: iload_2
/*   */     //   962: aload_1
/*   */     //   963: arraylength
/*   */     //   964: if_icmpge -> 1075
/*   */     //   967: aload_0
/*   */     //   968: getfield X : Lf/Gp0;
/*   */     //   971: getfield rx : Lf/ky;
/*   */     //   974: aload_0
/*   */     //   975: getfield xF0 : Lf/hm0;
/*   */     //   978: getfield ws : B
/*   */     //   981: invokevirtual cF : (I)Z
/*   */     //   984: ifeq -> 1006
/*   */     //   987: aload_1
/*   */     //   988: iload_2
/*   */     //   989: aaload
/*   */     //   990: bipush #11
/*   */     //   992: ldc_w 0.25
/*   */     //   995: invokestatic gq : (Ljava/lang/Object;IF)Lf/Wz0;
/*   */     //   998: fconst_0
/*   */     //   999: invokevirtual a : (F)Lf/Wz0;
/*   */     //   1002: astore_3
/*   */     //   1003: goto -> 1041
/*   */     //   1006: aload_1
/*   */     //   1007: iload_2
/*   */     //   1008: aaload
/*   */     //   1009: bipush #10
/*   */     //   1011: ldc_w 0.25
/*   */     //   1014: invokestatic gq : (Ljava/lang/Object;IF)Lf/Wz0;
/*   */     //   1017: iconst_4
/*   */     //   1018: newarray float
/*   */     //   1020: dup
/*   */     //   1021: dup
/*   */     //   1022: dup2
/*   */     //   1023: iconst_0
/*   */     //   1024: fconst_0
/*   */     //   1025: fastore
/*   */     //   1026: iconst_1
/*   */     //   1027: fconst_0
/*   */     //   1028: fastore
/*   */     //   1029: iconst_2
/*   */     //   1030: fconst_0
/*   */     //   1031: fastore
/*   */     //   1032: iconst_3
/*   */     //   1033: ldc_w 0.6
/*   */     //   1036: fastore
/*   */     //   1037: invokevirtual qY : ([F)Lf/Wz0;
/*   */     //   1040: astore_3
/*   */     //   1041: aload_0
/*   */     //   1042: getfield synchronized : Lf/So;
/*   */     //   1045: aload_1
/*   */     //   1046: iload_2
/*   */     //   1047: aaload
/*   */     //   1048: bipush #7
/*   */     //   1050: ldc_w 0.4
/*   */     //   1053: invokestatic gq : (Ljava/lang/Object;IF)Lf/Wz0;
/*   */     //   1056: fconst_1
/*   */     //   1057: fconst_1
/*   */     //   1058: invokevirtual n20 : (FF)Lf/Wz0;
/*   */     //   1061: invokevirtual PL : (Lf/Wz0;)Lf/So;
/*   */     //   1064: aload_3
/*   */     //   1065: invokevirtual PL : (Lf/Wz0;)Lf/So;
/*   */     //   1068: pop
/*   */     //   1069: iinc #2, 1
/*   */     //   1072: goto -> 961
/*   */     //   1075: aload_0
/*   */     //   1076: dup
/*   */     //   1077: dup
/*   */     //   1078: dup2
/*   */     //   1079: getfield synchronized : Lf/So;
/*   */     //   1082: invokevirtual Kr : ()Lf/So;
/*   */     //   1085: pop
/*   */     //   1086: getfield synchronized : Lf/So;
/*   */     //   1089: invokevirtual Kr : ()Lf/So;
/*   */     //   1092: pop
/*   */     //   1093: getfield synchronized : Lf/So;
/*   */     //   1096: invokevirtual Kr : ()Lf/So;
/*   */     //   1099: pop
/*   */     //   1100: getfield synchronized : Lf/So;
/*   */     //   1103: invokevirtual Kr : ()Lf/So;
/*   */     //   1106: pop
/*   */     //   1107: getfield synchronized : Lf/So;
/*   */     //   1110: areturn
/*   */     // Line number table:
/*   */     //   Java source line number -> byte code offset
/*   */     //   #1	-> 9
/*   */     //   #2	-> 15
/*   */     //   #3	-> 24
/*   */     //   #4	-> 29
/*   */     //   #5	-> 59
/*   */     //   #6	-> 62
/*   */     //   #7	-> 66
/*   */     //   #8	-> 70
/*   */     //   #9	-> 93
/*   */     //   #10	-> 98
/*   */     //   #11	-> 307
/*   */     //   #12	-> 310
/*   */     //   #13	-> 591
/*   */     //   #14	-> 594
/*   */     //   #15	-> 742
/*   */     //   #16	-> 745
/*   */     //   #17	-> 785
/*   */     //   #18	-> 804
/*   */     //   #19	-> 971
/*   */     //   #20	-> 975
/*   */     //   #21	-> 978
/* 4 */     //   #22	-> 981 } public final So yF0() { this.xF0.t30(); uT uT; eo eo1 = V1.w3((uT = this.xF0.rF0).He0, (uT = this.xF0.rF0).He0); (this.synchronized = So.k60().PL(Wz0.aG(7, uT).n20(0.0F, 0.0F)).PL(Wz0.aG(8, uT).qY(new float[] { 1.0F, 1.0F, 1.0F, 1.0F })).PL(Wz0.aG(10, uT).qY(new float[] { 1.0F, 1.0F, 1.0F, 1.0F }))).Wz0(0.5F); eo3.getClass();
/* 5 */     float f5 = eo1.x, f6 = eo1.y, f7 = eo1.z; eo eo3; (eo3 = q10.Rs).TG0(f5, f6, f7);
/* 6 */     eo2.getClass();
/* 7 */     float f3 = eo1.x, f4 = eo1.y; f6 = eo1.z; eo eo2; (eo2 = q10.HF).TG0(f3, f4, f6);
/* 8 */     q10.Nl = K50.qF; float f2 = this.Gc0.Ah.x; f3 = this.Gc0.Ah.y + 0.05F; f4 = this.Gc0.Ah.z; f2 = this.Gc0.I70.x; f3 = this.Gc0.I70.y + 0.05F; f4 = this.Gc0.I70.z; f2 = this.Gc0.Ah.x; f3 = this.Gc0.Ah.y; f4 = this.Gc0.Ah.z; float f1 = this.Gc0.I70.x; f2 = this.Gc0.I70.y; f3 = this.Gc0.I70.z; this.synchronized.eC().PL(Wz0.OC(this::P80)).Wz0(0.4F).L5().PL(Wz0.gq(uT, 7, 0.25F).n20(1.0F, 1.0F)).PL(Wz0.gq(uT, 11, 0.25F).a(0.0F)).Kr().L5().PL(Wz0.gq(this.Gc0, 4, 0.05F).qw0(f2, f3, f4)).PL(Wz0.gq(this.Gc0, 9, 0.05F).qw0(f2, f3, f4)).Kr().L5().PL(Wz0.gq(this.Gc0, 4, 0.1F).qw0(f2, f3, f4)).PL(Wz0.gq(this.Gc0, 9, 0.1F).qw0(f1, f2, f3)).Kr().Kr(); return this.synchronized; }
/*   */ 
/*   */   
/*   */   public final Wz0 cON(byte paramByte) {
/*   */     return (paramByte == 15) ? Wz0.OC(this::mG) : null;
/*   */   } }


/* Location:              /Users/vnnsnnt/Documents/Codespace/JavaWorkspace/RedTrainer/src/main/java/org/trainer/client/PokeMMO.jar!/f/Hd0.class
 * Java compiler version: 8 (52.0)
 * JD-Core Version:       1.1.3
 */