package f;

public final class hg0 implements con {
  public final void ng(Object paramObject, int paramInt, float[] paramArrayOffloat) {
    // Byte code:
    //   0: iload_2
    //   1: aload_1
    //   2: checkcast f/S60
    //   5: astore_0
    //   6: iconst_1
    //   7: if_icmpeq -> 65
    //   10: iload_2
    //   11: iconst_2
    //   12: if_icmpeq -> 32
    //   15: getstatic f/hg0.Pl : Z
    //   18: ifeq -> 24
    //   21: goto -> 95
    //   24: new java/lang/AssertionError
    //   27: dup
    //   28: invokespecial <init> : ()V
    //   31: athrow
    //   32: aload_0
    //   33: dup
    //   34: dup2
    //   35: aload_3
    //   36: iconst_0
    //   37: faload
    //   38: aload_0
    //   39: getfield nn : F
    //   42: fconst_0
    //   43: swap
    //   44: invokestatic SA0 : (FFF)F
    //   47: dup
    //   48: fstore_0
    //   49: putfield kB : F
    //   52: getfield LY : F
    //   55: putfield s90 : F
    //   58: fload_0
    //   59: putfield Gs : F
    //   62: goto -> 95
    //   65: aload_0
    //   66: dup
    //   67: dup2
    //   68: aload_3
    //   69: iconst_0
    //   70: faload
    //   71: aload_0
    //   72: getfield OH0 : F
    //   75: fconst_0
    //   76: swap
    //   77: invokestatic SA0 : (FFF)F
    //   80: dup
    //   81: fstore_0
    //   82: putfield LY : F
    //   85: fload_0
    //   86: putfield s90 : F
    //   89: getfield kB : F
    //   92: putfield Gs : F
    //   95: return
    // Line number table:
    //   Java source line number -> byte code offset
    //   #1	-> 15
    //   #2	-> 39
    //   #3	-> 44
    //   #4	-> 49
    //   #5	-> 52
    //   #6	-> 70
    //   #7	-> 72
    //   #8	-> 77
    //   #9	-> 82
    //   #10	-> 86
  }
  
  public final int Uu0(Object paramObject, int paramInt, float[] paramArrayOffloat) {
    // Byte code:
    //   0: iload_2
    //   1: aload_1
    //   2: checkcast f/S60
    //   5: astore_0
    //   6: iconst_1
    //   7: if_icmpeq -> 47
    //   10: iload_2
    //   11: iconst_2
    //   12: if_icmpeq -> 34
    //   15: getstatic f/hg0.Pl : Z
    //   18: ifeq -> 26
    //   21: iconst_0
    //   22: istore_0
    //   23: goto -> 57
    //   26: new java/lang/AssertionError
    //   29: dup
    //   30: invokespecial <init> : ()V
    //   33: athrow
    //   34: aload_3
    //   35: aload_0
    //   36: getfield kB : F
    //   39: iconst_0
    //   40: swap
    //   41: fastore
    //   42: iconst_1
    //   43: istore_0
    //   44: goto -> 57
    //   47: aload_3
    //   48: aload_0
    //   49: getfield LY : F
    //   52: iconst_0
    //   53: swap
    //   54: fastore
    //   55: iconst_1
    //   56: istore_0
    //   57: iload_0
    //   58: ireturn
    // Line number table:
    //   Java source line number -> byte code offset
    //   #1	-> 15
    //   #2	-> 36
    //   #3	-> 41
    //   #4	-> 49
    //   #5	-> 54
  }
}


/* Location:              /Users/vnnsnnt/Documents/Codespace/JavaWorkspace/RedTrainer/src/main/java/org/trainer/client/PokeMMO.jar!/f/hg0.class
 * Java compiler version: 8 (52.0)
 * JD-Core Version:       1.1.3
 */