/*  1 */ package f;public final class hI0 extends Qa0 implements r60 { public static final Comparator Ug0 = hI0::eD0; public static final Comparator nx0 = Comparator.comparing(i::Dw); public final pA Q3; public final Ip lI0; public final Ip Kc; public final Ip HQ; public final Vq0 QA; public final rS G90; public final rS sA0; public final Un kK; public final zT prn; public final rh T70; public final Un On0; public final dQ Ej0; public final dQ Mc0; public final dQ lO; public hI0(pA parampA, int paramInt1, int paramInt2, boolean paramBoolean1, boolean paramBoolean2, boolean paramBoolean3) { super(km.XU()); zT zT1; Ip ip1; pRn pRn; Ip ip2; dQ dQ1; this.yM = 0; this.lj0 = -1; Uk uk = km.u4.BR(); this.Q3 = parampA; this.Hk0 = paramInt1; this.W0 = paramInt2; this.aH = paramBoolean2; this.Nb0 = paramBoolean3; TG0(parampA::Yd); this((byte)-1, (byte)-1, (byte)-1, (byte)-1); Vo0(new I(this, pRn)); if (km.XU()) { if (km.wI0.Kh() != null) km.wI0.Kh().Zq0(false, paramInt2);  Xu("itemshop-mobile"); } else { Xu("itemshop"); }  if (uk.CA() > 0) { Lo(Ml0.OH0(uk.CA())); } else { Lo(Ml0.OH0(0) + " MART"); }  EP(1); jJ0(true); (this.lI0 = new Ip()).Xu("itemshop-dialoglayout-left"); J8(new Ip()); (this.QA = new Vq0()).T1(false); byte b1; (this.G90 = new rS()).zG0(b1 = 2); this(); this.sA0 = rS2; rS rS2; (rS2 = new rS()).zG0(b1); this
/*  2 */       .Ej0 = new dQ(B40.df("$ ").append(Ml0.OH0(1137)).toString()); this(); cr0 cr0 = (new Ip()).d7(); g0 g0 = (new Ip()).mE0(); this.Mc0 = new dQ(""); this(""); this.lO = new dQ(); this.U8 = new dQ(""); Un un2 = new Un(); String str2 = Ml0.OH0((uk.CoM2() > 0) ? uk.CoM2() : 56); this(str2); this.kK = un2; un2.sk0(false); this.tu0 = new dQ(Ml0.Go(1925, "0")); this.bg0 = new dQ(); this(); this.oC0 = rS1; rS1.zG0(b1); rS rS1; (rS1 = new rS()).Gz0(dQ1); un2.tW(new tk0(this)); this(1, 999, 1); this.prn = new zT(); this(zT1); this.T70 = rh1; rh rh1; (rh1 = new rh()).Te0(this::gJ); this(Ml0.OH0(8117)); this.On0 = un1; Un un1; (un1 = new Un()).tW(() -> { i i1; if ((i1 = this.Y) != null) this.T70.l4(nx0.Uw0(i1.WM(), 0, rB0()));  }); i[] arrayOfI; int j, k; byte b2; for (j = 1, k = (arrayOfI = uk.qh()).length, b2 = 0; b2 < k; ) { i i1; if ((i1 = arrayOfI[b2]).Nm0() == null || i1.Nm0().a90() < 1) { j = 0; break; }  b2++; }  if (j) { Arrays.sort(arrayOfI, Ug0); for (j = 0; j < arrayOfI.length; ) { arrayOfI[j].ej0(j); j++; }  } else { Arrays.sort(arrayOfI, nx0); }  for (this.Vm0 = (Un[])new F50[arrayOfI.length], j = 0, k = arrayOfI.length, b2 = 0; b2 < k; ) { i i1 = arrayOfI[b2]; if (this.pA.D5() != Ud0.GA || !((ArrayList)i1.yb()).isEmpty()) { this(i1, false); F50 f50; (f50 = new F50()).tW(() -> xl(parami)); this.Vm0[j++] = f50; }  b2++; }  cr0.Mg((JG0[])this.Vm0); g0.Mg((JG0[])this.Vm0); ip3.WN(cr0); ip3.rK0(g0); this.G90.Gz0(ip3); this(); this.Kc = new Ip(); if (km.XU()) { ip1.rK0(ip1.mE0().cOM8(new U90[] { ip1.d7().Mg(new JG0[] { this.QA }) })); } else { ip1.rK0(ip1.mE0().cOM8(new U90[] { ip1.d7().Aq(300).Mg(new JG0[] { this.QA }) })); }  ip1.WN(ip1.d7().cOM8(new U90[] { ip1.mE0().Mg(new JG0[] { this.QA }) })); J8(ip1); this(); this(); this(); this.HQ = ip3; Ip ip3; (ip3 = new Ip()).Xu("label-area-market"); (new Ip()).J8(new Ip()); if (km.XU()) { ip3.rK0(ip3.mE0().cOM8(new U90[] { ip3.vo0(new JG0[] { this.Mc0 }).Em0(), ip3.vo0(new JG0[] { this.oC0 }).Em0() })); ip3.WN(ip3.d7().cOM8(new U90[] { ip3.AUX(new JG0[] { this.Mc0 }), ip3.AUX(new JG0[] { this.oC0 }) })); ip1.J8(this.U8); } else { arrayOfU90[0] = ip3.vo0(new JG0[] { this.Mc0 }); arrayOfU90[1] = ip3.vo0(new JG0[] { this.oC0 }); U90[] arrayOfU90; (arrayOfU90 = new U90[3])[2] = ip3.vo0(new JG0[] { this.U8 }); ip3.rK0(ip3.mE0().cOM8(new U90[3])); ip3.WN(ip3.d7().cOM8(new U90[] { ip3.AUX(new JG0[] { this.Mc0 }), ip3.AUX(new JG0[] { this.oC0 }) }).Em0().cOM8(new U90[] { ip3.AUX(new JG0[] { this.U8 }) })); }  ip2.rK0(ip2.mE0().cOM8(new U90[] { ip2.d7().Aq(10).Mg(new JG0[] { this.G90 }) })); ip2.WN(ip2.d7().cOM8(new U90[] { ip2.mE0().Mg(new JG0[] { this.G90 }) })); this(); (new Ip()).rK0((new Ip()).mE0().cOM8(new U90[] { ip3.d7().Aq(10).Mg(new JG0[] { this.sA0 }) })); (new Ip()).WN((new Ip()).d7().cOM8(new U90[] { ip3.mE0().Mg(new JG0[] { this.sA0 }) })); this.kK.uh0(90, 25); this.kK.Tm(90, 25); this.On0.uh0(90, 25); this.On0.Tm(90, 25); ip1.J8(this.T70); ip1.J8(this.On0); ip1.J8(this.kK); ip1.J8(this.tu0); ip1.J8(this.bg0); arrayOfUn[0] = this.T70.mc0; arrayOfUn[1] = this.T70.Xx; arrayOfUn[2] = this.On0; Un[] arrayOfUn; (arrayOfUn = new Un[4])[3] = this.kK; this.wr0 = new Un[4]; if (km.XU() || this.pA.D5() != Ud0.X30) ip1.J8(this.Ej0);  J8(ip1); Vq0 vq0 = this.QA; String str1 = Ml0.OH0((this.pA.CoM2() > 0) ? this.pA.CoM2() : 56); vq0.WS(ip2, str1).Ac0(this::Yx0); if (paramBoolean1) { Ag(); this.QA.WS(ip3, Ml0.OH0(62)).Ac0(this::Yx0); }  uh0(600, 140); Tm(600, 140); Di(); if (km.XU()) { jf0(this.Ki); J8(this.Ki); }  } public final dQ U8; public final dQ tu0; public final dQ bg0; public final rS oC0; public final Uk pA; public i Y; public Xo qV; public int yM; public int lj0; public Un[] s8; public Un[] Vm0; public Un[] wr0; public final int Hk0; public final int W0; public final boolean aH; public final boolean Nb0; private void gJ() { if (this.Y != null) { int j = this.T70.T8; int k; if (this.QA.nv0() == 0 && j > (k = rB0())) j = k;  rh rh1; if (j < (rh1 = this.T70)
/*  3 */         .T8) rh1
/*  4 */           .l4(j);  }  if (this.Y == null) return;  Di(); }
/*    */   public static int eD0(i parami1, i parami2) { Comparator<?> comparator1 = Comparator.comparingInt(Ht0::oI), comparator2 = Comparator.comparing(hI0::do0);
/*  6 */     WD wD2 = yk0.cw().mP(parami2.BC.kx0); WD wD1; if ((wD1 = yk0.cw().mP(parami1.BC.kx0)) == null || wD2 == null)
/*    */     {
/*    */       
/*  9 */       return comparator2.compare(parami1, parami2); }  Ht0 ht01, ht02; if ((ht01 = wD1.Wt(null, null)) != (ht02 = wD2.Wt(null, null))) return comparator1.compare(ht01, ht02);  return comparator2.compare(parami1, parami2); } public static String do0(i parami) { return Ml0.OH0(parami.BC.Iu); } public final void d40() { Ip ip; if (km.XU()) { Tm(km.wI0.dG(), km.wI0.k1()); super.d40(); this.T70.mM(); et et; this.T70.QJ0(et = et.dw0, -200, -30); this.On0.Tm(150, 65); this.On0.QJ0(et, -480, -30); this.kK.QJ0(et, -30, -30); this.Kc.Tm(480, km.wI0.k1() - 200); this.Kc.js0(et.t9); this.lI0.Tm(340, 50); this.lI0.QJ0(et = et.Em, 2, 2); this.HQ.Tm(km.wI0.dG(), 200); this.HQ.js0(et.F30); int j = this.U8.Kd - this.oC0.Kd; this.oC0.RI(j, this.oC0.Rr); i i1; if ((i1 = this.Y) != null && i1.Lc0 == Ud0.GA) { this.U8.QJ0(et, 395, 620); } else { this.U8.QJ0(et = et.T90, 655, -180); this.tu0.QJ0(et, 655, -150); this.bg0.QJ0(et, 655, -120); }  this.Ej0.ME((ip = this.lI0).Kd + 20, this.er0 + 25); } else { Tm(510, 390); ((hI0)super).Kc.Tm(170, 270); ((hI0)super).T70.Tm(135, 25); ((hI0)super).T70
/*    */ 
/*    */         
/* 12 */         .ME(this.Kd + 15 + 5, this.er0 + 322);
/* 13 */       ((hI0)super).kK.Tm(135, 25); ((hI0)super).kK
/*    */ 
/*    */         
/* 16 */         .ME(this.Kd + 155 + 5, this.er0 + 350);
/* 17 */       ((hI0)super).HQ.Tm(290, 240); ((hI0)super).HQ
/*    */ 
/*    */         
/* 20 */         .ME(this.Kd + 10, this.er0 + 57);
/* 21 */       ((hI0)super).tu0
/*    */ 
/*    */         
/* 24 */         .ME(this.Kd + 164, this.er0 + 310);
/* 25 */       ((hI0)super).Ej0
/*    */ 
/*    */         
/* 28 */         .ME(this.Kd + 164, this.er0 + 333);
/* 29 */       ((hI0)super).bg0
/*    */ 
/*    */         
/* 32 */         .ME(this.Kd + 15 + 5, this.er0 + 310);
/* 33 */       ((hI0)super).On0.Tm(135, 25); ((hI0)super).On0
/*    */ 
/*    */         
/* 36 */         .ME(this.Kd + 15 + 5, this.er0 + 350);
/* 37 */       super.d40(); ((hI0)super).lI0
/* 38 */         .kN(5, 5, 5, 5);
/* 39 */       ((hI0)super).lI0
/*    */ 
/*    */         
/* 42 */         .ME(this.Kd + 10, this.er0 + 293);
/* 43 */       ((hI0)super).lI0.Tm(290, 91); }
/*    */      }
/*    */ 
/*    */   
/*    */   public final void Ag() {
/*    */     // Byte code:
/*    */     //   0: getstatic f/km.u4 : Lf/R8;
/*    */     //   3: dup
/*    */     //   4: getfield jG0 : Lf/yM;
/*    */     //   7: invokevirtual gN : (Lf/yM;)Lf/zr0;
/*    */     //   10: new java/util/ArrayList
/*    */     //   13: dup
/*    */     //   14: astore_1
/*    */     //   15: invokespecial <init> : ()V
/*    */     //   18: invokevirtual ro0 : ()[Lf/Y;
/*    */     //   21: dup
/*    */     //   22: astore_2
/*    */     //   23: arraylength
/*    */     //   24: istore_3
/*    */     //   25: iconst_0
/*    */     //   26: istore #4
/*    */     //   28: iload #4
/*    */     //   30: iload_3
/*    */     //   31: if_icmpge -> 247
/*    */     //   34: aload_2
/*    */     //   35: iload #4
/*    */     //   37: aaload
/*    */     //   38: dup
/*    */     //   39: astore #5
/*    */     //   41: getfield Bp0 : Lf/LPT3;
/*    */     //   44: dup
/*    */     //   45: astore #6
/*    */     //   47: getfield Y8 : Lf/Hu0;
/*    */     //   50: dup
/*    */     //   51: astore #7
/*    */     //   53: getstatic f/Hu0.Bm : Lf/Hu0;
/*    */     //   56: if_acmpeq -> 241
/*    */     //   59: aload #7
/*    */     //   61: getstatic f/Hu0.w2 : Lf/Hu0;
/*    */     //   64: if_acmpne -> 70
/*    */     //   67: goto -> 241
/*    */     //   70: aload #6
/*    */     //   72: invokevirtual bj : ()Z
/*    */     //   75: ifeq -> 81
/*    */     //   78: goto -> 241
/*    */     //   81: aload_0
/*    */     //   82: getfield pA : Lf/Uk;
/*    */     //   85: dup
/*    */     //   86: astore #6
/*    */     //   88: getfield Xp0 : Lf/Ud0;
/*    */     //   91: dup
/*    */     //   92: astore #7
/*    */     //   94: getstatic f/Ud0.X30 : Lf/Ud0;
/*    */     //   97: if_acmpne -> 127
/*    */     //   100: aload #5
/*    */     //   102: getfield Bp0 : Lf/LPT3;
/*    */     //   105: dup
/*    */     //   106: astore #6
/*    */     //   108: getfield ph0 : I
/*    */     //   111: iconst_1
/*    */     //   112: if_icmplt -> 241
/*    */     //   115: aload #6
/*    */     //   117: invokevirtual coM8 : ()I
/*    */     //   120: iconst_1
/*    */     //   121: if_icmpge -> 234
/*    */     //   124: goto -> 241
/*    */     //   127: aload #7
/*    */     //   129: getstatic f/Ud0.GA : Lf/Ud0;
/*    */     //   132: if_acmpne -> 234
/*    */     //   135: aload #6
/*    */     //   137: aload #5
/*    */     //   139: getfield Lh : Lf/nH0;
/*    */     //   142: getfield p1 : S
/*    */     //   145: istore #6
/*    */     //   147: getfield w5 : Lf/qw0;
/*    */     //   150: iload #6
/*    */     //   152: invokevirtual Fb : (S)Z
/*    */     //   155: ifeq -> 234
/*    */     //   158: aload_0
/*    */     //   159: getfield pA : Lf/Uk;
/*    */     //   162: dup
/*    */     //   163: astore #6
/*    */     //   165: aload #5
/*    */     //   167: getfield Lh : Lf/nH0;
/*    */     //   170: getfield p1 : S
/*    */     //   173: istore #7
/*    */     //   175: getfield w5 : Lf/qw0;
/*    */     //   178: iload #7
/*    */     //   180: invokevirtual Fb : (S)Z
/*    */     //   183: ifeq -> 204
/*    */     //   186: aload #6
/*    */     //   188: getfield w5 : Lf/qw0;
/*    */     //   191: iload #7
/*    */     //   193: invokevirtual Z90 : (S)Ljava/lang/Object;
/*    */     //   196: checkcast f/i
/*    */     //   199: astore #6
/*    */     //   201: goto -> 220
/*    */     //   204: aload #6
/*    */     //   206: dup
/*    */     //   207: getfield Xp0 : Lf/Ud0;
/*    */     //   210: iload #7
/*    */     //   212: swap
/*    */     //   213: iconst_0
/*    */     //   214: iconst_0
/*    */     //   215: invokevirtual rd0 : (SLf/Ud0;SS)Lf/i;
/*    */     //   218: astore #6
/*    */     //   220: aload #6
/*    */     //   222: getfield Lq0 : Ljava/util/ArrayList;
/*    */     //   225: invokevirtual isEmpty : ()Z
/*    */     //   228: ifeq -> 234
/*    */     //   231: goto -> 241
/*    */     //   234: aload_1
/*    */     //   235: aload #5
/*    */     //   237: invokevirtual add : (Ljava/lang/Object;)Z
/*    */     //   240: pop
/*    */     //   241: iinc #4, 1
/*    */     //   244: goto -> 28
/*    */     //   247: aload_0
/*    */     //   248: aload_1
/*    */     //   249: invokestatic sort : (Ljava/util/List;)V
/*    */     //   252: new java/util/ArrayList
/*    */     //   255: dup
/*    */     //   256: astore_2
/*    */     //   257: invokespecial <init> : ()V
/*    */     //   260: iconst_0
/*    */     //   261: istore_3
/*    */     //   262: getfield pA : Lf/Uk;
/*    */     //   265: getfield Xp0 : Lf/Ud0;
/*    */     //   268: dup
/*    */     //   269: astore #4
/*    */     //   271: getstatic f/Ud0.X30 : Lf/Ud0;
/*    */     //   274: if_acmpne -> 330
/*    */     //   277: aload_1
/*    */     //   278: invokevirtual iterator : ()Ljava/util/Iterator;
/*    */     //   281: astore_1
/*    */     //   282: aload_1
/*    */     //   283: invokeinterface hasNext : ()Z
/*    */     //   288: ifeq -> 559
/*    */     //   291: aload_2
/*    */     //   292: aload_1
/*    */     //   293: invokeinterface next : ()Ljava/lang/Object;
/*    */     //   298: checkcast f/Y
/*    */     //   301: astore #4
/*    */     //   303: new f/Qf
/*    */     //   306: dup
/*    */     //   307: aload #4
/*    */     //   309: aload_0
/*    */     //   310: getfield pA : Lf/Uk;
/*    */     //   313: getfield Xp0 : Lf/Ud0;
/*    */     //   316: iload_3
/*    */     //   317: invokespecial <init> : (Lf/Y;Lf/Ud0;I)V
/*    */     //   320: invokevirtual add : (Ljava/lang/Object;)Z
/*    */     //   323: pop
/*    */     //   324: iinc #3, 1
/*    */     //   327: goto -> 282
/*    */     //   330: aload #4
/*    */     //   332: getstatic f/Ud0.GA : Lf/Ud0;
/*    */     //   335: if_acmpne -> 559
/*    */     //   338: aload_1
/*    */     //   339: invokevirtual iterator : ()Ljava/util/Iterator;
/*    */     //   342: astore_1
/*    */     //   343: aload_1
/*    */     //   344: invokeinterface hasNext : ()Z
/*    */     //   349: ifeq -> 559
/*    */     //   352: aload_0
/*    */     //   353: aload_1
/*    */     //   354: invokeinterface next : ()Ljava/lang/Object;
/*    */     //   359: checkcast f/Y
/*    */     //   362: astore #4
/*    */     //   364: getfield pA : Lf/Uk;
/*    */     //   367: aload #4
/*    */     //   369: getfield Lh : Lf/nH0;
/*    */     //   372: getfield p1 : S
/*    */     //   375: istore #5
/*    */     //   377: getfield w5 : Lf/qw0;
/*    */     //   380: iload #5
/*    */     //   382: invokevirtual Fb : (S)Z
/*    */     //   385: ifeq -> 343
/*    */     //   388: aload_0
/*    */     //   389: getfield pA : Lf/Uk;
/*    */     //   392: dup
/*    */     //   393: astore #5
/*    */     //   395: aload #4
/*    */     //   397: getfield Lh : Lf/nH0;
/*    */     //   400: getfield p1 : S
/*    */     //   403: istore #6
/*    */     //   405: getfield w5 : Lf/qw0;
/*    */     //   408: iload #6
/*    */     //   410: invokevirtual Fb : (S)Z
/*    */     //   413: ifeq -> 434
/*    */     //   416: aload #5
/*    */     //   418: getfield w5 : Lf/qw0;
/*    */     //   421: iload #6
/*    */     //   423: invokevirtual Z90 : (S)Ljava/lang/Object;
/*    */     //   426: checkcast f/i
/*    */     //   429: astore #5
/*    */     //   431: goto -> 450
/*    */     //   434: aload #5
/*    */     //   436: dup
/*    */     //   437: getfield Xp0 : Lf/Ud0;
/*    */     //   440: iload #6
/*    */     //   442: swap
/*    */     //   443: iconst_0
/*    */     //   444: iconst_0
/*    */     //   445: invokevirtual rd0 : (SLf/Ud0;SS)Lf/i;
/*    */     //   448: astore #5
/*    */     //   450: aload #5
/*    */     //   452: getfield Lq0 : Ljava/util/ArrayList;
/*    */     //   455: invokevirtual isEmpty : ()Z
/*    */     //   458: ifne -> 343
/*    */     //   461: aload #5
/*    */     //   463: new f/Qf
/*    */     //   466: dup
/*    */     //   467: astore #5
/*    */     //   469: aload #4
/*    */     //   471: aload_0
/*    */     //   472: getfield pA : Lf/Uk;
/*    */     //   475: getfield Xp0 : Lf/Ud0;
/*    */     //   478: iload_3
/*    */     //   479: invokespecial <init> : (Lf/Y;Lf/Ud0;I)V
/*    */     //   482: getfield Lq0 : Ljava/util/ArrayList;
/*    */     //   485: invokevirtual iterator : ()Ljava/util/Iterator;
/*    */     //   488: astore #4
/*    */     //   490: aload #4
/*    */     //   492: invokeinterface hasNext : ()Z
/*    */     //   497: ifeq -> 546
/*    */     //   500: aload #5
/*    */     //   502: aload #4
/*    */     //   504: invokeinterface next : ()Ljava/lang/Object;
/*    */     //   509: checkcast f/S3
/*    */     //   512: dup
/*    */     //   513: getfield Oz0 : S
/*    */     //   516: istore #6
/*    */     //   518: getfield cO : S
/*    */     //   521: i2b
/*    */     //   522: i2s
/*    */     //   523: istore #7
/*    */     //   525: getfield Lq0 : Ljava/util/ArrayList;
/*    */     //   528: new f/S3
/*    */     //   531: dup
/*    */     //   532: iload #6
/*    */     //   534: iload #7
/*    */     //   536: invokespecial <init> : (SS)V
/*    */     //   539: invokevirtual add : (Ljava/lang/Object;)Z
/*    */     //   542: pop
/*    */     //   543: goto -> 490
/*    */     //   546: aload_2
/*    */     //   547: aload #5
/*    */     //   549: invokevirtual add : (Ljava/lang/Object;)Z
/*    */     //   552: pop
/*    */     //   553: iinc #3, 1
/*    */     //   556: goto -> 343
/*    */     //   559: aload_2
/*    */     //   560: aload_0
/*    */     //   561: aload_2
/*    */     //   562: invokevirtual size : ()I
/*    */     //   565: anewarray f/F50
/*    */     //   568: putfield s8 : [Lf/Un;
/*    */     //   571: iconst_0
/*    */     //   572: istore_1
/*    */     //   573: invokevirtual iterator : ()Ljava/util/Iterator;
/*    */     //   576: astore_2
/*    */     //   577: aload_2
/*    */     //   578: invokeinterface hasNext : ()Z
/*    */     //   583: ifeq -> 643
/*    */     //   586: aload_0
/*    */     //   587: aload_2
/*    */     //   588: invokeinterface next : ()Ljava/lang/Object;
/*    */     //   593: checkcast f/i
/*    */     //   596: astore_3
/*    */     //   597: new f/F50
/*    */     //   600: dup
/*    */     //   601: astore #4
/*    */     //   603: aload_0
/*    */     //   604: aload #4
/*    */     //   606: aload_0
/*    */     //   607: aload_3
/*    */     //   608: aload #4
/*    */     //   610: aload_3
/*    */     //   611: iconst_1
/*    */     //   612: invokespecial <init> : (Lf/i;Z)V
/*    */     //   615: <illegal opcode> run : (Lf/hI0;Lf/i;)Ljava/lang/Runnable;
/*    */     //   620: invokevirtual tW : (Ljava/lang/Runnable;)V
/*    */     //   623: getfield Nb0 : Z
/*    */     //   626: invokevirtual sk0 : (Z)V
/*    */     //   629: getfield s8 : [Lf/Un;
/*    */     //   632: iload_1
/*    */     //   633: dup
/*    */     //   634: iconst_1
/*    */     //   635: iadd
/*    */     //   636: istore_1
/*    */     //   637: aload #4
/*    */     //   639: aastore
/*    */     //   640: goto -> 577
/*    */     //   643: aload_0
/*    */     //   644: new f/Ip
/*    */     //   647: dup
/*    */     //   648: dup2
/*    */     //   649: astore_1
/*    */     //   650: invokespecial <init> : ()V
/*    */     //   653: new f/cr0
/*    */     //   656: dup
/*    */     //   657: dup
/*    */     //   658: astore_2
/*    */     //   659: aload_1
/*    */     //   660: invokespecial <init> : (Lf/Ip;)V
/*    */     //   663: new f/g0
/*    */     //   666: dup
/*    */     //   667: astore_3
/*    */     //   668: aload_0
/*    */     //   669: aload_2
/*    */     //   670: aload_0
/*    */     //   671: aload_3
/*    */     //   672: aload_1
/*    */     //   673: invokespecial <init> : (Lf/Ip;)V
/*    */     //   676: getfield s8 : [Lf/Un;
/*    */     //   679: invokevirtual Mg : ([Lf/JG0;)Lf/U90;
/*    */     //   682: pop
/*    */     //   683: getfield s8 : [Lf/Un;
/*    */     //   686: invokevirtual Mg : ([Lf/JG0;)Lf/U90;
/*    */     //   689: pop
/*    */     //   690: invokevirtual WN : (Lf/U90;)V
/*    */     //   693: aload_3
/*    */     //   694: invokevirtual rK0 : (Lf/U90;)V
/*    */     //   697: getfield sA0 : Lf/rS;
/*    */     //   700: aload_1
/*    */     //   701: invokevirtual Gz0 : (Lf/JG0;)V
/*    */     //   704: return
/*    */     // Line number table:
/*    */     //   Java source line number -> byte code offset
/*    */     //   #1	-> 4
/*    */     //   #2	-> 7
/*    */     //   #3	-> 10
/*    */     //   #4	-> 41
/*    */     //   #5	-> 47
/*    */     //   #6	-> 53
/*    */     //   #7	-> 88
/*    */     //   #8	-> 94
/*    */     //   #9	-> 102
/*    */     //   #10	-> 108
/*    */     //   #11	-> 117
/*    */     //   #12	-> 139
/*    */     //   #13	-> 142
/*    */     //   #14	-> 147
/*    */     //   #15	-> 152
/*    */     //   #16	-> 159
/*    */     //   #17	-> 167
/*    */     //   #18	-> 170
/*    */     //   #19	-> 175
/*    */     //   #20	-> 180
/*    */     //   #21	-> 188
/*    */     //   #22	-> 222
/*    */     //   #23	-> 225
/*    */     //   #24	-> 265
/*    */     //   #25	-> 271
/*    */     //   #26	-> 313
/*    */     //   #27	-> 317
/*    */     //   #28	-> 369
/*    */     //   #29	-> 372
/*    */     //   #30	-> 377
/*    */     //   #31	-> 382
/*    */     //   #32	-> 389
/*    */     //   #33	-> 397
/*    */     //   #34	-> 400
/*    */     //   #35	-> 405
/*    */     //   #36	-> 410
/*    */     //   #37	-> 418
/*    */     //   #38	-> 452
/*    */     //   #39	-> 455
/*    */     //   #40	-> 475
/*    */     //   #41	-> 479
/*    */     //   #42	-> 482
/*    */     //   #43	-> 485
/*    */     //   #44	-> 513
/*    */     //   #45	-> 518
/*    */     //   #46	-> 525
/*    */     //   #47	-> 549
/*    */     //   #48	-> 653
/*    */     //   #49	-> 663
/*    */     //   #50	-> 676
/*    */   }
/*    */   
/*    */   public final void Yx0() {
/*    */     xl(null);
/*    */     if (this.QA.nv0() == 0) {
/*    */       Un un = this.kK;
/*    */       int j;
/*    */       if ((j = this.pA.vr0) <= 0)
/*    */         j = 56; 
/*    */       un.s6(Ml0.OH0(j));
/*    */       this.kK.sk0(false);
/*    */     } else {
/*    */       this.kK.s6(Ml0.OH0(62));
/*    */       this.kK.sk0(false);
/*    */     } 
/*    */   }
/*    */   
/*    */   public final boolean jf0(JG0 paramJG0) {
/*    */     if (paramJG0 == this.qV)
/*    */       this.qV = null; 
/*    */     return super.jf0(paramJG0);
/*    */   }
/*    */   
/*    */   public final void YF0() {
/*    */     Un un;
/*    */     if ((un = Kc()) == null)
/*    */       return; 
/*    */     VA0.c90(un);
/*    */     hm.Fz0(un.TG0.oh0);
/*    */     this.G90.ai(un);
/*    */     this.sA0.ai(un);
/*    */   }
/*    */   
/*    */   public final void xl(i parami) {
/*    */     // Byte code:
/*    */     //   0: aload_1
/*    */     //   1: aload_0
/*    */     //   2: dup
/*    */     //   3: dup
/*    */     //   4: aload_1
/*    */     //   5: putfield Y : Lf/i;
/*    */     //   8: getfield T70 : Lf/rh;
/*    */     //   11: iconst_1
/*    */     //   12: invokevirtual l4 : (I)V
/*    */     //   15: getfield prn : Lf/zT;
/*    */     //   18: astore_2
/*    */     //   19: ifnonnull -> 28
/*    */     //   22: bipush #99
/*    */     //   24: istore_1
/*    */     //   25: goto -> 33
/*    */     //   28: aload_1
/*    */     //   29: invokevirtual WM : ()S
/*    */     //   32: istore_1
/*    */     //   33: aload_0
/*    */     //   34: aload_2
/*    */     //   35: iload_1
/*    */     //   36: putfield lK : I
/*    */     //   39: invokevirtual Di : ()V
/*    */     //   42: return
/*    */     // Line number table:
/*    */     //   Java source line number -> byte code offset
/*    */     //   #1	-> 36
/*    */     //   #2	-> 39
/*    */   }
/*    */   
/*    */   public final void Di() {
/*    */     // Byte code:
/*    */     //   0: aload_0
/*    */     //   1: getfield pA : Lf/Uk;
/*    */     //   4: dup
/*    */     //   5: astore_1
/*    */     //   6: ifnonnull -> 10
/*    */     //   9: return
/*    */     //   10: aload_1
/*    */     //   11: getfield Xp0 : Lf/Ud0;
/*    */     //   14: dup
/*    */     //   15: astore_1
/*    */     //   16: getfield tn0 : I
/*    */     //   19: ifle -> 154
/*    */     //   22: aload_1
/*    */     //   23: aload_0
/*    */     //   24: dup
/*    */     //   25: getfield lI0 : Lf/Ip;
/*    */     //   28: iconst_1
/*    */     //   29: invokevirtual wI0 : (Z)V
/*    */     //   32: getfield Ej0 : Lf/dQ;
/*    */     //   35: astore_2
/*    */     //   36: getfield tn0 : I
/*    */     //   39: istore_3
/*    */     //   40: invokestatic getInstance : ()Ljava/text/NumberFormat;
/*    */     //   43: astore #4
/*    */     //   45: getstatic f/km.u4 : Lf/R8;
/*    */     //   48: dup
/*    */     //   49: astore #5
/*    */     //   51: ifnull -> 132
/*    */     //   54: aload #5
/*    */     //   56: getfield Lz : Lf/fH0;
/*    */     //   59: ifnonnull -> 65
/*    */     //   62: goto -> 132
/*    */     //   65: aload_1
/*    */     //   66: invokevirtual ordinal : ()I
/*    */     //   69: dup
/*    */     //   70: istore #5
/*    */     //   72: ifeq -> 118
/*    */     //   75: iload #5
/*    */     //   77: iconst_1
/*    */     //   78: if_icmpeq -> 104
/*    */     //   81: iload #5
/*    */     //   83: iconst_2
/*    */     //   84: if_icmpeq -> 90
/*    */     //   87: goto -> 132
/*    */     //   90: getstatic f/km.u4 : Lf/R8;
/*    */     //   93: getfield Lz : Lf/fH0;
/*    */     //   96: getfield NC0 : I
/*    */     //   99: istore #5
/*    */     //   101: goto -> 135
/*    */     //   104: getstatic f/km.u4 : Lf/R8;
/*    */     //   107: getfield Lz : Lf/fH0;
/*    */     //   110: getfield aY : S
/*    */     //   113: istore #5
/*    */     //   115: goto -> 135
/*    */     //   118: getstatic f/km.u4 : Lf/R8;
/*    */     //   121: getfield Lz : Lf/fH0;
/*    */     //   124: getfield Ii : I
/*    */     //   127: istore #5
/*    */     //   129: goto -> 135
/*    */     //   132: iconst_0
/*    */     //   133: istore #5
/*    */     //   135: aload_2
/*    */     //   136: iload_3
/*    */     //   137: aload #4
/*    */     //   139: iload #5
/*    */     //   141: i2l
/*    */     //   142: invokevirtual format : (J)Ljava/lang/String;
/*    */     //   145: invokestatic Go : (ILjava/lang/String;)Ljava/lang/String;
/*    */     //   148: invokevirtual E1 : (Ljava/lang/String;)V
/*    */     //   151: goto -> 171
/*    */     //   154: aload_0
/*    */     //   155: dup
/*    */     //   156: getfield lI0 : Lf/Ip;
/*    */     //   159: iconst_0
/*    */     //   160: invokevirtual wI0 : (Z)V
/*    */     //   163: getfield Ej0 : Lf/dQ;
/*    */     //   166: ldc ''
/*    */     //   168: invokevirtual E1 : (Ljava/lang/String;)V
/*    */     //   171: aload_0
/*    */     //   172: getfield Y : Lf/i;
/*    */     //   175: dup
/*    */     //   176: astore_2
/*    */     //   177: ifnonnull -> 267
/*    */     //   180: aload_1
/*    */     //   181: aload_0
/*    */     //   182: dup
/*    */     //   183: dup2
/*    */     //   184: iconst_m1
/*    */     //   185: putfield lj0 : I
/*    */     //   188: getfield Mc0 : Lf/dQ;
/*    */     //   191: ldc ''
/*    */     //   193: invokevirtual E1 : (Ljava/lang/String;)V
/*    */     //   196: getfield lO : Lf/dQ;
/*    */     //   199: ldc ''
/*    */     //   201: invokevirtual E1 : (Ljava/lang/String;)V
/*    */     //   204: getfield U8 : Lf/dQ;
/*    */     //   207: ldc ''
/*    */     //   209: invokevirtual E1 : (Ljava/lang/String;)V
/*    */     //   212: getfield kj0 : I
/*    */     //   215: dup
/*    */     //   216: istore_1
/*    */     //   217: iconst_1
/*    */     //   218: if_icmpge -> 233
/*    */     //   221: aload_0
/*    */     //   222: getfield tu0 : Lf/dQ;
/*    */     //   225: ldc ''
/*    */     //   227: invokevirtual E1 : (Ljava/lang/String;)V
/*    */     //   230: goto -> 247
/*    */     //   233: aload_0
/*    */     //   234: getfield tu0 : Lf/dQ;
/*    */     //   237: iload_1
/*    */     //   238: ldc_w '0'
/*    */     //   241: invokestatic Go : (ILjava/lang/String;)Ljava/lang/String;
/*    */     //   244: invokevirtual E1 : (Ljava/lang/String;)V
/*    */     //   247: aload_0
/*    */     //   248: dup
/*    */     //   249: getfield bg0 : Lf/dQ;
/*    */     //   252: ldc ''
/*    */     //   254: invokevirtual E1 : (Ljava/lang/String;)V
/*    */     //   257: getfield kK : Lf/Un;
/*    */     //   260: iconst_0
/*    */     //   261: invokevirtual sk0 : (Z)V
/*    */     //   264: goto -> 1087
/*    */     //   267: aload_0
/*    */     //   268: aload_2
/*    */     //   269: getfield Lc0 : Lf/Ud0;
/*    */     //   272: astore_1
/*    */     //   273: getfield QA : Lf/Vq0;
/*    */     //   276: invokevirtual nv0 : ()I
/*    */     //   279: ifne -> 377
/*    */     //   282: aload_1
/*    */     //   283: getstatic f/Ud0.X30 : Lf/Ud0;
/*    */     //   286: if_acmpne -> 311
/*    */     //   289: aload_0
/*    */     //   290: getfield Y : Lf/i;
/*    */     //   293: invokevirtual SK0 : ()I
/*    */     //   296: getstatic f/km.u4 : Lf/R8;
/*    */     //   299: getfield Lz : Lf/fH0;
/*    */     //   302: getfield Ii : I
/*    */     //   305: if_icmple -> 311
/*    */     //   308: goto -> 366
/*    */     //   311: aload_1
/*    */     //   312: getstatic f/Ud0.Bk0 : Lf/Ud0;
/*    */     //   315: if_acmpne -> 340
/*    */     //   318: aload_0
/*    */     //   319: getfield Y : Lf/i;
/*    */     //   322: invokevirtual SK0 : ()I
/*    */     //   325: getstatic f/km.u4 : Lf/R8;
/*    */     //   328: getfield Lz : Lf/fH0;
/*    */     //   331: getfield NC0 : I
/*    */     //   334: if_icmple -> 340
/*    */     //   337: goto -> 366
/*    */     //   340: aload_1
/*    */     //   341: getstatic f/Ud0.t7 : Lf/Ud0;
/*    */     //   344: if_acmpne -> 377
/*    */     //   347: aload_0
/*    */     //   348: getfield Y : Lf/i;
/*    */     //   351: invokevirtual SK0 : ()I
/*    */     //   354: getstatic f/km.u4 : Lf/R8;
/*    */     //   357: getfield Lz : Lf/fH0;
/*    */     //   360: getfield aY : S
/*    */     //   363: if_icmple -> 377
/*    */     //   366: aload_0
/*    */     //   367: getfield kK : Lf/Un;
/*    */     //   370: iconst_0
/*    */     //   371: invokevirtual sk0 : (Z)V
/*    */     //   374: goto -> 388
/*    */     //   377: aload_0
/*    */     //   378: getfield kK : Lf/Un;
/*    */     //   381: aload_0
/*    */     //   382: getfield aH : Z
/*    */     //   385: invokevirtual sk0 : (Z)V
/*    */     //   388: aload_0
/*    */     //   389: getfield yM : I
/*    */     //   392: ifne -> 406
/*    */     //   395: aload_0
/*    */     //   396: dup
/*    */     //   397: getfield Y : Lf/i;
/*    */     //   400: getfield n30 : I
/*    */     //   403: putfield lj0 : I
/*    */     //   406: aload_1
/*    */     //   407: aload_0
/*    */     //   408: dup
/*    */     //   409: getfield Mc0 : Lf/dQ;
/*    */     //   412: new java/lang/StringBuilder
/*    */     //   415: dup
/*    */     //   416: aload_0
/*    */     //   417: swap
/*    */     //   418: invokespecial <init> : ()V
/*    */     //   421: getfield Y : Lf/i;
/*    */     //   424: getfield cq0 : S
/*    */     //   427: invokevirtual append : (I)Ljava/lang/StringBuilder;
/*    */     //   430: ldc_w 'x '
/*    */     //   433: invokevirtual append : (Ljava/lang/String;)Ljava/lang/StringBuilder;
/*    */     //   436: aload_0
/*    */     //   437: getfield Y : Lf/i;
/*    */     //   440: invokevirtual WQ : ()Ljava/lang/String;
/*    */     //   443: invokevirtual append : (Ljava/lang/String;)Ljava/lang/StringBuilder;
/*    */     //   446: invokevirtual toString : ()Ljava/lang/String;
/*    */     //   449: invokevirtual E1 : (Ljava/lang/String;)V
/*    */     //   452: getfield lO : Lf/dQ;
/*    */     //   455: aload_0
/*    */     //   456: getfield Y : Lf/i;
/*    */     //   459: invokevirtual H0 : ()Ljava/lang/String;
/*    */     //   462: invokevirtual E1 : (Ljava/lang/String;)V
/*    */     //   465: getfield kj0 : I
/*    */     //   468: dup
/*    */     //   469: istore_2
/*    */     //   470: iconst_1
/*    */     //   471: if_icmpge -> 486
/*    */     //   474: aload_0
/*    */     //   475: getfield tu0 : Lf/dQ;
/*    */     //   478: ldc ''
/*    */     //   480: invokevirtual E1 : (Ljava/lang/String;)V
/*    */     //   483: goto -> 519
/*    */     //   486: aload_0
/*    */     //   487: getfield tu0 : Lf/dQ;
/*    */     //   490: iload_2
/*    */     //   491: invokestatic getInstance : ()Ljava/text/NumberFormat;
/*    */     //   494: aload_0
/*    */     //   495: getfield Y : Lf/i;
/*    */     //   498: invokevirtual SK0 : ()I
/*    */     //   501: aload_0
/*    */     //   502: getfield T70 : Lf/rh;
/*    */     //   505: getfield T8 : I
/*    */     //   508: imul
/*    */     //   509: i2l
/*    */     //   510: invokevirtual format : (J)Ljava/lang/String;
/*    */     //   513: invokestatic Go : (ILjava/lang/String;)Ljava/lang/String;
/*    */     //   516: invokevirtual E1 : (Ljava/lang/String;)V
/*    */     //   519: aload_0
/*    */     //   520: getfield QA : Lf/Vq0;
/*    */     //   523: invokevirtual nv0 : ()I
/*    */     //   526: iconst_1
/*    */     //   527: if_icmpne -> 704
/*    */     //   530: aload_0
/*    */     //   531: getfield pA : Lf/Uk;
/*    */     //   534: getfield Xp0 : Lf/Ud0;
/*    */     //   537: dup
/*    */     //   538: astore_1
/*    */     //   539: getstatic f/Ud0.X30 : Lf/Ud0;
/*    */     //   542: if_acmpne -> 604
/*    */     //   545: aload_0
/*    */     //   546: dup
/*    */     //   547: getfield U8 : Lf/dQ;
/*    */     //   550: invokestatic getInstance : ()Ljava/text/NumberFormat;
/*    */     //   553: aload_0
/*    */     //   554: getfield Y : Lf/i;
/*    */     //   557: invokevirtual SK0 : ()I
/*    */     //   560: i2l
/*    */     //   561: invokevirtual format : (J)Ljava/lang/String;
/*    */     //   564: sipush #1930
/*    */     //   567: swap
/*    */     //   568: invokestatic Go : (ILjava/lang/String;)Ljava/lang/String;
/*    */     //   571: invokevirtual E1 : (Ljava/lang/String;)V
/*    */     //   574: getfield bg0 : Lf/dQ;
/*    */     //   577: invokestatic getInstance : ()Ljava/text/NumberFormat;
/*    */     //   580: aload_0
/*    */     //   581: getfield Y : Lf/i;
/*    */     //   584: invokevirtual WM : ()S
/*    */     //   587: i2l
/*    */     //   588: invokevirtual format : (J)Ljava/lang/String;
/*    */     //   591: sipush #1929
/*    */     //   594: swap
/*    */     //   595: invokestatic Go : (ILjava/lang/String;)Ljava/lang/String;
/*    */     //   598: invokevirtual E1 : (Ljava/lang/String;)V
/*    */     //   601: goto -> 1087
/*    */     //   604: aload_1
/*    */     //   605: getstatic f/Ud0.GA : Lf/Ud0;
/*    */     //   608: if_acmpne -> 1087
/*    */     //   611: aload_0
/*    */     //   612: getfield Y : Lf/i;
/*    */     //   615: getfield Lq0 : Ljava/util/ArrayList;
/*    */     //   618: dup
/*    */     //   619: astore_1
/*    */     //   620: invokevirtual size : ()I
/*    */     //   623: iconst_1
/*    */     //   624: if_icmpge -> 638
/*    */     //   627: aload_0
/*    */     //   628: getfield U8 : Lf/dQ;
/*    */     //   631: iconst_0
/*    */     //   632: invokevirtual wI0 : (Z)V
/*    */     //   635: goto -> 1087
/*    */     //   638: aload_0
/*    */     //   639: aload_1
/*    */     //   640: aload_0
/*    */     //   641: getfield U8 : Lf/dQ;
/*    */     //   644: iconst_1
/*    */     //   645: invokevirtual wI0 : (Z)V
/*    */     //   648: iconst_0
/*    */     //   649: invokeinterface get : (I)Ljava/lang/Object;
/*    */     //   654: checkcast f/S3
/*    */     //   657: astore_1
/*    */     //   658: getfield U8 : Lf/dQ;
/*    */     //   661: iconst_2
/*    */     //   662: anewarray java/lang/String
/*    */     //   665: dup
/*    */     //   666: astore_2
/*    */     //   667: aload_1
/*    */     //   668: aload_2
/*    */     //   669: aload_1
/*    */     //   670: getfield cO : S
/*    */     //   673: invokestatic toString : (S)Ljava/lang/String;
/*    */     //   676: iconst_0
/*    */     //   677: swap
/*    */     //   678: aastore
/*    */     //   679: getfield wj0 : Lf/LPT3;
/*    */     //   682: getfield Iu : I
/*    */     //   685: invokestatic OH0 : (I)Ljava/lang/String;
/*    */     //   688: iconst_1
/*    */     //   689: swap
/*    */     //   690: aastore
/*    */     //   691: sipush #1937
/*    */     //   694: aload_2
/*    */     //   695: invokestatic sB : (I[Ljava/lang/String;)Ljava/lang/String;
/*    */     //   698: invokevirtual E1 : (Ljava/lang/String;)V
/*    */     //   701: goto -> 1087
/*    */     //   704: aload_0
/*    */     //   705: getfield Y : Lf/i;
/*    */     //   708: getfield wS : Ljava/util/ArrayList;
/*    */     //   711: invokevirtual isEmpty : ()Z
/*    */     //   714: ifeq -> 748
/*    */     //   717: aload_0
/*    */     //   718: getfield U8 : Lf/dQ;
/*    */     //   721: aload_1
/*    */     //   722: getfield CoM4 : I
/*    */     //   725: invokestatic getInstance : ()Ljava/text/NumberFormat;
/*    */     //   728: aload_0
/*    */     //   729: getfield Y : Lf/i;
/*    */     //   732: invokevirtual SK0 : ()I
/*    */     //   735: i2l
/*    */     //   736: invokevirtual format : (J)Ljava/lang/String;
/*    */     //   739: invokestatic Go : (ILjava/lang/String;)Ljava/lang/String;
/*    */     //   742: invokevirtual E1 : (Ljava/lang/String;)V
/*    */     //   745: goto -> 881
/*    */     //   748: aload_0
/*    */     //   749: dup
/*    */     //   750: getfield U8 : Lf/dQ;
/*    */     //   753: astore_1
/*    */     //   754: getfield Y : Lf/i;
/*    */     //   757: dup
/*    */     //   758: iconst_1
/*    */     //   759: istore_2
/*    */     //   760: invokevirtual getClass : ()Ljava/lang/Class;
/*    */     //   763: pop
/*    */     //   764: new java/lang/StringBuilder
/*    */     //   767: dup
/*    */     //   768: dup
/*    */     //   769: astore_3
/*    */     //   770: invokespecial <init> : ()V
/*    */     //   773: sipush #1948
/*    */     //   776: invokestatic OH0 : (I)Ljava/lang/String;
/*    */     //   779: invokevirtual append : (Ljava/lang/String;)Ljava/lang/StringBuilder;
/*    */     //   782: pop
/*    */     //   783: getfield wS : Ljava/util/ArrayList;
/*    */     //   786: invokevirtual iterator : ()Ljava/util/Iterator;
/*    */     //   789: astore #4
/*    */     //   791: aload #4
/*    */     //   793: invokeinterface hasNext : ()Z
/*    */     //   798: ifeq -> 865
/*    */     //   801: aload_3
/*    */     //   802: dup
/*    */     //   803: dup
/*    */     //   804: aload #4
/*    */     //   806: invokeinterface next : ()Ljava/lang/Object;
/*    */     //   811: checkcast f/S3
/*    */     //   814: astore #5
/*    */     //   816: ldc_w '\\n'
/*    */     //   819: invokevirtual append : (Ljava/lang/String;)Ljava/lang/StringBuilder;
/*    */     //   822: pop
/*    */     //   823: invokestatic getInstance : ()Ljava/text/NumberFormat;
/*    */     //   826: aload #5
/*    */     //   828: getfield cO : S
/*    */     //   831: iload_2
/*    */     //   832: imul
/*    */     //   833: i2l
/*    */     //   834: invokevirtual format : (J)Ljava/lang/String;
/*    */     //   837: invokevirtual append : (Ljava/lang/String;)Ljava/lang/StringBuilder;
/*    */     //   840: ldc_w 'x '
/*    */     //   843: invokevirtual append : (Ljava/lang/String;)Ljava/lang/StringBuilder;
/*    */     //   846: pop
/*    */     //   847: aload #5
/*    */     //   849: getfield wj0 : Lf/LPT3;
/*    */     //   852: getfield Iu : I
/*    */     //   855: invokestatic OH0 : (I)Ljava/lang/String;
/*    */     //   858: invokevirtual append : (Ljava/lang/String;)Ljava/lang/StringBuilder;
/*    */     //   861: pop
/*    */     //   862: goto -> 791
/*    */     //   865: aload_1
/*    */     //   866: aload_3
/*    */     //   867: dup
/*    */     //   868: ldc_w '\\n'
/*    */     //   871: invokevirtual append : (Ljava/lang/String;)Ljava/lang/StringBuilder;
/*    */     //   874: pop
/*    */     //   875: invokevirtual toString : ()Ljava/lang/String;
/*    */     //   878: invokevirtual E1 : (Ljava/lang/String;)V
/*    */     //   881: aload_0
/*    */     //   882: getfield Y : Lf/i;
/*    */     //   885: dup
/*    */     //   886: astore_1
/*    */     //   887: getfield BC : Lf/LPT3;
/*    */     //   890: ifnull -> 947
/*    */     //   893: aload_0
/*    */     //   894: dup
/*    */     //   895: getstatic f/km.u4 : Lf/R8;
/*    */     //   898: dup
/*    */     //   899: getfield jG0 : Lf/yM;
/*    */     //   902: invokevirtual gN : (Lf/yM;)Lf/zr0;
/*    */     //   905: aload_0
/*    */     //   906: getfield Y : Lf/i;
/*    */     //   909: invokevirtual iq0 : ()S
/*    */     //   912: invokevirtual jW : (S)I
/*    */     //   915: istore_1
/*    */     //   916: getfield bg0 : Lf/dQ;
/*    */     //   919: invokestatic getInstance : ()Ljava/text/NumberFormat;
/*    */     //   922: iload_1
/*    */     //   923: i2l
/*    */     //   924: invokevirtual format : (J)Ljava/lang/String;
/*    */     //   927: sipush #1929
/*    */     //   930: swap
/*    */     //   931: invokestatic Go : (ILjava/lang/String;)Ljava/lang/String;
/*    */     //   934: invokevirtual E1 : (Ljava/lang/String;)V
/*    */     //   937: getfield bg0 : Lf/dQ;
/*    */     //   940: iconst_1
/*    */     //   941: invokevirtual wI0 : (Z)V
/*    */     //   944: goto -> 1087
/*    */     //   947: aload_1
/*    */     //   948: getfield cZ : Lf/lj0;
/*    */     //   951: ifnull -> 1079
/*    */     //   954: getstatic f/km.u4 : Lf/R8;
/*    */     //   957: getstatic f/CJ.ST : Lf/CJ;
/*    */     //   960: invokevirtual Y40 : (Lf/CJ;)Lf/hP;
/*    */     //   963: dup
/*    */     //   964: aload_0
/*    */     //   965: getfield Y : Lf/i;
/*    */     //   968: invokevirtual iq0 : ()S
/*    */     //   971: istore_1
/*    */     //   972: getfield p20 : Ljava/util/HashMap;
/*    */     //   975: dup
/*    */     //   976: astore_2
/*    */     //   977: monitorenter
/*    */     //   978: iconst_0
/*    */     //   979: istore_3
/*    */     //   980: getfield p20 : Ljava/util/HashMap;
/*    */     //   983: invokevirtual values : ()Ljava/util/Collection;
/*    */     //   986: invokeinterface iterator : ()Ljava/util/Iterator;
/*    */     //   991: astore #4
/*    */     //   993: aload #4
/*    */     //   995: invokeinterface hasNext : ()Z
/*    */     //   1000: ifeq -> 1039
/*    */     //   1003: aload #4
/*    */     //   1005: invokeinterface next : ()Ljava/lang/Object;
/*    */     //   1010: checkcast f/uQ
/*    */     //   1013: dup
/*    */     //   1014: astore #5
/*    */     //   1016: ifnull -> 993
/*    */     //   1019: aload #5
/*    */     //   1021: getfield wj : Lf/Xm;
/*    */     //   1024: getfield eS : S
/*    */     //   1027: iload_1
/*    */     //   1028: if_icmpne -> 993
/*    */     //   1031: iload_3
/*    */     //   1032: iconst_1
/*    */     //   1033: iadd
/*    */     //   1034: i2s
/*    */     //   1035: istore_3
/*    */     //   1036: goto -> 993
/*    */     //   1039: aload_0
/*    */     //   1040: dup
/*    */     //   1041: aload_2
/*    */     //   1042: monitorexit
/*    */     //   1043: getfield bg0 : Lf/dQ;
/*    */     //   1046: invokestatic getInstance : ()Ljava/text/NumberFormat;
/*    */     //   1049: iload_3
/*    */     //   1050: i2l
/*    */     //   1051: invokevirtual format : (J)Ljava/lang/String;
/*    */     //   1054: sipush #1929
/*    */     //   1057: swap
/*    */     //   1058: invokestatic Go : (ILjava/lang/String;)Ljava/lang/String;
/*    */     //   1061: invokevirtual E1 : (Ljava/lang/String;)V
/*    */     //   1064: getfield bg0 : Lf/dQ;
/*    */     //   1067: iconst_1
/*    */     //   1068: invokevirtual wI0 : (Z)V
/*    */     //   1071: goto -> 1087
/*    */     //   1074: astore_0
/*    */     //   1075: aload_0
/*    */     //   1076: aload_2
/*    */     //   1077: monitorexit
/*    */     //   1078: athrow
/*    */     //   1079: aload_0
/*    */     //   1080: getfield bg0 : Lf/dQ;
/*    */     //   1083: iconst_0
/*    */     //   1084: invokevirtual wI0 : (Z)V
/*    */     //   1087: aload_0
/*    */     //   1088: getfield QA : Lf/Vq0;
/*    */     //   1091: invokevirtual nv0 : ()I
/*    */     //   1094: ifne -> 1227
/*    */     //   1097: aload_0
/*    */     //   1098: getfield Y : Lf/i;
/*    */     //   1101: dup
/*    */     //   1102: astore_1
/*    */     //   1103: ifnull -> 1132
/*    */     //   1106: aload_1
/*    */     //   1107: getfield Lc0 : Lf/Ud0;
/*    */     //   1110: getstatic f/Ud0.GA : Lf/Ud0;
/*    */     //   1113: if_acmpne -> 1132
/*    */     //   1116: aload_0
/*    */     //   1117: getfield kK : Lf/Un;
/*    */     //   1120: sipush #1931
/*    */     //   1123: invokestatic OH0 : (I)Ljava/lang/String;
/*    */     //   1126: invokevirtual s6 : (Ljava/lang/String;)V
/*    */     //   1129: goto -> 1239
/*    */     //   1132: aload_1
/*    */     //   1133: ifnull -> 1193
/*    */     //   1136: aload_1
/*    */     //   1137: getfield B70 : Lf/UD0;
/*    */     //   1140: ifnonnull -> 1193
/*    */     //   1143: aload_1
/*    */     //   1144: getfield cZ : Lf/lj0;
/*    */     //   1147: ifnonnull -> 1193
/*    */     //   1150: aload_1
/*    */     //   1151: getfield BC : Lf/LPT3;
/*    */     //   1154: dup
/*    */     //   1155: astore_1
/*    */     //   1156: ifnull -> 1169
/*    */     //   1159: aload_1
/*    */     //   1160: getfield c3 : Lf/wc;
/*    */     //   1163: ifnonnull -> 1169
/*    */     //   1166: goto -> 1193
/*    */     //   1169: aload_0
/*    */     //   1170: dup
/*    */     //   1171: getfield kK : Lf/Un;
/*    */     //   1174: sipush #3006
/*    */     //   1177: invokestatic OH0 : (I)Ljava/lang/String;
/*    */     //   1180: invokevirtual s6 : (Ljava/lang/String;)V
/*    */     //   1183: getfield kK : Lf/Un;
/*    */     //   1186: iconst_1
/*    */     //   1187: invokevirtual sk0 : (Z)V
/*    */     //   1190: goto -> 1239
/*    */     //   1193: aload_0
/*    */     //   1194: dup
/*    */     //   1195: getfield kK : Lf/Un;
/*    */     //   1198: astore_0
/*    */     //   1199: getfield pA : Lf/Uk;
/*    */     //   1202: getfield vr0 : I
/*    */     //   1205: dup
/*    */     //   1206: istore_1
/*    */     //   1207: ifle -> 1213
/*    */     //   1210: goto -> 1216
/*    */     //   1213: bipush #56
/*    */     //   1215: istore_1
/*    */     //   1216: aload_0
/*    */     //   1217: iload_1
/*    */     //   1218: invokestatic OH0 : (I)Ljava/lang/String;
/*    */     //   1221: invokevirtual s6 : (Ljava/lang/String;)V
/*    */     //   1224: goto -> 1239
/*    */     //   1227: aload_0
/*    */     //   1228: getfield kK : Lf/Un;
/*    */     //   1231: bipush #62
/*    */     //   1233: invokestatic OH0 : (I)Ljava/lang/String;
/*    */     //   1236: invokevirtual s6 : (Ljava/lang/String;)V
/*    */     //   1239: return
/*    */     // Line number table:
/*    */     //   Java source line number -> byte code offset
/*    */     //   #1	-> 11
/*    */     //   #2	-> 16
/*    */     //   #3	-> 25
/*    */     //   #4	-> 36
/*    */     //   #5	-> 40
/*    */     //   #6	-> 45
/*    */     //   #7	-> 56
/*    */     //   #8	-> 66
/*    */     //   #9	-> 93
/*    */     //   #10	-> 96
/*    */     //   #11	-> 104
/*    */     //   #12	-> 107
/*    */     //   #13	-> 110
/*    */     //   #14	-> 118
/*    */     //   #15	-> 121
/*    */     //   #16	-> 124
/*    */     //   #17	-> 142
/*    */     //   #18	-> 212
/*    */     //   #19	-> 222
/*    */     //   #20	-> 269
/*    */     //   #21	-> 273
/*    */     //   #22	-> 299
/*    */     //   #23	-> 302
/*    */     //   #24	-> 312
/*    */     //   #25	-> 328
/*    */     //   #26	-> 331
/*    */     //   #27	-> 341
/*    */     //   #28	-> 357
/*    */     //   #29	-> 360
/*    */     //   #30	-> 367
/*    */     //   #31	-> 400
/*    */     //   #32	-> 403
/*    */     //   #33	-> 424
/*    */     //   #34	-> 427
/*    */     //   #35	-> 465
/*    */     //   #36	-> 475
/*    */     //   #37	-> 505
/*    */     //   #38	-> 510
/*    */     //   #39	-> 534
/*    */     //   #40	-> 539
/*    */     //   #41	-> 615
/*    */     //   #42	-> 620
/*    */     //   #43	-> 670
/*    */     //   #44	-> 673
/*    */     //   #45	-> 679
/*    */     //   #46	-> 682
/*    */     //   #47	-> 685
/*    */     //   #48	-> 690
/*    */     //   #49	-> 708
/*    */     //   #50	-> 711
/*    */     //   #51	-> 722
/*    */     //   #52	-> 725
/*    */     //   #53	-> 764
/*    */     //   #54	-> 828
/*    */     //   #55	-> 834
/*    */     //   #56	-> 849
/*    */     //   #57	-> 852
/*    */     //   #58	-> 855
/*    */     //   #59	-> 858
/*    */     //   #60	-> 878
/*    */     //   #61	-> 887
/*    */     //   #62	-> 895
/*    */     //   #63	-> 899
/*    */     //   #64	-> 902
/*    */     //   #65	-> 906
/*    */     //   #66	-> 948
/*    */     //   #67	-> 954
/*    */     //   #68	-> 972
/*    */     //   #69	-> 1021
/*    */     //   #70	-> 1024
/*    */     //   #71	-> 1042
/*    */     //   #72	-> 1043
/*    */     //   #73	-> 1077
/*    */     //   #74	-> 1080
/*    */     //   #75	-> 1107
/*    */     //   #76	-> 1110
/*    */     //   #77	-> 1137
/*    */     //   #78	-> 1144
/*    */     //   #79	-> 1151
/*    */     //   #80	-> 1160
/*    */     //   #81	-> 1171
/*    */     //   #82	-> 1202
/*    */     //   #83	-> 1218
/*    */     // Exception table:
/*    */     //   from	to	target	type
/*    */     //   980	991	1074	finally
/*    */     //   993	1000	1074	finally
/*    */     //   1003	1013	1074	finally
/*    */     //   1019	1027	1074	finally
/*    */     //   1039	1043	1074	finally
/*    */     //   1075	1078	1074	finally
/*    */   }
/*    */   
/*    */   public final void IG0() {
/*    */     this.lj0 = 0;
/*    */     YF0();
/*    */   }
/*    */   
/*    */   public final boolean i2(oa0 paramoa0) {
/*    */     // Byte code:
/*    */     //   0: aload_1
/*    */     //   1: getfield cz0 : I
/*    */     //   4: invokestatic Wm0 : (I)Z
/*    */     //   7: ifeq -> 414
/*    */     //   10: aload_1
/*    */     //   11: invokevirtual oO : ()Z
/*    */     //   14: ifeq -> 414
/*    */     //   17: aload_0
/*    */     //   18: aload_1
/*    */     //   19: getfield GG0 : I
/*    */     //   22: istore_2
/*    */     //   23: getfield yM : I
/*    */     //   26: ifne -> 230
/*    */     //   29: iload_2
/*    */     //   30: getstatic f/BM.ni : Lf/BM;
/*    */     //   33: invokestatic J20 : (ILf/BM;)Z
/*    */     //   36: ifeq -> 61
/*    */     //   39: aload_0
/*    */     //   40: getfield lj0 : I
/*    */     //   43: dup
/*    */     //   44: istore_1
/*    */     //   45: ifle -> 59
/*    */     //   48: aload_0
/*    */     //   49: dup
/*    */     //   50: iload_1
/*    */     //   51: iconst_1
/*    */     //   52: isub
/*    */     //   53: putfield lj0 : I
/*    */     //   56: invokevirtual YF0 : ()V
/*    */     //   59: iconst_1
/*    */     //   60: ireturn
/*    */     //   61: iload_2
/*    */     //   62: getstatic f/BM.N70 : Lf/BM;
/*    */     //   65: invokestatic J20 : (ILf/BM;)Z
/*    */     //   68: ifeq -> 87
/*    */     //   71: aload_0
/*    */     //   72: dup
/*    */     //   73: dup
/*    */     //   74: getfield lj0 : I
/*    */     //   77: iconst_1
/*    */     //   78: iadd
/*    */     //   79: putfield lj0 : I
/*    */     //   82: invokevirtual YF0 : ()V
/*    */     //   85: iconst_1
/*    */     //   86: ireturn
/*    */     //   87: iload_2
/*    */     //   88: getstatic f/BM.Oq : Lf/BM;
/*    */     //   91: invokestatic J20 : (ILf/BM;)Z
/*    */     //   94: ifeq -> 127
/*    */     //   97: aload_0
/*    */     //   98: getfield QA : Lf/Vq0;
/*    */     //   101: invokevirtual nv0 : ()I
/*    */     //   104: iconst_1
/*    */     //   105: if_icmpne -> 116
/*    */     //   108: aload_0
/*    */     //   109: getfield QA : Lf/Vq0;
/*    */     //   112: iconst_m1
/*    */     //   113: invokevirtual E00 : (I)V
/*    */     //   116: aload_0
/*    */     //   117: dup
/*    */     //   118: iconst_0
/*    */     //   119: putfield lj0 : I
/*    */     //   122: invokevirtual YF0 : ()V
/*    */     //   125: iconst_1
/*    */     //   126: ireturn
/*    */     //   127: iload_2
/*    */     //   128: getstatic f/BM.M8 : Lf/BM;
/*    */     //   131: invokestatic J20 : (ILf/BM;)Z
/*    */     //   134: ifeq -> 166
/*    */     //   137: aload_0
/*    */     //   138: getfield QA : Lf/Vq0;
/*    */     //   141: invokevirtual nv0 : ()I
/*    */     //   144: ifne -> 155
/*    */     //   147: aload_0
/*    */     //   148: getfield QA : Lf/Vq0;
/*    */     //   151: iconst_1
/*    */     //   152: invokevirtual E00 : (I)V
/*    */     //   155: aload_0
/*    */     //   156: dup
/*    */     //   157: iconst_0
/*    */     //   158: putfield lj0 : I
/*    */     //   161: invokevirtual YF0 : ()V
/*    */     //   164: iconst_1
/*    */     //   165: ireturn
/*    */     //   166: iload_2
/*    */     //   167: getstatic f/BM.bC : Lf/BM;
/*    */     //   170: invokestatic J20 : (ILf/BM;)Z
/*    */     //   173: ifeq -> 211
/*    */     //   176: aload_0
/*    */     //   177: invokevirtual Kc : ()Lf/Un;
/*    */     //   180: ifnull -> 209
/*    */     //   183: aload_0
/*    */     //   184: dup
/*    */     //   185: iconst_1
/*    */     //   186: putfield yM : I
/*    */     //   189: getfield wr0 : [Lf/Un;
/*    */     //   192: dup
/*    */     //   193: aload_0
/*    */     //   194: swap
/*    */     //   195: arraylength
/*    */     //   196: iconst_1
/*    */     //   197: isub
/*    */     //   198: dup
/*    */     //   199: istore_0
/*    */     //   200: putfield lj0 : I
/*    */     //   203: iload_0
/*    */     //   204: aaload
/*    */     //   205: invokestatic c90 : (Lf/JG0;)Z
/*    */     //   208: pop
/*    */     //   209: iconst_1
/*    */     //   210: ireturn
/*    */     //   211: iload_2
/*    */     //   212: getstatic f/BM.lc : Lf/BM;
/*    */     //   215: invokestatic J20 : (ILf/BM;)Z
/*    */     //   218: ifeq -> 230
/*    */     //   221: aload_0
/*    */     //   222: getfield Q3 : Lf/pA;
/*    */     //   225: invokevirtual Yd : ()V
/*    */     //   228: iconst_1
/*    */     //   229: ireturn
/*    */     //   230: aload_0
/*    */     //   231: getfield yM : I
/*    */     //   234: iconst_1
/*    */     //   235: if_icmpne -> 414
/*    */     //   238: iload_2
/*    */     //   239: getstatic f/BM.Oq : Lf/BM;
/*    */     //   242: invokestatic J20 : (ILf/BM;)Z
/*    */     //   245: ifeq -> 281
/*    */     //   248: aload_0
/*    */     //   249: getfield lj0 : I
/*    */     //   252: dup
/*    */     //   253: istore_1
/*    */     //   254: iconst_1
/*    */     //   255: if_icmpge -> 260
/*    */     //   258: iconst_1
/*    */     //   259: ireturn
/*    */     //   260: aload_0
/*    */     //   261: dup
/*    */     //   262: iload_1
/*    */     //   263: iconst_1
/*    */     //   264: isub
/*    */     //   265: dup
/*    */     //   266: istore_0
/*    */     //   267: putfield lj0 : I
/*    */     //   270: getfield wr0 : [Lf/Un;
/*    */     //   273: iload_0
/*    */     //   274: aaload
/*    */     //   275: invokestatic c90 : (Lf/JG0;)Z
/*    */     //   278: pop
/*    */     //   279: iconst_1
/*    */     //   280: ireturn
/*    */     //   281: iload_2
/*    */     //   282: getstatic f/BM.M8 : Lf/BM;
/*    */     //   285: invokestatic J20 : (ILf/BM;)Z
/*    */     //   288: ifeq -> 329
/*    */     //   291: aload_0
/*    */     //   292: getfield lj0 : I
/*    */     //   295: dup
/*    */     //   296: istore_1
/*    */     //   297: aload_0
/*    */     //   298: getfield wr0 : [Lf/Un;
/*    */     //   301: dup
/*    */     //   302: astore_2
/*    */     //   303: arraylength
/*    */     //   304: iconst_1
/*    */     //   305: isub
/*    */     //   306: if_icmplt -> 311
/*    */     //   309: iconst_1
/*    */     //   310: ireturn
/*    */     //   311: aload_2
/*    */     //   312: aload_0
/*    */     //   313: iload_1
/*    */     //   314: iconst_1
/*    */     //   315: iadd
/*    */     //   316: dup
/*    */     //   317: istore_0
/*    */     //   318: putfield lj0 : I
/*    */     //   321: iload_0
/*    */     //   322: aaload
/*    */     //   323: invokestatic c90 : (Lf/JG0;)Z
/*    */     //   326: pop
/*    */     //   327: iconst_1
/*    */     //   328: ireturn
/*    */     //   329: iload_2
/*    */     //   330: getstatic f/BM.bC : Lf/BM;
/*    */     //   333: invokestatic J20 : (ILf/BM;)Z
/*    */     //   336: ifeq -> 361
/*    */     //   339: aload_0
/*    */     //   340: invokevirtual Kc : ()Lf/Un;
/*    */     //   343: ifnull -> 359
/*    */     //   346: aload_0
/*    */     //   347: invokevirtual Kc : ()Lf/Un;
/*    */     //   350: getfield TG0 : Lf/protected;
/*    */     //   353: getfield oh0 : [Ljava/lang/Runnable;
/*    */     //   356: invokestatic Fz0 : ([Ljava/lang/Runnable;)V
/*    */     //   359: iconst_1
/*    */     //   360: ireturn
/*    */     //   361: iload_2
/*    */     //   362: getstatic f/BM.lc : Lf/BM;
/*    */     //   365: invokestatic J20 : (ILf/BM;)Z
/*    */     //   368: ifeq -> 414
/*    */     //   371: aload_0
/*    */     //   372: dup
/*    */     //   373: dup
/*    */     //   374: dup2
/*    */     //   375: dup2
/*    */     //   376: iconst_0
/*    */     //   377: putfield yM : I
/*    */     //   380: iconst_m1
/*    */     //   381: putfield lj0 : I
/*    */     //   384: getfield G90 : Lf/rS;
/*    */     //   387: iconst_0
/*    */     //   388: invokevirtual rt : (I)V
/*    */     //   391: getfield sA0 : Lf/rS;
/*    */     //   394: iconst_0
/*    */     //   395: invokevirtual rt : (I)V
/*    */     //   398: aconst_null
/*    */     //   399: invokevirtual xl : (Lf/i;)V
/*    */     //   402: getfield kK : Lf/Un;
/*    */     //   405: invokevirtual xI0 : ()V
/*    */     //   408: invokestatic c90 : (Lf/JG0;)Z
/*    */     //   411: pop
/*    */     //   412: iconst_1
/*    */     //   413: ireturn
/*    */     //   414: aload_0
/*    */     //   415: aload_1
/*    */     //   416: invokespecial i2 : (Lf/oa0;)Z
/*    */     //   419: ireturn
/*    */     // Line number table:
/*    */     //   Java source line number -> byte code offset
/*    */     //   #1	-> 1
/*    */     //   #2	-> 4
/*    */     //   #3	-> 11
/*    */     //   #4	-> 19
/*    */     //   #5	-> 23
/*    */     //   #6	-> 350
/*    */     //   #7	-> 353
/*    */     //   #8	-> 356
/*    */     //   #9	-> 362
/*    */   }
/*    */   
/*    */   public final int rB0() {
/*    */     // Byte code:
/*    */     //   0: aload_0
/*    */     //   1: getfield Y : Lf/i;
/*    */     //   4: dup
/*    */     //   5: astore_1
/*    */     //   6: getfield Lc0 : Lf/Ud0;
/*    */     //   9: getstatic f/Ud0.GA : Lf/Ud0;
/*    */     //   12: if_acmpeq -> 25
/*    */     //   15: aload_1
/*    */     //   16: invokevirtual SK0 : ()I
/*    */     //   19: iconst_1
/*    */     //   20: if_icmpge -> 25
/*    */     //   23: iconst_0
/*    */     //   24: ireturn
/*    */     //   25: aload_0
/*    */     //   26: getfield QA : Lf/Vq0;
/*    */     //   29: invokevirtual nv0 : ()I
/*    */     //   32: ifeq -> 39
/*    */     //   35: sipush #999
/*    */     //   38: ireturn
/*    */     //   39: aload_0
/*    */     //   40: iconst_0
/*    */     //   41: istore_1
/*    */     //   42: getfield Y : Lf/i;
/*    */     //   45: getfield Lc0 : Lf/Ud0;
/*    */     //   48: invokevirtual ordinal : ()I
/*    */     //   51: tableswitch default -> 80, 0 -> 183, 1 -> 171, 2 -> 159, 3 -> 83
/*    */     //   80: goto -> 201
/*    */     //   83: aload_0
/*    */     //   84: ldc_w 2147483647
/*    */     //   87: istore_0
/*    */     //   88: getfield Y : Lf/i;
/*    */     //   91: getfield wS : Ljava/util/ArrayList;
/*    */     //   94: invokevirtual iterator : ()Ljava/util/Iterator;
/*    */     //   97: astore_2
/*    */     //   98: aload_2
/*    */     //   99: invokeinterface hasNext : ()Z
/*    */     //   104: ifeq -> 147
/*    */     //   107: aload_2
/*    */     //   108: invokeinterface next : ()Ljava/lang/Object;
/*    */     //   113: checkcast f/S3
/*    */     //   116: astore_3
/*    */     //   117: getstatic f/km.u4 : Lf/R8;
/*    */     //   120: dup
/*    */     //   121: getfield jG0 : Lf/yM;
/*    */     //   124: invokevirtual gN : (Lf/yM;)Lf/zr0;
/*    */     //   127: aload_3
/*    */     //   128: getfield Oz0 : S
/*    */     //   131: invokevirtual jW : (S)I
/*    */     //   134: aload_3
/*    */     //   135: getfield cO : S
/*    */     //   138: idiv
/*    */     //   139: iload_0
/*    */     //   140: invokestatic min : (II)I
/*    */     //   143: istore_0
/*    */     //   144: goto -> 98
/*    */     //   147: iload_0
/*    */     //   148: ldc_w 2147483647
/*    */     //   151: if_icmpeq -> 201
/*    */     //   154: iload_0
/*    */     //   155: istore_1
/*    */     //   156: goto -> 201
/*    */     //   159: getstatic f/km.u4 : Lf/R8;
/*    */     //   162: getfield Lz : Lf/fH0;
/*    */     //   165: getfield NC0 : I
/*    */     //   168: goto -> 192
/*    */     //   171: getstatic f/km.u4 : Lf/R8;
/*    */     //   174: getfield Lz : Lf/fH0;
/*    */     //   177: getfield aY : S
/*    */     //   180: goto -> 192
/*    */     //   183: getstatic f/km.u4 : Lf/R8;
/*    */     //   186: getfield Lz : Lf/fH0;
/*    */     //   189: getfield Ii : I
/*    */     //   192: aload_0
/*    */     //   193: getfield Y : Lf/i;
/*    */     //   196: invokevirtual SK0 : ()I
/*    */     //   199: idiv
/*    */     //   200: istore_1
/*    */     //   201: iload_1
/*    */     //   202: sipush #999
/*    */     //   205: if_icmple -> 212
/*    */     //   208: sipush #999
/*    */     //   211: istore_1
/*    */     //   212: iload_1
/*    */     //   213: ireturn
/*    */     // Line number table:
/*    */     //   Java source line number -> byte code offset
/*    */     //   #1	-> 6
/*    */     //   #2	-> 9
/*    */     //   #3	-> 45
/*    */     //   #4	-> 48
/*    */     //   #5	-> 91
/*    */     //   #6	-> 94
/*    */     //   #7	-> 121
/*    */     //   #8	-> 124
/*    */     //   #9	-> 128
/*    */     //   #10	-> 131
/*    */     //   #11	-> 135
/*    */     //   #12	-> 138
/*    */     //   #13	-> 162
/*    */     //   #14	-> 165
/*    */     //   #15	-> 171
/*    */     //   #16	-> 174
/*    */     //   #17	-> 177
/*    */     //   #18	-> 183
/*    */     //   #19	-> 186
/*    */     //   #20	-> 189
/*    */     //   #21	-> 193
/*    */   }
/*    */   
/*    */   public final Un Kc() {
/*    */     Un[] arrayOfUn;
/*    */     if (this.yM == 0) {
/*    */       if (this.QA.nv0() == 0) {
/*    */         arrayOfUn = this.Vm0;
/*    */       } else {
/*    */         arrayOfUn = this.s8;
/*    */       } 
/*    */     } else {
/*    */       arrayOfUn = this.wr0;
/*    */     } 
/*    */     if (this.lj0 >= arrayOfUn.length)
/*    */       this.lj0 = arrayOfUn.length - 1; 
/*    */     int j;
/*    */     return ((j = this.lj0) < 0) ? null : arrayOfUn[j];
/*    */   } }


/* Location:              /Users/vnnsnnt/Documents/Codespace/JavaWorkspace/RedTrainer/src/main/java/org/trainer/client/PokeMMO.jar!/f/hI0.class
 * Java compiler version: 8 (52.0)
 * JD-Core Version:       1.1.3
 */