/*  1 */ package f;public final class Hj { public kf Or; public Gp0 AF; public hm0 oN; public final boolean E; public final byte u4; public final byte Oq0; public final JG0 vO; public I50 lC; public aU Zu0; public dQ EK0; public vF0 nf; public dQ aJ; public final void COM8(hm0 paramhm0, boolean paramBoolean, short paramShort) { byte b; String str; this.oN = paramhm0; dQ dQ2 = this.aJ; if (paramhm0 == null) { str = ""; }
/*  2 */     else { str = pv.X9(59, (new StringBuilder()).append(paramhm0.fA()).append(" "), " ").append(paramhm0.Hk()).toString(); }  dQ2.E1(str); if (paramhm0 == null) { b = 0; } else { b = paramhm0.Hk(); }  this.LG0 = b; if (paramhm0 != null && km.MR != null) { this.Or
/*    */         
/*  4 */         .DQ(paramhm0.RN); I50 i50 = this.lC; if (paramShort < 0) paramShort = paramhm0.XW();
/*    */       
/*  6 */       short s = paramhm0.K0.hp0;
/*  7 */       i50.jC0 = false;
/*  8 */       i50.wg0 = paramShort; i50.Vz0 = s; if (!paramBoolean) { i50.j40 = paramShort; i50.uX(); }  this
/*    */ 
/*    */ 
/*    */         
/* 12 */         .YG = rG0.P70(this.AF, paramhm0.RN, false); this.aJ.VH(null); this.aJ
/* 13 */         .z4 = this.YG;
/* 14 */       this.aJ.zn();
/* 15 */       this.aJ
/* 16 */         .jl = 100; } else { this
/* 17 */         .aJ.VH(null); this.aJ
/* 18 */         .z4 = "";
/* 19 */       this.aJ.zn(); }  if (paramhm0 == null || paramhm0
/* 20 */       .hE() < 0 || paramhm0.hE() > 1)
/*    */     
/*    */     { 
/*    */ 
/*    */ 
/*    */ 
/*    */ 
/*    */ 
/*    */       
/* 29 */       this.sa
/* 30 */         .TS
/* 31 */         .H(); } else { interface interface = interface.ZZ(); this.sa.TS.Pn(new pe0[] { interface.iy0[paramhm0.hE()] }); if (km.XU()) { this.sa.TS.tL(32, 32); } else { this.sa.TS.tL(19, 19); }  }  dQ dQ1; if ((dQ1 = this.EK0) != null && paramhm0 == null) dQ1.E1("- / -");  if (this.Zu0 != null && !this.AF.Vg() && paramhm0 != null) { j40 j40; float f = 0.0F; Uc0 uc0; if ((uc0 = km.u4.s40(aq0.LI)) == null) { uc0 = null; } else { j40 = uc0.de0(paramhm0.ih()); }  if (j40 != null)
/*    */       { float f1; Q90 q90;
/* 33 */         if ((b = (q90 = j40.Zs).od) == 100) { f1 = 100.0F;
/*    */ 
/*    */           
/*    */            }
/*    */         
/*    */         else
/*    */         
/*    */         { 
/*    */           
/* 42 */           int i = j40.VP.eb.GJ(j40.Zs.od + 1) - j40.VP.eb.GJ(b); f = (f1.pA - j40.VP.eb.GJ(b)) / i; }  }  this.Zu0
/* 43 */         .Th = f;
/* 44 */       this.Zu0.Ih0 = f; this.Zu0.Nu(f); }
/* 45 */      Cg0(paramhm0); } public int LG0; public vF0 sa; public vF0 ec0; public vF0 ji0; public String YG; public boolean GC; public boolean li; public boolean AG; public int pz0; public int Ll; public int p9; public int ho0; public Hj(byte paramByte1, byte paramByte2, kf paramkf, Gp0 paramGp0) { // Byte code:
/*    */     //   0: iload_1
/*    */     //   1: aload #4
/*    */     //   3: aload_0
/*    */     //   4: aload #4
/*    */     //   6: aload_0
/*    */     //   7: aload_3
/*    */     //   8: aload_0
/*    */     //   9: dup
/*    */     //   10: dup2
/*    */     //   11: dup2
/*    */     //   12: dup2
/*    */     //   13: dup2
/*    */     //   14: invokespecial <init> : ()V
/*    */     //   17: aconst_null
/*    */     //   18: putfield EK0 : Lf/dQ;
/*    */     //   21: aconst_null
/*    */     //   22: putfield ec0 : Lf/vF0;
/*    */     //   25: iconst_0
/*    */     //   26: putfield GC : Z
/*    */     //   29: iconst_0
/*    */     //   30: putfield li : Z
/*    */     //   33: iconst_0
/*    */     //   34: putfield AG : Z
/*    */     //   37: iconst_0
/*    */     //   38: putfield pz0 : I
/*    */     //   41: iconst_0
/*    */     //   42: putfield Ll : I
/*    */     //   45: iconst_0
/*    */     //   46: putfield p9 : I
/*    */     //   49: iconst_0
/*    */     //   50: putfield ho0 : I
/*    */     //   53: putfield Or : Lf/kf;
/*    */     //   56: putfield AF : Lf/Gp0;
/*    */     //   59: invokevirtual hG0 : ()B
/*    */     //   62: if_icmpne -> 71
/*    */     //   65: iconst_1
/*    */     //   66: istore #5
/*    */     //   68: goto -> 74
/*    */     //   71: iconst_0
/*    */     //   72: istore #5
/*    */     //   74: aload #4
/*    */     //   76: iload_1
/*    */     //   77: aload_0
/*    */     //   78: aload #4
/*    */     //   80: iload_1
/*    */     //   81: aload_0
/*    */     //   82: iload_2
/*    */     //   83: aload_0
/*    */     //   84: iload #5
/*    */     //   86: putfield E : Z
/*    */     //   89: putfield u4 : B
/*    */     //   92: invokevirtual wI : (B)B
/*    */     //   95: putfield Oq0 : B
/*    */     //   98: iload_2
/*    */     //   99: invokevirtual N0 : (BB)Lf/hm0;
/*    */     //   102: dup
/*    */     //   103: astore #6
/*    */     //   105: ifnull -> 125
/*    */     //   108: aload_0
/*    */     //   109: aload #4
/*    */     //   111: aload #6
/*    */     //   113: invokevirtual x6 : ()Lf/cOm4;
/*    */     //   116: invokestatic Ef0 : (Lf/Gp0;Lf/cOm4;)Ljava/lang/String;
/*    */     //   119: putfield YG : Ljava/lang/String;
/*    */     //   122: goto -> 131
/*    */     //   125: aload_0
/*    */     //   126: ldc ''
/*    */     //   128: putfield YG : Ljava/lang/String;
/*    */     //   131: iload #5
/*    */     //   133: aload_0
/*    */     //   134: dup
/*    */     //   135: aload #6
/*    */     //   137: putfield oN : Lf/hm0;
/*    */     //   140: new f/JG0
/*    */     //   143: dup
/*    */     //   144: astore #5
/*    */     //   146: invokespecial <init> : ()V
/*    */     //   149: aload #5
/*    */     //   151: putfield vO : Lf/JG0;
/*    */     //   154: ifeq -> 714
/*    */     //   157: aload #4
/*    */     //   159: invokevirtual DQ : ()Lf/Mn;
/*    */     //   162: getstatic f/Mn.VK : Lf/Mn;
/*    */     //   165: if_acmpne -> 266
/*    */     //   168: aload_0
/*    */     //   169: dup
/*    */     //   170: dup
/*    */     //   171: aload #5
/*    */     //   173: ldc 'battle-gui-float'
/*    */     //   175: invokevirtual Xu : (Ljava/lang/String;)V
/*    */     //   178: iconst_1
/*    */     //   179: putfield AG : Z
/*    */     //   182: iconst_1
/*    */     //   183: putfield GC : Z
/*    */     //   186: iconst_1
/*    */     //   187: putfield li : Z
/*    */     //   190: sipush #307
/*    */     //   193: istore_2
/*    */     //   194: invokestatic XU : ()Z
/*    */     //   197: ifeq -> 207
/*    */     //   200: bipush #38
/*    */     //   202: istore #6
/*    */     //   204: goto -> 211
/*    */     //   207: bipush #28
/*    */     //   209: istore #6
/*    */     //   211: aload #5
/*    */     //   213: iload_2
/*    */     //   214: iload #6
/*    */     //   216: invokevirtual uh0 : (II)V
/*    */     //   219: sipush #307
/*    */     //   222: istore_2
/*    */     //   223: invokestatic XU : ()Z
/*    */     //   226: ifeq -> 236
/*    */     //   229: bipush #38
/*    */     //   231: istore #6
/*    */     //   233: goto -> 240
/*    */     //   236: bipush #28
/*    */     //   238: istore #6
/*    */     //   240: aload #5
/*    */     //   242: iload_2
/*    */     //   243: iload #6
/*    */     //   245: invokevirtual Tm : (II)Z
/*    */     //   248: pop
/*    */     //   249: sipush #307
/*    */     //   252: istore_2
/*    */     //   253: invokestatic XU : ()Z
/*    */     //   256: ifeq -> 401
/*    */     //   259: bipush #38
/*    */     //   261: istore #6
/*    */     //   263: goto -> 405
/*    */     //   266: aload #4
/*    */     //   268: invokevirtual sQ : ()Z
/*    */     //   271: ifeq -> 416
/*    */     //   274: aload #5
/*    */     //   276: aload_0
/*    */     //   277: iconst_1
/*    */     //   278: putfield GC : Z
/*    */     //   281: ldc 'battle-gui-self-slim'
/*    */     //   283: invokevirtual Xu : (Ljava/lang/String;)V
/*    */     //   286: invokestatic XU : ()Z
/*    */     //   289: ifeq -> 299
/*    */     //   292: sipush #320
/*    */     //   295: istore_2
/*    */     //   296: goto -> 303
/*    */     //   299: sipush #299
/*    */     //   302: istore_2
/*    */     //   303: invokestatic XU : ()Z
/*    */     //   306: ifeq -> 316
/*    */     //   309: bipush #39
/*    */     //   311: istore #6
/*    */     //   313: goto -> 320
/*    */     //   316: bipush #28
/*    */     //   318: istore #6
/*    */     //   320: aload #5
/*    */     //   322: iload_2
/*    */     //   323: iload #6
/*    */     //   325: invokevirtual uh0 : (II)V
/*    */     //   328: invokestatic XU : ()Z
/*    */     //   331: ifeq -> 341
/*    */     //   334: sipush #320
/*    */     //   337: istore_2
/*    */     //   338: goto -> 345
/*    */     //   341: sipush #299
/*    */     //   344: istore_2
/*    */     //   345: invokestatic XU : ()Z
/*    */     //   348: ifeq -> 358
/*    */     //   351: bipush #39
/*    */     //   353: istore #6
/*    */     //   355: goto -> 362
/*    */     //   358: bipush #28
/*    */     //   360: istore #6
/*    */     //   362: aload #5
/*    */     //   364: iload_2
/*    */     //   365: iload #6
/*    */     //   367: invokevirtual Tm : (II)Z
/*    */     //   370: pop
/*    */     //   371: invokestatic XU : ()Z
/*    */     //   374: ifeq -> 384
/*    */     //   377: sipush #320
/*    */     //   380: istore_2
/*    */     //   381: goto -> 388
/*    */     //   384: sipush #299
/*    */     //   387: istore_2
/*    */     //   388: invokestatic XU : ()Z
/*    */     //   391: ifeq -> 401
/*    */     //   394: bipush #39
/*    */     //   396: istore #6
/*    */     //   398: goto -> 405
/*    */     //   401: bipush #28
/*    */     //   403: istore #6
/*    */     //   405: aload #5
/*    */     //   407: iload_2
/*    */     //   408: iload #6
/*    */     //   410: invokevirtual RI : (II)V
/*    */     //   413: goto -> 635
/*    */     //   416: aload #5
/*    */     //   418: iload_2
/*    */     //   419: aload #5
/*    */     //   421: ldc 'battle-gui-self'
/*    */     //   423: invokevirtual Xu : (Ljava/lang/String;)V
/*    */     //   426: getstatic f/km.wI0 : Lf/Pw;
/*    */     //   429: invokevirtual dG : ()I
/*    */     //   432: iconst_2
/*    */     //   433: idiv
/*    */     //   434: sipush #326
/*    */     //   437: iadd
/*    */     //   438: istore_2
/*    */     //   439: bipush #40
/*    */     //   441: imul
/*    */     //   442: sipush #310
/*    */     //   445: iadd
/*    */     //   446: iload_2
/*    */     //   447: swap
/*    */     //   448: invokevirtual Ol0 : (II)V
/*    */     //   451: invokestatic XU : ()Z
/*    */     //   454: ifeq -> 464
/*    */     //   457: sipush #320
/*    */     //   460: istore_2
/*    */     //   461: goto -> 468
/*    */     //   464: sipush #299
/*    */     //   467: istore_2
/*    */     //   468: invokestatic XU : ()Z
/*    */     //   471: ifeq -> 481
/*    */     //   474: bipush #54
/*    */     //   476: istore #6
/*    */     //   478: goto -> 485
/*    */     //   481: bipush #40
/*    */     //   483: istore #6
/*    */     //   485: aload #5
/*    */     //   487: iload_2
/*    */     //   488: iload #6
/*    */     //   490: invokevirtual uh0 : (II)V
/*    */     //   493: invokestatic XU : ()Z
/*    */     //   496: ifeq -> 506
/*    */     //   499: sipush #320
/*    */     //   502: istore_2
/*    */     //   503: goto -> 510
/*    */     //   506: sipush #299
/*    */     //   509: istore_2
/*    */     //   510: invokestatic XU : ()Z
/*    */     //   513: ifeq -> 523
/*    */     //   516: bipush #54
/*    */     //   518: istore #6
/*    */     //   520: goto -> 527
/*    */     //   523: bipush #40
/*    */     //   525: istore #6
/*    */     //   527: aload #5
/*    */     //   529: iload_2
/*    */     //   530: iload #6
/*    */     //   532: invokevirtual Tm : (II)Z
/*    */     //   535: pop
/*    */     //   536: invokestatic XU : ()Z
/*    */     //   539: ifeq -> 549
/*    */     //   542: sipush #320
/*    */     //   545: istore_2
/*    */     //   546: goto -> 553
/*    */     //   549: sipush #299
/*    */     //   552: istore_2
/*    */     //   553: invokestatic XU : ()Z
/*    */     //   556: ifeq -> 566
/*    */     //   559: bipush #54
/*    */     //   561: istore #6
/*    */     //   563: goto -> 570
/*    */     //   566: bipush #40
/*    */     //   568: istore #6
/*    */     //   570: aload_0
/*    */     //   571: aload #5
/*    */     //   573: iload_2
/*    */     //   574: iload #6
/*    */     //   576: invokevirtual RI : (II)V
/*    */     //   579: getfield GC : Z
/*    */     //   582: ifne -> 635
/*    */     //   585: aload_0
/*    */     //   586: new f/dQ
/*    */     //   589: dup
/*    */     //   590: dup
/*    */     //   591: aload_0
/*    */     //   592: swap
/*    */     //   593: dup
/*    */     //   594: ldc ''
/*    */     //   596: invokespecial <init> : (Ljava/lang/String;)V
/*    */     //   599: putfield EK0 : Lf/dQ;
/*    */     //   602: invokevirtual kz0 : ()I
/*    */     //   605: sipush #200
/*    */     //   608: swap
/*    */     //   609: invokevirtual Tm : (II)Z
/*    */     //   612: pop
/*    */     //   613: getfield EK0 : Lf/dQ;
/*    */     //   616: aload #5
/*    */     //   618: invokevirtual a40 : ()I
/*    */     //   621: bipush #80
/*    */     //   623: iadd
/*    */     //   624: aload #5
/*    */     //   626: invokevirtual CB : ()I
/*    */     //   629: bipush #29
/*    */     //   631: iadd
/*    */     //   632: invokevirtual Ol0 : (II)V
/*    */     //   635: aload #4
/*    */     //   637: invokevirtual Vg : ()Z
/*    */     //   640: ifne -> 956
/*    */     //   643: aload #4
/*    */     //   645: invokevirtual sQ : ()Z
/*    */     //   648: ifne -> 956
/*    */     //   651: aload #4
/*    */     //   653: iload_1
/*    */     //   654: invokevirtual wI : (B)B
/*    */     //   657: iconst_2
/*    */     //   658: if_icmpge -> 956
/*    */     //   661: aload_0
/*    */     //   662: dup
/*    */     //   663: new f/aU
/*    */     //   666: dup
/*    */     //   667: aload_0
/*    */     //   668: swap
/*    */     //   669: dup
/*    */     //   670: aload_0
/*    */     //   671: invokespecial <init> : (Lf/Hj;)V
/*    */     //   674: putfield Zu0 : Lf/aU;
/*    */     //   677: fconst_0
/*    */     //   678: invokevirtual Nu : (F)V
/*    */     //   681: getfield Zu0 : Lf/aU;
/*    */     //   684: ldc 'xp-progressbar'
/*    */     //   686: invokevirtual Xu : (Ljava/lang/String;)V
/*    */     //   689: getfield Zu0 : Lf/aU;
/*    */     //   692: aload #5
/*    */     //   694: invokevirtual a40 : ()I
/*    */     //   697: bipush #80
/*    */     //   699: iadd
/*    */     //   700: aload #5
/*    */     //   702: invokevirtual CB : ()I
/*    */     //   705: bipush #42
/*    */     //   707: iadd
/*    */     //   708: invokevirtual Ol0 : (II)V
/*    */     //   711: goto -> 956
/*    */     //   714: aload #4
/*    */     //   716: invokevirtual DQ : ()Lf/Mn;
/*    */     //   719: invokevirtual Sg0 : ()Z
/*    */     //   722: ifeq -> 728
/*    */     //   725: goto -> 739
/*    */     //   728: aload #4
/*    */     //   730: invokevirtual Zo : ()Lf/ky;
/*    */     //   733: getstatic f/ky.We0 : Lf/ky;
/*    */     //   736: if_acmpne -> 754
/*    */     //   739: aload_0
/*    */     //   740: aload #5
/*    */     //   742: ldc 'battle-gui-float'
/*    */     //   744: invokevirtual Xu : (Ljava/lang/String;)V
/*    */     //   747: iconst_1
/*    */     //   748: putfield AG : Z
/*    */     //   751: goto -> 761
/*    */     //   754: aload #5
/*    */     //   756: ldc 'battle-gui-enemy'
/*    */     //   758: invokevirtual Xu : (Ljava/lang/String;)V
/*    */     //   761: sipush #307
/*    */     //   764: istore #6
/*    */     //   766: invokestatic XU : ()Z
/*    */     //   769: ifeq -> 779
/*    */     //   772: bipush #38
/*    */     //   774: istore #7
/*    */     //   776: goto -> 783
/*    */     //   779: bipush #28
/*    */     //   781: istore #7
/*    */     //   783: aload #5
/*    */     //   785: iload #6
/*    */     //   787: iload #7
/*    */     //   789: invokevirtual uh0 : (II)V
/*    */     //   792: sipush #307
/*    */     //   795: istore #6
/*    */     //   797: invokestatic XU : ()Z
/*    */     //   800: ifeq -> 810
/*    */     //   803: bipush #38
/*    */     //   805: istore #7
/*    */     //   807: goto -> 814
/*    */     //   810: bipush #28
/*    */     //   812: istore #7
/*    */     //   814: aload #5
/*    */     //   816: iload #6
/*    */     //   818: iload #7
/*    */     //   820: invokevirtual Tm : (II)Z
/*    */     //   823: pop
/*    */     //   824: sipush #307
/*    */     //   827: istore #6
/*    */     //   829: invokestatic XU : ()Z
/*    */     //   832: ifeq -> 842
/*    */     //   835: bipush #38
/*    */     //   837: istore #7
/*    */     //   839: goto -> 846
/*    */     //   842: bipush #28
/*    */     //   844: istore #7
/*    */     //   846: aload #4
/*    */     //   848: iload_1
/*    */     //   849: aload #5
/*    */     //   851: iload #6
/*    */     //   853: iload #7
/*    */     //   855: invokevirtual RI : (II)V
/*    */     //   858: invokevirtual wB : (B)Lf/QZ;
/*    */     //   861: invokevirtual Us : ()Z
/*    */     //   864: ifeq -> 956
/*    */     //   867: aload #4
/*    */     //   869: iload_1
/*    */     //   870: invokevirtual S10 : (B)[Lf/hm0;
/*    */     //   873: iload_2
/*    */     //   874: aaload
/*    */     //   875: ifnull -> 956
/*    */     //   878: getstatic f/km.u4 : Lf/R8;
/*    */     //   881: invokevirtual DS : ()Lf/qc0;
/*    */     //   884: aload #4
/*    */     //   886: iload_1
/*    */     //   887: invokevirtual S10 : (B)[Lf/hm0;
/*    */     //   890: iload_2
/*    */     //   891: aaload
/*    */     //   892: invokevirtual Jx : ()S
/*    */     //   895: iconst_1
/*    */     //   896: swap
/*    */     //   897: invokevirtual JO : (BS)Z
/*    */     //   900: ifeq -> 956
/*    */     //   903: aload_0
/*    */     //   904: dup
/*    */     //   905: new f/vF0
/*    */     //   908: dup
/*    */     //   909: dup
/*    */     //   910: astore_1
/*    */     //   911: bipush #32
/*    */     //   913: bipush #32
/*    */     //   915: invokespecial <init> : (II)V
/*    */     //   918: putfield ec0 : Lf/vF0;
/*    */     //   921: aload_1
/*    */     //   922: invokevirtual ZH0 : ()Lf/rH;
/*    */     //   925: iconst_1
/*    */     //   926: anewarray f/U70
/*    */     //   929: dup
/*    */     //   930: invokestatic Kw0 : ()Lf/h90;
/*    */     //   933: iconst_3
/*    */     //   934: invokevirtual j : (B)Lf/U70;
/*    */     //   937: iconst_0
/*    */     //   938: swap
/*    */     //   939: aastore
/*    */     //   940: invokevirtual qt : ([Lf/U70;)Lf/JG0;
/*    */     //   943: pop
/*    */     //   944: getfield ec0 : Lf/vF0;
/*    */     //   947: invokevirtual ZH0 : ()Lf/rH;
/*    */     //   950: getstatic f/et.Wi0 : Lf/et;
/*    */     //   953: invokevirtual uE0 : (Lf/et;)V
/*    */     //   956: aload_0
/*    */     //   957: dup
/*    */     //   958: new f/dQ
/*    */     //   961: dup
/*    */     //   962: aload_0
/*    */     //   963: swap
/*    */     //   964: dup
/*    */     //   965: ldc ''
/*    */     //   967: invokespecial <init> : (Ljava/lang/String;)V
/*    */     //   970: putfield aJ : Lf/dQ;
/*    */     //   973: ldc_w 'redlabel'
/*    */     //   976: invokevirtual Xu : (Ljava/lang/String;)V
/*    */     //   979: new f/I50
/*    */     //   982: dup
/*    */     //   983: aload_0
/*    */     //   984: swap
/*    */     //   985: dup
/*    */     //   986: aload_0
/*    */     //   987: getfield EK0 : Lf/dQ;
/*    */     //   990: invokespecial <init> : (Lf/dQ;)V
/*    */     //   993: putfield lC : Lf/I50;
/*    */     //   996: ldc_w 'health-progressbar'
/*    */     //   999: invokevirtual Xu : (Ljava/lang/String;)V
/*    */     //   1002: getfield lC : Lf/I50;
/*    */     //   1005: fconst_1
/*    */     //   1006: invokevirtual Nu : (F)V
/*    */     //   1009: getfield lC : Lf/I50;
/*    */     //   1012: aload #5
/*    */     //   1014: invokevirtual a40 : ()I
/*    */     //   1017: bipush #80
/*    */     //   1019: iadd
/*    */     //   1020: aload #5
/*    */     //   1022: invokevirtual CB : ()I
/*    */     //   1025: bipush #7
/*    */     //   1027: iadd
/*    */     //   1028: invokevirtual Ol0 : (II)V
/*    */     //   1031: invokestatic XU : ()Z
/*    */     //   1034: ifeq -> 1219
/*    */     //   1037: aload_0
/*    */     //   1038: dup
/*    */     //   1039: dup
/*    */     //   1040: new f/vF0
/*    */     //   1043: dup
/*    */     //   1044: dup
/*    */     //   1045: astore_1
/*    */     //   1046: bipush #32
/*    */     //   1048: bipush #32
/*    */     //   1050: invokespecial <init> : (II)V
/*    */     //   1053: putfield sa : Lf/vF0;
/*    */     //   1056: aload_1
/*    */     //   1057: invokevirtual ZH0 : ()Lf/rH;
/*    */     //   1060: iconst_4
/*    */     //   1061: iconst_4
/*    */     //   1062: invokevirtual zT : (II)Lf/JG0;
/*    */     //   1065: pop
/*    */     //   1066: getfield lC : Lf/I50;
/*    */     //   1069: astore_1
/*    */     //   1070: getfield AG : Z
/*    */     //   1073: ifeq -> 1083
/*    */     //   1076: sipush #150
/*    */     //   1079: istore_2
/*    */     //   1080: goto -> 1087
/*    */     //   1083: sipush #200
/*    */     //   1086: istore_2
/*    */     //   1087: aload_0
/*    */     //   1088: dup
/*    */     //   1089: dup
/*    */     //   1090: dup2
/*    */     //   1091: aload_1
/*    */     //   1092: iload_2
/*    */     //   1093: bipush #12
/*    */     //   1095: invokevirtual Tm : (II)Z
/*    */     //   1098: pop
/*    */     //   1099: new f/vF0
/*    */     //   1102: dup
/*    */     //   1103: dup
/*    */     //   1104: astore_1
/*    */     //   1105: bipush #24
/*    */     //   1107: bipush #24
/*    */     //   1109: invokespecial <init> : (II)V
/*    */     //   1112: putfield nf : Lf/vF0;
/*    */     //   1115: aload_1
/*    */     //   1116: invokevirtual ZH0 : ()Lf/rH;
/*    */     //   1119: bipush #24
/*    */     //   1121: bipush #24
/*    */     //   1123: invokevirtual tL : (II)V
/*    */     //   1126: getfield nf : Lf/vF0;
/*    */     //   1129: invokevirtual ZH0 : ()Lf/rH;
/*    */     //   1132: iconst_4
/*    */     //   1133: iconst_4
/*    */     //   1134: invokevirtual zT : (II)Lf/JG0;
/*    */     //   1137: pop
/*    */     //   1138: new f/vF0
/*    */     //   1141: dup
/*    */     //   1142: dup
/*    */     //   1143: astore_1
/*    */     //   1144: bipush #32
/*    */     //   1146: bipush #32
/*    */     //   1148: invokespecial <init> : (II)V
/*    */     //   1151: putfield ji0 : Lf/vF0;
/*    */     //   1154: aload_1
/*    */     //   1155: invokevirtual ZH0 : ()Lf/rH;
/*    */     //   1158: bipush #25
/*    */     //   1160: bipush #22
/*    */     //   1162: invokevirtual tL : (II)V
/*    */     //   1165: getfield ji0 : Lf/vF0;
/*    */     //   1168: invokevirtual ZH0 : ()Lf/rH;
/*    */     //   1171: iconst_4
/*    */     //   1172: bipush #-12
/*    */     //   1174: invokevirtual zT : (II)Lf/JG0;
/*    */     //   1177: pop
/*    */     //   1178: getfield Zu0 : Lf/aU;
/*    */     //   1181: dup
/*    */     //   1182: astore_1
/*    */     //   1183: ifnull -> 1196
/*    */     //   1186: aload_1
/*    */     //   1187: sipush #200
/*    */     //   1190: bipush #10
/*    */     //   1192: invokevirtual Tm : (II)Z
/*    */     //   1195: pop
/*    */     //   1196: aload_0
/*    */     //   1197: getfield ec0 : Lf/vF0;
/*    */     //   1200: dup
/*    */     //   1201: astore_1
/*    */     //   1202: ifnull -> 1365
/*    */     //   1205: aload_1
/*    */     //   1206: invokevirtual ZH0 : ()Lf/rH;
/*    */     //   1209: bipush #32
/*    */     //   1211: bipush #32
/*    */     //   1213: invokevirtual tL : (II)V
/*    */     //   1216: goto -> 1365
/*    */     //   1219: aload_0
/*    */     //   1220: dup
/*    */     //   1221: dup
/*    */     //   1222: new f/vF0
/*    */     //   1225: dup
/*    */     //   1226: bipush #16
/*    */     //   1228: bipush #16
/*    */     //   1230: invokespecial <init> : (II)V
/*    */     //   1233: putfield sa : Lf/vF0;
/*    */     //   1236: getfield lC : Lf/I50;
/*    */     //   1239: astore_1
/*    */     //   1240: getfield AG : Z
/*    */     //   1243: ifeq -> 1253
/*    */     //   1246: sipush #150
/*    */     //   1249: istore_2
/*    */     //   1250: goto -> 1257
/*    */     //   1253: sipush #200
/*    */     //   1256: istore_2
/*    */     //   1257: aload_0
/*    */     //   1258: dup
/*    */     //   1259: dup
/*    */     //   1260: dup2
/*    */     //   1261: aload_1
/*    */     //   1262: iload_2
/*    */     //   1263: bipush #8
/*    */     //   1265: invokevirtual Tm : (II)Z
/*    */     //   1268: pop
/*    */     //   1269: new f/vF0
/*    */     //   1272: dup
/*    */     //   1273: dup
/*    */     //   1274: astore_1
/*    */     //   1275: bipush #16
/*    */     //   1277: bipush #16
/*    */     //   1279: invokespecial <init> : (II)V
/*    */     //   1282: putfield nf : Lf/vF0;
/*    */     //   1285: aload_1
/*    */     //   1286: invokevirtual ZH0 : ()Lf/rH;
/*    */     //   1289: bipush #16
/*    */     //   1291: bipush #16
/*    */     //   1293: invokevirtual tL : (II)V
/*    */     //   1296: getfield nf : Lf/vF0;
/*    */     //   1299: invokevirtual ZH0 : ()Lf/rH;
/*    */     //   1302: iconst_4
/*    */     //   1303: iconst_4
/*    */     //   1304: invokevirtual zT : (II)Lf/JG0;
/*    */     //   1307: pop
/*    */     //   1308: new f/vF0
/*    */     //   1311: dup
/*    */     //   1312: dup
/*    */     //   1313: astore_1
/*    */     //   1314: bipush #16
/*    */     //   1316: bipush #16
/*    */     //   1318: invokespecial <init> : (II)V
/*    */     //   1321: putfield ji0 : Lf/vF0;
/*    */     //   1324: aload_1
/*    */     //   1325: invokevirtual ZH0 : ()Lf/rH;
/*    */     //   1328: bipush #16
/*    */     //   1330: bipush #14
/*    */     //   1332: invokevirtual tL : (II)V
/*    */     //   1335: getfield ji0 : Lf/vF0;
/*    */     //   1338: invokevirtual ZH0 : ()Lf/rH;
/*    */     //   1341: iconst_2
/*    */     //   1342: iconst_2
/*    */     //   1343: invokevirtual zT : (II)Lf/JG0;
/*    */     //   1346: pop
/*    */     //   1347: getfield Zu0 : Lf/aU;
/*    */     //   1350: dup
/*    */     //   1351: astore_1
/*    */     //   1352: ifnull -> 1365
/*    */     //   1355: aload_1
/*    */     //   1356: sipush #200
/*    */     //   1359: bipush #6
/*    */     //   1361: invokevirtual Tm : (II)Z
/*    */     //   1364: pop
/*    */     //   1365: aload_0
/*    */     //   1366: aload_3
/*    */     //   1367: aload_0
/*    */     //   1368: aload_3
/*    */     //   1369: aload #5
/*    */     //   1371: aload_0
/*    */     //   1372: dup
/*    */     //   1373: getfield ji0 : Lf/vF0;
/*    */     //   1376: iconst_0
/*    */     //   1377: invokevirtual wI0 : (Z)V
/*    */     //   1380: getfield nf : Lf/vF0;
/*    */     //   1383: bipush #100
/*    */     //   1385: invokevirtual Pb0 : (I)V
/*    */     //   1388: invokevirtual J8 : (Lf/JG0;)V
/*    */     //   1391: getfield lC : Lf/I50;
/*    */     //   1394: invokevirtual J8 : (Lf/JG0;)V
/*    */     //   1397: getfield Zu0 : Lf/aU;
/*    */     //   1400: dup
/*    */     //   1401: astore_1
/*    */     //   1402: ifnull -> 1410
/*    */     //   1405: aload_3
/*    */     //   1406: aload_1
/*    */     //   1407: invokevirtual J8 : (Lf/JG0;)V
/*    */     //   1410: aload_0
/*    */     //   1411: getfield EK0 : Lf/dQ;
/*    */     //   1414: dup
/*    */     //   1415: astore_1
/*    */     //   1416: ifnull -> 1424
/*    */     //   1419: aload_3
/*    */     //   1420: aload_1
/*    */     //   1421: invokevirtual J8 : (Lf/JG0;)V
/*    */     //   1424: aload_0
/*    */     //   1425: aload_3
/*    */     //   1426: aload_0
/*    */     //   1427: aload_3
/*    */     //   1428: aload_0
/*    */     //   1429: aload_3
/*    */     //   1430: aload_0
/*    */     //   1431: getfield aJ : Lf/dQ;
/*    */     //   1434: invokevirtual J8 : (Lf/JG0;)V
/*    */     //   1437: getfield sa : Lf/vF0;
/*    */     //   1440: invokevirtual J8 : (Lf/JG0;)V
/*    */     //   1443: getfield nf : Lf/vF0;
/*    */     //   1446: invokevirtual J8 : (Lf/JG0;)V
/*    */     //   1449: getfield ec0 : Lf/vF0;
/*    */     //   1452: dup
/*    */     //   1453: astore_1
/*    */     //   1454: ifnull -> 1462
/*    */     //   1457: aload_3
/*    */     //   1458: aload_1
/*    */     //   1459: invokevirtual J8 : (Lf/JG0;)V
/*    */     //   1462: aload_0
/*    */     //   1463: aload_3
/*    */     //   1464: aload_0
/*    */     //   1465: getfield ji0 : Lf/vF0;
/*    */     //   1468: invokevirtual J8 : (Lf/JG0;)V
/*    */     //   1471: iconst_0
/*    */     //   1472: invokevirtual CX : (Z)V
/*    */     //   1475: return } public final void Io0(int paramInt1, int paramInt2, int paramInt3, int paramInt4, boolean paramBoolean) { // Byte code:
/*    */     //   0: iload #5
/*    */     //   2: ifne -> 25
/*    */     //   5: aload_0
/*    */     //   6: dup
/*    */     //   7: dup2
/*    */     //   8: iload_1
/*    */     //   9: putfield pz0 : I
/*    */     //   12: iload_2
/*    */     //   13: putfield Ll : I
/*    */     //   16: iload_3
/*    */     //   17: putfield p9 : I
/*    */     //   20: iload #4
/*    */     //   22: putfield ho0 : I
/*    */     //   25: aload_0
/*    */     //   26: getfield AF : Lf/Gp0;
/*    */     //   29: getfield Ja : Lf/Mn;
/*    */     //   32: getstatic f/Mn.VK : Lf/Mn;
/*    */     //   35: if_acmpne -> 387
/*    */     //   38: invokestatic Nr : ()Z
/*    */     //   41: ifne -> 54
/*    */     //   44: aload_0
/*    */     //   45: getfield AF : Lf/Gp0;
/*    */     //   48: invokevirtual sQ : ()Z
/*    */     //   51: ifeq -> 387
/*    */     //   54: aload_0
/*    */     //   55: iinc #1, -10
/*    */     //   58: getfield u4 : B
/*    */     //   61: tableswitch default -> 100, 0 -> 291, 1 -> 199, 2 -> 103, 3 -> 291, 4 -> 199, 5 -> 103
/*    */     //   100: goto -> 693
/*    */     //   103: aload_0
/*    */     //   104: iload_3
/*    */     //   105: iconst_2
/*    */     //   106: idiv
/*    */     //   107: sipush #130
/*    */     //   110: isub
/*    */     //   111: sipush #260
/*    */     //   114: iadd
/*    */     //   115: iload_1
/*    */     //   116: iadd
/*    */     //   117: istore_1
/*    */     //   118: getfield E : Z
/*    */     //   121: ifeq -> 149
/*    */     //   124: invokestatic XU : ()Z
/*    */     //   127: ifeq -> 137
/*    */     //   130: sipush #320
/*    */     //   133: istore_3
/*    */     //   134: goto -> 141
/*    */     //   137: sipush #190
/*    */     //   140: istore_3
/*    */     //   141: iload #4
/*    */     //   143: iload_3
/*    */     //   144: isub
/*    */     //   145: istore_3
/*    */     //   146: goto -> 152
/*    */     //   149: bipush #75
/*    */     //   151: istore_3
/*    */     //   152: aload_0
/*    */     //   153: dup
/*    */     //   154: getfield u4 : B
/*    */     //   157: istore #4
/*    */     //   159: getfield E : Z
/*    */     //   162: ifeq -> 171
/*    */     //   165: iconst_5
/*    */     //   166: istore #5
/*    */     //   168: goto -> 174
/*    */     //   171: iconst_2
/*    */     //   172: istore #5
/*    */     //   174: iload #4
/*    */     //   176: iload #5
/*    */     //   178: if_icmpne -> 187
/*    */     //   181: iconst_1
/*    */     //   182: istore #4
/*    */     //   184: goto -> 190
/*    */     //   187: iconst_0
/*    */     //   188: istore #4
/*    */     //   190: invokestatic XU : ()Z
/*    */     //   193: ifeq -> 511
/*    */     //   196: goto -> 504
/*    */     //   199: aload_0
/*    */     //   200: iload_3
/*    */     //   201: iconst_2
/*    */     //   202: idiv
/*    */     //   203: sipush #130
/*    */     //   206: isub
/*    */     //   207: iload_1
/*    */     //   208: iadd
/*    */     //   209: istore_1
/*    */     //   210: getfield E : Z
/*    */     //   213: ifeq -> 241
/*    */     //   216: invokestatic XU : ()Z
/*    */     //   219: ifeq -> 229
/*    */     //   222: sipush #320
/*    */     //   225: istore_3
/*    */     //   226: goto -> 233
/*    */     //   229: sipush #190
/*    */     //   232: istore_3
/*    */     //   233: iload #4
/*    */     //   235: iload_3
/*    */     //   236: isub
/*    */     //   237: istore_3
/*    */     //   238: goto -> 244
/*    */     //   241: bipush #75
/*    */     //   243: istore_3
/*    */     //   244: aload_0
/*    */     //   245: dup
/*    */     //   246: getfield u4 : B
/*    */     //   249: istore #4
/*    */     //   251: getfield E : Z
/*    */     //   254: ifeq -> 263
/*    */     //   257: iconst_4
/*    */     //   258: istore #5
/*    */     //   260: goto -> 266
/*    */     //   263: iconst_1
/*    */     //   264: istore #5
/*    */     //   266: iload #4
/*    */     //   268: iload #5
/*    */     //   270: if_icmpne -> 279
/*    */     //   273: iconst_1
/*    */     //   274: istore #4
/*    */     //   276: goto -> 282
/*    */     //   279: iconst_0
/*    */     //   280: istore #4
/*    */     //   282: invokestatic XU : ()Z
/*    */     //   285: ifeq -> 511
/*    */     //   288: goto -> 504
/*    */     //   291: aload_0
/*    */     //   292: iload_3
/*    */     //   293: iconst_2
/*    */     //   294: idiv
/*    */     //   295: sipush #130
/*    */     //   298: isub
/*    */     //   299: sipush #260
/*    */     //   302: isub
/*    */     //   303: iload_1
/*    */     //   304: iadd
/*    */     //   305: istore_1
/*    */     //   306: getfield E : Z
/*    */     //   309: ifeq -> 337
/*    */     //   312: invokestatic XU : ()Z
/*    */     //   315: ifeq -> 325
/*    */     //   318: sipush #320
/*    */     //   321: istore_3
/*    */     //   322: goto -> 329
/*    */     //   325: sipush #190
/*    */     //   328: istore_3
/*    */     //   329: iload #4
/*    */     //   331: iload_3
/*    */     //   332: isub
/*    */     //   333: istore_3
/*    */     //   334: goto -> 340
/*    */     //   337: bipush #75
/*    */     //   339: istore_3
/*    */     //   340: aload_0
/*    */     //   341: dup
/*    */     //   342: getfield u4 : B
/*    */     //   345: istore #4
/*    */     //   347: getfield E : Z
/*    */     //   350: ifeq -> 359
/*    */     //   353: iconst_3
/*    */     //   354: istore #5
/*    */     //   356: goto -> 362
/*    */     //   359: iconst_0
/*    */     //   360: istore #5
/*    */     //   362: iload #4
/*    */     //   364: iload #5
/*    */     //   366: if_icmpne -> 375
/*    */     //   369: iconst_1
/*    */     //   370: istore #4
/*    */     //   372: goto -> 378
/*    */     //   375: iconst_0
/*    */     //   376: istore #4
/*    */     //   378: invokestatic XU : ()Z
/*    */     //   381: ifeq -> 511
/*    */     //   384: goto -> 504
/*    */     //   387: aload_0
/*    */     //   388: getfield E : Z
/*    */     //   391: ifne -> 528
/*    */     //   394: aload_0
/*    */     //   395: getfield AF : Lf/Gp0;
/*    */     //   398: getfield rx : Lf/ky;
/*    */     //   401: getstatic f/ky.We0 : Lf/ky;
/*    */     //   404: if_acmpne -> 528
/*    */     //   407: aload_0
/*    */     //   408: iinc #1, -10
/*    */     //   411: getfield u4 : B
/*    */     //   414: dup
/*    */     //   415: istore #4
/*    */     //   417: iconst_2
/*    */     //   418: if_icmpge -> 453
/*    */     //   421: iload_3
/*    */     //   422: iconst_2
/*    */     //   423: idiv
/*    */     //   424: sipush #130
/*    */     //   427: isub
/*    */     //   428: sipush #260
/*    */     //   431: isub
/*    */     //   432: iload_1
/*    */     //   433: iadd
/*    */     //   434: istore_1
/*    */     //   435: bipush #30
/*    */     //   437: istore_3
/*    */     //   438: iconst_1
/*    */     //   439: iload #4
/*    */     //   441: isub
/*    */     //   442: istore #4
/*    */     //   444: invokestatic XU : ()Z
/*    */     //   447: ifeq -> 511
/*    */     //   450: goto -> 504
/*    */     //   453: iload #4
/*    */     //   455: iconst_2
/*    */     //   456: if_icmpne -> 475
/*    */     //   459: iload_3
/*    */     //   460: iconst_2
/*    */     //   461: idiv
/*    */     //   462: sipush #130
/*    */     //   465: isub
/*    */     //   466: iload_1
/*    */     //   467: iadd
/*    */     //   468: istore_1
/*    */     //   469: iinc #2, 30
/*    */     //   472: goto -> 693
/*    */     //   475: iload #4
/*    */     //   477: iload_3
/*    */     //   478: iconst_2
/*    */     //   479: idiv
/*    */     //   480: sipush #130
/*    */     //   483: isub
/*    */     //   484: sipush #260
/*    */     //   487: iadd
/*    */     //   488: iload_1
/*    */     //   489: iadd
/*    */     //   490: istore_1
/*    */     //   491: bipush #30
/*    */     //   493: istore_3
/*    */     //   494: iconst_3
/*    */     //   495: isub
/*    */     //   496: istore #4
/*    */     //   498: invokestatic XU : ()Z
/*    */     //   501: ifeq -> 511
/*    */     //   504: bipush #60
/*    */     //   506: istore #5
/*    */     //   508: goto -> 515
/*    */     //   511: bipush #40
/*    */     //   513: istore #5
/*    */     //   515: iload #4
/*    */     //   517: iload #5
/*    */     //   519: imul
/*    */     //   520: iload_3
/*    */     //   521: iadd
/*    */     //   522: iload_2
/*    */     //   523: iadd
/*    */     //   524: istore_2
/*    */     //   525: goto -> 693
/*    */     //   528: invokestatic XU : ()Z
/*    */     //   531: ifeq -> 631
/*    */     //   534: aload_0
/*    */     //   535: getfield E : Z
/*    */     //   538: ifeq -> 618
/*    */     //   541: aload_0
/*    */     //   542: getfield GC : Z
/*    */     //   545: ifeq -> 564
/*    */     //   548: aload_0
/*    */     //   549: getfield u4 : B
/*    */     //   552: bipush #60
/*    */     //   554: imul
/*    */     //   555: bipush #60
/*    */     //   557: isub
/*    */     //   558: iload_2
/*    */     //   559: iadd
/*    */     //   560: istore_2
/*    */     //   561: goto -> 693
/*    */     //   564: aload_0
/*    */     //   565: getfield Oq0 : B
/*    */     //   568: dup
/*    */     //   569: istore_3
/*    */     //   570: iconst_1
/*    */     //   571: if_icmpeq -> 608
/*    */     //   574: iload_3
/*    */     //   575: iconst_2
/*    */     //   576: if_icmpeq -> 595
/*    */     //   579: aload_0
/*    */     //   580: getfield u4 : B
/*    */     //   583: iconst_1
/*    */     //   584: isub
/*    */     //   585: bipush #80
/*    */     //   587: imul
/*    */     //   588: bipush #40
/*    */     //   590: isub
/*    */     //   591: istore_3
/*    */     //   592: goto -> 611
/*    */     //   595: aload_0
/*    */     //   596: getfield u4 : B
/*    */     //   599: iconst_1
/*    */     //   600: isub
/*    */     //   601: bipush #80
/*    */     //   603: imul
/*    */     //   604: istore_3
/*    */     //   605: goto -> 611
/*    */     //   608: bipush #-40
/*    */     //   610: istore_3
/*    */     //   611: iload_2
/*    */     //   612: iload_3
/*    */     //   613: iadd
/*    */     //   614: istore_2
/*    */     //   615: goto -> 693
/*    */     //   618: aload_0
/*    */     //   619: getfield u4 : B
/*    */     //   622: bipush #60
/*    */     //   624: imul
/*    */     //   625: iload_2
/*    */     //   626: iadd
/*    */     //   627: istore_2
/*    */     //   628: goto -> 693
/*    */     //   631: invokestatic Nr : ()Z
/*    */     //   634: ifeq -> 693
/*    */     //   637: aload_0
/*    */     //   638: getfield E : Z
/*    */     //   641: ifeq -> 683
/*    */     //   644: aload_0
/*    */     //   645: getfield GC : Z
/*    */     //   648: ifeq -> 667
/*    */     //   651: aload_0
/*    */     //   652: getfield u4 : B
/*    */     //   655: bipush #40
/*    */     //   657: imul
/*    */     //   658: bipush #40
/*    */     //   660: isub
/*    */     //   661: iload_2
/*    */     //   662: iadd
/*    */     //   663: istore_2
/*    */     //   664: goto -> 693
/*    */     //   667: aload_0
/*    */     //   668: getfield u4 : B
/*    */     //   671: bipush #55
/*    */     //   673: imul
/*    */     //   674: bipush #55
/*    */     //   676: isub
/*    */     //   677: iload_2
/*    */     //   678: iadd
/*    */     //   679: istore_2
/*    */     //   680: goto -> 693
/*    */     //   683: aload_0
/*    */     //   684: getfield u4 : B
/*    */     //   687: bipush #40
/*    */     //   689: imul
/*    */     //   690: iload_2
/*    */     //   691: iadd
/*    */     //   692: istore_2
/*    */     //   693: aload_0
/*    */     //   694: dup
/*    */     //   695: dup
/*    */     //   696: dup2
/*    */     //   697: getfield vO : Lf/JG0;
/*    */     //   700: iload_1
/*    */     //   701: iload_2
/*    */     //   702: invokevirtual ME : (II)Z
/*    */     //   705: pop
/*    */     //   706: getfield aJ : Lf/dQ;
/*    */     //   709: invokevirtual Td0 : ()I
/*    */     //   712: istore_3
/*    */     //   713: getfield aJ : Lf/dQ;
/*    */     //   716: invokevirtual n70 : ()I
/*    */     //   719: istore #4
/*    */     //   721: getfield aJ : Lf/dQ;
/*    */     //   724: iload_3
/*    */     //   725: iload #4
/*    */     //   727: invokevirtual uh0 : (II)V
/*    */     //   730: getfield aJ : Lf/dQ;
/*    */     //   733: iload_3
/*    */     //   734: iload #4
/*    */     //   736: invokevirtual Tm : (II)Z
/*    */     //   739: pop
/*    */     //   740: invokestatic XU : ()Z
/*    */     //   743: ifeq -> 1247
/*    */     //   746: aload_0
/*    */     //   747: getfield E : Z
/*    */     //   750: ifeq -> 1001
/*    */     //   753: aload_0
/*    */     //   754: dup
/*    */     //   755: dup
/*    */     //   756: getfield aJ : Lf/dQ;
/*    */     //   759: dup
/*    */     //   760: iload_2
/*    */     //   761: swap
/*    */     //   762: iload_1
/*    */     //   763: bipush #50
/*    */     //   765: iadd
/*    */     //   766: istore #4
/*    */     //   768: getfield HC : I
/*    */     //   771: i2d
/*    */     //   772: ldc2_w 1.7
/*    */     //   775: ddiv
/*    */     //   776: d2i
/*    */     //   777: isub
/*    */     //   778: iload #4
/*    */     //   780: swap
/*    */     //   781: invokevirtual ME : (II)Z
/*    */     //   784: pop
/*    */     //   785: getfield lC : Lf/I50;
/*    */     //   788: astore #4
/*    */     //   790: getfield li : Z
/*    */     //   793: dup
/*    */     //   794: istore #5
/*    */     //   796: ifne -> 806
/*    */     //   799: bipush #88
/*    */     //   801: istore #6
/*    */     //   803: goto -> 810
/*    */     //   806: bipush #72
/*    */     //   808: istore #6
/*    */     //   810: iload #5
/*    */     //   812: iload_1
/*    */     //   813: iload #6
/*    */     //   815: iadd
/*    */     //   816: istore #5
/*    */     //   818: ifne -> 828
/*    */     //   821: bipush #11
/*    */     //   823: istore #6
/*    */     //   825: goto -> 832
/*    */     //   828: bipush #12
/*    */     //   830: istore #6
/*    */     //   832: aload_0
/*    */     //   833: dup
/*    */     //   834: aload #4
/*    */     //   836: iload #5
/*    */     //   838: iload_2
/*    */     //   839: iload #6
/*    */     //   841: iadd
/*    */     //   842: invokevirtual ME : (II)Z
/*    */     //   845: pop
/*    */     //   846: getfield nf : Lf/vF0;
/*    */     //   849: iload_2
/*    */     //   850: iload_1
/*    */     //   851: bipush #18
/*    */     //   853: iadd
/*    */     //   854: istore #4
/*    */     //   856: bipush #21
/*    */     //   858: isub
/*    */     //   859: iload #4
/*    */     //   861: swap
/*    */     //   862: invokevirtual ME : (II)Z
/*    */     //   865: pop
/*    */     //   866: getfield Zu0 : Lf/aU;
/*    */     //   869: dup
/*    */     //   870: astore #4
/*    */     //   872: ifnull -> 891
/*    */     //   875: aload #4
/*    */     //   877: iload_1
/*    */     //   878: bipush #86
/*    */     //   880: iadd
/*    */     //   881: iload_2
/*    */     //   882: bipush #57
/*    */     //   884: iadd
/*    */     //   885: swap
/*    */     //   886: swap
/*    */     //   887: invokevirtual ME : (II)Z
/*    */     //   890: pop
/*    */     //   891: aload_0
/*    */     //   892: getfield EK0 : Lf/dQ;
/*    */     //   895: dup
/*    */     //   896: astore #4
/*    */     //   898: ifnull -> 925
/*    */     //   901: aload_0
/*    */     //   902: aload #4
/*    */     //   904: iload_1
/*    */     //   905: bipush #80
/*    */     //   907: iadd
/*    */     //   908: iload_2
/*    */     //   909: bipush #38
/*    */     //   911: iadd
/*    */     //   912: invokevirtual ME : (II)Z
/*    */     //   915: pop
/*    */     //   916: getfield EK0 : Lf/dQ;
/*    */     //   919: getstatic f/et.Wi0 : Lf/et;
/*    */     //   922: invokevirtual C70 : (Lf/et;)V
/*    */     //   925: aload_0
/*    */     //   926: getfield sa : Lf/vF0;
/*    */     //   929: getfield TS : Lf/rH;
/*    */     //   932: invokevirtual e00 : ()I
/*    */     //   935: ifle -> 982
/*    */     //   938: aload_0
/*    */     //   939: dup
/*    */     //   940: dup
/*    */     //   941: getfield sa : Lf/vF0;
/*    */     //   944: iload_2
/*    */     //   945: iload_1
/*    */     //   946: bipush #45
/*    */     //   948: iadd
/*    */     //   949: iload_3
/*    */     //   950: iadd
/*    */     //   951: istore_0
/*    */     //   952: bipush #25
/*    */     //   954: isub
/*    */     //   955: iload_0
/*    */     //   956: swap
/*    */     //   957: invokevirtual ME : (II)Z
/*    */     //   960: pop
/*    */     //   961: getfield ji0 : Lf/vF0;
/*    */     //   964: astore_0
/*    */     //   965: getfield sa : Lf/vF0;
/*    */     //   968: dup
/*    */     //   969: getfield Kd : I
/*    */     //   972: bipush #28
/*    */     //   974: iadd
/*    */     //   975: istore_1
/*    */     //   976: getfield er0 : I
/*    */     //   979: goto -> 1130
/*    */     //   982: iload_2
/*    */     //   983: iload_1
/*    */     //   984: aload_0
/*    */     //   985: getfield ji0 : Lf/vF0;
/*    */     //   988: astore_0
/*    */     //   989: bipush #52
/*    */     //   991: iadd
/*    */     //   992: iload_3
/*    */     //   993: iadd
/*    */     //   994: istore_1
/*    */     //   995: iconst_3
/*    */     //   996: isub
/*    */     //   997: istore_2
/*    */     //   998: goto -> 1654
/*    */     //   1001: aload_0
/*    */     //   1002: dup
/*    */     //   1003: dup
/*    */     //   1004: dup2
/*    */     //   1005: getfield aJ : Lf/dQ;
/*    */     //   1008: dup
/*    */     //   1009: iload_2
/*    */     //   1010: swap
/*    */     //   1011: iload_1
/*    */     //   1012: bipush #45
/*    */     //   1014: iadd
/*    */     //   1015: istore #4
/*    */     //   1017: getfield HC : I
/*    */     //   1020: i2d
/*    */     //   1021: ldc2_w 1.7
/*    */     //   1024: ddiv
/*    */     //   1025: d2i
/*    */     //   1026: isub
/*    */     //   1027: iload #4
/*    */     //   1029: swap
/*    */     //   1030: invokevirtual ME : (II)Z
/*    */     //   1033: pop
/*    */     //   1034: getfield sa : Lf/vF0;
/*    */     //   1037: iload_2
/*    */     //   1038: iload_1
/*    */     //   1039: bipush #40
/*    */     //   1041: iadd
/*    */     //   1042: iload_3
/*    */     //   1043: iadd
/*    */     //   1044: istore #4
/*    */     //   1046: bipush #25
/*    */     //   1048: isub
/*    */     //   1049: iload #4
/*    */     //   1051: swap
/*    */     //   1052: invokevirtual ME : (II)Z
/*    */     //   1055: pop
/*    */     //   1056: getfield lC : Lf/I50;
/*    */     //   1059: iload_1
/*    */     //   1060: bipush #72
/*    */     //   1062: iadd
/*    */     //   1063: iload_2
/*    */     //   1064: bipush #12
/*    */     //   1066: iadd
/*    */     //   1067: invokevirtual ME : (II)Z
/*    */     //   1070: pop
/*    */     //   1071: getfield nf : Lf/vF0;
/*    */     //   1074: iload_2
/*    */     //   1075: iload_1
/*    */     //   1076: bipush #11
/*    */     //   1078: iadd
/*    */     //   1079: istore #4
/*    */     //   1081: bipush #21
/*    */     //   1083: isub
/*    */     //   1084: iload #4
/*    */     //   1086: swap
/*    */     //   1087: invokevirtual ME : (II)Z
/*    */     //   1090: pop
/*    */     //   1091: getfield ec0 : Lf/vF0;
/*    */     //   1094: ifnonnull -> 1156
/*    */     //   1097: aload_0
/*    */     //   1098: getfield sa : Lf/vF0;
/*    */     //   1101: getfield TS : Lf/rH;
/*    */     //   1104: invokevirtual e00 : ()I
/*    */     //   1107: ifle -> 1137
/*    */     //   1110: aload_0
/*    */     //   1111: dup
/*    */     //   1112: getfield ji0 : Lf/vF0;
/*    */     //   1115: astore_0
/*    */     //   1116: getfield sa : Lf/vF0;
/*    */     //   1119: dup
/*    */     //   1120: getfield Kd : I
/*    */     //   1123: bipush #28
/*    */     //   1125: iadd
/*    */     //   1126: istore_1
/*    */     //   1127: getfield er0 : I
/*    */     //   1130: bipush #21
/*    */     //   1132: iadd
/*    */     //   1133: istore_2
/*    */     //   1134: goto -> 1654
/*    */     //   1137: iload_2
/*    */     //   1138: iload_1
/*    */     //   1139: aload_0
/*    */     //   1140: getfield ji0 : Lf/vF0;
/*    */     //   1143: astore_0
/*    */     //   1144: bipush #50
/*    */     //   1146: iadd
/*    */     //   1147: iload_3
/*    */     //   1148: iadd
/*    */     //   1149: istore_1
/*    */     //   1150: iconst_3
/*    */     //   1151: isub
/*    */     //   1152: istore_2
/*    */     //   1153: goto -> 1654
/*    */     //   1156: aload_0
/*    */     //   1157: getfield sa : Lf/vF0;
/*    */     //   1160: getfield TS : Lf/rH;
/*    */     //   1163: invokevirtual e00 : ()I
/*    */     //   1166: ifle -> 1199
/*    */     //   1169: aload_0
/*    */     //   1170: getfield ec0 : Lf/vF0;
/*    */     //   1173: aload_0
/*    */     //   1174: getfield sa : Lf/vF0;
/*    */     //   1177: dup
/*    */     //   1178: astore_1
/*    */     //   1179: getfield Kd : I
/*    */     //   1182: bipush #25
/*    */     //   1184: iadd
/*    */     //   1185: aload_1
/*    */     //   1186: getfield er0 : I
/*    */     //   1189: bipush #7
/*    */     //   1191: isub
/*    */     //   1192: invokevirtual ME : (II)Z
/*    */     //   1195: pop
/*    */     //   1196: goto -> 1220
/*    */     //   1199: aload_0
/*    */     //   1200: getfield ec0 : Lf/vF0;
/*    */     //   1203: iload_2
/*    */     //   1204: iload_1
/*    */     //   1205: bipush #50
/*    */     //   1207: iadd
/*    */     //   1208: iload_3
/*    */     //   1209: iadd
/*    */     //   1210: istore_1
/*    */     //   1211: bipush #34
/*    */     //   1213: isub
/*    */     //   1214: iload_1
/*    */     //   1215: swap
/*    */     //   1216: invokevirtual ME : (II)Z
/*    */     //   1219: pop
/*    */     //   1220: aload_0
/*    */     //   1221: dup
/*    */     //   1222: getfield ji0 : Lf/vF0;
/*    */     //   1225: astore_0
/*    */     //   1226: getfield ec0 : Lf/vF0;
/*    */     //   1229: dup
/*    */     //   1230: getfield Kd : I
/*    */     //   1233: bipush #38
/*    */     //   1235: iadd
/*    */     //   1236: istore_1
/*    */     //   1237: getfield er0 : I
/*    */     //   1240: bipush #28
/*    */     //   1242: iadd
/*    */     //   1243: istore_2
/*    */     //   1244: goto -> 1654
/*    */     //   1247: invokestatic Nr : ()Z
/*    */     //   1250: ifeq -> 1755
/*    */     //   1253: aload_0
/*    */     //   1254: getfield E : Z
/*    */     //   1257: ifeq -> 1484
/*    */     //   1260: aload_0
/*    */     //   1261: dup
/*    */     //   1262: dup
/*    */     //   1263: getfield aJ : Lf/dQ;
/*    */     //   1266: dup
/*    */     //   1267: iload_2
/*    */     //   1268: iload_1
/*    */     //   1269: bipush #65
/*    */     //   1271: iadd
/*    */     //   1272: istore #4
/*    */     //   1274: iconst_1
/*    */     //   1275: isub
/*    */     //   1276: swap
/*    */     //   1277: getfield HC : I
/*    */     //   1280: iconst_2
/*    */     //   1281: idiv
/*    */     //   1282: isub
/*    */     //   1283: iload #4
/*    */     //   1285: swap
/*    */     //   1286: invokevirtual ME : (II)Z
/*    */     //   1289: pop
/*    */     //   1290: getfield lC : Lf/I50;
/*    */     //   1293: astore #5
/*    */     //   1295: iload_1
/*    */     //   1296: bipush #80
/*    */     //   1298: iadd
/*    */     //   1299: istore #6
/*    */     //   1301: getfield li : Z
/*    */     //   1304: ifne -> 1314
/*    */     //   1307: bipush #8
/*    */     //   1309: istore #7
/*    */     //   1311: goto -> 1318
/*    */     //   1314: bipush #9
/*    */     //   1316: istore #7
/*    */     //   1318: aload_0
/*    */     //   1319: dup
/*    */     //   1320: aload #5
/*    */     //   1322: iload #6
/*    */     //   1324: iload_2
/*    */     //   1325: iload #7
/*    */     //   1327: iadd
/*    */     //   1328: invokevirtual ME : (II)Z
/*    */     //   1331: pop
/*    */     //   1332: getfield nf : Lf/vF0;
/*    */     //   1335: iload_2
/*    */     //   1336: iload_1
/*    */     //   1337: bipush #40
/*    */     //   1339: iadd
/*    */     //   1340: istore #5
/*    */     //   1342: bipush #15
/*    */     //   1344: isub
/*    */     //   1345: iload #5
/*    */     //   1347: swap
/*    */     //   1348: invokevirtual ME : (II)Z
/*    */     //   1351: pop
/*    */     //   1352: getfield Zu0 : Lf/aU;
/*    */     //   1355: dup
/*    */     //   1356: astore #5
/*    */     //   1358: ifnull -> 1374
/*    */     //   1361: aload #5
/*    */     //   1363: iload_2
/*    */     //   1364: bipush #41
/*    */     //   1366: iadd
/*    */     //   1367: iload #6
/*    */     //   1369: swap
/*    */     //   1370: invokevirtual ME : (II)Z
/*    */     //   1373: pop
/*    */     //   1374: aload_0
/*    */     //   1375: getfield EK0 : Lf/dQ;
/*    */     //   1378: dup
/*    */     //   1379: astore #5
/*    */     //   1381: ifnull -> 1406
/*    */     //   1384: aload_0
/*    */     //   1385: aload #5
/*    */     //   1387: iload #6
/*    */     //   1389: iload_2
/*    */     //   1390: bipush #28
/*    */     //   1392: iadd
/*    */     //   1393: invokevirtual ME : (II)Z
/*    */     //   1396: pop
/*    */     //   1397: getfield EK0 : Lf/dQ;
/*    */     //   1400: getstatic f/et.Wi0 : Lf/et;
/*    */     //   1403: invokevirtual C70 : (Lf/et;)V
/*    */     //   1406: aload_0
/*    */     //   1407: getfield sa : Lf/vF0;
/*    */     //   1410: getfield TS : Lf/rH;
/*    */     //   1413: invokevirtual e00 : ()I
/*    */     //   1416: ifle -> 1459
/*    */     //   1419: aload_0
/*    */     //   1420: dup
/*    */     //   1421: dup
/*    */     //   1422: getfield sa : Lf/vF0;
/*    */     //   1425: iload_2
/*    */     //   1426: iload #4
/*    */     //   1428: iload_3
/*    */     //   1429: iadd
/*    */     //   1430: istore_0
/*    */     //   1431: bipush #12
/*    */     //   1433: isub
/*    */     //   1434: iload_0
/*    */     //   1435: swap
/*    */     //   1436: invokevirtual ME : (II)Z
/*    */     //   1439: pop
/*    */     //   1440: getfield ji0 : Lf/vF0;
/*    */     //   1443: astore_0
/*    */     //   1444: getfield sa : Lf/vF0;
/*    */     //   1447: dup
/*    */     //   1448: astore_1
/*    */     //   1449: getfield Kd : I
/*    */     //   1452: bipush #14
/*    */     //   1454: iadd
/*    */     //   1455: istore_2
/*    */     //   1456: goto -> 1625
/*    */     //   1459: aload_0
/*    */     //   1460: iload_1
/*    */     //   1461: iload_3
/*    */     //   1462: aload_0
/*    */     //   1463: getfield ji0 : Lf/vF0;
/*    */     //   1466: astore_0
/*    */     //   1467: iadd
/*    */     //   1468: bipush #65
/*    */     //   1470: iadd
/*    */     //   1471: istore_1
/*    */     //   1472: getfield aJ : Lf/dQ;
/*    */     //   1475: getfield er0 : I
/*    */     //   1478: iconst_1
/*    */     //   1479: isub
/*    */     //   1480: istore_2
/*    */     //   1481: goto -> 1654
/*    */     //   1484: aload_0
/*    */     //   1485: dup
/*    */     //   1486: dup2
/*    */     //   1487: getfield aJ : Lf/dQ;
/*    */     //   1490: dup
/*    */     //   1491: iload_2
/*    */     //   1492: iload_1
/*    */     //   1493: bipush #50
/*    */     //   1495: iadd
/*    */     //   1496: istore #4
/*    */     //   1498: iconst_1
/*    */     //   1499: isub
/*    */     //   1500: swap
/*    */     //   1501: getfield HC : I
/*    */     //   1504: iconst_2
/*    */     //   1505: idiv
/*    */     //   1506: isub
/*    */     //   1507: iload #4
/*    */     //   1509: swap
/*    */     //   1510: invokevirtual ME : (II)Z
/*    */     //   1513: pop
/*    */     //   1514: getfield lC : Lf/I50;
/*    */     //   1517: iload_1
/*    */     //   1518: bipush #70
/*    */     //   1520: iadd
/*    */     //   1521: iload_2
/*    */     //   1522: bipush #9
/*    */     //   1524: iadd
/*    */     //   1525: invokevirtual ME : (II)Z
/*    */     //   1528: pop
/*    */     //   1529: getfield nf : Lf/vF0;
/*    */     //   1532: iload_2
/*    */     //   1533: iload_1
/*    */     //   1534: bipush #60
/*    */     //   1536: iadd
/*    */     //   1537: bipush #36
/*    */     //   1539: isub
/*    */     //   1540: istore #4
/*    */     //   1542: bipush #15
/*    */     //   1544: isub
/*    */     //   1545: iload #4
/*    */     //   1547: swap
/*    */     //   1548: invokevirtual ME : (II)Z
/*    */     //   1551: pop
/*    */     //   1552: getfield sa : Lf/vF0;
/*    */     //   1555: getfield TS : Lf/rH;
/*    */     //   1558: invokevirtual e00 : ()I
/*    */     //   1561: ifle -> 1587
/*    */     //   1564: aload_0
/*    */     //   1565: getfield sa : Lf/vF0;
/*    */     //   1568: iload_2
/*    */     //   1569: iload_1
/*    */     //   1570: bipush #52
/*    */     //   1572: iadd
/*    */     //   1573: iload_3
/*    */     //   1574: iadd
/*    */     //   1575: istore #4
/*    */     //   1577: bipush #12
/*    */     //   1579: isub
/*    */     //   1580: iload #4
/*    */     //   1582: swap
/*    */     //   1583: invokevirtual ME : (II)Z
/*    */     //   1586: pop
/*    */     //   1587: aload_0
/*    */     //   1588: getfield ec0 : Lf/vF0;
/*    */     //   1591: ifnonnull -> 1664
/*    */     //   1594: aload_0
/*    */     //   1595: getfield sa : Lf/vF0;
/*    */     //   1598: getfield TS : Lf/rH;
/*    */     //   1601: invokevirtual e00 : ()I
/*    */     //   1604: ifle -> 1637
/*    */     //   1607: aload_0
/*    */     //   1608: dup
/*    */     //   1609: getfield ji0 : Lf/vF0;
/*    */     //   1612: astore_0
/*    */     //   1613: getfield sa : Lf/vF0;
/*    */     //   1616: dup
/*    */     //   1617: astore_1
/*    */     //   1618: getfield Kd : I
/*    */     //   1621: bipush #15
/*    */     //   1623: iadd
/*    */     //   1624: istore_2
/*    */     //   1625: aload_1
/*    */     //   1626: getfield er0 : I
/*    */     //   1629: istore_1
/*    */     //   1630: iload_2
/*    */     //   1631: iload_1
/*    */     //   1632: istore_2
/*    */     //   1633: istore_1
/*    */     //   1634: goto -> 1654
/*    */     //   1637: iload_2
/*    */     //   1638: iload_1
/*    */     //   1639: aload_0
/*    */     //   1640: getfield ji0 : Lf/vF0;
/*    */     //   1643: astore_0
/*    */     //   1644: bipush #55
/*    */     //   1646: iadd
/*    */     //   1647: iload_3
/*    */     //   1648: iadd
/*    */     //   1649: istore_1
/*    */     //   1650: bipush #12
/*    */     //   1652: isub
/*    */     //   1653: istore_2
/*    */     //   1654: aload_0
/*    */     //   1655: iload_1
/*    */     //   1656: iload_2
/*    */     //   1657: invokevirtual ME : (II)Z
/*    */     //   1660: pop
/*    */     //   1661: goto -> 1755
/*    */     //   1664: aload_0
/*    */     //   1665: getfield sa : Lf/vF0;
/*    */     //   1668: getfield TS : Lf/rH;
/*    */     //   1671: invokevirtual e00 : ()I
/*    */     //   1674: ifle -> 1707
/*    */     //   1677: aload_0
/*    */     //   1678: getfield ec0 : Lf/vF0;
/*    */     //   1681: aload_0
/*    */     //   1682: getfield sa : Lf/vF0;
/*    */     //   1685: dup
/*    */     //   1686: astore_1
/*    */     //   1687: getfield Kd : I
/*    */     //   1690: bipush #12
/*    */     //   1692: iadd
/*    */     //   1693: aload_1
/*    */     //   1694: getfield er0 : I
/*    */     //   1697: bipush #7
/*    */     //   1699: isub
/*    */     //   1700: invokevirtual ME : (II)Z
/*    */     //   1703: pop
/*    */     //   1704: goto -> 1728
/*    */     //   1707: aload_0
/*    */     //   1708: getfield ec0 : Lf/vF0;
/*    */     //   1711: iload_2
/*    */     //   1712: iload_1
/*    */     //   1713: bipush #55
/*    */     //   1715: iadd
/*    */     //   1716: iload_3
/*    */     //   1717: iadd
/*    */     //   1718: istore_1
/*    */     //   1719: bipush #19
/*    */     //   1721: isub
/*    */     //   1722: iload_1
/*    */     //   1723: swap
/*    */     //   1724: invokevirtual ME : (II)Z
/*    */     //   1727: pop
/*    */     //   1728: aload_0
/*    */     //   1729: dup
/*    */     //   1730: getfield ji0 : Lf/vF0;
/*    */     //   1733: astore_0
/*    */     //   1734: getfield ec0 : Lf/vF0;
/*    */     //   1737: dup
/*    */     //   1738: getfield Kd : I
/*    */     //   1741: bipush #22
/*    */     //   1743: iadd
/*    */     //   1744: istore_1
/*    */     //   1745: getfield er0 : I
/*    */     //   1748: bipush #6
/*    */     //   1750: iadd
/*    */     //   1751: istore_2
/*    */     //   1752: goto -> 1654
/*    */     //   1755: return
/*    */     // Line number table:
/*    */     //   Java source line number -> byte code offset
/*    */     //   #1	-> 29
/*    */     //   #2	-> 32
/*    */     //   #3	-> 398
/*    */     //   #4	-> 401
/*    */     //   #5	-> 702
/*    */     //   #6	-> 706
/*    */     //   #7	-> 768
/*    */     //   #8	-> 781
/*    */     //   #9	-> 785
/*    */     //   #10	-> 842
/*    */     //   #11	-> 846
/*    */     //   #12	-> 862
/*    */     //   #13	-> 866
/*    */     //   #14	-> 887
/*    */     //   #15	-> 892
/*    */     //   #16	-> 912
/*    */     //   #17	-> 916
/*    */     //   #18	-> 929
/*    */     //   #19	-> 932
/*    */     //   #20	-> 957
/*    */     //   #21	-> 961
/*    */     //   #22	-> 969
/*    */     //   #23	-> 976
/*    */     //   #24	-> 985
/*    */     //   #25	-> 1017
/*    */     //   #26	-> 1030
/*    */     //   #27	-> 1034
/*    */     //   #28	-> 1052
/*    */     //   #29	-> 1056
/*    */     //   #30	-> 1067
/*    */     //   #31	-> 1071
/*    */     //   #32	-> 1087
/*    */     //   #33	-> 1091
/*    */     //   #34	-> 1101
/*    */     //   #35	-> 1104
/*    */     //   #36	-> 1120
/*    */     //   #37	-> 1127
/*    */     //   #38	-> 1140
/*    */     //   #39	-> 1160
/*    */     //   #40	-> 1163
/*    */     //   #41	-> 1179
/*    */     //   #42	-> 1186
/*    */     //   #43	-> 1192
/*    */     //   #44	-> 1200
/*    */     //   #45	-> 1216
/*    */     //   #46	-> 1222
/*    */     //   #47	-> 1230
/*    */     //   #48	-> 1237
/*    */     //   #49	-> 1247
/*    */     //   #50	-> 1277
/*    */     //   #51	-> 1281
/*    */     //   #52	-> 1286
/*    */     //   #53	-> 1290
/*    */     //   #54	-> 1328
/*    */     //   #55	-> 1332
/*    */     //   #56	-> 1348
/*    */     //   #57	-> 1352
/*    */     //   #58	-> 1370
/*    */     //   #59	-> 1375
/*    */     //   #60	-> 1393
/*    */     //   #61	-> 1397
/*    */     //   #62	-> 1410
/*    */     //   #63	-> 1413
/*    */     //   #64	-> 1436
/*    */     //   #65	-> 1440
/*    */     //   #66	-> 1449
/*    */     //   #67	-> 1463
/*    */     //   #68	-> 1475
/*    */     //   #69	-> 1487
/*    */     //   #70	-> 1501
/*    */     //   #71	-> 1505
/*    */     //   #72	-> 1510
/*    */     //   #73	-> 1514
/*    */     //   #74	-> 1525
/*    */     //   #75	-> 1529
/*    */     //   #76	-> 1548
/*    */     //   #77	-> 1552
/*    */     //   #78	-> 1555
/*    */     //   #79	-> 1558
/*    */     //   #80	-> 1583
/*    */     //   #81	-> 1588
/*    */     //   #82	-> 1598
/*    */     //   #83	-> 1601
/*    */     //   #84	-> 1618
/*    */     //   #85	-> 1626
/*    */     //   #86	-> 1640
/*    */     //   #87	-> 1657
/*    */     //   #88	-> 1665
/*    */     //   #89	-> 1668
/*    */     //   #90	-> 1671
/*    */     //   #91	-> 1687
/*    */     //   #92	-> 1694
/*    */     //   #93	-> 1700
/*    */     //   #94	-> 1708
/*    */     //   #95	-> 1724
/*    */     //   #96	-> 1730
/*    */     //   #97	-> 1738
/* 45 */     //   #98	-> 1745 } public final void CX(boolean paramBoolean) { this.lC.wI0(paramBoolean); dQ dQ1; if ((dQ1 = this.EK0) != null) dQ1.wI0(paramBoolean);  aU aU1; if ((aU1 = this.Zu0) != null) aU1.wI0(paramBoolean);  this.vO.wI0(paramBoolean); this.aJ.wI0(paramBoolean); this.sa.wI0(paramBoolean); this.nf.wI0(paramBoolean); vF0 vF01; if (!this.E && (vF01 = this.ec0) != null) vF01.wI0(paramBoolean);  hm0 hm01; if ((hm01 = this.oN) != null && ((hm01.K0.y6 > 0))) { this.ji0.wI0(paramBoolean); this.ji0.TS.sm(new zh0[] { (h90.Kw0()).e1 }); } else { this.ji0.wI0(false); this.ji0.TS.H(); }  } public final void Cg0(hm0 paramhm0) { if (paramhm0 == null || km.MR == null) { this.nf
/* 46 */         .TS
/* 47 */         .H(); this.nf
/* 48 */         .z4 = null;
/* 49 */       this.nf.zn();
/*    */       return; }
/*    */     
/*    */     byte b;
/*    */     if ((b = Q90.Ft(paramhm0.K0.K())) != Byte.MIN_VALUE) {
/*    */       if (b != 16) {
/*    */         if (b != 32) {
/*    */           if (b != 64) {
/*    */             if (b != 7) {
/*    */               if (b != 8) {
/*    */                 this.nf.TS.H();
/*    */                 this.nf.z4 = null;
/*    */                 this.nf.zn();
/*    */               } else {
/*    */                 this.nf.z4 = Ml0.OH0(5221);
/*    */                 this.nf.zn();
/*    */                 this.nf.TS.Pn(new pe0[] { interface.ZZ().zk0((byte)8) });
/*    */               } 
/*    */             } else {
/*    */               this.nf.z4 = Ml0.OH0(5220);
/*    */               this.nf.zn();
/*    */               this.nf.TS.Pn(new pe0[] { interface.ZZ().zk0((byte)7) });
/*    */             } 
/*    */           } else {
/*    */             this.nf.z4 = Ml0.OH0(5224);
/*    */             this.nf.zn();
/*    */             this.nf.TS.Pn(new pe0[] { interface.ZZ().zk0((byte)64) });
/*    */           } 
/*    */         } else {
/*    */           this.nf.z4 = Ml0.OH0(5223);
/*    */           this.nf.zn();
/*    */           this.nf.TS.Pn(new pe0[] { interface.ZZ().zk0((byte)32) });
/*    */         } 
/*    */       } else {
/*    */         this.nf.z4 = Ml0.OH0(5222);
/*    */         this.nf.zn();
/*    */         this.nf.TS.Pn(new pe0[] { interface.ZZ().zk0((byte)16) });
/*    */       } 
/*    */     } else {
/*    */       this.nf.z4 = Ml0.OH0(5225);
/*    */       this.nf.zn();
/*    */       this.nf.TS.Pn(new pe0[] { interface.ZZ().zk0(-128) });
/*    */     } 
/*    */     String str = rG0.P70(this.AF, paramhm0.RN, false);
/*    */     this.aJ.z4 = this;
/*    */     this.aJ.zn();
/*    */     this.Or.DQ(paramhm0.RN); }
/*    */ 
/*    */   
/*    */   public final int lpt9() {
/*    */     return this.lC.wg0;
/*    */   }
/*    */   
/*    */   public final void bd() {
/*    */     // Byte code:
/*    */     //   0: aload_0
/*    */     //   1: getfield oN : Lf/hm0;
/*    */     //   4: dup
/*    */     //   5: astore_1
/*    */     //   6: ifnull -> 35
/*    */     //   9: aload_1
/*    */     //   10: getfield K0 : Lf/jd0;
/*    */     //   13: getfield y6 : S
/*    */     //   16: ifle -> 24
/*    */     //   19: iconst_1
/*    */     //   20: istore_2
/*    */     //   21: goto -> 26
/*    */     //   24: iconst_0
/*    */     //   25: istore_2
/*    */     //   26: iload_2
/*    */     //   27: ifeq -> 35
/*    */     //   30: iconst_1
/*    */     //   31: istore_2
/*    */     //   32: goto -> 37
/*    */     //   35: iconst_0
/*    */     //   36: istore_2
/*    */     //   37: aload_1
/*    */     //   38: ifnull -> 94
/*    */     //   41: aload_1
/*    */     //   42: getfield K0 : Lf/jd0;
/*    */     //   45: getfield y6 : S
/*    */     //   48: ifle -> 55
/*    */     //   51: iconst_1
/*    */     //   52: goto -> 56
/*    */     //   55: iconst_0
/*    */     //   56: ifeq -> 94
/*    */     //   59: aload_0
/*    */     //   60: dup
/*    */     //   61: getfield ji0 : Lf/vF0;
/*    */     //   64: iload_2
/*    */     //   65: invokevirtual wI0 : (Z)V
/*    */     //   68: getfield ji0 : Lf/vF0;
/*    */     //   71: getfield TS : Lf/rH;
/*    */     //   74: iconst_1
/*    */     //   75: anewarray f/zh0
/*    */     //   78: dup
/*    */     //   79: invokestatic Kw0 : ()Lf/h90;
/*    */     //   82: getfield e1 : Lf/zh0;
/*    */     //   85: iconst_0
/*    */     //   86: swap
/*    */     //   87: aastore
/*    */     //   88: invokevirtual sm : ([Lf/zh0;)V
/*    */     //   91: goto -> 112
/*    */     //   94: aload_0
/*    */     //   95: dup
/*    */     //   96: getfield ji0 : Lf/vF0;
/*    */     //   99: iconst_0
/*    */     //   100: invokevirtual wI0 : (Z)V
/*    */     //   103: getfield ji0 : Lf/vF0;
/*    */     //   106: getfield TS : Lf/rH;
/*    */     //   109: invokevirtual H : ()V
/*    */     //   112: return
/*    */     // Line number table:
/*    */     //   Java source line number -> byte code offset
/*    */     //   #1	-> 10
/*    */     //   #2	-> 13
/*    */     //   #3	-> 42
/*    */     //   #4	-> 45
/*    */     //   #5	-> 61
/*    */     //   #6	-> 71
/*    */     //   #7	-> 75
/*    */     //   #8	-> 82
/*    */     //   #9	-> 87
/*    */     //   #10	-> 106
/*    */     //   #11	-> 109
/*    */   }
/*    */   
/*    */   public final void Eh() {
/*    */     Gp0 gp0;
/*    */     if ((gp0 = this.AF) == null)
/*    */       return; 
/*    */     hm0 hm01;
/*    */     if ((hm01 = this.oN) != null) {
/*    */       this.YG = rG0.P70(gp0, hm01.RN, false);
/*    */     } else {
/*    */       this.YG = "";
/*    */     } 
/*    */     this.aJ.Gq0(this.YG);
/*    */   } }


/* Location:              /Users/vnnsnnt/Documents/Codespace/JavaWorkspace/RedTrainer/src/main/java/org/trainer/client/PokeMMO.jar!/f/Hj.class
 * Java compiler version: 8 (52.0)
 * JD-Core Version:       1.1.3
 */