/*    */ package f;public final class Ht extends Qa0 implements r60 { public static int gQ = 0; public final h2 lk; public final Vq0 hd0; public Ht(h2 paramh2) { // Byte code:
/*    */     //   0: aload_0
/*    */     //   1: aload_1
/*    */     //   2: dup
/*    */     //   3: aload_0
/*    */     //   4: dup
/*    */     //   5: dup
/*    */     //   6: aload_1
/*    */     //   7: aload_0
/*    */     //   8: dup
/*    */     //   9: dup
/*    */     //   10: invokestatic XU : ()Z
/*    */     //   13: invokespecial <init> : (Z)V
/*    */     //   16: new f/Vq0
/*    */     //   19: dup
/*    */     //   20: invokespecial <init> : ()V
/*    */     //   23: putfield hd0 : Lf/Vq0;
/*    */     //   26: iconst_1
/*    */     //   27: invokevirtual EP : (I)V
/*    */     //   30: putfield lk : Lf/h2;
/*    */     //   33: ldc 'tp-menu'
/*    */     //   35: invokevirtual Xu : (Ljava/lang/String;)V
/*    */     //   38: ldc 'Teleport Menu'
/*    */     //   40: invokevirtual Lo : (Ljava/lang/String;)V
/*    */     //   43: invokevirtual getClass : ()Ljava/lang/Class;
/*    */     //   46: pop
/*    */     //   47: <illegal opcode> run : (Lf/h2;)Ljava/lang/Runnable;
/*    */     //   52: invokevirtual TG0 : (Ljava/lang/Runnable;)V
/*    */     //   55: getstatic f/km.u4 : Lf/R8;
/*    */     //   58: invokevirtual Zm : ()B
/*    */     //   61: ifle -> 320
/*    */     //   64: getstatic f/Mk0.tJ : [B
/*    */     //   67: astore_2
/*    */     //   68: bipush #6
/*    */     //   70: istore_3
/*    */     //   71: iconst_0
/*    */     //   72: istore #4
/*    */     //   74: iload #4
/*    */     //   76: iload_3
/*    */     //   77: if_icmpge -> 266
/*    */     //   80: aload_2
/*    */     //   81: iload #4
/*    */     //   83: baload
/*    */     //   84: dup
/*    */     //   85: istore #5
/*    */     //   87: new f/YA0
/*    */     //   90: dup
/*    */     //   91: astore #6
/*    */     //   93: invokespecial <init> : ()V
/*    */     //   96: new f/rS
/*    */     //   99: dup
/*    */     //   100: astore #7
/*    */     //   102: aload #6
/*    */     //   104: invokespecial <init> : (Lf/JG0;)V
/*    */     //   107: bipush #10
/*    */     //   109: if_icmpne -> 119
/*    */     //   112: ldc 'Hotspots'
/*    */     //   114: astore #8
/*    */     //   116: goto -> 126
/*    */     //   119: iload #5
/*    */     //   121: invokestatic zd : (B)Ljava/lang/String;
/*    */     //   124: astore #8
/*    */     //   126: aload_0
/*    */     //   127: iload #5
/*    */     //   129: aload_0
/*    */     //   130: getfield hd0 : Lf/Vq0;
/*    */     //   133: aload #7
/*    */     //   135: aload #8
/*    */     //   137: invokevirtual WS : (Lf/JG0;Ljava/lang/String;)Lf/Li0;
/*    */     //   140: dup
/*    */     //   141: aload_0
/*    */     //   142: swap
/*    */     //   143: <illegal opcode> run : (Lf/Ht;Lf/Li0;)Ljava/lang/Runnable;
/*    */     //   148: invokevirtual Ac0 : (Ljava/lang/Runnable;)V
/*    */     //   151: invokevirtual CD0 : (B)Ljava/util/List;
/*    */     //   154: iconst_0
/*    */     //   155: istore #5
/*    */     //   157: invokeinterface iterator : ()Ljava/util/Iterator;
/*    */     //   162: astore #7
/*    */     //   164: aload #7
/*    */     //   166: invokeinterface hasNext : ()Z
/*    */     //   171: ifeq -> 260
/*    */     //   174: aload #7
/*    */     //   176: invokeinterface next : ()Ljava/lang/Object;
/*    */     //   181: checkcast f/JG0
/*    */     //   184: dup
/*    */     //   185: astore #8
/*    */     //   187: ifnonnull -> 193
/*    */     //   190: goto -> 164
/*    */     //   193: aload #8
/*    */     //   195: instanceof f/dQ
/*    */     //   198: ifeq -> 224
/*    */     //   201: aload #6
/*    */     //   203: dup
/*    */     //   204: dup
/*    */     //   205: iconst_0
/*    */     //   206: istore #5
/*    */     //   208: invokevirtual ZE : ()Lf/nJ0;
/*    */     //   211: pop
/*    */     //   212: aload #8
/*    */     //   214: invokevirtual J8 : (Lf/JG0;)V
/*    */     //   217: invokevirtual ZE : ()Lf/nJ0;
/*    */     //   220: pop
/*    */     //   221: goto -> 164
/*    */     //   224: aload #8
/*    */     //   226: instanceof f/Un
/*    */     //   229: ifeq -> 164
/*    */     //   232: aload #6
/*    */     //   234: aload #8
/*    */     //   236: invokevirtual J8 : (Lf/JG0;)V
/*    */     //   239: iload #5
/*    */     //   241: iconst_1
/*    */     //   242: iadd
/*    */     //   243: dup
/*    */     //   244: istore #5
/*    */     //   246: iconst_4
/*    */     //   247: irem
/*    */     //   248: ifne -> 164
/*    */     //   251: aload #6
/*    */     //   253: invokevirtual ZE : ()Lf/nJ0;
/*    */     //   256: pop
/*    */     //   257: goto -> 164
/*    */     //   260: iinc #4, 1
/*    */     //   263: goto -> 74
/*    */     //   266: aload_0
/*    */     //   267: dup
/*    */     //   268: dup2
/*    */     //   269: getfield hd0 : Lf/Vq0;
/*    */     //   272: new f/JG0
/*    */     //   275: dup
/*    */     //   276: invokespecial <init> : ()V
/*    */     //   279: ldc 'Direction TP'
/*    */     //   281: invokevirtual WS : (Lf/JG0;Ljava/lang/String;)Lf/Li0;
/*    */     //   284: dup
/*    */     //   285: aload_1
/*    */     //   286: swap
/*    */     //   287: aload_0
/*    */     //   288: <illegal opcode> run : (Lf/Ht;)Ljava/lang/Runnable;
/*    */     //   293: invokevirtual Ac0 : (Ljava/lang/Runnable;)V
/*    */     //   296: <illegal opcode> run : (Lf/h2;)Ljava/lang/Runnable;
/*    */     //   301: invokevirtual Ac0 : (Ljava/lang/Runnable;)V
/*    */     //   304: getfield hd0 : Lf/Vq0;
/*    */     //   307: invokevirtual J8 : (Lf/JG0;)V
/*    */     //   310: getfield hd0 : Lf/Vq0;
/*    */     //   313: getstatic f/Ht.gQ : I
/*    */     //   316: invokevirtual dD : (I)V
/*    */     //   319: return
/*    */     //   320: aconst_null
/*    */     //   321: athrow } private void VK0(Li0 paramLi0) { // Byte code:
/*    */     //   0: aload_0
/*    */     //   1: getfield hd0 : Lf/Vq0;
/*    */     //   4: dup
/*    */     //   5: astore_0
/*    */     //   6: getfield Us0 : Ljava/util/ArrayList;
/*    */     //   9: invokevirtual isEmpty : ()Z
/*    */     //   12: ifeq -> 20
/*    */     //   15: iconst_m1
/*    */     //   16: istore_0
/*    */     //   17: goto -> 29
/*    */     //   20: aload_0
/*    */     //   21: getfield Us0 : Ljava/util/ArrayList;
/*    */     //   24: aload_1
/*    */     //   25: invokevirtual indexOf : (Ljava/lang/Object;)I
/*    */     //   28: istore_0
/*    */     //   29: iload_0
/*    */     //   30: putstatic f/Ht.gQ : I
/*    */     //   33: return
/*    */     // Line number table:
/*    */     //   Java source line number -> byte code offset
/*    */     //   #1	-> 6
/*    */     //   #2	-> 9
/*  1 */     //   #3	-> 30 } public final void V90(throws paramthrows) { super.V90(paramthrows); } public final void d40() { if (km.XU()) { QI(); }
/*    */     
/*    */     else
/*    */     
/*  5 */     { ME(km.wI0.dG() / 2 - this.xY / 2, km.wI0.k1() / 2 - this.HC / 2); }  super
/*  6 */       .d40(); } public final List CD0(byte paramByte) { String str; ArrayList<dQ> arrayList; if (!km.mI0.s2(paramByte)) return Collections.emptyList();  if (paramByte == 0) { this(); str = Mk0.zd((byte)0) + " Pt1"; (new dQ()).E1(this); arrayList.add(new dQ()); arrayList.add(ga0((byte)0, (byte)3, (byte)0, (short)11, (short)9, 140000)); arrayList.add(ga0((byte)0, (byte)3, (byte)1, (short)26, (short)27, 140001)); arrayList.add(ga0((byte)0, (byte)3, (byte)2, (short)17, (short)26, 140002)); arrayList.add(ga0((byte)0, (byte)3, (byte)3, (short)22, (short)20, 140003)); arrayList.add(ga0((byte)0, (byte)3, (byte)28, (short)7, (short)42, 140022)); arrayList.add(ga0((byte)0, (byte)3, (byte)4, (short)6, (short)6, 140004)); arrayList.add(ga0((byte)0, (byte)3, (byte)5, (short)15, (short)7, 140005)); arrayList.add(ga0((byte)0, (byte)3, (byte)6, (short)48, (short)12, 140006)); arrayList.add(ga0((byte)0, (byte)3, (byte)7, (short)25, (short)32, 140007)); arrayList.add(ga0((byte)0, (byte)3, (byte)10, (short)33, (short)31, 140010)); arrayList.add(ga0((byte)0, (byte)3, (byte)8, (short)14, (short)12, 140008)); arrayList.add(ga0((byte)0, (byte)3, (byte)9, (short)11, (short)7, 140009)); str = Mk0.zd((byte)0) + " Pt2"; (new dQ()).E1(this); arrayList.add(new dQ()); arrayList.add(ga0((byte)0, (byte)3, (byte)12, (short)14, (short)6, 140055)); arrayList.add(ga0((byte)0, (byte)3, (byte)13, (short)21, (short)8, 140056)); arrayList.add(ga0((byte)0, (byte)3, (byte)14, (short)14, (short)28, 140057)); arrayList.add(ga0((byte)0, (byte)3, (byte)15, (short)18, (short)21, 140058)); arrayList.add(ga0((byte)0, (byte)3, (byte)16, (short)18, (short)7, 140059)); arrayList.add(ga0((byte)0, (byte)3, (byte)18, (short)11, (short)12, 140061)); arrayList.add(ga0((byte)0, (byte)3, (byte)17, (short)12, (short)4, 140060)); arrayList.add(ga0((byte)0, (byte)2, (byte)0, (short)9, (short)9, 140086)); arrayList.add(ga0((byte)0, (byte)2, (byte)56, (short)15, (short)13, 140099)); (arrayList = (ArrayList)new ArrayList<>()).add(ga0((byte)0, (byte)2, (byte)10, (short)9, (short)11, 140091)); return new ArrayList<>(); }  if (arrayList == true) { this(); str = Mk0.zd((byte)1); (new dQ()).E1(this); arrayList.add(new dQ()); arrayList.add(super.ga0((byte)1, (byte)50, (byte)9, (short)9, (short)10, 141000)); arrayList.add(super.ga0((byte)1, (byte)50, (byte)0, (short)20, (short)17, 141007)); arrayList.add(super.ga0((byte)1, (byte)50, (byte)1, (short)19, (short)20, 141008)); arrayList.add(super.ga0((byte)1, (byte)50, (byte)2, (short)22, (short)6, 141009)); arrayList.add(super.ga0((byte)1, (byte)50, (byte)3, (short)16, (short)39, 141010)); arrayList.add(super.ga0((byte)1, (byte)50, (byte)4, (short)5, (short)7, 141011)); arrayList.add(super.ga0((byte)1, (byte)50, (byte)5, (short)24, (short)15, 141012)); arrayList.add(super.ga0((byte)1, (byte)50, (byte)6, (short)28, (short)17, 141013)); arrayList.add(super.ga0((byte)1, (byte)50, (byte)7, (short)43, (short)32, 141014)); arrayList.add(super.ga0((byte)1, (byte)50, (byte)8, (short)18, (short)6, 141015)); arrayList.add(super.ga0((byte)1, (byte)50, (byte)10, (short)6, (short)17, 141001)); arrayList.add(super.ga0((byte)1, (byte)50, (byte)11, (short)2, (short)11, 141002)); arrayList.add(super.ga0((byte)1, (byte)50, (byte)12, (short)9, (short)7, 141003)); arrayList.add(super.ga0((byte)1, (byte)50, (byte)13, (short)14, (short)8, 141004)); arrayList.add(super.ga0((byte)1, (byte)50, (byte)14, (short)16, (short)4, 141005)); arrayList.add(super.ga0((byte)1, (byte)50, (byte)15, (short)8, (short)16, 141006)); arrayList.add(super.ga0((byte)1, (byte)74, (byte)78, (short)14, (short)6, 141085)); (new dQ())
/*  7 */         .E1("Instances");
/*  8 */       arrayList.add(new dQ()); arrayList.add(super.ga0((byte)1, (byte)76, (byte)4, (short)26, (short)43, 141058)); arrayList.add(super.ga0((byte)1, (byte)76, (byte)60, (short)9, (short)13, 141212)); arrayList.add(super.z()); (new dQ())
/*  9 */         .E1("Islands");
/* 10 */       arrayList.add(new dQ()); arrayList.add(super.ga0((byte)1, (byte)76, (byte)56, (short)13, (short)38, 141201)); arrayList.add(super.ga0((byte)1, (byte)76, (byte)9, (short)13, (short)22, 141073)); arrayList.add(super.ga0((byte)1, (byte)76, (byte)58, (short)15, (short)12, 141200)); arrayList.add(super.ga0((byte)1, (byte)76, (byte)66, (short)10, (short)11, 141211)); (new dQ())
/* 11 */         .E1("Berries");
/* 12 */       arrayList.add(new dQ()); arrayList.add(super.ga0((byte)1, (byte)50, (byte)19, (short)8, (short)22, 141019)); (arrayList = new ArrayList<>()).add(super.ga0((byte)1, (byte)50, (byte)38, (short)14, (short)7, 141038)); return new ArrayList<>(); }  if (arrayList == 2) { this(); String str2 = Mk0.zd((byte)2); (new dQ())
/* 13 */         .E1(str2);
/* 14 */       (new ArrayList<>()).add(new dQ()); gb[] arrayOfGb2;
/*    */       int i;
/*    */       byte b;
/* 17 */       for (i = (arrayOfGb2 = (gb[])km.mI0.AN.YP.Z6).length, b = 0; b < i; ) { gb gb; int j; if ((j = (gb = arrayOfGb2[b]).Rb0) != 0 && gb.F70 == 0) { int k = gb.SE0; short s; switch (s = gb.Ga) { case 383: j = 478; k = 442; break;case 374: j = 710; k = 362; break;case 370: j = 675; k = 204; break;case 368: j = 592; k = 175; break;case 365: j = 463; k = 175; break;case 355: j = 434; k = 120; break;case 348: j = 358; k = 175; break;case 345: j = 203; k = 183; break;case 319: j = 756; k = 648; break;case 238: j = 725; k = 715; break;case 235: j = 298; k = 757; break;case 205: j = 180; k = 147; break; }  k = (short)j; j = (short)k; arrayList.add(super.yx0((byte)2, s, k, j, (byte)0, false)); }  b++; }  arrayList.add(super.yx0((byte)2, (short)0, (short)43, (short)39, (byte)0, false)); arrayList.add(super.yx0((byte)2, (short)295, (short)43, (short)39, (byte)0, false)); String str1 = Mk0.zd((byte)2) + " Nogrid Maps"; (new dQ())
/* 18 */         .E1(str1);
/* 19 */       arrayList.add(new dQ());
/*    */       
/*    */       gb[] arrayOfGb1;
/* 22 */       for (i = (arrayOfGb1 = (gb[])km.mI0.AN.YP.Z6).length, b = 0; b < i; ) { km.mI0.AN.getClass(); gb gb; if (rE.tu((byte)2, (gb = arrayOfGb1[b]).Ga) >= 0) { boolean bool3; byte b1 = 2; boolean bool1 = false, bool2 = false; short s; if ((s = gb.Ga) == 28) { bool3 = true; } else { bool3 = false; }  arrayList.add(super.yx0(b1, s, bool1, bool2, bool3, true)); }  b++; }  return arrayList; }  if (arrayList == 3) { this(); str = Mk0.zd((byte)3); (new dQ())
/* 23 */         .E1(this);
/* 24 */       arrayList.add(new dQ()); arrayList.add(super.yx0((byte)3, (short)411, (short)116, (short)886, (byte)0, false)); arrayList.add(super.yx0((byte)3, (short)418, (short)177, (short)843, (byte)0, false)); arrayList.add(super.yx0((byte)3, (short)426, (short)176, (short)667, (byte)0, false)); arrayList.add(super.yx0((byte)3, (short)433, (short)566, (short)657, (byte)0, false)); arrayList.add(super.yx0((byte)3, (short)442, (short)472, (short)539, (byte)0, false)); arrayList.add(super.yx0((byte)3, (short)3, (short)180, (short)777, (byte)0, false)); arrayList.add(super.yx0((byte)3, (short)33, (short)58, (short)723, (byte)0, false)); arrayList.add(super.yx0((byte)3, (short)45, (short)303, (short)757, (byte)0, false)); arrayList.add(super.yx0((byte)3, (short)65, (short)305, (short)531, (byte)0, false)); arrayList.add(super.yx0((byte)3, (short)86, (short)465, (short)698, (byte)0, false)); arrayList.add(super.yx0((byte)3, (short)120, (short)600, (short)816, (byte)0, false)); arrayList.add(super.yx0((byte)3, (short)132, (short)717, (short)612, (byte)0, false)); arrayList.add(super.yx0((byte)3, (short)150, (short)860, (short)785, (byte)0, false)); arrayList.add(super.yx0((byte)3, (short)165, (short)379, (short)234, (byte)0, false)); arrayList.add(super.yx0((byte)3, (short)172, (short)842, (short)599, (byte)0, false)); arrayList.add(super.yx0((byte)3, (short)172, (short)847, (short)560, (byte)0, false)); arrayList.add(super.yx0((byte)3, (short)573, (short)55, (short)40, (byte)0, false)); str = Ml0.OH0(143112); (new dQ())
/* 25 */         .E1(this);
/* 26 */       arrayList.add(new dQ()); arrayList.add(super.yx0((byte)3, (short)188, (short)647, (short)430, (byte)0, false)); arrayList.add(super.yx0((byte)3, (short)450, (short)659, (short)339, (byte)0, false)); arrayList.add(super.yx0((byte)3, (short)457, (short)802, (short)473, (byte)0, false)); (arrayList = new ArrayList<>()).add(super.yx0((byte)3, (short)392, (short)306, (short)910, (byte)0, false)); return new ArrayList<>(); }  if (arrayList == 4) { this(); str = Mk0.zd((byte)4); (new dQ())
/* 27 */         .E1(this);
/* 28 */       arrayList.add(new dQ()); arrayList.add(super.yx0((byte)4, (short)60, (short)695, (short)397, (byte)0, false)); arrayList.add(super.yx0((byte)4, (short)67, (short)564, (short)392, (byte)0, false)); arrayList.add(super.yx0((byte)4, (short)73, (short)497, (short)272, (byte)0, false)); arrayList.add(super.yx0((byte)4, (short)74, (short)410, (short)461, (byte)0, false)); arrayList.add(super.yx0((byte)4, (short)75, (short)187, (short)370, (byte)0, false)); arrayList.add(super.yx0((byte)4, (short)76, (short)352, (short)369, (byte)0, false)); arrayList.add(super.yx0((byte)4, (short)77, (short)272, (short)258, (byte)0, false)); arrayList.add(super.yx0((byte)4, (short)78, (short)397, (short)184, (byte)0, false)); arrayList.add(super.yx0((byte)4, (short)87, (short)534, (short)184, (byte)0, false)); arrayList.add(super.yx0((byte)4, (short)88, (short)536, (short)90, (byte)0, false)); arrayList.add(super.yx0((byte)4, (short)89, (short)674, (short)177, (byte)0, false)); arrayList.add(super.yx0((byte)4, (short)90, (short)820, (short)266, (byte)0, false)); arrayList.add(super.yx0((byte)4, (short)174, (short)82, (short)303, (byte)0, false)); arrayList.add(super.yx0((byte)4, (short)411, (short)8, (short)15, (byte)0, false)); arrayList.add(super.yx0((byte)4, (short)280, (short)42, (short)23, (byte)0, false)); arrayList.add(super.yx0((byte)4, (short)30, (short)909, (short)297, (byte)0, false)); arrayList.add(super.yx0((byte)4, (short)36, (short)468, (short)419, (byte)0, false)); str = Mk0.zd((byte)0) + "2"; (new dQ())
/* 29 */         .E1(this);
/* 30 */       arrayList.add(new dQ()); arrayList.add(super.yx0((byte)4, (short)49, (short)1033, (short)364, (byte)0, false)); arrayList.add(super.yx0((byte)4, (short)50, (short)1032, (short)263, (byte)0, false)); arrayList.add(super.yx0((byte)4, (short)51, (short)1048, (short)107, (byte)0, false)); arrayList.add(super.yx0((byte)4, (short)52, (short)1309, (short)132, (byte)0, false)); arrayList.add(super.yx0((byte)4, (short)53, (short)1418, (short)235, (byte)0, false)); arrayList.add(super.yx0((byte)4, (short)54, (short)1297, (short)295, (byte)0, false)); arrayList.add(super.yx0((byte)4, (short)55, (short)1231, (short)238, (byte)0, false)); arrayList.add(super.yx0((byte)4, (short)56, (short)1209, (short)440, (byte)0, false)); arrayList.add(super.yx0((byte)4, (short)57, (short)1039, (short)503, (byte)0, false)); arrayList.add(super.yx0((byte)4, (short)58, (short)912, (short)201, (byte)0, false)); arrayList.add(super.yx0((byte)4, (short)59, (short)1294, (short)243, (byte)0, false)); arrayList.add(super.yx0((byte)4, (short)11, (short)1167, (short)107, (byte)0, false)); arrayList.add(super.yx0((byte)4, (short)18, (short)1426, (short)164, (byte)0, false)); (new dQ())
/* 31 */         .E1("Instances");
/* 32 */       arrayList.add(new dQ()); arrayList.add(super.yx0((byte)4, (short)340, (short)15, (short)19, (byte)0, false)); (arrayList = new ArrayList<>()).add(super.yx0((byte)4, (short)465, (short)30, (short)16, (byte)0, false)); return new ArrayList<>(); }  if (arrayList == 10) { this(); if (km.mI0.s2((byte)0)) { String str1 = Mk0.zd((byte)0); (new dQ())
/* 33 */           .E1(str1);
/* 34 */         arrayList.add(new dQ()); arrayList.add(super.ga0((byte)0, (byte)3, (byte)23, (short)24, (short)2, 140017)); arrayList.add(super.ga0((byte)0, (byte)1, (byte)63, (short)36, (short)17, 140048)); arrayList.add(super.ga0((byte)0, (byte)3, (byte)45, (short)14, (short)112, 140062)); }  if (km.mI0.s2((byte)4)) { String str1 = Mk0.zd((byte)4); (new dQ())
/* 35 */           .E1(str1);
/* 36 */         arrayList.add(new dQ()); arrayList.add(super.yx0((byte)4, (short)151, (short)131, (short)369, (byte)0, false)); }  if (km.mI0.s2((byte)1)) { String str1 = Mk0.zd((byte)1); (new dQ())
/* 37 */           .E1(str1);
/* 38 */         arrayList.add(new dQ()); arrayList.add(super.ga0((byte)1, (byte)74, (byte)11, (short)11, (short)35, 141059)); arrayList.add(super.ga0((byte)1, (byte)74, (byte)98, (short)16, (short)9, 141209)); arrayList.add(super.ga0((byte)1, (byte)76, (byte)14, (short)38, (short)57, 141058)); }  if (km.mI0.s2((byte)3)) { String str1 = Mk0.zd((byte)3); (new dQ())
/* 39 */           .E1(str1);
/* 40 */         arrayList.add(new dQ()); arrayList.add(super.yx0((byte)3, (short)356, (short)563, (short)688, (byte)0, false)); }  str = Mk0.zd((byte)2); (new dQ())
/* 41 */         .E1(this);
/* 42 */       arrayList.add(new dQ()); arrayList.add(super.yx0((byte)2, (short)240, (short)773, (short)302, (byte)0, false)); arrayList.add(super.yx0((byte)2, (short)368, (short)624, (short)185, (byte)0, false)); arrayList.add(super.yx0((byte)2, (short)206, (short)22, (short)44, (byte)0, false)); arrayList.add(super.yx0((byte)2, (short)232, (short)33, (short)25, (byte)0, false)); arrayList.add(super.yx0((byte)2, (short)96, (short)202, (short)412, (byte)0, false)); arrayList.add(super.yx0((byte)2, (short)215, (short)10, (short)38, (byte)0, false)); arrayList.add(super.yx0((byte)2, (short)182, (short)16, (short)12, (byte)0, false)); arrayList.add(super.yx0((byte)2, (short)354, (short)10, (short)23, (byte)0, false)); return arrayList; }  return Collections.emptyList(); }
/*    */ 
/*    */   
/*    */   public final void mM() {
/*    */     if (km.XU()) {
/*    */       ME(0, 0);
/*    */       Tm(km.wI0.dG(), km.wI0.k1());
/*    */     } else {
/*    */       super.mM();
/*    */     } 
/*    */   }
/*    */   
/*    */   public final boolean i2(oa0 paramoa0) {
/*    */     if (B8.Wm0(paramoa0.cz0) && paramoa0.oO() && h1.J20(paramoa0.GG0, BM.lc)) {
/*    */       this.lk.cH0();
/*    */       return true;
/*    */     } 
/*    */     return super.i2(paramoa0);
/*    */   }
/*    */   
/*    */   public final void IG0() {
/*    */     VA0.c90(this);
/*    */   }
/*    */   
/*    */   public final Un ga0(byte paramByte1, byte paramByte2, byte paramByte3, short paramShort1, short paramShort2, int paramInt) {
/*    */     // Byte code:
/*    */     //   0: new f/Un
/*    */     //   3: dup
/*    */     //   4: astore #7
/*    */     //   6: iload_1
/*    */     //   7: iload_2
/*    */     //   8: aload #7
/*    */     //   10: iload #6
/*    */     //   12: invokestatic OH0 : (I)Ljava/lang/String;
/*    */     //   15: invokespecial <init> : (Ljava/lang/String;)V
/*    */     //   18: iload_3
/*    */     //   19: iload #4
/*    */     //   21: iload #5
/*    */     //   23: <illegal opcode> run : (BBBSS)Ljava/lang/Runnable;
/*    */     //   28: invokevirtual tW : (Ljava/lang/Runnable;)V
/*    */     //   31: invokestatic XU : ()Z
/*    */     //   34: ifeq -> 56
/*    */     //   37: aload #7
/*    */     //   39: aload_0
/*    */     //   40: getfield lk : Lf/h2;
/*    */     //   43: dup
/*    */     //   44: invokevirtual getClass : ()Ljava/lang/Class;
/*    */     //   47: pop
/*    */     //   48: <illegal opcode> run : (Lf/h2;)Ljava/lang/Runnable;
/*    */     //   53: invokevirtual tW : (Ljava/lang/Runnable;)V
/*    */     //   56: aload #7
/*    */     //   58: areturn
/*    */   }
/*    */   
/*    */   public final Un z() {
/*    */     // Byte code:
/*    */     //   0: new f/Un
/*    */     //   3: dup
/*    */     //   4: dup
/*    */     //   5: astore_1
/*    */     //   6: ldc_w 'CONTEST HALL'
/*    */     //   9: invokespecial <init> : (Ljava/lang/String;)V
/*    */     //   12: iconst_1
/*    */     //   13: bipush #63
/*    */     //   15: iconst_4
/*    */     //   16: bipush #14
/*    */     //   18: bipush #6
/*    */     //   20: <illegal opcode> run : (BBBSS)Ljava/lang/Runnable;
/*    */     //   25: invokevirtual tW : (Ljava/lang/Runnable;)V
/*    */     //   28: invokestatic XU : ()Z
/*    */     //   31: ifeq -> 52
/*    */     //   34: aload_1
/*    */     //   35: aload_0
/*    */     //   36: getfield lk : Lf/h2;
/*    */     //   39: dup
/*    */     //   40: invokevirtual getClass : ()Ljava/lang/Class;
/*    */     //   43: pop
/*    */     //   44: <illegal opcode> run : (Lf/h2;)Ljava/lang/Runnable;
/*    */     //   49: invokevirtual tW : (Ljava/lang/Runnable;)V
/*    */     //   52: aload_1
/*    */     //   53: areturn
/*    */   }
/*    */   
/*    */   public final Un yx0(byte paramByte1, short paramShort1, short paramShort2, short paramShort3, byte paramByte2, boolean paramBoolean) {
/*    */     // Byte code:
/*    */     //   0: iload_1
/*    */     //   1: aconst_null
/*    */     //   2: astore #7
/*    */     //   4: iconst_2
/*    */     //   5: if_icmpeq -> 78
/*    */     //   8: iload_1
/*    */     //   9: iconst_3
/*    */     //   10: if_icmpeq -> 53
/*    */     //   13: iload_1
/*    */     //   14: iconst_4
/*    */     //   15: if_icmpeq -> 21
/*    */     //   18: goto -> 97
/*    */     //   21: getstatic f/km.mI0 : Lf/P1;
/*    */     //   24: getfield yE : Lf/BE;
/*    */     //   27: dup
/*    */     //   28: astore #7
/*    */     //   30: ifnonnull -> 35
/*    */     //   33: aconst_null
/*    */     //   34: areturn
/*    */     //   35: aload #7
/*    */     //   37: getfield qN : Lf/Fg0;
/*    */     //   40: getfield Z6 : [Lf/Ws0;
/*    */     //   43: iload_2
/*    */     //   44: aaload
/*    */     //   45: checkcast f/iy0
/*    */     //   48: astore #7
/*    */     //   50: goto -> 97
/*    */     //   53: getstatic f/km.mI0 : Lf/P1;
/*    */     //   56: getfield MT : Lf/gD;
/*    */     //   59: dup
/*    */     //   60: astore #7
/*    */     //   62: ifnonnull -> 67
/*    */     //   65: aconst_null
/*    */     //   66: areturn
/*    */     //   67: aload #7
/*    */     //   69: iload_2
/*    */     //   70: invokevirtual U40 : (I)Lf/iy0;
/*    */     //   73: astore #7
/*    */     //   75: goto -> 97
/*    */     //   78: getstatic f/km.mI0 : Lf/P1;
/*    */     //   81: getfield AN : Lf/Wo;
/*    */     //   84: getfield YP : Lf/TA0;
/*    */     //   87: getfield Z6 : [Lf/Ws0;
/*    */     //   90: iload_2
/*    */     //   91: aaload
/*    */     //   92: checkcast f/gb
/*    */     //   95: astore #7
/*    */     //   97: aload #7
/*    */     //   99: ifnonnull -> 104
/*    */     //   102: aconst_null
/*    */     //   103: areturn
/*    */     //   104: new f/Un
/*    */     //   107: dup
/*    */     //   108: astore #8
/*    */     //   110: iload_1
/*    */     //   111: iload_2
/*    */     //   112: aload #8
/*    */     //   114: aload #7
/*    */     //   116: invokevirtual getName : ()Ljava/lang/String;
/*    */     //   119: invokespecial <init> : (Ljava/lang/String;)V
/*    */     //   122: iload_3
/*    */     //   123: iload #4
/*    */     //   125: iload #5
/*    */     //   127: iload #6
/*    */     //   129: <illegal opcode> run : (BSSSBZ)Ljava/lang/Runnable;
/*    */     //   134: invokevirtual tW : (Ljava/lang/Runnable;)V
/*    */     //   137: invokestatic XU : ()Z
/*    */     //   140: ifeq -> 162
/*    */     //   143: aload #8
/*    */     //   145: aload_0
/*    */     //   146: getfield lk : Lf/h2;
/*    */     //   149: dup
/*    */     //   150: invokevirtual getClass : ()Ljava/lang/Class;
/*    */     //   153: pop
/*    */     //   154: <illegal opcode> run : (Lf/h2;)Ljava/lang/Runnable;
/*    */     //   159: invokevirtual tW : (Ljava/lang/Runnable;)V
/*    */     //   162: aload #8
/*    */     //   164: areturn
/*    */     // Line number table:
/*    */     //   Java source line number -> byte code offset
/*    */     //   #1	-> 37
/*    */     //   #2	-> 40
/*    */     //   #3	-> 44
/*    */     //   #4	-> 45
/*    */     //   #5	-> 53
/*    */     //   #6	-> 84
/*    */     //   #7	-> 87
/*    */     //   #8	-> 91
/*    */     //   #9	-> 92
/*    */     //   #10	-> 104
/*    */   } }


/* Location:              /Users/vnnsnnt/Documents/Codespace/JavaWorkspace/RedTrainer/src/main/java/org/trainer/client/PokeMMO.jar!/f/Ht.class
 * Java compiler version: 8 (52.0)
 * JD-Core Version:       1.1.3
 */