/*  1 */ package f;public final class Hy extends Qa0 implements r60 { public static final int[] cOM6 = new int[] { 255, 255, 255, 255, 255, 255, 680 }; public final qc0 ZS; public final rS up; public final Ro0 Az0; public final vF0 dm0; public final Un gH; public final Un uk0; public final JG0[] Tn0; public final Q20 nG; public final dQ EI; public final vF0 SB; public final vF0 So0; public final dQ XD; public final dQ Xy0; public final dQ Me; public final dQ dk; public final dQ VV; public final dQ mf0; public final Q20 Gd; public final dQ J5; public final dQ bE0; public final Un y7; public final Ip xZ; public final Ip ci0; public final Ip O40; public final gl instanceof; public final Ip COm7; public final Ip y8; private void Hs0() { UD0 uD0 = this.cr0;
/*  2 */     If((byte)((this.Lh + 1) % this.Uf), this); } public final Ip Gc0; public final Vq0 RB; public final IN[] Sk0; public final dQ[] oe0; public final of BW; public final IN TH0; public final IN nW; public final IN vJ; public final IN GC0; public final dQ Kv0; public final dQ oA0; public final dQ XH; public final dQ EO; public final ge0 EJ0; public final Ip PRn; public final W1 l80; public final B9 y6; public final W1 W7; public UD0 cr0; public byte Lh; public k2[] NZ; public final rS ED0; public final rS Uz0; public final rS IU; public byte HH; public int ay0; public Hy(pA parampA, qc0 paramqc0) { // Byte code:
/*    */     //   0: aload_0
/*    */     //   1: dup
/*    */     //   2: dup
/*    */     //   3: dup2
/*    */     //   4: aload_1
/*    */     //   5: dup
/*    */     //   6: aload_0
/*    */     //   7: aload_2
/*    */     //   8: aload_0
/*    */     //   9: dup
/*    */     //   10: dup2
/*    */     //   11: dup2
/*    */     //   12: dup2
/*    */     //   13: dup2
/*    */     //   14: dup2
/*    */     //   15: dup2
/*    */     //   16: invokestatic XU : ()Z
/*    */     //   19: invokespecial <init> : (Z)V
/*    */     //   22: new f/dQ
/*    */     //   25: dup
/*    */     //   26: dup
/*    */     //   27: astore_1
/*    */     //   28: ldc ''
/*    */     //   30: invokespecial <init> : (Ljava/lang/String;)V
/*    */     //   33: putfield XD : Lf/dQ;
/*    */     //   36: new f/dQ
/*    */     //   39: dup
/*    */     //   40: dup
/*    */     //   41: astore_3
/*    */     //   42: ldc ''
/*    */     //   44: invokespecial <init> : (Ljava/lang/String;)V
/*    */     //   47: putfield Xy0 : Lf/dQ;
/*    */     //   50: new f/dQ
/*    */     //   53: dup
/*    */     //   54: dup
/*    */     //   55: astore #4
/*    */     //   57: ldc ''
/*    */     //   59: invokespecial <init> : (Ljava/lang/String;)V
/*    */     //   62: putfield Me : Lf/dQ;
/*    */     //   65: new f/dQ
/*    */     //   68: dup
/*    */     //   69: dup
/*    */     //   70: astore #5
/*    */     //   72: ldc ''
/*    */     //   74: invokespecial <init> : (Ljava/lang/String;)V
/*    */     //   77: putfield dk : Lf/dQ;
/*    */     //   80: new f/dQ
/*    */     //   83: dup
/*    */     //   84: dup
/*    */     //   85: astore #6
/*    */     //   87: ldc ''
/*    */     //   89: invokespecial <init> : (Ljava/lang/String;)V
/*    */     //   92: putfield VV : Lf/dQ;
/*    */     //   95: new f/dQ
/*    */     //   98: dup
/*    */     //   99: dup
/*    */     //   100: astore #7
/*    */     //   102: ldc ''
/*    */     //   104: invokespecial <init> : (Ljava/lang/String;)V
/*    */     //   107: putfield mf0 : Lf/dQ;
/*    */     //   110: new f/dQ
/*    */     //   113: dup
/*    */     //   114: dup
/*    */     //   115: astore #8
/*    */     //   117: ldc ''
/*    */     //   119: invokespecial <init> : (Ljava/lang/String;)V
/*    */     //   122: putfield J5 : Lf/dQ;
/*    */     //   125: new f/dQ
/*    */     //   128: dup
/*    */     //   129: dup
/*    */     //   130: astore #9
/*    */     //   132: ldc ''
/*    */     //   134: invokespecial <init> : (Ljava/lang/String;)V
/*    */     //   137: putfield bE0 : Lf/dQ;
/*    */     //   140: getstatic f/hR.Tm0 : [Lf/hR;
/*    */     //   143: dup
/*    */     //   144: astore #10
/*    */     //   146: arraylength
/*    */     //   147: iconst_1
/*    */     //   148: iadd
/*    */     //   149: anewarray f/IN
/*    */     //   152: putfield Sk0 : [Lf/IN;
/*    */     //   155: aload #10
/*    */     //   157: arraylength
/*    */     //   158: iconst_1
/*    */     //   159: iadd
/*    */     //   160: anewarray f/dQ
/*    */     //   163: putfield oe0 : [Lf/dQ;
/*    */     //   166: iconst_0
/*    */     //   167: anewarray f/k2
/*    */     //   170: putfield NZ : [Lf/k2;
/*    */     //   173: iconst_m1
/*    */     //   174: putfield HH : B
/*    */     //   177: iconst_0
/*    */     //   178: putfield ay0 : I
/*    */     //   181: putfield ZS : Lf/qc0;
/*    */     //   184: invokevirtual getClass : ()Ljava/lang/Class;
/*    */     //   187: pop
/*    */     //   188: <illegal opcode> run : (Lf/pA;)Ljava/lang/Runnable;
/*    */     //   193: invokevirtual TG0 : (Ljava/lang/Runnable;)V
/*    */     //   196: ldc 'monsterdex-frame'
/*    */     //   198: invokevirtual Xu : (Ljava/lang/String;)V
/*    */     //   201: iconst_1
/*    */     //   202: invokestatic OH0 : (I)Ljava/lang/String;
/*    */     //   205: invokevirtual Lo : (Ljava/lang/String;)V
/*    */     //   208: iconst_1
/*    */     //   209: invokevirtual EP : (I)V
/*    */     //   212: new f/rS
/*    */     //   215: dup
/*    */     //   216: aload_0
/*    */     //   217: swap
/*    */     //   218: dup
/*    */     //   219: invokespecial <init> : ()V
/*    */     //   222: putfield up : Lf/rS;
/*    */     //   225: iconst_2
/*    */     //   226: invokevirtual zG0 : (I)V
/*    */     //   229: new f/Ro0
/*    */     //   232: dup
/*    */     //   233: dup
/*    */     //   234: astore #10
/*    */     //   236: invokespecial <init> : ()V
/*    */     //   239: putfield Az0 : Lf/Ro0;
/*    */     //   242: new f/vF0
/*    */     //   245: astore #11
/*    */     //   247: invokestatic XU : ()Z
/*    */     //   250: ifeq -> 261
/*    */     //   253: sipush #200
/*    */     //   256: istore #12
/*    */     //   258: goto -> 266
/*    */     //   261: sipush #170
/*    */     //   264: istore #12
/*    */     //   266: invokestatic XU : ()Z
/*    */     //   269: ifeq -> 280
/*    */     //   272: sipush #200
/*    */     //   275: istore #13
/*    */     //   277: goto -> 285
/*    */     //   280: sipush #185
/*    */     //   283: istore #13
/*    */     //   285: aload_0
/*    */     //   286: dup
/*    */     //   287: aload #11
/*    */     //   289: aload_0
/*    */     //   290: aload #11
/*    */     //   292: dup
/*    */     //   293: iload #12
/*    */     //   295: iload #13
/*    */     //   297: invokespecial <init> : (II)V
/*    */     //   300: putfield dm0 : Lf/vF0;
/*    */     //   303: ldc 'monstergear-pic'
/*    */     //   305: invokevirtual Xu : (Ljava/lang/String;)V
/*    */     //   308: new f/Un
/*    */     //   311: dup
/*    */     //   312: astore #12
/*    */     //   314: aload_0
/*    */     //   315: aload_2
/*    */     //   316: aload_0
/*    */     //   317: aload #12
/*    */     //   319: dup
/*    */     //   320: sipush #1727
/*    */     //   323: invokestatic OH0 : (I)Ljava/lang/String;
/*    */     //   326: invokespecial <init> : (Ljava/lang/String;)V
/*    */     //   329: putfield gH : Lf/Un;
/*    */     //   332: <illegal opcode> run : (Lf/Hy;Lf/qc0;)Ljava/lang/Runnable;
/*    */     //   337: invokevirtual tW : (Ljava/lang/Runnable;)V
/*    */     //   340: new f/Un
/*    */     //   343: dup
/*    */     //   344: astore_2
/*    */     //   345: aload_0
/*    */     //   346: dup
/*    */     //   347: aload_2
/*    */     //   348: dup
/*    */     //   349: sipush #1760
/*    */     //   352: invokestatic OH0 : (I)Ljava/lang/String;
/*    */     //   355: invokespecial <init> : (Ljava/lang/String;)V
/*    */     //   358: putfield uk0 : Lf/Un;
/*    */     //   361: <illegal opcode> run : (Lf/Hy;)Ljava/lang/Runnable;
/*    */     //   366: invokevirtual tW : (Ljava/lang/Runnable;)V
/*    */     //   369: new f/Ip
/*    */     //   372: dup
/*    */     //   373: invokespecial <init> : ()V
/*    */     //   376: putfield PRn : Lf/Ip;
/*    */     //   379: new f/Ip
/*    */     //   382: dup
/*    */     //   383: dup
/*    */     //   384: astore #13
/*    */     //   386: invokespecial <init> : ()V
/*    */     //   389: putfield xZ : Lf/Ip;
/*    */     //   392: new f/Un
/*    */     //   395: dup
/*    */     //   396: astore #14
/*    */     //   398: aload_0
/*    */     //   399: dup
/*    */     //   400: aload #14
/*    */     //   402: dup
/*    */     //   403: bipush #58
/*    */     //   405: invokestatic OH0 : (I)Ljava/lang/String;
/*    */     //   408: invokespecial <init> : (Ljava/lang/String;)V
/*    */     //   411: putfield y7 : Lf/Un;
/*    */     //   414: <illegal opcode> run : (Lf/Hy;)Ljava/lang/Runnable;
/*    */     //   419: invokevirtual tW : (Ljava/lang/Runnable;)V
/*    */     //   422: invokestatic XU : ()Z
/*    */     //   425: ifeq -> 442
/*    */     //   428: aload #14
/*    */     //   430: dup
/*    */     //   431: ldc ''
/*    */     //   433: invokevirtual s6 : (Ljava/lang/String;)V
/*    */     //   436: ldc_w 'button-return'
/*    */     //   439: invokevirtual Xu : (Ljava/lang/String;)V
/*    */     //   442: aload_0
/*    */     //   443: dup
/*    */     //   444: dup
/*    */     //   445: aload #7
/*    */     //   447: aload #9
/*    */     //   449: aload #8
/*    */     //   451: aload #6
/*    */     //   453: aload #5
/*    */     //   455: aload #4
/*    */     //   457: aload_3
/*    */     //   458: aload_1
/*    */     //   459: aload #10
/*    */     //   461: new f/Q20
/*    */     //   464: dup
/*    */     //   465: astore #15
/*    */     //   467: aload_0
/*    */     //   468: aload #15
/*    */     //   470: dup
/*    */     //   471: iconst_2
/*    */     //   472: invokespecial <init> : (I)V
/*    */     //   475: putfield nG : Lf/Q20;
/*    */     //   478: ldc_w 'label-area-monsterdex'
/*    */     //   481: invokevirtual Xu : (Ljava/lang/String;)V
/*    */     //   484: ldc_w 'label-value-dex2'
/*    */     //   487: invokevirtual Xu : (Ljava/lang/String;)V
/*    */     //   490: ldc_w 'label-value-dex2'
/*    */     //   493: invokevirtual Xu : (Ljava/lang/String;)V
/*    */     //   496: ldc_w 'label-value-dex2'
/*    */     //   499: invokevirtual Xu : (Ljava/lang/String;)V
/*    */     //   502: ldc_w 'label-value-dex2'
/*    */     //   505: invokevirtual Xu : (Ljava/lang/String;)V
/*    */     //   508: ldc_w 'label-value-dex2'
/*    */     //   511: invokevirtual Xu : (Ljava/lang/String;)V
/*    */     //   514: ldc_w 'label-value-dex2'
/*    */     //   517: invokevirtual Xu : (Ljava/lang/String;)V
/*    */     //   520: ldc_w 'label-value-dex2'
/*    */     //   523: invokevirtual Xu : (Ljava/lang/String;)V
/*    */     //   526: ldc_w 'label-value-dex2'
/*    */     //   529: invokevirtual Xu : (Ljava/lang/String;)V
/*    */     //   532: ldc_w 'label-value-dex2'
/*    */     //   535: invokevirtual Xu : (Ljava/lang/String;)V
/*    */     //   538: new f/dQ
/*    */     //   541: dup
/*    */     //   542: astore #16
/*    */     //   544: sipush #1706
/*    */     //   547: invokestatic OH0 : (I)Ljava/lang/String;
/*    */     //   550: invokespecial <init> : (Ljava/lang/String;)V
/*    */     //   553: new f/dQ
/*    */     //   556: dup
/*    */     //   557: astore #17
/*    */     //   559: sipush #1707
/*    */     //   562: invokestatic OH0 : (I)Ljava/lang/String;
/*    */     //   565: invokespecial <init> : (Ljava/lang/String;)V
/*    */     //   568: new f/dQ
/*    */     //   571: dup
/*    */     //   572: astore #18
/*    */     //   574: sipush #1708
/*    */     //   577: invokestatic OH0 : (I)Ljava/lang/String;
/*    */     //   580: invokespecial <init> : (Ljava/lang/String;)V
/*    */     //   583: new f/dQ
/*    */     //   586: dup
/*    */     //   587: astore #19
/*    */     //   589: sipush #1709
/*    */     //   592: invokestatic OH0 : (I)Ljava/lang/String;
/*    */     //   595: invokespecial <init> : (Ljava/lang/String;)V
/*    */     //   598: new f/dQ
/*    */     //   601: dup
/*    */     //   602: astore #20
/*    */     //   604: sipush #1710
/*    */     //   607: invokestatic OH0 : (I)Ljava/lang/String;
/*    */     //   610: invokespecial <init> : (Ljava/lang/String;)V
/*    */     //   613: new f/dQ
/*    */     //   616: dup
/*    */     //   617: astore #21
/*    */     //   619: sipush #1730
/*    */     //   622: invokestatic OH0 : (I)Ljava/lang/String;
/*    */     //   625: invokespecial <init> : (Ljava/lang/String;)V
/*    */     //   628: new f/dQ
/*    */     //   631: dup
/*    */     //   632: astore #22
/*    */     //   634: sipush #1733
/*    */     //   637: invokestatic OH0 : (I)Ljava/lang/String;
/*    */     //   640: invokespecial <init> : (Ljava/lang/String;)V
/*    */     //   643: new f/dQ
/*    */     //   646: dup
/*    */     //   647: dup
/*    */     //   648: astore #23
/*    */     //   650: sipush #1886
/*    */     //   653: invokestatic OH0 : (I)Ljava/lang/String;
/*    */     //   656: invokespecial <init> : (Ljava/lang/String;)V
/*    */     //   659: sipush #1761
/*    */     //   662: invokestatic OH0 : (I)Ljava/lang/String;
/*    */     //   665: invokevirtual Gq0 : (Ljava/lang/Object;)V
/*    */     //   668: new f/dQ
/*    */     //   671: dup
/*    */     //   672: astore #24
/*    */     //   674: sipush #1734
/*    */     //   677: invokestatic OH0 : (I)Ljava/lang/String;
/*    */     //   680: invokespecial <init> : (Ljava/lang/String;)V
/*    */     //   683: new f/dQ
/*    */     //   686: dup
/*    */     //   687: astore #25
/*    */     //   689: aload #24
/*    */     //   691: aload #23
/*    */     //   693: aload #22
/*    */     //   695: aload #21
/*    */     //   697: aload #20
/*    */     //   699: aload #19
/*    */     //   701: aload #18
/*    */     //   703: aload #17
/*    */     //   705: aload #16
/*    */     //   707: aload #25
/*    */     //   709: sipush #1735
/*    */     //   712: invokestatic OH0 : (I)Ljava/lang/String;
/*    */     //   715: invokespecial <init> : (Ljava/lang/String;)V
/*    */     //   718: ldc_w 'label-title-dex'
/*    */     //   721: invokevirtual Xu : (Ljava/lang/String;)V
/*    */     //   724: ldc_w 'label-title-dex'
/*    */     //   727: invokevirtual Xu : (Ljava/lang/String;)V
/*    */     //   730: ldc_w 'label-title-dex'
/*    */     //   733: invokevirtual Xu : (Ljava/lang/String;)V
/*    */     //   736: ldc_w 'label-title-dex'
/*    */     //   739: invokevirtual Xu : (Ljava/lang/String;)V
/*    */     //   742: ldc_w 'label-title-dex'
/*    */     //   745: invokevirtual Xu : (Ljava/lang/String;)V
/*    */     //   748: ldc_w 'label-title-dex'
/*    */     //   751: invokevirtual Xu : (Ljava/lang/String;)V
/*    */     //   754: ldc_w 'label-title-dex'
/*    */     //   757: invokevirtual Xu : (Ljava/lang/String;)V
/*    */     //   760: ldc_w 'label-title-dex'
/*    */     //   763: invokevirtual Xu : (Ljava/lang/String;)V
/*    */     //   766: ldc_w 'label-title-dex'
/*    */     //   769: invokevirtual Xu : (Ljava/lang/String;)V
/*    */     //   772: ldc_w 'label-title-dex'
/*    */     //   775: invokevirtual Xu : (Ljava/lang/String;)V
/*    */     //   778: bipush #10
/*    */     //   780: anewarray f/JG0
/*    */     //   783: dup
/*    */     //   784: dup
/*    */     //   785: dup2
/*    */     //   786: dup2
/*    */     //   787: dup2
/*    */     //   788: dup2
/*    */     //   789: iconst_0
/*    */     //   790: aload #16
/*    */     //   792: aastore
/*    */     //   793: iconst_1
/*    */     //   794: aload #17
/*    */     //   796: aastore
/*    */     //   797: iconst_2
/*    */     //   798: aload #18
/*    */     //   800: aastore
/*    */     //   801: iconst_3
/*    */     //   802: aload #19
/*    */     //   804: aastore
/*    */     //   805: iconst_4
/*    */     //   806: aload #20
/*    */     //   808: aastore
/*    */     //   809: iconst_5
/*    */     //   810: aload #21
/*    */     //   812: aastore
/*    */     //   813: bipush #6
/*    */     //   815: aload #22
/*    */     //   817: aastore
/*    */     //   818: bipush #7
/*    */     //   820: aload #23
/*    */     //   822: aastore
/*    */     //   823: bipush #8
/*    */     //   825: aload #24
/*    */     //   827: aastore
/*    */     //   828: bipush #9
/*    */     //   830: aload #25
/*    */     //   832: aastore
/*    */     //   833: putfield Tn0 : [Lf/JG0;
/*    */     //   836: new f/ge0
/*    */     //   839: dup
/*    */     //   840: astore #26
/*    */     //   842: aload_0
/*    */     //   843: aload #26
/*    */     //   845: aload_0
/*    */     //   846: aload #26
/*    */     //   848: dup
/*    */     //   849: invokespecial <init> : ()V
/*    */     //   852: putfield EJ0 : Lf/ge0;
/*    */     //   855: iconst_0
/*    */     //   856: invokevirtual zs : (Z)V
/*    */     //   859: <illegal opcode> run : (Lf/Hy;)Ljava/lang/Runnable;
/*    */     //   864: invokevirtual tW : (Ljava/lang/Runnable;)V
/*    */     //   867: new f/dQ
/*    */     //   870: dup
/*    */     //   871: aload #26
/*    */     //   873: swap
/*    */     //   874: sipush #1700
/*    */     //   877: invokestatic OH0 : (I)Ljava/lang/String;
/*    */     //   880: invokespecial <init> : (Ljava/lang/String;)V
/*    */     //   883: invokevirtual VH : (Lf/JG0;)V
/*    */     //   886: new f/IN
/*    */     //   889: dup
/*    */     //   890: dup
/*    */     //   891: aload_0
/*    */     //   892: swap
/*    */     //   893: dup
/*    */     //   894: invokespecial <init> : ()V
/*    */     //   897: putfield vJ : Lf/IN;
/*    */     //   900: fconst_0
/*    */     //   901: invokevirtual Nu : (F)V
/*    */     //   904: ldc_w 'progressbar-white'
/*    */     //   907: invokevirtual Xu : (Ljava/lang/String;)V
/*    */     //   910: new f/IN
/*    */     //   913: dup
/*    */     //   914: dup
/*    */     //   915: aload_0
/*    */     //   916: swap
/*    */     //   917: dup
/*    */     //   918: invokespecial <init> : ()V
/*    */     //   921: putfield TH0 : Lf/IN;
/*    */     //   924: fconst_0
/*    */     //   925: invokevirtual Nu : (F)V
/*    */     //   928: ldc_w 'progressbar-blue'
/*    */     //   931: invokevirtual Xu : (Ljava/lang/String;)V
/*    */     //   934: new f/IN
/*    */     //   937: dup
/*    */     //   938: dup
/*    */     //   939: aload_0
/*    */     //   940: swap
/*    */     //   941: dup
/*    */     //   942: invokespecial <init> : ()V
/*    */     //   945: putfield nW : Lf/IN;
/*    */     //   948: fconst_0
/*    */     //   949: invokevirtual Nu : (F)V
/*    */     //   952: ldc_w 'progressbar-green'
/*    */     //   955: invokevirtual Xu : (Ljava/lang/String;)V
/*    */     //   958: new f/IN
/*    */     //   961: dup
/*    */     //   962: dup
/*    */     //   963: aload_0
/*    */     //   964: swap
/*    */     //   965: dup
/*    */     //   966: invokespecial <init> : ()V
/*    */     //   969: putfield GC0 : Lf/IN;
/*    */     //   972: fconst_0
/*    */     //   973: invokevirtual Nu : (F)V
/*    */     //   976: ldc_w 'progressbar-pink'
/*    */     //   979: invokevirtual Xu : (Ljava/lang/String;)V
/*    */     //   982: invokestatic ZZ : ()Lf/interface;
/*    */     //   985: getstatic f/Ht0.QS : Lf/Ht0;
/*    */     //   988: invokevirtual Ev0 : (Lf/Ht0;)Lf/pe0;
/*    */     //   991: astore #26
/*    */     //   993: new f/dQ
/*    */     //   996: dup
/*    */     //   997: astore #27
/*    */     //   999: aload_0
/*    */     //   1000: aload #27
/*    */     //   1002: dup
/*    */     //   1003: ldc ''
/*    */     //   1005: invokespecial <init> : (Ljava/lang/String;)V
/*    */     //   1008: putfield EI : Lf/dQ;
/*    */     //   1011: ldc_w 'label-value-dex2'
/*    */     //   1014: invokevirtual Xu : (Ljava/lang/String;)V
/*    */     //   1017: new f/vF0
/*    */     //   1020: dup
/*    */     //   1021: dup
/*    */     //   1022: astore #28
/*    */     //   1024: aload #26
/*    */     //   1026: invokevirtual qY : ()I
/*    */     //   1029: iconst_0
/*    */     //   1030: swap
/*    */     //   1031: invokespecial <init> : (II)V
/*    */     //   1034: putfield SB : Lf/vF0;
/*    */     //   1037: new f/vF0
/*    */     //   1040: dup
/*    */     //   1041: dup
/*    */     //   1042: astore #29
/*    */     //   1044: aload #26
/*    */     //   1046: invokevirtual qY : ()I
/*    */     //   1049: iconst_0
/*    */     //   1050: swap
/*    */     //   1051: invokespecial <init> : (II)V
/*    */     //   1054: putfield So0 : Lf/vF0;
/*    */     //   1057: invokestatic XU : ()Z
/*    */     //   1060: ifeq -> 1081
/*    */     //   1063: aload #29
/*    */     //   1065: aload #28
/*    */     //   1067: invokevirtual ZH0 : ()Lf/rH;
/*    */     //   1070: fconst_2
/*    */     //   1071: invokevirtual Ii0 : (F)V
/*    */     //   1074: invokevirtual ZH0 : ()Lf/rH;
/*    */     //   1077: fconst_2
/*    */     //   1078: invokevirtual Ii0 : (F)V
/*    */     //   1081: aload #15
/*    */     //   1083: dup
/*    */     //   1084: dup
/*    */     //   1085: dup2
/*    */     //   1086: aload_0
/*    */     //   1087: aload #15
/*    */     //   1089: dup
/*    */     //   1090: dup
/*    */     //   1091: dup2
/*    */     //   1092: new f/Q20
/*    */     //   1095: dup
/*    */     //   1096: astore #26
/*    */     //   1098: iconst_3
/*    */     //   1099: anewarray f/JG0
/*    */     //   1102: dup
/*    */     //   1103: dup2
/*    */     //   1104: iconst_0
/*    */     //   1105: aload #27
/*    */     //   1107: aastore
/*    */     //   1108: iconst_1
/*    */     //   1109: aload #28
/*    */     //   1111: aastore
/*    */     //   1112: iconst_2
/*    */     //   1113: aload #29
/*    */     //   1115: aastore
/*    */     //   1116: invokespecial <init> : ([Lf/JG0;)V
/*    */     //   1119: new f/Q20
/*    */     //   1122: dup
/*    */     //   1123: iconst_2
/*    */     //   1124: anewarray f/JG0
/*    */     //   1127: dup
/*    */     //   1128: dup
/*    */     //   1129: iconst_0
/*    */     //   1130: aload #16
/*    */     //   1132: aastore
/*    */     //   1133: iconst_1
/*    */     //   1134: aload #26
/*    */     //   1136: aastore
/*    */     //   1137: invokespecial <init> : ([Lf/JG0;)V
/*    */     //   1140: invokevirtual J8 : (Lf/JG0;)V
/*    */     //   1143: new f/Q20
/*    */     //   1146: dup
/*    */     //   1147: iconst_2
/*    */     //   1148: anewarray f/JG0
/*    */     //   1151: dup
/*    */     //   1152: dup
/*    */     //   1153: iconst_0
/*    */     //   1154: aload #17
/*    */     //   1156: aastore
/*    */     //   1157: iconst_1
/*    */     //   1158: aload #10
/*    */     //   1160: aastore
/*    */     //   1161: invokespecial <init> : ([Lf/JG0;)V
/*    */     //   1164: invokevirtual J8 : (Lf/JG0;)V
/*    */     //   1167: new f/Q20
/*    */     //   1170: dup
/*    */     //   1171: iconst_2
/*    */     //   1172: anewarray f/JG0
/*    */     //   1175: dup
/*    */     //   1176: dup
/*    */     //   1177: iconst_0
/*    */     //   1178: aload #19
/*    */     //   1180: aastore
/*    */     //   1181: iconst_1
/*    */     //   1182: aload_3
/*    */     //   1183: aastore
/*    */     //   1184: invokespecial <init> : ([Lf/JG0;)V
/*    */     //   1187: invokevirtual J8 : (Lf/JG0;)V
/*    */     //   1190: new f/Q20
/*    */     //   1193: dup
/*    */     //   1194: iconst_2
/*    */     //   1195: anewarray f/JG0
/*    */     //   1198: dup
/*    */     //   1199: dup
/*    */     //   1200: iconst_0
/*    */     //   1201: aload #20
/*    */     //   1203: aastore
/*    */     //   1204: iconst_1
/*    */     //   1205: aload #4
/*    */     //   1207: aastore
/*    */     //   1208: invokespecial <init> : ([Lf/JG0;)V
/*    */     //   1211: invokevirtual J8 : (Lf/JG0;)V
/*    */     //   1214: new f/Q20
/*    */     //   1217: dup
/*    */     //   1218: iconst_2
/*    */     //   1219: anewarray f/JG0
/*    */     //   1222: dup
/*    */     //   1223: dup
/*    */     //   1224: iconst_0
/*    */     //   1225: aload #22
/*    */     //   1227: aastore
/*    */     //   1228: iconst_1
/*    */     //   1229: aload #6
/*    */     //   1231: aastore
/*    */     //   1232: invokespecial <init> : ([Lf/JG0;)V
/*    */     //   1235: invokevirtual J8 : (Lf/JG0;)V
/*    */     //   1238: new f/Q20
/*    */     //   1241: dup
/*    */     //   1242: dup
/*    */     //   1243: astore_3
/*    */     //   1244: iconst_2
/*    */     //   1245: anewarray f/JG0
/*    */     //   1248: dup
/*    */     //   1249: dup
/*    */     //   1250: iconst_0
/*    */     //   1251: aload #23
/*    */     //   1253: aastore
/*    */     //   1254: iconst_1
/*    */     //   1255: aload #7
/*    */     //   1257: aastore
/*    */     //   1258: invokespecial <init> : ([Lf/JG0;)V
/*    */     //   1261: putfield Gd : Lf/Q20;
/*    */     //   1264: aload_3
/*    */     //   1265: invokevirtual J8 : (Lf/JG0;)V
/*    */     //   1268: new f/Q20
/*    */     //   1271: dup
/*    */     //   1272: iconst_2
/*    */     //   1273: anewarray f/JG0
/*    */     //   1276: dup
/*    */     //   1277: dup
/*    */     //   1278: iconst_0
/*    */     //   1279: aload #25
/*    */     //   1281: aastore
/*    */     //   1282: iconst_1
/*    */     //   1283: aload #9
/*    */     //   1285: aastore
/*    */     //   1286: invokespecial <init> : ([Lf/JG0;)V
/*    */     //   1289: invokevirtual J8 : (Lf/JG0;)V
/*    */     //   1292: new f/Q20
/*    */     //   1295: dup
/*    */     //   1296: iconst_2
/*    */     //   1297: anewarray f/JG0
/*    */     //   1300: dup
/*    */     //   1301: dup
/*    */     //   1302: iconst_0
/*    */     //   1303: aload #21
/*    */     //   1305: aastore
/*    */     //   1306: iconst_1
/*    */     //   1307: aload #5
/*    */     //   1309: aastore
/*    */     //   1310: invokespecial <init> : ([Lf/JG0;)V
/*    */     //   1313: invokevirtual J8 : (Lf/JG0;)V
/*    */     //   1316: new f/Q20
/*    */     //   1319: dup
/*    */     //   1320: iconst_2
/*    */     //   1321: anewarray f/JG0
/*    */     //   1324: dup
/*    */     //   1325: dup
/*    */     //   1326: iconst_0
/*    */     //   1327: aload #18
/*    */     //   1329: aastore
/*    */     //   1330: iconst_1
/*    */     //   1331: aload_1
/*    */     //   1332: aastore
/*    */     //   1333: invokespecial <init> : ([Lf/JG0;)V
/*    */     //   1336: invokevirtual J8 : (Lf/JG0;)V
/*    */     //   1339: new f/Q20
/*    */     //   1342: dup
/*    */     //   1343: iconst_2
/*    */     //   1344: anewarray f/JG0
/*    */     //   1347: dup
/*    */     //   1348: dup
/*    */     //   1349: iconst_0
/*    */     //   1350: aload #24
/*    */     //   1352: aastore
/*    */     //   1353: iconst_1
/*    */     //   1354: aload #8
/*    */     //   1356: aastore
/*    */     //   1357: invokespecial <init> : ([Lf/JG0;)V
/*    */     //   1360: invokevirtual J8 : (Lf/JG0;)V
/*    */     //   1363: invokestatic XU : ()Z
/*    */     //   1366: ifeq -> 1495
/*    */     //   1369: aload #13
/*    */     //   1371: dup
/*    */     //   1372: invokevirtual mE0 : ()Lf/g0;
/*    */     //   1375: iconst_2
/*    */     //   1376: anewarray f/U90
/*    */     //   1379: dup
/*    */     //   1380: dup
/*    */     //   1381: aload #13
/*    */     //   1383: swap
/*    */     //   1384: aload #13
/*    */     //   1386: iconst_3
/*    */     //   1387: anewarray f/JG0
/*    */     //   1390: dup
/*    */     //   1391: dup2
/*    */     //   1392: iconst_0
/*    */     //   1393: aload #11
/*    */     //   1395: aastore
/*    */     //   1396: iconst_1
/*    */     //   1397: aload #12
/*    */     //   1399: aastore
/*    */     //   1400: iconst_2
/*    */     //   1401: aload_2
/*    */     //   1402: aastore
/*    */     //   1403: invokevirtual vo0 : ([Lf/JG0;)Lf/U90;
/*    */     //   1406: iconst_0
/*    */     //   1407: swap
/*    */     //   1408: aastore
/*    */     //   1409: iconst_1
/*    */     //   1410: anewarray f/JG0
/*    */     //   1413: dup
/*    */     //   1414: iconst_0
/*    */     //   1415: aload #15
/*    */     //   1417: aastore
/*    */     //   1418: invokevirtual vo0 : ([Lf/JG0;)Lf/U90;
/*    */     //   1421: iconst_1
/*    */     //   1422: swap
/*    */     //   1423: aastore
/*    */     //   1424: invokevirtual cOM8 : ([Lf/U90;)Lf/U90;
/*    */     //   1427: astore_1
/*    */     //   1428: invokevirtual d7 : ()Lf/cr0;
/*    */     //   1431: iconst_5
/*    */     //   1432: invokevirtual Aq : (I)Lf/U90;
/*    */     //   1435: iconst_2
/*    */     //   1436: anewarray f/U90
/*    */     //   1439: dup
/*    */     //   1440: dup
/*    */     //   1441: aload #13
/*    */     //   1443: swap
/*    */     //   1444: aload #13
/*    */     //   1446: iconst_3
/*    */     //   1447: anewarray f/JG0
/*    */     //   1450: dup
/*    */     //   1451: dup2
/*    */     //   1452: iconst_0
/*    */     //   1453: aload #11
/*    */     //   1455: aastore
/*    */     //   1456: iconst_1
/*    */     //   1457: aload #12
/*    */     //   1459: aastore
/*    */     //   1460: iconst_2
/*    */     //   1461: aload_2
/*    */     //   1462: aastore
/*    */     //   1463: invokevirtual AUX : ([Lf/JG0;)Lf/U90;
/*    */     //   1466: iconst_0
/*    */     //   1467: swap
/*    */     //   1468: aastore
/*    */     //   1469: iconst_1
/*    */     //   1470: anewarray f/JG0
/*    */     //   1473: dup
/*    */     //   1474: iconst_0
/*    */     //   1475: aload #15
/*    */     //   1477: aastore
/*    */     //   1478: invokevirtual AUX : ([Lf/JG0;)Lf/U90;
/*    */     //   1481: iconst_1
/*    */     //   1482: swap
/*    */     //   1483: aastore
/*    */     //   1484: invokevirtual cOM8 : ([Lf/U90;)Lf/U90;
/*    */     //   1487: iconst_5
/*    */     //   1488: invokevirtual Aq : (I)Lf/U90;
/*    */     //   1491: astore_2
/*    */     //   1492: goto -> 1631
/*    */     //   1495: aload #13
/*    */     //   1497: dup
/*    */     //   1498: invokevirtual mE0 : ()Lf/g0;
/*    */     //   1501: iconst_2
/*    */     //   1502: anewarray f/U90
/*    */     //   1505: dup
/*    */     //   1506: dup
/*    */     //   1507: aload #13
/*    */     //   1509: swap
/*    */     //   1510: aload #13
/*    */     //   1512: iconst_3
/*    */     //   1513: anewarray f/JG0
/*    */     //   1516: dup
/*    */     //   1517: dup2
/*    */     //   1518: iconst_0
/*    */     //   1519: aload #11
/*    */     //   1521: aastore
/*    */     //   1522: iconst_1
/*    */     //   1523: aload #12
/*    */     //   1525: aastore
/*    */     //   1526: iconst_2
/*    */     //   1527: aload_2
/*    */     //   1528: aastore
/*    */     //   1529: invokevirtual vo0 : ([Lf/JG0;)Lf/U90;
/*    */     //   1532: iconst_0
/*    */     //   1533: swap
/*    */     //   1534: aastore
/*    */     //   1535: iconst_1
/*    */     //   1536: anewarray f/JG0
/*    */     //   1539: dup
/*    */     //   1540: iconst_0
/*    */     //   1541: aload #15
/*    */     //   1543: aastore
/*    */     //   1544: invokevirtual vo0 : ([Lf/JG0;)Lf/U90;
/*    */     //   1547: invokevirtual Em0 : ()Lf/U90;
/*    */     //   1550: aload #14
/*    */     //   1552: invokevirtual Ya : (Lf/JG0;)Lf/U90;
/*    */     //   1555: iconst_1
/*    */     //   1556: swap
/*    */     //   1557: aastore
/*    */     //   1558: invokevirtual cOM8 : ([Lf/U90;)Lf/U90;
/*    */     //   1561: astore_1
/*    */     //   1562: invokevirtual d7 : ()Lf/cr0;
/*    */     //   1565: iconst_5
/*    */     //   1566: invokevirtual Aq : (I)Lf/U90;
/*    */     //   1569: iconst_2
/*    */     //   1570: anewarray f/U90
/*    */     //   1573: dup
/*    */     //   1574: dup
/*    */     //   1575: aload #13
/*    */     //   1577: swap
/*    */     //   1578: aload #13
/*    */     //   1580: iconst_3
/*    */     //   1581: anewarray f/JG0
/*    */     //   1584: dup
/*    */     //   1585: dup2
/*    */     //   1586: iconst_0
/*    */     //   1587: aload #11
/*    */     //   1589: aastore
/*    */     //   1590: iconst_1
/*    */     //   1591: aload #12
/*    */     //   1593: aastore
/*    */     //   1594: iconst_2
/*    */     //   1595: aload_2
/*    */     //   1596: aastore
/*    */     //   1597: invokevirtual AUX : ([Lf/JG0;)Lf/U90;
/*    */     //   1600: iconst_0
/*    */     //   1601: swap
/*    */     //   1602: aastore
/*    */     //   1603: iconst_2
/*    */     //   1604: anewarray f/JG0
/*    */     //   1607: dup
/*    */     //   1608: dup
/*    */     //   1609: iconst_0
/*    */     //   1610: aload #15
/*    */     //   1612: aastore
/*    */     //   1613: iconst_1
/*    */     //   1614: aload #14
/*    */     //   1616: aastore
/*    */     //   1617: invokevirtual AUX : ([Lf/JG0;)Lf/U90;
/*    */     //   1620: iconst_1
/*    */     //   1621: swap
/*    */     //   1622: aastore
/*    */     //   1623: invokevirtual cOM8 : ([Lf/U90;)Lf/U90;
/*    */     //   1626: iconst_5
/*    */     //   1627: invokevirtual Aq : (I)Lf/U90;
/*    */     //   1630: astore_2
/*    */     //   1631: aload_0
/*    */     //   1632: dup
/*    */     //   1633: dup2
/*    */     //   1634: aload #13
/*    */     //   1636: aload_2
/*    */     //   1637: aload #13
/*    */     //   1639: aload_1
/*    */     //   1640: invokevirtual WN : (Lf/U90;)V
/*    */     //   1643: invokevirtual rK0 : (Lf/U90;)V
/*    */     //   1646: new f/dQ
/*    */     //   1649: dup
/*    */     //   1650: sipush #1701
/*    */     //   1653: invokestatic OH0 : (I)Ljava/lang/String;
/*    */     //   1656: invokespecial <init> : (Ljava/lang/String;)V
/*    */     //   1659: putfield XH : Lf/dQ;
/*    */     //   1662: new f/dQ
/*    */     //   1665: dup
/*    */     //   1666: sipush #1702
/*    */     //   1669: invokestatic OH0 : (I)Ljava/lang/String;
/*    */     //   1672: invokespecial <init> : (Ljava/lang/String;)V
/*    */     //   1675: putfield Kv0 : Lf/dQ;
/*    */     //   1678: new f/dQ
/*    */     //   1681: dup
/*    */     //   1682: sipush #1728
/*    */     //   1685: invokestatic OH0 : (I)Ljava/lang/String;
/*    */     //   1688: invokespecial <init> : (Ljava/lang/String;)V
/*    */     //   1691: putfield oA0 : Lf/dQ;
/*    */     //   1694: new f/dQ
/*    */     //   1697: dup
/*    */     //   1698: sipush #1762
/*    */     //   1701: invokestatic OH0 : (I)Ljava/lang/String;
/*    */     //   1704: invokespecial <init> : (Ljava/lang/String;)V
/*    */     //   1707: putfield EO : Lf/dQ;
/*    */     //   1710: new f/of
/*    */     //   1713: dup
/*    */     //   1714: astore_1
/*    */     //   1715: aload_0
/*    */     //   1716: aload_1
/*    */     //   1717: dup
/*    */     //   1718: aload_0
/*    */     //   1719: aload_1
/*    */     //   1720: dup
/*    */     //   1721: invokespecial <init> : ()V
/*    */     //   1724: putfield BW : Lf/of;
/*    */     //   1727: invokevirtual LE : ()V
/*    */     //   1730: ldc_w 'editfield-search'
/*    */     //   1733: invokevirtual Xu : (Ljava/lang/String;)V
/*    */     //   1736: <illegal opcode> SX : (Lf/Hy;)Lf/a70;
/*    */     //   1741: invokevirtual JD0 : (Lf/a70;)V
/*    */     //   1744: new f/B9
/*    */     //   1747: dup
/*    */     //   1748: dup
/*    */     //   1749: aload_0
/*    */     //   1750: swap
/*    */     //   1751: dup
/*    */     //   1752: invokespecial <init> : ()V
/*    */     //   1755: putfield y6 : Lf/B9;
/*    */     //   1758: new f/OZ
/*    */     //   1761: dup
/*    */     //   1762: dup2
/*    */     //   1763: astore_1
/*    */     //   1764: invokespecial <init> : ()V
/*    */     //   1767: getstatic f/F40.ef0 : Lf/F40;
/*    */     //   1770: sipush #276
/*    */     //   1773: iconst_1
/*    */     //   1774: invokestatic Qf0 : (Lf/F40;II)Ljava/lang/String;
/*    */     //   1777: invokestatic Gt0 : (Ljava/lang/String;)Ljava/lang/String;
/*    */     //   1780: invokevirtual i3 : (Ljava/lang/Object;)V
/*    */     //   1783: sipush #1763
/*    */     //   1786: invokestatic OH0 : (I)Ljava/lang/String;
/*    */     //   1789: invokevirtual i3 : (Ljava/lang/Object;)V
/*    */     //   1792: iconst_m1
/*    */     //   1793: invokevirtual Be : (B)V
/*    */     //   1796: bipush #-2
/*    */     //   1798: invokevirtual Be : (B)V
/*    */     //   1801: getstatic f/Mk0.Pc0 : [B
/*    */     //   1804: astore_2
/*    */     //   1805: iconst_5
/*    */     //   1806: istore_3
/*    */     //   1807: iconst_0
/*    */     //   1808: istore #4
/*    */     //   1810: iload #4
/*    */     //   1812: iload_3
/*    */     //   1813: if_icmpge -> 1887
/*    */     //   1816: aload_2
/*    */     //   1817: iload #4
/*    */     //   1819: baload
/*    */     //   1820: istore #5
/*    */     //   1822: getstatic f/km.mI0 : Lf/P1;
/*    */     //   1825: iload #5
/*    */     //   1827: invokevirtual s2 : (B)Z
/*    */     //   1830: ifne -> 1836
/*    */     //   1833: goto -> 1881
/*    */     //   1836: aload_0
/*    */     //   1837: aload_1
/*    */     //   1838: new java/lang/StringBuilder
/*    */     //   1841: dup
/*    */     //   1842: iload #5
/*    */     //   1844: swap
/*    */     //   1845: invokespecial <init> : ()V
/*    */     //   1848: invokestatic zd : (B)Ljava/lang/String;
/*    */     //   1851: invokevirtual append : (Ljava/lang/String;)Ljava/lang/StringBuilder;
/*    */     //   1854: ldc_w ' '
/*    */     //   1857: invokevirtual append : (Ljava/lang/String;)Ljava/lang/StringBuilder;
/*    */     //   1860: iconst_1
/*    */     //   1861: invokestatic OH0 : (I)Ljava/lang/String;
/*    */     //   1864: invokevirtual append : (Ljava/lang/String;)Ljava/lang/StringBuilder;
/*    */     //   1867: invokevirtual toString : ()Ljava/lang/String;
/*    */     //   1870: invokevirtual i3 : (Ljava/lang/Object;)V
/*    */     //   1873: getfield y6 : Lf/B9;
/*    */     //   1876: iload #5
/*    */     //   1878: invokevirtual Be : (B)V
/*    */     //   1881: iinc #4, 1
/*    */     //   1884: goto -> 1810
/*    */     //   1887: new f/W1
/*    */     //   1890: dup
/*    */     //   1891: astore_2
/*    */     //   1892: aload_0
/*    */     //   1893: aload_2
/*    */     //   1894: aload_0
/*    */     //   1895: aload_2
/*    */     //   1896: dup
/*    */     //   1897: aload_1
/*    */     //   1898: invokespecial <init> : (Lf/cQ;)V
/*    */     //   1901: putfield l80 : Lf/W1;
/*    */     //   1904: iconst_0
/*    */     //   1905: invokevirtual Z30 : (I)V
/*    */     //   1908: <illegal opcode> run : (Lf/Hy;)Ljava/lang/Runnable;
/*    */     //   1913: invokevirtual D30 : (Ljava/lang/Runnable;)V
/*    */     //   1916: new f/OZ
/*    */     //   1919: dup
/*    */     //   1920: dup
/*    */     //   1921: astore_1
/*    */     //   1922: invokespecial <init> : ()V
/*    */     //   1925: sipush #5749
/*    */     //   1928: invokestatic OH0 : (I)Ljava/lang/String;
/*    */     //   1931: invokevirtual i3 : (Ljava/lang/Object;)V
/*    */     //   1934: getstatic f/DO.HB0 : [Lf/DO;
/*    */     //   1937: dup
/*    */     //   1938: astore_2
/*    */     //   1939: arraylength
/*    */     //   1940: istore_3
/*    */     //   1941: iconst_0
/*    */     //   1942: istore #4
/*    */     //   1944: iload #4
/*    */     //   1946: iload_3
/*    */     //   1947: if_icmpge -> 1970
/*    */     //   1950: aload_1
/*    */     //   1951: aload_2
/*    */     //   1952: iload #4
/*    */     //   1954: aaload
/*    */     //   1955: invokevirtual V00 : ()I
/*    */     //   1958: invokestatic OH0 : (I)Ljava/lang/String;
/*    */     //   1961: invokevirtual i3 : (Ljava/lang/Object;)V
/*    */     //   1964: iinc #4, 1
/*    */     //   1967: goto -> 1944
/*    */     //   1970: aload_0
/*    */     //   1971: dup
/*    */     //   1972: dup
/*    */     //   1973: dup2
/*    */     //   1974: new f/W1
/*    */     //   1977: dup
/*    */     //   1978: astore_2
/*    */     //   1979: aload_0
/*    */     //   1980: aload_2
/*    */     //   1981: aload_0
/*    */     //   1982: aload_2
/*    */     //   1983: dup
/*    */     //   1984: aload_1
/*    */     //   1985: invokespecial <init> : (Lf/cQ;)V
/*    */     //   1988: putfield W7 : Lf/W1;
/*    */     //   1991: iconst_0
/*    */     //   1992: invokevirtual Z30 : (I)V
/*    */     //   1995: <illegal opcode> run : (Lf/Hy;)Ljava/lang/Runnable;
/*    */     //   2000: invokevirtual D30 : (Ljava/lang/Runnable;)V
/*    */     //   2003: getfield PRn : Lf/Ip;
/*    */     //   2006: invokevirtual d7 : ()Lf/cr0;
/*    */     //   2009: dup
/*    */     //   2010: astore_1
/*    */     //   2011: aload_0
/*    */     //   2012: getfield PRn : Lf/Ip;
/*    */     //   2015: invokevirtual mE0 : ()Lf/g0;
/*    */     //   2018: dup
/*    */     //   2019: astore_3
/*    */     //   2020: iconst_3
/*    */     //   2021: anewarray f/JG0
/*    */     //   2024: dup
/*    */     //   2025: dup2
/*    */     //   2026: aload_0
/*    */     //   2027: swap
/*    */     //   2028: aload_0
/*    */     //   2029: getfield l80 : Lf/W1;
/*    */     //   2032: iconst_0
/*    */     //   2033: swap
/*    */     //   2034: aastore
/*    */     //   2035: getfield BW : Lf/of;
/*    */     //   2038: iconst_1
/*    */     //   2039: swap
/*    */     //   2040: aastore
/*    */     //   2041: iconst_2
/*    */     //   2042: aload_2
/*    */     //   2043: aastore
/*    */     //   2044: invokevirtual Mg : ([Lf/JG0;)Lf/U90;
/*    */     //   2047: pop
/*    */     //   2048: iconst_3
/*    */     //   2049: anewarray f/JG0
/*    */     //   2052: dup
/*    */     //   2053: dup2
/*    */     //   2054: aload_0
/*    */     //   2055: swap
/*    */     //   2056: aload_0
/*    */     //   2057: getfield l80 : Lf/W1;
/*    */     //   2060: iconst_0
/*    */     //   2061: swap
/*    */     //   2062: aastore
/*    */     //   2063: getfield BW : Lf/of;
/*    */     //   2066: iconst_1
/*    */     //   2067: swap
/*    */     //   2068: aastore
/*    */     //   2069: iconst_2
/*    */     //   2070: aload_2
/*    */     //   2071: aastore
/*    */     //   2072: invokevirtual Mg : ([Lf/JG0;)Lf/U90;
/*    */     //   2075: pop
/*    */     //   2076: getfield PRn : Lf/Ip;
/*    */     //   2079: dup
/*    */     //   2080: invokevirtual d7 : ()Lf/cr0;
/*    */     //   2083: bipush #24
/*    */     //   2085: invokevirtual Aq : (I)Lf/U90;
/*    */     //   2088: aload_3
/*    */     //   2089: invokevirtual ee0 : (Lf/U90;)Lf/U90;
/*    */     //   2092: aload_0
/*    */     //   2093: getfield up : Lf/rS;
/*    */     //   2096: invokevirtual Ya : (Lf/JG0;)Lf/U90;
/*    */     //   2099: aload_0
/*    */     //   2100: getfield PRn : Lf/Ip;
/*    */     //   2103: dup
/*    */     //   2104: astore_2
/*    */     //   2105: iconst_4
/*    */     //   2106: anewarray f/U90
/*    */     //   2109: dup
/*    */     //   2110: dup
/*    */     //   2111: astore_3
/*    */     //   2112: aload_0
/*    */     //   2113: aload_3
/*    */     //   2114: aload_0
/*    */     //   2115: aload_3
/*    */     //   2116: aload_0
/*    */     //   2117: aload_3
/*    */     //   2118: aload_2
/*    */     //   2119: iconst_2
/*    */     //   2120: anewarray f/JG0
/*    */     //   2123: dup
/*    */     //   2124: dup
/*    */     //   2125: aload_0
/*    */     //   2126: swap
/*    */     //   2127: aload_0
/*    */     //   2128: getfield XH : Lf/dQ;
/*    */     //   2131: iconst_0
/*    */     //   2132: swap
/*    */     //   2133: aastore
/*    */     //   2134: getfield vJ : Lf/IN;
/*    */     //   2137: iconst_1
/*    */     //   2138: swap
/*    */     //   2139: aastore
/*    */     //   2140: invokevirtual vo0 : ([Lf/JG0;)Lf/U90;
/*    */     //   2143: iconst_0
/*    */     //   2144: swap
/*    */     //   2145: aastore
/*    */     //   2146: getfield PRn : Lf/Ip;
/*    */     //   2149: iconst_2
/*    */     //   2150: anewarray f/JG0
/*    */     //   2153: dup
/*    */     //   2154: dup
/*    */     //   2155: aload_0
/*    */     //   2156: swap
/*    */     //   2157: aload_0
/*    */     //   2158: getfield Kv0 : Lf/dQ;
/*    */     //   2161: iconst_0
/*    */     //   2162: swap
/*    */     //   2163: aastore
/*    */     //   2164: getfield TH0 : Lf/IN;
/*    */     //   2167: iconst_1
/*    */     //   2168: swap
/*    */     //   2169: aastore
/*    */     //   2170: invokevirtual vo0 : ([Lf/JG0;)Lf/U90;
/*    */     //   2173: iconst_1
/*    */     //   2174: swap
/*    */     //   2175: aastore
/*    */     //   2176: getfield PRn : Lf/Ip;
/*    */     //   2179: iconst_2
/*    */     //   2180: anewarray f/JG0
/*    */     //   2183: dup
/*    */     //   2184: dup
/*    */     //   2185: aload_0
/*    */     //   2186: swap
/*    */     //   2187: aload_0
/*    */     //   2188: getfield oA0 : Lf/dQ;
/*    */     //   2191: iconst_0
/*    */     //   2192: swap
/*    */     //   2193: aastore
/*    */     //   2194: getfield nW : Lf/IN;
/*    */     //   2197: iconst_1
/*    */     //   2198: swap
/*    */     //   2199: aastore
/*    */     //   2200: invokevirtual vo0 : ([Lf/JG0;)Lf/U90;
/*    */     //   2203: iconst_2
/*    */     //   2204: swap
/*    */     //   2205: aastore
/*    */     //   2206: getfield PRn : Lf/Ip;
/*    */     //   2209: iconst_2
/*    */     //   2210: anewarray f/JG0
/*    */     //   2213: dup
/*    */     //   2214: dup
/*    */     //   2215: aload_0
/*    */     //   2216: swap
/*    */     //   2217: aload_0
/*    */     //   2218: getfield EO : Lf/dQ;
/*    */     //   2221: iconst_0
/*    */     //   2222: swap
/*    */     //   2223: aastore
/*    */     //   2224: getfield GC0 : Lf/IN;
/*    */     //   2227: iconst_1
/*    */     //   2228: swap
/*    */     //   2229: aastore
/*    */     //   2230: invokevirtual vo0 : ([Lf/JG0;)Lf/U90;
/*    */     //   2233: iconst_3
/*    */     //   2234: swap
/*    */     //   2235: aastore
/*    */     //   2236: invokevirtual Yw0 : ([Lf/U90;)Lf/U90;
/*    */     //   2239: invokevirtual ee0 : (Lf/U90;)Lf/U90;
/*    */     //   2242: iconst_5
/*    */     //   2243: invokevirtual Aq : (I)Lf/U90;
/*    */     //   2246: invokevirtual WN : (Lf/U90;)V
/*    */     //   2249: getfield PRn : Lf/Ip;
/*    */     //   2252: dup
/*    */     //   2253: invokevirtual mE0 : ()Lf/g0;
/*    */     //   2256: aload_1
/*    */     //   2257: invokevirtual ee0 : (Lf/U90;)Lf/U90;
/*    */     //   2260: aload_0
/*    */     //   2261: getfield up : Lf/rS;
/*    */     //   2264: invokevirtual Ya : (Lf/JG0;)Lf/U90;
/*    */     //   2267: aload_0
/*    */     //   2268: getfield PRn : Lf/Ip;
/*    */     //   2271: dup
/*    */     //   2272: astore_1
/*    */     //   2273: iconst_4
/*    */     //   2274: anewarray f/U90
/*    */     //   2277: dup
/*    */     //   2278: dup
/*    */     //   2279: astore_2
/*    */     //   2280: aload_0
/*    */     //   2281: aload_2
/*    */     //   2282: aload_0
/*    */     //   2283: aload_2
/*    */     //   2284: aload_0
/*    */     //   2285: aload_2
/*    */     //   2286: aload_1
/*    */     //   2287: iconst_2
/*    */     //   2288: anewarray f/JG0
/*    */     //   2291: dup
/*    */     //   2292: dup
/*    */     //   2293: aload_0
/*    */     //   2294: swap
/*    */     //   2295: aload_0
/*    */     //   2296: getfield XH : Lf/dQ;
/*    */     //   2299: iconst_0
/*    */     //   2300: swap
/*    */     //   2301: aastore
/*    */     //   2302: getfield vJ : Lf/IN;
/*    */     //   2305: iconst_1
/*    */     //   2306: swap
/*    */     //   2307: aastore
/*    */     //   2308: invokevirtual AUX : ([Lf/JG0;)Lf/U90;
/*    */     //   2311: iconst_0
/*    */     //   2312: swap
/*    */     //   2313: aastore
/*    */     //   2314: getfield PRn : Lf/Ip;
/*    */     //   2317: iconst_2
/*    */     //   2318: anewarray f/JG0
/*    */     //   2321: dup
/*    */     //   2322: dup
/*    */     //   2323: aload_0
/*    */     //   2324: swap
/*    */     //   2325: aload_0
/*    */     //   2326: getfield Kv0 : Lf/dQ;
/*    */     //   2329: iconst_0
/*    */     //   2330: swap
/*    */     //   2331: aastore
/*    */     //   2332: getfield TH0 : Lf/IN;
/*    */     //   2335: iconst_1
/*    */     //   2336: swap
/*    */     //   2337: aastore
/*    */     //   2338: invokevirtual AUX : ([Lf/JG0;)Lf/U90;
/*    */     //   2341: iconst_1
/*    */     //   2342: swap
/*    */     //   2343: aastore
/*    */     //   2344: getfield PRn : Lf/Ip;
/*    */     //   2347: iconst_2
/*    */     //   2348: anewarray f/JG0
/*    */     //   2351: dup
/*    */     //   2352: dup
/*    */     //   2353: aload_0
/*    */     //   2354: swap
/*    */     //   2355: aload_0
/*    */     //   2356: getfield oA0 : Lf/dQ;
/*    */     //   2359: iconst_0
/*    */     //   2360: swap
/*    */     //   2361: aastore
/*    */     //   2362: getfield nW : Lf/IN;
/*    */     //   2365: iconst_1
/*    */     //   2366: swap
/*    */     //   2367: aastore
/*    */     //   2368: invokevirtual AUX : ([Lf/JG0;)Lf/U90;
/*    */     //   2371: iconst_2
/*    */     //   2372: swap
/*    */     //   2373: aastore
/*    */     //   2374: getfield PRn : Lf/Ip;
/*    */     //   2377: iconst_2
/*    */     //   2378: anewarray f/JG0
/*    */     //   2381: dup
/*    */     //   2382: dup
/*    */     //   2383: aload_0
/*    */     //   2384: swap
/*    */     //   2385: aload_0
/*    */     //   2386: getfield EO : Lf/dQ;
/*    */     //   2389: iconst_0
/*    */     //   2390: swap
/*    */     //   2391: aastore
/*    */     //   2392: getfield GC0 : Lf/IN;
/*    */     //   2395: iconst_1
/*    */     //   2396: swap
/*    */     //   2397: aastore
/*    */     //   2398: invokevirtual AUX : ([Lf/JG0;)Lf/U90;
/*    */     //   2401: iconst_3
/*    */     //   2402: swap
/*    */     //   2403: aastore
/*    */     //   2404: invokevirtual Gs : ([Lf/U90;)Lf/U90;
/*    */     //   2407: invokevirtual ee0 : (Lf/U90;)Lf/U90;
/*    */     //   2410: invokevirtual rK0 : (Lf/U90;)V
/*    */     //   2413: getfield PRn : Lf/Ip;
/*    */     //   2416: invokevirtual J8 : (Lf/JG0;)V
/*    */     //   2419: new f/Ip
/*    */     //   2422: dup
/*    */     //   2423: dup
/*    */     //   2424: dup2
/*    */     //   2425: astore_1
/*    */     //   2426: aload_0
/*    */     //   2427: dup
/*    */     //   2428: dup
/*    */     //   2429: aload_1
/*    */     //   2430: dup
/*    */     //   2431: invokespecial <init> : ()V
/*    */     //   2434: putfield ci0 : Lf/Ip;
/*    */     //   2437: new f/gl
/*    */     //   2440: dup
/*    */     //   2441: dup
/*    */     //   2442: astore_1
/*    */     //   2443: invokespecial <init> : ()V
/*    */     //   2446: putfield instanceof : Lf/gl;
/*    */     //   2449: new f/rS
/*    */     //   2452: dup
/*    */     //   2453: dup
/*    */     //   2454: astore_2
/*    */     //   2455: aload_1
/*    */     //   2456: invokespecial <init> : (Lf/JG0;)V
/*    */     //   2459: putfield ED0 : Lf/rS;
/*    */     //   2462: invokevirtual mE0 : ()Lf/g0;
/*    */     //   2465: aload_2
/*    */     //   2466: invokevirtual Ya : (Lf/JG0;)Lf/U90;
/*    */     //   2469: invokevirtual WN : (Lf/U90;)V
/*    */     //   2472: invokevirtual d7 : ()Lf/cr0;
/*    */     //   2475: invokevirtual Em0 : ()Lf/U90;
/*    */     //   2478: aload_2
/*    */     //   2479: invokevirtual Ya : (Lf/JG0;)Lf/U90;
/*    */     //   2482: invokevirtual Em0 : ()Lf/U90;
/*    */     //   2485: invokevirtual rK0 : (Lf/U90;)V
/*    */     //   2488: new f/Ip
/*    */     //   2491: dup
/*    */     //   2492: aload_0
/*    */     //   2493: swap
/*    */     //   2494: dup
/*    */     //   2495: invokespecial <init> : ()V
/*    */     //   2498: putfield COm7 : Lf/Ip;
/*    */     //   2501: ldc_w 'label-area-monsterdex'
/*    */     //   2504: invokevirtual Xu : (Ljava/lang/String;)V
/*    */     //   2507: iconst_0
/*    */     //   2508: istore_1
/*    */     //   2509: iload_1
/*    */     //   2510: aload_0
/*    */     //   2511: getfield Sk0 : [Lf/IN;
/*    */     //   2514: dup
/*    */     //   2515: astore_2
/*    */     //   2516: arraylength
/*    */     //   2517: if_icmpge -> 2538
/*    */     //   2520: aload_2
/*    */     //   2521: new f/IN
/*    */     //   2524: dup
/*    */     //   2525: astore_2
/*    */     //   2526: invokespecial <init> : ()V
/*    */     //   2529: iload_1
/*    */     //   2530: aload_2
/*    */     //   2531: aastore
/*    */     //   2532: iinc #1, 1
/*    */     //   2535: goto -> 2509
/*    */     //   2538: aload_0
/*    */     //   2539: dup
/*    */     //   2540: dup
/*    */     //   2541: dup2
/*    */     //   2542: dup2
/*    */     //   2543: dup2
/*    */     //   2544: aload_2
/*    */     //   2545: iconst_0
/*    */     //   2546: aaload
/*    */     //   2547: ldc_w 'progressbar-hp'
/*    */     //   2550: invokevirtual Xu : (Ljava/lang/String;)V
/*    */     //   2553: getfield Sk0 : [Lf/IN;
/*    */     //   2556: iconst_1
/*    */     //   2557: aaload
/*    */     //   2558: ldc_w 'progressbar-attack'
/*    */     //   2561: invokevirtual Xu : (Ljava/lang/String;)V
/*    */     //   2564: getfield Sk0 : [Lf/IN;
/*    */     //   2567: iconst_2
/*    */     //   2568: aaload
/*    */     //   2569: ldc_w 'progressbar-defense'
/*    */     //   2572: invokevirtual Xu : (Ljava/lang/String;)V
/*    */     //   2575: getfield Sk0 : [Lf/IN;
/*    */     //   2578: iconst_3
/*    */     //   2579: aaload
/*    */     //   2580: ldc_w 'progressbar-spatk'
/*    */     //   2583: invokevirtual Xu : (Ljava/lang/String;)V
/*    */     //   2586: getfield Sk0 : [Lf/IN;
/*    */     //   2589: iconst_4
/*    */     //   2590: aaload
/*    */     //   2591: ldc_w 'progressbar-spdef'
/*    */     //   2594: invokevirtual Xu : (Ljava/lang/String;)V
/*    */     //   2597: getfield Sk0 : [Lf/IN;
/*    */     //   2600: iconst_5
/*    */     //   2601: aaload
/*    */     //   2602: ldc_w 'progressbar-speed'
/*    */     //   2605: invokevirtual Xu : (Ljava/lang/String;)V
/*    */     //   2608: getfield Sk0 : [Lf/IN;
/*    */     //   2611: bipush #6
/*    */     //   2613: aaload
/*    */     //   2614: ldc_w 'progressbar-total'
/*    */     //   2617: invokevirtual Xu : (Ljava/lang/String;)V
/*    */     //   2620: getfield Sk0 : [Lf/IN;
/*    */     //   2623: dup
/*    */     //   2624: arraylength
/*    */     //   2625: anewarray f/dQ
/*    */     //   2628: astore_1
/*    */     //   2629: arraylength
/*    */     //   2630: anewarray f/JG0
/*    */     //   2633: astore_2
/*    */     //   2634: getfield COm7 : Lf/Ip;
/*    */     //   2637: invokevirtual mE0 : ()Lf/g0;
/*    */     //   2640: astore_3
/*    */     //   2641: getfield COm7 : Lf/Ip;
/*    */     //   2644: invokevirtual d7 : ()Lf/cr0;
/*    */     //   2647: astore #4
/*    */     //   2649: iconst_0
/*    */     //   2650: istore #5
/*    */     //   2652: iload #5
/*    */     //   2654: aload_0
/*    */     //   2655: getfield Sk0 : [Lf/IN;
/*    */     //   2658: dup
/*    */     //   2659: astore #6
/*    */     //   2661: arraylength
/*    */     //   2662: if_icmpge -> 2899
/*    */     //   2665: iload #5
/*    */     //   2667: iconst_1
/*    */     //   2668: iadd
/*    */     //   2669: dup
/*    */     //   2670: istore #7
/*    */     //   2672: aload #6
/*    */     //   2674: arraylength
/*    */     //   2675: if_icmpge -> 2712
/*    */     //   2678: aload_1
/*    */     //   2679: iload #5
/*    */     //   2681: new f/dQ
/*    */     //   2684: dup
/*    */     //   2685: astore #6
/*    */     //   2687: getstatic f/hR.Tm0 : [Lf/hR;
/*    */     //   2690: iload #5
/*    */     //   2692: aaload
/*    */     //   2693: invokevirtual E0 : ()B
/*    */     //   2696: sipush #1720
/*    */     //   2699: iadd
/*    */     //   2700: invokestatic OH0 : (I)Ljava/lang/String;
/*    */     //   2703: invokespecial <init> : (Ljava/lang/String;)V
/*    */     //   2706: aload #6
/*    */     //   2708: aastore
/*    */     //   2709: goto -> 2738
/*    */     //   2712: aload_1
/*    */     //   2713: iload #5
/*    */     //   2715: new f/dQ
/*    */     //   2718: dup
/*    */     //   2719: astore #6
/*    */     //   2721: getstatic f/hR.Tm0 : [Lf/hR;
/*    */     //   2724: arraylength
/*    */     //   2725: sipush #1720
/*    */     //   2728: iadd
/*    */     //   2729: invokestatic OH0 : (I)Ljava/lang/String;
/*    */     //   2732: invokespecial <init> : (Ljava/lang/String;)V
/*    */     //   2735: aload #6
/*    */     //   2737: aastore
/*    */     //   2738: aload #4
/*    */     //   2740: aload_0
/*    */     //   2741: aload_3
/*    */     //   2742: aload_0
/*    */     //   2743: dup
/*    */     //   2744: getfield oe0 : [Lf/dQ;
/*    */     //   2747: iload #5
/*    */     //   2749: new f/dQ
/*    */     //   2752: dup
/*    */     //   2753: astore #6
/*    */     //   2755: ldc_w '-'
/*    */     //   2758: invokespecial <init> : (Ljava/lang/String;)V
/*    */     //   2761: aload #6
/*    */     //   2763: aastore
/*    */     //   2764: new f/JG0
/*    */     //   2767: dup
/*    */     //   2768: astore #6
/*    */     //   2770: aload_0
/*    */     //   2771: aload_2
/*    */     //   2772: iload #5
/*    */     //   2774: aload #6
/*    */     //   2776: invokespecial <init> : ()V
/*    */     //   2779: aload #6
/*    */     //   2781: aastore
/*    */     //   2782: getfield Sk0 : [Lf/IN;
/*    */     //   2785: iload #5
/*    */     //   2787: aaload
/*    */     //   2788: invokevirtual J8 : (Lf/JG0;)V
/*    */     //   2791: getfield COm7 : Lf/Ip;
/*    */     //   2794: invokevirtual d7 : ()Lf/cr0;
/*    */     //   2797: invokevirtual Em0 : ()Lf/U90;
/*    */     //   2800: iconst_3
/*    */     //   2801: anewarray f/JG0
/*    */     //   2804: dup
/*    */     //   2805: dup
/*    */     //   2806: astore #6
/*    */     //   2808: aload_2
/*    */     //   2809: iload #5
/*    */     //   2811: aload #6
/*    */     //   2813: aload_0
/*    */     //   2814: aload #6
/*    */     //   2816: aload_1
/*    */     //   2817: iload #5
/*    */     //   2819: aaload
/*    */     //   2820: iconst_0
/*    */     //   2821: swap
/*    */     //   2822: aastore
/*    */     //   2823: getfield oe0 : [Lf/dQ;
/*    */     //   2826: iload #5
/*    */     //   2828: aaload
/*    */     //   2829: iconst_1
/*    */     //   2830: swap
/*    */     //   2831: aastore
/*    */     //   2832: aaload
/*    */     //   2833: iconst_2
/*    */     //   2834: swap
/*    */     //   2835: aastore
/*    */     //   2836: invokevirtual Mg : ([Lf/JG0;)Lf/U90;
/*    */     //   2839: invokevirtual Em0 : ()Lf/U90;
/*    */     //   2842: invokevirtual ee0 : (Lf/U90;)Lf/U90;
/*    */     //   2845: pop
/*    */     //   2846: getfield COm7 : Lf/Ip;
/*    */     //   2849: iconst_3
/*    */     //   2850: anewarray f/JG0
/*    */     //   2853: dup
/*    */     //   2854: dup
/*    */     //   2855: astore #6
/*    */     //   2857: aload_2
/*    */     //   2858: iload #5
/*    */     //   2860: aload #6
/*    */     //   2862: aload_0
/*    */     //   2863: aload #6
/*    */     //   2865: aload_1
/*    */     //   2866: iload #5
/*    */     //   2868: aaload
/*    */     //   2869: iconst_0
/*    */     //   2870: swap
/*    */     //   2871: aastore
/*    */     //   2872: getfield oe0 : [Lf/dQ;
/*    */     //   2875: iload #5
/*    */     //   2877: aaload
/*    */     //   2878: iconst_1
/*    */     //   2879: swap
/*    */     //   2880: aastore
/*    */     //   2881: aaload
/*    */     //   2882: iconst_2
/*    */     //   2883: swap
/*    */     //   2884: aastore
/*    */     //   2885: invokevirtual AUX : ([Lf/JG0;)Lf/U90;
/*    */     //   2888: invokevirtual ee0 : (Lf/U90;)Lf/U90;
/*    */     //   2891: pop
/*    */     //   2892: iload #7
/*    */     //   2894: istore #5
/*    */     //   2896: goto -> 2652
/*    */     //   2899: aload_0
/*    */     //   2900: dup
/*    */     //   2901: dup2
/*    */     //   2902: getfield COm7 : Lf/Ip;
/*    */     //   2905: aload_3
/*    */     //   2906: invokevirtual rK0 : (Lf/U90;)V
/*    */     //   2909: getfield COm7 : Lf/Ip;
/*    */     //   2912: aload #4
/*    */     //   2914: invokevirtual WN : (Lf/U90;)V
/*    */     //   2917: new f/Ip
/*    */     //   2920: dup
/*    */     //   2921: dup2
/*    */     //   2922: dup2
/*    */     //   2923: astore_1
/*    */     //   2924: aload_0
/*    */     //   2925: aload_1
/*    */     //   2926: dup
/*    */     //   2927: invokespecial <init> : ()V
/*    */     //   2930: putfield y8 : Lf/Ip;
/*    */     //   2933: ldc_w 'label-area-monsterdex'
/*    */     //   2936: invokevirtual Xu : (Ljava/lang/String;)V
/*    */     //   2939: invokevirtual d7 : ()Lf/cr0;
/*    */     //   2942: invokevirtual rK0 : (Lf/U90;)V
/*    */     //   2945: invokevirtual mE0 : ()Lf/g0;
/*    */     //   2948: invokevirtual WN : (Lf/U90;)V
/*    */     //   2951: new f/rS
/*    */     //   2954: dup
/*    */     //   2955: astore_2
/*    */     //   2956: aload_1
/*    */     //   2957: aload_0
/*    */     //   2958: aload_2
/*    */     //   2959: dup
/*    */     //   2960: invokespecial <init> : ()V
/*    */     //   2963: putfield Uz0 : Lf/rS;
/*    */     //   2966: invokevirtual Gz0 : (Lf/JG0;)V
/*    */     //   2969: new f/Ip
/*    */     //   2972: dup
/*    */     //   2973: dup
/*    */     //   2974: astore_1
/*    */     //   2975: invokespecial <init> : ()V
/*    */     //   2978: putfield O40 : Lf/Ip;
/*    */     //   2981: new f/Ip
/*    */     //   2984: dup
/*    */     //   2985: dup
/*    */     //   2986: dup2
/*    */     //   2987: astore_3
/*    */     //   2988: aload_1
/*    */     //   2989: dup
/*    */     //   2990: dup2
/*    */     //   2991: aload_3
/*    */     //   2992: aload_0
/*    */     //   2993: aload_3
/*    */     //   2994: dup
/*    */     //   2995: invokespecial <init> : ()V
/*    */     //   2998: putfield Gc0 : Lf/Ip;
/*    */     //   3001: ldc_w 'label-area-monsterdex'
/*    */     //   3004: invokevirtual Xu : (Ljava/lang/String;)V
/*    */     //   3007: new f/rS
/*    */     //   3010: dup
/*    */     //   3011: astore #4
/*    */     //   3013: aload_3
/*    */     //   3014: aload_0
/*    */     //   3015: aload #4
/*    */     //   3017: dup
/*    */     //   3018: invokespecial <init> : ()V
/*    */     //   3021: putfield IU : Lf/rS;
/*    */     //   3024: invokevirtual Gz0 : (Lf/JG0;)V
/*    */     //   3027: invokevirtual mE0 : ()Lf/g0;
/*    */     //   3030: aload #4
/*    */     //   3032: invokevirtual Ya : (Lf/JG0;)Lf/U90;
/*    */     //   3035: invokevirtual WN : (Lf/U90;)V
/*    */     //   3038: invokevirtual d7 : ()Lf/cr0;
/*    */     //   3041: invokevirtual Em0 : ()Lf/U90;
/*    */     //   3044: aload #4
/*    */     //   3046: invokevirtual Ya : (Lf/JG0;)Lf/U90;
/*    */     //   3049: invokevirtual Em0 : ()Lf/U90;
/*    */     //   3052: invokevirtual rK0 : (Lf/U90;)V
/*    */     //   3055: invokevirtual mE0 : ()Lf/g0;
/*    */     //   3058: invokevirtual rK0 : (Lf/U90;)V
/*    */     //   3061: invokevirtual d7 : ()Lf/cr0;
/*    */     //   3064: invokevirtual WN : (Lf/U90;)V
/*    */     //   3067: new f/Vq0
/*    */     //   3070: dup
/*    */     //   3071: dup2
/*    */     //   3072: astore_3
/*    */     //   3073: aload_2
/*    */     //   3074: aload_3
/*    */     //   3075: aload_1
/*    */     //   3076: aload_3
/*    */     //   3077: aload_0
/*    */     //   3078: aload_3
/*    */     //   3079: aload_0
/*    */     //   3080: aload_3
/*    */     //   3081: aload_0
/*    */     //   3082: dup
/*    */     //   3083: aload_3
/*    */     //   3084: dup
/*    */     //   3085: invokespecial <init> : ()V
/*    */     //   3088: putfield RB : Lf/Vq0;
/*    */     //   3091: sipush #1703
/*    */     //   3094: invokestatic OH0 : (I)Ljava/lang/String;
/*    */     //   3097: astore_1
/*    */     //   3098: getfield xZ : Lf/Ip;
/*    */     //   3101: aload_1
/*    */     //   3102: invokevirtual WS : (Lf/JG0;Ljava/lang/String;)Lf/Li0;
/*    */     //   3105: pop
/*    */     //   3106: sipush #1704
/*    */     //   3109: invokestatic OH0 : (I)Ljava/lang/String;
/*    */     //   3112: astore_1
/*    */     //   3113: getfield ci0 : Lf/Ip;
/*    */     //   3116: aload_1
/*    */     //   3117: invokevirtual WS : (Lf/JG0;Ljava/lang/String;)Lf/Li0;
/*    */     //   3120: pop
/*    */     //   3121: sipush #1717
/*    */     //   3124: invokestatic OH0 : (I)Ljava/lang/String;
/*    */     //   3127: astore_1
/*    */     //   3128: getfield COm7 : Lf/Ip;
/*    */     //   3131: aload_1
/*    */     //   3132: invokevirtual WS : (Lf/JG0;Ljava/lang/String;)Lf/Li0;
/*    */     //   3135: pop
/*    */     //   3136: sipush #1775
/*    */     //   3139: invokestatic OH0 : (I)Ljava/lang/String;
/*    */     //   3142: invokevirtual WS : (Lf/JG0;Ljava/lang/String;)Lf/Li0;
/*    */     //   3145: pop
/*    */     //   3146: sipush #2550
/*    */     //   3149: invokestatic OH0 : (I)Ljava/lang/String;
/*    */     //   3152: invokevirtual WS : (Lf/JG0;Ljava/lang/String;)Lf/Li0;
/*    */     //   3155: pop
/*    */     //   3156: iconst_0
/*    */     //   3157: invokevirtual wI0 : (Z)V
/*    */     //   3160: invokevirtual J8 : (Lf/JG0;)V
/*    */     //   3163: invokestatic XU : ()Z
/*    */     //   3166: ifeq -> 3185
/*    */     //   3169: aload_0
/*    */     //   3170: dup
/*    */     //   3171: dup
/*    */     //   3172: getfield y7 : Lf/Un;
/*    */     //   3175: iconst_0
/*    */     //   3176: invokevirtual wI0 : (Z)V
/*    */     //   3179: getfield y7 : Lf/Un;
/*    */     //   3182: invokevirtual J8 : (Lf/JG0;)V
/*    */     //   3185: aload_0
/*    */     //   3186: invokevirtual Id0 : ()V
/*    */     //   3189: return } private int fm(Hq paramHq1, Hq paramHq2) { // Byte code:
/*    */     //   0: aload_1
/*    */     //   1: getfield tO : B
/*    */     //   4: aload_2
/*    */     //   5: getfield tO : B
/*    */     //   8: if_icmpeq -> 148
/*    */     //   11: aload_0
/*    */     //   12: getfield HH : B
/*    */     //   15: istore_0
/*    */     //   16: iconst_0
/*    */     //   17: istore_3
/*    */     //   18: iload_3
/*    */     //   19: getstatic f/Mk0.tJ : [B
/*    */     //   22: astore #4
/*    */     //   24: bipush #6
/*    */     //   26: if_icmpge -> 48
/*    */     //   29: aload #4
/*    */     //   31: iload_3
/*    */     //   32: baload
/*    */     //   33: iload_0
/*    */     //   34: if_icmpne -> 40
/*    */     //   37: goto -> 50
/*    */     //   40: iload_3
/*    */     //   41: iconst_1
/*    */     //   42: iadd
/*    */     //   43: i2b
/*    */     //   44: istore_3
/*    */     //   45: goto -> 18
/*    */     //   48: iconst_m1
/*    */     //   49: istore_3
/*    */     //   50: aload_1
/*    */     //   51: getfield tO : B
/*    */     //   54: istore_0
/*    */     //   55: iconst_0
/*    */     //   56: istore_1
/*    */     //   57: iload_1
/*    */     //   58: getstatic f/Mk0.tJ : [B
/*    */     //   61: astore #4
/*    */     //   63: bipush #6
/*    */     //   65: if_icmpge -> 87
/*    */     //   68: aload #4
/*    */     //   70: iload_1
/*    */     //   71: baload
/*    */     //   72: iload_0
/*    */     //   73: if_icmpne -> 79
/*    */     //   76: goto -> 89
/*    */     //   79: iload_1
/*    */     //   80: iconst_1
/*    */     //   81: iadd
/*    */     //   82: i2b
/*    */     //   83: istore_1
/*    */     //   84: goto -> 57
/*    */     //   87: iconst_m1
/*    */     //   88: istore_1
/*    */     //   89: aload_2
/*    */     //   90: getfield tO : B
/*    */     //   93: istore_0
/*    */     //   94: iconst_0
/*    */     //   95: istore_2
/*    */     //   96: iload_2
/*    */     //   97: getstatic f/Mk0.tJ : [B
/*    */     //   100: astore #4
/*    */     //   102: bipush #6
/*    */     //   104: if_icmpge -> 126
/*    */     //   107: aload #4
/*    */     //   109: iload_2
/*    */     //   110: baload
/*    */     //   111: iload_0
/*    */     //   112: if_icmpne -> 118
/*    */     //   115: goto -> 128
/*    */     //   118: iload_2
/*    */     //   119: iconst_1
/*    */     //   120: iadd
/*    */     //   121: i2b
/*    */     //   122: istore_2
/*    */     //   123: goto -> 96
/*    */     //   126: iconst_m1
/*    */     //   127: istore_2
/*    */     //   128: iload_1
/*    */     //   129: iload_3
/*    */     //   130: if_icmpne -> 135
/*    */     //   133: iconst_m1
/*    */     //   134: ireturn
/*    */     //   135: iload_2
/*    */     //   136: iload_3
/*    */     //   137: if_icmpne -> 142
/*    */     //   140: iconst_1
/*    */     //   141: ireturn
/*    */     //   142: iload_1
/*    */     //   143: iload_2
/*    */     //   144: invokestatic compare : (II)I
/*    */     //   147: ireturn
/*    */     //   148: aload_1
/*    */     //   149: aload_2
/*    */     //   150: invokevirtual IS : (Lf/Hq;)I
/*    */     //   153: ireturn
/*    */     // Line number table:
/*    */     //   Java source line number -> byte code offset
/*    */     //   #1	-> 1
/*    */     //   #2	-> 12
/*    */     //   #3	-> 19
/*    */     //   #4	-> 51
/*    */     //   #5	-> 58
/*    */     //   #6	-> 90
/*    */     //   #7	-> 97
/*  2 */     //   #8	-> 144 } private void eb(qc0 paramqc0) { UD0 uD0; if ((uD0 = this.cr0) == null) return;  boolean bool = false; if (!paramqc0.JO(bool, uD0.AP))
/*    */       return; 
/*  4 */     D0.MJ0(this.cr0.AP); } public final qc0 H60() { return this.ZS; } public final void If(byte paramByte, UD0 paramUD0) { // Byte code:
/*    */     //   0: aload_2
/*    */     //   1: ifnonnull -> 5
/*    */     //   4: return
/*    */     //   5: aload_2
/*    */     //   6: getfield TL : S
/*    */     //   9: ifle -> 35
/*    */     //   12: iload_1
/*    */     //   13: ifle -> 35
/*    */     //   16: invokestatic v30 : ()Lf/On;
/*    */     //   19: aload_2
/*    */     //   20: getfield TL : S
/*    */     //   23: iload_1
/*    */     //   24: iadd
/*    */     //   25: iconst_1
/*    */     //   26: isub
/*    */     //   27: i2s
/*    */     //   28: invokevirtual lpT3 : (S)Lf/UD0;
/*    */     //   31: astore_3
/*    */     //   32: goto -> 37
/*    */     //   35: aload_2
/*    */     //   36: astore_3
/*    */     //   37: aload_0
/*    */     //   38: dup
/*    */     //   39: aload_2
/*    */     //   40: aload_0
/*    */     //   41: iload_1
/*    */     //   42: putfield Lh : B
/*    */     //   45: putfield cr0 : Lf/UD0;
/*    */     //   48: getfield RB : Lf/Vq0;
/*    */     //   51: dup
/*    */     //   52: astore #4
/*    */     //   54: getfield dP : Z
/*    */     //   57: ifeq -> 73
/*    */     //   60: aload #4
/*    */     //   62: dup
/*    */     //   63: iconst_0
/*    */     //   64: invokevirtual Hf : (I)Lf/Li0;
/*    */     //   67: invokevirtual dA0 : (Lf/Li0;)V
/*    */     //   70: goto -> 101
/*    */     //   73: aload_0
/*    */     //   74: aload #4
/*    */     //   76: iconst_1
/*    */     //   77: invokevirtual wI0 : (Z)V
/*    */     //   80: getfield PRn : Lf/Ip;
/*    */     //   83: iconst_0
/*    */     //   84: invokevirtual wI0 : (Z)V
/*    */     //   87: invokestatic XU : ()Z
/*    */     //   90: ifeq -> 101
/*    */     //   93: aload_0
/*    */     //   94: getfield y7 : Lf/Un;
/*    */     //   97: iconst_1
/*    */     //   98: invokevirtual wI0 : (Z)V
/*    */     //   101: aload_2
/*    */     //   102: aload_0
/*    */     //   103: dup
/*    */     //   104: dup
/*    */     //   105: dup2
/*    */     //   106: getfield ED0 : Lf/rS;
/*    */     //   109: iconst_0
/*    */     //   110: invokevirtual rt : (I)V
/*    */     //   113: getfield IU : Lf/rS;
/*    */     //   116: iconst_0
/*    */     //   117: invokevirtual rt : (I)V
/*    */     //   120: getfield Uz0 : Lf/rS;
/*    */     //   123: iconst_0
/*    */     //   124: invokevirtual rt : (I)V
/*    */     //   127: new java/text/DecimalFormat
/*    */     //   130: dup
/*    */     //   131: astore #4
/*    */     //   133: ldc_w '000'
/*    */     //   136: invokespecial <init> : (Ljava/lang/String;)V
/*    */     //   139: getfield ZS : Lf/qc0;
/*    */     //   142: aload_2
/*    */     //   143: getfield AP : S
/*    */     //   146: iconst_0
/*    */     //   147: swap
/*    */     //   148: invokevirtual JO : (BS)Z
/*    */     //   151: istore #5
/*    */     //   153: getfield ZS : Lf/qc0;
/*    */     //   156: aload_2
/*    */     //   157: getfield AP : S
/*    */     //   160: iconst_1
/*    */     //   161: swap
/*    */     //   162: invokevirtual JO : (BS)Z
/*    */     //   165: istore #6
/*    */     //   167: getfield Uf : B
/*    */     //   170: iconst_1
/*    */     //   171: if_icmple -> 268
/*    */     //   174: aload_0
/*    */     //   175: getfield ZS : Lf/qc0;
/*    */     //   178: aload_2
/*    */     //   179: getfield AP : S
/*    */     //   182: invokevirtual hp0 : (S)I
/*    */     //   185: ifne -> 227
/*    */     //   188: iload #5
/*    */     //   190: ifeq -> 203
/*    */     //   193: iload_1
/*    */     //   194: ifne -> 203
/*    */     //   197: iconst_1
/*    */     //   198: istore #7
/*    */     //   200: goto -> 206
/*    */     //   203: iconst_0
/*    */     //   204: istore #7
/*    */     //   206: iload #6
/*    */     //   208: ifeq -> 221
/*    */     //   211: iload_1
/*    */     //   212: ifne -> 221
/*    */     //   215: iconst_1
/*    */     //   216: istore #6
/*    */     //   218: goto -> 272
/*    */     //   221: iconst_0
/*    */     //   222: istore #6
/*    */     //   224: goto -> 272
/*    */     //   227: aload_0
/*    */     //   228: dup
/*    */     //   229: getfield ZS : Lf/qc0;
/*    */     //   232: aload_2
/*    */     //   233: getfield AP : S
/*    */     //   236: istore #6
/*    */     //   238: iconst_0
/*    */     //   239: iload_1
/*    */     //   240: iload #6
/*    */     //   242: invokevirtual cu0 : (BIS)Z
/*    */     //   245: istore #7
/*    */     //   247: getfield ZS : Lf/qc0;
/*    */     //   250: aload_2
/*    */     //   251: getfield AP : S
/*    */     //   254: istore #6
/*    */     //   256: iconst_1
/*    */     //   257: iload_1
/*    */     //   258: iload #6
/*    */     //   260: invokevirtual cu0 : (BIS)Z
/*    */     //   263: istore #6
/*    */     //   265: goto -> 272
/*    */     //   268: iload #5
/*    */     //   270: istore #7
/*    */     //   272: aload_2
/*    */     //   273: aload_0
/*    */     //   274: dup
/*    */     //   275: getfield gH : Lf/Un;
/*    */     //   278: iload #7
/*    */     //   280: invokevirtual sk0 : (Z)V
/*    */     //   283: getfield uk0 : Lf/Un;
/*    */     //   286: astore #8
/*    */     //   288: getfield Uf : B
/*    */     //   291: iconst_1
/*    */     //   292: if_icmple -> 301
/*    */     //   295: iconst_1
/*    */     //   296: istore #9
/*    */     //   298: goto -> 304
/*    */     //   301: iconst_0
/*    */     //   302: istore #9
/*    */     //   304: aload_2
/*    */     //   305: aload_0
/*    */     //   306: aload #8
/*    */     //   308: iload #9
/*    */     //   310: invokevirtual sk0 : (Z)V
/*    */     //   313: getfield uk0 : Lf/Un;
/*    */     //   316: astore #8
/*    */     //   318: getfield Uf : B
/*    */     //   321: iconst_1
/*    */     //   322: if_icmple -> 331
/*    */     //   325: iconst_1
/*    */     //   326: istore #9
/*    */     //   328: goto -> 334
/*    */     //   331: iconst_0
/*    */     //   332: istore #9
/*    */     //   334: iload_1
/*    */     //   335: aload_2
/*    */     //   336: aload #8
/*    */     //   338: iload #9
/*    */     //   340: invokevirtual wI0 : (Z)V
/*    */     //   343: aconst_null
/*    */     //   344: astore #8
/*    */     //   346: getfield AP : S
/*    */     //   349: invokestatic HZ : (BS)S
/*    */     //   352: istore #9
/*    */     //   354: getstatic f/um0.Kt0 : Lf/um0;
/*    */     //   357: iconst_0
/*    */     //   358: iload #9
/*    */     //   360: iconst_0
/*    */     //   361: iconst_0
/*    */     //   362: invokevirtual H9 : (BSZZ)[Lf/zh0;
/*    */     //   365: dup
/*    */     //   366: astore #10
/*    */     //   368: iconst_0
/*    */     //   369: aaload
/*    */     //   370: astore #11
/*    */     //   372: getstatic f/um0.Kt0 : Lf/um0;
/*    */     //   375: iconst_0
/*    */     //   376: iload #9
/*    */     //   378: iconst_0
/*    */     //   379: iconst_0
/*    */     //   380: invokevirtual F7 : (BSZZ)Z
/*    */     //   383: ifeq -> 402
/*    */     //   386: getstatic f/um0.Kt0 : Lf/um0;
/*    */     //   389: iconst_0
/*    */     //   390: iload #9
/*    */     //   392: iconst_0
/*    */     //   393: iconst_0
/*    */     //   394: invokevirtual Hr : (BSZZ)[I
/*    */     //   397: astore #8
/*    */     //   399: goto -> 405
/*    */     //   402: aconst_null
/*    */     //   403: astore #10
/*    */     //   405: aload #10
/*    */     //   407: aload #11
/*    */     //   409: dup
/*    */     //   410: invokevirtual Uu0 : ()Lf/pe0;
/*    */     //   413: getfield H0 : I
/*    */     //   416: iconst_2
/*    */     //   417: idiv
/*    */     //   418: bipush #80
/*    */     //   420: swap
/*    */     //   421: isub
/*    */     //   422: istore #9
/*    */     //   424: invokevirtual Uu0 : ()Lf/pe0;
/*    */     //   427: getfield Vn0 : I
/*    */     //   430: iconst_2
/*    */     //   431: idiv
/*    */     //   432: bipush #80
/*    */     //   434: swap
/*    */     //   435: isub
/*    */     //   436: istore #12
/*    */     //   438: ifnull -> 486
/*    */     //   441: aload #10
/*    */     //   443: arraylength
/*    */     //   444: iconst_2
/*    */     //   445: if_icmple -> 486
/*    */     //   448: aload_0
/*    */     //   449: dup
/*    */     //   450: dup
/*    */     //   451: getfield dm0 : Lf/vF0;
/*    */     //   454: getfield TS : Lf/rH;
/*    */     //   457: aload #10
/*    */     //   459: invokevirtual sm : ([Lf/zh0;)V
/*    */     //   462: getfield dm0 : Lf/vF0;
/*    */     //   465: getfield TS : Lf/rH;
/*    */     //   468: aload #8
/*    */     //   470: invokevirtual s8 : ([I)V
/*    */     //   473: getfield dm0 : Lf/vF0;
/*    */     //   476: getfield TS : Lf/rH;
/*    */     //   479: iconst_1
/*    */     //   480: putfield vU : Z
/*    */     //   483: goto -> 505
/*    */     //   486: aload_0
/*    */     //   487: getfield dm0 : Lf/vF0;
/*    */     //   490: getfield TS : Lf/rH;
/*    */     //   493: iconst_1
/*    */     //   494: anewarray f/zh0
/*    */     //   497: dup
/*    */     //   498: iconst_0
/*    */     //   499: aload #11
/*    */     //   501: aastore
/*    */     //   502: invokevirtual sm : ([Lf/zh0;)V
/*    */     //   505: aload_0
/*    */     //   506: getfield dm0 : Lf/vF0;
/*    */     //   509: getfield TS : Lf/rH;
/*    */     //   512: fconst_2
/*    */     //   513: putfield V1 : F
/*    */     //   516: invokestatic XU : ()Z
/*    */     //   519: ifeq -> 571
/*    */     //   522: iload #12
/*    */     //   524: iload #9
/*    */     //   526: i2f
/*    */     //   527: aload_0
/*    */     //   528: getfield dm0 : Lf/vF0;
/*    */     //   531: getfield TS : Lf/rH;
/*    */     //   534: dup
/*    */     //   535: astore #8
/*    */     //   537: getfield Ej : I
/*    */     //   540: i2f
/*    */     //   541: fconst_2
/*    */     //   542: fdiv
/*    */     //   543: ldc_w 20.0
/*    */     //   546: fsub
/*    */     //   547: fsub
/*    */     //   548: f2i
/*    */     //   549: istore #9
/*    */     //   551: i2f
/*    */     //   552: aload #8
/*    */     //   554: getfield WB0 : I
/*    */     //   557: i2f
/*    */     //   558: fconst_2
/*    */     //   559: fdiv
/*    */     //   560: ldc_w 40.0
/*    */     //   563: fsub
/*    */     //   564: fsub
/*    */     //   565: f2i
/*    */     //   566: istore #8
/*    */     //   568: goto -> 617
/*    */     //   571: iload #12
/*    */     //   573: iload #9
/*    */     //   575: i2f
/*    */     //   576: aload_0
/*    */     //   577: getfield dm0 : Lf/vF0;
/*    */     //   580: getfield TS : Lf/rH;
/*    */     //   583: dup
/*    */     //   584: astore #8
/*    */     //   586: getfield Ej : I
/*    */     //   589: i2f
/*    */     //   590: fconst_2
/*    */     //   591: fdiv
/*    */     //   592: ldc_w 7.0
/*    */     //   595: fsub
/*    */     //   596: fsub
/*    */     //   597: f2i
/*    */     //   598: istore #9
/*    */     //   600: i2f
/*    */     //   601: aload #8
/*    */     //   603: getfield WB0 : I
/*    */     //   606: i2f
/*    */     //   607: fconst_2
/*    */     //   608: fdiv
/*    */     //   609: ldc_w 20.0
/*    */     //   612: fsub
/*    */     //   613: fsub
/*    */     //   614: f2i
/*    */     //   615: istore #8
/*    */     //   617: iload #7
/*    */     //   619: aload_0
/*    */     //   620: getfield dm0 : Lf/vF0;
/*    */     //   623: getfield TS : Lf/rH;
/*    */     //   626: iload #9
/*    */     //   628: iload #8
/*    */     //   630: invokevirtual zT : (II)Lf/JG0;
/*    */     //   633: pop
/*    */     //   634: ifeq -> 651
/*    */     //   637: aload_0
/*    */     //   638: getfield dm0 : Lf/vF0;
/*    */     //   641: getfield TS : Lf/rH;
/*    */     //   644: aconst_null
/*    */     //   645: invokevirtual FB0 : (Lf/pRn;)V
/*    */     //   648: goto -> 673
/*    */     //   651: aload_0
/*    */     //   652: getfield dm0 : Lf/vF0;
/*    */     //   655: getfield TS : Lf/rH;
/*    */     //   658: new f/pRn
/*    */     //   661: dup
/*    */     //   662: iconst_0
/*    */     //   663: iconst_0
/*    */     //   664: iconst_0
/*    */     //   665: bipush #127
/*    */     //   667: invokespecial <init> : (BBBB)V
/*    */     //   670: invokevirtual FB0 : (Lf/pRn;)V
/*    */     //   673: iload #5
/*    */     //   675: ifeq -> 800
/*    */     //   678: aload_0
/*    */     //   679: dup
/*    */     //   680: getfield dm0 : Lf/vF0;
/*    */     //   683: new java/lang/StringBuilder
/*    */     //   686: dup
/*    */     //   687: astore #5
/*    */     //   689: invokespecial <init> : ()V
/*    */     //   692: sipush #1705
/*    */     //   695: aload #5
/*    */     //   697: ldc_w ' '
/*    */     //   700: invokestatic X9 : (ILjava/lang/StringBuilder;Ljava/lang/String;)Ljava/lang/StringBuilder;
/*    */     //   703: aload #4
/*    */     //   705: aload_2
/*    */     //   706: aload_0
/*    */     //   707: getfield HH : B
/*    */     //   710: invokevirtual PP : (B)S
/*    */     //   713: i2l
/*    */     //   714: invokevirtual format : (J)Ljava/lang/String;
/*    */     //   717: invokevirtual append : (Ljava/lang/String;)Ljava/lang/StringBuilder;
/*    */     //   720: ldc_w ' '
/*    */     //   723: invokevirtual append : (Ljava/lang/String;)Ljava/lang/StringBuilder;
/*    */     //   726: aload_2
/*    */     //   727: iconst_0
/*    */     //   728: invokevirtual o60 : (Z)Ljava/lang/String;
/*    */     //   731: invokevirtual append : (Ljava/lang/String;)Ljava/lang/StringBuilder;
/*    */     //   734: invokevirtual toString : ()Ljava/lang/String;
/*    */     //   737: invokevirtual E1 : (Ljava/lang/String;)V
/*    */     //   740: new java/lang/StringBuilder
/*    */     //   743: dup
/*    */     //   744: astore #5
/*    */     //   746: invokespecial <init> : ()V
/*    */     //   749: sipush #1705
/*    */     //   752: aload #5
/*    */     //   754: ldc_w ' '
/*    */     //   757: invokestatic X9 : (ILjava/lang/StringBuilder;Ljava/lang/String;)Ljava/lang/StringBuilder;
/*    */     //   760: aload #4
/*    */     //   762: aload_2
/*    */     //   763: aload_0
/*    */     //   764: getfield HH : B
/*    */     //   767: invokevirtual PP : (B)S
/*    */     //   770: i2l
/*    */     //   771: invokevirtual format : (J)Ljava/lang/String;
/*    */     //   774: invokevirtual append : (Ljava/lang/String;)Ljava/lang/StringBuilder;
/*    */     //   777: ldc_w ' '
/*    */     //   780: invokevirtual append : (Ljava/lang/String;)Ljava/lang/StringBuilder;
/*    */     //   783: aload_2
/*    */     //   784: iconst_0
/*    */     //   785: invokevirtual o60 : (Z)Ljava/lang/String;
/*    */     //   788: invokevirtual append : (Ljava/lang/String;)Ljava/lang/StringBuilder;
/*    */     //   791: invokevirtual toString : ()Ljava/lang/String;
/*    */     //   794: invokevirtual Lo : (Ljava/lang/String;)V
/*    */     //   797: goto -> 903
/*    */     //   800: aload_0
/*    */     //   801: dup
/*    */     //   802: getfield dm0 : Lf/vF0;
/*    */     //   805: new java/lang/StringBuilder
/*    */     //   808: dup
/*    */     //   809: astore #5
/*    */     //   811: invokespecial <init> : ()V
/*    */     //   814: sipush #1705
/*    */     //   817: aload #5
/*    */     //   819: ldc_w ' '
/*    */     //   822: invokestatic X9 : (ILjava/lang/StringBuilder;Ljava/lang/String;)Ljava/lang/StringBuilder;
/*    */     //   825: aload #4
/*    */     //   827: aload_2
/*    */     //   828: aload_0
/*    */     //   829: getfield HH : B
/*    */     //   832: invokevirtual PP : (B)S
/*    */     //   835: i2l
/*    */     //   836: invokevirtual format : (J)Ljava/lang/String;
/*    */     //   839: invokevirtual append : (Ljava/lang/String;)Ljava/lang/StringBuilder;
/*    */     //   842: ldc_w ' ???'
/*    */     //   845: invokevirtual append : (Ljava/lang/String;)Ljava/lang/StringBuilder;
/*    */     //   848: invokevirtual toString : ()Ljava/lang/String;
/*    */     //   851: invokevirtual E1 : (Ljava/lang/String;)V
/*    */     //   854: new java/lang/StringBuilder
/*    */     //   857: dup
/*    */     //   858: astore #5
/*    */     //   860: invokespecial <init> : ()V
/*    */     //   863: sipush #1705
/*    */     //   866: aload #5
/*    */     //   868: ldc_w ' '
/*    */     //   871: invokestatic X9 : (ILjava/lang/StringBuilder;Ljava/lang/String;)Ljava/lang/StringBuilder;
/*    */     //   874: aload #4
/*    */     //   876: aload_2
/*    */     //   877: aload_0
/*    */     //   878: getfield HH : B
/*    */     //   881: invokevirtual PP : (B)S
/*    */     //   884: i2l
/*    */     //   885: invokevirtual format : (J)Ljava/lang/String;
/*    */     //   888: invokevirtual append : (Ljava/lang/String;)Ljava/lang/StringBuilder;
/*    */     //   891: ldc_w ' ???'
/*    */     //   894: invokevirtual append : (Ljava/lang/String;)Ljava/lang/StringBuilder;
/*    */     //   897: invokevirtual toString : ()Ljava/lang/String;
/*    */     //   900: invokevirtual Lo : (Ljava/lang/String;)V
/*    */     //   903: aload_0
/*    */     //   904: getfield instanceof : Lf/gl;
/*    */     //   907: getfield Lpt8 : Ljava/util/ArrayList;
/*    */     //   910: invokevirtual clear : ()V
/*    */     //   913: iconst_0
/*    */     //   914: istore #4
/*    */     //   916: iload #4
/*    */     //   918: aload_0
/*    */     //   919: getfield Sk0 : [Lf/IN;
/*    */     //   922: arraylength
/*    */     //   923: if_icmpge -> 956
/*    */     //   926: aload_0
/*    */     //   927: dup
/*    */     //   928: getfield oe0 : [Lf/dQ;
/*    */     //   931: iload #4
/*    */     //   933: aaload
/*    */     //   934: ldc_w '?'
/*    */     //   937: invokevirtual E1 : (Ljava/lang/String;)V
/*    */     //   940: getfield Sk0 : [Lf/IN;
/*    */     //   943: iload #4
/*    */     //   945: aaload
/*    */     //   946: fconst_0
/*    */     //   947: invokevirtual Nu : (F)V
/*    */     //   950: iinc #4, 1
/*    */     //   953: goto -> 916
/*    */     //   956: iload #6
/*    */     //   958: ifeq -> 2327
/*    */     //   961: aload_3
/*    */     //   962: iload_1
/*    */     //   963: aload_0
/*    */     //   964: dup
/*    */     //   965: dup2
/*    */     //   966: getfield Az0 : Lf/Ro0;
/*    */     //   969: getstatic f/F40.ef0 : Lf/F40;
/*    */     //   972: dup
/*    */     //   973: astore #4
/*    */     //   975: aload_2
/*    */     //   976: getstatic f/km.mI0 : Lf/P1;
/*    */     //   979: getfield AN : Lf/Wo;
/*    */     //   982: getfield qa0 : Lf/ml;
/*    */     //   985: getfield UI : Ljava/lang/String;
/*    */     //   988: ldc_w 'IRA'
/*    */     //   991: invokevirtual equals : (Ljava/lang/Object;)Z
/*    */     //   994: sipush #235
/*    */     //   997: iadd
/*    */     //   998: istore #5
/*    */     //   1000: getfield AP : S
/*    */     //   1003: iload #5
/*    */     //   1005: swap
/*    */     //   1006: invokestatic Qf0 : (Lf/F40;II)Ljava/lang/String;
/*    */     //   1009: invokevirtual E1 : (Ljava/lang/String;)V
/*    */     //   1012: getfield Az0 : Lf/Ro0;
/*    */     //   1015: invokevirtual mM : ()V
/*    */     //   1018: getfield EI : Lf/dQ;
/*    */     //   1021: aload #4
/*    */     //   1023: aload_2
/*    */     //   1024: getfield AP : S
/*    */     //   1027: sipush #260
/*    */     //   1030: swap
/*    */     //   1031: invokestatic Qf0 : (Lf/F40;II)Ljava/lang/String;
/*    */     //   1034: invokevirtual E1 : (Ljava/lang/String;)V
/*    */     //   1037: getfield SB : Lf/vF0;
/*    */     //   1040: getfield TS : Lf/rH;
/*    */     //   1043: iconst_1
/*    */     //   1044: anewarray f/pe0
/*    */     //   1047: dup
/*    */     //   1048: invokestatic ZZ : ()Lf/interface;
/*    */     //   1051: aload_3
/*    */     //   1052: iload_1
/*    */     //   1053: invokevirtual Sl0 : (B)Lf/Ht0;
/*    */     //   1056: getfield zm0 : B
/*    */     //   1059: invokevirtual xk0 : (I)Lf/pe0;
/*    */     //   1062: iconst_0
/*    */     //   1063: swap
/*    */     //   1064: aastore
/*    */     //   1065: invokevirtual Pn : ([Lf/pe0;)Lf/JG0;
/*    */     //   1068: pop
/*    */     //   1069: invokevirtual Sl0 : (B)Lf/Ht0;
/*    */     //   1072: aload_3
/*    */     //   1073: iload_1
/*    */     //   1074: invokevirtual pf0 : (B)Lf/Ht0;
/*    */     //   1077: if_acmpeq -> 1116
/*    */     //   1080: aload_0
/*    */     //   1081: getfield So0 : Lf/vF0;
/*    */     //   1084: getfield TS : Lf/rH;
/*    */     //   1087: iconst_1
/*    */     //   1088: anewarray f/pe0
/*    */     //   1091: dup
/*    */     //   1092: invokestatic ZZ : ()Lf/interface;
/*    */     //   1095: aload_3
/*    */     //   1096: iload_1
/*    */     //   1097: invokevirtual pf0 : (B)Lf/Ht0;
/*    */     //   1100: getfield zm0 : B
/*    */     //   1103: invokevirtual xk0 : (I)Lf/pe0;
/*    */     //   1106: iconst_0
/*    */     //   1107: swap
/*    */     //   1108: aastore
/*    */     //   1109: invokevirtual Pn : ([Lf/pe0;)Lf/JG0;
/*    */     //   1112: pop
/*    */     //   1113: goto -> 1126
/*    */     //   1116: aload_0
/*    */     //   1117: getfield So0 : Lf/vF0;
/*    */     //   1120: getfield TS : Lf/rH;
/*    */     //   1123: invokevirtual H : ()V
/*    */     //   1126: invokestatic XU : ()Z
/*    */     //   1129: ifeq -> 1197
/*    */     //   1132: aload_0
/*    */     //   1133: getfield So0 : Lf/vF0;
/*    */     //   1136: getfield TS : Lf/rH;
/*    */     //   1139: invokevirtual AX : ()Z
/*    */     //   1142: ifeq -> 1163
/*    */     //   1145: aload_0
/*    */     //   1146: getfield SB : Lf/vF0;
/*    */     //   1149: getfield TS : Lf/rH;
/*    */     //   1152: bipush #-110
/*    */     //   1154: bipush #-6
/*    */     //   1156: invokevirtual zT : (II)Lf/JG0;
/*    */     //   1159: pop
/*    */     //   1160: goto -> 1245
/*    */     //   1163: aload_0
/*    */     //   1164: dup
/*    */     //   1165: getfield SB : Lf/vF0;
/*    */     //   1168: getfield TS : Lf/rH;
/*    */     //   1171: sipush #-210
/*    */     //   1174: bipush #-6
/*    */     //   1176: invokevirtual zT : (II)Lf/JG0;
/*    */     //   1179: pop
/*    */     //   1180: getfield So0 : Lf/vF0;
/*    */     //   1183: getfield TS : Lf/rH;
/*    */     //   1186: bipush #-115
/*    */     //   1188: bipush #-6
/*    */     //   1190: invokevirtual zT : (II)Lf/JG0;
/*    */     //   1193: pop
/*    */     //   1194: goto -> 1245
/*    */     //   1197: aload_0
/*    */     //   1198: getfield So0 : Lf/vF0;
/*    */     //   1201: getfield TS : Lf/rH;
/*    */     //   1204: invokevirtual AX : ()Z
/*    */     //   1207: ifeq -> 1217
/*    */     //   1210: aload_0
/*    */     //   1211: getfield SB : Lf/vF0;
/*    */     //   1214: goto -> 1235
/*    */     //   1217: aload_0
/*    */     //   1218: dup
/*    */     //   1219: getfield SB : Lf/vF0;
/*    */     //   1222: getfield TS : Lf/rH;
/*    */     //   1225: bipush #-115
/*    */     //   1227: iconst_0
/*    */     //   1228: invokevirtual zT : (II)Lf/JG0;
/*    */     //   1231: pop
/*    */     //   1232: getfield So0 : Lf/vF0;
/*    */     //   1235: getfield TS : Lf/rH;
/*    */     //   1238: bipush #-65
/*    */     //   1240: iconst_0
/*    */     //   1241: invokevirtual zT : (II)Lf/JG0;
/*    */     //   1244: pop
/*    */     //   1245: iconst_0
/*    */     //   1246: istore #4
/*    */     //   1248: iload #4
/*    */     //   1250: getstatic f/hR.Tm0 : [Lf/hR;
/*    */     //   1253: dup
/*    */     //   1254: astore #5
/*    */     //   1256: arraylength
/*    */     //   1257: if_icmpge -> 1316
/*    */     //   1260: aload_0
/*    */     //   1261: dup
/*    */     //   1262: getfield oe0 : [Lf/dQ;
/*    */     //   1265: iload #4
/*    */     //   1267: aaload
/*    */     //   1268: aload_3
/*    */     //   1269: aload #5
/*    */     //   1271: iload #4
/*    */     //   1273: aaload
/*    */     //   1274: invokevirtual qC : (Lf/hR;)I
/*    */     //   1277: invokestatic toString : (I)Ljava/lang/String;
/*    */     //   1280: invokevirtual E1 : (Ljava/lang/String;)V
/*    */     //   1283: getfield Sk0 : [Lf/IN;
/*    */     //   1286: iload #4
/*    */     //   1288: aaload
/*    */     //   1289: aload_3
/*    */     //   1290: aload #5
/*    */     //   1292: iload #4
/*    */     //   1294: aaload
/*    */     //   1295: invokevirtual qC : (Lf/hR;)I
/*    */     //   1298: i2f
/*    */     //   1299: getstatic f/Hy.cOM6 : [I
/*    */     //   1302: iload #4
/*    */     //   1304: iaload
/*    */     //   1305: i2f
/*    */     //   1306: fdiv
/*    */     //   1307: invokevirtual Nu : (F)V
/*    */     //   1310: iinc #4, 1
/*    */     //   1313: goto -> 1248
/*    */     //   1316: aload_0
/*    */     //   1317: dup
/*    */     //   1318: getfield oe0 : [Lf/dQ;
/*    */     //   1321: bipush #6
/*    */     //   1323: aaload
/*    */     //   1324: ldc ''
/*    */     //   1326: invokestatic df : (Ljava/lang/String;)Ljava/lang/StringBuilder;
/*    */     //   1329: aload_3
/*    */     //   1330: getfield my0 : I
/*    */     //   1333: aload_3
/*    */     //   1334: getfield dv0 : I
/*    */     //   1337: iadd
/*    */     //   1338: aload_3
/*    */     //   1339: getfield UH0 : I
/*    */     //   1342: iadd
/*    */     //   1343: aload_3
/*    */     //   1344: getfield qA0 : I
/*    */     //   1347: iadd
/*    */     //   1348: aload_3
/*    */     //   1349: getfield j90 : I
/*    */     //   1352: iadd
/*    */     //   1353: aload_3
/*    */     //   1354: getfield ha0 : I
/*    */     //   1357: iadd
/*    */     //   1358: invokevirtual append : (I)Ljava/lang/StringBuilder;
/*    */     //   1361: invokevirtual toString : ()Ljava/lang/String;
/*    */     //   1364: invokevirtual E1 : (Ljava/lang/String;)V
/*    */     //   1367: getfield Sk0 : [Lf/IN;
/*    */     //   1370: bipush #6
/*    */     //   1372: aaload
/*    */     //   1373: aload_3
/*    */     //   1374: getfield my0 : I
/*    */     //   1377: aload_3
/*    */     //   1378: getfield dv0 : I
/*    */     //   1381: iadd
/*    */     //   1382: aload_3
/*    */     //   1383: getfield UH0 : I
/*    */     //   1386: iadd
/*    */     //   1387: aload_3
/*    */     //   1388: getfield qA0 : I
/*    */     //   1391: iadd
/*    */     //   1392: aload_3
/*    */     //   1393: getfield j90 : I
/*    */     //   1396: iadd
/*    */     //   1397: aload_3
/*    */     //   1398: getfield ha0 : I
/*    */     //   1401: iadd
/*    */     //   1402: i2f
/*    */     //   1403: getstatic f/Hy.cOM6 : [I
/*    */     //   1406: bipush #6
/*    */     //   1408: iaload
/*    */     //   1409: i2f
/*    */     //   1410: fdiv
/*    */     //   1411: invokevirtual Nu : (F)V
/*    */     //   1414: ldc ''
/*    */     //   1416: astore #4
/*    */     //   1418: getstatic f/hR.Tt0 : [Lf/hR;
/*    */     //   1421: dup
/*    */     //   1422: astore #5
/*    */     //   1424: arraylength
/*    */     //   1425: istore #6
/*    */     //   1427: iconst_0
/*    */     //   1428: istore #8
/*    */     //   1430: iload #8
/*    */     //   1432: iload #6
/*    */     //   1434: if_icmpge -> 1528
/*    */     //   1437: aload #5
/*    */     //   1439: iload #8
/*    */     //   1441: aaload
/*    */     //   1442: dup
/*    */     //   1443: astore #9
/*    */     //   1445: getfield NT : Z
/*    */     //   1448: ifeq -> 1454
/*    */     //   1451: goto -> 1522
/*    */     //   1454: aload_2
/*    */     //   1455: getfield HL0 : [B
/*    */     //   1458: aload #9
/*    */     //   1460: getfield dL : B
/*    */     //   1463: baload
/*    */     //   1464: ifle -> 1522
/*    */     //   1467: aload #4
/*    */     //   1469: invokevirtual isEmpty : ()Z
/*    */     //   1472: ifne -> 1485
/*    */     //   1475: aload #4
/*    */     //   1477: ldc_w ', '
/*    */     //   1480: invokestatic tF0 : (Ljava/lang/String;Ljava/lang/String;)Ljava/lang/String;
/*    */     //   1483: astore #4
/*    */     //   1485: aload #4
/*    */     //   1487: ldc_w '+'
/*    */     //   1490: invokestatic vz : (Ljava/lang/String;Ljava/lang/String;)Ljava/lang/StringBuilder;
/*    */     //   1493: aload_2
/*    */     //   1494: getfield HL0 : [B
/*    */     //   1497: aload #9
/*    */     //   1499: getfield dL : B
/*    */     //   1502: baload
/*    */     //   1503: invokevirtual append : (I)Ljava/lang/StringBuilder;
/*    */     //   1506: ldc_w ' '
/*    */     //   1509: invokevirtual append : (Ljava/lang/String;)Ljava/lang/StringBuilder;
/*    */     //   1512: aload #9
/*    */     //   1514: invokevirtual append : (Ljava/lang/Object;)Ljava/lang/StringBuilder;
/*    */     //   1517: invokevirtual toString : ()Ljava/lang/String;
/*    */     //   1520: astore #4
/*    */     //   1522: iinc #8, 1
/*    */     //   1525: goto -> 1430
/*    */     //   1528: aload_3
/*    */     //   1529: iconst_0
/*    */     //   1530: invokevirtual zq0 : (I)S
/*    */     //   1533: aload_3
/*    */     //   1534: iconst_1
/*    */     //   1535: invokevirtual zq0 : (I)S
/*    */     //   1538: if_icmpeq -> 1610
/*    */     //   1541: aload_3
/*    */     //   1542: iconst_1
/*    */     //   1543: invokevirtual zq0 : (I)S
/*    */     //   1546: iconst_1
/*    */     //   1547: if_icmpge -> 1553
/*    */     //   1550: goto -> 1610
/*    */     //   1553: aload_0
/*    */     //   1554: getfield VV : Lf/dQ;
/*    */     //   1557: new java/lang/StringBuilder
/*    */     //   1560: dup
/*    */     //   1561: aload_3
/*    */     //   1562: swap
/*    */     //   1563: invokespecial <init> : ()V
/*    */     //   1566: iconst_0
/*    */     //   1567: invokevirtual zq0 : (I)S
/*    */     //   1570: ldc_w 210000
/*    */     //   1573: iadd
/*    */     //   1574: invokestatic OH0 : (I)Ljava/lang/String;
/*    */     //   1577: invokevirtual append : (Ljava/lang/String;)Ljava/lang/StringBuilder;
/*    */     //   1580: ldc_w ' / '
/*    */     //   1583: invokevirtual append : (Ljava/lang/String;)Ljava/lang/StringBuilder;
/*    */     //   1586: aload_3
/*    */     //   1587: iconst_1
/*    */     //   1588: invokevirtual zq0 : (I)S
/*    */     //   1591: ldc_w 210000
/*    */     //   1594: iadd
/*    */     //   1595: invokestatic OH0 : (I)Ljava/lang/String;
/*    */     //   1598: invokevirtual append : (Ljava/lang/String;)Ljava/lang/StringBuilder;
/*    */     //   1601: invokevirtual toString : ()Ljava/lang/String;
/*    */     //   1604: invokevirtual E1 : (Ljava/lang/String;)V
/*    */     //   1607: goto -> 1629
/*    */     //   1610: aload_0
/*    */     //   1611: getfield VV : Lf/dQ;
/*    */     //   1614: aload_3
/*    */     //   1615: iconst_0
/*    */     //   1616: invokevirtual zq0 : (I)S
/*    */     //   1619: ldc_w 210000
/*    */     //   1622: iadd
/*    */     //   1623: invokestatic OH0 : (I)Ljava/lang/String;
/*    */     //   1626: invokevirtual E1 : (Ljava/lang/String;)V
/*    */     //   1629: aload_3
/*    */     //   1630: dup
/*    */     //   1631: aload_0
/*    */     //   1632: dup
/*    */     //   1633: getfield VV : Lf/dQ;
/*    */     //   1636: dup
/*    */     //   1637: aload_3
/*    */     //   1638: invokestatic Vk : (Lf/UD0;)Ljava/lang/String;
/*    */     //   1641: putfield z4 : Ljava/lang/Object;
/*    */     //   1644: invokevirtual zn : ()V
/*    */     //   1647: getfield VV : Lf/dQ;
/*    */     //   1650: bipush #100
/*    */     //   1652: putfield jl : I
/*    */     //   1655: invokevirtual Fk0 : ()Lf/UD0;
/*    */     //   1658: getfield AP : S
/*    */     //   1661: istore #5
/*    */     //   1663: invokevirtual ct : ()Z
/*    */     //   1666: ifeq -> 1695
/*    */     //   1669: iload #5
/*    */     //   1671: getstatic f/gm.EI0 : [S
/*    */     //   1674: invokestatic c7 : (S[S)Z
/*    */     //   1677: ifne -> 1691
/*    */     //   1680: iload #5
/*    */     //   1682: getstatic f/gm.QN : [S
/*    */     //   1685: invokestatic c7 : (S[S)Z
/*    */     //   1688: ifeq -> 1695
/*    */     //   1691: iconst_1
/*    */     //   1692: goto -> 1696
/*    */     //   1695: iconst_0
/*    */     //   1696: ifeq -> 1814
/*    */     //   1699: aload_0
/*    */     //   1700: dup
/*    */     //   1701: dup2
/*    */     //   1702: getfield mf0 : Lf/dQ;
/*    */     //   1705: aload_3
/*    */     //   1706: iconst_2
/*    */     //   1707: invokevirtual zq0 : (I)S
/*    */     //   1710: ldc_w 210000
/*    */     //   1713: iadd
/*    */     //   1714: invokestatic OH0 : (I)Ljava/lang/String;
/*    */     //   1717: invokevirtual E1 : (Ljava/lang/String;)V
/*    */     //   1720: getfield mf0 : Lf/dQ;
/*    */     //   1723: dup
/*    */     //   1724: ldc ''
/*    */     //   1726: invokestatic df : (Ljava/lang/String;)Ljava/lang/StringBuilder;
/*    */     //   1729: aload_3
/*    */     //   1730: iconst_2
/*    */     //   1731: invokevirtual zq0 : (I)S
/*    */     //   1734: ldc_w 210000
/*    */     //   1737: iadd
/*    */     //   1738: invokestatic OH0 : (I)Ljava/lang/String;
/*    */     //   1741: invokevirtual append : (Ljava/lang/String;)Ljava/lang/StringBuilder;
/*    */     //   1744: ldc_w '\\n------\\n'
/*    */     //   1747: invokevirtual append : (Ljava/lang/String;)Ljava/lang/StringBuilder;
/*    */     //   1750: aload_3
/*    */     //   1751: iconst_2
/*    */     //   1752: invokevirtual zq0 : (I)S
/*    */     //   1755: ldc_w 220000
/*    */     //   1758: iadd
/*    */     //   1759: invokestatic OH0 : (I)Ljava/lang/String;
/*    */     //   1762: invokevirtual append : (Ljava/lang/String;)Ljava/lang/StringBuilder;
/*    */     //   1765: invokevirtual toString : ()Ljava/lang/String;
/*    */     //   1768: putfield z4 : Ljava/lang/Object;
/*    */     //   1771: invokevirtual zn : ()V
/*    */     //   1774: getfield mf0 : Lf/dQ;
/*    */     //   1777: bipush #100
/*    */     //   1779: putfield jl : I
/*    */     //   1782: getfield nG : Lf/Q20;
/*    */     //   1785: getfield Li0 : Lf/d10;
/*    */     //   1788: aload_0
/*    */     //   1789: getfield Gd : Lf/Q20;
/*    */     //   1792: iconst_1
/*    */     //   1793: invokevirtual mB : (Ljava/lang/Object;Z)Z
/*    */     //   1796: ifne -> 1826
/*    */     //   1799: aload_0
/*    */     //   1800: getfield nG : Lf/Q20;
/*    */     //   1803: aload_0
/*    */     //   1804: getfield Gd : Lf/Q20;
/*    */     //   1807: iconst_5
/*    */     //   1808: invokevirtual si : (Lf/JG0;I)V
/*    */     //   1811: goto -> 1826
/*    */     //   1814: aload_0
/*    */     //   1815: getfield nG : Lf/Q20;
/*    */     //   1818: aload_0
/*    */     //   1819: getfield Gd : Lf/Q20;
/*    */     //   1822: invokevirtual jf0 : (Lf/JG0;)Z
/*    */     //   1825: pop
/*    */     //   1826: aload_3
/*    */     //   1827: getfield G2 : Ljava/util/HashSet;
/*    */     //   1830: dup
/*    */     //   1831: astore #5
/*    */     //   1833: invokevirtual size : ()I
/*    */     //   1836: ifle -> 1967
/*    */     //   1839: aload #5
/*    */     //   1841: new java/lang/StringBuilder
/*    */     //   1844: dup
/*    */     //   1845: dup
/*    */     //   1846: astore #6
/*    */     //   1848: aload_3
/*    */     //   1849: aload #6
/*    */     //   1851: invokespecial <init> : ()V
/*    */     //   1854: getfield ee : Lf/DO;
/*    */     //   1857: getfield mt0 : I
/*    */     //   1860: invokestatic OH0 : (I)Ljava/lang/String;
/*    */     //   1863: invokevirtual append : (Ljava/lang/String;)Ljava/lang/StringBuilder;
/*    */     //   1866: pop
/*    */     //   1867: ldc_w ' / '
/*    */     //   1870: invokevirtual append : (Ljava/lang/String;)Ljava/lang/StringBuilder;
/*    */     //   1873: pop
/*    */     //   1874: iconst_0
/*    */     //   1875: istore #8
/*    */     //   1877: invokevirtual iterator : ()Ljava/util/Iterator;
/*    */     //   1880: astore #9
/*    */     //   1882: aload #9
/*    */     //   1884: invokeinterface hasNext : ()Z
/*    */     //   1889: ifeq -> 1952
/*    */     //   1892: aload #9
/*    */     //   1894: invokeinterface next : ()Ljava/lang/Object;
/*    */     //   1899: checkcast f/DO
/*    */     //   1902: dup
/*    */     //   1903: astore #10
/*    */     //   1905: ifnonnull -> 1911
/*    */     //   1908: goto -> 1882
/*    */     //   1911: iload #8
/*    */     //   1913: iconst_1
/*    */     //   1914: iadd
/*    */     //   1915: dup
/*    */     //   1916: istore #8
/*    */     //   1918: aload #5
/*    */     //   1920: aload #6
/*    */     //   1922: aload #10
/*    */     //   1924: getfield mt0 : I
/*    */     //   1927: invokestatic OH0 : (I)Ljava/lang/String;
/*    */     //   1930: invokevirtual append : (Ljava/lang/String;)Ljava/lang/StringBuilder;
/*    */     //   1933: pop
/*    */     //   1934: invokevirtual size : ()I
/*    */     //   1937: if_icmpge -> 1882
/*    */     //   1940: aload #6
/*    */     //   1942: ldc_w ' / '
/*    */     //   1945: invokevirtual append : (Ljava/lang/String;)Ljava/lang/StringBuilder;
/*    */     //   1948: pop
/*    */     //   1949: goto -> 1882
/*    */     //   1952: aload_0
/*    */     //   1953: getfield J5 : Lf/dQ;
/*    */     //   1956: aload #6
/*    */     //   1958: invokevirtual toString : ()Ljava/lang/String;
/*    */     //   1961: invokevirtual E1 : (Ljava/lang/String;)V
/*    */     //   1964: goto -> 1984
/*    */     //   1967: aload_0
/*    */     //   1968: getfield J5 : Lf/dQ;
/*    */     //   1971: aload_3
/*    */     //   1972: getfield ee : Lf/DO;
/*    */     //   1975: getfield mt0 : I
/*    */     //   1978: invokestatic OH0 : (I)Ljava/lang/String;
/*    */     //   1981: invokevirtual E1 : (Ljava/lang/String;)V
/*    */     //   1984: aload #4
/*    */     //   1986: invokevirtual isEmpty : ()Z
/*    */     //   1989: ifeq -> 1997
/*    */     //   1992: ldc_w 'None'
/*    */     //   1995: astore #4
/*    */     //   1997: aload_2
/*    */     //   1998: aload_0
/*    */     //   1999: dup
/*    */     //   2000: dup
/*    */     //   2001: getfield XD : Lf/dQ;
/*    */     //   2004: aload #4
/*    */     //   2006: invokevirtual E1 : (Ljava/lang/String;)V
/*    */     //   2009: getfield Xy0 : Lf/dQ;
/*    */     //   2012: getstatic f/F40.ef0 : Lf/F40;
/*    */     //   2015: dup
/*    */     //   2016: astore #4
/*    */     //   2018: aload_2
/*    */     //   2019: getfield AP : S
/*    */     //   2022: sipush #245
/*    */     //   2025: swap
/*    */     //   2026: invokestatic Qf0 : (Lf/F40;II)Ljava/lang/String;
/*    */     //   2029: invokevirtual E1 : (Ljava/lang/String;)V
/*    */     //   2032: getfield Me : Lf/dQ;
/*    */     //   2035: aload #4
/*    */     //   2037: aload_2
/*    */     //   2038: getfield AP : S
/*    */     //   2041: sipush #268
/*    */     //   2044: swap
/*    */     //   2045: invokestatic Qf0 : (Lf/F40;II)Ljava/lang/String;
/*    */     //   2048: invokevirtual E1 : (Ljava/lang/String;)V
/*    */     //   2051: getfield Ny : [S
/*    */     //   2054: dup
/*    */     //   2055: astore #4
/*    */     //   2057: arraylength
/*    */     //   2058: ifle -> 2166
/*    */     //   2061: new java/lang/StringBuilder
/*    */     //   2064: dup
/*    */     //   2065: astore #5
/*    */     //   2067: invokespecial <init> : ()V
/*    */     //   2070: iconst_1
/*    */     //   2071: istore #6
/*    */     //   2073: iconst_0
/*    */     //   2074: istore #8
/*    */     //   2076: iload #8
/*    */     //   2078: aload #4
/*    */     //   2080: arraylength
/*    */     //   2081: if_icmpge -> 2151
/*    */     //   2084: iload #8
/*    */     //   2086: aload #5
/*    */     //   2088: getstatic f/Of.eH : Lf/Of;
/*    */     //   2091: aload #4
/*    */     //   2093: iload #8
/*    */     //   2095: saload
/*    */     //   2096: invokevirtual On0 : (S)Lf/LPT3;
/*    */     //   2099: getfield Iu : I
/*    */     //   2102: invokestatic OH0 : (I)Ljava/lang/String;
/*    */     //   2105: invokevirtual append : (Ljava/lang/String;)Ljava/lang/StringBuilder;
/*    */     //   2108: pop
/*    */     //   2109: iconst_1
/*    */     //   2110: iadd
/*    */     //   2111: dup
/*    */     //   2112: istore #8
/*    */     //   2114: aload #4
/*    */     //   2116: arraylength
/*    */     //   2117: if_icmpge -> 2145
/*    */     //   2120: iload #6
/*    */     //   2122: aload #5
/*    */     //   2124: ldc_w ', '
/*    */     //   2127: invokevirtual append : (Ljava/lang/String;)Ljava/lang/StringBuilder;
/*    */     //   2130: pop
/*    */     //   2131: iconst_2
/*    */     //   2132: irem
/*    */     //   2133: ifne -> 2145
/*    */     //   2136: aload #5
/*    */     //   2138: ldc_w '\\n'
/*    */     //   2141: invokevirtual append : (Ljava/lang/String;)Ljava/lang/StringBuilder;
/*    */     //   2144: pop
/*    */     //   2145: iinc #6, 1
/*    */     //   2148: goto -> 2076
/*    */     //   2151: aload_0
/*    */     //   2152: getfield bE0 : Lf/dQ;
/*    */     //   2155: aload #5
/*    */     //   2157: invokevirtual toString : ()Ljava/lang/String;
/*    */     //   2160: invokevirtual E1 : (Ljava/lang/String;)V
/*    */     //   2163: goto -> 2178
/*    */     //   2166: aload_0
/*    */     //   2167: getfield bE0 : Lf/dQ;
/*    */     //   2170: bipush #61
/*    */     //   2172: invokestatic OH0 : (I)Ljava/lang/String;
/*    */     //   2175: invokevirtual E1 : (Ljava/lang/String;)V
/*    */     //   2178: aload_2
/*    */     //   2179: ldc ''
/*    */     //   2181: astore #4
/*    */     //   2183: getfield I30 : Lf/Ls0;
/*    */     //   2186: dup
/*    */     //   2187: astore #5
/*    */     //   2189: aload_2
/*    */     //   2190: getfield LPt6 : Lf/Ls0;
/*    */     //   2193: dup
/*    */     //   2194: astore #6
/*    */     //   2196: if_acmpne -> 2213
/*    */     //   2199: iconst_1
/*    */     //   2200: anewarray f/Ls0
/*    */     //   2203: dup
/*    */     //   2204: astore #6
/*    */     //   2206: iconst_0
/*    */     //   2207: aload #5
/*    */     //   2209: aastore
/*    */     //   2210: goto -> 2233
/*    */     //   2213: iconst_2
/*    */     //   2214: anewarray f/Ls0
/*    */     //   2217: dup
/*    */     //   2218: dup
/*    */     //   2219: astore #8
/*    */     //   2221: iconst_0
/*    */     //   2222: aload #5
/*    */     //   2224: aastore
/*    */     //   2225: iconst_1
/*    */     //   2226: aload #6
/*    */     //   2228: aastore
/*    */     //   2229: aload #8
/*    */     //   2231: astore #6
/*    */     //   2233: aload #6
/*    */     //   2235: arraylength
/*    */     //   2236: istore #5
/*    */     //   2238: iconst_0
/*    */     //   2239: istore #8
/*    */     //   2241: iload #8
/*    */     //   2243: iload #5
/*    */     //   2245: if_icmpge -> 2304
/*    */     //   2248: aload #4
/*    */     //   2250: aload #6
/*    */     //   2252: iload #8
/*    */     //   2254: aaload
/*    */     //   2255: astore #9
/*    */     //   2257: invokevirtual isEmpty : ()Z
/*    */     //   2260: ifne -> 2273
/*    */     //   2263: aload #4
/*    */     //   2265: ldc_w ', '
/*    */     //   2268: invokestatic tF0 : (Ljava/lang/String;Ljava/lang/String;)Ljava/lang/String;
/*    */     //   2271: astore #4
/*    */     //   2273: aload #4
/*    */     //   2275: invokestatic df : (Ljava/lang/String;)Ljava/lang/StringBuilder;
/*    */     //   2278: aload #9
/*    */     //   2280: getfield Hr0 : B
/*    */     //   2283: ldc_w 181000
/*    */     //   2286: iadd
/*    */     //   2287: invokestatic OH0 : (I)Ljava/lang/String;
/*    */     //   2290: invokevirtual append : (Ljava/lang/String;)Ljava/lang/StringBuilder;
/*    */     //   2293: invokevirtual toString : ()Ljava/lang/String;
/*    */     //   2296: astore #4
/*    */     //   2298: iinc #8, 1
/*    */     //   2301: goto -> 2241
/*    */     //   2304: aload_0
/*    */     //   2305: dup
/*    */     //   2306: getfield dk : Lf/dQ;
/*    */     //   2309: aload #4
/*    */     //   2311: invokevirtual E1 : (Ljava/lang/String;)V
/*    */     //   2314: getfield instanceof : Lf/gl;
/*    */     //   2317: getfield hi0 : Lf/uW;
/*    */     //   2320: iconst_1
/*    */     //   2321: putfield m20 : Z
/*    */     //   2324: goto -> 2540
/*    */     //   2327: aload_3
/*    */     //   2328: dup
/*    */     //   2329: aload_0
/*    */     //   2330: dup
/*    */     //   2331: dup2
/*    */     //   2332: dup2
/*    */     //   2333: dup2
/*    */     //   2334: dup2
/*    */     //   2335: dup2
/*    */     //   2336: getfield Az0 : Lf/Ro0;
/*    */     //   2339: ldc_w '?????'
/*    */     //   2342: invokevirtual E1 : (Ljava/lang/String;)V
/*    */     //   2345: getfield EI : Lf/dQ;
/*    */     //   2348: ldc_w '????? '
/*    */     //   2351: invokestatic df : (Ljava/lang/String;)Ljava/lang/StringBuilder;
/*    */     //   2354: iconst_0
/*    */     //   2355: invokestatic OH0 : (I)Ljava/lang/String;
/*    */     //   2358: invokevirtual append : (Ljava/lang/String;)Ljava/lang/StringBuilder;
/*    */     //   2361: invokevirtual toString : ()Ljava/lang/String;
/*    */     //   2364: invokevirtual E1 : (Ljava/lang/String;)V
/*    */     //   2367: getfield SB : Lf/vF0;
/*    */     //   2370: getfield TS : Lf/rH;
/*    */     //   2373: invokevirtual H : ()V
/*    */     //   2376: getfield So0 : Lf/vF0;
/*    */     //   2379: getfield TS : Lf/rH;
/*    */     //   2382: invokevirtual H : ()V
/*    */     //   2385: getfield XD : Lf/dQ;
/*    */     //   2388: ldc_w '?????'
/*    */     //   2391: invokevirtual E1 : (Ljava/lang/String;)V
/*    */     //   2394: getfield dk : Lf/dQ;
/*    */     //   2397: ldc_w '?????'
/*    */     //   2400: invokevirtual E1 : (Ljava/lang/String;)V
/*    */     //   2403: getfield Xy0 : Lf/dQ;
/*    */     //   2406: ldc_w '?????'
/*    */     //   2409: invokevirtual E1 : (Ljava/lang/String;)V
/*    */     //   2412: getfield Me : Lf/dQ;
/*    */     //   2415: ldc_w '?????'
/*    */     //   2418: invokevirtual E1 : (Ljava/lang/String;)V
/*    */     //   2421: getfield VV : Lf/dQ;
/*    */     //   2424: ldc_w '?????'
/*    */     //   2427: invokevirtual E1 : (Ljava/lang/String;)V
/*    */     //   2430: getfield VV : Lf/dQ;
/*    */     //   2433: dup
/*    */     //   2434: ldc ''
/*    */     //   2436: putfield z4 : Ljava/lang/Object;
/*    */     //   2439: invokevirtual zn : ()V
/*    */     //   2442: getfield J5 : Lf/dQ;
/*    */     //   2445: ldc_w '?????'
/*    */     //   2448: invokevirtual E1 : (Ljava/lang/String;)V
/*    */     //   2451: getfield bE0 : Lf/dQ;
/*    */     //   2454: ldc_w '?????'
/*    */     //   2457: invokevirtual E1 : (Ljava/lang/String;)V
/*    */     //   2460: invokevirtual Fk0 : ()Lf/UD0;
/*    */     //   2463: getfield AP : S
/*    */     //   2466: istore #4
/*    */     //   2468: invokevirtual ct : ()Z
/*    */     //   2471: ifeq -> 2500
/*    */     //   2474: iload #4
/*    */     //   2476: getstatic f/gm.EI0 : [S
/*    */     //   2479: invokestatic c7 : (S[S)Z
/*    */     //   2482: ifne -> 2496
/*    */     //   2485: iload #4
/*    */     //   2487: getstatic f/gm.QN : [S
/*    */     //   2490: invokestatic c7 : (S[S)Z
/*    */     //   2493: ifeq -> 2500
/*    */     //   2496: iconst_1
/*    */     //   2497: goto -> 2501
/*    */     //   2500: iconst_0
/*    */     //   2501: ifeq -> 2517
/*    */     //   2504: aload_0
/*    */     //   2505: getfield mf0 : Lf/dQ;
/*    */     //   2508: ldc_w '?????'
/*    */     //   2511: invokevirtual E1 : (Ljava/lang/String;)V
/*    */     //   2514: goto -> 2529
/*    */     //   2517: aload_0
/*    */     //   2518: getfield nG : Lf/Q20;
/*    */     //   2521: aload_0
/*    */     //   2522: getfield Gd : Lf/Q20;
/*    */     //   2525: invokevirtual jf0 : (Lf/JG0;)Z
/*    */     //   2528: pop
/*    */     //   2529: aload_0
/*    */     //   2530: getfield instanceof : Lf/gl;
/*    */     //   2533: getfield hi0 : Lf/uW;
/*    */     //   2536: iconst_0
/*    */     //   2537: putfield m20 : Z
/*    */     //   2540: aload_3
/*    */     //   2541: getfield hz0 : Ljava/util/List;
/*    */     //   2544: invokeinterface iterator : ()Ljava/util/Iterator;
/*    */     //   2549: astore #4
/*    */     //   2551: aload #4
/*    */     //   2553: invokeinterface hasNext : ()Z
/*    */     //   2558: ifeq -> 2614
/*    */     //   2561: aload_0
/*    */     //   2562: aload #4
/*    */     //   2564: invokeinterface next : ()Ljava/lang/Object;
/*    */     //   2569: checkcast f/oC0
/*    */     //   2572: astore #5
/*    */     //   2574: getfield instanceof : Lf/gl;
/*    */     //   2577: new f/J80
/*    */     //   2580: dup
/*    */     //   2581: astore #6
/*    */     //   2583: aload #5
/*    */     //   2585: dup
/*    */     //   2586: getfield ly0 : S
/*    */     //   2589: istore #5
/*    */     //   2591: getfield pE : B
/*    */     //   2594: iload #5
/*    */     //   2596: swap
/*    */     //   2597: aconst_null
/*    */     //   2598: aconst_null
/*    */     //   2599: invokespecial <init> : (SBLf/KM;Lf/LPT3;)V
/*    */     //   2602: getfield Lpt8 : Ljava/util/ArrayList;
/*    */     //   2605: aload #6
/*    */     //   2607: invokevirtual add : (Ljava/lang/Object;)Z
/*    */     //   2610: pop
/*    */     //   2611: goto -> 2551
/*    */     //   2614: new java/util/HashSet
/*    */     //   2617: dup
/*    */     //   2618: astore #4
/*    */     //   2620: invokespecial <init> : ()V
/*    */     //   2623: new f/Lw
/*    */     //   2626: dup
/*    */     //   2627: astore #5
/*    */     //   2629: invokespecial <init> : ()V
/*    */     //   2632: getstatic f/Of.eH : Lf/Of;
/*    */     //   2635: getfield cOm7 : Ljava/util/TreeMap;
/*    */     //   2638: invokevirtual values : ()Ljava/util/Collection;
/*    */     //   2641: invokeinterface iterator : ()Ljava/util/Iterator;
/*    */     //   2646: astore #6
/*    */     //   2648: aload #6
/*    */     //   2650: invokeinterface hasNext : ()Z
/*    */     //   2655: ifeq -> 2767
/*    */     //   2658: aload #4
/*    */     //   2660: aload #6
/*    */     //   2662: invokeinterface next : ()Ljava/lang/Object;
/*    */     //   2667: checkcast f/LPT3
/*    */     //   2670: dup
/*    */     //   2671: astore #8
/*    */     //   2673: getfield Iu : I
/*    */     //   2676: invokestatic OH0 : (I)Ljava/lang/String;
/*    */     //   2679: dup
/*    */     //   2680: astore #9
/*    */     //   2682: invokevirtual contains : (Ljava/lang/Object;)Z
/*    */     //   2685: ifeq -> 2691
/*    */     //   2688: goto -> 2648
/*    */     //   2691: aload #8
/*    */     //   2693: aload #4
/*    */     //   2695: aload #9
/*    */     //   2697: invokevirtual add : (Ljava/lang/Object;)Z
/*    */     //   2700: pop
/*    */     //   2701: getfield kx0 : S
/*    */     //   2704: dup
/*    */     //   2705: istore #9
/*    */     //   2707: ifle -> 2648
/*    */     //   2710: aload_3
/*    */     //   2711: getstatic f/KM.e6 : Lf/KM;
/*    */     //   2714: iload #9
/*    */     //   2716: invokevirtual HH0 : (Lf/KM;S)Z
/*    */     //   2719: ifeq -> 2648
/*    */     //   2722: aload #5
/*    */     //   2724: aload #8
/*    */     //   2726: aload_0
/*    */     //   2727: getfield instanceof : Lf/gl;
/*    */     //   2730: new f/J80
/*    */     //   2733: dup
/*    */     //   2734: astore #9
/*    */     //   2736: aload #8
/*    */     //   2738: getfield kx0 : S
/*    */     //   2741: iconst_0
/*    */     //   2742: aconst_null
/*    */     //   2743: aload #8
/*    */     //   2745: invokespecial <init> : (SBLf/KM;Lf/LPT3;)V
/*    */     //   2748: getfield Lpt8 : Ljava/util/ArrayList;
/*    */     //   2751: aload #9
/*    */     //   2753: invokevirtual add : (Ljava/lang/Object;)Z
/*    */     //   2756: pop
/*    */     //   2757: getfield kx0 : S
/*    */     //   2760: invokevirtual Ye0 : (S)Z
/*    */     //   2763: pop
/*    */     //   2764: goto -> 2648
/*    */     //   2767: aload_3
/*    */     //   2768: getstatic f/KM.Jx : Lf/KM;
/*    */     //   2771: pop
/*    */     //   2772: getfield Pw0 : [[S
/*    */     //   2775: iconst_4
/*    */     //   2776: aaload
/*    */     //   2777: dup
/*    */     //   2778: astore #4
/*    */     //   2780: arraylength
/*    */     //   2781: istore #6
/*    */     //   2783: iconst_0
/*    */     //   2784: istore #8
/*    */     //   2786: iload #8
/*    */     //   2788: iload #6
/*    */     //   2790: if_icmpge -> 2848
/*    */     //   2793: aload #5
/*    */     //   2795: aload #4
/*    */     //   2797: iload #8
/*    */     //   2799: saload
/*    */     //   2800: dup
/*    */     //   2801: istore #9
/*    */     //   2803: invokevirtual Fb : (S)Z
/*    */     //   2806: ifeq -> 2812
/*    */     //   2809: goto -> 2842
/*    */     //   2812: aload_0
/*    */     //   2813: getfield instanceof : Lf/gl;
/*    */     //   2816: new f/J80
/*    */     //   2819: dup
/*    */     //   2820: astore #10
/*    */     //   2822: iload #9
/*    */     //   2824: getstatic f/KM.e6 : Lf/KM;
/*    */     //   2827: iconst_0
/*    */     //   2828: swap
/*    */     //   2829: aconst_null
/*    */     //   2830: invokespecial <init> : (SBLf/KM;Lf/LPT3;)V
/*    */     //   2833: getfield Lpt8 : Ljava/util/ArrayList;
/*    */     //   2836: aload #10
/*    */     //   2838: invokevirtual add : (Ljava/lang/Object;)Z
/*    */     //   2841: pop
/*    */     //   2842: iinc #8, 1
/*    */     //   2845: goto -> 2786
/*    */     //   2848: aload_3
/*    */     //   2849: getstatic f/KM.Jx : Lf/KM;
/*    */     //   2852: pop
/*    */     //   2853: getfield Pw0 : [[S
/*    */     //   2856: iconst_3
/*    */     //   2857: aaload
/*    */     //   2858: dup
/*    */     //   2859: astore #4
/*    */     //   2861: arraylength
/*    */     //   2862: istore #5
/*    */     //   2864: iconst_0
/*    */     //   2865: istore #6
/*    */     //   2867: iload #6
/*    */     //   2869: iload #5
/*    */     //   2871: if_icmpge -> 2917
/*    */     //   2874: aload_0
/*    */     //   2875: aload #4
/*    */     //   2877: iload #6
/*    */     //   2879: saload
/*    */     //   2880: istore #8
/*    */     //   2882: getfield instanceof : Lf/gl;
/*    */     //   2885: new f/J80
/*    */     //   2888: dup
/*    */     //   2889: astore #9
/*    */     //   2891: iload #8
/*    */     //   2893: getstatic f/KM.tG0 : Lf/KM;
/*    */     //   2896: iconst_0
/*    */     //   2897: swap
/*    */     //   2898: aconst_null
/*    */     //   2899: invokespecial <init> : (SBLf/KM;Lf/LPT3;)V
/*    */     //   2902: getfield Lpt8 : Ljava/util/ArrayList;
/*    */     //   2905: aload #9
/*    */     //   2907: invokevirtual add : (Ljava/lang/Object;)Z
/*    */     //   2910: pop
/*    */     //   2911: iinc #6, 1
/*    */     //   2914: goto -> 2867
/*    */     //   2917: new f/Lw
/*    */     //   2920: dup
/*    */     //   2921: astore #4
/*    */     //   2923: invokespecial <init> : ()V
/*    */     //   2926: new f/Lw
/*    */     //   2929: dup
/*    */     //   2930: astore #5
/*    */     //   2932: invokespecial <init> : ()V
/*    */     //   2935: aload_2
/*    */     //   2936: astore #6
/*    */     //   2938: aload #6
/*    */     //   2940: ifnull -> 3104
/*    */     //   2943: aload #4
/*    */     //   2945: aload #6
/*    */     //   2947: getfield AP : S
/*    */     //   2950: invokevirtual Fb : (S)Z
/*    */     //   2953: ifne -> 3104
/*    */     //   2956: aload #6
/*    */     //   2958: getfield TL : S
/*    */     //   2961: ifle -> 2989
/*    */     //   2964: iload_1
/*    */     //   2965: ifle -> 2989
/*    */     //   2968: invokestatic v30 : ()Lf/On;
/*    */     //   2971: aload #6
/*    */     //   2973: getfield TL : S
/*    */     //   2976: iload_1
/*    */     //   2977: iadd
/*    */     //   2978: iconst_1
/*    */     //   2979: isub
/*    */     //   2980: i2s
/*    */     //   2981: invokevirtual lpT3 : (S)Lf/UD0;
/*    */     //   2984: astore #8
/*    */     //   2986: goto -> 2993
/*    */     //   2989: aload #6
/*    */     //   2991: astore #8
/*    */     //   2993: aload #8
/*    */     //   2995: aload #4
/*    */     //   2997: aload #6
/*    */     //   2999: getfield AP : S
/*    */     //   3002: invokevirtual Ye0 : (S)Z
/*    */     //   3005: pop
/*    */     //   3006: getstatic f/KM.Jx : Lf/KM;
/*    */     //   3009: pop
/*    */     //   3010: getfield Pw0 : [[S
/*    */     //   3013: iconst_0
/*    */     //   3014: aaload
/*    */     //   3015: dup
/*    */     //   3016: astore #8
/*    */     //   3018: arraylength
/*    */     //   3019: istore #9
/*    */     //   3021: iconst_0
/*    */     //   3022: istore #10
/*    */     //   3024: iload #10
/*    */     //   3026: iload #9
/*    */     //   3028: if_icmpge -> 3094
/*    */     //   3031: aload #5
/*    */     //   3033: aload #8
/*    */     //   3035: iload #10
/*    */     //   3037: saload
/*    */     //   3038: dup
/*    */     //   3039: istore #11
/*    */     //   3041: invokevirtual Fb : (S)Z
/*    */     //   3044: ifeq -> 3050
/*    */     //   3047: goto -> 3088
/*    */     //   3050: aload_0
/*    */     //   3051: aload #5
/*    */     //   3053: iload #11
/*    */     //   3055: invokevirtual Ye0 : (S)Z
/*    */     //   3058: pop
/*    */     //   3059: getfield instanceof : Lf/gl;
/*    */     //   3062: new f/J80
/*    */     //   3065: dup
/*    */     //   3066: astore #12
/*    */     //   3068: iload #11
/*    */     //   3070: getstatic f/KM.Jx : Lf/KM;
/*    */     //   3073: iconst_0
/*    */     //   3074: swap
/*    */     //   3075: aconst_null
/*    */     //   3076: invokespecial <init> : (SBLf/KM;Lf/LPT3;)V
/*    */     //   3079: getfield Lpt8 : Ljava/util/ArrayList;
/*    */     //   3082: aload #12
/*    */     //   3084: invokevirtual add : (Ljava/lang/Object;)Z
/*    */     //   3087: pop
/*    */     //   3088: iinc #10, 1
/*    */     //   3091: goto -> 3024
/*    */     //   3094: aload #6
/*    */     //   3096: getfield FW : Lf/UD0;
/*    */     //   3099: astore #6
/*    */     //   3101: goto -> 2938
/*    */     //   3104: aload_3
/*    */     //   3105: getstatic f/KM.Jx : Lf/KM;
/*    */     //   3108: pop
/*    */     //   3109: getfield Pw0 : [[S
/*    */     //   3112: iconst_1
/*    */     //   3113: aaload
/*    */     //   3114: dup
/*    */     //   3115: astore_1
/*    */     //   3116: arraylength
/*    */     //   3117: istore #4
/*    */     //   3119: iconst_0
/*    */     //   3120: istore #5
/*    */     //   3122: iload #5
/*    */     //   3124: iload #4
/*    */     //   3126: if_icmpge -> 3171
/*    */     //   3129: aload_0
/*    */     //   3130: aload_1
/*    */     //   3131: iload #5
/*    */     //   3133: saload
/*    */     //   3134: istore #6
/*    */     //   3136: getfield instanceof : Lf/gl;
/*    */     //   3139: new f/J80
/*    */     //   3142: dup
/*    */     //   3143: astore #8
/*    */     //   3145: iload #6
/*    */     //   3147: getstatic f/KM.U40 : Lf/KM;
/*    */     //   3150: iconst_0
/*    */     //   3151: swap
/*    */     //   3152: aconst_null
/*    */     //   3153: invokespecial <init> : (SBLf/KM;Lf/LPT3;)V
/*    */     //   3156: getfield Lpt8 : Ljava/util/ArrayList;
/*    */     //   3159: aload #8
/*    */     //   3161: invokevirtual add : (Ljava/lang/Object;)Z
/*    */     //   3164: pop
/*    */     //   3165: iinc #5, 1
/*    */     //   3168: goto -> 3122
/*    */     //   3171: aload_3
/*    */     //   3172: getstatic f/KM.Jx : Lf/KM;
/*    */     //   3175: pop
/*    */     //   3176: getfield Pw0 : [[S
/*    */     //   3179: iconst_2
/*    */     //   3180: aaload
/*    */     //   3181: dup
/*    */     //   3182: astore_1
/*    */     //   3183: arraylength
/*    */     //   3184: istore #4
/*    */     //   3186: iconst_0
/*    */     //   3187: istore #5
/*    */     //   3189: iload #5
/*    */     //   3191: iload #4
/*    */     //   3193: if_icmpge -> 3238
/*    */     //   3196: aload_0
/*    */     //   3197: aload_1
/*    */     //   3198: iload #5
/*    */     //   3200: saload
/*    */     //   3201: istore #6
/*    */     //   3203: getfield instanceof : Lf/gl;
/*    */     //   3206: new f/J80
/*    */     //   3209: dup
/*    */     //   3210: astore #8
/*    */     //   3212: iload #6
/*    */     //   3214: getstatic f/KM.H70 : Lf/KM;
/*    */     //   3217: iconst_0
/*    */     //   3218: swap
/*    */     //   3219: aconst_null
/*    */     //   3220: invokespecial <init> : (SBLf/KM;Lf/LPT3;)V
/*    */     //   3223: getfield Lpt8 : Ljava/util/ArrayList;
/*    */     //   3226: aload #8
/*    */     //   3228: invokevirtual add : (Ljava/lang/Object;)Z
/*    */     //   3231: pop
/*    */     //   3232: iinc #5, 1
/*    */     //   3235: goto -> 3189
/*    */     //   3238: aload_3
/*    */     //   3239: getstatic f/KM.Jx : Lf/KM;
/*    */     //   3242: pop
/*    */     //   3243: getfield Pw0 : [[S
/*    */     //   3246: iconst_5
/*    */     //   3247: aaload
/*    */     //   3248: dup
/*    */     //   3249: astore_1
/*    */     //   3250: arraylength
/*    */     //   3251: istore #4
/*    */     //   3253: iconst_0
/*    */     //   3254: istore #5
/*    */     //   3256: iload #5
/*    */     //   3258: iload #4
/*    */     //   3260: if_icmpge -> 3305
/*    */     //   3263: aload_0
/*    */     //   3264: aload_1
/*    */     //   3265: iload #5
/*    */     //   3267: saload
/*    */     //   3268: istore #6
/*    */     //   3270: getfield instanceof : Lf/gl;
/*    */     //   3273: new f/J80
/*    */     //   3276: dup
/*    */     //   3277: astore #8
/*    */     //   3279: iload #6
/*    */     //   3281: getstatic f/KM.mA : Lf/KM;
/*    */     //   3284: iconst_0
/*    */     //   3285: swap
/*    */     //   3286: aconst_null
/*    */     //   3287: invokespecial <init> : (SBLf/KM;Lf/LPT3;)V
/*    */     //   3290: getfield Lpt8 : Ljava/util/ArrayList;
/*    */     //   3293: aload #8
/*    */     //   3295: invokevirtual add : (Ljava/lang/Object;)Z
/*    */     //   3298: pop
/*    */     //   3299: iinc #5, 1
/*    */     //   3302: goto -> 3256
/*    */     //   3305: aload_3
/*    */     //   3306: getstatic f/KM.Jx : Lf/KM;
/*    */     //   3309: pop
/*    */     //   3310: getfield Pw0 : [[S
/*    */     //   3313: bipush #6
/*    */     //   3315: aaload
/*    */     //   3316: dup
/*    */     //   3317: astore_1
/*    */     //   3318: arraylength
/*    */     //   3319: istore_3
/*    */     //   3320: iconst_0
/*    */     //   3321: istore #4
/*    */     //   3323: iload #4
/*    */     //   3325: iload_3
/*    */     //   3326: if_icmpge -> 3371
/*    */     //   3329: aload_0
/*    */     //   3330: aload_1
/*    */     //   3331: iload #4
/*    */     //   3333: saload
/*    */     //   3334: istore #5
/*    */     //   3336: getfield instanceof : Lf/gl;
/*    */     //   3339: new f/J80
/*    */     //   3342: dup
/*    */     //   3343: astore #6
/*    */     //   3345: iload #5
/*    */     //   3347: getstatic f/KM.d5 : Lf/KM;
/*    */     //   3350: iconst_0
/*    */     //   3351: swap
/*    */     //   3352: aconst_null
/*    */     //   3353: invokespecial <init> : (SBLf/KM;Lf/LPT3;)V
/*    */     //   3356: getfield Lpt8 : Ljava/util/ArrayList;
/*    */     //   3359: aload #6
/*    */     //   3361: invokevirtual add : (Ljava/lang/Object;)Z
/*    */     //   3364: pop
/*    */     //   3365: iinc #4, 1
/*    */     //   3368: goto -> 3323
/*    */     //   3371: aload_2
/*    */     //   3372: aload_0
/*    */     //   3373: dup
/*    */     //   3374: dup2
/*    */     //   3375: getfield instanceof : Lf/gl;
/*    */     //   3378: invokevirtual Sj : ()V
/*    */     //   3381: getstatic f/UB0.Kg0 : Lf/Q50;
/*    */     //   3384: aload_0
/*    */     //   3385: getfield ci0 : Lf/Ip;
/*    */     //   3388: dup
/*    */     //   3389: invokevirtual getClass : ()Ljava/lang/Class;
/*    */     //   3392: pop
/*    */     //   3393: <illegal opcode> run : (Lf/Ip;)Ljava/lang/Runnable;
/*    */     //   3398: invokevirtual fN : (Ljava/lang/Runnable;)V
/*    */     //   3401: getfield Gc0 : Lf/Ip;
/*    */     //   3404: getfield Xz0 : Lf/U90;
/*    */     //   3407: invokevirtual Hb : ()V
/*    */     //   3410: getfield Gc0 : Lf/Ip;
/*    */     //   3413: getfield o30 : Lf/U90;
/*    */     //   3416: invokevirtual Hb : ()V
/*    */     //   3419: sipush #1776
/*    */     //   3422: invokestatic OH0 : (I)Ljava/lang/String;
/*    */     //   3425: sipush #1777
/*    */     //   3428: invokestatic OH0 : (I)Ljava/lang/String;
/*    */     //   3431: astore_1
/*    */     //   3432: sipush #1778
/*    */     //   3435: invokestatic OH0 : (I)Ljava/lang/String;
/*    */     //   3438: astore_3
/*    */     //   3439: sipush #1779
/*    */     //   3442: invokestatic OH0 : (I)Ljava/lang/String;
/*    */     //   3445: astore #4
/*    */     //   3447: sipush #1781
/*    */     //   3450: invokestatic OH0 : (I)Ljava/lang/String;
/*    */     //   3453: astore #5
/*    */     //   3455: iconst_1
/*    */     //   3456: swap
/*    */     //   3457: aload_1
/*    */     //   3458: aload_3
/*    */     //   3459: aload #4
/*    */     //   3461: aload #5
/*    */     //   3463: iconst_1
/*    */     //   3464: invokevirtual NG : (ZLjava/lang/String;Ljava/lang/String;Ljava/lang/String;Ljava/lang/String;Ljava/lang/String;Z)V
/*    */     //   3467: getstatic f/k50.Gp : Lf/k50;
/*    */     //   3470: astore_1
/*    */     //   3471: getfield AP : S
/*    */     //   3474: istore_3
/*    */     //   3475: aload_1
/*    */     //   3476: getfield g90 : Lf/qw0;
/*    */     //   3479: iload_3
/*    */     //   3480: invokevirtual Z90 : (S)Ljava/lang/Object;
/*    */     //   3483: checkcast f/Jt
/*    */     //   3486: dup
/*    */     //   3487: astore #4
/*    */     //   3489: ifnonnull -> 3513
/*    */     //   3492: aload_1
/*    */     //   3493: new f/Jt
/*    */     //   3496: dup
/*    */     //   3497: astore #4
/*    */     //   3499: iload_3
/*    */     //   3500: invokespecial <init> : (S)V
/*    */     //   3503: getfield g90 : Lf/qw0;
/*    */     //   3506: iload_3
/*    */     //   3507: aload #4
/*    */     //   3509: invokevirtual Vh0 : (SLjava/lang/Object;)Ljava/lang/Object;
/*    */     //   3512: pop
/*    */     //   3513: aload #4
/*    */     //   3515: getfield s20 : Ljava/util/ArrayList;
/*    */     //   3518: dup
/*    */     //   3519: astore_1
/*    */     //   3520: invokevirtual isEmpty : ()Z
/*    */     //   3523: ifeq -> 3765
/*    */     //   3526: getstatic f/km.u4 : Lf/R8;
/*    */     //   3529: getfield GN : [S
/*    */     //   3532: dup
/*    */     //   3533: astore_1
/*    */     //   3534: aload_2
/*    */     //   3535: getfield AP : S
/*    */     //   3538: istore_3
/*    */     //   3539: iconst_0
/*    */     //   3540: istore #4
/*    */     //   3542: ifnull -> 3578
/*    */     //   3545: aload_1
/*    */     //   3546: arraylength
/*    */     //   3547: iconst_1
/*    */     //   3548: if_icmpge -> 3554
/*    */     //   3551: goto -> 3578
/*    */     //   3554: iload #4
/*    */     //   3556: aload_1
/*    */     //   3557: arraylength
/*    */     //   3558: if_icmpge -> 3578
/*    */     //   3561: iload_3
/*    */     //   3562: aload_1
/*    */     //   3563: iload #4
/*    */     //   3565: saload
/*    */     //   3566: if_icmpne -> 3572
/*    */     //   3569: goto -> 3581
/*    */     //   3572: iinc #4, 1
/*    */     //   3575: goto -> 3554
/*    */     //   3578: iconst_m1
/*    */     //   3579: istore #4
/*    */     //   3581: iload #4
/*    */     //   3583: iconst_m1
/*    */     //   3584: if_icmpeq -> 3736
/*    */     //   3587: getstatic f/km.u4 : Lf/R8;
/*    */     //   3590: invokevirtual vC : ()Lf/BF;
/*    */     //   3593: aload_2
/*    */     //   3594: invokevirtual Uf : ()S
/*    */     //   3597: invokevirtual J80 : (S)Z
/*    */     //   3600: ifeq -> 3736
/*    */     //   3603: iload #4
/*    */     //   3605: i2b
/*    */     //   3606: invokestatic zd : (B)Ljava/lang/String;
/*    */     //   3609: astore_1
/*    */     //   3610: getstatic f/km.u4 : Lf/R8;
/*    */     //   3613: aload_2
/*    */     //   3614: invokevirtual Uf : ()S
/*    */     //   3617: invokevirtual Nz : (S)Z
/*    */     //   3620: ifeq -> 3657
/*    */     //   3623: aload_0
/*    */     //   3624: sipush #1765
/*    */     //   3627: invokestatic OH0 : (I)Ljava/lang/String;
/*    */     //   3630: astore_3
/*    */     //   3631: sipush #1767
/*    */     //   3634: invokestatic OH0 : (I)Ljava/lang/String;
/*    */     //   3637: astore #4
/*    */     //   3639: iconst_1
/*    */     //   3640: ldc_w '--'
/*    */     //   3643: aload_1
/*    */     //   3644: aload_3
/*    */     //   3645: ldc_w '50'
/*    */     //   3648: aload #4
/*    */     //   3650: iconst_0
/*    */     //   3651: invokevirtual NG : (ZLjava/lang/String;Ljava/lang/String;Ljava/lang/String;Ljava/lang/String;Ljava/lang/String;Z)V
/*    */     //   3654: goto -> 3809
/*    */     //   3657: aload_2
/*    */     //   3658: getstatic f/km.u4 : Lf/R8;
/*    */     //   3661: astore_3
/*    */     //   3662: invokevirtual Uf : ()S
/*    */     //   3665: aload_3
/*    */     //   3666: invokevirtual getClass : ()Ljava/lang/Class;
/*    */     //   3669: pop
/*    */     //   3670: invokestatic sc : (S)[Lf/pM;
/*    */     //   3673: dup
/*    */     //   3674: astore_3
/*    */     //   3675: arraylength
/*    */     //   3676: istore #4
/*    */     //   3678: iconst_0
/*    */     //   3679: istore #5
/*    */     //   3681: iload #5
/*    */     //   3683: iload #4
/*    */     //   3685: if_icmpge -> 3809
/*    */     //   3688: aload_0
/*    */     //   3689: aload_3
/*    */     //   3690: iload #5
/*    */     //   3692: aaload
/*    */     //   3693: invokevirtual Rg0 : ()I
/*    */     //   3696: invokestatic OH0 : (I)Ljava/lang/String;
/*    */     //   3699: sipush #1766
/*    */     //   3702: aload_1
/*    */     //   3703: invokestatic Go : (ILjava/lang/String;)Ljava/lang/String;
/*    */     //   3706: astore #6
/*    */     //   3708: sipush #1767
/*    */     //   3711: invokestatic OH0 : (I)Ljava/lang/String;
/*    */     //   3714: astore #7
/*    */     //   3716: iconst_1
/*    */     //   3717: swap
/*    */     //   3718: aload_1
/*    */     //   3719: aload #6
/*    */     //   3721: ldc_w '???'
/*    */     //   3724: aload #7
/*    */     //   3726: iconst_0
/*    */     //   3727: invokevirtual NG : (ZLjava/lang/String;Ljava/lang/String;Ljava/lang/String;Ljava/lang/String;Ljava/lang/String;Z)V
/*    */     //   3730: iinc #5, 1
/*    */     //   3733: goto -> 3681
/*    */     //   3736: aload_0
/*    */     //   3737: sipush #1791
/*    */     //   3740: invokestatic OH0 : (I)Ljava/lang/String;
/*    */     //   3743: astore_1
/*    */     //   3744: iconst_1
/*    */     //   3745: ldc_w '--'
/*    */     //   3748: ldc_w '--'
/*    */     //   3751: aload_1
/*    */     //   3752: ldc_w '--'
/*    */     //   3755: ldc_w '--'
/*    */     //   3758: iconst_0
/*    */     //   3759: invokevirtual NG : (ZLjava/lang/String;Ljava/lang/String;Ljava/lang/String;Ljava/lang/String;Ljava/lang/String;Z)V
/*    */     //   3762: goto -> 3809
/*    */     //   3765: aload_1
/*    */     //   3766: dup
/*    */     //   3767: aload_0
/*    */     //   3768: <illegal opcode> compare : (Lf/Hy;)Ljava/util/Comparator;
/*    */     //   3773: invokestatic sort : (Ljava/util/List;Ljava/util/Comparator;)V
/*    */     //   3776: invokeinterface iterator : ()Ljava/util/Iterator;
/*    */     //   3781: astore_1
/*    */     //   3782: aload_1
/*    */     //   3783: invokeinterface hasNext : ()Z
/*    */     //   3788: ifeq -> 3809
/*    */     //   3791: aload_0
/*    */     //   3792: iload #7
/*    */     //   3794: aload_1
/*    */     //   3795: invokeinterface next : ()Ljava/lang/Object;
/*    */     //   3800: checkcast f/Hq
/*    */     //   3803: invokevirtual V5 : (ZLf/Hq;)V
/*    */     //   3806: goto -> 3782
/*    */     //   3809: aload_0
/*    */     //   3810: dup
/*    */     //   3811: dup2
/*    */     //   3812: getfield Gc0 : Lf/Ip;
/*    */     //   3815: invokevirtual mM : ()V
/*    */     //   3818: getstatic f/UB0.Kg0 : Lf/Q50;
/*    */     //   3821: aload_0
/*    */     //   3822: getfield O40 : Lf/Ip;
/*    */     //   3825: dup
/*    */     //   3826: invokevirtual getClass : ()Ljava/lang/Class;
/*    */     //   3829: pop
/*    */     //   3830: <illegal opcode> run : (Lf/Ip;)Ljava/lang/Runnable;
/*    */     //   3835: invokevirtual fN : (Ljava/lang/Runnable;)V
/*    */     //   3838: getfield y8 : Lf/Ip;
/*    */     //   3841: invokevirtual iJ0 : ()Lf/U90;
/*    */     //   3844: invokevirtual Hb : ()V
/*    */     //   3847: getfield y8 : Lf/Ip;
/*    */     //   3850: invokevirtual xh : ()Lf/U90;
/*    */     //   3853: invokevirtual Hb : ()V
/*    */     //   3856: getfield y8 : Lf/Ip;
/*    */     //   3859: invokevirtual iJ0 : ()Lf/U90;
/*    */     //   3862: invokevirtual Em0 : ()Lf/U90;
/*    */     //   3865: pop
/*    */     //   3866: new f/aI0
/*    */     //   3869: dup
/*    */     //   3870: astore_1
/*    */     //   3871: aload_2
/*    */     //   3872: invokespecial <init> : (Lf/UD0;)V
/*    */     //   3875: iconst_1
/*    */     //   3876: istore_2
/*    */     //   3877: invokestatic XU : ()Z
/*    */     //   3880: ifeq -> 3889
/*    */     //   3883: bipush #92
/*    */     //   3885: istore_3
/*    */     //   3886: goto -> 3892
/*    */     //   3889: bipush #46
/*    */     //   3891: istore_3
/*    */     //   3892: aload_1
/*    */     //   3893: getfield Lm0 : Ljava/util/TreeMap;
/*    */     //   3896: invokevirtual values : ()Ljava/util/Collection;
/*    */     //   3899: invokeinterface iterator : ()Ljava/util/Iterator;
/*    */     //   3904: astore #4
/*    */     //   3906: aload #4
/*    */     //   3908: invokeinterface hasNext : ()Z
/*    */     //   3913: ifeq -> 4775
/*    */     //   3916: aload #4
/*    */     //   3918: invokeinterface next : ()Ljava/lang/Object;
/*    */     //   3923: checkcast f/Mr0
/*    */     //   3926: astore #5
/*    */     //   3928: iconst_0
/*    */     //   3929: anewarray f/Fy0
/*    */     //   3932: astore #6
/*    */     //   3934: iconst_0
/*    */     //   3935: istore #7
/*    */     //   3937: iload #7
/*    */     //   3939: iconst_2
/*    */     //   3940: if_icmpge -> 3906
/*    */     //   3943: iload #7
/*    */     //   3945: ifne -> 4062
/*    */     //   3948: iload_2
/*    */     //   3949: ifeq -> 3957
/*    */     //   3952: iconst_0
/*    */     //   3953: istore_2
/*    */     //   3954: goto -> 4769
/*    */     //   3957: aload #5
/*    */     //   3959: getfield com5 : Ljava/util/TreeMap;
/*    */     //   3962: invokevirtual values : ()Ljava/util/Collection;
/*    */     //   3965: iconst_0
/*    */     //   3966: anewarray f/UD0
/*    */     //   3969: invokeinterface toArray : ([Ljava/lang/Object;)[Ljava/lang/Object;
/*    */     //   3974: checkcast [Lf/UD0;
/*    */     //   3977: arraylength
/*    */     //   3978: aload #5
/*    */     //   3980: getfield Kn : Ljava/util/TreeMap;
/*    */     //   3983: invokevirtual values : ()Ljava/util/Collection;
/*    */     //   3986: iconst_0
/*    */     //   3987: anewarray f/Vx0
/*    */     //   3990: invokeinterface toArray : ([Ljava/lang/Object;)[Ljava/lang/Object;
/*    */     //   3995: checkcast [Lf/Vx0;
/*    */     //   3998: arraylength
/*    */     //   3999: invokestatic max : (II)I
/*    */     //   4002: dup
/*    */     //   4003: istore #6
/*    */     //   4005: anewarray f/Fy0
/*    */     //   4008: astore #8
/*    */     //   4010: iconst_0
/*    */     //   4011: istore #9
/*    */     //   4013: iload #9
/*    */     //   4015: iload #6
/*    */     //   4017: if_icmpge -> 4055
/*    */     //   4020: new f/Fy0
/*    */     //   4023: dup
/*    */     //   4024: astore #10
/*    */     //   4026: aload #8
/*    */     //   4028: iload #9
/*    */     //   4030: aload #10
/*    */     //   4032: ldc_w '─➤'
/*    */     //   4035: iload_3
/*    */     //   4036: dup
/*    */     //   4037: invokespecial <init> : (Ljava/lang/String;II)V
/*    */     //   4040: aload #10
/*    */     //   4042: aastore
/*    */     //   4043: ldc_w 'monsterdex-button-evo-tree'
/*    */     //   4046: invokevirtual Xu : (Ljava/lang/String;)V
/*    */     //   4049: iinc #9, 1
/*    */     //   4052: goto -> 4013
/*    */     //   4055: aload #8
/*    */     //   4057: astore #6
/*    */     //   4059: goto -> 4608
/*    */     //   4062: aload #5
/*    */     //   4064: getfield com5 : Ljava/util/TreeMap;
/*    */     //   4067: invokevirtual values : ()Ljava/util/Collection;
/*    */     //   4070: iconst_0
/*    */     //   4071: anewarray f/UD0
/*    */     //   4074: invokeinterface toArray : ([Ljava/lang/Object;)[Ljava/lang/Object;
/*    */     //   4079: checkcast [Lf/UD0;
/*    */     //   4082: arraylength
/*    */     //   4083: ifle -> 4501
/*    */     //   4086: aload #5
/*    */     //   4088: getfield com5 : Ljava/util/TreeMap;
/*    */     //   4091: invokevirtual values : ()Ljava/util/Collection;
/*    */     //   4094: iconst_0
/*    */     //   4095: anewarray f/UD0
/*    */     //   4098: invokeinterface toArray : ([Ljava/lang/Object;)[Ljava/lang/Object;
/*    */     //   4103: checkcast [Lf/UD0;
/*    */     //   4106: dup
/*    */     //   4107: astore #6
/*    */     //   4109: arraylength
/*    */     //   4110: dup
/*    */     //   4111: istore #8
/*    */     //   4113: anewarray f/Fy0
/*    */     //   4116: astore #9
/*    */     //   4118: iconst_0
/*    */     //   4119: istore #10
/*    */     //   4121: iload #10
/*    */     //   4123: iload #8
/*    */     //   4125: if_icmpge -> 4189
/*    */     //   4128: aload #9
/*    */     //   4130: iload #10
/*    */     //   4132: new f/k2
/*    */     //   4135: dup
/*    */     //   4136: astore #11
/*    */     //   4138: aload #9
/*    */     //   4140: iload #10
/*    */     //   4142: aload #11
/*    */     //   4144: dup
/*    */     //   4145: aload_0
/*    */     //   4146: dup
/*    */     //   4147: aload #6
/*    */     //   4149: iload #10
/*    */     //   4151: aaload
/*    */     //   4152: astore #11
/*    */     //   4154: getfield HH : B
/*    */     //   4157: istore #12
/*    */     //   4159: aload #11
/*    */     //   4161: iconst_0
/*    */     //   4162: iload #12
/*    */     //   4164: invokespecial <init> : (Lf/Hy;Lf/UD0;BB)V
/*    */     //   4167: aastore
/*    */     //   4168: ldc ''
/*    */     //   4170: invokevirtual s6 : (Ljava/lang/String;)V
/*    */     //   4173: aaload
/*    */     //   4174: invokevirtual zY : ()Lf/rH;
/*    */     //   4177: iconst_5
/*    */     //   4178: iconst_2
/*    */     //   4179: invokevirtual zT : (II)Lf/JG0;
/*    */     //   4182: pop
/*    */     //   4183: iinc #10, 1
/*    */     //   4186: goto -> 4121
/*    */     //   4189: aload_1
/*    */     //   4190: aload #5
/*    */     //   4192: getfield a9 : I
/*    */     //   4195: istore #6
/*    */     //   4197: getfield Lm0 : Ljava/util/TreeMap;
/*    */     //   4200: iload #6
/*    */     //   4202: iconst_1
/*    */     //   4203: iadd
/*    */     //   4204: invokestatic valueOf : (I)Ljava/lang/Integer;
/*    */     //   4207: invokevirtual get : (Ljava/lang/Object;)Ljava/lang/Object;
/*    */     //   4210: checkcast f/Mr0
/*    */     //   4213: dup
/*    */     //   4214: astore #6
/*    */     //   4216: ifnonnull -> 4222
/*    */     //   4219: goto -> 4244
/*    */     //   4222: aload #6
/*    */     //   4224: getfield com5 : Ljava/util/TreeMap;
/*    */     //   4227: invokevirtual size : ()I
/*    */     //   4230: aload #6
/*    */     //   4232: getfield Kn : Ljava/util/TreeMap;
/*    */     //   4235: invokevirtual size : ()I
/*    */     //   4238: invokestatic max : (II)I
/*    */     //   4241: ifne -> 4248
/*    */     //   4244: iconst_0
/*    */     //   4245: goto -> 4269
/*    */     //   4248: aload #6
/*    */     //   4250: getfield com5 : Ljava/util/TreeMap;
/*    */     //   4253: invokevirtual size : ()I
/*    */     //   4256: aload #6
/*    */     //   4258: getfield Kn : Ljava/util/TreeMap;
/*    */     //   4261: invokevirtual size : ()I
/*    */     //   4264: invokestatic max : (II)I
/*    */     //   4267: iconst_1
/*    */     //   4268: ior
/*    */     //   4269: iload #8
/*    */     //   4271: iconst_1
/*    */     //   4272: ior
/*    */     //   4273: if_icmple -> 4604
/*    */     //   4276: aload_1
/*    */     //   4277: aload #5
/*    */     //   4279: getfield a9 : I
/*    */     //   4282: istore #6
/*    */     //   4284: getfield Lm0 : Ljava/util/TreeMap;
/*    */     //   4287: iload #6
/*    */     //   4289: iconst_1
/*    */     //   4290: iadd
/*    */     //   4291: invokestatic valueOf : (I)Ljava/lang/Integer;
/*    */     //   4294: invokevirtual get : (Ljava/lang/Object;)Ljava/lang/Object;
/*    */     //   4297: checkcast f/Mr0
/*    */     //   4300: dup
/*    */     //   4301: astore #6
/*    */     //   4303: ifnonnull -> 4309
/*    */     //   4306: goto -> 4331
/*    */     //   4309: aload #6
/*    */     //   4311: getfield com5 : Ljava/util/TreeMap;
/*    */     //   4314: invokevirtual size : ()I
/*    */     //   4317: aload #6
/*    */     //   4319: getfield Kn : Ljava/util/TreeMap;
/*    */     //   4322: invokevirtual size : ()I
/*    */     //   4325: invokestatic max : (II)I
/*    */     //   4328: ifne -> 4337
/*    */     //   4331: iconst_0
/*    */     //   4332: istore #6
/*    */     //   4334: goto -> 4360
/*    */     //   4337: aload #6
/*    */     //   4339: getfield com5 : Ljava/util/TreeMap;
/*    */     //   4342: invokevirtual size : ()I
/*    */     //   4345: aload #6
/*    */     //   4347: getfield Kn : Ljava/util/TreeMap;
/*    */     //   4350: invokevirtual size : ()I
/*    */     //   4353: invokestatic max : (II)I
/*    */     //   4356: iconst_1
/*    */     //   4357: ior
/*    */     //   4358: istore #6
/*    */     //   4360: iload #6
/*    */     //   4362: anewarray f/Fy0
/*    */     //   4365: astore #10
/*    */     //   4367: iconst_0
/*    */     //   4368: istore #11
/*    */     //   4370: iload #11
/*    */     //   4372: iload #6
/*    */     //   4374: if_icmpge -> 4412
/*    */     //   4377: new f/Fy0
/*    */     //   4380: dup
/*    */     //   4381: astore #12
/*    */     //   4383: aload #10
/*    */     //   4385: iload #11
/*    */     //   4387: aload #12
/*    */     //   4389: ldc_w '─➤'
/*    */     //   4392: iload_3
/*    */     //   4393: dup
/*    */     //   4394: invokespecial <init> : (Ljava/lang/String;II)V
/*    */     //   4397: aload #12
/*    */     //   4399: aastore
/*    */     //   4400: ldc_w 'monsterdex-button-evo-tree'
/*    */     //   4403: invokevirtual Xu : (Ljava/lang/String;)V
/*    */     //   4406: iinc #11, 1
/*    */     //   4409: goto -> 4370
/*    */     //   4412: iload #6
/*    */     //   4414: iload #8
/*    */     //   4416: isub
/*    */     //   4417: dup
/*    */     //   4418: istore #11
/*    */     //   4420: aload #9
/*    */     //   4422: iload #11
/*    */     //   4424: iconst_2
/*    */     //   4425: idiv
/*    */     //   4426: istore #9
/*    */     //   4428: iconst_0
/*    */     //   4429: aload #10
/*    */     //   4431: iload #9
/*    */     //   4433: iload #8
/*    */     //   4435: invokestatic arraycopy : (Ljava/lang/Object;ILjava/lang/Object;II)V
/*    */     //   4438: iconst_2
/*    */     //   4439: if_icmplt -> 4494
/*    */     //   4442: iload #11
/*    */     //   4444: aload #10
/*    */     //   4446: iload #6
/*    */     //   4448: aload #10
/*    */     //   4450: iconst_0
/*    */     //   4451: aaload
/*    */     //   4452: ldc_w '┌─'
/*    */     //   4455: invokevirtual s6 : (Ljava/lang/String;)V
/*    */     //   4458: iconst_1
/*    */     //   4459: isub
/*    */     //   4460: aaload
/*    */     //   4461: ldc_w '└─'
/*    */     //   4464: invokevirtual s6 : (Ljava/lang/String;)V
/*    */     //   4467: iconst_4
/*    */     //   4468: if_icmplt -> 4494
/*    */     //   4471: aload #10
/*    */     //   4473: iload #6
/*    */     //   4475: aload #10
/*    */     //   4477: iconst_1
/*    */     //   4478: aaload
/*    */     //   4479: ldc_w '├─'
/*    */     //   4482: invokevirtual s6 : (Ljava/lang/String;)V
/*    */     //   4485: iconst_2
/*    */     //   4486: isub
/*    */     //   4487: aaload
/*    */     //   4488: ldc_w '├─'
/*    */     //   4491: invokevirtual s6 : (Ljava/lang/String;)V
/*    */     //   4494: aload #10
/*    */     //   4496: astore #6
/*    */     //   4498: goto -> 4608
/*    */     //   4501: aload #5
/*    */     //   4503: getfield Kn : Ljava/util/TreeMap;
/*    */     //   4506: invokevirtual values : ()Ljava/util/Collection;
/*    */     //   4509: iconst_0
/*    */     //   4510: anewarray f/Vx0
/*    */     //   4513: invokeinterface toArray : ([Ljava/lang/Object;)[Ljava/lang/Object;
/*    */     //   4518: checkcast [Lf/Vx0;
/*    */     //   4521: arraylength
/*    */     //   4522: ifle -> 4608
/*    */     //   4525: aload #5
/*    */     //   4527: getfield Kn : Ljava/util/TreeMap;
/*    */     //   4530: invokevirtual values : ()Ljava/util/Collection;
/*    */     //   4533: iconst_0
/*    */     //   4534: anewarray f/Vx0
/*    */     //   4537: invokeinterface toArray : ([Ljava/lang/Object;)[Ljava/lang/Object;
/*    */     //   4542: checkcast [Lf/Vx0;
/*    */     //   4545: dup
/*    */     //   4546: astore #6
/*    */     //   4548: arraylength
/*    */     //   4549: dup
/*    */     //   4550: istore #8
/*    */     //   4552: anewarray f/Fy0
/*    */     //   4555: astore #9
/*    */     //   4557: iconst_0
/*    */     //   4558: istore #10
/*    */     //   4560: iload #10
/*    */     //   4562: iload #8
/*    */     //   4564: if_icmpge -> 4604
/*    */     //   4567: aload #9
/*    */     //   4569: iload #10
/*    */     //   4571: new f/YX
/*    */     //   4574: dup
/*    */     //   4575: astore #11
/*    */     //   4577: aload_0
/*    */     //   4578: aload #6
/*    */     //   4580: iload #10
/*    */     //   4582: aaload
/*    */     //   4583: astore #12
/*    */     //   4585: getfield ZS : Lf/qc0;
/*    */     //   4588: aload #12
/*    */     //   4590: swap
/*    */     //   4591: iload_3
/*    */     //   4592: invokespecial <init> : (Lf/Vx0;Lf/qc0;I)V
/*    */     //   4595: aload #11
/*    */     //   4597: aastore
/*    */     //   4598: iinc #10, 1
/*    */     //   4601: goto -> 4560
/*    */     //   4604: aload #9
/*    */     //   4606: astore #6
/*    */     //   4608: aload #6
/*    */     //   4610: arraylength
/*    */     //   4611: ifle -> 4720
/*    */     //   4614: aload #6
/*    */     //   4616: arraylength
/*    */     //   4617: iconst_2
/*    */     //   4618: irem
/*    */     //   4619: ifne -> 4720
/*    */     //   4622: aload #6
/*    */     //   4624: arraylength
/*    */     //   4625: iconst_1
/*    */     //   4626: iadd
/*    */     //   4627: anewarray f/Fy0
/*    */     //   4630: astore #8
/*    */     //   4632: iconst_0
/*    */     //   4633: istore #9
/*    */     //   4635: iload #9
/*    */     //   4637: aload #6
/*    */     //   4639: arraylength
/*    */     //   4640: if_icmpge -> 4685
/*    */     //   4643: iload #9
/*    */     //   4645: aload #6
/*    */     //   4647: arraylength
/*    */     //   4648: iconst_2
/*    */     //   4649: idiv
/*    */     //   4650: if_icmplt -> 4659
/*    */     //   4653: iconst_1
/*    */     //   4654: istore #10
/*    */     //   4656: goto -> 4662
/*    */     //   4659: iconst_0
/*    */     //   4660: istore #10
/*    */     //   4662: aload #8
/*    */     //   4664: aload #6
/*    */     //   4666: iload #9
/*    */     //   4668: dup
/*    */     //   4669: iload #10
/*    */     //   4671: iadd
/*    */     //   4672: istore #10
/*    */     //   4674: aaload
/*    */     //   4675: iload #10
/*    */     //   4677: swap
/*    */     //   4678: aastore
/*    */     //   4679: iinc #9, 1
/*    */     //   4682: goto -> 4635
/*    */     //   4685: aload #8
/*    */     //   4687: aload #6
/*    */     //   4689: aload #8
/*    */     //   4691: aload #6
/*    */     //   4693: arraylength
/*    */     //   4694: iconst_2
/*    */     //   4695: idiv
/*    */     //   4696: new f/Fy0
/*    */     //   4699: dup
/*    */     //   4700: ldc ''
/*    */     //   4702: iload_3
/*    */     //   4703: dup
/*    */     //   4704: invokespecial <init> : (Ljava/lang/String;II)V
/*    */     //   4707: aastore
/*    */     //   4708: arraylength
/*    */     //   4709: iconst_2
/*    */     //   4710: idiv
/*    */     //   4711: aaload
/*    */     //   4712: iconst_0
/*    */     //   4713: invokevirtual wI0 : (Z)V
/*    */     //   4716: aload #8
/*    */     //   4718: astore #6
/*    */     //   4720: aload_0
/*    */     //   4721: dup
/*    */     //   4722: getfield y8 : Lf/Ip;
/*    */     //   4725: invokevirtual xh : ()Lf/U90;
/*    */     //   4728: aload_0
/*    */     //   4729: getfield y8 : Lf/Ip;
/*    */     //   4732: invokevirtual d7 : ()Lf/cr0;
/*    */     //   4735: invokevirtual Em0 : ()Lf/U90;
/*    */     //   4738: aload #6
/*    */     //   4740: invokevirtual Mg : ([Lf/JG0;)Lf/U90;
/*    */     //   4743: invokevirtual Em0 : ()Lf/U90;
/*    */     //   4746: invokevirtual ee0 : (Lf/U90;)Lf/U90;
/*    */     //   4749: pop
/*    */     //   4750: getfield y8 : Lf/Ip;
/*    */     //   4753: invokevirtual iJ0 : ()Lf/U90;
/*    */     //   4756: aload_0
/*    */     //   4757: getfield y8 : Lf/Ip;
/*    */     //   4760: aload #6
/*    */     //   4762: invokevirtual AUX : ([Lf/JG0;)Lf/U90;
/*    */     //   4765: invokevirtual ee0 : (Lf/U90;)Lf/U90;
/*    */     //   4768: pop
/*    */     //   4769: iinc #7, 1
/*    */     //   4772: goto -> 3937
/*    */     //   4775: aload_0
/*    */     //   4776: getfield y8 : Lf/Ip;
/*    */     //   4779: invokevirtual iJ0 : ()Lf/U90;
/*    */     //   4782: invokevirtual Em0 : ()Lf/U90;
/*    */     //   4785: pop
/*    */     //   4786: return
/*    */     // Line number table:
/*    */     //   Java source line number -> byte code offset
/*    */     //   #1	-> 6
/*    */     //   #2	-> 16
/*    */     //   #3	-> 20
/*    */     //   #4	-> 28
/*    */     //   #5	-> 54
/*    */     //   #6	-> 64
/*    */     //   #7	-> 143
/*    */     //   #8	-> 148
/*    */     //   #9	-> 157
/*    */     //   #10	-> 162
/*    */     //   #11	-> 167
/*    */     //   #12	-> 175
/*    */     //   #13	-> 179
/*    */     //   #14	-> 182
/*    */     //   #15	-> 233
/*    */     //   #16	-> 242
/*    */     //   #17	-> 251
/*    */     //   #18	-> 260
/*    */     //   #19	-> 288
/*    */     //   #20	-> 310
/*    */     //   #21	-> 318
/*    */     //   #22	-> 340
/*    */     //   #23	-> 346
/*    */     //   #24	-> 349
/*    */     //   #25	-> 354
/*    */     //   #26	-> 362
/*    */     //   #27	-> 372
/*    */     //   #28	-> 380
/*    */     //   #29	-> 386
/*    */     //   #30	-> 394
/*    */     //   #31	-> 413
/*    */     //   #32	-> 417
/*    */     //   #33	-> 427
/*    */     //   #34	-> 431
/*    */     //   #35	-> 454
/*    */     //   #36	-> 459
/*    */     //   #37	-> 465
/*    */     //   #38	-> 470
/*    */     //   #39	-> 476
/*    */     //   #40	-> 480
/*    */     //   #41	-> 487
/*    */     //   #42	-> 490
/*    */     //   #43	-> 494
/*    */     //   #44	-> 509
/*    */     //   #45	-> 513
/*    */     //   #46	-> 516
/*    */     //   #47	-> 531
/*    */     //   #48	-> 537
/*    */     //   #49	-> 580
/*    */     //   #50	-> 586
/*    */     //   #51	-> 623
/*    */     //   #52	-> 630
/*    */     //   #53	-> 641
/*    */     //   #54	-> 645
/*    */     //   #55	-> 655
/*    */     //   #56	-> 658
/*    */     //   #57	-> 697
/*    */     //   #58	-> 707
/*    */     //   #59	-> 728
/*    */     //   #60	-> 731
/*    */     //   #61	-> 754
/*    */     //   #62	-> 764
/*    */     //   #63	-> 785
/*    */     //   #64	-> 788
/*    */     //   #65	-> 819
/*    */     //   #66	-> 829
/*    */     //   #67	-> 868
/*    */     //   #68	-> 878
/*    */     //   #69	-> 907
/*    */     //   #70	-> 910
/*    */     //   #71	-> 919
/*    */     //   #72	-> 982
/*    */     //   #73	-> 985
/*    */     //   #74	-> 1000
/*    */     //   #75	-> 1006
/*    */     //   #76	-> 1024
/*    */     //   #77	-> 1031
/*    */     //   #78	-> 1040
/*    */     //   #79	-> 1044
/*    */     //   #80	-> 1056
/*    */     //   #81	-> 1059
/*    */     //   #82	-> 1084
/*    */     //   #83	-> 1088
/*    */     //   #84	-> 1100
/*    */     //   #85	-> 1103
/*    */     //   #86	-> 1120
/*    */     //   #87	-> 1123
/*    */     //   #88	-> 1136
/*    */     //   #89	-> 1139
/*    */     //   #90	-> 1149
/*    */     //   #91	-> 1156
/*    */     //   #92	-> 1168
/*    */     //   #93	-> 1176
/*    */     //   #94	-> 1183
/*    */     //   #95	-> 1190
/*    */     //   #96	-> 1201
/*    */     //   #97	-> 1204
/*    */     //   #98	-> 1222
/*    */     //   #99	-> 1228
/*    */     //   #100	-> 1235
/*    */     //   #101	-> 1241
/*    */     //   #102	-> 1324
/*    */     //   #103	-> 1330
/*    */     //   #104	-> 1334
/*    */     //   #105	-> 1339
/*    */     //   #106	-> 1344
/*    */     //   #107	-> 1349
/*    */     //   #108	-> 1354
/*    */     //   #109	-> 1358
/*    */     //   #110	-> 1374
/*    */     //   #111	-> 1378
/*    */     //   #112	-> 1383
/*    */     //   #113	-> 1388
/*    */     //   #114	-> 1393
/*    */     //   #115	-> 1398
/*    */     //   #116	-> 1403
/*    */     //   #117	-> 1445
/*    */     //   #118	-> 1455
/*    */     //   #119	-> 1460
/*    */     //   #120	-> 1463
/*    */     //   #121	-> 1469
/*    */     //   #122	-> 1477
/*    */     //   #123	-> 1487
/*    */     //   #124	-> 1494
/*    */     //   #125	-> 1499
/*    */     //   #126	-> 1502
/*    */     //   #127	-> 1503
/*    */     //   #128	-> 1641
/*    */     //   #129	-> 1644
/*    */     //   #130	-> 1647
/*    */     //   #131	-> 1652
/*    */     //   #132	-> 1655
/*    */     //   #133	-> 1658
/*    */     //   #134	-> 1663
/*    */     //   #135	-> 1702
/*    */     //   #136	-> 1724
/*    */     //   #137	-> 1731
/*    */     //   #138	-> 1768
/*    */     //   #139	-> 1771
/*    */     //   #140	-> 1774
/*    */     //   #141	-> 1779
/*    */     //   #142	-> 1782
/*    */     //   #143	-> 1785
/*    */     //   #144	-> 1789
/*    */     //   #145	-> 1827
/*    */     //   #146	-> 1833
/*    */     //   #147	-> 1854
/*    */     //   #148	-> 1857
/*    */     //   #149	-> 1860
/*    */     //   #150	-> 1924
/*    */     //   #151	-> 1927
/*    */     //   #152	-> 1972
/*    */     //   #153	-> 1975
/*    */     //   #154	-> 1978
/*    */     //   #155	-> 2019
/*    */     //   #156	-> 2026
/*    */     //   #157	-> 2038
/*    */     //   #158	-> 2045
/*    */     //   #159	-> 2051
/*    */     //   #160	-> 2057
/*    */     //   #161	-> 2088
/*    */     //   #162	-> 2095
/*    */     //   #163	-> 2099
/*    */     //   #164	-> 2105
/*    */     //   #165	-> 2183
/*    */     //   #166	-> 2235
/*    */     //   #167	-> 2265
/*    */     //   #168	-> 2275
/*    */     //   #169	-> 2280
/*    */     //   #170	-> 2287
/*    */     //   #171	-> 2290
/*    */     //   #172	-> 2317
/*    */     //   #173	-> 2321
/*    */     //   #174	-> 2336
/*    */     //   #175	-> 2348
/*    */     //   #176	-> 2355
/*    */     //   #177	-> 2370
/*    */     //   #178	-> 2373
/*    */     //   #179	-> 2379
/*    */     //   #180	-> 2382
/*    */     //   #181	-> 2434
/*    */     //   #182	-> 2439
/*    */     //   #183	-> 2442
/*    */     //   #184	-> 2460
/*    */     //   #185	-> 2463
/*    */     //   #186	-> 2468
/*    */     //   #187	-> 2505
/*    */     //   #188	-> 2533
/*    */     //   #189	-> 2537
/*    */     //   #190	-> 2541
/*    */     //   #191	-> 2544
/*    */     //   #192	-> 2586
/*    */     //   #193	-> 2591
/*    */     //   #194	-> 2599
/*    */     //   #195	-> 2602
/*    */     //   #196	-> 2607
/*    */     //   #197	-> 2614
/*    */     //   #198	-> 2632
/*    */     //   #199	-> 2635
/*    */     //   #200	-> 2638
/*    */     //   #201	-> 2641
/*    */     //   #202	-> 2673
/*    */     //   #203	-> 2676
/*    */     //   #204	-> 2682
/*    */     //   #205	-> 2701
/*    */     //   #206	-> 2711
/*    */     //   #207	-> 2738
/*    */     //   #208	-> 2745
/*    */     //   #209	-> 2748
/*    */     //   #210	-> 2753
/*    */     //   #211	-> 2757
/*    */     //   #212	-> 2760
/*    */     //   #213	-> 2772
/*    */     //   #214	-> 2776
/*    */     //   #215	-> 2780
/*    */     //   #216	-> 2833
/*    */     //   #217	-> 2838
/*    */     //   #218	-> 2849
/*    */     //   #219	-> 2853
/*    */     //   #220	-> 2857
/*    */     //   #221	-> 2861
/*    */     //   #222	-> 2902
/*    */     //   #223	-> 2907
/*    */     //   #224	-> 2917
/*    */     //   #225	-> 2947
/*    */     //   #226	-> 2950
/*    */     //   #227	-> 2958
/*    */     //   #228	-> 2968
/*    */     //   #229	-> 2973
/*    */     //   #230	-> 2981
/*    */     //   #231	-> 2999
/*    */     //   #232	-> 3002
/*    */     //   #233	-> 3010
/*    */     //   #234	-> 3014
/*    */     //   #235	-> 3018
/*    */     //   #236	-> 3079
/*    */     //   #237	-> 3084
/*    */     //   #238	-> 3096
/*    */     //   #239	-> 3105
/*    */     //   #240	-> 3109
/*    */     //   #241	-> 3113
/*    */     //   #242	-> 3116
/*    */     //   #243	-> 3156
/*    */     //   #244	-> 3161
/*    */     //   #245	-> 3172
/*    */     //   #246	-> 3176
/*    */     //   #247	-> 3180
/*    */     //   #248	-> 3183
/*    */     //   #249	-> 3223
/*    */     //   #250	-> 3228
/*    */     //   #251	-> 3239
/*    */     //   #252	-> 3243
/*    */     //   #253	-> 3247
/*    */     //   #254	-> 3250
/*    */     //   #255	-> 3290
/*    */     //   #256	-> 3295
/*    */     //   #257	-> 3306
/*    */     //   #258	-> 3310
/*    */     //   #259	-> 3315
/*    */     //   #260	-> 3318
/*    */     //   #261	-> 3356
/*    */     //   #262	-> 3361
/*    */     //   #263	-> 3375
/*    */     //   #264	-> 3404
/*    */     //   #265	-> 3407
/*    */     //   #266	-> 3413
/*    */     //   #267	-> 3416
/*    */     //   #268	-> 3467
/*    */     //   #269	-> 3471
/*    */     //   #270	-> 3476
/*    */     //   #271	-> 3480
/*    */     //   #272	-> 3515
/*    */     //   #273	-> 3520
/*    */     //   #274	-> 3529
/*    */     //   #275	-> 3535
/*    */     //   #276	-> 3546
/*    */     //   #277	-> 3587
/*    */     //   #278	-> 3959
/*    */     //   #279	-> 3962
/*    */     //   #280	-> 3977
/*    */     //   #281	-> 3980
/*    */     //   #282	-> 3998
/*    */     //   #283	-> 4064
/*    */     //   #284	-> 4067
/*    */     //   #285	-> 4082
/*    */     //   #286	-> 4088
/*    */     //   #287	-> 4109
/*    */     //   #288	-> 4197
/*    */     //   #289	-> 4224
/*    */     //   #290	-> 4279
/*    */     //   #291	-> 4284
/*    */     //   #292	-> 4311
/*    */     //   #293	-> 4362
/*    */     //   #294	-> 4503
/*    */     //   #295	-> 4521
/*    */     //   #296	-> 4527
/*  4 */     //   #297	-> 4548 } public final void Id0() { this(); Ip ip; cr0 cr0; g0 g0; ArrayList<UD0> arrayList; ArrayList<k2> arrayList1; this(ip); this(ip); k2[] arrayOfK2 = new k2[12]; int i = 0; byte b1 = 0, b2 = 0, b3 = 0, b4 = 0, b5 = 0, b6 = 0; short[] arrayOfShort = gm.EI0; On.v30().getClass(); this();
/*    */     
/*  6 */     for (Iterator<UD0> iterator = (On.v30()).iI0.values().iterator(); iterator.hasNext();) {
/*    */       
/*  8 */       if (py.c7(((uD0 = iterator.next()).Fk0()).AP, arrayOfShort)) arrayList.add(uD0); 
/*  9 */     }  int j = arrayList.size(); B9 b9 = this.y6;
/*    */     int k;
/* 11 */     if ((k = this.l80.Wa0.go) < b9
/* 12 */       .y90) { byte b; DO dO; ArrayList arrayList2; this
/*    */         
/* 14 */         .HH = b9.COM8[k];
/*    */       int m;
/* 16 */       if ((m = this.W7.Wa0.go) < 1) { b = null; }
/* 17 */       else { dO = DO.HB0[b - 1]; }  this();
/*    */ 
/*    */ 
/*    */       
/* 21 */       String str = LF.Ll0(this.BW.F2.PH0.toString(), true);
/* 22 */       if (this.HH == -2) { short[] arrayOfShort1 = gm.EI0; On.v30().getClass();
/* 23 */         this();
/*    */         
/* 25 */         for (Iterator<UD0> iterator1 = (On.v30()).iI0.values().iterator(); iterator1.hasNext();) {
/*    */           
/* 27 */           if (py.c7(((uD0 = iterator1.next()).Fk0()).AP, arrayOfShort1)) arrayList2.add(uD0); 
/* 28 */         }  Collections.sort(arrayList2, Comparator.comparingInt(paramUD0 -> paramUD0.PP(this.HH))); } else { arrayList2 = On.v30().K6(this.HH); }  for (UD0 uD0 : arrayList2) { k2 k21; if (this.ZS
/*    */           
/* 30 */           .JO((byte)1, uD0.AP)) { b1++; b3++; if (this.ZS
/*    */             
/* 32 */             .JO((byte)2, uD0.AP)) b2++;  if (this.ZS
/*    */             
/* 34 */             .JO((byte)3, uD0.AP)) b4++;  b5++; b6++; } else if (this.ZS
/*    */           
/* 36 */           .JO((byte)0, uD0.AP)) { b3++; b6++;
/* 37 */           if (!uD0.lS && 
/* 38 */             !uD0.hL) b5++;  } else { if (uD0
/* 39 */             .lS || uD0
/* 40 */             .hL) continue;  b6++; b5++; }
/*    */         
/* 42 */         if (this.BW.F2
/* 43 */           .PH0
/* 44 */           .length() > 0)
/*    */         {
/* 46 */           if (LF.qS(uD0.o60(false), str))
/*    */           
/* 48 */           { if (!this.ZS.JO((byte)0, uD0.AP)) continue;  } else { continue; }  }  if (this.EJ0
/* 49 */           .TG0
/* 50 */           .nm0() && 
/*    */ 
/*    */           
/* 53 */           !this.ZS.JO((byte)0, uD0.AP)) continue;  if (dO != null) { byte b8; if (uD0
/* 54 */             .ee == dO || uD0
/* 55 */             .G2
/* 56 */             .contains(dO)) { b8 = 1; } else { b8 = 0; }  if (uD0
/* 57 */             .TL > 0) { b8 = 0; while (b8 < uD0
/* 58 */               .Uf)
/* 59 */             { short s = uD0.AP; if (b8 > 0)
/* 60 */                 s = (short)(uD0.TL + b8 - 1);  UD0 uD01;
/* 61 */               if ((uD01 = On.v30().lpT3(s))
/* 62 */                 .ee == dO || uD01
/* 63 */                 .G2
/* 64 */                 .contains(dO)) { k2 k22; byte b10 = this.HH; this(this, uD0, b8, b10); arrayOfK2[i] = k22; arrayList1.add(k22); int i1; if ((i1 = i + 1) % 12 == 0) { i = 0; cr0
/*    */                     
/* 66 */                     .ee0((new g0(ip)).Mg((JG0[])arrayOfK2));
/*    */                   
/* 68 */                   g0.ee0((new cr0(ip)).Mg((JG0[])arrayOfK2)); } else { i = i1; }  }  b8 = (byte)(b8 + 1); }  continue; }  if (b8 == 0) continue;  }  byte b7 = this.HH; this(this, uD0, (byte)-1, b7); arrayOfK2[i] = k21; arrayList1.add(k21); int n; if ((n = i + 1) % 12 == 0) { i = 0; cr0
/*    */             
/* 70 */             .ee0((new g0(ip)).Mg((JG0[])arrayOfK2));
/*    */           
/* 72 */           g0.ee0((new cr0(ip)).Mg((JG0[])arrayOfK2)); continue; }  i = n; }  this.NZ = arrayList1.<k2>toArray(new k2[0]); if (i > 0) { arrayOfK2 = new k2[i]; System.arraycopy(arrayOfK2, 0, arrayOfK2, 0, i); cr0
/*    */           
/* 74 */           .ee0((new g0(ip)).Mg((JG0[])arrayOfK2));
/*    */         
/* 76 */         g0.ee0((new cr0(ip)).Mg((JG0[])arrayOfK2)); }  this.vJ.Nu(b3 / b6); float f; this.TH0.Nu(b1 / (f = b5)); this.nW.Nu(b2 / f); this.GC0.Nu(b4 / j); this.XH.E1(Ml0.OH0(1701) + " " + b3 + " / " + b6); this.Kv0.E1(Ml0.OH0(1702) + " " + b1 + " / " + b5); this.oA0.E1(Ml0.OH0(1728) + " " + b2 + " / " + b5); this.EO.E1(Ml0.OH0(1762) + " " + b4 + " / " + j); ip.WN(cr0); ip.rK0(g0); this.up.Gz0(ip); d40(); this.ay0 = 0;
/* 77 */       js.vu0
/* 78 */         .KE(); return; }
/* 79 */      throw new ArrayIndexOutOfBoundsException(arrayList1); }
/*    */ 
/*    */   
/*    */   public final void EX(nY paramnY) {}
/*    */   
/*    */   public final void d40() {
/*    */     super.d40();
/*    */     int k = this.up.xY;
/*    */     this.IU.Tm(k, this.up.HC);
/*    */     k = this.up.xY;
/*    */     this.Uz0.Tm(k, this.up.HC);
/*    */     k = this.up.xY;
/*    */     this.ED0.Tm(k, this.up.HC);
/*    */     IN[] arrayOfIN;
/*    */     int n;
/*    */     for (int m = (arrayOfIN = this.Sk0).length; n < m; ) {
/*    */       byte b1;
/*    */       IN iN = arrayOfIN[n];
/*    */       char c = 'ú';
/*    */       if (km.XU()) {
/*    */         b1 = 12;
/*    */       } else {
/*    */         b1 = 8;
/*    */       } 
/*    */       iN.Tm(c, b1);
/*    */       JG0 jG01;
/*    */       (jG01 = iN.fr0).getClass();
/*    */       int i1 = jG01.er0 - iN.HC / 2;
/*    */       iN.Ol0(iN.Kd, jG01.HC / 2 + i1);
/*    */       n++;
/*    */     } 
/*    */     if (km.XU()) {
/*    */       Tm(km.wI0.dG(), km.wI0.k1());
/*    */       ME(0, 0);
/*    */       Vq0 vq0;
/*    */       this.RB.ME((vq0 = this.RB).Kd, vq0.er0 + 60);
/*    */       this.RB.Tm((vq0 = this.RB).xY, vq0.HC - 120);
/*    */       this.y7.Tm(114, 114);
/*    */       this.y7.ME(m40() - this.y7.xY - 30, mD() - this.y7.HC - 70);
/*    */     } else {
/*    */       uh0(670, this.HC);
/*    */     } 
/*    */     int j = this.up.xY;
/*    */     this.y8.uh0(j, this.up.HC);
/*    */     Ip ip;
/*    */     JG0 jG0;
/*    */     (jG0 = (ip = this.y8).fr0).getClass();
/*    */     int i = jG0.er0 - ip.HC / 2;
/*    */     this.y8.Ol0(this.y8.Kd, jG0.HC / 2 + i);
/*    */     i = 0;
/*    */     JG0[] arrayOfJG0;
/*    */     byte b;
/*    */     for (n = (arrayOfJG0 = this.Tn0).length, b = 0; b < n; ) {
/*    */       int i1;
/*    */       if ((i1 = (arrayOfJG0[b]).xY) > i)
/*    */         i = i1; 
/*    */       b++;
/*    */     } 
/*    */     if (i > 75)
/*    */       for (n = (arrayOfJG0 = this.Tn0).length, b = 0; b < n; ) {
/*    */         arrayOfJG0[b].uh0(i, 28);
/*    */         b++;
/*    */       }  
/*    */     if (t90.bigCJKFontSizes()) {
/*    */       JG0[] arrayOfJG01;
/*    */       byte b1;
/*    */       for (i = (arrayOfJG01 = this.Tn0).length, b1 = 0; b1 < i; ) {
/*    */         this[b1].uh0(this[b1].AW(), 32);
/*    */         b1++;
/*    */       } 
/*    */     } 
/*    */   }
/*    */   
/*    */   public final void IG0() {
/*    */     VA0.c90(this);
/*    */   }
/*    */   
/*    */   public final void ED0(throws paramthrows) {
/*    */     super.ED0(paramthrows);
/*    */     js.vu0.KE();
/*    */   }
/*    */   
/*    */   public final void A30() {
/*    */     k2 k21;
/*    */     int i;
/*    */     k2[] arrayOfK2;
/*    */     if ((i = this.ay0) >= (arrayOfK2 = this.NZ).length) {
/*    */       k21 = null;
/*    */     } else {
/*    */       k21 = arrayOfK2[k21];
/*    */     } 
/*    */     VA0.c90(k21);
/*    */     this.up.ai(k21);
/*    */     Object object;
/*    */     if (k21 != null && (object = k21.z4) != null) {
/*    */       js.vu0.j90(k21, this, et.F30);
/*    */     } else {
/*    */       js.vu0.KE();
/*    */     } 
/*    */   }
/*    */   
/*    */   public final boolean i2(oa0 paramoa0) {
/*    */     k2 k21;
/*    */     int i;
/*    */     if (B8.Pg(paramoa0.cz0))
/*    */       js.vu0.KE(); 
/*    */     if (B8.Wm0(paramoa0.cz0) && paramoa0.oO()) {
/*    */       if (js.com3(this))
/*    */         return super.i2(paramoa0); 
/*    */       int j = paramoa0.GG0;
/*    */       if (this.RB.dP) {
/*    */         js.vu0.KE();
/*    */         if (h1.J20(j, BM.ni)) {
/*    */           if (this.RB.nv0() == 4) {
/*    */           
/*    */           } else {
/*    */             return true;
/*    */           } 
/*    */           ((this.RB.nv0() == 1) ? this.ED0 : ((this.RB.nv0() == 3) ? this.IU : "JD-Core does not support Kotlin")).rt(((rS)((this.RB.nv0() == 1) ? this.ED0 : ((this.RB.nv0() == 3) ? this.IU : "JD-Core does not support Kotlin"))).PB.Ny0 - 20);
/*    */           return true;
/*    */         } 
/*    */         if (h1.J20(j, BM.N70)) {
/*    */           if (this.RB.nv0() == 4) {
/*    */           
/*    */           } else {
/*    */             return true;
/*    */           } 
/*    */           ((this.RB.nv0() == 1) ? this.ED0 : ((this.RB.nv0() == 3) ? this.IU : "JD-Core does not support Kotlin")).rt(((rS)((this.RB.nv0() == 1) ? this.ED0 : ((this.RB.nv0() == 3) ? this.IU : "JD-Core does not support Kotlin"))).PB.Ny0 + 20);
/*    */           return true;
/*    */         } 
/*    */         if (h1.J20(j, BM.Oq)) {
/*    */           this.RB.E00(-1);
/*    */           return true;
/*    */         } 
/*    */         if (h1.J20(j, BM.M8)) {
/*    */           this.RB.E00(1);
/*    */           return true;
/*    */         } 
/*    */         if (h1.J20(j, BM.bC)) {
/*    */           if (this.RB.nv0() == 0)
/*    */             hm.Fz0(this.gH.TG0.oh0); 
/*    */           return true;
/*    */         } 
/*    */         if (h1.J20(j, BM.lc)) {
/*    */           Tc0();
/*    */           return true;
/*    */         } 
/*    */         return super.i2(paramoa0);
/*    */       } 
/*    */       if (j == 34 && paramoa0.com8 == 4) {
/*    */         this.BW.BA();
/*    */         return true;
/*    */       } 
/*    */       if (h1.J20(j, BM.ni)) {
/*    */         if ((i = this.ay0) < 12)
/*    */           return true; 
/*    */         this.ay0 = i - 12;
/*    */         A30();
/*    */         return true;
/*    */       } 
/*    */       if (h1.J20(j, BM.N70)) {
/*    */         if ((i = this.ay0 + 12) < this.NZ.length)
/*    */           this.ay0 = i; 
/*    */         A30();
/*    */         return true;
/*    */       } 
/*    */       if (h1.J20(j, BM.Oq)) {
/*    */         if ((i = this.ay0) < 1)
/*    */           return true; 
/*    */         this.ay0 = i - 1;
/*    */         A30();
/*    */         return true;
/*    */       } 
/*    */       if (h1.J20(j, BM.M8)) {
/*    */         if ((i = this.ay0 + 1) < this.NZ.length)
/*    */           this.ay0 = i; 
/*    */         A30();
/*    */         return true;
/*    */       } 
/*    */       if (h1.J20(j, BM.bC)) {
/*    */         k2[] arrayOfK2;
/*    */         if ((i = this.ay0) >= (arrayOfK2 = this.NZ).length) {
/*    */           arrayOfK2 = null;
/*    */         } else {
/*    */           k21 = this[i];
/*    */         } 
/*    */         if (this != null) {
/*    */           hm.Fz0(this.TG0.oh0);
/*    */           js.vu0.KE();
/*    */         } 
/*    */         return true;
/*    */       } 
/*    */       if (h1.J20(j, BM.lc)) {
/*    */         pA.Dg0.uq0();
/*    */         return true;
/*    */       } 
/*    */     } 
/*    */     return super.i2(i);
/*    */   }
/*    */   
/*    */   public final void Tc0() {
/*    */     vq0.wI0(false);
/*    */     this.PRn.wI0(true);
/*    */     Lo(Ml0.OH0(1));
/*    */     Vq0 vq0;
/*    */     if ((vq0 = this.RB).dP)
/*    */       this.RB.dA0(this.RB.Hf(0)); 
/*    */     if (km.XU())
/*    */       this.y7.wI0(false); 
/*    */     this.cr0 = null;
/*    */   }
/*    */   
/*    */   public final void V5(boolean paramBoolean, Hq paramHq) {
/*    */     byte b;
/*    */     if ((b = paramHq.Ce) != -1 && b != L70.gq.fu())
/*    */       return; 
/*    */     String str1 = Ml0.OH0(paramHq.Fg.oc0);
/*    */     String str2 = paramHq.Ee0 + " - " + paramHq.Kn;
/*    */     if (paramHq.Ee0 == paramHq.Kn)
/*    */       str2 = N.Gl0(new StringBuilder(), paramHq.Ee0, ""); 
/*    */     String str3 = "???";
/*    */     if (paramHq.TG0((short)1))
/*    */       str3 = Ml0.OH0(1774); 
/*    */     if (paramHq.TG0((short)2)) {
/*    */       str3 = Ml0.OH0(1782);
/*    */     } else if (paramHq.TG0((short)4)) {
/*    */       str3 = Ml0.OH0(1783);
/*    */     } else if (paramHq.TG0((short)8)) {
/*    */       str3 = Ml0.OH0(1784);
/*    */     } else if (paramHq.TG0((short)16)) {
/*    */       str3 = Ml0.OH0(1773);
/*    */     } else if (paramHq.TG0((short)64)) {
/*    */       str3 = Ml0.OH0(1795);
/*    */     } else if (paramHq.TG0((short)128)) {
/*    */       str3 = Ml0.OH0(1799);
/*    */     } else if (paramHq.TG0((short)256)) {
/*    */       str3 = Ml0.OH0(1794);
/*    */     } 
/*    */     String str4 = Ml0.la(paramHq.tO * 1000 + 140000 + (paramHq.h70 & 0xFF), "???");
/*    */     if (paramHq.TG0((short)32))
/*    */       str1 = str4 = Ml0.OH0(1798); 
/*    */     if (paramHq.gj()) {
/*    */       ArrayList<String> arrayList;
/*    */       this();
/*    */       if (paramHq.Gj((byte)1))
/*    */         arrayList.add(Ml0.OH0(oE.ZQ(oE.Q3))); 
/*    */       if (paramHq.Gj((byte)2))
/*    */         arrayList.add(Ml0.OH0(oE.ZQ(oE.z70))); 
/*    */       if (paramHq.Gj((byte)4))
/*    */         arrayList.add(Ml0.OH0(oE.ZQ(oE.g90))); 
/*    */       if (arrayList.size() > 0) {
/*    */         StringBuilder stringBuilder;
/*    */         this();
/*    */         (new StringBuilder()).append(str4);
/*    */         (new StringBuilder()).append(" (");
/*    */         int j;
/*    */         Iterator<String> iterator;
/*    */         for (j = arrayList.size(), iterator = arrayList.iterator(); iterator.hasNext(); ) {
/*    */           stringBuilder.append(iterator.next());
/*    */           if (j > 1) {
/*    */             stringBuilder.append("/");
/*    */             j--;
/*    */           } 
/*    */         } 
/*    */         stringBuilder.append(")");
/*    */         str4 = stringBuilder.toString();
/*    */       } 
/*    */     } 
/*    */     int i;
/*    */     if ((i = paramHq.Fg.ordinal()) != 0) {
/*    */       if (i == 3) {
/*    */         byte b1;
/*    */         if ((b1 = paramHq.Ra) < 0 || paramHq.tO == 2)
/*    */           b1 = 2; 
/*    */         String str = Ml0.OH0(b1 + 245445);
/*    */       } 
/*    */     } else if ((i = paramHq.Ra) != 1) {
/*    */       if (i == 2)
/*    */         str1 = Ml0.OH0(1793); 
/*    */     } else {
/*    */       str1 = Ml0.OH0(1792);
/*    */     } 
/*    */     NG(paramBoolean, str1, Mk0.zd(paramHq.tO), str4, str2, str3, false);
/*    */   }
/*    */   
/*    */   public final void NG(boolean paramBoolean1, String paramString1, String paramString2, String paramString3, String paramString4, String paramString5, boolean paramBoolean2) {
/*    */     dQ dQ5 = new dQ();
/*    */     if (!paramBoolean1)
/*    */       paramString1 = "???"; 
/*    */     this();
/*    */     dQ5.E1(paramString1);
/*    */     dQ dQ2 = new dQ();
/*    */     if (!paramBoolean1)
/*    */       paramString2 = "???"; 
/*    */     this();
/*    */     dQ2.E1(paramString2);
/*    */     dQ dQ3 = new dQ();
/*    */     if (!paramBoolean1)
/*    */       paramString3 = "???"; 
/*    */     this();
/*    */     dQ3.E1(paramString3);
/*    */     dQ dQ4 = new dQ();
/*    */     if (!paramBoolean1)
/*    */       paramString4 = "???"; 
/*    */     this();
/*    */     dQ4.E1(paramString4);
/*    */     dQ dQ1 = new dQ();
/*    */     if (!paramBoolean1)
/*    */       paramString5 = "???"; 
/*    */     this();
/*    */     dQ1.E1(paramString5);
/*    */     if (paramBoolean2) {
/*    */       dQ5.Xu("label-title-dex-medium");
/*    */       dQ2.Xu("label-title-dex-small");
/*    */       dQ3.Xu("label-title-dex-name");
/*    */       dQ4.Xu("label-title-dex-smallest");
/*    */       dQ1.Xu("label-title-dex-medium");
/*    */     } else {
/*    */       dQ5.Xu("label-value-dex-medium");
/*    */       dQ2.Xu("label-value-dex-small");
/*    */       dQ3.Xu("label-value-dex-name");
/*    */       dQ4.Xu("label-value-dex-smallest");
/*    */       dQ1.Xu("label-value-dex-medium");
/*    */     } 
/*    */     dQ3.mM();
/*    */     Ip ip;
/*    */     (ip = this.Gc0).o30.ee0(AUX(new JG0[] { dQ5, dQ2, dQ3, dQ4, dQ1 }));
/*    */     (ip = this.Gc0).Xz0.ee0(vo0(new JG0[] { dQ5, dQ2, dQ3, dQ4, dQ1 }));
/*    */   } }


/* Location:              /Users/vnnsnnt/Documents/Codespace/JavaWorkspace/RedTrainer/src/main/java/org/trainer/client/PokeMMO.jar!/f/Hy.class
 * Java compiler version: 8 (52.0)
 * JD-Core Version:       1.1.3
 */