/*    */ package f;public final class Ia extends Qa0 implements r60 { public static final byte[] qr = new byte[] { 2, 0, 1, 3, 4 }; public static final Comparator Xd = Ia::NO; public final Ip ki; public final Un VF0; public final Un MI0; public final Fy0[] qU; public final Zz0 Zz0; public final cQ[] J5; public final W1[] Lc0; public final dQ[] gz0; public final Ip Tt; public final Un[] Yq0; public final Fy0 L2; public final Fy0 Tz0; public short[] yq0; public byte[] E10; public short[] package; public byte[] GG0; public int mv; public byte Pb0; public byte rb0; public final Dn0 Vh; public boolean z70; public boolean cOm3; public boolean Yb0; public boolean Y70; public int j7; public byte ar0; public of cOm5; public Un Bi0; public W1 Ih0; public W1 iP; public int rE0; public byte HP; public boolean jA0; public Un hw0; public Ia(js paramjs, boolean paramBoolean1, boolean paramBoolean2, boolean paramBoolean3, boolean paramBoolean4, int paramInt) { // Byte code:
/*    */     //   0: iload_3
/*    */     //   1: aload_0
/*    */     //   2: dup
/*    */     //   3: dup2
/*    */     //   4: dup2
/*    */     //   5: invokestatic XU : ()Z
/*    */     //   8: invokespecial <init> : (Z)V
/*    */     //   11: iconst_m1
/*    */     //   12: putfield mv : I
/*    */     //   15: iconst_m1
/*    */     //   16: putfield Pb0 : B
/*    */     //   19: iconst_0
/*    */     //   20: putfield rE0 : I
/*    */     //   23: getstatic f/Ia.qr : [B
/*    */     //   26: iconst_0
/*    */     //   27: baload
/*    */     //   28: putfield HP : B
/*    */     //   31: iconst_0
/*    */     //   32: putfield jA0 : Z
/*    */     //   35: ifeq -> 42
/*    */     //   38: iload_2
/*    */     //   39: ifeq -> 58
/*    */     //   42: iload_2
/*    */     //   43: ifeq -> 86
/*    */     //   46: iload_3
/*    */     //   47: ifeq -> 86
/*    */     //   50: iload #4
/*    */     //   52: ifeq -> 58
/*    */     //   55: goto -> 86
/*    */     //   58: invokestatic XU : ()Z
/*    */     //   61: ifeq -> 105
/*    */     //   64: aload_0
/*    */     //   65: new f/H5
/*    */     //   68: dup
/*    */     //   69: astore #7
/*    */     //   71: aload_0
/*    */     //   72: aload_1
/*    */     //   73: iload #6
/*    */     //   75: invokespecial <init> : (Lf/Ia;Lf/js;I)V
/*    */     //   78: aload #7
/*    */     //   80: invokevirtual TG0 : (Ljava/lang/Runnable;)V
/*    */     //   83: goto -> 105
/*    */     //   86: aload_0
/*    */     //   87: new f/Me0
/*    */     //   90: dup
/*    */     //   91: astore #7
/*    */     //   93: aload_0
/*    */     //   94: aload_1
/*    */     //   95: iload #6
/*    */     //   97: invokespecial <init> : (Lf/Ia;Lf/js;I)V
/*    */     //   100: aload #7
/*    */     //   102: invokevirtual TG0 : (Ljava/lang/Runnable;)V
/*    */     //   105: aload_0
/*    */     //   106: ldc 'customize-widget'
/*    */     //   108: invokevirtual Xu : (Ljava/lang/String;)V
/*    */     //   111: iconst_0
/*    */     //   112: istore #7
/*    */     //   114: getstatic f/km.a3 : Lf/vh0;
/*    */     //   117: dup
/*    */     //   118: astore #8
/*    */     //   120: ifnull -> 148
/*    */     //   123: aload #8
/*    */     //   125: invokevirtual wQ : ()Lf/Jo;
/*    */     //   128: ifnull -> 148
/*    */     //   131: getstatic f/km.a3 : Lf/vh0;
/*    */     //   134: invokevirtual wQ : ()Lf/Jo;
/*    */     //   137: invokevirtual cM : ()Lf/OE0;
/*    */     //   140: invokevirtual OD : ()Lf/H10;
/*    */     //   143: invokevirtual bo0 : ()B
/*    */     //   146: istore #7
/*    */     //   148: iload #4
/*    */     //   150: aload_0
/*    */     //   151: dup
/*    */     //   152: new f/Dn0
/*    */     //   155: dup
/*    */     //   156: astore #8
/*    */     //   158: aload_0
/*    */     //   159: iload #7
/*    */     //   161: invokespecial <init> : (Lf/JG0;B)V
/*    */     //   164: aload #8
/*    */     //   166: putfield Vh : Lf/Dn0;
/*    */     //   169: iconst_1
/*    */     //   170: invokevirtual EP : (I)V
/*    */     //   173: ifeq -> 182
/*    */     //   176: sipush #1050
/*    */     //   179: goto -> 204
/*    */     //   182: iload_2
/*    */     //   183: ifeq -> 201
/*    */     //   186: iload #5
/*    */     //   188: ifeq -> 196
/*    */     //   191: ldc 101106
/*    */     //   193: goto -> 204
/*    */     //   196: ldc 100009
/*    */     //   198: goto -> 204
/*    */     //   201: sipush #2800
/*    */     //   204: invokestatic OH0 : (I)Ljava/lang/String;
/*    */     //   207: astore #8
/*    */     //   209: iload_3
/*    */     //   210: aload_0
/*    */     //   211: dup
/*    */     //   212: dup2
/*    */     //   213: dup2
/*    */     //   214: aload #8
/*    */     //   216: invokevirtual Lo : (Ljava/lang/String;)V
/*    */     //   219: new f/Ip
/*    */     //   222: dup
/*    */     //   223: astore #8
/*    */     //   225: invokespecial <init> : ()V
/*    */     //   228: aload #8
/*    */     //   230: putfield ki : Lf/Ip;
/*    */     //   233: iload_2
/*    */     //   234: putfield z70 : Z
/*    */     //   237: iload_3
/*    */     //   238: putfield cOm3 : Z
/*    */     //   241: iload #4
/*    */     //   243: putfield Yb0 : Z
/*    */     //   246: iload #5
/*    */     //   248: putfield Y70 : Z
/*    */     //   251: ifne -> 277
/*    */     //   254: iload_2
/*    */     //   255: ifeq -> 261
/*    */     //   258: goto -> 277
/*    */     //   261: aload_0
/*    */     //   262: getstatic f/km.u4 : Lf/R8;
/*    */     //   265: invokevirtual IQ : ()Lf/fH0;
/*    */     //   268: invokevirtual Hn : ()B
/*    */     //   271: putfield ar0 : B
/*    */     //   274: goto -> 369
/*    */     //   277: iload #4
/*    */     //   279: ifne -> 364
/*    */     //   282: getstatic f/km.u4 : Lf/R8;
/*    */     //   285: invokevirtual UK : ()Lf/qN;
/*    */     //   288: iload #6
/*    */     //   290: invokevirtual a80 : (I)Lf/T60;
/*    */     //   293: ifnull -> 326
/*    */     //   296: aload_0
/*    */     //   297: iload #6
/*    */     //   299: aload_0
/*    */     //   300: getstatic f/km.u4 : Lf/R8;
/*    */     //   303: invokevirtual UK : ()Lf/qN;
/*    */     //   306: iload #6
/*    */     //   308: invokevirtual a80 : (I)Lf/T60;
/*    */     //   311: invokevirtual i4 : ()Lf/fH0;
/*    */     //   314: invokevirtual Hn : ()B
/*    */     //   317: putfield ar0 : B
/*    */     //   320: putfield j7 : I
/*    */     //   323: goto -> 369
/*    */     //   326: getstatic f/km.u4 : Lf/R8;
/*    */     //   329: invokevirtual IQ : ()Lf/fH0;
/*    */     //   332: ifnull -> 369
/*    */     //   335: aload_0
/*    */     //   336: dup
/*    */     //   337: getstatic f/km.u4 : Lf/R8;
/*    */     //   340: invokevirtual IQ : ()Lf/fH0;
/*    */     //   343: invokevirtual Hn : ()B
/*    */     //   346: putfield ar0 : B
/*    */     //   349: getstatic f/km.u4 : Lf/R8;
/*    */     //   352: invokevirtual IQ : ()Lf/fH0;
/*    */     //   355: invokevirtual fV : ()I
/*    */     //   358: putfield j7 : I
/*    */     //   361: goto -> 369
/*    */     //   364: aload_0
/*    */     //   365: iconst_0
/*    */     //   366: putfield ar0 : B
/*    */     //   369: iload #5
/*    */     //   371: ifeq -> 392
/*    */     //   374: aload_0
/*    */     //   375: getfield ar0 : B
/*    */     //   378: ifne -> 385
/*    */     //   381: iconst_1
/*    */     //   382: goto -> 386
/*    */     //   385: iconst_0
/*    */     //   386: i2b
/*    */     //   387: aload_0
/*    */     //   388: swap
/*    */     //   389: putfield ar0 : B
/*    */     //   392: iload_3
/*    */     //   393: getstatic f/km.a3 : Lf/vh0;
/*    */     //   396: invokevirtual wQ : ()Lf/Jo;
/*    */     //   399: astore #8
/*    */     //   401: ifne -> 503
/*    */     //   404: iload #5
/*    */     //   406: ifne -> 503
/*    */     //   409: iload_2
/*    */     //   410: aload_0
/*    */     //   411: aload #8
/*    */     //   413: aload_0
/*    */     //   414: aload #8
/*    */     //   416: aload_0
/*    */     //   417: aload #8
/*    */     //   419: aload_0
/*    */     //   420: aload #8
/*    */     //   422: dup
/*    */     //   423: invokevirtual cM : ()Lf/OE0;
/*    */     //   426: invokevirtual I1 : ()Lf/H10;
/*    */     //   429: invokevirtual bo0 : ()B
/*    */     //   432: istore #5
/*    */     //   434: invokevirtual cM : ()Lf/OE0;
/*    */     //   437: invokevirtual I1 : ()Lf/H10;
/*    */     //   440: invokevirtual uz0 : ()[S
/*    */     //   443: putfield yq0 : [S
/*    */     //   446: invokevirtual cM : ()Lf/OE0;
/*    */     //   449: invokevirtual I1 : ()Lf/H10;
/*    */     //   452: invokevirtual fG : ()[B
/*    */     //   455: putfield E10 : [B
/*    */     //   458: invokevirtual cM : ()Lf/OE0;
/*    */     //   461: invokevirtual OD : ()Lf/H10;
/*    */     //   464: invokevirtual uz0 : ()[S
/*    */     //   467: putfield package : [S
/*    */     //   470: invokevirtual cM : ()Lf/OE0;
/*    */     //   473: invokevirtual OD : ()Lf/H10;
/*    */     //   476: invokevirtual fG : ()[B
/*    */     //   479: putfield GG0 : [B
/*    */     //   482: ifeq -> 1519
/*    */     //   485: aload_0
/*    */     //   486: dup
/*    */     //   487: dup2
/*    */     //   488: getfield yq0 : [S
/*    */     //   491: putfield package : [S
/*    */     //   494: getfield E10 : [B
/*    */     //   497: putfield GG0 : [B
/*    */     //   500: goto -> 1519
/*    */     //   503: aload_0
/*    */     //   504: dup
/*    */     //   505: bipush #12
/*    */     //   507: newarray short
/*    */     //   509: dup
/*    */     //   510: dup
/*    */     //   511: dup2
/*    */     //   512: dup2
/*    */     //   513: dup2
/*    */     //   514: dup2
/*    */     //   515: dup2
/*    */     //   516: astore #9
/*    */     //   518: iconst_0
/*    */     //   519: iconst_m1
/*    */     //   520: sastore
/*    */     //   521: iconst_1
/*    */     //   522: iconst_m1
/*    */     //   523: sastore
/*    */     //   524: iconst_2
/*    */     //   525: iconst_3
/*    */     //   526: sastore
/*    */     //   527: iconst_3
/*    */     //   528: iconst_2
/*    */     //   529: sastore
/*    */     //   530: iconst_4
/*    */     //   531: iconst_m1
/*    */     //   532: sastore
/*    */     //   533: iconst_5
/*    */     //   534: iconst_m1
/*    */     //   535: sastore
/*    */     //   536: bipush #6
/*    */     //   538: iconst_5
/*    */     //   539: sastore
/*    */     //   540: bipush #7
/*    */     //   542: iconst_m1
/*    */     //   543: sastore
/*    */     //   544: bipush #8
/*    */     //   546: iconst_0
/*    */     //   547: sastore
/*    */     //   548: bipush #9
/*    */     //   550: iconst_0
/*    */     //   551: sastore
/*    */     //   552: bipush #10
/*    */     //   554: iconst_0
/*    */     //   555: sastore
/*    */     //   556: bipush #11
/*    */     //   558: iconst_0
/*    */     //   559: sastore
/*    */     //   560: aload #9
/*    */     //   562: putfield yq0 : [S
/*    */     //   565: bipush #12
/*    */     //   567: newarray byte
/*    */     //   569: dup
/*    */     //   570: dup
/*    */     //   571: dup2
/*    */     //   572: dup2
/*    */     //   573: dup2
/*    */     //   574: dup2
/*    */     //   575: dup2
/*    */     //   576: astore #9
/*    */     //   578: iconst_0
/*    */     //   579: iconst_0
/*    */     //   580: bastore
/*    */     //   581: iconst_1
/*    */     //   582: iconst_0
/*    */     //   583: bastore
/*    */     //   584: iconst_2
/*    */     //   585: iconst_0
/*    */     //   586: bastore
/*    */     //   587: iconst_3
/*    */     //   588: iconst_0
/*    */     //   589: bastore
/*    */     //   590: iconst_4
/*    */     //   591: iconst_0
/*    */     //   592: bastore
/*    */     //   593: iconst_5
/*    */     //   594: iconst_0
/*    */     //   595: bastore
/*    */     //   596: bipush #6
/*    */     //   598: iconst_0
/*    */     //   599: bastore
/*    */     //   600: bipush #7
/*    */     //   602: iconst_0
/*    */     //   603: bastore
/*    */     //   604: bipush #8
/*    */     //   606: iconst_0
/*    */     //   607: bastore
/*    */     //   608: bipush #9
/*    */     //   610: iconst_0
/*    */     //   611: bastore
/*    */     //   612: bipush #10
/*    */     //   614: iconst_0
/*    */     //   615: bastore
/*    */     //   616: bipush #11
/*    */     //   618: iconst_0
/*    */     //   619: bastore
/*    */     //   620: aload #9
/*    */     //   622: putfield E10 : [B
/*    */     //   625: bipush #12
/*    */     //   627: newarray short
/*    */     //   629: dup
/*    */     //   630: dup
/*    */     //   631: dup2
/*    */     //   632: dup2
/*    */     //   633: dup2
/*    */     //   634: dup2
/*    */     //   635: dup2
/*    */     //   636: astore #9
/*    */     //   638: iconst_0
/*    */     //   639: iconst_m1
/*    */     //   640: sastore
/*    */     //   641: iconst_1
/*    */     //   642: iconst_m1
/*    */     //   643: sastore
/*    */     //   644: iconst_2
/*    */     //   645: iconst_m1
/*    */     //   646: sastore
/*    */     //   647: iconst_3
/*    */     //   648: iconst_m1
/*    */     //   649: sastore
/*    */     //   650: iconst_4
/*    */     //   651: iconst_m1
/*    */     //   652: sastore
/*    */     //   653: iconst_5
/*    */     //   654: iconst_m1
/*    */     //   655: sastore
/*    */     //   656: bipush #6
/*    */     //   658: iconst_m1
/*    */     //   659: sastore
/*    */     //   660: bipush #7
/*    */     //   662: iconst_m1
/*    */     //   663: sastore
/*    */     //   664: bipush #8
/*    */     //   666: iconst_m1
/*    */     //   667: sastore
/*    */     //   668: bipush #9
/*    */     //   670: iconst_m1
/*    */     //   671: sastore
/*    */     //   672: bipush #10
/*    */     //   674: iconst_m1
/*    */     //   675: sastore
/*    */     //   676: bipush #11
/*    */     //   678: iconst_m1
/*    */     //   679: sastore
/*    */     //   680: bipush #12
/*    */     //   682: newarray byte
/*    */     //   684: dup
/*    */     //   685: dup
/*    */     //   686: dup2
/*    */     //   687: dup2
/*    */     //   688: dup2
/*    */     //   689: dup2
/*    */     //   690: dup2
/*    */     //   691: astore #10
/*    */     //   693: iconst_0
/*    */     //   694: iconst_0
/*    */     //   695: bastore
/*    */     //   696: iconst_1
/*    */     //   697: iconst_0
/*    */     //   698: bastore
/*    */     //   699: iconst_2
/*    */     //   700: iconst_0
/*    */     //   701: bastore
/*    */     //   702: iconst_3
/*    */     //   703: iconst_0
/*    */     //   704: bastore
/*    */     //   705: iconst_4
/*    */     //   706: iconst_0
/*    */     //   707: bastore
/*    */     //   708: iconst_5
/*    */     //   709: iconst_0
/*    */     //   710: bastore
/*    */     //   711: bipush #6
/*    */     //   713: iconst_0
/*    */     //   714: bastore
/*    */     //   715: bipush #7
/*    */     //   717: iconst_0
/*    */     //   718: bastore
/*    */     //   719: bipush #8
/*    */     //   721: iconst_0
/*    */     //   722: bastore
/*    */     //   723: bipush #9
/*    */     //   725: iconst_0
/*    */     //   726: bastore
/*    */     //   727: bipush #10
/*    */     //   729: iconst_0
/*    */     //   730: bastore
/*    */     //   731: bipush #11
/*    */     //   733: iconst_0
/*    */     //   734: bastore
/*    */     //   735: getstatic f/km.u4 : Lf/R8;
/*    */     //   738: dup
/*    */     //   739: astore #11
/*    */     //   741: ifnull -> 1127
/*    */     //   744: aload #11
/*    */     //   746: invokevirtual UK : ()Lf/qN;
/*    */     //   749: ifnull -> 1127
/*    */     //   752: getstatic f/km.u4 : Lf/R8;
/*    */     //   755: invokevirtual UK : ()Lf/qN;
/*    */     //   758: iload #6
/*    */     //   760: invokevirtual a80 : (I)Lf/T60;
/*    */     //   763: dup
/*    */     //   764: astore #6
/*    */     //   766: ifnull -> 1127
/*    */     //   769: aload #10
/*    */     //   771: aload #6
/*    */     //   773: dup
/*    */     //   774: invokevirtual Zw0 : ()Lf/H10;
/*    */     //   777: invokevirtual bo0 : ()B
/*    */     //   780: istore #7
/*    */     //   782: invokevirtual Zw0 : ()Lf/H10;
/*    */     //   785: dup
/*    */     //   786: astore #6
/*    */     //   788: aload #9
/*    */     //   790: aload #6
/*    */     //   792: aload #9
/*    */     //   794: aload #6
/*    */     //   796: aload #9
/*    */     //   798: aload #6
/*    */     //   800: aload #9
/*    */     //   802: aload #6
/*    */     //   804: aload #9
/*    */     //   806: aload #6
/*    */     //   808: aload #9
/*    */     //   810: aload #6
/*    */     //   812: aload #9
/*    */     //   814: aload #6
/*    */     //   816: getstatic f/Vp0.MP : Lf/Vp0;
/*    */     //   819: dup
/*    */     //   820: dup
/*    */     //   821: astore #11
/*    */     //   823: invokevirtual CoM8 : ()B
/*    */     //   826: istore #12
/*    */     //   828: invokevirtual Hb : (Lf/Vp0;)S
/*    */     //   831: iload #12
/*    */     //   833: swap
/*    */     //   834: sastore
/*    */     //   835: getstatic f/Vp0.K7 : Lf/Vp0;
/*    */     //   838: dup
/*    */     //   839: dup
/*    */     //   840: astore #12
/*    */     //   842: invokevirtual CoM8 : ()B
/*    */     //   845: istore #13
/*    */     //   847: invokevirtual Hb : (Lf/Vp0;)S
/*    */     //   850: iload #13
/*    */     //   852: swap
/*    */     //   853: sastore
/*    */     //   854: getstatic f/Vp0.Pa0 : Lf/Vp0;
/*    */     //   857: dup
/*    */     //   858: dup
/*    */     //   859: astore #13
/*    */     //   861: invokevirtual CoM8 : ()B
/*    */     //   864: istore #14
/*    */     //   866: invokevirtual Hb : (Lf/Vp0;)S
/*    */     //   869: iload #14
/*    */     //   871: swap
/*    */     //   872: sastore
/*    */     //   873: getstatic f/Vp0.CR : Lf/Vp0;
/*    */     //   876: dup
/*    */     //   877: dup
/*    */     //   878: astore #14
/*    */     //   880: invokevirtual CoM8 : ()B
/*    */     //   883: istore #15
/*    */     //   885: invokevirtual Hb : (Lf/Vp0;)S
/*    */     //   888: iload #15
/*    */     //   890: swap
/*    */     //   891: sastore
/*    */     //   892: getstatic f/Vp0.Sz0 : Lf/Vp0;
/*    */     //   895: dup
/*    */     //   896: dup
/*    */     //   897: astore #15
/*    */     //   899: invokevirtual CoM8 : ()B
/*    */     //   902: istore #16
/*    */     //   904: invokevirtual Hb : (Lf/Vp0;)S
/*    */     //   907: iload #16
/*    */     //   909: swap
/*    */     //   910: sastore
/*    */     //   911: getstatic f/Vp0.rK : Lf/Vp0;
/*    */     //   914: dup
/*    */     //   915: dup
/*    */     //   916: astore #16
/*    */     //   918: invokevirtual CoM8 : ()B
/*    */     //   921: istore #17
/*    */     //   923: invokevirtual Hb : (Lf/Vp0;)S
/*    */     //   926: iload #17
/*    */     //   928: swap
/*    */     //   929: sastore
/*    */     //   930: getstatic f/Vp0.sg0 : Lf/Vp0;
/*    */     //   933: dup
/*    */     //   934: dup
/*    */     //   935: astore #17
/*    */     //   937: invokevirtual CoM8 : ()B
/*    */     //   940: istore #18
/*    */     //   942: invokevirtual Hb : (Lf/Vp0;)S
/*    */     //   945: iload #18
/*    */     //   947: swap
/*    */     //   948: sastore
/*    */     //   949: getstatic f/Vp0.M9 : Lf/Vp0;
/*    */     //   952: dup
/*    */     //   953: dup
/*    */     //   954: astore #18
/*    */     //   956: aload #10
/*    */     //   958: aload #6
/*    */     //   960: aload #17
/*    */     //   962: dup
/*    */     //   963: aload #10
/*    */     //   965: aload #6
/*    */     //   967: aload #16
/*    */     //   969: dup
/*    */     //   970: aload #10
/*    */     //   972: aload #6
/*    */     //   974: aload #15
/*    */     //   976: dup
/*    */     //   977: aload #10
/*    */     //   979: aload #6
/*    */     //   981: aload #14
/*    */     //   983: dup
/*    */     //   984: aload #10
/*    */     //   986: aload #6
/*    */     //   988: aload #13
/*    */     //   990: dup
/*    */     //   991: aload #10
/*    */     //   993: aload #6
/*    */     //   995: aload #12
/*    */     //   997: dup
/*    */     //   998: aload #10
/*    */     //   1000: aload #6
/*    */     //   1002: aload #11
/*    */     //   1004: dup
/*    */     //   1005: aload #9
/*    */     //   1007: aload #6
/*    */     //   1009: aload #18
/*    */     //   1011: dup
/*    */     //   1012: invokevirtual CoM8 : ()B
/*    */     //   1015: istore #6
/*    */     //   1017: invokevirtual Hb : (Lf/Vp0;)S
/*    */     //   1020: iload #6
/*    */     //   1022: swap
/*    */     //   1023: sastore
/*    */     //   1024: invokevirtual CoM8 : ()B
/*    */     //   1027: istore #6
/*    */     //   1029: invokevirtual rB : (Lf/Vp0;)B
/*    */     //   1032: iload #6
/*    */     //   1034: swap
/*    */     //   1035: bastore
/*    */     //   1036: invokevirtual CoM8 : ()B
/*    */     //   1039: istore #6
/*    */     //   1041: invokevirtual rB : (Lf/Vp0;)B
/*    */     //   1044: iload #6
/*    */     //   1046: swap
/*    */     //   1047: bastore
/*    */     //   1048: invokevirtual CoM8 : ()B
/*    */     //   1051: istore #6
/*    */     //   1053: invokevirtual rB : (Lf/Vp0;)B
/*    */     //   1056: iload #6
/*    */     //   1058: swap
/*    */     //   1059: bastore
/*    */     //   1060: invokevirtual CoM8 : ()B
/*    */     //   1063: istore #6
/*    */     //   1065: invokevirtual rB : (Lf/Vp0;)B
/*    */     //   1068: iload #6
/*    */     //   1070: swap
/*    */     //   1071: bastore
/*    */     //   1072: invokevirtual CoM8 : ()B
/*    */     //   1075: istore #6
/*    */     //   1077: invokevirtual rB : (Lf/Vp0;)B
/*    */     //   1080: iload #6
/*    */     //   1082: swap
/*    */     //   1083: bastore
/*    */     //   1084: invokevirtual CoM8 : ()B
/*    */     //   1087: istore #6
/*    */     //   1089: invokevirtual rB : (Lf/Vp0;)B
/*    */     //   1092: iload #6
/*    */     //   1094: swap
/*    */     //   1095: bastore
/*    */     //   1096: invokevirtual CoM8 : ()B
/*    */     //   1099: istore #6
/*    */     //   1101: invokevirtual rB : (Lf/Vp0;)B
/*    */     //   1104: iload #6
/*    */     //   1106: swap
/*    */     //   1107: bastore
/*    */     //   1108: invokevirtual CoM8 : ()B
/*    */     //   1111: istore #6
/*    */     //   1113: invokevirtual rB : (Lf/Vp0;)B
/*    */     //   1116: iload #6
/*    */     //   1118: swap
/*    */     //   1119: bastore
/*    */     //   1120: iload #7
/*    */     //   1122: istore #6
/*    */     //   1124: goto -> 1131
/*    */     //   1127: iload #7
/*    */     //   1129: istore #6
/*    */     //   1131: iload #5
/*    */     //   1133: ifeq -> 1166
/*    */     //   1136: aload #8
/*    */     //   1138: ifnull -> 1166
/*    */     //   1141: aload #8
/*    */     //   1143: dup
/*    */     //   1144: invokevirtual cM : ()Lf/OE0;
/*    */     //   1147: invokevirtual I1 : ()Lf/H10;
/*    */     //   1150: invokevirtual uz0 : ()[S
/*    */     //   1153: astore #9
/*    */     //   1155: invokevirtual cM : ()Lf/OE0;
/*    */     //   1158: invokevirtual I1 : ()Lf/H10;
/*    */     //   1161: invokevirtual fG : ()[B
/*    */     //   1164: astore #10
/*    */     //   1166: getstatic f/Vp0.Jo : [Lf/Vp0;
/*    */     //   1169: dup
/*    */     //   1170: astore #5
/*    */     //   1172: arraylength
/*    */     //   1173: istore #7
/*    */     //   1175: iconst_0
/*    */     //   1176: istore #8
/*    */     //   1178: iload #8
/*    */     //   1180: iload #7
/*    */     //   1182: if_icmpge -> 1500
/*    */     //   1185: aload #5
/*    */     //   1187: iload #8
/*    */     //   1189: aaload
/*    */     //   1190: dup
/*    */     //   1191: astore #11
/*    */     //   1193: new java/util/ArrayList
/*    */     //   1196: dup
/*    */     //   1197: astore #12
/*    */     //   1199: invokespecial <init> : ()V
/*    */     //   1202: invokevirtual oH0 : ()Lf/qw0;
/*    */     //   1205: invokevirtual pr : ()Ljava/util/Collection;
/*    */     //   1208: checkcast f/iL
/*    */     //   1211: invokevirtual iterator : ()Ljava/util/Iterator;
/*    */     //   1214: astore #13
/*    */     //   1216: aload #13
/*    */     //   1218: checkcast f/DA0
/*    */     //   1221: invokevirtual hasNext : ()Z
/*    */     //   1224: ifeq -> 1295
/*    */     //   1227: aload #13
/*    */     //   1229: checkcast f/Ke
/*    */     //   1232: invokevirtual next : ()Ljava/lang/Object;
/*    */     //   1235: checkcast f/wc
/*    */     //   1238: dup
/*    */     //   1239: astore #14
/*    */     //   1241: invokevirtual mv0 : ()B
/*    */     //   1244: iflt -> 1262
/*    */     //   1247: aload #14
/*    */     //   1249: invokevirtual mv0 : ()B
/*    */     //   1252: aload_0
/*    */     //   1253: getfield ar0 : B
/*    */     //   1256: if_icmpeq -> 1262
/*    */     //   1259: goto -> 1216
/*    */     //   1262: aload #14
/*    */     //   1264: invokevirtual uJ : ()S
/*    */     //   1267: ifge -> 1216
/*    */     //   1270: aload #14
/*    */     //   1272: invokevirtual aW : ()Z
/*    */     //   1275: ifne -> 1216
/*    */     //   1278: aload #12
/*    */     //   1280: aload #14
/*    */     //   1282: invokevirtual Zj : ()S
/*    */     //   1285: invokestatic valueOf : (S)Ljava/lang/Short;
/*    */     //   1288: invokevirtual add : (Ljava/lang/Object;)Z
/*    */     //   1291: pop
/*    */     //   1292: goto -> 1216
/*    */     //   1295: aload #12
/*    */     //   1297: invokevirtual size : ()I
/*    */     //   1300: ifle -> 1494
/*    */     //   1303: aload #9
/*    */     //   1305: aload #11
/*    */     //   1307: invokevirtual CoM8 : ()B
/*    */     //   1310: saload
/*    */     //   1311: iconst_m1
/*    */     //   1312: if_icmple -> 1359
/*    */     //   1315: aload #12
/*    */     //   1317: aload #9
/*    */     //   1319: aload #11
/*    */     //   1321: invokevirtual CoM8 : ()B
/*    */     //   1324: saload
/*    */     //   1325: invokestatic valueOf : (S)Ljava/lang/Short;
/*    */     //   1328: invokevirtual contains : (Ljava/lang/Object;)Z
/*    */     //   1331: ifeq -> 1359
/*    */     //   1334: aload_0
/*    */     //   1335: getfield yq0 : [S
/*    */     //   1338: aload #9
/*    */     //   1340: aload #11
/*    */     //   1342: dup
/*    */     //   1343: invokevirtual CoM8 : ()B
/*    */     //   1346: istore #12
/*    */     //   1348: invokevirtual CoM8 : ()B
/*    */     //   1351: saload
/*    */     //   1352: iload #12
/*    */     //   1354: swap
/*    */     //   1355: sastore
/*    */     //   1356: goto -> 1407
/*    */     //   1359: aload #11
/*    */     //   1361: getstatic f/Vp0.Pa0 : Lf/Vp0;
/*    */     //   1364: if_acmpne -> 1370
/*    */     //   1367: goto -> 1494
/*    */     //   1370: aload_0
/*    */     //   1371: getfield yq0 : [S
/*    */     //   1374: aload #12
/*    */     //   1376: dup
/*    */     //   1377: aload #11
/*    */     //   1379: invokevirtual CoM8 : ()B
/*    */     //   1382: istore #12
/*    */     //   1384: invokevirtual size : ()I
/*    */     //   1387: iconst_1
/*    */     //   1388: isub
/*    */     //   1389: iconst_0
/*    */     //   1390: swap
/*    */     //   1391: invokestatic A90 : (II)I
/*    */     //   1394: invokevirtual get : (I)Ljava/lang/Object;
/*    */     //   1397: checkcast java/lang/Short
/*    */     //   1400: invokevirtual shortValue : ()S
/*    */     //   1403: iload #12
/*    */     //   1405: swap
/*    */     //   1406: sastore
/*    */     //   1407: aload #11
/*    */     //   1409: aload_0
/*    */     //   1410: getfield yq0 : [S
/*    */     //   1413: aload #11
/*    */     //   1415: invokevirtual CoM8 : ()B
/*    */     //   1418: saload
/*    */     //   1419: invokevirtual Ko : (S)Z
/*    */     //   1422: ifne -> 1439
/*    */     //   1425: aload_0
/*    */     //   1426: getfield E10 : [B
/*    */     //   1429: aload #11
/*    */     //   1431: invokevirtual CoM8 : ()B
/*    */     //   1434: iconst_0
/*    */     //   1435: bastore
/*    */     //   1436: goto -> 1494
/*    */     //   1439: aload #9
/*    */     //   1441: aload #11
/*    */     //   1443: invokevirtual CoM8 : ()B
/*    */     //   1446: saload
/*    */     //   1447: iconst_m1
/*    */     //   1448: if_icmple -> 1476
/*    */     //   1451: aload_0
/*    */     //   1452: getfield E10 : [B
/*    */     //   1455: aload #10
/*    */     //   1457: aload #11
/*    */     //   1459: dup
/*    */     //   1460: invokevirtual CoM8 : ()B
/*    */     //   1463: istore #11
/*    */     //   1465: invokevirtual CoM8 : ()B
/*    */     //   1468: baload
/*    */     //   1469: iload #11
/*    */     //   1471: swap
/*    */     //   1472: bastore
/*    */     //   1473: goto -> 1494
/*    */     //   1476: aload_0
/*    */     //   1477: getfield E10 : [B
/*    */     //   1480: aload #11
/*    */     //   1482: invokevirtual CoM8 : ()B
/*    */     //   1485: getstatic f/UX.jj : [Lf/UX;
/*    */     //   1488: arraylength
/*    */     //   1489: invokestatic qX : (I)I
/*    */     //   1492: i2b
/*    */     //   1493: bastore
/*    */     //   1494: iinc #8, 1
/*    */     //   1497: goto -> 1178
/*    */     //   1500: aload_0
/*    */     //   1501: dup
/*    */     //   1502: dup2
/*    */     //   1503: getfield yq0 : [S
/*    */     //   1506: putfield package : [S
/*    */     //   1509: getfield E10 : [B
/*    */     //   1512: putfield GG0 : [B
/*    */     //   1515: iload #6
/*    */     //   1517: istore #5
/*    */     //   1519: iload #4
/*    */     //   1521: aload_0
/*    */     //   1522: new f/Zz0
/*    */     //   1525: dup
/*    */     //   1526: astore #6
/*    */     //   1528: invokespecial <init> : ()V
/*    */     //   1531: aload #6
/*    */     //   1533: putfield Zz0 : Lf/Zz0;
/*    */     //   1536: ifeq -> 1652
/*    */     //   1539: aload #6
/*    */     //   1541: aload_0
/*    */     //   1542: new f/dQ
/*    */     //   1545: dup
/*    */     //   1546: dup
/*    */     //   1547: astore #6
/*    */     //   1549: sipush #1055
/*    */     //   1552: invokestatic OH0 : (I)Ljava/lang/String;
/*    */     //   1555: invokespecial <init> : (Ljava/lang/String;)V
/*    */     //   1558: ldc_w 'customization-label'
/*    */     //   1561: invokevirtual Xu : (Ljava/lang/String;)V
/*    */     //   1564: new f/OZ
/*    */     //   1567: dup
/*    */     //   1568: astore #7
/*    */     //   1570: iconst_2
/*    */     //   1571: anewarray java/lang/String
/*    */     //   1574: dup
/*    */     //   1575: dup
/*    */     //   1576: sipush #1056
/*    */     //   1579: invokestatic OH0 : (I)Ljava/lang/String;
/*    */     //   1582: iconst_0
/*    */     //   1583: swap
/*    */     //   1584: aastore
/*    */     //   1585: sipush #1057
/*    */     //   1588: invokestatic OH0 : (I)Ljava/lang/String;
/*    */     //   1591: iconst_1
/*    */     //   1592: swap
/*    */     //   1593: aastore
/*    */     //   1594: invokespecial <init> : ([Ljava/lang/Object;)V
/*    */     //   1597: new f/W1
/*    */     //   1600: dup
/*    */     //   1601: astore #8
/*    */     //   1603: aload_0
/*    */     //   1604: dup
/*    */     //   1605: aload #8
/*    */     //   1607: dup
/*    */     //   1608: aload #7
/*    */     //   1610: invokespecial <init> : (Lf/cQ;)V
/*    */     //   1613: putfield Ih0 : Lf/W1;
/*    */     //   1616: <illegal opcode> run : (Lf/Ia;)Ljava/lang/Runnable;
/*    */     //   1621: invokevirtual D30 : (Ljava/lang/Runnable;)V
/*    */     //   1624: getfield Ih0 : Lf/W1;
/*    */     //   1627: iconst_0
/*    */     //   1628: invokevirtual Z30 : (I)V
/*    */     //   1631: iconst_2
/*    */     //   1632: anewarray f/JG0
/*    */     //   1635: dup
/*    */     //   1636: dup
/*    */     //   1637: aload_0
/*    */     //   1638: swap
/*    */     //   1639: iconst_0
/*    */     //   1640: aload #6
/*    */     //   1642: aastore
/*    */     //   1643: getfield Ih0 : Lf/W1;
/*    */     //   1646: iconst_1
/*    */     //   1647: swap
/*    */     //   1648: aastore
/*    */     //   1649: invokevirtual of0 : ([Lf/JG0;)V
/*    */     //   1652: aload_0
/*    */     //   1653: dup
/*    */     //   1654: dup2
/*    */     //   1655: bipush #13
/*    */     //   1657: anewarray f/cQ
/*    */     //   1660: putfield J5 : [Lf/cQ;
/*    */     //   1663: bipush #13
/*    */     //   1665: anewarray f/W1
/*    */     //   1668: putfield Lc0 : [Lf/W1;
/*    */     //   1671: bipush #13
/*    */     //   1673: anewarray f/Fy0
/*    */     //   1676: putfield qU : [Lf/Fy0;
/*    */     //   1679: bipush #13
/*    */     //   1681: anewarray f/dQ
/*    */     //   1684: putfield gz0 : [Lf/dQ;
/*    */     //   1687: iconst_0
/*    */     //   1688: istore #6
/*    */     //   1690: iload #6
/*    */     //   1692: aload_0
/*    */     //   1693: getfield qU : [Lf/Fy0;
/*    */     //   1696: arraylength
/*    */     //   1697: if_icmpge -> 1750
/*    */     //   1700: iload #6
/*    */     //   1702: aload_0
/*    */     //   1703: dup
/*    */     //   1704: getfield gz0 : [Lf/dQ;
/*    */     //   1707: iload #6
/*    */     //   1709: new f/dQ
/*    */     //   1712: dup
/*    */     //   1713: astore #7
/*    */     //   1715: iload #6
/*    */     //   1717: sipush #2870
/*    */     //   1720: iadd
/*    */     //   1721: invokestatic OH0 : (I)Ljava/lang/String;
/*    */     //   1724: invokespecial <init> : (Ljava/lang/String;)V
/*    */     //   1727: aload #7
/*    */     //   1729: aastore
/*    */     //   1730: getfield gz0 : [Lf/dQ;
/*    */     //   1733: iload #6
/*    */     //   1735: aaload
/*    */     //   1736: ldc_w 'customization-label'
/*    */     //   1739: invokevirtual Xu : (Ljava/lang/String;)V
/*    */     //   1742: iconst_1
/*    */     //   1743: iadd
/*    */     //   1744: i2b
/*    */     //   1745: istore #6
/*    */     //   1747: goto -> 1690
/*    */     //   1750: iconst_0
/*    */     //   1751: istore #6
/*    */     //   1753: iload #6
/*    */     //   1755: aload_0
/*    */     //   1756: getfield qU : [Lf/Fy0;
/*    */     //   1759: dup
/*    */     //   1760: astore #7
/*    */     //   1762: arraylength
/*    */     //   1763: if_icmpge -> 2246
/*    */     //   1766: aload_0
/*    */     //   1767: dup
/*    */     //   1768: aload #7
/*    */     //   1770: iload #6
/*    */     //   1772: new f/Fy0
/*    */     //   1775: dup
/*    */     //   1776: astore #7
/*    */     //   1778: ldc_w ''
/*    */     //   1781: invokespecial <init> : (Ljava/lang/String;)V
/*    */     //   1784: aload #7
/*    */     //   1786: aastore
/*    */     //   1787: getfield qU : [Lf/Fy0;
/*    */     //   1790: iload #6
/*    */     //   1792: aaload
/*    */     //   1793: invokevirtual zY : ()Lf/rH;
/*    */     //   1796: iconst_1
/*    */     //   1797: anewarray f/pe0
/*    */     //   1800: dup
/*    */     //   1801: invokestatic ZZ : ()Lf/interface;
/*    */     //   1804: invokevirtual hJ0 : ()Lf/pe0;
/*    */     //   1807: iconst_0
/*    */     //   1808: swap
/*    */     //   1809: aastore
/*    */     //   1810: invokevirtual Pn : ([Lf/pe0;)Lf/JG0;
/*    */     //   1813: pop
/*    */     //   1814: getfield qU : [Lf/Fy0;
/*    */     //   1817: iload #6
/*    */     //   1819: aaload
/*    */     //   1820: invokevirtual zY : ()Lf/rH;
/*    */     //   1823: astore #7
/*    */     //   1825: invokestatic XU : ()Z
/*    */     //   1828: ifeq -> 1837
/*    */     //   1831: fconst_2
/*    */     //   1832: fstore #8
/*    */     //   1834: goto -> 1840
/*    */     //   1837: fconst_1
/*    */     //   1838: fstore #8
/*    */     //   1840: aload_0
/*    */     //   1841: aload #7
/*    */     //   1843: fload #8
/*    */     //   1845: invokevirtual Ii0 : (F)V
/*    */     //   1848: getfield qU : [Lf/Fy0;
/*    */     //   1851: iload #6
/*    */     //   1853: aaload
/*    */     //   1854: invokevirtual zY : ()Lf/rH;
/*    */     //   1857: astore #7
/*    */     //   1859: iconst_0
/*    */     //   1860: istore #8
/*    */     //   1862: invokestatic XU : ()Z
/*    */     //   1865: ifeq -> 1875
/*    */     //   1868: bipush #6
/*    */     //   1870: istore #9
/*    */     //   1872: goto -> 1879
/*    */     //   1875: bipush #12
/*    */     //   1877: istore #9
/*    */     //   1879: iload #6
/*    */     //   1881: aload_0
/*    */     //   1882: dup
/*    */     //   1883: aload #7
/*    */     //   1885: iload #8
/*    */     //   1887: iload #9
/*    */     //   1889: invokevirtual zT : (II)Lf/JG0;
/*    */     //   1892: pop
/*    */     //   1893: getfield qU : [Lf/Fy0;
/*    */     //   1896: iload #6
/*    */     //   1898: aaload
/*    */     //   1899: ldc_w 'customization-color'
/*    */     //   1902: invokevirtual Xu : (Ljava/lang/String;)V
/*    */     //   1905: getfield qU : [Lf/Fy0;
/*    */     //   1908: iload #6
/*    */     //   1910: aaload
/*    */     //   1911: iconst_0
/*    */     //   1912: invokevirtual wI0 : (Z)V
/*    */     //   1915: ifle -> 1998
/*    */     //   1918: aload_0
/*    */     //   1919: dup
/*    */     //   1920: dup
/*    */     //   1921: iload #6
/*    */     //   1923: iconst_1
/*    */     //   1924: isub
/*    */     //   1925: i2b
/*    */     //   1926: istore #7
/*    */     //   1928: getfield J5 : [Lf/cQ;
/*    */     //   1931: iload #6
/*    */     //   1933: new f/OZ
/*    */     //   1936: dup
/*    */     //   1937: astore #8
/*    */     //   1939: aload_0
/*    */     //   1940: iload #7
/*    */     //   1942: invokestatic cOm1 : (I)Lf/Vp0;
/*    */     //   1945: invokevirtual W0 : (Lf/Vp0;)[Lf/uK;
/*    */     //   1948: invokespecial <init> : ([Ljava/lang/Object;)V
/*    */     //   1951: aload #8
/*    */     //   1953: aastore
/*    */     //   1954: getfield Lc0 : [Lf/W1;
/*    */     //   1957: iload #6
/*    */     //   1959: new f/JD0
/*    */     //   1962: dup
/*    */     //   1963: astore #8
/*    */     //   1965: aload_0
/*    */     //   1966: getfield J5 : [Lf/cQ;
/*    */     //   1969: iload #6
/*    */     //   1971: aaload
/*    */     //   1972: invokespecial <init> : (Lf/cQ;)V
/*    */     //   1975: aload #8
/*    */     //   1977: aastore
/*    */     //   1978: getfield qU : [Lf/Fy0;
/*    */     //   1981: iload #6
/*    */     //   1983: aaload
/*    */     //   1984: aload_0
/*    */     //   1985: iload #7
/*    */     //   1987: <illegal opcode> run : (Lf/Ia;B)Ljava/lang/Runnable;
/*    */     //   1992: invokevirtual tW : (Ljava/lang/Runnable;)V
/*    */     //   1995: goto -> 2123
/*    */     //   1998: iconst_5
/*    */     //   1999: dup
/*    */     //   2000: istore #7
/*    */     //   2002: anewarray f/uK
/*    */     //   2005: astore #8
/*    */     //   2007: iconst_0
/*    */     //   2008: istore #9
/*    */     //   2010: iload #9
/*    */     //   2012: iload #7
/*    */     //   2014: if_icmpge -> 2066
/*    */     //   2017: aload #8
/*    */     //   2019: iload #9
/*    */     //   2021: new f/uK
/*    */     //   2024: dup
/*    */     //   2025: ldc_w ''
/*    */     //   2028: invokestatic df : (Ljava/lang/String;)Ljava/lang/StringBuilder;
/*    */     //   2031: iload #9
/*    */     //   2033: iconst_1
/*    */     //   2034: iadd
/*    */     //   2035: dup
/*    */     //   2036: istore #10
/*    */     //   2038: invokevirtual append : (I)Ljava/lang/StringBuilder;
/*    */     //   2041: invokevirtual toString : ()Ljava/lang/String;
/*    */     //   2044: sipush #2808
/*    */     //   2047: swap
/*    */     //   2048: invokestatic Go : (ILjava/lang/String;)Ljava/lang/String;
/*    */     //   2051: iload #9
/*    */     //   2053: i2b
/*    */     //   2054: i2s
/*    */     //   2055: invokespecial <init> : (Ljava/lang/String;S)V
/*    */     //   2058: aastore
/*    */     //   2059: iload #10
/*    */     //   2061: istore #9
/*    */     //   2063: goto -> 2010
/*    */     //   2066: aload_0
/*    */     //   2067: dup
/*    */     //   2068: dup
/*    */     //   2069: getfield J5 : [Lf/cQ;
/*    */     //   2072: iload #6
/*    */     //   2074: new f/OZ
/*    */     //   2077: dup
/*    */     //   2078: astore #7
/*    */     //   2080: aload #8
/*    */     //   2082: invokespecial <init> : ([Ljava/lang/Object;)V
/*    */     //   2085: aload #7
/*    */     //   2087: aastore
/*    */     //   2088: getfield Lc0 : [Lf/W1;
/*    */     //   2091: iload #6
/*    */     //   2093: new f/JD0
/*    */     //   2096: dup
/*    */     //   2097: astore #7
/*    */     //   2099: aload_0
/*    */     //   2100: getfield J5 : [Lf/cQ;
/*    */     //   2103: iload #6
/*    */     //   2105: aaload
/*    */     //   2106: invokespecial <init> : (Lf/cQ;)V
/*    */     //   2109: aload #7
/*    */     //   2111: aastore
/*    */     //   2112: getfield Lc0 : [Lf/W1;
/*    */     //   2115: iload #6
/*    */     //   2117: aaload
/*    */     //   2118: iload #5
/*    */     //   2120: invokevirtual Z30 : (I)V
/*    */     //   2123: aload_0
/*    */     //   2124: dup
/*    */     //   2125: getfield Lc0 : [Lf/W1;
/*    */     //   2128: iload #6
/*    */     //   2130: aaload
/*    */     //   2131: aload_0
/*    */     //   2132: iload #6
/*    */     //   2134: <illegal opcode> run : (Lf/Ia;I)Ljava/lang/Runnable;
/*    */     //   2139: invokevirtual D30 : (Ljava/lang/Runnable;)V
/*    */     //   2142: getfield J5 : [Lf/cQ;
/*    */     //   2145: iload #6
/*    */     //   2147: aaload
/*    */     //   2148: invokevirtual pu : ()I
/*    */     //   2151: iconst_2
/*    */     //   2152: if_icmpge -> 2166
/*    */     //   2155: aload_0
/*    */     //   2156: getfield Lc0 : [Lf/W1;
/*    */     //   2159: iload #6
/*    */     //   2161: aaload
/*    */     //   2162: iconst_0
/*    */     //   2163: invokevirtual sk0 : (Z)V
/*    */     //   2166: iload #6
/*    */     //   2168: iconst_1
/*    */     //   2169: if_icmpeq -> 2236
/*    */     //   2172: iload #6
/*    */     //   2174: bipush #11
/*    */     //   2176: if_icmpne -> 2187
/*    */     //   2179: iload #4
/*    */     //   2181: ifeq -> 2187
/*    */     //   2184: goto -> 2236
/*    */     //   2187: aload_0
/*    */     //   2188: getfield Zz0 : Lf/Zz0;
/*    */     //   2191: iconst_3
/*    */     //   2192: anewarray f/JG0
/*    */     //   2195: dup
/*    */     //   2196: dup
/*    */     //   2197: astore #7
/*    */     //   2199: aload_0
/*    */     //   2200: aload #7
/*    */     //   2202: aload_0
/*    */     //   2203: aload #7
/*    */     //   2205: aload_0
/*    */     //   2206: getfield gz0 : [Lf/dQ;
/*    */     //   2209: iload #6
/*    */     //   2211: aaload
/*    */     //   2212: iconst_0
/*    */     //   2213: swap
/*    */     //   2214: aastore
/*    */     //   2215: getfield Lc0 : [Lf/W1;
/*    */     //   2218: iload #6
/*    */     //   2220: aaload
/*    */     //   2221: iconst_1
/*    */     //   2222: swap
/*    */     //   2223: aastore
/*    */     //   2224: getfield qU : [Lf/Fy0;
/*    */     //   2227: iload #6
/*    */     //   2229: aaload
/*    */     //   2230: iconst_2
/*    */     //   2231: swap
/*    */     //   2232: aastore
/*    */     //   2233: invokevirtual of0 : ([Lf/JG0;)V
/*    */     //   2236: iload #6
/*    */     //   2238: iconst_1
/*    */     //   2239: iadd
/*    */     //   2240: i2b
/*    */     //   2241: istore #6
/*    */     //   2243: goto -> 1753
/*    */     //   2246: iload #4
/*    */     //   2248: aload_0
/*    */     //   2249: invokevirtual z10 : ()V
/*    */     //   2252: new f/Un
/*    */     //   2255: astore #5
/*    */     //   2257: ifeq -> 2266
/*    */     //   2260: sipush #1051
/*    */     //   2263: goto -> 2269
/*    */     //   2266: sipush #2802
/*    */     //   2269: invokestatic OH0 : (I)Ljava/lang/String;
/*    */     //   2272: astore #6
/*    */     //   2274: iload_2
/*    */     //   2275: aload #5
/*    */     //   2277: aload_0
/*    */     //   2278: aload #5
/*    */     //   2280: dup
/*    */     //   2281: aload_0
/*    */     //   2282: aload #5
/*    */     //   2284: dup
/*    */     //   2285: aload #6
/*    */     //   2287: invokespecial <init> : (Ljava/lang/String;)V
/*    */     //   2290: putfield MI0 : Lf/Un;
/*    */     //   2293: ldc_w 'button'
/*    */     //   2296: invokevirtual Xu : (Ljava/lang/String;)V
/*    */     //   2299: iconst_1
/*    */     //   2300: invokevirtual wI0 : (Z)V
/*    */     //   2303: <illegal opcode> run : (Lf/Ia;)Ljava/lang/Runnable;
/*    */     //   2308: invokevirtual tW : (Ljava/lang/Runnable;)V
/*    */     //   2311: ifne -> 2324
/*    */     //   2314: aload_0
/*    */     //   2315: getfield Lc0 : [Lf/W1;
/*    */     //   2318: iconst_0
/*    */     //   2319: aaload
/*    */     //   2320: iconst_0
/*    */     //   2321: invokevirtual sk0 : (Z)V
/*    */     //   2324: invokestatic XU : ()Z
/*    */     //   2327: ifeq -> 2345
/*    */     //   2330: aload #5
/*    */     //   2332: dup
/*    */     //   2333: ldc_w 'mobile-save-icon'
/*    */     //   2336: invokevirtual Xu : (Ljava/lang/String;)V
/*    */     //   2339: ldc_w ''
/*    */     //   2342: invokevirtual s6 : (Ljava/lang/String;)V
/*    */     //   2345: new f/Ip
/*    */     //   2348: dup
/*    */     //   2349: dup2
/*    */     //   2350: dup2
/*    */     //   2351: dup2
/*    */     //   2352: astore #5
/*    */     //   2354: aload_0
/*    */     //   2355: aload #5
/*    */     //   2357: dup
/*    */     //   2358: invokespecial <init> : ()V
/*    */     //   2361: putfield Tt : Lf/Ip;
/*    */     //   2364: ldc_w 'color-dialog'
/*    */     //   2367: invokevirtual Xu : (Ljava/lang/String;)V
/*    */     //   2370: invokevirtual d7 : ()Lf/cr0;
/*    */     //   2373: invokevirtual rK0 : (Lf/U90;)V
/*    */     //   2376: invokevirtual mE0 : ()Lf/g0;
/*    */     //   2379: invokevirtual WN : (Lf/U90;)V
/*    */     //   2382: invokevirtual mE0 : ()Lf/g0;
/*    */     //   2385: astore #6
/*    */     //   2387: invokevirtual d7 : ()Lf/cr0;
/*    */     //   2390: astore #7
/*    */     //   2392: getstatic f/UX.jj : [Lf/UX;
/*    */     //   2395: dup
/*    */     //   2396: astore #8
/*    */     //   2398: aload #5
/*    */     //   2400: aload_0
/*    */     //   2401: aload #8
/*    */     //   2403: arraylength
/*    */     //   2404: anewarray f/Un
/*    */     //   2407: putfield Yq0 : [Lf/Un;
/*    */     //   2410: invokevirtual iJ0 : ()Lf/U90;
/*    */     //   2413: invokevirtual Em0 : ()Lf/U90;
/*    */     //   2416: pop
/*    */     //   2417: iconst_0
/*    */     //   2418: istore #5
/*    */     //   2420: arraylength
/*    */     //   2421: istore #9
/*    */     //   2423: iconst_0
/*    */     //   2424: istore #10
/*    */     //   2426: iload #10
/*    */     //   2428: iload #9
/*    */     //   2430: if_icmpge -> 2664
/*    */     //   2433: aload_0
/*    */     //   2434: aload #8
/*    */     //   2436: iload #10
/*    */     //   2438: aaload
/*    */     //   2439: astore #11
/*    */     //   2441: getfield Yq0 : [Lf/Un;
/*    */     //   2444: astore #12
/*    */     //   2446: new f/Fy0
/*    */     //   2449: astore #13
/*    */     //   2451: aconst_null
/*    */     //   2452: astore #14
/*    */     //   2454: invokestatic XU : ()Z
/*    */     //   2457: ifeq -> 2467
/*    */     //   2460: bipush #70
/*    */     //   2462: istore #15
/*    */     //   2464: goto -> 2471
/*    */     //   2467: bipush #30
/*    */     //   2469: istore #15
/*    */     //   2471: invokestatic XU : ()Z
/*    */     //   2474: ifeq -> 2484
/*    */     //   2477: bipush #70
/*    */     //   2479: istore #16
/*    */     //   2481: goto -> 2488
/*    */     //   2484: bipush #30
/*    */     //   2486: istore #16
/*    */     //   2488: aload #7
/*    */     //   2490: aload_0
/*    */     //   2491: aload #6
/*    */     //   2493: aload_0
/*    */     //   2494: dup
/*    */     //   2495: dup2
/*    */     //   2496: aload #12
/*    */     //   2498: iload #5
/*    */     //   2500: aload #13
/*    */     //   2502: aload #14
/*    */     //   2504: iload #15
/*    */     //   2506: iload #16
/*    */     //   2508: invokespecial <init> : (Ljava/lang/String;II)V
/*    */     //   2511: aload #13
/*    */     //   2513: aastore
/*    */     //   2514: getfield Yq0 : [Lf/Un;
/*    */     //   2517: iload #5
/*    */     //   2519: aaload
/*    */     //   2520: ldc_w 'color-button'
/*    */     //   2523: invokevirtual Xu : (Ljava/lang/String;)V
/*    */     //   2526: getfield Yq0 : [Lf/Un;
/*    */     //   2529: iload #5
/*    */     //   2531: aaload
/*    */     //   2532: dup
/*    */     //   2533: astore #12
/*    */     //   2535: new f/I
/*    */     //   2538: dup
/*    */     //   2539: aload #12
/*    */     //   2541: new f/pRn
/*    */     //   2544: dup
/*    */     //   2545: astore #12
/*    */     //   2547: aload #11
/*    */     //   2549: invokevirtual Lv : ()Lf/ao;
/*    */     //   2552: invokevirtual Jt : ()I
/*    */     //   2555: invokespecial <init> : (I)V
/*    */     //   2558: aload #12
/*    */     //   2560: invokespecial <init> : (Lf/JG0;Lf/pRn;)V
/*    */     //   2563: invokevirtual Vo0 : (Lf/I;)V
/*    */     //   2566: getfield Yq0 : [Lf/Un;
/*    */     //   2569: iload #5
/*    */     //   2571: aaload
/*    */     //   2572: aload_0
/*    */     //   2573: aload #11
/*    */     //   2575: <illegal opcode> run : (Lf/Ia;Lf/UX;)Ljava/lang/Runnable;
/*    */     //   2580: invokevirtual tW : (Ljava/lang/Runnable;)V
/*    */     //   2583: getfield Yq0 : [Lf/Un;
/*    */     //   2586: iload #5
/*    */     //   2588: aaload
/*    */     //   2589: invokevirtual Ya : (Lf/JG0;)Lf/U90;
/*    */     //   2592: pop
/*    */     //   2593: getfield Yq0 : [Lf/Un;
/*    */     //   2596: iload #5
/*    */     //   2598: aaload
/*    */     //   2599: invokevirtual Ya : (Lf/JG0;)Lf/U90;
/*    */     //   2602: pop
/*    */     //   2603: iload #5
/*    */     //   2605: iconst_1
/*    */     //   2606: iadd
/*    */     //   2607: dup
/*    */     //   2608: istore #5
/*    */     //   2610: iconst_3
/*    */     //   2611: irem
/*    */     //   2612: ifne -> 2658
/*    */     //   2615: aload_0
/*    */     //   2616: dup
/*    */     //   2617: dup2
/*    */     //   2618: getfield Tt : Lf/Ip;
/*    */     //   2621: invokevirtual iJ0 : ()Lf/U90;
/*    */     //   2624: aload #6
/*    */     //   2626: invokevirtual ee0 : (Lf/U90;)Lf/U90;
/*    */     //   2629: pop
/*    */     //   2630: getfield Tt : Lf/Ip;
/*    */     //   2633: invokevirtual xh : ()Lf/U90;
/*    */     //   2636: aload #7
/*    */     //   2638: invokevirtual ee0 : (Lf/U90;)Lf/U90;
/*    */     //   2641: pop
/*    */     //   2642: getfield Tt : Lf/Ip;
/*    */     //   2645: invokevirtual mE0 : ()Lf/g0;
/*    */     //   2648: astore #6
/*    */     //   2650: getfield Tt : Lf/Ip;
/*    */     //   2653: invokevirtual d7 : ()Lf/cr0;
/*    */     //   2656: astore #7
/*    */     //   2658: iinc #10, 1
/*    */     //   2661: goto -> 2426
/*    */     //   2664: aload_0
/*    */     //   2665: dup
/*    */     //   2666: dup
/*    */     //   2667: getfield Tt : Lf/Ip;
/*    */     //   2670: invokevirtual iJ0 : ()Lf/U90;
/*    */     //   2673: aload #6
/*    */     //   2675: invokevirtual ee0 : (Lf/U90;)Lf/U90;
/*    */     //   2678: invokevirtual Em0 : ()Lf/U90;
/*    */     //   2681: pop
/*    */     //   2682: getfield Tt : Lf/Ip;
/*    */     //   2685: invokevirtual xh : ()Lf/U90;
/*    */     //   2688: aload #7
/*    */     //   2690: invokevirtual ee0 : (Lf/U90;)Lf/U90;
/*    */     //   2693: pop
/*    */     //   2694: getfield Tt : Lf/Ip;
/*    */     //   2697: iconst_0
/*    */     //   2698: invokevirtual wI0 : (Z)V
/*    */     //   2701: invokestatic XU : ()Z
/*    */     //   2704: ifeq -> 2715
/*    */     //   2707: sipush #128
/*    */     //   2710: istore #5
/*    */     //   2712: goto -> 2719
/*    */     //   2715: bipush #64
/*    */     //   2717: istore #5
/*    */     //   2719: iload #4
/*    */     //   2721: aload_0
/*    */     //   2722: dup
/*    */     //   2723: dup
/*    */     //   2724: new f/Fy0
/*    */     //   2727: dup
/*    */     //   2728: ldc_w ''
/*    */     //   2731: iload #5
/*    */     //   2733: dup
/*    */     //   2734: invokespecial <init> : (Ljava/lang/String;II)V
/*    */     //   2737: invokevirtual zY : ()Lf/rH;
/*    */     //   2740: iconst_1
/*    */     //   2741: anewarray f/pe0
/*    */     //   2744: dup
/*    */     //   2745: invokestatic ZZ : ()Lf/interface;
/*    */     //   2748: invokevirtual qs : ()Lf/pe0;
/*    */     //   2751: iconst_0
/*    */     //   2752: swap
/*    */     //   2753: aastore
/*    */     //   2754: invokevirtual Pn : ([Lf/pe0;)Lf/JG0;
/*    */     //   2757: checkcast f/Fy0
/*    */     //   2760: dup
/*    */     //   2761: astore #6
/*    */     //   2763: putfield L2 : Lf/Fy0;
/*    */     //   2766: aload #6
/*    */     //   2768: new f/Fy0
/*    */     //   2771: dup
/*    */     //   2772: ldc_w ''
/*    */     //   2775: iload #5
/*    */     //   2777: dup
/*    */     //   2778: invokespecial <init> : (Ljava/lang/String;II)V
/*    */     //   2781: invokevirtual zY : ()Lf/rH;
/*    */     //   2784: iconst_1
/*    */     //   2785: anewarray f/pe0
/*    */     //   2788: dup
/*    */     //   2789: invokestatic ZZ : ()Lf/interface;
/*    */     //   2792: invokevirtual VH0 : ()Lf/pe0;
/*    */     //   2795: iconst_0
/*    */     //   2796: swap
/*    */     //   2797: aastore
/*    */     //   2798: invokevirtual Pn : ([Lf/pe0;)Lf/JG0;
/*    */     //   2801: checkcast f/Fy0
/*    */     //   2804: dup
/*    */     //   2805: astore #7
/*    */     //   2807: aload_0
/*    */     //   2808: aload #6
/*    */     //   2810: aload_0
/*    */     //   2811: aload #7
/*    */     //   2813: aload #6
/*    */     //   2815: aload #7
/*    */     //   2817: aload #6
/*    */     //   2819: aload_0
/*    */     //   2820: aload #7
/*    */     //   2822: putfield Tz0 : Lf/Fy0;
/*    */     //   2825: invokevirtual zY : ()Lf/rH;
/*    */     //   2828: iload #5
/*    */     //   2830: dup
/*    */     //   2831: invokevirtual tL : (II)V
/*    */     //   2834: invokevirtual zY : ()Lf/rH;
/*    */     //   2837: iload #5
/*    */     //   2839: dup
/*    */     //   2840: invokevirtual tL : (II)V
/*    */     //   2843: ldc_w 'widget'
/*    */     //   2846: invokevirtual Xu : (Ljava/lang/String;)V
/*    */     //   2849: ldc_w 'widget'
/*    */     //   2852: invokevirtual Xu : (Ljava/lang/String;)V
/*    */     //   2855: <illegal opcode> run : (Lf/Ia;)Ljava/lang/Runnable;
/*    */     //   2860: invokevirtual tW : (Ljava/lang/Runnable;)V
/*    */     //   2863: <illegal opcode> run : (Lf/Ia;)Ljava/lang/Runnable;
/*    */     //   2868: invokevirtual tW : (Ljava/lang/Runnable;)V
/*    */     //   2871: invokevirtual J8 : (Lf/JG0;)V
/*    */     //   2874: aload #7
/*    */     //   2876: invokevirtual J8 : (Lf/JG0;)V
/*    */     //   2879: new f/Un
/*    */     //   2882: dup
/*    */     //   2883: astore #5
/*    */     //   2885: aload_0
/*    */     //   2886: aload #5
/*    */     //   2888: dup
/*    */     //   2889: aload_0
/*    */     //   2890: aload #5
/*    */     //   2892: dup
/*    */     //   2893: sipush #2801
/*    */     //   2896: invokestatic OH0 : (I)Ljava/lang/String;
/*    */     //   2899: invokespecial <init> : (Ljava/lang/String;)V
/*    */     //   2902: putfield VF0 : Lf/Un;
/*    */     //   2905: ldc_w 'button'
/*    */     //   2908: invokevirtual Xu : (Ljava/lang/String;)V
/*    */     //   2911: iconst_0
/*    */     //   2912: invokevirtual wI0 : (Z)V
/*    */     //   2915: <illegal opcode> run : (Lf/Ia;)Ljava/lang/Runnable;
/*    */     //   2920: invokevirtual tW : (Ljava/lang/Runnable;)V
/*    */     //   2923: new f/Ip
/*    */     //   2926: dup
/*    */     //   2927: astore #5
/*    */     //   2929: invokespecial <init> : ()V
/*    */     //   2932: ifeq -> 3308
/*    */     //   2935: aload_0
/*    */     //   2936: dup
/*    */     //   2937: dup
/*    */     //   2938: iconst_0
/*    */     //   2939: invokevirtual jJ0 : (Z)V
/*    */     //   2942: new f/Ip
/*    */     //   2945: dup
/*    */     //   2946: invokespecial <init> : ()V
/*    */     //   2949: ldc_w 'login-panel'
/*    */     //   2952: invokevirtual Xu : (Ljava/lang/String;)V
/*    */     //   2955: new f/of
/*    */     //   2958: dup
/*    */     //   2959: aload_0
/*    */     //   2960: swap
/*    */     //   2961: dup
/*    */     //   2962: invokespecial <init> : ()V
/*    */     //   2965: putfield cOm5 : Lf/of;
/*    */     //   2968: bipush #16
/*    */     //   2970: invokevirtual co : (I)V
/*    */     //   2973: getfield cOm5 : Lf/of;
/*    */     //   2976: ldc_w '[a-zA-Z]'
/*    */     //   2979: invokevirtual Lpt5 : (Ljava/lang/String;)V
/*    */     //   2982: new f/dQ
/*    */     //   2985: dup
/*    */     //   2986: dup
/*    */     //   2987: astore #6
/*    */     //   2989: aload_0
/*    */     //   2990: aload #6
/*    */     //   2992: sipush #1053
/*    */     //   2995: invokestatic OH0 : (I)Ljava/lang/String;
/*    */     //   2998: invokespecial <init> : (Ljava/lang/String;)V
/*    */     //   3001: getfield cOm5 : Lf/of;
/*    */     //   3004: invokevirtual VH : (Lf/JG0;)V
/*    */     //   3007: ldc_w 'customization-label'
/*    */     //   3010: invokevirtual Xu : (Ljava/lang/String;)V
/*    */     //   3013: getfield cOm5 : Lf/of;
/*    */     //   3016: aload #6
/*    */     //   3018: invokevirtual Xy : ()Ljava/lang/String;
/*    */     //   3021: pop
/*    */     //   3022: invokevirtual getClass : ()Ljava/lang/Class;
/*    */     //   3025: pop
/*    */     //   3026: new f/Un
/*    */     //   3029: dup
/*    */     //   3030: astore #7
/*    */     //   3032: aload_1
/*    */     //   3033: aload_0
/*    */     //   3034: aload #7
/*    */     //   3036: dup
/*    */     //   3037: bipush #53
/*    */     //   3039: invokestatic OH0 : (I)Ljava/lang/String;
/*    */     //   3042: invokespecial <init> : (Ljava/lang/String;)V
/*    */     //   3045: putfield Bi0 : Lf/Un;
/*    */     //   3048: <illegal opcode> run : (Lf/js;)Ljava/lang/Runnable;
/*    */     //   3053: invokevirtual tW : (Ljava/lang/Runnable;)V
/*    */     //   3056: new f/dQ
/*    */     //   3059: dup
/*    */     //   3060: dup
/*    */     //   3061: astore_1
/*    */     //   3062: sipush #1060
/*    */     //   3065: invokestatic OH0 : (I)Ljava/lang/String;
/*    */     //   3068: invokespecial <init> : (Ljava/lang/String;)V
/*    */     //   3071: ldc_w 'customization-label'
/*    */     //   3074: invokevirtual Xu : (Ljava/lang/String;)V
/*    */     //   3077: new java/util/ArrayList
/*    */     //   3080: dup
/*    */     //   3081: astore #7
/*    */     //   3083: invokespecial <init> : ()V
/*    */     //   3086: iconst_0
/*    */     //   3087: istore #8
/*    */     //   3089: iload #8
/*    */     //   3091: iconst_5
/*    */     //   3092: if_icmpge -> 3124
/*    */     //   3095: iload #8
/*    */     //   3097: aload #7
/*    */     //   3099: getstatic f/Ia.qr : [B
/*    */     //   3102: iload #8
/*    */     //   3104: baload
/*    */     //   3105: ldc_w 250000
/*    */     //   3108: iadd
/*    */     //   3109: invokestatic OH0 : (I)Ljava/lang/String;
/*    */     //   3112: invokevirtual add : (Ljava/lang/Object;)Z
/*    */     //   3115: pop
/*    */     //   3116: iconst_1
/*    */     //   3117: iadd
/*    */     //   3118: i2b
/*    */     //   3119: istore #8
/*    */     //   3121: goto -> 3089
/*    */     //   3124: aload #5
/*    */     //   3126: dup
/*    */     //   3127: dup2
/*    */     //   3128: aload_0
/*    */     //   3129: new f/OZ
/*    */     //   3132: dup
/*    */     //   3133: astore #8
/*    */     //   3135: aload #7
/*    */     //   3137: invokespecial <init> : (Ljava/util/Collection;)V
/*    */     //   3140: new f/W1
/*    */     //   3143: dup
/*    */     //   3144: astore #7
/*    */     //   3146: aload_0
/*    */     //   3147: dup
/*    */     //   3148: aload #7
/*    */     //   3150: dup
/*    */     //   3151: aload #8
/*    */     //   3153: invokespecial <init> : (Lf/cQ;)V
/*    */     //   3156: putfield iP : Lf/W1;
/*    */     //   3159: <illegal opcode> run : (Lf/Ia;)Ljava/lang/Runnable;
/*    */     //   3164: invokevirtual D30 : (Ljava/lang/Runnable;)V
/*    */     //   3167: getfield iP : Lf/W1;
/*    */     //   3170: iconst_0
/*    */     //   3171: invokevirtual Z30 : (I)V
/*    */     //   3174: invokevirtual d7 : ()Lf/cr0;
/*    */     //   3177: astore #7
/*    */     //   3179: invokevirtual mE0 : ()Lf/g0;
/*    */     //   3182: astore #8
/*    */     //   3184: aload #7
/*    */     //   3186: aload #8
/*    */     //   3188: aload #5
/*    */     //   3190: aload #7
/*    */     //   3192: aload #5
/*    */     //   3194: aload #8
/*    */     //   3196: aload #5
/*    */     //   3198: aload #7
/*    */     //   3200: aload #5
/*    */     //   3202: iconst_2
/*    */     //   3203: anewarray f/JG0
/*    */     //   3206: dup
/*    */     //   3207: dup
/*    */     //   3208: aload_0
/*    */     //   3209: swap
/*    */     //   3210: iconst_0
/*    */     //   3211: aload #6
/*    */     //   3213: aastore
/*    */     //   3214: getfield cOm5 : Lf/of;
/*    */     //   3217: iconst_1
/*    */     //   3218: swap
/*    */     //   3219: aastore
/*    */     //   3220: invokevirtual AUX : ([Lf/JG0;)Lf/U90;
/*    */     //   3223: invokevirtual ee0 : (Lf/U90;)Lf/U90;
/*    */     //   3226: pop
/*    */     //   3227: iconst_2
/*    */     //   3228: anewarray f/JG0
/*    */     //   3231: dup
/*    */     //   3232: dup
/*    */     //   3233: aload_0
/*    */     //   3234: swap
/*    */     //   3235: iconst_0
/*    */     //   3236: aload #6
/*    */     //   3238: aastore
/*    */     //   3239: getfield cOm5 : Lf/of;
/*    */     //   3242: iconst_1
/*    */     //   3243: swap
/*    */     //   3244: aastore
/*    */     //   3245: invokevirtual vo0 : ([Lf/JG0;)Lf/U90;
/*    */     //   3248: invokevirtual ee0 : (Lf/U90;)Lf/U90;
/*    */     //   3251: pop
/*    */     //   3252: iconst_2
/*    */     //   3253: anewarray f/JG0
/*    */     //   3256: dup
/*    */     //   3257: dup
/*    */     //   3258: aload_0
/*    */     //   3259: swap
/*    */     //   3260: iconst_0
/*    */     //   3261: aload_1
/*    */     //   3262: aastore
/*    */     //   3263: getfield iP : Lf/W1;
/*    */     //   3266: iconst_1
/*    */     //   3267: swap
/*    */     //   3268: aastore
/*    */     //   3269: invokevirtual AUX : ([Lf/JG0;)Lf/U90;
/*    */     //   3272: invokevirtual ee0 : (Lf/U90;)Lf/U90;
/*    */     //   3275: pop
/*    */     //   3276: iconst_2
/*    */     //   3277: anewarray f/JG0
/*    */     //   3280: dup
/*    */     //   3281: dup
/*    */     //   3282: aload_0
/*    */     //   3283: swap
/*    */     //   3284: iconst_0
/*    */     //   3285: aload_1
/*    */     //   3286: aastore
/*    */     //   3287: getfield iP : Lf/W1;
/*    */     //   3290: iconst_1
/*    */     //   3291: swap
/*    */     //   3292: aastore
/*    */     //   3293: invokevirtual vo0 : ([Lf/JG0;)Lf/U90;
/*    */     //   3296: invokevirtual ee0 : (Lf/U90;)Lf/U90;
/*    */     //   3299: pop
/*    */     //   3300: invokevirtual WN : (Lf/U90;)V
/*    */     //   3303: aload #8
/*    */     //   3305: invokevirtual rK0 : (Lf/U90;)V
/*    */     //   3308: iload_2
/*    */     //   3309: ifne -> 3355
/*    */     //   3312: iload #4
/*    */     //   3314: ifne -> 3355
/*    */     //   3317: iload_3
/*    */     //   3318: ifne -> 3355
/*    */     //   3321: new f/Fy0
/*    */     //   3324: dup
/*    */     //   3325: dup2
/*    */     //   3326: ldc_w ''
/*    */     //   3329: bipush #16
/*    */     //   3331: bipush #16
/*    */     //   3333: invokespecial <init> : (Ljava/lang/String;II)V
/*    */     //   3336: ldc_w 'tooltip-button2'
/*    */     //   3339: invokevirtual Xu : (Ljava/lang/String;)V
/*    */     //   3342: iconst_0
/*    */     //   3343: invokevirtual Pb0 : (I)V
/*    */     //   3346: sipush #2809
/*    */     //   3349: invokestatic OH0 : (I)Ljava/lang/String;
/*    */     //   3352: invokevirtual Gq0 : (Ljava/lang/Object;)V
/*    */     //   3355: iload #4
/*    */     //   3357: aload_0
/*    */     //   3358: dup
/*    */     //   3359: getfield ki : Lf/Ip;
/*    */     //   3362: invokevirtual mE0 : ()Lf/g0;
/*    */     //   3365: astore_1
/*    */     //   3366: getfield ki : Lf/Ip;
/*    */     //   3369: invokevirtual d7 : ()Lf/cr0;
/*    */     //   3372: dup
/*    */     //   3373: astore_2
/*    */     //   3374: aload_0
/*    */     //   3375: aload_1
/*    */     //   3376: aload_0
/*    */     //   3377: getfield Zz0 : Lf/Zz0;
/*    */     //   3380: invokevirtual Ya : (Lf/JG0;)Lf/U90;
/*    */     //   3383: pop
/*    */     //   3384: getfield Zz0 : Lf/Zz0;
/*    */     //   3387: invokevirtual Ya : (Lf/JG0;)Lf/U90;
/*    */     //   3390: iconst_5
/*    */     //   3391: bipush #10
/*    */     //   3393: bipush #10
/*    */     //   3395: invokevirtual tA : (III)Lf/U90;
/*    */     //   3398: pop
/*    */     //   3399: ifeq -> 3419
/*    */     //   3402: aload_2
/*    */     //   3403: aload #5
/*    */     //   3405: aload_1
/*    */     //   3406: aload #5
/*    */     //   3408: invokevirtual Ya : (Lf/JG0;)Lf/U90;
/*    */     //   3411: pop
/*    */     //   3412: invokevirtual Ya : (Lf/JG0;)Lf/U90;
/*    */     //   3415: invokevirtual Em0 : ()Lf/U90;
/*    */     //   3418: pop
/*    */     //   3419: aload_0
/*    */     //   3420: dup
/*    */     //   3421: dup2
/*    */     //   3422: dup2
/*    */     //   3423: getfield ki : Lf/Ip;
/*    */     //   3426: aload_1
/*    */     //   3427: invokevirtual WN : (Lf/U90;)V
/*    */     //   3430: getfield ki : Lf/Ip;
/*    */     //   3433: aload_2
/*    */     //   3434: invokevirtual rK0 : (Lf/U90;)V
/*    */     //   3437: getfield ki : Lf/Ip;
/*    */     //   3440: invokevirtual J8 : (Lf/JG0;)V
/*    */     //   3443: getfield Tt : Lf/Ip;
/*    */     //   3446: invokevirtual J8 : (Lf/JG0;)V
/*    */     //   3449: invokestatic XU : ()Z
/*    */     //   3452: ifne -> 3463
/*    */     //   3455: aload_0
/*    */     //   3456: dup
/*    */     //   3457: getfield VF0 : Lf/Un;
/*    */     //   3460: invokevirtual J8 : (Lf/JG0;)V
/*    */     //   3463: aload_0
/*    */     //   3464: dup
/*    */     //   3465: dup
/*    */     //   3466: getfield MI0 : Lf/Un;
/*    */     //   3469: invokevirtual J8 : (Lf/JG0;)V
/*    */     //   3472: iconst_1
/*    */     //   3473: invokevirtual t2 : (I)V
/*    */     //   3476: invokestatic zp : ()Z
/*    */     //   3479: ifeq -> 3530
/*    */     //   3482: aload_0
/*    */     //   3483: dup
/*    */     //   3484: dup2
/*    */     //   3485: new f/Un
/*    */     //   3488: dup
/*    */     //   3489: aload_0
/*    */     //   3490: swap
/*    */     //   3491: dup
/*    */     //   3492: invokespecial <init> : ()V
/*    */     //   3495: putfield hw0 : Lf/Un;
/*    */     //   3498: <illegal opcode> run : ()Ljava/lang/Runnable;
/*    */     //   3503: invokevirtual tW : (Ljava/lang/Runnable;)V
/*    */     //   3506: getfield hw0 : Lf/Un;
/*    */     //   3509: ldc_w 'mobile-share-icon'
/*    */     //   3512: invokevirtual Xu : (Ljava/lang/String;)V
/*    */     //   3515: getfield hw0 : Lf/Un;
/*    */     //   3518: ldc_w ''
/*    */     //   3521: invokevirtual s6 : (Ljava/lang/String;)V
/*    */     //   3524: getfield hw0 : Lf/Un;
/*    */     //   3527: invokevirtual J8 : (Lf/JG0;)V
/*    */     //   3530: return
/*    */     // Line number table:
/*    */     //   Java source line number -> byte code offset
/*    */     //   #1	-> 2025
/*  1 */     //   #2	-> 2038 } private void L20(H10 paramH10) { R8 r8 = km.u4; int i = this.j7; boolean bool = this.Y70; this.e20
/*  2 */       .W3(new Vc(i, bool, paramH10)); } private void lo(H10 paramH10) { R8 r8 = km.u4; int i = this.j7; boolean bool = this.Y70; this.e20.W3(new Vc(i, bool, paramH10)); }
/*    */   private void NG0() { this.HP = qr[this.iP.Wa0.go]; }
/*  4 */   private void fL(UX paramUX) { byte b = paramUX.Ii; Dn0 dn0; (dn0 = this.Vh).QL0[dn0.wh0.gw0] = b; } public static uK fF(Y paramY) { String str = paramY.Bp0.UQ(paramY.Lh.Nj);
/*    */ 
/*    */     
/*  7 */     short s = paramY.Bp0.c3.Lk;
/*    */     
/*  9 */     byte b = paramY.Lh.Nj;
/* 10 */     int i = paramY.Lh.Wy; return new uK(str, s, b, i); } private void b8(int paramInt) { if (paramInt > 0 && !this.jA0) { short s = -1; byte b = -1; int i; if ((i = (this.Lc0[paramInt]).Wa0.go) >= 0) { s = ((uK)this.J5[paramInt].c90(i)).COm4; b = ((uK)this.J5[paramInt].c90(i)).ce0; }  paramInt--; if (s < 0) { this.yq0[paramInt] = s; this.qU[paramInt + 1].wI0(false); if (km.XU()) Zt();  } else { wc wc; if ((wc = Vp0.cOm1(paramInt).fM0(s)) != null) { boolean bool; Fy0 fy0 = this.qU[paramInt + 1]; if (wc.XF0() && this.z70) { bool = true; } else { bool = false; }  fy0.wI0(bool); if (!this.Yb0 && !this.z70) this.E10[paramInt] = b;  byte[] arrayOfByte; if (this.z70 && wc.XF0() && (arrayOfByte = this.E10)[paramInt] < 0) arrayOfByte[paramInt] = (byte)xi0.qX(UX.jj.length);  this.yq0[paramInt] = s; }  }  }  } private void mg(byte paramByte) { if (this.Tt != null) { wc wc; if ((wc = Vp0.cOm1(paramByte).fM0(this.yq0[paramByte])) != null && wc.XF0()) { this.Pb0 = paramByte; byte b = this.E10[paramByte]; short s = this.yq0[paramByte]; this.Vh.X7(b, wc.Hl0, s); this.Tt.wI0(true); this.VF0.wI0(true); this.MI0.wI0(false); this.ki.wI0(false); }  p40(); }  } private void X6() { int i; if (this.ar0 == (i = this.Ih0.Wa0.go)) return;  this.ar0 = (byte)i; Vp0[] arrayOfVp0; int j; byte b1; for (this.jA0 = true, this.yq0 = new short[] { -1, -1, 3, 2, -1, -1, 5, -1, 0, 0, 0, 0 }, this.E10 = new byte[] { 0, 0, 0, 0, 0, 0, 0, 0, 0, 0, 0, 0 }, j = (arrayOfVp0 = Vp0.Jo).length, b1 = 0; b1 < j; ) { Vp0 vp0; if ((vp0 = arrayOfVp0[b1]) != Vp0.Pa0) { ArrayList<Short> arrayList; this(); qw0 qw0; (qw0 = vp0.aU).getClass(); for (Iterator iterator = (new iL(qw0)).iterator(); ((DA0)iterator).hasNext();) { if (((wc = (wc)((Ke)iterator).q00()).mv0() < 0 || wc.mv0() == this.ar0) && wc.Wk0 < 0 && !wc.aW()) arrayList
/*    */               
/* 12 */               .add(Short.valueOf(wc.Lk));  }  if (arrayList.size() > 0)
/* 13 */         { byte b2 = vp0.gw0;
/* 14 */           this.yq0[b2] = ((Short)arrayList.get(xi0.A90(0, arrayList.size() - 1))).shortValue(); UX[] arrayOfUX; this.E10[vp0
/* 15 */               .gw0] = 
/* 16 */             (byte)xi0.qX((arrayOfUX = UX.jj).length);
/*    */           
/* 18 */           if (!vp0.Ko(this.yq0[vp0.gw0])) { this.E10[vp0
/* 19 */                 .gw0] = 0; }
/* 20 */           else { this.E10[vp0
/* 21 */                 .gw0] = 
/* 22 */               (byte)xi0.qX(arrayOfUX.length); }  }  }  b1++; }  byte b; for (this.package = this.yq0, this.GG0 = this.E10, b = 0; b < this.qU.length; ) { if (b > 0) { OZ oZ; j = (byte)(b - 1); this((Object[])W0(Vp0.cOm1(j))); this.J5[b] = oZ; this.Lc0[b].rk0(this.J5[b]); }  W1 w1 = this.Lc0[b]; if (this.J5[b].pu() > 1) { b1 = 1; } else { b1 = 0; }  w1.sk0(b1); b = (byte)(b + 1); }  z10(); this.jA0 = false; } public static boolean D1(Vp0 paramVp0, V6 paramV6, Y paramY) { wc wc; if ((wc = paramY.Bp0.c3).Hl0 == paramVp0) { int i; if (wc == null) { i = 0; } else { i = wc.Lk & 0xFFFF | (paramY.Lh.Nj & 0xFF) << 16; }  if (paramV6.uX(i)); }  return false; } public final uK[] W0(Vp0 paramVp0) { // Byte code:
/*    */     //   0: aload_1
/*    */     //   1: new java/util/ArrayList
/*    */     //   4: dup
/*    */     //   5: astore_2
/*    */     //   6: invokespecial <init> : ()V
/*    */     //   9: getfield gz : Z
/*    */     //   12: ifeq -> 22
/*    */     //   15: aload_0
/*    */     //   16: getfield z70 : Z
/*    */     //   19: ifeq -> 43
/*    */     //   22: aload_1
/*    */     //   23: getfield dM : Z
/*    */     //   26: ifeq -> 62
/*    */     //   29: aload_0
/*    */     //   30: getfield cOm3 : Z
/*    */     //   33: ifne -> 43
/*    */     //   36: aload_0
/*    */     //   37: getfield z70 : Z
/*    */     //   40: ifeq -> 62
/*    */     //   43: aload_2
/*    */     //   44: new f/uK
/*    */     //   47: dup
/*    */     //   48: sipush #2803
/*    */     //   51: invokestatic OH0 : (I)Ljava/lang/String;
/*    */     //   54: iconst_m1
/*    */     //   55: invokespecial <init> : (Ljava/lang/String;S)V
/*    */     //   58: invokevirtual add : (Ljava/lang/Object;)Z
/*    */     //   61: pop
/*    */     //   62: aload_0
/*    */     //   63: getfield cOm3 : Z
/*    */     //   66: ifne -> 634
/*    */     //   69: aload_0
/*    */     //   70: getfield Yb0 : Z
/*    */     //   73: ifne -> 634
/*    */     //   76: aload_0
/*    */     //   77: getfield z70 : Z
/*    */     //   80: ifeq -> 86
/*    */     //   83: goto -> 634
/*    */     //   86: aload_1
/*    */     //   87: iconst_0
/*    */     //   88: istore_3
/*    */     //   89: getfield aU : Lf/qw0;
/*    */     //   92: dup
/*    */     //   93: astore #4
/*    */     //   95: invokevirtual getClass : ()Ljava/lang/Class;
/*    */     //   98: pop
/*    */     //   99: new f/iL
/*    */     //   102: dup
/*    */     //   103: aload #4
/*    */     //   105: invokespecial <init> : (Lf/qw0;)V
/*    */     //   108: invokevirtual iterator : ()Ljava/util/Iterator;
/*    */     //   111: astore #4
/*    */     //   113: aload #4
/*    */     //   115: checkcast f/DA0
/*    */     //   118: invokevirtual hasNext : ()Z
/*    */     //   121: ifeq -> 560
/*    */     //   124: aload_0
/*    */     //   125: aload #4
/*    */     //   127: checkcast f/Ke
/*    */     //   130: invokevirtual q00 : ()Ljava/lang/Object;
/*    */     //   133: checkcast f/wc
/*    */     //   136: astore #5
/*    */     //   138: getfield yq0 : [S
/*    */     //   141: aload_1
/*    */     //   142: getfield gw0 : B
/*    */     //   145: saload
/*    */     //   146: aload #5
/*    */     //   148: getfield Lk : S
/*    */     //   151: dup
/*    */     //   152: istore #6
/*    */     //   154: if_icmpne -> 271
/*    */     //   157: aload #5
/*    */     //   159: new f/uK
/*    */     //   162: astore #7
/*    */     //   164: getfield Hl0 : Lf/Vp0;
/*    */     //   167: getfield gw0 : B
/*    */     //   170: sipush #1000
/*    */     //   173: imul
/*    */     //   174: sipush #20000
/*    */     //   177: iadd
/*    */     //   178: iload #6
/*    */     //   180: ldc_w 65535
/*    */     //   183: iand
/*    */     //   184: iadd
/*    */     //   185: getstatic f/Ml0.nW : Lf/Ut0;
/*    */     //   188: swap
/*    */     //   189: invokevirtual return : (I)Z
/*    */     //   192: ifne -> 205
/*    */     //   195: aload #5
/*    */     //   197: getfield bG : Ljava/lang/String;
/*    */     //   200: astore #6
/*    */     //   202: goto -> 236
/*    */     //   205: aload #5
/*    */     //   207: getfield Hl0 : Lf/Vp0;
/*    */     //   210: getfield gw0 : B
/*    */     //   213: sipush #1000
/*    */     //   216: imul
/*    */     //   217: sipush #20000
/*    */     //   220: iadd
/*    */     //   221: aload #5
/*    */     //   223: getfield Lk : S
/*    */     //   226: ldc_w 65535
/*    */     //   229: iand
/*    */     //   230: iadd
/*    */     //   231: invokestatic OH0 : (I)Ljava/lang/String;
/*    */     //   234: astore #6
/*    */     //   236: aload_2
/*    */     //   237: aload #7
/*    */     //   239: dup
/*    */     //   240: aload #6
/*    */     //   242: aload_0
/*    */     //   243: aload #5
/*    */     //   245: getfield Lk : S
/*    */     //   248: istore #5
/*    */     //   250: getfield E10 : [B
/*    */     //   253: aload_1
/*    */     //   254: getfield gw0 : B
/*    */     //   257: baload
/*    */     //   258: iload #5
/*    */     //   260: swap
/*    */     //   261: invokespecial <init> : (Ljava/lang/String;SB)V
/*    */     //   264: invokevirtual add : (Ljava/lang/Object;)Z
/*    */     //   267: pop
/*    */     //   268: goto -> 113
/*    */     //   271: aload #5
/*    */     //   273: invokevirtual aW : ()Z
/*    */     //   276: ifeq -> 389
/*    */     //   279: aload #5
/*    */     //   281: new f/uK
/*    */     //   284: astore #6
/*    */     //   286: getfield Hl0 : Lf/Vp0;
/*    */     //   289: getfield gw0 : B
/*    */     //   292: sipush #1000
/*    */     //   295: imul
/*    */     //   296: sipush #20000
/*    */     //   299: iadd
/*    */     //   300: aload #5
/*    */     //   302: getfield Lk : S
/*    */     //   305: ldc_w 65535
/*    */     //   308: iand
/*    */     //   309: iadd
/*    */     //   310: getstatic f/Ml0.nW : Lf/Ut0;
/*    */     //   313: swap
/*    */     //   314: invokevirtual return : (I)Z
/*    */     //   317: ifne -> 330
/*    */     //   320: aload #5
/*    */     //   322: getfield bG : Ljava/lang/String;
/*    */     //   325: astore #7
/*    */     //   327: goto -> 361
/*    */     //   330: aload #5
/*    */     //   332: getfield Hl0 : Lf/Vp0;
/*    */     //   335: getfield gw0 : B
/*    */     //   338: sipush #1000
/*    */     //   341: imul
/*    */     //   342: sipush #20000
/*    */     //   345: iadd
/*    */     //   346: aload #5
/*    */     //   348: getfield Lk : S
/*    */     //   351: ldc_w 65535
/*    */     //   354: iand
/*    */     //   355: iadd
/*    */     //   356: invokestatic OH0 : (I)Ljava/lang/String;
/*    */     //   359: astore #7
/*    */     //   361: aload_2
/*    */     //   362: aload #6
/*    */     //   364: dup
/*    */     //   365: aload #5
/*    */     //   367: getfield Lk : S
/*    */     //   370: aload #7
/*    */     //   372: swap
/*    */     //   373: invokespecial <init> : (Ljava/lang/String;S)V
/*    */     //   376: iconst_1
/*    */     //   377: putfield VA0 : Z
/*    */     //   380: aload #6
/*    */     //   382: invokevirtual add : (Ljava/lang/Object;)Z
/*    */     //   385: pop
/*    */     //   386: goto -> 113
/*    */     //   389: getstatic f/km.u4 : Lf/R8;
/*    */     //   392: dup
/*    */     //   393: astore #6
/*    */     //   395: ifnull -> 113
/*    */     //   398: aload #6
/*    */     //   400: getfield fF0 : Lf/BF;
/*    */     //   403: iconst_4
/*    */     //   404: sipush #2409
/*    */     //   407: invokevirtual y5 : (BS)Z
/*    */     //   410: ifeq -> 113
/*    */     //   413: aload_1
/*    */     //   414: getstatic f/Vp0.bG : Lf/Vp0;
/*    */     //   417: if_acmpne -> 430
/*    */     //   420: aload #5
/*    */     //   422: getfield Lk : S
/*    */     //   425: bipush #39
/*    */     //   427: if_icmpeq -> 447
/*    */     //   430: aload_1
/*    */     //   431: getstatic f/Vp0.Sz0 : Lf/Vp0;
/*    */     //   434: if_acmpne -> 113
/*    */     //   437: aload #5
/*    */     //   439: getfield Lk : S
/*    */     //   442: bipush #8
/*    */     //   444: if_icmpne -> 113
/*    */     //   447: aload #5
/*    */     //   449: aload_2
/*    */     //   450: invokevirtual clear : ()V
/*    */     //   453: new f/uK
/*    */     //   456: astore_3
/*    */     //   457: getfield Hl0 : Lf/Vp0;
/*    */     //   460: getfield gw0 : B
/*    */     //   463: sipush #1000
/*    */     //   466: imul
/*    */     //   467: sipush #20000
/*    */     //   470: iadd
/*    */     //   471: aload #5
/*    */     //   473: getfield Lk : S
/*    */     //   476: ldc_w 65535
/*    */     //   479: iand
/*    */     //   480: iadd
/*    */     //   481: getstatic f/Ml0.nW : Lf/Ut0;
/*    */     //   484: swap
/*    */     //   485: invokevirtual return : (I)Z
/*    */     //   488: ifne -> 501
/*    */     //   491: aload #5
/*    */     //   493: getfield bG : Ljava/lang/String;
/*    */     //   496: astore #6
/*    */     //   498: goto -> 532
/*    */     //   501: aload #5
/*    */     //   503: getfield Hl0 : Lf/Vp0;
/*    */     //   506: getfield gw0 : B
/*    */     //   509: sipush #1000
/*    */     //   512: imul
/*    */     //   513: sipush #20000
/*    */     //   516: iadd
/*    */     //   517: aload #5
/*    */     //   519: getfield Lk : S
/*    */     //   522: ldc_w 65535
/*    */     //   525: iand
/*    */     //   526: iadd
/*    */     //   527: invokestatic OH0 : (I)Ljava/lang/String;
/*    */     //   530: astore #6
/*    */     //   532: aload_2
/*    */     //   533: aload_3
/*    */     //   534: dup
/*    */     //   535: aload #5
/*    */     //   537: getfield Lk : S
/*    */     //   540: aload #6
/*    */     //   542: swap
/*    */     //   543: invokespecial <init> : (Ljava/lang/String;S)V
/*    */     //   546: iconst_1
/*    */     //   547: putfield VA0 : Z
/*    */     //   550: aload_3
/*    */     //   551: invokevirtual add : (Ljava/lang/Object;)Z
/*    */     //   554: pop
/*    */     //   555: iconst_1
/*    */     //   556: istore_3
/*    */     //   557: goto -> 113
/*    */     //   560: iload_3
/*    */     //   561: ifne -> 901
/*    */     //   564: aload_2
/*    */     //   565: new f/V6
/*    */     //   568: dup
/*    */     //   569: astore_0
/*    */     //   570: invokespecial <init> : ()V
/*    */     //   573: getstatic f/km.u4 : Lf/R8;
/*    */     //   576: getstatic f/yM.r4 : Lf/yM;
/*    */     //   579: pop
/*    */     //   580: getfield Fe : [Lf/zr0;
/*    */     //   583: iconst_1
/*    */     //   584: aaload
/*    */     //   585: getstatic f/Hu0.w2 : Lf/Hu0;
/*    */     //   588: invokevirtual Qw0 : (Lf/Hu0;)[Lf/Y;
/*    */     //   591: invokestatic stream : ([Ljava/lang/Object;)Ljava/util/stream/Stream;
/*    */     //   594: aload_1
/*    */     //   595: aload_0
/*    */     //   596: <illegal opcode> test : (Lf/Vp0;Lf/V6;)Ljava/util/function/Predicate;
/*    */     //   601: invokeinterface filter : (Ljava/util/function/Predicate;)Ljava/util/stream/Stream;
/*    */     //   606: <illegal opcode> apply : ()Ljava/util/function/Function;
/*    */     //   611: invokeinterface map : (Ljava/util/function/Function;)Ljava/util/stream/Stream;
/*    */     //   616: invokestatic toList : ()Ljava/util/stream/Collector;
/*    */     //   619: invokeinterface collect : (Ljava/util/stream/Collector;)Ljava/lang/Object;
/*    */     //   624: checkcast java/util/Collection
/*    */     //   627: invokevirtual addAll : (Ljava/util/Collection;)Z
/*    */     //   630: pop
/*    */     //   631: goto -> 901
/*    */     //   634: aload_1
/*    */     //   635: getfield aU : Lf/qw0;
/*    */     //   638: dup
/*    */     //   639: astore_3
/*    */     //   640: invokevirtual getClass : ()Ljava/lang/Class;
/*    */     //   643: pop
/*    */     //   644: new f/iL
/*    */     //   647: dup
/*    */     //   648: aload_3
/*    */     //   649: invokespecial <init> : (Lf/qw0;)V
/*    */     //   652: invokevirtual iterator : ()Ljava/util/Iterator;
/*    */     //   655: astore_3
/*    */     //   656: aload_3
/*    */     //   657: checkcast f/DA0
/*    */     //   660: invokevirtual hasNext : ()Z
/*    */     //   663: ifeq -> 901
/*    */     //   666: aload_0
/*    */     //   667: aload_3
/*    */     //   668: checkcast f/Ke
/*    */     //   671: invokevirtual q00 : ()Ljava/lang/Object;
/*    */     //   674: checkcast f/wc
/*    */     //   677: astore #4
/*    */     //   679: getfield yq0 : [S
/*    */     //   682: aload_1
/*    */     //   683: getfield gw0 : B
/*    */     //   686: saload
/*    */     //   687: aload #4
/*    */     //   689: getfield Lk : S
/*    */     //   692: if_icmpeq -> 725
/*    */     //   695: aload #4
/*    */     //   697: getfield Wk0 : S
/*    */     //   700: dup
/*    */     //   701: istore #5
/*    */     //   703: ifle -> 713
/*    */     //   706: aload_0
/*    */     //   707: getfield z70 : Z
/*    */     //   710: ifeq -> 725
/*    */     //   713: iload #5
/*    */     //   715: ifge -> 656
/*    */     //   718: aload_0
/*    */     //   719: getfield z70 : Z
/*    */     //   722: ifeq -> 656
/*    */     //   725: aload #4
/*    */     //   727: invokevirtual mv0 : ()B
/*    */     //   730: iflt -> 748
/*    */     //   733: aload #4
/*    */     //   735: invokevirtual mv0 : ()B
/*    */     //   738: aload_0
/*    */     //   739: getfield ar0 : B
/*    */     //   742: if_icmpeq -> 748
/*    */     //   745: goto -> 656
/*    */     //   748: aload #4
/*    */     //   750: getfield Wk0 : S
/*    */     //   753: ifle -> 759
/*    */     //   756: goto -> 656
/*    */     //   759: aload_0
/*    */     //   760: getfield z70 : Z
/*    */     //   763: ifne -> 773
/*    */     //   766: aload_0
/*    */     //   767: getfield Yb0 : Z
/*    */     //   770: ifeq -> 784
/*    */     //   773: aload #4
/*    */     //   775: invokevirtual aW : ()Z
/*    */     //   778: ifeq -> 784
/*    */     //   781: goto -> 656
/*    */     //   784: aload #4
/*    */     //   786: new f/uK
/*    */     //   789: astore #5
/*    */     //   791: getfield Hl0 : Lf/Vp0;
/*    */     //   794: getfield gw0 : B
/*    */     //   797: sipush #1000
/*    */     //   800: imul
/*    */     //   801: sipush #20000
/*    */     //   804: iadd
/*    */     //   805: aload #4
/*    */     //   807: getfield Lk : S
/*    */     //   810: ldc_w 65535
/*    */     //   813: iand
/*    */     //   814: iadd
/*    */     //   815: getstatic f/Ml0.nW : Lf/Ut0;
/*    */     //   818: swap
/*    */     //   819: invokevirtual return : (I)Z
/*    */     //   822: ifne -> 835
/*    */     //   825: aload #4
/*    */     //   827: getfield bG : Ljava/lang/String;
/*    */     //   830: astore #6
/*    */     //   832: goto -> 866
/*    */     //   835: aload #4
/*    */     //   837: getfield Hl0 : Lf/Vp0;
/*    */     //   840: getfield gw0 : B
/*    */     //   843: sipush #1000
/*    */     //   846: imul
/*    */     //   847: sipush #20000
/*    */     //   850: iadd
/*    */     //   851: aload #4
/*    */     //   853: getfield Lk : S
/*    */     //   856: ldc_w 65535
/*    */     //   859: iand
/*    */     //   860: iadd
/*    */     //   861: invokestatic OH0 : (I)Ljava/lang/String;
/*    */     //   864: astore #6
/*    */     //   866: aload_2
/*    */     //   867: aload #5
/*    */     //   869: dup
/*    */     //   870: aload #6
/*    */     //   872: aload_0
/*    */     //   873: aload #4
/*    */     //   875: getfield Lk : S
/*    */     //   878: istore #4
/*    */     //   880: getfield E10 : [B
/*    */     //   883: aload_1
/*    */     //   884: getfield gw0 : B
/*    */     //   887: baload
/*    */     //   888: iload #4
/*    */     //   890: swap
/*    */     //   891: invokespecial <init> : (Ljava/lang/String;SB)V
/*    */     //   894: invokevirtual add : (Ljava/lang/Object;)Z
/*    */     //   897: pop
/*    */     //   898: goto -> 656
/*    */     //   901: aload_2
/*    */     //   902: iconst_0
/*    */     //   903: anewarray f/uK
/*    */     //   906: invokevirtual toArray : ([Ljava/lang/Object;)[Ljava/lang/Object;
/*    */     //   909: checkcast [Lf/uK;
/*    */     //   912: dup
/*    */     //   913: getstatic f/Ia.Xd : Ljava/util/Comparator;
/*    */     //   916: invokestatic sort : ([Ljava/lang/Object;Ljava/util/Comparator;)V
/*    */     //   919: areturn
/*    */     // Line number table:
/*    */     //   Java source line number -> byte code offset
/*    */     //   #1	-> 9
/*    */     //   #2	-> 16
/*    */     //   #3	-> 23
/*    */     //   #4	-> 30
/*    */     //   #5	-> 89
/*    */     //   #6	-> 95
/*    */     //   #7	-> 99
/*    */     //   #8	-> 108
/*    */     //   #9	-> 142
/*    */     //   #10	-> 145
/*    */     //   #11	-> 148
/*    */     //   #12	-> 159
/*    */     //   #13	-> 164
/*    */     //   #14	-> 167
/*    */     //   #15	-> 185
/*    */     //   #16	-> 189
/*    */     //   #17	-> 197
/*    */     //   #18	-> 207
/*    */     //   #19	-> 210
/*    */     //   #20	-> 223
/*    */     //   #21	-> 231
/*    */     //   #22	-> 245
/*    */     //   #23	-> 250
/*    */     //   #24	-> 254
/*    */     //   #25	-> 257
/*    */     //   #26	-> 286
/*    */     //   #27	-> 289
/*    */     //   #28	-> 302
/*    */     //   #29	-> 310
/*    */     //   #30	-> 314
/*    */     //   #31	-> 322
/*    */     //   #32	-> 332
/*    */     //   #33	-> 335
/*    */     //   #34	-> 348
/*    */     //   #35	-> 356
/*    */     //   #36	-> 367
/*    */     //   #37	-> 373
/*    */     //   #38	-> 377
/*    */     //   #39	-> 382
/*    */     //   #40	-> 400
/*    */     //   #41	-> 407
/*    */     //   #42	-> 422
/*    */     //   #43	-> 431
/*    */     //   #44	-> 439
/*    */     //   #45	-> 450
/*    */     //   #46	-> 457
/*    */     //   #47	-> 460
/*    */     //   #48	-> 473
/*    */     //   #49	-> 481
/*    */     //   #50	-> 485
/*    */     //   #51	-> 493
/*    */     //   #52	-> 503
/*    */     //   #53	-> 506
/*    */     //   #54	-> 519
/*    */     //   #55	-> 527
/*    */     //   #56	-> 537
/*    */     //   #57	-> 543
/*    */     //   #58	-> 547
/*    */     //   #59	-> 551
/*    */     //   #60	-> 580
/*    */     //   #61	-> 584
/*    */     //   #62	-> 585
/*    */     //   #63	-> 635
/*    */     //   #64	-> 640
/*    */     //   #65	-> 644
/*    */     //   #66	-> 652
/*    */     //   #67	-> 683
/*    */     //   #68	-> 686
/*    */     //   #69	-> 689
/*    */     //   #70	-> 697
/*    */     //   #71	-> 707
/*    */     //   #72	-> 750
/*    */     //   #73	-> 760
/*    */     //   #74	-> 791
/*    */     //   #75	-> 794
/*    */     //   #76	-> 807
/*    */     //   #77	-> 815
/*    */     //   #78	-> 819
/*    */     //   #79	-> 827
/*    */     //   #80	-> 837
/*    */     //   #81	-> 840
/*    */     //   #82	-> 853
/*    */     //   #83	-> 861
/*    */     //   #84	-> 875
/*    */     //   #85	-> 880
/*    */     //   #86	-> 884
/* 22 */     //   #87	-> 887 } public final void d40() { if (km.XU()) { ME(0, 0); Tm(km.wI0.dG(), km.wI0.k1()); }  this.ki.mM(); super.d40(); if (this.Yb0 || this.z70) { if (km.XU()) { this.Tt.Tm(km.wI0.dG(), km.wI0.k1()); } else { Ip ip; if ((ip = this.Tt).dP) { int j = this.xY; ip.Tm(j, this.HC); } else if (!km.XU()) { uh0(500, 540); ME(km.wI0.dG() / 2 - this.xY / 2, km.wI0.k1() / 2 - this.HC / 2); }  }  this.VF0.Tm(150, 50); int i = this.Kd; this.VF0.ME(this.xY / 2 + i - this.VF0.xY / 2, this.er0 + 200); }  if (km.XU()) { this.MI0.mM(); this.MI0.QJ0(et.t9, -68, 0); Un un; if ((un = this.hw0) != null) { un.mM(); this.hw0.js0(et.dw0); }  } else { this.MI0.Tm(qF() - this.Zz0.xY, 50); this.MI0
/*    */ 
/*    */ 
/*    */ 
/*    */ 
/*    */         
/* 28 */         .ME(this.Kd + this.Zz0.xY, mD() - this.MI0.HC); }
/* 29 */      p40(); if (!km.XU()) qB0(et.Wi0);  }
/*    */ 
/*    */   
/*    */   public final byte eC(Vp0 paramVp0) {
/*    */     qw0 qw0;
/*    */     (qw0 = paramVp0.aU).getClass();
/*    */     for (Iterator<wc> iterator = (new iL(qw0)).iterator(); iterator.hasNext();) {
/*    */       if ((wc = iterator.next()).Lk == this.yq0[paramVp0.gw0]) {
/*    */         if (wc.XF0())
/*    */           return this.E10[paramVp0.gw0]; 
/*    */         return -1;
/*    */       } 
/*    */     } 
/*    */     return -1;
/*    */   }
/*    */   
/*    */   public final void z10() {
/*    */     for (byte b = 1; b < 13; ) {
/*    */       short s = this.package[i];
/*    */       int i = this.GG0[i];
/*    */       Vp0 vp0;
/*    */       if ((((vp0 = Vp0.cOm1(i = b - 1)).gz && !this.z70) || (vp0.dM && (this.cOm3 || this.z70))) && s == -1) {
/*    */         this.Lc0[b].Z30(0);
/*    */       } else {
/*    */         wc wc;
/*    */         if ((wc = vp0.fM0(s)) != null) {
/*    */           boolean bool;
/*    */           Fy0 fy0 = this.qU[b];
/*    */           if (wc.XF0() && this.z70) {
/*    */             bool = true;
/*    */           } else {
/*    */             bool = false;
/*    */           } 
/*    */           fy0.wI0(bool);
/*    */           for (byte b1 = 0; b1 < this.J5[b].pu(); ) {
/*    */             if (s == ((uK)this.J5[b].c90(b1)).COm4 && (i == ((uK)this.J5[b].c90(b1)).ce0 || ((uK)this.J5[b].c90(b1)).ce0 == -1))
/*    */               this.Lc0[b].Z30(b1); 
/*    */             b1++;
/*    */           } 
/*    */         } 
/*    */       } 
/*    */       b++;
/*    */     } 
/*    */   }
/*    */   
/*    */   public final void p40() {
/*    */     byte b;
/*    */     int i = 640;
/*    */     char c = 'ĉ';
/*    */     if (km.XU()) {
/*    */       b = 520;
/*    */       if (this.Yb0 || this.z70)
/*    */         c = 'Ɵ'; 
/*    */     } else {
/*    */       i = 390;
/*    */       if (this.Tt.dP) {
/*    */         c = 'Ļ';
/*    */         b = 350;
/*    */         i = this.xY / 2 - 175;
/*    */       } else if (this.Yb0) {
/*    */         i = 410;
/*    */         c = 'Ļ';
/*    */         b = 200;
/*    */       } else {
/*    */         c = 'Ɵ';
/*    */         b = 120;
/*    */       } 
/*    */     } 
/*    */     if (this.Tt.dP)
/*    */       i = this.xY / 2 - b / 2 - this.L2.xY / 2; 
/*    */     this.L2.ME(this.Kd + i, this.er0 + c);
/*    */     this.Tz0.ME(this.Kd + i + b, this.er0 + c);
/*    */   }
/*    */   
/*    */   public final W1 H1() {
/*    */     if (this.rE0 < 0)
/*    */       this.rE0 = 0; 
/*    */     W1[] arrayOfW1;
/*    */     if (this.rE0 >= (arrayOfW1 = this.Lc0).length)
/*    */       this.rE0 = arrayOfW1.length - 1; 
/*    */     return arrayOfW1[this.rE0];
/*    */   }
/*    */   
/*    */   public final void B8() {
/*    */     // Byte code:
/*    */     //   0: aload_0
/*    */     //   1: new f/H10
/*    */     //   4: dup
/*    */     //   5: dup2
/*    */     //   6: dup2
/*    */     //   7: dup2
/*    */     //   8: dup2
/*    */     //   9: astore_1
/*    */     //   10: aload_0
/*    */     //   11: dup
/*    */     //   12: dup
/*    */     //   13: dup2
/*    */     //   14: dup2
/*    */     //   15: dup2
/*    */     //   16: dup2
/*    */     //   17: dup2
/*    */     //   18: dup2
/*    */     //   19: dup2
/*    */     //   20: aload_1
/*    */     //   21: invokespecial <init> : ()V
/*    */     //   24: getfield Lc0 : [Lf/W1;
/*    */     //   27: iconst_0
/*    */     //   28: aaload
/*    */     //   29: getfield Wa0 : Lf/A60;
/*    */     //   32: getfield go : I
/*    */     //   35: i2b
/*    */     //   36: istore_2
/*    */     //   37: getfield yq0 : [S
/*    */     //   40: getstatic f/Vp0.MP : Lf/Vp0;
/*    */     //   43: dup
/*    */     //   44: astore_3
/*    */     //   45: getfield gw0 : B
/*    */     //   48: saload
/*    */     //   49: istore #4
/*    */     //   51: aload_3
/*    */     //   52: invokevirtual eC : (Lf/Vp0;)B
/*    */     //   55: istore #5
/*    */     //   57: getfield yq0 : [S
/*    */     //   60: getstatic f/Vp0.K7 : Lf/Vp0;
/*    */     //   63: dup
/*    */     //   64: astore #6
/*    */     //   66: getfield gw0 : B
/*    */     //   69: saload
/*    */     //   70: istore #7
/*    */     //   72: aload #6
/*    */     //   74: invokevirtual eC : (Lf/Vp0;)B
/*    */     //   77: istore #8
/*    */     //   79: getfield yq0 : [S
/*    */     //   82: getstatic f/Vp0.Pa0 : Lf/Vp0;
/*    */     //   85: dup
/*    */     //   86: astore #9
/*    */     //   88: getfield gw0 : B
/*    */     //   91: saload
/*    */     //   92: istore #10
/*    */     //   94: aload #9
/*    */     //   96: invokevirtual eC : (Lf/Vp0;)B
/*    */     //   99: istore #11
/*    */     //   101: getfield yq0 : [S
/*    */     //   104: getstatic f/Vp0.CR : Lf/Vp0;
/*    */     //   107: dup
/*    */     //   108: astore #12
/*    */     //   110: getfield gw0 : B
/*    */     //   113: saload
/*    */     //   114: istore #13
/*    */     //   116: aload #12
/*    */     //   118: invokevirtual eC : (Lf/Vp0;)B
/*    */     //   121: istore #14
/*    */     //   123: getfield yq0 : [S
/*    */     //   126: getstatic f/Vp0.Sz0 : Lf/Vp0;
/*    */     //   129: dup
/*    */     //   130: astore #15
/*    */     //   132: getfield gw0 : B
/*    */     //   135: saload
/*    */     //   136: istore #16
/*    */     //   138: aload #15
/*    */     //   140: invokevirtual eC : (Lf/Vp0;)B
/*    */     //   143: istore #17
/*    */     //   145: getfield yq0 : [S
/*    */     //   148: getstatic f/Vp0.rK : Lf/Vp0;
/*    */     //   151: dup
/*    */     //   152: astore #18
/*    */     //   154: getfield gw0 : B
/*    */     //   157: saload
/*    */     //   158: istore #19
/*    */     //   160: aload #18
/*    */     //   162: invokevirtual eC : (Lf/Vp0;)B
/*    */     //   165: istore #20
/*    */     //   167: getfield yq0 : [S
/*    */     //   170: getstatic f/Vp0.sg0 : Lf/Vp0;
/*    */     //   173: dup
/*    */     //   174: astore #21
/*    */     //   176: getfield gw0 : B
/*    */     //   179: saload
/*    */     //   180: istore #22
/*    */     //   182: aload #21
/*    */     //   184: invokevirtual eC : (Lf/Vp0;)B
/*    */     //   187: istore #23
/*    */     //   189: getfield yq0 : [S
/*    */     //   192: getstatic f/Vp0.M9 : Lf/Vp0;
/*    */     //   195: dup
/*    */     //   196: astore #24
/*    */     //   198: getfield gw0 : B
/*    */     //   201: saload
/*    */     //   202: istore #25
/*    */     //   204: aload #24
/*    */     //   206: invokevirtual eC : (Lf/Vp0;)B
/*    */     //   209: istore #26
/*    */     //   211: iload_2
/*    */     //   212: putfield goto : B
/*    */     //   215: iload #5
/*    */     //   217: aload_3
/*    */     //   218: iload #4
/*    */     //   220: invokevirtual cq0 : (BLf/Vp0;S)V
/*    */     //   223: iload #8
/*    */     //   225: aload #6
/*    */     //   227: iload #7
/*    */     //   229: invokevirtual cq0 : (BLf/Vp0;S)V
/*    */     //   232: iload #11
/*    */     //   234: aload #9
/*    */     //   236: iload #10
/*    */     //   238: invokevirtual cq0 : (BLf/Vp0;S)V
/*    */     //   241: iload #14
/*    */     //   243: aload #12
/*    */     //   245: iload #13
/*    */     //   247: invokevirtual cq0 : (BLf/Vp0;S)V
/*    */     //   250: iload #17
/*    */     //   252: aload #15
/*    */     //   254: iload #16
/*    */     //   256: invokevirtual cq0 : (BLf/Vp0;S)V
/*    */     //   259: iload #20
/*    */     //   261: aload #18
/*    */     //   263: iload #19
/*    */     //   265: invokevirtual cq0 : (BLf/Vp0;S)V
/*    */     //   268: iload #23
/*    */     //   270: aload #21
/*    */     //   272: iload #22
/*    */     //   274: invokevirtual cq0 : (BLf/Vp0;S)V
/*    */     //   277: iload #26
/*    */     //   279: aload #24
/*    */     //   281: iload #25
/*    */     //   283: invokevirtual cq0 : (BLf/Vp0;S)V
/*    */     //   286: getfield Yb0 : Z
/*    */     //   289: ifeq -> 397
/*    */     //   292: getstatic f/km.mI0 : Lf/P1;
/*    */     //   295: aload_0
/*    */     //   296: getfield HP : B
/*    */     //   299: invokevirtual s2 : (B)Z
/*    */     //   302: ifne -> 320
/*    */     //   305: getstatic f/js.vu0 : Lf/js;
/*    */     //   308: sipush #2108
/*    */     //   311: invokestatic OH0 : (I)Ljava/lang/String;
/*    */     //   314: iconst_m1
/*    */     //   315: swap
/*    */     //   316: invokevirtual Pu : (ILjava/lang/String;)V
/*    */     //   319: return
/*    */     //   320: aload_0
/*    */     //   321: dup
/*    */     //   322: dup
/*    */     //   323: dup2
/*    */     //   324: getfield MI0 : Lf/Un;
/*    */     //   327: iconst_0
/*    */     //   328: invokevirtual sk0 : (Z)V
/*    */     //   331: getfield cOm5 : Lf/of;
/*    */     //   334: iconst_0
/*    */     //   335: invokevirtual sk0 : (Z)V
/*    */     //   338: getstatic f/km.u4 : Lf/R8;
/*    */     //   341: astore_0
/*    */     //   342: getfield cOm5 : Lf/of;
/*    */     //   345: getfield F2 : Lf/ak0;
/*    */     //   348: getfield PH0 : Ljava/lang/StringBuilder;
/*    */     //   351: invokevirtual toString : ()Ljava/lang/String;
/*    */     //   354: astore_2
/*    */     //   355: getfield ar0 : B
/*    */     //   358: istore_3
/*    */     //   359: getfield HP : B
/*    */     //   362: istore #4
/*    */     //   364: aload_0
/*    */     //   365: invokevirtual dm0 : ()I
/*    */     //   368: iconst_3
/*    */     //   369: if_icmpeq -> 375
/*    */     //   372: goto -> 670
/*    */     //   375: aload_0
/*    */     //   376: getfield e20 : Lf/c4;
/*    */     //   379: new f/iD
/*    */     //   382: dup
/*    */     //   383: aload_2
/*    */     //   384: iload_3
/*    */     //   385: iload #4
/*    */     //   387: aload_1
/*    */     //   388: invokespecial <init> : (Ljava/lang/String;BBLf/H10;)V
/*    */     //   391: invokevirtual W3 : (Lf/Bi;)V
/*    */     //   394: goto -> 670
/*    */     //   397: aload_0
/*    */     //   398: getfield cOm3 : Z
/*    */     //   401: ifeq -> 437
/*    */     //   404: getstatic f/js.vu0 : Lf/js;
/*    */     //   407: new f/h70
/*    */     //   410: dup
/*    */     //   411: aload_0
/*    */     //   412: aload_1
/*    */     //   413: sipush #2890
/*    */     //   416: invokestatic OH0 : (I)Ljava/lang/String;
/*    */     //   419: astore_1
/*    */     //   420: <illegal opcode> run : (Lf/Ia;Lf/H10;)Ljava/lang/Runnable;
/*    */     //   425: aload_1
/*    */     //   426: swap
/*    */     //   427: aload_0
/*    */     //   428: invokespecial <init> : (Ljava/lang/String;Ljava/lang/Runnable;Lf/JG0;)V
/*    */     //   431: invokevirtual uh : (Lf/h70;)V
/*    */     //   434: goto -> 670
/*    */     //   437: aload_0
/*    */     //   438: getfield z70 : Z
/*    */     //   441: ifeq -> 477
/*    */     //   444: getstatic f/js.vu0 : Lf/js;
/*    */     //   447: new f/h70
/*    */     //   450: dup
/*    */     //   451: aload_0
/*    */     //   452: aload_1
/*    */     //   453: sipush #2891
/*    */     //   456: invokestatic OH0 : (I)Ljava/lang/String;
/*    */     //   459: astore_1
/*    */     //   460: <illegal opcode> run : (Lf/Ia;Lf/H10;)Ljava/lang/Runnable;
/*    */     //   465: aload_1
/*    */     //   466: swap
/*    */     //   467: aload_0
/*    */     //   468: invokespecial <init> : (Ljava/lang/String;Ljava/lang/Runnable;Lf/JG0;)V
/*    */     //   471: invokevirtual uh : (Lf/h70;)V
/*    */     //   474: goto -> 670
/*    */     //   477: getstatic f/km.a3 : Lf/vh0;
/*    */     //   480: getfield Ct : Lf/Jo;
/*    */     //   483: dup
/*    */     //   484: astore_1
/*    */     //   485: ifnonnull -> 489
/*    */     //   488: return
/*    */     //   489: aload_1
/*    */     //   490: getfield lB0 : Lf/OE0;
/*    */     //   493: getfield Xu : Lf/H10;
/*    */     //   496: astore_1
/*    */     //   497: getstatic f/Vp0.Jo : [Lf/Vp0;
/*    */     //   500: dup
/*    */     //   501: astore_2
/*    */     //   502: arraylength
/*    */     //   503: istore_3
/*    */     //   504: iconst_0
/*    */     //   505: istore #4
/*    */     //   507: iload #4
/*    */     //   509: iload_3
/*    */     //   510: if_icmpge -> 658
/*    */     //   513: aload_0
/*    */     //   514: aload_2
/*    */     //   515: iload #4
/*    */     //   517: aaload
/*    */     //   518: astore #5
/*    */     //   520: getfield Lc0 : [Lf/W1;
/*    */     //   523: aload #5
/*    */     //   525: getfield gw0 : B
/*    */     //   528: iconst_1
/*    */     //   529: iadd
/*    */     //   530: dup
/*    */     //   531: istore #6
/*    */     //   533: aaload
/*    */     //   534: dup
/*    */     //   535: astore #7
/*    */     //   537: getfield kN : Z
/*    */     //   540: ifne -> 546
/*    */     //   543: goto -> 652
/*    */     //   546: aload #7
/*    */     //   548: getfield Wa0 : Lf/A60;
/*    */     //   551: getfield go : I
/*    */     //   554: dup
/*    */     //   555: istore #7
/*    */     //   557: iflt -> 652
/*    */     //   560: aload_1
/*    */     //   561: aload_0
/*    */     //   562: getfield J5 : [Lf/cQ;
/*    */     //   565: iload #6
/*    */     //   567: aaload
/*    */     //   568: iload #7
/*    */     //   570: invokevirtual c90 : (I)Ljava/lang/Object;
/*    */     //   573: checkcast f/uK
/*    */     //   576: astore #6
/*    */     //   578: getfield Hd0 : [S
/*    */     //   581: aload #5
/*    */     //   583: getfield gw0 : B
/*    */     //   586: dup
/*    */     //   587: istore #5
/*    */     //   589: saload
/*    */     //   590: aload #6
/*    */     //   592: getfield COm4 : S
/*    */     //   595: dup
/*    */     //   596: istore #7
/*    */     //   598: if_icmpne -> 625
/*    */     //   601: aload_1
/*    */     //   602: getfield Kw0 : [B
/*    */     //   605: iload #5
/*    */     //   607: baload
/*    */     //   608: aload #6
/*    */     //   610: getfield ce0 : B
/*    */     //   613: if_icmpeq -> 652
/*    */     //   616: iload #7
/*    */     //   618: iconst_m1
/*    */     //   619: if_icmpne -> 625
/*    */     //   622: goto -> 652
/*    */     //   625: getstatic f/km.u4 : Lf/R8;
/*    */     //   628: iload #5
/*    */     //   630: aload #6
/*    */     //   632: dup
/*    */     //   633: getfield IN : I
/*    */     //   636: istore #5
/*    */     //   638: getfield VA0 : Z
/*    */     //   641: istore #6
/*    */     //   643: iload #5
/*    */     //   645: iload #7
/*    */     //   647: iload #6
/*    */     //   649: invokevirtual OI : (BISZ)V
/*    */     //   652: iinc #4, 1
/*    */     //   655: goto -> 507
/*    */     //   658: getstatic f/js.vu0 : Lf/js;
/*    */     //   661: iconst_0
/*    */     //   662: iconst_0
/*    */     //   663: iconst_0
/*    */     //   664: iconst_0
/*    */     //   665: iconst_0
/*    */     //   666: iconst_0
/*    */     //   667: invokevirtual h4 : (IZZZZZ)V
/*    */     //   670: return
/*    */     // Line number table:
/*    */     //   Java source line number -> byte code offset
/*    */     //   #1	-> 29
/*    */     //   #2	-> 32
/*    */     //   #3	-> 37
/*    */     //   #4	-> 45
/*    */     //   #5	-> 48
/*    */     //   #6	-> 66
/*    */     //   #7	-> 69
/*    */     //   #8	-> 88
/*    */     //   #9	-> 91
/*    */     //   #10	-> 110
/*    */     //   #11	-> 113
/*    */     //   #12	-> 132
/*    */     //   #13	-> 135
/*    */     //   #14	-> 154
/*    */     //   #15	-> 157
/*    */     //   #16	-> 176
/*    */     //   #17	-> 179
/*    */     //   #18	-> 198
/*    */     //   #19	-> 201
/*    */     //   #20	-> 212
/*    */     //   #21	-> 286
/*    */     //   #22	-> 305
/*    */     //   #23	-> 311
/*    */     //   #24	-> 316
/*    */     //   #25	-> 324
/*    */     //   #26	-> 345
/*    */     //   #27	-> 348
/*    */     //   #28	-> 351
/*    */     //   #29	-> 355
/*    */     //   #30	-> 365
/*    */     //   #31	-> 376
/*    */     //   #32	-> 398
/*    */     //   #33	-> 404
/*    */     //   #34	-> 407
/*    */     //   #35	-> 444
/*    */     //   #36	-> 447
/*    */     //   #37	-> 480
/*    */     //   #38	-> 490
/*    */     //   #39	-> 493
/*    */     //   #40	-> 497
/*    */     //   #41	-> 525
/*    */     //   #42	-> 533
/*    */     //   #43	-> 537
/*    */     //   #44	-> 548
/*    */     //   #45	-> 551
/*    */     //   #46	-> 562
/*    */     //   #47	-> 578
/*    */     //   #48	-> 583
/*    */     //   #49	-> 589
/*    */     //   #50	-> 592
/*    */     //   #51	-> 602
/*    */     //   #52	-> 607
/*    */     //   #53	-> 610
/*    */     //   #54	-> 658
/*    */     //   #55	-> 667
/*    */   }
/*    */   
/*    */   public final void Zt() {
/*    */     Ip ip;
/*    */     if ((ip = this.Tt) == null)
/*    */       return; 
/*    */     ip.wI0(false);
/*    */     this.VF0.wI0(false);
/*    */     if (!(ip = this.ki).dP)
/*    */       ip.wI0(true); 
/*    */     Un un;
/*    */     if (!(un = this.MI0).dP)
/*    */       un.wI0(true); 
/*    */     byte b;
/*    */     if ((b = this.Pb0) >= 0) {
/*    */       byte b1 = this.rb0;
/*    */       short s = this.yq0[b];
/*    */       byte b2;
/*    */       dn0.com8[b2 = vp0.gw0] = s;
/*    */       dn0.QL0[b2] = b1;
/*    */       Dn0 dn0;
/*    */       Vp0 vp0 = Vp0.cOm1(b);
/*    */     } 
/*    */     this.Pb0 = -1;
/*    */     this.rb0 = 0;
/*    */     p40();
/*    */   }
/*    */   
/*    */   public final void t2(int paramInt) {
/*    */     Dn0 dn0;
/*    */     int i;
/*    */     if ((i = this.mv) == 0 && paramInt < 0) {
/*    */       this.mv = 4;
/*    */     } else {
/*    */       this.mv = (i + paramInt) % 5;
/*    */     } 
/*    */     if ((paramInt = this.mv) == 4) {
/*    */       dn0 = this.Vh;
/*    */       if (km.XU()) {
/*    */         i = 4;
/*    */       } else {
/*    */         i = 3;
/*    */       } 
/*    */       dn0.Dd = i;
/*    */     } else {
/*    */       dn0 = this.Vh;
/*    */       if (km.XU()) {
/*    */         i = 4;
/*    */       } else {
/*    */         i = 3;
/*    */       } 
/*    */       dn0.Dd = i;
/*    */       dn0 = this.Vh;
/*    */       if (km.XU()) {
/*    */         i = 6;
/*    */       } else {
/*    */         i = 4;
/*    */       } 
/*    */       dn0.Dd = i;
/*    */     } 
/*    */     this.Vh.Ng0 = (dn0 == 3) ? lPT9.jR : lPT9.U4;
/*    */   }
/*    */   
/*    */   public final void R60(throws paramthrows) {
/*    */     char c1 = 'ʀ', c2 = '(';
/*    */     if (km.XU()) {
/*    */       if (this.Yb0 || this.z70)
/*    */         c2 = '¾'; 
/*    */     } else {
/*    */       c1 = 'Ⱥ';
/*    */       c2 = 'Z';
/*    */       if (this.Yb0 || this.Tt.dP) {
/*    */         c1 = 'ʀ';
/*    */         c2 = 'È';
/*    */       } 
/*    */     } 
/*    */     if (this.Tt.dP)
/*    */       c1 = 'Ķ'; 
/*    */     for (byte b = 0; b < 3; ) {
/*    */       int i;
/*    */       if (((i = this.mv) != 3 && i != 4) || b == 1) {
/*    */         int j;
/*    */         if (this.Tt.dP) {
/*    */           i = this.xY / 2 - 210;
/*    */           i = b * 100 + i;
/*    */           j = c2 + 50;
/*    */         } else {
/*    */           i = c1 - 200;
/*    */           j = c2 - 80;
/*    */           j = b * 120 + j;
/*    */         } 
/*    */         if (km.XU()) {
/*    */           j = c1 + (i = b * 160);
/*    */           int m = c2 + 80;
/*    */           if (this.Tt.dP) {
/*    */             i = this.xY / 2 - 320 + i;
/*    */             j = m;
/*    */           } else {
/*    */             i = j = m;
/*    */           } 
/*    */         } 
/*    */         byte b1 = 0;
/*    */         int k;
/*    */         switch (k = this.mv) {
/*    */           case 4:
/*    */             b1 = Rg.vs0[Rg.uj0.Nn0()];
/*    */             break;
/*    */           case 3:
/*    */             b1 = this.ar0;
/*    */             break;
/*    */           case 0:
/*    */           case 1:
/*    */           case 2:
/*    */             b1 = Rg.Za[k * 3 + b][Rg.VE.Nn0()];
/*    */             break;
/*    */         } 
/*    */         b1 = (byte)(this.Lc0[0]).Wa0.go;
/*    */         short[] arrayOfShort = this.yq0;
/*    */         byte[] arrayOfByte = this.E10;
/*    */         this.Vh.rh = b1;
/*    */         this.Vh.com8 = arrayOfShort;
/*    */         this.Vh.QL0 = arrayOfByte;
/*    */         this.Vh.FD0((byte)b1, i, j);
/*    */       } 
/*    */       b++;
/*    */     } 
/*    */     p40();
/*    */   }
/*    */   
/*    */   public final void IG0() {
/*    */     UB0.Kg0.fN(this::zC0);
/*    */   }
/*    */   
/*    */   public final void zC0() {
/*    */     VA0.c90(H1());
/*    */   }
/*    */   
/*    */   public final boolean i2(oa0 paramoa0) {
/*    */     // Byte code:
/*    */     //   0: aload_1
/*    */     //   1: getfield cz0 : I
/*    */     //   4: invokestatic Wm0 : (I)Z
/*    */     //   7: ifeq -> 379
/*    */     //   10: aload_1
/*    */     //   11: invokevirtual oO : ()Z
/*    */     //   14: ifeq -> 379
/*    */     //   17: aload_0
/*    */     //   18: getfield cOm5 : Lf/of;
/*    */     //   21: dup
/*    */     //   22: astore_2
/*    */     //   23: ifnull -> 39
/*    */     //   26: aload_2
/*    */     //   27: invokevirtual p3 : ()Z
/*    */     //   30: ifeq -> 39
/*    */     //   33: aload_0
/*    */     //   34: aload_1
/*    */     //   35: invokespecial i2 : (Lf/oa0;)Z
/*    */     //   38: ireturn
/*    */     //   39: aload_0
/*    */     //   40: getfield Tt : Lf/Ip;
/*    */     //   43: getfield dP : Z
/*    */     //   46: ifeq -> 51
/*    */     //   49: iconst_1
/*    */     //   50: ireturn
/*    */     //   51: aload_1
/*    */     //   52: getfield GG0 : I
/*    */     //   55: dup
/*    */     //   56: istore_2
/*    */     //   57: getstatic f/BM.ni : Lf/BM;
/*    */     //   60: invokestatic J20 : (ILf/BM;)Z
/*    */     //   63: ifeq -> 105
/*    */     //   66: aload_0
/*    */     //   67: dup
/*    */     //   68: dup2
/*    */     //   69: getfield rE0 : I
/*    */     //   72: iconst_1
/*    */     //   73: isub
/*    */     //   74: putfield rE0 : I
/*    */     //   77: invokevirtual H1 : ()Lf/W1;
/*    */     //   80: invokestatic c90 : (Lf/JG0;)Z
/*    */     //   83: pop
/*    */     //   84: invokevirtual H1 : ()Lf/W1;
/*    */     //   87: ifnull -> 103
/*    */     //   90: aload_0
/*    */     //   91: invokevirtual H1 : ()Lf/W1;
/*    */     //   94: getfield dP : Z
/*    */     //   97: ifne -> 103
/*    */     //   100: goto -> 66
/*    */     //   103: iconst_1
/*    */     //   104: ireturn
/*    */     //   105: iload_2
/*    */     //   106: getstatic f/BM.N70 : Lf/BM;
/*    */     //   109: invokestatic J20 : (ILf/BM;)Z
/*    */     //   112: ifeq -> 154
/*    */     //   115: aload_0
/*    */     //   116: dup
/*    */     //   117: dup2
/*    */     //   118: getfield rE0 : I
/*    */     //   121: iconst_1
/*    */     //   122: iadd
/*    */     //   123: putfield rE0 : I
/*    */     //   126: invokevirtual H1 : ()Lf/W1;
/*    */     //   129: invokestatic c90 : (Lf/JG0;)Z
/*    */     //   132: pop
/*    */     //   133: invokevirtual H1 : ()Lf/W1;
/*    */     //   136: ifnull -> 152
/*    */     //   139: aload_0
/*    */     //   140: invokevirtual H1 : ()Lf/W1;
/*    */     //   143: getfield dP : Z
/*    */     //   146: ifne -> 152
/*    */     //   149: goto -> 115
/*    */     //   152: iconst_1
/*    */     //   153: ireturn
/*    */     //   154: iload_2
/*    */     //   155: getstatic f/BM.Oq : Lf/BM;
/*    */     //   158: invokestatic J20 : (ILf/BM;)Z
/*    */     //   161: ifeq -> 208
/*    */     //   164: aload_0
/*    */     //   165: invokevirtual H1 : ()Lf/W1;
/*    */     //   168: getfield kN : Z
/*    */     //   171: ifeq -> 206
/*    */     //   174: aload_0
/*    */     //   175: invokevirtual H1 : ()Lf/W1;
/*    */     //   178: getfield Wa0 : Lf/A60;
/*    */     //   181: getfield go : I
/*    */     //   184: ifle -> 206
/*    */     //   187: aload_0
/*    */     //   188: invokevirtual H1 : ()Lf/W1;
/*    */     //   191: aload_0
/*    */     //   192: invokevirtual H1 : ()Lf/W1;
/*    */     //   195: getfield Wa0 : Lf/A60;
/*    */     //   198: getfield go : I
/*    */     //   201: iconst_1
/*    */     //   202: isub
/*    */     //   203: invokevirtual Z30 : (I)V
/*    */     //   206: iconst_1
/*    */     //   207: ireturn
/*    */     //   208: iload_2
/*    */     //   209: getstatic f/BM.M8 : Lf/BM;
/*    */     //   212: invokestatic J20 : (ILf/BM;)Z
/*    */     //   215: ifeq -> 277
/*    */     //   218: aload_0
/*    */     //   219: invokevirtual H1 : ()Lf/W1;
/*    */     //   222: getfield kN : Z
/*    */     //   225: ifeq -> 275
/*    */     //   228: aload_0
/*    */     //   229: invokevirtual H1 : ()Lf/W1;
/*    */     //   232: getfield Wa0 : Lf/A60;
/*    */     //   235: getfield go : I
/*    */     //   238: iconst_1
/*    */     //   239: iadd
/*    */     //   240: aload_0
/*    */     //   241: invokevirtual H1 : ()Lf/W1;
/*    */     //   244: getfield Wa0 : Lf/A60;
/*    */     //   247: getfield my : Lf/cQ;
/*    */     //   250: invokevirtual pu : ()I
/*    */     //   253: if_icmpge -> 275
/*    */     //   256: aload_0
/*    */     //   257: invokevirtual H1 : ()Lf/W1;
/*    */     //   260: aload_0
/*    */     //   261: invokevirtual H1 : ()Lf/W1;
/*    */     //   264: getfield Wa0 : Lf/A60;
/*    */     //   267: getfield go : I
/*    */     //   270: iconst_1
/*    */     //   271: iadd
/*    */     //   272: invokevirtual Z30 : (I)V
/*    */     //   275: iconst_1
/*    */     //   276: ireturn
/*    */     //   277: iload_2
/*    */     //   278: getstatic f/BM.bC : Lf/BM;
/*    */     //   281: invokestatic J20 : (ILf/BM;)Z
/*    */     //   284: ifeq -> 316
/*    */     //   287: aload_0
/*    */     //   288: getfield Yb0 : Z
/*    */     //   291: ifne -> 314
/*    */     //   294: aload_0
/*    */     //   295: getfield cOm3 : Z
/*    */     //   298: ifne -> 314
/*    */     //   301: aload_0
/*    */     //   302: getfield MI0 : Lf/Un;
/*    */     //   305: getfield TG0 : Lf/protected;
/*    */     //   308: getfield oh0 : [Ljava/lang/Runnable;
/*    */     //   311: invokestatic Fz0 : ([Ljava/lang/Runnable;)V
/*    */     //   314: iconst_1
/*    */     //   315: ireturn
/*    */     //   316: iload_2
/*    */     //   317: getstatic f/BM.lc : Lf/BM;
/*    */     //   320: invokestatic J20 : (ILf/BM;)Z
/*    */     //   323: ifeq -> 379
/*    */     //   326: aload_0
/*    */     //   327: getfield Bi0 : Lf/Un;
/*    */     //   330: dup
/*    */     //   331: astore_1
/*    */     //   332: ifnull -> 355
/*    */     //   335: aload_0
/*    */     //   336: getfield Yb0 : Z
/*    */     //   339: ifeq -> 355
/*    */     //   342: aload_1
/*    */     //   343: getfield TG0 : Lf/protected;
/*    */     //   346: getfield oh0 : [Ljava/lang/Runnable;
/*    */     //   349: invokestatic Fz0 : ([Ljava/lang/Runnable;)V
/*    */     //   352: goto -> 377
/*    */     //   355: getstatic f/js.vu0 : Lf/js;
/*    */     //   358: aload_0
/*    */     //   359: dup
/*    */     //   360: getfield cOm3 : Z
/*    */     //   363: istore_0
/*    */     //   364: getfield Yb0 : Z
/*    */     //   367: istore_1
/*    */     //   368: iconst_0
/*    */     //   369: iconst_0
/*    */     //   370: iconst_0
/*    */     //   371: iload_0
/*    */     //   372: iload_1
/*    */     //   373: iconst_0
/*    */     //   374: invokevirtual h4 : (IZZZZZ)V
/*    */     //   377: iconst_1
/*    */     //   378: ireturn
/*    */     //   379: aload_0
/*    */     //   380: aload_1
/*    */     //   381: invokespecial i2 : (Lf/oa0;)Z
/*    */     //   384: ireturn
/*    */     // Line number table:
/*    */     //   Java source line number -> byte code offset
/*    */     //   #1	-> 1
/*    */     //   #2	-> 4
/*    */     //   #3	-> 11
/*    */     //   #4	-> 43
/*    */     //   #5	-> 52
/*    */     //   #6	-> 57
/*    */     //   #7	-> 77
/*    */     //   #8	-> 84
/*    */     //   #9	-> 94
/*    */     //   #10	-> 106
/*    */     //   #11	-> 126
/*    */     //   #12	-> 133
/*    */     //   #13	-> 143
/*    */     //   #14	-> 155
/*    */     //   #15	-> 168
/*    */     //   #16	-> 175
/*    */     //   #17	-> 178
/*    */     //   #18	-> 181
/*    */     //   #19	-> 188
/*    */     //   #20	-> 195
/*    */     //   #21	-> 198
/*    */     //   #22	-> 203
/*    */     //   #23	-> 222
/*    */     //   #24	-> 229
/*    */     //   #25	-> 232
/*    */     //   #26	-> 235
/*    */     //   #27	-> 241
/*    */     //   #28	-> 244
/*    */     //   #29	-> 247
/*    */     //   #30	-> 250
/*    */     //   #31	-> 264
/*    */     //   #32	-> 267
/*    */     //   #33	-> 272
/*    */     //   #34	-> 305
/*    */     //   #35	-> 308
/*    */     //   #36	-> 311
/*    */     //   #37	-> 317
/*    */     //   #38	-> 343
/*    */     //   #39	-> 346
/*    */     //   #40	-> 349
/*    */     //   #41	-> 355
/*    */     //   #42	-> 360
/*    */   } }


/* Location:              /Users/vnnsnnt/Documents/Codespace/JavaWorkspace/RedTrainer/src/main/java/org/trainer/client/PokeMMO.jar!/f/Ia.class
 * Java compiler version: 8 (52.0)
 * JD-Core Version:       1.1.3
 */