/*  1 */ package f;public final class IF0 extends KI { public AC0 hz0; public int Jf; public int kZ; public xW[][] pM; public xW[][] Tu0; public Rw0[] r4 = new Rw0[0]; public short ar; public String gz; public boolean Pp0 = false; public String f1 = ""; public g40[][] im0; public byte Jh0; public boolean tL = false; public int Ew = 0; public int n1 = 0; public pB0 Lq0 = null; public else[][] rE = null; public xv Px = null; public Tm Y1 = null; public int[] vp0 = new int[1]; public fQ ip0 = new fQ(); public Jc0 M6 = new Jc0(); public boolean Sf = false; public final void Jj(tc paramtc, boolean paramBoolean) { if (paramtc == null) return;  int i; if ((i = vh0.H90) != -1) { boolean bool = false; int j; if ((j = paramtc.Jg) == i) bool = true;  vh0 vh0;
/*  2 */       if ((vh0 = km.a3) != null && vh0
/*  3 */         .yD == j) bool = true;  if (!bool)
/*    */         return;  }
/*  5 */      G5 g5; short s1 = (g5 = paramtc.HW).mm;
/*  6 */     short s2 = paramtc.HW.Yu0; if ((paramBoolean && g5
/*  7 */       .Qf0 < 3) || (!paramBoolean && g5
/*  8 */       .Qf0 > 2)) return;  if (s1 >= this
/*  9 */       .Fk0 || s2 >= this.nT || s1 < 0 || s2 < 0) return;  g40[] arrayOfG40; if ((arrayOfG40 = this.im0[s1])[s2] == null) { g40 g401; this(); arrayOfG40[s2] = g401; }  this.im0[s1][s2].Et(paramtc); } public final void uY(tH paramtH, Tm paramTm, Eb paramEb, int paramInt) { int[] arrayOfInt; xv xv1; int i = this.Ew, j = this.n1, k = i + 0; i = j + 0; j = this.nT * 16 + j; eo eo1, eo2; if ((this.Fk0 * 16 + i) < (eo2 = paramEb.pp0).x || k > (eo1 = paramEb.s60).x) return;  if (j < eo2.y || i > eo1.y) return;  if (this.Lq0 != null && (paramInt == 0 || paramInt == 2)) { paramtH.end(); if (this.Px == null) { this.Px = new xv(this.Lq0); float f = paramTm.gV; this.Y1 = new Tm(f, paramTm.oA); }  tm1.gV = paramTm.gV; tm1.oA = paramTm.oA; float f3 = paramTm.gV; Tm tm1; (tm1 = this.Y1).Wt(f3, paramTm.oA, false); this.Y1.H.JL(paramTm.H); eo3.x -= this.Ew; eo eo3; this.Y1.H.y = (eo3 = this.Y1.H).y * -1.0F + (this.nT * 16) + this.n1; this.Y1.UX(true); xv xv2 = this.Px; Tm tm2 = this.Y1; M30 m302 = xv2.BM; ((JX)m302).d60(tm2.VD0); float f2, f4 = tm2.gV * (f2 = tm2.nUl); f2 = tm2.oA * f2; float f5 = Math.abs(tm2.nj0.y) * f4; f5 = Math.abs(tm2.nj0.x) * f2 + f5; f2 = Math.abs(tm2.nj0.y) * f2; f2 = Math.abs(tm2.nj0.x) * f4 + f2; eo eo4; xv2.K7.jG((eo4 = tm2.H).x - f5 / 2.0F, eo4.y - f2 / 2.0F, f5, f2); M30 m301 = this.Px.BM; Rm0 rm0; if ((rm0 = paramtH.J30) == null) rm0 = paramtH.fe; 
/* 10 */       if (((JX)(m301 = m301))
/* 11 */         .V10) m301
/* 12 */           .ot();  ((JX)m301).J30 = rm0; if (((JX)m301).V10) { if (rm0 != null) { rm0.bind(); } else { ((JX)m301).fe.bind(); }  m301.A6(); }
/*    */ 
/*    */       
/* 15 */       float f1 = Xc0.Nn0; ((JX)this.Px.BM).og0(f1); arrayOfInt = this.vp0; boolean bool = false; if (paramInt == 0) { m = 0; } else { m = 1; }  arrayOfInt[bool] = m; xv xv3; (xv3 = this.Px).getClass();
/*    */ 
/*    */       
/* 18 */       kp.Sv = System.currentTimeMillis() - kp.CS;
/* 19 */       ((JX)this.Px.BM).Tx(); int m, n;
/* 20 */       for (m = arrayOfInt.length, n = 0; n < m; ) { int i1 = arrayOfInt[n]; xv3
/*    */ 
/*    */ 
/*    */           
/* 24 */           .QT((ql0)xv3.Vc.TC.VD0.get(i1)); n++; }
/* 25 */        ((JX)xv3.BM).end(); if (paramInt == 1)
/*    */       
/*    */       { 
/* 28 */         float f = Color.WHITE_FLOAT_BITS; ((JX)this.Px.BM).og0(f); arrayOfInt[0] = 2; (xv1 = this.Px).getClass();
/*    */ 
/*    */         
/* 31 */         kp.Sv = System.currentTimeMillis() - kp.CS;
/* 32 */         ((JX)this.Px.BM).Tx();
/* 33 */         for (int i1 = (arrayOfInt = this.vp0).length; m < i1; ) { n = arrayOfInt[m]; xv1
/*    */ 
/*    */ 
/*    */             
/* 37 */             .QT((ql0)xv1.Vc.TC.VD0.get(n)); m++; }
/* 38 */          ((JX)xv1.BM).end(); }  paramtH
/* 39 */         .Tx(); paramtH.d60(paramTm.VD0); pm0(paramtH, paramTm, true); return; }  paramtH.og0(Xc0.Nn0); if (xv1 == null) { It0(0, paramtH, (Eb)arrayOfInt); } else if (xv1 == true) { pm0(paramtH, paramTm, false); } else if (xv1 == 2) { It0(1, paramtH, (Eb)arrayOfInt); pm0(paramtH, paramTm, true); It0(2, paramtH, (Eb)arrayOfInt); }  for (Hc0 hc0 = this.ip0.r30(); hc0.hasNext(); )
/* 40 */     { bH0 bH0; Ui0 ui0 = (bH0 = (bH0)hc0.next()).Ns0;
/* 41 */       boolean bool1 = ((bH0)hc0.next()).W5, bool2 = ((bH0)hc0.next()).KB0; boolean bool3 = false, bool4 = false;
/*    */       
/* 43 */       if (((ui0.mP > ui0.zV)) != bool1) bool3 = true; 
/* 44 */       if (((ui0.WT > ui0.bh0)) != bool2) bool4 = true;  ui0
/* 45 */         .zt0(bool3, bool4);
/* 46 */       float f = bH0.us; bH0.Ns0.Hc0(f, bH0.Gd); bH0.Ns0.Ne(paramtH); }  this
/* 47 */       .M6.freeAll(this.ip0); this.ip0.clear(); }
/*    */ 
/*    */   
/*    */   public final void f00(short[] paramArrayOfshort) {
/*    */     xW[][] arrayOfXW;
/*    */     int i;
/*    */     short s;
/*    */     int j;
/*    */     for (arrayOfXW = new xW[this.Fk0][this.nT], i = 0, s = 0; s < (j = this.nT); ) {
/*    */       for (j = 0; j < this.Fk0; ) {
/*    */         xW xW1;
/*    */         this(paramArrayOfshort[i++], this, j, s);
/*    */         arrayOfXW[j][s] = xW1;
/*    */         AC0 aC0 = this.hz0;
/*    */         j = (arrayOfXW[j][s]).IF0;
/*    */         (arrayOfXW[j][s]).lS = aC0.KL[j];
/*    */         j = (short)(j + 1);
/*    */       } 
/*    */       s = (short)(s + 1);
/*    */     } 
/*    */     this.Tu0 = arrayOfXW;
/*    */     this.im0 = new g40[this.Fk0][j];
/*    */   }
/*    */   
/*    */   public final String xc0() {
/*    */     return this.Pp0 ? (this.f1 + "'s " + this.gz) : this.gz;
/*    */   }
/*    */   
/*    */   public final Rw0 MH(c6 paramc6, int paramInt1, int paramInt2) {
/*    */     // Byte code:
/*    */     //   0: aload_0
/*    */     //   1: getfield r4 : [Lf/Rw0;
/*    */     //   4: dup
/*    */     //   5: astore_0
/*    */     //   6: arraylength
/*    */     //   7: istore #4
/*    */     //   9: iconst_0
/*    */     //   10: istore #5
/*    */     //   12: iload #5
/*    */     //   14: iload #4
/*    */     //   16: if_icmpge -> 153
/*    */     //   19: aload_0
/*    */     //   20: iload #5
/*    */     //   22: aaload
/*    */     //   23: dup
/*    */     //   24: astore #6
/*    */     //   26: getfield Ac : Lf/c6;
/*    */     //   29: aload_1
/*    */     //   30: if_acmpne -> 147
/*    */     //   33: getstatic f/km.a3 : Lf/vh0;
/*    */     //   36: aload #6
/*    */     //   38: dup
/*    */     //   39: dup
/*    */     //   40: getfield El0 : B
/*    */     //   43: istore #7
/*    */     //   45: getfield uj0 : B
/*    */     //   48: istore #8
/*    */     //   50: getfield Wy0 : B
/*    */     //   53: istore #9
/*    */     //   55: iload #7
/*    */     //   57: iload #8
/*    */     //   59: iload #9
/*    */     //   61: invokevirtual COm8 : (BBB)Lf/KI;
/*    */     //   64: dup
/*    */     //   65: astore #7
/*    */     //   67: ifnonnull -> 73
/*    */     //   70: goto -> 147
/*    */     //   73: aload_1
/*    */     //   74: getstatic f/c6.JS : Lf/c6;
/*    */     //   77: if_acmpeq -> 117
/*    */     //   80: aload_1
/*    */     //   81: getstatic f/c6.g00 : Lf/c6;
/*    */     //   84: if_acmpne -> 90
/*    */     //   87: goto -> 117
/*    */     //   90: iload_2
/*    */     //   91: aload #6
/*    */     //   93: getfield eO : I
/*    */     //   96: dup
/*    */     //   97: istore #8
/*    */     //   99: if_icmplt -> 147
/*    */     //   102: iload_2
/*    */     //   103: iload #8
/*    */     //   105: aload #7
/*    */     //   107: getfield Fk0 : I
/*    */     //   110: iadd
/*    */     //   111: if_icmple -> 144
/*    */     //   114: goto -> 147
/*    */     //   117: iload_3
/*    */     //   118: aload #6
/*    */     //   120: getfield eO : I
/*    */     //   123: dup
/*    */     //   124: istore #8
/*    */     //   126: if_icmplt -> 147
/*    */     //   129: iload_3
/*    */     //   130: iload #8
/*    */     //   132: aload #7
/*    */     //   134: getfield nT : I
/*    */     //   137: iadd
/*    */     //   138: if_icmple -> 144
/*    */     //   141: goto -> 147
/*    */     //   144: aload #6
/*    */     //   146: areturn
/*    */     //   147: iinc #5, 1
/*    */     //   150: goto -> 12
/*    */     //   153: aconst_null
/*    */     //   154: areturn
/*    */     // Line number table:
/*    */     //   Java source line number -> byte code offset
/*    */     //   #1	-> 26
/*    */     //   #2	-> 33
/*    */     //   #3	-> 74
/*    */     //   #4	-> 93
/*    */     //   #5	-> 107
/*    */     //   #6	-> 120
/*    */     //   #7	-> 134
/*    */   }
/*    */   
/*    */   public final xr0 v50(int paramInt1, int paramInt2, int paramInt3) {
/*    */     // Byte code:
/*    */     //   0: iload_1
/*    */     //   1: aload_0
/*    */     //   2: getfield Fk0 : I
/*    */     //   5: if_icmplt -> 84
/*    */     //   8: aload_0
/*    */     //   9: getstatic f/c6.g00 : Lf/c6;
/*    */     //   12: iload_1
/*    */     //   13: iload_2
/*    */     //   14: invokevirtual MH : (Lf/c6;II)Lf/Rw0;
/*    */     //   17: dup
/*    */     //   18: astore_3
/*    */     //   19: ifnonnull -> 24
/*    */     //   22: aconst_null
/*    */     //   23: areturn
/*    */     //   24: getstatic f/km.a3 : Lf/vh0;
/*    */     //   27: aload_3
/*    */     //   28: dup
/*    */     //   29: dup
/*    */     //   30: getfield El0 : B
/*    */     //   33: istore #4
/*    */     //   35: getfield uj0 : B
/*    */     //   38: istore #5
/*    */     //   40: getfield Wy0 : B
/*    */     //   43: istore #6
/*    */     //   45: iload #4
/*    */     //   47: iload #5
/*    */     //   49: iload #6
/*    */     //   51: invokevirtual COm8 : (BBB)Lf/KI;
/*    */     //   54: dup
/*    */     //   55: astore #4
/*    */     //   57: ifnonnull -> 62
/*    */     //   60: aconst_null
/*    */     //   61: areturn
/*    */     //   62: aload #4
/*    */     //   64: iload_2
/*    */     //   65: aload_3
/*    */     //   66: iload_1
/*    */     //   67: aload_0
/*    */     //   68: getfield Fk0 : I
/*    */     //   71: isub
/*    */     //   72: istore_0
/*    */     //   73: getfield eO : I
/*    */     //   76: isub
/*    */     //   77: iload_0
/*    */     //   78: swap
/*    */     //   79: iconst_0
/*    */     //   80: invokevirtual v50 : (III)Lf/xr0;
/*    */     //   83: areturn
/*    */     //   84: iload_1
/*    */     //   85: ifge -> 160
/*    */     //   88: aload_0
/*    */     //   89: getstatic f/c6.JS : Lf/c6;
/*    */     //   92: iload_1
/*    */     //   93: iload_2
/*    */     //   94: invokevirtual MH : (Lf/c6;II)Lf/Rw0;
/*    */     //   97: dup
/*    */     //   98: astore_0
/*    */     //   99: ifnonnull -> 104
/*    */     //   102: aconst_null
/*    */     //   103: areturn
/*    */     //   104: getstatic f/km.a3 : Lf/vh0;
/*    */     //   107: aload_0
/*    */     //   108: dup
/*    */     //   109: dup
/*    */     //   110: getfield El0 : B
/*    */     //   113: istore_3
/*    */     //   114: getfield uj0 : B
/*    */     //   117: istore #4
/*    */     //   119: getfield Wy0 : B
/*    */     //   122: istore #5
/*    */     //   124: iload_3
/*    */     //   125: iload #4
/*    */     //   127: iload #5
/*    */     //   129: invokevirtual COm8 : (BBB)Lf/KI;
/*    */     //   132: dup
/*    */     //   133: astore_3
/*    */     //   134: ifnonnull -> 139
/*    */     //   137: aconst_null
/*    */     //   138: areturn
/*    */     //   139: aload_3
/*    */     //   140: iload_2
/*    */     //   141: aload_0
/*    */     //   142: aload_3
/*    */     //   143: getfield Fk0 : I
/*    */     //   146: iload_1
/*    */     //   147: iadd
/*    */     //   148: istore_0
/*    */     //   149: getfield eO : I
/*    */     //   152: isub
/*    */     //   153: iload_0
/*    */     //   154: swap
/*    */     //   155: iconst_0
/*    */     //   156: invokevirtual v50 : (III)Lf/xr0;
/*    */     //   159: areturn
/*    */     //   160: iload_2
/*    */     //   161: aload_0
/*    */     //   162: getfield nT : I
/*    */     //   165: if_icmplt -> 244
/*    */     //   168: aload_0
/*    */     //   169: getstatic f/c6.m20 : Lf/c6;
/*    */     //   172: iload_1
/*    */     //   173: iload_2
/*    */     //   174: invokevirtual MH : (Lf/c6;II)Lf/Rw0;
/*    */     //   177: dup
/*    */     //   178: astore_3
/*    */     //   179: ifnonnull -> 184
/*    */     //   182: aconst_null
/*    */     //   183: areturn
/*    */     //   184: getstatic f/km.a3 : Lf/vh0;
/*    */     //   187: aload_3
/*    */     //   188: dup
/*    */     //   189: dup
/*    */     //   190: getfield El0 : B
/*    */     //   193: istore #4
/*    */     //   195: getfield uj0 : B
/*    */     //   198: istore #5
/*    */     //   200: getfield Wy0 : B
/*    */     //   203: istore #6
/*    */     //   205: iload #4
/*    */     //   207: iload #5
/*    */     //   209: iload #6
/*    */     //   211: invokevirtual COm8 : (BBB)Lf/KI;
/*    */     //   214: dup
/*    */     //   215: astore #4
/*    */     //   217: ifnonnull -> 222
/*    */     //   220: aconst_null
/*    */     //   221: areturn
/*    */     //   222: aload #4
/*    */     //   224: iload_2
/*    */     //   225: aload_0
/*    */     //   226: iload_1
/*    */     //   227: aload_3
/*    */     //   228: getfield eO : I
/*    */     //   231: isub
/*    */     //   232: istore_0
/*    */     //   233: getfield nT : I
/*    */     //   236: isub
/*    */     //   237: iload_0
/*    */     //   238: swap
/*    */     //   239: iconst_0
/*    */     //   240: invokevirtual v50 : (III)Lf/xr0;
/*    */     //   243: areturn
/*    */     //   244: iload_2
/*    */     //   245: ifge -> 317
/*    */     //   248: aload_0
/*    */     //   249: getstatic f/c6.xA0 : Lf/c6;
/*    */     //   252: iload_1
/*    */     //   253: iload_2
/*    */     //   254: invokevirtual MH : (Lf/c6;II)Lf/Rw0;
/*    */     //   257: dup
/*    */     //   258: astore_0
/*    */     //   259: ifnonnull -> 264
/*    */     //   262: aconst_null
/*    */     //   263: areturn
/*    */     //   264: getstatic f/km.a3 : Lf/vh0;
/*    */     //   267: aload_0
/*    */     //   268: dup
/*    */     //   269: dup
/*    */     //   270: getfield El0 : B
/*    */     //   273: istore_3
/*    */     //   274: getfield uj0 : B
/*    */     //   277: istore #4
/*    */     //   279: getfield Wy0 : B
/*    */     //   282: istore #5
/*    */     //   284: iload_3
/*    */     //   285: iload #4
/*    */     //   287: iload #5
/*    */     //   289: invokevirtual COm8 : (BBB)Lf/KI;
/*    */     //   292: dup
/*    */     //   293: astore_3
/*    */     //   294: ifnonnull -> 299
/*    */     //   297: aconst_null
/*    */     //   298: areturn
/*    */     //   299: aload_3
/*    */     //   300: iload_1
/*    */     //   301: aload_0
/*    */     //   302: getfield eO : I
/*    */     //   305: isub
/*    */     //   306: aload_3
/*    */     //   307: getfield nT : I
/*    */     //   310: iload_2
/*    */     //   311: iadd
/*    */     //   312: iconst_0
/*    */     //   313: invokevirtual v50 : (III)Lf/xr0;
/*    */     //   316: areturn
/*    */     //   317: aload_0
/*    */     //   318: getfield Tu0 : [[Lf/xW;
/*    */     //   321: iload_1
/*    */     //   322: aaload
/*    */     //   323: iload_2
/*    */     //   324: aaload
/*    */     //   325: areturn
/*    */     // Line number table:
/*    */     //   Java source line number -> byte code offset
/*    */     //   #1	-> 2
/*    */     //   #2	-> 9
/*    */     //   #3	-> 24
/*    */     //   #4	-> 68
/*    */     //   #5	-> 73
/*    */     //   #6	-> 80
/*    */     //   #7	-> 89
/*    */     //   #8	-> 104
/*    */     //   #9	-> 143
/*    */     //   #10	-> 149
/*    */     //   #11	-> 156
/*    */     //   #12	-> 162
/*    */     //   #13	-> 169
/*    */     //   #14	-> 184
/*    */     //   #15	-> 228
/*    */     //   #16	-> 233
/*    */     //   #17	-> 240
/*    */     //   #18	-> 249
/*    */     //   #19	-> 264
/*    */     //   #20	-> 302
/*    */     //   #21	-> 307
/*    */     //   #22	-> 313
/*    */     //   #23	-> 318
/*    */   }
/*    */   
/*    */   public final short zu() {
/*    */     return this.ar;
/*    */   }
/*    */   
/*    */   public final boolean J4() {
/*    */     if (this.l1 != null) {
/*    */       b1 = 1;
/*    */     } else {
/*    */       b1 = 0;
/*    */     } 
/*    */     if (b1)
/*    */       return true; 
/*    */     byte b1;
/*    */     if ((b1 = this.E10) == 0 && !km.u4.fF0.y5(b1, (short)2095))
/*    */       return false; 
/*    */     if ((b1 = this.E10) == 1 && !km.u4.fF0.y5(b1, (short)2240))
/*    */       return false; 
/*    */     byte b;
/*    */     if ((b = this.E10) == 2 && !km.u4.fF0.y5(b, (short)2403))
/*    */       return false; 
/*    */     return true;
/*    */   }
/*    */   
/*    */   public final int cp0() {
/*    */     return this.Ew;
/*    */   }
/*    */   
/*    */   public final int kf0() {
/*    */     return this.n1;
/*    */   }
/*    */   
/*    */   public final void dispose() {
/*    */     pB0 pB01;
/*    */     if ((pB01 = this.Lq0) != null)
/*    */       pB01.dispose(); 
/*    */     xv xv1;
/*    */     if ((xv1 = this.Px) != null)
/*    */       super.dispose(); 
/*    */   }
/*    */   
/*    */   public final void It0(int paramInt, tH paramtH, Eb paramEb) {
/*    */     // Byte code:
/*    */     //   0: iload_1
/*    */     //   1: aload_0
/*    */     //   2: dup
/*    */     //   3: dup
/*    */     //   4: dup2
/*    */     //   5: getfield Ew : I
/*    */     //   8: istore #4
/*    */     //   10: getfield n1 : I
/*    */     //   13: istore #5
/*    */     //   15: getfield nT : I
/*    */     //   18: istore #6
/*    */     //   20: getfield Fk0 : I
/*    */     //   23: istore #7
/*    */     //   25: getfield Tu0 : [[Lf/xW;
/*    */     //   28: astore #8
/*    */     //   30: ifne -> 714
/*    */     //   33: iconst_0
/*    */     //   34: istore_1
/*    */     //   35: iload_1
/*    */     //   36: iload #6
/*    */     //   38: if_icmpge -> 1223
/*    */     //   41: iload_1
/*    */     //   42: bipush #16
/*    */     //   44: imul
/*    */     //   45: iload #5
/*    */     //   47: iadd
/*    */     //   48: dup
/*    */     //   49: istore #9
/*    */     //   51: i2f
/*    */     //   52: dup
/*    */     //   53: fstore #10
/*    */     //   55: aload_3
/*    */     //   56: getfield pp0 : Lf/eo;
/*    */     //   59: getfield y : F
/*    */     //   62: fcmpg
/*    */     //   63: iflt -> 708
/*    */     //   66: fload #10
/*    */     //   68: aload_3
/*    */     //   69: getfield s60 : Lf/eo;
/*    */     //   72: getfield y : F
/*    */     //   75: fcmpl
/*    */     //   76: ifle -> 82
/*    */     //   79: goto -> 708
/*    */     //   82: iconst_0
/*    */     //   83: istore #11
/*    */     //   85: iload #11
/*    */     //   87: iload #7
/*    */     //   89: if_icmpge -> 708
/*    */     //   92: iload #11
/*    */     //   94: bipush #16
/*    */     //   96: imul
/*    */     //   97: iload #4
/*    */     //   99: iadd
/*    */     //   100: dup
/*    */     //   101: istore #12
/*    */     //   103: i2f
/*    */     //   104: dup
/*    */     //   105: fstore #13
/*    */     //   107: aload_3
/*    */     //   108: getfield pp0 : Lf/eo;
/*    */     //   111: getfield x : F
/*    */     //   114: fcmpg
/*    */     //   115: iflt -> 702
/*    */     //   118: fload #13
/*    */     //   120: aload_3
/*    */     //   121: getfield s60 : Lf/eo;
/*    */     //   124: getfield x : F
/*    */     //   127: fcmpl
/*    */     //   128: ifle -> 134
/*    */     //   131: goto -> 702
/*    */     //   134: aload #8
/*    */     //   136: iload #11
/*    */     //   138: aaload
/*    */     //   139: iload_1
/*    */     //   140: aaload
/*    */     //   141: dup
/*    */     //   142: astore #14
/*    */     //   144: getfield lS : Lf/a4;
/*    */     //   147: dup
/*    */     //   148: astore #15
/*    */     //   150: iconst_0
/*    */     //   151: invokevirtual GC0 : (I)Lf/pe0;
/*    */     //   154: ifnull -> 171
/*    */     //   157: aload_2
/*    */     //   158: aload #15
/*    */     //   160: iconst_0
/*    */     //   161: invokevirtual GC0 : (I)Lf/pe0;
/*    */     //   164: fload #13
/*    */     //   166: fload #10
/*    */     //   168: invokevirtual TB : (Lf/pe0;FF)V
/*    */     //   171: aload #15
/*    */     //   173: iconst_0
/*    */     //   174: istore #16
/*    */     //   176: getfield LpT9 : [[Lf/Ui0;
/*    */     //   179: dup
/*    */     //   180: astore #17
/*    */     //   182: ifnull -> 199
/*    */     //   185: aload #17
/*    */     //   187: iload #16
/*    */     //   189: aaload
/*    */     //   190: ifnull -> 199
/*    */     //   193: iconst_1
/*    */     //   194: istore #16
/*    */     //   196: goto -> 202
/*    */     //   199: iconst_0
/*    */     //   200: istore #16
/*    */     //   202: iload #16
/*    */     //   204: ifeq -> 393
/*    */     //   207: aload #14
/*    */     //   209: invokevirtual gc : ()Z
/*    */     //   212: ifne -> 393
/*    */     //   215: getstatic f/Xc0.jE : I
/*    */     //   218: ifle -> 393
/*    */     //   221: iconst_0
/*    */     //   222: istore #16
/*    */     //   224: iload #16
/*    */     //   226: iconst_4
/*    */     //   227: if_icmpge -> 393
/*    */     //   230: aload #15
/*    */     //   232: iconst_0
/*    */     //   233: iload #16
/*    */     //   235: invokevirtual cx0 : (II)Lf/Ui0;
/*    */     //   238: dup
/*    */     //   239: astore #17
/*    */     //   241: ifnull -> 387
/*    */     //   244: aload #17
/*    */     //   246: aload_0
/*    */     //   247: dup
/*    */     //   248: aload #17
/*    */     //   250: iload #16
/*    */     //   252: aload #17
/*    */     //   254: iload #16
/*    */     //   256: iconst_2
/*    */     //   257: irem
/*    */     //   258: bipush #8
/*    */     //   260: imul
/*    */     //   261: iload #12
/*    */     //   263: iadd
/*    */     //   264: i2f
/*    */     //   265: invokevirtual aR : (F)V
/*    */     //   268: iconst_2
/*    */     //   269: idiv
/*    */     //   270: bipush #8
/*    */     //   272: imul
/*    */     //   273: iload #9
/*    */     //   275: iadd
/*    */     //   276: i2f
/*    */     //   277: invokevirtual Zq0 : (F)V
/*    */     //   280: getfield ip0 : Lf/fQ;
/*    */     //   283: astore #18
/*    */     //   285: getfield M6 : Lf/Jc0;
/*    */     //   288: invokevirtual obtain : ()Ljava/lang/Object;
/*    */     //   291: checkcast f/bH0
/*    */     //   294: dup
/*    */     //   295: astore #19
/*    */     //   297: aload #17
/*    */     //   299: aload #19
/*    */     //   301: aload #17
/*    */     //   303: aload #19
/*    */     //   305: aload #17
/*    */     //   307: putfield Ns0 : Lf/Ui0;
/*    */     //   310: invokevirtual Vw : ()F
/*    */     //   313: putfield us : F
/*    */     //   316: invokevirtual UT : ()F
/*    */     //   319: putfield Gd : F
/*    */     //   322: getfield mP : F
/*    */     //   325: aload #17
/*    */     //   327: getfield zV : F
/*    */     //   330: fcmpl
/*    */     //   331: ifle -> 340
/*    */     //   334: iconst_1
/*    */     //   335: istore #20
/*    */     //   337: goto -> 343
/*    */     //   340: iconst_0
/*    */     //   341: istore #20
/*    */     //   343: aload #17
/*    */     //   345: aload #19
/*    */     //   347: iload #20
/*    */     //   349: putfield W5 : Z
/*    */     //   352: getfield WT : F
/*    */     //   355: aload #17
/*    */     //   357: getfield bh0 : F
/*    */     //   360: fcmpl
/*    */     //   361: ifle -> 370
/*    */     //   364: iconst_1
/*    */     //   365: istore #17
/*    */     //   367: goto -> 373
/*    */     //   370: iconst_0
/*    */     //   371: istore #17
/*    */     //   373: aload #18
/*    */     //   375: aload #19
/*    */     //   377: iload #17
/*    */     //   379: putfield KB0 : Z
/*    */     //   382: aload #19
/*    */     //   384: invokevirtual Com3 : (Ljava/lang/Object;)V
/*    */     //   387: iinc #16, 1
/*    */     //   390: goto -> 224
/*    */     //   393: aload #15
/*    */     //   395: getfield Ht : B
/*    */     //   398: aload_0
/*    */     //   399: getfield Jh0 : B
/*    */     //   402: iand
/*    */     //   403: ifeq -> 429
/*    */     //   406: aload #15
/*    */     //   408: iconst_1
/*    */     //   409: invokevirtual GC0 : (I)Lf/pe0;
/*    */     //   412: ifnull -> 429
/*    */     //   415: aload_2
/*    */     //   416: aload #15
/*    */     //   418: iconst_1
/*    */     //   419: invokevirtual GC0 : (I)Lf/pe0;
/*    */     //   422: fload #13
/*    */     //   424: fload #10
/*    */     //   426: invokevirtual TB : (Lf/pe0;FF)V
/*    */     //   429: aload #14
/*    */     //   431: invokevirtual gc : ()Z
/*    */     //   434: ifeq -> 480
/*    */     //   437: aload #14
/*    */     //   439: dup
/*    */     //   440: invokevirtual gc : ()Z
/*    */     //   443: pop
/*    */     //   444: getfield Gl : Lf/fQ;
/*    */     //   447: invokevirtual r30 : ()Lf/Hc0;
/*    */     //   450: astore #13
/*    */     //   452: aload #13
/*    */     //   454: invokevirtual hasNext : ()Z
/*    */     //   457: ifeq -> 480
/*    */     //   460: aload #13
/*    */     //   462: invokevirtual next : ()Ljava/lang/Object;
/*    */     //   465: checkcast f/fZ
/*    */     //   468: aload_2
/*    */     //   469: iconst_0
/*    */     //   470: iload #12
/*    */     //   472: iload #9
/*    */     //   474: invokevirtual tU : (Lf/tH;III)V
/*    */     //   477: goto -> 452
/*    */     //   480: aload #15
/*    */     //   482: iconst_1
/*    */     //   483: istore #13
/*    */     //   485: getfield LpT9 : [[Lf/Ui0;
/*    */     //   488: dup
/*    */     //   489: astore #16
/*    */     //   491: ifnull -> 508
/*    */     //   494: aload #16
/*    */     //   496: iload #13
/*    */     //   498: aaload
/*    */     //   499: ifnull -> 508
/*    */     //   502: iconst_1
/*    */     //   503: istore #13
/*    */     //   505: goto -> 511
/*    */     //   508: iconst_0
/*    */     //   509: istore #13
/*    */     //   511: iload #13
/*    */     //   513: ifeq -> 702
/*    */     //   516: aload #14
/*    */     //   518: invokevirtual gc : ()Z
/*    */     //   521: ifne -> 702
/*    */     //   524: getstatic f/Xc0.jE : I
/*    */     //   527: ifle -> 702
/*    */     //   530: iconst_0
/*    */     //   531: istore #13
/*    */     //   533: iload #13
/*    */     //   535: iconst_4
/*    */     //   536: if_icmpge -> 702
/*    */     //   539: aload #15
/*    */     //   541: iconst_1
/*    */     //   542: iload #13
/*    */     //   544: invokevirtual cx0 : (II)Lf/Ui0;
/*    */     //   547: dup
/*    */     //   548: astore #14
/*    */     //   550: ifnull -> 696
/*    */     //   553: aload #14
/*    */     //   555: aload_0
/*    */     //   556: dup
/*    */     //   557: aload #14
/*    */     //   559: iload #13
/*    */     //   561: aload #14
/*    */     //   563: iload #13
/*    */     //   565: iconst_2
/*    */     //   566: irem
/*    */     //   567: bipush #8
/*    */     //   569: imul
/*    */     //   570: iload #12
/*    */     //   572: iadd
/*    */     //   573: i2f
/*    */     //   574: invokevirtual aR : (F)V
/*    */     //   577: iconst_2
/*    */     //   578: idiv
/*    */     //   579: bipush #8
/*    */     //   581: imul
/*    */     //   582: iload #9
/*    */     //   584: iadd
/*    */     //   585: i2f
/*    */     //   586: invokevirtual Zq0 : (F)V
/*    */     //   589: getfield ip0 : Lf/fQ;
/*    */     //   592: astore #16
/*    */     //   594: getfield M6 : Lf/Jc0;
/*    */     //   597: invokevirtual obtain : ()Ljava/lang/Object;
/*    */     //   600: checkcast f/bH0
/*    */     //   603: dup
/*    */     //   604: astore #17
/*    */     //   606: aload #14
/*    */     //   608: aload #17
/*    */     //   610: aload #14
/*    */     //   612: aload #17
/*    */     //   614: aload #14
/*    */     //   616: putfield Ns0 : Lf/Ui0;
/*    */     //   619: invokevirtual Vw : ()F
/*    */     //   622: putfield us : F
/*    */     //   625: invokevirtual UT : ()F
/*    */     //   628: putfield Gd : F
/*    */     //   631: getfield mP : F
/*    */     //   634: aload #14
/*    */     //   636: getfield zV : F
/*    */     //   639: fcmpl
/*    */     //   640: ifle -> 649
/*    */     //   643: iconst_1
/*    */     //   644: istore #18
/*    */     //   646: goto -> 652
/*    */     //   649: iconst_0
/*    */     //   650: istore #18
/*    */     //   652: aload #14
/*    */     //   654: aload #17
/*    */     //   656: iload #18
/*    */     //   658: putfield W5 : Z
/*    */     //   661: getfield WT : F
/*    */     //   664: aload #14
/*    */     //   666: getfield bh0 : F
/*    */     //   669: fcmpl
/*    */     //   670: ifle -> 679
/*    */     //   673: iconst_1
/*    */     //   674: istore #14
/*    */     //   676: goto -> 682
/*    */     //   679: iconst_0
/*    */     //   680: istore #14
/*    */     //   682: aload #16
/*    */     //   684: aload #17
/*    */     //   686: iload #14
/*    */     //   688: putfield KB0 : Z
/*    */     //   691: aload #17
/*    */     //   693: invokevirtual Com3 : (Ljava/lang/Object;)V
/*    */     //   696: iinc #13, 1
/*    */     //   699: goto -> 533
/*    */     //   702: iinc #11, 1
/*    */     //   705: goto -> 85
/*    */     //   708: iinc #1, 1
/*    */     //   711: goto -> 35
/*    */     //   714: iload_1
/*    */     //   715: iconst_1
/*    */     //   716: if_icmpeq -> 724
/*    */     //   719: iload_1
/*    */     //   720: iconst_2
/*    */     //   721: if_icmpne -> 1223
/*    */     //   724: iload_1
/*    */     //   725: iconst_1
/*    */     //   726: if_icmpne -> 737
/*    */     //   729: aload_0
/*    */     //   730: iconst_0
/*    */     //   731: putfield Sf : Z
/*    */     //   734: goto -> 750
/*    */     //   737: iload_1
/*    */     //   738: iconst_2
/*    */     //   739: if_icmpne -> 750
/*    */     //   742: aload_0
/*    */     //   743: getfield Sf : Z
/*    */     //   746: ifne -> 750
/*    */     //   749: return
/*    */     //   750: iconst_0
/*    */     //   751: istore #9
/*    */     //   753: iload #9
/*    */     //   755: iload #6
/*    */     //   757: if_icmpge -> 1223
/*    */     //   760: iload #9
/*    */     //   762: bipush #16
/*    */     //   764: imul
/*    */     //   765: iload #5
/*    */     //   767: iadd
/*    */     //   768: dup
/*    */     //   769: istore #10
/*    */     //   771: i2f
/*    */     //   772: dup
/*    */     //   773: fstore #11
/*    */     //   775: aload_3
/*    */     //   776: getfield pp0 : Lf/eo;
/*    */     //   779: getfield y : F
/*    */     //   782: fcmpg
/*    */     //   783: iflt -> 1217
/*    */     //   786: fload #11
/*    */     //   788: aload_3
/*    */     //   789: getfield s60 : Lf/eo;
/*    */     //   792: getfield y : F
/*    */     //   795: fcmpl
/*    */     //   796: ifle -> 802
/*    */     //   799: goto -> 1217
/*    */     //   802: iconst_0
/*    */     //   803: istore #12
/*    */     //   805: iload #12
/*    */     //   807: iload #7
/*    */     //   809: if_icmpge -> 1217
/*    */     //   812: iload #12
/*    */     //   814: bipush #16
/*    */     //   816: imul
/*    */     //   817: iload #4
/*    */     //   819: iadd
/*    */     //   820: dup
/*    */     //   821: istore #13
/*    */     //   823: i2f
/*    */     //   824: dup
/*    */     //   825: fstore #14
/*    */     //   827: aload_3
/*    */     //   828: getfield pp0 : Lf/eo;
/*    */     //   831: getfield x : F
/*    */     //   834: fcmpg
/*    */     //   835: iflt -> 1211
/*    */     //   838: fload #14
/*    */     //   840: aload_3
/*    */     //   841: getfield s60 : Lf/eo;
/*    */     //   844: getfield x : F
/*    */     //   847: fcmpl
/*    */     //   848: ifle -> 854
/*    */     //   851: goto -> 1211
/*    */     //   854: iload_1
/*    */     //   855: aload #8
/*    */     //   857: iload #12
/*    */     //   859: aaload
/*    */     //   860: iload #9
/*    */     //   862: aaload
/*    */     //   863: astore #15
/*    */     //   865: iconst_1
/*    */     //   866: if_icmpne -> 886
/*    */     //   869: aload #15
/*    */     //   871: invokevirtual bl0 : ()B
/*    */     //   874: iconst_3
/*    */     //   875: if_icmple -> 903
/*    */     //   878: aload_0
/*    */     //   879: iconst_1
/*    */     //   880: putfield Sf : Z
/*    */     //   883: goto -> 1211
/*    */     //   886: iload_1
/*    */     //   887: iconst_2
/*    */     //   888: if_icmpne -> 903
/*    */     //   891: aload #15
/*    */     //   893: invokevirtual bl0 : ()B
/*    */     //   896: iconst_4
/*    */     //   897: if_icmpge -> 903
/*    */     //   900: goto -> 1211
/*    */     //   903: aload #15
/*    */     //   905: getfield lS : Lf/a4;
/*    */     //   908: dup
/*    */     //   909: astore #16
/*    */     //   911: getfield Ht : B
/*    */     //   914: aload_0
/*    */     //   915: getfield Jh0 : B
/*    */     //   918: iand
/*    */     //   919: ifne -> 1159
/*    */     //   922: aload #16
/*    */     //   924: iconst_1
/*    */     //   925: invokevirtual GC0 : (I)Lf/pe0;
/*    */     //   928: ifnull -> 945
/*    */     //   931: aload_2
/*    */     //   932: aload #16
/*    */     //   934: iconst_1
/*    */     //   935: invokevirtual GC0 : (I)Lf/pe0;
/*    */     //   938: fload #14
/*    */     //   940: fload #11
/*    */     //   942: invokevirtual TB : (Lf/pe0;FF)V
/*    */     //   945: aload #16
/*    */     //   947: iconst_1
/*    */     //   948: istore #14
/*    */     //   950: getfield LpT9 : [[Lf/Ui0;
/*    */     //   953: dup
/*    */     //   954: astore #17
/*    */     //   956: ifnull -> 973
/*    */     //   959: aload #17
/*    */     //   961: iload #14
/*    */     //   963: aaload
/*    */     //   964: ifnull -> 973
/*    */     //   967: iconst_1
/*    */     //   968: istore #14
/*    */     //   970: goto -> 976
/*    */     //   973: iconst_0
/*    */     //   974: istore #14
/*    */     //   976: iload #14
/*    */     //   978: ifeq -> 1159
/*    */     //   981: getstatic f/Xc0.jE : I
/*    */     //   984: ifle -> 1159
/*    */     //   987: iconst_0
/*    */     //   988: istore #14
/*    */     //   990: iload #14
/*    */     //   992: iconst_4
/*    */     //   993: if_icmpge -> 1159
/*    */     //   996: aload #16
/*    */     //   998: iconst_1
/*    */     //   999: iload #14
/*    */     //   1001: invokevirtual cx0 : (II)Lf/Ui0;
/*    */     //   1004: dup
/*    */     //   1005: astore #17
/*    */     //   1007: ifnull -> 1153
/*    */     //   1010: aload #17
/*    */     //   1012: aload_0
/*    */     //   1013: dup
/*    */     //   1014: aload #17
/*    */     //   1016: iload #14
/*    */     //   1018: aload #17
/*    */     //   1020: iload #14
/*    */     //   1022: iconst_2
/*    */     //   1023: irem
/*    */     //   1024: bipush #8
/*    */     //   1026: imul
/*    */     //   1027: iload #13
/*    */     //   1029: iadd
/*    */     //   1030: i2f
/*    */     //   1031: invokevirtual aR : (F)V
/*    */     //   1034: iconst_2
/*    */     //   1035: idiv
/*    */     //   1036: bipush #8
/*    */     //   1038: imul
/*    */     //   1039: iload #10
/*    */     //   1041: iadd
/*    */     //   1042: i2f
/*    */     //   1043: invokevirtual Zq0 : (F)V
/*    */     //   1046: getfield ip0 : Lf/fQ;
/*    */     //   1049: astore #18
/*    */     //   1051: getfield M6 : Lf/Jc0;
/*    */     //   1054: invokevirtual obtain : ()Ljava/lang/Object;
/*    */     //   1057: checkcast f/bH0
/*    */     //   1060: dup
/*    */     //   1061: astore #19
/*    */     //   1063: aload #17
/*    */     //   1065: aload #19
/*    */     //   1067: aload #17
/*    */     //   1069: aload #19
/*    */     //   1071: aload #17
/*    */     //   1073: putfield Ns0 : Lf/Ui0;
/*    */     //   1076: invokevirtual Vw : ()F
/*    */     //   1079: putfield us : F
/*    */     //   1082: invokevirtual UT : ()F
/*    */     //   1085: putfield Gd : F
/*    */     //   1088: getfield mP : F
/*    */     //   1091: aload #17
/*    */     //   1093: getfield zV : F
/*    */     //   1096: fcmpl
/*    */     //   1097: ifle -> 1106
/*    */     //   1100: iconst_1
/*    */     //   1101: istore #20
/*    */     //   1103: goto -> 1109
/*    */     //   1106: iconst_0
/*    */     //   1107: istore #20
/*    */     //   1109: aload #17
/*    */     //   1111: aload #19
/*    */     //   1113: iload #20
/*    */     //   1115: putfield W5 : Z
/*    */     //   1118: getfield WT : F
/*    */     //   1121: aload #17
/*    */     //   1123: getfield bh0 : F
/*    */     //   1126: fcmpl
/*    */     //   1127: ifle -> 1136
/*    */     //   1130: iconst_1
/*    */     //   1131: istore #17
/*    */     //   1133: goto -> 1139
/*    */     //   1136: iconst_0
/*    */     //   1137: istore #17
/*    */     //   1139: aload #18
/*    */     //   1141: aload #19
/*    */     //   1143: iload #17
/*    */     //   1145: putfield KB0 : Z
/*    */     //   1148: aload #19
/*    */     //   1150: invokevirtual Com3 : (Ljava/lang/Object;)V
/*    */     //   1153: iinc #14, 1
/*    */     //   1156: goto -> 990
/*    */     //   1159: aload #15
/*    */     //   1161: invokevirtual gc : ()Z
/*    */     //   1164: ifeq -> 1211
/*    */     //   1167: aload #15
/*    */     //   1169: dup
/*    */     //   1170: invokevirtual gc : ()Z
/*    */     //   1173: pop
/*    */     //   1174: getfield Gl : Lf/fQ;
/*    */     //   1177: invokevirtual r30 : ()Lf/Hc0;
/*    */     //   1180: astore #14
/*    */     //   1182: aload #14
/*    */     //   1184: invokevirtual hasNext : ()Z
/*    */     //   1187: ifeq -> 1211
/*    */     //   1190: aload #14
/*    */     //   1192: invokevirtual next : ()Ljava/lang/Object;
/*    */     //   1195: checkcast f/fZ
/*    */     //   1198: aload_2
/*    */     //   1199: bipush #10
/*    */     //   1201: iload #13
/*    */     //   1203: iload #10
/*    */     //   1205: invokevirtual tU : (Lf/tH;III)V
/*    */     //   1208: goto -> 1182
/*    */     //   1211: iinc #12, 1
/*    */     //   1214: goto -> 805
/*    */     //   1217: iinc #9, 1
/*    */     //   1220: goto -> 753
/*    */     //   1223: return
/*    */     // Line number table:
/*    */     //   Java source line number -> byte code offset
/*    */     //   #1	-> 144
/*    */     //   #2	-> 151
/*    */     //   #3	-> 176
/*    */     //   #4	-> 209
/*    */     //   #5	-> 307
/*    */     //   #6	-> 310
/*    */     //   #7	-> 322
/*    */     //   #8	-> 349
/*    */     //   #9	-> 352
/*    */     //   #10	-> 379
/*    */     //   #11	-> 384
/*    */     //   #12	-> 395
/*    */     //   #13	-> 399
/*    */     //   #14	-> 440
/*    */     //   #15	-> 447
/*    */     //   #16	-> 485
/*    */     //   #17	-> 518
/*    */     //   #18	-> 616
/*    */     //   #19	-> 619
/*    */     //   #20	-> 631
/*    */     //   #21	-> 658
/*    */     //   #22	-> 661
/*    */     //   #23	-> 688
/*    */     //   #24	-> 693
/*    */     //   #25	-> 905
/*    */     //   #26	-> 911
/*    */     //   #27	-> 915
/*    */     //   #28	-> 950
/*    */     //   #29	-> 981
/*    */     //   #30	-> 1073
/*    */     //   #31	-> 1076
/*    */     //   #32	-> 1088
/*    */     //   #33	-> 1115
/*    */     //   #34	-> 1118
/*    */     //   #35	-> 1145
/*    */     //   #36	-> 1150
/*    */     //   #37	-> 1170
/*    */     //   #38	-> 1177
/*    */   }
/*    */   
/*    */   public final void pm0(tH paramtH, Tm paramTm, boolean paramBoolean) {
/*    */     // Byte code:
/*    */     //   0: getstatic f/km.a3 : Lf/vh0;
/*    */     //   3: dup
/*    */     //   4: astore #4
/*    */     //   6: ifnonnull -> 10
/*    */     //   9: return
/*    */     //   10: aload #4
/*    */     //   12: invokevirtual iterator : ()Ljava/util/Iterator;
/*    */     //   15: astore #4
/*    */     //   17: aload #4
/*    */     //   19: invokeinterface hasNext : ()Z
/*    */     //   24: ifeq -> 203
/*    */     //   27: aload #4
/*    */     //   29: invokeinterface next : ()Ljava/lang/Object;
/*    */     //   34: checkcast f/tc
/*    */     //   37: dup
/*    */     //   38: astore #5
/*    */     //   40: invokevirtual zl : ()Z
/*    */     //   43: ifeq -> 49
/*    */     //   46: goto -> 17
/*    */     //   49: aload #5
/*    */     //   51: getfield HW : Lf/G5;
/*    */     //   54: dup
/*    */     //   55: astore #6
/*    */     //   57: getfield kD0 : B
/*    */     //   60: aload_0
/*    */     //   61: getfield cA : B
/*    */     //   64: if_icmpne -> 141
/*    */     //   67: aload #6
/*    */     //   69: getfield vu0 : B
/*    */     //   72: aload_0
/*    */     //   73: getfield VZ : B
/*    */     //   76: if_icmpne -> 141
/*    */     //   79: aload #5
/*    */     //   81: getfield Ae : Lf/zk0;
/*    */     //   84: ifnull -> 193
/*    */     //   87: aload #5
/*    */     //   89: invokevirtual AJ0 : ()Z
/*    */     //   92: ifeq -> 193
/*    */     //   95: aload #5
/*    */     //   97: getfield Ae : Lf/zk0;
/*    */     //   100: dup
/*    */     //   101: astore #6
/*    */     //   103: getfield HW : Lf/G5;
/*    */     //   106: dup
/*    */     //   107: astore #7
/*    */     //   109: getfield kD0 : B
/*    */     //   112: aload_0
/*    */     //   113: getfield cA : B
/*    */     //   116: if_icmpne -> 193
/*    */     //   119: aload #7
/*    */     //   121: getfield vu0 : B
/*    */     //   124: aload_0
/*    */     //   125: getfield VZ : B
/*    */     //   128: if_icmpne -> 193
/*    */     //   131: aload_0
/*    */     //   132: aload #6
/*    */     //   134: iload_3
/*    */     //   135: invokevirtual Jj : (Lf/tc;Z)V
/*    */     //   138: goto -> 193
/*    */     //   141: aload #5
/*    */     //   143: getfield Ae : Lf/zk0;
/*    */     //   146: ifnull -> 17
/*    */     //   149: aload #5
/*    */     //   151: invokevirtual AJ0 : ()Z
/*    */     //   154: ifeq -> 17
/*    */     //   157: aload #5
/*    */     //   159: getfield Ae : Lf/zk0;
/*    */     //   162: dup
/*    */     //   163: astore #5
/*    */     //   165: getfield HW : Lf/G5;
/*    */     //   168: dup
/*    */     //   169: astore #6
/*    */     //   171: getfield kD0 : B
/*    */     //   174: aload_0
/*    */     //   175: getfield cA : B
/*    */     //   178: if_icmpne -> 17
/*    */     //   181: aload #6
/*    */     //   183: getfield vu0 : B
/*    */     //   186: aload_0
/*    */     //   187: getfield VZ : B
/*    */     //   190: if_icmpne -> 17
/*    */     //   193: aload_0
/*    */     //   194: aload #5
/*    */     //   196: iload_3
/*    */     //   197: invokevirtual Jj : (Lf/tc;Z)V
/*    */     //   200: goto -> 17
/*    */     //   203: getstatic f/km.a3 : Lf/vh0;
/*    */     //   206: invokevirtual iterator : ()Ljava/util/Iterator;
/*    */     //   209: astore #4
/*    */     //   211: aload #4
/*    */     //   213: invokeinterface hasNext : ()Z
/*    */     //   218: ifeq -> 283
/*    */     //   221: aload #4
/*    */     //   223: invokeinterface next : ()Ljava/lang/Object;
/*    */     //   228: checkcast f/tc
/*    */     //   231: dup
/*    */     //   232: astore #5
/*    */     //   234: invokevirtual zl : ()Z
/*    */     //   237: ifne -> 243
/*    */     //   240: goto -> 211
/*    */     //   243: aload #5
/*    */     //   245: getfield HW : Lf/G5;
/*    */     //   248: dup
/*    */     //   249: astore #6
/*    */     //   251: getfield kD0 : B
/*    */     //   254: aload_0
/*    */     //   255: getfield cA : B
/*    */     //   258: if_icmpne -> 211
/*    */     //   261: aload #6
/*    */     //   263: getfield vu0 : B
/*    */     //   266: aload_0
/*    */     //   267: getfield VZ : B
/*    */     //   270: if_icmpne -> 211
/*    */     //   273: aload_0
/*    */     //   274: aload #5
/*    */     //   276: iload_3
/*    */     //   277: invokevirtual Jj : (Lf/tc;Z)V
/*    */     //   280: goto -> 211
/*    */     //   283: getstatic f/km.a3 : Lf/vh0;
/*    */     //   286: getfield Ct : Lf/Jo;
/*    */     //   289: dup
/*    */     //   290: astore #4
/*    */     //   292: ifnull -> 383
/*    */     //   295: aload #4
/*    */     //   297: invokevirtual AJ0 : ()Z
/*    */     //   300: ifeq -> 346
/*    */     //   303: aload #4
/*    */     //   305: getfield Ae : Lf/zk0;
/*    */     //   308: dup
/*    */     //   309: astore #5
/*    */     //   311: getfield HW : Lf/G5;
/*    */     //   314: dup
/*    */     //   315: astore #6
/*    */     //   317: getfield kD0 : B
/*    */     //   320: aload_0
/*    */     //   321: getfield cA : B
/*    */     //   324: if_icmpne -> 346
/*    */     //   327: aload #6
/*    */     //   329: getfield vu0 : B
/*    */     //   332: aload_0
/*    */     //   333: getfield VZ : B
/*    */     //   336: if_icmpne -> 346
/*    */     //   339: aload_0
/*    */     //   340: aload #5
/*    */     //   342: iload_3
/*    */     //   343: invokevirtual Jj : (Lf/tc;Z)V
/*    */     //   346: aload #4
/*    */     //   348: getfield HW : Lf/G5;
/*    */     //   351: dup
/*    */     //   352: astore #5
/*    */     //   354: getfield kD0 : B
/*    */     //   357: aload_0
/*    */     //   358: getfield cA : B
/*    */     //   361: if_icmpne -> 383
/*    */     //   364: aload #5
/*    */     //   366: getfield vu0 : B
/*    */     //   369: aload_0
/*    */     //   370: getfield VZ : B
/*    */     //   373: if_icmpne -> 383
/*    */     //   376: aload_0
/*    */     //   377: aload #4
/*    */     //   379: iload_3
/*    */     //   380: invokevirtual Jj : (Lf/tc;Z)V
/*    */     //   383: iconst_0
/*    */     //   384: istore_3
/*    */     //   385: iload_3
/*    */     //   386: aload_0
/*    */     //   387: getfield nT : I
/*    */     //   390: if_icmpge -> 1154
/*    */     //   393: iconst_0
/*    */     //   394: istore #4
/*    */     //   396: iload #4
/*    */     //   398: aload_0
/*    */     //   399: getfield Fk0 : I
/*    */     //   402: if_icmpge -> 1148
/*    */     //   405: aload_0
/*    */     //   406: getfield im0 : [[Lf/g40;
/*    */     //   409: iload #4
/*    */     //   411: aaload
/*    */     //   412: iload_3
/*    */     //   413: aaload
/*    */     //   414: dup
/*    */     //   415: astore #5
/*    */     //   417: aload_0
/*    */     //   418: getfield Tu0 : [[Lf/xW;
/*    */     //   421: iload #4
/*    */     //   423: aaload
/*    */     //   424: iload_3
/*    */     //   425: aaload
/*    */     //   426: astore #6
/*    */     //   428: ifnull -> 1060
/*    */     //   431: aload #5
/*    */     //   433: invokevirtual Z30 : ()Z
/*    */     //   436: ifeq -> 1060
/*    */     //   439: aload #5
/*    */     //   441: invokevirtual Ng0 : ()Lf/tc;
/*    */     //   444: invokevirtual default : ()Lf/static;
/*    */     //   447: dup
/*    */     //   448: astore #7
/*    */     //   450: aload_2
/*    */     //   451: aload #7
/*    */     //   453: dup
/*    */     //   454: dup2
/*    */     //   455: dup2
/*    */     //   456: dup2
/*    */     //   457: dup2
/*    */     //   458: getstatic f/zm0.u20 : J
/*    */     //   461: aload #7
/*    */     //   463: getfield zS : Lf/tc;
/*    */     //   466: getfield pm : Lf/d7;
/*    */     //   469: dup
/*    */     //   470: astore #8
/*    */     //   472: getfield HQ : J
/*    */     //   475: lsub
/*    */     //   476: putfield xu0 : J
/*    */     //   479: aload #8
/*    */     //   481: getfield J4 : Z
/*    */     //   484: putfield CK : Z
/*    */     //   487: aload #8
/*    */     //   489: getfield eF : Z
/*    */     //   492: putfield GQ : Z
/*    */     //   495: iconst_1
/*    */     //   496: putfield v : Z
/*    */     //   499: getfield lpt8 : Lf/eo;
/*    */     //   502: aload #8
/*    */     //   504: getfield cOm3 : Lf/eo;
/*    */     //   507: invokevirtual JL : (Lf/eo;)Lf/eo;
/*    */     //   510: pop
/*    */     //   511: getfield lpt8 : Lf/eo;
/*    */     //   514: ldc_w 16.0
/*    */     //   517: invokevirtual uu : (F)Lf/eo;
/*    */     //   520: pop
/*    */     //   521: getfield lpt8 : Lf/eo;
/*    */     //   524: dup
/*    */     //   525: dup2
/*    */     //   526: dup2
/*    */     //   527: dup2
/*    */     //   528: astore #8
/*    */     //   530: getfield x : F
/*    */     //   533: aload_0
/*    */     //   534: getfield Ew : I
/*    */     //   537: i2f
/*    */     //   538: fadd
/*    */     //   539: dup
/*    */     //   540: fstore #9
/*    */     //   542: putfield x : F
/*    */     //   545: getfield y : F
/*    */     //   548: aload_0
/*    */     //   549: getfield n1 : I
/*    */     //   552: iconst_2
/*    */     //   553: isub
/*    */     //   554: i2f
/*    */     //   555: fadd
/*    */     //   556: dup
/*    */     //   557: fstore #10
/*    */     //   559: putfield y : F
/*    */     //   562: fconst_0
/*    */     //   563: putfield z : F
/*    */     //   566: fload #9
/*    */     //   568: f2i
/*    */     //   569: i2f
/*    */     //   570: putfield x : F
/*    */     //   573: fload #10
/*    */     //   575: f2i
/*    */     //   576: i2f
/*    */     //   577: putfield y : F
/*    */     //   580: getfield ao : Lf/eo;
/*    */     //   583: dup
/*    */     //   584: astore #9
/*    */     //   586: aload #8
/*    */     //   588: dup
/*    */     //   589: dup
/*    */     //   590: aload #9
/*    */     //   592: invokevirtual getClass : ()Ljava/lang/Class;
/*    */     //   595: pop
/*    */     //   596: getfield x : F
/*    */     //   599: fstore #8
/*    */     //   601: getfield y : F
/*    */     //   604: fstore #9
/*    */     //   606: getfield z : F
/*    */     //   609: fstore #10
/*    */     //   611: fload #8
/*    */     //   613: fload #9
/*    */     //   615: fload #10
/*    */     //   617: invokevirtual TG0 : (FFF)Lf/eo;
/*    */     //   620: pop
/*    */     //   621: getfield ao : Lf/eo;
/*    */     //   624: aload #7
/*    */     //   626: getfield Bm0 : Lf/eo;
/*    */     //   629: invokevirtual zT : (Lf/eo;)Lf/eo;
/*    */     //   632: pop
/*    */     //   633: getfield ao : Lf/eo;
/*    */     //   636: dup
/*    */     //   637: dup
/*    */     //   638: dup2
/*    */     //   639: getfield x : F
/*    */     //   642: ldc_w 8.0
/*    */     //   645: fadd
/*    */     //   646: putfield x : F
/*    */     //   649: getfield y : F
/*    */     //   652: ldc_w 10.0
/*    */     //   655: fsub
/*    */     //   656: putfield y : F
/*    */     //   659: invokevirtual w8 : (Lf/eo;)Lf/eo;
/*    */     //   662: pop
/*    */     //   663: getfield zS : Lf/tc;
/*    */     //   666: dup
/*    */     //   667: astore #8
/*    */     //   669: getfield pm : Lf/d7;
/*    */     //   672: getfield Mv : Lf/nl;
/*    */     //   675: dup
/*    */     //   676: astore #9
/*    */     //   678: getstatic f/nl.Qp0 : Lf/nl;
/*    */     //   681: if_acmpeq -> 757
/*    */     //   684: aload #9
/*    */     //   686: getstatic f/nl.ih : Lf/nl;
/*    */     //   689: if_acmpeq -> 757
/*    */     //   692: aload #9
/*    */     //   694: getstatic f/nl.lh0 : Lf/nl;
/*    */     //   697: if_acmpeq -> 757
/*    */     //   700: aload #9
/*    */     //   702: getstatic f/nl.xr : Lf/nl;
/*    */     //   705: if_acmpeq -> 757
/*    */     //   708: aload #9
/*    */     //   710: getstatic f/nl.aV : Lf/nl;
/*    */     //   713: if_acmpeq -> 757
/*    */     //   716: aload #9
/*    */     //   718: getstatic f/nl.Gp0 : Lf/nl;
/*    */     //   721: if_acmpeq -> 757
/*    */     //   724: aload #9
/*    */     //   726: getstatic f/nl.xr0 : Lf/nl;
/*    */     //   729: if_acmpne -> 735
/*    */     //   732: goto -> 757
/*    */     //   735: aload #8
/*    */     //   737: getfield kK0 : Lf/Z50;
/*    */     //   740: getstatic f/Z50.xO : Lf/Z50;
/*    */     //   743: if_acmpne -> 765
/*    */     //   746: aload #8
/*    */     //   748: getstatic f/Z50.yx0 : Lf/Z50;
/*    */     //   751: invokevirtual q90 : (Lf/Z50;)V
/*    */     //   754: goto -> 765
/*    */     //   757: aload #8
/*    */     //   759: getstatic f/Z50.xO : Lf/Z50;
/*    */     //   762: invokevirtual q90 : (Lf/Z50;)V
/*    */     //   765: aload #7
/*    */     //   767: dup
/*    */     //   768: getfield zS : Lf/tc;
/*    */     //   771: getfield pm : Lf/d7;
/*    */     //   774: invokevirtual si0 : ()V
/*    */     //   777: getfield zS : Lf/tc;
/*    */     //   780: invokevirtual yO : ()Z
/*    */     //   783: ifeq -> 863
/*    */     //   786: aload #7
/*    */     //   788: iconst_0
/*    */     //   789: istore #8
/*    */     //   791: getfield zS : Lf/tc;
/*    */     //   794: dup
/*    */     //   795: invokevirtual getClass : ()Ljava/lang/Class;
/*    */     //   798: pop
/*    */     //   799: instanceof f/Jo
/*    */     //   802: ifeq -> 818
/*    */     //   805: aload #7
/*    */     //   807: getfield zS : Lf/tc;
/*    */     //   810: checkcast f/Jo
/*    */     //   813: getfield CC : B
/*    */     //   816: istore #8
/*    */     //   818: getstatic f/km.si0 : Lf/My;
/*    */     //   821: aload #7
/*    */     //   823: dup
/*    */     //   824: getfield zS : Lf/tc;
/*    */     //   827: dup
/*    */     //   828: astore #9
/*    */     //   830: invokevirtual a : ()Ljava/lang/String;
/*    */     //   833: astore #10
/*    */     //   835: getfield ao : Lf/eo;
/*    */     //   838: astore #11
/*    */     //   840: aload #9
/*    */     //   842: aload #7
/*    */     //   844: getfield zS : Lf/tc;
/*    */     //   847: getfield kK0 : Lf/Z50;
/*    */     //   850: astore #9
/*    */     //   852: iload #8
/*    */     //   854: aload #10
/*    */     //   856: aload #11
/*    */     //   858: aload #9
/*    */     //   860: invokevirtual NO : (Lf/tc;ILjava/lang/String;Lf/eo;Lf/Z50;)V
/*    */     //   863: aload #7
/*    */     //   865: getfield zS : Lf/tc;
/*    */     //   868: invokevirtual zl : ()Z
/*    */     //   871: ifeq -> 899
/*    */     //   874: getstatic f/km.si0 : Lf/My;
/*    */     //   877: aload #7
/*    */     //   879: getfield zS : Lf/tc;
/*    */     //   882: dup
/*    */     //   883: aload #7
/*    */     //   885: getfield ao : Lf/eo;
/*    */     //   888: astore #8
/*    */     //   890: getfield kK0 : Lf/Z50;
/*    */     //   893: aload #8
/*    */     //   895: swap
/*    */     //   896: invokevirtual dy0 : (Lf/tc;Lf/eo;Lf/Z50;)V
/*    */     //   899: aload #7
/*    */     //   901: getfield zS : Lf/tc;
/*    */     //   904: dup
/*    */     //   905: invokevirtual getClass : ()Ljava/lang/Class;
/*    */     //   908: pop
/*    */     //   909: instanceof f/zk0
/*    */     //   912: ifne -> 938
/*    */     //   915: getstatic f/km.kH0 : Lf/Qz0;
/*    */     //   918: aload #7
/*    */     //   920: dup
/*    */     //   921: getfield zS : Lf/tc;
/*    */     //   924: getfield Jg : I
/*    */     //   927: istore #8
/*    */     //   929: getfield ao : Lf/eo;
/*    */     //   932: iload #8
/*    */     //   934: swap
/*    */     //   935: invokevirtual w8 : (ILf/eo;)V
/*    */     //   938: aload #7
/*    */     //   940: aload_1
/*    */     //   941: aload #7
/*    */     //   943: getfield zS : Lf/tc;
/*    */     //   946: getfield pm : Lf/d7;
/*    */     //   949: getfield Mv : Lf/nl;
/*    */     //   952: astore #8
/*    */     //   954: aconst_null
/*    */     //   955: aconst_null
/*    */     //   956: aconst_null
/*    */     //   957: aload #8
/*    */     //   959: invokevirtual Vn : (Lf/tH;Lf/K70;Lf/Ih0;Lf/fo0;Lf/nl;)Z
/*    */     //   962: ifeq -> 968
/*    */     //   965: goto -> 431
/*    */     //   968: aload #7
/*    */     //   970: getfield zS : Lf/tc;
/*    */     //   973: dup
/*    */     //   974: astore #8
/*    */     //   976: instanceof f/Kr0
/*    */     //   979: ifeq -> 999
/*    */     //   982: aload #8
/*    */     //   984: checkcast f/Kr0
/*    */     //   987: getfield Lq : Lf/V4;
/*    */     //   990: getfield L7 : Z
/*    */     //   993: ifeq -> 999
/*    */     //   996: goto -> 431
/*    */     //   999: aload #7
/*    */     //   1001: aload_1
/*    */     //   1002: invokevirtual fY : (Lf/tH;)Z
/*    */     //   1005: ifeq -> 1011
/*    */     //   1008: goto -> 431
/*    */     //   1011: aload #7
/*    */     //   1013: aload_1
/*    */     //   1014: aconst_null
/*    */     //   1015: aconst_null
/*    */     //   1016: invokevirtual kE0 : (Lf/tH;Lf/K70;Lf/fo0;)Z
/*    */     //   1019: ifeq -> 1025
/*    */     //   1022: goto -> 431
/*    */     //   1025: aload #7
/*    */     //   1027: invokevirtual DE0 : ()B
/*    */     //   1030: dup
/*    */     //   1031: istore #8
/*    */     //   1033: iconst_3
/*    */     //   1034: if_icmpne -> 1040
/*    */     //   1037: iinc #8, -1
/*    */     //   1040: aload #7
/*    */     //   1042: aload_1
/*    */     //   1043: aload #7
/*    */     //   1045: getfield zS : Lf/tc;
/*    */     //   1048: invokevirtual D4 : ()S
/*    */     //   1051: iload #8
/*    */     //   1053: iconst_0
/*    */     //   1054: invokevirtual HY : (Lf/tH;IIZ)V
/*    */     //   1057: goto -> 431
/*    */     //   1060: aload #6
/*    */     //   1062: invokevirtual gc : ()Z
/*    */     //   1065: ifeq -> 1142
/*    */     //   1068: aload #6
/*    */     //   1070: dup
/*    */     //   1071: invokevirtual gc : ()Z
/*    */     //   1074: pop
/*    */     //   1075: getfield Gl : Lf/fQ;
/*    */     //   1078: invokevirtual r30 : ()Lf/Hc0;
/*    */     //   1081: astore #5
/*    */     //   1083: aload #5
/*    */     //   1085: invokevirtual hasNext : ()Z
/*    */     //   1088: ifeq -> 1142
/*    */     //   1091: aload #5
/*    */     //   1093: invokevirtual next : ()Ljava/lang/Object;
/*    */     //   1096: checkcast f/fZ
/*    */     //   1099: aload_1
/*    */     //   1100: iload_3
/*    */     //   1101: aload_0
/*    */     //   1102: iload #4
/*    */     //   1104: aload_0
/*    */     //   1105: getfield Ew : I
/*    */     //   1108: istore #6
/*    */     //   1110: bipush #16
/*    */     //   1112: imul
/*    */     //   1113: iload #6
/*    */     //   1115: iadd
/*    */     //   1116: istore #6
/*    */     //   1118: getfield n1 : I
/*    */     //   1121: istore #7
/*    */     //   1123: bipush #16
/*    */     //   1125: imul
/*    */     //   1126: iload #7
/*    */     //   1128: iadd
/*    */     //   1129: istore #7
/*    */     //   1131: iconst_1
/*    */     //   1132: iload #6
/*    */     //   1134: iload #7
/*    */     //   1136: invokevirtual tU : (Lf/tH;III)V
/*    */     //   1139: goto -> 1083
/*    */     //   1142: iinc #4, 1
/*    */     //   1145: goto -> 396
/*    */     //   1148: iinc #3, 1
/*    */     //   1151: goto -> 385
/*    */     //   1154: return
/*    */     // Line number table:
/*    */     //   Java source line number -> byte code offset
/*    */     //   #1	-> 51
/*    */     //   #2	-> 57
/*    */     //   #3	-> 61
/*    */     //   #4	-> 69
/*    */     //   #5	-> 73
/*    */     //   #6	-> 81
/*    */     //   #7	-> 89
/*    */     //   #8	-> 97
/*    */     //   #9	-> 103
/*    */     //   #10	-> 109
/*    */     //   #11	-> 113
/*    */     //   #12	-> 121
/*    */     //   #13	-> 125
/*    */     //   #14	-> 143
/*    */     //   #15	-> 151
/*    */     //   #16	-> 159
/*    */     //   #17	-> 165
/*    */     //   #18	-> 171
/*    */     //   #19	-> 175
/*    */     //   #20	-> 183
/*    */     //   #21	-> 187
/*    */     //   #22	-> 245
/*    */     //   #23	-> 251
/*    */     //   #24	-> 255
/*    */     //   #25	-> 263
/*    */     //   #26	-> 267
/*    */     //   #27	-> 286
/*    */     //   #28	-> 297
/*    */     //   #29	-> 305
/*    */     //   #30	-> 311
/*    */     //   #31	-> 317
/*    */     //   #32	-> 321
/*    */     //   #33	-> 329
/*    */     //   #34	-> 333
/*    */     //   #35	-> 348
/*    */     //   #36	-> 354
/*    */     //   #37	-> 358
/*    */     //   #38	-> 366
/*    */     //   #39	-> 370
/*    */     //   #40	-> 458
/*    */     //   #41	-> 463
/*    */     //   #42	-> 466
/*    */     //   #43	-> 472
/*    */     //   #44	-> 476
/*    */     //   #45	-> 481
/*    */     //   #46	-> 484
/*    */     //   #47	-> 489
/*    */     //   #48	-> 492
/*    */     //   #49	-> 504
/*    */     //   #50	-> 507
/*    */     //   #51	-> 534
/*    */     //   #52	-> 542
/*    */     //   #53	-> 549
/*    */     //   #54	-> 559
/*    */     //   #55	-> 596
/*    */     //   #56	-> 621
/*    */     //   #57	-> 669
/*    */     //   #58	-> 672
/*    */     //   #59	-> 678
/*    */     //   #60	-> 737
/*    */     //   #61	-> 740
/*    */     //   #62	-> 771
/*    */     //   #63	-> 774
/*    */     //   #64	-> 799
/*    */     //   #65	-> 807
/*    */     //   #66	-> 813
/*    */     //   #67	-> 818
/*    */     //   #68	-> 847
/*    */     //   #69	-> 860
/*    */     //   #70	-> 890
/*    */     //   #71	-> 896
/*    */     //   #72	-> 909
/*    */     //   #73	-> 915
/*    */     //   #74	-> 924
/*    */     //   #75	-> 929
/*    */     //   #76	-> 946
/*    */     //   #77	-> 949
/*    */     //   #78	-> 959
/*    */     //   #79	-> 987
/*    */     //   #80	-> 990
/*    */     //   #81	-> 1002
/*    */     //   #82	-> 1062
/*    */     //   #83	-> 1071
/*    */     //   #84	-> 1078
/*    */   }
/*    */   
/*    */   public IF0(byte paramByte1, byte paramByte2, byte paramByte3, byte paramByte4, int paramInt1, int paramInt2, int paramInt3, int paramInt4, byte paramByte5, byte paramByte6) {
/*    */     super(paramByte1, paramByte2, paramByte3, paramByte4);
/*    */     this.Fk0 = paramInt1;
/*    */     this.nT = paramInt2;
/*    */     this.Jf = paramByte5;
/*    */     this.kZ = paramByte6;
/*    */     this.hz0 = km.xn.L(paramInt3, paramInt4);
/*    */     this.Jh0 = (byte)((paramByte1 == 1) ? 16 : 32);
/*    */   } }


/* Location:              /Users/vnnsnnt/Documents/Codespace/JavaWorkspace/RedTrainer/src/main/java/org/trainer/client/PokeMMO.jar!/f/IF0.class
 * Java compiler version: 8 (52.0)
 * JD-Core Version:       1.1.3
 */