/*    */ package f;public abstract class iK extends yv { public iK(ByteBuffer paramByteBuffer, int paramInt) { super(paramByteBuffer, paramInt); } public final fH0 LU(boolean paramBoolean) { // Byte code:
/*    */     //   0: iload_1
/*    */     //   1: aload_0
/*    */     //   2: dup
/*    */     //   3: dup
/*    */     //   4: dup2
/*    */     //   5: new f/fH0
/*    */     //   8: astore_1
/*    */     //   9: getfield Ws : Ljava/nio/ByteBuffer;
/*    */     //   12: invokevirtual getInt : ()I
/*    */     //   15: istore_2
/*    */     //   16: invokevirtual au : ()Ljava/lang/String;
/*    */     //   19: astore_3
/*    */     //   20: getfield Ws : Ljava/nio/ByteBuffer;
/*    */     //   23: invokevirtual getInt : ()I
/*    */     //   26: istore #4
/*    */     //   28: getfield Ws : Ljava/nio/ByteBuffer;
/*    */     //   31: invokevirtual get : ()B
/*    */     //   34: istore #5
/*    */     //   36: getfield Ws : Ljava/nio/ByteBuffer;
/*    */     //   39: invokevirtual getInt : ()I
/*    */     //   42: istore #6
/*    */     //   44: ifeq -> 53
/*    */     //   47: lconst_0
/*    */     //   48: lstore #7
/*    */     //   50: goto -> 62
/*    */     //   53: aload_0
/*    */     //   54: getfield Ws : Ljava/nio/ByteBuffer;
/*    */     //   57: invokevirtual getLong : ()J
/*    */     //   60: lstore #7
/*    */     //   62: aload_0
/*    */     //   63: aload_1
/*    */     //   64: dup
/*    */     //   65: dup
/*    */     //   66: aload_0
/*    */     //   67: aload_1
/*    */     //   68: dup
/*    */     //   69: aload_0
/*    */     //   70: aload_1
/*    */     //   71: dup
/*    */     //   72: dup
/*    */     //   73: dup2
/*    */     //   74: aload_0
/*    */     //   75: dup
/*    */     //   76: dup2
/*    */     //   77: aload_1
/*    */     //   78: iload_2
/*    */     //   79: aload_3
/*    */     //   80: aload_0
/*    */     //   81: dup
/*    */     //   82: dup
/*    */     //   83: dup2
/*    */     //   84: dup2
/*    */     //   85: dup2
/*    */     //   86: dup2
/*    */     //   87: dup2
/*    */     //   88: dup2
/*    */     //   89: dup2
/*    */     //   90: dup2
/*    */     //   91: dup2
/*    */     //   92: dup2
/*    */     //   93: dup2
/*    */     //   94: dup2
/*    */     //   95: getfield Ws : Ljava/nio/ByteBuffer;
/*    */     //   98: invokevirtual getInt : ()I
/*    */     //   101: istore_2
/*    */     //   102: getfield Ws : Ljava/nio/ByteBuffer;
/*    */     //   105: invokevirtual getInt : ()I
/*    */     //   108: pop
/*    */     //   109: getfield Ws : Ljava/nio/ByteBuffer;
/*    */     //   112: invokevirtual get : ()B
/*    */     //   115: pop
/*    */     //   116: getfield Ws : Ljava/nio/ByteBuffer;
/*    */     //   119: invokevirtual getInt : ()I
/*    */     //   122: istore_3
/*    */     //   123: getfield Ws : Ljava/nio/ByteBuffer;
/*    */     //   126: invokevirtual getInt : ()I
/*    */     //   129: istore #9
/*    */     //   131: getfield Ws : Ljava/nio/ByteBuffer;
/*    */     //   134: invokevirtual getShort : ()S
/*    */     //   137: istore #10
/*    */     //   139: getfield Ws : Ljava/nio/ByteBuffer;
/*    */     //   142: invokevirtual getInt : ()I
/*    */     //   145: istore #11
/*    */     //   147: getfield Ws : Ljava/nio/ByteBuffer;
/*    */     //   150: invokevirtual get : ()B
/*    */     //   153: istore #12
/*    */     //   155: getfield Ws : Ljava/nio/ByteBuffer;
/*    */     //   158: invokevirtual get : ()B
/*    */     //   161: pop
/*    */     //   162: getfield Ws : Ljava/nio/ByteBuffer;
/*    */     //   165: invokevirtual get : ()B
/*    */     //   168: istore #13
/*    */     //   170: getfield Ws : Ljava/nio/ByteBuffer;
/*    */     //   173: invokevirtual getInt : ()I
/*    */     //   176: pop
/*    */     //   177: getfield Ws : Ljava/nio/ByteBuffer;
/*    */     //   180: invokevirtual get : ()B
/*    */     //   183: pop
/*    */     //   184: getfield Ws : Ljava/nio/ByteBuffer;
/*    */     //   187: invokevirtual get : ()B
/*    */     //   190: pop
/*    */     //   191: getfield Ws : Ljava/nio/ByteBuffer;
/*    */     //   194: invokevirtual get : ()B
/*    */     //   197: pop
/*    */     //   198: getfield Ws : Ljava/nio/ByteBuffer;
/*    */     //   201: invokevirtual get : ()B
/*    */     //   204: pop
/*    */     //   205: getfield Ws : Ljava/nio/ByteBuffer;
/*    */     //   208: invokevirtual get : ()B
/*    */     //   211: pop
/*    */     //   212: getfield Ws : Ljava/nio/ByteBuffer;
/*    */     //   215: invokevirtual get : ()B
/*    */     //   218: pop
/*    */     //   219: getfield Ws : Ljava/nio/ByteBuffer;
/*    */     //   222: invokevirtual get : ()B
/*    */     //   225: pop
/*    */     //   226: getfield Ws : Ljava/nio/ByteBuffer;
/*    */     //   229: invokevirtual get : ()B
/*    */     //   232: pop
/*    */     //   233: getfield Ws : Ljava/nio/ByteBuffer;
/*    */     //   236: invokevirtual getShort : ()S
/*    */     //   239: istore #14
/*    */     //   241: getfield Ws : Ljava/nio/ByteBuffer;
/*    */     //   244: invokevirtual get : ()B
/*    */     //   247: istore #15
/*    */     //   249: getfield Ws : Ljava/nio/ByteBuffer;
/*    */     //   252: invokevirtual getInt : ()I
/*    */     //   255: istore #16
/*    */     //   257: getfield Ws : Ljava/nio/ByteBuffer;
/*    */     //   260: invokevirtual get : ()B
/*    */     //   263: istore #17
/*    */     //   265: getfield Ws : Ljava/nio/ByteBuffer;
/*    */     //   268: invokevirtual get : ()B
/*    */     //   271: istore #18
/*    */     //   273: getfield Ws : Ljava/nio/ByteBuffer;
/*    */     //   276: invokevirtual get : ()B
/*    */     //   279: pop
/*    */     //   280: getfield Ws : Ljava/nio/ByteBuffer;
/*    */     //   283: invokevirtual get : ()B
/*    */     //   286: pop
/*    */     //   287: getfield Ws : Ljava/nio/ByteBuffer;
/*    */     //   290: invokevirtual get : ()B
/*    */     //   293: pop
/*    */     //   294: iload #4
/*    */     //   296: iload #5
/*    */     //   298: iload #6
/*    */     //   300: lload #7
/*    */     //   302: iload_2
/*    */     //   303: iload_3
/*    */     //   304: iload #9
/*    */     //   306: iload #10
/*    */     //   308: iload #11
/*    */     //   310: iload #12
/*    */     //   312: iload #13
/*    */     //   314: iload #14
/*    */     //   316: iload #15
/*    */     //   318: iload #16
/*    */     //   320: iload #17
/*    */     //   322: iload #18
/*    */     //   324: invokespecial <init> : (ILjava/lang/String;IBIJIIISIBBSBIBB)V
/*    */     //   327: getfield Ws : Ljava/nio/ByteBuffer;
/*    */     //   330: invokevirtual get : ()B
/*    */     //   333: istore_2
/*    */     //   334: getfield Ws : Ljava/nio/ByteBuffer;
/*    */     //   337: invokevirtual get : ()B
/*    */     //   340: istore_3
/*    */     //   341: getfield Ws : Ljava/nio/ByteBuffer;
/*    */     //   344: invokevirtual get : ()B
/*    */     //   347: istore #4
/*    */     //   349: invokevirtual R00 : ()I
/*    */     //   352: pop
/*    */     //   353: iload_2
/*    */     //   354: aload_0
/*    */     //   355: dup
/*    */     //   356: dup2
/*    */     //   357: getfield Ws : Ljava/nio/ByteBuffer;
/*    */     //   360: invokevirtual getShort : ()S
/*    */     //   363: istore_2
/*    */     //   364: getfield Ws : Ljava/nio/ByteBuffer;
/*    */     //   367: invokevirtual getShort : ()S
/*    */     //   370: istore #5
/*    */     //   372: getfield Ws : Ljava/nio/ByteBuffer;
/*    */     //   375: invokevirtual get : ()B
/*    */     //   378: pop
/*    */     //   379: getfield Ws : Ljava/nio/ByteBuffer;
/*    */     //   382: invokevirtual get : ()B
/*    */     //   385: pop
/*    */     //   386: putfield bv : B
/*    */     //   389: iload_3
/*    */     //   390: putfield GL0 : B
/*    */     //   393: iload #4
/*    */     //   395: putfield oI : B
/*    */     //   398: iload_2
/*    */     //   399: putfield WM : S
/*    */     //   402: iload #5
/*    */     //   404: putfield bg0 : S
/*    */     //   407: getfield Ws : Ljava/nio/ByteBuffer;
/*    */     //   410: invokevirtual getShort : ()S
/*    */     //   413: aload_0
/*    */     //   414: getfield Ws : Ljava/nio/ByteBuffer;
/*    */     //   417: invokevirtual getShort : ()S
/*    */     //   420: istore_2
/*    */     //   421: putfield rH0 : S
/*    */     //   424: iload_2
/*    */     //   425: putfield f6 : S
/*    */     //   428: getfield Ws : Ljava/nio/ByteBuffer;
/*    */     //   431: invokevirtual get : ()B
/*    */     //   434: invokestatic a8 : (B)Lf/m9;
/*    */     //   437: aload_0
/*    */     //   438: dup
/*    */     //   439: getfield Ws : Ljava/nio/ByteBuffer;
/*    */     //   442: invokevirtual getShort : ()S
/*    */     //   445: istore_2
/*    */     //   446: getfield Ws : Ljava/nio/ByteBuffer;
/*    */     //   449: invokevirtual getShort : ()S
/*    */     //   452: istore_3
/*    */     //   453: putfield YN : Lf/m9;
/*    */     //   456: iload_2
/*    */     //   457: putfield fa0 : S
/*    */     //   460: iload_3
/*    */     //   461: putfield Cr : S
/*    */     //   464: getfield Ws : Ljava/nio/ByteBuffer;
/*    */     //   467: invokevirtual get : ()B
/*    */     //   470: dup
/*    */     //   471: istore_2
/*    */     //   472: anewarray f/mA
/*    */     //   475: astore_3
/*    */     //   476: iconst_0
/*    */     //   477: istore #4
/*    */     //   479: iload #4
/*    */     //   481: iload_2
/*    */     //   482: if_icmpge -> 505
/*    */     //   485: aload_3
/*    */     //   486: iload #4
/*    */     //   488: aload_0
/*    */     //   489: getfield Ws : Ljava/nio/ByteBuffer;
/*    */     //   492: invokevirtual get : ()B
/*    */     //   495: invokestatic qq : (B)Lf/mA;
/*    */     //   498: aastore
/*    */     //   499: iinc #4, 1
/*    */     //   502: goto -> 479
/*    */     //   505: aload_1
/*    */     //   506: dup
/*    */     //   507: getfield k0 : Ljava/lang/Object;
/*    */     //   510: dup
/*    */     //   511: astore_0
/*    */     //   512: aload_1
/*    */     //   513: aload_0
/*    */     //   514: monitorenter
/*    */     //   515: aload_3
/*    */     //   516: putfield IV : [Lf/mA;
/*    */     //   519: monitorexit
/*    */     //   520: areturn
/*    */     //   521: astore_1
/*    */     //   522: aload_1
/*    */     //   523: aload_0
/*    */     //   524: monitorexit
/*    */     //   525: athrow
/*    */     // Line number table:
/*    */     //   Java source line number -> byte code offset
/*    */     //   #1	-> 9
/*    */     //   #2	-> 16
/*    */     //   #3	-> 20
/*    */     //   #4	-> 28
/*    */     //   #5	-> 36
/*    */     //   #6	-> 54
/*    */     //   #7	-> 95
/*    */     //   #8	-> 109
/*    */     //   #9	-> 116
/*    */     //   #10	-> 131
/*    */     //   #11	-> 139
/*    */     //   #12	-> 147
/*    */     //   #13	-> 170
/*    */     //   #14	-> 177
/*    */     //   #15	-> 233
/*    */     //   #16	-> 241
/*    */     //   #17	-> 249
/*    */     //   #18	-> 257
/*    */     //   #19	-> 324
/*    */     //   #20	-> 327
/*    */     //   #21	-> 349
/*    */     //   #22	-> 357
/*    */     //   #23	-> 372
/*    */     //   #24	-> 386
/*    */     //   #25	-> 407
/*    */     //   #26	-> 421
/*    */     //   #27	-> 428
/*    */     //   #28	-> 434
/*    */     //   #29	-> 439
/*    */     //   #30	-> 453
/*    */     //   #31	-> 464
/*    */     //   #32	-> 472
/*    */     //   #33	-> 489
/*    */     //   #34	-> 495
/*    */     //   #35	-> 507
/*    */     // Exception table:
/*    */     //   from	to	target	type
/*    */     //   515	520	521	finally
/*  1 */     //   522	525	521	finally } public final H10 ZV() { this(); H10 h10; (h10 = new H10())
/*  2 */       .goto = this.Ws.get();
/*  3 */     short s = this.Ws.getShort(); Vp0[] arrayOfVp0; int i; byte b;
/*  4 */     for (i = (arrayOfVp0 = Vp0.Jo).length, b = 0; b < i; ) { Vp0 vp0; if ((s & 
/*  5 */         1 << (vp0 = arrayOfVp0[b]).gw0) != 0)
/*    */       
/*  7 */       { short[] arrayOfShort = h10.Hd0;
/*  8 */         byte b1 = vp0.gw0; short s1, s2; if ((s2 = (short)((s1 = this.Ws.getShort()) & 0x3FF)) == 1023) s2 = -1;  arrayOfShort[b1] = s2;
/*  9 */         byte[] arrayOfByte = h10.Kw0; if ((s1 = (byte)((s1 & 0xFFFF) >> 10)) == 63) s1 = -1;  arrayOfByte[b1] = s1; }  b++; }  return h10; } public final yy pu() { int i = this.Ws.getInt(); String str1 = au(), str2 = au(); int j = this.Ws.getInt(); String str3 = au(); int k = this.Ws.getInt(); short s1 = this.Ws.getShort(), s2 = this.Ws.getShort(), s3 = this.Ws.getShort(), s4 = this.Ws.getShort(), s5 = this.Ws.getShort(); int m = this.Ws.getInt(); byte b; String[] arrayOfString; byte b1; for (arrayOfString = new String[b = this.Ws.get()], b1 = 0; b1 < b; ) { arrayOfString[b1] = au(); b1++; }  return new yy(i, str1, str2, j, str3, k, s1, s2, s3, s4, s5, m, arrayOfString); } public final LPT1 Ac() { byte b1 = this.Ws.get(); byte b = 0; byte b2; if (((b2 = this.Ws.get()) & 0x80) != 0) { b2 = (byte)(b2 & Byte.MAX_VALUE); b = this.Ws.get(); }  if (b2 != 5) if (b2 != 28) { if (b2 != 9 && b2 != 10 && b2 != 17) { if (b2 != 18) { int i; short[] arrayOfShort; byte b3; for (arrayOfShort = new short[i = R00()], b3 = 0; b3 < i; ) { arrayOfShort[b3] = this.Ws.getShort(); b3++; }  (new LPT1(b1, b2, arrayOfShort)).UP = b; return new LPT1(b1, b2, arrayOfShort); }  } else { (new LPT1(b1, b2, this.Ws.getInt())).UP = b; return new LPT1(b1, b2, this.Ws.getInt()); }  } else { (new LPT1(b1, b2)).UP = b; return new LPT1(b1, b2); }   String str = au(); (new LPT1(b1, b2, this)).UP = b; return new LPT1(b1, b2, this); } public final hj K1() { // Byte code:
/*    */     //   0: aload_0
/*    */     //   1: getfield Ws : Ljava/nio/ByteBuffer;
/*    */     //   4: invokevirtual get : ()B
/*    */     //   7: tableswitch default -> 40, -1 -> 235, 0 -> 183, 1 -> 130, 2 -> 99, 3 -> 54
/*    */     //   40: new f/fp
/*    */     //   43: dup
/*    */     //   44: iconst_0
/*    */     //   45: anewarray f/LPT1
/*    */     //   48: iconst_0
/*    */     //   49: swap
/*    */     //   50: invokespecial <init> : (I[Lf/LPT1;)V
/*    */     //   53: areturn
/*    */     //   54: new f/bo
/*    */     //   57: dup
/*    */     //   58: aload_0
/*    */     //   59: getfield Ws : Ljava/nio/ByteBuffer;
/*    */     //   62: invokevirtual get : ()B
/*    */     //   65: aload_0
/*    */     //   66: dup
/*    */     //   67: dup
/*    */     //   68: getfield Ws : Ljava/nio/ByteBuffer;
/*    */     //   71: invokevirtual get : ()B
/*    */     //   74: invokestatic ZD0 : (B)Lf/F40;
/*    */     //   77: astore_0
/*    */     //   78: getfield Ws : Ljava/nio/ByteBuffer;
/*    */     //   81: invokevirtual getShort : ()S
/*    */     //   84: istore_1
/*    */     //   85: getfield Ws : Ljava/nio/ByteBuffer;
/*    */     //   88: invokevirtual getShort : ()S
/*    */     //   91: istore_2
/*    */     //   92: aload_0
/*    */     //   93: iload_1
/*    */     //   94: iload_2
/*    */     //   95: invokespecial <init> : (BLf/F40;SS)V
/*    */     //   98: areturn
/*    */     //   99: new f/de0
/*    */     //   102: dup
/*    */     //   103: aload_0
/*    */     //   104: getfield Ws : Ljava/nio/ByteBuffer;
/*    */     //   107: invokevirtual get : ()B
/*    */     //   110: aload_0
/*    */     //   111: dup
/*    */     //   112: getfield Ws : Ljava/nio/ByteBuffer;
/*    */     //   115: invokevirtual getShort : ()S
/*    */     //   118: istore_0
/*    */     //   119: getfield Ws : Ljava/nio/ByteBuffer;
/*    */     //   122: invokevirtual get : ()B
/*    */     //   125: iload_0
/*    */     //   126: invokespecial <init> : (BBS)V
/*    */     //   129: areturn
/*    */     //   130: aload_0
/*    */     //   131: dup
/*    */     //   132: getfield Ws : Ljava/nio/ByteBuffer;
/*    */     //   135: invokevirtual get : ()B
/*    */     //   138: istore_1
/*    */     //   139: invokevirtual R00 : ()I
/*    */     //   142: dup
/*    */     //   143: istore_2
/*    */     //   144: newarray short
/*    */     //   146: astore_3
/*    */     //   147: iconst_0
/*    */     //   148: istore #4
/*    */     //   150: iload #4
/*    */     //   152: iload_2
/*    */     //   153: if_icmpge -> 173
/*    */     //   156: aload_3
/*    */     //   157: iload #4
/*    */     //   159: aload_0
/*    */     //   160: getfield Ws : Ljava/nio/ByteBuffer;
/*    */     //   163: invokevirtual getShort : ()S
/*    */     //   166: sastore
/*    */     //   167: iinc #4, 1
/*    */     //   170: goto -> 150
/*    */     //   173: new f/Zh0
/*    */     //   176: dup
/*    */     //   177: iload_1
/*    */     //   178: aload_3
/*    */     //   179: invokespecial <init> : (B[S)V
/*    */     //   182: areturn
/*    */     //   183: aload_0
/*    */     //   184: dup
/*    */     //   185: getfield Ws : Ljava/nio/ByteBuffer;
/*    */     //   188: invokevirtual getInt : ()I
/*    */     //   191: istore_1
/*    */     //   192: invokevirtual R00 : ()I
/*    */     //   195: dup
/*    */     //   196: istore_2
/*    */     //   197: anewarray f/LPT1
/*    */     //   200: astore_3
/*    */     //   201: iconst_0
/*    */     //   202: istore #4
/*    */     //   204: iload #4
/*    */     //   206: iload_2
/*    */     //   207: if_icmpge -> 225
/*    */     //   210: aload_3
/*    */     //   211: aload_0
/*    */     //   212: invokevirtual Ac : ()Lf/LPT1;
/*    */     //   215: iload #4
/*    */     //   217: swap
/*    */     //   218: aastore
/*    */     //   219: iinc #4, 1
/*    */     //   222: goto -> 204
/*    */     //   225: new f/fp
/*    */     //   228: dup
/*    */     //   229: iload_1
/*    */     //   230: aload_3
/*    */     //   231: invokespecial <init> : (I[Lf/LPT1;)V
/*    */     //   234: areturn
/*    */     //   235: aconst_null
/*    */     //   236: areturn
/*    */     // Line number table:
/*    */     //   Java source line number -> byte code offset
/*    */     //   #1	-> 1
/*    */     //   #2	-> 40
/*    */     //   #3	-> 59
/*    */     //   #4	-> 74
/*    */     //   #5	-> 78
/*    */     //   #6	-> 95
/*    */     //   #7	-> 104
/*    */     //   #8	-> 112
/*    */     //   #9	-> 119
/*    */     //   #10	-> 126
/*    */     //   #11	-> 132
/*    */     //   #12	-> 139
/*    */     //   #13	-> 160
/*    */     //   #14	-> 166
/*    */     //   #15	-> 185
/*  9 */     //   #16	-> 192 } public final qa0 OH() { qa0 qa0 = new qa0(); int i = this.Ws.getInt(); byte b1 = this.Ws.get(), b2 = this.Ws.get(); String str = au(); short s = this.Ws.getShort(); byte b3 = this.Ws.get(); ky ky = ky.Mt0(this.Ws.get()); long l = this.Ws.getLong(); byte b4 = this.Ws.get(); int j = this.Ws.getInt(); byte b5 = this.Ws.get(); if (this.Ws.get() == 1) { bool1 = true; } else { bool1 = false; }  if (this.Ws.get() == 1) { bool2 = true; } else { bool2 = false; }  this.Ws.get(); this(i, b1, b2, str, s, b3, ky, l, b4, j, b5, bool1, bool2); boolean bool1, bool2; return qa0; } public final FV k60() { String str = au(); this(this.Ws.get(), this.Ws.getInt(), str); FV fV; (fV = new FV()).k0 = this.Ws.get(); Vp0 vp04 = Vp0.MP; short[] arrayOfShort4 = fV.zi; byte b = vp04.TH0; short s2, s4; if ((s4 = (short)((s2 = this.Ws.getShort()) & 0x3FF)) == 1023) s4 = -1;  arrayOfShort4[b] = s4;
/* 10 */     byte[] arrayOfByte4 = fV.hL; if ((s2 = (byte)((s2 & 0xFFFF) >> 10)) == 63) s2 = -1;  arrayOfByte4[b] = s2;
/* 11 */     Vp0 vp03 = Vp0.K7;
/*    */     
/* 13 */     short[] arrayOfShort3 = fV.zi;
/* 14 */     b = vp03.TH0; if ((s4 = (short)((s2 = this.Ws.getShort()) & 0x3FF)) == 1023) s4 = -1;  arrayOfShort3[b] = s4;
/* 15 */     byte[] arrayOfByte3 = fV.hL; if ((s2 = (byte)((s2 & 0xFFFF) >> 10)) == 63) s2 = -1;  arrayOfByte3[b] = s2;
/* 16 */     Vp0 vp02 = Vp0.Pa0;
/*    */     
/* 18 */     short[] arrayOfShort2 = fV.zi;
/* 19 */     b = vp02.TH0; if ((s4 = (short)((s2 = this.Ws.getShort()) & 0x3FF)) == 1023) s4 = -1;  arrayOfShort2[b] = s4;
/* 20 */     byte[] arrayOfByte2 = fV.hL; if ((s2 = (byte)((s2 & 0xFFFF) >> 10)) == 63) s2 = -1;  arrayOfByte2[b] = s2;
/* 21 */     Vp0 vp01 = Vp0.bG;
/*    */     
/* 23 */     short[] arrayOfShort1 = fV.zi;
/* 24 */     s2 = this.TH0; short s1, s3; if ((s3 = (short)((s1 = this.Ws.getShort()) & 0x3FF)) == 1023) s3 = -1;  this[s2] = s3;
/* 25 */     byte[] arrayOfByte1 = fV.hL; if ((s1 = (byte)((s1 & 0xFFFF) >> 10)) == 63) s1 = -1;  this[s2] = s1; return fV; } public final A30 Com5(int paramInt) { // Byte code:
/*    */     //   0: aload_0
/*    */     //   1: dup
/*    */     //   2: dup
/*    */     //   3: getfield Ws : Ljava/nio/ByteBuffer;
/*    */     //   6: invokevirtual get : ()B
/*    */     //   9: istore_1
/*    */     //   10: getfield Ws : Ljava/nio/ByteBuffer;
/*    */     //   13: invokevirtual get : ()B
/*    */     //   16: istore_2
/*    */     //   17: getfield Ws : Ljava/nio/ByteBuffer;
/*    */     //   20: invokevirtual get : ()B
/*    */     //   23: iconst_1
/*    */     //   24: if_icmpeq -> 95
/*    */     //   27: new f/A30
/*    */     //   30: dup
/*    */     //   31: iload_1
/*    */     //   32: aload_0
/*    */     //   33: dup
/*    */     //   34: dup2
/*    */     //   35: dup2
/*    */     //   36: getfield Ws : Ljava/nio/ByteBuffer;
/*    */     //   39: invokevirtual getInt : ()I
/*    */     //   42: istore_0
/*    */     //   43: getfield Ws : Ljava/nio/ByteBuffer;
/*    */     //   46: invokevirtual getInt : ()I
/*    */     //   49: istore_1
/*    */     //   50: getfield Ws : Ljava/nio/ByteBuffer;
/*    */     //   53: invokevirtual getInt : ()I
/*    */     //   56: istore_3
/*    */     //   57: getfield Ws : Ljava/nio/ByteBuffer;
/*    */     //   60: invokevirtual getShort : ()S
/*    */     //   63: istore #4
/*    */     //   65: getfield Ws : Ljava/nio/ByteBuffer;
/*    */     //   68: invokevirtual getShort : ()S
/*    */     //   71: istore #5
/*    */     //   73: getfield Ws : Ljava/nio/ByteBuffer;
/*    */     //   76: invokevirtual get : ()B
/*    */     //   79: istore #6
/*    */     //   81: iload_2
/*    */     //   82: iload_0
/*    */     //   83: iload_1
/*    */     //   84: iload_3
/*    */     //   85: iload #4
/*    */     //   87: iload #5
/*    */     //   89: iload #6
/*    */     //   91: invokespecial <init> : (BBIIISSB)V
/*    */     //   94: areturn
/*    */     //   95: aload_0
/*    */     //   96: dup
/*    */     //   97: new f/A30
/*    */     //   100: astore_3
/*    */     //   101: getfield Ws : Ljava/nio/ByteBuffer;
/*    */     //   104: invokevirtual getShort : ()S
/*    */     //   107: istore #4
/*    */     //   109: invokevirtual R00 : ()I
/*    */     //   112: iconst_1
/*    */     //   113: if_icmpne -> 122
/*    */     //   116: iconst_1
/*    */     //   117: istore #5
/*    */     //   119: goto -> 125
/*    */     //   122: iconst_0
/*    */     //   123: istore #5
/*    */     //   125: aload_0
/*    */     //   126: invokevirtual R00 : ()I
/*    */     //   129: iconst_1
/*    */     //   130: if_icmpne -> 139
/*    */     //   133: iconst_1
/*    */     //   134: istore #6
/*    */     //   136: goto -> 142
/*    */     //   139: iconst_0
/*    */     //   140: istore #6
/*    */     //   142: aload_0
/*    */     //   143: dup
/*    */     //   144: getfield Ws : Ljava/nio/ByteBuffer;
/*    */     //   147: invokevirtual get : ()B
/*    */     //   150: istore #7
/*    */     //   152: invokevirtual R00 : ()I
/*    */     //   155: iconst_1
/*    */     //   156: if_icmpne -> 165
/*    */     //   159: iconst_1
/*    */     //   160: istore #8
/*    */     //   162: goto -> 168
/*    */     //   165: iconst_0
/*    */     //   166: istore #8
/*    */     //   168: aload_0
/*    */     //   169: invokevirtual R00 : ()I
/*    */     //   172: iconst_1
/*    */     //   173: if_icmpne -> 182
/*    */     //   176: iconst_1
/*    */     //   177: istore #9
/*    */     //   179: goto -> 185
/*    */     //   182: iconst_0
/*    */     //   183: istore #9
/*    */     //   185: aload_3
/*    */     //   186: dup
/*    */     //   187: iload_1
/*    */     //   188: aload_0
/*    */     //   189: dup
/*    */     //   190: dup
/*    */     //   191: getfield Ws : Ljava/nio/ByteBuffer;
/*    */     //   194: invokevirtual get : ()B
/*    */     //   197: istore_0
/*    */     //   198: getfield Ws : Ljava/nio/ByteBuffer;
/*    */     //   201: invokevirtual get : ()B
/*    */     //   204: istore_1
/*    */     //   205: getfield Ws : Ljava/nio/ByteBuffer;
/*    */     //   208: invokevirtual get : ()B
/*    */     //   211: istore_3
/*    */     //   212: iload_2
/*    */     //   213: iload #4
/*    */     //   215: iload #5
/*    */     //   217: iload #6
/*    */     //   219: iload #7
/*    */     //   221: iload #8
/*    */     //   223: iload #9
/*    */     //   225: iload_0
/*    */     //   226: iload_1
/*    */     //   227: iload_3
/*    */     //   228: invokespecial <init> : (BBSZZBZZBBB)V
/*    */     //   231: areturn
/*    */     // Line number table:
/*    */     //   Java source line number -> byte code offset
/*    */     //   #1	-> 3
/*    */     //   #2	-> 27
/*    */     //   #3	-> 36
/*    */     //   #4	-> 57
/*    */     //   #5	-> 73
/*    */     //   #6	-> 91
/*    */     //   #7	-> 101
/*    */     //   #8	-> 109
/*    */     //   #9	-> 144
/*    */     //   #10	-> 152
/*    */     //   #11	-> 191
/* 25 */     //   #12	-> 228 } public final yX[] NG() { byte b; if ((b = this.Ws.get()) > 0) { HashMap<Object, Object> hashMap; this(); for (byte b1 = 0; b1 < b; ) { CC0 cC0; DO dO; Pi pi; byte b2 = this.Ws.get(); short s1 = this.Ws.getShort(), s2 = this.Ws.getShort(), s3 = this.Ws.getShort(), s4 = this.Ws.getShort(); byte b3; if ((b3 = this.Ws.get()) < 0) { cC0 = null; } else { cC0 = CC0.Jo0(cC0); }  byte b4; if ((b4 = this.Ws.get()) < 0) { dO = null; } else { dO = DO.kk(dO); }  yX yX; if ((yX = (yX)hashMap.get(dO)) == null) { this(dO); hashMap.put(dO, yX); }  this(b2, s1, s2, s3, s4, cC0, dO); if (!yX.U30.contains(pi)) yX.U30.add(pi);  b1++; }  Arrays.sort(hashMap.values().toArray((Object[])new yX[0])); return (yX[])hashMap.values().toArray((Object[])new yX[0]); }  return new yX[0]; } public final T60 Nz() { fH0 fH0 = LU(true); H10 h101 = ZV(); this(h101); ArrayList<Q90> arrayList; H10 h102; T60 t60; short s = this.Ws.getShort(); Vp0[] arrayOfVp0; int j; byte b2; for (j = (arrayOfVp0 = Vp0.Jo).length, b2 = 0; b2 < j; ) { Vp0 vp0; if ((s & 1 << (vp0 = arrayOfVp0[b2]).gw0) != 0) { short[] arrayOfShort = h102.Hd0; byte b = vp0.gw0; short s1, s2; if ((s2 = (short)((s1 = this.Ws.getShort()) & 0x3FF)) == 1023) s2 = -1;  arrayOfShort[b] = s2; byte[] arrayOfByte = h102.Kw0; if ((s1 = (byte)((s1 & 0xFFFF) >> 10)) == 63) s1 = -1;  arrayOfByte[b] = s1; }  b2++; }  this(fH0, h101, h102); if (R00() == 1) { ZD zD; (ZG0)ZG0.fc.Ha0(this.Ws.get()); this(au(), this.Ws.getInt()); } else { fH0 = null; }  t60.Vx = (ZD)fH0; int i = R00(); this(); for (byte b1 = 0; b1 < i; ) { arrayList.add(vy0()); b1++; }  t60.YI0 = arrayList; System.currentTimeMillis(); return t60; } public final Q90 vy0() { this(this.Ws.getInt()); Q90 q90; int i = this.Ws.getInt(); aq0 aq0 = aq0.BQ(this.Ws.get()); short s1 = this.Ws.getShort(), s2 = this.Ws.getShort(); int j = this.Ws.getInt(), k = this.Ws.getInt(); String str1 = au(), str2 = au(); this.Ws.get(); byte b3 = this.Ws.get(), b4 = this.Ws.get(); short s3 = this.Ws.getShort(), s4 = this.Ws.getShort(); int m = this.Ws.getInt(); byte b5 = this.Ws.get(); short s5 = this.Ws.getShort(), s6 = this.Ws.getShort(), s7 = this.Ws.getShort(), s8 = this.Ws.getShort(), s9 = this.Ws.getShort(); byte b6 = this.Ws.get(), b7 = this.Ws.get(), b8 = this.Ws.get(), b9 = this.Ws.get(); short s10 = this.Ws.getShort(), s11 = this.Ws.getShort(), s12 = this.Ws.getShort(), s13 = this.Ws.getShort(); short s14 = (short)this.Ws.get(), s15 = (short)this.Ws.get(), s16 = (short)this.Ws.get(), s17 = (short)this.Ws.get(), s18 = (short)this.Ws.get(), s19 = (short)this.Ws.get(); byte b10 = this.Ws.get(), b11 = this.Ws.get(), b12 = this.Ws.get(), b13 = this.Ws.get(), b14 = this.Ws.get(); this.Ws.get(); byte b15 = this.Ws.get(), b16 = this.Ws.get(), b17 = this.Ws.get(), b18 = this.Ws.get(), b19 = this.Ws.get(); int n = this.Ws.getInt(); long l = this.Ws.getLong(); i = this.Ws.get(); j = this.Ws.getInt(); k = this.Ws.getShort(); byte b1 = this.Ws.get(), b2 = this.Ws.get(); q90.c80 = i; q90.COm1 = aq0; q90.Tl0 = s1; q90.Cw0 = s2; q90.MD0 = j; q90.Yt0 = k; q90.Yq0 = str1; q90.nr = str2; q90.u0 = b3; q90.od = b4; q90.Hq0 = s3; q90.ld0 = s4; q90.pA = m; q90.j00 = b5; q90.Bl0 = s5; q90.En0[0] = s6; q90.En0[1] = s7; q90.En0[2] = s8; q90.En0[3] = s9; q90.rI0[0] = b6; q90.rI0[1] = b7; q90.rI0[2] = b8; q90.rI0[3] = b9; q90.AY[0] = s10; q90.AY[1] = s11; q90.AY[2] = s12; q90.AY[3] = s13; arrayOfShort[0] = (short)(s14 & 0xFF); arrayOfShort[1] = (short)(s15 & 0xFF); arrayOfShort[2] = (short)(s16 & 0xFF); arrayOfShort[3] = (short)(s17 & 0xFF); arrayOfShort[4] = (short)(s18 & 0xFF); short[] arrayOfShort; (arrayOfShort = q90.ko0)[5] = (short)(s19 & 0xFF); q90.COm4 = b10; q90.Ij = b11; q90.Jk = b12; q90.IF0 = b13; q90.Sf0 = b14; q90.YH0 = b15; q90.sq0 = b16; q90.UK0 = b17; q90.qz = b18; q90.Vp = b19; q90.Jx0 = n; q90.u4 = l; q90.eH = i; q90.Ck = j; q90.LPt7 = k; byte b20; if ((b20 = this.Ws.get()) == 2 && !q90.iL() && !aq0.Eb) { q90
/* 26 */         .cC = 0; } else { q90.cC = b20; }  if (b1 < 0) { q90
/* 27 */         .GJ0 = null; } else { q90.GJ0 = Ht0.Gt0(b1); }  q90
/* 28 */       .xH = mA.qq(b2);
/* 29 */     q90.k0 = nV.Y4((byte)(int)((q90.MD0 & 0xFFFFFFFFL) % 25L)); mA[] arrayOfMA;
/*    */     byte b;
/* 31 */     for (arrayOfMA = new mA[i = this.Ws.get()], b = 0; b < i; ) { arrayOfMA[b] = 
/*    */         
/* 33 */         mA.qq(this.Ws.get()); b++; }  q90
/* 34 */       .wH = arrayOfMA; return q90; } public final V50 eU(boolean paramBoolean1, boolean paramBoolean2) { V50 v50 = new V50(); int i = this.Ws.getInt(), j = this.Ws.getInt(), k = this.Ws.getInt(); if (paramBoolean1) { str2 = ""; } else { str2 = au(); }  if (paramBoolean1) { str1 = au(); } else { str1 = ""; }  int m = this.Ws.getInt(); String str3 = au(); if (paramBoolean2) { str4 = au(); } else { str4 = ""; }  byte b = this.Ws.get(); this.Ws.get(); this(i, j, k, str2, str1, m, str3, str4, b); String str1, str2, str4; if (paramBoolean2) { HashMap<Object, Object> hashMap; int n = R00(); this(); for (i = 0; i < n; ) { nE0 nE0 = new nE0(); k = v50.z70; byte b1 = this.Ws.get(); if (this.Ws.get() == 1) { m = 1; } else { m = 0; }  k = this.Ws.getInt(); this.Ws.get(); int i1 = this.Ws.getInt(); short s = this.Ws.getShort(); this(k, b1, m, b2, k, i1, s); byte b2; if ((b2 = this.Ws.get()) != 0) { if (b2 != 1) { if (b2 != 3) { if (b2 == 4 && R00() == 1) { MM mM; this.Ws.getInt(); if ((k = this.Ws.get()) == 1) { boolean bool1, bool2; mM = new MM(); m = this.Ws.getShort(); b2 = this.Ws.get(); i1 = this.Ws.get(); s = this.Ws.get(); if (this.Ws.get() == 1) { bool1 = true; } else { bool1 = false; }  if (this.Ws.get() == 1) { bool2 = true; } else { bool2 = false; }  this(k, m, b2, i1, s, bool1, bool2); } else if (k == 2) { this(k, this.Ws.getShort()); } else { throw new RuntimeException(""); }  nE0.Kz0 = mM; }  } else if (R00() == 1) { if (nE0.Jf == 3) { nE0.Ao0 = Com5(nE0.n8); } else { throw new UnsupportedOperationException(); }  }  } else if (R00() == 1) { for (nE0.Ml = vy0(), k = 0; k < 6; ) { short s1 = this.Ws.getShort(); nE0.WK0[k] = s1; k = (byte)(k + 1); }  }  } else if (R00() == 1) { ByteBuffer byteBuffer = this.Ws;
/* 35 */           int i2 = byteBuffer.getInt(); m = byteBuffer.getShort(); short s1 = byteBuffer.getShort(); byteBuffer.get(); i1 = byteBuffer.get(); s = byteBuffer.get(); yM yM = yM.qx0(byteBuffer.get());
/* 36 */           nE0.Xu0 = new nH0(i2, m, s1, i1, s, yM); }  hashMap
/*    */           
/* 38 */           .put(Byte.valueOf(nE0.Ly), nE0); i++; }  v50
/* 39 */         .Ml0 = Collections.unmodifiableMap(hashMap); }  return v50; }
/*    */ 
/*    */   
/*    */   public final U50 eD() {
/*    */     this.Ws.get();
/*    */     z5 z51 = bI(), z52 = bI();
/*    */     short s = this.Ws.getShort();
/*    */     byte b = this.Ws.get();
/*    */     return new U50(z51, z52, s, b);
/*    */   } }


/* Location:              /Users/vnnsnnt/Documents/Codespace/JavaWorkspace/RedTrainer/src/main/java/org/trainer/client/PokeMMO.jar!/f/iK.class
 * Java compiler version: 8 (52.0)
 * JD-Core Version:       1.1.3
 */