package f;

public final class Im0 implements con {
  public final void ng(Object paramObject, int paramInt, float[] paramArrayOffloat) {
    // Byte code:
    //   0: iload_2
    //   1: aload_1
    //   2: checkcast f/JG0
    //   5: astore_0
    //   6: tableswitch default -> 44, 1 -> 149, 2 -> 131, 3 -> 113, 4 -> 94, 5 -> 75, 6 -> 53
    //   44: getstatic f/Im0.Lk0 : Z
    //   47: ifeq -> 165
    //   50: goto -> 164
    //   53: aload_0
    //   54: dup
    //   55: aload_3
    //   56: dup
    //   57: iconst_0
    //   58: faload
    //   59: f2i
    //   60: istore_0
    //   61: iconst_1
    //   62: faload
    //   63: f2i
    //   64: iload_0
    //   65: swap
    //   66: invokevirtual Xg0 : (II)V
    //   69: invokevirtual mM : ()V
    //   72: goto -> 164
    //   75: aload_0
    //   76: aload_3
    //   77: aload_0
    //   78: getfield xY : I
    //   81: istore_0
    //   82: iconst_0
    //   83: faload
    //   84: f2i
    //   85: iload_0
    //   86: swap
    //   87: invokevirtual Tm : (II)Z
    //   90: pop
    //   91: goto -> 164
    //   94: aload_0
    //   95: dup
    //   96: aload_3
    //   97: iconst_0
    //   98: faload
    //   99: f2i
    //   100: istore_0
    //   101: getfield HC : I
    //   104: iload_0
    //   105: swap
    //   106: invokevirtual Tm : (II)Z
    //   109: pop
    //   110: goto -> 164
    //   113: aload_0
    //   114: aload_3
    //   115: dup
    //   116: iconst_0
    //   117: faload
    //   118: f2i
    //   119: istore_0
    //   120: iconst_1
    //   121: faload
    //   122: f2i
    //   123: iload_0
    //   124: swap
    //   125: invokevirtual Ol0 : (II)V
    //   128: goto -> 164
    //   131: aload_0
    //   132: aload_3
    //   133: aload_0
    //   134: getfield Kd : I
    //   137: istore_0
    //   138: iconst_0
    //   139: faload
    //   140: f2i
    //   141: iload_0
    //   142: swap
    //   143: invokevirtual Ol0 : (II)V
    //   146: goto -> 164
    //   149: aload_0
    //   150: dup
    //   151: aload_3
    //   152: iconst_0
    //   153: faload
    //   154: f2i
    //   155: istore_0
    //   156: getfield er0 : I
    //   159: iload_0
    //   160: swap
    //   161: invokevirtual Ol0 : (II)V
    //   164: return
    //   165: new java/lang/AssertionError
    //   168: dup
    //   169: invokespecial <init> : ()V
    //   172: athrow
    // Line number table:
    //   Java source line number -> byte code offset
    //   #1	-> 44
    //   #2	-> 78
    //   #3	-> 83
    //   #4	-> 101
    //   #5	-> 106
    //   #6	-> 134
    //   #7	-> 139
    //   #8	-> 156
    //   #9	-> 161
  }
  
  public final int Uu0(Object paramObject, int paramInt, float[] paramArrayOffloat) {
    // Byte code:
    //   0: iload_2
    //   1: aload_1
    //   2: checkcast f/JG0
    //   5: astore_0
    //   6: tableswitch default -> 44, 1 -> 143, 2 -> 129, 3 -> 106, 4 -> 92, 5 -> 78, 6 -> 55
    //   44: getstatic f/Im0.Lk0 : Z
    //   47: ifeq -> 156
    //   50: iconst_0
    //   51: istore_0
    //   52: goto -> 154
    //   55: aload_3
    //   56: aload_0
    //   57: aload_3
    //   58: aload_0
    //   59: getfield xY : I
    //   62: i2f
    //   63: iconst_0
    //   64: swap
    //   65: fastore
    //   66: getfield HC : I
    //   69: i2f
    //   70: iconst_1
    //   71: swap
    //   72: fastore
    //   73: iconst_2
    //   74: istore_0
    //   75: goto -> 154
    //   78: aload_3
    //   79: aload_0
    //   80: getfield HC : I
    //   83: i2f
    //   84: iconst_0
    //   85: swap
    //   86: fastore
    //   87: iconst_1
    //   88: istore_0
    //   89: goto -> 154
    //   92: aload_3
    //   93: aload_0
    //   94: getfield xY : I
    //   97: i2f
    //   98: iconst_0
    //   99: swap
    //   100: fastore
    //   101: iconst_1
    //   102: istore_0
    //   103: goto -> 154
    //   106: aload_3
    //   107: aload_0
    //   108: aload_3
    //   109: aload_0
    //   110: getfield Kd : I
    //   113: i2f
    //   114: iconst_0
    //   115: swap
    //   116: fastore
    //   117: getfield er0 : I
    //   120: i2f
    //   121: iconst_1
    //   122: swap
    //   123: fastore
    //   124: iconst_2
    //   125: istore_0
    //   126: goto -> 154
    //   129: aload_3
    //   130: aload_0
    //   131: getfield er0 : I
    //   134: i2f
    //   135: iconst_0
    //   136: swap
    //   137: fastore
    //   138: iconst_1
    //   139: istore_0
    //   140: goto -> 154
    //   143: aload_3
    //   144: aload_0
    //   145: getfield Kd : I
    //   148: i2f
    //   149: iconst_0
    //   150: swap
    //   151: fastore
    //   152: iconst_1
    //   153: istore_0
    //   154: iload_0
    //   155: ireturn
    //   156: new java/lang/AssertionError
    //   159: dup
    //   160: invokespecial <init> : ()V
    //   163: athrow
    // Line number table:
    //   Java source line number -> byte code offset
    //   #1	-> 44
    //   #2	-> 59
    //   #3	-> 65
    //   #4	-> 66
    //   #5	-> 72
    //   #6	-> 80
    //   #7	-> 86
    //   #8	-> 94
    //   #9	-> 100
    //   #10	-> 110
    //   #11	-> 116
    //   #12	-> 117
    //   #13	-> 123
    //   #14	-> 131
    //   #15	-> 137
    //   #16	-> 145
    //   #17	-> 151
  }
}


/* Location:              /Users/vnnsnnt/Documents/Codespace/JavaWorkspace/RedTrainer/src/main/java/org/trainer/client/PokeMMO.jar!/f/Im0.class
 * Java compiler version: 8 (52.0)
 * JD-Core Version:       1.1.3
 */