/* 1 */ package f;public class Iq extends Ew { static { Uc uc; (Z30 = new KV(uc = Uc.xi0)).Np(Color.BLACK); KV kV; (kV = Z30).Con
/* 2 */       .Tt(kV.coM6); }
/* 3 */   public final Texture j5(String paramString) { return (this.W60.pd0(paramString) != null) ? (Texture)this.W60.pd0(paramString) : Qm; } public static S1 Qm = new S1(Z30); public final void yq(hC paramhC, Wd paramWd) { if (D.hS()) this.Ef = paramWd;  for (byte b = 0; b < paramhC.p3.Z8; b++) { Texture texture2; tC tC = (tC)paramhC.p3.get(b); this(new AB(zH, null, false, false, false)); (new Texture()).setFilter(cu0.Fh, cu0.Fh); (new Texture()).setWrap(A00.OW, A00.OW); zH.dispose(); Texture texture1; ZH zH; if ((zH = Q4(paramhC, paramWd, b)) != null && (texture1 = (Texture)this.W60.X00(tC.Ih, texture2)) != null) texture1.dispose();  }  } public ZH Q4(hC paramhC, Wd paramWd, int paramInt) { // Byte code:
/*   */     //   0: aload_1
/*   */     //   1: getfield p3 : Lf/fQ;
/*   */     //   4: iload_3
/*   */     //   5: invokevirtual get : (I)Ljava/lang/Object;
/*   */     //   8: checkcast f/tC
/*   */     //   11: dup
/*   */     //   12: astore #4
/*   */     //   14: getfield Ih : Ljava/lang/String;
/*   */     //   17: dup
/*   */     //   18: astore #5
/*   */     //   20: ifnonnull -> 32
/*   */     //   23: getstatic f/eI.zi : Lf/ik;
/*   */     //   26: invokevirtual getClass : ()Ljava/lang/Class;
/*   */     //   29: pop
/*   */     //   30: aconst_null
/*   */     //   31: areturn
/*   */     //   32: aload #4
/*   */     //   34: getfield JZ : Ljava/lang/String;
/*   */     //   37: ifnonnull -> 92
/*   */     //   40: aload_0
/*   */     //   41: getstatic f/eI.zi : Lf/ik;
/*   */     //   44: invokevirtual getClass : ()Ljava/lang/Class;
/*   */     //   47: pop
/*   */     //   48: getfield zm0 : B
/*   */     //   51: dup
/*   */     //   52: istore_0
/*   */     //   53: iconst_4
/*   */     //   54: if_icmpne -> 64
/*   */     //   57: getstatic f/Iq.Tk0 : Lf/Lf;
/*   */     //   60: astore_2
/*   */     //   61: goto -> 68
/*   */     //   64: getstatic f/Iq.Z30 : Lf/KV;
/*   */     //   67: astore_2
/*   */     //   68: iload_0
/*   */     //   69: iconst_m1
/*   */     //   70: if_icmpne -> 90
/*   */     //   73: aload_1
/*   */     //   74: getfield Ih : Ljava/lang/String;
/*   */     //   77: ldc 'tt_tabletop'
/*   */     //   79: swap
/*   */     //   80: invokevirtual equals : (Ljava/lang/Object;)Z
/*   */     //   83: ifeq -> 90
/*   */     //   86: getstatic f/Iq.Tk0 : Lf/Lf;
/*   */     //   89: astore_2
/*   */     //   90: aload_2
/*   */     //   91: areturn
/*   */     //   92: aload_0
/*   */     //   93: getfield W60 : Lf/f7;
/*   */     //   96: aload #5
/*   */     //   98: invokevirtual GB0 : (Ljava/lang/Object;)Z
/*   */     //   101: ifeq -> 106
/*   */     //   104: aconst_null
/*   */     //   105: areturn
/*   */     //   106: aload_2
/*   */     //   107: aload #4
/*   */     //   109: dup
/*   */     //   110: getfield JZ : Ljava/lang/String;
/*   */     //   113: astore #5
/*   */     //   115: getfield C0 : Ljava/lang/String;
/*   */     //   118: astore #6
/*   */     //   120: getfield K5 : Lf/Nn;
/*   */     //   123: aload #5
/*   */     //   125: invokevirtual pd0 : (Ljava/lang/Object;)Ljava/lang/Object;
/*   */     //   128: checkcast java/lang/Integer
/*   */     //   131: dup
/*   */     //   132: astore #5
/*   */     //   134: aload_2
/*   */     //   135: getfield zg0 : Lf/Nn;
/*   */     //   138: aload #6
/*   */     //   140: invokevirtual pd0 : (Ljava/lang/Object;)Ljava/lang/Object;
/*   */     //   143: checkcast java/lang/Integer
/*   */     //   146: astore #6
/*   */     //   148: ifnull -> 762
/*   */     //   151: aload #6
/*   */     //   153: ifnonnull -> 159
/*   */     //   156: goto -> 762
/*   */     //   159: aload_0
/*   */     //   160: aload_1
/*   */     //   161: getfield p3 : Lf/fQ;
/*   */     //   164: iload_3
/*   */     //   165: invokevirtual get : (I)Ljava/lang/Object;
/*   */     //   168: checkcast f/tC
/*   */     //   171: astore_1
/*   */     //   172: getfield td0 : I
/*   */     //   175: bipush #6
/*   */     //   177: if_icmpne -> 217
/*   */     //   180: aload #5
/*   */     //   182: invokevirtual intValue : ()I
/*   */     //   185: bipush #51
/*   */     //   187: if_icmpne -> 217
/*   */     //   190: aload #6
/*   */     //   192: invokevirtual intValue : ()I
/*   */     //   195: bipush #48
/*   */     //   197: if_icmpne -> 217
/*   */     //   200: getstatic f/L70.gq : Lf/L70;
/*   */     //   203: invokevirtual fu : ()B
/*   */     //   206: iconst_3
/*   */     //   207: if_icmpeq -> 217
/*   */     //   210: bipush #50
/*   */     //   212: invokestatic valueOf : (I)Ljava/lang/Integer;
/*   */     //   215: astore #5
/*   */     //   217: aload #4
/*   */     //   219: dup
/*   */     //   220: aload_2
/*   */     //   221: getfield TE : Lf/Yy0;
/*   */     //   224: aload #5
/*   */     //   226: invokevirtual intValue : ()I
/*   */     //   229: invokevirtual yO : (I)Lf/vO;
/*   */     //   232: checkcast f/fk0
/*   */     //   235: dup
/*   */     //   236: astore_3
/*   */     //   237: aload_2
/*   */     //   238: getfield Va0 : Lf/Yy0;
/*   */     //   241: aload #6
/*   */     //   243: invokevirtual intValue : ()I
/*   */     //   246: invokevirtual yO : (I)Lf/vO;
/*   */     //   249: checkcast f/ZA0
/*   */     //   252: astore #7
/*   */     //   254: getfield b70 : Lf/f20;
/*   */     //   257: getfield Io0 : B
/*   */     //   260: putfield T1 : I
/*   */     //   263: aload_3
/*   */     //   264: getfield rW : B
/*   */     //   267: putfield SS : I
/*   */     //   270: getstatic f/km.ln : Lf/ei;
/*   */     //   273: dup
/*   */     //   274: astore_3
/*   */     //   275: ifnull -> 292
/*   */     //   278: aload_3
/*   */     //   279: getfield tn : Lf/fQ;
/*   */     //   282: invokevirtual isEmpty : ()Z
/*   */     //   285: iconst_1
/*   */     //   286: ixor
/*   */     //   287: ifeq -> 292
/*   */     //   290: aconst_null
/*   */     //   291: areturn
/*   */     //   292: aload_0
/*   */     //   293: getfield zm0 : B
/*   */     //   296: aload #7
/*   */     //   298: aload_0
/*   */     //   299: getstatic f/L70.gq : Lf/L70;
/*   */     //   302: dup
/*   */     //   303: astore_3
/*   */     //   304: invokevirtual fu : ()B
/*   */     //   307: istore #8
/*   */     //   309: getfield td0 : I
/*   */     //   312: istore #9
/*   */     //   314: getfield Vk : I
/*   */     //   317: istore #10
/*   */     //   319: iload #8
/*   */     //   321: iload #9
/*   */     //   323: iload #10
/*   */     //   325: invokestatic jF : (BIII)Z
/*   */     //   328: ifeq -> 393
/*   */     //   331: aload_2
/*   */     //   332: aload_0
/*   */     //   333: getfield zm0 : B
/*   */     //   336: aload_2
/*   */     //   337: aload #7
/*   */     //   339: aload #5
/*   */     //   341: aload_0
/*   */     //   342: aload_3
/*   */     //   343: invokevirtual fu : ()B
/*   */     //   346: istore_2
/*   */     //   347: getfield td0 : I
/*   */     //   350: istore_3
/*   */     //   351: invokevirtual intValue : ()I
/*   */     //   354: istore #8
/*   */     //   356: getfield Vk : I
/*   */     //   359: istore #9
/*   */     //   361: iload_2
/*   */     //   362: iload_3
/*   */     //   363: iload #8
/*   */     //   365: iload #9
/*   */     //   367: invokestatic Ks0 : (BLf/Wd;IIII)[I
/*   */     //   370: astore_2
/*   */     //   371: getfield TE : Lf/Yy0;
/*   */     //   374: aload #5
/*   */     //   376: invokevirtual intValue : ()I
/*   */     //   379: invokevirtual yO : (I)Lf/vO;
/*   */     //   382: checkcast f/fk0
/*   */     //   385: aload_2
/*   */     //   386: invokestatic IV : (Lf/fk0;[I)Lf/ZH;
/*   */     //   389: astore_2
/*   */     //   390: goto -> 411
/*   */     //   393: aload_2
/*   */     //   394: aload #6
/*   */     //   396: aload #5
/*   */     //   398: invokevirtual intValue : ()I
/*   */     //   401: istore_2
/*   */     //   402: invokevirtual intValue : ()I
/*   */     //   405: iload_2
/*   */     //   406: swap
/*   */     //   407: invokevirtual bI : (II)Lf/ZH;
/*   */     //   410: astore_2
/*   */     //   411: aload_2
/*   */     //   412: ifnonnull -> 424
/*   */     //   415: getstatic f/eI.zi : Lf/ik;
/*   */     //   418: invokevirtual getClass : ()Ljava/lang/Class;
/*   */     //   421: pop
/*   */     //   422: aconst_null
/*   */     //   423: areturn
/*   */     //   424: aload_1
/*   */     //   425: getfield gf0 : J
/*   */     //   428: dup2
/*   */     //   429: lstore #8
/*   */     //   431: bipush #18
/*   */     //   433: lshr
/*   */     //   434: lconst_1
/*   */     //   435: land
/*   */     //   436: lconst_1
/*   */     //   437: ladd
/*   */     //   438: l2i
/*   */     //   439: dup
/*   */     //   440: istore_3
/*   */     //   441: lload #8
/*   */     //   443: bipush #19
/*   */     //   445: lshr
/*   */     //   446: lconst_1
/*   */     //   447: land
/*   */     //   448: lconst_1
/*   */     //   449: ladd
/*   */     //   450: l2i
/*   */     //   451: istore #8
/*   */     //   453: iconst_1
/*   */     //   454: if_icmpne -> 463
/*   */     //   457: iload #8
/*   */     //   459: iconst_1
/*   */     //   460: if_icmpeq -> 657
/*   */     //   463: aload_1
/*   */     //   464: new f/ZH
/*   */     //   467: dup
/*   */     //   468: astore #9
/*   */     //   470: aload_2
/*   */     //   471: aload #9
/*   */     //   473: dup
/*   */     //   474: aload_2
/*   */     //   475: dup
/*   */     //   476: getfield Con : Lcom/badlogic/gdx/graphics/g2d/Gdx2DPixmap;
/*   */     //   479: dup
/*   */     //   480: getfield ju : I
/*   */     //   483: iload_3
/*   */     //   484: imul
/*   */     //   485: istore_3
/*   */     //   486: getfield Og0 : I
/*   */     //   489: iload #8
/*   */     //   491: imul
/*   */     //   492: istore #8
/*   */     //   494: invokevirtual TU : ()Lf/Uc;
/*   */     //   497: astore #10
/*   */     //   499: iload_3
/*   */     //   500: iload #8
/*   */     //   502: aload #10
/*   */     //   504: invokespecial <init> : (IILf/Uc;)V
/*   */     //   507: getstatic f/y1.Zj : Lf/y1;
/*   */     //   510: invokevirtual r1 : (Lf/y1;)V
/*   */     //   513: iconst_0
/*   */     //   514: iconst_0
/*   */     //   515: invokevirtual fL : (Lf/ZH;II)V
/*   */     //   518: iconst_0
/*   */     //   519: istore_3
/*   */     //   520: iconst_0
/*   */     //   521: istore #8
/*   */     //   523: getfield gf0 : J
/*   */     //   526: dup2
/*   */     //   527: lstore #10
/*   */     //   529: bipush #16
/*   */     //   531: lshr
/*   */     //   532: lconst_1
/*   */     //   533: land
/*   */     //   534: lconst_1
/*   */     //   535: lcmp
/*   */     //   536: ifne -> 569
/*   */     //   539: lload #10
/*   */     //   541: bipush #18
/*   */     //   543: lshr
/*   */     //   544: lconst_1
/*   */     //   545: land
/*   */     //   546: lconst_1
/*   */     //   547: lcmp
/*   */     //   548: ifne -> 569
/*   */     //   551: aload_2
/*   */     //   552: aload #9
/*   */     //   554: aload_2
/*   */     //   555: getfield Con : Lcom/badlogic/gdx/graphics/g2d/Gdx2DPixmap;
/*   */     //   558: getfield ju : I
/*   */     //   561: iconst_0
/*   */     //   562: iconst_1
/*   */     //   563: iconst_0
/*   */     //   564: invokestatic sH0 : (Lf/ZH;Lf/ZH;IIZZ)V
/*   */     //   567: iconst_1
/*   */     //   568: istore_3
/*   */     //   569: aload_1
/*   */     //   570: getfield gf0 : J
/*   */     //   573: dup2
/*   */     //   574: lstore #10
/*   */     //   576: bipush #17
/*   */     //   578: lshr
/*   */     //   579: lconst_1
/*   */     //   580: land
/*   */     //   581: lconst_1
/*   */     //   582: lcmp
/*   */     //   583: ifne -> 618
/*   */     //   586: lload #10
/*   */     //   588: bipush #19
/*   */     //   590: lshr
/*   */     //   591: lconst_1
/*   */     //   592: land
/*   */     //   593: lconst_1
/*   */     //   594: lcmp
/*   */     //   595: ifne -> 618
/*   */     //   598: aload_2
/*   */     //   599: aload #9
/*   */     //   601: aload_2
/*   */     //   602: getfield Con : Lcom/badlogic/gdx/graphics/g2d/Gdx2DPixmap;
/*   */     //   605: getfield Og0 : I
/*   */     //   608: iconst_0
/*   */     //   609: swap
/*   */     //   610: iconst_0
/*   */     //   611: iconst_1
/*   */     //   612: invokestatic sH0 : (Lf/ZH;Lf/ZH;IIZZ)V
/*   */     //   615: iconst_1
/*   */     //   616: istore #8
/*   */     //   618: iload_3
/*   */     //   619: ifeq -> 650
/*   */     //   622: iload #8
/*   */     //   624: ifeq -> 650
/*   */     //   627: aload_2
/*   */     //   628: dup
/*   */     //   629: getfield Con : Lcom/badlogic/gdx/graphics/g2d/Gdx2DPixmap;
/*   */     //   632: dup
/*   */     //   633: getfield ju : I
/*   */     //   636: istore_1
/*   */     //   637: getfield Og0 : I
/*   */     //   640: istore_3
/*   */     //   641: aload #9
/*   */     //   643: iload_1
/*   */     //   644: iload_3
/*   */     //   645: iconst_1
/*   */     //   646: iconst_1
/*   */     //   647: invokestatic sH0 : (Lf/ZH;Lf/ZH;IIZZ)V
/*   */     //   650: aload_2
/*   */     //   651: invokevirtual dispose : ()V
/*   */     //   654: aload #9
/*   */     //   656: astore_2
/*   */     //   657: invokestatic hS : ()Z
/*   */     //   660: ifeq -> 760
/*   */     //   663: aload_0
/*   */     //   664: dup
/*   */     //   665: dup
/*   */     //   666: getfield OK : Lf/f7;
/*   */     //   669: aload #4
/*   */     //   671: getfield Ih : Ljava/lang/String;
/*   */     //   674: aload #5
/*   */     //   676: invokevirtual X00 : (Ljava/lang/Object;Ljava/lang/Object;)Ljava/lang/Object;
/*   */     //   679: pop
/*   */     //   680: getfield dH : Lf/f7;
/*   */     //   683: aload #4
/*   */     //   685: getfield Ih : Ljava/lang/String;
/*   */     //   688: aload #6
/*   */     //   690: invokevirtual X00 : (Ljava/lang/Object;Ljava/lang/Object;)Ljava/lang/Object;
/*   */     //   693: pop
/*   */     //   694: getfield NUl : Lf/f7;
/*   */     //   697: aload #7
/*   */     //   699: getfield Vk : I
/*   */     //   702: invokestatic valueOf : (I)Ljava/lang/Integer;
/*   */     //   705: invokevirtual GB0 : (Ljava/lang/Object;)Z
/*   */     //   708: ifne -> 734
/*   */     //   711: aload_0
/*   */     //   712: getfield NUl : Lf/f7;
/*   */     //   715: aload #7
/*   */     //   717: getfield Vk : I
/*   */     //   720: invokestatic valueOf : (I)Ljava/lang/Integer;
/*   */     //   723: new f/fQ
/*   */     //   726: dup
/*   */     //   727: invokespecial <init> : ()V
/*   */     //   730: invokevirtual X00 : (Ljava/lang/Object;Ljava/lang/Object;)Ljava/lang/Object;
/*   */     //   733: pop
/*   */     //   734: aload_0
/*   */     //   735: getfield NUl : Lf/f7;
/*   */     //   738: aload #7
/*   */     //   740: getfield Vk : I
/*   */     //   743: invokestatic valueOf : (I)Ljava/lang/Integer;
/*   */     //   746: invokevirtual pd0 : (Ljava/lang/Object;)Ljava/lang/Object;
/*   */     //   749: checkcast f/fQ
/*   */     //   752: aload #4
/*   */     //   754: getfield Ih : Ljava/lang/String;
/*   */     //   757: invokevirtual Com3 : (Ljava/lang/Object;)V
/*   */     //   760: aload_2
/*   */     //   761: areturn
/*   */     //   762: getstatic f/eI.zi : Lf/ik;
/*   */     //   765: invokevirtual getClass : ()Ljava/lang/Class;
/*   */     //   768: pop
/*   */     //   769: aconst_null
/*   */     //   770: areturn
/*   */     // Line number table:
/*   */     //   Java source line number -> byte code offset
/*   */     //   #1	-> 23
/*   */     //   #2	-> 26
/*   */     //   #3	-> 41
/*   */     //   #4	-> 44
/*   */     //   #5	-> 200
/*   */     //   #6	-> 203
/*   */     //   #7	-> 279
/*   */     //   #8	-> 293
/*   */     //   #9	-> 299
/*   */     //   #10	-> 304
/*   */     //   #11	-> 415
/*   */     //   #12	-> 418
/*   */     //   #13	-> 476
/*   */     //   #14	-> 480
/*   */     //   #15	-> 486
/*   */     //   #16	-> 494
/*   */     //   #17	-> 555
/*   */     //   #18	-> 558
/*   */     //   #19	-> 564
/*   */     //   #20	-> 602
/*   */     //   #21	-> 605
/*   */     //   #22	-> 612
/*   */     //   #23	-> 629
/*   */     //   #24	-> 633
/*   */     //   #25	-> 637
/*   */     //   #26	-> 647
/*   */     //   #27	-> 762
/* 3 */     //   #28	-> 765 } public static Lf Tk0; public static KV Z30; public byte zm0; static { (Tk0 = new Lf(uc)).Np(Color.WHITE); Lf lf; (lf = Tk0)
/* 4 */       .Con
/* 5 */       .Tt(lf.coM6); }
/*   */ 
/*   */   
/*   */   public Iq(byte paramByte, hC paramhC, Wd paramWd, int paramInt) {
/*   */     this.zm0 = paramByte;
/*   */     this.td0 = paramInt;
/*   */     yq(paramhC, paramWd);
/*   */   }
/*   */   
/*   */   public Iq(byte paramByte, hC paramhC, Wd paramWd) {
/*   */     this.zm0 = paramByte;
/*   */     yq(paramhC, paramWd);
/*   */   }
/*   */   
/*   */   public Iq() {
/*   */     super(0);
/*   */   } }


/* Location:              /Users/vnnsnnt/Documents/Codespace/JavaWorkspace/RedTrainer/src/main/java/org/trainer/client/PokeMMO.jar!/f/Iq.class
 * Java compiler version: 8 (52.0)
 * JD-Core Version:       1.1.3
 */