/*  1 */ package f;public final class Is0 extends GS implements Np0 { public static void vC(hm0 paramhm0, kf paramkf) { Wl wl; if ((wl = km.wI0.K7) == null)
/*  2 */       return;  byte b = paramhm0.FT;
/*    */     hm0[] arrayOfHm02;
/*    */     int j;
/*    */     byte b1;
/*  6 */     for (j = (arrayOfHm02 = paramkf.AD.cl[b]).length, b1 = 0; b1 < j; ) { hm0 hm01; if ((hm01 = arrayOfHm02[b1]) != null) { byte b2 = 0; byte[] arrayOfByte; while (b2 < (
/*  7 */           arrayOfByte = hm01.wt).length) { if (arrayOfByte[b2] < 0) arrayOfByte[b2] = 0;  b2++; }  wl
/*  8 */           .LW
/*  9 */           .oD(hm01).Eh(); }  b1++; }
/* 10 */      Gp0 gp0 = paramkf.AD;
/*    */     
/*    */     hm0[] arrayOfHm01;
/*    */     
/* 14 */     for (int i = (arrayOfHm01 = gp0.cl[Gp0.Sr0(b)]).length; j < i; ) { hm0 hm01; if ((hm01 = arrayOfHm01[j]) != null) { byte b2 = 0; byte[] arrayOfByte; while (b2 < (
/* 15 */           arrayOfByte = hm01.wt).length) { if (arrayOfByte[b2] > 0) arrayOfByte[b2] = 0;  b2++; }  wl
/* 16 */           .LW
/* 17 */           .oD(hm01).Eh(); }  j++; }  this(paramhm0); LV lV; o60 o60; this((byte)0, o60); paramkf
/* 18 */       .YP.add(lV); }
/*    */ 
/*    */   
/*    */   public final byte Ry0;
/*    */   
/*    */   public Is0(byte paramByte) {
/*    */     this.Ry0 = paramByte;
/*    */   }
/*    */   
/*    */   public static void DS(kf paramkf) {
/*    */     Wl wl;
/*    */     if ((wl = km.wI0.K7) != null) {
/*    */       (paramkf.AD.a0(b)).h30 = 0;
/*    */       byte b;
/*    */       wl.qg0(b = km.MR.hG0(), (short)366);
/*    */       paramkf.AD.Bn(paramkf, b);
/*    */     } 
/*    */   }
/*    */   
/*    */   public static void RY(kf paramkf) {
/*    */     Wl wl;
/*    */     if ((wl = km.wI0.K7) != null) {
/*    */       (paramkf.AD.a0(b)).h30 = 4;
/*    */       byte b;
/*    */       wl.yw0(b = km.MR.hG0(), (short)366);
/*    */       paramkf.AD.Bn(paramkf, b);
/*    */     } 
/*    */   }
/*    */   
/*    */   public static void pi(kf paramkf, hm0 paramhm0) {
/*    */     paramkf.AD.tp(paramhm0);
/*    */     int i = paramhm0.ih();
/*    */     byte b = paramhm0.FT;
/*    */     paramkf.AD.iC0(b, paramhm0.iJ, i).M2();
/*    */     i = paramhm0.FT;
/*    */     paramkf.Oh(i, paramhm0.ws).CX(false);
/*    */     paramkf.Oh(i, paramhm0.ws).COM8(null, false, (short)0);
/*    */   }
/*    */   
/*    */   public static void N00(hm0 paramhm0, kf paramkf) {
/*    */     byte b = Gp0.Sr0(paramhm0.FT);
/*    */     hm0[] arrayOfHm0 = (hm0[])Arrays.<hm0>stream(paramkf.AD.cl[b]).filter(Objects::nonNull).toArray(Is0::NC0);
/*    */     this(paramhm0, false, arrayOfHm0);
/*    */     LV lV;
/*    */     nj nj;
/*    */     this((byte)0, nj);
/*    */     paramkf.YP.add(lV);
/*    */   }
/*    */   
/*    */   public static void k7(hm0 paramhm0, kf paramkf) {
/*    */     Ht0 ht0 = Ht0.cm0;
/*    */     paramhm0.se = ht0;
/*    */     paramkf.oD(paramhm0).Eh();
/*    */   }
/*    */   
/*    */   public final byte YG0() {
/*    */     return 85;
/*    */   }
/*    */   
/*    */   public final void Nl(hm0 paramhm01, hm0 paramhm02, boolean paramBoolean1, boolean paramBoolean2, short paramShort, boolean paramBoolean3, kf paramkf, b60 paramb60) {
/*    */     // Byte code:
/*    */     //   0: aload_0
/*    */     //   1: getfield Ry0 : B
/*    */     //   4: tableswitch default -> 236, 0 -> 1447, 1 -> 1310, 2 -> 1288, 3 -> 1278, 4 -> 1267, 5 -> 1256, 6 -> 1245, 7 -> 1235, 8 -> 1186, 9 -> 1175, 10 -> 1165, 11 -> 1075, 12 -> 1064, 13 -> 1053, 14 -> 236, 15 -> 236, 16 -> 1042, 17 -> 1031, 18 -> 1020, 19 -> 1009, 20 -> 998, 21 -> 966, 22 -> 955, 23 -> 944, 24 -> 933, 25 -> 922, 26 -> 871, 27 -> 814, 28 -> 705, 29 -> 656, 30 -> 646, 31 -> 635, 32 -> 619, 33 -> 604, 34 -> 593, 35 -> 583, 36 -> 551, 37 -> 479, 38 -> 468, 39 -> 457, 40 -> 447, 41 -> 391, 42 -> 380, 43 -> 323, 44 -> 304, 45 -> 236, 46 -> 236, 47 -> 236, 48 -> 287, 49 -> 278, 50 -> 269, 51 -> 259, 52 -> 249, 53 -> 239
/*    */     //   236: goto -> 1511
/*    */     //   239: aload_2
/*    */     //   240: invokevirtual coM1 : ()Ljava/lang/String;
/*    */     //   243: astore_0
/*    */     //   244: ldc 200439
/*    */     //   246: goto -> 1296
/*    */     //   249: aload_2
/*    */     //   250: invokevirtual coM1 : ()Ljava/lang/String;
/*    */     //   253: astore_0
/*    */     //   254: ldc 200404
/*    */     //   256: goto -> 1296
/*    */     //   259: aload_2
/*    */     //   260: invokevirtual coM1 : ()Ljava/lang/String;
/*    */     //   263: astore_0
/*    */     //   264: ldc 200438
/*    */     //   266: goto -> 1296
/*    */     //   269: ldc 200414
/*    */     //   271: invokestatic OH0 : (I)Ljava/lang/String;
/*    */     //   274: astore_0
/*    */     //   275: goto -> 1301
/*    */     //   278: ldc 200413
/*    */     //   280: invokestatic OH0 : (I)Ljava/lang/String;
/*    */     //   283: astore_0
/*    */     //   284: goto -> 1301
/*    */     //   287: aload #7
/*    */     //   289: ldc 200412
/*    */     //   291: invokestatic OH0 : (I)Ljava/lang/String;
/*    */     //   294: astore_0
/*    */     //   295: <illegal opcode> run : (Lf/kf;)Ljava/lang/Runnable;
/*    */     //   300: astore_1
/*    */     //   301: goto -> 1353
/*    */     //   304: aload_2
/*    */     //   305: ldc_w 200512
/*    */     //   308: invokestatic OH0 : (I)Ljava/lang/String;
/*    */     //   311: astore_0
/*    */     //   312: aload #7
/*    */     //   314: <illegal opcode> run : (Lf/hm0;Lf/kf;)Ljava/lang/Runnable;
/*    */     //   319: astore_1
/*    */     //   320: goto -> 1353
/*    */     //   323: aload #7
/*    */     //   325: aload_2
/*    */     //   326: dup
/*    */     //   327: aload #7
/*    */     //   329: new f/LV
/*    */     //   332: dup
/*    */     //   333: astore_0
/*    */     //   334: new f/ky0
/*    */     //   337: dup
/*    */     //   338: aload_2
/*    */     //   339: swap
/*    */     //   340: aload_2
/*    */     //   341: invokespecial <init> : (Lf/hm0;)V
/*    */     //   344: invokevirtual SK : (Lf/hm0;)Lf/wb;
/*    */     //   347: iconst_0
/*    */     //   348: swap
/*    */     //   349: invokespecial <init> : (BLf/wb;)V
/*    */     //   352: getfield YP : Ljava/util/LinkedList;
/*    */     //   355: aload_0
/*    */     //   356: invokevirtual add : (Ljava/lang/Object;)Z
/*    */     //   359: pop
/*    */     //   360: invokevirtual coM1 : ()Ljava/lang/String;
/*    */     //   363: ldc_w 16807029
/*    */     //   366: swap
/*    */     //   367: invokestatic Go : (ILjava/lang/String;)Ljava/lang/String;
/*    */     //   370: astore_0
/*    */     //   371: <illegal opcode> run : (Lf/kf;Lf/hm0;)Ljava/lang/Runnable;
/*    */     //   376: astore_1
/*    */     //   377: goto -> 801
/*    */     //   380: aload_2
/*    */     //   381: invokevirtual coM1 : ()Ljava/lang/String;
/*    */     //   384: astore_0
/*    */     //   385: ldc_w 200437
/*    */     //   388: goto -> 1296
/*    */     //   391: aload #7
/*    */     //   393: dup
/*    */     //   394: dup
/*    */     //   395: new f/LV
/*    */     //   398: dup
/*    */     //   399: astore_0
/*    */     //   400: getstatic f/O5.AU : Lf/O5;
/*    */     //   403: aload_2
/*    */     //   404: sipush #366
/*    */     //   407: invokevirtual xa : (Lf/hm0;S)Lf/wb;
/*    */     //   410: iconst_0
/*    */     //   411: swap
/*    */     //   412: invokespecial <init> : (BLf/wb;)V
/*    */     //   415: getfield YP : Ljava/util/LinkedList;
/*    */     //   418: aload_0
/*    */     //   419: invokevirtual add : (Ljava/lang/Object;)Z
/*    */     //   422: pop
/*    */     //   423: ldc_w 200411
/*    */     //   426: invokestatic OH0 : (I)Ljava/lang/String;
/*    */     //   429: astore_0
/*    */     //   430: <illegal opcode> run : (Lf/kf;)Ljava/lang/Runnable;
/*    */     //   435: astore_1
/*    */     //   436: aload_0
/*    */     //   437: ldc_w ''
/*    */     //   440: aload_1
/*    */     //   441: invokevirtual r00 : (Ljava/lang/String;Ljava/lang/String;Ljava/lang/Runnable;)V
/*    */     //   444: goto -> 1511
/*    */     //   447: ldc_w 200410
/*    */     //   450: invokestatic OH0 : (I)Ljava/lang/String;
/*    */     //   453: astore_0
/*    */     //   454: goto -> 1301
/*    */     //   457: aload_2
/*    */     //   458: invokevirtual coM1 : ()Ljava/lang/String;
/*    */     //   461: astore_0
/*    */     //   462: ldc_w 200409
/*    */     //   465: goto -> 1296
/*    */     //   468: aload_2
/*    */     //   469: invokevirtual coM1 : ()Ljava/lang/String;
/*    */     //   472: astore_0
/*    */     //   473: ldc_w 200408
/*    */     //   476: goto -> 1296
/*    */     //   479: aload #7
/*    */     //   481: ldc_w 200407
/*    */     //   484: invokestatic OH0 : (I)Ljava/lang/String;
/*    */     //   487: invokevirtual Kq : (Ljava/lang/String;)V
/*    */     //   490: getstatic f/km.MR : Lf/Gp0;
/*    */     //   493: dup
/*    */     //   494: astore_0
/*    */     //   495: ifnull -> 1511
/*    */     //   498: aload_0
/*    */     //   499: aload_2
/*    */     //   500: getfield FT : B
/*    */     //   503: istore_0
/*    */     //   504: getfield cl : [[Lf/hm0;
/*    */     //   507: iload_0
/*    */     //   508: aaload
/*    */     //   509: dup
/*    */     //   510: astore_0
/*    */     //   511: arraylength
/*    */     //   512: istore_1
/*    */     //   513: iconst_0
/*    */     //   514: istore_2
/*    */     //   515: iload_2
/*    */     //   516: iload_1
/*    */     //   517: if_icmpge -> 1511
/*    */     //   520: aload_0
/*    */     //   521: iload_2
/*    */     //   522: aaload
/*    */     //   523: dup
/*    */     //   524: astore_3
/*    */     //   525: ifnull -> 545
/*    */     //   528: aload_3
/*    */     //   529: getfield K0 : Lf/jd0;
/*    */     //   532: invokevirtual AL : ()Z
/*    */     //   535: ifeq -> 541
/*    */     //   538: goto -> 545
/*    */     //   541: aload_3
/*    */     //   542: invokevirtual K00 : ()V
/*    */     //   545: iinc #2, 1
/*    */     //   548: goto -> 515
/*    */     //   551: iconst_2
/*    */     //   552: anewarray java/lang/String
/*    */     //   555: dup
/*    */     //   556: astore_0
/*    */     //   557: aload_2
/*    */     //   558: aload_0
/*    */     //   559: aload_1
/*    */     //   560: invokevirtual coM1 : ()Ljava/lang/String;
/*    */     //   563: iconst_0
/*    */     //   564: swap
/*    */     //   565: aastore
/*    */     //   566: invokevirtual coM1 : ()Ljava/lang/String;
/*    */     //   569: iconst_1
/*    */     //   570: swap
/*    */     //   571: aastore
/*    */     //   572: ldc_w 200406
/*    */     //   575: aload_0
/*    */     //   576: invokestatic sB : (I[Ljava/lang/String;)Ljava/lang/String;
/*    */     //   579: astore_0
/*    */     //   580: goto -> 1301
/*    */     //   583: ldc_w 200405
/*    */     //   586: invokestatic OH0 : (I)Ljava/lang/String;
/*    */     //   589: astore_0
/*    */     //   590: goto -> 1301
/*    */     //   593: aload_2
/*    */     //   594: invokevirtual coM1 : ()Ljava/lang/String;
/*    */     //   597: astore_0
/*    */     //   598: ldc_w 200403
/*    */     //   601: goto -> 1296
/*    */     //   604: aload_2
/*    */     //   605: dup
/*    */     //   606: invokevirtual getClass : ()Ljava/lang/Class;
/*    */     //   609: pop
/*    */     //   610: invokevirtual coM1 : ()Ljava/lang/String;
/*    */     //   613: astore_0
/*    */     //   614: ldc 200404
/*    */     //   616: goto -> 1296
/*    */     //   619: aload_2
/*    */     //   620: dup
/*    */     //   621: invokevirtual getClass : ()Ljava/lang/Class;
/*    */     //   624: pop
/*    */     //   625: invokevirtual coM1 : ()Ljava/lang/String;
/*    */     //   628: astore_0
/*    */     //   629: ldc_w 200403
/*    */     //   632: goto -> 1296
/*    */     //   635: aload_2
/*    */     //   636: invokevirtual coM1 : ()Ljava/lang/String;
/*    */     //   639: astore_0
/*    */     //   640: ldc_w 200356
/*    */     //   643: goto -> 1296
/*    */     //   646: ldc_w 200357
/*    */     //   649: invokestatic OH0 : (I)Ljava/lang/String;
/*    */     //   652: astore_0
/*    */     //   653: goto -> 1301
/*    */     //   656: aload #7
/*    */     //   658: aload_2
/*    */     //   659: invokevirtual coM1 : ()Ljava/lang/String;
/*    */     //   662: ldc_w 200358
/*    */     //   665: swap
/*    */     //   666: invokestatic Go : (ILjava/lang/String;)Ljava/lang/String;
/*    */     //   669: invokevirtual Kq : (Ljava/lang/String;)V
/*    */     //   672: new f/LV
/*    */     //   675: dup
/*    */     //   676: astore_0
/*    */     //   677: new f/nj
/*    */     //   680: dup
/*    */     //   681: astore_3
/*    */     //   682: aload_1
/*    */     //   683: iconst_1
/*    */     //   684: anewarray f/hm0
/*    */     //   687: dup
/*    */     //   688: astore_1
/*    */     //   689: iconst_0
/*    */     //   690: aload_2
/*    */     //   691: aastore
/*    */     //   692: iconst_0
/*    */     //   693: aload_1
/*    */     //   694: invokespecial <init> : (Lf/hm0;Z[Lf/hm0;)V
/*    */     //   697: iconst_0
/*    */     //   698: aload_3
/*    */     //   699: invokespecial <init> : (BLf/wb;)V
/*    */     //   702: goto -> 1501
/*    */     //   705: aload_2
/*    */     //   706: aload #7
/*    */     //   708: aload_2
/*    */     //   709: aload #7
/*    */     //   711: dup
/*    */     //   712: dup
/*    */     //   713: new f/LV
/*    */     //   716: dup
/*    */     //   717: astore_0
/*    */     //   718: new f/xU
/*    */     //   721: dup
/*    */     //   722: aload_2
/*    */     //   723: swap
/*    */     //   724: aload_2
/*    */     //   725: invokespecial <init> : (Lf/hm0;)V
/*    */     //   728: invokevirtual SK : (Lf/hm0;)Lf/wb;
/*    */     //   731: iconst_0
/*    */     //   732: swap
/*    */     //   733: invokespecial <init> : (BLf/wb;)V
/*    */     //   736: getfield YP : Ljava/util/LinkedList;
/*    */     //   739: aload_0
/*    */     //   740: invokevirtual add : (Ljava/lang/Object;)Z
/*    */     //   743: pop
/*    */     //   744: getstatic f/F40.ef0 : Lf/F40;
/*    */     //   747: astore_0
/*    */     //   748: getfield AD : Lf/Gp0;
/*    */     //   751: sipush #736
/*    */     //   754: aload_2
/*    */     //   755: invokevirtual ex : (ILf/hm0;)I
/*    */     //   758: istore_1
/*    */     //   759: iconst_1
/*    */     //   760: anewarray java/lang/String
/*    */     //   763: dup
/*    */     //   764: astore_3
/*    */     //   765: aload_2
/*    */     //   766: invokevirtual coM1 : ()Ljava/lang/String;
/*    */     //   769: iconst_0
/*    */     //   770: swap
/*    */     //   771: aastore
/*    */     //   772: iconst_2
/*    */     //   773: aload_0
/*    */     //   774: bipush #14
/*    */     //   776: iload_1
/*    */     //   777: aload_3
/*    */     //   778: invokestatic lz : (BLf/F40;II[Ljava/lang/String;)Ljava/lang/String;
/*    */     //   781: invokevirtual Kq : (Ljava/lang/String;)V
/*    */     //   784: iconst_1
/*    */     //   785: putfield N3 : Z
/*    */     //   788: ldc_w 200366
/*    */     //   791: invokestatic OH0 : (I)Ljava/lang/String;
/*    */     //   794: astore_0
/*    */     //   795: <illegal opcode> run : (Lf/hm0;Lf/kf;)Ljava/lang/Runnable;
/*    */     //   800: astore_1
/*    */     //   801: aload #7
/*    */     //   803: aload_0
/*    */     //   804: ldc_w ''
/*    */     //   807: aload_1
/*    */     //   808: invokevirtual RV : (Ljava/lang/String;Ljava/lang/String;Ljava/lang/Runnable;)V
/*    */     //   811: goto -> 1511
/*    */     //   814: aload #7
/*    */     //   816: aload_2
/*    */     //   817: invokevirtual coM1 : ()Ljava/lang/String;
/*    */     //   820: ldc_w 200368
/*    */     //   823: swap
/*    */     //   824: invokestatic Go : (ILjava/lang/String;)Ljava/lang/String;
/*    */     //   827: invokevirtual cr : (Ljava/lang/String;)V
/*    */     //   830: new f/Sr0
/*    */     //   833: dup
/*    */     //   834: astore_0
/*    */     //   835: aload_2
/*    */     //   836: dup
/*    */     //   837: aload_1
/*    */     //   838: dup
/*    */     //   839: getfield FT : B
/*    */     //   842: istore_1
/*    */     //   843: getfield ws : B
/*    */     //   846: istore_2
/*    */     //   847: getfield FT : B
/*    */     //   850: istore_3
/*    */     //   851: getfield ws : B
/*    */     //   854: istore #4
/*    */     //   856: iload_1
/*    */     //   857: iload_2
/*    */     //   858: iload_3
/*    */     //   859: iload #4
/*    */     //   861: sipush #1026
/*    */     //   864: iconst_0
/*    */     //   865: invokespecial <init> : (BBBBSZ)V
/*    */     //   868: goto -> 1501
/*    */     //   871: aload #7
/*    */     //   873: new f/Sr0
/*    */     //   876: dup
/*    */     //   877: astore_0
/*    */     //   878: aload_2
/*    */     //   879: dup
/*    */     //   880: aload_1
/*    */     //   881: dup
/*    */     //   882: getfield FT : B
/*    */     //   885: istore_1
/*    */     //   886: getfield ws : B
/*    */     //   889: istore_2
/*    */     //   890: getfield FT : B
/*    */     //   893: istore_3
/*    */     //   894: getfield ws : B
/*    */     //   897: istore #4
/*    */     //   899: iload_1
/*    */     //   900: iload_2
/*    */     //   901: iload_3
/*    */     //   902: iload #4
/*    */     //   904: sipush #1025
/*    */     //   907: iconst_0
/*    */     //   908: invokespecial <init> : (BBBBSZ)V
/*    */     //   911: getfield YP : Ljava/util/LinkedList;
/*    */     //   914: aload_0
/*    */     //   915: invokevirtual add : (Ljava/lang/Object;)Z
/*    */     //   918: pop
/*    */     //   919: goto -> 1511
/*    */     //   922: aload_2
/*    */     //   923: invokevirtual coM1 : ()Ljava/lang/String;
/*    */     //   926: astore_0
/*    */     //   927: ldc_w 200399
/*    */     //   930: goto -> 1296
/*    */     //   933: aload_2
/*    */     //   934: invokevirtual coM1 : ()Ljava/lang/String;
/*    */     //   937: astore_0
/*    */     //   938: ldc_w 200398
/*    */     //   941: goto -> 1296
/*    */     //   944: aload_2
/*    */     //   945: invokevirtual coM1 : ()Ljava/lang/String;
/*    */     //   948: astore_0
/*    */     //   949: ldc_w 200397
/*    */     //   952: goto -> 1296
/*    */     //   955: aload_2
/*    */     //   956: invokevirtual coM1 : ()Ljava/lang/String;
/*    */     //   959: astore_0
/*    */     //   960: ldc_w 200396
/*    */     //   963: goto -> 1296
/*    */     //   966: iconst_2
/*    */     //   967: anewarray java/lang/String
/*    */     //   970: dup
/*    */     //   971: astore_0
/*    */     //   972: aload_2
/*    */     //   973: aload_0
/*    */     //   974: aload_1
/*    */     //   975: invokevirtual coM1 : ()Ljava/lang/String;
/*    */     //   978: iconst_0
/*    */     //   979: swap
/*    */     //   980: aastore
/*    */     //   981: invokevirtual coM1 : ()Ljava/lang/String;
/*    */     //   984: iconst_1
/*    */     //   985: swap
/*    */     //   986: aastore
/*    */     //   987: ldc_w 200395
/*    */     //   990: aload_0
/*    */     //   991: invokestatic sB : (I[Ljava/lang/String;)Ljava/lang/String;
/*    */     //   994: astore_0
/*    */     //   995: goto -> 1301
/*    */     //   998: aload_2
/*    */     //   999: invokevirtual coM1 : ()Ljava/lang/String;
/*    */     //   1002: astore_0
/*    */     //   1003: ldc_w 200393
/*    */     //   1006: goto -> 1296
/*    */     //   1009: aload_2
/*    */     //   1010: invokevirtual coM1 : ()Ljava/lang/String;
/*    */     //   1013: astore_0
/*    */     //   1014: ldc_w 200392
/*    */     //   1017: goto -> 1296
/*    */     //   1020: aload_2
/*    */     //   1021: invokevirtual coM1 : ()Ljava/lang/String;
/*    */     //   1024: astore_0
/*    */     //   1025: ldc_w 200391
/*    */     //   1028: goto -> 1296
/*    */     //   1031: aload_2
/*    */     //   1032: invokevirtual coM1 : ()Ljava/lang/String;
/*    */     //   1035: astore_0
/*    */     //   1036: ldc_w 200390
/*    */     //   1039: goto -> 1296
/*    */     //   1042: aload_2
/*    */     //   1043: invokevirtual coM1 : ()Ljava/lang/String;
/*    */     //   1046: astore_0
/*    */     //   1047: ldc_w 200389
/*    */     //   1050: goto -> 1296
/*    */     //   1053: aload_2
/*    */     //   1054: invokevirtual coM1 : ()Ljava/lang/String;
/*    */     //   1057: astore_0
/*    */     //   1058: ldc_w 200523
/*    */     //   1061: goto -> 1296
/*    */     //   1064: aload_2
/*    */     //   1065: invokevirtual coM1 : ()Ljava/lang/String;
/*    */     //   1068: astore_0
/*    */     //   1069: ldc_w 200521
/*    */     //   1072: goto -> 1296
/*    */     //   1075: aload #7
/*    */     //   1077: aload_2
/*    */     //   1078: aload #7
/*    */     //   1080: dup
/*    */     //   1081: getstatic f/F40.ef0 : Lf/F40;
/*    */     //   1084: astore_0
/*    */     //   1085: getfield AD : Lf/Gp0;
/*    */     //   1088: sipush #896
/*    */     //   1091: aload_2
/*    */     //   1092: invokevirtual ex : (ILf/hm0;)I
/*    */     //   1095: istore_1
/*    */     //   1096: iconst_2
/*    */     //   1097: anewarray java/lang/String
/*    */     //   1100: dup
/*    */     //   1101: dup
/*    */     //   1102: astore_3
/*    */     //   1103: aload_2
/*    */     //   1104: invokevirtual coM1 : ()Ljava/lang/String;
/*    */     //   1107: iconst_0
/*    */     //   1108: swap
/*    */     //   1109: aastore
/*    */     //   1110: getstatic f/Ht0.cm0 : Lf/Ht0;
/*    */     //   1113: invokevirtual mn0 : ()Ljava/lang/String;
/*    */     //   1116: iconst_1
/*    */     //   1117: swap
/*    */     //   1118: aastore
/*    */     //   1119: iconst_2
/*    */     //   1120: aload_0
/*    */     //   1121: bipush #14
/*    */     //   1123: iload_1
/*    */     //   1124: aload_3
/*    */     //   1125: invokestatic lz : (BLf/F40;II[Ljava/lang/String;)Ljava/lang/String;
/*    */     //   1128: astore_0
/*    */     //   1129: <illegal opcode> run : (Lf/hm0;Lf/kf;)Ljava/lang/Runnable;
/*    */     //   1134: astore_1
/*    */     //   1135: aload_0
/*    */     //   1136: ldc_w ''
/*    */     //   1139: aload_1
/*    */     //   1140: invokevirtual r00 : (Ljava/lang/String;Ljava/lang/String;Ljava/lang/Runnable;)V
/*    */     //   1143: new f/LV
/*    */     //   1146: dup
/*    */     //   1147: astore_0
/*    */     //   1148: new f/SH
/*    */     //   1151: dup
/*    */     //   1152: astore_1
/*    */     //   1153: aload_2
/*    */     //   1154: invokespecial <init> : (Lf/hm0;)V
/*    */     //   1157: iconst_0
/*    */     //   1158: aload_1
/*    */     //   1159: invokespecial <init> : (BLf/wb;)V
/*    */     //   1162: goto -> 1501
/*    */     //   1165: ldc_w 200381
/*    */     //   1168: invokestatic OH0 : (I)Ljava/lang/String;
/*    */     //   1171: astore_0
/*    */     //   1172: goto -> 1301
/*    */     //   1175: aload_2
/*    */     //   1176: invokevirtual coM1 : ()Ljava/lang/String;
/*    */     //   1179: astore_0
/*    */     //   1180: ldc_w 200514
/*    */     //   1183: goto -> 1296
/*    */     //   1186: aload_2
/*    */     //   1187: iconst_3
/*    */     //   1188: anewarray java/lang/String
/*    */     //   1191: dup
/*    */     //   1192: dup
/*    */     //   1193: astore_0
/*    */     //   1194: aload_2
/*    */     //   1195: aload_0
/*    */     //   1196: aload_1
/*    */     //   1197: invokevirtual coM1 : ()Ljava/lang/String;
/*    */     //   1200: iconst_0
/*    */     //   1201: swap
/*    */     //   1202: aastore
/*    */     //   1203: invokevirtual coM1 : ()Ljava/lang/String;
/*    */     //   1206: iconst_1
/*    */     //   1207: swap
/*    */     //   1208: aastore
/*    */     //   1209: ldc_w 100033
/*    */     //   1212: invokestatic OH0 : (I)Ljava/lang/String;
/*    */     //   1215: iconst_2
/*    */     //   1216: swap
/*    */     //   1217: aastore
/*    */     //   1218: ldc_w 200377
/*    */     //   1221: aload_0
/*    */     //   1222: invokestatic sB : (I[Ljava/lang/String;)Ljava/lang/String;
/*    */     //   1225: astore_0
/*    */     //   1226: <illegal opcode> run : (Lf/hm0;)Ljava/lang/Runnable;
/*    */     //   1231: astore_1
/*    */     //   1232: goto -> 1353
/*    */     //   1235: ldc_w 200387
/*    */     //   1238: invokestatic OH0 : (I)Ljava/lang/String;
/*    */     //   1241: astore_0
/*    */     //   1242: goto -> 1301
/*    */     //   1245: aload_2
/*    */     //   1246: invokevirtual coM1 : ()Ljava/lang/String;
/*    */     //   1249: astore_0
/*    */     //   1250: ldc_w 200383
/*    */     //   1253: goto -> 1296
/*    */     //   1256: aload_2
/*    */     //   1257: invokevirtual coM1 : ()Ljava/lang/String;
/*    */     //   1260: astore_0
/*    */     //   1261: ldc_w 200382
/*    */     //   1264: goto -> 1296
/*    */     //   1267: aload_2
/*    */     //   1268: invokevirtual coM1 : ()Ljava/lang/String;
/*    */     //   1271: astore_0
/*    */     //   1272: ldc_w 200386
/*    */     //   1275: goto -> 1296
/*    */     //   1278: ldc_w 200385
/*    */     //   1281: invokestatic OH0 : (I)Ljava/lang/String;
/*    */     //   1284: astore_0
/*    */     //   1285: goto -> 1301
/*    */     //   1288: aload_2
/*    */     //   1289: invokevirtual coM1 : ()Ljava/lang/String;
/*    */     //   1292: astore_0
/*    */     //   1293: ldc_w 200379
/*    */     //   1296: aload_0
/*    */     //   1297: invokestatic Go : (ILjava/lang/String;)Ljava/lang/String;
/*    */     //   1300: astore_0
/*    */     //   1301: aload #7
/*    */     //   1303: aload_0
/*    */     //   1304: invokevirtual Kq : (Ljava/lang/String;)V
/*    */     //   1307: goto -> 1511
/*    */     //   1310: aload_1
/*    */     //   1311: aload_2
/*    */     //   1312: if_acmpne -> 1366
/*    */     //   1315: aload_2
/*    */     //   1316: iconst_2
/*    */     //   1317: anewarray java/lang/String
/*    */     //   1320: dup
/*    */     //   1321: dup
/*    */     //   1322: astore_0
/*    */     //   1323: aload_1
/*    */     //   1324: invokevirtual coM1 : ()Ljava/lang/String;
/*    */     //   1327: iconst_0
/*    */     //   1328: swap
/*    */     //   1329: aastore
/*    */     //   1330: ldc_w 100037
/*    */     //   1333: invokestatic OH0 : (I)Ljava/lang/String;
/*    */     //   1336: iconst_1
/*    */     //   1337: swap
/*    */     //   1338: aastore
/*    */     //   1339: sipush #6062
/*    */     //   1342: aload_0
/*    */     //   1343: invokestatic sB : (I[Ljava/lang/String;)Ljava/lang/String;
/*    */     //   1346: astore_0
/*    */     //   1347: <illegal opcode> run : (Lf/hm0;)Ljava/lang/Runnable;
/*    */     //   1352: astore_1
/*    */     //   1353: aload #7
/*    */     //   1355: aload_0
/*    */     //   1356: ldc_w ''
/*    */     //   1359: aload_1
/*    */     //   1360: invokevirtual RV : (Ljava/lang/String;Ljava/lang/String;Ljava/lang/Runnable;)V
/*    */     //   1363: goto -> 1511
/*    */     //   1366: aload #7
/*    */     //   1368: aload_2
/*    */     //   1369: iconst_3
/*    */     //   1370: anewarray java/lang/String
/*    */     //   1373: dup
/*    */     //   1374: dup
/*    */     //   1375: astore_0
/*    */     //   1376: aload_2
/*    */     //   1377: aload_0
/*    */     //   1378: aload_1
/*    */     //   1379: invokevirtual coM1 : ()Ljava/lang/String;
/*    */     //   1382: iconst_0
/*    */     //   1383: swap
/*    */     //   1384: aastore
/*    */     //   1385: invokevirtual coM1 : ()Ljava/lang/String;
/*    */     //   1388: iconst_1
/*    */     //   1389: swap
/*    */     //   1390: aastore
/*    */     //   1391: ldc_w 100037
/*    */     //   1394: invokestatic OH0 : (I)Ljava/lang/String;
/*    */     //   1397: iconst_2
/*    */     //   1398: swap
/*    */     //   1399: aastore
/*    */     //   1400: ldc_w 200377
/*    */     //   1403: aload_0
/*    */     //   1404: invokestatic sB : (I[Ljava/lang/String;)Ljava/lang/String;
/*    */     //   1407: astore_0
/*    */     //   1408: <illegal opcode> run : (Lf/hm0;)Ljava/lang/Runnable;
/*    */     //   1413: astore_3
/*    */     //   1414: aload_0
/*    */     //   1415: ldc_w ''
/*    */     //   1418: aload_3
/*    */     //   1419: invokevirtual r00 : (Ljava/lang/String;Ljava/lang/String;Ljava/lang/Runnable;)V
/*    */     //   1422: new f/LV
/*    */     //   1425: dup
/*    */     //   1426: astore_0
/*    */     //   1427: new f/yP
/*    */     //   1430: dup
/*    */     //   1431: aload_1
/*    */     //   1432: invokespecial <init> : (Lf/hm0;)V
/*    */     //   1435: aload_2
/*    */     //   1436: invokevirtual SK : (Lf/hm0;)Lf/wb;
/*    */     //   1439: iconst_0
/*    */     //   1440: swap
/*    */     //   1441: invokespecial <init> : (BLf/wb;)V
/*    */     //   1444: goto -> 1501
/*    */     //   1447: aload #7
/*    */     //   1449: iconst_2
/*    */     //   1450: anewarray java/lang/String
/*    */     //   1453: dup
/*    */     //   1454: dup
/*    */     //   1455: astore_0
/*    */     //   1456: aload_1
/*    */     //   1457: invokevirtual coM1 : ()Ljava/lang/String;
/*    */     //   1460: iconst_0
/*    */     //   1461: swap
/*    */     //   1462: aastore
/*    */     //   1463: ldc_w 100037
/*    */     //   1466: invokestatic OH0 : (I)Ljava/lang/String;
/*    */     //   1469: iconst_1
/*    */     //   1470: swap
/*    */     //   1471: aastore
/*    */     //   1472: ldc_w 200378
/*    */     //   1475: aload_0
/*    */     //   1476: invokestatic sB : (I[Ljava/lang/String;)Ljava/lang/String;
/*    */     //   1479: invokevirtual cr : (Ljava/lang/String;)V
/*    */     //   1482: new f/LV
/*    */     //   1485: dup
/*    */     //   1486: astore_0
/*    */     //   1487: new f/s60
/*    */     //   1490: dup
/*    */     //   1491: astore_1
/*    */     //   1492: aload_2
/*    */     //   1493: invokespecial <init> : (Lf/hm0;)V
/*    */     //   1496: iconst_0
/*    */     //   1497: aload_1
/*    */     //   1498: invokespecial <init> : (BLf/wb;)V
/*    */     //   1501: aload #7
/*    */     //   1503: getfield YP : Ljava/util/LinkedList;
/*    */     //   1506: aload_0
/*    */     //   1507: invokevirtual add : (Ljava/lang/Object;)Z
/*    */     //   1510: pop
/*    */     //   1511: return
/*    */     // Line number table:
/*    */     //   Java source line number -> byte code offset
/*    */     //   #1	-> 1
/*    */     //   #2	-> 240
/*    */     //   #3	-> 352
/*    */     //   #4	-> 356
/*    */     //   #5	-> 360
/*    */     //   #6	-> 400
/*    */     //   #7	-> 407
/*    */     //   #8	-> 415
/*    */     //   #9	-> 419
/*    */     //   #10	-> 426
/*    */     //   #11	-> 437
/*    */     //   #12	-> 450
/*    */     //   #13	-> 500
/*    */     //   #14	-> 504
/*    */     //   #15	-> 508
/*    */     //   #16	-> 511
/*    */     //   #17	-> 529
/*    */     //   #18	-> 542
/*    */     //   #19	-> 736
/*    */     //   #20	-> 740
/*    */     //   #21	-> 744
/*    */     //   #22	-> 748
/*    */     //   #23	-> 755
/*    */     //   #24	-> 778
/*    */     //   #25	-> 781
/*    */     //   #26	-> 785
/*    */     //   #27	-> 791
/*    */     //   #28	-> 804
/*    */     //   #29	-> 817
/*    */     //   #30	-> 839
/*    */     //   #31	-> 843
/*    */     //   #32	-> 847
/*    */     //   #33	-> 851
/*    */     //   #34	-> 865
/*    */     //   #35	-> 882
/*    */     //   #36	-> 886
/*    */     //   #37	-> 890
/*    */     //   #38	-> 894
/*    */     //   #39	-> 908
/*    */     //   #40	-> 911
/*    */     //   #41	-> 915
/*    */     //   #42	-> 923
/*    */     //   #43	-> 1085
/*    */     //   #44	-> 1092
/*    */     //   #45	-> 1125
/*    */     //   #46	-> 1129
/*    */     //   #47	-> 1136
/*    */     //   #48	-> 1143
/*    */     //   #49	-> 1356
/*    */     //   #50	-> 1370
/*    */     //   #51	-> 1415
/*    */     //   #52	-> 1422
/*    */     //   #53	-> 1503
/*    */   }
/*    */   
/*    */   public final boolean Lt() {
/*    */     switch (this.Ry0) {
/*    */       default:
/*    */         return true;
/*    */       case 3:
/*    */       case 7:
/*    */       case 10:
/*    */       case 16:
/*    */       case 30:
/*    */       case 35:
/*    */       case 37:
/*    */       case 40:
/*    */       case 41:
/*    */       case 48:
/*    */       case 49:
/*    */       case 50:
/*    */         return false;
/*    */       case 0:
/*    */       case 1:
/*    */       case 2:
/*    */       case 4:
/*    */       case 5:
/*    */       case 6:
/*    */       case 8:
/*    */       case 9:
/*    */       case 11:
/*    */       case 12:
/*    */       case 13:
/*    */       case 17:
/*    */       case 18:
/*    */       case 19:
/*    */       case 20:
/*    */       case 21:
/*    */       case 22:
/*    */       case 23:
/*    */       case 24:
/*    */       case 25:
/*    */       case 26:
/*    */       case 27:
/*    */       case 28:
/*    */       case 29:
/*    */       case 31:
/*    */       case 32:
/*    */       case 33:
/*    */       case 34:
/*    */       case 36:
/*    */       case 38:
/*    */       case 42:
/*    */       case 43:
/*    */       case 44:
/*    */         break;
/*    */     } 
/*    */     return true;
/*    */   } }


/* Location:              /Users/vnnsnnt/Documents/Codespace/JavaWorkspace/RedTrainer/src/main/java/org/trainer/client/PokeMMO.jar!/f/Is0.class
 * Java compiler version: 8 (52.0)
 * JD-Core Version:       1.1.3
 */