/*  1 */ package f;public class It { public wR q1; public String y5; public boolean KE; public BB kI; public boolean Xj; public final f7 mw0; public final f7 B80; public static Object Tx(Class<?> paramClass) { try { return paramClass.newInstance(); } catch (InstantiationException null) { throw new BC("Could not instantiate instance of class: " + paramClass.getName(), exception); } catch (IllegalAccessException null) { throw new BC("Could not instantiate instance of class: " + paramClass.getName(), exception); } catch (Exception null) {} 
/*  2 */     try { Class[] arrayOfClass = new Class[0]; 
/*  3 */       try { boolean bool = true; (new N00(paramClass.getDeclaredConstructor(arrayOfClass)))
/*  4 */           .hx0.setAccessible(bool);
/*  5 */         return (new N00(paramClass.getDeclaredConstructor(arrayOfClass))).qC(new Object[0]); }
/*  6 */       catch (SecurityException securityException) { throw new BC("Security violation while getting constructor for class: " + paramClass.getName(), securityException); } catch (NoSuchMethodException noSuchMethodException) { throw new BC("Constructor not found for class: " + paramClass.getName(), noSuchMethodException);
/*    */ 
/*    */ 
/*    */         
/*    */          }
/*    */ 
/*    */ 
/*    */ 
/*    */       
/*    */        }
/*    */     
/* 17 */     catch (SecurityException securityException) {  } catch (BC bC) { if (Enum.class.isAssignableFrom(paramClass)) { if (paramClass.getEnumConstants() == null) paramClass = paramClass.getSuperclass();  return paramClass.getEnumConstants()[0]; }  if (!paramClass.isArray()) { if (paramClass.isMemberClass() && !Modifier.isStatic(paramClass.getModifiers())) throw new kN(B40.df("Class cannot be created (non-static member class): ").append(paramClass.getName()).toString(), exception);  throw new kN(B40.df("Class cannot be created (missing no-arg constructor): ").append(paramClass.getName()).toString(), exception); }  throw new kN(B40.df("Encountered JSON object when expected array of type: ").append(paramClass.getName()).toString(), exception); } catch (Exception exception) {} throw new kN(
/* 18 */         B40.df("Error constructing instance of class: ")
/* 19 */         .append(paramClass.getName()).toString(), exception); }
/*    */   public final f7 zd0;
/* 21 */   public final f7 f3; public final f7 gp; public final Object[] pU; public final Object[] Jv0; public It() { this.y5 = "class"; this.KE = true; this.Xj = true; this.mw0 = new f7(); this.B80 = new f7(); this.zd0 = new f7(); this.f3 = new f7(); this.gp = new f7(); this.pU = new Object[] { null }; this.Jv0 = new Object[] { null }; this.kI = BB.NH0; } public It(BB paramBB) { f7 f71; this.y5 = "class"; this.KE = true; this.Xj = true; this(); this.mw0 = this; this(); this.B80 = this; this(); this.zd0 = this; this(); this.f3 = this; this(); this.gp = this; Object[] arrayOfObject; (arrayOfObject = new Object[1])[0] = null; this.pU = this; (arrayOfObject = new Object[1])[0] = null; this.Jv0 = this; this.kI = paramBB; } public void for(Object paramObject, bM0 parambM0) { Class<?> clazz; Nn nn = gf0(clazz = paramObject.getClass()); bM0 bM01 = parambM0.Rr0; while (true) { if (bM01 != null) { CoM2 coM2; if ((coM2 = (CoM2)nn.pd0(bM01.as0.replace(" ", "_"))) == null) { if (!bM01.as0.equals(this.y5) && !fa(bM01.as0)) { (new kN(B40.df("Field not found: ").append(bM01.as0).append(" (").append(clazz.getName()).append(")").toString())).K7(bM01.in()); throw new kN(B40.df("Field not found: ").append(bM01.as0).append(" (").append(clazz.getName()).append(")").toString()); }  } else { CL0 cL0; try { Class<?> clazz1 = (cL0 = coM2.WW).Lh.getType(); Object object = Uj0(clazz1, coM2.WU, bM01); try { cL0.Lh.set(paramObject, object); bM01 = bM01.H7; continue; } catch (IllegalArgumentException illegalArgumentException) { throw new BC("Argument not valid for field: " + cL0.Lh.getName(), this); } catch (IllegalAccessException illegalAccessException) { throw new BC("Illegal access to field: " + cL0.Lh.getName(), this); }  } catch (BC bC) { throw new kN(
/* 22 */                 B40.df("Error accessing field: ")
/*    */ 
/*    */                 
/* 25 */                 .append(cL0.Lh.getName()).append(" (").append(clazz.getName()).append(")").toString(), this); }
/*    */           catch (kN kN)
/*    */           { K7(cL0.Lh.getName() + " (" + clazz.getName() + ")");
/*    */             throw this; }
/*    */           catch (RuntimeException runtimeException)
/*    */           { (new kN(this)).K7(bM01.in());
/*    */             (new kN(this)).K7(cL0.Lh.getName() + " (" + clazz.getName() + ")");
/*    */             throw new kN(this); }
/*    */            }
/*    */          }
/*    */       else
/*    */       { break; }
/*    */       
/*    */       bM01 = bM01.H7; }
/*    */      }
/*    */ 
/*    */   
/*    */   public final Nn gf0(Class<Object> paramClass) {
/*    */     Nn nn2;
/*    */     if ((nn2 = (Nn)this.mw0.pd0(paramClass)) != null)
/*    */       return nn2; 
/*    */     this();
/*    */     fQ fQ;
/*    */     Nn nn1;
/*    */     ArrayList<? super CL0> arrayList;
/*    */     for (Class<Object> clazz = paramClass; clazz != Object.class; ) {
/*    */       fQ.Com3(clazz);
/*    */       clazz = (Class)clazz.getSuperclass();
/*    */     } 
/*    */     this();
/*    */     int i;
/*    */     for (i = fQ.Z8 - 1; i >= 0; ) {
/*    */       Field[] arrayOfField;
/*    */       CL0[] arrayOfCL0;
/*    */       byte b;
/*    */       int k;
/*    */       for (arrayOfCL0 = new CL0[(arrayOfField = ((Class)fQ.get(i)).getDeclaredFields()).length], b = 0, k = (((Class)fQ.get(i)).getDeclaredFields()).length; b < k; ) {
/*    */         CL0 cL0;
/*    */         this(arrayOfField[b]);
/*    */         arrayOfCL0[b] = cL0;
/*    */         b++;
/*    */       } 
/*    */       Collections.addAll(arrayList, arrayOfCL0);
/*    */       i--;
/*    */     } 
/*    */     this(arrayList.size());
/*    */     int j;
/*    */     for (i = 0, j = arrayList.size(); i < j; ) {
/*    */       CL0 cL0;
/*    */       if (!Modifier.isTransient((cL0 = arrayList.get(i)).Lh.getModifiers()) && !Modifier.isStatic(cL0.Lh.getModifiers()) && !cL0.Lh.isSynthetic()) {
/*    */         if (!cL0.Lh.isAccessible()) {
/*    */           boolean bool = true;
/*    */           try {
/*    */             cL0.Lh.setAccessible(bool);
/*    */           } catch (AccessControlException accessControlException) {}
/*    */         } 
/*    */         nn1.X00(cL0.Lh.getName(), new CoM2(cL0));
/*    */       } 
/*    */       i++;
/*    */     } 
/*    */     this.mw0.X00(paramClass, nn1);
/*    */     return nn1;
/*    */   }
/*    */   
/*    */   public final String P70(Object paramObject) {
/*    */     if (paramObject instanceof Enum) {
/*    */       String str;
/*    */       Enum enum_ = (Enum)paramObject;
/*    */       if (this.Xj) {
/*    */         str = name();
/*    */       } else {
/*    */         str = toString();
/*    */       } 
/*    */       return this;
/*    */     } 
/*    */     return (paramObject instanceof Class) ? ((Class)paramObject).getName() : String.valueOf(paramObject);
/*    */   }
/*    */   
/*    */   public final void C70(BB paramBB) {
/*    */     this.kI = paramBB;
/*    */   }
/*    */   
/*    */   public final void oS(Writer paramWriter) {
/*    */     if (!(paramWriter instanceof wR)) {
/*    */       wR wR1;
/*    */       this(paramWriter);
/*    */       paramWriter = wR1;
/*    */     } 
/*    */     this.q1 = (wR)paramWriter;
/*    */     ((wR)(paramWriter = paramWriter)).ay0 = this.kI;
/*    */     ((wR)paramWriter).wR = false;
/*    */   }
/*    */   
/*    */   public final void K9(Object paramObject) {
/*    */     // Byte code:
/*    */     //   0: aload_0
/*    */     //   1: aload_1
/*    */     //   2: invokevirtual getClass : ()Ljava/lang/Class;
/*    */     //   5: astore_2
/*    */     //   6: getfield KE : Z
/*    */     //   9: ifne -> 17
/*    */     //   12: aconst_null
/*    */     //   13: astore_3
/*    */     //   14: goto -> 297
/*    */     //   17: aload_0
/*    */     //   18: getfield gp : Lf/f7;
/*    */     //   21: aload_2
/*    */     //   22: invokevirtual GB0 : (Ljava/lang/Object;)Z
/*    */     //   25: ifeq -> 43
/*    */     //   28: aload_0
/*    */     //   29: getfield gp : Lf/f7;
/*    */     //   32: aload_2
/*    */     //   33: invokevirtual pd0 : (Ljava/lang/Object;)Ljava/lang/Object;
/*    */     //   36: checkcast [Ljava/lang/Object;
/*    */     //   39: astore_3
/*    */     //   40: goto -> 297
/*    */     //   43: aload_0
/*    */     //   44: aload_2
/*    */     //   45: dup
/*    */     //   46: invokestatic Tx : (Ljava/lang/Class;)Ljava/lang/Object;
/*    */     //   49: astore_3
/*    */     //   50: invokevirtual gf0 : (Ljava/lang/Class;)Lf/Nn;
/*    */     //   53: dup
/*    */     //   54: astore #4
/*    */     //   56: aload_0
/*    */     //   57: aload #4
/*    */     //   59: getfield Cx0 : I
/*    */     //   62: anewarray java/lang/Object
/*    */     //   65: astore #5
/*    */     //   67: getfield gp : Lf/f7;
/*    */     //   70: aload_2
/*    */     //   71: aload #5
/*    */     //   73: invokevirtual X00 : (Ljava/lang/Object;Ljava/lang/Object;)Ljava/lang/Object;
/*    */     //   76: pop
/*    */     //   77: iconst_0
/*    */     //   78: istore #6
/*    */     //   80: getfield CO : Lf/fQ;
/*    */     //   83: dup
/*    */     //   84: astore #7
/*    */     //   86: iconst_0
/*    */     //   87: istore #8
/*    */     //   89: getfield Z8 : I
/*    */     //   92: istore #9
/*    */     //   94: iload #8
/*    */     //   96: iload #9
/*    */     //   98: if_icmpge -> 278
/*    */     //   101: aload #5
/*    */     //   103: iload #6
/*    */     //   105: aload #4
/*    */     //   107: aload #7
/*    */     //   109: iload #8
/*    */     //   111: invokevirtual get : (I)Ljava/lang/Object;
/*    */     //   114: invokevirtual pd0 : (Ljava/lang/Object;)Ljava/lang/Object;
/*    */     //   117: checkcast f/CoM2
/*    */     //   120: getfield WW : Lf/CL0;
/*    */     //   123: dup
/*    */     //   124: astore #10
/*    */     //   126: aload_3
/*    */     //   127: iinc #6, 1
/*    */     //   130: invokevirtual Op : (Ljava/lang/Object;)Ljava/lang/Object;
/*    */     //   133: aastore
/*    */     //   134: iinc #8, 1
/*    */     //   137: goto -> 94
/*    */     //   140: astore_0
/*    */     //   141: new f/kN
/*    */     //   144: dup
/*    */     //   145: dup
/*    */     //   146: aload_0
/*    */     //   147: invokespecial <init> : (Ljava/lang/Throwable;)V
/*    */     //   150: new java/lang/StringBuilder
/*    */     //   153: dup
/*    */     //   154: aload #10
/*    */     //   156: swap
/*    */     //   157: invokespecial <init> : ()V
/*    */     //   160: invokevirtual append : (Ljava/lang/Object;)Ljava/lang/StringBuilder;
/*    */     //   163: ldc_w ' ('
/*    */     //   166: invokevirtual append : (Ljava/lang/String;)Ljava/lang/StringBuilder;
/*    */     //   169: aload_2
/*    */     //   170: invokevirtual getName : ()Ljava/lang/String;
/*    */     //   173: invokevirtual append : (Ljava/lang/String;)Ljava/lang/StringBuilder;
/*    */     //   176: ldc_w ')'
/*    */     //   179: invokevirtual append : (Ljava/lang/String;)Ljava/lang/StringBuilder;
/*    */     //   182: invokevirtual toString : ()Ljava/lang/String;
/*    */     //   185: invokevirtual K7 : (Ljava/lang/String;)V
/*    */     //   188: athrow
/*    */     //   189: dup
/*    */     //   190: new java/lang/StringBuilder
/*    */     //   193: dup
/*    */     //   194: aload #10
/*    */     //   196: swap
/*    */     //   197: invokespecial <init> : ()V
/*    */     //   200: invokevirtual append : (Ljava/lang/Object;)Ljava/lang/StringBuilder;
/*    */     //   203: ldc_w ' ('
/*    */     //   206: invokevirtual append : (Ljava/lang/String;)Ljava/lang/StringBuilder;
/*    */     //   209: aload_2
/*    */     //   210: invokevirtual getName : ()Ljava/lang/String;
/*    */     //   213: invokevirtual append : (Ljava/lang/String;)Ljava/lang/StringBuilder;
/*    */     //   216: ldc_w ')'
/*    */     //   219: invokevirtual append : (Ljava/lang/String;)Ljava/lang/StringBuilder;
/*    */     //   222: invokevirtual toString : ()Ljava/lang/String;
/*    */     //   225: invokevirtual K7 : (Ljava/lang/String;)V
/*    */     //   228: athrow
/*    */     //   229: astore_0
/*    */     //   230: new f/kN
/*    */     //   233: dup
/*    */     //   234: ldc_w 'Error accessing field: '
/*    */     //   237: invokestatic df : (Ljava/lang/String;)Ljava/lang/StringBuilder;
/*    */     //   240: aload #10
/*    */     //   242: getfield Lh : Ljava/lang/reflect/Field;
/*    */     //   245: invokevirtual getName : ()Ljava/lang/String;
/*    */     //   248: invokevirtual append : (Ljava/lang/String;)Ljava/lang/StringBuilder;
/*    */     //   251: ldc_w ' ('
/*    */     //   254: invokevirtual append : (Ljava/lang/String;)Ljava/lang/StringBuilder;
/*    */     //   257: aload_2
/*    */     //   258: invokevirtual getName : ()Ljava/lang/String;
/*    */     //   261: invokevirtual append : (Ljava/lang/String;)Ljava/lang/StringBuilder;
/*    */     //   264: ldc_w ')'
/*    */     //   267: invokevirtual append : (Ljava/lang/String;)Ljava/lang/StringBuilder;
/*    */     //   270: invokevirtual toString : ()Ljava/lang/String;
/*    */     //   273: aload_0
/*    */     //   274: invokespecial <init> : (Ljava/lang/String;Ljava/lang/Throwable;)V
/*    */     //   277: athrow
/*    */     //   278: aload #5
/*    */     //   280: astore_3
/*    */     //   281: goto -> 297
/*    */     //   284: pop
/*    */     //   285: aload_0
/*    */     //   286: getfield gp : Lf/f7;
/*    */     //   289: aload_2
/*    */     //   290: aconst_null
/*    */     //   291: invokevirtual X00 : (Ljava/lang/Object;Ljava/lang/Object;)Ljava/lang/Object;
/*    */     //   294: pop
/*    */     //   295: aconst_null
/*    */     //   296: astore_3
/*    */     //   297: aload_0
/*    */     //   298: aload_2
/*    */     //   299: invokevirtual gf0 : (Ljava/lang/Class;)Lf/Nn;
/*    */     //   302: dup
/*    */     //   303: astore #4
/*    */     //   305: iconst_0
/*    */     //   306: istore #5
/*    */     //   308: getfield CO : Lf/fQ;
/*    */     //   311: dup
/*    */     //   312: astore #6
/*    */     //   314: iconst_0
/*    */     //   315: istore #7
/*    */     //   317: getfield Z8 : I
/*    */     //   320: istore #8
/*    */     //   322: iload #7
/*    */     //   324: iload #8
/*    */     //   326: if_icmpge -> 644
/*    */     //   329: aload_3
/*    */     //   330: aload #4
/*    */     //   332: aload #6
/*    */     //   334: iload #7
/*    */     //   336: invokevirtual get : (I)Ljava/lang/Object;
/*    */     //   339: invokevirtual pd0 : (Ljava/lang/Object;)Ljava/lang/Object;
/*    */     //   342: checkcast f/CoM2
/*    */     //   345: dup
/*    */     //   346: astore #9
/*    */     //   348: getfield WW : Lf/CL0;
/*    */     //   351: dup
/*    */     //   352: astore #10
/*    */     //   354: aload_1
/*    */     //   355: invokevirtual Op : (Ljava/lang/Object;)Ljava/lang/Object;
/*    */     //   358: astore #11
/*    */     //   360: ifnull -> 460
/*    */     //   363: aload #11
/*    */     //   365: aload_3
/*    */     //   366: iload #5
/*    */     //   368: dup
/*    */     //   369: iconst_1
/*    */     //   370: iadd
/*    */     //   371: istore #5
/*    */     //   373: aaload
/*    */     //   374: astore #12
/*    */     //   376: ifnonnull -> 387
/*    */     //   379: aload #12
/*    */     //   381: ifnonnull -> 387
/*    */     //   384: goto -> 500
/*    */     //   387: aload #11
/*    */     //   389: ifnull -> 460
/*    */     //   392: aload #12
/*    */     //   394: ifnull -> 460
/*    */     //   397: aload #11
/*    */     //   399: aload #12
/*    */     //   401: invokevirtual equals : (Ljava/lang/Object;)Z
/*    */     //   404: ifeq -> 410
/*    */     //   407: goto -> 500
/*    */     //   410: aload #11
/*    */     //   412: invokevirtual getClass : ()Ljava/lang/Class;
/*    */     //   415: invokevirtual isArray : ()Z
/*    */     //   418: ifeq -> 460
/*    */     //   421: aload #12
/*    */     //   423: invokevirtual getClass : ()Ljava/lang/Class;
/*    */     //   426: invokevirtual isArray : ()Z
/*    */     //   429: ifeq -> 460
/*    */     //   432: aload_0
/*    */     //   433: getfield pU : [Ljava/lang/Object;
/*    */     //   436: dup
/*    */     //   437: aload_0
/*    */     //   438: swap
/*    */     //   439: iconst_0
/*    */     //   440: aload #11
/*    */     //   442: aastore
/*    */     //   443: getfield Jv0 : [Ljava/lang/Object;
/*    */     //   446: dup
/*    */     //   447: iconst_0
/*    */     //   448: aload #12
/*    */     //   450: aastore
/*    */     //   451: invokestatic deepEquals : ([Ljava/lang/Object;[Ljava/lang/Object;)Z
/*    */     //   454: ifeq -> 460
/*    */     //   457: goto -> 500
/*    */     //   460: aload_0
/*    */     //   461: aload #11
/*    */     //   463: aload #9
/*    */     //   465: aload #10
/*    */     //   467: aload_0
/*    */     //   468: getfield q1 : Lf/wR;
/*    */     //   471: aload #10
/*    */     //   473: getfield Lh : Ljava/lang/reflect/Field;
/*    */     //   476: invokevirtual getName : ()Ljava/lang/String;
/*    */     //   479: invokevirtual Lj0 : (Ljava/lang/String;)Lf/wR;
/*    */     //   482: pop
/*    */     //   483: getfield Lh : Ljava/lang/reflect/Field;
/*    */     //   486: invokevirtual getType : ()Ljava/lang/Class;
/*    */     //   489: astore #9
/*    */     //   491: getfield WU : Ljava/lang/Class;
/*    */     //   494: aload #9
/*    */     //   496: swap
/*    */     //   497: invokevirtual d80 : (Ljava/lang/Object;Ljava/lang/Class;Ljava/lang/Class;)V
/*    */     //   500: iinc #7, 1
/*    */     //   503: goto -> 322
/*    */     //   506: astore_0
/*    */     //   507: new f/kN
/*    */     //   510: dup
/*    */     //   511: dup
/*    */     //   512: aload_0
/*    */     //   513: invokespecial <init> : (Ljava/lang/Throwable;)V
/*    */     //   516: new java/lang/StringBuilder
/*    */     //   519: dup
/*    */     //   520: aload #10
/*    */     //   522: swap
/*    */     //   523: invokespecial <init> : ()V
/*    */     //   526: invokevirtual append : (Ljava/lang/Object;)Ljava/lang/StringBuilder;
/*    */     //   529: ldc_w ' ('
/*    */     //   532: invokevirtual append : (Ljava/lang/String;)Ljava/lang/StringBuilder;
/*    */     //   535: aload_2
/*    */     //   536: invokevirtual getName : ()Ljava/lang/String;
/*    */     //   539: invokevirtual append : (Ljava/lang/String;)Ljava/lang/StringBuilder;
/*    */     //   542: ldc_w ')'
/*    */     //   545: invokevirtual append : (Ljava/lang/String;)Ljava/lang/StringBuilder;
/*    */     //   548: invokevirtual toString : ()Ljava/lang/String;
/*    */     //   551: invokevirtual K7 : (Ljava/lang/String;)V
/*    */     //   554: athrow
/*    */     //   555: dup
/*    */     //   556: new java/lang/StringBuilder
/*    */     //   559: dup
/*    */     //   560: aload #10
/*    */     //   562: swap
/*    */     //   563: invokespecial <init> : ()V
/*    */     //   566: invokevirtual append : (Ljava/lang/Object;)Ljava/lang/StringBuilder;
/*    */     //   569: ldc_w ' ('
/*    */     //   572: invokevirtual append : (Ljava/lang/String;)Ljava/lang/StringBuilder;
/*    */     //   575: aload_2
/*    */     //   576: invokevirtual getName : ()Ljava/lang/String;
/*    */     //   579: invokevirtual append : (Ljava/lang/String;)Ljava/lang/StringBuilder;
/*    */     //   582: ldc_w ')'
/*    */     //   585: invokevirtual append : (Ljava/lang/String;)Ljava/lang/StringBuilder;
/*    */     //   588: invokevirtual toString : ()Ljava/lang/String;
/*    */     //   591: invokevirtual K7 : (Ljava/lang/String;)V
/*    */     //   594: athrow
/*    */     //   595: astore_0
/*    */     //   596: new f/kN
/*    */     //   599: dup
/*    */     //   600: ldc_w 'Error accessing field: '
/*    */     //   603: invokestatic df : (Ljava/lang/String;)Ljava/lang/StringBuilder;
/*    */     //   606: aload #10
/*    */     //   608: getfield Lh : Ljava/lang/reflect/Field;
/*    */     //   611: invokevirtual getName : ()Ljava/lang/String;
/*    */     //   614: invokevirtual append : (Ljava/lang/String;)Ljava/lang/StringBuilder;
/*    */     //   617: ldc_w ' ('
/*    */     //   620: invokevirtual append : (Ljava/lang/String;)Ljava/lang/StringBuilder;
/*    */     //   623: aload_2
/*    */     //   624: invokevirtual getName : ()Ljava/lang/String;
/*    */     //   627: invokevirtual append : (Ljava/lang/String;)Ljava/lang/StringBuilder;
/*    */     //   630: ldc_w ')'
/*    */     //   633: invokevirtual append : (Ljava/lang/String;)Ljava/lang/StringBuilder;
/*    */     //   636: invokevirtual toString : ()Ljava/lang/String;
/*    */     //   639: aload_0
/*    */     //   640: invokespecial <init> : (Ljava/lang/String;Ljava/lang/Throwable;)V
/*    */     //   643: athrow
/*    */     //   644: return
/*    */     // Line number table:
/*    */     //   Java source line number -> byte code offset
/*    */     //   #1	-> 6
/*    */     //   #2	-> 80
/*    */     //   #3	-> 89
/*    */     //   #4	-> 234
/*    */     //   #5	-> 242
/*    */     //   #6	-> 245
/*    */     //   #7	-> 248
/*    */     //   #8	-> 299
/*    */     //   #9	-> 308
/*    */     //   #10	-> 317
/*    */     //   #11	-> 473
/*    */     //   #12	-> 479
/*    */     //   #13	-> 483
/*    */     //   #14	-> 491
/*    */     //   #15	-> 600
/*    */     //   #16	-> 608
/*    */     //   #17	-> 611
/*    */     //   #18	-> 614
/*    */     // Exception table:
/*    */     //   from	to	target	type
/*    */     //   43	49	284	java/lang/Exception
/*    */     //   130	134	229	f/BC
/*    */     //   130	134	189	f/kN
/*    */     //   130	134	140	java/lang/RuntimeException
/*    */     //   354	358	595	f/BC
/*    */     //   354	358	555	f/kN
/*    */     //   354	358	506	java/lang/Exception
/*    */     //   373	374	595	f/BC
/*    */     //   373	374	555	f/kN
/*    */     //   373	374	506	java/lang/Exception
/*    */     //   397	404	595	f/BC
/*    */     //   397	404	555	f/kN
/*    */     //   397	404	506	java/lang/Exception
/*    */     //   410	418	595	f/BC
/*    */     //   410	418	555	f/kN
/*    */     //   410	418	506	java/lang/Exception
/*    */     //   421	429	595	f/BC
/*    */     //   421	429	555	f/kN
/*    */     //   421	429	506	java/lang/Exception
/*    */     //   432	436	595	f/BC
/*    */     //   432	436	555	f/kN
/*    */     //   432	436	506	java/lang/Exception
/*    */     //   437	454	595	f/BC
/*    */     //   437	454	555	f/kN
/*    */     //   437	454	506	java/lang/Exception
/*    */     //   460	482	595	f/BC
/*    */     //   460	482	555	f/kN
/*    */     //   460	482	506	java/lang/Exception
/*    */     //   483	489	595	f/BC
/*    */     //   483	489	555	f/kN
/*    */     //   483	489	506	java/lang/Exception
/*    */     //   491	500	595	f/BC
/*    */     //   491	500	555	f/kN
/*    */     //   491	500	506	java/lang/Exception
/*    */   }
/*    */   
/*    */   public final void Vp0(String paramString, Object paramObject, Class paramClass1, Class paramClass2) {
/*    */     try {
/*    */       this.q1.Lj0(paramString);
/*    */       d80(paramObject, paramClass1, paramClass2);
/*    */       return;
/*    */     } catch (IOException iOException) {
/*    */       throw new kN(this);
/*    */     } 
/*    */   }
/*    */   
/*    */   public final void d80(Object paramObject, Class<String> paramClass1, Class paramClass2) {
/*    */     // Byte code:
/*    */     //   0: aload_1
/*    */     //   1: ifnonnull -> 14
/*    */     //   4: aload_0
/*    */     //   5: getfield q1 : Lf/wR;
/*    */     //   8: aconst_null
/*    */     //   9: invokevirtual AQ : (Ljava/lang/Object;)Lf/wR;
/*    */     //   12: pop
/*    */     //   13: return
/*    */     //   14: aload_2
/*    */     //   15: ifnull -> 25
/*    */     //   18: aload_2
/*    */     //   19: invokevirtual isPrimitive : ()Z
/*    */     //   22: ifne -> 2041
/*    */     //   25: aload_2
/*    */     //   26: ldc_w java/lang/String
/*    */     //   29: if_acmpeq -> 2041
/*    */     //   32: aload_2
/*    */     //   33: ldc_w java/lang/Integer
/*    */     //   36: if_acmpeq -> 2041
/*    */     //   39: aload_2
/*    */     //   40: ldc_w java/lang/Boolean
/*    */     //   43: if_acmpeq -> 2041
/*    */     //   46: aload_2
/*    */     //   47: ldc_w java/lang/Float
/*    */     //   50: if_acmpeq -> 2041
/*    */     //   53: aload_2
/*    */     //   54: ldc_w java/lang/Long
/*    */     //   57: if_acmpeq -> 2041
/*    */     //   60: aload_2
/*    */     //   61: ldc_w java/lang/Double
/*    */     //   64: if_acmpeq -> 2041
/*    */     //   67: aload_2
/*    */     //   68: ldc_w java/lang/Short
/*    */     //   71: if_acmpeq -> 2041
/*    */     //   74: aload_2
/*    */     //   75: ldc_w java/lang/Byte
/*    */     //   78: if_acmpeq -> 2041
/*    */     //   81: aload_2
/*    */     //   82: ldc_w java/lang/Character
/*    */     //   85: if_acmpne -> 91
/*    */     //   88: goto -> 2041
/*    */     //   91: aload_1
/*    */     //   92: invokevirtual getClass : ()Ljava/lang/Class;
/*    */     //   95: dup
/*    */     //   96: astore #4
/*    */     //   98: invokevirtual isPrimitive : ()Z
/*    */     //   101: ifne -> 2020
/*    */     //   104: aload #4
/*    */     //   106: ldc_w java/lang/String
/*    */     //   109: if_acmpeq -> 2020
/*    */     //   112: aload #4
/*    */     //   114: ldc_w java/lang/Integer
/*    */     //   117: if_acmpeq -> 2020
/*    */     //   120: aload #4
/*    */     //   122: ldc_w java/lang/Boolean
/*    */     //   125: if_acmpeq -> 2020
/*    */     //   128: aload #4
/*    */     //   130: ldc_w java/lang/Float
/*    */     //   133: if_acmpeq -> 2020
/*    */     //   136: aload #4
/*    */     //   138: ldc_w java/lang/Long
/*    */     //   141: if_acmpeq -> 2020
/*    */     //   144: aload #4
/*    */     //   146: ldc_w java/lang/Double
/*    */     //   149: if_acmpeq -> 2020
/*    */     //   152: aload #4
/*    */     //   154: ldc_w java/lang/Short
/*    */     //   157: if_acmpeq -> 2020
/*    */     //   160: aload #4
/*    */     //   162: ldc_w java/lang/Byte
/*    */     //   165: if_acmpeq -> 2020
/*    */     //   168: aload #4
/*    */     //   170: ldc_w java/lang/Character
/*    */     //   173: if_acmpne -> 179
/*    */     //   176: goto -> 2020
/*    */     //   179: aload_1
/*    */     //   180: instanceof f/dB
/*    */     //   183: ifeq -> 208
/*    */     //   186: aload_0
/*    */     //   187: aload_1
/*    */     //   188: aload_0
/*    */     //   189: aload #4
/*    */     //   191: aload_2
/*    */     //   192: invokevirtual i10 : (Ljava/lang/Class;Ljava/lang/Class;)V
/*    */     //   195: checkcast f/dB
/*    */     //   198: aload_0
/*    */     //   199: invokeinterface write : (Lf/It;)V
/*    */     //   204: invokevirtual cd0 : ()V
/*    */     //   207: return
/*    */     //   208: aload_0
/*    */     //   209: getfield f3 : Lf/f7;
/*    */     //   212: aload #4
/*    */     //   214: invokevirtual pd0 : (Ljava/lang/Object;)Ljava/lang/Object;
/*    */     //   217: checkcast f/TF0
/*    */     //   220: ifnull -> 224
/*    */     //   223: return
/*    */     //   224: aload_1
/*    */     //   225: instanceof f/fQ
/*    */     //   228: ifeq -> 335
/*    */     //   231: aload_2
/*    */     //   232: ifnull -> 290
/*    */     //   235: aload #4
/*    */     //   237: aload_2
/*    */     //   238: if_acmpeq -> 290
/*    */     //   241: aload #4
/*    */     //   243: ldc f/fQ
/*    */     //   245: if_acmpne -> 251
/*    */     //   248: goto -> 290
/*    */     //   251: new f/kN
/*    */     //   254: dup
/*    */     //   255: new java/lang/StringBuilder
/*    */     //   258: dup
/*    */     //   259: invokespecial <init> : ()V
/*    */     //   262: ldc_w 'Serialization of an Array other than the known type is not supported.\\nKnown type: '
/*    */     //   265: invokevirtual append : (Ljava/lang/String;)Ljava/lang/StringBuilder;
/*    */     //   268: aload_2
/*    */     //   269: invokevirtual append : (Ljava/lang/Object;)Ljava/lang/StringBuilder;
/*    */     //   272: ldc_w '\\nActual type: '
/*    */     //   275: invokevirtual append : (Ljava/lang/String;)Ljava/lang/StringBuilder;
/*    */     //   278: aload #4
/*    */     //   280: invokevirtual append : (Ljava/lang/Object;)Ljava/lang/StringBuilder;
/*    */     //   283: invokevirtual toString : ()Ljava/lang/String;
/*    */     //   286: invokespecial <init> : (Ljava/lang/String;)V
/*    */     //   289: athrow
/*    */     //   290: aload_1
/*    */     //   291: aload_0
/*    */     //   292: invokevirtual ty0 : ()V
/*    */     //   295: checkcast f/fQ
/*    */     //   298: dup
/*    */     //   299: astore_1
/*    */     //   300: iconst_0
/*    */     //   301: istore_2
/*    */     //   302: getfield Z8 : I
/*    */     //   305: istore #4
/*    */     //   307: iload_2
/*    */     //   308: iload #4
/*    */     //   310: if_icmpge -> 330
/*    */     //   313: aload_0
/*    */     //   314: aload_1
/*    */     //   315: iload_2
/*    */     //   316: invokevirtual get : (I)Ljava/lang/Object;
/*    */     //   319: aload_3
/*    */     //   320: aconst_null
/*    */     //   321: invokevirtual d80 : (Ljava/lang/Object;Ljava/lang/Class;Ljava/lang/Class;)V
/*    */     //   324: iinc #2, 1
/*    */     //   327: goto -> 307
/*    */     //   330: aload_0
/*    */     //   331: invokevirtual Rw0 : ()V
/*    */     //   334: return
/*    */     //   335: aload_1
/*    */     //   336: instanceof f/mf0
/*    */     //   339: ifeq -> 447
/*    */     //   342: aload_2
/*    */     //   343: ifnull -> 402
/*    */     //   346: aload #4
/*    */     //   348: aload_2
/*    */     //   349: if_acmpeq -> 402
/*    */     //   352: aload #4
/*    */     //   354: ldc_w f/mf0
/*    */     //   357: if_acmpne -> 363
/*    */     //   360: goto -> 402
/*    */     //   363: new f/kN
/*    */     //   366: dup
/*    */     //   367: new java/lang/StringBuilder
/*    */     //   370: dup
/*    */     //   371: invokespecial <init> : ()V
/*    */     //   374: ldc_w 'Serialization of a Queue other than the known type is not supported.\\nKnown type: '
/*    */     //   377: invokevirtual append : (Ljava/lang/String;)Ljava/lang/StringBuilder;
/*    */     //   380: aload_2
/*    */     //   381: invokevirtual append : (Ljava/lang/Object;)Ljava/lang/StringBuilder;
/*    */     //   384: ldc_w '\\nActual type: '
/*    */     //   387: invokevirtual append : (Ljava/lang/String;)Ljava/lang/StringBuilder;
/*    */     //   390: aload #4
/*    */     //   392: invokevirtual append : (Ljava/lang/Object;)Ljava/lang/StringBuilder;
/*    */     //   395: invokevirtual toString : ()Ljava/lang/String;
/*    */     //   398: invokespecial <init> : (Ljava/lang/String;)V
/*    */     //   401: athrow
/*    */     //   402: aload_1
/*    */     //   403: aload_0
/*    */     //   404: invokevirtual ty0 : ()V
/*    */     //   407: checkcast f/mf0
/*    */     //   410: dup
/*    */     //   411: astore_1
/*    */     //   412: iconst_0
/*    */     //   413: istore_2
/*    */     //   414: getfield bK : I
/*    */     //   417: istore #4
/*    */     //   419: iload_2
/*    */     //   420: iload #4
/*    */     //   422: if_icmpge -> 442
/*    */     //   425: aload_0
/*    */     //   426: aload_1
/*    */     //   427: iload_2
/*    */     //   428: invokevirtual get : (I)Ljava/lang/Object;
/*    */     //   431: aload_3
/*    */     //   432: aconst_null
/*    */     //   433: invokevirtual d80 : (Ljava/lang/Object;Ljava/lang/Class;Ljava/lang/Class;)V
/*    */     //   436: iinc #2, 1
/*    */     //   439: goto -> 419
/*    */     //   442: aload_0
/*    */     //   443: invokevirtual Rw0 : ()V
/*    */     //   446: return
/*    */     //   447: aload_1
/*    */     //   448: instanceof java/util/Collection
/*    */     //   451: ifeq -> 580
/*    */     //   454: aload_0
/*    */     //   455: getfield y5 : Ljava/lang/String;
/*    */     //   458: ifnull -> 537
/*    */     //   461: aload #4
/*    */     //   463: ldc java/util/ArrayList
/*    */     //   465: if_acmpeq -> 537
/*    */     //   468: aload_2
/*    */     //   469: ifnull -> 478
/*    */     //   472: aload_2
/*    */     //   473: aload #4
/*    */     //   475: if_acmpeq -> 537
/*    */     //   478: aload_1
/*    */     //   479: aload_0
/*    */     //   480: dup
/*    */     //   481: aload #4
/*    */     //   483: aload_2
/*    */     //   484: invokevirtual i10 : (Ljava/lang/Class;Ljava/lang/Class;)V
/*    */     //   487: ldc_w 'items'
/*    */     //   490: invokevirtual Rg : (Ljava/lang/String;)V
/*    */     //   493: checkcast java/util/Collection
/*    */     //   496: invokeinterface iterator : ()Ljava/util/Iterator;
/*    */     //   501: astore_1
/*    */     //   502: aload_1
/*    */     //   503: invokeinterface hasNext : ()Z
/*    */     //   508: ifeq -> 526
/*    */     //   511: aload_0
/*    */     //   512: aload_1
/*    */     //   513: invokeinterface next : ()Ljava/lang/Object;
/*    */     //   518: aload_3
/*    */     //   519: aconst_null
/*    */     //   520: invokevirtual d80 : (Ljava/lang/Object;Ljava/lang/Class;Ljava/lang/Class;)V
/*    */     //   523: goto -> 502
/*    */     //   526: aload_0
/*    */     //   527: dup
/*    */     //   528: invokevirtual Rw0 : ()V
/*    */     //   531: invokevirtual cd0 : ()V
/*    */     //   534: goto -> 579
/*    */     //   537: aload_1
/*    */     //   538: aload_0
/*    */     //   539: invokevirtual ty0 : ()V
/*    */     //   542: checkcast java/util/Collection
/*    */     //   545: invokeinterface iterator : ()Ljava/util/Iterator;
/*    */     //   550: astore_1
/*    */     //   551: aload_1
/*    */     //   552: invokeinterface hasNext : ()Z
/*    */     //   557: ifeq -> 575
/*    */     //   560: aload_0
/*    */     //   561: aload_1
/*    */     //   562: invokeinterface next : ()Ljava/lang/Object;
/*    */     //   567: aload_3
/*    */     //   568: aconst_null
/*    */     //   569: invokevirtual d80 : (Ljava/lang/Object;Ljava/lang/Class;Ljava/lang/Class;)V
/*    */     //   572: goto -> 551
/*    */     //   575: aload_0
/*    */     //   576: invokevirtual Rw0 : ()V
/*    */     //   579: return
/*    */     //   580: aload #4
/*    */     //   582: invokevirtual isArray : ()Z
/*    */     //   585: ifeq -> 639
/*    */     //   588: aload_3
/*    */     //   589: ifnonnull -> 598
/*    */     //   592: aload #4
/*    */     //   594: invokevirtual getComponentType : ()Ljava/lang/Class;
/*    */     //   597: astore_3
/*    */     //   598: aload_0
/*    */     //   599: aload_1
/*    */     //   600: invokestatic getLength : (Ljava/lang/Object;)I
/*    */     //   603: istore_2
/*    */     //   604: invokevirtual ty0 : ()V
/*    */     //   607: iconst_0
/*    */     //   608: istore #4
/*    */     //   610: iload #4
/*    */     //   612: iload_2
/*    */     //   613: if_icmpge -> 634
/*    */     //   616: aload_0
/*    */     //   617: aload_1
/*    */     //   618: iload #4
/*    */     //   620: invokestatic get : (Ljava/lang/Object;I)Ljava/lang/Object;
/*    */     //   623: aload_3
/*    */     //   624: aconst_null
/*    */     //   625: invokevirtual d80 : (Ljava/lang/Object;Ljava/lang/Class;Ljava/lang/Class;)V
/*    */     //   628: iinc #4, 1
/*    */     //   631: goto -> 610
/*    */     //   634: aload_0
/*    */     //   635: invokevirtual Rw0 : ()V
/*    */     //   638: return
/*    */     //   639: aload_1
/*    */     //   640: instanceof f/f7
/*    */     //   643: ifeq -> 724
/*    */     //   646: aload_2
/*    */     //   647: ifnonnull -> 653
/*    */     //   650: ldc f/f7
/*    */     //   652: astore_2
/*    */     //   653: aload_1
/*    */     //   654: aload_0
/*    */     //   655: aload #4
/*    */     //   657: aload_2
/*    */     //   658: invokevirtual i10 : (Ljava/lang/Class;Ljava/lang/Class;)V
/*    */     //   661: checkcast f/f7
/*    */     //   664: invokevirtual sh : ()Lf/oc;
/*    */     //   667: dup
/*    */     //   668: astore_1
/*    */     //   669: invokevirtual getClass : ()Ljava/lang/Class;
/*    */     //   672: pop
/*    */     //   673: aload_1
/*    */     //   674: invokevirtual hasNext : ()Z
/*    */     //   677: ifeq -> 719
/*    */     //   680: aload_0
/*    */     //   681: aload_1
/*    */     //   682: invokeinterface next : ()Ljava/lang/Object;
/*    */     //   687: checkcast f/yO
/*    */     //   690: dup
/*    */     //   691: astore_2
/*    */     //   692: aload_0
/*    */     //   693: getfield q1 : Lf/wR;
/*    */     //   696: aload_0
/*    */     //   697: aload_2
/*    */     //   698: getfield Lb : Ljava/lang/Object;
/*    */     //   701: invokevirtual P70 : (Ljava/lang/Object;)Ljava/lang/String;
/*    */     //   704: invokevirtual Lj0 : (Ljava/lang/String;)Lf/wR;
/*    */     //   707: pop
/*    */     //   708: getfield mm : Ljava/lang/Object;
/*    */     //   711: aload_3
/*    */     //   712: aconst_null
/*    */     //   713: invokevirtual d80 : (Ljava/lang/Object;Ljava/lang/Class;Ljava/lang/Class;)V
/*    */     //   716: goto -> 673
/*    */     //   719: aload_0
/*    */     //   720: invokevirtual cd0 : ()V
/*    */     //   723: return
/*    */     //   724: aload_1
/*    */     //   725: instanceof f/Nu0
/*    */     //   728: ifeq -> 905
/*    */     //   731: aload_2
/*    */     //   732: ifnonnull -> 739
/*    */     //   735: ldc_w f/Nu0
/*    */     //   738: astore_2
/*    */     //   739: aload_1
/*    */     //   740: aload_0
/*    */     //   741: aload #4
/*    */     //   743: aload_2
/*    */     //   744: invokevirtual i10 : (Ljava/lang/Class;Ljava/lang/Class;)V
/*    */     //   747: checkcast f/Nu0
/*    */     //   750: dup
/*    */     //   751: astore_1
/*    */     //   752: getfield fM0 : Lf/oO;
/*    */     //   755: ifnonnull -> 786
/*    */     //   758: aload_1
/*    */     //   759: dup
/*    */     //   760: new f/oO
/*    */     //   763: dup
/*    */     //   764: astore_2
/*    */     //   765: aload_1
/*    */     //   766: invokespecial <init> : (Lf/Nu0;)V
/*    */     //   769: aload_2
/*    */     //   770: putfield fM0 : Lf/oO;
/*    */     //   773: new f/oO
/*    */     //   776: dup
/*    */     //   777: astore_2
/*    */     //   778: aload_1
/*    */     //   779: invokespecial <init> : (Lf/Nu0;)V
/*    */     //   782: aload_2
/*    */     //   783: putfield QD : Lf/oO;
/*    */     //   786: aload_1
/*    */     //   787: getfield fM0 : Lf/oO;
/*    */     //   790: dup
/*    */     //   791: astore_2
/*    */     //   792: getfield di0 : Z
/*    */     //   795: ifne -> 827
/*    */     //   798: aload_1
/*    */     //   799: dup
/*    */     //   800: aload_2
/*    */     //   801: invokevirtual F2 : ()V
/*    */     //   804: getfield fM0 : Lf/oO;
/*    */     //   807: dup
/*    */     //   808: astore_1
/*    */     //   809: iconst_1
/*    */     //   810: putfield di0 : Z
/*    */     //   813: getfield QD : Lf/oO;
/*    */     //   816: iconst_0
/*    */     //   817: putfield di0 : Z
/*    */     //   820: goto -> 851
/*    */     //   823: astore_0
/*    */     //   824: goto -> 2051
/*    */     //   827: aload_1
/*    */     //   828: dup
/*    */     //   829: dup
/*    */     //   830: getfield QD : Lf/oO;
/*    */     //   833: invokevirtual F2 : ()V
/*    */     //   836: getfield QD : Lf/oO;
/*    */     //   839: dup
/*    */     //   840: astore_1
/*    */     //   841: iconst_1
/*    */     //   842: putfield di0 : Z
/*    */     //   845: getfield fM0 : Lf/oO;
/*    */     //   848: goto -> 816
/*    */     //   851: aload_1
/*    */     //   852: invokevirtual hasNext : ()Z
/*    */     //   855: ifeq -> 900
/*    */     //   858: aload_0
/*    */     //   859: aload_1
/*    */     //   860: invokevirtual next : ()Ljava/lang/Object;
/*    */     //   863: checkcast f/o20
/*    */     //   866: dup
/*    */     //   867: astore_2
/*    */     //   868: aload_0
/*    */     //   869: getfield q1 : Lf/wR;
/*    */     //   872: aload_0
/*    */     //   873: aload_2
/*    */     //   874: getfield SD : Ljava/lang/Object;
/*    */     //   877: invokevirtual P70 : (Ljava/lang/Object;)Ljava/lang/String;
/*    */     //   880: invokevirtual Lj0 : (Ljava/lang/String;)Lf/wR;
/*    */     //   883: pop
/*    */     //   884: getfield jo0 : I
/*    */     //   887: invokestatic valueOf : (I)Ljava/lang/Integer;
/*    */     //   890: ldc_w java/lang/Integer
/*    */     //   893: aconst_null
/*    */     //   894: invokevirtual d80 : (Ljava/lang/Object;Ljava/lang/Class;Ljava/lang/Class;)V
/*    */     //   897: goto -> 851
/*    */     //   900: aload_0
/*    */     //   901: invokevirtual cd0 : ()V
/*    */     //   904: return
/*    */     //   905: aload_1
/*    */     //   906: instanceof f/com9
/*    */     //   909: ifeq -> 1082
/*    */     //   912: aload_2
/*    */     //   913: ifnonnull -> 920
/*    */     //   916: ldc_w f/com9
/*    */     //   919: astore_2
/*    */     //   920: aload_1
/*    */     //   921: aload_0
/*    */     //   922: aload #4
/*    */     //   924: aload_2
/*    */     //   925: invokevirtual i10 : (Ljava/lang/Class;Ljava/lang/Class;)V
/*    */     //   928: checkcast f/com9
/*    */     //   931: dup
/*    */     //   932: astore_1
/*    */     //   933: getfield XY : Lf/av;
/*    */     //   936: ifnonnull -> 967
/*    */     //   939: aload_1
/*    */     //   940: dup
/*    */     //   941: new f/av
/*    */     //   944: dup
/*    */     //   945: astore_2
/*    */     //   946: aload_1
/*    */     //   947: invokespecial <init> : (Lf/com9;)V
/*    */     //   950: aload_2
/*    */     //   951: putfield XY : Lf/av;
/*    */     //   954: new f/av
/*    */     //   957: dup
/*    */     //   958: astore_2
/*    */     //   959: aload_1
/*    */     //   960: invokespecial <init> : (Lf/com9;)V
/*    */     //   963: aload_2
/*    */     //   964: putfield Wl : Lf/av;
/*    */     //   967: aload_1
/*    */     //   968: getfield XY : Lf/av;
/*    */     //   971: dup
/*    */     //   972: astore_2
/*    */     //   973: getfield Nt : Z
/*    */     //   976: ifne -> 1004
/*    */     //   979: aload_1
/*    */     //   980: dup
/*    */     //   981: aload_2
/*    */     //   982: invokevirtual ox0 : ()V
/*    */     //   985: getfield XY : Lf/av;
/*    */     //   988: dup
/*    */     //   989: astore_1
/*    */     //   990: iconst_1
/*    */     //   991: putfield Nt : Z
/*    */     //   994: getfield Wl : Lf/av;
/*    */     //   997: iconst_0
/*    */     //   998: putfield Nt : Z
/*    */     //   1001: goto -> 1028
/*    */     //   1004: aload_1
/*    */     //   1005: dup
/*    */     //   1006: dup
/*    */     //   1007: getfield Wl : Lf/av;
/*    */     //   1010: invokevirtual ox0 : ()V
/*    */     //   1013: getfield Wl : Lf/av;
/*    */     //   1016: dup
/*    */     //   1017: astore_1
/*    */     //   1018: iconst_1
/*    */     //   1019: putfield Nt : Z
/*    */     //   1022: getfield XY : Lf/av;
/*    */     //   1025: goto -> 997
/*    */     //   1028: aload_1
/*    */     //   1029: invokevirtual hasNext : ()Z
/*    */     //   1032: ifeq -> 1077
/*    */     //   1035: aload_0
/*    */     //   1036: aload_1
/*    */     //   1037: invokevirtual next : ()Ljava/lang/Object;
/*    */     //   1040: checkcast f/RY
/*    */     //   1043: dup
/*    */     //   1044: astore_2
/*    */     //   1045: aload_0
/*    */     //   1046: getfield q1 : Lf/wR;
/*    */     //   1049: aload_0
/*    */     //   1050: aload_2
/*    */     //   1051: getfield Fw0 : Ljava/lang/Object;
/*    */     //   1054: invokevirtual P70 : (Ljava/lang/Object;)Ljava/lang/String;
/*    */     //   1057: invokevirtual Lj0 : (Ljava/lang/String;)Lf/wR;
/*    */     //   1060: pop
/*    */     //   1061: getfield oE0 : F
/*    */     //   1064: invokestatic valueOf : (F)Ljava/lang/Float;
/*    */     //   1067: ldc_w java/lang/Float
/*    */     //   1070: aconst_null
/*    */     //   1071: invokevirtual d80 : (Ljava/lang/Object;Ljava/lang/Class;Ljava/lang/Class;)V
/*    */     //   1074: goto -> 1028
/*    */     //   1077: aload_0
/*    */     //   1078: invokevirtual cd0 : ()V
/*    */     //   1081: return
/*    */     //   1082: aload_1
/*    */     //   1083: instanceof f/MG
/*    */     //   1086: ifeq -> 1156
/*    */     //   1089: aload_2
/*    */     //   1090: ifnonnull -> 1097
/*    */     //   1093: ldc_w f/MG
/*    */     //   1096: astore_2
/*    */     //   1097: aload_1
/*    */     //   1098: aload_0
/*    */     //   1099: dup
/*    */     //   1100: dup
/*    */     //   1101: aload #4
/*    */     //   1103: aload_2
/*    */     //   1104: invokevirtual i10 : (Ljava/lang/Class;Ljava/lang/Class;)V
/*    */     //   1107: getfield q1 : Lf/wR;
/*    */     //   1110: ldc_w 'values'
/*    */     //   1113: invokevirtual Lj0 : (Ljava/lang/String;)Lf/wR;
/*    */     //   1116: pop
/*    */     //   1117: invokevirtual ty0 : ()V
/*    */     //   1120: checkcast f/MG
/*    */     //   1123: invokevirtual jF0 : ()Lf/To;
/*    */     //   1126: astore_1
/*    */     //   1127: aload_1
/*    */     //   1128: invokevirtual hasNext : ()Z
/*    */     //   1131: ifeq -> 1147
/*    */     //   1134: aload_0
/*    */     //   1135: aload_1
/*    */     //   1136: invokevirtual next : ()Ljava/lang/Object;
/*    */     //   1139: aload_3
/*    */     //   1140: aconst_null
/*    */     //   1141: invokevirtual d80 : (Ljava/lang/Object;Ljava/lang/Class;Ljava/lang/Class;)V
/*    */     //   1144: goto -> 1127
/*    */     //   1147: aload_0
/*    */     //   1148: dup
/*    */     //   1149: invokevirtual Rw0 : ()V
/*    */     //   1152: invokevirtual cd0 : ()V
/*    */     //   1155: return
/*    */     //   1156: aload_1
/*    */     //   1157: instanceof f/y10
/*    */     //   1160: ifeq -> 1326
/*    */     //   1163: aload_2
/*    */     //   1164: ifnonnull -> 1171
/*    */     //   1167: ldc_w f/y10
/*    */     //   1170: astore_2
/*    */     //   1171: aload_1
/*    */     //   1172: aload_0
/*    */     //   1173: aload #4
/*    */     //   1175: aload_2
/*    */     //   1176: invokevirtual i10 : (Ljava/lang/Class;Ljava/lang/Class;)V
/*    */     //   1179: checkcast f/y10
/*    */     //   1182: dup
/*    */     //   1183: astore_1
/*    */     //   1184: getfield M00 : Lf/Gt;
/*    */     //   1187: ifnonnull -> 1218
/*    */     //   1190: aload_1
/*    */     //   1191: dup
/*    */     //   1192: new f/Gt
/*    */     //   1195: dup
/*    */     //   1196: astore_2
/*    */     //   1197: aload_1
/*    */     //   1198: invokespecial <init> : (Lf/y10;)V
/*    */     //   1201: aload_2
/*    */     //   1202: putfield M00 : Lf/Gt;
/*    */     //   1205: new f/Gt
/*    */     //   1208: dup
/*    */     //   1209: astore_2
/*    */     //   1210: aload_1
/*    */     //   1211: invokespecial <init> : (Lf/y10;)V
/*    */     //   1214: aload_2
/*    */     //   1215: putfield x8 : Lf/Gt;
/*    */     //   1218: aload_1
/*    */     //   1219: getfield M00 : Lf/Gt;
/*    */     //   1222: dup
/*    */     //   1223: astore_2
/*    */     //   1224: getfield Jc : Z
/*    */     //   1227: ifne -> 1255
/*    */     //   1230: aload_1
/*    */     //   1231: dup
/*    */     //   1232: aload_2
/*    */     //   1233: invokevirtual GS : ()V
/*    */     //   1236: getfield M00 : Lf/Gt;
/*    */     //   1239: dup
/*    */     //   1240: astore_1
/*    */     //   1241: iconst_1
/*    */     //   1242: putfield Jc : Z
/*    */     //   1245: getfield x8 : Lf/Gt;
/*    */     //   1248: iconst_0
/*    */     //   1249: putfield Jc : Z
/*    */     //   1252: goto -> 1279
/*    */     //   1255: aload_1
/*    */     //   1256: dup
/*    */     //   1257: dup
/*    */     //   1258: getfield x8 : Lf/Gt;
/*    */     //   1261: invokevirtual GS : ()V
/*    */     //   1264: getfield x8 : Lf/Gt;
/*    */     //   1267: dup
/*    */     //   1268: astore_1
/*    */     //   1269: iconst_1
/*    */     //   1270: putfield Jc : Z
/*    */     //   1273: getfield M00 : Lf/Gt;
/*    */     //   1276: goto -> 1248
/*    */     //   1279: aload_1
/*    */     //   1280: invokevirtual hasNext : ()Z
/*    */     //   1283: ifeq -> 1321
/*    */     //   1286: aload_0
/*    */     //   1287: aload_1
/*    */     //   1288: invokevirtual next : ()Ljava/lang/Object;
/*    */     //   1291: checkcast f/cOm8
/*    */     //   1294: dup
/*    */     //   1295: aload_0
/*    */     //   1296: getfield q1 : Lf/wR;
/*    */     //   1299: swap
/*    */     //   1300: getfield COm2 : I
/*    */     //   1303: invokestatic valueOf : (I)Ljava/lang/String;
/*    */     //   1306: invokevirtual Lj0 : (Ljava/lang/String;)Lf/wR;
/*    */     //   1309: pop
/*    */     //   1310: getfield bH : Ljava/lang/Object;
/*    */     //   1313: aload_3
/*    */     //   1314: aconst_null
/*    */     //   1315: invokevirtual d80 : (Ljava/lang/Object;Ljava/lang/Class;Ljava/lang/Class;)V
/*    */     //   1318: goto -> 1279
/*    */     //   1321: aload_0
/*    */     //   1322: invokevirtual cd0 : ()V
/*    */     //   1325: return
/*    */     //   1326: aload_1
/*    */     //   1327: instanceof f/LF0
/*    */     //   1330: ifeq -> 1496
/*    */     //   1333: aload_2
/*    */     //   1334: ifnonnull -> 1341
/*    */     //   1337: ldc_w f/LF0
/*    */     //   1340: astore_2
/*    */     //   1341: aload_1
/*    */     //   1342: aload_0
/*    */     //   1343: aload #4
/*    */     //   1345: aload_2
/*    */     //   1346: invokevirtual i10 : (Ljava/lang/Class;Ljava/lang/Class;)V
/*    */     //   1349: checkcast f/LF0
/*    */     //   1352: dup
/*    */     //   1353: astore_1
/*    */     //   1354: getfield Up : Lf/lM;
/*    */     //   1357: ifnonnull -> 1388
/*    */     //   1360: aload_1
/*    */     //   1361: dup
/*    */     //   1362: new f/lM
/*    */     //   1365: dup
/*    */     //   1366: astore_2
/*    */     //   1367: aload_1
/*    */     //   1368: invokespecial <init> : (Lf/LF0;)V
/*    */     //   1371: aload_2
/*    */     //   1372: putfield Up : Lf/lM;
/*    */     //   1375: new f/lM
/*    */     //   1378: dup
/*    */     //   1379: astore_2
/*    */     //   1380: aload_1
/*    */     //   1381: invokespecial <init> : (Lf/LF0;)V
/*    */     //   1384: aload_2
/*    */     //   1385: putfield uH : Lf/lM;
/*    */     //   1388: aload_1
/*    */     //   1389: getfield Up : Lf/lM;
/*    */     //   1392: dup
/*    */     //   1393: astore_2
/*    */     //   1394: getfield SJ : Z
/*    */     //   1397: ifne -> 1425
/*    */     //   1400: aload_1
/*    */     //   1401: dup
/*    */     //   1402: aload_2
/*    */     //   1403: invokevirtual We0 : ()V
/*    */     //   1406: getfield Up : Lf/lM;
/*    */     //   1409: dup
/*    */     //   1410: astore_1
/*    */     //   1411: iconst_1
/*    */     //   1412: putfield SJ : Z
/*    */     //   1415: getfield uH : Lf/lM;
/*    */     //   1418: iconst_0
/*    */     //   1419: putfield SJ : Z
/*    */     //   1422: goto -> 1449
/*    */     //   1425: aload_1
/*    */     //   1426: dup
/*    */     //   1427: dup
/*    */     //   1428: getfield uH : Lf/lM;
/*    */     //   1431: invokevirtual We0 : ()V
/*    */     //   1434: getfield uH : Lf/lM;
/*    */     //   1437: dup
/*    */     //   1438: astore_1
/*    */     //   1439: iconst_1
/*    */     //   1440: putfield SJ : Z
/*    */     //   1443: getfield Up : Lf/lM;
/*    */     //   1446: goto -> 1418
/*    */     //   1449: aload_1
/*    */     //   1450: invokevirtual hasNext : ()Z
/*    */     //   1453: ifeq -> 1491
/*    */     //   1456: aload_0
/*    */     //   1457: aload_1
/*    */     //   1458: invokevirtual next : ()Ljava/lang/Object;
/*    */     //   1461: checkcast f/dq0
/*    */     //   1464: dup
/*    */     //   1465: aload_0
/*    */     //   1466: getfield q1 : Lf/wR;
/*    */     //   1469: swap
/*    */     //   1470: getfield o10 : J
/*    */     //   1473: invokestatic valueOf : (J)Ljava/lang/String;
/*    */     //   1476: invokevirtual Lj0 : (Ljava/lang/String;)Lf/wR;
/*    */     //   1479: pop
/*    */     //   1480: getfield Pn : Ljava/lang/Object;
/*    */     //   1483: aload_3
/*    */     //   1484: aconst_null
/*    */     //   1485: invokevirtual d80 : (Ljava/lang/Object;Ljava/lang/Class;Ljava/lang/Class;)V
/*    */     //   1488: goto -> 1449
/*    */     //   1491: aload_0
/*    */     //   1492: invokevirtual cd0 : ()V
/*    */     //   1495: return
/*    */     //   1496: aload_1
/*    */     //   1497: instanceof f/S4
/*    */     //   1500: ifeq -> 1683
/*    */     //   1503: aload_2
/*    */     //   1504: ifnonnull -> 1511
/*    */     //   1507: ldc_w f/S4
/*    */     //   1510: astore_2
/*    */     //   1511: aload_1
/*    */     //   1512: aload_0
/*    */     //   1513: dup
/*    */     //   1514: dup
/*    */     //   1515: aload #4
/*    */     //   1517: aload_2
/*    */     //   1518: invokevirtual i10 : (Ljava/lang/Class;Ljava/lang/Class;)V
/*    */     //   1521: getfield q1 : Lf/wR;
/*    */     //   1524: ldc_w 'values'
/*    */     //   1527: invokevirtual Lj0 : (Ljava/lang/String;)Lf/wR;
/*    */     //   1530: pop
/*    */     //   1531: invokevirtual ty0 : ()V
/*    */     //   1534: checkcast f/S4
/*    */     //   1537: invokevirtual Jg0 : ()Lf/f70;
/*    */     //   1540: astore_1
/*    */     //   1541: aload_1
/*    */     //   1542: getfield coM5 : Z
/*    */     //   1545: dup
/*    */     //   1546: istore_2
/*    */     //   1547: ifeq -> 1674
/*    */     //   1550: iload_2
/*    */     //   1551: ifeq -> 1666
/*    */     //   1554: aload_1
/*    */     //   1555: getfield jK : Z
/*    */     //   1558: ifeq -> 1655
/*    */     //   1561: aload_1
/*    */     //   1562: getfield Mz : I
/*    */     //   1565: dup
/*    */     //   1566: istore_2
/*    */     //   1567: iconst_m1
/*    */     //   1568: if_icmpne -> 1576
/*    */     //   1571: iconst_0
/*    */     //   1572: istore_2
/*    */     //   1573: goto -> 1586
/*    */     //   1576: aload_1
/*    */     //   1577: getfield mr : Lf/S4;
/*    */     //   1580: getfield k4 : [I
/*    */     //   1583: iload_2
/*    */     //   1584: iaload
/*    */     //   1585: istore_2
/*    */     //   1586: aload_1
/*    */     //   1587: getfield mr : Lf/S4;
/*    */     //   1590: getfield k4 : [I
/*    */     //   1593: dup
/*    */     //   1594: astore_3
/*    */     //   1595: arraylength
/*    */     //   1596: istore #4
/*    */     //   1598: aload_1
/*    */     //   1599: getfield Mz : I
/*    */     //   1602: iconst_1
/*    */     //   1603: iadd
/*    */     //   1604: dup
/*    */     //   1605: istore #5
/*    */     //   1607: iload #4
/*    */     //   1609: aload_1
/*    */     //   1610: iload #5
/*    */     //   1612: putfield Mz : I
/*    */     //   1615: if_icmpge -> 1633
/*    */     //   1618: aload_3
/*    */     //   1619: iload #5
/*    */     //   1621: iaload
/*    */     //   1622: ifeq -> 1598
/*    */     //   1625: aload_1
/*    */     //   1626: iconst_1
/*    */     //   1627: putfield coM5 : Z
/*    */     //   1630: goto -> 1638
/*    */     //   1633: aload_1
/*    */     //   1634: iconst_0
/*    */     //   1635: putfield coM5 : Z
/*    */     //   1638: aload_0
/*    */     //   1639: iload_2
/*    */     //   1640: invokestatic valueOf : (I)Ljava/lang/Integer;
/*    */     //   1643: ldc_w java/lang/Integer
/*    */     //   1646: swap
/*    */     //   1647: swap
/*    */     //   1648: aconst_null
/*    */     //   1649: invokevirtual d80 : (Ljava/lang/Object;Ljava/lang/Class;Ljava/lang/Class;)V
/*    */     //   1652: goto -> 1541
/*    */     //   1655: new f/JU
/*    */     //   1658: dup
/*    */     //   1659: ldc_w '#iterator() cannot be used nested.'
/*    */     //   1662: invokespecial <init> : (Ljava/lang/String;)V
/*    */     //   1665: athrow
/*    */     //   1666: new java/util/NoSuchElementException
/*    */     //   1669: dup
/*    */     //   1670: invokespecial <init> : ()V
/*    */     //   1673: athrow
/*    */     //   1674: aload_0
/*    */     //   1675: dup
/*    */     //   1676: invokevirtual Rw0 : ()V
/*    */     //   1679: invokevirtual cd0 : ()V
/*    */     //   1682: return
/*    */     //   1683: aload_1
/*    */     //   1684: instanceof f/eM
/*    */     //   1687: ifeq -> 1765
/*    */     //   1690: aload_2
/*    */     //   1691: ifnonnull -> 1698
/*    */     //   1694: ldc_w f/eM
/*    */     //   1697: astore_2
/*    */     //   1698: aload_1
/*    */     //   1699: aload_0
/*    */     //   1700: aload #4
/*    */     //   1702: aload_2
/*    */     //   1703: invokevirtual i10 : (Ljava/lang/Class;Ljava/lang/Class;)V
/*    */     //   1706: checkcast f/eM
/*    */     //   1709: dup
/*    */     //   1710: astore_1
/*    */     //   1711: iconst_0
/*    */     //   1712: istore_2
/*    */     //   1713: getfield uJ0 : I
/*    */     //   1716: istore #4
/*    */     //   1718: iload_2
/*    */     //   1719: iload #4
/*    */     //   1721: if_icmpge -> 1760
/*    */     //   1724: aload_0
/*    */     //   1725: aload_1
/*    */     //   1726: aload_0
/*    */     //   1727: getfield q1 : Lf/wR;
/*    */     //   1730: aload_0
/*    */     //   1731: aload_1
/*    */     //   1732: getfield Jo : [Ljava/lang/Object;
/*    */     //   1735: iload_2
/*    */     //   1736: aaload
/*    */     //   1737: invokevirtual P70 : (Ljava/lang/Object;)Ljava/lang/String;
/*    */     //   1740: invokevirtual Lj0 : (Ljava/lang/String;)Lf/wR;
/*    */     //   1743: pop
/*    */     //   1744: getfield WD0 : [Ljava/lang/Object;
/*    */     //   1747: iload_2
/*    */     //   1748: aaload
/*    */     //   1749: aload_3
/*    */     //   1750: aconst_null
/*    */     //   1751: invokevirtual d80 : (Ljava/lang/Object;Ljava/lang/Class;Ljava/lang/Class;)V
/*    */     //   1754: iinc #2, 1
/*    */     //   1757: goto -> 1718
/*    */     //   1760: aload_0
/*    */     //   1761: invokevirtual cd0 : ()V
/*    */     //   1764: return
/*    */     //   1765: aload_1
/*    */     //   1766: instanceof java/util/Map
/*    */     //   1769: ifeq -> 1859
/*    */     //   1772: aload_2
/*    */     //   1773: ifnonnull -> 1780
/*    */     //   1776: ldc_w java/util/HashMap
/*    */     //   1779: astore_2
/*    */     //   1780: aload_1
/*    */     //   1781: aload_0
/*    */     //   1782: aload #4
/*    */     //   1784: aload_2
/*    */     //   1785: invokevirtual i10 : (Ljava/lang/Class;Ljava/lang/Class;)V
/*    */     //   1788: checkcast java/util/Map
/*    */     //   1791: invokeinterface entrySet : ()Ljava/util/Set;
/*    */     //   1796: invokeinterface iterator : ()Ljava/util/Iterator;
/*    */     //   1801: astore_1
/*    */     //   1802: aload_1
/*    */     //   1803: invokeinterface hasNext : ()Z
/*    */     //   1808: ifeq -> 1854
/*    */     //   1811: aload_0
/*    */     //   1812: aload_1
/*    */     //   1813: invokeinterface next : ()Ljava/lang/Object;
/*    */     //   1818: checkcast java/util/Map$Entry
/*    */     //   1821: dup
/*    */     //   1822: astore_2
/*    */     //   1823: aload_0
/*    */     //   1824: getfield q1 : Lf/wR;
/*    */     //   1827: aload_0
/*    */     //   1828: aload_2
/*    */     //   1829: invokeinterface getKey : ()Ljava/lang/Object;
/*    */     //   1834: invokevirtual P70 : (Ljava/lang/Object;)Ljava/lang/String;
/*    */     //   1837: invokevirtual Lj0 : (Ljava/lang/String;)Lf/wR;
/*    */     //   1840: pop
/*    */     //   1841: invokeinterface getValue : ()Ljava/lang/Object;
/*    */     //   1846: aload_3
/*    */     //   1847: aconst_null
/*    */     //   1848: invokevirtual d80 : (Ljava/lang/Object;Ljava/lang/Class;Ljava/lang/Class;)V
/*    */     //   1851: goto -> 1802
/*    */     //   1854: aload_0
/*    */     //   1855: invokevirtual cd0 : ()V
/*    */     //   1858: return
/*    */     //   1859: ldc java/lang/Enum
/*    */     //   1861: aload #4
/*    */     //   1863: invokevirtual isAssignableFrom : (Ljava/lang/Class;)Z
/*    */     //   1866: ifeq -> 2003
/*    */     //   1869: aload #4
/*    */     //   1871: invokevirtual getEnumConstants : ()[Ljava/lang/Object;
/*    */     //   1874: ifnonnull -> 1884
/*    */     //   1877: aload #4
/*    */     //   1879: invokevirtual getSuperclass : ()Ljava/lang/Class;
/*    */     //   1882: astore #4
/*    */     //   1884: aload_0
/*    */     //   1885: getfield y5 : Ljava/lang/String;
/*    */     //   1888: ifnull -> 1964
/*    */     //   1891: aload_2
/*    */     //   1892: ifnull -> 1901
/*    */     //   1895: aload_2
/*    */     //   1896: aload #4
/*    */     //   1898: if_acmpeq -> 1964
/*    */     //   1901: aload_0
/*    */     //   1902: aload_1
/*    */     //   1903: aload_0
/*    */     //   1904: dup
/*    */     //   1905: dup
/*    */     //   1906: aload #4
/*    */     //   1908: aconst_null
/*    */     //   1909: invokevirtual i10 : (Ljava/lang/Class;Ljava/lang/Class;)V
/*    */     //   1912: getfield q1 : Lf/wR;
/*    */     //   1915: ldc_w 'value'
/*    */     //   1918: invokevirtual Lj0 : (Ljava/lang/String;)Lf/wR;
/*    */     //   1921: pop
/*    */     //   1922: getfield q1 : Lf/wR;
/*    */     //   1925: astore_1
/*    */     //   1926: checkcast java/lang/Enum
/*    */     //   1929: astore_2
/*    */     //   1930: getfield Xj : Z
/*    */     //   1933: ifeq -> 1944
/*    */     //   1936: aload_2
/*    */     //   1937: invokevirtual name : ()Ljava/lang/String;
/*    */     //   1940: astore_2
/*    */     //   1941: goto -> 1951
/*    */     //   1944: aload_2
/*    */     //   1945: invokevirtual toString : ()Ljava/lang/String;
/*    */     //   1948: goto -> 1940
/*    */     //   1951: aload_0
/*    */     //   1952: aload_1
/*    */     //   1953: aload_2
/*    */     //   1954: invokevirtual AQ : (Ljava/lang/Object;)Lf/wR;
/*    */     //   1957: pop
/*    */     //   1958: invokevirtual cd0 : ()V
/*    */     //   1961: goto -> 2002
/*    */     //   1964: aload_0
/*    */     //   1965: aload_1
/*    */     //   1966: aload_0
/*    */     //   1967: getfield q1 : Lf/wR;
/*    */     //   1970: astore_0
/*    */     //   1971: checkcast java/lang/Enum
/*    */     //   1974: astore_1
/*    */     //   1975: getfield Xj : Z
/*    */     //   1978: ifeq -> 1989
/*    */     //   1981: aload_1
/*    */     //   1982: invokevirtual name : ()Ljava/lang/String;
/*    */     //   1985: astore_1
/*    */     //   1986: goto -> 1996
/*    */     //   1989: aload_1
/*    */     //   1990: invokevirtual toString : ()Ljava/lang/String;
/*    */     //   1993: goto -> 1985
/*    */     //   1996: aload_0
/*    */     //   1997: aload_1
/*    */     //   1998: invokevirtual AQ : (Ljava/lang/Object;)Lf/wR;
/*    */     //   2001: pop
/*    */     //   2002: return
/*    */     //   2003: aload_0
/*    */     //   2004: dup
/*    */     //   2005: dup
/*    */     //   2006: aload #4
/*    */     //   2008: aload_2
/*    */     //   2009: invokevirtual i10 : (Ljava/lang/Class;Ljava/lang/Class;)V
/*    */     //   2012: aload_1
/*    */     //   2013: invokevirtual K9 : (Ljava/lang/Object;)V
/*    */     //   2016: invokevirtual cd0 : ()V
/*    */     //   2019: return
/*    */     //   2020: aload_0
/*    */     //   2021: dup
/*    */     //   2022: dup
/*    */     //   2023: aload #4
/*    */     //   2025: aconst_null
/*    */     //   2026: invokevirtual i10 : (Ljava/lang/Class;Ljava/lang/Class;)V
/*    */     //   2029: ldc_w 'value'
/*    */     //   2032: aload_1
/*    */     //   2033: swap
/*    */     //   2034: invokevirtual Jv0 : (Ljava/lang/Object;Ljava/lang/String;)V
/*    */     //   2037: invokevirtual cd0 : ()V
/*    */     //   2040: return
/*    */     //   2041: aload_0
/*    */     //   2042: getfield q1 : Lf/wR;
/*    */     //   2045: aload_1
/*    */     //   2046: invokevirtual AQ : (Ljava/lang/Object;)Lf/wR;
/*    */     //   2049: pop
/*    */     //   2050: return
/*    */     //   2051: new f/kN
/*    */     //   2054: dup
/*    */     //   2055: aload_0
/*    */     //   2056: invokespecial <init> : (Ljava/lang/Throwable;)V
/*    */     //   2059: athrow
/*    */     // Line number table:
/*    */     //   Java source line number -> byte code offset
/*    */     //   #1	-> 600
/*    */     //   #2	-> 604
/*    */     //   #3	-> 620
/*    */     //   #4	-> 625
/*    */     //   #5	-> 752
/*    */     //   #6	-> 852
/*    */     //   #7	-> 894
/*    */     //   #8	-> 901
/*    */     //   #9	-> 933
/*    */     //   #10	-> 1029
/*    */     //   #11	-> 1071
/*    */     //   #12	-> 1078
/*    */     //   #13	-> 1184
/*    */     //   #14	-> 1280
/*    */     //   #15	-> 1354
/*    */     //   #16	-> 1450
/*    */     //   #17	-> 1555
/*    */     //   #18	-> 1587
/*    */     //   #19	-> 1640
/*    */     //   #20	-> 1655
/*    */     //   #21	-> 1676
/*    */     //   #22	-> 1863
/*    */     //   #23	-> 1871
/*    */     //   #24	-> 1930
/*    */     //   #25	-> 1954
/*    */     //   #26	-> 1975
/*    */     //   #27	-> 1998
/*    */     // Exception table:
/*    */     //   from	to	target	type
/*    */     //   4	12	823	java/io/IOException
/*    */     //   18	22	823	java/io/IOException
/*    */     //   25	29	823	java/io/IOException
/*    */     //   32	36	823	java/io/IOException
/*    */     //   39	43	823	java/io/IOException
/*    */     //   46	50	823	java/io/IOException
/*    */     //   53	57	823	java/io/IOException
/*    */     //   60	64	823	java/io/IOException
/*    */     //   67	71	823	java/io/IOException
/*    */     //   74	78	823	java/io/IOException
/*    */     //   81	85	823	java/io/IOException
/*    */     //   91	95	823	java/io/IOException
/*    */     //   98	101	823	java/io/IOException
/*    */     //   104	109	823	java/io/IOException
/*    */     //   112	117	823	java/io/IOException
/*    */     //   120	125	823	java/io/IOException
/*    */     //   128	133	823	java/io/IOException
/*    */     //   136	141	823	java/io/IOException
/*    */     //   144	149	823	java/io/IOException
/*    */     //   152	157	823	java/io/IOException
/*    */     //   160	165	823	java/io/IOException
/*    */     //   168	173	823	java/io/IOException
/*    */     //   179	183	823	java/io/IOException
/*    */     //   186	207	823	java/io/IOException
/*    */     //   208	220	823	java/io/IOException
/*    */     //   224	228	823	java/io/IOException
/*    */     //   241	245	823	java/io/IOException
/*    */     //   251	298	823	java/io/IOException
/*    */     //   302	305	823	java/io/IOException
/*    */     //   313	324	823	java/io/IOException
/*    */     //   330	334	823	java/io/IOException
/*    */     //   335	339	823	java/io/IOException
/*    */     //   352	357	823	java/io/IOException
/*    */     //   363	410	823	java/io/IOException
/*    */     //   414	417	823	java/io/IOException
/*    */     //   425	436	823	java/io/IOException
/*    */     //   442	446	823	java/io/IOException
/*    */     //   447	451	823	java/io/IOException
/*    */     //   454	458	823	java/io/IOException
/*    */     //   461	465	823	java/io/IOException
/*    */     //   478	501	823	java/io/IOException
/*    */     //   502	508	823	java/io/IOException
/*    */     //   511	550	823	java/io/IOException
/*    */     //   551	557	823	java/io/IOException
/*    */     //   560	579	823	java/io/IOException
/*    */     //   580	585	823	java/io/IOException
/*    */     //   592	597	823	java/io/IOException
/*    */     //   598	603	823	java/io/IOException
/*    */     //   604	607	823	java/io/IOException
/*    */     //   616	628	823	java/io/IOException
/*    */     //   634	638	823	java/io/IOException
/*    */     //   639	643	823	java/io/IOException
/*    */     //   650	652	823	java/io/IOException
/*    */     //   653	667	823	java/io/IOException
/*    */     //   669	672	823	java/io/IOException
/*    */     //   673	677	823	java/io/IOException
/*    */     //   680	690	823	java/io/IOException
/*    */     //   692	707	823	java/io/IOException
/*    */     //   708	723	823	java/io/IOException
/*    */     //   724	728	823	java/io/IOException
/*    */     //   735	738	823	java/io/IOException
/*    */     //   739	750	823	java/io/IOException
/*    */     //   752	755	823	java/io/IOException
/*    */     //   758	763	823	java/io/IOException
/*    */     //   765	776	823	java/io/IOException
/*    */     //   778	790	823	java/io/IOException
/*    */     //   792	795	823	java/io/IOException
/*    */     //   798	807	823	java/io/IOException
/*    */     //   809	823	823	java/io/IOException
/*    */     //   827	839	823	java/io/IOException
/*    */     //   841	855	823	java/io/IOException
/*    */     //   858	866	823	java/io/IOException
/*    */     //   868	883	823	java/io/IOException
/*    */     //   884	904	823	java/io/IOException
/*    */     //   905	909	823	java/io/IOException
/*    */     //   916	919	823	java/io/IOException
/*    */     //   920	931	823	java/io/IOException
/*    */     //   933	936	823	java/io/IOException
/*    */     //   939	944	823	java/io/IOException
/*    */     //   946	957	823	java/io/IOException
/*    */     //   959	971	823	java/io/IOException
/*    */     //   973	976	823	java/io/IOException
/*    */     //   979	988	823	java/io/IOException
/*    */     //   990	1016	823	java/io/IOException
/*    */     //   1018	1032	823	java/io/IOException
/*    */     //   1035	1043	823	java/io/IOException
/*    */     //   1045	1060	823	java/io/IOException
/*    */     //   1061	1081	823	java/io/IOException
/*    */     //   1082	1086	823	java/io/IOException
/*    */     //   1093	1096	823	java/io/IOException
/*    */     //   1097	1116	823	java/io/IOException
/*    */     //   1117	1126	823	java/io/IOException
/*    */     //   1127	1131	823	java/io/IOException
/*    */     //   1134	1155	823	java/io/IOException
/*    */     //   1156	1160	823	java/io/IOException
/*    */     //   1167	1170	823	java/io/IOException
/*    */     //   1171	1182	823	java/io/IOException
/*    */     //   1184	1187	823	java/io/IOException
/*    */     //   1190	1195	823	java/io/IOException
/*    */     //   1197	1208	823	java/io/IOException
/*    */     //   1210	1222	823	java/io/IOException
/*    */     //   1224	1227	823	java/io/IOException
/*    */     //   1230	1239	823	java/io/IOException
/*    */     //   1241	1267	823	java/io/IOException
/*    */     //   1269	1283	823	java/io/IOException
/*    */     //   1286	1294	823	java/io/IOException
/*    */     //   1295	1309	823	java/io/IOException
/*    */     //   1310	1325	823	java/io/IOException
/*    */     //   1326	1330	823	java/io/IOException
/*    */     //   1337	1340	823	java/io/IOException
/*    */     //   1341	1352	823	java/io/IOException
/*    */     //   1354	1357	823	java/io/IOException
/*    */     //   1360	1365	823	java/io/IOException
/*    */     //   1367	1378	823	java/io/IOException
/*    */     //   1380	1392	823	java/io/IOException
/*    */     //   1394	1397	823	java/io/IOException
/*    */     //   1400	1409	823	java/io/IOException
/*    */     //   1411	1437	823	java/io/IOException
/*    */     //   1439	1453	823	java/io/IOException
/*    */     //   1456	1464	823	java/io/IOException
/*    */     //   1465	1479	823	java/io/IOException
/*    */     //   1480	1495	823	java/io/IOException
/*    */     //   1496	1500	823	java/io/IOException
/*    */     //   1507	1510	823	java/io/IOException
/*    */     //   1511	1530	823	java/io/IOException
/*    */     //   1531	1540	823	java/io/IOException
/*    */     //   1541	1545	823	java/io/IOException
/*    */     //   1554	1558	823	java/io/IOException
/*    */     //   1561	1565	823	java/io/IOException
/*    */     //   1576	1585	823	java/io/IOException
/*    */     //   1586	1593	823	java/io/IOException
/*    */     //   1595	1596	823	java/io/IOException
/*    */     //   1598	1602	823	java/io/IOException
/*    */     //   1607	1615	823	java/io/IOException
/*    */     //   1618	1622	823	java/io/IOException
/*    */     //   1625	1682	823	java/io/IOException
/*    */     //   1683	1687	823	java/io/IOException
/*    */     //   1694	1697	823	java/io/IOException
/*    */     //   1698	1709	823	java/io/IOException
/*    */     //   1713	1716	823	java/io/IOException
/*    */     //   1724	1743	823	java/io/IOException
/*    */     //   1744	1754	823	java/io/IOException
/*    */     //   1760	1764	823	java/io/IOException
/*    */     //   1765	1769	823	java/io/IOException
/*    */     //   1776	1779	823	java/io/IOException
/*    */     //   1780	1801	823	java/io/IOException
/*    */     //   1802	1808	823	java/io/IOException
/*    */     //   1811	1821	823	java/io/IOException
/*    */     //   1823	1840	823	java/io/IOException
/*    */     //   1841	1858	823	java/io/IOException
/*    */     //   1859	1866	823	java/io/IOException
/*    */     //   1869	1874	823	java/io/IOException
/*    */     //   1877	1882	823	java/io/IOException
/*    */     //   1884	1888	823	java/io/IOException
/*    */     //   1901	1921	823	java/io/IOException
/*    */     //   1922	1925	823	java/io/IOException
/*    */     //   1926	1929	823	java/io/IOException
/*    */     //   1930	1933	823	java/io/IOException
/*    */     //   1936	1940	823	java/io/IOException
/*    */     //   1944	1957	823	java/io/IOException
/*    */     //   1958	1970	823	java/io/IOException
/*    */     //   1971	1974	823	java/io/IOException
/*    */     //   1975	1978	823	java/io/IOException
/*    */     //   1981	1985	823	java/io/IOException
/*    */     //   1989	2001	823	java/io/IOException
/*    */     //   2003	2019	823	java/io/IOException
/*    */     //   2020	2040	823	java/io/IOException
/*    */     //   2041	2049	823	java/io/IOException
/*    */   }
/*    */   
/*    */   public final void Qd() {
/*    */     try {
/*    */       Lv0 lv0;
/*    */       wR wR1;
/*    */       (wR1 = this.q1).wq0();
/*    */       this(this, false);
/*    */       this.x30 = new Lv0();
/*    */       this.q1.b7.Com3(lv0);
/*    */       return;
/*    */     } catch (IOException iOException) {
/*    */       throw new kN(this);
/*    */     } 
/*    */   }
/*    */   
/*    */   public final void i10(Class paramClass1, Class paramClass2) {
/*    */     try {
/*    */       Lv0 lv0;
/*    */       wR wR1;
/*    */       (wR1 = this.q1).wq0();
/*    */       this(wR1, false);
/*    */       wR1.x30 = new Lv0();
/*    */       this.q1.b7.Com3(lv0);
/*    */       if ((paramClass2 == null || paramClass2 != paramClass1) && this.y5 != null) {
/*    */         String str;
/*    */         if ((str = (String)this.zd0.pd0(paramClass1)) == null)
/*    */           str = paramClass1.getName(); 
/*    */         try {
/*    */           this.q1.Lj0(this.y5).AQ(str);
/*    */           return;
/*    */         } catch (IOException iOException) {
/*    */           throw new kN(this);
/*    */         } 
/*    */       } 
/*    */       return;
/*    */     } catch (IOException iOException) {
/*    */       throw new kN(this);
/*    */     } 
/*    */   }
/*    */   
/*    */   public final void cd0() {
/*    */     try {
/*    */       this.q1.q00();
/*    */       return;
/*    */     } catch (IOException iOException) {
/*    */       throw new kN(this);
/*    */     } 
/*    */   }
/*    */   
/*    */   public final void Rg(String paramString) {
/*    */     try {
/*    */       Lv0 lv0;
/*    */       this.q1.Lj0(paramString);
/*    */       wR wR1;
/*    */       (wR1 = this.q1).wq0();
/*    */       this(this, true);
/*    */       this.x30 = new Lv0();
/*    */       this.q1.b7.Com3(lv0);
/*    */       return;
/*    */     } catch (IOException iOException) {
/*    */       throw new kN(this);
/*    */     } 
/*    */   }
/*    */   
/*    */   public final void ty0() {
/*    */     try {
/*    */       Lv0 lv0;
/*    */       wR wR1;
/*    */       (wR1 = this.q1).wq0();
/*    */       this(this, true);
/*    */       this.x30 = new Lv0();
/*    */       this.q1.b7.Com3(lv0);
/*    */       return;
/*    */     } catch (IOException iOException) {
/*    */       throw new kN(this);
/*    */     } 
/*    */   }
/*    */   
/*    */   public final void Rw0() {
/*    */     try {
/*    */       this.q1.q00();
/*    */       return;
/*    */     } catch (IOException iOException) {
/*    */       throw new kN(this);
/*    */     } 
/*    */   }
/*    */   
/*    */   public Object Uj0(Class<?> paramClass1, Class paramClass2, bM0 parambM0) {
/*    */     // Byte code:
/*    */     //   0: aload_3
/*    */     //   1: ifnonnull -> 6
/*    */     //   4: aconst_null
/*    */     //   5: areturn
/*    */     //   6: aload_3
/*    */     //   7: getfield eR : Lf/nc;
/*    */     //   10: getstatic f/nc.Gg0 : Lf/nc;
/*    */     //   13: if_acmpne -> 22
/*    */     //   16: iconst_1
/*    */     //   17: istore #4
/*    */     //   19: goto -> 25
/*    */     //   22: iconst_0
/*    */     //   23: istore #4
/*    */     //   25: iload #4
/*    */     //   27: ifeq -> 1107
/*    */     //   30: aload_0
/*    */     //   31: getfield y5 : Ljava/lang/String;
/*    */     //   34: dup
/*    */     //   35: astore #4
/*    */     //   37: ifnonnull -> 46
/*    */     //   40: aconst_null
/*    */     //   41: astore #4
/*    */     //   43: goto -> 55
/*    */     //   46: aload_3
/*    */     //   47: aload #4
/*    */     //   49: aconst_null
/*    */     //   50: invokevirtual Bh0 : (Ljava/lang/String;Ljava/lang/String;)Ljava/lang/String;
/*    */     //   53: astore #4
/*    */     //   55: aload #4
/*    */     //   57: ifnull -> 127
/*    */     //   60: aload_0
/*    */     //   61: getfield B80 : Lf/f7;
/*    */     //   64: aload #4
/*    */     //   66: invokevirtual pd0 : (Ljava/lang/Object;)Ljava/lang/Object;
/*    */     //   69: checkcast java/lang/Class
/*    */     //   72: dup
/*    */     //   73: astore_1
/*    */     //   74: ifnonnull -> 127
/*    */     //   77: aload #4
/*    */     //   79: invokestatic forName : (Ljava/lang/String;)Ljava/lang/Class;
/*    */     //   82: astore_1
/*    */     //   83: goto -> 127
/*    */     //   86: astore_0
/*    */     //   87: new f/BC
/*    */     //   90: dup
/*    */     //   91: new java/lang/StringBuilder
/*    */     //   94: dup
/*    */     //   95: invokespecial <init> : ()V
/*    */     //   98: ldc_w 'Class not found: '
/*    */     //   101: invokevirtual append : (Ljava/lang/String;)Ljava/lang/StringBuilder;
/*    */     //   104: aload #4
/*    */     //   106: invokevirtual append : (Ljava/lang/String;)Ljava/lang/StringBuilder;
/*    */     //   109: invokevirtual toString : ()Ljava/lang/String;
/*    */     //   112: aload_0
/*    */     //   113: invokespecial <init> : (Ljava/lang/String;Ljava/lang/Throwable;)V
/*    */     //   116: athrow
/*    */     //   117: astore_0
/*    */     //   118: new f/kN
/*    */     //   121: dup
/*    */     //   122: aload_0
/*    */     //   123: invokespecial <init> : (Ljava/lang/Throwable;)V
/*    */     //   126: athrow
/*    */     //   127: aload_1
/*    */     //   128: ifnonnull -> 133
/*    */     //   131: aload_3
/*    */     //   132: areturn
/*    */     //   133: aload_0
/*    */     //   134: getfield y5 : Ljava/lang/String;
/*    */     //   137: ifnull -> 212
/*    */     //   140: ldc_w java/util/Collection
/*    */     //   143: aload_1
/*    */     //   144: invokevirtual isAssignableFrom : (Ljava/lang/Class;)Z
/*    */     //   147: ifeq -> 212
/*    */     //   150: aload_3
/*    */     //   151: ldc_w 'items'
/*    */     //   154: invokevirtual Jb : (Ljava/lang/String;)Lf/bM0;
/*    */     //   157: dup
/*    */     //   158: astore_3
/*    */     //   159: ifnull -> 165
/*    */     //   162: goto -> 1107
/*    */     //   165: new f/kN
/*    */     //   168: dup
/*    */     //   169: new java/lang/StringBuilder
/*    */     //   172: dup
/*    */     //   173: invokespecial <init> : ()V
/*    */     //   176: ldc_w 'Unable to convert object to collection: '
/*    */     //   179: invokevirtual append : (Ljava/lang/String;)Ljava/lang/StringBuilder;
/*    */     //   182: aload_3
/*    */     //   183: invokevirtual append : (Ljava/lang/Object;)Ljava/lang/StringBuilder;
/*    */     //   186: ldc_w ' ('
/*    */     //   189: invokevirtual append : (Ljava/lang/String;)Ljava/lang/StringBuilder;
/*    */     //   192: aload_1
/*    */     //   193: invokevirtual getName : ()Ljava/lang/String;
/*    */     //   196: invokevirtual append : (Ljava/lang/String;)Ljava/lang/StringBuilder;
/*    */     //   199: ldc_w ')'
/*    */     //   202: invokevirtual append : (Ljava/lang/String;)Ljava/lang/StringBuilder;
/*    */     //   205: invokevirtual toString : ()Ljava/lang/String;
/*    */     //   208: invokespecial <init> : (Ljava/lang/String;)V
/*    */     //   211: athrow
/*    */     //   212: aload_0
/*    */     //   213: getfield f3 : Lf/f7;
/*    */     //   216: aload_1
/*    */     //   217: invokevirtual pd0 : (Ljava/lang/Object;)Ljava/lang/Object;
/*    */     //   220: checkcast f/TF0
/*    */     //   223: dup
/*    */     //   224: astore #4
/*    */     //   226: ifnull -> 237
/*    */     //   229: aload #4
/*    */     //   231: aload_0
/*    */     //   232: aload_3
/*    */     //   233: invokevirtual COm7 : (Lf/It;Lf/bM0;)Ljava/lang/Object;
/*    */     //   236: areturn
/*    */     //   237: aload_1
/*    */     //   238: ldc_w java/lang/String
/*    */     //   241: if_acmpeq -> 1092
/*    */     //   244: aload_1
/*    */     //   245: ldc_w java/lang/Integer
/*    */     //   248: if_acmpeq -> 1092
/*    */     //   251: aload_1
/*    */     //   252: ldc_w java/lang/Boolean
/*    */     //   255: if_acmpeq -> 1092
/*    */     //   258: aload_1
/*    */     //   259: ldc_w java/lang/Float
/*    */     //   262: if_acmpeq -> 1092
/*    */     //   265: aload_1
/*    */     //   266: ldc_w java/lang/Long
/*    */     //   269: if_acmpeq -> 1092
/*    */     //   272: aload_1
/*    */     //   273: ldc_w java/lang/Double
/*    */     //   276: if_acmpeq -> 1092
/*    */     //   279: aload_1
/*    */     //   280: ldc_w java/lang/Short
/*    */     //   283: if_acmpeq -> 1092
/*    */     //   286: aload_1
/*    */     //   287: ldc_w java/lang/Byte
/*    */     //   290: if_acmpeq -> 1092
/*    */     //   293: aload_1
/*    */     //   294: ldc_w java/lang/Character
/*    */     //   297: if_acmpeq -> 1092
/*    */     //   300: ldc java/lang/Enum
/*    */     //   302: aload_1
/*    */     //   303: invokevirtual isAssignableFrom : (Ljava/lang/Class;)Z
/*    */     //   306: ifeq -> 312
/*    */     //   309: goto -> 1092
/*    */     //   312: aload_1
/*    */     //   313: invokestatic Tx : (Ljava/lang/Class;)Ljava/lang/Object;
/*    */     //   316: dup
/*    */     //   317: astore_1
/*    */     //   318: instanceof f/dB
/*    */     //   321: ifeq -> 337
/*    */     //   324: aload_1
/*    */     //   325: dup
/*    */     //   326: checkcast f/dB
/*    */     //   329: aload_0
/*    */     //   330: aload_3
/*    */     //   331: invokeinterface read : (Lf/It;Lf/bM0;)V
/*    */     //   336: areturn
/*    */     //   337: aload_1
/*    */     //   338: instanceof f/f7
/*    */     //   341: ifeq -> 389
/*    */     //   344: aload_3
/*    */     //   345: aload_1
/*    */     //   346: checkcast f/f7
/*    */     //   349: astore_1
/*    */     //   350: getfield Rr0 : Lf/bM0;
/*    */     //   353: astore_3
/*    */     //   354: aload_3
/*    */     //   355: ifnull -> 387
/*    */     //   358: aload_3
/*    */     //   359: aload_1
/*    */     //   360: aload_0
/*    */     //   361: aload_3
/*    */     //   362: getfield as0 : Ljava/lang/String;
/*    */     //   365: astore #4
/*    */     //   367: aload_2
/*    */     //   368: aconst_null
/*    */     //   369: aload_3
/*    */     //   370: invokevirtual Uj0 : (Ljava/lang/Class;Ljava/lang/Class;Lf/bM0;)Ljava/lang/Object;
/*    */     //   373: aload #4
/*    */     //   375: swap
/*    */     //   376: invokevirtual X00 : (Ljava/lang/Object;Ljava/lang/Object;)Ljava/lang/Object;
/*    */     //   379: pop
/*    */     //   380: getfield H7 : Lf/bM0;
/*    */     //   383: astore_3
/*    */     //   384: goto -> 354
/*    */     //   387: aload_1
/*    */     //   388: areturn
/*    */     //   389: aload_1
/*    */     //   390: instanceof f/Nu0
/*    */     //   393: ifeq -> 445
/*    */     //   396: aload_3
/*    */     //   397: aload_1
/*    */     //   398: checkcast f/Nu0
/*    */     //   401: astore_1
/*    */     //   402: getfield Rr0 : Lf/bM0;
/*    */     //   405: astore_2
/*    */     //   406: aload_2
/*    */     //   407: ifnull -> 443
/*    */     //   410: aload_2
/*    */     //   411: aload_1
/*    */     //   412: aload_0
/*    */     //   413: aload_2
/*    */     //   414: getfield as0 : Ljava/lang/String;
/*    */     //   417: astore_3
/*    */     //   418: ldc_w java/lang/Integer
/*    */     //   421: aconst_null
/*    */     //   422: aload_2
/*    */     //   423: invokevirtual Uj0 : (Ljava/lang/Class;Ljava/lang/Class;Lf/bM0;)Ljava/lang/Object;
/*    */     //   426: checkcast java/lang/Integer
/*    */     //   429: invokevirtual intValue : ()I
/*    */     //   432: aload_3
/*    */     //   433: invokevirtual b4 : (ILjava/lang/Object;)V
/*    */     //   436: getfield H7 : Lf/bM0;
/*    */     //   439: astore_2
/*    */     //   440: goto -> 406
/*    */     //   443: aload_1
/*    */     //   444: areturn
/*    */     //   445: aload_1
/*    */     //   446: instanceof f/com9
/*    */     //   449: ifeq -> 738
/*    */     //   452: aload_3
/*    */     //   453: aload_1
/*    */     //   454: checkcast f/com9
/*    */     //   457: astore_1
/*    */     //   458: getfield Rr0 : Lf/bM0;
/*    */     //   461: astore_2
/*    */     //   462: aload_2
/*    */     //   463: ifnull -> 736
/*    */     //   466: aload_1
/*    */     //   467: aload_0
/*    */     //   468: aload_2
/*    */     //   469: getfield as0 : Ljava/lang/String;
/*    */     //   472: astore_3
/*    */     //   473: ldc_w java/lang/Float
/*    */     //   476: aconst_null
/*    */     //   477: aload_2
/*    */     //   478: invokevirtual Uj0 : (Ljava/lang/Class;Ljava/lang/Class;Lf/bM0;)Ljava/lang/Object;
/*    */     //   481: checkcast java/lang/Float
/*    */     //   484: invokevirtual floatValue : ()F
/*    */     //   487: fstore #4
/*    */     //   489: aload_3
/*    */     //   490: invokevirtual Sr : (Ljava/lang/Object;)I
/*    */     //   493: dup
/*    */     //   494: istore #5
/*    */     //   496: iflt -> 511
/*    */     //   499: aload_1
/*    */     //   500: getfield lPT5 : [F
/*    */     //   503: iload #5
/*    */     //   505: fload #4
/*    */     //   507: fastore
/*    */     //   508: goto -> 728
/*    */     //   511: aload_1
/*    */     //   512: dup
/*    */     //   513: dup
/*    */     //   514: iload #5
/*    */     //   516: iconst_1
/*    */     //   517: iadd
/*    */     //   518: ineg
/*    */     //   519: istore #5
/*    */     //   521: getfield gg : [Ljava/lang/Object;
/*    */     //   524: dup
/*    */     //   525: astore #6
/*    */     //   527: iload #5
/*    */     //   529: aload_3
/*    */     //   530: aastore
/*    */     //   531: getfield lPT5 : [F
/*    */     //   534: iload #5
/*    */     //   536: fload #4
/*    */     //   538: fastore
/*    */     //   539: getfield Z3 : I
/*    */     //   542: iconst_1
/*    */     //   543: iadd
/*    */     //   544: dup
/*    */     //   545: istore_3
/*    */     //   546: aload_1
/*    */     //   547: dup
/*    */     //   548: iload_3
/*    */     //   549: putfield Z3 : I
/*    */     //   552: getfield Ei0 : I
/*    */     //   555: if_icmplt -> 728
/*    */     //   558: aload_1
/*    */     //   559: dup
/*    */     //   560: dup
/*    */     //   561: dup2
/*    */     //   562: dup2
/*    */     //   563: aload #6
/*    */     //   565: arraylength
/*    */     //   566: iconst_1
/*    */     //   567: ishl
/*    */     //   568: dup
/*    */     //   569: istore_3
/*    */     //   570: aload_1
/*    */     //   571: iload_3
/*    */     //   572: aload #6
/*    */     //   574: arraylength
/*    */     //   575: istore #4
/*    */     //   577: i2f
/*    */     //   578: aload_1
/*    */     //   579: getfield Tz : F
/*    */     //   582: fmul
/*    */     //   583: f2i
/*    */     //   584: putfield Ei0 : I
/*    */     //   587: iconst_1
/*    */     //   588: isub
/*    */     //   589: dup
/*    */     //   590: istore #5
/*    */     //   592: putfield y3 : I
/*    */     //   595: iload #5
/*    */     //   597: i2l
/*    */     //   598: invokestatic numberOfLeadingZeros : (J)I
/*    */     //   601: putfield UC0 : I
/*    */     //   604: getfield gg : [Ljava/lang/Object;
/*    */     //   607: astore #5
/*    */     //   609: getfield lPT5 : [F
/*    */     //   612: astore #6
/*    */     //   614: iload_3
/*    */     //   615: anewarray java/lang/Object
/*    */     //   618: putfield gg : [Ljava/lang/Object;
/*    */     //   621: iload_3
/*    */     //   622: newarray float
/*    */     //   624: putfield lPT5 : [F
/*    */     //   627: getfield Z3 : I
/*    */     //   630: ifle -> 728
/*    */     //   633: iconst_0
/*    */     //   634: istore_3
/*    */     //   635: iload_3
/*    */     //   636: iload #4
/*    */     //   638: if_icmpge -> 728
/*    */     //   641: aload #5
/*    */     //   643: iload_3
/*    */     //   644: aaload
/*    */     //   645: dup
/*    */     //   646: astore #7
/*    */     //   648: ifnull -> 722
/*    */     //   651: aload #7
/*    */     //   653: aload_1
/*    */     //   654: aload #6
/*    */     //   656: iload_3
/*    */     //   657: faload
/*    */     //   658: fstore #8
/*    */     //   660: getfield gg : [Ljava/lang/Object;
/*    */     //   663: astore #9
/*    */     //   665: invokevirtual hashCode : ()I
/*    */     //   668: i2l
/*    */     //   669: ldc2_w -7046029254386353131
/*    */     //   672: lmul
/*    */     //   673: aload_1
/*    */     //   674: getfield UC0 : I
/*    */     //   677: lushr
/*    */     //   678: l2i
/*    */     //   679: istore #10
/*    */     //   681: aload #9
/*    */     //   683: iload #10
/*    */     //   685: aaload
/*    */     //   686: ifnonnull -> 708
/*    */     //   689: aload_1
/*    */     //   690: aload #9
/*    */     //   692: iload #10
/*    */     //   694: aload #7
/*    */     //   696: aastore
/*    */     //   697: getfield lPT5 : [F
/*    */     //   700: iload #10
/*    */     //   702: fload #8
/*    */     //   704: fastore
/*    */     //   705: goto -> 722
/*    */     //   708: iload #10
/*    */     //   710: iconst_1
/*    */     //   711: iadd
/*    */     //   712: aload_1
/*    */     //   713: getfield y3 : I
/*    */     //   716: iand
/*    */     //   717: istore #10
/*    */     //   719: goto -> 681
/*    */     //   722: iinc #3, 1
/*    */     //   725: goto -> 635
/*    */     //   728: aload_2
/*    */     //   729: getfield H7 : Lf/bM0;
/*    */     //   732: astore_2
/*    */     //   733: goto -> 462
/*    */     //   736: aload_1
/*    */     //   737: areturn
/*    */     //   738: aload_1
/*    */     //   739: instanceof f/MG
/*    */     //   742: ifeq -> 797
/*    */     //   745: aload_3
/*    */     //   746: aload_1
/*    */     //   747: checkcast f/MG
/*    */     //   750: astore_1
/*    */     //   751: ldc_w 'values'
/*    */     //   754: invokevirtual Jb : (Ljava/lang/String;)Lf/bM0;
/*    */     //   757: dup
/*    */     //   758: astore_3
/*    */     //   759: ifnonnull -> 767
/*    */     //   762: aconst_null
/*    */     //   763: astore_3
/*    */     //   764: goto -> 772
/*    */     //   767: aload_3
/*    */     //   768: getfield Rr0 : Lf/bM0;
/*    */     //   771: astore_3
/*    */     //   772: aload_3
/*    */     //   773: ifnull -> 795
/*    */     //   776: aload_3
/*    */     //   777: aload_1
/*    */     //   778: aload_0
/*    */     //   779: aload_2
/*    */     //   780: aconst_null
/*    */     //   781: aload_3
/*    */     //   782: invokevirtual Uj0 : (Ljava/lang/Class;Ljava/lang/Class;Lf/bM0;)Ljava/lang/Object;
/*    */     //   785: invokevirtual GV : (Ljava/lang/Object;)V
/*    */     //   788: getfield H7 : Lf/bM0;
/*    */     //   791: astore_3
/*    */     //   792: goto -> 772
/*    */     //   795: aload_1
/*    */     //   796: areturn
/*    */     //   797: aload_1
/*    */     //   798: instanceof f/y10
/*    */     //   801: ifeq -> 851
/*    */     //   804: aload_3
/*    */     //   805: aload_1
/*    */     //   806: checkcast f/y10
/*    */     //   809: astore_1
/*    */     //   810: getfield Rr0 : Lf/bM0;
/*    */     //   813: astore_3
/*    */     //   814: aload_3
/*    */     //   815: ifnull -> 849
/*    */     //   818: aload_3
/*    */     //   819: aload_1
/*    */     //   820: aload_0
/*    */     //   821: aload_2
/*    */     //   822: aload_3
/*    */     //   823: getfield as0 : Ljava/lang/String;
/*    */     //   826: invokestatic parseInt : (Ljava/lang/String;)I
/*    */     //   829: istore #4
/*    */     //   831: aconst_null
/*    */     //   832: aload_3
/*    */     //   833: invokevirtual Uj0 : (Ljava/lang/Class;Ljava/lang/Class;Lf/bM0;)Ljava/lang/Object;
/*    */     //   836: iload #4
/*    */     //   838: swap
/*    */     //   839: invokevirtual tD0 : (ILjava/lang/Object;)V
/*    */     //   842: getfield H7 : Lf/bM0;
/*    */     //   845: astore_3
/*    */     //   846: goto -> 814
/*    */     //   849: aload_1
/*    */     //   850: areturn
/*    */     //   851: aload_1
/*    */     //   852: instanceof f/LF0
/*    */     //   855: ifeq -> 906
/*    */     //   858: aload_3
/*    */     //   859: aload_1
/*    */     //   860: checkcast f/LF0
/*    */     //   863: astore_1
/*    */     //   864: getfield Rr0 : Lf/bM0;
/*    */     //   867: astore_3
/*    */     //   868: aload_3
/*    */     //   869: ifnull -> 904
/*    */     //   872: aload_3
/*    */     //   873: aload_1
/*    */     //   874: aload_0
/*    */     //   875: aload_2
/*    */     //   876: aload_3
/*    */     //   877: getfield as0 : Ljava/lang/String;
/*    */     //   880: invokestatic parseLong : (Ljava/lang/String;)J
/*    */     //   883: lstore #4
/*    */     //   885: aconst_null
/*    */     //   886: aload_3
/*    */     //   887: invokevirtual Uj0 : (Ljava/lang/Class;Ljava/lang/Class;Lf/bM0;)Ljava/lang/Object;
/*    */     //   890: astore_3
/*    */     //   891: lload #4
/*    */     //   893: aload_3
/*    */     //   894: invokevirtual dG0 : (JLjava/lang/Object;)V
/*    */     //   897: getfield H7 : Lf/bM0;
/*    */     //   900: astore_3
/*    */     //   901: goto -> 868
/*    */     //   904: aload_1
/*    */     //   905: areturn
/*    */     //   906: aload_1
/*    */     //   907: instanceof f/S4
/*    */     //   910: ifeq -> 962
/*    */     //   913: aload_3
/*    */     //   914: aload_1
/*    */     //   915: checkcast f/S4
/*    */     //   918: astore_0
/*    */     //   919: ldc_w 'values'
/*    */     //   922: invokevirtual Jb : (Ljava/lang/String;)Lf/bM0;
/*    */     //   925: dup
/*    */     //   926: astore_1
/*    */     //   927: ifnonnull -> 935
/*    */     //   930: aconst_null
/*    */     //   931: astore_1
/*    */     //   932: goto -> 940
/*    */     //   935: aload_1
/*    */     //   936: getfield Rr0 : Lf/bM0;
/*    */     //   939: astore_1
/*    */     //   940: aload_1
/*    */     //   941: ifnull -> 960
/*    */     //   944: aload_1
/*    */     //   945: aload_0
/*    */     //   946: aload_1
/*    */     //   947: invokevirtual v60 : ()I
/*    */     //   950: invokevirtual V9 : (I)V
/*    */     //   953: getfield H7 : Lf/bM0;
/*    */     //   956: astore_1
/*    */     //   957: goto -> 940
/*    */     //   960: aload_0
/*    */     //   961: areturn
/*    */     //   962: aload_1
/*    */     //   963: instanceof f/eM
/*    */     //   966: ifeq -> 1013
/*    */     //   969: aload_3
/*    */     //   970: aload_1
/*    */     //   971: checkcast f/eM
/*    */     //   974: astore_1
/*    */     //   975: getfield Rr0 : Lf/bM0;
/*    */     //   978: astore_3
/*    */     //   979: aload_3
/*    */     //   980: ifnull -> 1011
/*    */     //   983: aload_3
/*    */     //   984: aload_1
/*    */     //   985: aload_0
/*    */     //   986: aload_3
/*    */     //   987: getfield as0 : Ljava/lang/String;
/*    */     //   990: astore #4
/*    */     //   992: aload_2
/*    */     //   993: aconst_null
/*    */     //   994: aload_3
/*    */     //   995: invokevirtual Uj0 : (Ljava/lang/Class;Ljava/lang/Class;Lf/bM0;)Ljava/lang/Object;
/*    */     //   998: aload #4
/*    */     //   1000: swap
/*    */     //   1001: invokevirtual Ed0 : (Ljava/lang/Object;Ljava/lang/Object;)V
/*    */     //   1004: getfield H7 : Lf/bM0;
/*    */     //   1007: astore_3
/*    */     //   1008: goto -> 979
/*    */     //   1011: aload_1
/*    */     //   1012: areturn
/*    */     //   1013: aload_1
/*    */     //   1014: instanceof java/util/Map
/*    */     //   1017: ifeq -> 1084
/*    */     //   1020: aload_3
/*    */     //   1021: aload_1
/*    */     //   1022: checkcast java/util/Map
/*    */     //   1025: astore_1
/*    */     //   1026: getfield Rr0 : Lf/bM0;
/*    */     //   1029: astore_3
/*    */     //   1030: aload_3
/*    */     //   1031: ifnull -> 1082
/*    */     //   1034: aload_3
/*    */     //   1035: getfield as0 : Ljava/lang/String;
/*    */     //   1038: aload_0
/*    */     //   1039: getfield y5 : Ljava/lang/String;
/*    */     //   1042: invokevirtual equals : (Ljava/lang/Object;)Z
/*    */     //   1045: ifeq -> 1051
/*    */     //   1048: goto -> 1074
/*    */     //   1051: aload_1
/*    */     //   1052: aload_0
/*    */     //   1053: aload_3
/*    */     //   1054: getfield as0 : Ljava/lang/String;
/*    */     //   1057: astore #4
/*    */     //   1059: aload_2
/*    */     //   1060: aconst_null
/*    */     //   1061: aload_3
/*    */     //   1062: invokevirtual Uj0 : (Ljava/lang/Class;Ljava/lang/Class;Lf/bM0;)Ljava/lang/Object;
/*    */     //   1065: aload #4
/*    */     //   1067: swap
/*    */     //   1068: invokeinterface put : (Ljava/lang/Object;Ljava/lang/Object;)Ljava/lang/Object;
/*    */     //   1073: pop
/*    */     //   1074: aload_3
/*    */     //   1075: getfield H7 : Lf/bM0;
/*    */     //   1078: astore_3
/*    */     //   1079: goto -> 1030
/*    */     //   1082: aload_1
/*    */     //   1083: areturn
/*    */     //   1084: aload_1
/*    */     //   1085: aload_0
/*    */     //   1086: aload_1
/*    */     //   1087: aload_3
/*    */     //   1088: invokevirtual for : (Ljava/lang/Object;Lf/bM0;)V
/*    */     //   1091: areturn
/*    */     //   1092: aload_0
/*    */     //   1093: aload_1
/*    */     //   1094: aload_3
/*    */     //   1095: ldc_w 'value'
/*    */     //   1098: invokevirtual Jb : (Ljava/lang/String;)Lf/bM0;
/*    */     //   1101: aconst_null
/*    */     //   1102: swap
/*    */     //   1103: invokevirtual Uj0 : (Ljava/lang/Class;Ljava/lang/Class;Lf/bM0;)Ljava/lang/Object;
/*    */     //   1106: areturn
/*    */     //   1107: aload_1
/*    */     //   1108: ifnull -> 1162
/*    */     //   1111: aload_0
/*    */     //   1112: getfield f3 : Lf/f7;
/*    */     //   1115: aload_1
/*    */     //   1116: invokevirtual pd0 : (Ljava/lang/Object;)Ljava/lang/Object;
/*    */     //   1119: checkcast f/TF0
/*    */     //   1122: dup
/*    */     //   1123: astore #4
/*    */     //   1125: ifnull -> 1136
/*    */     //   1128: aload #4
/*    */     //   1130: aload_0
/*    */     //   1131: aload_3
/*    */     //   1132: invokevirtual COm7 : (Lf/It;Lf/bM0;)Ljava/lang/Object;
/*    */     //   1135: areturn
/*    */     //   1136: ldc_w f/dB
/*    */     //   1139: aload_1
/*    */     //   1140: invokevirtual isAssignableFrom : (Ljava/lang/Class;)Z
/*    */     //   1143: ifeq -> 1162
/*    */     //   1146: aload_1
/*    */     //   1147: invokestatic Tx : (Ljava/lang/Class;)Ljava/lang/Object;
/*    */     //   1150: dup
/*    */     //   1151: checkcast f/dB
/*    */     //   1154: aload_0
/*    */     //   1155: aload_3
/*    */     //   1156: invokeinterface read : (Lf/It;Lf/bM0;)V
/*    */     //   1161: areturn
/*    */     //   1162: aload_3
/*    */     //   1163: invokevirtual OA0 : ()Z
/*    */     //   1166: ifeq -> 1685
/*    */     //   1169: aload_1
/*    */     //   1170: ifnull -> 1179
/*    */     //   1173: aload_1
/*    */     //   1174: ldc java/lang/Object
/*    */     //   1176: if_acmpne -> 1182
/*    */     //   1179: ldc f/fQ
/*    */     //   1181: astore_1
/*    */     //   1182: ldc f/fQ
/*    */     //   1184: aload_1
/*    */     //   1185: invokevirtual isAssignableFrom : (Ljava/lang/Class;)Z
/*    */     //   1188: ifeq -> 1246
/*    */     //   1191: aload_1
/*    */     //   1192: ldc f/fQ
/*    */     //   1194: if_acmpne -> 1208
/*    */     //   1197: new f/fQ
/*    */     //   1200: dup
/*    */     //   1201: astore_1
/*    */     //   1202: invokespecial <init> : ()V
/*    */     //   1205: goto -> 1216
/*    */     //   1208: aload_1
/*    */     //   1209: invokestatic Tx : (Ljava/lang/Class;)Ljava/lang/Object;
/*    */     //   1212: checkcast f/fQ
/*    */     //   1215: astore_1
/*    */     //   1216: aload_3
/*    */     //   1217: getfield Rr0 : Lf/bM0;
/*    */     //   1220: astore_3
/*    */     //   1221: aload_3
/*    */     //   1222: ifnull -> 1244
/*    */     //   1225: aload_3
/*    */     //   1226: aload_1
/*    */     //   1227: aload_0
/*    */     //   1228: aload_2
/*    */     //   1229: aconst_null
/*    */     //   1230: aload_3
/*    */     //   1231: invokevirtual Uj0 : (Ljava/lang/Class;Ljava/lang/Class;Lf/bM0;)Ljava/lang/Object;
/*    */     //   1234: invokevirtual Com3 : (Ljava/lang/Object;)V
/*    */     //   1237: getfield H7 : Lf/bM0;
/*    */     //   1240: astore_3
/*    */     //   1241: goto -> 1221
/*    */     //   1244: aload_1
/*    */     //   1245: areturn
/*    */     //   1246: ldc_w f/mf0
/*    */     //   1249: aload_1
/*    */     //   1250: invokevirtual isAssignableFrom : (Ljava/lang/Class;)Z
/*    */     //   1253: ifeq -> 1495
/*    */     //   1256: aload_1
/*    */     //   1257: ldc_w f/mf0
/*    */     //   1260: if_acmpne -> 1274
/*    */     //   1263: new f/mf0
/*    */     //   1266: dup
/*    */     //   1267: astore_1
/*    */     //   1268: invokespecial <init> : ()V
/*    */     //   1271: goto -> 1282
/*    */     //   1274: aload_1
/*    */     //   1275: invokestatic Tx : (Ljava/lang/Class;)Ljava/lang/Object;
/*    */     //   1278: checkcast f/mf0
/*    */     //   1281: astore_1
/*    */     //   1282: aload_3
/*    */     //   1283: getfield Rr0 : Lf/bM0;
/*    */     //   1286: astore_3
/*    */     //   1287: aload_3
/*    */     //   1288: ifnull -> 1493
/*    */     //   1291: aload_1
/*    */     //   1292: dup
/*    */     //   1293: aload_0
/*    */     //   1294: aload_2
/*    */     //   1295: aconst_null
/*    */     //   1296: aload_3
/*    */     //   1297: invokevirtual Uj0 : (Ljava/lang/Class;Ljava/lang/Class;Lf/bM0;)Ljava/lang/Object;
/*    */     //   1300: astore #4
/*    */     //   1302: getfield public : [Ljava/lang/Object;
/*    */     //   1305: astore #5
/*    */     //   1307: getfield bK : I
/*    */     //   1310: aload #5
/*    */     //   1312: arraylength
/*    */     //   1313: if_icmpne -> 1440
/*    */     //   1316: aload_1
/*    */     //   1317: aload #5
/*    */     //   1319: arraylength
/*    */     //   1320: iconst_1
/*    */     //   1321: ishl
/*    */     //   1322: istore #6
/*    */     //   1324: getfield Ye0 : I
/*    */     //   1327: dup
/*    */     //   1328: istore #7
/*    */     //   1330: aload_1
/*    */     //   1331: getfield JH0 : I
/*    */     //   1334: dup
/*    */     //   1335: istore #8
/*    */     //   1337: aload #5
/*    */     //   1339: invokevirtual getClass : ()Ljava/lang/Class;
/*    */     //   1342: invokevirtual getComponentType : ()Ljava/lang/Class;
/*    */     //   1345: iload #6
/*    */     //   1347: invokestatic newInstance : (Ljava/lang/Class;I)Ljava/lang/Object;
/*    */     //   1350: checkcast [Ljava/lang/Object;
/*    */     //   1353: astore #6
/*    */     //   1355: if_icmpge -> 1380
/*    */     //   1358: aload #5
/*    */     //   1360: iload #8
/*    */     //   1362: iload #7
/*    */     //   1364: isub
/*    */     //   1365: istore #5
/*    */     //   1367: iload #7
/*    */     //   1369: aload #6
/*    */     //   1371: iconst_0
/*    */     //   1372: iload #5
/*    */     //   1374: invokestatic arraycopy : (Ljava/lang/Object;ILjava/lang/Object;II)V
/*    */     //   1377: goto -> 1418
/*    */     //   1380: aload_1
/*    */     //   1381: getfield bK : I
/*    */     //   1384: ifle -> 1418
/*    */     //   1387: aload #5
/*    */     //   1389: dup
/*    */     //   1390: iload #7
/*    */     //   1392: aload #5
/*    */     //   1394: arraylength
/*    */     //   1395: iload #7
/*    */     //   1397: isub
/*    */     //   1398: istore #5
/*    */     //   1400: aload #6
/*    */     //   1402: iconst_0
/*    */     //   1403: iload #5
/*    */     //   1405: invokestatic arraycopy : (Ljava/lang/Object;ILjava/lang/Object;II)V
/*    */     //   1408: iconst_0
/*    */     //   1409: aload #6
/*    */     //   1411: iload #5
/*    */     //   1413: iload #8
/*    */     //   1415: invokestatic arraycopy : (Ljava/lang/Object;ILjava/lang/Object;II)V
/*    */     //   1418: aload_1
/*    */     //   1419: dup
/*    */     //   1420: dup2
/*    */     //   1421: aload #6
/*    */     //   1423: putfield public : [Ljava/lang/Object;
/*    */     //   1426: iconst_0
/*    */     //   1427: putfield Ye0 : I
/*    */     //   1430: getfield bK : I
/*    */     //   1433: putfield JH0 : I
/*    */     //   1436: aload #6
/*    */     //   1438: astore #5
/*    */     //   1440: aload_1
/*    */     //   1441: getfield JH0 : I
/*    */     //   1444: dup
/*    */     //   1445: istore #6
/*    */     //   1447: iconst_1
/*    */     //   1448: iadd
/*    */     //   1449: dup
/*    */     //   1450: istore #7
/*    */     //   1452: aload #5
/*    */     //   1454: dup
/*    */     //   1455: iload #6
/*    */     //   1457: aload_1
/*    */     //   1458: iload #7
/*    */     //   1460: putfield JH0 : I
/*    */     //   1463: aload #4
/*    */     //   1465: aastore
/*    */     //   1466: arraylength
/*    */     //   1467: if_icmpne -> 1475
/*    */     //   1470: aload_1
/*    */     //   1471: iconst_0
/*    */     //   1472: putfield JH0 : I
/*    */     //   1475: aload_3
/*    */     //   1476: aload_1
/*    */     //   1477: dup
/*    */     //   1478: getfield bK : I
/*    */     //   1481: iconst_1
/*    */     //   1482: iadd
/*    */     //   1483: putfield bK : I
/*    */     //   1486: getfield H7 : Lf/bM0;
/*    */     //   1489: astore_3
/*    */     //   1490: goto -> 1287
/*    */     //   1493: aload_1
/*    */     //   1494: areturn
/*    */     //   1495: ldc_w java/util/Collection
/*    */     //   1498: aload_1
/*    */     //   1499: invokevirtual isAssignableFrom : (Ljava/lang/Class;)Z
/*    */     //   1502: ifeq -> 1564
/*    */     //   1505: aload_1
/*    */     //   1506: invokevirtual isInterface : ()Z
/*    */     //   1509: ifeq -> 1523
/*    */     //   1512: new java/util/ArrayList
/*    */     //   1515: dup
/*    */     //   1516: astore_1
/*    */     //   1517: invokespecial <init> : ()V
/*    */     //   1520: goto -> 1531
/*    */     //   1523: aload_1
/*    */     //   1524: invokestatic Tx : (Ljava/lang/Class;)Ljava/lang/Object;
/*    */     //   1527: checkcast java/util/Collection
/*    */     //   1530: astore_1
/*    */     //   1531: aload_3
/*    */     //   1532: getfield Rr0 : Lf/bM0;
/*    */     //   1535: astore_3
/*    */     //   1536: aload_3
/*    */     //   1537: ifnull -> 1562
/*    */     //   1540: aload_3
/*    */     //   1541: aload_1
/*    */     //   1542: aload_0
/*    */     //   1543: aload_2
/*    */     //   1544: aconst_null
/*    */     //   1545: aload_3
/*    */     //   1546: invokevirtual Uj0 : (Ljava/lang/Class;Ljava/lang/Class;Lf/bM0;)Ljava/lang/Object;
/*    */     //   1549: invokeinterface add : (Ljava/lang/Object;)Z
/*    */     //   1554: pop
/*    */     //   1555: getfield H7 : Lf/bM0;
/*    */     //   1558: astore_3
/*    */     //   1559: goto -> 1536
/*    */     //   1562: aload_1
/*    */     //   1563: areturn
/*    */     //   1564: aload_1
/*    */     //   1565: invokevirtual isArray : ()Z
/*    */     //   1568: ifeq -> 1638
/*    */     //   1571: aload_2
/*    */     //   1572: aload_1
/*    */     //   1573: invokevirtual getComponentType : ()Ljava/lang/Class;
/*    */     //   1576: astore_1
/*    */     //   1577: ifnonnull -> 1582
/*    */     //   1580: aload_1
/*    */     //   1581: astore_2
/*    */     //   1582: aload_3
/*    */     //   1583: aload_1
/*    */     //   1584: aload_3
/*    */     //   1585: getfield LG : I
/*    */     //   1588: invokestatic newInstance : (Ljava/lang/Class;I)Ljava/lang/Object;
/*    */     //   1591: astore_1
/*    */     //   1592: iconst_0
/*    */     //   1593: istore_3
/*    */     //   1594: getfield Rr0 : Lf/bM0;
/*    */     //   1597: astore #4
/*    */     //   1599: aload #4
/*    */     //   1601: ifnull -> 1636
/*    */     //   1604: aload #4
/*    */     //   1606: aload_1
/*    */     //   1607: aload_0
/*    */     //   1608: iload_3
/*    */     //   1609: iconst_1
/*    */     //   1610: iadd
/*    */     //   1611: istore #5
/*    */     //   1613: aload_2
/*    */     //   1614: aconst_null
/*    */     //   1615: aload #4
/*    */     //   1617: invokevirtual Uj0 : (Ljava/lang/Class;Ljava/lang/Class;Lf/bM0;)Ljava/lang/Object;
/*    */     //   1620: iload_3
/*    */     //   1621: swap
/*    */     //   1622: invokestatic set : (Ljava/lang/Object;ILjava/lang/Object;)V
/*    */     //   1625: getfield H7 : Lf/bM0;
/*    */     //   1628: astore #4
/*    */     //   1630: iload #5
/*    */     //   1632: istore_3
/*    */     //   1633: goto -> 1599
/*    */     //   1636: aload_1
/*    */     //   1637: areturn
/*    */     //   1638: new f/kN
/*    */     //   1641: dup
/*    */     //   1642: new java/lang/StringBuilder
/*    */     //   1645: dup
/*    */     //   1646: invokespecial <init> : ()V
/*    */     //   1649: ldc_w 'Unable to convert value to required type: '
/*    */     //   1652: invokevirtual append : (Ljava/lang/String;)Ljava/lang/StringBuilder;
/*    */     //   1655: aload_3
/*    */     //   1656: invokevirtual append : (Ljava/lang/Object;)Ljava/lang/StringBuilder;
/*    */     //   1659: ldc_w ' ('
/*    */     //   1662: invokevirtual append : (Ljava/lang/String;)Ljava/lang/StringBuilder;
/*    */     //   1665: aload_1
/*    */     //   1666: invokevirtual getName : ()Ljava/lang/String;
/*    */     //   1669: invokevirtual append : (Ljava/lang/String;)Ljava/lang/StringBuilder;
/*    */     //   1672: ldc_w ')'
/*    */     //   1675: invokevirtual append : (Ljava/lang/String;)Ljava/lang/StringBuilder;
/*    */     //   1678: invokevirtual toString : ()Ljava/lang/String;
/*    */     //   1681: invokespecial <init> : (Ljava/lang/String;)V
/*    */     //   1684: athrow
/*    */     //   1685: aload_3
/*    */     //   1686: getfield eR : Lf/nc;
/*    */     //   1689: dup
/*    */     //   1690: astore_2
/*    */     //   1691: getstatic f/nc.zK0 : Lf/nc;
/*    */     //   1694: if_acmpeq -> 1712
/*    */     //   1697: aload_2
/*    */     //   1698: getstatic f/nc.ci0 : Lf/nc;
/*    */     //   1701: if_acmpne -> 1707
/*    */     //   1704: goto -> 1712
/*    */     //   1707: iconst_0
/*    */     //   1708: istore_2
/*    */     //   1709: goto -> 1714
/*    */     //   1712: iconst_1
/*    */     //   1713: istore_2
/*    */     //   1714: iload_2
/*    */     //   1715: ifeq -> 1896
/*    */     //   1718: aload_1
/*    */     //   1719: ifnull -> 1873
/*    */     //   1722: aload_1
/*    */     //   1723: getstatic java/lang/Float.TYPE : Ljava/lang/Class;
/*    */     //   1726: if_acmpeq -> 1873
/*    */     //   1729: aload_1
/*    */     //   1730: ldc_w java/lang/Float
/*    */     //   1733: if_acmpne -> 1739
/*    */     //   1736: goto -> 1873
/*    */     //   1739: aload_1
/*    */     //   1740: getstatic java/lang/Integer.TYPE : Ljava/lang/Class;
/*    */     //   1743: if_acmpeq -> 1865
/*    */     //   1746: aload_1
/*    */     //   1747: ldc_w java/lang/Integer
/*    */     //   1750: if_acmpne -> 1756
/*    */     //   1753: goto -> 1865
/*    */     //   1756: aload_1
/*    */     //   1757: getstatic java/lang/Long.TYPE : Ljava/lang/Class;
/*    */     //   1760: if_acmpeq -> 1857
/*    */     //   1763: aload_1
/*    */     //   1764: ldc_w java/lang/Long
/*    */     //   1767: if_acmpne -> 1773
/*    */     //   1770: goto -> 1857
/*    */     //   1773: aload_1
/*    */     //   1774: getstatic java/lang/Double.TYPE : Ljava/lang/Class;
/*    */     //   1777: if_acmpeq -> 1849
/*    */     //   1780: aload_1
/*    */     //   1781: ldc_w java/lang/Double
/*    */     //   1784: if_acmpne -> 1790
/*    */     //   1787: goto -> 1849
/*    */     //   1790: aload_1
/*    */     //   1791: ldc_w java/lang/String
/*    */     //   1794: if_acmpne -> 1802
/*    */     //   1797: aload_3
/*    */     //   1798: invokevirtual DX : ()Ljava/lang/String;
/*    */     //   1801: areturn
/*    */     //   1802: aload_1
/*    */     //   1803: getstatic java/lang/Short.TYPE : Ljava/lang/Class;
/*    */     //   1806: if_acmpeq -> 1841
/*    */     //   1809: aload_1
/*    */     //   1810: ldc_w java/lang/Short
/*    */     //   1813: if_acmpne -> 1819
/*    */     //   1816: goto -> 1841
/*    */     //   1819: aload_1
/*    */     //   1820: getstatic java/lang/Byte.TYPE : Ljava/lang/Class;
/*    */     //   1823: if_acmpeq -> 1833
/*    */     //   1826: aload_1
/*    */     //   1827: ldc_w java/lang/Byte
/*    */     //   1830: if_acmpne -> 1882
/*    */     //   1833: aload_3
/*    */     //   1834: invokevirtual z70 : ()B
/*    */     //   1837: invokestatic valueOf : (B)Ljava/lang/Byte;
/*    */     //   1840: areturn
/*    */     //   1841: aload_3
/*    */     //   1842: invokevirtual B9 : ()S
/*    */     //   1845: invokestatic valueOf : (S)Ljava/lang/Short;
/*    */     //   1848: areturn
/*    */     //   1849: aload_3
/*    */     //   1850: invokevirtual cQ : ()D
/*    */     //   1853: invokestatic valueOf : (D)Ljava/lang/Double;
/*    */     //   1856: areturn
/*    */     //   1857: aload_3
/*    */     //   1858: invokevirtual YO : ()J
/*    */     //   1861: invokestatic valueOf : (J)Ljava/lang/Long;
/*    */     //   1864: areturn
/*    */     //   1865: aload_3
/*    */     //   1866: invokevirtual v60 : ()I
/*    */     //   1869: invokestatic valueOf : (I)Ljava/lang/Integer;
/*    */     //   1872: areturn
/*    */     //   1873: aload_3
/*    */     //   1874: invokevirtual hy0 : ()F
/*    */     //   1877: invokestatic valueOf : (F)Ljava/lang/Float;
/*    */     //   1880: areturn
/*    */     //   1881: pop
/*    */     //   1882: new f/bM0
/*    */     //   1885: dup
/*    */     //   1886: astore_2
/*    */     //   1887: aload_3
/*    */     //   1888: invokevirtual DX : ()Ljava/lang/String;
/*    */     //   1891: invokespecial <init> : (Ljava/lang/String;)V
/*    */     //   1894: aload_2
/*    */     //   1895: astore_3
/*    */     //   1896: aload_3
/*    */     //   1897: getfield eR : Lf/nc;
/*    */     //   1900: getstatic f/nc.hK0 : Lf/nc;
/*    */     //   1903: if_acmpne -> 1911
/*    */     //   1906: iconst_1
/*    */     //   1907: istore_2
/*    */     //   1908: goto -> 1913
/*    */     //   1911: iconst_0
/*    */     //   1912: istore_2
/*    */     //   1913: iload_2
/*    */     //   1914: ifeq -> 1958
/*    */     //   1917: aload_1
/*    */     //   1918: ifnull -> 1935
/*    */     //   1921: aload_1
/*    */     //   1922: getstatic java/lang/Boolean.TYPE : Ljava/lang/Class;
/*    */     //   1925: if_acmpeq -> 1935
/*    */     //   1928: aload_1
/*    */     //   1929: ldc_w java/lang/Boolean
/*    */     //   1932: if_acmpne -> 1944
/*    */     //   1935: aload_3
/*    */     //   1936: invokevirtual gI0 : ()Z
/*    */     //   1939: invokestatic valueOf : (Z)Ljava/lang/Boolean;
/*    */     //   1942: areturn
/*    */     //   1943: pop
/*    */     //   1944: new f/bM0
/*    */     //   1947: dup
/*    */     //   1948: astore_2
/*    */     //   1949: aload_3
/*    */     //   1950: invokevirtual DX : ()Ljava/lang/String;
/*    */     //   1953: invokespecial <init> : (Ljava/lang/String;)V
/*    */     //   1956: aload_2
/*    */     //   1957: astore_3
/*    */     //   1958: aload_3
/*    */     //   1959: getfield eR : Lf/nc;
/*    */     //   1962: getstatic f/nc.O80 : Lf/nc;
/*    */     //   1965: if_acmpne -> 1973
/*    */     //   1968: iconst_1
/*    */     //   1969: istore_2
/*    */     //   1970: goto -> 1975
/*    */     //   1973: iconst_0
/*    */     //   1974: istore_2
/*    */     //   1975: iload_2
/*    */     //   1976: ifeq -> 2315
/*    */     //   1979: aload_1
/*    */     //   1980: aload_3
/*    */     //   1981: invokevirtual DX : ()Ljava/lang/String;
/*    */     //   1984: astore_2
/*    */     //   1985: ifnull -> 2313
/*    */     //   1988: aload_1
/*    */     //   1989: ldc_w java/lang/String
/*    */     //   1992: if_acmpne -> 1998
/*    */     //   1995: goto -> 2313
/*    */     //   1998: aload_1
/*    */     //   1999: getstatic java/lang/Integer.TYPE : Ljava/lang/Class;
/*    */     //   2002: if_acmpeq -> 2122
/*    */     //   2005: aload_1
/*    */     //   2006: ldc_w java/lang/Integer
/*    */     //   2009: if_acmpne -> 2015
/*    */     //   2012: goto -> 2122
/*    */     //   2015: aload_1
/*    */     //   2016: getstatic java/lang/Float.TYPE : Ljava/lang/Class;
/*    */     //   2019: if_acmpeq -> 2117
/*    */     //   2022: aload_1
/*    */     //   2023: ldc_w java/lang/Float
/*    */     //   2026: if_acmpne -> 2032
/*    */     //   2029: goto -> 2117
/*    */     //   2032: aload_1
/*    */     //   2033: getstatic java/lang/Long.TYPE : Ljava/lang/Class;
/*    */     //   2036: if_acmpeq -> 2112
/*    */     //   2039: aload_1
/*    */     //   2040: ldc_w java/lang/Long
/*    */     //   2043: if_acmpne -> 2049
/*    */     //   2046: goto -> 2112
/*    */     //   2049: aload_1
/*    */     //   2050: getstatic java/lang/Double.TYPE : Ljava/lang/Class;
/*    */     //   2053: if_acmpeq -> 2107
/*    */     //   2056: aload_1
/*    */     //   2057: ldc_w java/lang/Double
/*    */     //   2060: if_acmpne -> 2066
/*    */     //   2063: goto -> 2107
/*    */     //   2066: aload_1
/*    */     //   2067: getstatic java/lang/Short.TYPE : Ljava/lang/Class;
/*    */     //   2070: if_acmpeq -> 2102
/*    */     //   2073: aload_1
/*    */     //   2074: ldc_w java/lang/Short
/*    */     //   2077: if_acmpne -> 2083
/*    */     //   2080: goto -> 2102
/*    */     //   2083: aload_1
/*    */     //   2084: getstatic java/lang/Byte.TYPE : Ljava/lang/Class;
/*    */     //   2087: if_acmpeq -> 2097
/*    */     //   2090: aload_1
/*    */     //   2091: ldc_w java/lang/Byte
/*    */     //   2094: if_acmpne -> 2128
/*    */     //   2097: aload_2
/*    */     //   2098: invokestatic valueOf : (Ljava/lang/String;)Ljava/lang/Byte;
/*    */     //   2101: areturn
/*    */     //   2102: aload_2
/*    */     //   2103: invokestatic valueOf : (Ljava/lang/String;)Ljava/lang/Short;
/*    */     //   2106: areturn
/*    */     //   2107: aload_2
/*    */     //   2108: invokestatic valueOf : (Ljava/lang/String;)Ljava/lang/Double;
/*    */     //   2111: areturn
/*    */     //   2112: aload_2
/*    */     //   2113: invokestatic valueOf : (Ljava/lang/String;)Ljava/lang/Long;
/*    */     //   2116: areturn
/*    */     //   2117: aload_2
/*    */     //   2118: invokestatic valueOf : (Ljava/lang/String;)Ljava/lang/Float;
/*    */     //   2121: areturn
/*    */     //   2122: aload_2
/*    */     //   2123: invokestatic valueOf : (Ljava/lang/String;)Ljava/lang/Integer;
/*    */     //   2126: areturn
/*    */     //   2127: pop
/*    */     //   2128: aload_1
/*    */     //   2129: getstatic java/lang/Boolean.TYPE : Ljava/lang/Class;
/*    */     //   2132: if_acmpeq -> 2308
/*    */     //   2135: aload_1
/*    */     //   2136: ldc_w java/lang/Boolean
/*    */     //   2139: if_acmpne -> 2145
/*    */     //   2142: goto -> 2308
/*    */     //   2145: aload_1
/*    */     //   2146: getstatic java/lang/Character.TYPE : Ljava/lang/Class;
/*    */     //   2149: if_acmpeq -> 2299
/*    */     //   2152: aload_1
/*    */     //   2153: ldc_w java/lang/Character
/*    */     //   2156: if_acmpne -> 2162
/*    */     //   2159: goto -> 2299
/*    */     //   2162: ldc java/lang/Enum
/*    */     //   2164: aload_1
/*    */     //   2165: invokevirtual isAssignableFrom : (Ljava/lang/Class;)Z
/*    */     //   2168: ifeq -> 2243
/*    */     //   2171: aload_1
/*    */     //   2172: invokevirtual getEnumConstants : ()[Ljava/lang/Object;
/*    */     //   2175: checkcast [Ljava/lang/Enum;
/*    */     //   2178: dup
/*    */     //   2179: astore #4
/*    */     //   2181: iconst_0
/*    */     //   2182: istore #5
/*    */     //   2184: arraylength
/*    */     //   2185: istore #6
/*    */     //   2187: iload #5
/*    */     //   2189: iload #6
/*    */     //   2191: if_icmpge -> 2243
/*    */     //   2194: aload_0
/*    */     //   2195: aload #4
/*    */     //   2197: iload #5
/*    */     //   2199: aaload
/*    */     //   2200: astore #7
/*    */     //   2202: getfield Xj : Z
/*    */     //   2205: ifeq -> 2218
/*    */     //   2208: aload #7
/*    */     //   2210: invokevirtual name : ()Ljava/lang/String;
/*    */     //   2213: astore #8
/*    */     //   2215: goto -> 2225
/*    */     //   2218: aload #7
/*    */     //   2220: invokevirtual toString : ()Ljava/lang/String;
/*    */     //   2223: astore #8
/*    */     //   2225: aload_2
/*    */     //   2226: aload #8
/*    */     //   2228: invokevirtual equals : (Ljava/lang/Object;)Z
/*    */     //   2231: ifeq -> 2237
/*    */     //   2234: aload #7
/*    */     //   2236: areturn
/*    */     //   2237: iinc #5, 1
/*    */     //   2240: goto -> 2187
/*    */     //   2243: aload_1
/*    */     //   2244: ldc_w java/lang/CharSequence
/*    */     //   2247: if_acmpne -> 2252
/*    */     //   2250: aload_2
/*    */     //   2251: areturn
/*    */     //   2252: new f/kN
/*    */     //   2255: dup
/*    */     //   2256: new java/lang/StringBuilder
/*    */     //   2259: dup
/*    */     //   2260: invokespecial <init> : ()V
/*    */     //   2263: ldc_w 'Unable to convert value to required type: '
/*    */     //   2266: invokevirtual append : (Ljava/lang/String;)Ljava/lang/StringBuilder;
/*    */     //   2269: aload_3
/*    */     //   2270: invokevirtual append : (Ljava/lang/Object;)Ljava/lang/StringBuilder;
/*    */     //   2273: ldc_w ' ('
/*    */     //   2276: invokevirtual append : (Ljava/lang/String;)Ljava/lang/StringBuilder;
/*    */     //   2279: aload_1
/*    */     //   2280: invokevirtual getName : ()Ljava/lang/String;
/*    */     //   2283: invokevirtual append : (Ljava/lang/String;)Ljava/lang/StringBuilder;
/*    */     //   2286: ldc_w ')'
/*    */     //   2289: invokevirtual append : (Ljava/lang/String;)Ljava/lang/StringBuilder;
/*    */     //   2292: invokevirtual toString : ()Ljava/lang/String;
/*    */     //   2295: invokespecial <init> : (Ljava/lang/String;)V
/*    */     //   2298: athrow
/*    */     //   2299: aload_2
/*    */     //   2300: iconst_0
/*    */     //   2301: invokevirtual charAt : (I)C
/*    */     //   2304: invokestatic valueOf : (C)Ljava/lang/Character;
/*    */     //   2307: areturn
/*    */     //   2308: aload_2
/*    */     //   2309: invokestatic valueOf : (Ljava/lang/String;)Ljava/lang/Boolean;
/*    */     //   2312: areturn
/*    */     //   2313: aload_2
/*    */     //   2314: areturn
/*    */     //   2315: aconst_null
/*    */     //   2316: areturn
/*    */     // Line number table:
/*    */     //   Java source line number -> byte code offset
/*    */     //   #1	-> 7
/*    */     //   #2	-> 31
/*    */     //   #3	-> 61
/*    */     //   #4	-> 79
/*    */     //   #5	-> 118
/*    */     //   #6	-> 140
/*    */     //   #7	-> 151
/*    */     //   #8	-> 300
/*    */     //   #9	-> 313
/*    */     //   #10	-> 490
/*    */     //   #11	-> 500
/*    */     //   #12	-> 574
/*    */     //   #13	-> 660
/*    */     //   #14	-> 665
/*    */     //   #15	-> 685
/*    */     //   #16	-> 729
/*    */     //   #17	-> 751
/*    */     //   #18	-> 782
/*    */     //   #19	-> 919
/*    */     //   #20	-> 947
/*    */     //   #21	-> 1095
/*    */     //   #22	-> 1112
/*    */     //   #23	-> 1136
/*    */     //   #24	-> 1147
/*    */     //   #25	-> 1182
/*    */     //   #26	-> 1192
/*    */     //   #27	-> 1246
/*    */     //   #28	-> 1257
/*    */     //   #29	-> 1302
/*    */     //   #30	-> 1307
/*    */     //   #31	-> 1324
/*    */     //   #32	-> 1347
/*    */     //   #33	-> 1350
/*    */     //   #34	-> 1441
/*    */     //   #35	-> 1486
/*    */     //   #36	-> 1495
/*    */     //   #37	-> 1506
/*    */     //   #38	-> 1588
/*    */     //   #39	-> 1594
/*    */     //   #40	-> 1622
/*    */     //   #41	-> 1625
/*    */     //   #42	-> 1686
/*    */     //   #43	-> 1723
/*    */     //   #44	-> 1897
/*    */     //   #45	-> 1922
/*    */     //   #46	-> 1959
/*    */     //   #47	-> 1981
/*    */     //   #48	-> 2162
/*    */     //   #49	-> 2172
/*    */     //   #50	-> 2202
/*    */     //   #51	-> 2228
/*    */     // Exception table:
/*    */     //   from	to	target	type
/*    */     //   77	82	86	java/lang/ClassNotFoundException
/*    */     //   77	82	117	f/BC
/*    */     //   87	117	117	f/BC
/*    */     //   1722	1726	1881	java/lang/NumberFormatException
/*    */     //   1729	1733	1881	java/lang/NumberFormatException
/*    */     //   1739	1743	1881	java/lang/NumberFormatException
/*    */     //   1746	1750	1881	java/lang/NumberFormatException
/*    */     //   1756	1760	1881	java/lang/NumberFormatException
/*    */     //   1763	1767	1881	java/lang/NumberFormatException
/*    */     //   1773	1777	1881	java/lang/NumberFormatException
/*    */     //   1780	1784	1881	java/lang/NumberFormatException
/*    */     //   1790	1794	1881	java/lang/NumberFormatException
/*    */     //   1797	1801	1881	java/lang/NumberFormatException
/*    */     //   1802	1806	1881	java/lang/NumberFormatException
/*    */     //   1809	1813	1881	java/lang/NumberFormatException
/*    */     //   1819	1823	1881	java/lang/NumberFormatException
/*    */     //   1826	1830	1881	java/lang/NumberFormatException
/*    */     //   1833	1840	1881	java/lang/NumberFormatException
/*    */     //   1841	1848	1881	java/lang/NumberFormatException
/*    */     //   1849	1856	1881	java/lang/NumberFormatException
/*    */     //   1857	1864	1881	java/lang/NumberFormatException
/*    */     //   1865	1872	1881	java/lang/NumberFormatException
/*    */     //   1873	1880	1881	java/lang/NumberFormatException
/*    */     //   1921	1925	1943	java/lang/NumberFormatException
/*    */     //   1928	1932	1943	java/lang/NumberFormatException
/*    */     //   1935	1942	1943	java/lang/NumberFormatException
/*    */     //   1998	2002	2127	java/lang/NumberFormatException
/*    */     //   2005	2009	2127	java/lang/NumberFormatException
/*    */     //   2015	2019	2127	java/lang/NumberFormatException
/*    */     //   2022	2026	2127	java/lang/NumberFormatException
/*    */     //   2032	2036	2127	java/lang/NumberFormatException
/*    */     //   2039	2043	2127	java/lang/NumberFormatException
/*    */     //   2049	2053	2127	java/lang/NumberFormatException
/*    */     //   2056	2060	2127	java/lang/NumberFormatException
/*    */     //   2066	2070	2127	java/lang/NumberFormatException
/*    */     //   2073	2077	2127	java/lang/NumberFormatException
/*    */     //   2083	2087	2127	java/lang/NumberFormatException
/*    */     //   2090	2094	2127	java/lang/NumberFormatException
/*    */     //   2097	2101	2127	java/lang/NumberFormatException
/*    */     //   2102	2106	2127	java/lang/NumberFormatException
/*    */     //   2107	2111	2127	java/lang/NumberFormatException
/*    */     //   2112	2116	2127	java/lang/NumberFormatException
/*    */     //   2117	2121	2127	java/lang/NumberFormatException
/*    */     //   2122	2126	2127	java/lang/NumberFormatException
/*    */   }
/*    */   
/*    */   public final void PH0(Object paramObject1, Object paramObject2) {
/*    */     Nn nn = gf0(paramObject2.getClass());
/*    */     oc oc = gf0(paramObject1.getClass()).sh();
/*    */     while (oc.hasNext()) {
/*    */       CL0 cL01, cL02 = ((CoM2)yO.mm).WW;
/*    */       yO yO;
/*    */       CoM2 coM2;
/*    */       if ((coM2 = (CoM2)pd0((yO = oc.next()).Lb)) != null)
/*    */         try {
/*    */           Object object = cL02.Op(paramObject1);
/*    */           (cL01 = coM2.WW).getClass();
/*    */           try {
/*    */             coM2.WW.Lh.set(paramObject2, object);
/*    */             continue;
/*    */           } catch (IllegalArgumentException illegalArgumentException) {
/*    */             throw new BC("Argument not valid for field: " + cL01.Lh.getName(), this);
/*    */           } catch (IllegalAccessException illegalAccessException) {
/*    */             throw new BC("Illegal access to field: " + cL01.Lh.getName(), this);
/*    */           } 
/*    */         } catch (BC bC) {
/*    */           throw new kN(B40.df("Error copying field: ").append(cL02.Lh.getName()).toString(), this);
/*    */         }  
/*    */       throw new kN(B40.df("To object is missing field: ").append((String)cL01.Lb).toString());
/*    */     } 
/*    */   }
/*    */   
/*    */   public final void Jv0(Object paramObject, String paramString) {
/*    */     try {
/*    */       this.q1.Lj0(paramString);
/*    */       if (paramObject == null) {
/*    */         d80(paramObject, null, null);
/*    */       } else {
/*    */         d80(paramObject, paramObject.getClass(), null);
/*    */       } 
/*    */       return;
/*    */     } catch (IOException iOException) {
/*    */       throw new kN(this);
/*    */     } 
/*    */   }
/*    */   
/*    */   public final void Zg(Class paramClass, Object paramObject, String paramString) {
/*    */     try {
/*    */       this.q1.Lj0(paramString);
/*    */       d80(paramObject, paramClass, null);
/*    */       return;
/*    */     } catch (IOException iOException) {
/*    */       throw new kN(this);
/*    */     } 
/*    */   }
/*    */   
/*    */   public final Object VL0(RD0 paramRD0, Class paramClass) {
/*    */     try {
/*    */       return Uj0(paramClass, null, (new nP()).PL0(paramRD0));
/*    */     } catch (Exception exception) {
/*    */       throw new kN("Error reading file: " + paramRD0, this);
/*    */     } 
/*    */   }
/*    */   
/*    */   public final void mt0(ResourceData paramResourceData, RD0 paramRD0) {
/*    */     Class<?> clazz;
/*    */     if (paramResourceData == null) {
/*    */       clazz = null;
/*    */     } else {
/*    */       clazz = paramResourceData.getClass();
/*    */     } 
/*    */     OutputStreamWriter outputStreamWriter = null;
/*    */     try {
/*    */       paramResourceData = null;
/*    */       oS(outputStreamWriter);
/*    */       try {
/*    */         d80(paramResourceData, clazz, (Class)paramResourceData);
/*    */         Ui.JC0(this.q1);
/*    */         return;
/*    */       } finally {
/*    */         Ui.JC0(this.q1);
/*    */         this.q1 = null;
/*    */       } 
/*    */     } catch (Exception exception) {
/*    */       throw new kN("Error writing file: " + paramRD0, this);
/*    */     } finally {}
/*    */     Ui.JC0(outputStreamWriter);
/*    */     throw this;
/*    */   }
/*    */   
/*    */   public boolean fa(String paramString) {
/*    */     return false;
/*    */   } }


/* Location:              /Users/vnnsnnt/Documents/Codespace/JavaWorkspace/RedTrainer/src/main/java/org/trainer/client/PokeMMO.jar!/f/It.class
 * Java compiler version: 7 (51.0)
 * JD-Core Version:       1.1.3
 */