/*  1 */ package f;public final class j0 extends kV { public final void QA0() { gD gD2 = km.mI0.MT;
/*  2 */     this(gD2.TI.B8("/arc/demo_tengan_gra.narc")); U70[] arrayOfU70; ig ig1;
/*    */     pe0 pe0;
/*  4 */     this(gD2.TI.B8("/data/demo_climax.narc")); int[] arrayOfInt4; (arrayOfInt4 = new int[1])[0] = -1; eI.Lj().getClass(); lpt1 lpt12 = eI.L4(ig1, 46, arrayOfInt4);
/*  5 */     this.oe0.Com3(lpt12); int[] arrayOfInt3;
/*  6 */     (arrayOfInt3 = new int[2])[0] = 22; (new int[2])[1] = 23; eI.Lj()
/*  7 */       .getClass();
/*  8 */     lpt1 lpt11 = eI.QO(ig1, 24, true, true, false, arrayOfInt3);
/*    */     
/* 10 */     this.oe0.Com3(lpt11); int[] arrayOfInt2;
/* 11 */     (arrayOfInt2 = new int[2])[0] = 51; (new int[2])[1] = 52; eI.Lj().getClass(); this.Na0 = eI.L4(ig1, 53, arrayOfInt2); (arrayOfInt2 = new int[2])[0] = 54; (new int[2])[1] = 56; eI.Lj().getClass(); this.AUx = eI.L4(ig1, 55, arrayOfInt2); (arrayOfInt2 = new int[1])[0] = 82; eI.Lj().getClass(); this.Cw = eI.L4(ig1, 84, arrayOfInt2); (arrayOfInt2 = new int[4])[0] = 8; (new int[4])[1] = 9; (new int[4])[2] = 10; (new int[4])[3] = 11; eI.Lj().getClass(); zP zP; ig ig2; if ((zP = (this.j70 = eI.QO(ig2 = new ig(), 7, false, false, true, arrayOfInt2)).kB0("polygon1_tama_naka", true)) != null) { this.j70.vC0.Ct(zP, true); this.j70
/* 12 */         .kB0("bubble_out", true)
/* 13 */         .V0(zP); zP.z7.Tz(0.0F, 0.0F, 0.02F); }  if ((zP = this.j70.kB0("polygon2_tama_edge", true)) != null) { this.j70.vC0.Ct(zP, true); this.j70
/* 14 */         .kB0("bubble_in", true)
/* 15 */         .V0(zP); zP.z7.Tz(0.0F, 0.0F, 0.05F); zP.nH.TG0(1.05F, 1.05F, 1.05F); }  if ((zP = this.j70.kB0("polygon3_tama_edge", true)) != null) { this.j70.vC0.Ct(zP, true); this.j70
/* 16 */         .kB0("bubble_in", true)
/* 17 */         .V0(zP); zP.z7.Tz(10000.0F, 10000.0F, 0.15F); }  int[] arrayOfInt1; (arrayOfInt1 = new int[1])[0] = 40; eI.Lj().getClass(); this.q10 = eI.L4(ig1, 41, arrayOfInt1); (arrayOfInt1 = new int[1])[0] = -1; eI.Lj().getClass(); this.m2 = eI.L4(ig1, 42, arrayOfInt1); (arrayOfInt1 = new int[2])[0] = 25; (new int[2])[1] = 27; eI.Lj().getClass(); this.NU = eI.L4(ig1, 26, arrayOfInt1); (arrayOfInt1 = new int[2])[0] = 28; (new int[2])[1] = 30; eI.Lj().getClass(); this.tP = eI.L4(ig1, 29, arrayOfInt1); (arrayOfInt1 = new int[2])[0] = 31; (new int[2])[1] = 33; eI.Lj().getClass(); this.Ka = eI.L4(ig1, 32, arrayOfInt1); (arrayOfInt1 = new int[2])[0] = 34; (new int[2])[1] = 36; eI.Lj().getClass(); this.Ah = eI.L4(ig1, 35, arrayOfInt1); (arrayOfInt1 = new int[2])[0] = 37; (new int[2])[1] = 39; eI.Lj().getClass(); this.F50 = eI.L4(ig1, 38, arrayOfInt1); (arrayOfInt1 = new int[1])[0] = 67; eI.Lj().getClass(); this.xf = eI.L4(ig1, 66, arrayOfInt1); (arrayOfInt1 = new int[1])[0] = 69; eI.Lj().getClass(); this.x20 = eI.L4(ig1, 68, arrayOfInt1); byte b = 120;
/*    */     gD gD1;
/* 19 */     if (!(gD1 = km.mI0.MT).fm.Fb(b)) { gD1 = null; }
/* 20 */     else { arrayOfU70 = (U70[])gD1.sk.Z90(gD1.fm.Z90(b)); }  this
/* 21 */       .y7 = arrayOfU70; this(arrayOfU70[0].HA0()); (this.E50 = uT.xz(32, 32, pe0)).lM(true); this.E50.zO(0.011F); }
/*    */ 
/*    */   
/*    */   public final eo PRn = new eo();
/*    */   public final eo cr = new eo(0.0F, 1.0F, 0.0F);
/*    */   public final eo jE = new eo(0.0F, 0.1F, 3.0F);
/*    */   public final eo Vw0 = new eo(0.0F, 1.2F, 4.0F);
/*    */   public final eo He0 = new eo(0.0F, 0.1F, 1.1F);
/*    */   public final eo bQ = new eo(0.0F, 1.2F, 2.1F);
/*    */   public int o8 = 0;
/*    */   public uT[][] Nd0 = new uT[6][Vp0.Jo.length + 1];
/*    */   public lpt1 fa;
/*    */   public lpt1 Na0;
/*    */   public lpt1 AUx;
/*    */   public lpt1 Cw;
/*    */   public lpt1 j70;
/*    */   public lpt1 q10;
/*    */   public lpt1 m2;
/*    */   public lpt1 NU;
/*    */   public lpt1 tP;
/*    */   public lpt1 Ka;
/*    */   public lpt1 Ah;
/*    */   public lpt1 F50;
/*    */   public lpt1 xf;
/*    */   public lpt1 x20;
/*    */   public lpt1 sj0;
/*    */   public lpt1 Jq;
/*    */   public U70[] y7;
/*    */   public uT E50;
/*    */   public So f3;
/*    */   
/*    */   public j0() {
/*    */     super(30, false);
/*    */     this.Xc0.set(1.0F, 1.0F, 1.0F, 1.0F);
/*    */   }
/*    */   
/*    */   public final void Wy() {
/*    */     super.Wy();
/*    */     this.YL.Ce0 = 0.1F;
/*    */     this.YL.l6 = 200.0F;
/*    */     this.YL.Bj = 20.0F;
/*    */     this.YL.Mp = 0.0F;
/*    */     this.YL.IG0 = -40.0F;
/*    */     this.YL.el0 = 8.0F;
/*    */   }
/*    */   
/*    */   public final void uZ() {
/*    */     int i;
/*    */     if ((i = this.o8) >= 4 && i < 6) {
/*    */       float f;
/*    */       eo eo1 = this.YL.c5;
/*    */       if (System.currentTimeMillis() % 5L == 0L) {
/*    */         f = 0.01F;
/*    */       } else {
/*    */         f = 0.0F;
/*    */       } 
/*    */       eo1.x = f;
/*    */     } 
/*    */     this.YL.I70.JL(this.cr).uD(0.0F, 1.0F, 0.0F);
/*    */     float f1 = this.cr.x;
/*    */     float f2 = this.cr.y;
/*    */     float f3 = this.cr.z;
/*    */     this.YL.mP(f1, f2, f3);
/*    */   }
/*    */   
/*    */   public final void tc0() {
/*    */     // Byte code:
/*    */     //   0: getstatic f/km.kH0 : Lf/Qz0;
/*    */     //   3: invokevirtual tc : ()Lf/hO;
/*    */     //   6: dup
/*    */     //   7: astore_1
/*    */     //   8: ifnull -> 119
/*    */     //   11: aload_1
/*    */     //   12: aload_0
/*    */     //   13: dup
/*    */     //   14: dup
/*    */     //   15: getstatic f/km.wI0 : Lf/Pw;
/*    */     //   18: getfield fi0 : Lf/Ur0;
/*    */     //   21: astore_1
/*    */     //   22: getfield PRn : Lf/eo;
/*    */     //   25: aload_0
/*    */     //   26: getfield He0 : Lf/eo;
/*    */     //   29: invokevirtual JL : (Lf/eo;)Lf/eo;
/*    */     //   32: fconst_0
/*    */     //   33: ldc_w 0.125
/*    */     //   36: fconst_0
/*    */     //   37: invokevirtual Tz : (FFF)Lf/eo;
/*    */     //   40: pop
/*    */     //   41: getfield YL : Lf/Ih0;
/*    */     //   44: aload_0
/*    */     //   45: getfield PRn : Lf/eo;
/*    */     //   48: invokevirtual w8 : (Lf/eo;)Lf/eo;
/*    */     //   51: pop
/*    */     //   52: getfield PRn : Lf/eo;
/*    */     //   55: aload_1
/*    */     //   56: getfield Xe : Lf/ny;
/*    */     //   59: swap
/*    */     //   60: aload_1
/*    */     //   61: dup
/*    */     //   62: dup2
/*    */     //   63: getfield G80 : I
/*    */     //   66: i2f
/*    */     //   67: fstore_1
/*    */     //   68: getfield Cn0 : I
/*    */     //   71: i2f
/*    */     //   72: fstore_2
/*    */     //   73: getfield QQ : I
/*    */     //   76: i2f
/*    */     //   77: fstore_3
/*    */     //   78: getfield o6 : I
/*    */     //   81: i2f
/*    */     //   82: fstore #4
/*    */     //   84: fload_1
/*    */     //   85: fload_2
/*    */     //   86: fload_3
/*    */     //   87: fload #4
/*    */     //   89: invokevirtual jf0 : (Lf/eo;FFFF)V
/*    */     //   92: getstatic f/km.kH0 : Lf/Qz0;
/*    */     //   95: aload_0
/*    */     //   96: getfield PRn : Lf/eo;
/*    */     //   99: dup
/*    */     //   100: getfield x : F
/*    */     //   103: f2i
/*    */     //   104: istore_1
/*    */     //   105: getfield y : F
/*    */     //   108: f2i
/*    */     //   109: istore_2
/*    */     //   110: invokevirtual getClass : ()Ljava/lang/Class;
/*    */     //   113: pop
/*    */     //   114: iload_1
/*    */     //   115: iload_2
/*    */     //   116: invokestatic aX : (Lf/hO;II)V
/*    */     //   119: aload_0
/*    */     //   120: getfield o8 : I
/*    */     //   123: dup
/*    */     //   124: istore_1
/*    */     //   125: tableswitch default -> 324, 0 -> 2054, 1 -> 324, 2 -> 2045, 3 -> 324, 4 -> 1881, 5 -> 324, 6 -> 1823, 7 -> 1743, 8 -> 1715, 9 -> 1689, 10 -> 1452, 11 -> 1443, 12 -> 324, 13 -> 1434, 14 -> 324, 15 -> 1400, 16 -> 1733, 17 -> 1733, 18 -> 1348, 19 -> 1329, 20 -> 324, 21 -> 1282, 22 -> 1246, 23 -> 324, 24 -> 1237, 25 -> 324, 26 -> 1164, 27 -> 1145, 28 -> 324, 29 -> 1096, 30 -> 1030, 31 -> 324, 32 -> 974, 33 -> 934, 34 -> 825, 35 -> 787, 36 -> 778, 37 -> 324, 38 -> 629, 39 -> 324, 40 -> 557, 41 -> 324, 42 -> 497, 43 -> 417, 44 -> 324, 45 -> 327
/*    */     //   324: goto -> 2060
/*    */     //   327: getstatic f/km.kH0 : Lf/Qz0;
/*    */     //   330: invokevirtual tc : ()Lf/hO;
/*    */     //   333: dup
/*    */     //   334: astore_1
/*    */     //   335: ifnonnull -> 341
/*    */     //   338: goto -> 345
/*    */     //   341: aload_1
/*    */     //   342: invokevirtual EE0 : ()V
/*    */     //   345: aload_0
/*    */     //   346: dup
/*    */     //   347: invokestatic k60 : ()Lf/So;
/*    */     //   350: invokevirtual L5 : ()Lf/So;
/*    */     //   353: aload_0
/*    */     //   354: getfield oD : Lf/qo;
/*    */     //   357: getfield vF0 : Lcom/badlogic/gdx/graphics/Color;
/*    */     //   360: iconst_0
/*    */     //   361: ldc 0.1
/*    */     //   363: invokestatic gq : (Ljava/lang/Object;IF)Lf/Wz0;
/*    */     //   366: iconst_4
/*    */     //   367: newarray float
/*    */     //   369: dup
/*    */     //   370: dup
/*    */     //   371: dup2
/*    */     //   372: iconst_0
/*    */     //   373: fconst_0
/*    */     //   374: fastore
/*    */     //   375: iconst_1
/*    */     //   376: fconst_0
/*    */     //   377: fastore
/*    */     //   378: iconst_2
/*    */     //   379: fconst_0
/*    */     //   380: fastore
/*    */     //   381: iconst_3
/*    */     //   382: fconst_1
/*    */     //   383: fastore
/*    */     //   384: invokevirtual qY : ([F)Lf/Wz0;
/*    */     //   387: invokevirtual PL : (Lf/Wz0;)Lf/So;
/*    */     //   390: fconst_1
/*    */     //   391: invokevirtual Wz0 : (F)Lf/So;
/*    */     //   394: invokevirtual Kr : ()Lf/So;
/*    */     //   397: aload_0
/*    */     //   398: getfield Rv0 : Lf/G30;
/*    */     //   401: invokevirtual mg : (Lf/G30;)Lf/sh;
/*    */     //   404: checkcast f/So
/*    */     //   407: putfield f3 : Lf/So;
/*    */     //   410: getfield o8 : I
/*    */     //   413: istore_1
/*    */     //   414: goto -> 1733
/*    */     //   417: aload_0
/*    */     //   418: dup
/*    */     //   419: dup2
/*    */     //   420: dup2
/*    */     //   421: getfield F50 : Lf/lpt1;
/*    */     //   424: getfield mh : Lcom/badlogic/gdx/math/Matrix4;
/*    */     //   427: dup
/*    */     //   428: aload_0
/*    */     //   429: getfield Ah : Lf/lpt1;
/*    */     //   432: getfield mh : Lcom/badlogic/gdx/math/Matrix4;
/*    */     //   435: astore_1
/*    */     //   436: invokevirtual getClass : ()Ljava/lang/Class;
/*    */     //   439: pop
/*    */     //   440: aload_1
/*    */     //   441: getfield Z0 : [F
/*    */     //   444: invokevirtual Qw : ([F)Lcom/badlogic/gdx/math/Matrix4;
/*    */     //   447: pop
/*    */     //   448: getfield F50 : Lf/lpt1;
/*    */     //   451: new f/Gx0
/*    */     //   454: dup
/*    */     //   455: astore_1
/*    */     //   456: aload_0
/*    */     //   457: invokespecial <init> : (Lf/j0;)V
/*    */     //   460: iconst_0
/*    */     //   461: iconst_0
/*    */     //   462: aload_1
/*    */     //   463: invokevirtual rd : (IZLf/J3;)Lf/KI0;
/*    */     //   466: pop
/*    */     //   467: getfield F50 : Lf/lpt1;
/*    */     //   470: astore_1
/*    */     //   471: getfield oe0 : Lf/fQ;
/*    */     //   474: aload_1
/*    */     //   475: invokevirtual Com3 : (Ljava/lang/Object;)V
/*    */     //   478: getfield oe0 : Lf/fQ;
/*    */     //   481: aload_0
/*    */     //   482: getfield Ah : Lf/lpt1;
/*    */     //   485: iconst_1
/*    */     //   486: invokevirtual Ct : (Ljava/lang/Object;Z)Z
/*    */     //   489: pop
/*    */     //   490: getfield o8 : I
/*    */     //   493: istore_1
/*    */     //   494: goto -> 1733
/*    */     //   497: aload_0
/*    */     //   498: getstatic f/km.kH0 : Lf/Qz0;
/*    */     //   501: dup
/*    */     //   502: getstatic f/F40.wI : Lf/F40;
/*    */     //   505: getstatic f/Ml0.EH0 : [Ljava/lang/String;
/*    */     //   508: astore_1
/*    */     //   509: iconst_3
/*    */     //   510: swap
/*    */     //   511: sipush #234
/*    */     //   514: bipush #26
/*    */     //   516: aload_1
/*    */     //   517: invokestatic tG : (BLf/F40;II[Ljava/lang/String;)Ljava/lang/String;
/*    */     //   520: astore_1
/*    */     //   521: getstatic f/Aq.ur : Lf/Aq;
/*    */     //   524: astore_2
/*    */     //   525: bipush #-2
/*    */     //   527: istore_3
/*    */     //   528: aconst_null
/*    */     //   529: astore #4
/*    */     //   531: invokevirtual getClass : ()Ljava/lang/Class;
/*    */     //   534: pop
/*    */     //   535: new f/zB0
/*    */     //   538: dup
/*    */     //   539: astore #5
/*    */     //   541: aload_1
/*    */     //   542: aload_2
/*    */     //   543: iload_3
/*    */     //   544: aload #4
/*    */     //   546: invokespecial <init> : (Ljava/lang/String;Lf/Aq;ILf/Ku0;)V
/*    */     //   549: aload #5
/*    */     //   551: invokevirtual wV : (Lf/zB0;)V
/*    */     //   554: goto -> 1729
/*    */     //   557: aload_0
/*    */     //   558: dup
/*    */     //   559: dup2
/*    */     //   560: dup2
/*    */     //   561: getfield Ah : Lf/lpt1;
/*    */     //   564: getfield mh : Lcom/badlogic/gdx/math/Matrix4;
/*    */     //   567: dup
/*    */     //   568: aload_0
/*    */     //   569: getfield Ka : Lf/lpt1;
/*    */     //   572: getfield mh : Lcom/badlogic/gdx/math/Matrix4;
/*    */     //   575: astore_1
/*    */     //   576: invokevirtual getClass : ()Ljava/lang/Class;
/*    */     //   579: pop
/*    */     //   580: aload_1
/*    */     //   581: getfield Z0 : [F
/*    */     //   584: invokevirtual Qw : ([F)Lcom/badlogic/gdx/math/Matrix4;
/*    */     //   587: pop
/*    */     //   588: getfield Ah : Lf/lpt1;
/*    */     //   591: iconst_0
/*    */     //   592: iconst_1
/*    */     //   593: aconst_null
/*    */     //   594: invokevirtual rd : (IZLf/J3;)Lf/KI0;
/*    */     //   597: pop
/*    */     //   598: getfield Ah : Lf/lpt1;
/*    */     //   601: astore_1
/*    */     //   602: getfield oe0 : Lf/fQ;
/*    */     //   605: aload_1
/*    */     //   606: invokevirtual Com3 : (Ljava/lang/Object;)V
/*    */     //   609: getfield oe0 : Lf/fQ;
/*    */     //   612: aload_0
/*    */     //   613: getfield Ka : Lf/lpt1;
/*    */     //   616: iconst_1
/*    */     //   617: invokevirtual Ct : (Ljava/lang/Object;Z)Z
/*    */     //   620: pop
/*    */     //   621: bipush #25
/*    */     //   623: invokevirtual bz0 : (I)V
/*    */     //   626: goto -> 2060
/*    */     //   629: aload_0
/*    */     //   630: dup
/*    */     //   631: dup
/*    */     //   632: dup2
/*    */     //   633: dup2
/*    */     //   634: getfield Ka : Lf/lpt1;
/*    */     //   637: getfield mh : Lcom/badlogic/gdx/math/Matrix4;
/*    */     //   640: dup
/*    */     //   641: aload_0
/*    */     //   642: getfield tP : Lf/lpt1;
/*    */     //   645: getfield mh : Lcom/badlogic/gdx/math/Matrix4;
/*    */     //   648: astore_1
/*    */     //   649: invokevirtual getClass : ()Ljava/lang/Class;
/*    */     //   652: pop
/*    */     //   653: aload_1
/*    */     //   654: getfield Z0 : [F
/*    */     //   657: invokevirtual Qw : ([F)Lcom/badlogic/gdx/math/Matrix4;
/*    */     //   660: pop
/*    */     //   661: getfield Ka : Lf/lpt1;
/*    */     //   664: new f/fi0
/*    */     //   667: dup
/*    */     //   668: astore_1
/*    */     //   669: aload_0
/*    */     //   670: invokespecial <init> : (Lf/j0;)V
/*    */     //   673: iconst_0
/*    */     //   674: iconst_0
/*    */     //   675: aload_1
/*    */     //   676: invokevirtual rd : (IZLf/J3;)Lf/KI0;
/*    */     //   679: pop
/*    */     //   680: getfield Ka : Lf/lpt1;
/*    */     //   683: astore_1
/*    */     //   684: getfield oe0 : Lf/fQ;
/*    */     //   687: aload_1
/*    */     //   688: invokevirtual Com3 : (Ljava/lang/Object;)V
/*    */     //   691: getfield oe0 : Lf/fQ;
/*    */     //   694: aload_0
/*    */     //   695: getfield tP : Lf/lpt1;
/*    */     //   698: iconst_1
/*    */     //   699: invokevirtual Ct : (Ljava/lang/Object;Z)Z
/*    */     //   702: pop
/*    */     //   703: getfield Na0 : Lf/lpt1;
/*    */     //   706: invokevirtual ro0 : ()Lf/lpt1;
/*    */     //   709: astore_1
/*    */     //   710: getfield Na0 : Lf/lpt1;
/*    */     //   713: invokevirtual ro0 : ()Lf/lpt1;
/*    */     //   716: dup
/*    */     //   717: astore_2
/*    */     //   718: aload_1
/*    */     //   719: aload_2
/*    */     //   720: aload_1
/*    */     //   721: aload_0
/*    */     //   722: dup
/*    */     //   723: getfield oe0 : Lf/fQ;
/*    */     //   726: aload_1
/*    */     //   727: invokevirtual Com3 : (Ljava/lang/Object;)V
/*    */     //   730: getfield oe0 : Lf/fQ;
/*    */     //   733: aload_2
/*    */     //   734: invokevirtual Com3 : (Ljava/lang/Object;)V
/*    */     //   737: getfield mh : Lcom/badlogic/gdx/math/Matrix4;
/*    */     //   740: ldc_w -0.25
/*    */     //   743: fconst_0
/*    */     //   744: fconst_0
/*    */     //   745: invokevirtual g7 : (FFF)Lcom/badlogic/gdx/math/Matrix4;
/*    */     //   748: pop
/*    */     //   749: getfield mh : Lcom/badlogic/gdx/math/Matrix4;
/*    */     //   752: ldc_w 0.25
/*    */     //   755: fconst_0
/*    */     //   756: fconst_0
/*    */     //   757: invokevirtual g7 : (FFF)Lcom/badlogic/gdx/math/Matrix4;
/*    */     //   760: pop
/*    */     //   761: iconst_0
/*    */     //   762: iconst_0
/*    */     //   763: aconst_null
/*    */     //   764: invokevirtual rd : (IZLf/J3;)Lf/KI0;
/*    */     //   767: pop
/*    */     //   768: iconst_0
/*    */     //   769: iconst_0
/*    */     //   770: aconst_null
/*    */     //   771: invokevirtual rd : (IZLf/J3;)Lf/KI0;
/*    */     //   774: pop
/*    */     //   775: goto -> 1707
/*    */     //   778: aload_0
/*    */     //   779: bipush #24
/*    */     //   781: invokevirtual bz0 : (I)V
/*    */     //   784: goto -> 2060
/*    */     //   787: aload_0
/*    */     //   788: getfield tP : Lf/lpt1;
/*    */     //   791: getfield mh : Lcom/badlogic/gdx/math/Matrix4;
/*    */     //   794: getfield Z0 : [F
/*    */     //   797: dup
/*    */     //   798: astore_1
/*    */     //   799: bipush #13
/*    */     //   801: faload
/*    */     //   802: dup
/*    */     //   803: fstore_2
/*    */     //   804: fconst_0
/*    */     //   805: fcmpl
/*    */     //   806: iflt -> 812
/*    */     //   809: goto -> 2060
/*    */     //   812: aload_1
/*    */     //   813: fload_2
/*    */     //   814: ldc_w 0.005
/*    */     //   817: fadd
/*    */     //   818: bipush #13
/*    */     //   820: swap
/*    */     //   821: fastore
/*    */     //   822: goto -> 2060
/*    */     //   825: aload_0
/*    */     //   826: dup
/*    */     //   827: dup
/*    */     //   828: dup2
/*    */     //   829: dup2
/*    */     //   830: dup2
/*    */     //   831: getfield AUx : Lf/lpt1;
/*    */     //   834: astore_1
/*    */     //   835: getfield oe0 : Lf/fQ;
/*    */     //   838: aload_1
/*    */     //   839: invokevirtual Com3 : (Ljava/lang/Object;)V
/*    */     //   842: getfield AUx : Lf/lpt1;
/*    */     //   845: iconst_0
/*    */     //   846: iconst_0
/*    */     //   847: aconst_null
/*    */     //   848: invokevirtual rd : (IZLf/J3;)Lf/KI0;
/*    */     //   851: pop
/*    */     //   852: getfield fa : Lf/lpt1;
/*    */     //   855: new f/prn
/*    */     //   858: dup
/*    */     //   859: astore_1
/*    */     //   860: aload_0
/*    */     //   861: invokespecial <init> : (Lf/j0;)V
/*    */     //   864: iconst_0
/*    */     //   865: iconst_0
/*    */     //   866: aload_1
/*    */     //   867: invokevirtual rd : (IZLf/J3;)Lf/KI0;
/*    */     //   870: pop
/*    */     //   871: getfield oe0 : Lf/fQ;
/*    */     //   874: aload_0
/*    */     //   875: getfield NU : Lf/lpt1;
/*    */     //   878: iconst_1
/*    */     //   879: invokevirtual Ct : (Ljava/lang/Object;Z)Z
/*    */     //   882: pop
/*    */     //   883: getfield tP : Lf/lpt1;
/*    */     //   886: getfield mh : Lcom/badlogic/gdx/math/Matrix4;
/*    */     //   889: dup
/*    */     //   890: aload_0
/*    */     //   891: getfield NU : Lf/lpt1;
/*    */     //   894: getfield mh : Lcom/badlogic/gdx/math/Matrix4;
/*    */     //   897: astore_1
/*    */     //   898: invokevirtual getClass : ()Ljava/lang/Class;
/*    */     //   901: pop
/*    */     //   902: aload_1
/*    */     //   903: getfield Z0 : [F
/*    */     //   906: invokevirtual Qw : ([F)Lcom/badlogic/gdx/math/Matrix4;
/*    */     //   909: pop
/*    */     //   910: getfield tP : Lf/lpt1;
/*    */     //   913: astore_1
/*    */     //   914: getfield oe0 : Lf/fQ;
/*    */     //   917: aload_1
/*    */     //   918: invokevirtual Com3 : (Ljava/lang/Object;)V
/*    */     //   921: getfield tP : Lf/lpt1;
/*    */     //   924: iconst_0
/*    */     //   925: iconst_1
/*    */     //   926: aconst_null
/*    */     //   927: invokevirtual rd : (IZLf/J3;)Lf/KI0;
/*    */     //   930: pop
/*    */     //   931: goto -> 1707
/*    */     //   934: aload_0
/*    */     //   935: getfield NU : Lf/lpt1;
/*    */     //   938: getfield mh : Lcom/badlogic/gdx/math/Matrix4;
/*    */     //   941: getfield Z0 : [F
/*    */     //   944: dup
/*    */     //   945: astore_1
/*    */     //   946: bipush #13
/*    */     //   948: faload
/*    */     //   949: dup
/*    */     //   950: fstore_2
/*    */     //   951: ldc_w -0.8
/*    */     //   954: fcmpl
/*    */     //   955: ifle -> 961
/*    */     //   958: goto -> 2060
/*    */     //   961: aload_1
/*    */     //   962: fload_2
/*    */     //   963: ldc_w 0.005
/*    */     //   966: fadd
/*    */     //   967: bipush #13
/*    */     //   969: swap
/*    */     //   970: fastore
/*    */     //   971: goto -> 2060
/*    */     //   974: aload_0
/*    */     //   975: dup
/*    */     //   976: dup
/*    */     //   977: dup2
/*    */     //   978: getfield NU : Lf/lpt1;
/*    */     //   981: astore_1
/*    */     //   982: getfield oe0 : Lf/fQ;
/*    */     //   985: aload_1
/*    */     //   986: invokevirtual Com3 : (Ljava/lang/Object;)V
/*    */     //   989: getfield NU : Lf/lpt1;
/*    */     //   992: new f/d2
/*    */     //   995: dup
/*    */     //   996: astore_1
/*    */     //   997: aload_0
/*    */     //   998: invokespecial <init> : (Lf/j0;)V
/*    */     //   1001: iconst_0
/*    */     //   1002: iconst_0
/*    */     //   1003: aload_1
/*    */     //   1004: invokevirtual rd : (IZLf/J3;)Lf/KI0;
/*    */     //   1007: pop
/*    */     //   1008: getfield NU : Lf/lpt1;
/*    */     //   1011: getfield mh : Lcom/badlogic/gdx/math/Matrix4;
/*    */     //   1014: fconst_0
/*    */     //   1015: ldc_w -1.2
/*    */     //   1018: fconst_0
/*    */     //   1019: invokevirtual gv0 : (FFF)Lcom/badlogic/gdx/math/Matrix4;
/*    */     //   1022: pop
/*    */     //   1023: getfield o8 : I
/*    */     //   1026: istore_1
/*    */     //   1027: goto -> 1733
/*    */     //   1030: aload_0
/*    */     //   1031: getfield f3 : Lf/So;
/*    */     //   1034: invokevirtual DD : ()Z
/*    */     //   1037: ifeq -> 2060
/*    */     //   1040: aload_0
/*    */     //   1041: dup
/*    */     //   1042: dup
/*    */     //   1043: dup2
/*    */     //   1044: getfield E50 : Lf/uT;
/*    */     //   1047: aload_0
/*    */     //   1048: getfield y7 : [Lf/U70;
/*    */     //   1051: iconst_0
/*    */     //   1052: aaload
/*    */     //   1053: invokevirtual HA0 : ()Lcom/badlogic/gdx/graphics/Texture;
/*    */     //   1056: invokevirtual Bo : (Lcom/badlogic/gdx/graphics/Texture;)V
/*    */     //   1059: getfield q10 : Lf/lpt1;
/*    */     //   1062: astore_1
/*    */     //   1063: getfield oe0 : Lf/fQ;
/*    */     //   1066: aload_1
/*    */     //   1067: invokevirtual Com3 : (Ljava/lang/Object;)V
/*    */     //   1070: getfield q10 : Lf/lpt1;
/*    */     //   1073: new f/Zh
/*    */     //   1076: dup
/*    */     //   1077: astore_1
/*    */     //   1078: aload_0
/*    */     //   1079: invokespecial <init> : (Lf/j0;)V
/*    */     //   1082: iconst_0
/*    */     //   1083: iconst_0
/*    */     //   1084: aload_1
/*    */     //   1085: invokevirtual rd : (IZLf/J3;)Lf/KI0;
/*    */     //   1088: pop
/*    */     //   1089: getfield o8 : I
/*    */     //   1092: istore_1
/*    */     //   1093: goto -> 1733
/*    */     //   1096: aload_0
/*    */     //   1097: dup
/*    */     //   1098: invokestatic k60 : ()Lf/So;
/*    */     //   1101: invokevirtual L5 : ()Lf/So;
/*    */     //   1104: aload_0
/*    */     //   1105: getfield cr : Lf/eo;
/*    */     //   1108: iconst_3
/*    */     //   1109: fconst_1
/*    */     //   1110: invokestatic gq : (Ljava/lang/Object;IF)Lf/Wz0;
/*    */     //   1113: ldc_w -0.75
/*    */     //   1116: invokevirtual a : (F)Lf/Wz0;
/*    */     //   1119: invokevirtual PL : (Lf/Wz0;)Lf/So;
/*    */     //   1122: invokevirtual Kr : ()Lf/So;
/*    */     //   1125: aload_0
/*    */     //   1126: getfield Rv0 : Lf/G30;
/*    */     //   1129: invokevirtual mg : (Lf/G30;)Lf/sh;
/*    */     //   1132: checkcast f/So
/*    */     //   1135: putfield f3 : Lf/So;
/*    */     //   1138: getfield o8 : I
/*    */     //   1141: istore_1
/*    */     //   1142: goto -> 1733
/*    */     //   1145: aload_0
/*    */     //   1146: getfield f3 : Lf/So;
/*    */     //   1149: invokevirtual DD : ()Z
/*    */     //   1152: ifeq -> 2060
/*    */     //   1155: aload_0
/*    */     //   1156: bipush #23
/*    */     //   1158: invokevirtual bz0 : (I)V
/*    */     //   1161: goto -> 2060
/*    */     //   1164: aload_0
/*    */     //   1165: dup
/*    */     //   1166: invokestatic k60 : ()Lf/So;
/*    */     //   1169: invokevirtual L5 : ()Lf/So;
/*    */     //   1172: aload_0
/*    */     //   1173: getfield oD : Lf/qo;
/*    */     //   1176: getfield vF0 : Lcom/badlogic/gdx/graphics/Color;
/*    */     //   1179: iconst_0
/*    */     //   1180: fconst_1
/*    */     //   1181: invokestatic gq : (Ljava/lang/Object;IF)Lf/Wz0;
/*    */     //   1184: iconst_4
/*    */     //   1185: newarray float
/*    */     //   1187: dup
/*    */     //   1188: dup
/*    */     //   1189: dup2
/*    */     //   1190: iconst_0
/*    */     //   1191: ldc_w 0.55
/*    */     //   1194: fastore
/*    */     //   1195: iconst_1
/*    */     //   1196: ldc_w 0.55
/*    */     //   1199: fastore
/*    */     //   1200: iconst_2
/*    */     //   1201: ldc_w 0.55
/*    */     //   1204: fastore
/*    */     //   1205: iconst_3
/*    */     //   1206: fconst_1
/*    */     //   1207: fastore
/*    */     //   1208: invokevirtual qY : ([F)Lf/Wz0;
/*    */     //   1211: invokevirtual PL : (Lf/Wz0;)Lf/So;
/*    */     //   1214: invokevirtual Kr : ()Lf/So;
/*    */     //   1217: aload_0
/*    */     //   1218: getfield Rv0 : Lf/G30;
/*    */     //   1221: invokevirtual mg : (Lf/G30;)Lf/sh;
/*    */     //   1224: checkcast f/So
/*    */     //   1227: putfield f3 : Lf/So;
/*    */     //   1230: getfield o8 : I
/*    */     //   1233: istore_1
/*    */     //   1234: goto -> 1733
/*    */     //   1237: aload_0
/*    */     //   1238: bipush #22
/*    */     //   1240: invokevirtual bz0 : (I)V
/*    */     //   1243: goto -> 2060
/*    */     //   1246: aload_0
/*    */     //   1247: getfield f3 : Lf/So;
/*    */     //   1250: invokevirtual DD : ()Z
/*    */     //   1253: ifeq -> 2060
/*    */     //   1256: aload_0
/*    */     //   1257: dup
/*    */     //   1258: getfield E50 : Lf/uT;
/*    */     //   1261: aload_0
/*    */     //   1262: getfield y7 : [Lf/U70;
/*    */     //   1265: bipush #11
/*    */     //   1267: aaload
/*    */     //   1268: invokevirtual HA0 : ()Lcom/badlogic/gdx/graphics/Texture;
/*    */     //   1271: invokevirtual Bo : (Lcom/badlogic/gdx/graphics/Texture;)V
/*    */     //   1274: bipush #21
/*    */     //   1276: invokevirtual bz0 : (I)V
/*    */     //   1279: goto -> 2060
/*    */     //   1282: aload_0
/*    */     //   1283: dup
/*    */     //   1284: invokestatic k60 : ()Lf/So;
/*    */     //   1287: invokevirtual L5 : ()Lf/So;
/*    */     //   1290: aload_0
/*    */     //   1291: getfield cr : Lf/eo;
/*    */     //   1294: iconst_3
/*    */     //   1295: fconst_1
/*    */     //   1296: invokestatic gq : (Ljava/lang/Object;IF)Lf/Wz0;
/*    */     //   1299: fconst_1
/*    */     //   1300: invokevirtual a : (F)Lf/Wz0;
/*    */     //   1303: invokevirtual PL : (Lf/Wz0;)Lf/So;
/*    */     //   1306: invokevirtual Kr : ()Lf/So;
/*    */     //   1309: aload_0
/*    */     //   1310: getfield Rv0 : Lf/G30;
/*    */     //   1313: invokevirtual mg : (Lf/G30;)Lf/sh;
/*    */     //   1316: checkcast f/So
/*    */     //   1319: putfield f3 : Lf/So;
/*    */     //   1322: getfield o8 : I
/*    */     //   1325: istore_1
/*    */     //   1326: goto -> 1733
/*    */     //   1329: aload_0
/*    */     //   1330: getfield f3 : Lf/So;
/*    */     //   1333: invokevirtual DD : ()Z
/*    */     //   1336: ifeq -> 2060
/*    */     //   1339: aload_0
/*    */     //   1340: bipush #20
/*    */     //   1342: invokevirtual bz0 : (I)V
/*    */     //   1345: goto -> 2060
/*    */     //   1348: aload_0
/*    */     //   1349: dup
/*    */     //   1350: iload_1
/*    */     //   1351: iconst_1
/*    */     //   1352: iadd
/*    */     //   1353: putfield o8 : I
/*    */     //   1356: invokestatic k60 : ()Lf/So;
/*    */     //   1359: invokevirtual L5 : ()Lf/So;
/*    */     //   1362: aload_0
/*    */     //   1363: getfield YL : Lf/Ih0;
/*    */     //   1366: bipush #6
/*    */     //   1368: fconst_1
/*    */     //   1369: invokestatic gq : (Ljava/lang/Object;IF)Lf/Wz0;
/*    */     //   1372: ldc_w -25.0
/*    */     //   1375: invokevirtual a : (F)Lf/Wz0;
/*    */     //   1378: invokevirtual PL : (Lf/Wz0;)Lf/So;
/*    */     //   1381: invokevirtual Kr : ()Lf/So;
/*    */     //   1384: aload_0
/*    */     //   1385: getfield Rv0 : Lf/G30;
/*    */     //   1388: invokevirtual mg : (Lf/G30;)Lf/sh;
/*    */     //   1391: checkcast f/So
/*    */     //   1394: putfield f3 : Lf/So;
/*    */     //   1397: goto -> 2060
/*    */     //   1400: aload_0
/*    */     //   1401: dup
/*    */     //   1402: dup
/*    */     //   1403: getfield oe0 : Lf/fQ;
/*    */     //   1406: aload_0
/*    */     //   1407: getfield sj0 : Lf/lpt1;
/*    */     //   1410: iconst_1
/*    */     //   1411: invokevirtual Ct : (Ljava/lang/Object;Z)Z
/*    */     //   1414: pop
/*    */     //   1415: getfield oe0 : Lf/fQ;
/*    */     //   1418: aload_0
/*    */     //   1419: getfield Jq : Lf/lpt1;
/*    */     //   1422: iconst_1
/*    */     //   1423: invokevirtual Ct : (Ljava/lang/Object;Z)Z
/*    */     //   1426: pop
/*    */     //   1427: getfield o8 : I
/*    */     //   1430: istore_1
/*    */     //   1431: goto -> 1733
/*    */     //   1434: aload_0
/*    */     //   1435: bipush #19
/*    */     //   1437: invokevirtual bz0 : (I)V
/*    */     //   1440: goto -> 2060
/*    */     //   1443: aload_0
/*    */     //   1444: bipush #18
/*    */     //   1446: invokevirtual bz0 : (I)V
/*    */     //   1449: goto -> 2060
/*    */     //   1452: aload_0
/*    */     //   1453: getfield sj0 : Lf/lpt1;
/*    */     //   1456: ifnonnull -> 1589
/*    */     //   1459: aload_0
/*    */     //   1460: dup
/*    */     //   1461: dup2
/*    */     //   1462: dup2
/*    */     //   1463: dup2
/*    */     //   1464: dup2
/*    */     //   1465: dup2
/*    */     //   1466: dup2
/*    */     //   1467: getfield Cw : Lf/lpt1;
/*    */     //   1470: invokevirtual ro0 : ()Lf/lpt1;
/*    */     //   1473: putfield sj0 : Lf/lpt1;
/*    */     //   1476: getfield Cw : Lf/lpt1;
/*    */     //   1479: invokevirtual ro0 : ()Lf/lpt1;
/*    */     //   1482: putfield Jq : Lf/lpt1;
/*    */     //   1485: getfield sj0 : Lf/lpt1;
/*    */     //   1488: astore_1
/*    */     //   1489: getfield oe0 : Lf/fQ;
/*    */     //   1492: aload_1
/*    */     //   1493: invokevirtual Com3 : (Ljava/lang/Object;)V
/*    */     //   1496: getfield Jq : Lf/lpt1;
/*    */     //   1499: astore_1
/*    */     //   1500: getfield oe0 : Lf/fQ;
/*    */     //   1503: aload_1
/*    */     //   1504: invokevirtual Com3 : (Ljava/lang/Object;)V
/*    */     //   1507: getfield sj0 : Lf/lpt1;
/*    */     //   1510: getfield mh : Lcom/badlogic/gdx/math/Matrix4;
/*    */     //   1513: ldc_w -0.75
/*    */     //   1516: ldc_w 0.25
/*    */     //   1519: ldc_w -0.75
/*    */     //   1522: invokevirtual g7 : (FFF)Lcom/badlogic/gdx/math/Matrix4;
/*    */     //   1525: pop
/*    */     //   1526: getfield Jq : Lf/lpt1;
/*    */     //   1529: getfield mh : Lcom/badlogic/gdx/math/Matrix4;
/*    */     //   1532: ldc_w 0.75
/*    */     //   1535: ldc_w 0.25
/*    */     //   1538: ldc_w -0.75
/*    */     //   1541: invokevirtual g7 : (FFF)Lcom/badlogic/gdx/math/Matrix4;
/*    */     //   1544: pop
/*    */     //   1545: getfield sj0 : Lf/lpt1;
/*    */     //   1548: getfield mh : Lcom/badlogic/gdx/math/Matrix4;
/*    */     //   1551: ldc_w 0.01
/*    */     //   1554: invokevirtual implements : (F)V
/*    */     //   1557: getfield Jq : Lf/lpt1;
/*    */     //   1560: getfield mh : Lcom/badlogic/gdx/math/Matrix4;
/*    */     //   1563: ldc_w 0.01
/*    */     //   1566: invokevirtual implements : (F)V
/*    */     //   1569: getfield sj0 : Lf/lpt1;
/*    */     //   1572: iconst_0
/*    */     //   1573: iconst_1
/*    */     //   1574: aconst_null
/*    */     //   1575: invokevirtual rd : (IZLf/J3;)Lf/KI0;
/*    */     //   1578: pop
/*    */     //   1579: getfield Jq : Lf/lpt1;
/*    */     //   1582: iconst_0
/*    */     //   1583: iconst_1
/*    */     //   1584: aconst_null
/*    */     //   1585: invokevirtual rd : (IZLf/J3;)Lf/KI0;
/*    */     //   1588: pop
/*    */     //   1589: aload_0
/*    */     //   1590: getfield sj0 : Lf/lpt1;
/*    */     //   1593: getfield mh : Lcom/badlogic/gdx/math/Matrix4;
/*    */     //   1596: getfield Z0 : [F
/*    */     //   1599: dup
/*    */     //   1600: astore_1
/*    */     //   1601: iconst_0
/*    */     //   1602: faload
/*    */     //   1603: dup
/*    */     //   1604: fstore_2
/*    */     //   1605: ldc_w 0.6
/*    */     //   1608: fcmpg
/*    */     //   1609: ifge -> 1707
/*    */     //   1612: aload_0
/*    */     //   1613: aload_1
/*    */     //   1614: dup
/*    */     //   1615: dup
/*    */     //   1616: dup2
/*    */     //   1617: fload_2
/*    */     //   1618: ldc_w 0.0075
/*    */     //   1621: fadd
/*    */     //   1622: iconst_0
/*    */     //   1623: swap
/*    */     //   1624: fastore
/*    */     //   1625: iconst_5
/*    */     //   1626: faload
/*    */     //   1627: ldc_w 0.0075
/*    */     //   1630: fadd
/*    */     //   1631: iconst_5
/*    */     //   1632: swap
/*    */     //   1633: fastore
/*    */     //   1634: bipush #10
/*    */     //   1636: faload
/*    */     //   1637: ldc_w 0.0075
/*    */     //   1640: fadd
/*    */     //   1641: bipush #10
/*    */     //   1643: swap
/*    */     //   1644: fastore
/*    */     //   1645: getfield Jq : Lf/lpt1;
/*    */     //   1648: getfield mh : Lcom/badlogic/gdx/math/Matrix4;
/*    */     //   1651: getfield Z0 : [F
/*    */     //   1654: dup
/*    */     //   1655: dup2
/*    */     //   1656: dup2
/*    */     //   1657: iconst_0
/*    */     //   1658: faload
/*    */     //   1659: ldc_w 0.0075
/*    */     //   1662: fadd
/*    */     //   1663: iconst_0
/*    */     //   1664: swap
/*    */     //   1665: fastore
/*    */     //   1666: iconst_5
/*    */     //   1667: faload
/*    */     //   1668: ldc_w 0.0075
/*    */     //   1671: fadd
/*    */     //   1672: iconst_5
/*    */     //   1673: swap
/*    */     //   1674: fastore
/*    */     //   1675: bipush #10
/*    */     //   1677: faload
/*    */     //   1678: ldc_w 0.0075
/*    */     //   1681: fadd
/*    */     //   1682: bipush #10
/*    */     //   1684: swap
/*    */     //   1685: fastore
/*    */     //   1686: goto -> 2060
/*    */     //   1689: getstatic f/km.wI0 : Lf/Pw;
/*    */     //   1692: getfield iE0 : Lf/dw;
/*    */     //   1695: dup
/*    */     //   1696: astore_1
/*    */     //   1697: ifnull -> 1707
/*    */     //   1700: aload_1
/*    */     //   1701: invokevirtual Dm0 : ()Z
/*    */     //   1704: ifeq -> 2060
/*    */     //   1707: aload_0
/*    */     //   1708: getfield o8 : I
/*    */     //   1711: istore_1
/*    */     //   1712: goto -> 1733
/*    */     //   1715: aload_0
/*    */     //   1716: getstatic f/km.wI0 : Lf/Pw;
/*    */     //   1719: new f/cb0
/*    */     //   1722: dup
/*    */     //   1723: invokespecial <init> : ()V
/*    */     //   1726: putfield iE0 : Lf/dw;
/*    */     //   1729: getfield o8 : I
/*    */     //   1732: istore_1
/*    */     //   1733: aload_0
/*    */     //   1734: iload_1
/*    */     //   1735: iconst_1
/*    */     //   1736: iadd
/*    */     //   1737: putfield o8 : I
/*    */     //   1740: goto -> 2060
/*    */     //   1743: aload_0
/*    */     //   1744: getfield xf : Lf/lpt1;
/*    */     //   1747: getfield mh : Lcom/badlogic/gdx/math/Matrix4;
/*    */     //   1750: getfield Z0 : [F
/*    */     //   1753: iconst_0
/*    */     //   1754: faload
/*    */     //   1755: fconst_1
/*    */     //   1756: invokestatic JC0 : (FF)Z
/*    */     //   1759: ifeq -> 1772
/*    */     //   1762: aload_0
/*    */     //   1763: dup
/*    */     //   1764: getfield o8 : I
/*    */     //   1767: iconst_1
/*    */     //   1768: iadd
/*    */     //   1769: putfield o8 : I
/*    */     //   1772: aload_0
/*    */     //   1773: dup
/*    */     //   1774: getfield xf : Lf/lpt1;
/*    */     //   1777: getfield mh : Lcom/badlogic/gdx/math/Matrix4;
/*    */     //   1780: getfield Z0 : [F
/*    */     //   1783: dup
/*    */     //   1784: iconst_0
/*    */     //   1785: faload
/*    */     //   1786: ldc 0.05
/*    */     //   1788: fadd
/*    */     //   1789: fconst_1
/*    */     //   1790: swap
/*    */     //   1791: invokestatic min : (FF)F
/*    */     //   1794: iconst_0
/*    */     //   1795: swap
/*    */     //   1796: fastore
/*    */     //   1797: getfield x20 : Lf/lpt1;
/*    */     //   1800: getfield mh : Lcom/badlogic/gdx/math/Matrix4;
/*    */     //   1803: getfield Z0 : [F
/*    */     //   1806: dup
/*    */     //   1807: iconst_0
/*    */     //   1808: faload
/*    */     //   1809: ldc 0.05
/*    */     //   1811: fadd
/*    */     //   1812: fconst_1
/*    */     //   1813: swap
/*    */     //   1814: invokestatic min : (FF)F
/*    */     //   1817: iconst_0
/*    */     //   1818: swap
/*    */     //   1819: fastore
/*    */     //   1820: goto -> 2060
/*    */     //   1823: aload_0
/*    */     //   1824: dup
/*    */     //   1825: dup2
/*    */     //   1826: dup2
/*    */     //   1827: dup2
/*    */     //   1828: getfield xf : Lf/lpt1;
/*    */     //   1831: astore_1
/*    */     //   1832: getfield oe0 : Lf/fQ;
/*    */     //   1835: aload_1
/*    */     //   1836: invokevirtual Com3 : (Ljava/lang/Object;)V
/*    */     //   1839: getfield x20 : Lf/lpt1;
/*    */     //   1842: astore_1
/*    */     //   1843: getfield oe0 : Lf/fQ;
/*    */     //   1846: aload_1
/*    */     //   1847: invokevirtual Com3 : (Ljava/lang/Object;)V
/*    */     //   1850: getfield o8 : I
/*    */     //   1853: iconst_1
/*    */     //   1854: iadd
/*    */     //   1855: putfield o8 : I
/*    */     //   1858: getfield xf : Lf/lpt1;
/*    */     //   1861: iconst_0
/*    */     //   1862: iconst_1
/*    */     //   1863: aconst_null
/*    */     //   1864: invokevirtual rd : (IZLf/J3;)Lf/KI0;
/*    */     //   1867: pop
/*    */     //   1868: getfield x20 : Lf/lpt1;
/*    */     //   1871: iconst_0
/*    */     //   1872: iconst_1
/*    */     //   1873: aconst_null
/*    */     //   1874: invokevirtual rd : (IZLf/J3;)Lf/KI0;
/*    */     //   1877: pop
/*    */     //   1878: goto -> 2060
/*    */     //   1881: aload_0
/*    */     //   1882: dup
/*    */     //   1883: dup
/*    */     //   1884: dup2
/*    */     //   1885: dup2
/*    */     //   1886: dup2
/*    */     //   1887: iload_1
/*    */     //   1888: iconst_1
/*    */     //   1889: iadd
/*    */     //   1890: putfield o8 : I
/*    */     //   1893: getfield j70 : Lf/lpt1;
/*    */     //   1896: invokevirtual ro0 : ()Lf/lpt1;
/*    */     //   1899: astore_1
/*    */     //   1900: getfield j70 : Lf/lpt1;
/*    */     //   1903: invokevirtual ro0 : ()Lf/lpt1;
/*    */     //   1906: dup
/*    */     //   1907: astore_2
/*    */     //   1908: aload_1
/*    */     //   1909: aload_2
/*    */     //   1910: aload_1
/*    */     //   1911: getfield mh : Lcom/badlogic/gdx/math/Matrix4;
/*    */     //   1914: ldc_w -0.75
/*    */     //   1917: ldc 0.15
/*    */     //   1919: ldc_w -0.75
/*    */     //   1922: invokevirtual g7 : (FFF)Lcom/badlogic/gdx/math/Matrix4;
/*    */     //   1925: pop
/*    */     //   1926: getfield mh : Lcom/badlogic/gdx/math/Matrix4;
/*    */     //   1929: ldc_w 0.75
/*    */     //   1932: ldc 0.15
/*    */     //   1934: ldc_w -0.75
/*    */     //   1937: invokevirtual g7 : (FFF)Lcom/badlogic/gdx/math/Matrix4;
/*    */     //   1940: pop
/*    */     //   1941: iconst_0
/*    */     //   1942: iconst_0
/*    */     //   1943: aconst_null
/*    */     //   1944: invokevirtual rd : (IZLf/J3;)Lf/KI0;
/*    */     //   1947: pop
/*    */     //   1948: new f/dn
/*    */     //   1951: dup
/*    */     //   1952: astore_3
/*    */     //   1953: aload_0
/*    */     //   1954: aload_1
/*    */     //   1955: aload_2
/*    */     //   1956: invokespecial <init> : (Lf/j0;Lf/lpt1;Lf/lpt1;)V
/*    */     //   1959: iconst_0
/*    */     //   1960: iconst_0
/*    */     //   1961: aload_3
/*    */     //   1962: invokevirtual rd : (IZLf/J3;)Lf/KI0;
/*    */     //   1965: pop
/*    */     //   1966: getfield oe0 : Lf/fQ;
/*    */     //   1969: aload_1
/*    */     //   1970: invokevirtual Com3 : (Ljava/lang/Object;)V
/*    */     //   1973: getfield oe0 : Lf/fQ;
/*    */     //   1976: aload_2
/*    */     //   1977: invokevirtual Com3 : (Ljava/lang/Object;)V
/*    */     //   1980: getfield xf : Lf/lpt1;
/*    */     //   1983: getfield mh : Lcom/badlogic/gdx/math/Matrix4;
/*    */     //   1986: ldc_w -0.75
/*    */     //   1989: ldc 0.15
/*    */     //   1991: ldc_w -0.75
/*    */     //   1994: invokevirtual g7 : (FFF)Lcom/badlogic/gdx/math/Matrix4;
/*    */     //   1997: pop
/*    */     //   1998: getfield x20 : Lf/lpt1;
/*    */     //   2001: getfield mh : Lcom/badlogic/gdx/math/Matrix4;
/*    */     //   2004: ldc_w 0.75
/*    */     //   2007: ldc 0.15
/*    */     //   2009: ldc_w -0.75
/*    */     //   2012: invokevirtual g7 : (FFF)Lcom/badlogic/gdx/math/Matrix4;
/*    */     //   2015: pop
/*    */     //   2016: getfield xf : Lf/lpt1;
/*    */     //   2019: getfield mh : Lcom/badlogic/gdx/math/Matrix4;
/*    */     //   2022: getfield Z0 : [F
/*    */     //   2025: iconst_0
/*    */     //   2026: ldc 0.05
/*    */     //   2028: fastore
/*    */     //   2029: getfield x20 : Lf/lpt1;
/*    */     //   2032: getfield mh : Lcom/badlogic/gdx/math/Matrix4;
/*    */     //   2035: getfield Z0 : [F
/*    */     //   2038: iconst_0
/*    */     //   2039: ldc 0.05
/*    */     //   2041: fastore
/*    */     //   2042: goto -> 2060
/*    */     //   2045: aload_0
/*    */     //   2046: bipush #16
/*    */     //   2048: invokevirtual bz0 : (I)V
/*    */     //   2051: goto -> 2060
/*    */     //   2054: aload_0
/*    */     //   2055: bipush #14
/*    */     //   2057: invokevirtual bz0 : (I)V
/*    */     //   2060: aload_0
/*    */     //   2061: dup
/*    */     //   2062: dup
/*    */     //   2063: getfield pK : Lf/K70;
/*    */     //   2066: aload_0
/*    */     //   2067: dup
/*    */     //   2068: getfield oe0 : Lf/fQ;
/*    */     //   2071: astore_1
/*    */     //   2072: getfield lPt8 : Lf/fo0;
/*    */     //   2075: aload_1
/*    */     //   2076: swap
/*    */     //   2077: invokevirtual QJ0 : (Lf/fQ;Lf/fo0;)V
/*    */     //   2080: getfield jE : Lf/eo;
/*    */     //   2083: fconst_0
/*    */     //   2084: ldc_w 0.5
/*    */     //   2087: ldc 3.0
/*    */     //   2089: invokevirtual TG0 : (FFF)Lf/eo;
/*    */     //   2092: pop
/*    */     //   2093: getfield Vw0 : Lf/eo;
/*    */     //   2096: fconst_0
/*    */     //   2097: ldc_w 1.5
/*    */     //   2100: ldc 4.0
/*    */     //   2102: invokevirtual TG0 : (FFF)Lf/eo;
/*    */     //   2105: pop
/*    */     //   2106: iconst_1
/*    */     //   2107: istore_1
/*    */     //   2108: getstatic f/km.a3 : Lf/vh0;
/*    */     //   2111: getfield Ct : Lf/Jo;
/*    */     //   2114: dup
/*    */     //   2115: astore_2
/*    */     //   2116: invokevirtual UG : ()Z
/*    */     //   2119: ifne -> 2145
/*    */     //   2122: aload_2
/*    */     //   2123: invokevirtual VO : ()Z
/*    */     //   2126: ifeq -> 2132
/*    */     //   2129: goto -> 2145
/*    */     //   2132: aload_2
/*    */     //   2133: invokevirtual XC : ()Z
/*    */     //   2136: ifeq -> 2148
/*    */     //   2139: bipush #-17
/*    */     //   2141: istore_1
/*    */     //   2142: goto -> 2148
/*    */     //   2145: bipush #-26
/*    */     //   2147: istore_1
/*    */     //   2148: aload_0
/*    */     //   2149: dup
/*    */     //   2150: dup2
/*    */     //   2151: getfield y7 : [Lf/U70;
/*    */     //   2154: dup
/*    */     //   2155: iconst_0
/*    */     //   2156: aaload
/*    */     //   2157: getstatic f/zm0.u20 : J
/*    */     //   2160: dup2
/*    */     //   2161: lstore_2
/*    */     //   2162: putfield mk : J
/*    */     //   2165: bipush #11
/*    */     //   2167: aaload
/*    */     //   2168: lload_2
/*    */     //   2169: putfield mk : J
/*    */     //   2172: getstatic f/km.q00 : Lf/Hk;
/*    */     //   2175: aload_0
/*    */     //   2176: dup
/*    */     //   2177: iload_1
/*    */     //   2178: aload_0
/*    */     //   2179: dup
/*    */     //   2180: dup
/*    */     //   2181: getfield pK : Lf/K70;
/*    */     //   2184: astore_1
/*    */     //   2185: getfield lPt8 : Lf/fo0;
/*    */     //   2188: astore_2
/*    */     //   2189: getstatic f/km.a3 : Lf/vh0;
/*    */     //   2192: getfield Ct : Lf/Jo;
/*    */     //   2195: astore_3
/*    */     //   2196: getfield Nd0 : [[Lf/uT;
/*    */     //   2199: astore #4
/*    */     //   2201: i2b
/*    */     //   2202: istore #5
/*    */     //   2204: getfield jE : Lf/eo;
/*    */     //   2207: astore #6
/*    */     //   2209: getfield Vw0 : Lf/eo;
/*    */     //   2212: astore #7
/*    */     //   2214: aload_1
/*    */     //   2215: aload_2
/*    */     //   2216: aload_0
/*    */     //   2217: getfield YL : Lf/Ih0;
/*    */     //   2220: getfield nj0 : Lf/eo;
/*    */     //   2223: astore_1
/*    */     //   2224: aload_3
/*    */     //   2225: aconst_null
/*    */     //   2226: aload #4
/*    */     //   2228: iload #5
/*    */     //   2230: aload #6
/*    */     //   2232: aload #7
/*    */     //   2234: aload_1
/*    */     //   2235: iconst_0
/*    */     //   2236: iconst_0
/*    */     //   2237: invokevirtual qi0 : (Lf/K70;Lf/fo0;Lf/Jo;Lf/uT;[[Lf/uT;BLf/eo;Lf/eo;Lf/eo;ZZ)Lf/uT;
/*    */     //   2240: pop
/*    */     //   2241: getfield E50 : Lf/uT;
/*    */     //   2244: aload_0
/*    */     //   2245: getfield He0 : Lf/eo;
/*    */     //   2248: invokevirtual WI0 : (Lf/eo;)V
/*    */     //   2251: getfield E50 : Lf/uT;
/*    */     //   2254: aload_0
/*    */     //   2255: getfield bQ : Lf/eo;
/*    */     //   2258: aload_0
/*    */     //   2259: getfield YL : Lf/Ih0;
/*    */     //   2262: getfield nj0 : Lf/eo;
/*    */     //   2265: invokevirtual si : (Lf/eo;Lf/eo;)V
/*    */     //   2268: getfield pK : Lf/K70;
/*    */     //   2271: aload_0
/*    */     //   2272: dup
/*    */     //   2273: getfield E50 : Lf/uT;
/*    */     //   2276: astore_0
/*    */     //   2277: getfield lPt8 : Lf/fo0;
/*    */     //   2280: aload_0
/*    */     //   2281: swap
/*    */     //   2282: invokevirtual q10 : (Lf/tk;Lf/fo0;)V
/*    */     //   2285: return
/*    */     // Line number table:
/*    */     //   Java source line number -> byte code offset
/*    */     //   #1	-> 0
/*    */     //   #2	-> 18
/*    */     //   #3	-> 22
/*    */     //   #4	-> 56
/*    */     //   #5	-> 63
/*    */     //   #6	-> 92
/*    */     //   #7	-> 330
/*    */     //   #8	-> 342
/*    */     //   #9	-> 347
/*    */     //   #10	-> 441
/*    */     //   #11	-> 448
/*    */     //   #12	-> 471
/*    */     //   #13	-> 478
/*    */     //   #14	-> 505
/*    */     //   #15	-> 521
/*    */     //   #16	-> 535
/*    */     //   #17	-> 561
/*    */     //   #18	-> 581
/*    */     //   #19	-> 588
/*    */     //   #20	-> 594
/*    */     //   #21	-> 598
/*    */     //   #22	-> 602
/*    */     //   #23	-> 609
/*    */     //   #24	-> 654
/*    */     //   #25	-> 661
/*    */     //   #26	-> 684
/*    */     //   #27	-> 691
/*    */     //   #28	-> 723
/*    */     //   #29	-> 737
/*    */     //   #30	-> 764
/*    */     //   #31	-> 781
/*    */     //   #32	-> 835
/*    */     //   #33	-> 842
/*    */     //   #34	-> 848
/*    */     //   #35	-> 852
/*    */     //   #36	-> 903
/*    */     //   #37	-> 910
/*    */     //   #38	-> 914
/*    */     //   #39	-> 921
/*    */     //   #40	-> 927
/*    */     //   #41	-> 935
/*    */     //   #42	-> 982
/*    */     //   #43	-> 989
/*    */     //   #44	-> 1063
/*    */     //   #45	-> 1070
/*    */     //   #46	-> 1489
/*    */     //   #47	-> 1496
/*    */     //   #48	-> 1500
/*    */     //   #49	-> 1507
/*    */     //   #50	-> 1575
/*    */     //   #51	-> 1579
/*    */     //   #52	-> 1585
/*    */     //   #53	-> 1590
/*    */     //   #54	-> 1692
/*    */     //   #55	-> 1701
/*    */     //   #56	-> 1726
/*    */     //   #57	-> 1729
/*    */     //   #58	-> 1832
/*    */     //   #59	-> 1839
/*    */     //   #60	-> 1843
/*    */     //   #61	-> 1850
/*    */     //   #62	-> 1864
/*    */     //   #63	-> 1868
/*    */     //   #64	-> 1874
/*    */     //   #65	-> 1890
/*    */     //   #66	-> 1944
/*    */     //   #67	-> 1948
/*    */     //   #68	-> 1966
/*    */     //   #69	-> 1980
/*    */     //   #70	-> 2063
/*    */     //   #71	-> 2111
/*    */     //   #72	-> 2116
/*    */     //   #73	-> 2157
/*    */     //   #74	-> 2162
/*    */     //   #75	-> 2167
/*    */     //   #76	-> 2169
/*    */     //   #77	-> 2172
/*    */     //   #78	-> 2192
/*    */     //   #79	-> 2196
/*    */   }
/*    */   
/*    */   public final boolean ng() {
/*    */     return (this.o8 == 46 && this.f3.DD());
/*    */   }
/*    */   
/*    */   public final void bz0(int paramInt) {
/*    */     String str2 = "";
/*    */     Jo jo;
/*    */     if ((jo = km.a3.Ct) != null)
/*    */       str2 = jo.ED0; 
/*    */     String[] arrayOfString;
/*    */     (arrayOfString = new String[1])[0] = str2;
/*    */     String str1 = Ml0.tG((byte)3, F40.wI, 234, paramInt, arrayOfString);
/*    */     Aq aq = Aq.ur;
/*    */     this(this);
/*    */     kg kg;
/*    */     byte b = -2;
/*    */     km.kH0.getClass();
/*    */     km.kH0.wV(new zB0(str1, aq, b, kg));
/*    */     this.o8++;
/*    */   } }


/* Location:              /Users/vnnsnnt/Documents/Codespace/JavaWorkspace/RedTrainer/src/main/java/org/trainer/client/PokeMMO.jar!/f/j0.class
 * Java compiler version: 8 (52.0)
 * JD-Core Version:       1.1.3
 */