/*   */ package f;public abstract class JB0 { public static Rc CE0 = JB0::Jd0; public static Rc B4 = JB0::jA0; public static Rc sp0 = JB0::op0; public static B3 qk0(of paramof) { // Byte code:
/*   */     //   0: new f/B3
/*   */     //   3: dup
/*   */     //   4: astore_1
/*   */     //   5: invokespecial <init> : ()V
/*   */     //   8: getstatic f/km.u4 : Lf/R8;
/*   */     //   11: getfield E50 : Lf/Oc0;
/*   */     //   14: invokevirtual iterator : ()Ljava/util/Iterator;
/*   */     //   17: astore_2
/*   */     //   18: aload_2
/*   */     //   19: invokeinterface hasNext : ()Z
/*   */     //   24: ifeq -> 84
/*   */     //   27: aload_1
/*   */     //   28: aload_2
/*   */     //   29: invokeinterface next : ()Ljava/lang/Object;
/*   */     //   34: checkcast f/CD0
/*   */     //   37: astore_3
/*   */     //   38: new f/LA0
/*   */     //   41: dup
/*   */     //   42: astore #4
/*   */     //   44: aload_0
/*   */     //   45: aload_3
/*   */     //   46: dup
/*   */     //   47: getfield hY : Lf/FV;
/*   */     //   50: dup
/*   */     //   51: astore_3
/*   */     //   52: getfield Pb : Ljava/lang/String;
/*   */     //   55: astore #5
/*   */     //   57: <illegal opcode> run : (Lf/of;Lf/CD0;)Ljava/lang/Runnable;
/*   */     //   62: astore #6
/*   */     //   64: aload #5
/*   */     //   66: aload_3
/*   */     //   67: aload #6
/*   */     //   69: invokespecial <init> : (Ljava/lang/String;Lf/FV;Ljava/lang/Runnable;)V
/*   */     //   72: getfield aV : Ljava/util/ArrayList;
/*   */     //   75: aload #4
/*   */     //   77: invokevirtual add : (Ljava/lang/Object;)Z
/*   */     //   80: pop
/*   */     //   81: goto -> 18
/*   */     //   84: getstatic f/km.u4 : Lf/R8;
/*   */     //   87: getfield Wn0 : Lf/mG;
/*   */     //   90: dup
/*   */     //   91: astore_2
/*   */     //   92: ifnull -> 195
/*   */     //   95: aload_2
/*   */     //   96: invokevirtual DQ : ()[Lf/ON;
/*   */     //   99: dup
/*   */     //   100: astore_2
/*   */     //   101: arraylength
/*   */     //   102: istore_3
/*   */     //   103: iconst_0
/*   */     //   104: istore #4
/*   */     //   106: iload #4
/*   */     //   108: iload_3
/*   */     //   109: if_icmpge -> 195
/*   */     //   112: aload_2
/*   */     //   113: iload #4
/*   */     //   115: aaload
/*   */     //   116: dup
/*   */     //   117: astore #5
/*   */     //   119: getstatic f/km.u4 : Lf/R8;
/*   */     //   122: getfield E50 : Lf/Oc0;
/*   */     //   125: astore #6
/*   */     //   127: getfield Y90 : I
/*   */     //   130: aload #6
/*   */     //   132: getfield tl0 : Lf/Ut0;
/*   */     //   135: swap
/*   */     //   136: invokevirtual return : (I)Z
/*   */     //   139: ifne -> 189
/*   */     //   142: aload_1
/*   */     //   143: new f/LA0
/*   */     //   146: dup
/*   */     //   147: astore #6
/*   */     //   149: aload_0
/*   */     //   150: aload #5
/*   */     //   152: dup
/*   */     //   153: getfield cy0 : Lf/FV;
/*   */     //   156: dup
/*   */     //   157: astore #5
/*   */     //   159: getfield Pb : Ljava/lang/String;
/*   */     //   162: astore #7
/*   */     //   164: <illegal opcode> run : (Lf/of;Lf/ON;)Ljava/lang/Runnable;
/*   */     //   169: astore #8
/*   */     //   171: aload #7
/*   */     //   173: aload #5
/*   */     //   175: aload #8
/*   */     //   177: invokespecial <init> : (Ljava/lang/String;Lf/FV;Ljava/lang/Runnable;)V
/*   */     //   180: getfield aV : Ljava/util/ArrayList;
/*   */     //   183: aload #6
/*   */     //   185: invokevirtual add : (Ljava/lang/Object;)Z
/*   */     //   188: pop
/*   */     //   189: iinc #4, 1
/*   */     //   192: goto -> 106
/*   */     //   195: aload_1
/*   */     //   196: getfield aV : Ljava/util/ArrayList;
/*   */     //   199: invokevirtual size : ()I
/*   */     //   202: ifne -> 224
/*   */     //   205: aload_1
/*   */     //   206: new f/Hk0
/*   */     //   209: dup
/*   */     //   210: astore_0
/*   */     //   211: ldc '--'
/*   */     //   213: invokespecial <init> : (Ljava/lang/String;)V
/*   */     //   216: getfield aV : Ljava/util/ArrayList;
/*   */     //   219: aload_0
/*   */     //   220: invokevirtual add : (Ljava/lang/Object;)Z
/*   */     //   223: pop
/*   */     //   224: aload_1
/*   */     //   225: areturn
/*   */     // Line number table:
/*   */     //   Java source line number -> byte code offset
/*   */     //   #1	-> 11
/*   */     //   #2	-> 14
/*   */     //   #3	-> 47
/*   */     //   #4	-> 52
/*   */     //   #5	-> 57
/*   */     //   #6	-> 72
/*   */     //   #7	-> 84
/*   */     //   #8	-> 87
/*   */     //   #9	-> 96
/*   */     //   #10	-> 122
/*   */     //   #11	-> 127
/*   */     //   #12	-> 132
/*   */     //   #13	-> 136
/*   */     //   #14	-> 143
/*   */     //   #15	-> 153
/*   */     //   #16	-> 159
/*   */     //   #17	-> 164
/*   */     //   #18	-> 180
/*   */     //   #19	-> 196
/*   */     //   #20	-> 206
/* 1 */     //   #21	-> 216 } public static void Oh0(Qv0 paramQv0, j40 paramj40) { Uc0 uc0; if (paramj40 != null)
/*   */     
/* 3 */     { uc0 = km.u4.s40(paramj40.Zs.COm1); } else { uc0 = km.u4.s40(aq0.ne0); }  if (paramQv0
/* 4 */       .y1()) { paramQv0.zf(paramj40); } else { if (uc0 != null) { if (km.MR == null) km.u4
/*   */ 
/*   */             
/* 7 */             .lO(new Qv0(uc0, paramj40.Zs.Tl0, false), paramQv0);  return; }  throw new IllegalArgumentException(); }  } public static B3 Ww(O0 paramO0, Rc paramRc, boolean paramBoolean) { return hy(paramO0::Tm0, paramRc, paramBoolean); } public static B3 hy(Oq0 paramOq0, Rc paramRc, boolean paramBoolean) { // Byte code:
/*   */     //   0: new f/B3
/*   */     //   3: dup
/*   */     //   4: astore_3
/*   */     //   5: getstatic f/Hu0.M8 : Lf/Hu0;
/*   */     //   8: getfield jC0 : I
/*   */     //   11: invokestatic OH0 : (I)Ljava/lang/String;
/*   */     //   14: invokespecial <init> : (Ljava/lang/String;)V
/*   */     //   17: getstatic f/Hu0.pJ : [Lf/Hu0;
/*   */     //   20: dup
/*   */     //   21: astore #4
/*   */     //   23: arraylength
/*   */     //   24: istore #5
/*   */     //   26: iconst_0
/*   */     //   27: istore #6
/*   */     //   29: iload #6
/*   */     //   31: iload #5
/*   */     //   33: if_icmpge -> 466
/*   */     //   36: aload #4
/*   */     //   38: iload #6
/*   */     //   40: aaload
/*   */     //   41: dup
/*   */     //   42: astore #7
/*   */     //   44: invokevirtual ordinal : ()I
/*   */     //   47: tableswitch default -> 92, 0 -> 148, 1 -> 140, 2 -> 132, 3 -> 124, 4 -> 116, 5 -> 92, 6 -> 108, 7 -> 100
/*   */     //   92: sipush #5459
/*   */     //   95: istore #8
/*   */     //   97: goto -> 153
/*   */     //   100: sipush #5057
/*   */     //   103: istore #8
/*   */     //   105: goto -> 153
/*   */     //   108: sipush #5017
/*   */     //   111: istore #8
/*   */     //   113: goto -> 153
/*   */     //   116: sipush #5155
/*   */     //   119: istore #8
/*   */     //   121: goto -> 153
/*   */     //   124: sipush #5252
/*   */     //   127: istore #8
/*   */     //   129: goto -> 153
/*   */     //   132: sipush #5004
/*   */     //   135: istore #8
/*   */     //   137: goto -> 153
/*   */     //   140: sipush #5476
/*   */     //   143: istore #8
/*   */     //   145: goto -> 153
/*   */     //   148: sipush #5436
/*   */     //   151: istore #8
/*   */     //   153: getstatic f/wm0.y0 : Lf/wm0;
/*   */     //   156: iload #8
/*   */     //   158: iconst_0
/*   */     //   159: invokevirtual SJ0 : (SZ)Lf/U70;
/*   */     //   162: astore #8
/*   */     //   164: new f/aP
/*   */     //   167: dup
/*   */     //   168: astore #9
/*   */     //   170: aload #7
/*   */     //   172: getfield jC0 : I
/*   */     //   175: invokestatic OH0 : (I)Ljava/lang/String;
/*   */     //   178: aload #8
/*   */     //   180: invokespecial <init> : (Ljava/lang/String;Lf/U70;)V
/*   */     //   183: getstatic f/km.a3 : Lf/vh0;
/*   */     //   186: getfield eA : B
/*   */     //   189: istore #8
/*   */     //   191: new java/util/ArrayList
/*   */     //   194: dup
/*   */     //   195: astore #10
/*   */     //   197: invokespecial <init> : ()V
/*   */     //   200: getstatic f/km.u4 : Lf/R8;
/*   */     //   203: dup
/*   */     //   204: getfield jG0 : Lf/yM;
/*   */     //   207: invokevirtual gN : (Lf/yM;)Lf/zr0;
/*   */     //   210: invokevirtual ro0 : ()[Lf/Y;
/*   */     //   213: dup
/*   */     //   214: astore #11
/*   */     //   216: arraylength
/*   */     //   217: istore #12
/*   */     //   219: iconst_0
/*   */     //   220: istore #13
/*   */     //   222: iload #13
/*   */     //   224: iload #12
/*   */     //   226: if_icmpge -> 303
/*   */     //   229: aload_1
/*   */     //   230: aload #11
/*   */     //   232: iload #13
/*   */     //   234: aaload
/*   */     //   235: astore #14
/*   */     //   237: ifnull -> 254
/*   */     //   240: aload_1
/*   */     //   241: aload #14
/*   */     //   243: invokeinterface Wx : (Ljava/lang/Object;)Z
/*   */     //   248: ifne -> 254
/*   */     //   251: goto -> 297
/*   */     //   254: aload #14
/*   */     //   256: getfield Bp0 : Lf/LPT3;
/*   */     //   259: getfield Y8 : Lf/Hu0;
/*   */     //   262: aload #7
/*   */     //   264: if_acmpne -> 297
/*   */     //   267: aload #14
/*   */     //   269: getfield Lh : Lf/nH0;
/*   */     //   272: getfield Pw0 : B
/*   */     //   275: dup
/*   */     //   276: istore #15
/*   */     //   278: iload #8
/*   */     //   280: if_icmpeq -> 289
/*   */     //   283: iload #15
/*   */     //   285: iconst_m1
/*   */     //   286: if_icmpne -> 297
/*   */     //   289: aload #10
/*   */     //   291: aload #14
/*   */     //   293: invokevirtual add : (Ljava/lang/Object;)Z
/*   */     //   296: pop
/*   */     //   297: iinc #13, 1
/*   */     //   300: goto -> 222
/*   */     //   303: aload #10
/*   */     //   305: invokevirtual isEmpty : ()Z
/*   */     //   308: ifeq -> 314
/*   */     //   311: goto -> 460
/*   */     //   314: aload #10
/*   */     //   316: dup
/*   */     //   317: aload_3
/*   */     //   318: getfield aV : Ljava/util/ArrayList;
/*   */     //   321: aload #9
/*   */     //   323: invokevirtual add : (Ljava/lang/Object;)Z
/*   */     //   326: pop
/*   */     //   327: <illegal opcode> compare : ()Ljava/util/Comparator;
/*   */     //   332: invokestatic sort : (Ljava/util/List;Ljava/util/Comparator;)V
/*   */     //   335: invokevirtual iterator : ()Ljava/util/Iterator;
/*   */     //   338: astore #7
/*   */     //   340: aload #7
/*   */     //   342: invokeinterface hasNext : ()Z
/*   */     //   347: ifeq -> 460
/*   */     //   350: aload #9
/*   */     //   352: aload #7
/*   */     //   354: invokeinterface next : ()Ljava/lang/Object;
/*   */     //   359: checkcast f/Y
/*   */     //   362: astore #8
/*   */     //   364: new f/vi
/*   */     //   367: dup
/*   */     //   368: astore #10
/*   */     //   370: aload_0
/*   */     //   371: aload #8
/*   */     //   373: new java/lang/StringBuilder
/*   */     //   376: dup
/*   */     //   377: aload #8
/*   */     //   379: swap
/*   */     //   380: invokespecial <init> : ()V
/*   */     //   383: getfield Lh : Lf/nH0;
/*   */     //   386: getfield Sf0 : S
/*   */     //   389: invokevirtual append : (I)Ljava/lang/StringBuilder;
/*   */     //   392: ldc_w 'x '
/*   */     //   395: invokevirtual append : (Ljava/lang/String;)Ljava/lang/StringBuilder;
/*   */     //   398: aload #8
/*   */     //   400: invokevirtual JG0 : ()Ljava/lang/String;
/*   */     //   403: invokevirtual append : (Ljava/lang/String;)Ljava/lang/StringBuilder;
/*   */     //   406: invokevirtual toString : ()Ljava/lang/String;
/*   */     //   409: astore #11
/*   */     //   411: getstatic f/wm0.y0 : Lf/wm0;
/*   */     //   414: aload #8
/*   */     //   416: getfield Bp0 : Lf/LPT3;
/*   */     //   419: iconst_0
/*   */     //   420: invokevirtual HR : (Lf/LPT3;Z)Lf/U70;
/*   */     //   423: astore #8
/*   */     //   425: <illegal opcode> run : (Lf/Oq0;Lf/Y;)Ljava/lang/Runnable;
/*   */     //   430: astore #12
/*   */     //   432: aload #11
/*   */     //   434: aload #8
/*   */     //   436: iconst_3
/*   */     //   437: iconst_3
/*   */     //   438: bipush #24
/*   */     //   440: bipush #24
/*   */     //   442: aload #12
/*   */     //   444: iconst_0
/*   */     //   445: invokespecial <init> : (Ljava/lang/String;Lf/U70;IIIILjava/lang/Runnable;Z)V
/*   */     //   448: getfield aV : Ljava/util/ArrayList;
/*   */     //   451: aload #10
/*   */     //   453: invokevirtual add : (Ljava/lang/Object;)Z
/*   */     //   456: pop
/*   */     //   457: goto -> 340
/*   */     //   460: iinc #6, 1
/*   */     //   463: goto -> 29
/*   */     //   466: aload_3
/*   */     //   467: getfield aV : Ljava/util/ArrayList;
/*   */     //   470: invokevirtual size : ()I
/*   */     //   473: iconst_1
/*   */     //   474: if_icmpge -> 488
/*   */     //   477: aload_3
/*   */     //   478: sipush #6007
/*   */     //   481: invokestatic OH0 : (I)Ljava/lang/String;
/*   */     //   484: aconst_null
/*   */     //   485: invokevirtual mD : (Ljava/lang/String;Ljava/lang/Runnable;)V
/*   */     //   488: aload_3
/*   */     //   489: getfield aV : Ljava/util/ArrayList;
/*   */     //   492: invokevirtual size : ()I
/*   */     //   495: ifle -> 534
/*   */     //   498: iload_2
/*   */     //   499: ifeq -> 534
/*   */     //   502: aload_3
/*   */     //   503: new f/Hk0
/*   */     //   506: dup
/*   */     //   507: astore_1
/*   */     //   508: aload_0
/*   */     //   509: sipush #1656
/*   */     //   512: invokestatic OH0 : (I)Ljava/lang/String;
/*   */     //   515: astore_0
/*   */     //   516: <illegal opcode> run : (Lf/Oq0;)Ljava/lang/Runnable;
/*   */     //   521: aload_0
/*   */     //   522: swap
/*   */     //   523: invokespecial <init> : (Ljava/lang/String;Ljava/lang/Runnable;)V
/*   */     //   526: getfield aV : Ljava/util/ArrayList;
/*   */     //   529: aload_1
/*   */     //   530: invokevirtual add : (Ljava/lang/Object;)Z
/*   */     //   533: pop
/*   */     //   534: aload_3
/*   */     //   535: areturn
/*   */     // Line number table:
/*   */     //   Java source line number -> byte code offset
/*   */     //   #1	-> 8
/*   */     //   #2	-> 11
/*   */     //   #3	-> 153
/*   */     //   #4	-> 159
/*   */     //   #5	-> 164
/*   */     //   #6	-> 172
/*   */     //   #7	-> 175
/*   */     //   #8	-> 186
/*   */     //   #9	-> 191
/*   */     //   #10	-> 204
/*   */     //   #11	-> 207
/*   */     //   #12	-> 256
/*   */     //   #13	-> 259
/*   */     //   #14	-> 269
/*   */     //   #15	-> 272
/*   */     //   #16	-> 293
/*   */     //   #17	-> 318
/*   */     //   #18	-> 327
/*   */     //   #19	-> 383
/*   */     //   #20	-> 386
/*   */     //   #21	-> 389
/*   */     //   #22	-> 411
/*   */     //   #23	-> 416
/*   */     //   #24	-> 420
/*   */     //   #25	-> 425
/*   */     //   #26	-> 445
/*   */     //   #27	-> 448
/*   */     //   #28	-> 467
/*   */     //   #29	-> 481
/*   */     //   #30	-> 489
/*   */     //   #31	-> 503
/*   */     //   #32	-> 526 } public static B3 n7(Qv0 paramQv0, Uc0 paramUc0) { // Byte code:
/*   */     //   0: aload_0
/*   */     //   1: aload_1
/*   */     //   2: <illegal opcode> jg0 : (Lf/Qv0;Lf/Uc0;)Lf/Oq0;
/*   */     //   7: astore_0
/*   */     //   8: iconst_0
/*   */     //   9: istore_2
/*   */     //   10: new java/util/ArrayList
/*   */     //   13: dup
/*   */     //   14: astore_3
/*   */     //   15: invokespecial <init> : ()V
/*   */     //   18: iconst_0
/*   */     //   19: istore #4
/*   */     //   21: iload #4
/*   */     //   23: aload_1
/*   */     //   24: invokevirtual oq : ()I
/*   */     //   27: if_icmpge -> 59
/*   */     //   30: aload_1
/*   */     //   31: iload #4
/*   */     //   33: invokevirtual ky : (S)Lf/j40;
/*   */     //   36: dup
/*   */     //   37: astore #5
/*   */     //   39: ifnull -> 49
/*   */     //   42: aload_3
/*   */     //   43: aload #5
/*   */     //   45: invokevirtual add : (Ljava/lang/Object;)Z
/*   */     //   48: pop
/*   */     //   49: iload #4
/*   */     //   51: iconst_1
/*   */     //   52: iadd
/*   */     //   53: i2s
/*   */     //   54: istore #4
/*   */     //   56: goto -> 21
/*   */     //   59: aload_0
/*   */     //   60: aload_3
/*   */     //   61: iload_2
/*   */     //   62: invokestatic z40 : (Lf/Oq0;Ljava/util/List;Z)Lf/B3;
/*   */     //   65: areturn
/*   */     // Line number table:
/*   */     //   Java source line number -> byte code offset
/*   */     //   #1	-> 10 } public static B3 at0(Qv0 paramQv0, List paramList, boolean paramBoolean) { return z40(paramQv0::Oh0, paramList, paramBoolean); } public static B3 z40(Oq0 paramOq0, List paramList, boolean paramBoolean) { // Byte code:
/*   */     //   0: aload_1
/*   */     //   1: new f/B3
/*   */     //   4: dup
/*   */     //   5: astore_1
/*   */     //   6: iconst_0
/*   */     //   7: invokestatic OH0 : (I)Ljava/lang/String;
/*   */     //   10: invokespecial <init> : (Ljava/lang/String;)V
/*   */     //   13: invokeinterface iterator : ()Ljava/util/Iterator;
/*   */     //   18: astore_3
/*   */     //   19: aload_3
/*   */     //   20: invokeinterface hasNext : ()Z
/*   */     //   25: ifeq -> 121
/*   */     //   28: aload_1
/*   */     //   29: aload_3
/*   */     //   30: invokeinterface next : ()Ljava/lang/Object;
/*   */     //   35: checkcast f/j40
/*   */     //   38: astore #4
/*   */     //   40: new f/vi
/*   */     //   43: dup
/*   */     //   44: astore #5
/*   */     //   46: aload_0
/*   */     //   47: aload #4
/*   */     //   49: dup
/*   */     //   50: invokevirtual m : ()Ljava/lang/String;
/*   */     //   53: astore #6
/*   */     //   55: getstatic f/um0.Kt0 : Lf/um0;
/*   */     //   58: aload #4
/*   */     //   60: dup
/*   */     //   61: getfield Zs : Lf/Q90;
/*   */     //   64: invokevirtual Vf0 : ()S
/*   */     //   67: istore #7
/*   */     //   69: invokevirtual s5 : ()B
/*   */     //   72: istore #8
/*   */     //   74: iload #7
/*   */     //   76: aload #4
/*   */     //   78: getfield Zs : Lf/Q90;
/*   */     //   81: invokevirtual da : ()Z
/*   */     //   84: iload #8
/*   */     //   86: invokevirtual lb : (SZB)[Lf/zh0;
/*   */     //   89: iconst_0
/*   */     //   90: aaload
/*   */     //   91: astore #4
/*   */     //   93: <illegal opcode> run : (Lf/Oq0;Lf/j40;)Ljava/lang/Runnable;
/*   */     //   98: astore #7
/*   */     //   100: aload #6
/*   */     //   102: aload #4
/*   */     //   104: aload #7
/*   */     //   106: invokespecial <init> : (Ljava/lang/String;Lf/zh0;Ljava/lang/Runnable;)V
/*   */     //   109: getfield aV : Ljava/util/ArrayList;
/*   */     //   112: aload #5
/*   */     //   114: invokevirtual add : (Ljava/lang/Object;)Z
/*   */     //   117: pop
/*   */     //   118: goto -> 19
/*   */     //   121: aload_1
/*   */     //   122: getfield aV : Ljava/util/ArrayList;
/*   */     //   125: invokevirtual size : ()I
/*   */     //   128: iconst_1
/*   */     //   129: if_icmpge -> 143
/*   */     //   132: aload_1
/*   */     //   133: sipush #6007
/*   */     //   136: invokestatic OH0 : (I)Ljava/lang/String;
/*   */     //   139: aconst_null
/*   */     //   140: invokevirtual mD : (Ljava/lang/String;Ljava/lang/Runnable;)V
/*   */     //   143: aload_1
/*   */     //   144: getfield aV : Ljava/util/ArrayList;
/*   */     //   147: invokevirtual size : ()I
/*   */     //   150: ifle -> 189
/*   */     //   153: iload_2
/*   */     //   154: ifeq -> 189
/*   */     //   157: aload_1
/*   */     //   158: new f/Hk0
/*   */     //   161: dup
/*   */     //   162: astore_2
/*   */     //   163: aload_0
/*   */     //   164: sipush #1656
/*   */     //   167: invokestatic OH0 : (I)Ljava/lang/String;
/*   */     //   170: astore_0
/*   */     //   171: <illegal opcode> run : (Lf/Oq0;)Ljava/lang/Runnable;
/*   */     //   176: aload_0
/*   */     //   177: swap
/*   */     //   178: invokespecial <init> : (Ljava/lang/String;Ljava/lang/Runnable;)V
/*   */     //   181: getfield aV : Ljava/util/ArrayList;
/*   */     //   184: aload_2
/*   */     //   185: invokevirtual add : (Ljava/lang/Object;)Z
/*   */     //   188: pop
/*   */     //   189: aload_1
/*   */     //   190: areturn
/*   */     // Line number table:
/*   */     //   Java source line number -> byte code offset
/*   */     //   #1	-> 55
/*   */     //   #2	-> 61
/*   */     //   #3	-> 64
/*   */     //   #4	-> 78
/*   */     //   #5	-> 86
/*   */     //   #6	-> 109
/*   */     //   #7	-> 122
/*   */     //   #8	-> 136
/*   */     //   #9	-> 144
/*   */     //   #10	-> 158
/* 7 */     //   #11	-> 181 } public static void VN(Qv0 paramQv0, Uc0 paramUc0, j40 paramj40) { if (paramQv0.y1()) { paramQv0.zf(paramj40); } else { if (paramUc0 != null) { if (km.MR == null) km.u4.lO(new Qv0(paramUc0, paramj40.Zs.Tl0, false), paramQv0);  return; }  throw new IllegalArgumentException(); }  } public static void lB(of paramof, ON paramON) { paramof.Zh((paramON.wN()).Pb); } public static void Ss0(of paramof, CD0 paramCD0) { paramof.Zh((paramCD0.wN()).Pb); } public static boolean op0(Y paramY) { LPT3 lPT3; Hu0 hu0; if ((hu0 = (lPT3 = paramY.Bp0).Y8) == Hu0.Bm || hu0 == Hu0.w2) return false;  if (lPT3.bj()) return false;  short s; if ((s = paramY.Lh.p1) == 1 || s == 5001 || s == 1132) return false;  return paramY.Bp0.kd; }
/*   */ 
/*   */   
/*   */   public static boolean jA0(Y paramY) {
/*   */     return paramY.Bp0.vx();
/*   */   }
/*   */   
/*   */   public static boolean Jd0(Y paramY) {
/*   */     LPT3 lPT3;
/*   */     return ((lPT3 = paramY.Bp0).vx() && !lPT3.IK0);
/*   */   } }


/* Location:              /Users/vnnsnnt/Documents/Codespace/JavaWorkspace/RedTrainer/src/main/java/org/trainer/client/PokeMMO.jar!/f/JB0.class
 * Java compiler version: 8 (52.0)
 * JD-Core Version:       1.1.3
 */