/*  1 */ package f;public final class jd { public final VF0 iI; public Ip mj0; public rS Sz0; public W1 aj0; public of VW; public YA0 af0; public YA0 qb0; public Comparator y50 = yG0.AG0; public dQ MK0; public byte RA = (byte)YearMonth.now(ZoneId.of("UTC")).getMonthValue(); public short a8; public Gu0 Ou0; public UL e2 = new UL(); public ec0 p2; public Un kt; public vF0 r2; public UA0 tf0; public fQ ba = new fQ(); public final ec0 Q30; public final byte Lx; public final yX[] E90; public final Li0 UK; public int g4 = 0; public jd(VF0 paramVF0, Li0 paramLi0, ec0 paramec0, byte paramByte, yX[] paramArrayOfyX) { this.iI = paramVF0; this.UK = paramLi0; this.Q30 = paramec0; this.Lx = paramByte; this.E90 = paramArrayOfyX; } private void T3() { byte b = (byte)YearMonth.now(ZoneId.of("UTC")).getMonthValue(); ky ky = this.Q30.Ud0; km.u4
/*    */       
/*  3 */       .M6(b, this, this.Q30.aU); } private kt Ih0(String paramString, int paramInt, kt paramkt) { qw0 qw0; Gu0 gu0; if ((gu0 = this.Ou0) == null) return null;  String[] arrayOfString = (String[])(new iL(this)).stream().map(jd::Hf).filter(paramString::k1).toArray(jd::o5); return new TW(paramString.length(), true, this); } public static String Hf(yG0 paramyG0) { return On.v30().lpT3(paramyG0.Vo).o60(false); } private void Jx() { byte b = (byte)((YearMonth)this.aj0.WW()).getMonthValue(); this.kt = null; this.Ou0 = null; ky ky = this.p2.Ud0; km.u4.M6(b, this, this.p2.aU); } private void Uh0(Un paramUn, short paramShort, yG0 paramyG0) { this.kt = paramUn; R8 r8 = km.u4; byte b2 = this.RA, b1 = this.p2.Ud0.Xm0; byte b3 = this.p2.aU.y1;
/*  4 */     this.e20
/*  5 */       .W3(new Ow(b2, b1, b3, paramShort));
/*    */     
/*  7 */     this.a8 = paramyG0.Vo; } private void Sa0() { this.qb0.gx(); this.qb0 = null; this.e2.Jh0.d90 = new short[10]; this.e2.Jh0.Mp0 = 0; this.UK.qs0(oc(true)); UB0.Kg0.fN(() -> this.Sz0.ey0(this::jz)); } private boolean jz(JG0 paramJG0) { return (paramJG0 instanceof Un && ((Un)paramJG0).GE0.equals(this.kt.GE0)); } private void wP(short paramShort1, short paramShort2) { R8 r8 = km.u4; byte b2 = this.RA, b1 = this.p2.Ud0.Xm0; byte b3 = this.p2.aU.y1; this.e20.W3(new Ow(b2, b1, b3, paramShort1)); this.a8 = paramShort1; this.e2.Jh0
/*  8 */       .F40(paramShort2); } private void KF0(short paramShort) { R8 r8 = km.u4; byte b2 = this.RA, b1 = this.p2.Ud0.Xm0; byte b3 = this.p2.aU.y1; this.e20.W3(new Ow(b2, b1, b3, paramShort)); this.a8 = paramShort; wx0 wx0; int i, j; if ((j = (i = (wx0 = this.e2.Jh0).Mp0) - 1) < i) {
/*  9 */       short[] arrayOfShort; (arrayOfShort = this.d90)[j]; byte b = 1; if (j >= 0 && j < i) { if (j == 0) { i -= b;
/* 10 */           System.arraycopy(arrayOfShort, b, arrayOfShort, 0, i); } else if (i - b != j) { int k = i - (i = j + b); System.arraycopy(arrayOfShort, i, arrayOfShort, j, k); }  this.Mp0 -= b; return; }  throw new ArrayIndexOutOfBoundsException(j);
/* 11 */     }  throw new ArrayIndexOutOfBoundsException(j); }
/*    */ 
/*    */   
/*    */   public final void CE(int paramInt1, int paramInt2, int paramInt3, int paramInt4, int paramInt5, int paramInt6, int paramInt7, short paramShort, jY[] paramArrayOfjY1, jY[] paramArrayOfjY2, jY[] paramArrayOfjY3, jY[] paramArrayOfjY4) {
/*    */     // Byte code:
/*    */     //   0: iload #8
/*    */     //   2: aload_0
/*    */     //   3: getfield a8 : S
/*    */     //   6: if_icmpeq -> 10
/*    */     //   9: return
/*    */     //   10: aload_0
/*    */     //   11: getfield qb0 : Lf/YA0;
/*    */     //   14: dup
/*    */     //   15: astore #13
/*    */     //   17: ifnull -> 86
/*    */     //   20: aload_0
/*    */     //   21: aload #13
/*    */     //   23: invokevirtual gx : ()V
/*    */     //   26: getfield r2 : Lf/vF0;
/*    */     //   29: dup
/*    */     //   30: astore #13
/*    */     //   32: ifnull -> 43
/*    */     //   35: aload #13
/*    */     //   37: getfield TS : Lf/rH;
/*    */     //   40: invokevirtual H : ()V
/*    */     //   43: aload_0
/*    */     //   44: getfield ba : Lf/fQ;
/*    */     //   47: invokevirtual r30 : ()Lf/Hc0;
/*    */     //   50: astore #13
/*    */     //   52: aload #13
/*    */     //   54: invokevirtual hasNext : ()Z
/*    */     //   57: ifeq -> 76
/*    */     //   60: aload #13
/*    */     //   62: invokevirtual next : ()Ljava/lang/Object;
/*    */     //   65: checkcast f/iq0
/*    */     //   68: invokeinterface dispose : ()V
/*    */     //   73: goto -> 52
/*    */     //   76: aload_0
/*    */     //   77: dup
/*    */     //   78: aconst_null
/*    */     //   79: putfield tf0 : Lf/UA0;
/*    */     //   82: aconst_null
/*    */     //   83: putfield qb0 : Lf/YA0;
/*    */     //   86: aload_0
/*    */     //   87: new f/YA0
/*    */     //   90: dup
/*    */     //   91: invokespecial <init> : ()V
/*    */     //   94: putfield qb0 : Lf/YA0;
/*    */     //   97: invokestatic v30 : ()Lf/On;
/*    */     //   100: iload #8
/*    */     //   102: invokevirtual lpT3 : (S)Lf/UD0;
/*    */     //   105: dup
/*    */     //   106: astore #13
/*    */     //   108: invokevirtual Qo0 : ()Lf/UD0;
/*    */     //   111: aload #13
/*    */     //   113: if_acmpeq -> 122
/*    */     //   116: iconst_1
/*    */     //   117: istore #14
/*    */     //   119: goto -> 125
/*    */     //   122: iconst_0
/*    */     //   123: istore #14
/*    */     //   125: aconst_null
/*    */     //   126: astore #15
/*    */     //   128: getstatic f/km.u4 : Lf/R8;
/*    */     //   131: invokevirtual Zm : ()B
/*    */     //   134: aload_0
/*    */     //   135: getfield p2 : Lf/ec0;
/*    */     //   138: getfield aU : Lf/DO;
/*    */     //   141: dup
/*    */     //   142: astore #16
/*    */     //   144: getfield bC : B
/*    */     //   147: if_icmplt -> 156
/*    */     //   150: iconst_1
/*    */     //   151: istore #17
/*    */     //   153: goto -> 159
/*    */     //   156: iconst_0
/*    */     //   157: istore #17
/*    */     //   159: aload #16
/*    */     //   161: getfield Jm0 : Z
/*    */     //   164: ifeq -> 297
/*    */     //   167: aload #16
/*    */     //   169: invokevirtual Hb0 : ()Z
/*    */     //   172: ifeq -> 297
/*    */     //   175: aload_0
/*    */     //   176: getfield p2 : Lf/ec0;
/*    */     //   179: getfield aU : Lf/DO;
/*    */     //   182: dup
/*    */     //   183: astore #16
/*    */     //   185: ifnonnull -> 191
/*    */     //   188: goto -> 201
/*    */     //   191: aload #13
/*    */     //   193: getfield ee : Lf/DO;
/*    */     //   196: aload #16
/*    */     //   198: if_acmpne -> 205
/*    */     //   201: iconst_1
/*    */     //   202: goto -> 215
/*    */     //   205: aload #13
/*    */     //   207: getfield G2 : Ljava/util/HashSet;
/*    */     //   210: aload #16
/*    */     //   212: invokevirtual contains : (Ljava/lang/Object;)Z
/*    */     //   215: ifne -> 297
/*    */     //   218: new f/dQ
/*    */     //   221: dup
/*    */     //   222: dup
/*    */     //   223: astore #15
/*    */     //   225: iconst_3
/*    */     //   226: anewarray java/lang/String
/*    */     //   229: dup
/*    */     //   230: astore #16
/*    */     //   232: aload #13
/*    */     //   234: aload #16
/*    */     //   236: aload_0
/*    */     //   237: aload #16
/*    */     //   239: aload #13
/*    */     //   241: iload #14
/*    */     //   243: invokevirtual o60 : (Z)Ljava/lang/String;
/*    */     //   246: iconst_0
/*    */     //   247: swap
/*    */     //   248: aastore
/*    */     //   249: getfield p2 : Lf/ec0;
/*    */     //   252: getfield aU : Lf/DO;
/*    */     //   255: getfield mt0 : I
/*    */     //   258: invokestatic OH0 : (I)Ljava/lang/String;
/*    */     //   261: iconst_1
/*    */     //   262: swap
/*    */     //   263: aastore
/*    */     //   264: getfield ee : Lf/DO;
/*    */     //   267: getfield mt0 : I
/*    */     //   270: invokestatic OH0 : (I)Ljava/lang/String;
/*    */     //   273: iconst_2
/*    */     //   274: swap
/*    */     //   275: aastore
/*    */     //   276: sipush #5688
/*    */     //   279: aload #16
/*    */     //   281: invokestatic sB : (I[Ljava/lang/String;)Ljava/lang/String;
/*    */     //   284: astore #16
/*    */     //   286: invokespecial <init> : ()V
/*    */     //   289: aload #16
/*    */     //   291: invokevirtual E1 : (Ljava/lang/String;)V
/*    */     //   294: goto -> 473
/*    */     //   297: aload_0
/*    */     //   298: getfield p2 : Lf/ec0;
/*    */     //   301: getfield aU : Lf/DO;
/*    */     //   304: dup
/*    */     //   305: astore #16
/*    */     //   307: getfield Jm0 : Z
/*    */     //   310: ifne -> 408
/*    */     //   313: aload #13
/*    */     //   315: getfield ee : Lf/DO;
/*    */     //   318: getfield y1 : B
/*    */     //   321: aload #16
/*    */     //   323: getfield y1 : B
/*    */     //   326: if_icmpge -> 408
/*    */     //   329: new f/dQ
/*    */     //   332: dup
/*    */     //   333: dup
/*    */     //   334: astore #15
/*    */     //   336: iconst_3
/*    */     //   337: anewarray java/lang/String
/*    */     //   340: dup
/*    */     //   341: astore #16
/*    */     //   343: aload #13
/*    */     //   345: aload #16
/*    */     //   347: aload_0
/*    */     //   348: aload #16
/*    */     //   350: aload #13
/*    */     //   352: iload #14
/*    */     //   354: invokevirtual o60 : (Z)Ljava/lang/String;
/*    */     //   357: iconst_0
/*    */     //   358: swap
/*    */     //   359: aastore
/*    */     //   360: getfield p2 : Lf/ec0;
/*    */     //   363: getfield aU : Lf/DO;
/*    */     //   366: getfield mt0 : I
/*    */     //   369: invokestatic OH0 : (I)Ljava/lang/String;
/*    */     //   372: iconst_1
/*    */     //   373: swap
/*    */     //   374: aastore
/*    */     //   375: getfield ee : Lf/DO;
/*    */     //   378: getfield mt0 : I
/*    */     //   381: invokestatic OH0 : (I)Ljava/lang/String;
/*    */     //   384: iconst_2
/*    */     //   385: swap
/*    */     //   386: aastore
/*    */     //   387: sipush #5687
/*    */     //   390: aload #16
/*    */     //   392: invokestatic sB : (I[Ljava/lang/String;)Ljava/lang/String;
/*    */     //   395: astore #16
/*    */     //   397: invokespecial <init> : ()V
/*    */     //   400: aload #16
/*    */     //   402: invokevirtual E1 : (Ljava/lang/String;)V
/*    */     //   405: goto -> 473
/*    */     //   408: iload #17
/*    */     //   410: ifeq -> 484
/*    */     //   413: aload #16
/*    */     //   415: getfield bC : B
/*    */     //   418: ifle -> 484
/*    */     //   421: new f/dQ
/*    */     //   424: dup
/*    */     //   425: dup
/*    */     //   426: astore #15
/*    */     //   428: aload_0
/*    */     //   429: new java/lang/StringBuilder
/*    */     //   432: dup
/*    */     //   433: astore #16
/*    */     //   435: invokespecial <init> : ()V
/*    */     //   438: getfield p2 : Lf/ec0;
/*    */     //   441: getfield aU : Lf/DO;
/*    */     //   444: getfield mt0 : I
/*    */     //   447: aload #16
/*    */     //   449: ldc_w ' '
/*    */     //   452: invokestatic X9 : (ILjava/lang/StringBuilder;Ljava/lang/String;)Ljava/lang/StringBuilder;
/*    */     //   455: iconst_0
/*    */     //   456: swap
/*    */     //   457: ldc_w ' tiering data is restricted to GameMasters'
/*    */     //   460: invokestatic jJ0 : (ILjava/lang/StringBuilder;Ljava/lang/String;)Ljava/lang/String;
/*    */     //   463: astore #16
/*    */     //   465: invokespecial <init> : ()V
/*    */     //   468: aload #16
/*    */     //   470: invokevirtual E1 : (Ljava/lang/String;)V
/*    */     //   473: aload #15
/*    */     //   475: ldc_w 'label-name-monster-tier-banned'
/*    */     //   478: invokevirtual Xu : (Ljava/lang/String;)V
/*    */     //   481: goto -> 650
/*    */     //   484: aload_0
/*    */     //   485: getfield E90 : [Lf/yX;
/*    */     //   488: dup
/*    */     //   489: astore #16
/*    */     //   491: arraylength
/*    */     //   492: istore #18
/*    */     //   494: iconst_0
/*    */     //   495: istore #19
/*    */     //   497: iload #19
/*    */     //   499: iload #18
/*    */     //   501: if_icmpge -> 650
/*    */     //   504: aload #16
/*    */     //   506: iload #19
/*    */     //   508: aaload
/*    */     //   509: getfield U30 : Ljava/util/ArrayList;
/*    */     //   512: invokevirtual iterator : ()Ljava/util/Iterator;
/*    */     //   515: astore #20
/*    */     //   517: aload #20
/*    */     //   519: invokeinterface hasNext : ()Z
/*    */     //   524: ifeq -> 644
/*    */     //   527: aload #20
/*    */     //   529: invokeinterface next : ()Ljava/lang/Object;
/*    */     //   534: checkcast f/Pi
/*    */     //   537: dup
/*    */     //   538: astore #21
/*    */     //   540: getfield PQ : S
/*    */     //   543: aload #13
/*    */     //   545: getfield AP : S
/*    */     //   548: if_icmpne -> 517
/*    */     //   551: aload #21
/*    */     //   553: new f/dQ
/*    */     //   556: astore #15
/*    */     //   558: sipush #5689
/*    */     //   561: istore #20
/*    */     //   563: iconst_2
/*    */     //   564: anewarray java/lang/String
/*    */     //   567: dup
/*    */     //   568: astore #21
/*    */     //   570: aload #13
/*    */     //   572: iload #14
/*    */     //   574: invokevirtual o60 : (Z)Ljava/lang/String;
/*    */     //   577: iconst_0
/*    */     //   578: swap
/*    */     //   579: aastore
/*    */     //   580: iconst_1
/*    */     //   581: istore #22
/*    */     //   583: getfield U9 : Lf/DO;
/*    */     //   586: dup
/*    */     //   587: astore #23
/*    */     //   589: ifnull -> 605
/*    */     //   592: aload #23
/*    */     //   594: getfield mt0 : I
/*    */     //   597: invokestatic OH0 : (I)Ljava/lang/String;
/*    */     //   600: astore #23
/*    */     //   602: goto -> 610
/*    */     //   605: ldc_w ''
/*    */     //   608: astore #23
/*    */     //   610: aload #15
/*    */     //   612: dup
/*    */     //   613: dup
/*    */     //   614: iload #20
/*    */     //   616: aload #21
/*    */     //   618: iload #22
/*    */     //   620: aload #23
/*    */     //   622: aastore
/*    */     //   623: aload #21
/*    */     //   625: invokestatic sB : (I[Ljava/lang/String;)Ljava/lang/String;
/*    */     //   628: astore #20
/*    */     //   630: invokespecial <init> : ()V
/*    */     //   633: aload #20
/*    */     //   635: invokevirtual E1 : (Ljava/lang/String;)V
/*    */     //   638: ldc_w 'label-name-monster-tier-warning'
/*    */     //   641: invokevirtual Xu : (Ljava/lang/String;)V
/*    */     //   644: iinc #19, 1
/*    */     //   647: goto -> 497
/*    */     //   650: aload #15
/*    */     //   652: ifnull -> 682
/*    */     //   655: aload_0
/*    */     //   656: getfield qb0 : Lf/YA0;
/*    */     //   659: getfield Dv0 : Lf/SA;
/*    */     //   662: invokevirtual wP : ()Lf/nJ0;
/*    */     //   665: dup
/*    */     //   666: iconst_3
/*    */     //   667: invokestatic valueOf : (I)Ljava/lang/Integer;
/*    */     //   670: putfield ss : Ljava/lang/Integer;
/*    */     //   673: getfield Ox : Lf/ZP;
/*    */     //   676: aload #15
/*    */     //   678: invokevirtual S7 : (Ljava/lang/Object;)Lf/nJ0;
/*    */     //   681: pop
/*    */     //   682: aload_0
/*    */     //   683: new f/YA0
/*    */     //   686: dup
/*    */     //   687: dup
/*    */     //   688: astore #15
/*    */     //   690: invokespecial <init> : ()V
/*    */     //   693: new f/dQ
/*    */     //   696: dup
/*    */     //   697: dup2
/*    */     //   698: astore #16
/*    */     //   700: new java/lang/StringBuilder
/*    */     //   703: dup
/*    */     //   704: astore #18
/*    */     //   706: aload #13
/*    */     //   708: iload #14
/*    */     //   710: aload #18
/*    */     //   712: invokespecial <init> : ()V
/*    */     //   715: invokevirtual o60 : (Z)Ljava/lang/String;
/*    */     //   718: invokevirtual append : (Ljava/lang/String;)Ljava/lang/StringBuilder;
/*    */     //   721: ldc_w ' ('
/*    */     //   724: invokevirtual append : (Ljava/lang/String;)Ljava/lang/StringBuilder;
/*    */     //   727: aload_0
/*    */     //   728: getfield aj0 : Lf/W1;
/*    */     //   731: invokevirtual WW : ()Ljava/lang/Object;
/*    */     //   734: invokevirtual append : (Ljava/lang/Object;)Ljava/lang/StringBuilder;
/*    */     //   737: ldc_w ') ('
/*    */     //   740: invokevirtual append : (Ljava/lang/String;)Ljava/lang/StringBuilder;
/*    */     //   743: aload_0
/*    */     //   744: getfield p2 : Lf/ec0;
/*    */     //   747: invokevirtual append : (Ljava/lang/Object;)Ljava/lang/StringBuilder;
/*    */     //   750: ldc_w ')'
/*    */     //   753: invokevirtual append : (Ljava/lang/String;)Ljava/lang/StringBuilder;
/*    */     //   756: invokevirtual toString : ()Ljava/lang/String;
/*    */     //   759: astore #14
/*    */     //   761: invokespecial <init> : ()V
/*    */     //   764: aload #14
/*    */     //   766: invokevirtual E1 : (Ljava/lang/String;)V
/*    */     //   769: ldc_w '/matchmaking-stats-frame.label-name-monster-tiering'
/*    */     //   772: invokevirtual Xu : (Ljava/lang/String;)V
/*    */     //   775: getfield Dv0 : Lf/SA;
/*    */     //   778: aload #16
/*    */     //   780: invokevirtual S7 : (Ljava/lang/Object;)Lf/nJ0;
/*    */     //   783: ldc_w 6.0
/*    */     //   786: invokevirtual Xj0 : (F)Lf/nJ0;
/*    */     //   789: pop
/*    */     //   790: getfield e2 : Lf/UL;
/*    */     //   793: getfield Jh0 : Lf/wx0;
/*    */     //   796: dup
/*    */     //   797: astore #14
/*    */     //   799: getfield Mp0 : I
/*    */     //   802: dup
/*    */     //   803: istore #16
/*    */     //   805: ifle -> 895
/*    */     //   808: iload #16
/*    */     //   810: iconst_1
/*    */     //   811: isub
/*    */     //   812: dup
/*    */     //   813: istore #18
/*    */     //   815: iload #16
/*    */     //   817: if_icmpge -> 885
/*    */     //   820: aload #15
/*    */     //   822: aload #14
/*    */     //   824: getfield d90 : [S
/*    */     //   827: iload #18
/*    */     //   829: saload
/*    */     //   830: istore #14
/*    */     //   832: new f/Un
/*    */     //   835: dup
/*    */     //   836: astore #16
/*    */     //   838: aload_0
/*    */     //   839: iload #14
/*    */     //   841: aload #16
/*    */     //   843: iload #14
/*    */     //   845: ldc_w 150000
/*    */     //   848: iadd
/*    */     //   849: invokestatic OH0 : (I)Ljava/lang/String;
/*    */     //   852: sipush #5683
/*    */     //   855: swap
/*    */     //   856: invokestatic Go : (ILjava/lang/String;)Ljava/lang/String;
/*    */     //   859: invokespecial <init> : (Ljava/lang/String;)V
/*    */     //   862: <illegal opcode> run : (Lf/jd;S)Ljava/lang/Runnable;
/*    */     //   867: invokevirtual tW : (Ljava/lang/Runnable;)V
/*    */     //   870: getfield Dv0 : Lf/SA;
/*    */     //   873: aload #16
/*    */     //   875: invokevirtual S7 : (Ljava/lang/Object;)Lf/nJ0;
/*    */     //   878: invokevirtual ti0 : ()Lf/nJ0;
/*    */     //   881: pop
/*    */     //   882: goto -> 895
/*    */     //   885: new java/lang/ArrayIndexOutOfBoundsException
/*    */     //   888: dup
/*    */     //   889: iload #18
/*    */     //   891: invokespecial <init> : (I)V
/*    */     //   894: athrow
/*    */     //   895: aload_0
/*    */     //   896: getfield qb0 : Lf/YA0;
/*    */     //   899: getfield Dv0 : Lf/SA;
/*    */     //   902: aload #15
/*    */     //   904: invokevirtual S7 : (Ljava/lang/Object;)Lf/nJ0;
/*    */     //   907: pop
/*    */     //   908: new f/YA0
/*    */     //   911: dup
/*    */     //   912: astore #14
/*    */     //   914: invokespecial <init> : ()V
/*    */     //   917: invokestatic XU : ()Z
/*    */     //   920: ifeq -> 961
/*    */     //   923: aload_0
/*    */     //   924: new f/vF0
/*    */     //   927: dup
/*    */     //   928: dup
/*    */     //   929: astore #15
/*    */     //   931: sipush #300
/*    */     //   934: sipush #300
/*    */     //   937: iconst_0
/*    */     //   938: invokespecial <init> : (III)V
/*    */     //   941: putfield r2 : Lf/vF0;
/*    */     //   944: aload #15
/*    */     //   946: getfield TS : Lf/rH;
/*    */     //   949: sipush #-200
/*    */     //   952: bipush #-90
/*    */     //   954: invokevirtual zT : (II)Lf/JG0;
/*    */     //   957: pop
/*    */     //   958: goto -> 995
/*    */     //   961: aload_0
/*    */     //   962: new f/vF0
/*    */     //   965: dup
/*    */     //   966: dup
/*    */     //   967: astore #15
/*    */     //   969: sipush #250
/*    */     //   972: sipush #180
/*    */     //   975: iconst_0
/*    */     //   976: invokespecial <init> : (III)V
/*    */     //   979: putfield r2 : Lf/vF0;
/*    */     //   982: aload #15
/*    */     //   984: getfield TS : Lf/rH;
/*    */     //   987: bipush #-70
/*    */     //   989: bipush #-70
/*    */     //   991: invokevirtual zT : (II)Lf/JG0;
/*    */     //   994: pop
/*    */     //   995: aload #13
/*    */     //   997: dup
/*    */     //   998: dup
/*    */     //   999: invokevirtual Qo0 : ()Lf/UD0;
/*    */     //   1002: getfield AP : S
/*    */     //   1005: istore #15
/*    */     //   1007: getfield D3 : B
/*    */     //   1010: iload #15
/*    */     //   1012: invokestatic HZ : (BS)S
/*    */     //   1015: istore #15
/*    */     //   1017: getfield FD : I
/*    */     //   1020: dup
/*    */     //   1021: istore #16
/*    */     //   1023: ifle -> 1038
/*    */     //   1026: iload #16
/*    */     //   1028: sipush #254
/*    */     //   1031: if_icmpge -> 1038
/*    */     //   1034: iconst_1
/*    */     //   1035: goto -> 1039
/*    */     //   1038: iconst_0
/*    */     //   1039: ifeq -> 1048
/*    */     //   1042: iconst_0
/*    */     //   1043: istore #16
/*    */     //   1045: goto -> 1065
/*    */     //   1048: iload #16
/*    */     //   1050: sipush #254
/*    */     //   1053: if_icmpne -> 1062
/*    */     //   1056: iconst_1
/*    */     //   1057: istore #16
/*    */     //   1059: goto -> 1065
/*    */     //   1062: iconst_m1
/*    */     //   1063: istore #16
/*    */     //   1065: aload_0
/*    */     //   1066: getstatic f/um0.Kt0 : Lf/um0;
/*    */     //   1069: iload #16
/*    */     //   1071: iload #15
/*    */     //   1073: iconst_0
/*    */     //   1074: iconst_0
/*    */     //   1075: invokevirtual H9 : (BSZZ)[Lf/zh0;
/*    */     //   1078: dup
/*    */     //   1079: astore #18
/*    */     //   1081: iconst_0
/*    */     //   1082: aaload
/*    */     //   1083: astore #19
/*    */     //   1085: aconst_null
/*    */     //   1086: astore #20
/*    */     //   1088: getfield tf0 : Lf/UA0;
/*    */     //   1091: ifnonnull -> 1155
/*    */     //   1094: getstatic f/um0.Kt0 : Lf/um0;
/*    */     //   1097: iload #16
/*    */     //   1099: iload #15
/*    */     //   1101: iconst_0
/*    */     //   1102: iconst_0
/*    */     //   1103: invokevirtual rE0 : (BSZZ)Z
/*    */     //   1106: ifne -> 1155
/*    */     //   1109: aload_0
/*    */     //   1110: dup
/*    */     //   1111: getstatic f/um0.Kt0 : Lf/um0;
/*    */     //   1114: iload #16
/*    */     //   1116: iload #15
/*    */     //   1118: iconst_0
/*    */     //   1119: iconst_0
/*    */     //   1120: invokevirtual vt : (BSZZ)Lf/UA0;
/*    */     //   1123: dup
/*    */     //   1124: astore #21
/*    */     //   1126: putfield tf0 : Lf/UA0;
/*    */     //   1129: getfield ba : Lf/fQ;
/*    */     //   1132: dup
/*    */     //   1133: iconst_1
/*    */     //   1134: anewarray f/iq0
/*    */     //   1137: dup
/*    */     //   1138: astore #22
/*    */     //   1140: iconst_0
/*    */     //   1141: aload #21
/*    */     //   1143: aastore
/*    */     //   1144: invokevirtual getClass : ()Ljava/lang/Class;
/*    */     //   1147: pop
/*    */     //   1148: aload #22
/*    */     //   1150: iconst_0
/*    */     //   1151: iconst_1
/*    */     //   1152: invokevirtual tu0 : ([Ljava/lang/Object;II)V
/*    */     //   1155: getstatic f/um0.Kt0 : Lf/um0;
/*    */     //   1158: iload #16
/*    */     //   1160: iload #15
/*    */     //   1162: iconst_0
/*    */     //   1163: iconst_0
/*    */     //   1164: invokevirtual F7 : (BSZZ)Z
/*    */     //   1167: ifeq -> 1187
/*    */     //   1170: getstatic f/um0.Kt0 : Lf/um0;
/*    */     //   1173: iload #16
/*    */     //   1175: iload #15
/*    */     //   1177: iconst_0
/*    */     //   1178: iconst_0
/*    */     //   1179: invokevirtual Hr : (BSZZ)[I
/*    */     //   1182: astore #20
/*    */     //   1184: goto -> 1190
/*    */     //   1187: aconst_null
/*    */     //   1188: astore #18
/*    */     //   1190: aload #18
/*    */     //   1192: aload_0
/*    */     //   1193: getfield r2 : Lf/vF0;
/*    */     //   1196: getfield TS : Lf/rH;
/*    */     //   1199: astore #15
/*    */     //   1201: ifnull -> 1239
/*    */     //   1204: aload #18
/*    */     //   1206: arraylength
/*    */     //   1207: iconst_2
/*    */     //   1208: if_icmple -> 1239
/*    */     //   1211: aload #15
/*    */     //   1213: dup
/*    */     //   1214: aload #20
/*    */     //   1216: aload #15
/*    */     //   1218: aload #18
/*    */     //   1220: invokevirtual sm : ([Lf/zh0;)V
/*    */     //   1223: invokevirtual s8 : ([I)V
/*    */     //   1226: iconst_1
/*    */     //   1227: putfield vU : Z
/*    */     //   1230: invokestatic XU : ()Z
/*    */     //   1233: ifeq -> 1325
/*    */     //   1236: goto -> 1317
/*    */     //   1239: aload_0
/*    */     //   1240: getfield tf0 : Lf/UA0;
/*    */     //   1243: dup
/*    */     //   1244: astore #16
/*    */     //   1246: ifnull -> 1297
/*    */     //   1249: invokestatic XU : ()Z
/*    */     //   1252: ifeq -> 1263
/*    */     //   1255: ldc_w 3.0
/*    */     //   1258: fstore #18
/*    */     //   1260: goto -> 1266
/*    */     //   1263: fconst_2
/*    */     //   1264: fstore #18
/*    */     //   1266: aload #15
/*    */     //   1268: aload #16
/*    */     //   1270: fload #18
/*    */     //   1272: invokevirtual Zz : (F)V
/*    */     //   1275: iconst_1
/*    */     //   1276: anewarray f/UA0
/*    */     //   1279: dup
/*    */     //   1280: astore #15
/*    */     //   1282: aload_0
/*    */     //   1283: getfield tf0 : Lf/UA0;
/*    */     //   1286: iconst_0
/*    */     //   1287: swap
/*    */     //   1288: aastore
/*    */     //   1289: aload #15
/*    */     //   1291: invokevirtual fc0 : ([Lf/UA0;)V
/*    */     //   1294: goto -> 1335
/*    */     //   1297: aload #15
/*    */     //   1299: iconst_1
/*    */     //   1300: anewarray f/zh0
/*    */     //   1303: dup
/*    */     //   1304: iconst_0
/*    */     //   1305: aload #19
/*    */     //   1307: aastore
/*    */     //   1308: invokevirtual sm : ([Lf/zh0;)V
/*    */     //   1311: invokestatic XU : ()Z
/*    */     //   1314: ifeq -> 1325
/*    */     //   1317: ldc_w 3.0
/*    */     //   1320: fstore #16
/*    */     //   1322: goto -> 1328
/*    */     //   1325: fconst_2
/*    */     //   1326: fstore #16
/*    */     //   1328: aload #15
/*    */     //   1330: fload #16
/*    */     //   1332: putfield V1 : F
/*    */     //   1335: iload_1
/*    */     //   1336: aload #14
/*    */     //   1338: aload_0
/*    */     //   1339: getfield r2 : Lf/vF0;
/*    */     //   1342: astore #15
/*    */     //   1344: getfield Dv0 : Lf/SA;
/*    */     //   1347: aload #15
/*    */     //   1349: invokevirtual S7 : (Ljava/lang/Object;)Lf/nJ0;
/*    */     //   1352: pop
/*    */     //   1353: new f/YA0
/*    */     //   1356: dup
/*    */     //   1357: astore #15
/*    */     //   1359: invokespecial <init> : ()V
/*    */     //   1362: new f/dQ
/*    */     //   1365: astore #16
/*    */     //   1367: sipush #5673
/*    */     //   1370: istore #18
/*    */     //   1372: ifle -> 1397
/*    */     //   1375: getstatic f/VF0.Bx : Ljava/text/DecimalFormat;
/*    */     //   1378: iload_2
/*    */     //   1379: i2d
/*    */     //   1380: iload_1
/*    */     //   1381: iconst_2
/*    */     //   1382: imul
/*    */     //   1383: i2d
/*    */     //   1384: ddiv
/*    */     //   1385: ldc2_w 100.0
/*    */     //   1388: dmul
/*    */     //   1389: invokevirtual format : (D)Ljava/lang/String;
/*    */     //   1392: astore #19
/*    */     //   1394: goto -> 1402
/*    */     //   1397: ldc_w '0.00'
/*    */     //   1400: astore #19
/*    */     //   1402: iload #4
/*    */     //   1404: aload #16
/*    */     //   1406: dup
/*    */     //   1407: dup2
/*    */     //   1408: dup2
/*    */     //   1409: iload #18
/*    */     //   1411: aload #19
/*    */     //   1413: invokestatic Go : (ILjava/lang/String;)Ljava/lang/String;
/*    */     //   1416: astore #18
/*    */     //   1418: invokespecial <init> : ()V
/*    */     //   1421: aload #18
/*    */     //   1423: invokevirtual E1 : (Ljava/lang/String;)V
/*    */     //   1426: new java/lang/StringBuilder
/*    */     //   1429: dup
/*    */     //   1430: iload_2
/*    */     //   1431: swap
/*    */     //   1432: invokespecial <init> : ()V
/*    */     //   1435: invokevirtual append : (I)Ljava/lang/StringBuilder;
/*    */     //   1438: ldc_w ' / '
/*    */     //   1441: invokevirtual append : (Ljava/lang/String;)Ljava/lang/StringBuilder;
/*    */     //   1444: iload_1
/*    */     //   1445: iconst_2
/*    */     //   1446: imul
/*    */     //   1447: invokevirtual append : (I)Ljava/lang/StringBuilder;
/*    */     //   1450: invokevirtual toString : ()Ljava/lang/String;
/*    */     //   1453: putfield z4 : Ljava/lang/Object;
/*    */     //   1456: invokevirtual zn : ()V
/*    */     //   1459: iconst_0
/*    */     //   1460: putfield jl : I
/*    */     //   1463: ldc_w '/matchmaking-stats-frame.label-name-monster-tiering-value'
/*    */     //   1466: invokevirtual Xu : (Ljava/lang/String;)V
/*    */     //   1469: new f/dQ
/*    */     //   1472: astore_1
/*    */     //   1473: sipush #5674
/*    */     //   1476: istore #18
/*    */     //   1478: ifle -> 1505
/*    */     //   1481: getstatic f/VF0.Bx : Ljava/text/DecimalFormat;
/*    */     //   1484: iload #5
/*    */     //   1486: i2d
/*    */     //   1487: iload #4
/*    */     //   1489: iconst_2
/*    */     //   1490: imul
/*    */     //   1491: i2d
/*    */     //   1492: ddiv
/*    */     //   1493: ldc2_w 100.0
/*    */     //   1496: dmul
/*    */     //   1497: invokevirtual format : (D)Ljava/lang/String;
/*    */     //   1500: astore #19
/*    */     //   1502: goto -> 1510
/*    */     //   1505: ldc_w '0.00'
/*    */     //   1508: astore #19
/*    */     //   1510: iload #6
/*    */     //   1512: aload_1
/*    */     //   1513: dup
/*    */     //   1514: dup2
/*    */     //   1515: dup2
/*    */     //   1516: iload #18
/*    */     //   1518: aload #19
/*    */     //   1520: invokestatic Go : (ILjava/lang/String;)Ljava/lang/String;
/*    */     //   1523: astore #18
/*    */     //   1525: invokespecial <init> : ()V
/*    */     //   1528: aload #18
/*    */     //   1530: invokevirtual E1 : (Ljava/lang/String;)V
/*    */     //   1533: new java/lang/StringBuilder
/*    */     //   1536: dup
/*    */     //   1537: iload #5
/*    */     //   1539: swap
/*    */     //   1540: invokespecial <init> : ()V
/*    */     //   1543: invokevirtual append : (I)Ljava/lang/StringBuilder;
/*    */     //   1546: ldc_w ' / '
/*    */     //   1549: invokevirtual append : (Ljava/lang/String;)Ljava/lang/StringBuilder;
/*    */     //   1552: iload #4
/*    */     //   1554: iconst_2
/*    */     //   1555: imul
/*    */     //   1556: invokevirtual append : (I)Ljava/lang/StringBuilder;
/*    */     //   1559: invokevirtual toString : ()Ljava/lang/String;
/*    */     //   1562: putfield z4 : Ljava/lang/Object;
/*    */     //   1565: invokevirtual zn : ()V
/*    */     //   1568: iconst_0
/*    */     //   1569: putfield jl : I
/*    */     //   1572: ldc_w '/matchmaking-stats-frame.label-name-monster-tiering-value'
/*    */     //   1575: invokevirtual Xu : (Ljava/lang/String;)V
/*    */     //   1578: new f/dQ
/*    */     //   1581: astore #4
/*    */     //   1583: sipush #5675
/*    */     //   1586: istore #5
/*    */     //   1588: ifle -> 1615
/*    */     //   1591: getstatic f/VF0.Bx : Ljava/text/DecimalFormat;
/*    */     //   1594: iload #7
/*    */     //   1596: i2d
/*    */     //   1597: iload #6
/*    */     //   1599: iconst_2
/*    */     //   1600: imul
/*    */     //   1601: i2d
/*    */     //   1602: ddiv
/*    */     //   1603: ldc2_w 100.0
/*    */     //   1606: dmul
/*    */     //   1607: invokevirtual format : (D)Ljava/lang/String;
/*    */     //   1610: astore #18
/*    */     //   1612: goto -> 1620
/*    */     //   1615: ldc_w '0.00'
/*    */     //   1618: astore #18
/*    */     //   1620: iload_2
/*    */     //   1621: aload #4
/*    */     //   1623: dup
/*    */     //   1624: dup2
/*    */     //   1625: dup2
/*    */     //   1626: iload #5
/*    */     //   1628: aload #18
/*    */     //   1630: invokestatic Go : (ILjava/lang/String;)Ljava/lang/String;
/*    */     //   1633: astore #5
/*    */     //   1635: invokespecial <init> : ()V
/*    */     //   1638: aload #5
/*    */     //   1640: invokevirtual E1 : (Ljava/lang/String;)V
/*    */     //   1643: new java/lang/StringBuilder
/*    */     //   1646: dup
/*    */     //   1647: iload #7
/*    */     //   1649: swap
/*    */     //   1650: invokespecial <init> : ()V
/*    */     //   1653: invokevirtual append : (I)Ljava/lang/StringBuilder;
/*    */     //   1656: ldc_w ' / '
/*    */     //   1659: invokevirtual append : (Ljava/lang/String;)Ljava/lang/StringBuilder;
/*    */     //   1662: iload #6
/*    */     //   1664: iconst_2
/*    */     //   1665: imul
/*    */     //   1666: invokevirtual append : (I)Ljava/lang/StringBuilder;
/*    */     //   1669: invokevirtual toString : ()Ljava/lang/String;
/*    */     //   1672: putfield z4 : Ljava/lang/Object;
/*    */     //   1675: invokevirtual zn : ()V
/*    */     //   1678: iconst_0
/*    */     //   1679: putfield jl : I
/*    */     //   1682: ldc_w '/matchmaking-stats-frame.label-name-monster-tiering-value'
/*    */     //   1685: invokevirtual Xu : (Ljava/lang/String;)V
/*    */     //   1688: new f/dQ
/*    */     //   1691: astore #5
/*    */     //   1693: sipush #5676
/*    */     //   1696: istore #6
/*    */     //   1698: ifle -> 1721
/*    */     //   1701: getstatic f/VF0.Bx : Ljava/text/DecimalFormat;
/*    */     //   1704: iload_3
/*    */     //   1705: i2d
/*    */     //   1706: iload_2
/*    */     //   1707: i2d
/*    */     //   1708: ddiv
/*    */     //   1709: ldc2_w 100.0
/*    */     //   1712: dmul
/*    */     //   1713: invokevirtual format : (D)Ljava/lang/String;
/*    */     //   1716: astore #7
/*    */     //   1718: goto -> 1726
/*    */     //   1721: ldc_w '0.00'
/*    */     //   1724: astore #7
/*    */     //   1726: aload #11
/*    */     //   1728: aload_0
/*    */     //   1729: aload #14
/*    */     //   1731: aload #15
/*    */     //   1733: dup
/*    */     //   1734: dup2
/*    */     //   1735: aload #5
/*    */     //   1737: dup
/*    */     //   1738: dup2
/*    */     //   1739: dup2
/*    */     //   1740: iload #6
/*    */     //   1742: aload #7
/*    */     //   1744: invokestatic Go : (ILjava/lang/String;)Ljava/lang/String;
/*    */     //   1747: astore #6
/*    */     //   1749: invokespecial <init> : ()V
/*    */     //   1752: aload #6
/*    */     //   1754: invokevirtual E1 : (Ljava/lang/String;)V
/*    */     //   1757: new java/lang/StringBuilder
/*    */     //   1760: dup
/*    */     //   1761: iload_3
/*    */     //   1762: swap
/*    */     //   1763: invokespecial <init> : ()V
/*    */     //   1766: invokevirtual append : (I)Ljava/lang/StringBuilder;
/*    */     //   1769: ldc_w ' / '
/*    */     //   1772: invokevirtual append : (Ljava/lang/String;)Ljava/lang/StringBuilder;
/*    */     //   1775: iload_2
/*    */     //   1776: invokevirtual append : (I)Ljava/lang/StringBuilder;
/*    */     //   1779: invokevirtual toString : ()Ljava/lang/String;
/*    */     //   1782: putfield z4 : Ljava/lang/Object;
/*    */     //   1785: invokevirtual zn : ()V
/*    */     //   1788: iconst_0
/*    */     //   1789: putfield jl : I
/*    */     //   1792: ldc_w '/matchmaking-stats-frame.label-name-monster-tiering-value'
/*    */     //   1795: invokevirtual Xu : (Ljava/lang/String;)V
/*    */     //   1798: getfield Dv0 : Lf/SA;
/*    */     //   1801: aload #16
/*    */     //   1803: invokevirtual S7 : (Ljava/lang/Object;)Lf/nJ0;
/*    */     //   1806: pop
/*    */     //   1807: getfield Dv0 : Lf/SA;
/*    */     //   1810: invokevirtual wP : ()Lf/nJ0;
/*    */     //   1813: getfield Ox : Lf/ZP;
/*    */     //   1816: aload_1
/*    */     //   1817: invokevirtual S7 : (Ljava/lang/Object;)Lf/nJ0;
/*    */     //   1820: pop
/*    */     //   1821: getfield Dv0 : Lf/SA;
/*    */     //   1824: invokevirtual wP : ()Lf/nJ0;
/*    */     //   1827: getfield Ox : Lf/ZP;
/*    */     //   1830: aload #4
/*    */     //   1832: invokevirtual S7 : (Ljava/lang/Object;)Lf/nJ0;
/*    */     //   1835: pop
/*    */     //   1836: getfield Dv0 : Lf/SA;
/*    */     //   1839: invokevirtual wP : ()Lf/nJ0;
/*    */     //   1842: getfield Ox : Lf/ZP;
/*    */     //   1845: aload #5
/*    */     //   1847: invokevirtual S7 : (Ljava/lang/Object;)Lf/nJ0;
/*    */     //   1850: pop
/*    */     //   1851: getfield Dv0 : Lf/SA;
/*    */     //   1854: aload #15
/*    */     //   1856: invokevirtual S7 : (Ljava/lang/Object;)Lf/nJ0;
/*    */     //   1859: invokevirtual ti0 : ()Lf/nJ0;
/*    */     //   1862: pop
/*    */     //   1863: getfield qb0 : Lf/YA0;
/*    */     //   1866: getfield Dv0 : Lf/SA;
/*    */     //   1869: invokevirtual wP : ()Lf/nJ0;
/*    */     //   1872: getfield Ox : Lf/ZP;
/*    */     //   1875: aload #14
/*    */     //   1877: invokevirtual S7 : (Ljava/lang/Object;)Lf/nJ0;
/*    */     //   1880: dup
/*    */     //   1881: iconst_3
/*    */     //   1882: invokestatic valueOf : (I)Ljava/lang/Integer;
/*    */     //   1885: putfield ss : Ljava/lang/Integer;
/*    */     //   1888: invokevirtual Kw : ()Lf/nJ0;
/*    */     //   1891: pop
/*    */     //   1892: new f/YA0
/*    */     //   1895: dup
/*    */     //   1896: dup2
/*    */     //   1897: dup2
/*    */     //   1898: astore_1
/*    */     //   1899: invokespecial <init> : ()V
/*    */     //   1902: new f/dQ
/*    */     //   1905: dup
/*    */     //   1906: dup2
/*    */     //   1907: astore_2
/*    */     //   1908: sipush #5677
/*    */     //   1911: invokestatic OH0 : (I)Ljava/lang/String;
/*    */     //   1914: astore #4
/*    */     //   1916: invokespecial <init> : ()V
/*    */     //   1919: aload #4
/*    */     //   1921: invokevirtual E1 : (Ljava/lang/String;)V
/*    */     //   1924: ldc_w '/matchmaking-stats-frame.label-name-monster-tiering'
/*    */     //   1927: invokevirtual Xu : (Ljava/lang/String;)V
/*    */     //   1930: getfield Dv0 : Lf/SA;
/*    */     //   1933: aload_2
/*    */     //   1934: invokevirtual S7 : (Ljava/lang/Object;)Lf/nJ0;
/*    */     //   1937: pop
/*    */     //   1938: new f/dQ
/*    */     //   1941: dup
/*    */     //   1942: dup2
/*    */     //   1943: astore_2
/*    */     //   1944: sipush #5678
/*    */     //   1947: invokestatic OH0 : (I)Ljava/lang/String;
/*    */     //   1950: astore #4
/*    */     //   1952: invokespecial <init> : ()V
/*    */     //   1955: aload #4
/*    */     //   1957: invokevirtual E1 : (Ljava/lang/String;)V
/*    */     //   1960: ldc_w '/matchmaking-stats-frame.label-name-monster-tiering'
/*    */     //   1963: invokevirtual Xu : (Ljava/lang/String;)V
/*    */     //   1966: getfield Dv0 : Lf/SA;
/*    */     //   1969: aload_2
/*    */     //   1970: invokevirtual S7 : (Ljava/lang/Object;)Lf/nJ0;
/*    */     //   1973: pop
/*    */     //   1974: new f/dQ
/*    */     //   1977: dup
/*    */     //   1978: dup2
/*    */     //   1979: astore_2
/*    */     //   1980: sipush #5679
/*    */     //   1983: invokestatic OH0 : (I)Ljava/lang/String;
/*    */     //   1986: astore #4
/*    */     //   1988: invokespecial <init> : ()V
/*    */     //   1991: aload #4
/*    */     //   1993: invokevirtual E1 : (Ljava/lang/String;)V
/*    */     //   1996: ldc_w '/matchmaking-stats-frame.label-name-monster-tiering'
/*    */     //   1999: invokevirtual Xu : (Ljava/lang/String;)V
/*    */     //   2002: getfield Dv0 : Lf/SA;
/*    */     //   2005: aload_2
/*    */     //   2006: invokevirtual S7 : (Ljava/lang/Object;)Lf/nJ0;
/*    */     //   2009: pop
/*    */     //   2010: getfield Dv0 : Lf/SA;
/*    */     //   2013: invokevirtual wP : ()Lf/nJ0;
/*    */     //   2016: pop
/*    */     //   2017: new f/YA0
/*    */     //   2020: dup
/*    */     //   2021: astore_2
/*    */     //   2022: invokespecial <init> : ()V
/*    */     //   2025: arraylength
/*    */     //   2026: istore #4
/*    */     //   2028: iconst_0
/*    */     //   2029: istore #5
/*    */     //   2031: iload #5
/*    */     //   2033: iload #4
/*    */     //   2035: if_icmpge -> 2261
/*    */     //   2038: aload #11
/*    */     //   2040: iload #5
/*    */     //   2042: aaload
/*    */     //   2043: dup
/*    */     //   2044: astore #6
/*    */     //   2046: new f/dQ
/*    */     //   2049: dup
/*    */     //   2050: dup
/*    */     //   2051: astore #7
/*    */     //   2053: new java/lang/StringBuilder
/*    */     //   2056: dup
/*    */     //   2057: aload #6
/*    */     //   2059: swap
/*    */     //   2060: invokespecial <init> : ()V
/*    */     //   2063: getfield Bw : I
/*    */     //   2066: ldc_w 210000
/*    */     //   2069: iadd
/*    */     //   2070: invokestatic OH0 : (I)Ljava/lang/String;
/*    */     //   2073: invokevirtual append : (Ljava/lang/String;)Ljava/lang/StringBuilder;
/*    */     //   2076: ldc_w ' ('
/*    */     //   2079: invokevirtual append : (Ljava/lang/String;)Ljava/lang/StringBuilder;
/*    */     //   2082: getstatic f/VF0.Bx : Ljava/text/DecimalFormat;
/*    */     //   2085: aload #6
/*    */     //   2087: getfield kk0 : I
/*    */     //   2090: i2d
/*    */     //   2091: iload_3
/*    */     //   2092: i2d
/*    */     //   2093: ddiv
/*    */     //   2094: ldc2_w 100.0
/*    */     //   2097: dmul
/*    */     //   2098: invokevirtual format : (D)Ljava/lang/String;
/*    */     //   2101: invokevirtual append : (Ljava/lang/String;)Ljava/lang/StringBuilder;
/*    */     //   2104: ldc_w '%)'
/*    */     //   2107: invokevirtual append : (Ljava/lang/String;)Ljava/lang/StringBuilder;
/*    */     //   2110: invokevirtual toString : ()Ljava/lang/String;
/*    */     //   2113: astore #14
/*    */     //   2115: invokespecial <init> : ()V
/*    */     //   2118: aload #14
/*    */     //   2120: invokevirtual E1 : (Ljava/lang/String;)V
/*    */     //   2123: getfield Bw : I
/*    */     //   2126: i2s
/*    */     //   2127: istore #14
/*    */     //   2129: iconst_0
/*    */     //   2130: istore #15
/*    */     //   2132: iload #15
/*    */     //   2134: aload #13
/*    */     //   2136: getfield Po : [S
/*    */     //   2139: dup
/*    */     //   2140: astore #16
/*    */     //   2142: arraylength
/*    */     //   2143: if_icmpge -> 2169
/*    */     //   2146: aload #16
/*    */     //   2148: iload #15
/*    */     //   2150: saload
/*    */     //   2151: iload #14
/*    */     //   2153: if_icmpne -> 2159
/*    */     //   2156: goto -> 2172
/*    */     //   2159: iload #15
/*    */     //   2161: iconst_1
/*    */     //   2162: iadd
/*    */     //   2163: i2b
/*    */     //   2164: istore #15
/*    */     //   2166: goto -> 2132
/*    */     //   2169: iconst_m1
/*    */     //   2170: istore #15
/*    */     //   2172: iload #15
/*    */     //   2174: iconst_2
/*    */     //   2175: if_icmpne -> 2189
/*    */     //   2178: aload #7
/*    */     //   2180: ldc_w '/matchmaking-stats-frame.label-hidden-ability'
/*    */     //   2183: invokevirtual Xu : (Ljava/lang/String;)V
/*    */     //   2186: goto -> 2197
/*    */     //   2189: aload #7
/*    */     //   2191: ldc_w '/matchmaking-stats-frame.label-name-monster-tiering-value'
/*    */     //   2194: invokevirtual Xu : (Ljava/lang/String;)V
/*    */     //   2197: aload_2
/*    */     //   2198: aload #7
/*    */     //   2200: dup
/*    */     //   2201: dup
/*    */     //   2202: aload #6
/*    */     //   2204: dup
/*    */     //   2205: getfield Bw : I
/*    */     //   2208: istore #6
/*    */     //   2210: getfield kk0 : I
/*    */     //   2213: iload_3
/*    */     //   2214: iload #6
/*    */     //   2216: getstatic f/rG0.J2 : Ljava/text/DecimalFormat;
/*    */     //   2219: pop
/*    */     //   2220: ldc_w 220000
/*    */     //   2223: iadd
/*    */     //   2224: invokestatic OH0 : (I)Ljava/lang/String;
/*    */     //   2227: invokestatic wY : (IILjava/lang/String;)Ljava/lang/String;
/*    */     //   2230: putfield z4 : Ljava/lang/Object;
/*    */     //   2233: invokevirtual zn : ()V
/*    */     //   2236: iconst_0
/*    */     //   2237: putfield jl : I
/*    */     //   2240: getfield Dv0 : Lf/SA;
/*    */     //   2243: invokevirtual wP : ()Lf/nJ0;
/*    */     //   2246: getfield Ox : Lf/ZP;
/*    */     //   2249: aload #7
/*    */     //   2251: invokevirtual S7 : (Ljava/lang/Object;)Lf/nJ0;
/*    */     //   2254: pop
/*    */     //   2255: iinc #5, 1
/*    */     //   2258: goto -> 2031
/*    */     //   2261: aload #9
/*    */     //   2263: aload_1
/*    */     //   2264: getfield Dv0 : Lf/SA;
/*    */     //   2267: aload_2
/*    */     //   2268: invokevirtual S7 : (Ljava/lang/Object;)Lf/nJ0;
/*    */     //   2271: invokevirtual Xs0 : ()Lf/nJ0;
/*    */     //   2274: pop
/*    */     //   2275: new f/YA0
/*    */     //   2278: dup
/*    */     //   2279: astore_2
/*    */     //   2280: invokespecial <init> : ()V
/*    */     //   2283: arraylength
/*    */     //   2284: istore #4
/*    */     //   2286: iconst_0
/*    */     //   2287: istore #5
/*    */     //   2289: iload #5
/*    */     //   2291: iload #4
/*    */     //   2293: if_icmpge -> 2587
/*    */     //   2296: aload #9
/*    */     //   2298: iload #5
/*    */     //   2300: aaload
/*    */     //   2301: dup
/*    */     //   2302: astore #6
/*    */     //   2304: new f/YA0
/*    */     //   2307: dup
/*    */     //   2308: astore #7
/*    */     //   2310: invokespecial <init> : ()V
/*    */     //   2313: bipush #61
/*    */     //   2315: invokestatic OH0 : (I)Ljava/lang/String;
/*    */     //   2318: astore #11
/*    */     //   2320: aconst_null
/*    */     //   2321: astore #13
/*    */     //   2323: getfield Bw : I
/*    */     //   2326: dup
/*    */     //   2327: istore #14
/*    */     //   2329: ifle -> 2375
/*    */     //   2332: aload #6
/*    */     //   2334: getstatic f/Of.eH : Lf/Of;
/*    */     //   2337: iload #14
/*    */     //   2339: i2s
/*    */     //   2340: invokevirtual On0 : (S)Lf/LPT3;
/*    */     //   2343: astore #13
/*    */     //   2345: getfield Bw : I
/*    */     //   2348: sipush #5137
/*    */     //   2351: if_icmpne -> 2365
/*    */     //   2354: sipush #1452
/*    */     //   2357: invokestatic OH0 : (I)Ljava/lang/String;
/*    */     //   2360: astore #11
/*    */     //   2362: goto -> 2375
/*    */     //   2365: aload #13
/*    */     //   2367: getfield Iu : I
/*    */     //   2370: invokestatic OH0 : (I)Ljava/lang/String;
/*    */     //   2373: astore #11
/*    */     //   2375: aload #13
/*    */     //   2377: new f/dQ
/*    */     //   2380: dup
/*    */     //   2381: dup2
/*    */     //   2382: astore #14
/*    */     //   2384: aload #11
/*    */     //   2386: ldc_w ' ('
/*    */     //   2389: invokestatic vz : (Ljava/lang/String;Ljava/lang/String;)Ljava/lang/StringBuilder;
/*    */     //   2392: getstatic f/VF0.Bx : Ljava/text/DecimalFormat;
/*    */     //   2395: aload #6
/*    */     //   2397: getfield kk0 : I
/*    */     //   2400: i2d
/*    */     //   2401: iload_3
/*    */     //   2402: i2d
/*    */     //   2403: ddiv
/*    */     //   2404: ldc2_w 100.0
/*    */     //   2407: dmul
/*    */     //   2408: invokevirtual format : (D)Ljava/lang/String;
/*    */     //   2411: invokevirtual append : (Ljava/lang/String;)Ljava/lang/StringBuilder;
/*    */     //   2414: ldc_w '%)'
/*    */     //   2417: invokevirtual append : (Ljava/lang/String;)Ljava/lang/StringBuilder;
/*    */     //   2420: invokevirtual toString : ()Ljava/lang/String;
/*    */     //   2423: astore #11
/*    */     //   2425: invokespecial <init> : ()V
/*    */     //   2428: aload #11
/*    */     //   2430: invokevirtual E1 : (Ljava/lang/String;)V
/*    */     //   2433: ldc_w '/matchmaking-stats-frame.label-name-monster-tiering-value'
/*    */     //   2436: invokevirtual Xu : (Ljava/lang/String;)V
/*    */     //   2439: ifnull -> 2554
/*    */     //   2442: aload #14
/*    */     //   2444: dup
/*    */     //   2445: dup
/*    */     //   2446: aload #6
/*    */     //   2448: getfield kk0 : I
/*    */     //   2451: iload_3
/*    */     //   2452: aload #13
/*    */     //   2454: bipush #38
/*    */     //   2456: invokevirtual Ey0 : (I)Ljava/lang/String;
/*    */     //   2459: invokestatic wY : (IILjava/lang/String;)Ljava/lang/String;
/*    */     //   2462: putfield z4 : Ljava/lang/Object;
/*    */     //   2465: invokevirtual zn : ()V
/*    */     //   2468: iconst_0
/*    */     //   2469: putfield jl : I
/*    */     //   2472: invokestatic XU : ()Z
/*    */     //   2475: ifeq -> 2503
/*    */     //   2478: new f/vF0
/*    */     //   2481: dup
/*    */     //   2482: dup
/*    */     //   2483: astore #6
/*    */     //   2485: bipush #48
/*    */     //   2487: bipush #48
/*    */     //   2489: iconst_0
/*    */     //   2490: invokespecial <init> : (III)V
/*    */     //   2493: getfield TS : Lf/rH;
/*    */     //   2496: fconst_2
/*    */     //   2497: putfield V1 : F
/*    */     //   2500: goto -> 2517
/*    */     //   2503: new f/vF0
/*    */     //   2506: dup
/*    */     //   2507: astore #6
/*    */     //   2509: bipush #24
/*    */     //   2511: bipush #24
/*    */     //   2513: iconst_0
/*    */     //   2514: invokespecial <init> : (III)V
/*    */     //   2517: aload #7
/*    */     //   2519: aload #6
/*    */     //   2521: getfield TS : Lf/rH;
/*    */     //   2524: iconst_1
/*    */     //   2525: anewarray f/U70
/*    */     //   2528: dup
/*    */     //   2529: getstatic f/wm0.y0 : Lf/wm0;
/*    */     //   2532: aload #13
/*    */     //   2534: iconst_0
/*    */     //   2535: invokevirtual HR : (Lf/LPT3;Z)Lf/U70;
/*    */     //   2538: iconst_0
/*    */     //   2539: swap
/*    */     //   2540: aastore
/*    */     //   2541: invokevirtual qt : ([Lf/U70;)Lf/JG0;
/*    */     //   2544: pop
/*    */     //   2545: getfield Dv0 : Lf/SA;
/*    */     //   2548: aload #6
/*    */     //   2550: invokevirtual S7 : (Ljava/lang/Object;)Lf/nJ0;
/*    */     //   2553: pop
/*    */     //   2554: aload_2
/*    */     //   2555: aload #7
/*    */     //   2557: getfield Dv0 : Lf/SA;
/*    */     //   2560: aload #14
/*    */     //   2562: invokevirtual S7 : (Ljava/lang/Object;)Lf/nJ0;
/*    */     //   2565: pop
/*    */     //   2566: getfield Dv0 : Lf/SA;
/*    */     //   2569: invokevirtual wP : ()Lf/nJ0;
/*    */     //   2572: getfield Ox : Lf/ZP;
/*    */     //   2575: aload #7
/*    */     //   2577: invokevirtual S7 : (Ljava/lang/Object;)Lf/nJ0;
/*    */     //   2580: pop
/*    */     //   2581: iinc #5, 1
/*    */     //   2584: goto -> 2289
/*    */     //   2587: aload #10
/*    */     //   2589: aload_1
/*    */     //   2590: getfield Dv0 : Lf/SA;
/*    */     //   2593: aload_2
/*    */     //   2594: invokevirtual S7 : (Ljava/lang/Object;)Lf/nJ0;
/*    */     //   2597: invokevirtual Xs0 : ()Lf/nJ0;
/*    */     //   2600: pop
/*    */     //   2601: new f/YA0
/*    */     //   2604: dup
/*    */     //   2605: astore_2
/*    */     //   2606: invokespecial <init> : ()V
/*    */     //   2609: arraylength
/*    */     //   2610: istore #4
/*    */     //   2612: iconst_0
/*    */     //   2613: istore #5
/*    */     //   2615: iload #5
/*    */     //   2617: iload #4
/*    */     //   2619: if_icmpge -> 2769
/*    */     //   2622: aload_2
/*    */     //   2623: aload #10
/*    */     //   2625: iload #5
/*    */     //   2627: aaload
/*    */     //   2628: astore #6
/*    */     //   2630: new f/dQ
/*    */     //   2633: dup
/*    */     //   2634: dup2
/*    */     //   2635: astore #7
/*    */     //   2637: aload #6
/*    */     //   2639: aload #7
/*    */     //   2641: dup
/*    */     //   2642: dup
/*    */     //   2643: new java/lang/StringBuilder
/*    */     //   2646: dup
/*    */     //   2647: aload #6
/*    */     //   2649: swap
/*    */     //   2650: invokespecial <init> : ()V
/*    */     //   2653: getfield Bw : I
/*    */     //   2656: i2b
/*    */     //   2657: invokestatic Y4 : (B)Lf/nV;
/*    */     //   2660: invokevirtual cK0 : ()Ljava/lang/String;
/*    */     //   2663: invokevirtual append : (Ljava/lang/String;)Ljava/lang/StringBuilder;
/*    */     //   2666: ldc_w ' ('
/*    */     //   2669: invokevirtual append : (Ljava/lang/String;)Ljava/lang/StringBuilder;
/*    */     //   2672: getstatic f/VF0.Bx : Ljava/text/DecimalFormat;
/*    */     //   2675: aload #6
/*    */     //   2677: getfield kk0 : I
/*    */     //   2680: i2d
/*    */     //   2681: iload_3
/*    */     //   2682: i2d
/*    */     //   2683: ddiv
/*    */     //   2684: ldc2_w 100.0
/*    */     //   2687: dmul
/*    */     //   2688: invokevirtual format : (D)Ljava/lang/String;
/*    */     //   2691: invokevirtual append : (Ljava/lang/String;)Ljava/lang/StringBuilder;
/*    */     //   2694: ldc_w '%)'
/*    */     //   2697: invokevirtual append : (Ljava/lang/String;)Ljava/lang/StringBuilder;
/*    */     //   2700: invokevirtual toString : ()Ljava/lang/String;
/*    */     //   2703: astore #9
/*    */     //   2705: invokespecial <init> : ()V
/*    */     //   2708: aload #9
/*    */     //   2710: invokevirtual E1 : (Ljava/lang/String;)V
/*    */     //   2713: ldc_w '/matchmaking-stats-frame.label-name-monster-tiering-value'
/*    */     //   2716: invokevirtual Xu : (Ljava/lang/String;)V
/*    */     //   2719: getfield kk0 : I
/*    */     //   2722: iload_3
/*    */     //   2723: aload #6
/*    */     //   2725: getfield Bw : I
/*    */     //   2728: i2b
/*    */     //   2729: invokestatic Y4 : (B)Lf/nV;
/*    */     //   2732: invokestatic Em0 : (Lf/nV;)Ljava/lang/String;
/*    */     //   2735: invokestatic wY : (IILjava/lang/String;)Ljava/lang/String;
/*    */     //   2738: putfield z4 : Ljava/lang/Object;
/*    */     //   2741: invokevirtual zn : ()V
/*    */     //   2744: iconst_0
/*    */     //   2745: putfield jl : I
/*    */     //   2748: getfield Dv0 : Lf/SA;
/*    */     //   2751: invokevirtual wP : ()Lf/nJ0;
/*    */     //   2754: getfield Ox : Lf/ZP;
/*    */     //   2757: aload #7
/*    */     //   2759: invokevirtual S7 : (Ljava/lang/Object;)Lf/nJ0;
/*    */     //   2762: pop
/*    */     //   2763: iinc #5, 1
/*    */     //   2766: goto -> 2615
/*    */     //   2769: aload #12
/*    */     //   2771: aload_0
/*    */     //   2772: dup
/*    */     //   2773: dup
/*    */     //   2774: aload_1
/*    */     //   2775: getfield Dv0 : Lf/SA;
/*    */     //   2778: aload_2
/*    */     //   2779: invokevirtual S7 : (Ljava/lang/Object;)Lf/nJ0;
/*    */     //   2782: invokevirtual Xs0 : ()Lf/nJ0;
/*    */     //   2785: pop
/*    */     //   2786: getfield qb0 : Lf/YA0;
/*    */     //   2789: getfield Dv0 : Lf/SA;
/*    */     //   2792: invokevirtual wP : ()Lf/nJ0;
/*    */     //   2795: getfield Ox : Lf/ZP;
/*    */     //   2798: aload_1
/*    */     //   2799: invokevirtual S7 : (Ljava/lang/Object;)Lf/nJ0;
/*    */     //   2802: pop
/*    */     //   2803: new f/dQ
/*    */     //   2806: dup
/*    */     //   2807: dup
/*    */     //   2808: astore_1
/*    */     //   2809: sipush #5680
/*    */     //   2812: invokestatic OH0 : (I)Ljava/lang/String;
/*    */     //   2815: astore_2
/*    */     //   2816: invokespecial <init> : ()V
/*    */     //   2819: aload_2
/*    */     //   2820: invokevirtual E1 : (Ljava/lang/String;)V
/*    */     //   2823: getfield qb0 : Lf/YA0;
/*    */     //   2826: getfield Dv0 : Lf/SA;
/*    */     //   2829: invokevirtual wP : ()Lf/nJ0;
/*    */     //   2832: getfield Ox : Lf/ZP;
/*    */     //   2835: aload_1
/*    */     //   2836: invokevirtual S7 : (Ljava/lang/Object;)Lf/nJ0;
/*    */     //   2839: invokevirtual fu : ()Lf/nJ0;
/*    */     //   2842: pop
/*    */     //   2843: getfield qb0 : Lf/YA0;
/*    */     //   2846: getfield Dv0 : Lf/SA;
/*    */     //   2849: invokevirtual wP : ()Lf/nJ0;
/*    */     //   2852: pop
/*    */     //   2853: new f/YA0
/*    */     //   2856: dup
/*    */     //   2857: astore_2
/*    */     //   2858: invokespecial <init> : ()V
/*    */     //   2861: new f/YA0
/*    */     //   2864: dup
/*    */     //   2865: astore #4
/*    */     //   2867: invokespecial <init> : ()V
/*    */     //   2870: iconst_0
/*    */     //   2871: istore #5
/*    */     //   2873: arraylength
/*    */     //   2874: istore #6
/*    */     //   2876: iconst_0
/*    */     //   2877: istore #7
/*    */     //   2879: iload #7
/*    */     //   2881: iload #6
/*    */     //   2883: if_icmpge -> 3291
/*    */     //   2886: iload #17
/*    */     //   2888: aload #12
/*    */     //   2890: iload #7
/*    */     //   2892: aaload
/*    */     //   2893: dup
/*    */     //   2894: astore #9
/*    */     //   2896: getfield Bw : I
/*    */     //   2899: i2s
/*    */     //   2900: istore #10
/*    */     //   2902: ifeq -> 2996
/*    */     //   2905: new f/Un
/*    */     //   2908: dup
/*    */     //   2909: dup
/*    */     //   2910: astore #11
/*    */     //   2912: aload_0
/*    */     //   2913: iload #10
/*    */     //   2915: aload #11
/*    */     //   2917: new java/lang/StringBuilder
/*    */     //   2920: dup
/*    */     //   2921: iload #10
/*    */     //   2923: swap
/*    */     //   2924: invokespecial <init> : ()V
/*    */     //   2927: ldc_w 150000
/*    */     //   2930: iadd
/*    */     //   2931: invokestatic OH0 : (I)Ljava/lang/String;
/*    */     //   2934: invokevirtual append : (Ljava/lang/String;)Ljava/lang/StringBuilder;
/*    */     //   2937: ldc_w ' ('
/*    */     //   2940: invokevirtual append : (Ljava/lang/String;)Ljava/lang/StringBuilder;
/*    */     //   2943: getstatic f/VF0.Bx : Ljava/text/DecimalFormat;
/*    */     //   2946: aload #9
/*    */     //   2948: getfield kk0 : I
/*    */     //   2951: i2d
/*    */     //   2952: iload_3
/*    */     //   2953: i2d
/*    */     //   2954: ddiv
/*    */     //   2955: ldc2_w 100.0
/*    */     //   2958: dmul
/*    */     //   2959: invokevirtual format : (D)Ljava/lang/String;
/*    */     //   2962: invokevirtual append : (Ljava/lang/String;)Ljava/lang/StringBuilder;
/*    */     //   2965: ldc_w '%)'
/*    */     //   2968: invokevirtual append : (Ljava/lang/String;)Ljava/lang/StringBuilder;
/*    */     //   2971: invokevirtual toString : ()Ljava/lang/String;
/*    */     //   2974: invokespecial <init> : (Ljava/lang/String;)V
/*    */     //   2977: iload #8
/*    */     //   2979: <illegal opcode> run : (Lf/jd;SS)Ljava/lang/Runnable;
/*    */     //   2984: invokevirtual tW : (Ljava/lang/Runnable;)V
/*    */     //   2987: ldc_w '/matchmaking-stats-frame.label-name-monster-tiering-button'
/*    */     //   2990: invokevirtual Xu : (Ljava/lang/String;)V
/*    */     //   2993: goto -> 3076
/*    */     //   2996: new f/dQ
/*    */     //   2999: dup
/*    */     //   3000: dup2
/*    */     //   3001: astore #11
/*    */     //   3003: new java/lang/StringBuilder
/*    */     //   3006: dup
/*    */     //   3007: iload #10
/*    */     //   3009: swap
/*    */     //   3010: invokespecial <init> : ()V
/*    */     //   3013: ldc_w 150000
/*    */     //   3016: iadd
/*    */     //   3017: invokestatic OH0 : (I)Ljava/lang/String;
/*    */     //   3020: invokevirtual append : (Ljava/lang/String;)Ljava/lang/StringBuilder;
/*    */     //   3023: ldc_w ' ('
/*    */     //   3026: invokevirtual append : (Ljava/lang/String;)Ljava/lang/StringBuilder;
/*    */     //   3029: getstatic f/VF0.Bx : Ljava/text/DecimalFormat;
/*    */     //   3032: aload #9
/*    */     //   3034: getfield kk0 : I
/*    */     //   3037: i2d
/*    */     //   3038: iload_3
/*    */     //   3039: i2d
/*    */     //   3040: ddiv
/*    */     //   3041: ldc2_w 100.0
/*    */     //   3044: dmul
/*    */     //   3045: invokevirtual format : (D)Ljava/lang/String;
/*    */     //   3048: invokevirtual append : (Ljava/lang/String;)Ljava/lang/StringBuilder;
/*    */     //   3051: ldc_w '%)'
/*    */     //   3054: invokevirtual append : (Ljava/lang/String;)Ljava/lang/StringBuilder;
/*    */     //   3057: invokevirtual toString : ()Ljava/lang/String;
/*    */     //   3060: astore #13
/*    */     //   3062: invokespecial <init> : ()V
/*    */     //   3065: aload #13
/*    */     //   3067: invokevirtual E1 : (Ljava/lang/String;)V
/*    */     //   3070: ldc_w '/matchmaking-stats-frame.label-name-monster-tiering'
/*    */     //   3073: invokevirtual Xu : (Ljava/lang/String;)V
/*    */     //   3076: aload #11
/*    */     //   3078: dup
/*    */     //   3079: new java/lang/StringBuilder
/*    */     //   3082: dup
/*    */     //   3083: aload #9
/*    */     //   3085: swap
/*    */     //   3086: invokespecial <init> : ()V
/*    */     //   3089: getfield kk0 : I
/*    */     //   3092: invokevirtual append : (I)Ljava/lang/StringBuilder;
/*    */     //   3095: ldc_w ' / '
/*    */     //   3098: invokevirtual append : (Ljava/lang/String;)Ljava/lang/StringBuilder;
/*    */     //   3101: iload_3
/*    */     //   3102: invokevirtual append : (I)Ljava/lang/StringBuilder;
/*    */     //   3105: invokevirtual toString : ()Ljava/lang/String;
/*    */     //   3108: invokevirtual Gq0 : (Ljava/lang/Object;)V
/*    */     //   3111: iconst_0
/*    */     //   3112: putfield jl : I
/*    */     //   3115: invokestatic XU : ()Z
/*    */     //   3118: ifeq -> 3157
/*    */     //   3121: new f/vF0
/*    */     //   3124: dup
/*    */     //   3125: dup2
/*    */     //   3126: astore #9
/*    */     //   3128: bipush #64
/*    */     //   3130: bipush #64
/*    */     //   3132: iconst_0
/*    */     //   3133: invokespecial <init> : (III)V
/*    */     //   3136: getfield TS : Lf/rH;
/*    */     //   3139: bipush #-2
/*    */     //   3141: bipush #-12
/*    */     //   3143: invokevirtual zT : (II)Lf/JG0;
/*    */     //   3146: pop
/*    */     //   3147: getfield TS : Lf/rH;
/*    */     //   3150: fconst_2
/*    */     //   3151: putfield V1 : F
/*    */     //   3154: goto -> 3183
/*    */     //   3157: new f/vF0
/*    */     //   3160: dup
/*    */     //   3161: dup
/*    */     //   3162: astore #9
/*    */     //   3164: bipush #32
/*    */     //   3166: bipush #32
/*    */     //   3168: iconst_0
/*    */     //   3169: invokespecial <init> : (III)V
/*    */     //   3172: getfield TS : Lf/rH;
/*    */     //   3175: bipush #-2
/*    */     //   3177: bipush #-6
/*    */     //   3179: invokevirtual zT : (II)Lf/JG0;
/*    */     //   3182: pop
/*    */     //   3183: aload #9
/*    */     //   3185: invokestatic v30 : ()Lf/On;
/*    */     //   3188: iload #10
/*    */     //   3190: invokevirtual lpT3 : (S)Lf/UD0;
/*    */     //   3193: astore #10
/*    */     //   3195: getfield TS : Lf/rH;
/*    */     //   3198: iconst_1
/*    */     //   3199: anewarray f/zh0
/*    */     //   3202: dup
/*    */     //   3203: getstatic f/um0.Kt0 : Lf/um0;
/*    */     //   3206: aload #10
/*    */     //   3208: dup
/*    */     //   3209: invokevirtual Qo0 : ()Lf/UD0;
/*    */     //   3212: getfield AP : S
/*    */     //   3215: istore #10
/*    */     //   3217: getfield D3 : B
/*    */     //   3220: iload #10
/*    */     //   3222: invokestatic HZ : (BS)S
/*    */     //   3225: iconst_0
/*    */     //   3226: iconst_0
/*    */     //   3227: invokevirtual lb : (SZB)[Lf/zh0;
/*    */     //   3230: iconst_0
/*    */     //   3231: aaload
/*    */     //   3232: iconst_0
/*    */     //   3233: swap
/*    */     //   3234: aastore
/*    */     //   3235: invokevirtual sm : ([Lf/zh0;)V
/*    */     //   3238: iload #5
/*    */     //   3240: iconst_1
/*    */     //   3241: iadd
/*    */     //   3242: dup
/*    */     //   3243: istore #5
/*    */     //   3245: bipush #8
/*    */     //   3247: if_icmpgt -> 3260
/*    */     //   3250: aload_2
/*    */     //   3251: getfield Dv0 : Lf/SA;
/*    */     //   3254: invokevirtual wP : ()Lf/nJ0;
/*    */     //   3257: goto -> 3268
/*    */     //   3260: aload #4
/*    */     //   3262: getfield Dv0 : Lf/SA;
/*    */     //   3265: invokevirtual wP : ()Lf/nJ0;
/*    */     //   3268: getfield Ox : Lf/ZP;
/*    */     //   3271: aload #9
/*    */     //   3273: invokevirtual S7 : (Ljava/lang/Object;)Lf/nJ0;
/*    */     //   3276: getfield Ox : Lf/ZP;
/*    */     //   3279: aload #11
/*    */     //   3281: invokevirtual S7 : (Ljava/lang/Object;)Lf/nJ0;
/*    */     //   3284: pop
/*    */     //   3285: iinc #7, 1
/*    */     //   3288: goto -> 2879
/*    */     //   3291: aload_0
/*    */     //   3292: dup
/*    */     //   3293: dup
/*    */     //   3294: dup2
/*    */     //   3295: aload_1
/*    */     //   3296: aload_0
/*    */     //   3297: new f/YA0
/*    */     //   3300: dup
/*    */     //   3301: dup2
/*    */     //   3302: astore_1
/*    */     //   3303: invokespecial <init> : ()V
/*    */     //   3306: getfield Dv0 : Lf/SA;
/*    */     //   3309: aload_2
/*    */     //   3310: invokevirtual S7 : (Ljava/lang/Object;)Lf/nJ0;
/*    */     //   3313: invokevirtual Xs0 : ()Lf/nJ0;
/*    */     //   3316: pop
/*    */     //   3317: getfield Dv0 : Lf/SA;
/*    */     //   3320: aload #4
/*    */     //   3322: invokevirtual S7 : (Ljava/lang/Object;)Lf/nJ0;
/*    */     //   3325: invokevirtual Xs0 : ()Lf/nJ0;
/*    */     //   3328: pop
/*    */     //   3329: getfield qb0 : Lf/YA0;
/*    */     //   3332: getfield Dv0 : Lf/SA;
/*    */     //   3335: aload_1
/*    */     //   3336: invokevirtual S7 : (Ljava/lang/Object;)Lf/nJ0;
/*    */     //   3339: pop
/*    */     //   3340: ldc_w '/matchmaking-stats-frame.label-name-monster-tiering'
/*    */     //   3343: invokevirtual Xu : (Ljava/lang/String;)V
/*    */     //   3346: new f/Un
/*    */     //   3349: dup
/*    */     //   3350: astore_1
/*    */     //   3351: aload_0
/*    */     //   3352: aload_1
/*    */     //   3353: sipush #5681
/*    */     //   3356: invokestatic OH0 : (I)Ljava/lang/String;
/*    */     //   3359: invokespecial <init> : (Ljava/lang/String;)V
/*    */     //   3362: <illegal opcode> run : (Lf/jd;)Ljava/lang/Runnable;
/*    */     //   3367: invokevirtual tW : (Ljava/lang/Runnable;)V
/*    */     //   3370: getfield qb0 : Lf/YA0;
/*    */     //   3373: getfield Dv0 : Lf/SA;
/*    */     //   3376: invokevirtual wP : ()Lf/nJ0;
/*    */     //   3379: pop
/*    */     //   3380: getfield qb0 : Lf/YA0;
/*    */     //   3383: getfield Dv0 : Lf/SA;
/*    */     //   3386: aload_1
/*    */     //   3387: invokevirtual S7 : (Ljava/lang/Object;)Lf/nJ0;
/*    */     //   3390: dup
/*    */     //   3391: iconst_3
/*    */     //   3392: invokestatic valueOf : (I)Ljava/lang/Integer;
/*    */     //   3395: putfield ss : Ljava/lang/Integer;
/*    */     //   3398: invokevirtual Kw : ()Lf/nJ0;
/*    */     //   3401: pop
/*    */     //   3402: getfield Sz0 : Lf/rS;
/*    */     //   3405: aload_0
/*    */     //   3406: getfield qb0 : Lf/YA0;
/*    */     //   3409: invokevirtual Gz0 : (Lf/JG0;)V
/*    */     //   3412: getfield Sz0 : Lf/rS;
/*    */     //   3415: iconst_0
/*    */     //   3416: invokevirtual rt : (I)V
/*    */     //   3419: getfield UK : Lf/Li0;
/*    */     //   3422: getfield EC0 : Lf/JG0;
/*    */     //   3425: dup
/*    */     //   3426: astore_1
/*    */     //   3427: aload_0
/*    */     //   3428: getfield mj0 : Lf/Ip;
/*    */     //   3431: if_acmpne -> 3449
/*    */     //   3434: aload_0
/*    */     //   3435: aload_1
/*    */     //   3436: invokevirtual gx : ()V
/*    */     //   3439: getfield UK : Lf/Li0;
/*    */     //   3442: aload_0
/*    */     //   3443: getfield Sz0 : Lf/rS;
/*    */     //   3446: invokevirtual qs0 : (Lf/JG0;)V
/*    */     //   3449: return
/*    */     // Line number table:
/*    */     //   Java source line number -> byte code offset
/*    */     //   #1	-> 26
/*    */     //   #2	-> 37
/*    */     //   #3	-> 40
/*    */     //   #4	-> 87
/*    */     //   #5	-> 144
/*    */     //   #6	-> 161
/*    */     //   #7	-> 169
/*    */     //   #8	-> 193
/*    */     //   #9	-> 218
/*    */     //   #10	-> 255
/*    */     //   #11	-> 258
/*    */     //   #12	-> 263
/*    */     //   #13	-> 264
/*    */     //   #14	-> 267
/*    */     //   #15	-> 270
/*    */     //   #16	-> 275
/*    */     //   #17	-> 286
/*    */     //   #18	-> 298
/*    */     //   #19	-> 307
/*    */     //   #20	-> 315
/*    */     //   #21	-> 318
/*    */     //   #22	-> 329
/*    */     //   #23	-> 366
/*    */     //   #24	-> 369
/*    */     //   #25	-> 374
/*    */     //   #26	-> 375
/*    */     //   #27	-> 378
/*    */     //   #28	-> 381
/*    */     //   #29	-> 386
/*    */     //   #30	-> 397
/*    */     //   #31	-> 415
/*    */     //   #32	-> 421
/*    */     //   #33	-> 444
/*    */     //   #34	-> 449
/*    */     //   #35	-> 457
/*    */     //   #36	-> 465
/*    */     //   #37	-> 475
/*    */     //   #38	-> 509
/*    */     //   #39	-> 512
/*    */     //   #40	-> 540
/*    */     //   #41	-> 545
/*    */     //   #42	-> 553
/*    */     //   #43	-> 583
/*    */     //   #44	-> 594
/*    */     //   #45	-> 597
/*    */     //   #46	-> 605
/*    */     //   #47	-> 630
/*    */     //   #48	-> 638
/*    */     //   #49	-> 659
/*    */     //   #50	-> 662
/*    */     //   #51	-> 667
/*    */     //   #52	-> 670
/*    */     //   #53	-> 673
/*    */     //   #54	-> 683
/*    */     //   #55	-> 761
/*    */     //   #56	-> 769
/*    */     //   #57	-> 775
/*    */     //   #58	-> 786
/*    */     //   #59	-> 793
/*    */     //   #60	-> 799
/*    */     //   #61	-> 824
/*    */     //   #62	-> 832
/*    */     //   #63	-> 870
/*    */     //   #64	-> 878
/*    */     //   #65	-> 885
/*    */     //   #66	-> 896
/*    */     //   #67	-> 899
/*    */     //   #68	-> 904
/*    */     //   #69	-> 908
/*    */     //   #70	-> 938
/*    */     //   #71	-> 941
/*    */     //   #72	-> 946
/*    */     //   #73	-> 954
/*    */     //   #74	-> 976
/*    */     //   #75	-> 979
/*    */     //   #76	-> 984
/*    */     //   #77	-> 991
/*    */     //   #78	-> 999
/*    */     //   #79	-> 1002
/*    */     //   #80	-> 1007
/*    */     //   #81	-> 1012
/*    */     //   #82	-> 1017
/*    */     //   #83	-> 1066
/*    */     //   #84	-> 1075
/*    */     //   #85	-> 1094
/*    */     //   #86	-> 1103
/*    */     //   #87	-> 1111
/*    */     //   #88	-> 1120
/*    */     //   #89	-> 1152
/*    */     //   #90	-> 1155
/*    */     //   #91	-> 1164
/*    */     //   #92	-> 1170
/*    */     //   #93	-> 1179
/*    */     //   #94	-> 1196
/*    */     //   #95	-> 1206
/*    */     //   #96	-> 1227
/*    */     //   #97	-> 1230
/*    */     //   #98	-> 1332
/*    */     //   #99	-> 1339
/*    */     //   #100	-> 1344
/*    */     //   #101	-> 1353
/*    */     //   #102	-> 1418
/*    */     //   #103	-> 1426
/*    */     //   #104	-> 1453
/*    */     //   #105	-> 1460
/*    */     //   #106	-> 1463
/*    */     //   #107	-> 1525
/*    */     //   #108	-> 1533
/*    */     //   #109	-> 1562
/*    */     //   #110	-> 1569
/*    */     //   #111	-> 1572
/*    */     //   #112	-> 1635
/*    */     //   #113	-> 1643
/*    */     //   #114	-> 1672
/*    */     //   #115	-> 1679
/*    */     //   #116	-> 1682
/*    */     //   #117	-> 1749
/*    */     //   #118	-> 1757
/*    */     //   #119	-> 1782
/*    */     //   #120	-> 1789
/*    */     //   #121	-> 1792
/*    */     //   #122	-> 1798
/*    */     //   #123	-> 1807
/*    */     //   #124	-> 1813
/*    */     //   #125	-> 1817
/*    */     //   #126	-> 1821
/*    */     //   #127	-> 1827
/*    */     //   #128	-> 1832
/*    */     //   #129	-> 1836
/*    */     //   #130	-> 1842
/*    */     //   #131	-> 1847
/*    */     //   #132	-> 1851
/*    */     //   #133	-> 1859
/*    */     //   #134	-> 1866
/*    */     //   #135	-> 1869
/*    */     //   #136	-> 1872
/*    */     //   #137	-> 1877
/*    */     //   #138	-> 1882
/*    */     //   #139	-> 1885
/*    */     //   #140	-> 1888
/*    */     //   #141	-> 1916
/*    */     //   #142	-> 1924
/*    */     //   #143	-> 1930
/*    */     //   #144	-> 1938
/*    */     //   #145	-> 1952
/*    */     //   #146	-> 1960
/*    */     //   #147	-> 1966
/*    */     //   #148	-> 1974
/*    */     //   #149	-> 1988
/*    */     //   #150	-> 1996
/*    */     //   #151	-> 2002
/*    */     //   #152	-> 2010
/*    */     //   #153	-> 2017
/*    */     //   #154	-> 2063
/*    */     //   #155	-> 2070
/*    */     //   #156	-> 2087
/*    */     //   #157	-> 2098
/*    */     //   #158	-> 2115
/*    */     //   #159	-> 2123
/*    */     //   #160	-> 2136
/*    */     //   #161	-> 2180
/*    */     //   #162	-> 2205
/*    */     //   #163	-> 2210
/*    */     //   #164	-> 2216
/*    */     //   #165	-> 2224
/*    */     //   #166	-> 2230
/*    */     //   #167	-> 2237
/*    */     //   #168	-> 2240
/*    */     //   #169	-> 2246
/*    */     //   #170	-> 2251
/*    */     //   #171	-> 2264
/*    */     //   #172	-> 2271
/*    */     //   #173	-> 2323
/*    */     //   #174	-> 2334
/*    */     //   #175	-> 2340
/*    */     //   #176	-> 2345
/*    */     //   #177	-> 2357
/*    */     //   #178	-> 2367
/*    */     //   #179	-> 2377
/*    */     //   #180	-> 2386
/*    */     //   #181	-> 2392
/*    */     //   #182	-> 2397
/*    */     //   #183	-> 2408
/*    */     //   #184	-> 2425
/*    */     //   #185	-> 2433
/*    */     //   #186	-> 2448
/*    */     //   #187	-> 2456
/*    */     //   #188	-> 2459
/*    */     //   #189	-> 2462
/*    */     //   #190	-> 2469
/*    */     //   #191	-> 2472
/*    */     //   #192	-> 2490
/*    */     //   #193	-> 2493
/*    */     //   #194	-> 2497
/*    */     //   #195	-> 2503
/*    */     //   #196	-> 2514
/*    */     //   #197	-> 2521
/*    */     //   #198	-> 2525
/*    */     //   #199	-> 2529
/*    */     //   #200	-> 2535
/*    */     //   #201	-> 2540
/*    */     //   #202	-> 2545
/*    */     //   #203	-> 2566
/*    */     //   #204	-> 2572
/*    */     //   #205	-> 2577
/*    */     //   #206	-> 2590
/*    */     //   #207	-> 2597
/*    */     //   #208	-> 2653
/*    */     //   #209	-> 2657
/*    */     //   #210	-> 2677
/*    */     //   #211	-> 2688
/*    */     //   #212	-> 2705
/*    */     //   #213	-> 2713
/*    */     //   #214	-> 2719
/*    */     //   #215	-> 2725
/*    */     //   #216	-> 2729
/*    */     //   #217	-> 2738
/*    */     //   #218	-> 2745
/*    */     //   #219	-> 2748
/*    */     //   #220	-> 2754
/*    */     //   #221	-> 2759
/*    */     //   #222	-> 2775
/*    */     //   #223	-> 2782
/*    */     //   #224	-> 2789
/*    */     //   #225	-> 2792
/*    */     //   #226	-> 2795
/*    */     //   #227	-> 2799
/*    */     //   #228	-> 2803
/*    */     //   #229	-> 2816
/*    */     //   #230	-> 2823
/*    */     //   #231	-> 2826
/*    */     //   #232	-> 2829
/*    */     //   #233	-> 2832
/*    */     //   #234	-> 2836
/*    */     //   #235	-> 2839
/*    */     //   #236	-> 2846
/*    */     //   #237	-> 2849
/*    */     //   #238	-> 2853
/*    */     //   #239	-> 2896
/*    */     //   #240	-> 2905
/*    */     //   #241	-> 2948
/*    */     //   #242	-> 2959
/*    */     //   #243	-> 3034
/*    */     //   #244	-> 3045
/*    */     //   #245	-> 3062
/*    */     //   #246	-> 3070
/*    */     //   #247	-> 3089
/*    */     //   #248	-> 3092
/*    */     //   #249	-> 3112
/*    */     //   #250	-> 3115
/*    */     //   #251	-> 3133
/*    */     //   #252	-> 3136
/*    */     //   #253	-> 3143
/*    */     //   #254	-> 3147
/*    */     //   #255	-> 3151
/*    */     //   #256	-> 3157
/*    */     //   #257	-> 3169
/*    */     //   #258	-> 3172
/*    */     //   #259	-> 3179
/*    */     //   #260	-> 3195
/*    */     //   #261	-> 3199
/*    */     //   #262	-> 3203
/*    */     //   #263	-> 3209
/*    */     //   #264	-> 3212
/*    */     //   #265	-> 3217
/*    */     //   #266	-> 3222
/*    */     //   #267	-> 3251
/*    */     //   #268	-> 3268
/*    */     //   #269	-> 3273
/*    */     //   #270	-> 3297
/*    */     //   #271	-> 3306
/*    */     //   #272	-> 3313
/*    */     //   #273	-> 3317
/*    */     //   #274	-> 3325
/*    */     //   #275	-> 3332
/*    */     //   #276	-> 3336
/*    */     //   #277	-> 3340
/*    */     //   #278	-> 3373
/*    */     //   #279	-> 3376
/*    */     //   #280	-> 3380
/*    */     //   #281	-> 3383
/*    */     //   #282	-> 3387
/*    */     //   #283	-> 3392
/*    */     //   #284	-> 3395
/*    */     //   #285	-> 3398
/*    */     //   #286	-> 3422
/*    */     //   #287	-> 3428
/*    */   }
/*    */   
/*    */   public final JG0 sl() {
/*    */     YA0 yA0;
/*    */     if ((yA0 = this.qb0) != null)
/*    */       return yA0; 
/*    */     if ((yA0 = this.af0) != null)
/*    */       return yA0; 
/*    */     String str = Ml0.OH0(74);
/*    */     (new dQ()).E1(str);
/*    */     (new dQ()).Xu("/matchmaking-stats-frame.label-tiering-updated-time");
/*    */     UB0.Kg0.fN(this::T3);
/*    */     return new dQ();
/*    */   }
/*    */   
/*    */   public final Ip oc(boolean paramBoolean) {
/*    */     // Byte code:
/*    */     //   0: aload_0
/*    */     //   1: getfield r2 : Lf/vF0;
/*    */     //   4: dup
/*    */     //   5: astore_2
/*    */     //   6: ifnull -> 16
/*    */     //   9: aload_2
/*    */     //   10: getfield TS : Lf/rH;
/*    */     //   13: invokevirtual H : ()V
/*    */     //   16: aload_0
/*    */     //   17: getfield ba : Lf/fQ;
/*    */     //   20: invokevirtual r30 : ()Lf/Hc0;
/*    */     //   23: astore_2
/*    */     //   24: aload_2
/*    */     //   25: invokevirtual hasNext : ()Z
/*    */     //   28: ifeq -> 46
/*    */     //   31: aload_2
/*    */     //   32: invokevirtual next : ()Ljava/lang/Object;
/*    */     //   35: checkcast f/iq0
/*    */     //   38: invokeinterface dispose : ()V
/*    */     //   43: goto -> 24
/*    */     //   46: aload_0
/*    */     //   47: dup
/*    */     //   48: dup
/*    */     //   49: aconst_null
/*    */     //   50: putfield tf0 : Lf/UA0;
/*    */     //   53: aconst_null
/*    */     //   54: putfield qb0 : Lf/YA0;
/*    */     //   57: getfield mj0 : Lf/Ip;
/*    */     //   60: ifnull -> 67
/*    */     //   63: iload_1
/*    */     //   64: ifeq -> 446
/*    */     //   67: aload_0
/*    */     //   68: dup
/*    */     //   69: new f/Ip
/*    */     //   72: dup
/*    */     //   73: invokespecial <init> : ()V
/*    */     //   76: putfield mj0 : Lf/Ip;
/*    */     //   79: new f/rS
/*    */     //   82: dup
/*    */     //   83: aload_0
/*    */     //   84: swap
/*    */     //   85: dup
/*    */     //   86: aconst_null
/*    */     //   87: invokespecial <init> : (Lf/JG0;)V
/*    */     //   90: putfield Sz0 : Lf/rS;
/*    */     //   93: new f/dQ
/*    */     //   96: dup
/*    */     //   97: dup
/*    */     //   98: bipush #74
/*    */     //   100: invokestatic OH0 : (I)Ljava/lang/String;
/*    */     //   103: astore_1
/*    */     //   104: invokespecial <init> : ()V
/*    */     //   107: aload_1
/*    */     //   108: invokevirtual E1 : (Ljava/lang/String;)V
/*    */     //   111: invokevirtual Gz0 : (Lf/JG0;)V
/*    */     //   114: new java/util/ArrayList
/*    */     //   117: dup
/*    */     //   118: astore_1
/*    */     //   119: invokespecial <init> : ()V
/*    */     //   122: ldc 'UTC'
/*    */     //   124: invokestatic of : (Ljava/lang/String;)Ljava/time/ZoneId;
/*    */     //   127: invokestatic now : (Ljava/time/ZoneId;)Ljava/time/YearMonth;
/*    */     //   130: dup
/*    */     //   131: astore_2
/*    */     //   132: invokevirtual getMonthValue : ()I
/*    */     //   135: i2b
/*    */     //   136: putfield RA : B
/*    */     //   139: iconst_0
/*    */     //   140: istore_3
/*    */     //   141: iload_3
/*    */     //   142: aload_0
/*    */     //   143: getfield Lx : B
/*    */     //   146: if_icmpge -> 166
/*    */     //   149: aload_1
/*    */     //   150: aload_2
/*    */     //   151: iload_3
/*    */     //   152: i2l
/*    */     //   153: invokevirtual minusMonths : (J)Ljava/time/YearMonth;
/*    */     //   156: invokevirtual add : (Ljava/lang/Object;)Z
/*    */     //   159: pop
/*    */     //   160: iinc #3, 1
/*    */     //   163: goto -> 141
/*    */     //   166: aload_0
/*    */     //   167: new f/OZ
/*    */     //   170: dup
/*    */     //   171: astore_2
/*    */     //   172: aload_1
/*    */     //   173: invokespecial <init> : (Ljava/util/Collection;)V
/*    */     //   176: new f/W1
/*    */     //   179: dup
/*    */     //   180: astore_1
/*    */     //   181: aload_0
/*    */     //   182: aload_1
/*    */     //   183: dup
/*    */     //   184: aload_2
/*    */     //   185: aload_1
/*    */     //   186: invokespecial <init> : ()V
/*    */     //   189: invokevirtual rk0 : (Lf/cQ;)V
/*    */     //   192: putfield aj0 : Lf/W1;
/*    */     //   195: iconst_0
/*    */     //   196: invokevirtual Z30 : (I)V
/*    */     //   199: getfield aj0 : Lf/W1;
/*    */     //   202: aload_0
/*    */     //   203: <illegal opcode> run : (Lf/jd;)Ljava/lang/Runnable;
/*    */     //   208: invokevirtual D30 : (Ljava/lang/Runnable;)V
/*    */     //   211: new f/of
/*    */     //   214: dup
/*    */     //   215: astore_1
/*    */     //   216: aload_0
/*    */     //   217: aload_1
/*    */     //   218: aload_0
/*    */     //   219: aload_1
/*    */     //   220: dup
/*    */     //   221: aconst_null
/*    */     //   222: invokespecial <init> : (Lf/Sa0;)V
/*    */     //   225: putfield VW : Lf/of;
/*    */     //   228: iconst_1
/*    */     //   229: putfield n00 : Z
/*    */     //   232: <illegal opcode> SX : (Lf/jd;)Lf/a70;
/*    */     //   237: invokevirtual JD0 : (Lf/a70;)V
/*    */     //   240: invokestatic ER : ()Z
/*    */     //   243: ifeq -> 259
/*    */     //   246: aload_0
/*    */     //   247: getfield VW : Lf/of;
/*    */     //   250: aload_0
/*    */     //   251: <illegal opcode> Nj0 : (Lf/jd;)Lf/CF0;
/*    */     //   256: invokevirtual Aw0 : (Lf/CF0;)V
/*    */     //   259: aload_0
/*    */     //   260: dup
/*    */     //   261: dup
/*    */     //   262: getfield mj0 : Lf/Ip;
/*    */     //   265: dup
/*    */     //   266: dup
/*    */     //   267: astore_1
/*    */     //   268: iconst_1
/*    */     //   269: anewarray f/U90
/*    */     //   272: dup
/*    */     //   273: aload_1
/*    */     //   274: invokevirtual getClass : ()Ljava/lang/Class;
/*    */     //   277: pop
/*    */     //   278: new f/cr0
/*    */     //   281: dup
/*    */     //   282: aload_1
/*    */     //   283: invokespecial <init> : (Lf/Ip;)V
/*    */     //   286: invokevirtual Em0 : ()Lf/U90;
/*    */     //   289: iconst_2
/*    */     //   290: anewarray f/JG0
/*    */     //   293: dup
/*    */     //   294: dup
/*    */     //   295: aload_0
/*    */     //   296: swap
/*    */     //   297: aload_0
/*    */     //   298: getfield aj0 : Lf/W1;
/*    */     //   301: iconst_0
/*    */     //   302: swap
/*    */     //   303: aastore
/*    */     //   304: getfield VW : Lf/of;
/*    */     //   307: iconst_1
/*    */     //   308: swap
/*    */     //   309: aastore
/*    */     //   310: invokevirtual Mg : ([Lf/JG0;)Lf/U90;
/*    */     //   313: invokevirtual Em0 : ()Lf/U90;
/*    */     //   316: iconst_0
/*    */     //   317: swap
/*    */     //   318: aastore
/*    */     //   319: invokevirtual Yw0 : ([Lf/U90;)Lf/U90;
/*    */     //   322: aload_0
/*    */     //   323: getfield mj0 : Lf/Ip;
/*    */     //   326: iconst_1
/*    */     //   327: anewarray f/JG0
/*    */     //   330: dup
/*    */     //   331: aload_0
/*    */     //   332: getfield Sz0 : Lf/rS;
/*    */     //   335: iconst_0
/*    */     //   336: swap
/*    */     //   337: aastore
/*    */     //   338: invokevirtual AUX : ([Lf/JG0;)Lf/U90;
/*    */     //   341: invokevirtual ee0 : (Lf/U90;)Lf/U90;
/*    */     //   344: invokevirtual rK0 : (Lf/U90;)V
/*    */     //   347: getfield mj0 : Lf/Ip;
/*    */     //   350: dup
/*    */     //   351: dup
/*    */     //   352: astore_1
/*    */     //   353: iconst_1
/*    */     //   354: anewarray f/U90
/*    */     //   357: dup
/*    */     //   358: aload_1
/*    */     //   359: dup
/*    */     //   360: invokestatic X60 : (Lf/Ip;Lf/Ip;)Lf/g0;
/*    */     //   363: iconst_2
/*    */     //   364: anewarray f/JG0
/*    */     //   367: dup
/*    */     //   368: dup
/*    */     //   369: aload_0
/*    */     //   370: swap
/*    */     //   371: aload_0
/*    */     //   372: getfield aj0 : Lf/W1;
/*    */     //   375: iconst_0
/*    */     //   376: swap
/*    */     //   377: aastore
/*    */     //   378: getfield VW : Lf/of;
/*    */     //   381: iconst_1
/*    */     //   382: swap
/*    */     //   383: aastore
/*    */     //   384: invokevirtual Mg : ([Lf/JG0;)Lf/U90;
/*    */     //   387: iconst_0
/*    */     //   388: swap
/*    */     //   389: aastore
/*    */     //   390: invokevirtual Gs : ([Lf/U90;)Lf/U90;
/*    */     //   393: aload_0
/*    */     //   394: getfield mj0 : Lf/Ip;
/*    */     //   397: iconst_1
/*    */     //   398: anewarray f/JG0
/*    */     //   401: dup
/*    */     //   402: aload_0
/*    */     //   403: getfield Sz0 : Lf/rS;
/*    */     //   406: iconst_0
/*    */     //   407: swap
/*    */     //   408: aastore
/*    */     //   409: invokevirtual vo0 : ([Lf/JG0;)Lf/U90;
/*    */     //   412: invokevirtual ee0 : (Lf/U90;)Lf/U90;
/*    */     //   415: invokevirtual WN : (Lf/U90;)V
/*    */     //   418: getfield p2 : Lf/ec0;
/*    */     //   421: getfield aU : Lf/DO;
/*    */     //   424: getstatic f/DO.JO : Lf/DO;
/*    */     //   427: if_acmpne -> 437
/*    */     //   430: getstatic f/yG0.VC0 : Ljava/util/Comparator;
/*    */     //   433: astore_1
/*    */     //   434: goto -> 441
/*    */     //   437: getstatic f/yG0.AG0 : Ljava/util/Comparator;
/*    */     //   440: astore_1
/*    */     //   441: aload_0
/*    */     //   442: aload_1
/*    */     //   443: putfield y50 : Ljava/util/Comparator;
/*    */     //   446: aload_0
/*    */     //   447: dup
/*    */     //   448: dup
/*    */     //   449: new f/YA0
/*    */     //   452: dup
/*    */     //   453: invokespecial <init> : ()V
/*    */     //   456: putfield af0 : Lf/YA0;
/*    */     //   459: new f/dQ
/*    */     //   462: dup
/*    */     //   463: dup
/*    */     //   464: sipush #5650
/*    */     //   467: ldc_w '-'
/*    */     //   470: invokestatic Go : (ILjava/lang/String;)Ljava/lang/String;
/*    */     //   473: astore_1
/*    */     //   474: invokespecial <init> : ()V
/*    */     //   477: aload_1
/*    */     //   478: invokevirtual E1 : (Ljava/lang/String;)V
/*    */     //   481: putfield MK0 : Lf/dQ;
/*    */     //   484: getfield Ou0 : Lf/Gu0;
/*    */     //   487: ifnonnull -> 543
/*    */     //   490: aload_0
/*    */     //   491: dup
/*    */     //   492: dup
/*    */     //   493: new f/dQ
/*    */     //   496: dup
/*    */     //   497: dup2
/*    */     //   498: astore_1
/*    */     //   499: bipush #74
/*    */     //   501: invokestatic OH0 : (I)Ljava/lang/String;
/*    */     //   504: astore_2
/*    */     //   505: invokespecial <init> : ()V
/*    */     //   508: aload_2
/*    */     //   509: invokevirtual E1 : (Ljava/lang/String;)V
/*    */     //   512: ldc_w '/matchmaking-stats-frame.label-tiering-updated-time'
/*    */     //   515: invokevirtual Xu : (Ljava/lang/String;)V
/*    */     //   518: getfield af0 : Lf/YA0;
/*    */     //   521: getfield Dv0 : Lf/SA;
/*    */     //   524: aload_1
/*    */     //   525: invokevirtual S7 : (Ljava/lang/Object;)Lf/nJ0;
/*    */     //   528: pop
/*    */     //   529: getfield Sz0 : Lf/rS;
/*    */     //   532: aload_0
/*    */     //   533: getfield af0 : Lf/YA0;
/*    */     //   536: invokevirtual Gz0 : (Lf/JG0;)V
/*    */     //   539: getfield mj0 : Lf/Ip;
/*    */     //   542: areturn
/*    */     //   543: new java/util/ArrayList
/*    */     //   546: dup
/*    */     //   547: dup
/*    */     //   548: astore_1
/*    */     //   549: aload_0
/*    */     //   550: aload_1
/*    */     //   551: aload_0
/*    */     //   552: getfield Ou0 : Lf/Gu0;
/*    */     //   555: getfield y70 : Lf/qw0;
/*    */     //   558: dup
/*    */     //   559: astore_2
/*    */     //   560: invokevirtual getClass : ()Ljava/lang/Class;
/*    */     //   563: pop
/*    */     //   564: new f/iL
/*    */     //   567: dup
/*    */     //   568: aload_2
/*    */     //   569: invokespecial <init> : (Lf/qw0;)V
/*    */     //   572: invokespecial <init> : (Ljava/util/Collection;)V
/*    */     //   575: getfield y50 : Ljava/util/Comparator;
/*    */     //   578: invokestatic sort : (Ljava/util/List;Ljava/util/Comparator;)V
/*    */     //   581: invokevirtual size : ()I
/*    */     //   584: iconst_1
/*    */     //   585: if_icmpge -> 642
/*    */     //   588: aload_0
/*    */     //   589: dup
/*    */     //   590: dup
/*    */     //   591: new f/dQ
/*    */     //   594: dup
/*    */     //   595: dup2
/*    */     //   596: astore_1
/*    */     //   597: sipush #5633
/*    */     //   600: invokestatic OH0 : (I)Ljava/lang/String;
/*    */     //   603: astore_2
/*    */     //   604: invokespecial <init> : ()V
/*    */     //   607: aload_2
/*    */     //   608: invokevirtual E1 : (Ljava/lang/String;)V
/*    */     //   611: ldc_w '/matchmaking-stats-frame.label-tiering-updated-time'
/*    */     //   614: invokevirtual Xu : (Ljava/lang/String;)V
/*    */     //   617: getfield af0 : Lf/YA0;
/*    */     //   620: getfield Dv0 : Lf/SA;
/*    */     //   623: aload_1
/*    */     //   624: invokevirtual S7 : (Ljava/lang/Object;)Lf/nJ0;
/*    */     //   627: pop
/*    */     //   628: getfield Sz0 : Lf/rS;
/*    */     //   631: aload_0
/*    */     //   632: getfield af0 : Lf/YA0;
/*    */     //   635: invokevirtual Gz0 : (Lf/JG0;)V
/*    */     //   638: getfield mj0 : Lf/Ip;
/*    */     //   641: areturn
/*    */     //   642: aload_0
/*    */     //   643: dup
/*    */     //   644: getfield Ou0 : Lf/Gu0;
/*    */     //   647: getfield q3 : I
/*    */     //   650: dup
/*    */     //   651: istore_2
/*    */     //   652: iconst_2
/*    */     //   653: imul
/*    */     //   654: istore_3
/*    */     //   655: ldc_w ''
/*    */     //   658: invokestatic A : (Ljava/lang/String;)Lf/dQ;
/*    */     //   661: astore #4
/*    */     //   663: new f/dQ
/*    */     //   666: dup
/*    */     //   667: dup
/*    */     //   668: astore #5
/*    */     //   670: sipush #9155
/*    */     //   673: invokestatic OH0 : (I)Ljava/lang/String;
/*    */     //   676: astore #6
/*    */     //   678: invokespecial <init> : ()V
/*    */     //   681: aload #6
/*    */     //   683: invokevirtual E1 : (Ljava/lang/String;)V
/*    */     //   686: getfield p2 : Lf/ec0;
/*    */     //   689: getfield aU : Lf/DO;
/*    */     //   692: getstatic f/DO.JO : Lf/DO;
/*    */     //   695: if_acmpne -> 726
/*    */     //   698: new f/Un
/*    */     //   701: dup
/*    */     //   702: astore #6
/*    */     //   704: aload_0
/*    */     //   705: aload #6
/*    */     //   707: bipush #59
/*    */     //   709: invokestatic OH0 : (I)Ljava/lang/String;
/*    */     //   712: invokespecial <init> : (Ljava/lang/String;)V
/*    */     //   715: <illegal opcode> run : (Lf/jd;)Ljava/lang/Runnable;
/*    */     //   720: invokevirtual tW : (Ljava/lang/Runnable;)V
/*    */     //   723: goto -> 752
/*    */     //   726: new f/Un
/*    */     //   729: dup
/*    */     //   730: astore #6
/*    */     //   732: aload_0
/*    */     //   733: aload #6
/*    */     //   735: sipush #5671
/*    */     //   738: invokestatic OH0 : (I)Ljava/lang/String;
/*    */     //   741: invokespecial <init> : (Ljava/lang/String;)V
/*    */     //   744: <illegal opcode> run : (Lf/jd;)Ljava/lang/Runnable;
/*    */     //   749: invokevirtual tW : (Ljava/lang/Runnable;)V
/*    */     //   752: aload_0
/*    */     //   753: new f/Un
/*    */     //   756: dup
/*    */     //   757: astore #7
/*    */     //   759: aload #6
/*    */     //   761: aload #5
/*    */     //   763: aload #4
/*    */     //   765: aload #7
/*    */     //   767: aload_0
/*    */     //   768: aload #7
/*    */     //   770: sipush #5666
/*    */     //   773: invokestatic OH0 : (I)Ljava/lang/String;
/*    */     //   776: invokespecial <init> : (Ljava/lang/String;)V
/*    */     //   779: <illegal opcode> run : (Lf/jd;)Ljava/lang/Runnable;
/*    */     //   784: invokevirtual tW : (Ljava/lang/Runnable;)V
/*    */     //   787: ldc_w '/matchmaking-stats-frame.label-title-monster-sprite'
/*    */     //   790: invokevirtual Xu : (Ljava/lang/String;)V
/*    */     //   793: ldc_w '/matchmaking-stats-frame.label-name-tiering-overview'
/*    */     //   796: invokevirtual Xu : (Ljava/lang/String;)V
/*    */     //   799: ldc_w '/matchmaking-stats-frame.label-winpercent'
/*    */     //   802: invokevirtual Xu : (Ljava/lang/String;)V
/*    */     //   805: ldc_w '/matchmaking-stats-frame.label-winpercent'
/*    */     //   808: invokevirtual Xu : (Ljava/lang/String;)V
/*    */     //   811: getfield af0 : Lf/YA0;
/*    */     //   814: getfield Dv0 : Lf/SA;
/*    */     //   817: dup
/*    */     //   818: astore #8
/*    */     //   820: aload #7
/*    */     //   822: aload #8
/*    */     //   824: aload #6
/*    */     //   826: aload #8
/*    */     //   828: aload #5
/*    */     //   830: aload #8
/*    */     //   832: aload #4
/*    */     //   834: invokevirtual S7 : (Ljava/lang/Object;)Lf/nJ0;
/*    */     //   837: pop
/*    */     //   838: invokevirtual S7 : (Ljava/lang/Object;)Lf/nJ0;
/*    */     //   841: pop
/*    */     //   842: invokevirtual S7 : (Ljava/lang/Object;)Lf/nJ0;
/*    */     //   845: pop
/*    */     //   846: invokevirtual S7 : (Ljava/lang/Object;)Lf/nJ0;
/*    */     //   849: pop
/*    */     //   850: getstatic f/km.u4 : Lf/R8;
/*    */     //   853: invokevirtual Zm : ()B
/*    */     //   856: aload_0
/*    */     //   857: getfield p2 : Lf/ec0;
/*    */     //   860: getfield aU : Lf/DO;
/*    */     //   863: getfield bC : B
/*    */     //   866: if_icmplt -> 875
/*    */     //   869: iconst_1
/*    */     //   870: istore #4
/*    */     //   872: goto -> 878
/*    */     //   875: iconst_0
/*    */     //   876: istore #4
/*    */     //   878: aload_1
/*    */     //   879: invokevirtual iterator : ()Ljava/util/Iterator;
/*    */     //   882: astore_1
/*    */     //   883: aload_1
/*    */     //   884: invokeinterface hasNext : ()Z
/*    */     //   889: ifeq -> 1506
/*    */     //   892: aload_0
/*    */     //   893: aload_1
/*    */     //   894: invokeinterface next : ()Ljava/lang/Object;
/*    */     //   899: checkcast f/yG0
/*    */     //   902: dup
/*    */     //   903: astore #5
/*    */     //   905: getfield Vo : S
/*    */     //   908: istore #6
/*    */     //   910: invokestatic v30 : ()Lf/On;
/*    */     //   913: iload #6
/*    */     //   915: invokevirtual lpT3 : (S)Lf/UD0;
/*    */     //   918: astore #7
/*    */     //   920: getfield VW : Lf/of;
/*    */     //   923: getfield F2 : Lf/ak0;
/*    */     //   926: getfield PH0 : Ljava/lang/StringBuilder;
/*    */     //   929: invokevirtual toString : ()Ljava/lang/String;
/*    */     //   932: invokevirtual isEmpty : ()Z
/*    */     //   935: ifne -> 972
/*    */     //   938: aload #7
/*    */     //   940: iconst_0
/*    */     //   941: invokevirtual o60 : (Z)Ljava/lang/String;
/*    */     //   944: invokevirtual toLowerCase : ()Ljava/lang/String;
/*    */     //   947: aload_0
/*    */     //   948: getfield VW : Lf/of;
/*    */     //   951: getfield F2 : Lf/ak0;
/*    */     //   954: getfield PH0 : Ljava/lang/StringBuilder;
/*    */     //   957: invokevirtual toString : ()Ljava/lang/String;
/*    */     //   960: invokevirtual toLowerCase : ()Ljava/lang/String;
/*    */     //   963: invokevirtual startsWith : (Ljava/lang/String;)Z
/*    */     //   966: ifne -> 972
/*    */     //   969: goto -> 883
/*    */     //   972: aload #7
/*    */     //   974: dup
/*    */     //   975: dup
/*    */     //   976: invokevirtual Qo0 : ()Lf/UD0;
/*    */     //   979: getfield AP : S
/*    */     //   982: istore #9
/*    */     //   984: getfield D3 : B
/*    */     //   987: istore #10
/*    */     //   989: invokevirtual Qo0 : ()Lf/UD0;
/*    */     //   992: aload #7
/*    */     //   994: if_acmpeq -> 1003
/*    */     //   997: iconst_1
/*    */     //   998: istore #11
/*    */     //   1000: goto -> 1006
/*    */     //   1003: iconst_0
/*    */     //   1004: istore #11
/*    */     //   1006: iload #4
/*    */     //   1008: ifeq -> 1053
/*    */     //   1011: new f/Un
/*    */     //   1014: dup
/*    */     //   1015: dup
/*    */     //   1016: astore #12
/*    */     //   1018: aload_0
/*    */     //   1019: aload #12
/*    */     //   1021: dup
/*    */     //   1022: aload #7
/*    */     //   1024: iload #11
/*    */     //   1026: invokevirtual o60 : (Z)Ljava/lang/String;
/*    */     //   1029: invokespecial <init> : (Ljava/lang/String;)V
/*    */     //   1032: iload #6
/*    */     //   1034: aload #5
/*    */     //   1036: <illegal opcode> run : (Lf/jd;Lf/Un;SLf/yG0;)Ljava/lang/Runnable;
/*    */     //   1041: invokevirtual tW : (Ljava/lang/Runnable;)V
/*    */     //   1044: ldc_w '/matchmaking-stats-frame.label-name-tiering-overview-button'
/*    */     //   1047: invokevirtual Xu : (Ljava/lang/String;)V
/*    */     //   1050: goto -> 1083
/*    */     //   1053: new f/dQ
/*    */     //   1056: dup
/*    */     //   1057: dup2
/*    */     //   1058: astore #12
/*    */     //   1060: aload #7
/*    */     //   1062: iload #11
/*    */     //   1064: invokevirtual o60 : (Z)Ljava/lang/String;
/*    */     //   1067: astore #6
/*    */     //   1069: invokespecial <init> : ()V
/*    */     //   1072: aload #6
/*    */     //   1074: invokevirtual E1 : (Ljava/lang/String;)V
/*    */     //   1077: ldc_w '/matchmaking-stats-frame.label-name-tiering-overview-label'
/*    */     //   1080: invokevirtual Xu : (Ljava/lang/String;)V
/*    */     //   1083: invokestatic XU : ()Z
/*    */     //   1086: ifeq -> 1122
/*    */     //   1089: new f/vF0
/*    */     //   1092: dup
/*    */     //   1093: dup
/*    */     //   1094: astore #6
/*    */     //   1096: bipush #72
/*    */     //   1098: bipush #72
/*    */     //   1100: iconst_0
/*    */     //   1101: invokespecial <init> : (III)V
/*    */     //   1104: getfield TS : Lf/rH;
/*    */     //   1107: dup
/*    */     //   1108: fconst_2
/*    */     //   1109: putfield V1 : F
/*    */     //   1112: iconst_0
/*    */     //   1113: bipush #-5
/*    */     //   1115: invokevirtual zT : (II)Lf/JG0;
/*    */     //   1118: pop
/*    */     //   1119: goto -> 1148
/*    */     //   1122: new f/vF0
/*    */     //   1125: dup
/*    */     //   1126: dup
/*    */     //   1127: astore #6
/*    */     //   1129: bipush #32
/*    */     //   1131: bipush #32
/*    */     //   1133: iconst_0
/*    */     //   1134: invokespecial <init> : (III)V
/*    */     //   1137: getfield TS : Lf/rH;
/*    */     //   1140: bipush #-2
/*    */     //   1142: bipush #-6
/*    */     //   1144: invokevirtual zT : (II)Lf/JG0;
/*    */     //   1147: pop
/*    */     //   1148: aload_0
/*    */     //   1149: aload #5
/*    */     //   1151: dup
/*    */     //   1152: aload #6
/*    */     //   1154: getfield TS : Lf/rH;
/*    */     //   1157: iconst_1
/*    */     //   1158: anewarray f/zh0
/*    */     //   1161: dup
/*    */     //   1162: getstatic f/um0.Kt0 : Lf/um0;
/*    */     //   1165: iload #10
/*    */     //   1167: iload #9
/*    */     //   1169: invokestatic HZ : (BS)S
/*    */     //   1172: iconst_0
/*    */     //   1173: iconst_0
/*    */     //   1174: invokevirtual lb : (SZB)[Lf/zh0;
/*    */     //   1177: iconst_0
/*    */     //   1178: aaload
/*    */     //   1179: iconst_0
/*    */     //   1180: swap
/*    */     //   1181: aastore
/*    */     //   1182: invokevirtual sm : ([Lf/zh0;)V
/*    */     //   1185: getfield IE : I
/*    */     //   1188: istore #7
/*    */     //   1190: getfield iA : I
/*    */     //   1193: istore #9
/*    */     //   1195: getfield p2 : Lf/ec0;
/*    */     //   1198: getfield aU : Lf/DO;
/*    */     //   1201: getstatic f/DO.JO : Lf/DO;
/*    */     //   1204: if_acmpne -> 1252
/*    */     //   1207: aload #5
/*    */     //   1209: new f/dQ
/*    */     //   1212: astore #10
/*    */     //   1214: getfield L30 : B
/*    */     //   1217: dup
/*    */     //   1218: istore #11
/*    */     //   1220: ifle -> 1233
/*    */     //   1223: iload #11
/*    */     //   1225: invokestatic toString : (I)Ljava/lang/String;
/*    */     //   1228: astore #11
/*    */     //   1230: goto -> 1238
/*    */     //   1233: ldc_w '-'
/*    */     //   1236: astore #11
/*    */     //   1238: aload #10
/*    */     //   1240: dup
/*    */     //   1241: invokespecial <init> : ()V
/*    */     //   1244: aload #11
/*    */     //   1246: invokevirtual E1 : (Ljava/lang/String;)V
/*    */     //   1249: goto -> 1341
/*    */     //   1252: new f/dQ
/*    */     //   1255: dup
/*    */     //   1256: dup2
/*    */     //   1257: dup2
/*    */     //   1258: astore #10
/*    */     //   1260: new java/lang/StringBuilder
/*    */     //   1263: dup
/*    */     //   1264: invokespecial <init> : ()V
/*    */     //   1267: getstatic f/VF0.Bx : Ljava/text/DecimalFormat;
/*    */     //   1270: iload #9
/*    */     //   1272: i2d
/*    */     //   1273: iload_3
/*    */     //   1274: i2d
/*    */     //   1275: ddiv
/*    */     //   1276: ldc2_w 100.0
/*    */     //   1279: dmul
/*    */     //   1280: invokevirtual format : (D)Ljava/lang/String;
/*    */     //   1283: invokevirtual append : (Ljava/lang/String;)Ljava/lang/StringBuilder;
/*    */     //   1286: ldc_w '%'
/*    */     //   1289: invokevirtual append : (Ljava/lang/String;)Ljava/lang/StringBuilder;
/*    */     //   1292: invokevirtual toString : ()Ljava/lang/String;
/*    */     //   1295: astore #11
/*    */     //   1297: invokespecial <init> : ()V
/*    */     //   1300: aload #11
/*    */     //   1302: invokevirtual E1 : (Ljava/lang/String;)V
/*    */     //   1305: new java/lang/StringBuilder
/*    */     //   1308: dup
/*    */     //   1309: iload #9
/*    */     //   1311: swap
/*    */     //   1312: invokespecial <init> : ()V
/*    */     //   1315: invokevirtual append : (I)Ljava/lang/StringBuilder;
/*    */     //   1318: ldc_w ' / '
/*    */     //   1321: invokevirtual append : (Ljava/lang/String;)Ljava/lang/StringBuilder;
/*    */     //   1324: iload_3
/*    */     //   1325: invokevirtual append : (I)Ljava/lang/StringBuilder;
/*    */     //   1328: invokevirtual toString : ()Ljava/lang/String;
/*    */     //   1331: putfield z4 : Ljava/lang/Object;
/*    */     //   1334: invokevirtual zn : ()V
/*    */     //   1337: iconst_0
/*    */     //   1338: putfield jl : I
/*    */     //   1341: aload #8
/*    */     //   1343: dup
/*    */     //   1344: aload #10
/*    */     //   1346: aload #8
/*    */     //   1348: aload #12
/*    */     //   1350: aload #8
/*    */     //   1352: aload #6
/*    */     //   1354: aload #8
/*    */     //   1356: aload #10
/*    */     //   1358: new f/dQ
/*    */     //   1361: dup
/*    */     //   1362: dup
/*    */     //   1363: dup2
/*    */     //   1364: dup2
/*    */     //   1365: astore #6
/*    */     //   1367: new java/lang/StringBuilder
/*    */     //   1370: dup
/*    */     //   1371: invokespecial <init> : ()V
/*    */     //   1374: getstatic f/VF0.Bx : Ljava/text/DecimalFormat;
/*    */     //   1377: aload #5
/*    */     //   1379: getfield g20 : F
/*    */     //   1382: f2d
/*    */     //   1383: invokevirtual format : (D)Ljava/lang/String;
/*    */     //   1386: invokevirtual append : (Ljava/lang/String;)Ljava/lang/StringBuilder;
/*    */     //   1389: ldc_w '%'
/*    */     //   1392: invokevirtual append : (Ljava/lang/String;)Ljava/lang/StringBuilder;
/*    */     //   1395: invokevirtual toString : ()Ljava/lang/String;
/*    */     //   1398: astore #5
/*    */     //   1400: invokespecial <init> : ()V
/*    */     //   1403: aload #5
/*    */     //   1405: invokevirtual E1 : (Ljava/lang/String;)V
/*    */     //   1408: new java/lang/StringBuilder
/*    */     //   1411: dup
/*    */     //   1412: iload #7
/*    */     //   1414: swap
/*    */     //   1415: invokespecial <init> : ()V
/*    */     //   1418: invokevirtual append : (I)Ljava/lang/StringBuilder;
/*    */     //   1421: ldc_w ' / '
/*    */     //   1424: invokevirtual append : (Ljava/lang/String;)Ljava/lang/StringBuilder;
/*    */     //   1427: iload #9
/*    */     //   1429: invokevirtual append : (I)Ljava/lang/StringBuilder;
/*    */     //   1432: invokevirtual toString : ()Ljava/lang/String;
/*    */     //   1435: putfield z4 : Ljava/lang/Object;
/*    */     //   1438: invokevirtual zn : ()V
/*    */     //   1441: iconst_0
/*    */     //   1442: putfield jl : I
/*    */     //   1445: ldc_w '/matchmaking-stats-frame.label-winpercent-value'
/*    */     //   1448: invokevirtual Xu : (Ljava/lang/String;)V
/*    */     //   1451: ldc_w '/matchmaking-stats-frame.label-winpercent-value'
/*    */     //   1454: invokevirtual Xu : (Ljava/lang/String;)V
/*    */     //   1457: invokevirtual wP : ()Lf/nJ0;
/*    */     //   1460: astore #5
/*    */     //   1462: invokevirtual S7 : (Ljava/lang/Object;)Lf/nJ0;
/*    */     //   1465: pop
/*    */     //   1466: invokevirtual S7 : (Ljava/lang/Object;)Lf/nJ0;
/*    */     //   1469: pop
/*    */     //   1470: invokevirtual S7 : (Ljava/lang/Object;)Lf/nJ0;
/*    */     //   1473: pop
/*    */     //   1474: aload #6
/*    */     //   1476: invokevirtual S7 : (Ljava/lang/Object;)Lf/nJ0;
/*    */     //   1479: pop
/*    */     //   1480: invokestatic Nr : ()Z
/*    */     //   1483: ifeq -> 883
/*    */     //   1486: aload #5
/*    */     //   1488: dup
/*    */     //   1489: getstatic f/Ir.Sp0 : Lf/mg;
/*    */     //   1492: dup
/*    */     //   1493: astore #5
/*    */     //   1495: putfield YX : Lf/Ir;
/*    */     //   1498: aload #5
/*    */     //   1500: putfield Qj0 : Lf/Ir;
/*    */     //   1503: goto -> 883
/*    */     //   1506: aload_0
/*    */     //   1507: aload #8
/*    */     //   1509: dup
/*    */     //   1510: aload_0
/*    */     //   1511: aload #8
/*    */     //   1513: aload_0
/*    */     //   1514: dup
/*    */     //   1515: ldc_w '\\n'
/*    */     //   1518: invokestatic df : (Ljava/lang/String;)Ljava/lang/StringBuilder;
/*    */     //   1521: iload_2
/*    */     //   1522: invokestatic toString : (I)Ljava/lang/String;
/*    */     //   1525: sipush #5672
/*    */     //   1528: swap
/*    */     //   1529: invokestatic Go : (ILjava/lang/String;)Ljava/lang/String;
/*    */     //   1532: invokevirtual append : (Ljava/lang/String;)Ljava/lang/StringBuilder;
/*    */     //   1535: ldc_w '\\n'
/*    */     //   1538: invokevirtual append : (Ljava/lang/String;)Ljava/lang/StringBuilder;
/*    */     //   1541: aload_0
/*    */     //   1542: getfield iI : Lf/VF0;
/*    */     //   1545: getfield gh0 : Ljava/text/DateFormat;
/*    */     //   1548: aload_0
/*    */     //   1549: getfield Ou0 : Lf/Gu0;
/*    */     //   1552: getfield vl0 : I
/*    */     //   1555: i2l
/*    */     //   1556: ldc2_w 1000
/*    */     //   1559: lmul
/*    */     //   1560: invokestatic valueOf : (J)Ljava/lang/Long;
/*    */     //   1563: invokevirtual format : (Ljava/lang/Object;)Ljava/lang/String;
/*    */     //   1566: sipush #5650
/*    */     //   1569: swap
/*    */     //   1570: invokestatic Go : (ILjava/lang/String;)Ljava/lang/String;
/*    */     //   1573: invokevirtual append : (Ljava/lang/String;)Ljava/lang/StringBuilder;
/*    */     //   1576: invokevirtual toString : ()Ljava/lang/String;
/*    */     //   1579: astore_1
/*    */     //   1580: getfield MK0 : Lf/dQ;
/*    */     //   1583: aload_1
/*    */     //   1584: invokevirtual E1 : (Ljava/lang/String;)V
/*    */     //   1587: getfield MK0 : Lf/dQ;
/*    */     //   1590: ldc_w '/matchmaking-stats-frame.label-tiering-updated-time'
/*    */     //   1593: invokevirtual Xu : (Ljava/lang/String;)V
/*    */     //   1596: invokevirtual wP : ()Lf/nJ0;
/*    */     //   1599: invokevirtual ti0 : ()Lf/nJ0;
/*    */     //   1602: bipush #99
/*    */     //   1604: invokestatic valueOf : (I)Ljava/lang/Integer;
/*    */     //   1607: putfield ss : Ljava/lang/Integer;
/*    */     //   1610: getfield MK0 : Lf/dQ;
/*    */     //   1613: invokevirtual S7 : (Ljava/lang/Object;)Lf/nJ0;
/*    */     //   1616: pop
/*    */     //   1617: ldc_w 20.0
/*    */     //   1620: invokevirtual Dl0 : (F)V
/*    */     //   1623: getfield Sz0 : Lf/rS;
/*    */     //   1626: aload_0
/*    */     //   1627: getfield af0 : Lf/YA0;
/*    */     //   1630: invokevirtual Gz0 : (Lf/JG0;)V
/*    */     //   1633: invokestatic Nr : ()Z
/*    */     //   1636: ifeq -> 1721
/*    */     //   1639: aload_0
/*    */     //   1640: getfield g4 : I
/*    */     //   1643: iconst_1
/*    */     //   1644: if_icmpge -> 1700
/*    */     //   1647: aload #8
/*    */     //   1649: getfield iO : Z
/*    */     //   1652: ifeq -> 1660
/*    */     //   1655: aload #8
/*    */     //   1657: invokevirtual r3 : ()V
/*    */     //   1660: aload_0
/*    */     //   1661: aload #8
/*    */     //   1663: getfield xx : F
/*    */     //   1666: fstore_1
/*    */     //   1667: getfield Sz0 : Lf/rS;
/*    */     //   1670: getfield z9 : Lf/JG0;
/*    */     //   1673: getfield xY : I
/*    */     //   1676: i2f
/*    */     //   1677: fload_1
/*    */     //   1678: fsub
/*    */     //   1679: f2i
/*    */     //   1680: dup
/*    */     //   1681: istore_1
/*    */     //   1682: ifge -> 1689
/*    */     //   1685: iload_1
/*    */     //   1686: iconst_m1
/*    */     //   1687: imul
/*    */     //   1688: istore_1
/*    */     //   1689: iload_1
/*    */     //   1690: ifle -> 1700
/*    */     //   1693: aload_0
/*    */     //   1694: iload_1
/*    */     //   1695: iconst_2
/*    */     //   1696: idiv
/*    */     //   1697: putfield g4 : I
/*    */     //   1700: aload #8
/*    */     //   1702: aload_0
/*    */     //   1703: getfield g4 : I
/*    */     //   1706: i2f
/*    */     //   1707: invokevirtual to : (F)Lf/ZP;
/*    */     //   1710: checkcast f/SA
/*    */     //   1713: aload_0
/*    */     //   1714: getfield g4 : I
/*    */     //   1717: i2f
/*    */     //   1718: invokevirtual Ty0 : (F)V
/*    */     //   1721: aload_0
/*    */     //   1722: getfield mj0 : Lf/Ip;
/*    */     //   1725: areturn
/*    */     // Line number table:
/*    */     //   Java source line number -> byte code offset
/*    */     //   #1	-> 1
/*    */     //   #2	-> 10
/*    */     //   #3	-> 13
/*    */     //   #4	-> 57
/*    */     //   #5	-> 87
/*    */     //   #6	-> 90
/*    */     //   #7	-> 104
/*    */     //   #8	-> 111
/*    */     //   #9	-> 186
/*    */     //   #10	-> 192
/*    */     //   #11	-> 222
/*    */     //   #12	-> 225
/*    */     //   #13	-> 229
/*    */     //   #14	-> 232
/*    */     //   #15	-> 278
/*    */     //   #16	-> 286
/*    */     //   #17	-> 360
/*    */     //   #18	-> 364
/*    */     //   #19	-> 474
/*    */     //   #20	-> 481
/*    */     //   #21	-> 505
/*    */     //   #22	-> 512
/*    */     //   #23	-> 521
/*    */     //   #24	-> 529
/*    */     //   #25	-> 555
/*    */     //   #26	-> 560
/*    */     //   #27	-> 564
/*    */     //   #28	-> 572
/*    */     //   #29	-> 604
/*    */     //   #30	-> 611
/*    */     //   #31	-> 620
/*    */     //   #32	-> 628
/*    */     //   #33	-> 647
/*    */     //   #34	-> 655
/*    */     //   #35	-> 663
/*    */     //   #36	-> 678
/*    */     //   #37	-> 686
/*    */     //   #38	-> 863
/*    */     //   #39	-> 879
/*    */     //   #40	-> 905
/*    */     //   #41	-> 910
/*    */     //   #42	-> 923
/*    */     //   #43	-> 926
/*    */     //   #44	-> 929
/*    */     //   #45	-> 932
/*    */     //   #46	-> 941
/*    */     //   #47	-> 944
/*    */     //   #48	-> 951
/*    */     //   #49	-> 954
/*    */     //   #50	-> 957
/*    */     //   #51	-> 960
/*    */     //   #52	-> 979
/*    */     //   #53	-> 984
/*    */     //   #54	-> 989
/*    */     //   #55	-> 1069
/*    */     //   #56	-> 1077
/*    */     //   #57	-> 1101
/*    */     //   #58	-> 1104
/*    */     //   #59	-> 1109
/*    */     //   #60	-> 1115
/*    */     //   #61	-> 1134
/*    */     //   #62	-> 1137
/*    */     //   #63	-> 1144
/*    */     //   #64	-> 1154
/*    */     //   #65	-> 1158
/*    */     //   #66	-> 1162
/*    */     //   #67	-> 1169
/*    */     //   #68	-> 1185
/*    */     //   #69	-> 1190
/*    */     //   #70	-> 1195
/*    */     //   #71	-> 1214
/*    */     //   #72	-> 1225
/*    */     //   #73	-> 1241
/*    */     //   #74	-> 1252
/*    */     //   #75	-> 1297
/*    */     //   #76	-> 1305
/*    */     //   #77	-> 1331
/*    */     //   #78	-> 1338
/*    */     //   #79	-> 1358
/*    */     //   #80	-> 1379
/*    */     //   #81	-> 1383
/*    */     //   #82	-> 1400
/*    */     //   #83	-> 1408
/*    */     //   #84	-> 1435
/*    */     //   #85	-> 1442
/*    */     //   #86	-> 1445
/*    */     //   #87	-> 1495
/*    */     //   #88	-> 1500
/*    */     //   #89	-> 1515
/*    */     //   #90	-> 1522
/*    */     //   #91	-> 1552
/*    */     //   #92	-> 1560
/*    */     //   #93	-> 1607
/*    */     //   #94	-> 1610
/*    */     //   #95	-> 1649
/*    */     //   #96	-> 1667
/*    */     //   #97	-> 1670
/*    */     //   #98	-> 1673
/*    */     //   #99	-> 1696
/*    */   } }


/* Location:              /Users/vnnsnnt/Documents/Codespace/JavaWorkspace/RedTrainer/src/main/java/org/trainer/client/PokeMMO.jar!/f/jd.class
 * Java compiler version: 8 (52.0)
 * JD-Core Version:       1.1.3
 */