package f;

import java.nio.ByteBuffer;

public final class Jn extends iK {
  public Jn(ByteBuffer paramByteBuffer) {
    super(paramByteBuffer, 0);
  }
  
  public final boolean RH(ByteBuffer paramByteBuffer) {
    // Byte code:
    //   0: aload_1
    //   1: invokevirtual getShort : ()S
    //   4: istore_2
    //   5: new f/h30
    //   8: dup
    //   9: astore_3
    //   10: invokespecial <init> : ()V
    //   13: new f/Qr
    //   16: dup
    //   17: astore #4
    //   19: invokespecial <init> : ()V
    //   22: iconst_0
    //   23: istore #5
    //   25: iload #5
    //   27: iload_2
    //   28: if_icmpge -> 1260
    //   31: aload_1
    //   32: dup
    //   33: invokevirtual getShort : ()S
    //   36: istore #6
    //   38: invokevirtual getInt : ()I
    //   41: dup
    //   42: istore #7
    //   44: getstatic f/Of.eH : Lf/Of;
    //   47: dup
    //   48: astore #8
    //   50: iload #6
    //   52: invokevirtual On0 : (S)Lf/LPT3;
    //   55: astore #9
    //   57: iconst_1
    //   58: iand
    //   59: ifeq -> 107
    //   62: aload #9
    //   64: aload_1
    //   65: dup
    //   66: invokevirtual getInt : ()I
    //   69: istore #10
    //   71: invokevirtual getInt : ()I
    //   74: istore #11
    //   76: getfield ph0 : I
    //   79: iload #10
    //   81: if_icmpne -> 94
    //   84: aload #9
    //   86: invokevirtual coM8 : ()I
    //   89: iload #11
    //   91: if_icmpeq -> 107
    //   94: aload #9
    //   96: dup
    //   97: iload #10
    //   99: putfield ph0 : I
    //   102: iload #11
    //   104: putfield dk : I
    //   107: iload #7
    //   109: iconst_2
    //   110: iand
    //   111: ifeq -> 162
    //   114: aload_1
    //   115: invokevirtual get : ()B
    //   118: iconst_1
    //   119: if_icmpne -> 128
    //   122: iconst_1
    //   123: istore #10
    //   125: goto -> 131
    //   128: iconst_0
    //   129: istore #10
    //   131: aload_1
    //   132: aload #9
    //   134: iload #10
    //   136: putfield Sg0 : Z
    //   139: invokevirtual get : ()B
    //   142: iconst_1
    //   143: if_icmpne -> 152
    //   146: iconst_1
    //   147: istore #10
    //   149: goto -> 155
    //   152: iconst_0
    //   153: istore #10
    //   155: aload #9
    //   157: iload #10
    //   159: putfield IK0 : Z
    //   162: iload #7
    //   164: iconst_4
    //   165: iand
    //   166: ifeq -> 244
    //   169: aload_1
    //   170: invokevirtual get : ()B
    //   173: istore #10
    //   175: getstatic f/Hu0.It : [Lf/Hu0;
    //   178: dup
    //   179: astore #11
    //   181: arraylength
    //   182: istore #12
    //   184: iconst_0
    //   185: istore #13
    //   187: iload #13
    //   189: iload #12
    //   191: if_icmpge -> 219
    //   194: aload #11
    //   196: iload #13
    //   198: aaload
    //   199: dup
    //   200: astore #14
    //   202: getfield od : B
    //   205: iload #10
    //   207: if_icmpne -> 213
    //   210: goto -> 222
    //   213: iinc #13, 1
    //   216: goto -> 187
    //   219: aconst_null
    //   220: astore #14
    //   222: aload #14
    //   224: ifnull -> 244
    //   227: aload #9
    //   229: aload #14
    //   231: aload #9
    //   233: aload #14
    //   235: putfield Y8 : Lf/Hu0;
    //   238: getfield tj : S
    //   241: putfield O5 : S
    //   244: iload #7
    //   246: bipush #8
    //   248: iand
    //   249: ifeq -> 261
    //   252: aload #9
    //   254: aload_1
    //   255: invokevirtual getShort : ()S
    //   258: putfield O5 : S
    //   261: iload #7
    //   263: bipush #16
    //   265: iand
    //   266: ifeq -> 358
    //   269: aload_1
    //   270: invokevirtual get : ()B
    //   273: istore #10
    //   275: getstatic f/dv.X30 : Lf/ak;
    //   278: dup
    //   279: astore #11
    //   281: iload #10
    //   283: invokevirtual db0 : (B)Z
    //   286: ifeq -> 304
    //   289: aload #11
    //   291: iload #10
    //   293: invokevirtual Ha0 : (B)Ljava/lang/Object;
    //   296: checkcast f/dv
    //   299: astore #10
    //   301: goto -> 309
    //   304: getstatic f/dv.wS : Lf/dv;
    //   307: astore #10
    //   309: aload #11
    //   311: aload_1
    //   312: aload #9
    //   314: aload #10
    //   316: putfield qA0 : Lf/dv;
    //   319: invokevirtual get : ()B
    //   322: dup
    //   323: istore #10
    //   325: invokevirtual db0 : (B)Z
    //   328: ifeq -> 346
    //   331: aload #11
    //   333: iload #10
    //   335: invokevirtual Ha0 : (B)Ljava/lang/Object;
    //   338: checkcast f/dv
    //   341: astore #10
    //   343: goto -> 351
    //   346: getstatic f/dv.wS : Lf/dv;
    //   349: astore #10
    //   351: aload #9
    //   353: aload #10
    //   355: putfield i80 : Lf/dv;
    //   358: iload #7
    //   360: bipush #32
    //   362: iand
    //   363: ifeq -> 423
    //   366: aload #8
    //   368: dup
    //   369: dup
    //   370: aload_1
    //   371: invokevirtual getShort : ()S
    //   374: istore #10
    //   376: getfield ix : Ljava/util/TreeMap;
    //   379: aload #8
    //   381: iload #10
    //   383: iload #6
    //   385: invokestatic valueOf : (S)Ljava/lang/Short;
    //   388: astore #8
    //   390: invokevirtual On0 : (S)Lf/LPT3;
    //   393: aload #8
    //   395: swap
    //   396: invokevirtual put : (Ljava/lang/Object;Ljava/lang/Object;)Ljava/lang/Object;
    //   399: pop
    //   400: getfield cOm7 : Ljava/util/TreeMap;
    //   403: iload #6
    //   405: invokestatic valueOf : (S)Ljava/lang/Short;
    //   408: invokevirtual remove : (Ljava/lang/Object;)Ljava/lang/Object;
    //   411: pop
    //   412: getfield eF0 : Lf/h30;
    //   415: iload #6
    //   417: iload #10
    //   419: invokevirtual st : (SS)S
    //   422: pop
    //   423: iload #7
    //   425: bipush #64
    //   427: iand
    //   428: ifeq -> 452
    //   431: aload #4
    //   433: aload_3
    //   434: aload_1
    //   435: invokevirtual getShort : ()S
    //   438: iload #6
    //   440: swap
    //   441: invokevirtual st : (SS)S
    //   444: pop
    //   445: iload #7
    //   447: iload #6
    //   449: invokevirtual RD : (IS)V
    //   452: iload #7
    //   454: sipush #128
    //   457: iand
    //   458: ifeq -> 516
    //   461: aload_1
    //   462: dup
    //   463: invokevirtual getShort : ()S
    //   466: istore #6
    //   468: invokevirtual get : ()B
    //   471: iconst_1
    //   472: if_icmpne -> 481
    //   475: iconst_1
    //   476: istore #8
    //   478: goto -> 484
    //   481: iconst_0
    //   482: istore #8
    //   484: aload #9
    //   486: aload_1
    //   487: aload #9
    //   489: aload_1
    //   490: aload #9
    //   492: iload #8
    //   494: aload #9
    //   496: iload #6
    //   498: putfield Pa0 : S
    //   501: putfield Rv0 : Z
    //   504: invokevirtual get : ()B
    //   507: putfield C90 : B
    //   510: invokevirtual get : ()B
    //   513: putfield xp0 : B
    //   516: iload #7
    //   518: sipush #256
    //   521: iand
    //   522: ifeq -> 534
    //   525: aload #9
    //   527: aload_1
    //   528: invokevirtual getShort : ()S
    //   531: putfield GK : S
    //   534: iload #7
    //   536: sipush #512
    //   539: iand
    //   540: ifeq -> 552
    //   543: aload #9
    //   545: aload_1
    //   546: invokevirtual getShort : ()S
    //   549: putfield kx0 : S
    //   552: iload #7
    //   554: sipush #1024
    //   557: iand
    //   558: ifeq -> 582
    //   561: aload #9
    //   563: aload_1
    //   564: aload #9
    //   566: aload_1
    //   567: invokevirtual get : ()B
    //   570: invokestatic aU : (B)Lf/hR;
    //   573: putfield el : Lf/hR;
    //   576: invokevirtual getShort : ()S
    //   579: putfield lA : S
    //   582: iload #7
    //   584: sipush #2048
    //   587: iand
    //   588: ifeq -> 627
    //   591: aload_1
    //   592: dup
    //   593: invokevirtual getShort : ()S
    //   596: istore #6
    //   598: invokevirtual get : ()B
    //   601: iconst_1
    //   602: if_icmpne -> 611
    //   605: iconst_1
    //   606: istore #8
    //   608: goto -> 614
    //   611: iconst_0
    //   612: istore #8
    //   614: aload #9
    //   616: dup
    //   617: iload #6
    //   619: putfield Is : S
    //   622: iload #8
    //   624: putfield uL : Z
    //   627: iload #7
    //   629: sipush #4096
    //   632: iand
    //   633: ifeq -> 683
    //   636: aload_1
    //   637: invokevirtual get : ()B
    //   640: invokestatic qq : (B)Lf/mA;
    //   643: dup
    //   644: astore #6
    //   646: getstatic f/mA.Wh0 : Lf/mA;
    //   649: pop
    //   650: pop
    //   651: aload #9
    //   653: aload #6
    //   655: aload #9
    //   657: aload #6
    //   659: getfield WF : B
    //   662: dup
    //   663: aload #9
    //   665: swap
    //   666: sipush #11000
    //   669: iadd
    //   670: putfield Iu : I
    //   673: sipush #11400
    //   676: iadd
    //   677: putfield wC0 : I
    //   680: putfield KI : Lf/mA;
    //   683: iload #7
    //   685: sipush #8192
    //   688: iand
    //   689: ifeq -> 698
    //   692: aload #9
    //   694: iconst_1
    //   695: putfield TA0 : Z
    //   698: iload #7
    //   700: sipush #16384
    //   703: iand
    //   704: ifeq -> 713
    //   707: aload #9
    //   709: iconst_1
    //   710: putfield cOm4 : Z
    //   713: iload #7
    //   715: ldc 32768
    //   717: iand
    //   718: ifeq -> 727
    //   721: aload #9
    //   723: iconst_0
    //   724: putfield Ym0 : Z
    //   727: iload #7
    //   729: ldc 65536
    //   731: iand
    //   732: ifeq -> 763
    //   735: aload #9
    //   737: dup
    //   738: aload_1
    //   739: dup
    //   740: invokevirtual get : ()B
    //   743: invokestatic Gt0 : (B)Lf/Ht0;
    //   746: astore #6
    //   748: invokevirtual get : ()B
    //   751: istore #8
    //   753: aload #6
    //   755: putfield de0 : Lf/Ht0;
    //   758: iload #8
    //   760: putfield m20 : B
    //   763: iload #7
    //   765: ldc 131072
    //   767: iand
    //   768: ifeq -> 1040
    //   771: aload_1
    //   772: invokevirtual get : ()B
    //   775: getstatic f/v7.VW : Lf/ak;
    //   778: swap
    //   779: invokevirtual Ha0 : (B)Ljava/lang/Object;
    //   782: invokestatic requireNonNull : (Ljava/lang/Object;)Ljava/lang/Object;
    //   785: checkcast f/v7
    //   788: dup
    //   789: astore #6
    //   791: invokevirtual ordinal : ()I
    //   794: tableswitch default -> 828, 2 -> 897, 3 -> 897, 4 -> 881, 5 -> 831, 6 -> 897
    //   828: goto -> 929
    //   831: aload #9
    //   833: aload_1
    //   834: aload #9
    //   836: aload_1
    //   837: aload #9
    //   839: aload_1
    //   840: invokevirtual get : ()B
    //   843: invokestatic sD : (B)Lf/Uj;
    //   846: putfield sw : Lf/Uj;
    //   849: invokevirtual getShort : ()S
    //   852: aload_1
    //   853: invokevirtual get : ()B
    //   856: invokestatic of : (II)Ljava/time/YearMonth;
    //   859: putfield BU : Ljava/time/YearMonth;
    //   862: invokevirtual get : ()B
    //   865: getstatic f/yL.Gx0 : Lf/ak;
    //   868: swap
    //   869: invokevirtual Ha0 : (B)Ljava/lang/Object;
    //   872: checkcast f/yL
    //   875: putfield ge : Lf/yL;
    //   878: goto -> 929
    //   881: aload_1
    //   882: invokevirtual getShort : ()S
    //   885: aload_1
    //   886: invokevirtual get : ()B
    //   889: invokestatic of : (II)Ljava/time/YearMonth;
    //   892: astore #8
    //   894: goto -> 922
    //   897: aload_1
    //   898: aload #9
    //   900: aload_1
    //   901: invokevirtual get : ()B
    //   904: invokestatic sD : (B)Lf/Uj;
    //   907: putfield sw : Lf/Uj;
    //   910: invokevirtual getShort : ()S
    //   913: aload_1
    //   914: invokevirtual get : ()B
    //   917: invokestatic of : (II)Ljava/time/YearMonth;
    //   920: astore #8
    //   922: aload #9
    //   924: aload #8
    //   926: putfield BU : Ljava/time/YearMonth;
    //   929: aload_1
    //   930: aload #9
    //   932: aload #6
    //   934: putfield wg0 : Lf/v7;
    //   937: invokevirtual get : ()B
    //   940: dup
    //   941: istore #6
    //   943: anewarray f/uj
    //   946: astore #8
    //   948: iconst_0
    //   949: istore #10
    //   951: iload #10
    //   953: iload #6
    //   955: if_icmpge -> 1028
    //   958: aload_1
    //   959: dup
    //   960: invokevirtual getInt : ()I
    //   963: istore #11
    //   965: invokevirtual get : ()B
    //   968: dup
    //   969: istore #12
    //   971: anewarray f/LPT1
    //   974: astore #13
    //   976: iconst_0
    //   977: istore #14
    //   979: iload #14
    //   981: iload #12
    //   983: if_icmpge -> 1002
    //   986: aload #13
    //   988: aload_0
    //   989: invokevirtual Ac : ()Lf/LPT1;
    //   992: iload #14
    //   994: swap
    //   995: aastore
    //   996: iinc #14, 1
    //   999: goto -> 979
    //   1002: aload #8
    //   1004: new f/uj
    //   1007: dup
    //   1008: astore #12
    //   1010: iload #11
    //   1012: aload #13
    //   1014: invokespecial <init> : (I[Lf/LPT1;)V
    //   1017: iload #10
    //   1019: aload #12
    //   1021: aastore
    //   1022: iinc #10, 1
    //   1025: goto -> 951
    //   1028: iload #6
    //   1030: ifle -> 1040
    //   1033: aload #9
    //   1035: aload #8
    //   1037: putfield yq0 : [Lf/uj;
    //   1040: iload #7
    //   1042: ldc_w 262144
    //   1045: iand
    //   1046: ifeq -> 1055
    //   1049: aload #9
    //   1051: iconst_1
    //   1052: putfield EA : Z
    //   1055: iload #7
    //   1057: ldc_w 524288
    //   1060: iand
    //   1061: ifeq -> 1105
    //   1064: aload #9
    //   1066: dup
    //   1067: aload_1
    //   1068: dup
    //   1069: invokevirtual getShort : ()S
    //   1072: istore #6
    //   1074: invokevirtual get : ()B
    //   1077: istore #8
    //   1079: iload #6
    //   1081: getstatic f/XZ.DM : Lf/ak;
    //   1084: iload #8
    //   1086: invokevirtual Ha0 : (B)Ljava/lang/Object;
    //   1089: invokestatic requireNonNull : (Ljava/lang/Object;)Ljava/lang/Object;
    //   1092: checkcast f/XZ
    //   1095: astore #6
    //   1097: putfield KD0 : S
    //   1100: aload #6
    //   1102: putfield h3 : Lf/XZ;
    //   1105: iload #7
    //   1107: ldc_w 1048576
    //   1110: iand
    //   1111: ifeq -> 1123
    //   1114: aload #9
    //   1116: aload_1
    //   1117: invokevirtual get : ()B
    //   1120: putfield Kp : B
    //   1123: iload #7
    //   1125: ldc_w 2097152
    //   1128: iand
    //   1129: ifeq -> 1182
    //   1132: aload_1
    //   1133: invokevirtual getShort : ()S
    //   1136: dup
    //   1137: istore #6
    //   1139: anewarray f/UD0
    //   1142: astore #8
    //   1144: iconst_0
    //   1145: istore #10
    //   1147: iload #10
    //   1149: iload #6
    //   1151: if_icmpge -> 1175
    //   1154: aload #8
    //   1156: iload #10
    //   1158: invokestatic v30 : ()Lf/On;
    //   1161: aload_1
    //   1162: invokevirtual getShort : ()S
    //   1165: invokevirtual lpT3 : (S)Lf/UD0;
    //   1168: aastore
    //   1169: iinc #10, 1
    //   1172: goto -> 1147
    //   1175: aload #9
    //   1177: aload #8
    //   1179: putfield ia0 : [Lf/UD0;
    //   1182: iload #7
    //   1184: ldc_w 4194304
    //   1187: iand
    //   1188: ifeq -> 1200
    //   1191: aload #9
    //   1193: aload_1
    //   1194: invokevirtual getInt : ()I
    //   1197: putfield lh : I
    //   1200: iload #7
    //   1202: ldc_w 8388608
    //   1205: iand
    //   1206: ifeq -> 1215
    //   1209: aload #9
    //   1211: iconst_0
    //   1212: putfield kd : Z
    //   1215: iload #7
    //   1217: ldc_w 16777216
    //   1220: iand
    //   1221: ifeq -> 1236
    //   1224: aload #9
    //   1226: aload_1
    //   1227: invokevirtual get : ()B
    //   1230: invokestatic sD : (B)Lf/Uj;
    //   1233: putfield t5 : Lf/Uj;
    //   1236: iload #7
    //   1238: ldc_w 33554432
    //   1241: iand
    //   1242: ifeq -> 1254
    //   1245: aload #9
    //   1247: aload_1
    //   1248: invokevirtual get : ()B
    //   1251: putfield z20 : B
    //   1254: iinc #5, 1
    //   1257: goto -> 25
    //   1260: aload_3
    //   1261: dup
    //   1262: getfield ir0 : I
    //   1265: dup
    //   1266: istore_0
    //   1267: newarray short
    //   1269: astore_1
    //   1270: getfield h70 : [S
    //   1273: dup
    //   1274: astore_2
    //   1275: aload_3
    //   1276: getfield JO : [B
    //   1279: astore #5
    //   1281: arraylength
    //   1282: istore #6
    //   1284: iconst_0
    //   1285: istore #7
    //   1287: iload #6
    //   1289: dup
    //   1290: iconst_m1
    //   1291: iadd
    //   1292: istore #6
    //   1294: ifle -> 1328
    //   1297: aload #5
    //   1299: iload #6
    //   1301: baload
    //   1302: iconst_1
    //   1303: if_icmpne -> 1287
    //   1306: aload_1
    //   1307: aload_2
    //   1308: iload #7
    //   1310: iconst_1
    //   1311: iadd
    //   1312: istore #8
    //   1314: iload #6
    //   1316: saload
    //   1317: iload #7
    //   1319: swap
    //   1320: sastore
    //   1321: iload #8
    //   1323: istore #7
    //   1325: goto -> 1287
    //   1328: iconst_0
    //   1329: istore_2
    //   1330: iload_2
    //   1331: iload_0
    //   1332: if_icmpge -> 1490
    //   1335: aload #4
    //   1337: aload_1
    //   1338: iload_2
    //   1339: saload
    //   1340: dup
    //   1341: istore #5
    //   1343: getstatic f/Of.eH : Lf/Of;
    //   1346: dup
    //   1347: dup
    //   1348: astore #6
    //   1350: aload_3
    //   1351: iload #5
    //   1353: aload #6
    //   1355: iload #5
    //   1357: invokevirtual On0 : (S)Lf/LPT3;
    //   1360: astore #6
    //   1362: invokevirtual Z90 : (S)S
    //   1365: invokevirtual On0 : (S)Lf/LPT3;
    //   1368: iload #5
    //   1370: invokevirtual mi : (S)Lf/LPT3;
    //   1373: dup
    //   1374: astore #5
    //   1376: invokevirtual Rb0 : (Lf/LPT3;)V
    //   1379: invokevirtual X60 : (S)I
    //   1382: dup
    //   1383: istore #7
    //   1385: iconst_2
    //   1386: iand
    //   1387: ifeq -> 1410
    //   1390: aload #5
    //   1392: aload #6
    //   1394: aload #5
    //   1396: aload #6
    //   1398: invokevirtual vx : ()Z
    //   1401: putfield Sg0 : Z
    //   1404: getfield IK0 : Z
    //   1407: putfield IK0 : Z
    //   1410: iload #7
    //   1412: iconst_1
    //   1413: iand
    //   1414: ifeq -> 1437
    //   1417: aload #5
    //   1419: aload #6
    //   1421: aload #5
    //   1423: aload #6
    //   1425: getfield ph0 : I
    //   1428: putfield ph0 : I
    //   1431: invokevirtual coM8 : ()I
    //   1434: putfield dk : I
    //   1437: iload #7
    //   1439: iconst_4
    //   1440: iand
    //   1441: ifeq -> 1466
    //   1444: aload #5
    //   1446: dup
    //   1447: aload #6
    //   1449: getfield Y8 : Lf/Hu0;
    //   1452: dup
    //   1453: astore #6
    //   1455: putfield Y8 : Lf/Hu0;
    //   1458: aload #6
    //   1460: getfield tj : S
    //   1463: putfield O5 : S
    //   1466: iload #7
    //   1468: bipush #8
    //   1470: iand
    //   1471: ifeq -> 1484
    //   1474: aload #5
    //   1476: dup
    //   1477: invokevirtual wf0 : ()I
    //   1480: i2s
    //   1481: putfield O5 : S
    //   1484: iinc #2, 1
    //   1487: goto -> 1330
    //   1490: iconst_1
    //   1491: ireturn
    // Line number table:
    //   Java source line number -> byte code offset
    //   #1	-> 44
    //   #2	-> 52
    //   #3	-> 76
    //   #4	-> 86
    //   #5	-> 99
    //   #6	-> 104
    //   #7	-> 115
    //   #8	-> 136
    //   #9	-> 139
    //   #10	-> 159
    //   #11	-> 170
    //   #12	-> 175
    //   #13	-> 235
    //   #14	-> 238
    //   #15	-> 241
    //   #16	-> 255
    //   #17	-> 258
    //   #18	-> 270
    //   #19	-> 275
    //   #20	-> 283
    //   #21	-> 293
    //   #22	-> 316
    //   #23	-> 319
    //   #24	-> 325
    //   #25	-> 335
    //   #26	-> 355
    //   #27	-> 371
    //   #28	-> 376
    //   #29	-> 385
    //   #30	-> 435
    //   #31	-> 498
    //   #32	-> 504
    //   #33	-> 507
    //   #34	-> 510
    //   #35	-> 513
    //   #36	-> 528
    //   #37	-> 531
    //   #38	-> 546
    //   #39	-> 549
    //   #40	-> 567
    //   #41	-> 573
    //   #42	-> 576
    //   #43	-> 579
    //   #44	-> 593
    //   #45	-> 619
    //   #46	-> 637
    //   #47	-> 646
    //   #48	-> 670
    //   #49	-> 677
    //   #50	-> 680
    //   #51	-> 695
    //   #52	-> 710
    //   #53	-> 724
    //   #54	-> 740
    //   #55	-> 755
    //   #56	-> 772
    //   #57	-> 775
    //   #58	-> 791
    //   #59	-> 846
    //   #60	-> 849
    //   #61	-> 859
    //   #62	-> 862
    //   #63	-> 865
    //   #64	-> 875
    //   #65	-> 882
    //   #66	-> 907
    //   #67	-> 910
    //   #68	-> 926
    //   #69	-> 934
    //   #70	-> 937
    //   #71	-> 1037
    //   #72	-> 1052
    //   #73	-> 1069
    //   #74	-> 1081
    //   #75	-> 1097
    //   #76	-> 1117
    //   #77	-> 1120
    //   #78	-> 1133
    //   #79	-> 1179
    //   #80	-> 1194
    //   #81	-> 1197
    //   #82	-> 1212
    //   #83	-> 1227
    //   #84	-> 1233
    //   #85	-> 1248
    //   #86	-> 1251
    //   #87	-> 1262
    //   #88	-> 1267
    //   #89	-> 1339
    //   #90	-> 1343
    //   #91	-> 1357
    //   #92	-> 1401
    //   #93	-> 1404
    //   #94	-> 1407
    //   #95	-> 1425
    //   #96	-> 1428
    //   #97	-> 1431
    //   #98	-> 1434
    //   #99	-> 1449
    //   #100	-> 1455
    //   #101	-> 1460
    //   #102	-> 1463
    //   #103	-> 1477
    //   #104	-> 1481
  }
  
  public final void run() {}
  
  public final void sM() {}
}


/* Location:              /Users/vnnsnnt/Documents/Codespace/JavaWorkspace/RedTrainer/src/main/java/org/trainer/client/PokeMMO.jar!/f/Jn.class
 * Java compiler version: 8 (52.0)
 * JD-Core Version:       1.1.3
 */