/*  1 */ package f;public final class jp extends SI0 { public static final String B60(Gp0 paramGp0, short paramShort, int paramInt, hm0 paramhm0) { if (paramShort != 1) { String[] arrayOfString1; if (paramShort != 2) { if (paramShort != 4) { if (paramShort != 8) { String[] arrayOfString3; if (paramShort != 16) { String[] arrayOfString5; if (paramShort != 32) { if (paramShort == 128) { F40 f403 = F40.ef0; int i1 = paramGp0.ex(517, paramhm0); (arrayOfString4 = new String[1])[0] = paramhm0.fA(); return Ml0.lz((byte)2, f403, 14, i1, arrayOfString4); }
/*  2 */                  throw new IllegalArgumentException(); }  if (arrayOfString4 == true) { arrayOfString5 = new String[0];
/*  3 */                 return Ml0.lz((byte)2, F40.ef0, 15, 78, arrayOfString5); }
/*  4 */                F40 f402 = F40.ef0; int n = arrayOfString5.ex(6, paramhm0); (arrayOfString4 = new String[1])[0] = paramhm0.fA();
/*  5 */               return Ml0.lz((byte)2, f402, 14, n, arrayOfString4); }  if (arrayOfString4 == true) {
/*  6 */               arrayOfString3 = new String[0];
/*  7 */               return Ml0.lz((byte)2, F40.ef0, 15, 79, arrayOfString3);
/*  8 */             }  f401 = F40.ef0; int m = arrayOfString3.ex(15, paramhm0); String[] arrayOfString4; (arrayOfString4 = new String[1])[0] = paramhm0.fA();
/*  9 */             return Ml0.lz((byte)2, f401, 14, m, arrayOfString4); }
/* 10 */            F40 f401 = F40.ef0; int k = f401.ex(210, paramhm0); (arrayOfString2 = new String[1])[0] = paramhm0.fA();
/* 11 */           return Ml0.lz((byte)2, f401, 14, k, arrayOfString2); }
/* 12 */          arrayOfString1 = new String[0];
/* 13 */         return Ml0.lz((byte)2, F40.ef0, 15, 71, arrayOfString1); }  if (arrayOfString2 == true)
/* 14 */         return Ml0.Qf0(F40.ef0, 15, 81);  f40 = F40.ef0; int j = arrayOfString1.ex(384, paramhm0); String[] arrayOfString2; (arrayOfString2 = new String[1])[0] = paramhm0.fA();
/* 15 */       return Ml0.lz((byte)2, f40, 14, j, arrayOfString2); }
/* 16 */      F40 f40 = F40.ef0; int i = f40.ex(213, paramhm0); String[] arrayOfString; (arrayOfString = new String[1])[0] = paramhm0.fA();
/* 17 */     return Ml0.lz((byte)2, f40, 14, i, arrayOfString); }
/*    */ 
/*    */   
/*    */   public static final ik lPt7 = C00.gd(jp.class);
/*    */   public int ww;
/*    */   public short Xj0;
/*    */   public Collection Kx0;
/*    */   public boolean hv0 = false;
/*    */   
/*    */   public jp(int paramInt, short paramShort, ArrayList paramArrayList) {
/*    */     this.ww = paramInt;
/*    */     this.Xj0 = paramShort;
/*    */     this.Kx0 = paramArrayList;
/*    */   }
/*    */   
/*    */   public static final String Xh0(Gp0 paramGp0, short paramShort, hm0[] paramArrayOfhm0) {
/*    */     // Byte code:
/*    */     //   0: iload_1
/*    */     //   1: ifge -> 9
/*    */     //   4: iload_1
/*    */     //   5: iconst_m1
/*    */     //   6: imul
/*    */     //   7: i2s
/*    */     //   8: istore_1
/*    */     //   9: iload_1
/*    */     //   10: bipush #16
/*    */     //   12: if_icmpeq -> 122
/*    */     //   15: iload_1
/*    */     //   16: bipush #32
/*    */     //   18: if_icmpne -> 114
/*    */     //   21: aload_2
/*    */     //   22: arraylength
/*    */     //   23: iconst_3
/*    */     //   24: if_icmple -> 50
/*    */     //   27: getstatic f/F40.ef0 : Lf/F40;
/*    */     //   30: bipush #15
/*    */     //   32: istore_0
/*    */     //   33: bipush #78
/*    */     //   35: istore_1
/*    */     //   36: iconst_0
/*    */     //   37: anewarray java/lang/String
/*    */     //   40: astore_2
/*    */     //   41: iconst_2
/*    */     //   42: swap
/*    */     //   43: iload_0
/*    */     //   44: iload_1
/*    */     //   45: aload_2
/*    */     //   46: invokestatic lz : (BLf/F40;II[Ljava/lang/String;)Ljava/lang/String;
/*    */     //   49: areturn
/*    */     //   50: aload_2
/*    */     //   51: aload_0
/*    */     //   52: aload_2
/*    */     //   53: dup
/*    */     //   54: arraylength
/*    */     //   55: iconst_1
/*    */     //   56: isub
/*    */     //   57: iconst_3
/*    */     //   58: imul
/*    */     //   59: bipush #6
/*    */     //   61: iadd
/*    */     //   62: istore_0
/*    */     //   63: getstatic f/F40.ef0 : Lf/F40;
/*    */     //   66: astore_1
/*    */     //   67: bipush #14
/*    */     //   69: istore_2
/*    */     //   70: iconst_0
/*    */     //   71: aaload
/*    */     //   72: iload_0
/*    */     //   73: swap
/*    */     //   74: invokevirtual ex : (ILf/hm0;)I
/*    */     //   77: istore_0
/*    */     //   78: invokestatic of : ([Ljava/lang/Object;)Ljava/util/stream/Stream;
/*    */     //   81: <illegal opcode> apply : ()Ljava/util/function/Function;
/*    */     //   86: invokeinterface map : (Ljava/util/function/Function;)Ljava/util/stream/Stream;
/*    */     //   91: <illegal opcode> apply : ()Ljava/util/function/IntFunction;
/*    */     //   96: invokeinterface toArray : (Ljava/util/function/IntFunction;)[Ljava/lang/Object;
/*    */     //   101: checkcast [Ljava/lang/String;
/*    */     //   104: astore_3
/*    */     //   105: iconst_2
/*    */     //   106: aload_1
/*    */     //   107: iload_2
/*    */     //   108: iload_0
/*    */     //   109: aload_3
/*    */     //   110: invokestatic lz : (BLf/F40;II[Ljava/lang/String;)Ljava/lang/String;
/*    */     //   113: areturn
/*    */     //   114: new java/lang/IllegalArgumentException
/*    */     //   117: dup
/*    */     //   118: invokespecial <init> : ()V
/*    */     //   121: athrow
/*    */     //   122: aload_2
/*    */     //   123: arraylength
/*    */     //   124: iconst_3
/*    */     //   125: if_icmple -> 151
/*    */     //   128: getstatic f/F40.ef0 : Lf/F40;
/*    */     //   131: bipush #15
/*    */     //   133: istore_0
/*    */     //   134: bipush #79
/*    */     //   136: istore_1
/*    */     //   137: iconst_0
/*    */     //   138: anewarray java/lang/String
/*    */     //   141: astore_2
/*    */     //   142: iconst_2
/*    */     //   143: swap
/*    */     //   144: iload_0
/*    */     //   145: iload_1
/*    */     //   146: aload_2
/*    */     //   147: invokestatic lz : (BLf/F40;II[Ljava/lang/String;)Ljava/lang/String;
/*    */     //   150: areturn
/*    */     //   151: aload_2
/*    */     //   152: aload_0
/*    */     //   153: aload_2
/*    */     //   154: dup
/*    */     //   155: arraylength
/*    */     //   156: iconst_1
/*    */     //   157: isub
/*    */     //   158: iconst_3
/*    */     //   159: imul
/*    */     //   160: bipush #15
/*    */     //   162: iadd
/*    */     //   163: istore_0
/*    */     //   164: getstatic f/F40.ef0 : Lf/F40;
/*    */     //   167: astore_1
/*    */     //   168: bipush #14
/*    */     //   170: istore_2
/*    */     //   171: iconst_0
/*    */     //   172: aaload
/*    */     //   173: iload_0
/*    */     //   174: swap
/*    */     //   175: invokevirtual ex : (ILf/hm0;)I
/*    */     //   178: istore_0
/*    */     //   179: invokestatic of : ([Ljava/lang/Object;)Ljava/util/stream/Stream;
/*    */     //   182: <illegal opcode> apply : ()Ljava/util/function/Function;
/*    */     //   187: invokeinterface map : (Ljava/util/function/Function;)Ljava/util/stream/Stream;
/*    */     //   192: <illegal opcode> apply : ()Ljava/util/function/IntFunction;
/*    */     //   197: invokeinterface toArray : (Ljava/util/function/IntFunction;)[Ljava/lang/Object;
/*    */     //   202: checkcast [Ljava/lang/String;
/*    */     //   205: astore_3
/*    */     //   206: iconst_2
/*    */     //   207: aload_1
/*    */     //   208: iload_2
/*    */     //   209: iload_0
/*    */     //   210: aload_3
/*    */     //   211: invokestatic lz : (BLf/F40;II[Ljava/lang/String;)Ljava/lang/String;
/*    */     //   214: areturn
/*    */     // Line number table:
/*    */     //   Java source line number -> byte code offset
/*    */     //   #1	-> 46
/*    */     //   #2	-> 54
/*    */     //   #3	-> 110
/*    */     //   #4	-> 114
/*    */     //   #5	-> 147
/*    */     //   #6	-> 155
/*    */     //   #7	-> 211
/*    */   }
/*    */   
/*    */   public final void p4(kf paramkf) {
/*    */     // Byte code:
/*    */     //   0: aload_1
/*    */     //   1: invokestatic currentTimeMillis : ()J
/*    */     //   4: lstore_2
/*    */     //   5: getfield AD : Lf/Gp0;
/*    */     //   8: dup
/*    */     //   9: astore #4
/*    */     //   11: aload_0
/*    */     //   12: getfield ww : I
/*    */     //   15: invokevirtual fa : (I)Lf/hm0;
/*    */     //   18: dup
/*    */     //   19: astore #5
/*    */     //   21: ifnonnull -> 72
/*    */     //   24: aload_1
/*    */     //   25: ldc 'Error has occured, could not find\\n attacker with object id: '
/*    */     //   27: invokestatic df : (Ljava/lang/String;)Ljava/lang/StringBuilder;
/*    */     //   30: aload_0
/*    */     //   31: getfield ww : I
/*    */     //   34: invokevirtual append : (I)Ljava/lang/StringBuilder;
/*    */     //   37: invokevirtual toString : ()Ljava/lang/String;
/*    */     //   40: invokevirtual Kq : (Ljava/lang/String;)V
/*    */     //   43: getstatic f/jp.lPt7 : Lf/ik;
/*    */     //   46: ldc 'Fatal playback error when processing skill '
/*    */     //   48: invokestatic df : (Ljava/lang/String;)Ljava/lang/StringBuilder;
/*    */     //   51: aload_0
/*    */     //   52: getfield Xj0 : S
/*    */     //   55: invokevirtual append : (I)Ljava/lang/StringBuilder;
/*    */     //   58: ldc ' : Attacker was null'
/*    */     //   60: invokevirtual append : (Ljava/lang/String;)Ljava/lang/StringBuilder;
/*    */     //   63: invokevirtual toString : ()Ljava/lang/String;
/*    */     //   66: invokeinterface error : (Ljava/lang/String;)V
/*    */     //   71: return
/*    */     //   72: aload_0
/*    */     //   73: getfield Xj0 : S
/*    */     //   76: dup
/*    */     //   77: istore #6
/*    */     //   79: iflt -> 89
/*    */     //   82: aload #5
/*    */     //   84: iload #6
/*    */     //   86: putfield eH0 : S
/*    */     //   89: aload_0
/*    */     //   90: getfield Kx0 : Ljava/util/Collection;
/*    */     //   93: dup
/*    */     //   94: astore #6
/*    */     //   96: aconst_null
/*    */     //   97: astore #7
/*    */     //   99: new f/Ut0
/*    */     //   102: dup
/*    */     //   103: astore #8
/*    */     //   105: invokespecial <init> : ()V
/*    */     //   108: new f/y70
/*    */     //   111: dup
/*    */     //   112: astore #9
/*    */     //   114: invokespecial <init> : ()V
/*    */     //   117: invokeinterface iterator : ()Ljava/util/Iterator;
/*    */     //   122: astore #10
/*    */     //   124: aload #10
/*    */     //   126: invokeinterface hasNext : ()Z
/*    */     //   131: ifeq -> 698
/*    */     //   134: aload #10
/*    */     //   136: invokeinterface next : ()Ljava/lang/Object;
/*    */     //   141: checkcast f/b60
/*    */     //   144: dup
/*    */     //   145: astore #11
/*    */     //   147: getfield a0 : I
/*    */     //   150: dup
/*    */     //   151: istore #12
/*    */     //   153: ifne -> 163
/*    */     //   156: aload #5
/*    */     //   158: astore #12
/*    */     //   160: goto -> 172
/*    */     //   163: aload #4
/*    */     //   165: iload #12
/*    */     //   167: invokevirtual fa : (I)Lf/hm0;
/*    */     //   170: astore #12
/*    */     //   172: aload #12
/*    */     //   174: ifnonnull -> 225
/*    */     //   177: aload_1
/*    */     //   178: aload #11
/*    */     //   180: getfield a0 : I
/*    */     //   183: invokestatic toString : (I)Ljava/lang/String;
/*    */     //   186: sipush #5045
/*    */     //   189: swap
/*    */     //   190: invokestatic Go : (ILjava/lang/String;)Ljava/lang/String;
/*    */     //   193: invokevirtual Kq : (Ljava/lang/String;)V
/*    */     //   196: getstatic f/jp.lPt7 : Lf/ik;
/*    */     //   199: ldc 'Fatal playback error when processing skill '
/*    */     //   201: invokestatic df : (Ljava/lang/String;)Ljava/lang/StringBuilder;
/*    */     //   204: aload_0
/*    */     //   205: getfield Xj0 : S
/*    */     //   208: invokevirtual append : (I)Ljava/lang/StringBuilder;
/*    */     //   211: ldc ' : Target was null'
/*    */     //   213: invokevirtual append : (Ljava/lang/String;)Ljava/lang/StringBuilder;
/*    */     //   216: invokevirtual toString : ()Ljava/lang/String;
/*    */     //   219: invokeinterface error : (Ljava/lang/String;)V
/*    */     //   224: return
/*    */     //   225: aload #11
/*    */     //   227: getfield JX : Ljava/util/ArrayList;
/*    */     //   230: invokevirtual iterator : ()Ljava/util/Iterator;
/*    */     //   233: astore #13
/*    */     //   235: aload #13
/*    */     //   237: invokeinterface hasNext : ()Z
/*    */     //   242: ifeq -> 481
/*    */     //   245: aload #13
/*    */     //   247: invokeinterface next : ()Ljava/lang/Object;
/*    */     //   252: checkcast f/GS
/*    */     //   255: dup
/*    */     //   256: astore #14
/*    */     //   258: iconst_4
/*    */     //   259: invokevirtual QI : (B)Z
/*    */     //   262: ifeq -> 295
/*    */     //   265: aload_1
/*    */     //   266: aload_0
/*    */     //   267: aload #14
/*    */     //   269: bipush #16
/*    */     //   271: invokevirtual zb : (B)V
/*    */     //   274: getfield Xj0 : S
/*    */     //   277: istore #15
/*    */     //   279: aload #5
/*    */     //   281: aload #12
/*    */     //   283: aload #14
/*    */     //   285: iconst_0
/*    */     //   286: iconst_0
/*    */     //   287: iload #15
/*    */     //   289: iconst_0
/*    */     //   290: aload #11
/*    */     //   292: invokevirtual j90 : (Lf/hm0;Lf/hm0;Lf/GS;ZZSZLf/b60;)V
/*    */     //   295: aload #14
/*    */     //   297: invokevirtual YG0 : ()B
/*    */     //   300: ifne -> 235
/*    */     //   303: aload #14
/*    */     //   305: bipush #16
/*    */     //   307: invokevirtual QI : (B)Z
/*    */     //   310: ifne -> 235
/*    */     //   313: aload #14
/*    */     //   315: iconst_1
/*    */     //   316: invokevirtual QI : (B)Z
/*    */     //   319: ifeq -> 332
/*    */     //   322: aload #14
/*    */     //   324: getfield b70 : I
/*    */     //   327: istore #15
/*    */     //   329: goto -> 339
/*    */     //   332: aload #12
/*    */     //   334: invokevirtual ih : ()I
/*    */     //   337: istore #15
/*    */     //   339: aload #4
/*    */     //   341: aload #8
/*    */     //   343: iload #15
/*    */     //   345: aload #14
/*    */     //   347: invokevirtual A3 : (ILjava/lang/Object;)Ljava/lang/Object;
/*    */     //   350: pop
/*    */     //   351: iload #15
/*    */     //   353: invokevirtual fa : (I)Lf/hm0;
/*    */     //   356: dup
/*    */     //   357: astore #15
/*    */     //   359: ifnull -> 235
/*    */     //   362: aload #15
/*    */     //   364: invokevirtual XW : ()S
/*    */     //   367: aload #15
/*    */     //   369: aload #14
/*    */     //   371: checkcast f/JS
/*    */     //   374: getfield cOM9 : S
/*    */     //   377: istore #14
/*    */     //   379: getfield K0 : Lf/jd0;
/*    */     //   382: getfield hp0 : S
/*    */     //   385: dup
/*    */     //   386: istore #16
/*    */     //   388: invokestatic ri : (II)D
/*    */     //   391: dup2
/*    */     //   392: dstore #17
/*    */     //   394: iload #14
/*    */     //   396: iload #16
/*    */     //   398: invokestatic ri : (II)D
/*    */     //   401: dup2
/*    */     //   402: dstore #19
/*    */     //   404: dcmpl
/*    */     //   405: ifeq -> 235
/*    */     //   408: aload #9
/*    */     //   410: aload #15
/*    */     //   412: dload #17
/*    */     //   414: dload #19
/*    */     //   416: dsub
/*    */     //   417: ldc2_w -1.0
/*    */     //   420: dmul
/*    */     //   421: dstore #14
/*    */     //   423: invokevirtual Dg : (Ljava/lang/Object;)I
/*    */     //   426: dup
/*    */     //   427: istore #16
/*    */     //   429: iconst_1
/*    */     //   430: istore #17
/*    */     //   432: ifge -> 454
/*    */     //   435: aload #9
/*    */     //   437: iload #16
/*    */     //   439: ineg
/*    */     //   440: iconst_1
/*    */     //   441: isub
/*    */     //   442: istore #16
/*    */     //   444: getfield jI0 : [D
/*    */     //   447: iload #16
/*    */     //   449: daload
/*    */     //   450: pop2
/*    */     //   451: iconst_0
/*    */     //   452: istore #17
/*    */     //   454: iload #17
/*    */     //   456: aload #9
/*    */     //   458: getfield jI0 : [D
/*    */     //   461: iload #16
/*    */     //   463: dload #14
/*    */     //   465: dastore
/*    */     //   466: ifeq -> 235
/*    */     //   469: aload #9
/*    */     //   471: dup
/*    */     //   472: getfield Hs : Z
/*    */     //   475: invokevirtual xt0 : (Z)V
/*    */     //   478: goto -> 235
/*    */     //   481: aload_0
/*    */     //   482: getfield Xj0 : S
/*    */     //   485: istore #13
/*    */     //   487: invokestatic cw : ()Lf/yk0;
/*    */     //   490: aload_0
/*    */     //   491: getfield Xj0 : S
/*    */     //   494: invokevirtual mP : (S)Lf/WD;
/*    */     //   497: getfield DD : B
/*    */     //   500: tableswitch default -> 536, 4 -> 542, 5 -> 542, 6 -> 542, 7 -> 536, 8 -> 542
/*    */     //   536: iconst_0
/*    */     //   537: istore #14
/*    */     //   539: goto -> 545
/*    */     //   542: iconst_1
/*    */     //   543: istore #14
/*    */     //   545: aload #11
/*    */     //   547: iload #13
/*    */     //   549: aload_0
/*    */     //   550: getfield hv0 : Z
/*    */     //   553: iload #14
/*    */     //   555: swap
/*    */     //   556: invokevirtual vt0 : (SZZ)Z
/*    */     //   559: ifeq -> 124
/*    */     //   562: aload_0
/*    */     //   563: dup
/*    */     //   564: aload #12
/*    */     //   566: dup
/*    */     //   567: aload #5
/*    */     //   569: dup
/*    */     //   570: new f/Sr0
/*    */     //   573: astore #7
/*    */     //   575: getfield FT : B
/*    */     //   578: istore #12
/*    */     //   580: getfield ws : B
/*    */     //   583: istore #13
/*    */     //   585: getfield FT : B
/*    */     //   588: istore #14
/*    */     //   590: getfield ws : B
/*    */     //   593: istore #15
/*    */     //   595: getfield Xj0 : S
/*    */     //   598: istore #16
/*    */     //   600: bipush #64
/*    */     //   602: istore #17
/*    */     //   604: getfield Kx0 : Ljava/util/Collection;
/*    */     //   607: invokeinterface iterator : ()Ljava/util/Iterator;
/*    */     //   612: astore #18
/*    */     //   614: aload #18
/*    */     //   616: invokeinterface hasNext : ()Z
/*    */     //   621: ifeq -> 646
/*    */     //   624: aload #18
/*    */     //   626: invokeinterface next : ()Ljava/lang/Object;
/*    */     //   631: checkcast f/b60
/*    */     //   634: iload #17
/*    */     //   636: invokevirtual Fc0 : (S)Z
/*    */     //   639: ifeq -> 614
/*    */     //   642: iconst_1
/*    */     //   643: goto -> 647
/*    */     //   646: iconst_0
/*    */     //   647: ifne -> 670
/*    */     //   650: aload #11
/*    */     //   652: sipush #2048
/*    */     //   655: invokevirtual Fc0 : (S)Z
/*    */     //   658: ifeq -> 664
/*    */     //   661: goto -> 670
/*    */     //   664: iconst_0
/*    */     //   665: istore #11
/*    */     //   667: goto -> 673
/*    */     //   670: iconst_1
/*    */     //   671: istore #11
/*    */     //   673: aload_0
/*    */     //   674: aload #7
/*    */     //   676: iload #12
/*    */     //   678: iload #13
/*    */     //   680: iload #14
/*    */     //   682: iload #15
/*    */     //   684: iload #16
/*    */     //   686: iload #11
/*    */     //   688: invokespecial <init> : (BBBBSZ)V
/*    */     //   691: iconst_1
/*    */     //   692: putfield hv0 : Z
/*    */     //   695: goto -> 124
/*    */     //   698: aload_0
/*    */     //   699: ldc_w ''
/*    */     //   702: astore #10
/*    */     //   704: bipush #64
/*    */     //   706: istore #11
/*    */     //   708: getfield Kx0 : Ljava/util/Collection;
/*    */     //   711: invokeinterface iterator : ()Ljava/util/Iterator;
/*    */     //   716: astore #12
/*    */     //   718: aload #12
/*    */     //   720: invokeinterface hasNext : ()Z
/*    */     //   725: ifeq -> 750
/*    */     //   728: aload #12
/*    */     //   730: invokeinterface next : ()Ljava/lang/Object;
/*    */     //   735: checkcast f/b60
/*    */     //   738: iload #11
/*    */     //   740: invokevirtual Fc0 : (S)Z
/*    */     //   743: ifeq -> 718
/*    */     //   746: iconst_1
/*    */     //   747: goto -> 751
/*    */     //   750: iconst_0
/*    */     //   751: ifeq -> 1742
/*    */     //   754: aload_0
/*    */     //   755: getfield Xj0 : S
/*    */     //   758: dup
/*    */     //   759: istore #11
/*    */     //   761: lookupswitch default -> 924, 13 -> 1581, 19 -> 1534, 76 -> 1487, 91 -> 1440, 117 -> 1393, 130 -> 1346, 143 -> 1299, 248 -> 1944, 264 -> 1252, 291 -> 1205, 340 -> 1628, 353 -> 1944, 467 -> 1158, 507 -> 1030, 1003 -> 1158, 1006 -> 1158, 1012 -> 1015, 1041 -> 1944, 1049 -> 1030
/*    */     //   924: iload #11
/*    */     //   926: tableswitch default -> 968, 1017 -> 1677, 1018 -> 1677, 1019 -> 1628, 1020 -> 1628, 1021 -> 1628, 1022 -> 1628, 1023 -> 1628
/*    */     //   968: aload #4
/*    */     //   970: getstatic f/F40.ef0 : Lf/F40;
/*    */     //   973: astore #10
/*    */     //   975: sipush #664
/*    */     //   978: aload #5
/*    */     //   980: invokevirtual ex : (ILf/hm0;)I
/*    */     //   983: istore #11
/*    */     //   985: iconst_1
/*    */     //   986: anewarray java/lang/String
/*    */     //   989: dup
/*    */     //   990: astore #12
/*    */     //   992: aload #5
/*    */     //   994: invokevirtual fA : ()Ljava/lang/String;
/*    */     //   997: iconst_0
/*    */     //   998: swap
/*    */     //   999: aastore
/*    */     //   1000: iconst_2
/*    */     //   1001: aload #10
/*    */     //   1003: bipush #14
/*    */     //   1005: iload #11
/*    */     //   1007: aload #12
/*    */     //   1009: invokestatic lz : (BLf/F40;II[Ljava/lang/String;)Ljava/lang/String;
/*    */     //   1012: goto -> 1672
/*    */     //   1015: aload #5
/*    */     //   1017: invokevirtual fA : ()Ljava/lang/String;
/*    */     //   1020: ldc_w 200365
/*    */     //   1023: swap
/*    */     //   1024: invokestatic Go : (ILjava/lang/String;)Ljava/lang/String;
/*    */     //   1027: goto -> 1672
/*    */     //   1030: aload_0
/*    */     //   1031: getfield Kx0 : Ljava/util/Collection;
/*    */     //   1034: invokeinterface iterator : ()Ljava/util/Iterator;
/*    */     //   1039: astore #10
/*    */     //   1041: aload #5
/*    */     //   1043: astore #11
/*    */     //   1045: aload #10
/*    */     //   1047: invokeinterface hasNext : ()Z
/*    */     //   1052: ifeq -> 1097
/*    */     //   1055: aload #10
/*    */     //   1057: invokeinterface next : ()Ljava/lang/Object;
/*    */     //   1062: checkcast f/b60
/*    */     //   1065: getfield a0 : I
/*    */     //   1068: dup
/*    */     //   1069: istore #11
/*    */     //   1071: ifne -> 1081
/*    */     //   1074: aload #5
/*    */     //   1076: astore #11
/*    */     //   1078: goto -> 1090
/*    */     //   1081: aload #4
/*    */     //   1083: iload #11
/*    */     //   1085: invokevirtual fa : (I)Lf/hm0;
/*    */     //   1088: astore #11
/*    */     //   1090: aload #11
/*    */     //   1092: aload #5
/*    */     //   1094: if_acmpeq -> 1045
/*    */     //   1097: aload_1
/*    */     //   1098: getstatic f/F40.ef0 : Lf/F40;
/*    */     //   1101: astore #10
/*    */     //   1103: getfield AD : Lf/Gp0;
/*    */     //   1106: sipush #1118
/*    */     //   1109: aload #5
/*    */     //   1111: aload #11
/*    */     //   1113: invokevirtual Q40 : (ILf/hm0;Lf/hm0;)I
/*    */     //   1116: istore #12
/*    */     //   1118: iconst_2
/*    */     //   1119: anewarray java/lang/String
/*    */     //   1122: dup
/*    */     //   1123: astore #13
/*    */     //   1125: aload #11
/*    */     //   1127: aload #13
/*    */     //   1129: aload #5
/*    */     //   1131: invokevirtual fA : ()Ljava/lang/String;
/*    */     //   1134: iconst_0
/*    */     //   1135: swap
/*    */     //   1136: aastore
/*    */     //   1137: invokevirtual fA : ()Ljava/lang/String;
/*    */     //   1140: iconst_1
/*    */     //   1141: swap
/*    */     //   1142: aastore
/*    */     //   1143: iconst_2
/*    */     //   1144: aload #10
/*    */     //   1146: bipush #14
/*    */     //   1148: iload #12
/*    */     //   1150: aload #13
/*    */     //   1152: invokestatic lz : (BLf/F40;II[Ljava/lang/String;)Ljava/lang/String;
/*    */     //   1155: goto -> 1672
/*    */     //   1158: aload #4
/*    */     //   1160: getstatic f/F40.ef0 : Lf/F40;
/*    */     //   1163: astore #10
/*    */     //   1165: sipush #541
/*    */     //   1168: aload #5
/*    */     //   1170: invokevirtual ex : (ILf/hm0;)I
/*    */     //   1173: istore #11
/*    */     //   1175: iconst_1
/*    */     //   1176: anewarray java/lang/String
/*    */     //   1179: dup
/*    */     //   1180: astore #12
/*    */     //   1182: aload #5
/*    */     //   1184: invokevirtual fA : ()Ljava/lang/String;
/*    */     //   1187: iconst_0
/*    */     //   1188: swap
/*    */     //   1189: aastore
/*    */     //   1190: iconst_2
/*    */     //   1191: aload #10
/*    */     //   1193: bipush #14
/*    */     //   1195: iload #11
/*    */     //   1197: aload #12
/*    */     //   1199: invokestatic lz : (BLf/F40;II[Ljava/lang/String;)Ljava/lang/String;
/*    */     //   1202: goto -> 1672
/*    */     //   1205: aload #4
/*    */     //   1207: getstatic f/F40.ef0 : Lf/F40;
/*    */     //   1210: astore #10
/*    */     //   1212: sipush #535
/*    */     //   1215: aload #5
/*    */     //   1217: invokevirtual ex : (ILf/hm0;)I
/*    */     //   1220: istore #11
/*    */     //   1222: iconst_1
/*    */     //   1223: anewarray java/lang/String
/*    */     //   1226: dup
/*    */     //   1227: astore #12
/*    */     //   1229: aload #5
/*    */     //   1231: invokevirtual fA : ()Ljava/lang/String;
/*    */     //   1234: iconst_0
/*    */     //   1235: swap
/*    */     //   1236: aastore
/*    */     //   1237: iconst_2
/*    */     //   1238: aload #10
/*    */     //   1240: bipush #14
/*    */     //   1242: iload #11
/*    */     //   1244: aload #12
/*    */     //   1246: invokestatic lz : (BLf/F40;II[Ljava/lang/String;)Ljava/lang/String;
/*    */     //   1249: goto -> 1672
/*    */     //   1252: aload #4
/*    */     //   1254: getstatic f/F40.ef0 : Lf/F40;
/*    */     //   1257: astore #10
/*    */     //   1259: sipush #616
/*    */     //   1262: aload #5
/*    */     //   1264: invokevirtual ex : (ILf/hm0;)I
/*    */     //   1267: istore #11
/*    */     //   1269: iconst_1
/*    */     //   1270: anewarray java/lang/String
/*    */     //   1273: dup
/*    */     //   1274: astore #12
/*    */     //   1276: aload #5
/*    */     //   1278: invokevirtual fA : ()Ljava/lang/String;
/*    */     //   1281: iconst_0
/*    */     //   1282: swap
/*    */     //   1283: aastore
/*    */     //   1284: iconst_2
/*    */     //   1285: aload #10
/*    */     //   1287: bipush #14
/*    */     //   1289: iload #11
/*    */     //   1291: aload #12
/*    */     //   1293: invokestatic lz : (BLf/F40;II[Ljava/lang/String;)Ljava/lang/String;
/*    */     //   1296: goto -> 1672
/*    */     //   1299: aload #4
/*    */     //   1301: getstatic f/F40.ef0 : Lf/F40;
/*    */     //   1304: astore #10
/*    */     //   1306: sipush #550
/*    */     //   1309: aload #5
/*    */     //   1311: invokevirtual ex : (ILf/hm0;)I
/*    */     //   1314: istore #11
/*    */     //   1316: iconst_1
/*    */     //   1317: anewarray java/lang/String
/*    */     //   1320: dup
/*    */     //   1321: astore #12
/*    */     //   1323: aload #5
/*    */     //   1325: invokevirtual fA : ()Ljava/lang/String;
/*    */     //   1328: iconst_0
/*    */     //   1329: swap
/*    */     //   1330: aastore
/*    */     //   1331: iconst_2
/*    */     //   1332: aload #10
/*    */     //   1334: bipush #14
/*    */     //   1336: iload #11
/*    */     //   1338: aload #12
/*    */     //   1340: invokestatic lz : (BLf/F40;II[Ljava/lang/String;)Ljava/lang/String;
/*    */     //   1343: goto -> 1672
/*    */     //   1346: aload #4
/*    */     //   1348: getstatic f/F40.ef0 : Lf/F40;
/*    */     //   1351: astore #10
/*    */     //   1353: sipush #556
/*    */     //   1356: aload #5
/*    */     //   1358: invokevirtual ex : (ILf/hm0;)I
/*    */     //   1361: istore #11
/*    */     //   1363: iconst_1
/*    */     //   1364: anewarray java/lang/String
/*    */     //   1367: dup
/*    */     //   1368: astore #12
/*    */     //   1370: aload #5
/*    */     //   1372: invokevirtual fA : ()Ljava/lang/String;
/*    */     //   1375: iconst_0
/*    */     //   1376: swap
/*    */     //   1377: aastore
/*    */     //   1378: iconst_2
/*    */     //   1379: aload #10
/*    */     //   1381: bipush #14
/*    */     //   1383: iload #11
/*    */     //   1385: aload #12
/*    */     //   1387: invokestatic lz : (BLf/F40;II[Ljava/lang/String;)Ljava/lang/String;
/*    */     //   1390: goto -> 1672
/*    */     //   1393: aload #4
/*    */     //   1395: getstatic f/F40.ef0 : Lf/F40;
/*    */     //   1398: astore #10
/*    */     //   1400: sipush #745
/*    */     //   1403: aload #5
/*    */     //   1405: invokevirtual ex : (ILf/hm0;)I
/*    */     //   1408: istore #11
/*    */     //   1410: iconst_1
/*    */     //   1411: anewarray java/lang/String
/*    */     //   1414: dup
/*    */     //   1415: astore #12
/*    */     //   1417: aload #5
/*    */     //   1419: invokevirtual fA : ()Ljava/lang/String;
/*    */     //   1422: iconst_0
/*    */     //   1423: swap
/*    */     //   1424: aastore
/*    */     //   1425: iconst_2
/*    */     //   1426: aload #10
/*    */     //   1428: bipush #14
/*    */     //   1430: iload #11
/*    */     //   1432: aload #12
/*    */     //   1434: invokestatic lz : (BLf/F40;II[Ljava/lang/String;)Ljava/lang/String;
/*    */     //   1437: goto -> 1672
/*    */     //   1440: aload #4
/*    */     //   1442: getstatic f/F40.ef0 : Lf/F40;
/*    */     //   1445: astore #10
/*    */     //   1447: sipush #538
/*    */     //   1450: aload #5
/*    */     //   1452: invokevirtual ex : (ILf/hm0;)I
/*    */     //   1455: istore #11
/*    */     //   1457: iconst_1
/*    */     //   1458: anewarray java/lang/String
/*    */     //   1461: dup
/*    */     //   1462: astore #12
/*    */     //   1464: aload #5
/*    */     //   1466: invokevirtual fA : ()Ljava/lang/String;
/*    */     //   1469: iconst_0
/*    */     //   1470: swap
/*    */     //   1471: aastore
/*    */     //   1472: iconst_2
/*    */     //   1473: aload #10
/*    */     //   1475: bipush #14
/*    */     //   1477: iload #11
/*    */     //   1479: aload #12
/*    */     //   1481: invokestatic lz : (BLf/F40;II[Ljava/lang/String;)Ljava/lang/String;
/*    */     //   1484: goto -> 1672
/*    */     //   1487: aload #4
/*    */     //   1489: getstatic f/F40.ef0 : Lf/F40;
/*    */     //   1492: astore #10
/*    */     //   1494: sipush #553
/*    */     //   1497: aload #5
/*    */     //   1499: invokevirtual ex : (ILf/hm0;)I
/*    */     //   1502: istore #11
/*    */     //   1504: iconst_1
/*    */     //   1505: anewarray java/lang/String
/*    */     //   1508: dup
/*    */     //   1509: astore #12
/*    */     //   1511: aload #5
/*    */     //   1513: invokevirtual fA : ()Ljava/lang/String;
/*    */     //   1516: iconst_0
/*    */     //   1517: swap
/*    */     //   1518: aastore
/*    */     //   1519: iconst_2
/*    */     //   1520: aload #10
/*    */     //   1522: bipush #14
/*    */     //   1524: iload #11
/*    */     //   1526: aload #12
/*    */     //   1528: invokestatic lz : (BLf/F40;II[Ljava/lang/String;)Ljava/lang/String;
/*    */     //   1531: goto -> 1672
/*    */     //   1534: aload #4
/*    */     //   1536: getstatic f/F40.ef0 : Lf/F40;
/*    */     //   1539: astore #10
/*    */     //   1541: sipush #529
/*    */     //   1544: aload #5
/*    */     //   1546: invokevirtual ex : (ILf/hm0;)I
/*    */     //   1549: istore #11
/*    */     //   1551: iconst_1
/*    */     //   1552: anewarray java/lang/String
/*    */     //   1555: dup
/*    */     //   1556: astore #12
/*    */     //   1558: aload #5
/*    */     //   1560: invokevirtual fA : ()Ljava/lang/String;
/*    */     //   1563: iconst_0
/*    */     //   1564: swap
/*    */     //   1565: aastore
/*    */     //   1566: iconst_2
/*    */     //   1567: aload #10
/*    */     //   1569: bipush #14
/*    */     //   1571: iload #11
/*    */     //   1573: aload #12
/*    */     //   1575: invokestatic lz : (BLf/F40;II[Ljava/lang/String;)Ljava/lang/String;
/*    */     //   1578: goto -> 1672
/*    */     //   1581: aload #4
/*    */     //   1583: getstatic f/F40.ef0 : Lf/F40;
/*    */     //   1586: astore #10
/*    */     //   1588: sipush #547
/*    */     //   1591: aload #5
/*    */     //   1593: invokevirtual ex : (ILf/hm0;)I
/*    */     //   1596: istore #11
/*    */     //   1598: iconst_1
/*    */     //   1599: anewarray java/lang/String
/*    */     //   1602: dup
/*    */     //   1603: astore #12
/*    */     //   1605: aload #5
/*    */     //   1607: invokevirtual fA : ()Ljava/lang/String;
/*    */     //   1610: iconst_0
/*    */     //   1611: swap
/*    */     //   1612: aastore
/*    */     //   1613: iconst_2
/*    */     //   1614: aload #10
/*    */     //   1616: bipush #14
/*    */     //   1618: iload #11
/*    */     //   1620: aload #12
/*    */     //   1622: invokestatic lz : (BLf/F40;II[Ljava/lang/String;)Ljava/lang/String;
/*    */     //   1625: goto -> 1672
/*    */     //   1628: aload #4
/*    */     //   1630: getstatic f/F40.ef0 : Lf/F40;
/*    */     //   1633: astore #10
/*    */     //   1635: sipush #544
/*    */     //   1638: aload #5
/*    */     //   1640: invokevirtual ex : (ILf/hm0;)I
/*    */     //   1643: istore #11
/*    */     //   1645: iconst_1
/*    */     //   1646: anewarray java/lang/String
/*    */     //   1649: dup
/*    */     //   1650: astore #12
/*    */     //   1652: aload #5
/*    */     //   1654: invokevirtual fA : ()Ljava/lang/String;
/*    */     //   1657: iconst_0
/*    */     //   1658: swap
/*    */     //   1659: aastore
/*    */     //   1660: iconst_2
/*    */     //   1661: aload #10
/*    */     //   1663: bipush #14
/*    */     //   1665: iload #11
/*    */     //   1667: aload #12
/*    */     //   1669: invokestatic lz : (BLf/F40;II[Ljava/lang/String;)Ljava/lang/String;
/*    */     //   1672: astore #10
/*    */     //   1674: goto -> 1944
/*    */     //   1677: aload #5
/*    */     //   1679: getfield i8 : B
/*    */     //   1682: dup
/*    */     //   1683: istore #11
/*    */     //   1685: ifeq -> 1727
/*    */     //   1688: iload #11
/*    */     //   1690: iconst_1
/*    */     //   1691: if_icmpeq -> 1718
/*    */     //   1694: iload #11
/*    */     //   1696: iconst_2
/*    */     //   1697: if_icmpeq -> 1703
/*    */     //   1700: goto -> 1944
/*    */     //   1703: aload #5
/*    */     //   1705: invokevirtual fA : ()Ljava/lang/String;
/*    */     //   1708: ldc_w 200430
/*    */     //   1711: swap
/*    */     //   1712: invokestatic Go : (ILjava/lang/String;)Ljava/lang/String;
/*    */     //   1715: goto -> 1672
/*    */     //   1718: ldc_w 200429
/*    */     //   1721: invokestatic OH0 : (I)Ljava/lang/String;
/*    */     //   1724: goto -> 1672
/*    */     //   1727: aload #5
/*    */     //   1729: invokevirtual fA : ()Ljava/lang/String;
/*    */     //   1732: ldc_w 200428
/*    */     //   1735: swap
/*    */     //   1736: invokestatic Go : (ILjava/lang/String;)Ljava/lang/String;
/*    */     //   1739: goto -> 1672
/*    */     //   1742: aload_0
/*    */     //   1743: getfield Xj0 : S
/*    */     //   1746: ifle -> 1944
/*    */     //   1749: aload_0
/*    */     //   1750: invokestatic cw : ()Lf/yk0;
/*    */     //   1753: aload_0
/*    */     //   1754: getfield Xj0 : S
/*    */     //   1757: invokevirtual mP : (S)Lf/WD;
/*    */     //   1760: getfield iz : I
/*    */     //   1763: invokestatic OH0 : (I)Ljava/lang/String;
/*    */     //   1766: astore #10
/*    */     //   1768: getfield Xj0 : S
/*    */     //   1771: dup
/*    */     //   1772: istore #11
/*    */     //   1774: sipush #1000
/*    */     //   1777: if_icmpge -> 1907
/*    */     //   1780: iload #11
/*    */     //   1782: ldc_w 110000
/*    */     //   1785: iadd
/*    */     //   1786: getstatic f/Ml0.ha : Lf/V6;
/*    */     //   1789: swap
/*    */     //   1790: invokevirtual return : (I)Z
/*    */     //   1793: ifne -> 1907
/*    */     //   1796: aload #4
/*    */     //   1798: aload_0
/*    */     //   1799: getfield Xj0 : S
/*    */     //   1802: iconst_3
/*    */     //   1803: imul
/*    */     //   1804: aload #5
/*    */     //   1806: getstatic f/F40.ef0 : Lf/F40;
/*    */     //   1809: astore #11
/*    */     //   1811: invokevirtual ex : (ILf/hm0;)I
/*    */     //   1814: istore #12
/*    */     //   1816: iconst_1
/*    */     //   1817: anewarray java/lang/String
/*    */     //   1820: dup
/*    */     //   1821: astore #13
/*    */     //   1823: aload #5
/*    */     //   1825: invokevirtual fA : ()Ljava/lang/String;
/*    */     //   1828: iconst_0
/*    */     //   1829: swap
/*    */     //   1830: aastore
/*    */     //   1831: iconst_2
/*    */     //   1832: aload #11
/*    */     //   1834: bipush #13
/*    */     //   1836: iload #12
/*    */     //   1838: aload #13
/*    */     //   1840: invokestatic lz : (BLf/F40;II[Ljava/lang/String;)Ljava/lang/String;
/*    */     //   1843: dup
/*    */     //   1844: astore #11
/*    */     //   1846: aload #10
/*    */     //   1848: new java/lang/StringBuilder
/*    */     //   1851: dup
/*    */     //   1852: astore #12
/*    */     //   1854: aload #11
/*    */     //   1856: invokespecial <init> : (Ljava/lang/String;)V
/*    */     //   1859: invokevirtual lastIndexOf : (Ljava/lang/String;)I
/*    */     //   1862: dup
/*    */     //   1863: istore #13
/*    */     //   1865: iflt -> 1902
/*    */     //   1868: aload #12
/*    */     //   1870: iload #13
/*    */     //   1872: aload #10
/*    */     //   1874: invokevirtual length : ()I
/*    */     //   1877: iload #13
/*    */     //   1879: iadd
/*    */     //   1880: ldc_w '[#ff8a00]'
/*    */     //   1883: aload #10
/*    */     //   1885: ldc_w '[#]'
/*    */     //   1888: invokestatic AT : (Ljava/lang/String;Ljava/lang/String;Ljava/lang/String;)Ljava/lang/String;
/*    */     //   1891: swap
/*    */     //   1892: swap
/*    */     //   1893: invokevirtual replace : (IILjava/lang/String;)Ljava/lang/StringBuilder;
/*    */     //   1896: invokevirtual toString : ()Ljava/lang/String;
/*    */     //   1899: goto -> 1672
/*    */     //   1902: aload #11
/*    */     //   1904: goto -> 1672
/*    */     //   1907: getstatic f/F40.ef0 : Lf/F40;
/*    */     //   1910: iconst_2
/*    */     //   1911: anewarray java/lang/String
/*    */     //   1914: dup
/*    */     //   1915: dup
/*    */     //   1916: astore #11
/*    */     //   1918: aload #5
/*    */     //   1920: invokevirtual fA : ()Ljava/lang/String;
/*    */     //   1923: iconst_0
/*    */     //   1924: swap
/*    */     //   1925: aastore
/*    */     //   1926: iconst_1
/*    */     //   1927: aload #10
/*    */     //   1929: aastore
/*    */     //   1930: iconst_2
/*    */     //   1931: swap
/*    */     //   1932: bipush #8
/*    */     //   1934: bipush #52
/*    */     //   1936: aload #11
/*    */     //   1938: invokestatic lz : (BLf/F40;II[Ljava/lang/String;)Ljava/lang/String;
/*    */     //   1941: goto -> 1672
/*    */     //   1944: aload #4
/*    */     //   1946: ldc_w ''
/*    */     //   1949: astore #11
/*    */     //   1951: getstatic f/h1.A4 : Lf/ik;
/*    */     //   1954: pop
/*    */     //   1955: invokevirtual yx0 : ()Z
/*    */     //   1958: ifeq -> 1971
/*    */     //   1961: getstatic f/h1.ak0 : I
/*    */     //   1964: iconst_1
/*    */     //   1965: if_icmplt -> 1982
/*    */     //   1968: goto -> 1978
/*    */     //   1971: getstatic f/h1.ak0 : I
/*    */     //   1974: iconst_2
/*    */     //   1975: if_icmplt -> 1982
/*    */     //   1978: iconst_1
/*    */     //   1979: goto -> 1983
/*    */     //   1982: iconst_0
/*    */     //   1983: ifeq -> 2397
/*    */     //   1986: aload #9
/*    */     //   1988: getfield ir0 : I
/*    */     //   1991: ifle -> 2397
/*    */     //   1994: new java/lang/StringBuilder
/*    */     //   1997: dup
/*    */     //   1998: astore #11
/*    */     //   2000: aload #9
/*    */     //   2002: dup
/*    */     //   2003: aload #11
/*    */     //   2005: invokespecial <init> : ()V
/*    */     //   2008: getfield ir0 : I
/*    */     //   2011: istore #12
/*    */     //   2013: invokevirtual FH : ()I
/*    */     //   2016: istore #13
/*    */     //   2018: ldc_w '( '
/*    */     //   2021: invokevirtual append : (Ljava/lang/String;)Ljava/lang/StringBuilder;
/*    */     //   2024: pop
/*    */     //   2025: iload #12
/*    */     //   2027: aload #9
/*    */     //   2029: getfield ir0 : I
/*    */     //   2032: if_icmpne -> 2389
/*    */     //   2035: aload #9
/*    */     //   2037: getfield QG0 : [Ljava/lang/Object;
/*    */     //   2040: astore #14
/*    */     //   2042: iload #13
/*    */     //   2044: istore #15
/*    */     //   2046: iload #15
/*    */     //   2048: dup
/*    */     //   2049: iconst_m1
/*    */     //   2050: iadd
/*    */     //   2051: istore #15
/*    */     //   2053: ifle -> 2081
/*    */     //   2056: aload #14
/*    */     //   2058: iload #15
/*    */     //   2060: aaload
/*    */     //   2061: dup
/*    */     //   2062: astore #16
/*    */     //   2064: getstatic f/zb0.IM : Ljava/lang/Object;
/*    */     //   2067: if_acmpeq -> 2046
/*    */     //   2070: aload #16
/*    */     //   2072: getstatic f/zb0.ET : Ljava/lang/Object;
/*    */     //   2075: if_acmpne -> 2081
/*    */     //   2078: goto -> 2046
/*    */     //   2081: iload #15
/*    */     //   2083: iflt -> 2090
/*    */     //   2086: iconst_1
/*    */     //   2087: goto -> 2091
/*    */     //   2090: iconst_0
/*    */     //   2091: ifeq -> 2345
/*    */     //   2094: iload #12
/*    */     //   2096: aload #9
/*    */     //   2098: getfield ir0 : I
/*    */     //   2101: if_icmpne -> 2337
/*    */     //   2104: aload #9
/*    */     //   2106: getfield QG0 : [Ljava/lang/Object;
/*    */     //   2109: astore #14
/*    */     //   2111: iload #13
/*    */     //   2113: dup
/*    */     //   2114: iconst_m1
/*    */     //   2115: iadd
/*    */     //   2116: istore #13
/*    */     //   2118: ifle -> 2146
/*    */     //   2121: aload #14
/*    */     //   2123: iload #13
/*    */     //   2125: aaload
/*    */     //   2126: dup
/*    */     //   2127: astore #15
/*    */     //   2129: getstatic f/zb0.IM : Ljava/lang/Object;
/*    */     //   2132: if_acmpeq -> 2111
/*    */     //   2135: aload #15
/*    */     //   2137: getstatic f/zb0.ET : Ljava/lang/Object;
/*    */     //   2140: if_acmpne -> 2146
/*    */     //   2143: goto -> 2111
/*    */     //   2146: iload #13
/*    */     //   2148: iflt -> 2329
/*    */     //   2151: aload #9
/*    */     //   2153: aload #11
/*    */     //   2155: dup
/*    */     //   2156: aload #9
/*    */     //   2158: getfield QG0 : [Ljava/lang/Object;
/*    */     //   2161: iload #13
/*    */     //   2163: aaload
/*    */     //   2164: checkcast f/hm0
/*    */     //   2167: invokevirtual coM1 : ()Ljava/lang/String;
/*    */     //   2170: invokevirtual append : (Ljava/lang/String;)Ljava/lang/StringBuilder;
/*    */     //   2173: pop
/*    */     //   2174: ldc_w ' '
/*    */     //   2177: invokevirtual append : (Ljava/lang/String;)Ljava/lang/StringBuilder;
/*    */     //   2180: pop
/*    */     //   2181: getfield jI0 : [D
/*    */     //   2184: iload #13
/*    */     //   2186: daload
/*    */     //   2187: dconst_0
/*    */     //   2188: dcmpl
/*    */     //   2189: ifle -> 2200
/*    */     //   2192: ldc_w '+'
/*    */     //   2195: astore #14
/*    */     //   2197: goto -> 2205
/*    */     //   2200: ldc_w ''
/*    */     //   2203: astore #14
/*    */     //   2205: iload #12
/*    */     //   2207: aload #9
/*    */     //   2209: aload #11
/*    */     //   2211: dup
/*    */     //   2212: dup
/*    */     //   2213: aload #14
/*    */     //   2215: invokevirtual append : (Ljava/lang/String;)Ljava/lang/StringBuilder;
/*    */     //   2218: pop
/*    */     //   2219: invokestatic getInstance : ()Ljava/text/NumberFormat;
/*    */     //   2222: aload #9
/*    */     //   2224: getfield jI0 : [D
/*    */     //   2227: iload #13
/*    */     //   2229: daload
/*    */     //   2230: invokevirtual format : (D)Ljava/lang/String;
/*    */     //   2233: invokevirtual append : (Ljava/lang/String;)Ljava/lang/StringBuilder;
/*    */     //   2236: pop
/*    */     //   2237: ldc_w '%'
/*    */     //   2240: invokevirtual append : (Ljava/lang/String;)Ljava/lang/StringBuilder;
/*    */     //   2243: pop
/*    */     //   2244: getfield ir0 : I
/*    */     //   2247: if_icmpne -> 2321
/*    */     //   2250: aload #9
/*    */     //   2252: getfield QG0 : [Ljava/lang/Object;
/*    */     //   2255: astore #14
/*    */     //   2257: iload #13
/*    */     //   2259: istore #15
/*    */     //   2261: iload #15
/*    */     //   2263: dup
/*    */     //   2264: iconst_m1
/*    */     //   2265: iadd
/*    */     //   2266: istore #15
/*    */     //   2268: ifle -> 2296
/*    */     //   2271: aload #14
/*    */     //   2273: iload #15
/*    */     //   2275: aaload
/*    */     //   2276: dup
/*    */     //   2277: astore #16
/*    */     //   2279: getstatic f/zb0.IM : Ljava/lang/Object;
/*    */     //   2282: if_acmpeq -> 2261
/*    */     //   2285: aload #16
/*    */     //   2287: getstatic f/zb0.ET : Ljava/lang/Object;
/*    */     //   2290: if_acmpne -> 2296
/*    */     //   2293: goto -> 2261
/*    */     //   2296: iload #15
/*    */     //   2298: iflt -> 2305
/*    */     //   2301: iconst_1
/*    */     //   2302: goto -> 2306
/*    */     //   2305: iconst_0
/*    */     //   2306: ifeq -> 2025
/*    */     //   2309: aload #11
/*    */     //   2311: ldc_w ', '
/*    */     //   2314: invokevirtual append : (Ljava/lang/String;)Ljava/lang/StringBuilder;
/*    */     //   2317: pop
/*    */     //   2318: goto -> 2025
/*    */     //   2321: new java/util/ConcurrentModificationException
/*    */     //   2324: dup
/*    */     //   2325: invokespecial <init> : ()V
/*    */     //   2328: athrow
/*    */     //   2329: new java/util/NoSuchElementException
/*    */     //   2332: dup
/*    */     //   2333: invokespecial <init> : ()V
/*    */     //   2336: athrow
/*    */     //   2337: new java/util/ConcurrentModificationException
/*    */     //   2340: dup
/*    */     //   2341: invokespecial <init> : ()V
/*    */     //   2344: athrow
/*    */     //   2345: aload #11
/*    */     //   2347: ldc_w ' )'
/*    */     //   2350: invokevirtual append : (Ljava/lang/String;)Ljava/lang/StringBuilder;
/*    */     //   2353: pop
/*    */     //   2354: new java/lang/StringBuilder
/*    */     //   2357: dup
/*    */     //   2358: aload #10
/*    */     //   2360: swap
/*    */     //   2361: invokespecial <init> : ()V
/*    */     //   2364: invokevirtual append : (Ljava/lang/String;)Ljava/lang/StringBuilder;
/*    */     //   2367: ldc_w ' '
/*    */     //   2370: invokevirtual append : (Ljava/lang/String;)Ljava/lang/StringBuilder;
/*    */     //   2373: aload #11
/*    */     //   2375: invokevirtual toString : ()Ljava/lang/String;
/*    */     //   2378: invokevirtual append : (Ljava/lang/String;)Ljava/lang/StringBuilder;
/*    */     //   2381: invokevirtual toString : ()Ljava/lang/String;
/*    */     //   2384: astore #11
/*    */     //   2386: goto -> 2397
/*    */     //   2389: new java/util/ConcurrentModificationException
/*    */     //   2392: dup
/*    */     //   2393: invokespecial <init> : ()V
/*    */     //   2396: athrow
/*    */     //   2397: aload #7
/*    */     //   2399: ifnull -> 2452
/*    */     //   2402: aload_1
/*    */     //   2403: dup
/*    */     //   2404: dup
/*    */     //   2405: aload #10
/*    */     //   2407: aload #11
/*    */     //   2409: aconst_null
/*    */     //   2410: invokevirtual r00 : (Ljava/lang/String;Ljava/lang/String;Ljava/lang/Runnable;)V
/*    */     //   2413: getfield YP : Ljava/util/LinkedList;
/*    */     //   2416: new f/LV
/*    */     //   2419: dup
/*    */     //   2420: new f/MY
/*    */     //   2423: dup
/*    */     //   2424: aload #5
/*    */     //   2426: ldc_w 0.5
/*    */     //   2429: aconst_null
/*    */     //   2430: invokespecial <init> : (Lf/hm0;FLjava/lang/Runnable;)V
/*    */     //   2433: invokespecial <init> : (Lf/wb;)V
/*    */     //   2436: invokevirtual add : (Ljava/lang/Object;)Z
/*    */     //   2439: pop
/*    */     //   2440: getfield YP : Ljava/util/LinkedList;
/*    */     //   2443: aload #7
/*    */     //   2445: invokevirtual add : (Ljava/lang/Object;)Z
/*    */     //   2448: pop
/*    */     //   2449: goto -> 2470
/*    */     //   2452: aload #10
/*    */     //   2454: invokevirtual isEmpty : ()Z
/*    */     //   2457: ifne -> 2470
/*    */     //   2460: aload_1
/*    */     //   2461: aload #10
/*    */     //   2463: ldc_w ''
/*    */     //   2466: aconst_null
/*    */     //   2467: invokevirtual RV : (Ljava/lang/String;Ljava/lang/String;Ljava/lang/Runnable;)V
/*    */     //   2470: aload #4
/*    */     //   2472: getfield rx : Lf/ky;
/*    */     //   2475: getstatic f/ky.We0 : Lf/ky;
/*    */     //   2478: if_acmpne -> 2487
/*    */     //   2481: iconst_1
/*    */     //   2482: istore #7
/*    */     //   2484: goto -> 2490
/*    */     //   2487: iconst_0
/*    */     //   2488: istore #7
/*    */     //   2490: aload #4
/*    */     //   2492: dup
/*    */     //   2493: invokevirtual nI : ()B
/*    */     //   2496: istore #9
/*    */     //   2498: iconst_0
/*    */     //   2499: istore #10
/*    */     //   2501: getfield cl : [[Lf/hm0;
/*    */     //   2504: iload #9
/*    */     //   2506: aaload
/*    */     //   2507: dup
/*    */     //   2508: astore #9
/*    */     //   2510: arraylength
/*    */     //   2511: istore #11
/*    */     //   2513: iconst_0
/*    */     //   2514: istore #12
/*    */     //   2516: iload #12
/*    */     //   2518: iload #11
/*    */     //   2520: if_icmpge -> 2554
/*    */     //   2523: aload #9
/*    */     //   2525: iload #12
/*    */     //   2527: aaload
/*    */     //   2528: dup
/*    */     //   2529: astore #13
/*    */     //   2531: ifnull -> 2548
/*    */     //   2534: aload #13
/*    */     //   2536: getfield K0 : Lf/jd0;
/*    */     //   2539: invokevirtual AL : ()Z
/*    */     //   2542: ifne -> 2548
/*    */     //   2545: iinc #10, 1
/*    */     //   2548: iinc #12, 1
/*    */     //   2551: goto -> 2516
/*    */     //   2554: aload #6
/*    */     //   2556: new java/util/ArrayList
/*    */     //   2559: dup
/*    */     //   2560: astore #9
/*    */     //   2562: invokespecial <init> : ()V
/*    */     //   2565: new java/util/ArrayList
/*    */     //   2568: dup
/*    */     //   2569: astore #11
/*    */     //   2571: invokespecial <init> : ()V
/*    */     //   2574: new f/qw0
/*    */     //   2577: dup
/*    */     //   2578: astore #12
/*    */     //   2580: invokespecial <init> : ()V
/*    */     //   2583: new f/Xj0
/*    */     //   2586: dup
/*    */     //   2587: astore #13
/*    */     //   2589: invokespecial <init> : ()V
/*    */     //   2592: sipush #1380
/*    */     //   2595: istore #14
/*    */     //   2597: invokeinterface iterator : ()Ljava/util/Iterator;
/*    */     //   2602: astore #15
/*    */     //   2604: aload #15
/*    */     //   2606: invokeinterface hasNext : ()Z
/*    */     //   2611: ifeq -> 3040
/*    */     //   2614: iload #14
/*    */     //   2616: aload #15
/*    */     //   2618: invokeinterface next : ()Ljava/lang/Object;
/*    */     //   2623: checkcast f/b60
/*    */     //   2626: astore #16
/*    */     //   2628: sipush #1380
/*    */     //   2631: if_icmpgt -> 2667
/*    */     //   2634: aload #16
/*    */     //   2636: bipush #32
/*    */     //   2638: invokevirtual Fc0 : (S)Z
/*    */     //   2641: ifeq -> 2652
/*    */     //   2644: sipush #1379
/*    */     //   2647: istore #14
/*    */     //   2649: goto -> 2667
/*    */     //   2652: aload #16
/*    */     //   2654: bipush #16
/*    */     //   2656: invokevirtual Fc0 : (S)Z
/*    */     //   2659: ifeq -> 2667
/*    */     //   2662: sipush #1381
/*    */     //   2665: istore #14
/*    */     //   2667: aload #16
/*    */     //   2669: getfield a0 : I
/*    */     //   2672: dup
/*    */     //   2673: istore #17
/*    */     //   2675: ifne -> 2685
/*    */     //   2678: aload #5
/*    */     //   2680: astore #17
/*    */     //   2682: goto -> 2694
/*    */     //   2685: aload #4
/*    */     //   2687: iload #17
/*    */     //   2689: invokevirtual fa : (I)Lf/hm0;
/*    */     //   2692: astore #17
/*    */     //   2694: aload #17
/*    */     //   2696: getfield FT : B
/*    */     //   2699: aload #4
/*    */     //   2701: invokevirtual nI : ()B
/*    */     //   2704: if_icmpne -> 2713
/*    */     //   2707: iconst_1
/*    */     //   2708: istore #18
/*    */     //   2710: goto -> 2716
/*    */     //   2713: iconst_0
/*    */     //   2714: istore #18
/*    */     //   2716: aload #16
/*    */     //   2718: sipush #256
/*    */     //   2721: invokevirtual Fc0 : (S)Z
/*    */     //   2724: ifeq -> 2843
/*    */     //   2727: aload #16
/*    */     //   2729: iconst_0
/*    */     //   2730: istore #19
/*    */     //   2732: bipush #32
/*    */     //   2734: invokevirtual Fc0 : (S)Z
/*    */     //   2737: ifeq -> 2763
/*    */     //   2740: iload #18
/*    */     //   2742: bipush #32
/*    */     //   2744: istore #18
/*    */     //   2746: ifeq -> 2753
/*    */     //   2749: iconst_1
/*    */     //   2750: goto -> 2754
/*    */     //   2753: iconst_m1
/*    */     //   2754: iload #18
/*    */     //   2756: imul
/*    */     //   2757: i2s
/*    */     //   2758: istore #19
/*    */     //   2760: goto -> 2793
/*    */     //   2763: aload #16
/*    */     //   2765: bipush #16
/*    */     //   2767: invokevirtual Fc0 : (S)Z
/*    */     //   2770: ifeq -> 2793
/*    */     //   2773: iload #18
/*    */     //   2775: bipush #16
/*    */     //   2777: istore #18
/*    */     //   2779: ifeq -> 2786
/*    */     //   2782: iconst_1
/*    */     //   2783: goto -> 2787
/*    */     //   2786: iconst_m1
/*    */     //   2787: iload #18
/*    */     //   2789: imul
/*    */     //   2790: i2s
/*    */     //   2791: istore #19
/*    */     //   2793: iload #19
/*    */     //   2795: ifeq -> 2843
/*    */     //   2798: aload #12
/*    */     //   2800: iload #19
/*    */     //   2802: invokevirtual Z90 : (S)Ljava/lang/Object;
/*    */     //   2805: checkcast java/util/List
/*    */     //   2808: dup
/*    */     //   2809: astore #18
/*    */     //   2811: ifnonnull -> 2833
/*    */     //   2814: aload #12
/*    */     //   2816: new java/util/ArrayList
/*    */     //   2819: dup
/*    */     //   2820: astore #18
/*    */     //   2822: invokespecial <init> : ()V
/*    */     //   2825: iload #19
/*    */     //   2827: aload #18
/*    */     //   2829: invokevirtual Vh0 : (SLjava/lang/Object;)Ljava/lang/Object;
/*    */     //   2832: pop
/*    */     //   2833: aload #18
/*    */     //   2835: aload #17
/*    */     //   2837: invokeinterface add : (Ljava/lang/Object;)Z
/*    */     //   2842: pop
/*    */     //   2843: aload #16
/*    */     //   2845: getfield JX : Ljava/util/ArrayList;
/*    */     //   2848: invokevirtual iterator : ()Ljava/util/Iterator;
/*    */     //   2851: astore #18
/*    */     //   2853: aload #18
/*    */     //   2855: invokeinterface hasNext : ()Z
/*    */     //   2860: ifeq -> 2604
/*    */     //   2863: aload #18
/*    */     //   2865: invokeinterface next : ()Ljava/lang/Object;
/*    */     //   2870: checkcast f/GS
/*    */     //   2873: dup
/*    */     //   2874: astore #19
/*    */     //   2876: bipush #8
/*    */     //   2878: invokevirtual QI : (B)Z
/*    */     //   2881: ifeq -> 2997
/*    */     //   2884: iload #7
/*    */     //   2886: ifeq -> 2956
/*    */     //   2889: aload #19
/*    */     //   2891: invokevirtual YG0 : ()B
/*    */     //   2894: ifne -> 2956
/*    */     //   2897: aload #19
/*    */     //   2899: checkcast f/JS
/*    */     //   2902: getfield cOM9 : S
/*    */     //   2905: iconst_1
/*    */     //   2906: if_icmpge -> 2997
/*    */     //   2909: aload #17
/*    */     //   2911: getfield K0 : Lf/jd0;
/*    */     //   2914: invokevirtual AL : ()Z
/*    */     //   2917: ifne -> 2997
/*    */     //   2920: aload #9
/*    */     //   2922: aload #16
/*    */     //   2924: invokevirtual contains : (Ljava/lang/Object;)Z
/*    */     //   2927: ifne -> 2997
/*    */     //   2930: aload #17
/*    */     //   2932: aload #5
/*    */     //   2934: if_acmpeq -> 2997
/*    */     //   2937: aload #11
/*    */     //   2939: aload #9
/*    */     //   2941: aload #16
/*    */     //   2943: invokevirtual add : (Ljava/lang/Object;)Z
/*    */     //   2946: pop
/*    */     //   2947: aload #17
/*    */     //   2949: invokevirtual add : (Ljava/lang/Object;)Z
/*    */     //   2952: pop
/*    */     //   2953: goto -> 2997
/*    */     //   2956: aload #16
/*    */     //   2958: sipush #-32577
/*    */     //   2961: invokevirtual Fc0 : (S)Z
/*    */     //   2964: ifne -> 2997
/*    */     //   2967: aload #19
/*    */     //   2969: aload_1
/*    */     //   2970: aload_0
/*    */     //   2971: getfield Xj0 : S
/*    */     //   2974: istore #20
/*    */     //   2976: aload #5
/*    */     //   2978: aload #17
/*    */     //   2980: aload #19
/*    */     //   2982: iconst_0
/*    */     //   2983: iconst_0
/*    */     //   2984: iload #20
/*    */     //   2986: iconst_0
/*    */     //   2987: aload #16
/*    */     //   2989: invokevirtual j90 : (Lf/hm0;Lf/hm0;Lf/GS;ZZSZLf/b60;)V
/*    */     //   2992: bipush #16
/*    */     //   2994: invokevirtual zb : (B)V
/*    */     //   2997: aload #19
/*    */     //   2999: invokevirtual YG0 : ()B
/*    */     //   3002: ifne -> 2853
/*    */     //   3005: aload #19
/*    */     //   3007: iconst_1
/*    */     //   3008: invokevirtual QI : (B)Z
/*    */     //   3011: ifeq -> 3027
/*    */     //   3014: aload #19
/*    */     //   3016: getfield pn : I
/*    */     //   3019: aload #17
/*    */     //   3021: invokevirtual ih : ()I
/*    */     //   3024: if_icmpne -> 2853
/*    */     //   3027: aload #13
/*    */     //   3029: aload #17
/*    */     //   3031: invokevirtual ih : ()I
/*    */     //   3034: invokevirtual Lh0 : (I)V
/*    */     //   3037: goto -> 2853
/*    */     //   3040: aload #11
/*    */     //   3042: aconst_null
/*    */     //   3043: astore #7
/*    */     //   3045: invokevirtual size : ()I
/*    */     //   3048: iconst_1
/*    */     //   3049: if_icmple -> 3167
/*    */     //   3052: aload #9
/*    */     //   3054: aload #11
/*    */     //   3056: iconst_0
/*    */     //   3057: anewarray f/hm0
/*    */     //   3060: invokevirtual toArray : ([Ljava/lang/Object;)[Ljava/lang/Object;
/*    */     //   3063: checkcast [Lf/hm0;
/*    */     //   3066: astore #7
/*    */     //   3068: invokevirtual iterator : ()Ljava/util/Iterator;
/*    */     //   3071: astore #9
/*    */     //   3073: aload #9
/*    */     //   3075: invokeinterface hasNext : ()Z
/*    */     //   3080: ifeq -> 3140
/*    */     //   3083: aload #9
/*    */     //   3085: invokeinterface next : ()Ljava/lang/Object;
/*    */     //   3090: checkcast f/b60
/*    */     //   3093: getfield JX : Ljava/util/ArrayList;
/*    */     //   3096: invokevirtual iterator : ()Ljava/util/Iterator;
/*    */     //   3099: astore #14
/*    */     //   3101: aload #14
/*    */     //   3103: invokeinterface hasNext : ()Z
/*    */     //   3108: ifeq -> 3073
/*    */     //   3111: aload #14
/*    */     //   3113: invokeinterface next : ()Ljava/lang/Object;
/*    */     //   3118: checkcast f/GS
/*    */     //   3121: dup
/*    */     //   3122: astore #15
/*    */     //   3124: invokevirtual YG0 : ()B
/*    */     //   3127: ifne -> 3101
/*    */     //   3130: aload #15
/*    */     //   3132: bipush #16
/*    */     //   3134: invokevirtual zb : (B)V
/*    */     //   3137: goto -> 3101
/*    */     //   3140: new f/cC
/*    */     //   3143: dup
/*    */     //   3144: astore #9
/*    */     //   3146: aload_1
/*    */     //   3147: aload #11
/*    */     //   3149: aload #7
/*    */     //   3151: invokevirtual toArray : ([Ljava/lang/Object;)[Ljava/lang/Object;
/*    */     //   3154: checkcast [Lf/hm0;
/*    */     //   3157: aload #5
/*    */     //   3159: swap
/*    */     //   3160: invokespecial <init> : (Lf/kf;Lf/hm0;[Lf/hm0;)V
/*    */     //   3163: aload #9
/*    */     //   3165: astore #7
/*    */     //   3167: aload #12
/*    */     //   3169: getfield ir0 : I
/*    */     //   3172: ifle -> 3189
/*    */     //   3175: aload #12
/*    */     //   3177: aload_1
/*    */     //   3178: aload #4
/*    */     //   3180: <illegal opcode> Qc : (Lf/kf;Lf/Gp0;)Lf/HA0;
/*    */     //   3185: invokevirtual m8 : (Lf/HA0;)Z
/*    */     //   3188: pop
/*    */     //   3189: aload #6
/*    */     //   3191: invokeinterface iterator : ()Ljava/util/Iterator;
/*    */     //   3196: astore #6
/*    */     //   3198: aload #6
/*    */     //   3200: invokeinterface hasNext : ()Z
/*    */     //   3205: ifeq -> 3739
/*    */     //   3208: aload #6
/*    */     //   3210: invokeinterface next : ()Ljava/lang/Object;
/*    */     //   3215: checkcast f/b60
/*    */     //   3218: dup
/*    */     //   3219: astore #9
/*    */     //   3221: getfield a0 : I
/*    */     //   3224: dup
/*    */     //   3225: istore #11
/*    */     //   3227: ifne -> 3237
/*    */     //   3230: aload #5
/*    */     //   3232: astore #11
/*    */     //   3234: goto -> 3246
/*    */     //   3237: aload #4
/*    */     //   3239: iload #11
/*    */     //   3241: invokevirtual fa : (I)Lf/hm0;
/*    */     //   3244: astore #11
/*    */     //   3246: aload #11
/*    */     //   3248: ifnonnull -> 3299
/*    */     //   3251: aload_1
/*    */     //   3252: aload #9
/*    */     //   3254: getfield a0 : I
/*    */     //   3257: invokestatic toString : (I)Ljava/lang/String;
/*    */     //   3260: sipush #5045
/*    */     //   3263: swap
/*    */     //   3264: invokestatic Go : (ILjava/lang/String;)Ljava/lang/String;
/*    */     //   3267: invokevirtual Kq : (Ljava/lang/String;)V
/*    */     //   3270: getstatic f/jp.lPt7 : Lf/ik;
/*    */     //   3273: ldc 'Fatal playback error when processing skill '
/*    */     //   3275: invokestatic df : (Ljava/lang/String;)Ljava/lang/StringBuilder;
/*    */     //   3278: aload_0
/*    */     //   3279: getfield Xj0 : S
/*    */     //   3282: invokevirtual append : (I)Ljava/lang/StringBuilder;
/*    */     //   3285: ldc ' : Target was null'
/*    */     //   3287: invokevirtual append : (Ljava/lang/String;)Ljava/lang/StringBuilder;
/*    */     //   3290: invokevirtual toString : ()Ljava/lang/String;
/*    */     //   3293: invokeinterface error : (Ljava/lang/String;)V
/*    */     //   3298: return
/*    */     //   3299: aload #9
/*    */     //   3301: iconst_1
/*    */     //   3302: istore #12
/*    */     //   3304: iconst_1
/*    */     //   3305: invokevirtual Fc0 : (S)Z
/*    */     //   3308: ifeq -> 3331
/*    */     //   3311: aload_1
/*    */     //   3312: aload #4
/*    */     //   3314: iconst_0
/*    */     //   3315: istore #12
/*    */     //   3317: iconst_1
/*    */     //   3318: iload #10
/*    */     //   3320: aload #11
/*    */     //   3322: invokestatic B60 : (Lf/Gp0;SILf/hm0;)Ljava/lang/String;
/*    */     //   3325: invokevirtual Kq : (Ljava/lang/String;)V
/*    */     //   3328: goto -> 3511
/*    */     //   3331: aload #9
/*    */     //   3333: iconst_4
/*    */     //   3334: invokevirtual Fc0 : (S)Z
/*    */     //   3337: ifeq -> 3371
/*    */     //   3340: aload #9
/*    */     //   3342: iconst_0
/*    */     //   3343: istore #12
/*    */     //   3345: sipush #4096
/*    */     //   3348: invokevirtual Fc0 : (S)Z
/*    */     //   3351: ifne -> 3511
/*    */     //   3354: aload_1
/*    */     //   3355: aload #4
/*    */     //   3357: iconst_4
/*    */     //   3358: iload #10
/*    */     //   3360: aload #11
/*    */     //   3362: invokestatic B60 : (Lf/Gp0;SILf/hm0;)Ljava/lang/String;
/*    */     //   3365: invokevirtual Kq : (Ljava/lang/String;)V
/*    */     //   3368: goto -> 3511
/*    */     //   3371: aload #9
/*    */     //   3373: sipush #-32760
/*    */     //   3376: invokevirtual Fc0 : (S)Z
/*    */     //   3379: ifeq -> 3403
/*    */     //   3382: aload_1
/*    */     //   3383: aload #4
/*    */     //   3385: iconst_0
/*    */     //   3386: istore #12
/*    */     //   3388: bipush #8
/*    */     //   3390: iload #10
/*    */     //   3392: aload #11
/*    */     //   3394: invokestatic B60 : (Lf/Gp0;SILf/hm0;)Ljava/lang/String;
/*    */     //   3397: invokevirtual Kq : (Ljava/lang/String;)V
/*    */     //   3400: goto -> 3511
/*    */     //   3403: aload #9
/*    */     //   3405: sipush #128
/*    */     //   3408: invokevirtual Fc0 : (S)Z
/*    */     //   3411: ifeq -> 3436
/*    */     //   3414: aload_1
/*    */     //   3415: aload #4
/*    */     //   3417: iconst_0
/*    */     //   3418: istore #12
/*    */     //   3420: sipush #128
/*    */     //   3423: iload #10
/*    */     //   3425: aload #11
/*    */     //   3427: invokestatic B60 : (Lf/Gp0;SILf/hm0;)Ljava/lang/String;
/*    */     //   3430: invokevirtual Kq : (Ljava/lang/String;)V
/*    */     //   3433: goto -> 3511
/*    */     //   3436: aload #9
/*    */     //   3438: sipush #256
/*    */     //   3441: invokevirtual Fc0 : (S)Z
/*    */     //   3444: ifne -> 3475
/*    */     //   3447: aload #9
/*    */     //   3449: bipush #16
/*    */     //   3451: invokevirtual Fc0 : (S)Z
/*    */     //   3454: ifeq -> 3475
/*    */     //   3457: aload_1
/*    */     //   3458: aload #4
/*    */     //   3460: bipush #16
/*    */     //   3462: iload #10
/*    */     //   3464: aload #11
/*    */     //   3466: invokestatic B60 : (Lf/Gp0;SILf/hm0;)Ljava/lang/String;
/*    */     //   3469: invokevirtual Kq : (Ljava/lang/String;)V
/*    */     //   3472: goto -> 3511
/*    */     //   3475: aload #9
/*    */     //   3477: sipush #256
/*    */     //   3480: invokevirtual Fc0 : (S)Z
/*    */     //   3483: ifne -> 3511
/*    */     //   3486: aload #9
/*    */     //   3488: bipush #32
/*    */     //   3490: invokevirtual Fc0 : (S)Z
/*    */     //   3493: ifeq -> 3511
/*    */     //   3496: aload_1
/*    */     //   3497: aload #4
/*    */     //   3499: bipush #32
/*    */     //   3501: iload #10
/*    */     //   3503: aload #11
/*    */     //   3505: invokestatic B60 : (Lf/Gp0;SILf/hm0;)Ljava/lang/String;
/*    */     //   3508: invokevirtual Kq : (Ljava/lang/String;)V
/*    */     //   3511: aload #9
/*    */     //   3513: iconst_2
/*    */     //   3514: invokevirtual Fc0 : (S)Z
/*    */     //   3517: ifeq -> 3534
/*    */     //   3520: aload_1
/*    */     //   3521: aload #4
/*    */     //   3523: iconst_2
/*    */     //   3524: iload #10
/*    */     //   3526: aload #11
/*    */     //   3528: invokestatic B60 : (Lf/Gp0;SILf/hm0;)Ljava/lang/String;
/*    */     //   3531: invokevirtual Kq : (Ljava/lang/String;)V
/*    */     //   3534: aload #9
/*    */     //   3536: aload #13
/*    */     //   3538: aload #9
/*    */     //   3540: getfield a0 : I
/*    */     //   3543: invokevirtual xC : (I)I
/*    */     //   3546: istore #14
/*    */     //   3548: getfield JX : Ljava/util/ArrayList;
/*    */     //   3551: invokevirtual iterator : ()Ljava/util/Iterator;
/*    */     //   3554: astore #15
/*    */     //   3556: aload #15
/*    */     //   3558: invokeinterface hasNext : ()Z
/*    */     //   3563: ifeq -> 3692
/*    */     //   3566: aload #15
/*    */     //   3568: invokeinterface next : ()Ljava/lang/Object;
/*    */     //   3573: checkcast f/GS
/*    */     //   3576: dup
/*    */     //   3577: astore #16
/*    */     //   3579: bipush #16
/*    */     //   3581: invokevirtual QI : (B)Z
/*    */     //   3584: ifeq -> 3590
/*    */     //   3587: goto -> 3556
/*    */     //   3590: aload #16
/*    */     //   3592: iconst_1
/*    */     //   3593: invokevirtual QI : (B)Z
/*    */     //   3596: ifne -> 3609
/*    */     //   3599: aload #11
/*    */     //   3601: invokevirtual ih : ()I
/*    */     //   3604: istore #17
/*    */     //   3606: goto -> 3616
/*    */     //   3609: aload #16
/*    */     //   3611: getfield pn : I
/*    */     //   3614: istore #17
/*    */     //   3616: iload #14
/*    */     //   3618: iconst_1
/*    */     //   3619: if_icmple -> 3628
/*    */     //   3622: iconst_1
/*    */     //   3623: istore #18
/*    */     //   3625: goto -> 3631
/*    */     //   3628: iconst_0
/*    */     //   3629: istore #18
/*    */     //   3631: iload #18
/*    */     //   3633: ifeq -> 3654
/*    */     //   3636: aload #8
/*    */     //   3638: iload #17
/*    */     //   3640: invokevirtual Z6 : (I)Ljava/lang/Object;
/*    */     //   3643: aload #16
/*    */     //   3645: if_acmpne -> 3654
/*    */     //   3648: iconst_1
/*    */     //   3649: istore #17
/*    */     //   3651: goto -> 3657
/*    */     //   3654: iconst_0
/*    */     //   3655: istore #17
/*    */     //   3657: aload #16
/*    */     //   3659: aload_1
/*    */     //   3660: aload_0
/*    */     //   3661: getfield Xj0 : S
/*    */     //   3664: istore #19
/*    */     //   3666: aload #5
/*    */     //   3668: aload #11
/*    */     //   3670: aload #16
/*    */     //   3672: iload #18
/*    */     //   3674: iload #17
/*    */     //   3676: iload #19
/*    */     //   3678: iconst_0
/*    */     //   3679: aload #9
/*    */     //   3681: invokevirtual j90 : (Lf/hm0;Lf/hm0;Lf/GS;ZZSZLf/b60;)V
/*    */     //   3684: bipush #16
/*    */     //   3686: invokevirtual zb : (B)V
/*    */     //   3689: goto -> 3556
/*    */     //   3692: iload #12
/*    */     //   3694: ifeq -> 3198
/*    */     //   3697: iload #14
/*    */     //   3699: iconst_1
/*    */     //   3700: if_icmple -> 3198
/*    */     //   3703: aload_1
/*    */     //   3704: getstatic f/F40.ef0 : Lf/F40;
/*    */     //   3707: iconst_1
/*    */     //   3708: anewarray java/lang/String
/*    */     //   3711: dup
/*    */     //   3712: astore #9
/*    */     //   3714: iload #14
/*    */     //   3716: invokestatic toString : (I)Ljava/lang/String;
/*    */     //   3719: iconst_0
/*    */     //   3720: swap
/*    */     //   3721: aastore
/*    */     //   3722: iconst_2
/*    */     //   3723: swap
/*    */     //   3724: bipush #15
/*    */     //   3726: bipush #32
/*    */     //   3728: aload #9
/*    */     //   3730: invokestatic lz : (BLf/F40;II[Ljava/lang/String;)Ljava/lang/String;
/*    */     //   3733: invokevirtual Kq : (Ljava/lang/String;)V
/*    */     //   3736: goto -> 3198
/*    */     //   3739: aload #7
/*    */     //   3741: ifnull -> 3754
/*    */     //   3744: aload_1
/*    */     //   3745: getfield YP : Ljava/util/LinkedList;
/*    */     //   3748: aload #7
/*    */     //   3750: invokevirtual add : (Ljava/lang/Object;)Z
/*    */     //   3753: pop
/*    */     //   3754: getstatic f/Bz.mr0 : Z
/*    */     //   3757: ifeq -> 3779
/*    */     //   3760: aload_1
/*    */     //   3761: new f/Fu
/*    */     //   3764: dup
/*    */     //   3765: astore_1
/*    */     //   3766: aload_0
/*    */     //   3767: lload_2
/*    */     //   3768: invokespecial <init> : (Lf/jp;J)V
/*    */     //   3771: getfield YP : Ljava/util/LinkedList;
/*    */     //   3774: aload_1
/*    */     //   3775: invokevirtual add : (Ljava/lang/Object;)Z
/*    */     //   3778: pop
/*    */     //   3779: return
/*    */     // Line number table:
/*    */     //   Java source line number -> byte code offset
/*    */     //   #1	-> 5
/*    */     //   #2	-> 12
/*    */     //   #3	-> 15
/*    */     //   #4	-> 25
/*    */     //   #5	-> 31
/*    */     //   #6	-> 34
/*    */     //   #7	-> 46
/*    */     //   #8	-> 52
/*    */     //   #9	-> 55
/*    */     //   #10	-> 73
/*    */     //   #11	-> 86
/*    */     //   #12	-> 90
/*    */     //   #13	-> 99
/*    */     //   #14	-> 147
/*    */     //   #15	-> 167
/*    */     //   #16	-> 180
/*    */     //   #17	-> 183
/*    */     //   #18	-> 199
/*    */     //   #19	-> 205
/*    */     //   #20	-> 208
/*    */     //   #21	-> 227
/*    */     //   #22	-> 230
/*    */     //   #23	-> 274
/*    */     //   #24	-> 292
/*    */     //   #25	-> 324
/*    */     //   #26	-> 334
/*    */     //   #27	-> 374
/*    */     //   #28	-> 379
/*    */     //   #29	-> 382
/*    */     //   #30	-> 388
/*    */     //   #31	-> 423
/*    */     //   #32	-> 444
/*    */     //   #33	-> 482
/*    */     //   #34	-> 487
/*    */     //   #35	-> 497
/*    */     //   #36	-> 550
/*    */     //   #37	-> 575
/*    */     //   #38	-> 580
/*    */     //   #39	-> 585
/*    */     //   #40	-> 590
/*    */     //   #41	-> 595
/*    */     //   #42	-> 604
/*    */     //   #43	-> 655
/*    */     //   #44	-> 708
/*    */     //   #45	-> 755
/*    */     //   #46	-> 970
/*    */     //   #47	-> 1009
/*    */     //   #48	-> 1017
/*    */     //   #49	-> 1031
/*    */     //   #50	-> 1034
/*    */     //   #51	-> 1065
/*    */     //   #52	-> 1085
/*    */     //   #53	-> 1103
/*    */     //   #54	-> 1113
/*    */     //   #55	-> 1152
/*    */     //   #56	-> 1160
/*    */     //   #57	-> 1199
/*    */     //   #58	-> 1207
/*    */     //   #59	-> 1246
/*    */     //   #60	-> 1254
/*    */     //   #61	-> 1293
/*    */     //   #62	-> 1301
/*    */     //   #63	-> 1340
/*    */     //   #64	-> 1348
/*    */     //   #65	-> 1387
/*    */     //   #66	-> 1395
/*    */     //   #67	-> 1434
/*    */     //   #68	-> 1442
/*    */     //   #69	-> 1481
/*    */     //   #70	-> 1489
/*    */     //   #71	-> 1528
/*    */     //   #72	-> 1536
/*    */     //   #73	-> 1575
/*    */     //   #74	-> 1583
/*    */     //   #75	-> 1622
/*    */     //   #76	-> 1630
/*    */     //   #77	-> 1669
/*    */     //   #78	-> 1679
/*    */     //   #79	-> 1705
/*    */     //   #80	-> 1743
/*    */     //   #81	-> 1750
/*    */     //   #82	-> 1754
/*    */     //   #83	-> 1757
/*    */     //   #84	-> 1760
/*    */     //   #85	-> 1763
/*    */     //   #86	-> 1768
/*    */     //   #87	-> 1786
/*    */     //   #88	-> 1799
/*    */     //   #89	-> 1806
/*    */     //   #90	-> 1840
/*    */     //   #91	-> 1848
/*    */     //   #92	-> 1880
/*    */     //   #93	-> 1893
/*    */     //   #94	-> 1938
/*    */     //   #95	-> 1946
/*    */     //   #96	-> 1955
/*    */     //   #97	-> 1988
/*    */     //   #98	-> 1994
/*    */     //   #99	-> 2008
/*    */     //   #100	-> 2013
/*    */     //   #101	-> 2018
/*    */     //   #102	-> 2029
/*    */     //   #103	-> 2037
/*    */     //   #104	-> 2098
/*    */     //   #105	-> 2106
/*    */     //   #106	-> 2158
/*    */     //   #107	-> 2164
/*    */     //   #108	-> 2181
/*    */     //   #109	-> 2192
/*    */     //   #110	-> 2224
/*    */     //   #111	-> 2230
/*    */     //   #112	-> 2244
/*    */     //   #113	-> 2252
/*    */     //   #114	-> 2311
/*    */     //   #115	-> 2321
/*    */     //   #116	-> 2329
/*    */     //   #117	-> 2337
/*    */     //   #118	-> 2347
/*    */     //   #119	-> 2389
/*    */     //   #120	-> 2410
/*    */     //   #121	-> 2413
/*    */     //   #122	-> 2440
/*    */     //   #123	-> 2454
/*    */     //   #124	-> 2463
/*    */     //   #125	-> 2472
/*    */     //   #126	-> 2475
/*    */     //   #127	-> 2501
/*    */     //   #128	-> 2536
/*    */     //   #129	-> 2556
/*    */     //   #130	-> 2669
/*    */     //   #131	-> 2689
/*    */     //   #132	-> 2696
/*    */     //   #133	-> 2701
/*    */     //   #134	-> 2845
/*    */     //   #135	-> 2848
/*    */     //   #136	-> 2878
/*    */     //   #137	-> 2891
/*    */     //   #138	-> 2902
/*    */     //   #139	-> 2911
/*    */     //   #140	-> 2924
/*    */     //   #141	-> 2971
/*    */     //   #142	-> 2989
/*    */     //   #143	-> 3016
/*    */     //   #144	-> 3021
/*    */     //   #145	-> 3093
/*    */     //   #146	-> 3096
/*    */     //   #147	-> 3169
/*    */     //   #148	-> 3180
/*    */     //   #149	-> 3221
/*    */     //   #150	-> 3241
/*    */     //   #151	-> 3254
/*    */     //   #152	-> 3257
/*    */     //   #153	-> 3273
/*    */     //   #154	-> 3279
/*    */     //   #155	-> 3282
/*    */     //   #156	-> 3540
/*    */     //   #157	-> 3543
/*    */     //   #158	-> 3548
/*    */     //   #159	-> 3551
/*    */     //   #160	-> 3611
/*    */     //   #161	-> 3640
/*    */     //   #162	-> 3661
/*    */     //   #163	-> 3681
/*    */     //   #164	-> 3730
/*    */     //   #165	-> 3733
/*    */     //   #166	-> 3745
/*    */     //   #167	-> 3754
/*    */     //   #168	-> 3771
/*    */   } }


/* Location:              /Users/vnnsnnt/Documents/Codespace/JavaWorkspace/RedTrainer/src/main/java/org/trainer/client/PokeMMO.jar!/f/jp.class
 * Java compiler version: 8 (52.0)
 * JD-Core Version:       1.1.3
 */