/*  1 */ package f;public final class Jr0 extends DF { public final JG0 BL(JG0 paramJG0) { JG0 jG0; xy0 xy0; if (xy0 = this.fv0 instanceof UY) { xy0 = xy0; Qt0 qt0 = null; if (paramJG0 instanceof Qt0) qt0 = (Qt0)paramJG0;  if (this.LJ.Pl) { if (qt0 != null) paramJG0 = null; 
/*  2 */         return xy0.BL(paramJG0); }  if (qt0 == null) this();  ge0 ge0 = qt0.pF;
/*  3 */       ((xo)this.TG0)
/*    */         
/*  5 */         .BK(this.LJ);
/*  6 */       jG0 = xy0.BL(qt0.Wi0);
/*  7 */       if ((paramJG0 = qt0.Wi0) != this) { if (paramJG0 != null) qt0.fG0(1);  qt0.Wi0 = this; if (this != null) qt0.si(this, 1);  }  return qt0; }
/*  8 */      if (((Jr0)super).LJ
/*  9 */       .Pl) return null; 
/* 10 */     if ((paramJG0 = paramJG0) == null) { super(); (new ge0()).Xu("treeButton"); }  IG iG = ((Jr0)super).LJ;
/* 11 */     ((xo)((Un)paramJG0).TG0)
/*    */       
/* 13 */       .BK(this);
/*    */     return paramJG0; }
/*    */ 
/*    */   
/*    */   public IG LJ;
/*    */   
/*    */   public Jr0(LL paramLL) {
/*    */     super(paramLL);
/*    */   }
/*    */   
/*    */   public final String xp0() {
/*    */     return "TreeNodeCellRenderer";
/*    */   }
/*    */   
/*    */   public final void pe0(JG0 paramJG0, int paramInt1, int paramInt2, int paramInt3, int paramInt4) {
/*    */     // Byte code:
/*    */     //   0: aload_0
/*    */     //   1: aload_1
/*    */     //   2: iload #5
/*    */     //   4: aload_0
/*    */     //   5: iload_2
/*    */     //   6: iload #4
/*    */     //   8: aload_0
/*    */     //   9: getfield DV : I
/*    */     //   12: aload_0
/*    */     //   13: getfield ue : I
/*    */     //   16: imul
/*    */     //   17: dup
/*    */     //   18: istore_2
/*    */     //   19: isub
/*    */     //   20: istore #4
/*    */     //   22: iload_2
/*    */     //   23: iconst_0
/*    */     //   24: iload #4
/*    */     //   26: invokestatic max : (II)I
/*    */     //   29: aload_0
/*    */     //   30: getfield NL0 : Lf/db;
/*    */     //   33: getfield PO : I
/*    */     //   36: invokestatic min : (II)I
/*    */     //   39: istore_2
/*    */     //   40: iadd
/*    */     //   41: istore #6
/*    */     //   43: getfield NL0 : Lf/db;
/*    */     //   46: getfield bJ0 : I
/*    */     //   49: isub
/*    */     //   50: iconst_2
/*    */     //   51: idiv
/*    */     //   52: iload_3
/*    */     //   53: iadd
/*    */     //   54: iload #6
/*    */     //   56: swap
/*    */     //   57: invokevirtual Ol0 : (II)V
/*    */     //   60: getfield fv0 : Lf/xy0;
/*    */     //   63: dup
/*    */     //   64: astore #6
/*    */     //   66: instanceof f/UY
/*    */     //   69: ifeq -> 154
/*    */     //   72: aload_1
/*    */     //   73: aload #6
/*    */     //   75: checkcast f/UY
/*    */     //   78: astore #6
/*    */     //   80: checkcast f/Qt0
/*    */     //   83: dup
/*    */     //   84: dup
/*    */     //   85: astore #7
/*    */     //   87: getfield pF : Lf/ge0;
/*    */     //   90: dup
/*    */     //   91: astore #8
/*    */     //   93: iload_2
/*    */     //   94: aload_0
/*    */     //   95: aload #7
/*    */     //   97: iconst_0
/*    */     //   98: iload #4
/*    */     //   100: invokestatic max : (II)I
/*    */     //   103: iload #5
/*    */     //   105: invokevirtual Tm : (II)Z
/*    */     //   108: pop
/*    */     //   109: getfield NL0 : Lf/db;
/*    */     //   112: getfield bJ0 : I
/*    */     //   115: invokevirtual Tm : (II)Z
/*    */     //   118: pop
/*    */     //   119: getfield Wi0 : Lf/JG0;
/*    */     //   122: dup
/*    */     //   123: astore_0
/*    */     //   124: ifnull -> 167
/*    */     //   127: aload #6
/*    */     //   129: aload_1
/*    */     //   130: aload #8
/*    */     //   132: invokevirtual Xq : ()I
/*    */     //   135: istore_1
/*    */     //   136: getfield xY : I
/*    */     //   139: istore_2
/*    */     //   140: aload_0
/*    */     //   141: iload_1
/*    */     //   142: iload_3
/*    */     //   143: iload_2
/*    */     //   144: iload #5
/*    */     //   146: invokeinterface pe0 : (Lf/JG0;IIII)V
/*    */     //   151: goto -> 167
/*    */     //   154: aload_1
/*    */     //   155: iload_2
/*    */     //   156: aload_0
/*    */     //   157: getfield NL0 : Lf/db;
/*    */     //   160: getfield bJ0 : I
/*    */     //   163: invokevirtual Tm : (II)Z
/*    */     //   166: pop
/*    */     //   167: return
/*    */     // Line number table:
/*    */     //   Java source line number -> byte code offset
/*    */     //   #1	-> 33
/*    */     //   #2	-> 36
/*    */     //   #3	-> 46
/*    */     //   #4	-> 51
/*    */     //   #5	-> 112
/*    */     //   #6	-> 115
/*    */     //   #7	-> 136
/*    */     //   #8	-> 146
/*    */     //   #9	-> 160
/*    */     //   #10	-> 163
/*    */   } }


/* Location:              /Users/vnnsnnt/Documents/Codespace/JavaWorkspace/RedTrainer/src/main/java/org/trainer/client/PokeMMO.jar!/f/Jr0.class
 * Java compiler version: 8 (52.0)
 * JD-Core Version:       1.1.3
 */