/*  1 */ package f;public final class js extends Ks0 { public static final ik iK = C00.gd(js.class); public static js vu0; public NC0 Wx; public Qn0 uB0; public Yj0 l00; public Wx Dj0; public Oa0 mm; public BX th; public pA MH0; public QP GC0; public v10 vY; public wL Lz; public Ay V00; public zn0 ZF0; public kf BA; public FO iV; public final My eG0; public final Qz0 hW; public final tl0 sG; public final dQ oL0; public Ia aux; public final xs es; public DecimalFormat Do; public DecimalFormat Ux0; public static boolean com3(JG0 paramJG0) { byte b = 0; try { while (b < paramJG0.Ub()) { JG0 jG0; if ((jG0 = paramJG0.lPt3(b)).p3()) return (jG0 instanceof r60) ? true : ((jG0 instanceof fi && ((fi)jG0).RE0()) ? true : ((jG0 instanceof of) ? true : com3(jG0)));  b++; }  if (paramJG0.Bo0
/*  2 */         .q50) return true;  } catch (Exception exception) { exception
/*  3 */         .printStackTrace(); }  return false; } public dQ Fe0; public long o90; public long Am0; public long[] ZP; public mk ht; public su0 SQ; public h70 l5; public AI0 Ji; public ArrayList U1; public us0 Tc; public V00 tj; public Z9 mC0; public ArrayList tr0; public boolean al; public fQ ye; public La z1; public Q20 mw; public Un Nn; public JG0 Oi0; public int mk0; public Tv0 hw; public Pw bk; public js(Pw paramPw) { String str; DecimalFormatSymbols decimalFormatSymbols; My my; Qz0 qz0; this.Wx = new NC0(); this.uB0 = new Qn0(this); this.Dj0 = null; this.mm = null; this.th = null; this.MH0 = null; this.GC0 = null; this.vY = null; this.Lz = null; this.V00 = null; this.ZF0 = null; this.BA = null; this.iV = null; this.Do = new DecimalFormat("000.00"); this.Ux0 = new DecimalFormat("0000"); this.Fe0 = null; this.ZP = new long[2]; this.ht = null; this.l5 = null; this.Ji = null; this.U1 = new ArrayList(); this.Tc = null; this.tj = null; this.mC0 = null; this.tr0 = new ArrayList(); this.al = false; this.ye = new fQ(true, 8); this.mk0 = -1; this.oL0 = new dQ(); this(); this.sG = tl01; tl01.wI0(false); this.bk = paramPw; tl0 tl01; (tl01 = new tl0()).Xu("tooltip-help"); si(new tl0(), 0); StringBuilder stringBuilder = (new StringBuilder()).append("maingui"); if (h1.IC0) { str = "-cursor"; } else { str = ""; }  Xu(stringBuilder.append(str).toString()); this.l00 = new Yj0(this); this(); this.es = xs1; xs xs1; (xs1 = new xs()).KB(Bz.WI); (new xs()).MB0(); (new xs()).wI0(h1.Lf0); this(); (new DecimalFormatSymbols()).setDecimalSeparator('.'); this.Do.setDecimalFormatSymbols(decimalFormatSymbols); (this.Fe0 = new dQ()).Xu("fpscounter"); this.Fe0.MB0(); this.Fe0.wI0(h1.Lf0); this(); this.eG0 = new My(); this(this); this.hW = new Qz0(); this.z1 = new La(); if (km.XU()) { this.mw = new Q20(1); (this.Nn = new Un()).Xu("mobile-menu"); this.Nn.tW(this::xf); if (km.ER()) { (this.Oi0 = new JG0()).Xu("mobile-battery-10"); this.mw.J8(this.Oi0); }  this.mw.J8(this.Nn); J8(this.mw); }  J8(xs1); J8(my); J8(qz0); J8(this.l00); J8(this.z1); J8(this.Fe0); vu0 = this; if (Bz.fn) z30();  } public static js N2() { return vu0; } public static boolean RS(JG0 paramJG0) { byte b = 0; try { while (b < paramJG0.Ub()) { JG0 jG0; if ((jG0 = paramJG0.lPt3(b)).p3()) return (jG0 instanceof of) ? true : RS(jG0);  b++; }  if (paramJG0.Bo0.q50) return true;  } catch (Exception exception) { exception.printStackTrace(); }  return false; } public static boolean o(int paramInt, EW paramEW) { return (paramEW.zC0 == paramInt); } private void mN(boolean paramBoolean, List<tc> paramList, int paramInt1, int paramInt2) { if (paramBoolean && paramList.isEmpty()) return;  ((tc)paramList.get(0)).getClass(); if (paramList.size() == 1 && (tc)paramList.get(0) instanceof zk0) { F7.T1(uN(), this, paramInt1, paramInt2); return; }  this(); JG0 jG0; B3 b3; js js1; Collections.sort(paramList, tc.qL); if (km.D70(1) && paramList
/*  4 */       .stream().filter(js::vo).count() > 1L) b3.mD("Copy all names", paramList::il);  for (Iterator<tc> iterator = paramList.iterator(); iterator.hasNext(); ) { B3 b31; Hk0 hk0; B3 b32; tc tc; (tc = iterator.next()).getClass(); if ((tc)iterator.next() instanceof zk0)
/*    */       
/*  6 */       { b31 = uN(); b32 = b3; } else { B3 b33; if (b31 instanceof Jo)
/*    */         
/*  8 */         { Jo jo = (Jo)b31;
/*  9 */           if (((Qh0)b31).Jg == 
/*    */             
/* 11 */             km.a3.Ct
/* 12 */             .Jg)
/* 13 */           { b33 = bm(jo, Ml0.OH0(1123), paramInt1, paramInt2, false); b32 = b3; }
/* 14 */           else { String str = ((Jo)b33).ED0;
/* 15 */             boolean bool = b33.so0(-128); b33 = bm((Jo)b33, str, paramInt1, paramInt2, bool); b32 = b3; }  } else if (b33.zl()) { IB iB; Hk0 hk01; Kr0 kr02 = (Kr0)b33; this(b33.m()); b3
/* 16 */             .aV.add(b32);
/*    */           
/* 18 */           if (this.MH0.OU
/* 19 */             .fk != null) {
/* 20 */             Hk0 hk02; this("- COPY -", b33::NB);
/* 21 */             b32.aV.add(hk02);
/* 22 */             this("- DELETE -", b33::om);
/* 23 */             b32.aV.add(hk02);
/* 24 */           }  this("Force Interact", b33::g8);
/* 25 */           b32.aV.add(hk01);
/*    */           
/*    */           Kr0 kr01;
/* 28 */           if ((kr01 = ((Or)kr02.Y1).QH0)
/* 29 */             .hG0 != 2) { kr01 = null; }
/*    */           else
/*    */           
/* 32 */           { iB = km.mI0.AN.AuX(kr01.zH0); }  if (iB != null) {
/*    */ 
/*    */ 
/*    */             
/* 36 */             this(B40.df("Sprite ID: ").append(iB.Ce).toString());
/* 37 */             b32.aV.add(hk01);
/*    */ 
/*    */ 
/*    */             
/* 41 */             this(B40.df("Frame Type: ").append(iB.a30).toString());
/* 42 */             b32.aV.add(hk01);
/*    */ 
/*    */ 
/*    */             
/* 46 */             this(B40.df("Idle Frame: ").append(iB.LI0).toString());
/* 47 */             b32.aV.add(hk01);
/*    */           } 
/*    */ 
/*    */ 
/*    */ 
/*    */           
/* 53 */           this(B40.df("NPC Sprite ID: ").append(kr02.hG0).append(" / ").append(kr02.zH0).toString());
/* 54 */           b32.aV.add(hk0);
/*    */ 
/*    */ 
/*    */ 
/*    */           
/* 59 */           this(B40.df("Idle Movement: ").append(kr02.Lq.ne0).toString());
/* 60 */           b32.aV.add(hk0);
/*    */ 
/*    */ 
/*    */ 
/*    */ 
/*    */           
/* 66 */           this(B40.df("Movement Leash: ").append(kr02.n2).append(" | ").append(kr02.NH0).toString());
/* 67 */           b32.aV.add(hk0);
/*    */ 
/*    */ 
/*    */           
/* 71 */           this(B40.df("Object ID: ").append(kr02.Jg).toString());
/* 72 */           b32.aV.add(hk0);
/* 73 */           if (kr02.YP > 0)
/*    */           
/*    */           { 
/*    */             
/* 77 */             this(B40.df("Trainer Aggro Range: ").append(kr02.R3).toString());
/* 78 */             b32.aV.add(hk0);
/*    */ 
/*    */ 
/*    */             
/* 82 */             this(B40.df("Trainer ID: ").append(kr02.YP).toString()); } else { continue; }  } else { continue; }  }  b32
/* 83 */         .aV.add(hk0); }  if (paramList
/* 84 */       .isEmpty()) b3.mD(Ml0.OH0(1122), null);  if (paramInt1 < 0 && paramInt2 < 0)
/* 85 */     { F7 f7; this(this); if ((jG0 = (new F7()).qp(0, b3, this, false)) != null) { mM();
/*    */ 
/*    */ 
/*    */ 
/*    */ 
/*    */ 
/*    */ 
/*    */ 
/*    */         
/* 94 */         Ol0((js1 = vu0).xY / 2 - this.xY / 2, js1.HC / 2 - this.HC / 2); F7.c2(this); }  f7.Ev0(); }
/* 95 */     else { F7.T1((hu)js1, this, paramInt1, paramInt2); }
/*    */      }
/*    */ 
/*    */   
/*    */   public static void g8(tc paramtc) {
/*    */     km.u4.e20.W3(new cO(paramtc.Jg));
/*    */   }
/*    */   
/*    */   public static void om(tc paramtc) {
/*    */     km.u4.lF(B40.df("//eventdeletenpc ").append(paramtc.Jg).toString());
/*    */   }
/*    */   
/*    */   public static void NB(tc paramtc) {
/*    */     km.u4.lF(B40.df("//eventnpccopy ").append(paramtc.Jg).toString());
/*    */   }
/*    */   
/*    */   public static void il(List paramList) {
/*    */     this();
/*    */     StringBuilder stringBuilder;
/*    */     for (Iterator<tc> iterator = paramList.iterator(); iterator.hasNext();) {
/*    */       if (tc = iterator.next() instanceof Jo) {
/*    */         String str1;
/*    */         if (stringBuilder.length() > 0)
/*    */           stringBuilder.append(System.lineSeparator()); 
/*    */         if (((Jo)(tc = tc)).Zk0) {
/*    */           str1 = B40.df("{§}").append(((Jo)tc).ED0).toString();
/*    */         } else {
/*    */           str1 = ((Jo)str1).ED0;
/*    */         } 
/*    */         stringBuilder.append(str1);
/*    */       } 
/*    */     } 
/*    */     String str = stringBuilder.toString();
/*    */     UB0.Kg0.fl0.getClass();
/*    */     GLFW.glfwSetClipboardString(UB0.M60.AW.ne0, str);
/*    */   }
/*    */   
/*    */   public static void uA(Jo paramJo) {
/*    */     if (vh0.H90 == -1) {
/*    */       int i;
/*    */       if (paramJo == null) {
/*    */         i = -1;
/*    */       } else {
/*    */         i = i.Jg;
/*    */       } 
/*    */       vh0.H90 = i;
/*    */     } else {
/*    */       vh0.H90 = -1;
/*    */     } 
/*    */   }
/*    */   
/*    */   public static void vL0(String paramString) {
/*    */     h2 h2;
/*    */     YE yE;
/*    */     if ((yE = (h2 = pA.Dg0.OU).GL) != null) {
/*    */       yE.coM6.Be0(paramString, false);
/*    */     } else {
/*    */       this(h2);
/*    */       h2.GL = new YE();
/*    */       yE.coM6.Be0(paramString, false);
/*    */       h2.J8(h2.GL);
/*    */     } 
/*    */   }
/*    */   
/*    */   public static void co0(String paramString) {
/*    */     paramString = De0.AT("Are you sure you want to kick ", paramString, "?");
/*    */     vu0.uh(new h70(paramString, paramString::Nr, null));
/*    */   }
/*    */   
/*    */   public static void Mz0(String paramString, Xv0 paramXv0) {
/*    */     km.u4.lF("//setlanguage " + paramString + " " + paramXv0.Dd);
/*    */   }
/*    */   
/*    */   public static void Wy(String paramString, ZY paramZY) {
/*    */     km.u4.lF("//setchat " + paramString + " " + paramZY.oZ);
/*    */   }
/*    */   
/*    */   public static void Tz0(String paramString) {
/*    */     (new String[3])[0] = "Player Name";
/*    */     (new String[3])[1] = "Length in Seconds";
/*    */     (new String[3])[2] = "Reason";
/*    */     Xs0[] arrayOfXs0;
/*    */     (arrayOfXs0 = new Xs0[3])[0] = Xs0.sX;
/*    */     (new Xs0[3])[1] = Xs0.fz0;
/*    */     (new Xs0[3])[2] = Xs0.wX;
/*    */     h2.nL0.J8((new sc("//mute_ch", new String[3], arrayOfXs0, sc.Jt)).d6(0, paramString).lI0());
/*    */   }
/*    */   
/*    */   public static void ge(String paramString) {
/*    */     (new String[3])[0] = "Player Name";
/*    */     (new String[3])[1] = "Length in Seconds";
/*    */     (new String[3])[2] = "Reason";
/*    */     Xs0[] arrayOfXs0;
/*    */     (arrayOfXs0 = new Xs0[3])[0] = Xs0.sX;
/*    */     (new Xs0[3])[1] = Xs0.fz0;
/*    */     (new Xs0[3])[2] = Xs0.wX;
/*    */     h2.nL0.J8((new sc("//mute", new String[3], arrayOfXs0, sc.Jt)).d6(0, paramString).lI0());
/*    */   }
/*    */   
/*    */   public static void tj(String paramString, wQ paramwQ) {
/*    */     String[] arrayOfString;
/*    */     (arrayOfString = new String[3])[0] = "Player Name";
/*    */     (new String[3])[1] = "Warn Reason";
/*    */     (new String[3])[2] = "Custom Reason (if OTHER)";
/*    */     Xs0[] arrayOfXs0;
/*    */     (arrayOfXs0 = new Xs0[3])[0] = Xs0.sX;
/*    */     (new Xs0[3])[1] = Xs0.Ev;
/*    */     (new Xs0[3])[2] = Xs0.wX;
/*    */     String[][] arrayOfString1;
/*    */     (arrayOfString1 = new String[2][])[0] = yb0.mM;
/*    */     (new String[2][])[1] = yb0.FK0;
/*    */     h2.nL0.J8((new sc("//warn", arrayOfString, arrayOfXs0, arrayOfString1)).d6(0, paramString).d6(1, paramwQ.name()).lI0());
/*    */   }
/*    */   
/*    */   public static void B4(Jo paramJo) {
/*    */     if (paramJo == null)
/*    */       return; 
/*    */     R8 r8 = km.u4;
/*    */     int i = paramJo.Jg;
/*    */     r8.e20.W3(new ux0(i));
/*    */   }
/*    */   
/*    */   public static void qW(String paramString) {
/*    */     km.u4.e20.W3(new Zn0(paramString));
/*    */   }
/*    */   
/*    */   public static void UG0(String paramString) {
/*    */     km.u4.e20.W3(new JG(paramString));
/*    */   }
/*    */   
/*    */   public static void Kw(String paramString) {
/*    */     String str = "--";
/*    */     km.u4.e20.W3(new Dg(paramString, str));
/*    */   }
/*    */   
/*    */   private void Rg(String paramString) {
/*    */     // Byte code:
/*    */     //   0: getstatic f/km.u4 : Lf/R8;
/*    */     //   3: getfield E50 : Lf/Oc0;
/*    */     //   6: dup
/*    */     //   7: aload_1
/*    */     //   8: swap
/*    */     //   9: invokevirtual getClass : ()Ljava/lang/Class;
/*    */     //   12: pop
/*    */     //   13: getstatic java/util/Locale.ENGLISH : Ljava/util/Locale;
/*    */     //   16: invokevirtual toLowerCase : (Ljava/util/Locale;)Ljava/lang/String;
/*    */     //   19: astore_2
/*    */     //   20: getfield tl0 : Lf/Ut0;
/*    */     //   23: dup
/*    */     //   24: astore_3
/*    */     //   25: invokevirtual getClass : ()Ljava/lang/Class;
/*    */     //   28: pop
/*    */     //   29: new f/mt
/*    */     //   32: dup
/*    */     //   33: aload_3
/*    */     //   34: invokespecial <init> : (Lf/Ut0;)V
/*    */     //   37: invokevirtual iterator : ()Ljava/util/Iterator;
/*    */     //   40: astore_3
/*    */     //   41: aload_3
/*    */     //   42: checkcast f/DA0
/*    */     //   45: invokevirtual hasNext : ()Z
/*    */     //   48: ifeq -> 86
/*    */     //   51: aload_3
/*    */     //   52: checkcast f/iF0
/*    */     //   55: invokevirtual next : ()Ljava/lang/Object;
/*    */     //   58: checkcast f/CD0
/*    */     //   61: dup
/*    */     //   62: astore #4
/*    */     //   64: invokevirtual wN : ()Lf/FV;
/*    */     //   67: getfield Pb : Ljava/lang/String;
/*    */     //   70: getstatic java/util/Locale.ENGLISH : Ljava/util/Locale;
/*    */     //   73: invokevirtual toLowerCase : (Ljava/util/Locale;)Ljava/lang/String;
/*    */     //   76: aload_2
/*    */     //   77: invokevirtual equals : (Ljava/lang/Object;)Z
/*    */     //   80: ifeq -> 41
/*    */     //   83: goto -> 89
/*    */     //   86: aconst_null
/*    */     //   87: astore #4
/*    */     //   89: aload #4
/*    */     //   91: ifnull -> 127
/*    */     //   94: aload_0
/*    */     //   95: new f/h70
/*    */     //   98: dup
/*    */     //   99: astore_0
/*    */     //   100: aload_1
/*    */     //   101: sipush #2260
/*    */     //   104: aload_1
/*    */     //   105: invokestatic Go : (ILjava/lang/String;)Ljava/lang/String;
/*    */     //   108: astore_1
/*    */     //   109: <illegal opcode> run : (Ljava/lang/String;)Ljava/lang/Runnable;
/*    */     //   114: aload_1
/*    */     //   115: swap
/*    */     //   116: aconst_null
/*    */     //   117: invokespecial <init> : (Ljava/lang/String;Ljava/lang/Runnable;Lf/JG0;)V
/*    */     //   120: aload_0
/*    */     //   121: invokevirtual uh : (Lf/h70;)V
/*    */     //   124: goto -> 144
/*    */     //   127: getstatic f/km.u4 : Lf/R8;
/*    */     //   130: getfield e20 : Lf/c4;
/*    */     //   133: new f/Og
/*    */     //   136: dup
/*    */     //   137: aload_1
/*    */     //   138: invokespecial <init> : (Ljava/lang/String;)V
/*    */     //   141: invokevirtual W3 : (Lf/Bi;)V
/*    */     //   144: return
/*    */     // Line number table:
/*    */     //   Java source line number -> byte code offset
/*    */     //   #1	-> 3
/*    */     //   #2	-> 9
/*    */     //   #3	-> 13
/*    */     //   #4	-> 29
/*    */     //   #5	-> 37
/*    */     //   #6	-> 64
/*    */     //   #7	-> 67
/*    */     //   #8	-> 70
/*    */     //   #9	-> 95
/*    */     //   #10	-> 130
/*    */     //   #11	-> 133
/*    */   }
/*    */   
/*    */   public static void XA(String paramString) {
/*    */     km.u4.e20.W3(new Mh(paramString));
/*    */   }
/*    */   
/*    */   private void Rt(String paramString) {
/*    */     pA pA1;
/*    */     if ((pA1 = this.MH0) != null)
/*    */       Yv0(paramString); 
/*    */   }
/*    */   
/*    */   private void e00(String paramString) {
/*    */     pA pA1;
/*    */     wu wu;
/*    */     if ((pA1 = this.MH0) != null && (wu = this.TF) != null)
/*    */       hu0(paramString); 
/*    */   }
/*    */   
/*    */   private void BN(boolean paramBoolean, String paramString, int paramInt1, int paramInt2) {
/*    */     if (paramBoolean) {
/*    */       ky = ky.DL0;
/*    */       DO dO = DO.u;
/*    */       paramInt1 = 0;
/*    */       paramInt2 = 0;
/*    */       boolean bool1 = false, bool2 = false, bool3 = false, bool4 = false, bool5 = false;
/*    */       km.u4.e20.W3(new Gf0(paramString, this, paramInt1, paramInt2, bool1, bool2, bool3, dO, bool4, bool5));
/*    */       return;
/*    */     } 
/*    */     MF.KQ();
/*    */     this(paramString);
/*    */     ky ky;
/*    */     kq kq;
/*    */     si(this, Ub());
/*    */   }
/*    */   
/*    */   public static void pF(j40 paramj40, short paramShort, Jo paramJo, SG0 paramSG0, Runnable paramRunnable) {
/*    */     boolean bool;
/*    */     R2 r2;
/*    */     pA pA1;
/*    */     R8 r8 = km.u4;
/*    */     int i = paramj40.Jg, j = paramJo.Jg;
/*    */     int k = paramSG0.Ol;
/*    */     if (paramShort == 19) {
/*    */       r8.getClass();
/*    */       bool = true;
/*    */       r2 = null;
/*    */       if ((pA1 = r8.YG0.MH0) != null)
/*    */         pA1.U10(bool, r2); 
/*    */     } else {
/*    */       bool.e20.W3(new NH(pA1, j, k, r2));
/*    */     } 
/*    */     if (paramRunnable != null)
/*    */       UB0.Kg0.fN(paramRunnable); 
/*    */   }
/*    */   
/*    */   public static void l0(j40 paramj40, short paramShort, Jo paramJo, SG0 paramSG0, Runnable paramRunnable) {
/*    */     boolean bool;
/*    */     R2 r2;
/*    */     pA pA1;
/*    */     R8 r8 = km.u4;
/*    */     int i = paramj40.Jg, j = paramJo.Jg;
/*    */     int k = paramSG0.Ol;
/*    */     if (paramShort == 19) {
/*    */       r8.getClass();
/*    */       bool = true;
/*    */       r2 = null;
/*    */       if ((pA1 = r8.YG0.MH0) != null)
/*    */         pA1.U10(bool, r2); 
/*    */     } else {
/*    */       bool.e20.W3(new NH(pA1, j, k, r2));
/*    */     } 
/*    */     if (paramRunnable != null)
/*    */       UB0.Kg0.fN(paramRunnable); 
/*    */   }
/*    */   
/*    */   private void Gy(String paramString, int paramInt1, int paramInt2) {
/*    */     paramString = Ml0.OH0(1519);
/*    */     this(paramString, paramString::ZI);
/*    */     Hk0 hk0;
/*    */     (new B3()).aV.add(this);
/*    */     F7.T1(new B3(), this, paramInt1, paramInt2);
/*    */   }
/*    */   
/*    */   public static void JU(Qv0[] paramArrayOfQv0, int paramInt) {
/*    */     pA pA1;
/*    */     if ((pA1 = pA.Dg0) == null)
/*    */       return; 
/*    */     gO gO;
/*    */     if ((gO = pA1.dk0) == null)
/*    */       return; 
/*    */     byte b1 = 0;
/*    */     int i;
/*    */     byte b2;
/*    */     for (i = paramArrayOfQv0.length, b2 = 0; b2 < i; ) {
/*    */       Qv0 qv0 = paramArrayOfQv0[b2];
/*    */       int j = b1 + 1;
/*    */       Zq zq;
/*    */       if ((zq = gO.lg(paramInt, b1)) != null) {
/*    */         km.u4.lO(qv0, zq);
/*    */         b2++;
/*    */         int k = j;
/*    */         continue;
/*    */       } 
/*    */       vu0.Pu(-1, Ml0.Go(2306, km.u4.y80.Kg((byte)paramInt)));
/*    */     } 
/*    */   }
/*    */   
/*    */   public static void Ue(NR paramNR, Qv0[] paramArrayOfQv0) {
/*    */     Qv0 qv0;
/*    */     byte b1 = 0;
/*    */     while (true) {
/*    */       if (b1 < 6) {
/*    */         Qv0 qv01;
/*    */         if (paramNR.FB0[b1].public() == null) {
/*    */           qv01 = paramNR.FB0[b1];
/*    */           break;
/*    */         } 
/*    */         short s = (short)(qv01 + 1);
/*    */         continue;
/*    */       } 
/*    */       paramNR.getClass();
/*    */       qv0 = null;
/*    */       break;
/*    */     } 
/*    */     if (qv0 == null) {
/*    */       vu0.Pu(-1, Ml0.OH0(2305));
/*    */       return;
/*    */     } 
/*    */     int i = 6 - qv0.fH0();
/*    */     if (paramArrayOfQv0.length > i)
/*    */       paramArrayOfQv0 = Arrays.<Qv0>copyOf(paramArrayOfQv0, i); 
/*    */     Qv0[] arrayOfQv01, arrayOfQv02;
/*    */     byte b2;
/*    */     for (arrayOfQv01 = new Qv0[paramArrayOfQv0.length], arrayOfQv02 = new Qv0[paramArrayOfQv0.length], b2 = 0; b2 < paramArrayOfQv0.length; ) {
/*    */       Qv0 qv01;
/*    */       arrayOfQv01[b2] = paramArrayOfQv0[b2];
/*    */       int j;
/*    */       if ((j = 6 - i + b2) < 0 || j > 6) {
/*    */         qv01 = null;
/*    */       } else {
/*    */         qv01 = paramNR.FB0[qv01];
/*    */       } 
/*    */       arrayOfQv02[b2] = qv01;
/*    */       b2++;
/*    */     } 
/*    */     km.u4.Zt(arrayOfQv01, arrayOfQv02);
/*    */   }
/*    */   
/*    */   private void TB0(boolean paramBoolean, int paramInt1, int paramInt2, Qv0 paramQv0, Qv0[] paramArrayOfQv0, int paramInt3) {
/*    */     // Byte code:
/*    */     //   0: iload_1
/*    */     //   1: new f/B3
/*    */     //   4: dup
/*    */     //   5: astore_1
/*    */     //   6: invokespecial <init> : ()V
/*    */     //   9: ifne -> 83
/*    */     //   12: aload_1
/*    */     //   13: dup
/*    */     //   14: new f/Hk0
/*    */     //   17: dup
/*    */     //   18: astore #7
/*    */     //   20: iload_2
/*    */     //   21: iload_3
/*    */     //   22: aload #7
/*    */     //   24: sipush #2317
/*    */     //   27: invokestatic OH0 : (I)Ljava/lang/String;
/*    */     //   30: invokespecial <init> : (Ljava/lang/String;)V
/*    */     //   33: <illegal opcode> run : (II)Ljava/lang/Runnable;
/*    */     //   38: putfield rv : Ljava/lang/Runnable;
/*    */     //   41: getfield aV : Ljava/util/ArrayList;
/*    */     //   44: aload #7
/*    */     //   46: invokevirtual add : (Ljava/lang/Object;)Z
/*    */     //   49: pop
/*    */     //   50: new f/Hk0
/*    */     //   53: dup
/*    */     //   54: dup
/*    */     //   55: astore #7
/*    */     //   57: sipush #2314
/*    */     //   60: invokestatic OH0 : (I)Ljava/lang/String;
/*    */     //   63: invokespecial <init> : (Ljava/lang/String;)V
/*    */     //   66: <illegal opcode> run : ()Ljava/lang/Runnable;
/*    */     //   71: putfield rv : Ljava/lang/Runnable;
/*    */     //   74: getfield aV : Ljava/util/ArrayList;
/*    */     //   77: aload #7
/*    */     //   79: invokevirtual add : (Ljava/lang/Object;)Z
/*    */     //   82: pop
/*    */     //   83: aload #5
/*    */     //   85: aload_1
/*    */     //   86: new f/Hk0
/*    */     //   89: dup
/*    */     //   90: astore #7
/*    */     //   92: aload_0
/*    */     //   93: aload #4
/*    */     //   95: aload #7
/*    */     //   97: sipush #2300
/*    */     //   100: invokestatic OH0 : (I)Ljava/lang/String;
/*    */     //   103: invokespecial <init> : (Ljava/lang/String;)V
/*    */     //   106: <illegal opcode> run : (Lf/js;Lf/Qv0;)Ljava/lang/Runnable;
/*    */     //   111: putfield rv : Ljava/lang/Runnable;
/*    */     //   114: getfield aV : Ljava/util/ArrayList;
/*    */     //   117: aload #7
/*    */     //   119: invokevirtual add : (Ljava/lang/Object;)Z
/*    */     //   122: pop
/*    */     //   123: ldc ''
/*    */     //   125: astore_0
/*    */     //   126: iconst_0
/*    */     //   127: istore #7
/*    */     //   129: arraylength
/*    */     //   130: istore #8
/*    */     //   132: iconst_0
/*    */     //   133: istore #9
/*    */     //   135: iload #9
/*    */     //   137: iload #8
/*    */     //   139: if_icmpge -> 206
/*    */     //   142: aload #5
/*    */     //   144: iload #9
/*    */     //   146: aaload
/*    */     //   147: invokevirtual public : ()Lf/j40;
/*    */     //   150: dup
/*    */     //   151: astore #10
/*    */     //   153: ifnull -> 200
/*    */     //   156: aload #10
/*    */     //   158: getfield Zs : Lf/Q90;
/*    */     //   161: invokevirtual BM : ()Z
/*    */     //   164: ifne -> 170
/*    */     //   167: goto -> 200
/*    */     //   170: iload #7
/*    */     //   172: iconst_1
/*    */     //   173: if_icmpge -> 197
/*    */     //   176: getstatic f/Of.eH : Lf/Of;
/*    */     //   179: aload #10
/*    */     //   181: getfield Zs : Lf/Q90;
/*    */     //   184: invokevirtual p10 : ()S
/*    */     //   187: invokevirtual On0 : (S)Lf/LPT3;
/*    */     //   190: getfield Iu : I
/*    */     //   193: invokestatic OH0 : (I)Ljava/lang/String;
/*    */     //   196: astore_0
/*    */     //   197: iinc #7, 1
/*    */     //   200: iinc #9, 1
/*    */     //   203: goto -> 135
/*    */     //   206: iload #7
/*    */     //   208: ifle -> 295
/*    */     //   211: iload #7
/*    */     //   213: new f/Hk0
/*    */     //   216: dup
/*    */     //   217: astore #8
/*    */     //   219: invokespecial <init> : ()V
/*    */     //   222: iconst_1
/*    */     //   223: if_icmpne -> 237
/*    */     //   226: sipush #1421
/*    */     //   229: aload_0
/*    */     //   230: invokestatic Go : (ILjava/lang/String;)Ljava/lang/String;
/*    */     //   233: astore_0
/*    */     //   234: goto -> 250
/*    */     //   237: iload #7
/*    */     //   239: invokestatic valueOf : (I)Ljava/lang/String;
/*    */     //   242: sipush #1409
/*    */     //   245: swap
/*    */     //   246: invokestatic Go : (ILjava/lang/String;)Ljava/lang/String;
/*    */     //   249: astore_0
/*    */     //   250: aload_1
/*    */     //   251: aload #8
/*    */     //   253: aload #5
/*    */     //   255: aload #8
/*    */     //   257: dup
/*    */     //   258: aload_0
/*    */     //   259: aload #8
/*    */     //   261: getfield e0 : Ljava/lang/String;
/*    */     //   264: astore #7
/*    */     //   266: putfield e0 : Ljava/lang/String;
/*    */     //   269: ldc_w 'name'
/*    */     //   272: aload #7
/*    */     //   274: aload_0
/*    */     //   275: invokevirtual l8 : (Ljava/lang/String;Ljava/lang/String;Ljava/lang/String;)V
/*    */     //   278: <illegal opcode> run : ([Lf/Qv0;)Ljava/lang/Runnable;
/*    */     //   283: putfield rv : Ljava/lang/Runnable;
/*    */     //   286: getfield aV : Ljava/util/ArrayList;
/*    */     //   289: aload #8
/*    */     //   291: invokevirtual add : (Ljava/lang/Object;)Z
/*    */     //   294: pop
/*    */     //   295: aload #5
/*    */     //   297: arraylength
/*    */     //   298: iconst_1
/*    */     //   299: if_icmpne -> 336
/*    */     //   302: aload_1
/*    */     //   303: new f/Hk0
/*    */     //   306: dup
/*    */     //   307: astore_0
/*    */     //   308: aload #5
/*    */     //   310: aload_0
/*    */     //   311: sipush #8043
/*    */     //   314: invokestatic OH0 : (I)Ljava/lang/String;
/*    */     //   317: invokespecial <init> : (Ljava/lang/String;)V
/*    */     //   320: <illegal opcode> run : ([Lf/Qv0;)Ljava/lang/Runnable;
/*    */     //   325: putfield rv : Ljava/lang/Runnable;
/*    */     //   328: getfield aV : Ljava/util/ArrayList;
/*    */     //   331: aload_0
/*    */     //   332: invokevirtual add : (Ljava/lang/Object;)Z
/*    */     //   335: pop
/*    */     //   336: aload #5
/*    */     //   338: arraylength
/*    */     //   339: iconst_5
/*    */     //   340: if_icmpgt -> 377
/*    */     //   343: aload_1
/*    */     //   344: new f/Hk0
/*    */     //   347: dup
/*    */     //   348: astore_0
/*    */     //   349: aload #5
/*    */     //   351: aload_0
/*    */     //   352: sipush #5827
/*    */     //   355: invokestatic OH0 : (I)Ljava/lang/String;
/*    */     //   358: invokespecial <init> : (Ljava/lang/String;)V
/*    */     //   361: <illegal opcode> run : ([Lf/Qv0;)Ljava/lang/Runnable;
/*    */     //   366: putfield rv : Ljava/lang/Runnable;
/*    */     //   369: getfield aV : Ljava/util/ArrayList;
/*    */     //   372: aload_0
/*    */     //   373: invokevirtual add : (Ljava/lang/Object;)Z
/*    */     //   376: pop
/*    */     //   377: aload #5
/*    */     //   379: aload_1
/*    */     //   380: aload #5
/*    */     //   382: iload #6
/*    */     //   384: invokestatic pz : ([Lf/Qv0;I)Lf/B3;
/*    */     //   387: astore_0
/*    */     //   388: getfield aV : Ljava/util/ArrayList;
/*    */     //   391: aload_0
/*    */     //   392: invokevirtual add : (Ljava/lang/Object;)Z
/*    */     //   395: pop
/*    */     //   396: arraylength
/*    */     //   397: bipush #6
/*    */     //   399: if_icmpgt -> 517
/*    */     //   402: aload #4
/*    */     //   404: invokevirtual public : ()Lf/j40;
/*    */     //   407: ifnull -> 517
/*    */     //   410: new f/B3
/*    */     //   413: dup
/*    */     //   414: astore_0
/*    */     //   415: sipush #1412
/*    */     //   418: invokestatic OH0 : (I)Ljava/lang/String;
/*    */     //   421: invokespecial <init> : (Ljava/lang/String;)V
/*    */     //   424: iconst_0
/*    */     //   425: istore #6
/*    */     //   427: iload #6
/*    */     //   429: getstatic f/km.u4 : Lf/R8;
/*    */     //   432: getfield Lz : Lf/fH0;
/*    */     //   435: getfield wm0 : B
/*    */     //   438: invokestatic Gc : (B)B
/*    */     //   441: if_icmpge -> 508
/*    */     //   444: aload_0
/*    */     //   445: getstatic f/km.u4 : Lf/R8;
/*    */     //   448: getfield Mg0 : Lf/g2;
/*    */     //   451: iload #6
/*    */     //   453: i2b
/*    */     //   454: invokevirtual LPT5 : (B)Lf/super;
/*    */     //   457: dup
/*    */     //   458: astore #7
/*    */     //   460: invokevirtual toString : ()Ljava/lang/String;
/*    */     //   463: astore #8
/*    */     //   465: new f/Hk0
/*    */     //   468: dup
/*    */     //   469: dup
/*    */     //   470: astore #9
/*    */     //   472: aload #8
/*    */     //   474: invokespecial <init> : (Ljava/lang/String;)V
/*    */     //   477: new f/XG0
/*    */     //   480: dup
/*    */     //   481: aload #7
/*    */     //   483: aload #8
/*    */     //   485: aload #5
/*    */     //   487: invokespecial <init> : (Lf/super;Ljava/lang/String;[Lf/Qv0;)V
/*    */     //   490: putfield rv : Ljava/lang/Runnable;
/*    */     //   493: getfield aV : Ljava/util/ArrayList;
/*    */     //   496: aload #9
/*    */     //   498: invokevirtual add : (Ljava/lang/Object;)Z
/*    */     //   501: pop
/*    */     //   502: iinc #6, 1
/*    */     //   505: goto -> 427
/*    */     //   508: aload_1
/*    */     //   509: getfield aV : Ljava/util/ArrayList;
/*    */     //   512: aload_0
/*    */     //   513: invokevirtual add : (Ljava/lang/Object;)Z
/*    */     //   516: pop
/*    */     //   517: aload_1
/*    */     //   518: aload #4
/*    */     //   520: aload_1
/*    */     //   521: new f/Hk0
/*    */     //   524: dup
/*    */     //   525: astore_0
/*    */     //   526: aload #5
/*    */     //   528: aload #4
/*    */     //   530: aload_0
/*    */     //   531: sipush #2302
/*    */     //   534: invokestatic OH0 : (I)Ljava/lang/String;
/*    */     //   537: invokespecial <init> : (Ljava/lang/String;)V
/*    */     //   540: <illegal opcode> run : ([Lf/Qv0;Lf/Qv0;)Ljava/lang/Runnable;
/*    */     //   545: putfield rv : Ljava/lang/Runnable;
/*    */     //   548: getfield aV : Ljava/util/ArrayList;
/*    */     //   551: aload_0
/*    */     //   552: invokevirtual add : (Ljava/lang/Object;)Z
/*    */     //   555: pop
/*    */     //   556: iload_2
/*    */     //   557: iload_3
/*    */     //   558: invokestatic T1 : (Lf/hu;Lf/JG0;II)V
/*    */     //   561: return
/*    */     // Line number table:
/*    */     //   Java source line number -> byte code offset
/*    */     //   #1	-> 38
/*    */     //   #2	-> 41
/*    */     //   #3	-> 50
/*    */     //   #4	-> 71
/*    */     //   #5	-> 74
/*    */     //   #6	-> 86
/*    */     //   #7	-> 111
/*    */     //   #8	-> 114
/*    */     //   #9	-> 123
/*    */     //   #10	-> 158
/*    */     //   #11	-> 161
/*    */     //   #12	-> 176
/*    */     //   #13	-> 181
/*    */     //   #14	-> 184
/*    */     //   #15	-> 190
/*    */     //   #16	-> 213
/*    */     //   #17	-> 261
/*    */     //   #18	-> 278
/*    */     //   #19	-> 283
/*    */     //   #20	-> 286
/*    */     //   #21	-> 297
/*    */     //   #22	-> 325
/*    */     //   #23	-> 328
/*    */     //   #24	-> 338
/*    */     //   #25	-> 366
/*    */     //   #26	-> 369
/*    */     //   #27	-> 384
/*    */     //   #28	-> 388
/*    */     //   #29	-> 396
/*    */     //   #30	-> 410
/*    */     //   #31	-> 432
/*    */     //   #32	-> 435
/*    */     //   #33	-> 438
/*    */     //   #34	-> 448
/*    */     //   #35	-> 454
/*    */     //   #36	-> 490
/*    */     //   #37	-> 493
/*    */     //   #38	-> 509
/*    */     //   #39	-> 521
/*    */     //   #40	-> 545
/*    */     //   #41	-> 548
/*    */     //   #42	-> 558
/*    */   }
/*    */   
/*    */   public static void Rn(Qv0[] paramArrayOfQv0, Qv0 paramQv0) {
/*    */     // Byte code:
/*    */     //   0: aload_0
/*    */     //   1: iconst_0
/*    */     //   2: istore_2
/*    */     //   3: new f/Ip
/*    */     //   6: dup
/*    */     //   7: astore_3
/*    */     //   8: invokespecial <init> : ()V
/*    */     //   11: new f/cr0
/*    */     //   14: dup
/*    */     //   15: astore #4
/*    */     //   17: aload_3
/*    */     //   18: invokespecial <init> : (Lf/Ip;)V
/*    */     //   21: new f/g0
/*    */     //   24: dup
/*    */     //   25: astore #5
/*    */     //   27: aload_3
/*    */     //   28: invokespecial <init> : (Lf/Ip;)V
/*    */     //   31: new f/g0
/*    */     //   34: dup
/*    */     //   35: astore #6
/*    */     //   37: aload_3
/*    */     //   38: invokespecial <init> : (Lf/Ip;)V
/*    */     //   41: new f/cr0
/*    */     //   44: dup
/*    */     //   45: astore #7
/*    */     //   47: aload_3
/*    */     //   48: invokespecial <init> : (Lf/Ip;)V
/*    */     //   51: arraylength
/*    */     //   52: istore #8
/*    */     //   54: iconst_0
/*    */     //   55: istore #9
/*    */     //   57: iload #9
/*    */     //   59: iload #8
/*    */     //   61: if_icmpge -> 575
/*    */     //   64: aload_0
/*    */     //   65: iload #9
/*    */     //   67: aaload
/*    */     //   68: invokevirtual public : ()Lf/j40;
/*    */     //   71: dup
/*    */     //   72: astore #10
/*    */     //   74: ifnull -> 569
/*    */     //   77: aload #10
/*    */     //   79: getfield Zs : Lf/Q90;
/*    */     //   82: invokevirtual YC : ()Z
/*    */     //   85: ifeq -> 91
/*    */     //   88: goto -> 569
/*    */     //   91: aload #10
/*    */     //   93: new f/vF0
/*    */     //   96: dup
/*    */     //   97: astore #11
/*    */     //   99: bipush #16
/*    */     //   101: bipush #16
/*    */     //   103: iconst_0
/*    */     //   104: invokespecial <init> : (III)V
/*    */     //   107: getfield Zs : Lf/Q90;
/*    */     //   110: invokevirtual tm0 : ()Z
/*    */     //   113: ifeq -> 150
/*    */     //   116: aload #11
/*    */     //   118: getfield TS : Lf/rH;
/*    */     //   121: iconst_1
/*    */     //   122: anewarray f/pe0
/*    */     //   125: dup
/*    */     //   126: invokestatic ZZ : ()Lf/interface;
/*    */     //   129: aload #10
/*    */     //   131: getfield Zs : Lf/Q90;
/*    */     //   134: invokevirtual Gf : ()Z
/*    */     //   137: invokevirtual yI0 : (Z)Lf/pe0;
/*    */     //   140: iconst_0
/*    */     //   141: swap
/*    */     //   142: aastore
/*    */     //   143: invokevirtual Pn : ([Lf/pe0;)Lf/JG0;
/*    */     //   146: pop
/*    */     //   147: goto -> 185
/*    */     //   150: aload #10
/*    */     //   152: getfield Zs : Lf/Q90;
/*    */     //   155: getfield wH : [Lf/mA;
/*    */     //   158: arraylength
/*    */     //   159: ifle -> 192
/*    */     //   162: aload #11
/*    */     //   164: getfield TS : Lf/rH;
/*    */     //   167: iconst_1
/*    */     //   168: anewarray f/pe0
/*    */     //   171: dup
/*    */     //   172: invokestatic ZZ : ()Lf/interface;
/*    */     //   175: getfield oX : Lf/pe0;
/*    */     //   178: iconst_0
/*    */     //   179: swap
/*    */     //   180: aastore
/*    */     //   181: invokevirtual Pn : ([Lf/pe0;)Lf/JG0;
/*    */     //   184: pop
/*    */     //   185: aload #11
/*    */     //   187: bipush #100
/*    */     //   189: putfield jl : I
/*    */     //   192: aload #10
/*    */     //   194: aload #11
/*    */     //   196: getfield TS : Lf/rH;
/*    */     //   199: bipush #16
/*    */     //   201: bipush #16
/*    */     //   203: invokevirtual tL : (II)V
/*    */     //   206: new f/dQ
/*    */     //   209: dup
/*    */     //   210: dup2
/*    */     //   211: astore #12
/*    */     //   213: aload #10
/*    */     //   215: aload #12
/*    */     //   217: dup
/*    */     //   218: dup
/*    */     //   219: aload #10
/*    */     //   221: invokevirtual Hn : ()Ljava/lang/String;
/*    */     //   224: astore #13
/*    */     //   226: invokespecial <init> : ()V
/*    */     //   229: aload #13
/*    */     //   231: invokevirtual E1 : (Ljava/lang/String;)V
/*    */     //   234: ldc_w 'label-dark'
/*    */     //   237: invokevirtual Xu : (Ljava/lang/String;)V
/*    */     //   240: iconst_0
/*    */     //   241: iconst_0
/*    */     //   242: iconst_0
/*    */     //   243: invokestatic Zs0 : (Lf/j40;ZZZ)Ljava/lang/String;
/*    */     //   246: putfield z4 : Ljava/lang/Object;
/*    */     //   249: invokevirtual zn : ()V
/*    */     //   252: bipush #100
/*    */     //   254: putfield jl : I
/*    */     //   257: new f/vF0
/*    */     //   260: dup
/*    */     //   261: astore #13
/*    */     //   263: bipush #16
/*    */     //   265: bipush #16
/*    */     //   267: iconst_0
/*    */     //   268: invokespecial <init> : (III)V
/*    */     //   271: getfield Zs : Lf/Q90;
/*    */     //   274: invokevirtual p10 : ()S
/*    */     //   277: ifle -> 346
/*    */     //   280: aload #13
/*    */     //   282: dup
/*    */     //   283: dup
/*    */     //   284: dup2
/*    */     //   285: getfield TS : Lf/rH;
/*    */     //   288: iconst_1
/*    */     //   289: anewarray f/zh0
/*    */     //   292: dup
/*    */     //   293: invokestatic Kw0 : ()Lf/h90;
/*    */     //   296: getfield e1 : Lf/zh0;
/*    */     //   299: iconst_0
/*    */     //   300: swap
/*    */     //   301: aastore
/*    */     //   302: invokevirtual sm : ([Lf/zh0;)V
/*    */     //   305: getfield TS : Lf/rH;
/*    */     //   308: bipush #12
/*    */     //   310: bipush #10
/*    */     //   312: invokevirtual tL : (II)V
/*    */     //   315: getstatic f/Of.eH : Lf/Of;
/*    */     //   318: aload #10
/*    */     //   320: getfield Zs : Lf/Q90;
/*    */     //   323: invokevirtual p10 : ()S
/*    */     //   326: invokevirtual On0 : (S)Lf/LPT3;
/*    */     //   329: getfield Iu : I
/*    */     //   332: invokestatic OH0 : (I)Ljava/lang/String;
/*    */     //   335: putfield z4 : Ljava/lang/Object;
/*    */     //   338: invokevirtual zn : ()V
/*    */     //   341: bipush #100
/*    */     //   343: putfield jl : I
/*    */     //   346: aload #7
/*    */     //   348: aload #6
/*    */     //   350: new f/vF0
/*    */     //   353: dup
/*    */     //   354: dup
/*    */     //   355: dup2
/*    */     //   356: astore #14
/*    */     //   358: bipush #36
/*    */     //   360: bipush #36
/*    */     //   362: iconst_0
/*    */     //   363: invokespecial <init> : (III)V
/*    */     //   366: getfield TS : Lf/rH;
/*    */     //   369: iconst_1
/*    */     //   370: anewarray f/zh0
/*    */     //   373: dup
/*    */     //   374: getstatic f/um0.Kt0 : Lf/um0;
/*    */     //   377: aload #10
/*    */     //   379: dup
/*    */     //   380: getfield Zs : Lf/Q90;
/*    */     //   383: invokevirtual Vf0 : ()S
/*    */     //   386: istore #15
/*    */     //   388: invokevirtual s5 : ()B
/*    */     //   391: istore #16
/*    */     //   393: iload #15
/*    */     //   395: aload #10
/*    */     //   397: getfield Zs : Lf/Q90;
/*    */     //   400: invokevirtual da : ()Z
/*    */     //   403: iload #16
/*    */     //   405: invokevirtual lb : (SZB)[Lf/zh0;
/*    */     //   408: iconst_0
/*    */     //   409: aaload
/*    */     //   410: iconst_0
/*    */     //   411: swap
/*    */     //   412: aastore
/*    */     //   413: invokevirtual sm : ([Lf/zh0;)V
/*    */     //   416: getfield TS : Lf/rH;
/*    */     //   419: iconst_0
/*    */     //   420: bipush #-10
/*    */     //   422: invokevirtual zT : (II)Lf/JG0;
/*    */     //   425: pop
/*    */     //   426: getfield TS : Lf/rH;
/*    */     //   429: bipush #36
/*    */     //   431: bipush #36
/*    */     //   433: invokevirtual tL : (II)V
/*    */     //   436: new f/g0
/*    */     //   439: dup
/*    */     //   440: aload_3
/*    */     //   441: swap
/*    */     //   442: aload_3
/*    */     //   443: invokespecial <init> : (Lf/Ip;)V
/*    */     //   446: iconst_4
/*    */     //   447: anewarray f/JG0
/*    */     //   450: dup
/*    */     //   451: dup
/*    */     //   452: dup2
/*    */     //   453: iconst_0
/*    */     //   454: aload #11
/*    */     //   456: aastore
/*    */     //   457: iconst_1
/*    */     //   458: aload #14
/*    */     //   460: aastore
/*    */     //   461: iconst_2
/*    */     //   462: aload #12
/*    */     //   464: aastore
/*    */     //   465: iconst_3
/*    */     //   466: aload #13
/*    */     //   468: aastore
/*    */     //   469: invokevirtual vo0 : ([Lf/JG0;)Lf/U90;
/*    */     //   472: invokevirtual ee0 : (Lf/U90;)Lf/U90;
/*    */     //   475: invokevirtual ee0 : (Lf/U90;)Lf/U90;
/*    */     //   478: pop
/*    */     //   479: new f/cr0
/*    */     //   482: dup
/*    */     //   483: aload_3
/*    */     //   484: swap
/*    */     //   485: aload_3
/*    */     //   486: invokespecial <init> : (Lf/Ip;)V
/*    */     //   489: iconst_4
/*    */     //   490: anewarray f/JG0
/*    */     //   493: dup
/*    */     //   494: dup
/*    */     //   495: dup2
/*    */     //   496: iconst_0
/*    */     //   497: aload #11
/*    */     //   499: aastore
/*    */     //   500: iconst_1
/*    */     //   501: aload #14
/*    */     //   503: aastore
/*    */     //   504: iconst_2
/*    */     //   505: aload #12
/*    */     //   507: aastore
/*    */     //   508: iconst_3
/*    */     //   509: aload #13
/*    */     //   511: aastore
/*    */     //   512: invokevirtual AUX : ([Lf/JG0;)Lf/U90;
/*    */     //   515: invokevirtual ee0 : (Lf/U90;)Lf/U90;
/*    */     //   518: invokevirtual ee0 : (Lf/U90;)Lf/U90;
/*    */     //   521: pop
/*    */     //   522: iload_2
/*    */     //   523: iconst_1
/*    */     //   524: iadd
/*    */     //   525: dup
/*    */     //   526: istore_2
/*    */     //   527: bipush #15
/*    */     //   529: irem
/*    */     //   530: ifne -> 569
/*    */     //   533: aload #5
/*    */     //   535: aload #4
/*    */     //   537: aload #6
/*    */     //   539: invokevirtual ee0 : (Lf/U90;)Lf/U90;
/*    */     //   542: pop
/*    */     //   543: aload #7
/*    */     //   545: invokevirtual ee0 : (Lf/U90;)Lf/U90;
/*    */     //   548: pop
/*    */     //   549: new f/g0
/*    */     //   552: dup
/*    */     //   553: astore #6
/*    */     //   555: aload_3
/*    */     //   556: invokespecial <init> : (Lf/Ip;)V
/*    */     //   559: new f/cr0
/*    */     //   562: dup
/*    */     //   563: astore #7
/*    */     //   565: aload_3
/*    */     //   566: invokespecial <init> : (Lf/Ip;)V
/*    */     //   569: iinc #9, 1
/*    */     //   572: goto -> 57
/*    */     //   575: aload_3
/*    */     //   576: dup
/*    */     //   577: aload #5
/*    */     //   579: aload #7
/*    */     //   581: aload #4
/*    */     //   583: aload #6
/*    */     //   585: invokevirtual ee0 : (Lf/U90;)Lf/U90;
/*    */     //   588: pop
/*    */     //   589: invokevirtual ee0 : (Lf/U90;)Lf/U90;
/*    */     //   592: pop
/*    */     //   593: new f/dQ
/*    */     //   596: dup
/*    */     //   597: dup2
/*    */     //   598: astore_2
/*    */     //   599: sipush #2310
/*    */     //   602: ldc ''
/*    */     //   604: invokestatic Go : (ILjava/lang/String;)Ljava/lang/String;
/*    */     //   607: astore #6
/*    */     //   609: invokespecial <init> : ()V
/*    */     //   612: aload #6
/*    */     //   614: invokevirtual E1 : (Ljava/lang/String;)V
/*    */     //   617: ldc_w 'label-dark'
/*    */     //   620: invokevirtual Xu : (Ljava/lang/String;)V
/*    */     //   623: new f/g0
/*    */     //   626: dup
/*    */     //   627: aload_2
/*    */     //   628: swap
/*    */     //   629: aload_3
/*    */     //   630: invokespecial <init> : (Lf/Ip;)V
/*    */     //   633: invokevirtual Ya : (Lf/JG0;)Lf/U90;
/*    */     //   636: aload #4
/*    */     //   638: invokevirtual ee0 : (Lf/U90;)Lf/U90;
/*    */     //   641: invokevirtual rK0 : (Lf/U90;)V
/*    */     //   644: new f/cr0
/*    */     //   647: dup
/*    */     //   648: aload_2
/*    */     //   649: swap
/*    */     //   650: aload_3
/*    */     //   651: invokespecial <init> : (Lf/Ip;)V
/*    */     //   654: invokevirtual Ya : (Lf/JG0;)Lf/U90;
/*    */     //   657: aload #5
/*    */     //   659: invokevirtual ee0 : (Lf/U90;)Lf/U90;
/*    */     //   662: invokevirtual WN : (Lf/U90;)V
/*    */     //   665: getstatic f/js.vu0 : Lf/js;
/*    */     //   668: new f/h70
/*    */     //   671: dup
/*    */     //   672: dup
/*    */     //   673: aload_3
/*    */     //   674: aload_0
/*    */     //   675: aload_1
/*    */     //   676: <illegal opcode> run : ([Lf/Qv0;Lf/Qv0;)Ljava/lang/Runnable;
/*    */     //   681: aload_1
/*    */     //   682: iconst_1
/*    */     //   683: invokespecial <init> : (Lf/JG0;Ljava/lang/Runnable;Lf/JG0;I)V
/*    */     //   686: iconst_1
/*    */     //   687: putfield sD0 : Z
/*    */     //   690: invokevirtual uh : (Lf/h70;)V
/*    */     //   693: return
/*    */     // Line number table:
/*    */     //   Java source line number -> byte code offset
/*    */     //   #1	-> 11
/*    */     //   #2	-> 21
/*    */     //   #3	-> 41
/*    */     //   #4	-> 51
/*    */     //   #5	-> 79
/*    */     //   #6	-> 93
/*    */     //   #7	-> 104
/*    */     //   #8	-> 107
/*    */     //   #9	-> 110
/*    */     //   #10	-> 118
/*    */     //   #11	-> 122
/*    */     //   #12	-> 131
/*    */     //   #13	-> 134
/*    */     //   #14	-> 152
/*    */     //   #15	-> 155
/*    */     //   #16	-> 158
/*    */     //   #17	-> 164
/*    */     //   #18	-> 168
/*    */     //   #19	-> 175
/*    */     //   #20	-> 180
/*    */     //   #21	-> 189
/*    */     //   #22	-> 196
/*    */     //   #23	-> 203
/*    */     //   #24	-> 226
/*    */     //   #25	-> 234
/*    */     //   #26	-> 243
/*    */     //   #27	-> 246
/*    */     //   #28	-> 254
/*    */     //   #29	-> 257
/*    */     //   #30	-> 268
/*    */     //   #31	-> 271
/*    */     //   #32	-> 274
/*    */     //   #33	-> 285
/*    */     //   #34	-> 289
/*    */     //   #35	-> 296
/*    */     //   #36	-> 301
/*    */     //   #37	-> 305
/*    */     //   #38	-> 312
/*    */     //   #39	-> 315
/*    */     //   #40	-> 320
/*    */     //   #41	-> 323
/*    */     //   #42	-> 329
/*    */     //   #43	-> 335
/*    */     //   #44	-> 343
/*    */     //   #45	-> 350
/*    */     //   #46	-> 366
/*    */     //   #47	-> 370
/*    */     //   #48	-> 374
/*    */     //   #49	-> 380
/*    */     //   #50	-> 383
/*    */     //   #51	-> 397
/*    */     //   #52	-> 405
/*    */     //   #53	-> 416
/*    */     //   #54	-> 422
/*    */     //   #55	-> 426
/*    */     //   #56	-> 433
/*    */     //   #57	-> 436
/*    */     //   #58	-> 447
/*    */     //   #59	-> 479
/*    */     //   #60	-> 490
/*    */     //   #61	-> 549
/*    */     //   #62	-> 559
/*    */     //   #63	-> 585
/*    */     //   #64	-> 609
/*    */     //   #65	-> 617
/*    */     //   #66	-> 623
/*    */     //   #67	-> 633
/*    */     //   #68	-> 644
/*    */     //   #69	-> 654
/*    */     //   #70	-> 665
/*    */     //   #71	-> 668
/*    */     //   #72	-> 683
/*    */     //   #73	-> 687
/*    */     //   #74	-> 690
/*    */   }
/*    */   
/*    */   public static void Y40(Qv0[] paramArrayOfQv0, Qv0 paramQv0) {
/*    */     // Byte code:
/*    */     //   0: aload_0
/*    */     //   1: <illegal opcode> apply : ()Ljava/util/function/Function;
/*    */     //   6: astore_2
/*    */     //   7: invokestatic stream : ([Ljava/lang/Object;)Ljava/util/stream/Stream;
/*    */     //   10: <illegal opcode> apply : ()Ljava/util/function/Function;
/*    */     //   15: invokeinterface map : (Ljava/util/function/Function;)Ljava/util/stream/Stream;
/*    */     //   20: <illegal opcode> test : ()Ljava/util/function/Predicate;
/*    */     //   25: invokeinterface filter : (Ljava/util/function/Predicate;)Ljava/util/stream/Stream;
/*    */     //   30: <illegal opcode> test : ()Ljava/util/function/Predicate;
/*    */     //   35: invokeinterface filter : (Ljava/util/function/Predicate;)Ljava/util/stream/Stream;
/*    */     //   40: aload_2
/*    */     //   41: invokestatic toList : ()Ljava/util/stream/Collector;
/*    */     //   44: invokestatic groupingBy : (Ljava/util/function/Function;Ljava/util/stream/Collector;)Ljava/util/stream/Collector;
/*    */     //   47: invokeinterface collect : (Ljava/util/stream/Collector;)Ljava/lang/Object;
/*    */     //   52: checkcast java/util/Map
/*    */     //   55: dup
/*    */     //   56: astore_2
/*    */     //   57: invokeinterface size : ()I
/*    */     //   62: iconst_1
/*    */     //   63: if_icmpgt -> 135
/*    */     //   66: aload_2
/*    */     //   67: iconst_0
/*    */     //   68: invokestatic valueOf : (I)Ljava/lang/Integer;
/*    */     //   71: invokeinterface containsKey : (Ljava/lang/Object;)Z
/*    */     //   76: ifne -> 82
/*    */     //   79: goto -> 135
/*    */     //   82: aload_0
/*    */     //   83: arraylength
/*    */     //   84: istore_1
/*    */     //   85: iconst_0
/*    */     //   86: istore_2
/*    */     //   87: iload_2
/*    */     //   88: iload_1
/*    */     //   89: if_icmpge -> 337
/*    */     //   92: aload_0
/*    */     //   93: iload_2
/*    */     //   94: aaload
/*    */     //   95: dup
/*    */     //   96: astore_3
/*    */     //   97: invokevirtual public : ()Lf/j40;
/*    */     //   100: ifnull -> 129
/*    */     //   103: aload_3
/*    */     //   104: invokevirtual public : ()Lf/j40;
/*    */     //   107: getfield Zs : Lf/Q90;
/*    */     //   110: invokevirtual YC : ()Z
/*    */     //   113: ifne -> 129
/*    */     //   116: getstatic f/km.u4 : Lf/R8;
/*    */     //   119: aload_3
/*    */     //   120: invokevirtual public : ()Lf/j40;
/*    */     //   123: getfield Jg : I
/*    */     //   126: invokevirtual mO : (I)V
/*    */     //   129: iinc #2, 1
/*    */     //   132: goto -> 87
/*    */     //   135: aload_2
/*    */     //   136: new f/YA0
/*    */     //   139: dup
/*    */     //   140: dup
/*    */     //   141: dup2
/*    */     //   142: astore_0
/*    */     //   143: invokespecial <init> : ()V
/*    */     //   146: getfield Dv0 : Lf/SA;
/*    */     //   149: sipush #2370
/*    */     //   152: invokevirtual mv0 : (I)Lf/nJ0;
/*    */     //   155: getfield Ox : Lf/ZP;
/*    */     //   158: invokevirtual wP : ()Lf/nJ0;
/*    */     //   161: pop
/*    */     //   162: getfield Dv0 : Lf/SA;
/*    */     //   165: ldc_w ' '
/*    */     //   168: invokevirtual IR : (Ljava/lang/String;)Lf/nJ0;
/*    */     //   171: getfield Ox : Lf/ZP;
/*    */     //   174: invokevirtual wP : ()Lf/nJ0;
/*    */     //   177: pop
/*    */     //   178: <illegal opcode> accept : (Lf/YA0;)Ljava/util/function/BiConsumer;
/*    */     //   183: invokeinterface forEach : (Ljava/util/function/BiConsumer;)V
/*    */     //   188: aload_0
/*    */     //   189: dup
/*    */     //   190: getfield Dv0 : Lf/SA;
/*    */     //   193: ldc_w ' '
/*    */     //   196: invokevirtual IR : (Ljava/lang/String;)Lf/nJ0;
/*    */     //   199: getfield Ox : Lf/ZP;
/*    */     //   202: invokevirtual wP : ()Lf/nJ0;
/*    */     //   205: pop
/*    */     //   206: getfield Dv0 : Lf/SA;
/*    */     //   209: sipush #2379
/*    */     //   212: invokevirtual mv0 : (I)Lf/nJ0;
/*    */     //   215: getfield Ox : Lf/ZP;
/*    */     //   218: invokevirtual wP : ()Lf/nJ0;
/*    */     //   221: pop
/*    */     //   222: new f/Un
/*    */     //   225: dup
/*    */     //   226: dup
/*    */     //   227: astore_3
/*    */     //   228: aload_2
/*    */     //   229: aload_3
/*    */     //   230: sipush #2380
/*    */     //   233: invokestatic OH0 : (I)Ljava/lang/String;
/*    */     //   236: invokespecial <init> : (Ljava/lang/String;)V
/*    */     //   239: <illegal opcode> run : (Ljava/util/Map;)Ljava/lang/Runnable;
/*    */     //   244: invokevirtual tW : (Ljava/lang/Runnable;)V
/*    */     //   247: iconst_0
/*    */     //   248: invokevirtual sk0 : (Z)V
/*    */     //   251: new f/Un
/*    */     //   254: dup
/*    */     //   255: dup
/*    */     //   256: astore #4
/*    */     //   258: aload_2
/*    */     //   259: aload #4
/*    */     //   261: sipush #2381
/*    */     //   264: invokestatic OH0 : (I)Ljava/lang/String;
/*    */     //   267: invokespecial <init> : (Ljava/lang/String;)V
/*    */     //   270: <illegal opcode> run : (Ljava/util/Map;)Ljava/lang/Runnable;
/*    */     //   275: invokevirtual tW : (Ljava/lang/Runnable;)V
/*    */     //   278: iconst_0
/*    */     //   279: invokevirtual sk0 : (Z)V
/*    */     //   282: getstatic f/A1.L7 : Lf/A1;
/*    */     //   285: aload_3
/*    */     //   286: aload #4
/*    */     //   288: <illegal opcode> run : (Lf/Un;Lf/Un;)Ljava/lang/Runnable;
/*    */     //   293: ldc2_w 1000
/*    */     //   296: invokevirtual ac0 : (Ljava/lang/Runnable;J)Ljava/util/concurrent/ScheduledFuture;
/*    */     //   299: pop
/*    */     //   300: new f/Un
/*    */     //   303: dup
/*    */     //   304: astore_2
/*    */     //   305: sipush #2382
/*    */     //   308: invokestatic OH0 : (I)Ljava/lang/String;
/*    */     //   311: invokespecial <init> : (Ljava/lang/String;)V
/*    */     //   314: getstatic f/js.vu0 : Lf/js;
/*    */     //   317: new f/h70
/*    */     //   320: dup
/*    */     //   321: dup
/*    */     //   322: aload_0
/*    */     //   323: aload #4
/*    */     //   325: aload_2
/*    */     //   326: aload_1
/*    */     //   327: invokespecial <init> : (Lf/YA0;Lf/Un;Lf/Un;Lf/JG0;)V
/*    */     //   330: iconst_1
/*    */     //   331: putfield sD0 : Z
/*    */     //   334: invokevirtual uh : (Lf/h70;)V
/*    */     //   337: return
/*    */     // Line number table:
/*    */     //   Java source line number -> byte code offset
/*    */     //   #1	-> 107
/*    */     //   #2	-> 110
/*    */     //   #3	-> 116
/*    */     //   #4	-> 123
/*    */     //   #5	-> 126
/*    */     //   #6	-> 155
/*    */     //   #7	-> 162
/*    */     //   #8	-> 171
/*    */     //   #9	-> 178
/*    */     //   #10	-> 199
/*    */     //   #11	-> 206
/*    */     //   #12	-> 215
/*    */     //   #13	-> 222
/*    */     //   #14	-> 282
/*    */     //   #15	-> 288
/*    */     //   #16	-> 314
/*    */     //   #17	-> 317
/*    */     //   #18	-> 331
/*    */     //   #19	-> 334
/*    */   }
/*    */   
/*    */   public static void zj0(YA0 paramYA0, Integer paramInteger, List paramList) {
/*    */     if (paramInteger.intValue() == 0)
/*    */       return; 
/*    */     (paramYA0.Dv0.IR(paramList.size() + "x " + Ml0.OH0(paramInteger.intValue()))).Ox.wP();
/*    */   }
/*    */   
/*    */   public static boolean aw0(j40 paramj40) {
/*    */     return paramj40.Zs.YC() ^ true;
/*    */   }
/*    */   
/*    */   public static Integer ay0(j40 paramj40) {
/*    */     if (py.c7(paramj40.Zs.Cw0, km.u4.GN) || py.c7(paramj40.Zs.Cw0, Jf.c80))
/*    */       return Integer.valueOf(2371); 
/*    */     if (paramj40.Zs.tm0())
/*    */       return Integer.valueOf(2372); 
/*    */     if (paramj40.Zs.da())
/*    */       return Integer.valueOf(2373); 
/*    */     if (paramj40.Zs.iL())
/*    */       return Integer.valueOf(2374); 
/*    */     int i = paramj40.Zs.wH.length;
/*    */     if ((byte)(paramj40.Zs.tm0() + i) > 0)
/*    */       return Integer.valueOf(2375); 
/*    */     if (paramj40.Zs.ri0() == 31 || paramj40.Zs.UA0() >= 120)
/*    */       return Integer.valueOf(2376); 
/*    */     if (paramj40.Zs.od >= 75)
/*    */       return Integer.valueOf(2377); 
/*    */     Calendar.getInstance(TimeZone.getTimeZone("UTC")).setTimeInMillis(paramj40.Zs.Ck * 1000L);
/*    */     return (Calendar.getInstance(TimeZone.getTimeZone("UTC")).get(1) <= 2012) ? Integer.valueOf(2378) : Integer.valueOf(0);
/*    */   }
/*    */   
/*    */   public static void Ss(Qv0[] paramArrayOfQv0) {
/*    */     int i;
/*    */     byte b;
/*    */     for (i = paramArrayOfQv0.length, b = 0; b < i; ) {
/*    */       j40 j40;
/*    */       if ((j40 = paramArrayOfQv0[b].public()) != null && !j40.Zs.YC()) {
/*    */         pA pA1;
/*    */         Kf kf1;
/*    */         if ((kf1 = (pA1 = vu0.MH0).AL) == null) {
/*    */           pA1.BI0(j40, true, true);
/*    */         } else {
/*    */           kf1.zf0(j40);
/*    */         } 
/*    */       } 
/*    */       b++;
/*    */     } 
/*    */   }
/*    */   
/*    */   public static void iD0(Qv0[] paramArrayOfQv0) {
/*    */     int i;
/*    */     byte b;
/*    */     for (i = paramArrayOfQv0.length, b = 0; b < i; ) {
/*    */       j40 j40;
/*    */       if ((j40 = paramArrayOfQv0[b].public()) != null && !j40.Zs.YC()) {
/*    */         pA pA1;
/*    */         A a;
/*    */         if ((a = (pA1 = vu0.MH0).QI0) == null) {
/*    */           pA1.A4(j40, true, true);
/*    */         } else {
/*    */           a.bk.zf(j40);
/*    */           a.sr.dA0(a.sr.Hf(3));
/*    */           VA0.c90(a.bk);
/*    */         } 
/*    */       } 
/*    */       b++;
/*    */     } 
/*    */   }
/*    */   
/*    */   public static void Dp(Qv0[] paramArrayOfQv0) {
/*    */     int i;
/*    */     byte b;
/*    */     for (i = paramArrayOfQv0.length, b = 0; b < i; ) {
/*    */       j40 j40;
/*    */       if ((j40 = paramArrayOfQv0[b].public()) != null && j40.Zs.BM()) {
/*    */         R8 r8 = km.u4;
/*    */         int j = j40.Jg;
/*    */         byte b1 = -1;
/*    */         aq0 aq0 = j40.Zs.COm1;
/*    */         r8.e20.W3(new zD(j, b1, aq0));
/*    */       } 
/*    */       b++;
/*    */     } 
/*    */   }
/*    */   
/*    */   private void za(Qv0 paramQv0) {
/*    */     this.MH0.u30(paramQv0, paramQv0.public());
/*    */   }
/*    */   
/*    */   public static void lc() {
/*    */     pA.Dg0.dk0.e8().zn0(true);
/*    */   }
/*    */   
/*    */   public static void yb0(int paramInt1, int paramInt2) {
/*    */     JG0 jG0;
/*    */     if (!(jG0 = pA.Dg0.dk0.Va0(paramInt1, paramInt2) instanceof Qv0))
/*    */       jG0 = jG0.fr0; 
/*    */     if (!(jG0 instanceof Qv0))
/*    */       return; 
/*    */     paramInt2 = (jG0 = jG0).RS();
/*    */     paramInt2 = ((Qv0)jG0).qF() / 2 + paramInt2;
/*    */     int i = ((Qv0)jG0).e3();
/*    */     i = ((Qv0)jG0).Hy() / 2 + i;
/*    */     pA.Dg0.dk0.class((Qv0)jG0, Arrays.asList(pA.Dg0.dk0.e8().t00()));
/*    */     pA.Dg0.dk0.lf0(paramInt2, i);
/*    */     VA0.c90(jG0);
/*    */   }
/*    */   
/*    */   public static JG0 uD(JG0 paramJG0) {
/*    */     if (paramJG0 instanceof of && paramJG0.p3())
/*    */       return paramJG0; 
/*    */     for (byte b = 0; b < paramJG0.Ub(); b++) {
/*    */       JG0 jG0;
/*    */       if ((jG0 = uD(paramJG0.lPt3(b))) != null)
/*    */         return jG0; 
/*    */     } 
/*    */     return null;
/*    */   }
/*    */   
/*    */   public static B3 pz(Qv0[] paramArrayOfQv0, int paramInt) {
/*    */     // Byte code:
/*    */     //   0: new f/B3
/*    */     //   3: dup
/*    */     //   4: astore_2
/*    */     //   5: sipush #2301
/*    */     //   8: invokestatic OH0 : (I)Ljava/lang/String;
/*    */     //   11: invokespecial <init> : (Ljava/lang/String;)V
/*    */     //   14: getstatic f/pA.Dg0 : Lf/pA;
/*    */     //   17: getfield jc0 : Lf/NR;
/*    */     //   20: astore_3
/*    */     //   21: iconst_0
/*    */     //   22: istore #4
/*    */     //   24: iload #4
/*    */     //   26: bipush #6
/*    */     //   28: if_icmpge -> 66
/*    */     //   31: aload_3
/*    */     //   32: getfield FB0 : [Lf/Qv0;
/*    */     //   35: iload #4
/*    */     //   37: aaload
/*    */     //   38: invokevirtual public : ()Lf/j40;
/*    */     //   41: ifnonnull -> 56
/*    */     //   44: aload_3
/*    */     //   45: getfield FB0 : [Lf/Qv0;
/*    */     //   48: iload #4
/*    */     //   50: aaload
/*    */     //   51: astore #4
/*    */     //   53: goto -> 74
/*    */     //   56: iload #4
/*    */     //   58: iconst_1
/*    */     //   59: iadd
/*    */     //   60: i2s
/*    */     //   61: istore #4
/*    */     //   63: goto -> 24
/*    */     //   66: aload_3
/*    */     //   67: invokevirtual getClass : ()Ljava/lang/Class;
/*    */     //   70: pop
/*    */     //   71: aconst_null
/*    */     //   72: astore #4
/*    */     //   74: aload #4
/*    */     //   76: ifnonnull -> 83
/*    */     //   79: iconst_1
/*    */     //   80: goto -> 84
/*    */     //   83: iconst_0
/*    */     //   84: ifne -> 124
/*    */     //   87: aload_2
/*    */     //   88: new f/Hk0
/*    */     //   91: dup
/*    */     //   92: astore #4
/*    */     //   94: aload_3
/*    */     //   95: aload_0
/*    */     //   96: aload #4
/*    */     //   98: sipush #1117
/*    */     //   101: invokestatic OH0 : (I)Ljava/lang/String;
/*    */     //   104: invokespecial <init> : (Ljava/lang/String;)V
/*    */     //   107: <illegal opcode> run : (Lf/NR;[Lf/Qv0;)Ljava/lang/Runnable;
/*    */     //   112: putfield rv : Ljava/lang/Runnable;
/*    */     //   115: getfield aV : Ljava/util/ArrayList;
/*    */     //   118: aload #4
/*    */     //   120: invokevirtual add : (Ljava/lang/Object;)Z
/*    */     //   123: pop
/*    */     //   124: getstatic f/km.u4 : Lf/R8;
/*    */     //   127: getfield y80 : Lf/Iq0;
/*    */     //   130: getfield K4 : [B
/*    */     //   133: dup
/*    */     //   134: astore_3
/*    */     //   135: arraylength
/*    */     //   136: istore #4
/*    */     //   138: iconst_0
/*    */     //   139: istore #5
/*    */     //   141: iload #5
/*    */     //   143: iload #4
/*    */     //   145: if_icmpge -> 211
/*    */     //   148: iload_1
/*    */     //   149: aload_3
/*    */     //   150: iload #5
/*    */     //   152: baload
/*    */     //   153: dup
/*    */     //   154: istore #6
/*    */     //   156: if_icmpne -> 162
/*    */     //   159: goto -> 205
/*    */     //   162: aload_2
/*    */     //   163: new f/Hk0
/*    */     //   166: dup
/*    */     //   167: astore #7
/*    */     //   169: aload_0
/*    */     //   170: iload #6
/*    */     //   172: aload #7
/*    */     //   174: getstatic f/km.u4 : Lf/R8;
/*    */     //   177: getfield y80 : Lf/Iq0;
/*    */     //   180: iload #6
/*    */     //   182: invokevirtual Kg : (B)Ljava/lang/String;
/*    */     //   185: invokespecial <init> : (Ljava/lang/String;)V
/*    */     //   188: <illegal opcode> run : ([Lf/Qv0;I)Ljava/lang/Runnable;
/*    */     //   193: putfield rv : Ljava/lang/Runnable;
/*    */     //   196: getfield aV : Ljava/util/ArrayList;
/*    */     //   199: aload #7
/*    */     //   201: invokevirtual add : (Ljava/lang/Object;)Z
/*    */     //   204: pop
/*    */     //   205: iinc #5, 1
/*    */     //   208: goto -> 141
/*    */     //   211: aload_2
/*    */     //   212: areturn
/*    */     // Line number table:
/*    */     //   Java source line number -> byte code offset
/*    */     //   #1	-> 14
/*    */     //   #2	-> 17
/*    */     //   #3	-> 32
/*    */     //   #4	-> 37
/*    */     //   #5	-> 67
/*    */     //   #6	-> 88
/*    */     //   #7	-> 112
/*    */     //   #8	-> 115
/*    */     //   #9	-> 124
/*    */     //   #10	-> 127
/*    */     //   #11	-> 130
/*    */     //   #12	-> 135
/*    */     //   #13	-> 177
/*    */     //   #14	-> 182
/*    */     //   #15	-> 193
/*    */     //   #16	-> 196
/*    */   }
/*    */   
/*    */   public static void yC0(JG0 paramJG0, j40 paramj40, short paramShort, int paramInt1, int paramInt2, Runnable paramRunnable) {
/*    */     // Byte code:
/*    */     //   0: getstatic f/km.u4 : Lf/R8;
/*    */     //   3: getfield Tr0 : Lf/Yp0;
/*    */     //   6: dup
/*    */     //   7: astore #6
/*    */     //   9: ifnonnull -> 13
/*    */     //   12: return
/*    */     //   13: iload_2
/*    */     //   14: new f/hu
/*    */     //   17: dup
/*    */     //   18: astore #7
/*    */     //   20: invokespecial <init> : ()V
/*    */     //   23: getstatic f/LF.xL0 : Lf/ik;
/*    */     //   26: pop
/*    */     //   27: sipush #1030
/*    */     //   30: if_icmpne -> 39
/*    */     //   33: iconst_1
/*    */     //   34: istore #8
/*    */     //   36: goto -> 42
/*    */     //   39: iconst_0
/*    */     //   40: istore #8
/*    */     //   42: aload #6
/*    */     //   44: getfield nt0 : Lf/Ut0;
/*    */     //   47: dup
/*    */     //   48: dup
/*    */     //   49: astore #6
/*    */     //   51: getfield ir0 : I
/*    */     //   54: dup
/*    */     //   55: istore #9
/*    */     //   57: anewarray f/HH
/*    */     //   60: astore #10
/*    */     //   62: getfield ND : [Ljava/lang/Object;
/*    */     //   65: dup
/*    */     //   66: astore #11
/*    */     //   68: aload #6
/*    */     //   70: getfield JO : [B
/*    */     //   73: astore #6
/*    */     //   75: arraylength
/*    */     //   76: istore #12
/*    */     //   78: iconst_0
/*    */     //   79: istore #13
/*    */     //   81: iload #12
/*    */     //   83: dup
/*    */     //   84: iconst_m1
/*    */     //   85: iadd
/*    */     //   86: istore #12
/*    */     //   88: ifle -> 124
/*    */     //   91: aload #6
/*    */     //   93: iload #12
/*    */     //   95: baload
/*    */     //   96: iconst_1
/*    */     //   97: if_icmpne -> 81
/*    */     //   100: aload #10
/*    */     //   102: aload #11
/*    */     //   104: iload #13
/*    */     //   106: iconst_1
/*    */     //   107: iadd
/*    */     //   108: istore #14
/*    */     //   110: iload #12
/*    */     //   112: aaload
/*    */     //   113: iload #13
/*    */     //   115: swap
/*    */     //   116: aastore
/*    */     //   117: iload #14
/*    */     //   119: istore #13
/*    */     //   121: goto -> 81
/*    */     //   124: iconst_0
/*    */     //   125: istore #6
/*    */     //   127: iload #6
/*    */     //   129: iload #9
/*    */     //   131: if_icmpge -> 409
/*    */     //   134: iload #8
/*    */     //   136: aload #10
/*    */     //   138: iload #6
/*    */     //   140: aaload
/*    */     //   141: astore #11
/*    */     //   143: ifne -> 166
/*    */     //   146: getstatic f/km.a3 : Lf/vh0;
/*    */     //   149: getfield Ct : Lf/Jo;
/*    */     //   152: getfield Jg : I
/*    */     //   155: aload #11
/*    */     //   157: getfield Ia0 : I
/*    */     //   160: if_icmpne -> 166
/*    */     //   163: goto -> 403
/*    */     //   166: getstatic f/km.a3 : Lf/vh0;
/*    */     //   169: aload #11
/*    */     //   171: getfield Ia0 : I
/*    */     //   174: invokevirtual J7 : (I)Lf/Jo;
/*    */     //   177: dup
/*    */     //   178: astore #12
/*    */     //   180: ifnonnull -> 186
/*    */     //   183: goto -> 403
/*    */     //   186: aload #11
/*    */     //   188: getfield DQ : [Lf/SG0;
/*    */     //   191: dup
/*    */     //   192: astore #11
/*    */     //   194: arraylength
/*    */     //   195: iconst_1
/*    */     //   196: if_icmpne -> 260
/*    */     //   199: aload #11
/*    */     //   201: iconst_0
/*    */     //   202: aaload
/*    */     //   203: dup
/*    */     //   204: astore #11
/*    */     //   206: ifnull -> 403
/*    */     //   209: aload #7
/*    */     //   211: new f/LA0
/*    */     //   214: dup
/*    */     //   215: astore #13
/*    */     //   217: aload_1
/*    */     //   218: iload_2
/*    */     //   219: aload #12
/*    */     //   221: getfield ED0 : Ljava/lang/String;
/*    */     //   224: astore #14
/*    */     //   226: aload #12
/*    */     //   228: aload #11
/*    */     //   230: aload #5
/*    */     //   232: <illegal opcode> run : (Lf/j40;SLf/Jo;Lf/SG0;Ljava/lang/Runnable;)Ljava/lang/Runnable;
/*    */     //   237: astore #11
/*    */     //   239: aload #14
/*    */     //   241: aload #12
/*    */     //   243: aload #11
/*    */     //   245: invokespecial <init> : (Ljava/lang/String;Lf/Jo;Ljava/lang/Runnable;)V
/*    */     //   248: getfield aV : Ljava/util/ArrayList;
/*    */     //   251: aload #13
/*    */     //   253: invokevirtual add : (Ljava/lang/Object;)Z
/*    */     //   256: pop
/*    */     //   257: goto -> 403
/*    */     //   260: aload #11
/*    */     //   262: arraylength
/*    */     //   263: iconst_1
/*    */     //   264: if_icmple -> 403
/*    */     //   267: aload #11
/*    */     //   269: new f/fa0
/*    */     //   272: dup
/*    */     //   273: astore #13
/*    */     //   275: aload #12
/*    */     //   277: invokespecial <init> : (Lf/Jo;)V
/*    */     //   280: arraylength
/*    */     //   281: istore #14
/*    */     //   283: iconst_0
/*    */     //   284: istore #15
/*    */     //   286: iload #15
/*    */     //   288: iload #14
/*    */     //   290: if_icmpge -> 392
/*    */     //   293: aload #13
/*    */     //   295: aload #11
/*    */     //   297: iload #15
/*    */     //   299: aaload
/*    */     //   300: astore #16
/*    */     //   302: invokestatic v30 : ()Lf/On;
/*    */     //   305: aload #16
/*    */     //   307: getfield Im : S
/*    */     //   310: invokevirtual lpT3 : (S)Lf/UD0;
/*    */     //   313: astore #17
/*    */     //   315: new f/vi
/*    */     //   318: dup
/*    */     //   319: astore #18
/*    */     //   321: aload_1
/*    */     //   322: iload_2
/*    */     //   323: aload #17
/*    */     //   325: iconst_0
/*    */     //   326: invokevirtual o60 : (Z)Ljava/lang/String;
/*    */     //   329: astore #19
/*    */     //   331: getstatic f/um0.Kt0 : Lf/um0;
/*    */     //   334: aload #17
/*    */     //   336: getfield AP : S
/*    */     //   339: iconst_0
/*    */     //   340: swap
/*    */     //   341: iconst_0
/*    */     //   342: iconst_0
/*    */     //   343: invokevirtual H9 : (BSZZ)[Lf/zh0;
/*    */     //   346: iconst_0
/*    */     //   347: aaload
/*    */     //   348: astore #17
/*    */     //   350: aload #12
/*    */     //   352: aload #16
/*    */     //   354: aload #5
/*    */     //   356: <illegal opcode> run : (Lf/j40;SLf/Jo;Lf/SG0;Ljava/lang/Runnable;)Ljava/lang/Runnable;
/*    */     //   361: astore #16
/*    */     //   363: aload #19
/*    */     //   365: aload #17
/*    */     //   367: iconst_0
/*    */     //   368: bipush #36
/*    */     //   370: bipush #36
/*    */     //   372: aload #16
/*    */     //   374: invokespecial <init> : (Ljava/lang/String;Lf/zh0;IIILjava/lang/Runnable;)V
/*    */     //   377: getfield aV : Ljava/util/ArrayList;
/*    */     //   380: aload #18
/*    */     //   382: invokevirtual add : (Ljava/lang/Object;)Z
/*    */     //   385: pop
/*    */     //   386: iinc #15, 1
/*    */     //   389: goto -> 286
/*    */     //   392: aload #7
/*    */     //   394: getfield aV : Ljava/util/ArrayList;
/*    */     //   397: aload #13
/*    */     //   399: invokevirtual add : (Ljava/lang/Object;)Z
/*    */     //   402: pop
/*    */     //   403: iinc #6, 1
/*    */     //   406: goto -> 127
/*    */     //   409: aload #7
/*    */     //   411: getfield aV : Ljava/util/ArrayList;
/*    */     //   414: invokevirtual size : ()I
/*    */     //   417: iconst_1
/*    */     //   418: if_icmpge -> 445
/*    */     //   421: aload #7
/*    */     //   423: new f/Hk0
/*    */     //   426: dup
/*    */     //   427: astore_1
/*    */     //   428: sipush #1122
/*    */     //   431: invokestatic OH0 : (I)Ljava/lang/String;
/*    */     //   434: invokespecial <init> : (Ljava/lang/String;)V
/*    */     //   437: getfield aV : Ljava/util/ArrayList;
/*    */     //   440: aload_1
/*    */     //   441: invokevirtual add : (Ljava/lang/Object;)Z
/*    */     //   444: pop
/*    */     //   445: aload #7
/*    */     //   447: aload_0
/*    */     //   448: iload_3
/*    */     //   449: iload #4
/*    */     //   451: invokestatic T1 : (Lf/hu;Lf/JG0;II)V
/*    */     //   454: return
/*    */     // Line number table:
/*    */     //   Java source line number -> byte code offset
/*    */     //   #1	-> 3
/*    */     //   #2	-> 14
/*    */     //   #3	-> 44
/*    */     //   #4	-> 51
/*    */     //   #5	-> 57
/*    */     //   #6	-> 62
/*    */     //   #7	-> 140
/*    */     //   #8	-> 149
/*    */     //   #9	-> 152
/*    */     //   #10	-> 157
/*    */     //   #11	-> 166
/*    */     //   #12	-> 171
/*    */     //   #13	-> 174
/*    */     //   #14	-> 188
/*    */     //   #15	-> 194
/*    */     //   #16	-> 221
/*    */     //   #17	-> 232
/*    */     //   #18	-> 248
/*    */     //   #19	-> 262
/*    */     //   #20	-> 307
/*    */     //   #21	-> 310
/*    */     //   #22	-> 326
/*    */     //   #23	-> 331
/*    */     //   #24	-> 336
/*    */     //   #25	-> 343
/*    */     //   #26	-> 374
/*    */     //   #27	-> 377
/*    */     //   #28	-> 411
/*    */     //   #29	-> 423
/*    */     //   #30	-> 437
/*    */     //   #31	-> 451
/*    */   }
/*    */   
/*    */   public static B3 uN() {
/*    */     this(Ml0.OH0(1125));
/*    */     B3 b3;
/*    */     j40[] arrayOfJ40;
/*    */     int i;
/*    */     byte b;
/*    */     for (i = (arrayOfJ40 = km.u4.s40(aq0.LI).zc0()).length, b = 0; b < i; ) {
/*    */       j40 j40;
/*    */       if ((j40 = arrayOfJ40[b]) != null) {
/*    */         vi vi;
/*    */         short s = j40.Zs.Vf0();
/*    */         byte b1 = j40.s5();
/*    */         this(j40.m(), um0.Kt0.lb(s, j40.Zs.da(), b1)[0], new lS(j40));
/*    */         b3.aV.add(vi);
/*    */       } 
/*    */       b++;
/*    */     } 
/*    */     vh0 vh0;
/*    */     Jo jo;
/*    */     if ((vh0 = km.a3) != null && (jo = vh0.Ct) != null && jo.nX() != 0) {
/*    */       Fn0 fn0;
/*    */       String str = Ml0.OH0(2256);
/*    */       this();
/*    */       b3.mD(str, fn0);
/*    */     } 
/*    */     return b3;
/*    */   }
/*    */   
/*    */   public final void LM(throws paramthrows) {
/*    */     if (km.XU())
/*    */       paramthrows.xr.K90(new YG(new O4(this))); 
/*    */   }
/*    */   
/*    */   public final void xf() {
/*    */     if (this.hw == null) {
/*    */       (this.hw = new Tv0(this.mw)).wI0(false);
/*    */       Tv0 tv0 = this.hw;
/*    */       si(tv0, Ub());
/*    */       this.hw.uW();
/*    */     } 
/*    */     this.hw.ml0(this.hw.dP ^ true);
/*    */   }
/*    */   
/*    */   public final void Ih0(Qa0 paramQa0) {
/*    */     if (this.ye.mB(paramQa0, true))
/*    */       return; 
/*    */     this.ye.Com3(paramQa0);
/*    */   }
/*    */   
/*    */   public final boolean B5() {
/*    */     boolean bool;
/*    */     Pw pw;
/*    */     if (km.XU() && ((pw = this.bk).K00 != null || pw.eO != null))
/*    */       return true; 
/*    */     fQ fQ1;
/*    */     if ((fQ1 = this.ye).Z8 == 0)
/*    */       return false; 
/*    */     Qa0 qa0;
/*    */     I i;
/*    */     if ((i = (qa0 = (Qa0)peek()).db0) != null && i.en) {
/*    */       bool = true;
/*    */     } else {
/*    */       bool = false;
/*    */     } 
/*    */     if (bool || !vB0())
/*    */       return false; 
/*    */     return true;
/*    */   }
/*    */   
/*    */   public final boolean i2(oa0 paramoa0) {
/*    */     // Byte code:
/*    */     //   0: invokestatic XU : ()Z
/*    */     //   3: ifeq -> 59
/*    */     //   6: aload_1
/*    */     //   7: getfield cz0 : I
/*    */     //   10: dup
/*    */     //   11: istore_2
/*    */     //   12: invokestatic Pg : (I)Z
/*    */     //   15: ifeq -> 59
/*    */     //   18: iload_2
/*    */     //   19: iconst_3
/*    */     //   20: if_icmpne -> 59
/*    */     //   23: getstatic f/km.kH0 : Lf/Qz0;
/*    */     //   26: invokevirtual xy0 : ()Z
/*    */     //   29: ifeq -> 59
/*    */     //   32: getstatic f/km.kH0 : Lf/Qz0;
/*    */     //   35: getfield D1 : Lf/fQ;
/*    */     //   38: dup
/*    */     //   39: astore_0
/*    */     //   40: getfield Z8 : I
/*    */     //   43: ifeq -> 57
/*    */     //   46: aload_0
/*    */     //   47: invokevirtual peek : ()Ljava/lang/Object;
/*    */     //   50: checkcast f/hO
/*    */     //   53: invokevirtual Cs0 : ()Z
/*    */     //   56: pop
/*    */     //   57: iconst_1
/*    */     //   58: ireturn
/*    */     //   59: aload_1
/*    */     //   60: getfield cz0 : I
/*    */     //   63: invokestatic Wm0 : (I)Z
/*    */     //   66: ifeq -> 111
/*    */     //   69: aload_1
/*    */     //   70: invokevirtual oO : ()Z
/*    */     //   73: ifeq -> 111
/*    */     //   76: aload_0
/*    */     //   77: getfield Dj0 : Lf/Wx;
/*    */     //   80: ifnull -> 111
/*    */     //   83: aload_1
/*    */     //   84: getfield GG0 : I
/*    */     //   87: getstatic f/BM.eH0 : Lf/BM;
/*    */     //   90: invokestatic J20 : (ILf/BM;)Z
/*    */     //   93: ifeq -> 111
/*    */     //   96: aload_0
/*    */     //   97: getfield Dj0 : Lf/Wx;
/*    */     //   100: dup
/*    */     //   101: getfield dP : Z
/*    */     //   104: iconst_1
/*    */     //   105: ixor
/*    */     //   106: invokevirtual wI0 : (Z)V
/*    */     //   109: iconst_1
/*    */     //   110: ireturn
/*    */     //   111: getstatic f/Bz.fn : Z
/*    */     //   114: ifeq -> 214
/*    */     //   117: aload_1
/*    */     //   118: getfield cz0 : I
/*    */     //   121: invokestatic Wm0 : (I)Z
/*    */     //   124: ifeq -> 214
/*    */     //   127: aload_1
/*    */     //   128: invokevirtual oO : ()Z
/*    */     //   131: ifeq -> 214
/*    */     //   134: aload_1
/*    */     //   135: getfield com8 : I
/*    */     //   138: iconst_4
/*    */     //   139: if_icmpne -> 214
/*    */     //   142: aload_1
/*    */     //   143: getfield GG0 : I
/*    */     //   146: bipush #62
/*    */     //   148: if_icmpne -> 214
/*    */     //   151: aload_0
/*    */     //   152: getfield SQ : Lf/su0;
/*    */     //   155: dup
/*    */     //   156: astore_1
/*    */     //   157: ifnull -> 169
/*    */     //   160: aload_1
/*    */     //   161: getfield fr0 : Lf/JG0;
/*    */     //   164: ifnull -> 169
/*    */     //   167: iconst_1
/*    */     //   168: ireturn
/*    */     //   169: aload_0
/*    */     //   170: dup
/*    */     //   171: dup
/*    */     //   172: dup2
/*    */     //   173: new f/su0
/*    */     //   176: dup
/*    */     //   177: dup
/*    */     //   178: astore_0
/*    */     //   179: invokespecial <init> : ()V
/*    */     //   182: putfield SQ : Lf/su0;
/*    */     //   185: invokevirtual Ub : ()I
/*    */     //   188: aload_0
/*    */     //   189: swap
/*    */     //   190: invokevirtual si : (Lf/JG0;I)V
/*    */     //   193: getfield SQ : Lf/su0;
/*    */     //   196: invokevirtual mM : ()V
/*    */     //   199: getfield SQ : Lf/su0;
/*    */     //   202: getstatic f/et.Wi0 : Lf/et;
/*    */     //   205: iconst_0
/*    */     //   206: sipush #200
/*    */     //   209: invokevirtual QJ0 : (Lf/et;II)V
/*    */     //   212: iconst_1
/*    */     //   213: ireturn
/*    */     //   214: getstatic f/Bz.fn : Z
/*    */     //   217: ifeq -> 353
/*    */     //   220: aload_1
/*    */     //   221: getfield cz0 : I
/*    */     //   224: invokestatic Wm0 : (I)Z
/*    */     //   227: ifeq -> 353
/*    */     //   230: aload_1
/*    */     //   231: invokevirtual oO : ()Z
/*    */     //   234: ifeq -> 353
/*    */     //   237: aload_1
/*    */     //   238: getfield GG0 : I
/*    */     //   241: bipush #68
/*    */     //   243: if_icmpne -> 353
/*    */     //   246: aload_0
/*    */     //   247: getfield ht : Lf/mk;
/*    */     //   250: dup
/*    */     //   251: astore_1
/*    */     //   252: getfield dP : Z
/*    */     //   255: ifeq -> 299
/*    */     //   258: aload_0
/*    */     //   259: dup
/*    */     //   260: aload_1
/*    */     //   261: getfield Nx : Lf/jF;
/*    */     //   264: invokevirtual xI0 : ()V
/*    */     //   267: getfield ht : Lf/mk;
/*    */     //   270: getfield db0 : Lf/I;
/*    */     //   273: sipush #200
/*    */     //   276: invokevirtual oC0 : (I)V
/*    */     //   279: getfield ht : Lf/mk;
/*    */     //   282: getfield db0 : Lf/I;
/*    */     //   285: new f/oP
/*    */     //   288: dup
/*    */     //   289: aload_0
/*    */     //   290: invokespecial <init> : (Lf/js;)V
/*    */     //   293: invokevirtual md : (Ljava/lang/Runnable;)V
/*    */     //   296: goto -> 351
/*    */     //   299: aload_0
/*    */     //   300: dup
/*    */     //   301: dup
/*    */     //   302: aload_1
/*    */     //   303: iconst_1
/*    */     //   304: invokevirtual wI0 : (Z)V
/*    */     //   307: getfield ht : Lf/mk;
/*    */     //   310: getfield db0 : Lf/I;
/*    */     //   313: getstatic f/pRn.TRANSPARENT : Lf/pRn;
/*    */     //   316: invokevirtual Ix : (Lf/pRn;)V
/*    */     //   319: getfield ht : Lf/mk;
/*    */     //   322: getfield db0 : Lf/I;
/*    */     //   325: getstatic f/pRn.WHITE : Lf/pRn;
/*    */     //   328: sipush #200
/*    */     //   331: invokevirtual sz : (Lf/pRn;I)V
/*    */     //   334: getfield ht : Lf/mk;
/*    */     //   337: getfield db0 : Lf/I;
/*    */     //   340: new f/hB
/*    */     //   343: dup
/*    */     //   344: aload_0
/*    */     //   345: invokespecial <init> : (Lf/js;)V
/*    */     //   348: invokevirtual md : (Ljava/lang/Runnable;)V
/*    */     //   351: iconst_1
/*    */     //   352: ireturn
/*    */     //   353: getstatic f/km.a3 : Lf/vh0;
/*    */     //   356: dup
/*    */     //   357: astore_2
/*    */     //   358: ifnull -> 2419
/*    */     //   361: aload_2
/*    */     //   362: getfield Ct : Lf/Jo;
/*    */     //   365: ifnull -> 2419
/*    */     //   368: aload_1
/*    */     //   369: getfield cz0 : I
/*    */     //   372: invokestatic Pg : (I)Z
/*    */     //   375: ifeq -> 840
/*    */     //   378: aload_1
/*    */     //   379: getfield vl : I
/*    */     //   382: dup
/*    */     //   383: istore_2
/*    */     //   384: ifeq -> 392
/*    */     //   387: iload_2
/*    */     //   388: iconst_1
/*    */     //   389: if_icmpne -> 685
/*    */     //   392: aload_1
/*    */     //   393: getfield aK : I
/*    */     //   396: aload_0
/*    */     //   397: getfield bk : Lf/Pw;
/*    */     //   400: invokevirtual dG : ()I
/*    */     //   403: if_icmpge -> 685
/*    */     //   406: aload_1
/*    */     //   407: getfield gk0 : I
/*    */     //   410: aload_0
/*    */     //   411: getfield bk : Lf/Pw;
/*    */     //   414: invokevirtual k1 : ()I
/*    */     //   417: bipush #50
/*    */     //   419: isub
/*    */     //   420: if_icmpge -> 685
/*    */     //   423: aload_0
/*    */     //   424: getfield Li0 : Lf/d10;
/*    */     //   427: dup
/*    */     //   428: astore_2
/*    */     //   429: ifnull -> 466
/*    */     //   432: aload_2
/*    */     //   433: invokevirtual r30 : ()Lf/Hc0;
/*    */     //   436: astore_2
/*    */     //   437: aload_2
/*    */     //   438: invokevirtual hasNext : ()Z
/*    */     //   441: ifeq -> 466
/*    */     //   444: aload_2
/*    */     //   445: invokevirtual next : ()Ljava/lang/Object;
/*    */     //   448: checkcast f/JG0
/*    */     //   451: dup
/*    */     //   452: astore_3
/*    */     //   453: invokevirtual p3 : ()Z
/*    */     //   456: ifeq -> 437
/*    */     //   459: aload_3
/*    */     //   460: invokevirtual xI0 : ()V
/*    */     //   463: goto -> 437
/*    */     //   466: aload_0
/*    */     //   467: getfield bk : Lf/Pw;
/*    */     //   470: getfield K7 : Lf/Wl;
/*    */     //   473: dup
/*    */     //   474: astore_2
/*    */     //   475: ifnull -> 685
/*    */     //   478: aload_2
/*    */     //   479: getfield LW : Lf/kf;
/*    */     //   482: dup
/*    */     //   483: astore_2
/*    */     //   484: ifnull -> 685
/*    */     //   487: aload_2
/*    */     //   488: getfield rB : Lf/c90;
/*    */     //   491: dup
/*    */     //   492: astore_3
/*    */     //   493: ifnull -> 504
/*    */     //   496: aload_3
/*    */     //   497: getfield oV : [Lf/j90;
/*    */     //   500: astore_3
/*    */     //   501: goto -> 506
/*    */     //   504: aconst_null
/*    */     //   505: astore_3
/*    */     //   506: aload_3
/*    */     //   507: ifnull -> 685
/*    */     //   510: aload_0
/*    */     //   511: aload_1
/*    */     //   512: dup
/*    */     //   513: iconst_0
/*    */     //   514: istore #4
/*    */     //   516: getfield aK : I
/*    */     //   519: istore #5
/*    */     //   521: getfield gk0 : I
/*    */     //   524: istore #6
/*    */     //   526: getfield Li0 : Lf/d10;
/*    */     //   529: dup
/*    */     //   530: astore #7
/*    */     //   532: ifnull -> 600
/*    */     //   535: aload_0
/*    */     //   536: aload #7
/*    */     //   538: invokevirtual Jv0 : ()[Ljava/lang/Object;
/*    */     //   541: checkcast [Lf/JG0;
/*    */     //   544: astore #7
/*    */     //   546: getfield Li0 : Lf/d10;
/*    */     //   549: getfield Z8 : I
/*    */     //   552: istore #8
/*    */     //   554: iload #8
/*    */     //   556: dup
/*    */     //   557: iconst_m1
/*    */     //   558: iadd
/*    */     //   559: istore #8
/*    */     //   561: ifle -> 593
/*    */     //   564: aload #7
/*    */     //   566: iload #8
/*    */     //   568: aaload
/*    */     //   569: dup
/*    */     //   570: astore #9
/*    */     //   572: getfield dP : Z
/*    */     //   575: ifeq -> 554
/*    */     //   578: aload #9
/*    */     //   580: iload #5
/*    */     //   582: iload #6
/*    */     //   584: invokevirtual mu0 : (II)Z
/*    */     //   587: ifeq -> 554
/*    */     //   590: goto -> 603
/*    */     //   593: aload_0
/*    */     //   594: getfield Li0 : Lf/d10;
/*    */     //   597: invokevirtual At0 : ()V
/*    */     //   600: aconst_null
/*    */     //   601: astore #9
/*    */     //   603: aload #9
/*    */     //   605: ifnull -> 646
/*    */     //   608: aload_3
/*    */     //   609: arraylength
/*    */     //   610: istore #5
/*    */     //   612: iconst_0
/*    */     //   613: istore #6
/*    */     //   615: iload #6
/*    */     //   617: iload #5
/*    */     //   619: if_icmpge -> 646
/*    */     //   622: aload #9
/*    */     //   624: aload_3
/*    */     //   625: iload #6
/*    */     //   627: aaload
/*    */     //   628: invokevirtual Ji0 : (Lf/JG0;)Z
/*    */     //   631: ifeq -> 640
/*    */     //   634: iconst_1
/*    */     //   635: istore #4
/*    */     //   637: goto -> 646
/*    */     //   640: iinc #6, 1
/*    */     //   643: goto -> 615
/*    */     //   646: iload #4
/*    */     //   648: ifne -> 685
/*    */     //   651: aload_2
/*    */     //   652: getfield rB : Lf/c90;
/*    */     //   655: dup
/*    */     //   656: astore_3
/*    */     //   657: ifnull -> 685
/*    */     //   660: aload_3
/*    */     //   661: getfield nu : Z
/*    */     //   664: ifne -> 685
/*    */     //   667: aload_2
/*    */     //   668: dup
/*    */     //   669: dup
/*    */     //   670: aload_3
/*    */     //   671: invokevirtual jf0 : (Lf/JG0;)Z
/*    */     //   674: pop
/*    */     //   675: getfield rB : Lf/c90;
/*    */     //   678: invokevirtual dispose : ()V
/*    */     //   681: aconst_null
/*    */     //   682: putfield rB : Lf/c90;
/*    */     //   685: invokestatic Nr : ()Z
/*    */     //   688: ifeq -> 797
/*    */     //   691: aload_1
/*    */     //   692: getfield vl : I
/*    */     //   695: iconst_1
/*    */     //   696: if_icmpne -> 797
/*    */     //   699: aload_1
/*    */     //   700: getfield cz0 : I
/*    */     //   703: iconst_3
/*    */     //   704: if_icmpne -> 797
/*    */     //   707: invokestatic hS : ()Z
/*    */     //   710: ifeq -> 766
/*    */     //   713: getstatic f/km.wI0 : Lf/Pw;
/*    */     //   716: getfield iJ0 : Lf/Xi;
/*    */     //   719: dup
/*    */     //   720: astore_2
/*    */     //   721: ifnull -> 797
/*    */     //   724: aload_2
/*    */     //   725: invokevirtual UB0 : ()Lf/ny;
/*    */     //   728: ifnull -> 797
/*    */     //   731: aload_0
/*    */     //   732: aload_1
/*    */     //   733: dup
/*    */     //   734: aload_2
/*    */     //   735: dup
/*    */     //   736: getfield wN : Lf/fQ;
/*    */     //   739: astore_2
/*    */     //   740: invokevirtual UB0 : ()Lf/ny;
/*    */     //   743: astore_3
/*    */     //   744: getfield aK : I
/*    */     //   747: istore #4
/*    */     //   749: getfield gk0 : I
/*    */     //   752: istore #5
/*    */     //   754: aload_2
/*    */     //   755: aload_3
/*    */     //   756: iload #4
/*    */     //   758: iload #5
/*    */     //   760: invokevirtual mA0 : (Lf/fQ;Lf/ny;II)V
/*    */     //   763: goto -> 797
/*    */     //   766: aload_0
/*    */     //   767: aload_1
/*    */     //   768: dup
/*    */     //   769: getstatic f/km.a3 : Lf/vh0;
/*    */     //   772: invokevirtual getClass : ()Ljava/lang/Class;
/*    */     //   775: pop
/*    */     //   776: invokestatic Sh0 : ()Ljava/util/ArrayList;
/*    */     //   779: astore_2
/*    */     //   780: getfield aK : I
/*    */     //   783: istore_3
/*    */     //   784: getfield gk0 : I
/*    */     //   787: istore #4
/*    */     //   789: iconst_1
/*    */     //   790: aload_2
/*    */     //   791: iload_3
/*    */     //   792: iload #4
/*    */     //   794: invokevirtual s8 : (ZLjava/util/ArrayList;II)V
/*    */     //   797: aload_1
/*    */     //   798: getfield cz0 : I
/*    */     //   801: bipush #8
/*    */     //   803: if_icmpne -> 840
/*    */     //   806: aload_1
/*    */     //   807: getfield com8 : I
/*    */     //   810: iconst_1
/*    */     //   811: if_icmpne -> 840
/*    */     //   814: iconst_3
/*    */     //   815: invokestatic D70 : (I)Z
/*    */     //   818: ifeq -> 840
/*    */     //   821: aload_0
/*    */     //   822: getfield bk : Lf/Pw;
/*    */     //   825: getfield iJ0 : Lf/Xi;
/*    */     //   828: aload_1
/*    */     //   829: getfield kB0 : I
/*    */     //   832: i2d
/*    */     //   833: ldc2_w 5.0
/*    */     //   836: ddiv
/*    */     //   837: invokevirtual CH : (D)V
/*    */     //   840: aload_1
/*    */     //   841: getfield cz0 : I
/*    */     //   844: invokestatic Wm0 : (I)Z
/*    */     //   847: ifeq -> 2424
/*    */     //   850: aload_1
/*    */     //   851: invokevirtual oO : ()Z
/*    */     //   854: ifeq -> 2424
/*    */     //   857: getstatic f/ro.l10 : B
/*    */     //   860: ifle -> 1249
/*    */     //   863: getstatic f/wJ0.Nf0 : Lf/wJ0;
/*    */     //   866: dup
/*    */     //   867: astore_2
/*    */     //   868: getfield NuL : J
/*    */     //   871: getstatic f/zm0.u20 : J
/*    */     //   874: dup2
/*    */     //   875: lstore_3
/*    */     //   876: lcmp
/*    */     //   877: ifle -> 883
/*    */     //   880: goto -> 916
/*    */     //   883: lload_3
/*    */     //   884: aload_2
/*    */     //   885: getfield rs : J
/*    */     //   888: lsub
/*    */     //   889: aload_2
/*    */     //   890: getfield Gb : I
/*    */     //   893: i2l
/*    */     //   894: lcmp
/*    */     //   895: ifle -> 916
/*    */     //   898: lload_3
/*    */     //   899: aload_2
/*    */     //   900: getfield vM : J
/*    */     //   903: lsub
/*    */     //   904: bipush #100
/*    */     //   906: i2l
/*    */     //   907: lcmp
/*    */     //   908: ifle -> 916
/*    */     //   911: iconst_1
/*    */     //   912: istore_3
/*    */     //   913: goto -> 918
/*    */     //   916: iconst_0
/*    */     //   917: istore_3
/*    */     //   918: iload_3
/*    */     //   919: ifeq -> 1249
/*    */     //   922: getstatic f/km.a3 : Lf/vh0;
/*    */     //   925: dup
/*    */     //   926: getfield Ct : Lf/Jo;
/*    */     //   929: getfield HW : Lf/G5;
/*    */     //   932: dup
/*    */     //   933: getfield mm : S
/*    */     //   936: aload_2
/*    */     //   937: getfield uY : S
/*    */     //   940: iadd
/*    */     //   941: istore_0
/*    */     //   942: getfield Yu0 : S
/*    */     //   945: aload_2
/*    */     //   946: getfield Dk : S
/*    */     //   949: iadd
/*    */     //   950: istore_3
/*    */     //   951: invokevirtual Jr0 : ()Lf/KI;
/*    */     //   954: getfield Fk0 : I
/*    */     //   957: istore #4
/*    */     //   959: getstatic f/km.a3 : Lf/vh0;
/*    */     //   962: invokevirtual Jr0 : ()Lf/KI;
/*    */     //   965: getfield nT : I
/*    */     //   968: istore #5
/*    */     //   970: getstatic f/ro.l10 : B
/*    */     //   973: dup
/*    */     //   974: istore #6
/*    */     //   976: iconst_1
/*    */     //   977: if_icmpne -> 1023
/*    */     //   980: aload_1
/*    */     //   981: getfield GG0 : I
/*    */     //   984: getstatic f/BM.bC : Lf/BM;
/*    */     //   987: invokestatic J20 : (ILf/BM;)Z
/*    */     //   990: ifeq -> 1067
/*    */     //   993: getstatic f/km.u4 : Lf/R8;
/*    */     //   996: getstatic f/ro.eL : S
/*    */     //   999: istore_1
/*    */     //   1000: getfield e20 : Lf/c4;
/*    */     //   1003: new f/l50
/*    */     //   1006: dup
/*    */     //   1007: iload_3
/*    */     //   1008: iload_0
/*    */     //   1009: i2b
/*    */     //   1010: istore_0
/*    */     //   1011: i2b
/*    */     //   1012: iload_0
/*    */     //   1013: swap
/*    */     //   1014: iload_1
/*    */     //   1015: invokespecial <init> : (BBS)V
/*    */     //   1018: invokevirtual W3 : (Lf/Bi;)V
/*    */     //   1021: iconst_1
/*    */     //   1022: ireturn
/*    */     //   1023: iload #6
/*    */     //   1025: iconst_2
/*    */     //   1026: if_icmpne -> 1067
/*    */     //   1029: aload_1
/*    */     //   1030: getfield GG0 : I
/*    */     //   1033: getstatic f/BM.bC : Lf/BM;
/*    */     //   1036: invokestatic J20 : (ILf/BM;)Z
/*    */     //   1039: ifeq -> 1067
/*    */     //   1042: getstatic f/km.u4 : Lf/R8;
/*    */     //   1045: getfield e20 : Lf/c4;
/*    */     //   1048: new f/ku
/*    */     //   1051: dup
/*    */     //   1052: iload_3
/*    */     //   1053: iload_0
/*    */     //   1054: i2b
/*    */     //   1055: istore_0
/*    */     //   1056: i2b
/*    */     //   1057: iload_0
/*    */     //   1058: swap
/*    */     //   1059: invokespecial <init> : (BB)V
/*    */     //   1062: invokevirtual W3 : (Lf/Bi;)V
/*    */     //   1065: iconst_1
/*    */     //   1066: ireturn
/*    */     //   1067: aload_1
/*    */     //   1068: getfield GG0 : I
/*    */     //   1071: getstatic f/BM.lc : Lf/BM;
/*    */     //   1074: invokestatic J20 : (ILf/BM;)Z
/*    */     //   1077: ifeq -> 1086
/*    */     //   1080: iconst_0
/*    */     //   1081: putstatic f/ro.l10 : B
/*    */     //   1084: iconst_1
/*    */     //   1085: ireturn
/*    */     //   1086: aload_1
/*    */     //   1087: getfield GG0 : I
/*    */     //   1090: getstatic f/BM.ni : Lf/BM;
/*    */     //   1093: invokestatic J20 : (ILf/BM;)Z
/*    */     //   1096: ifeq -> 1125
/*    */     //   1099: iload_3
/*    */     //   1100: ifne -> 1105
/*    */     //   1103: iconst_0
/*    */     //   1104: ireturn
/*    */     //   1105: aload_2
/*    */     //   1106: iconst_1
/*    */     //   1107: anewarray f/nl
/*    */     //   1110: dup
/*    */     //   1111: astore_0
/*    */     //   1112: getstatic f/nl.O3 : Lf/nl;
/*    */     //   1115: iconst_0
/*    */     //   1116: swap
/*    */     //   1117: aastore
/*    */     //   1118: aload_0
/*    */     //   1119: invokevirtual rq : ([Lf/nl;)V
/*    */     //   1122: goto -> 1247
/*    */     //   1125: aload_1
/*    */     //   1126: getfield GG0 : I
/*    */     //   1129: getstatic f/BM.N70 : Lf/BM;
/*    */     //   1132: invokestatic J20 : (ILf/BM;)Z
/*    */     //   1135: ifeq -> 1168
/*    */     //   1138: iload_3
/*    */     //   1139: iload #5
/*    */     //   1141: iconst_1
/*    */     //   1142: isub
/*    */     //   1143: if_icmplt -> 1148
/*    */     //   1146: iconst_0
/*    */     //   1147: ireturn
/*    */     //   1148: aload_2
/*    */     //   1149: iconst_1
/*    */     //   1150: anewarray f/nl
/*    */     //   1153: dup
/*    */     //   1154: astore_0
/*    */     //   1155: getstatic f/nl.hI : Lf/nl;
/*    */     //   1158: iconst_0
/*    */     //   1159: swap
/*    */     //   1160: aastore
/*    */     //   1161: aload_0
/*    */     //   1162: invokevirtual rq : ([Lf/nl;)V
/*    */     //   1165: goto -> 1247
/*    */     //   1168: aload_1
/*    */     //   1169: getfield GG0 : I
/*    */     //   1172: getstatic f/BM.Oq : Lf/BM;
/*    */     //   1175: invokestatic J20 : (ILf/BM;)Z
/*    */     //   1178: ifeq -> 1207
/*    */     //   1181: iload_0
/*    */     //   1182: ifne -> 1187
/*    */     //   1185: iconst_0
/*    */     //   1186: ireturn
/*    */     //   1187: aload_2
/*    */     //   1188: iconst_1
/*    */     //   1189: anewarray f/nl
/*    */     //   1192: dup
/*    */     //   1193: astore_0
/*    */     //   1194: getstatic f/nl.cb0 : Lf/nl;
/*    */     //   1197: iconst_0
/*    */     //   1198: swap
/*    */     //   1199: aastore
/*    */     //   1200: aload_0
/*    */     //   1201: invokevirtual rq : ([Lf/nl;)V
/*    */     //   1204: goto -> 1247
/*    */     //   1207: aload_1
/*    */     //   1208: getfield GG0 : I
/*    */     //   1211: getstatic f/BM.M8 : Lf/BM;
/*    */     //   1214: invokestatic J20 : (ILf/BM;)Z
/*    */     //   1217: ifeq -> 1247
/*    */     //   1220: iload_0
/*    */     //   1221: iload #4
/*    */     //   1223: iconst_1
/*    */     //   1224: isub
/*    */     //   1225: if_icmplt -> 1230
/*    */     //   1228: iconst_0
/*    */     //   1229: ireturn
/*    */     //   1230: aload_2
/*    */     //   1231: iconst_1
/*    */     //   1232: anewarray f/nl
/*    */     //   1235: dup
/*    */     //   1236: astore_0
/*    */     //   1237: getstatic f/nl.KB0 : Lf/nl;
/*    */     //   1240: iconst_0
/*    */     //   1241: swap
/*    */     //   1242: aastore
/*    */     //   1243: aload_0
/*    */     //   1244: invokevirtual rq : ([Lf/nl;)V
/*    */     //   1247: iconst_1
/*    */     //   1248: ireturn
/*    */     //   1249: aload_1
/*    */     //   1250: getfield GG0 : I
/*    */     //   1253: getstatic f/BM.bC : Lf/BM;
/*    */     //   1256: invokestatic J20 : (ILf/BM;)Z
/*    */     //   1259: ifne -> 1327
/*    */     //   1262: aload_1
/*    */     //   1263: getfield GG0 : I
/*    */     //   1266: getstatic f/BM.lc : Lf/BM;
/*    */     //   1269: invokestatic J20 : (ILf/BM;)Z
/*    */     //   1272: ifne -> 1327
/*    */     //   1275: aload_1
/*    */     //   1276: getfield GG0 : I
/*    */     //   1279: getstatic f/BM.ni : Lf/BM;
/*    */     //   1282: invokestatic J20 : (ILf/BM;)Z
/*    */     //   1285: ifne -> 1327
/*    */     //   1288: aload_1
/*    */     //   1289: getfield GG0 : I
/*    */     //   1292: getstatic f/BM.N70 : Lf/BM;
/*    */     //   1295: invokestatic J20 : (ILf/BM;)Z
/*    */     //   1298: ifne -> 1327
/*    */     //   1301: aload_1
/*    */     //   1302: getfield GG0 : I
/*    */     //   1305: getstatic f/BM.Oq : Lf/BM;
/*    */     //   1308: invokestatic J20 : (ILf/BM;)Z
/*    */     //   1311: ifne -> 1327
/*    */     //   1314: aload_1
/*    */     //   1315: getfield GG0 : I
/*    */     //   1318: getstatic f/BM.M8 : Lf/BM;
/*    */     //   1321: invokestatic J20 : (ILf/BM;)Z
/*    */     //   1324: ifeq -> 1424
/*    */     //   1327: aload_0
/*    */     //   1328: getfield MH0 : Lf/pA;
/*    */     //   1331: dup
/*    */     //   1332: astore_2
/*    */     //   1333: ifnull -> 1424
/*    */     //   1336: aload_2
/*    */     //   1337: getfield TF : Lf/wu;
/*    */     //   1340: getfield b00 : Lf/of;
/*    */     //   1343: invokevirtual p3 : ()Z
/*    */     //   1346: ifne -> 1424
/*    */     //   1349: aload_0
/*    */     //   1350: getfield hW : Lf/Qz0;
/*    */     //   1353: dup
/*    */     //   1354: astore_2
/*    */     //   1355: aload_1
/*    */     //   1356: getfield GG0 : I
/*    */     //   1359: istore_3
/*    */     //   1360: getfield D1 : Lf/fQ;
/*    */     //   1363: dup
/*    */     //   1364: astore #4
/*    */     //   1366: getfield Z8 : I
/*    */     //   1369: ifeq -> 1387
/*    */     //   1372: aload #4
/*    */     //   1374: invokevirtual peek : ()Ljava/lang/Object;
/*    */     //   1377: checkcast f/hO
/*    */     //   1380: iload_3
/*    */     //   1381: invokevirtual RW : (I)Z
/*    */     //   1384: goto -> 1419
/*    */     //   1387: aload_2
/*    */     //   1388: getfield Ot : Lf/js;
/*    */     //   1391: getfield MH0 : Lf/pA;
/*    */     //   1394: dup
/*    */     //   1395: astore_2
/*    */     //   1396: ifnull -> 1418
/*    */     //   1399: aload_2
/*    */     //   1400: getfield er0 : Lf/XF;
/*    */     //   1403: dup
/*    */     //   1404: astore_2
/*    */     //   1405: ifnull -> 1418
/*    */     //   1408: aload_2
/*    */     //   1409: iload_3
/*    */     //   1410: invokevirtual Op : (I)Z
/*    */     //   1413: pop
/*    */     //   1414: iconst_1
/*    */     //   1415: goto -> 1419
/*    */     //   1418: iconst_0
/*    */     //   1419: ifeq -> 1424
/*    */     //   1422: iconst_1
/*    */     //   1423: ireturn
/*    */     //   1424: aload_0
/*    */     //   1425: aload_1
/*    */     //   1426: invokespecial i2 : (Lf/oa0;)Z
/*    */     //   1429: ifeq -> 1434
/*    */     //   1432: iconst_1
/*    */     //   1433: ireturn
/*    */     //   1434: aload_0
/*    */     //   1435: getfield BA : Lf/kf;
/*    */     //   1438: dup
/*    */     //   1439: astore_2
/*    */     //   1440: ifnull -> 1453
/*    */     //   1443: aload_2
/*    */     //   1444: aload_1
/*    */     //   1445: invokevirtual i2 : (Lf/oa0;)Z
/*    */     //   1448: ifeq -> 1453
/*    */     //   1451: iconst_1
/*    */     //   1452: ireturn
/*    */     //   1453: aload_0
/*    */     //   1454: getfield iV : Lf/FO;
/*    */     //   1457: dup
/*    */     //   1458: astore_2
/*    */     //   1459: ifnull -> 1472
/*    */     //   1462: aload_2
/*    */     //   1463: aload_1
/*    */     //   1464: invokevirtual i2 : (Lf/oa0;)Z
/*    */     //   1467: ifeq -> 1472
/*    */     //   1470: iconst_1
/*    */     //   1471: ireturn
/*    */     //   1472: aload_1
/*    */     //   1473: getfield GG0 : I
/*    */     //   1476: dup
/*    */     //   1477: istore_2
/*    */     //   1478: bipush #66
/*    */     //   1480: if_icmpeq -> 1535
/*    */     //   1483: iload_2
/*    */     //   1484: bipush #111
/*    */     //   1486: if_icmpeq -> 1492
/*    */     //   1489: goto -> 1605
/*    */     //   1492: aload_0
/*    */     //   1493: getfield Li0 : Lf/d10;
/*    */     //   1496: dup
/*    */     //   1497: astore_2
/*    */     //   1498: ifnull -> 1605
/*    */     //   1501: aload_2
/*    */     //   1502: invokevirtual r30 : ()Lf/Hc0;
/*    */     //   1505: astore_2
/*    */     //   1506: aload_2
/*    */     //   1507: invokevirtual hasNext : ()Z
/*    */     //   1510: ifeq -> 1605
/*    */     //   1513: aload_2
/*    */     //   1514: invokevirtual next : ()Ljava/lang/Object;
/*    */     //   1517: checkcast f/JG0
/*    */     //   1520: dup
/*    */     //   1521: astore_3
/*    */     //   1522: invokevirtual p3 : ()Z
/*    */     //   1525: ifeq -> 1506
/*    */     //   1528: aload_3
/*    */     //   1529: invokevirtual xI0 : ()V
/*    */     //   1532: goto -> 1506
/*    */     //   1535: aload_1
/*    */     //   1536: getfield com8 : I
/*    */     //   1539: dup
/*    */     //   1540: istore_2
/*    */     //   1541: iconst_1
/*    */     //   1542: if_icmpne -> 1557
/*    */     //   1545: aload_0
/*    */     //   1546: getfield MH0 : Lf/pA;
/*    */     //   1549: getfield TF : Lf/wu;
/*    */     //   1552: invokevirtual oh : ()V
/*    */     //   1555: iconst_1
/*    */     //   1556: ireturn
/*    */     //   1557: iload_2
/*    */     //   1558: ifne -> 1605
/*    */     //   1561: aload_0
/*    */     //   1562: invokestatic RS : (Lf/JG0;)Z
/*    */     //   1565: ifne -> 1605
/*    */     //   1568: aload_0
/*    */     //   1569: getfield MH0 : Lf/pA;
/*    */     //   1572: getfield TF : Lf/wu;
/*    */     //   1575: dup
/*    */     //   1576: astore_2
/*    */     //   1577: getfield b00 : Lf/of;
/*    */     //   1580: invokevirtual p3 : ()Z
/*    */     //   1583: ifeq -> 1591
/*    */     //   1586: iconst_0
/*    */     //   1587: istore_2
/*    */     //   1588: goto -> 1599
/*    */     //   1591: aload_2
/*    */     //   1592: getfield b00 : Lf/of;
/*    */     //   1595: invokestatic c90 : (Lf/JG0;)Z
/*    */     //   1598: istore_2
/*    */     //   1599: iload_2
/*    */     //   1600: ifeq -> 1605
/*    */     //   1603: iconst_1
/*    */     //   1604: ireturn
/*    */     //   1605: aload_0
/*    */     //   1606: getfield MH0 : Lf/pA;
/*    */     //   1609: getfield TF : Lf/wu;
/*    */     //   1612: getfield b00 : Lf/of;
/*    */     //   1615: invokevirtual p3 : ()Z
/*    */     //   1618: ifeq -> 1670
/*    */     //   1621: aload_1
/*    */     //   1622: getfield GG0 : I
/*    */     //   1625: dup
/*    */     //   1626: istore_2
/*    */     //   1627: bipush #19
/*    */     //   1629: if_icmpne -> 1645
/*    */     //   1632: aload_0
/*    */     //   1633: getfield MH0 : Lf/pA;
/*    */     //   1636: getfield TF : Lf/wu;
/*    */     //   1639: iconst_1
/*    */     //   1640: invokevirtual MS : (I)V
/*    */     //   1643: iconst_1
/*    */     //   1644: ireturn
/*    */     //   1645: iload_2
/*    */     //   1646: bipush #20
/*    */     //   1648: if_icmpne -> 1664
/*    */     //   1651: aload_0
/*    */     //   1652: getfield MH0 : Lf/pA;
/*    */     //   1655: getfield TF : Lf/wu;
/*    */     //   1658: iconst_m1
/*    */     //   1659: invokevirtual MS : (I)V
/*    */     //   1662: iconst_1
/*    */     //   1663: ireturn
/*    */     //   1664: aload_0
/*    */     //   1665: aload_1
/*    */     //   1666: invokespecial i2 : (Lf/oa0;)Z
/*    */     //   1669: ireturn
/*    */     //   1670: aload_0
/*    */     //   1671: invokestatic uD : (Lf/JG0;)Lf/JG0;
/*    */     //   1674: ifnull -> 1683
/*    */     //   1677: aload_0
/*    */     //   1678: aload_1
/*    */     //   1679: invokespecial i2 : (Lf/oa0;)Z
/*    */     //   1682: ireturn
/*    */     //   1683: aload_0
/*    */     //   1684: getfield MH0 : Lf/pA;
/*    */     //   1687: getfield LU : Lf/A8;
/*    */     //   1690: dup
/*    */     //   1691: astore_2
/*    */     //   1692: ifnull -> 1705
/*    */     //   1695: aload_2
/*    */     //   1696: aload_1
/*    */     //   1697: invokevirtual i2 : (Lf/oa0;)Z
/*    */     //   1700: ifeq -> 1705
/*    */     //   1703: iconst_1
/*    */     //   1704: ireturn
/*    */     //   1705: aload_0
/*    */     //   1706: getfield MH0 : Lf/pA;
/*    */     //   1709: getfield TF : Lf/wu;
/*    */     //   1712: getfield b00 : Lf/of;
/*    */     //   1715: invokevirtual p3 : ()Z
/*    */     //   1718: ifne -> 1755
/*    */     //   1721: iconst_3
/*    */     //   1722: invokestatic D70 : (I)Z
/*    */     //   1725: ifeq -> 1755
/*    */     //   1728: aload_1
/*    */     //   1729: getfield GG0 : I
/*    */     //   1732: bipush #124
/*    */     //   1734: if_icmpeq -> 1740
/*    */     //   1737: goto -> 1755
/*    */     //   1740: getstatic f/h2.nL0 : Lf/h2;
/*    */     //   1743: getfield xM : Lf/dQ;
/*    */     //   1746: dup
/*    */     //   1747: getfield dP : Z
/*    */     //   1750: iconst_1
/*    */     //   1751: ixor
/*    */     //   1752: invokevirtual wI0 : (Z)V
/*    */     //   1755: aload_0
/*    */     //   1756: dup
/*    */     //   1757: aload_1
/*    */     //   1758: invokevirtual xb0 : (Lf/oa0;)V
/*    */     //   1761: getfield MH0 : Lf/pA;
/*    */     //   1764: getfield TF : Lf/wu;
/*    */     //   1767: getfield b00 : Lf/of;
/*    */     //   1770: invokevirtual p3 : ()Z
/*    */     //   1773: ifne -> 2174
/*    */     //   1776: aload_0
/*    */     //   1777: getfield vY : Lf/v10;
/*    */     //   1780: ifnonnull -> 2174
/*    */     //   1783: aload_0
/*    */     //   1784: getfield MH0 : Lf/pA;
/*    */     //   1787: getfield OU : Lf/h2;
/*    */     //   1790: invokevirtual p3 : ()Z
/*    */     //   1793: ifne -> 2174
/*    */     //   1796: aload_1
/*    */     //   1797: getfield com8 : I
/*    */     //   1800: iconst_4
/*    */     //   1801: if_icmpne -> 1809
/*    */     //   1804: iconst_1
/*    */     //   1805: istore_2
/*    */     //   1806: goto -> 1811
/*    */     //   1809: iconst_0
/*    */     //   1810: istore_2
/*    */     //   1811: aload_1
/*    */     //   1812: getfield GG0 : I
/*    */     //   1815: getstatic f/BM.Rd : Lf/BM;
/*    */     //   1818: invokestatic J20 : (ILf/BM;)Z
/*    */     //   1821: ifeq -> 1838
/*    */     //   1824: iload_2
/*    */     //   1825: ifne -> 1838
/*    */     //   1828: aload_0
/*    */     //   1829: getfield MH0 : Lf/pA;
/*    */     //   1832: invokevirtual Ou0 : ()V
/*    */     //   1835: goto -> 2174
/*    */     //   1838: aload_1
/*    */     //   1839: getfield GG0 : I
/*    */     //   1842: getstatic f/BM.cf : Lf/BM;
/*    */     //   1845: invokestatic J20 : (ILf/BM;)Z
/*    */     //   1848: ifeq -> 1891
/*    */     //   1851: getstatic f/km.MR : Lf/Gp0;
/*    */     //   1854: dup
/*    */     //   1855: astore_2
/*    */     //   1856: ifnull -> 1881
/*    */     //   1859: aload_2
/*    */     //   1860: invokevirtual sQ : ()Z
/*    */     //   1863: ifne -> 1881
/*    */     //   1866: aload_0
/*    */     //   1867: sipush #6002
/*    */     //   1870: invokestatic OH0 : (I)Ljava/lang/String;
/*    */     //   1873: iconst_m1
/*    */     //   1874: swap
/*    */     //   1875: invokevirtual Pu : (ILjava/lang/String;)V
/*    */     //   1878: goto -> 2174
/*    */     //   1881: aload_0
/*    */     //   1882: getfield MH0 : Lf/pA;
/*    */     //   1885: invokevirtual cf : ()V
/*    */     //   1888: goto -> 2174
/*    */     //   1891: aload_1
/*    */     //   1892: getfield GG0 : I
/*    */     //   1895: getstatic f/BM.I0 : Lf/BM;
/*    */     //   1898: invokestatic J20 : (ILf/BM;)Z
/*    */     //   1901: ifeq -> 1914
/*    */     //   1904: aload_0
/*    */     //   1905: getfield MH0 : Lf/pA;
/*    */     //   1908: invokevirtual cJ0 : ()V
/*    */     //   1911: goto -> 2174
/*    */     //   1914: aload_1
/*    */     //   1915: getfield GG0 : I
/*    */     //   1918: getstatic f/BM.TC : Lf/BM;
/*    */     //   1921: invokestatic J20 : (ILf/BM;)Z
/*    */     //   1924: ifeq -> 1937
/*    */     //   1927: aload_0
/*    */     //   1928: getfield MH0 : Lf/pA;
/*    */     //   1931: invokevirtual RQ : ()V
/*    */     //   1934: goto -> 2174
/*    */     //   1937: aload_1
/*    */     //   1938: getfield GG0 : I
/*    */     //   1941: getstatic f/BM.l30 : Lf/BM;
/*    */     //   1944: invokestatic J20 : (ILf/BM;)Z
/*    */     //   1947: ifeq -> 1975
/*    */     //   1950: invokestatic XU : ()Z
/*    */     //   1953: ifeq -> 1959
/*    */     //   1956: goto -> 2119
/*    */     //   1959: aload_0
/*    */     //   1960: getfield MH0 : Lf/pA;
/*    */     //   1963: getfield Qp0 : Lf/finally;
/*    */     //   1966: iconst_m1
/*    */     //   1967: iconst_0
/*    */     //   1968: invokevirtual hq0 : (IZ)Z
/*    */     //   1971: pop
/*    */     //   1972: goto -> 2174
/*    */     //   1975: aload_1
/*    */     //   1976: getfield GG0 : I
/*    */     //   1979: getstatic f/BM.eH0 : Lf/BM;
/*    */     //   1982: invokestatic J20 : (ILf/BM;)Z
/*    */     //   1985: ifeq -> 2014
/*    */     //   1988: aload_0
/*    */     //   1989: dup
/*    */     //   1990: dup
/*    */     //   1991: getfield MH0 : Lf/pA;
/*    */     //   1994: dup
/*    */     //   1995: getfield dP : Z
/*    */     //   1998: iconst_1
/*    */     //   1999: ixor
/*    */     //   2000: invokevirtual wI0 : (Z)V
/*    */     //   2003: getfield dP : Z
/*    */     //   2006: iconst_1
/*    */     //   2007: ixor
/*    */     //   2008: invokevirtual wI0 : (Z)V
/*    */     //   2011: goto -> 2174
/*    */     //   2014: aload_1
/*    */     //   2015: getfield GG0 : I
/*    */     //   2018: getstatic f/BM.W1 : Lf/BM;
/*    */     //   2021: invokestatic J20 : (ILf/BM;)Z
/*    */     //   2024: ifeq -> 2038
/*    */     //   2027: aload_0
/*    */     //   2028: getfield MH0 : Lf/pA;
/*    */     //   2031: iconst_1
/*    */     //   2032: invokevirtual IA0 : (Z)V
/*    */     //   2035: goto -> 2174
/*    */     //   2038: aload_1
/*    */     //   2039: getfield GG0 : I
/*    */     //   2042: getstatic f/BM.Ij0 : Lf/BM;
/*    */     //   2045: invokestatic J20 : (ILf/BM;)Z
/*    */     //   2048: ifeq -> 2062
/*    */     //   2051: aload_0
/*    */     //   2052: getfield MH0 : Lf/pA;
/*    */     //   2055: iconst_1
/*    */     //   2056: invokevirtual ni : (Z)V
/*    */     //   2059: goto -> 2174
/*    */     //   2062: aload_1
/*    */     //   2063: getfield GG0 : I
/*    */     //   2066: getstatic f/BM.EW : Lf/BM;
/*    */     //   2069: invokestatic J20 : (ILf/BM;)Z
/*    */     //   2072: ifeq -> 2104
/*    */     //   2075: aload_0
/*    */     //   2076: getfield MH0 : Lf/pA;
/*    */     //   2079: dup
/*    */     //   2080: astore_2
/*    */     //   2081: getfield QI0 : Lf/A;
/*    */     //   2084: ifnonnull -> 2092
/*    */     //   2087: iconst_1
/*    */     //   2088: istore_3
/*    */     //   2089: goto -> 2094
/*    */     //   2092: iconst_0
/*    */     //   2093: istore_3
/*    */     //   2094: aload_2
/*    */     //   2095: aconst_null
/*    */     //   2096: iload_3
/*    */     //   2097: iconst_0
/*    */     //   2098: invokevirtual A4 : (Lf/j40;ZZ)V
/*    */     //   2101: goto -> 2174
/*    */     //   2104: aload_1
/*    */     //   2105: getfield GG0 : I
/*    */     //   2108: bipush #111
/*    */     //   2110: if_icmpne -> 2174
/*    */     //   2113: invokestatic XU : ()Z
/*    */     //   2116: ifeq -> 2126
/*    */     //   2119: aload_0
/*    */     //   2120: invokevirtual xf : ()V
/*    */     //   2123: goto -> 2174
/*    */     //   2126: aload_0
/*    */     //   2127: getfield GC0 : Lf/QP;
/*    */     //   2130: dup
/*    */     //   2131: astore_2
/*    */     //   2132: ifnull -> 2143
/*    */     //   2135: aload_2
/*    */     //   2136: invokevirtual ra0 : ()Z
/*    */     //   2139: pop
/*    */     //   2140: goto -> 2174
/*    */     //   2143: aload_0
/*    */     //   2144: dup
/*    */     //   2145: dup2
/*    */     //   2146: new f/QP
/*    */     //   2149: dup
/*    */     //   2150: dup
/*    */     //   2151: astore_2
/*    */     //   2152: aload_0
/*    */     //   2153: invokespecial <init> : (Lf/js;)V
/*    */     //   2156: putfield GC0 : Lf/QP;
/*    */     //   2159: invokevirtual Ub : ()I
/*    */     //   2162: aload_2
/*    */     //   2163: swap
/*    */     //   2164: invokevirtual si : (Lf/JG0;I)V
/*    */     //   2167: getfield GC0 : Lf/QP;
/*    */     //   2170: iconst_1
/*    */     //   2171: invokevirtual wI0 : (Z)V
/*    */     //   2174: aload_1
/*    */     //   2175: getfield GG0 : I
/*    */     //   2178: getstatic f/BM.i40 : Lf/BM;
/*    */     //   2181: invokestatic J20 : (ILf/BM;)Z
/*    */     //   2184: ifeq -> 2345
/*    */     //   2187: getstatic f/UB0.PU : Lf/aY;
/*    */     //   2190: bipush #59
/*    */     //   2192: invokevirtual Ak : (I)Z
/*    */     //   2195: ifne -> 2345
/*    */     //   2198: getstatic f/UB0.PU : Lf/aY;
/*    */     //   2201: sipush #129
/*    */     //   2204: invokevirtual Ak : (I)Z
/*    */     //   2207: ifne -> 2345
/*    */     //   2210: getstatic f/UB0.re0 : Lf/hj0;
/*    */     //   2213: ifnull -> 2345
/*    */     //   2216: aconst_null
/*    */     //   2217: astore_2
/*    */     //   2218: invokestatic Xx0 : ()Lf/ZH;
/*    */     //   2221: dup
/*    */     //   2222: astore_2
/*    */     //   2223: getstatic f/UB0.vj0 : Lf/XG;
/*    */     //   2226: new java/lang/StringBuilder
/*    */     //   2229: dup
/*    */     //   2230: invokespecial <init> : ()V
/*    */     //   2233: ldc_w './screenshots/screenshot_'
/*    */     //   2236: invokevirtual append : (Ljava/lang/String;)Ljava/lang/StringBuilder;
/*    */     //   2239: invokestatic currentTimeMillis : ()J
/*    */     //   2242: ldc2_w 1000
/*    */     //   2245: ldiv
/*    */     //   2246: invokevirtual append : (J)Ljava/lang/StringBuilder;
/*    */     //   2249: ldc_w '.png'
/*    */     //   2252: invokevirtual append : (Ljava/lang/String;)Ljava/lang/StringBuilder;
/*    */     //   2255: invokevirtual toString : ()Ljava/lang/String;
/*    */     //   2258: invokevirtual N0 : (Ljava/lang/String;)Lf/hZ;
/*    */     //   2261: dup
/*    */     //   2262: aload_2
/*    */     //   2263: swap
/*    */     //   2264: invokevirtual wT : ()Lf/RD0;
/*    */     //   2267: invokevirtual iz0 : ()V
/*    */     //   2270: invokestatic TJ0 : (Lf/RD0;Lf/ZH;)V
/*    */     //   2273: getstatic f/js.vu0 : Lf/js;
/*    */     //   2276: sipush #6000
/*    */     //   2279: invokestatic OH0 : (I)Ljava/lang/String;
/*    */     //   2282: iconst_m1
/*    */     //   2283: swap
/*    */     //   2284: invokevirtual Pu : (ILjava/lang/String;)V
/*    */     //   2287: getstatic f/km.pm0 : Lf/VD0;
/*    */     //   2290: sipush #1583
/*    */     //   2293: invokevirtual fy : (S)V
/*    */     //   2296: invokevirtual dispose : ()V
/*    */     //   2299: goto -> 2345
/*    */     //   2302: pop
/*    */     //   2303: goto -> 2310
/*    */     //   2306: astore_0
/*    */     //   2307: goto -> 2335
/*    */     //   2310: aload_2
/*    */     //   2311: getstatic f/js.vu0 : Lf/js;
/*    */     //   2314: sipush #6001
/*    */     //   2317: invokestatic OH0 : (I)Ljava/lang/String;
/*    */     //   2320: iconst_m1
/*    */     //   2321: swap
/*    */     //   2322: invokevirtual Pu : (ILjava/lang/String;)V
/*    */     //   2325: ifnull -> 2345
/*    */     //   2328: aload_2
/*    */     //   2329: invokevirtual dispose : ()V
/*    */     //   2332: goto -> 2345
/*    */     //   2335: aload_2
/*    */     //   2336: ifnull -> 2343
/*    */     //   2339: aload_2
/*    */     //   2340: invokevirtual dispose : ()V
/*    */     //   2343: aload_0
/*    */     //   2344: athrow
/*    */     //   2345: aload_1
/*    */     //   2346: getfield GG0 : I
/*    */     //   2349: getstatic f/BM.lc : Lf/BM;
/*    */     //   2352: invokestatic J20 : (ILf/BM;)Z
/*    */     //   2355: ifeq -> 2376
/*    */     //   2358: getstatic f/h1.sP : Z
/*    */     //   2361: ifeq -> 2376
/*    */     //   2364: getstatic f/km.n20 : Lf/q7;
/*    */     //   2367: dup
/*    */     //   2368: getfield qO : Z
/*    */     //   2371: iconst_1
/*    */     //   2372: ixor
/*    */     //   2373: putfield qO : Z
/*    */     //   2376: aload_0
/*    */     //   2377: getfield MH0 : Lf/pA;
/*    */     //   2380: getfield WH : Lf/xJ0;
/*    */     //   2383: aload_1
/*    */     //   2384: invokevirtual i2 : (Lf/oa0;)Z
/*    */     //   2387: ifeq -> 2392
/*    */     //   2390: iconst_1
/*    */     //   2391: ireturn
/*    */     //   2392: getstatic f/km.u4 : Lf/R8;
/*    */     //   2395: getfield hB0 : Lf/Ca;
/*    */     //   2398: dup
/*    */     //   2399: astore_2
/*    */     //   2400: ifnull -> 2424
/*    */     //   2403: aload_2
/*    */     //   2404: aload_1
/*    */     //   2405: getfield GG0 : I
/*    */     //   2408: iconst_1
/*    */     //   2409: swap
/*    */     //   2410: invokeinterface vQ : (ZI)Z
/*    */     //   2415: pop
/*    */     //   2416: goto -> 2424
/*    */     //   2419: aload_0
/*    */     //   2420: aload_1
/*    */     //   2421: invokevirtual xb0 : (Lf/oa0;)V
/*    */     //   2424: aload_0
/*    */     //   2425: getfield bk : Lf/Pw;
/*    */     //   2428: getfield LR : Lf/cj;
/*    */     //   2431: dup
/*    */     //   2432: astore_2
/*    */     //   2433: ifnull -> 2446
/*    */     //   2436: aload_2
/*    */     //   2437: aload_1
/*    */     //   2438: invokevirtual pT : (Lf/oa0;)Z
/*    */     //   2441: ifeq -> 2446
/*    */     //   2444: iconst_1
/*    */     //   2445: ireturn
/*    */     //   2446: aload_0
/*    */     //   2447: aload_1
/*    */     //   2448: invokespecial i2 : (Lf/oa0;)Z
/*    */     //   2451: ireturn
/*    */     // Line number table:
/*    */     //   Java source line number -> byte code offset
/*    */     //   #1	-> 7
/*    */     //   #2	-> 12
/*    */     //   #3	-> 23
/*    */     //   #4	-> 35
/*    */     //   #5	-> 40
/*    */     //   #6	-> 60
/*    */     //   #7	-> 63
/*    */     //   #8	-> 70
/*    */     //   #9	-> 84
/*    */     //   #10	-> 87
/*    */     //   #11	-> 101
/*    */     //   #12	-> 106
/*    */     //   #13	-> 118
/*    */     //   #14	-> 128
/*    */     //   #15	-> 135
/*    */     //   #16	-> 143
/*    */     //   #17	-> 152
/*    */     //   #18	-> 161
/*    */     //   #19	-> 173
/*    */     //   #20	-> 185
/*    */     //   #21	-> 193
/*    */     //   #22	-> 221
/*    */     //   #23	-> 231
/*    */     //   #24	-> 238
/*    */     //   #25	-> 247
/*    */     //   #26	-> 252
/*    */     //   #27	-> 261
/*    */     //   #28	-> 264
/*    */     //   #29	-> 270
/*    */     //   #30	-> 276
/*    */     //   #31	-> 282
/*    */     //   #32	-> 285
/*    */     //   #33	-> 310
/*    */     //   #34	-> 313
/*    */     //   #35	-> 322
/*    */     //   #36	-> 325
/*    */     //   #37	-> 337
/*    */     //   #38	-> 340
/*    */     //   #39	-> 362
/*    */     //   #40	-> 369
/*    */     //   #41	-> 379
/*    */     //   #42	-> 393
/*    */     //   #43	-> 397
/*    */     //   #44	-> 407
/*    */     //   #45	-> 411
/*    */     //   #46	-> 424
/*    */     //   #47	-> 433
/*    */     //   #48	-> 470
/*    */     //   #49	-> 479
/*    */     //   #50	-> 488
/*    */     //   #51	-> 497
/*    */     //   #52	-> 516
/*    */     //   #53	-> 521
/*    */     //   #54	-> 526
/*    */     //   #55	-> 609
/*    */     //   #56	-> 652
/*    */     //   #57	-> 661
/*    */     //   #58	-> 671
/*    */     //   #59	-> 685
/*    */     //   #60	-> 692
/*    */     //   #61	-> 700
/*    */     //   #62	-> 707
/*    */     //   #63	-> 716
/*    */     //   #64	-> 725
/*    */     //   #65	-> 736
/*    */     //   #66	-> 740
/*    */     //   #67	-> 744
/*    */     //   #68	-> 749
/*    */     //   #69	-> 760
/*    */     //   #70	-> 780
/*    */     //   #71	-> 784
/*    */     //   #72	-> 794
/*    */     //   #73	-> 798
/*    */     //   #74	-> 807
/*    */     //   #75	-> 815
/*    */     //   #76	-> 825
/*    */     //   #77	-> 829
/*    */     //   #78	-> 837
/*    */     //   #79	-> 841
/*    */     //   #80	-> 851
/*    */     //   #81	-> 863
/*    */     //   #82	-> 868
/*    */     //   #83	-> 871
/*    */     //   #84	-> 885
/*    */     //   #85	-> 922
/*    */     //   #86	-> 926
/*    */     //   #87	-> 929
/*    */     //   #88	-> 933
/*    */     //   #89	-> 937
/*    */     //   #90	-> 942
/*    */     //   #91	-> 946
/*    */     //   #92	-> 951
/*    */     //   #93	-> 954
/*    */     //   #94	-> 959
/*    */     //   #95	-> 965
/*    */     //   #96	-> 970
/*    */     //   #97	-> 981
/*    */     //   #98	-> 984
/*    */     //   #99	-> 1000
/*    */     //   #100	-> 1003
/*    */     //   #101	-> 1030
/*    */     //   #102	-> 1033
/*    */     //   #103	-> 1045
/*    */     //   #104	-> 1048
/*    */     //   #105	-> 1068
/*    */     //   #106	-> 1071
/*    */     //   #107	-> 1087
/*    */     //   #108	-> 1090
/*    */     //   #109	-> 1126
/*    */     //   #110	-> 1129
/*    */     //   #111	-> 1169
/*    */     //   #112	-> 1172
/*    */     //   #113	-> 1208
/*    */     //   #114	-> 1211
/*    */     //   #115	-> 1250
/*    */     //   #116	-> 1253
/*    */     //   #117	-> 1263
/*    */     //   #118	-> 1266
/*    */     //   #119	-> 1276
/*    */     //   #120	-> 1279
/*    */     //   #121	-> 1289
/*    */     //   #122	-> 1292
/*    */     //   #123	-> 1302
/*    */     //   #124	-> 1305
/*    */     //   #125	-> 1315
/*    */     //   #126	-> 1318
/*    */     //   #127	-> 1337
/*    */     //   #128	-> 1340
/*    */     //   #129	-> 1343
/*    */     //   #130	-> 1350
/*    */     //   #131	-> 1356
/*    */     //   #132	-> 1360
/*    */     //   #133	-> 1366
/*    */     //   #134	-> 1391
/*    */     //   #135	-> 1400
/*    */     //   #136	-> 1410
/*    */     //   #137	-> 1426
/*    */     //   #138	-> 1473
/*    */     //   #139	-> 1493
/*    */     //   #140	-> 1502
/*    */     //   #141	-> 1536
/*    */     //   #142	-> 1546
/*    */     //   #143	-> 1549
/*    */     //   #144	-> 1552
/*    */     //   #145	-> 1562
/*    */     //   #146	-> 1569
/*    */     //   #147	-> 1572
/*    */     //   #148	-> 1577
/*    */     //   #149	-> 1580
/*    */     //   #150	-> 1592
/*    */     //   #151	-> 1606
/*    */     //   #152	-> 1609
/*    */     //   #153	-> 1612
/*    */     //   #154	-> 1615
/*    */     //   #155	-> 1622
/*    */     //   #156	-> 1633
/*    */     //   #157	-> 1636
/*    */     //   #158	-> 1640
/*    */     //   #159	-> 1655
/*    */     //   #160	-> 1659
/*    */     //   #161	-> 1671
/*    */     //   #162	-> 1679
/*    */     //   #163	-> 1687
/*    */     //   #164	-> 1697
/*    */     //   #165	-> 1709
/*    */     //   #166	-> 1712
/*    */     //   #167	-> 1715
/*    */     //   #168	-> 1722
/*    */     //   #169	-> 1729
/*    */     //   #170	-> 1740
/*    */     //   #171	-> 1743
/*    */     //   #172	-> 1747
/*    */     //   #173	-> 1752
/*    */     //   #174	-> 1758
/*    */     //   #175	-> 1764
/*    */     //   #176	-> 1767
/*    */     //   #177	-> 1770
/*    */     //   #178	-> 1777
/*    */     //   #179	-> 1787
/*    */     //   #180	-> 1790
/*    */     //   #181	-> 1797
/*    */     //   #182	-> 1812
/*    */     //   #183	-> 1815
/*    */     //   #184	-> 1839
/*    */     //   #185	-> 1842
/*    */     //   #186	-> 1875
/*    */     //   #187	-> 1882
/*    */     //   #188	-> 1885
/*    */     //   #189	-> 1892
/*    */     //   #190	-> 1895
/*    */     //   #191	-> 1905
/*    */     //   #192	-> 1908
/*    */     //   #193	-> 1915
/*    */     //   #194	-> 1918
/*    */     //   #195	-> 1928
/*    */     //   #196	-> 1931
/*    */     //   #197	-> 1938
/*    */     //   #198	-> 1941
/*    */     //   #199	-> 1960
/*    */     //   #200	-> 1963
/*    */     //   #201	-> 1968
/*    */     //   #202	-> 1976
/*    */     //   #203	-> 1979
/*    */     //   #204	-> 1995
/*    */     //   #205	-> 2000
/*    */     //   #206	-> 2003
/*    */     //   #207	-> 2008
/*    */     //   #208	-> 2015
/*    */     //   #209	-> 2018
/*    */     //   #210	-> 2039
/*    */     //   #211	-> 2042
/*    */     //   #212	-> 2052
/*    */     //   #213	-> 2056
/*    */     //   #214	-> 2063
/*    */     //   #215	-> 2066
/*    */     //   #216	-> 2076
/*    */     //   #217	-> 2081
/*    */     //   #218	-> 2098
/*    */     //   #219	-> 2105
/*    */     //   #220	-> 2113
/*    */     //   #221	-> 2127
/*    */     //   #222	-> 2159
/*    */     //   #223	-> 2167
/*    */     //   #224	-> 2175
/*    */     //   #225	-> 2178
/*    */     //   #226	-> 2273
/*    */     //   #227	-> 2279
/*    */     //   #228	-> 2284
/*    */     //   #229	-> 2287
/*    */     //   #230	-> 2311
/*    */     //   #231	-> 2317
/*    */     //   #232	-> 2322
/*    */     //   #233	-> 2329
/*    */     //   #234	-> 2346
/*    */     //   #235	-> 2349
/*    */     //   #236	-> 2380
/*    */     //   #237	-> 2384
/*    */     //   #238	-> 2395
/*    */     //   #239	-> 2405
/*    */     //   #240	-> 2410
/*    */     //   #241	-> 2428
/*    */     //   #242	-> 2438
/*    */     // Exception table:
/*    */     //   from	to	target	type
/*    */     //   2218	2221	2302	java/lang/Exception
/*    */     //   2218	2221	2306	finally
/*    */     //   2223	2261	2302	java/lang/Exception
/*    */     //   2223	2261	2306	finally
/*    */     //   2262	2296	2302	java/lang/Exception
/*    */     //   2262	2296	2306	finally
/*    */     //   2310	2325	2306	finally
/*    */   }
/*    */   
/*    */   public final void xb0(oa0 paramoa0) {
/*    */     int k;
/*    */     pA pA1;
/*    */     finally finally;
/*    */     if (paramoa0.GG0 == 12 && ((k = paramoa0.com8) == 4 || k == 1) && paramoa0.oO() && (pA1 = pA.Dg0) != null && (finally = pA1.Qp0).fr0 != null) {
/*    */       finally finally1;
/*    */       finally.ra0();
/*    */       this();
/*    */       pA1.Qp0 = finally1;
/*    */       pA1.J8(finally1);
/*    */     } 
/*    */     int j;
/*    */     if (paramoa0.GG0 == 135 && ((j = paramoa0.com8) == 4 || j == 1) && paramoa0.oO())
/*    */       UB0.Kg0.fN(vC0::Zy); 
/*    */     if (paramoa0.GG0 == 136 && ((j = paramoa0.com8) == 4 || j == 1)) {
/*    */       cE.eo0.qK0(true);
/*    */       cE.eo0.qK0(false);
/*    */       vu0.Pu(-1, "Reloaded strings.");
/*    */     } 
/*    */     if (paramoa0.GG0 == 137 && ((j = paramoa0.com8) == 4 || j == 1) && paramoa0.oO()) {
/*    */       HashSet hashSet;
/*    */       this();
/*    */       Iterator<Map.Entry> iterator;
/*    */       for (j = 0, iterator = (new TreeMap<>(this.bk.Iv.cOm1)).entrySet().iterator(); iterator.hasNext(); ) {
/*    */         String str = (String)((Map.Entry)iterator.next()).getKey();
/*    */         t90 t90;
/*    */         if ((t90 = (t90)((Map.Entry)iterator.next()).getValue()).isCopy())
/*    */           continue; 
/*    */         while (str.length() < 30)
/*    */           str = m0.tF0(str, " "); 
/*    */         int m = (t90.getFont()).Eh0.Z8, n = 0;
/*    */         for (Hc0 hc0 = (t90.getFont()).Eh0.r30(); hc0.hasNext();)
/*    */           n = (pe0 = (pe0)hc0.next()).H0 * pe0.Vn0 * 4 + n; 
/*    */         try {
/*    */           t90.getFreeTypeFontData().getClass().getDeclaredField("packer").setAccessible(true);
/*    */           oF0 oF0;
/*    */           if ((oF0 = (oF0)t90.getFreeTypeFontData().getClass().getDeclaredField("packer").get(t90.getFreeTypeFontData())) != null && !contains(oF0)) {
/*    */             add((E)oF0);
/*    */             j += n;
/*    */           } 
/*    */         } catch (Exception exception) {
/*    */           null.printStackTrace();
/*    */         } 
/*    */         iK.info(str + " regionCount: " + m + " PixmapMemory: " + LF.F6(n));
/*    */       } 
/*    */       iK.info(B40.df("Totals - PixmapMemory: ").append(LF.F6(j)).toString());
/*    */     } 
/*    */     int i;
/*    */     if (paramoa0.GG0 == 138 && ((i = paramoa0.com8) == 4 || i == 1)) {
/*    */       d00.Je.Hg();
/*    */       vu0.Pu(-1, "Reloaded mods.");
/*    */     } 
/*    */   }
/*    */   
/*    */   public final void Co() {
/*    */     if (this.Dj0 != null)
/*    */       return; 
/*    */     this(this);
/*    */     Wx wx;
/*    */     this.Dj0 = new Wx();
/*    */     si(wx, Ub());
/*    */     if (km.mI0.Mv0) {
/*    */       YF();
/*    */     } else if (!h1.Bb) {
/*    */       zn0 zn01;
/*    */       if ((zn01 = this.ZF0) != null)
/*    */         zn01.ra0(); 
/*    */       this();
/*    */       this.ZF0 = new zn0();
/*    */       si(zn01, Ub());
/*    */       this.ZF0.mM();
/*    */       this.ZF0.ME(this.bk.dG() / 2 - this.ZF0.xY / 2, this.bk.k1() / 2 - this.ZF0.HC / 2);
/*    */       this.ZF0.wI0(true);
/*    */     } 
/*    */   }
/*    */   
/*    */   public final qq0 F90(CQ paramCQ) {
/*    */     kf kf1;
/*    */     if ((kf1 = this.BA) != null)
/*    */       kf1.ra0(); 
/*    */     pA pA2;
/*    */     if ((pA2 = this.MH0) != null)
/*    */       super.jf0(pA2); 
/*    */     this(this, paramCQ);
/*    */     qq0 qq0;
/*    */     this.BA = qq0;
/*    */     si(qq0, Ub());
/*    */     pA pA1;
/*    */     if ((pA1 = this.MH0) != null)
/*    */       si(pA1, Ub()); 
/*    */     return qq0;
/*    */   }
/*    */   
/*    */   public final void mA0(fQ paramfQ, ny paramny, int paramInt1, int paramInt2) {
/*    */     // Byte code:
/*    */     //   0: aload_1
/*    */     //   1: new f/B3
/*    */     //   4: dup
/*    */     //   5: astore_1
/*    */     //   6: invokespecial <init> : ()V
/*    */     //   9: new f/fQ
/*    */     //   12: dup
/*    */     //   13: astore #5
/*    */     //   15: invokespecial <init> : ()V
/*    */     //   18: invokevirtual r30 : ()Lf/Hc0;
/*    */     //   21: astore #6
/*    */     //   23: aload #6
/*    */     //   25: invokevirtual hasNext : ()Z
/*    */     //   28: ifeq -> 626
/*    */     //   31: aload_2
/*    */     //   32: dup
/*    */     //   33: dup2
/*    */     //   34: dup2
/*    */     //   35: aload #5
/*    */     //   37: aload #6
/*    */     //   39: invokevirtual next : ()Ljava/lang/Object;
/*    */     //   42: checkcast f/Ah
/*    */     //   45: astore #7
/*    */     //   47: invokevirtual clear : ()V
/*    */     //   50: getstatic f/km.wI0 : Lf/Pw;
/*    */     //   53: getfield Ds0 : Lf/Ag0;
/*    */     //   56: dup
/*    */     //   57: dup2
/*    */     //   58: getstatic f/UB0.PU : Lf/aY;
/*    */     //   61: dup
/*    */     //   62: getfield XK0 : I
/*    */     //   65: i2f
/*    */     //   66: fstore #8
/*    */     //   68: getfield ol : I
/*    */     //   71: i2f
/*    */     //   72: fstore #9
/*    */     //   74: getfield G80 : I
/*    */     //   77: i2f
/*    */     //   78: fstore #10
/*    */     //   80: getfield Cn0 : I
/*    */     //   83: i2f
/*    */     //   84: fstore #11
/*    */     //   86: getfield QQ : I
/*    */     //   89: i2f
/*    */     //   90: fstore #12
/*    */     //   92: getfield o6 : I
/*    */     //   95: i2f
/*    */     //   96: fstore #13
/*    */     //   98: getfield H90 : Lf/p10;
/*    */     //   101: getfield xh : Lf/eo;
/*    */     //   104: fload #8
/*    */     //   106: fload #9
/*    */     //   108: fconst_0
/*    */     //   109: invokevirtual TG0 : (FFF)Lf/eo;
/*    */     //   112: fload #10
/*    */     //   114: fload #11
/*    */     //   116: fload #12
/*    */     //   118: fload #13
/*    */     //   120: invokevirtual Ix0 : (Lf/eo;FFFF)V
/*    */     //   123: getfield H90 : Lf/p10;
/*    */     //   126: getfield N6 : Lf/eo;
/*    */     //   129: fload #8
/*    */     //   131: fload #9
/*    */     //   133: fconst_1
/*    */     //   134: invokevirtual TG0 : (FFF)Lf/eo;
/*    */     //   137: fload #10
/*    */     //   139: fload #11
/*    */     //   141: fload #12
/*    */     //   143: fload #13
/*    */     //   145: invokevirtual Ix0 : (Lf/eo;FFFF)V
/*    */     //   148: getfield H90 : Lf/p10;
/*    */     //   151: dup
/*    */     //   152: astore #8
/*    */     //   154: getfield N6 : Lf/eo;
/*    */     //   157: aload #8
/*    */     //   159: getfield xh : Lf/eo;
/*    */     //   162: invokevirtual zy0 : (Lf/eo;)Lf/eo;
/*    */     //   165: invokevirtual WC0 : ()Lf/eo;
/*    */     //   168: pop
/*    */     //   169: getfield H90 : Lf/p10;
/*    */     //   172: astore #8
/*    */     //   174: aload #7
/*    */     //   176: getfield W7 : Lf/fQ;
/*    */     //   179: invokevirtual r30 : ()Lf/Hc0;
/*    */     //   182: astore #9
/*    */     //   184: aload #9
/*    */     //   186: invokevirtual hasNext : ()Z
/*    */     //   189: ifeq -> 393
/*    */     //   192: aload #8
/*    */     //   194: aload #9
/*    */     //   196: invokevirtual next : ()Ljava/lang/Object;
/*    */     //   199: checkcast f/lpt1
/*    */     //   202: dup
/*    */     //   203: astore #10
/*    */     //   205: getfield Of : Lf/Eb;
/*    */     //   208: invokestatic Mb : (Lf/p10;Lf/Eb;)Z
/*    */     //   211: ifeq -> 184
/*    */     //   214: aload #5
/*    */     //   216: dup
/*    */     //   217: aload #10
/*    */     //   219: getfield xl0 : Lf/fQ;
/*    */     //   222: invokevirtual OG0 : (Lf/fQ;)V
/*    */     //   225: invokevirtual r30 : ()Lf/Hc0;
/*    */     //   228: astore #11
/*    */     //   230: aload #11
/*    */     //   232: invokevirtual hasNext : ()Z
/*    */     //   235: ifeq -> 184
/*    */     //   238: aload #11
/*    */     //   240: invokevirtual next : ()Ljava/lang/Object;
/*    */     //   243: checkcast f/T0
/*    */     //   246: dup
/*    */     //   247: astore #12
/*    */     //   249: aload #10
/*    */     //   251: dup
/*    */     //   252: getfield Cx0 : Lf/Ew;
/*    */     //   255: aload #12
/*    */     //   257: getfield Xy0 : Ljava/lang/String;
/*    */     //   260: invokevirtual Vv0 : (Ljava/lang/String;)I
/*    */     //   263: istore #13
/*    */     //   265: getfield Cx0 : Lf/Ew;
/*    */     //   268: astore #14
/*    */     //   270: getfield Xy0 : Ljava/lang/String;
/*    */     //   273: aload #14
/*    */     //   275: getfield dH : Lf/f7;
/*    */     //   278: swap
/*    */     //   279: invokevirtual pd0 : (Ljava/lang/Object;)Ljava/lang/Object;
/*    */     //   282: checkcast java/lang/Integer
/*    */     //   285: dup
/*    */     //   286: astore #14
/*    */     //   288: ifnonnull -> 297
/*    */     //   291: iconst_m1
/*    */     //   292: istore #14
/*    */     //   294: goto -> 304
/*    */     //   297: aload #14
/*    */     //   299: invokevirtual intValue : ()I
/*    */     //   302: istore #14
/*    */     //   304: iload #13
/*    */     //   306: aload #12
/*    */     //   308: aload #10
/*    */     //   310: getfield Cx0 : Lf/Ew;
/*    */     //   313: astore #15
/*    */     //   315: getfield Xy0 : Ljava/lang/String;
/*    */     //   318: aload #15
/*    */     //   320: getfield W60 : Lf/f7;
/*    */     //   323: swap
/*    */     //   324: invokevirtual pd0 : (Ljava/lang/Object;)Ljava/lang/Object;
/*    */     //   327: checkcast com/badlogic/gdx/graphics/Texture
/*    */     //   330: astore #15
/*    */     //   332: iflt -> 230
/*    */     //   335: iload #14
/*    */     //   337: ifge -> 343
/*    */     //   340: goto -> 230
/*    */     //   343: aload_1
/*    */     //   344: new f/vi
/*    */     //   347: dup
/*    */     //   348: astore #16
/*    */     //   350: aload #12
/*    */     //   352: aload #10
/*    */     //   354: aload #12
/*    */     //   356: getfield Xy0 : Ljava/lang/String;
/*    */     //   359: astore #12
/*    */     //   361: iload #13
/*    */     //   363: iload #14
/*    */     //   365: <illegal opcode> run : (Lf/T0;Lf/lpt1;II)Ljava/lang/Runnable;
/*    */     //   370: astore #13
/*    */     //   372: aload #12
/*    */     //   374: aload #15
/*    */     //   376: aload #13
/*    */     //   378: invokespecial <init> : (Ljava/lang/String;Lcom/badlogic/gdx/graphics/Texture;Ljava/lang/Runnable;)V
/*    */     //   381: getfield aV : Ljava/util/ArrayList;
/*    */     //   384: aload #16
/*    */     //   386: invokevirtual add : (Ljava/lang/Object;)Z
/*    */     //   389: pop
/*    */     //   390: goto -> 230
/*    */     //   393: aload #7
/*    */     //   395: aload #5
/*    */     //   397: invokevirtual clear : ()V
/*    */     //   400: getfield K9 : Lf/lpt1;
/*    */     //   403: getfield vC0 : Lf/fQ;
/*    */     //   406: invokevirtual r30 : ()Lf/Hc0;
/*    */     //   409: astore #9
/*    */     //   411: aload #9
/*    */     //   413: invokevirtual hasNext : ()Z
/*    */     //   416: ifeq -> 447
/*    */     //   419: aload #8
/*    */     //   421: aload #5
/*    */     //   423: aload #7
/*    */     //   425: aload #9
/*    */     //   427: invokevirtual next : ()Ljava/lang/Object;
/*    */     //   430: checkcast f/zP
/*    */     //   433: astore #10
/*    */     //   435: getfield od : Lf/eo;
/*    */     //   438: aload #10
/*    */     //   440: swap
/*    */     //   441: invokestatic iF0 : (Lf/p10;Lf/fQ;Lf/zP;Lf/eo;)V
/*    */     //   444: goto -> 411
/*    */     //   447: aload #5
/*    */     //   449: invokevirtual r30 : ()Lf/Hc0;
/*    */     //   452: astore #8
/*    */     //   454: aload #8
/*    */     //   456: invokevirtual hasNext : ()Z
/*    */     //   459: ifeq -> 23
/*    */     //   462: aload #8
/*    */     //   464: invokevirtual next : ()Ljava/lang/Object;
/*    */     //   467: checkcast f/T0
/*    */     //   470: dup
/*    */     //   471: astore #9
/*    */     //   473: aload #7
/*    */     //   475: dup
/*    */     //   476: getfield K9 : Lf/lpt1;
/*    */     //   479: getfield Cx0 : Lf/Ew;
/*    */     //   482: aload #9
/*    */     //   484: getfield Xy0 : Ljava/lang/String;
/*    */     //   487: invokevirtual Vv0 : (Ljava/lang/String;)I
/*    */     //   490: istore #10
/*    */     //   492: getfield K9 : Lf/lpt1;
/*    */     //   495: getfield Cx0 : Lf/Ew;
/*    */     //   498: astore #11
/*    */     //   500: getfield Xy0 : Ljava/lang/String;
/*    */     //   503: aload #11
/*    */     //   505: getfield dH : Lf/f7;
/*    */     //   508: swap
/*    */     //   509: invokevirtual pd0 : (Ljava/lang/Object;)Ljava/lang/Object;
/*    */     //   512: checkcast java/lang/Integer
/*    */     //   515: dup
/*    */     //   516: astore #11
/*    */     //   518: ifnonnull -> 527
/*    */     //   521: iconst_m1
/*    */     //   522: istore #11
/*    */     //   524: goto -> 534
/*    */     //   527: aload #11
/*    */     //   529: invokevirtual intValue : ()I
/*    */     //   532: istore #11
/*    */     //   534: iload #10
/*    */     //   536: aload #9
/*    */     //   538: aload #7
/*    */     //   540: getfield K9 : Lf/lpt1;
/*    */     //   543: getfield Cx0 : Lf/Ew;
/*    */     //   546: astore #12
/*    */     //   548: getfield Xy0 : Ljava/lang/String;
/*    */     //   551: aload #12
/*    */     //   553: getfield W60 : Lf/f7;
/*    */     //   556: swap
/*    */     //   557: invokevirtual pd0 : (Ljava/lang/Object;)Ljava/lang/Object;
/*    */     //   560: checkcast com/badlogic/gdx/graphics/Texture
/*    */     //   563: astore #12
/*    */     //   565: iflt -> 454
/*    */     //   568: iload #11
/*    */     //   570: ifge -> 576
/*    */     //   573: goto -> 454
/*    */     //   576: aload_1
/*    */     //   577: new f/vi
/*    */     //   580: dup
/*    */     //   581: astore #13
/*    */     //   583: aload #9
/*    */     //   585: aload #7
/*    */     //   587: aload #9
/*    */     //   589: getfield Xy0 : Ljava/lang/String;
/*    */     //   592: astore #9
/*    */     //   594: iload #10
/*    */     //   596: iload #11
/*    */     //   598: <illegal opcode> run : (Lf/T0;Lf/Ah;II)Ljava/lang/Runnable;
/*    */     //   603: astore #10
/*    */     //   605: aload #9
/*    */     //   607: aload #12
/*    */     //   609: aload #10
/*    */     //   611: invokespecial <init> : (Ljava/lang/String;Lcom/badlogic/gdx/graphics/Texture;Ljava/lang/Runnable;)V
/*    */     //   614: getfield aV : Ljava/util/ArrayList;
/*    */     //   617: aload #13
/*    */     //   619: invokevirtual add : (Ljava/lang/Object;)Z
/*    */     //   622: pop
/*    */     //   623: goto -> 454
/*    */     //   626: aload_1
/*    */     //   627: getfield aV : Ljava/util/ArrayList;
/*    */     //   630: invokevirtual size : ()I
/*    */     //   633: ifle -> 644
/*    */     //   636: aload_1
/*    */     //   637: aload_0
/*    */     //   638: iload_3
/*    */     //   639: iload #4
/*    */     //   641: invokestatic T1 : (Lf/hu;Lf/JG0;II)V
/*    */     //   644: return
/*    */     // Line number table:
/*    */     //   Java source line number -> byte code offset
/*    */     //   #1	-> 53
/*    */     //   #2	-> 58
/*    */     //   #3	-> 62
/*    */     //   #4	-> 68
/*    */     //   #5	-> 74
/*    */     //   #6	-> 80
/*    */     //   #7	-> 86
/*    */     //   #8	-> 92
/*    */     //   #9	-> 98
/*    */     //   #10	-> 101
/*    */     //   #11	-> 176
/*    */     //   #12	-> 252
/*    */     //   #13	-> 257
/*    */     //   #14	-> 265
/*    */     //   #15	-> 270
/*    */     //   #16	-> 275
/*    */     //   #17	-> 279
/*    */     //   #18	-> 310
/*    */     //   #19	-> 315
/*    */     //   #20	-> 320
/*    */     //   #21	-> 324
/*    */     //   #22	-> 344
/*    */     //   #23	-> 381
/*    */     //   #24	-> 397
/*    */     //   #25	-> 400
/*    */     //   #26	-> 449
/*    */     //   #27	-> 479
/*    */     //   #28	-> 484
/*    */     //   #29	-> 495
/*    */     //   #30	-> 500
/*    */     //   #31	-> 505
/*    */     //   #32	-> 509
/*    */     //   #33	-> 540
/*    */     //   #34	-> 543
/*    */     //   #35	-> 548
/*    */     //   #36	-> 553
/*    */     //   #37	-> 557
/*    */     //   #38	-> 577
/*    */     //   #39	-> 614
/*    */     //   #40	-> 627
/*    */     //   #41	-> 641
/*    */   }
/*    */   
/*    */   public final void qp0(boolean paramBoolean) {
/*    */     v10 v101;
/*    */     if ((v101 = this.vY) != null)
/*    */       v101.ra0(); 
/*    */     this(this, paramBoolean);
/*    */     this.vY = new v10();
/*    */     si(v101, Ub());
/*    */     this.vY.mM();
/*    */     this.vY.ME(this.bk.dG() / 2 - this.vY.xY / 2, this.bk.k1() / 2 - this.vY.HC / 2);
/*    */     this.vY.wI0(true);
/*    */     VA0.c90(this.vY);
/*    */   }
/*    */   
/*    */   public final void W20() {
/*    */     Ay ay;
/*    */     if ((ay = this.V00) != null)
/*    */       ay.ra0(); 
/*    */     this();
/*    */     this.V00 = new Ay();
/*    */     si(ay, Ub());
/*    */     this.V00.mM();
/*    */     this.V00.ME(this.bk.dG() / 2 - this.V00.xY / 2, this.bk.k1() / 2 - this.V00.HC / 2);
/*    */     this.V00.wI0(true);
/*    */   }
/*    */   
/*    */   public final boolean jf0(JG0 paramJG0) {
/*    */     if (paramJG0 == this.Dj0) {
/*    */       this.Dj0 = null;
/*    */     } else if (paramJG0 == this.l00) {
/*    */       this.l00 = null;
/*    */     } else if (paramJG0 == this.Ji) {
/*    */       this.Ji = null;
/*    */     } else if (paramJG0 == this.Tc) {
/*    */       this.Tc = null;
/*    */     } else if (paramJG0 == this.mC0) {
/*    */       this.mC0 = null;
/*    */     } else if (paramJG0 == this.tj) {
/*    */       this.tj = null;
/*    */     } else if (paramJG0 == this.th) {
/*    */       this.th = null;
/*    */     } else if (paramJG0 == this.MH0) {
/*    */       this.MH0 = null;
/*    */     } else if (paramJG0 == this.iV) {
/*    */       this.iV = null;
/*    */     } else if (paramJG0 == this.BA) {
/*    */       this.BA = null;
/*    */     } else if (paramJG0 == this.GC0) {
/*    */       this.GC0 = null;
/*    */     } else if (paramJG0 == this.vY) {
/*    */       this.vY = null;
/*    */     } else if (paramJG0 == this.Lz) {
/*    */       this.Lz = null;
/*    */     } else if (paramJG0 == this.V00) {
/*    */       this.V00 = null;
/*    */     } else if (paramJG0 == this.ZF0) {
/*    */       this.ZF0 = null;
/*    */     } else if (paramJG0 instanceof hO) {
/*    */       hO hO = (hO)paramJG0;
/*    */       this.hW.D1.Ct(hO, true);
/*    */       this.hW.Kd0 = System.currentTimeMillis();
/*    */     } else if (paramJG0 instanceof QW) {
/*    */       this.U1.remove(paramJG0);
/*    */     } else if (paramJG0 == this.mm) {
/*    */       this.mm = null;
/*    */     } else if (paramJG0 == this.l5) {
/*    */       this.l5 = null;
/*    */     } 
/*    */     return super.jf0(paramJG0);
/*    */   }
/*    */   
/*    */   public final void ln0(String paramString) {
/*    */     Pu(-1, paramString);
/*    */   }
/*    */   
/*    */   public final void DJ(String paramString, Runnable paramRunnable) {
/*    */     AI0 aI0;
/*    */     if ((aI0 = this.Ji) != null)
/*    */       aI0.ra0(); 
/*    */     this(paramString);
/*    */     this.Ji = aI0;
/*    */     (aI0 = new AI0()).e8 = paramRunnable;
/*    */     si(aI0, Ub());
/*    */     Af(this.Ji);
/*    */   }
/*    */   
/*    */   public final void S8(int paramInt) {
/*    */     // Byte code:
/*    */     //   0: aload_0
/*    */     //   1: dup
/*    */     //   2: getfield tr0 : Ljava/util/ArrayList;
/*    */     //   5: iload_1
/*    */     //   6: <illegal opcode> test : (I)Ljava/util/function/Predicate;
/*    */     //   11: invokevirtual removeIf : (Ljava/util/function/Predicate;)Z
/*    */     //   14: pop
/*    */     //   15: getfield tr0 : Ljava/util/ArrayList;
/*    */     //   18: invokevirtual isEmpty : ()Z
/*    */     //   21: ifne -> 136
/*    */     //   24: aload_0
/*    */     //   25: dup
/*    */     //   26: getfield tr0 : Ljava/util/ArrayList;
/*    */     //   29: iconst_0
/*    */     //   30: invokevirtual get : (I)Ljava/lang/Object;
/*    */     //   33: checkcast f/EW
/*    */     //   36: astore_1
/*    */     //   37: ldc_w f/EW
/*    */     //   40: astore_2
/*    */     //   41: getfield Li0 : Lf/d10;
/*    */     //   44: dup
/*    */     //   45: astore_3
/*    */     //   46: ifnull -> 117
/*    */     //   49: aload_0
/*    */     //   50: aload_3
/*    */     //   51: invokevirtual Jv0 : ()[Ljava/lang/Object;
/*    */     //   54: checkcast [Lf/JG0;
/*    */     //   57: astore_3
/*    */     //   58: iconst_0
/*    */     //   59: istore #4
/*    */     //   61: getfield Li0 : Lf/d10;
/*    */     //   64: getfield Z8 : I
/*    */     //   67: istore #5
/*    */     //   69: iload #4
/*    */     //   71: iload #5
/*    */     //   73: if_icmpge -> 110
/*    */     //   76: aload_3
/*    */     //   77: iload #4
/*    */     //   79: aaload
/*    */     //   80: invokevirtual getClass : ()Ljava/lang/Class;
/*    */     //   83: aload_2
/*    */     //   84: invokevirtual isAssignableFrom : (Ljava/lang/Class;)Z
/*    */     //   87: ifeq -> 104
/*    */     //   90: aload_3
/*    */     //   91: iload #4
/*    */     //   93: aload_0
/*    */     //   94: getfield Li0 : Lf/d10;
/*    */     //   97: invokevirtual At0 : ()V
/*    */     //   100: aaload
/*    */     //   101: goto -> 118
/*    */     //   104: iinc #4, 1
/*    */     //   107: goto -> 69
/*    */     //   110: aload_0
/*    */     //   111: getfield Li0 : Lf/d10;
/*    */     //   114: invokevirtual At0 : ()V
/*    */     //   117: aconst_null
/*    */     //   118: ifnonnull -> 136
/*    */     //   121: aload_0
/*    */     //   122: dup
/*    */     //   123: dup
/*    */     //   124: invokevirtual Ub : ()I
/*    */     //   127: aload_1
/*    */     //   128: swap
/*    */     //   129: invokevirtual si : (Lf/JG0;I)V
/*    */     //   132: aload_1
/*    */     //   133: invokevirtual Af : (Lf/JG0;)V
/*    */     //   136: return
/*    */     // Line number table:
/*    */     //   Java source line number -> byte code offset
/*    */     //   #1	-> 37
/*    */     //   #2	-> 41
/*    */     //   #3	-> 124
/*    */     //   #4	-> 133
/*    */   }
/*    */   
/*    */   public final void uh(h70 paramh70) {
/*    */     h70 h701;
/*    */     if ((h701 = this.l5) != null)
/*    */       h701.ra0(); 
/*    */     this.l5 = paramh70;
/*    */     si(paramh70, Ub());
/*    */   }
/*    */   
/*    */   public final void d40() {
/*    */     xs xs1;
/*    */     if ((xs1 = this.es) != null) {
/*    */       xs1.mM();
/*    */       et et;
/*    */       this.es.js0(et = et.t9);
/*    */       if (km.XU()) {
/*    */         this.es.QJ0(et.T90, 0, 0);
/*    */       } else {
/*    */         this.es.js0(et);
/*    */       } 
/*    */     } 
/*    */     dQ dQ1;
/*    */     if ((dQ1 = this.Fe0) != null) {
/*    */       dQ1.mM();
/*    */       if (km.XU()) {
/*    */         this.Fe0.QJ0(et.t9, -150, this.es.HC + 60);
/*    */       } else {
/*    */         this.Fe0.QJ0(et.t9, 0, this.es.HC);
/*    */       } 
/*    */     } 
/*    */     Q20 q20;
/*    */     if ((q20 = this.mw) != null && q20.dP) {
/*    */       q20.mM();
/*    */       this.mw.QJ0(et.t9, -5, 5);
/*    */     } 
/*    */     pA pA1;
/*    */     if ((pA1 = this.MH0) != null && pA1.Tm(this.bk.dG(), this.bk.k1()))
/*    */       this.MH0.dp0(); 
/*    */     kf kf1;
/*    */     if ((kf1 = this.BA) != null)
/*    */       kf1.Tm(this.bk.dG(), this.bk.k1()); 
/*    */     FO fO;
/*    */     if ((fO = this.iV) != null)
/*    */       fO.Tm(this.bk.dG(), this.bk.k1()); 
/*    */     Z9 z9;
/*    */     if ((z9 = this.mC0) != null) {
/*    */       z9.Tm(400, 500);
/*    */       int j = RS();
/*    */       j = JO.Se0(qF(), this.mC0.xY, 2, j);
/*    */       int k = e3();
/*    */       this.mC0.ME(j, (Hy() - this.mC0.HC) / 2 + k);
/*    */     } 
/*    */     Wx wx;
/*    */     if ((wx = this.Dj0) != null) {
/*    */       wx.Tm(this.bk.dG(), this.bk.k1());
/*    */       this.Dj0.ME(0, 0);
/*    */     } 
/*    */     Yj0 yj0;
/*    */     if ((yj0 = this.l00) != null) {
/*    */       yj0.Tm(this.bk.dG(), this.bk.k1());
/*    */       int j = RS();
/*    */       j = JO.Se0(qF(), this.l00.xY, 2, j);
/*    */       int k = e3();
/*    */       this.l00.ME(j, (Hy() - this.l00.HC) / 2 + k);
/*    */     } 
/*    */     Qn0 qn0;
/*    */     if ((qn0 = this.uB0) != null) {
/*    */       qn0.Tm(this.bk.dG(), this.bk.k1());
/*    */       int j = RS();
/*    */       j = JO.Se0(qF(), this.uB0.xY, 2, j);
/*    */       int k = e3();
/*    */       this.uB0.ME(j, (Hy() - this.uB0.HC) / 2 + k);
/*    */     } 
/*    */     AI0 aI0;
/*    */     if ((aI0 = this.Ji) != null) {
/*    */       aI0.Tm(400, 500);
/*    */       int j = RS();
/*    */       j = JO.Se0(qF(), this.Ji.xY, 2, j);
/*    */       int k = e3();
/*    */       this.Ji.ME(j, (Hy() - this.Ji.HC) / 2 + k);
/*    */     } 
/*    */     for (Hc0 hc0 = this.hW.D1.r30(); hc0.hasNext(); ((hO)hc0.next()).mM());
/*    */     Qz0 qz0;
/*    */     if ((qz0 = this.hW) != null)
/*    */       qz0.mM(); 
/*    */     int i = 100;
/*    */     try {
/*    */       for (Iterator<QW> iterator = this.U1.iterator(); iterator.hasNext(); ) {
/*    */         qW.mM();
/*    */         QW qW;
/*    */         (qW = iterator.next()).ME(RS() + (qF() - qW.xY) / 2, mD() - qW.HC - i);
/*    */         i = (iterator.next()).HC + 5 + i;
/*    */       } 
/*    */     } catch (ConcurrentModificationException concurrentModificationException) {
/*    */       iK.info("error", concurrentModificationException);
/*    */     } 
/*    */     BX bX;
/*    */     if ((bX = this.th) != null) {
/*    */       bX.Tm(this.bk.dG(), this.bk.k1());
/*    */       int j = RS();
/*    */       j = JO.Se0(qF(), this.th.xY, 2, j);
/*    */       int k = e3();
/*    */       this.th.ME(j, (Hy() - this.th.HC) / 2 + k);
/*    */     } 
/*    */     Oa0 oa0;
/*    */     if ((oa0 = this.mm) != null) {
/*    */       oa0.Tm(this.bk.dG(), this.bk.k1());
/*    */       int j = RS();
/*    */       j = JO.Se0(qF(), this.mm.xY, 2, j);
/*    */       int k = e3();
/*    */       this.mm.ME(j, (Hy() - this.mm.HC) / 2 + k);
/*    */     } 
/*    */     QP qP;
/*    */     if ((qP = this.GC0) != null) {
/*    */       qP.QI();
/*    */       this.GC0.js0(et.Wi0);
/*    */     } 
/*    */     v10 v101;
/*    */     if ((v101 = this.vY) != null)
/*    */       v101.mM(); 
/*    */     wL wL1;
/*    */     if ((wL1 = this.Lz) != null) {
/*    */       wL1.mM();
/*    */       this.Lz.ME(this.bk.dG() / 2 - this.Lz.xY / 2, this.bk.k1() / 2 - this.Lz.HC / 2);
/*    */     } 
/*    */     Ay ay;
/*    */     if ((ay = this.V00) != null) {
/*    */       ay.mM();
/*    */       this.V00.ME(this.bk.dG() / 2 - this.V00.xY / 2, this.bk.k1() / 2 - this.V00.HC / 2);
/*    */     } 
/*    */     zn0 zn01;
/*    */     if ((zn01 = this.ZF0) != null) {
/*    */       zn01.mM();
/*    */       this.ZF0.ME(this.bk.dG() / 2 - this.ZF0.xY / 2, this.bk.k1() / 2 - this.ZF0.HC / 2);
/*    */     } 
/*    */     My my;
/*    */     if ((my = this.eG0) != null) {
/*    */       my.Tm(this.bk.dG(), this.bk.k1());
/*    */       this.eG0.ME(0, 0);
/*    */     } 
/*    */     mk1.Tm(this.bk.dG(), this.ht.Hj());
/*    */     mk mk1;
/*    */     if ((mk1 = this.ht) != null && (mk1 = this.ht).dP)
/*    */       VA0.c90((JG0)mk1.Nx); 
/*    */     super.d40();
/*    */   }
/*    */   
/*    */   public final pA L40() {
/*    */     return this.MH0;
/*    */   }
/*    */   
/*    */   public final void So0(boolean paramBoolean) {
/*    */     UB0.Kg0.fN(new ni(this, paramBoolean));
/*    */   }
/*    */   
/*    */   public final void Mo() {
/*    */     String str1 = "";
/*    */     if (km.VH.Qs0 != null)
/*    */       str1 = UQ.Vr0(new StringBuilder(), km.VH.Qs0, "\n\n"); 
/*    */     String str2 = Ml0.la(1171, "Do you want to attempt to repair your PokeMMO client?");
/*    */     if (!Ml0.nW.return(50)) {
/*    */       Ml0.nW.A3(50, "Yes");
/*    */       Ml0.nW.A3(51, "No");
/*    */     } 
/*    */     vu0.uh(new h70(m0.tF0(str1, str2), new v(this), null));
/*    */   }
/*    */   
/*    */   public final void z30() {
/*    */     this();
/*    */     this.ht = new mk();
/*    */     si(this, Ub());
/*    */     this.ht.ME(0, 0);
/*    */     mk mk1;
/*    */     (mk1 = this.ht).db0 = new I(this);
/*    */     this.ht.wI0(false);
/*    */   }
/*    */   
/*    */   public final void KE() {
/*    */     tl0 tl02;
/*    */     if ((tl02 = this.sG) == null || !tl02.dP)
/*    */       return; 
/*    */     tl02.wI0(false);
/*    */     tl0 tl01;
/*    */     if (this.oL0.fr0 != (tl01 = this.sG))
/*    */       gx(); 
/*    */   }
/*    */   
/*    */   public final void j90(JG0 paramJG0, Object paramObject, et paramet) {
/*    */     int m = paramJG0.Kd;
/*    */     m = paramJG0.xY / 2 + m;
/*    */     int n = paramJG0.er0;
/*    */     if (paramObject == null) {
/*    */       KE();
/*    */       return;
/*    */     } 
/*    */     if (paramObject instanceof String) {
/*    */       if ((paramObject = paramObject).length() == 0) {
/*    */         KE();
/*    */         return;
/*    */       } 
/*    */       tl0 tl01;
/*    */       if (this.oL0.fr0 != (tl01 = this.sG)) {
/*    */         tl01.gx();
/*    */         dQ dQ1 = this.oL0;
/*    */         this.sG.si(dQ1, this.sG.Ub());
/*    */       } 
/*    */       this.oL0.td0 = null;
/*    */       this.oL0.E1((String)paramObject);
/*    */     } else if (paramObject instanceof JG0) {
/*    */       JG0 jG0;
/*    */       if ((jG0 = ((JG0)(paramObject = paramObject)).fr0) != null && jG0 != this.sG) {
/*    */         KE();
/*    */         return;
/*    */       } 
/*    */       this.sG.gx();
/*    */       this.sG.si((JG0)paramObject, this.sG.Ub());
/*    */     } else {
/*    */       throw new IllegalArgumentException("Unsupported data type");
/*    */     } 
/*    */     this.sG.mM();
/*    */     int j = this.sG.xY;
/*    */     int i1 = this.sG.HC;
/*    */     switch (paramet.ordinal()) {
/*    */       case 2:
/*    */       case 6:
/*    */       case 8:
/*    */         m -= j;
/*    */         break;
/*    */       case 1:
/*    */       case 3:
/*    */       case 4:
/*    */         m -= j / 2;
/*    */         break;
/*    */     } 
/*    */     switch (paramet.ordinal()) {
/*    */       case 4:
/*    */       case 7:
/*    */       case 8:
/*    */         n -= i1;
/*    */         break;
/*    */       case 0:
/*    */       case 1:
/*    */       case 2:
/*    */         n -= i1 / 2;
/*    */         break;
/*    */     } 
/*    */     int i = paramJG0.t8() + n;
/*    */     int k;
/*    */     if ((k = paramJG0.YR() + m) + j > this.Bo0.xY)
/*    */       k = this.Bo0.xY - j; 
/*    */     if (i + i1 > this.Bo0.HC)
/*    */       i = this.Bo0.HC - i1; 
/*    */     if (k < 0)
/*    */       k = 0; 
/*    */     if (i < 0)
/*    */       i = 0; 
/*    */     this.sG.ME(k, i);
/*    */     this.sG.wI0(true);
/*    */     UB0.Kg0.fN(new cq(this));
/*    */   }
/*    */   
/*    */   public final void V90(throws paramthrows) {
/*    */     StringBuilder stringBuilder;
/*    */     Pw pw;
/*    */     Hc0 hc0;
/*    */     int j;
/*    */     kg0 kg0 = null;
/*    */     if (Bz.SF) {
/*    */       Xi xi;
/*    */       if ((xi = this.bk.iJ0) != null)
/*    */         kg0 = xi.eA0(); 
/*    */       Wl wl;
/*    */       if ((wl = this.bk.K7) != null && wl instanceof vH)
/*    */         kg0 = ((vH)wl).jv0; 
/*    */       if (this.Am0 + 1000000000L < System.nanoTime()) {
/*    */         if (kg0 != null) {
/*    */           long l = kg0.jB;
/*    */           this.ZP[0] = l;
/*    */           l = kg0.nn;
/*    */           this.ZP[1] = l;
/*    */           kg0.nn = 0;
/*    */           kg0.jB = 0;
/*    */         } 
/*    */         this.Am0 = System.nanoTime();
/*    */       } 
/*    */     } 
/*    */     if (km.XU())
/*    */       if (B5()) {
/*    */         JG0 jG0;
/*    */         if ((jG0 = this.Oi0) != null)
/*    */           jG0.wI0(false); 
/*    */         if ((jG0 = this.Nn) != null)
/*    */           jG0.wI0(false); 
/*    */       } else {
/*    */         JG0 jG0;
/*    */         if ((jG0 = this.Oi0) != null)
/*    */           jG0.wI0(true); 
/*    */         if ((jG0 = this.Nn) != null)
/*    */           jG0.wI0(true); 
/*    */       }  
/*    */     if (h1.Lf0)
/*    */       this.Fe0.wI0(false); 
/*    */     super.V90(paramthrows);
/*    */     if (h1.Lf0) {
/*    */       this.Fe0.wI0(true);
/*    */       dQ dQ1;
/*    */       I i1;
/*    */       if ((i1 = (dQ1 = this.Fe0).db0) != null && i1.mi) {
/*    */         dQ1.NL0(paramthrows);
/*    */       } else if (dQ1.l0) {
/*    */         dQ1.Kr0(paramthrows);
/*    */       } else {
/*    */         dQ1.V90(paramthrows);
/*    */       } 
/*    */     } 
/*    */     if (this.o90 + 500000000L > System.nanoTime())
/*    */       return; 
/*    */     this.o90 = System.nanoTime();
/*    */     km.iE0.getClass();
/*    */     int i;
/*    */     if (this.Oi0 != null && (i = 100) != this.mk0) {
/*    */       this.mk0 = i;
/*    */       if ((i = Math.round(i / 10.0F) * 10) < 10)
/*    */         i = 10; 
/*    */       this.Oi0.jz0("mobile-battery-" + i);
/*    */     } 
/*    */     if (!Bz.e00) {
/*    */       if (!this.Fe0.wL.toString().isEmpty())
/*    */         this.Fe0.E1(""); 
/*    */       return;
/*    */     } 
/*    */     long arrayOfLong[], l1, l2, l3;
/*    */     int k;
/*    */     byte b;
/*    */     for (l1 = Long.MAX_VALUE, l2 = 0L, l3 = 0L, k = (arrayOfLong = Pw.Qd).length, b = 0; b < k; ) {
/*    */       long l;
/*    */       if ((l = arrayOfLong[b]) < l1)
/*    */         l1 = l; 
/*    */       if (l > l2)
/*    */         l2 = l; 
/*    */       l3 += l;
/*    */       if (l == 0L)
/*    */         return; 
/*    */       b++;
/*    */     } 
/*    */     l3 /= Pw.Qd.length;
/*    */     if (Pw.xc0 != null) {
/*    */       String str1, str3;
/*    */       double d;
/*    */       this.Fe0.E1(B40.df("min / max / avg / lst\n").append(this.Do.format(((float)l1 / 1000000.0F))).append(" / ").append(this.Do.format(((float)l2 / 1000000.0F))).append(" / ").append(this.Do.format(d = ((float)l3 / 1000000.0F))).append(" / ").append(this.Do.format(d)).toString());
/*    */       String str2;
/*    */       Iterator<Map.Entry> iterator;
/*    */       for (str2 = this.Fe0.wL.toString() + "\n\n", iterator = Pw.xc0.entrySet().iterator(); iterator.hasNext(); ) {
/*    */         Map.Entry<?, St0> entry;
/*    */         St0 st0;
/*    */         long[] arrayOfLong1;
/*    */         byte b1;
/*    */         for (j = (arrayOfLong1 = (st0 = (entry = iterator.next()).getValue()).cd0).length, b1 = 0; b1 < j; ) {
/*    */           float f;
/*    */           if ((f = (float)arrayOfLong1[b1]) < st0.g50)
/*    */             st0.g50 = f; 
/*    */           if (f > st0.YJ0)
/*    */             st0.YJ0 = f; 
/*    */           st0.fd0 += f;
/*    */           b1++;
/*    */         } 
/*    */         st0.g50 /= 1000000.0F;
/*    */         st0.YJ0 /= 1000000.0F;
/*    */         st0.fd0 = st0.fd0 / st0.cd0.length / 1000000.0F;
/*    */         str2 = B40.df(str2).append((String)entry.getKey()).append(" = ").append(entry.getValue()).append("\n").toString();
/*    */         if (((St0)entry.getValue()).fd0 > 0.01D && (((St0)entry.getValue()).j50 > 0.0F || ((St0)entry.getValue()).wi0 > 0))
/*    */           str2 = zw.vz(str2, "- Vertex count ").append(this.Ux0.format(((St0)entry.getValue()).j50)).append("\n- Render calls ").append(this.Ux0.format(((St0)entry.getValue()).wi0)).append("\n- Texture binds ").append(this.Ux0.format(((St0)entry.getValue()).ou0)).append("\n- Shader binds ").append(this.Ux0.format(((St0)entry.getValue()).ot)).append("\n\n").toString(); 
/*    */       } 
/*    */       dQ dQ1 = this.Fe0;
/*    */       StringBuilder stringBuilder1 = zw.vz(str2, "\n- Vertex count ").append(this.Ux0.format(km.ZY.zY.eO.COm2)).append("\n- Render calls ").append(this.Ux0.format(km.ZY.zY.w20)).append("\n- Texture Binds ").append(this.Ux0.format(km.ZY.zY.mG)).append("\n- Shader Binds ").append(this.Ux0.format(km.ZY.zY.ZZ)).append("\n- GL Calls ").append(this.Ux0.format(km.ZY.zY.MD));
/*    */       if (kg0 != null) {
/*    */         StringBuilder stringBuilder3 = B40.df("\n\nParticle System:\n- Effects: ").append(kg0.X90.Z8).append("\n- Batches: ");
/*    */         int n = 0;
/*    */         for (Hc0 hc01 = kg0.X90.r30(); hc01.hasNext(); n = ((ParticleEffectExt)hc01.next()).getBatchSize() + n);
/*    */         StringBuilder stringBuilder2 = stringBuilder3.append(n).append("\n- Billboards: ");
/*    */         int m = 0;
/*    */         for (hc0 = kg0.X90.r30(); hc0.hasNext(); m = ((ParticleEffectExt)hc0.next()).getBatchBufferedCount() + m);
/*    */         str1 = stringBuilder2.append(m).append("\n- Updates: ").append(this.ZP[0]).append("/s\n- PhysicsUpdates: ").append(this.ZP[1]).append("/s").toString();
/*    */       } else {
/*    */         str1 = "";
/*    */       } 
/*    */       stringBuilder = stringBuilder1.append(this);
/*    */       Pw pw1;
/*    */       gt0 gt0;
/*    */       if ((((gt0 = (pw1 = km.wI0).Jb0) != null) ? gt0.J7 : pw1.Uc0) != null) {
/*    */         StringBuilder stringBuilder2 = B40.df("\nFrame: ");
/*    */         gt0 gt01;
/*    */         str3 = stringBuilder2.append((((gt01 = (pw = km.wI0).Jb0) != null) ? gt01.J7 : pw.Uc0).Rq0).toString();
/*    */       } else {
/*    */         str3 = "";
/*    */       } 
/*    */       dQ1.E1(append(str3).toString());
/*    */     } else {
/*    */       ((js)super).Fe0.E1(((js)super).Do.format(((float)pw / 1000000.0F)) + " / " + ((js)super).Do.format(((float)hc0 / 1000000.0F)) + " / " + ((js)super).Do.format(((float)j / 1000000.0F)) + " min/max/avg");
/*    */     } 
/*    */   }
/*    */   
/*    */   public final void jv0(boolean paramBoolean, int paramInt1, int paramInt2, Qv0 paramQv0, Qv0[] paramArrayOfQv0, int paramInt3) {
/*    */     // Byte code:
/*    */     //   0: aload #5
/*    */     //   2: arraylength
/*    */     //   3: ifne -> 7
/*    */     //   6: return
/*    */     //   7: aload #5
/*    */     //   9: invokestatic stream : ([Ljava/lang/Object;)Ljava/util/stream/Stream;
/*    */     //   12: <illegal opcode> test : ()Ljava/util/function/Predicate;
/*    */     //   17: invokeinterface noneMatch : (Ljava/util/function/Predicate;)Z
/*    */     //   22: ifeq -> 26
/*    */     //   25: return
/*    */     //   26: getstatic f/UB0.Kg0 : Lf/Q50;
/*    */     //   29: aload_0
/*    */     //   30: iload_1
/*    */     //   31: iload_3
/*    */     //   32: iload #6
/*    */     //   34: aload #4
/*    */     //   36: aload #5
/*    */     //   38: iload_2
/*    */     //   39: <illegal opcode> run : (Lf/js;ZIILf/Qv0;[Lf/Qv0;I)Ljava/lang/Runnable;
/*    */     //   44: invokevirtual fN : (Ljava/lang/Runnable;)V
/*    */     //   47: return
/*    */   }
/*    */   
/*    */   public final void UU(int paramInt1, int paramInt2, String paramString) {
/*    */     // Byte code:
/*    */     //   0: getstatic f/UB0.Kg0 : Lf/Q50;
/*    */     //   3: aload_0
/*    */     //   4: aload_3
/*    */     //   5: iload_1
/*    */     //   6: iload_2
/*    */     //   7: <illegal opcode> run : (Lf/js;Ljava/lang/String;II)Ljava/lang/Runnable;
/*    */     //   12: invokevirtual fN : (Ljava/lang/Runnable;)V
/*    */     //   15: return
/*    */   }
/*    */   
/*    */   public final void h4(int paramInt, boolean paramBoolean1, boolean paramBoolean2, boolean paramBoolean3, boolean paramBoolean4, boolean paramBoolean5) {
/*    */     Ia ia3;
/*    */     if ((ia3 = this.aux) != null) {
/*    */       ia3.ra0();
/*    */       this.aux = null;
/*    */       if ((bX = this.th) != null)
/*    */         VA0.c90(Fy()); 
/*    */       return;
/*    */     } 
/*    */     if (!paramBoolean1)
/*    */       return; 
/*    */     this((js)this, paramBoolean2, paramBoolean3, paramBoolean4, paramBoolean5, paramInt);
/*    */     BX bX;
/*    */     ((js)super).aux = ia2;
/*    */     Ia ia2;
/*    */     (ia2 = new Ia()).mM();
/*    */     Ia ia1 = ((js)super).aux;
/*    */     si(this, Ub());
/*    */   }
/*    */   
/*    */   public final void Pu(int paramInt, String paramString) {
/*    */     this(this, paramString.trim(), paramInt);
/*    */     QW qW;
/*    */     this.U1.add(qW);
/*    */     si(qW, Ub());
/*    */     Af(qW);
/*    */   }
/*    */   
/*    */   public final void L8(B3 paramB3) {
/*    */     this(Ml0.OH0(2800), new MJ(this));
/*    */     B3 b3;
/*    */     Hk0 hk0;
/*    */     paramB3.aV.add(hk0);
/*    */     this(Ml0.OH0(2810));
/*    */     this(Ml0.OH0(23000), new W50());
/*    */     (new B3()).aV.add(hk0);
/*    */     this(Ml0.OH0(23001), new PT());
/*    */     (new B3()).aV.add(hk0);
/*    */     this(Ml0.OH0(61), new Kt0());
/*    */     (new B3()).aV.add(hk0);
/*    */     paramB3.aV.add(this);
/*    */   }
/*    */   
/*    */   public final B3 bm(Jo paramJo, String paramString, int paramInt1, int paramInt2, boolean paramBoolean) {
/*    */     // Byte code:
/*    */     //   0: aload_1
/*    */     //   1: ifnonnull -> 17
/*    */     //   4: new f/B3
/*    */     //   7: dup
/*    */     //   8: astore #6
/*    */     //   10: aload_2
/*    */     //   11: invokespecial <init> : (Ljava/lang/String;)V
/*    */     //   14: goto -> 28
/*    */     //   17: new f/fa0
/*    */     //   20: dup
/*    */     //   21: astore #6
/*    */     //   23: aload_1
/*    */     //   24: aload_2
/*    */     //   25: invokespecial <init> : (Lf/Jo;Ljava/lang/String;)V
/*    */     //   28: aload_1
/*    */     //   29: ifnull -> 57
/*    */     //   32: getstatic f/km.a3 : Lf/vh0;
/*    */     //   35: getfield Ct : Lf/Jo;
/*    */     //   38: getfield Jg : I
/*    */     //   41: aload_1
/*    */     //   42: getfield Jg : I
/*    */     //   45: if_icmpne -> 57
/*    */     //   48: aload_0
/*    */     //   49: aload #6
/*    */     //   51: invokevirtual L8 : (Lf/B3;)V
/*    */     //   54: goto -> 1404
/*    */     //   57: new f/Hk0
/*    */     //   60: dup
/*    */     //   61: astore #7
/*    */     //   63: sipush #2250
/*    */     //   66: invokestatic OH0 : (I)Ljava/lang/String;
/*    */     //   69: invokespecial <init> : (Ljava/lang/String;)V
/*    */     //   72: new f/Hk0
/*    */     //   75: dup
/*    */     //   76: astore #8
/*    */     //   78: sipush #2251
/*    */     //   81: invokestatic OH0 : (I)Ljava/lang/String;
/*    */     //   84: invokespecial <init> : (Ljava/lang/String;)V
/*    */     //   87: new f/Hk0
/*    */     //   90: dup
/*    */     //   91: astore #9
/*    */     //   93: sipush #2259
/*    */     //   96: invokestatic OH0 : (I)Ljava/lang/String;
/*    */     //   99: invokespecial <init> : (Ljava/lang/String;)V
/*    */     //   102: new f/Hk0
/*    */     //   105: dup
/*    */     //   106: astore #10
/*    */     //   108: sipush #2252
/*    */     //   111: invokestatic OH0 : (I)Ljava/lang/String;
/*    */     //   114: invokespecial <init> : (Ljava/lang/String;)V
/*    */     //   117: new f/Hk0
/*    */     //   120: astore #11
/*    */     //   122: getstatic f/km.u4 : Lf/R8;
/*    */     //   125: getfield E50 : Lf/Oc0;
/*    */     //   128: dup
/*    */     //   129: aload_2
/*    */     //   130: swap
/*    */     //   131: invokevirtual getClass : ()Ljava/lang/Class;
/*    */     //   134: pop
/*    */     //   135: getstatic java/util/Locale.ENGLISH : Ljava/util/Locale;
/*    */     //   138: invokevirtual toLowerCase : (Ljava/util/Locale;)Ljava/lang/String;
/*    */     //   141: astore #12
/*    */     //   143: getfield tl0 : Lf/Ut0;
/*    */     //   146: dup
/*    */     //   147: astore #13
/*    */     //   149: invokevirtual getClass : ()Ljava/lang/Class;
/*    */     //   152: pop
/*    */     //   153: new f/mt
/*    */     //   156: dup
/*    */     //   157: aload #13
/*    */     //   159: invokespecial <init> : (Lf/Ut0;)V
/*    */     //   162: invokevirtual iterator : ()Ljava/util/Iterator;
/*    */     //   165: astore #13
/*    */     //   167: aload #13
/*    */     //   169: checkcast f/DA0
/*    */     //   172: invokevirtual hasNext : ()Z
/*    */     //   175: ifeq -> 215
/*    */     //   178: aload #13
/*    */     //   180: checkcast f/iF0
/*    */     //   183: invokevirtual next : ()Ljava/lang/Object;
/*    */     //   186: checkcast f/CD0
/*    */     //   189: dup
/*    */     //   190: astore #14
/*    */     //   192: invokevirtual wN : ()Lf/FV;
/*    */     //   195: getfield Pb : Ljava/lang/String;
/*    */     //   198: getstatic java/util/Locale.ENGLISH : Ljava/util/Locale;
/*    */     //   201: invokevirtual toLowerCase : (Ljava/util/Locale;)Ljava/lang/String;
/*    */     //   204: aload #12
/*    */     //   206: invokevirtual equals : (Ljava/lang/Object;)Z
/*    */     //   209: ifeq -> 167
/*    */     //   212: goto -> 218
/*    */     //   215: aconst_null
/*    */     //   216: astore #14
/*    */     //   218: aload #14
/*    */     //   220: ifnull -> 234
/*    */     //   223: sipush #2254
/*    */     //   226: invokestatic OH0 : (I)Ljava/lang/String;
/*    */     //   229: astore #12
/*    */     //   231: goto -> 242
/*    */     //   234: sipush #2253
/*    */     //   237: invokestatic OH0 : (I)Ljava/lang/String;
/*    */     //   240: astore #12
/*    */     //   242: aload #11
/*    */     //   244: aload #12
/*    */     //   246: invokespecial <init> : (Ljava/lang/String;)V
/*    */     //   249: new f/Hk0
/*    */     //   252: dup
/*    */     //   253: astore #12
/*    */     //   255: sipush #2255
/*    */     //   258: invokestatic OH0 : (I)Ljava/lang/String;
/*    */     //   261: invokespecial <init> : (Ljava/lang/String;)V
/*    */     //   264: new f/Hk0
/*    */     //   267: dup
/*    */     //   268: astore #13
/*    */     //   270: sipush #2257
/*    */     //   273: invokestatic OH0 : (I)Ljava/lang/String;
/*    */     //   276: invokespecial <init> : (Ljava/lang/String;)V
/*    */     //   279: new f/Hk0
/*    */     //   282: dup
/*    */     //   283: astore #14
/*    */     //   285: sipush #2258
/*    */     //   288: invokestatic OH0 : (I)Ljava/lang/String;
/*    */     //   291: invokespecial <init> : (Ljava/lang/String;)V
/*    */     //   294: new f/Hk0
/*    */     //   297: dup
/*    */     //   298: astore #15
/*    */     //   300: aload_2
/*    */     //   301: aload #14
/*    */     //   303: aload_2
/*    */     //   304: aload #10
/*    */     //   306: aload_2
/*    */     //   307: aload #12
/*    */     //   309: aload_2
/*    */     //   310: aload #11
/*    */     //   312: aload_0
/*    */     //   313: aload_2
/*    */     //   314: aload #9
/*    */     //   316: aload_0
/*    */     //   317: aload_2
/*    */     //   318: aload #8
/*    */     //   320: aload_0
/*    */     //   321: aload_2
/*    */     //   322: aload #7
/*    */     //   324: aload_0
/*    */     //   325: iload #5
/*    */     //   327: aload #15
/*    */     //   329: sipush #2261
/*    */     //   332: invokestatic OH0 : (I)Ljava/lang/String;
/*    */     //   335: invokespecial <init> : (Ljava/lang/String;)V
/*    */     //   338: aload_2
/*    */     //   339: iload_3
/*    */     //   340: iload #4
/*    */     //   342: <illegal opcode> run : (Lf/js;ZLjava/lang/String;II)Ljava/lang/Runnable;
/*    */     //   347: putfield rv : Ljava/lang/Runnable;
/*    */     //   350: <illegal opcode> run : (Lf/js;Ljava/lang/String;)Ljava/lang/Runnable;
/*    */     //   355: putfield rv : Ljava/lang/Runnable;
/*    */     //   358: <illegal opcode> run : (Lf/js;Ljava/lang/String;)Ljava/lang/Runnable;
/*    */     //   363: putfield rv : Ljava/lang/Runnable;
/*    */     //   366: <illegal opcode> run : (Lf/js;Ljava/lang/String;)Ljava/lang/Runnable;
/*    */     //   371: putfield rv : Ljava/lang/Runnable;
/*    */     //   374: <illegal opcode> run : (Ljava/lang/String;)Ljava/lang/Runnable;
/*    */     //   379: putfield rv : Ljava/lang/Runnable;
/*    */     //   382: <illegal opcode> run : (Ljava/lang/String;)Ljava/lang/Runnable;
/*    */     //   387: putfield rv : Ljava/lang/Runnable;
/*    */     //   390: <illegal opcode> run : (Ljava/lang/String;)Ljava/lang/Runnable;
/*    */     //   395: putfield rv : Ljava/lang/Runnable;
/*    */     //   398: <illegal opcode> run : (Ljava/lang/String;)Ljava/lang/Runnable;
/*    */     //   403: putfield rv : Ljava/lang/Runnable;
/*    */     //   406: getstatic f/km.a3 : Lf/vh0;
/*    */     //   409: aload_2
/*    */     //   410: invokevirtual et : (Ljava/lang/String;)Lf/Jo;
/*    */     //   413: dup
/*    */     //   414: astore_0
/*    */     //   415: ifnull -> 442
/*    */     //   418: aload_0
/*    */     //   419: getfield kK0 : Lf/Z50;
/*    */     //   422: dup
/*    */     //   423: astore_3
/*    */     //   424: getstatic f/Z50.sF0 : Lf/Z50;
/*    */     //   427: if_acmpeq -> 437
/*    */     //   430: aload_3
/*    */     //   431: getstatic f/Z50.M3 : Lf/Z50;
/*    */     //   434: if_acmpne -> 442
/*    */     //   437: iconst_1
/*    */     //   438: istore_3
/*    */     //   439: goto -> 444
/*    */     //   442: iconst_0
/*    */     //   443: istore_3
/*    */     //   444: aload_0
/*    */     //   445: aload #13
/*    */     //   447: aload_1
/*    */     //   448: <illegal opcode> run : (Lf/Jo;)Ljava/lang/Runnable;
/*    */     //   453: putfield rv : Ljava/lang/Runnable;
/*    */     //   456: ifnull -> 478
/*    */     //   459: iload_3
/*    */     //   460: ifeq -> 467
/*    */     //   463: aload #13
/*    */     //   465: astore #7
/*    */     //   467: aload #6
/*    */     //   469: getfield aV : Ljava/util/ArrayList;
/*    */     //   472: aload #7
/*    */     //   474: invokevirtual add : (Ljava/lang/Object;)Z
/*    */     //   477: pop
/*    */     //   478: aload_0
/*    */     //   479: aload #6
/*    */     //   481: getfield aV : Ljava/util/ArrayList;
/*    */     //   484: aload #8
/*    */     //   486: invokevirtual add : (Ljava/lang/Object;)Z
/*    */     //   489: pop
/*    */     //   490: ifnull -> 506
/*    */     //   493: aload_0
/*    */     //   494: getfield Jg : I
/*    */     //   497: getstatic f/km.a3 : Lf/vh0;
/*    */     //   500: getfield yD : I
/*    */     //   503: if_icmpeq -> 517
/*    */     //   506: aload #6
/*    */     //   508: getfield aV : Ljava/util/ArrayList;
/*    */     //   511: aload #9
/*    */     //   513: invokevirtual add : (Ljava/lang/Object;)Z
/*    */     //   516: pop
/*    */     //   517: aload_0
/*    */     //   518: ifnull -> 563
/*    */     //   521: getstatic f/km.u4 : Lf/R8;
/*    */     //   524: dup
/*    */     //   525: astore_3
/*    */     //   526: ifnull -> 563
/*    */     //   529: aload_3
/*    */     //   530: getfield jG0 : Lf/yM;
/*    */     //   533: getfield dL : Z
/*    */     //   536: ifne -> 552
/*    */     //   539: aload_3
/*    */     //   540: getfield z2 : Lf/Uc0;
/*    */     //   543: getfield Nul : Lf/aq0;
/*    */     //   546: getfield va0 : Z
/*    */     //   549: ifeq -> 563
/*    */     //   552: aload #6
/*    */     //   554: getfield aV : Ljava/util/ArrayList;
/*    */     //   557: aload #10
/*    */     //   559: invokevirtual add : (Ljava/lang/Object;)Z
/*    */     //   562: pop
/*    */     //   563: getstatic f/km.u4 : Lf/R8;
/*    */     //   566: dup
/*    */     //   567: astore_3
/*    */     //   568: ifnull -> 713
/*    */     //   571: aload_3
/*    */     //   572: getfield Tr0 : Lf/Yp0;
/*    */     //   575: dup
/*    */     //   576: astore_3
/*    */     //   577: ifnull -> 702
/*    */     //   580: aload_3
/*    */     //   581: getfield nt0 : Lf/Ut0;
/*    */     //   584: dup
/*    */     //   585: dup
/*    */     //   586: astore_3
/*    */     //   587: getfield ir0 : I
/*    */     //   590: dup
/*    */     //   591: istore #4
/*    */     //   593: anewarray f/HH
/*    */     //   596: astore #5
/*    */     //   598: getfield ND : [Ljava/lang/Object;
/*    */     //   601: dup
/*    */     //   602: astore #7
/*    */     //   604: aload_3
/*    */     //   605: getfield JO : [B
/*    */     //   608: astore_3
/*    */     //   609: arraylength
/*    */     //   610: istore #8
/*    */     //   612: iconst_0
/*    */     //   613: istore #9
/*    */     //   615: iload #8
/*    */     //   617: dup
/*    */     //   618: iconst_m1
/*    */     //   619: iadd
/*    */     //   620: istore #8
/*    */     //   622: ifle -> 657
/*    */     //   625: aload_3
/*    */     //   626: iload #8
/*    */     //   628: baload
/*    */     //   629: iconst_1
/*    */     //   630: if_icmpne -> 615
/*    */     //   633: aload #5
/*    */     //   635: aload #7
/*    */     //   637: iload #9
/*    */     //   639: iconst_1
/*    */     //   640: iadd
/*    */     //   641: istore #10
/*    */     //   643: iload #8
/*    */     //   645: aaload
/*    */     //   646: iload #9
/*    */     //   648: swap
/*    */     //   649: aastore
/*    */     //   650: iload #10
/*    */     //   652: istore #9
/*    */     //   654: goto -> 615
/*    */     //   657: iconst_0
/*    */     //   658: istore_3
/*    */     //   659: iload_3
/*    */     //   660: iload #4
/*    */     //   662: if_icmpge -> 694
/*    */     //   665: aload #5
/*    */     //   667: iload_3
/*    */     //   668: aaload
/*    */     //   669: dup
/*    */     //   670: astore #7
/*    */     //   672: getfield TD : Lf/FV;
/*    */     //   675: getfield Pb : Ljava/lang/String;
/*    */     //   678: aload_2
/*    */     //   679: invokevirtual equals : (Ljava/lang/Object;)Z
/*    */     //   682: ifeq -> 688
/*    */     //   685: goto -> 697
/*    */     //   688: iinc #3, 1
/*    */     //   691: goto -> 659
/*    */     //   694: aconst_null
/*    */     //   695: astore #7
/*    */     //   697: aload #7
/*    */     //   699: ifnonnull -> 713
/*    */     //   702: aload #6
/*    */     //   704: getfield aV : Ljava/util/ArrayList;
/*    */     //   707: aload #14
/*    */     //   709: invokevirtual add : (Ljava/lang/Object;)Z
/*    */     //   712: pop
/*    */     //   713: aload_1
/*    */     //   714: aload #6
/*    */     //   716: getfield aV : Ljava/util/ArrayList;
/*    */     //   719: aload #11
/*    */     //   721: invokevirtual add : (Ljava/lang/Object;)Z
/*    */     //   724: pop
/*    */     //   725: ifnull -> 735
/*    */     //   728: aload_1
/*    */     //   729: getfield CC : B
/*    */     //   732: ifne -> 746
/*    */     //   735: aload #6
/*    */     //   737: getfield aV : Ljava/util/ArrayList;
/*    */     //   740: aload #12
/*    */     //   742: invokevirtual add : (Ljava/lang/Object;)Z
/*    */     //   745: pop
/*    */     //   746: aload #6
/*    */     //   748: getfield aV : Ljava/util/ArrayList;
/*    */     //   751: aload #15
/*    */     //   753: invokevirtual add : (Ljava/lang/Object;)Z
/*    */     //   756: pop
/*    */     //   757: iconst_1
/*    */     //   758: invokestatic D70 : (I)Z
/*    */     //   761: ifeq -> 1404
/*    */     //   764: new f/B3
/*    */     //   767: dup
/*    */     //   768: astore_1
/*    */     //   769: aload #6
/*    */     //   771: dup
/*    */     //   772: aload_1
/*    */     //   773: ldc_w 'Admin'
/*    */     //   776: invokespecial <init> : (Ljava/lang/String;)V
/*    */     //   779: new f/Hk0
/*    */     //   782: dup
/*    */     //   783: astore_3
/*    */     //   784: aload_2
/*    */     //   785: aload_3
/*    */     //   786: ldc_w 'Player Info'
/*    */     //   789: invokespecial <init> : (Ljava/lang/String;)V
/*    */     //   792: <illegal opcode> run : (Ljava/lang/String;)Ljava/lang/Runnable;
/*    */     //   797: putfield rv : Ljava/lang/Runnable;
/*    */     //   800: new f/Pu0
/*    */     //   803: dup
/*    */     //   804: astore #4
/*    */     //   806: invokespecial <init> : ()V
/*    */     //   809: getfield aV : Ljava/util/ArrayList;
/*    */     //   812: aload #4
/*    */     //   814: invokevirtual add : (Ljava/lang/Object;)Z
/*    */     //   817: pop
/*    */     //   818: getfield aV : Ljava/util/ArrayList;
/*    */     //   821: aload_1
/*    */     //   822: invokevirtual add : (Ljava/lang/Object;)Z
/*    */     //   825: pop
/*    */     //   826: getfield aV : Ljava/util/ArrayList;
/*    */     //   829: aload_3
/*    */     //   830: invokevirtual add : (Ljava/lang/Object;)Z
/*    */     //   833: pop
/*    */     //   834: iconst_4
/*    */     //   835: invokestatic D70 : (I)Z
/*    */     //   838: ifeq -> 1053
/*    */     //   841: new f/B3
/*    */     //   844: dup
/*    */     //   845: astore_3
/*    */     //   846: ldc_w 'Warn'
/*    */     //   849: invokespecial <init> : (Ljava/lang/String;)V
/*    */     //   852: getstatic f/wQ.kM : [Lf/wQ;
/*    */     //   855: astore #4
/*    */     //   857: bipush #10
/*    */     //   859: istore #5
/*    */     //   861: iconst_0
/*    */     //   862: istore #7
/*    */     //   864: iload #7
/*    */     //   866: iload #5
/*    */     //   868: if_icmpge -> 953
/*    */     //   871: aload #4
/*    */     //   873: iload #7
/*    */     //   875: aaload
/*    */     //   876: dup
/*    */     //   877: astore #8
/*    */     //   879: getstatic f/wQ.l8 : Lf/wQ;
/*    */     //   882: if_acmpeq -> 910
/*    */     //   885: aload_3
/*    */     //   886: aload_2
/*    */     //   887: aload #8
/*    */     //   889: invokevirtual name : ()Ljava/lang/String;
/*    */     //   892: astore #9
/*    */     //   894: aload #8
/*    */     //   896: <illegal opcode> run : (Ljava/lang/String;Lf/wQ;)Ljava/lang/Runnable;
/*    */     //   901: aload #9
/*    */     //   903: swap
/*    */     //   904: invokevirtual mD : (Ljava/lang/String;Ljava/lang/Runnable;)V
/*    */     //   907: goto -> 947
/*    */     //   910: aload_3
/*    */     //   911: new f/Hk0
/*    */     //   914: dup
/*    */     //   915: astore #9
/*    */     //   917: aload_2
/*    */     //   918: aload #8
/*    */     //   920: aload #9
/*    */     //   922: aload #8
/*    */     //   924: invokevirtual name : ()Ljava/lang/String;
/*    */     //   927: invokespecial <init> : (Ljava/lang/String;)V
/*    */     //   930: <illegal opcode> run : (Ljava/lang/String;Lf/wQ;)Ljava/lang/Runnable;
/*    */     //   935: putfield rv : Ljava/lang/Runnable;
/*    */     //   938: getfield aV : Ljava/util/ArrayList;
/*    */     //   941: aload #9
/*    */     //   943: invokevirtual add : (Ljava/lang/Object;)Z
/*    */     //   946: pop
/*    */     //   947: iinc #7, 1
/*    */     //   950: goto -> 864
/*    */     //   953: aload #6
/*    */     //   955: aload_1
/*    */     //   956: dup
/*    */     //   957: dup
/*    */     //   958: getfield aV : Ljava/util/ArrayList;
/*    */     //   961: aload_3
/*    */     //   962: invokevirtual add : (Ljava/lang/Object;)Z
/*    */     //   965: pop
/*    */     //   966: new f/Hk0
/*    */     //   969: dup
/*    */     //   970: astore_3
/*    */     //   971: aload_2
/*    */     //   972: aload_3
/*    */     //   973: ldc_w 'Mute'
/*    */     //   976: invokespecial <init> : (Ljava/lang/String;)V
/*    */     //   979: <illegal opcode> run : (Ljava/lang/String;)Ljava/lang/Runnable;
/*    */     //   984: putfield rv : Ljava/lang/Runnable;
/*    */     //   987: getfield aV : Ljava/util/ArrayList;
/*    */     //   990: aload_3
/*    */     //   991: invokevirtual add : (Ljava/lang/Object;)Z
/*    */     //   994: pop
/*    */     //   995: new f/Hk0
/*    */     //   998: dup
/*    */     //   999: astore_3
/*    */     //   1000: aload_2
/*    */     //   1001: aload_3
/*    */     //   1002: ldc_w 'Mute Channel'
/*    */     //   1005: invokespecial <init> : (Ljava/lang/String;)V
/*    */     //   1008: <illegal opcode> run : (Ljava/lang/String;)Ljava/lang/Runnable;
/*    */     //   1013: putfield rv : Ljava/lang/Runnable;
/*    */     //   1016: getfield aV : Ljava/util/ArrayList;
/*    */     //   1019: aload_3
/*    */     //   1020: invokevirtual add : (Ljava/lang/Object;)Z
/*    */     //   1023: pop
/*    */     //   1024: new f/Hk0
/*    */     //   1027: dup
/*    */     //   1028: astore_3
/*    */     //   1029: aload_2
/*    */     //   1030: aload_3
/*    */     //   1031: ldc_w 'ACP'
/*    */     //   1034: invokespecial <init> : (Ljava/lang/String;)V
/*    */     //   1037: <illegal opcode> run : (Ljava/lang/String;)Ljava/lang/Runnable;
/*    */     //   1042: putfield rv : Ljava/lang/Runnable;
/*    */     //   1045: getfield aV : Ljava/util/ArrayList;
/*    */     //   1048: aload_3
/*    */     //   1049: invokevirtual add : (Ljava/lang/Object;)Z
/*    */     //   1052: pop
/*    */     //   1053: iconst_1
/*    */     //   1054: invokestatic D70 : (I)Z
/*    */     //   1057: ifeq -> 1250
/*    */     //   1060: new f/B3
/*    */     //   1063: dup
/*    */     //   1064: astore_3
/*    */     //   1065: ldc_w 'Set Channel'
/*    */     //   1068: invokespecial <init> : (Ljava/lang/String;)V
/*    */     //   1071: getstatic f/ZY.R70 : [Lf/ZY;
/*    */     //   1074: dup
/*    */     //   1075: astore #4
/*    */     //   1077: arraylength
/*    */     //   1078: istore #5
/*    */     //   1080: iconst_0
/*    */     //   1081: istore #7
/*    */     //   1083: iload #7
/*    */     //   1085: iload #5
/*    */     //   1087: if_icmpge -> 1137
/*    */     //   1090: aload #4
/*    */     //   1092: iload #7
/*    */     //   1094: aaload
/*    */     //   1095: dup
/*    */     //   1096: astore #8
/*    */     //   1098: getfield DY : Z
/*    */     //   1101: ifne -> 1107
/*    */     //   1104: goto -> 1131
/*    */     //   1107: aload_3
/*    */     //   1108: aload_2
/*    */     //   1109: aload #8
/*    */     //   1111: dup
/*    */     //   1112: getfield UR : I
/*    */     //   1115: invokestatic OH0 : (I)Ljava/lang/String;
/*    */     //   1118: astore #8
/*    */     //   1120: <illegal opcode> run : (Ljava/lang/String;Lf/ZY;)Ljava/lang/Runnable;
/*    */     //   1125: aload #8
/*    */     //   1127: swap
/*    */     //   1128: invokevirtual mD : (Ljava/lang/String;Ljava/lang/Runnable;)V
/*    */     //   1131: iinc #7, 1
/*    */     //   1134: goto -> 1083
/*    */     //   1137: new f/B3
/*    */     //   1140: dup
/*    */     //   1141: astore #4
/*    */     //   1143: ldc_w 'Set Chat Language'
/*    */     //   1146: invokespecial <init> : (Ljava/lang/String;)V
/*    */     //   1149: getstatic f/Xv0.Kf0 : [Lf/Xv0;
/*    */     //   1152: dup
/*    */     //   1153: astore #5
/*    */     //   1155: arraylength
/*    */     //   1156: istore #7
/*    */     //   1158: iconst_0
/*    */     //   1159: istore #8
/*    */     //   1161: iload #8
/*    */     //   1163: iload #7
/*    */     //   1165: if_icmpge -> 1231
/*    */     //   1168: aload #4
/*    */     //   1170: aload_2
/*    */     //   1171: aload #5
/*    */     //   1173: iload #8
/*    */     //   1175: aaload
/*    */     //   1176: dup
/*    */     //   1177: astore #9
/*    */     //   1179: new java/lang/StringBuilder
/*    */     //   1182: dup
/*    */     //   1183: aload #9
/*    */     //   1185: swap
/*    */     //   1186: invokespecial <init> : ()V
/*    */     //   1189: getfield Nv0 : Ljava/lang/String;
/*    */     //   1192: invokevirtual append : (Ljava/lang/String;)Ljava/lang/StringBuilder;
/*    */     //   1195: ldc_w ' ('
/*    */     //   1198: invokevirtual append : (Ljava/lang/String;)Ljava/lang/StringBuilder;
/*    */     //   1201: aload #9
/*    */     //   1203: getfield w : Ljava/lang/String;
/*    */     //   1206: ldc_w ')'
/*    */     //   1209: invokestatic Vr0 : (Ljava/lang/StringBuilder;Ljava/lang/String;Ljava/lang/String;)Ljava/lang/String;
/*    */     //   1212: astore #9
/*    */     //   1214: <illegal opcode> run : (Ljava/lang/String;Lf/Xv0;)Ljava/lang/Runnable;
/*    */     //   1219: aload #9
/*    */     //   1221: swap
/*    */     //   1222: invokevirtual mD : (Ljava/lang/String;Ljava/lang/Runnable;)V
/*    */     //   1225: iinc #8, 1
/*    */     //   1228: goto -> 1161
/*    */     //   1231: aload_1
/*    */     //   1232: dup
/*    */     //   1233: getfield aV : Ljava/util/ArrayList;
/*    */     //   1236: aload_3
/*    */     //   1237: invokevirtual add : (Ljava/lang/Object;)Z
/*    */     //   1240: pop
/*    */     //   1241: getfield aV : Ljava/util/ArrayList;
/*    */     //   1244: aload #4
/*    */     //   1246: invokevirtual add : (Ljava/lang/Object;)Z
/*    */     //   1249: pop
/*    */     //   1250: iconst_5
/*    */     //   1251: invokestatic D70 : (I)Z
/*    */     //   1254: ifeq -> 1393
/*    */     //   1257: aload_1
/*    */     //   1258: dup
/*    */     //   1259: dup
/*    */     //   1260: new f/Hk0
/*    */     //   1263: dup
/*    */     //   1264: astore_3
/*    */     //   1265: aload_2
/*    */     //   1266: aload_3
/*    */     //   1267: ldc_w 'Kick'
/*    */     //   1270: invokespecial <init> : (Ljava/lang/String;)V
/*    */     //   1273: <illegal opcode> run : (Ljava/lang/String;)Ljava/lang/Runnable;
/*    */     //   1278: putfield rv : Ljava/lang/Runnable;
/*    */     //   1281: getfield aV : Ljava/util/ArrayList;
/*    */     //   1284: aload_3
/*    */     //   1285: invokevirtual add : (Ljava/lang/Object;)Z
/*    */     //   1288: pop
/*    */     //   1289: new f/Hk0
/*    */     //   1292: dup
/*    */     //   1293: astore_3
/*    */     //   1294: aload_2
/*    */     //   1295: aload_3
/*    */     //   1296: ldc_w 'Teleport To'
/*    */     //   1299: invokespecial <init> : (Ljava/lang/String;)V
/*    */     //   1302: <illegal opcode> run : (Ljava/lang/String;)Ljava/lang/Runnable;
/*    */     //   1307: putfield rv : Ljava/lang/Runnable;
/*    */     //   1310: getfield aV : Ljava/util/ArrayList;
/*    */     //   1313: aload_3
/*    */     //   1314: invokevirtual add : (Ljava/lang/Object;)Z
/*    */     //   1317: pop
/*    */     //   1318: new f/Hk0
/*    */     //   1321: dup
/*    */     //   1322: astore_3
/*    */     //   1323: aload_2
/*    */     //   1324: aload_3
/*    */     //   1325: ldc_w 'Bot Hunt'
/*    */     //   1328: invokespecial <init> : (Ljava/lang/String;)V
/*    */     //   1331: <illegal opcode> run : (Ljava/lang/String;)Ljava/lang/Runnable;
/*    */     //   1336: putfield rv : Ljava/lang/Runnable;
/*    */     //   1339: getfield aV : Ljava/util/ArrayList;
/*    */     //   1342: aload_3
/*    */     //   1343: invokevirtual add : (Ljava/lang/Object;)Z
/*    */     //   1346: pop
/*    */     //   1347: new f/Hk0
/*    */     //   1350: astore_2
/*    */     //   1351: getstatic f/vh0.H90 : I
/*    */     //   1354: iconst_m1
/*    */     //   1355: if_icmpne -> 1365
/*    */     //   1358: ldc_w 'Highlight'
/*    */     //   1361: astore_3
/*    */     //   1362: goto -> 1369
/*    */     //   1365: ldc_w 'Unhighlight'
/*    */     //   1368: astore_3
/*    */     //   1369: aload_1
/*    */     //   1370: aload_2
/*    */     //   1371: aload_0
/*    */     //   1372: aload_2
/*    */     //   1373: aload_3
/*    */     //   1374: invokespecial <init> : (Ljava/lang/String;)V
/*    */     //   1377: <illegal opcode> run : (Lf/Jo;)Ljava/lang/Runnable;
/*    */     //   1382: putfield rv : Ljava/lang/Runnable;
/*    */     //   1385: getfield aV : Ljava/util/ArrayList;
/*    */     //   1388: aload_2
/*    */     //   1389: invokevirtual add : (Ljava/lang/Object;)Z
/*    */     //   1392: pop
/*    */     //   1393: aload #6
/*    */     //   1395: getfield aV : Ljava/util/ArrayList;
/*    */     //   1398: aload #15
/*    */     //   1400: invokevirtual add : (Ljava/lang/Object;)Z
/*    */     //   1403: pop
/*    */     //   1404: aload #6
/*    */     //   1406: areturn
/*    */     // Line number table:
/*    */     //   Java source line number -> byte code offset
/*    */     //   #1	-> 35
/*    */     //   #2	-> 38
/*    */     //   #3	-> 42
/*    */     //   #4	-> 51
/*    */     //   #5	-> 125
/*    */     //   #6	-> 131
/*    */     //   #7	-> 135
/*    */     //   #8	-> 153
/*    */     //   #9	-> 162
/*    */     //   #10	-> 192
/*    */     //   #11	-> 195
/*    */     //   #12	-> 198
/*    */     //   #13	-> 226
/*    */     //   #14	-> 347
/*    */     //   #15	-> 350
/*    */     //   #16	-> 355
/*    */     //   #17	-> 358
/*    */     //   #18	-> 363
/*    */     //   #19	-> 366
/*    */     //   #20	-> 371
/*    */     //   #21	-> 374
/*    */     //   #22	-> 379
/*    */     //   #23	-> 382
/*    */     //   #24	-> 387
/*    */     //   #25	-> 390
/*    */     //   #26	-> 395
/*    */     //   #27	-> 398
/*    */     //   #28	-> 403
/*    */     //   #29	-> 406
/*    */     //   #30	-> 419
/*    */     //   #31	-> 424
/*    */     //   #32	-> 453
/*    */     //   #33	-> 469
/*    */     //   #34	-> 494
/*    */     //   #35	-> 497
/*    */     //   #36	-> 500
/*    */     //   #37	-> 508
/*    */     //   #38	-> 521
/*    */     //   #39	-> 530
/*    */     //   #40	-> 533
/*    */     //   #41	-> 540
/*    */     //   #42	-> 543
/*    */     //   #43	-> 546
/*    */     //   #44	-> 554
/*    */     //   #45	-> 563
/*    */     //   #46	-> 572
/*    */     //   #47	-> 581
/*    */     //   #48	-> 587
/*    */     //   #49	-> 593
/*    */     //   #50	-> 598
/*    */     //   #51	-> 668
/*    */     //   #52	-> 672
/*    */     //   #53	-> 675
/*    */     //   #54	-> 679
/*    */     //   #55	-> 704
/*    */     //   #56	-> 729
/*    */     //   #57	-> 737
/*    */     //   #58	-> 758
/*    */     //   #59	-> 764
/*    */     //   #60	-> 797
/*    */     //   #61	-> 800
/*    */     //   #62	-> 809
/*    */     //   #63	-> 818
/*    */     //   #64	-> 835
/*    */     //   #65	-> 935
/*    */     //   #66	-> 938
/*    */     //   #67	-> 966
/*    */     //   #68	-> 984
/*    */     //   #69	-> 987
/*    */     //   #70	-> 995
/*    */     //   #71	-> 1013
/*    */     //   #72	-> 1016
/*    */     //   #73	-> 1024
/*    */     //   #74	-> 1042
/*    */     //   #75	-> 1045
/*    */     //   #76	-> 1054
/*    */     //   #77	-> 1098
/*    */     //   #78	-> 1112
/*    */     //   #79	-> 1115
/*    */     //   #80	-> 1189
/*    */     //   #81	-> 1192
/*    */     //   #82	-> 1203
/*    */     //   #83	-> 1206
/*    */     //   #84	-> 1214
/*    */     //   #85	-> 1233
/*    */     //   #86	-> 1251
/*    */     //   #87	-> 1278
/*    */     //   #88	-> 1281
/*    */     //   #89	-> 1289
/*    */     //   #90	-> 1307
/*    */     //   #91	-> 1310
/*    */     //   #92	-> 1318
/*    */     //   #93	-> 1336
/*    */     //   #94	-> 1339
/*    */     //   #95	-> 1347
/*    */     //   #96	-> 1382
/*    */     //   #97	-> 1385
/*    */   }
/*    */   
/*    */   public final void YF() {
/*    */     wL wL1;
/*    */     if ((wL1 = this.Lz) != null)
/*    */       wL1.ra0(); 
/*    */     this();
/*    */     this.Lz = new wL();
/*    */     si(wL1, Ub());
/*    */     this.Lz.mM();
/*    */     this.Lz.ME(this.bk.dG() / 2 - this.Lz.xY / 2, this.bk.k1() / 2 - this.Lz.HC / 2);
/*    */     this.Lz.wI0(true);
/*    */   }
/*    */   
/*    */   public final void Gl() {
/*    */     for (Hc0 hc0 = this.hW.D1.r30(); hc0.hasNext(); super.jf0((hO)hc0.next()));
/*    */     Qz0 qz0;
/*    */     (qz0 = this.hW).getClass();
/*    */     MF.KQ();
/*    */     Fy fy;
/*    */     if ((fy = this.hW.W50) != null) {
/*    */       qz0.jf0(fy);
/*    */       qz0.W50 = null;
/*    */     } 
/*    */     qz0.A5.clear();
/*    */     qz0.D1.clear();
/*    */     qz0.gx();
/*    */     QW[] arrayOfQW;
/*    */     int i;
/*    */     byte b;
/*    */     for (i = (arrayOfQW = (QW[])this.U1.toArray((Object[])new QW[0])).length, b = 0; b < i; ) {
/*    */       QW qW;
/*    */       if ((qW = arrayOfQW[b]) != null)
/*    */         qW.ra0(); 
/*    */       b++;
/*    */     } 
/*    */     km.si0.getClass();
/*    */     MF.KQ();
/*    */     km.si0.qb.clear();
/*    */     km.si0.l3.clear();
/*    */     km.si0.gx();
/*    */     h4(0, false, false, false, false, false);
/*    */     VA0.nR(this.MH0, true);
/*    */     pA pA1;
/*    */     if ((pA1 = this.MH0) != null)
/*    */       pA1.ra0(); 
/*    */     Co();
/*    */   }
/*    */   
/*    */   public final void z70(String paramString, int paramInt1, int paramInt2) {
/*    */     UB0.Kg0.fN(() -> F7.T1(Ot(paramInt1, paramInt2, paramString), this, paramInt1, paramInt2));
/*    */   }
/*    */   
/*    */   public final B3 Ot(int paramInt1, int paramInt2, String paramString) {
/*    */     B3 b3;
/*    */     Jo jo;
/*    */     if ((jo = km.a3.Ct) != null && jo.ED0.equals(paramString)) {
/*    */       this();
/*    */       L8(b3);
/*    */       return b3 = new B3();
/*    */     } 
/*    */     return bm(null, paramString, b3, paramInt2, false);
/*    */   }
/*    */   
/*    */   public final void s8(boolean paramBoolean, ArrayList paramArrayList, int paramInt1, int paramInt2) {
/*    */     // Byte code:
/*    */     //   0: getstatic f/UB0.Kg0 : Lf/Q50;
/*    */     //   3: aload_0
/*    */     //   4: iload_1
/*    */     //   5: aload_2
/*    */     //   6: iload_3
/*    */     //   7: iload #4
/*    */     //   9: <illegal opcode> run : (Lf/js;ZLjava/util/List;II)Ljava/lang/Runnable;
/*    */     //   14: invokevirtual fN : (Ljava/lang/Runnable;)V
/*    */     //   17: return
/*    */   } }


/* Location:              /Users/vnnsnnt/Documents/Codespace/JavaWorkspace/RedTrainer/src/main/java/org/trainer/client/PokeMMO.jar!/f/js.class
 * Java compiler version: 8 (52.0)
 * JD-Core Version:       1.1.3
 */