/* 1 */ package f;public final class K40 { public final Kf eE0; public final boolean xL0; public rS jJ; public Ip Am0; private void kJ(Fy0 paramFy0, V50 paramV50) { paramFy0.sk0(false); R8 r8 = km.u4; int i = paramV50.z70;
/* 2 */     short s = this.w6; this
/* 3 */       .e20
/* 4 */       .W3(new B20(i, s)); } public dQ CY; public Yb fb0; public short w6; public V50[] d60; public K40(Kf paramKf, boolean paramBoolean) { dQ dQ1; Yb yb; this.w6 = 0; this.eE0 = paramKf; this.xL0 = paramBoolean; this.Am0 = new Ip(); (this.jJ = new rS()).Xu("mail-inner"); if (km.XU()) this.jJ.zG0(3);  this(); this.CY = dQ1; this(this); this.fb0 = yb; } private void Rg0(V50 paramV50) { this.eE0.getClass(); R8 r8 = km.u4; int i = paramV50.z70; this.e20.W3(new kD(i)); } public final void En(Ip paramIp) { this.Am0.gx(); this.Am0.MJ0(); arrayOfU902[0] = this.Am0.vo0(new JG0[] { this.CY }); arrayOfU902[1] = this.Am0.vo0(new JG0[] { this.jJ, paramIp }); Ip ip; (ip = this.Am0).getClass(); U90[] arrayOfU902; (arrayOfU902 = new U90[3])[
/*   */         
/* 6 */         2] = (new cr0(ip)).Em0().Ya(this.fb0).Em0(); this.Am0.rK0(V2.Ur(this.Am0, this.Am0).cOM8(new U90[] { Mr.X60(this.Am0, this.Am0).cOM8(new U90[3]) }).Em0());
/*   */     
/* 8 */     arrayOfU901[0] = this.Am0.AUX(new JG0[] { this.CY }); arrayOfU901[1] = this.Am0.AUX(new JG0[] { this.jJ, paramIp }); U90[] arrayOfU901; (arrayOfU901 = new U90[3])[2] = this.Am0.AUX(new JG0[] { this.fb0 }); this.Am0.WN(V2.Ur(this.Am0, this.Am0).cOM8(new U90[3])); }
/*   */ 
/*   */   
/*   */   public final void hI0() {
/*   */     // Byte code:
/*   */     //   0: aload_0
/*   */     //   1: getfield jJ : Lf/rS;
/*   */     //   4: getfield iR : Lf/JG0;
/*   */     //   7: dup
/*   */     //   8: astore_1
/*   */     //   9: ifnull -> 16
/*   */     //   12: aload_1
/*   */     //   13: invokevirtual gx : ()V
/*   */     //   16: aload_0
/*   */     //   17: new f/dQ
/*   */     //   20: astore_1
/*   */     //   21: getfield xL0 : Z
/*   */     //   24: ifeq -> 37
/*   */     //   27: sipush #5828
/*   */     //   30: invokestatic OH0 : (I)Ljava/lang/String;
/*   */     //   33: astore_2
/*   */     //   34: goto -> 44
/*   */     //   37: sipush #5836
/*   */     //   40: invokestatic OH0 : (I)Ljava/lang/String;
/*   */     //   43: astore_2
/*   */     //   44: aload_0
/*   */     //   45: aload_1
/*   */     //   46: dup
/*   */     //   47: aload_2
/*   */     //   48: aload_1
/*   */     //   49: invokespecial <init> : ()V
/*   */     //   52: invokevirtual E1 : (Ljava/lang/String;)V
/*   */     //   55: ldc 'button'
/*   */     //   57: invokevirtual Xu : (Ljava/lang/String;)V
/*   */     //   60: new f/dQ
/*   */     //   63: dup
/*   */     //   64: dup
/*   */     //   65: astore_2
/*   */     //   66: sipush #5829
/*   */     //   69: invokestatic OH0 : (I)Ljava/lang/String;
/*   */     //   72: astore_3
/*   */     //   73: invokespecial <init> : ()V
/*   */     //   76: aload_3
/*   */     //   77: invokevirtual E1 : (Ljava/lang/String;)V
/*   */     //   80: new f/dQ
/*   */     //   83: dup
/*   */     //   84: dup
/*   */     //   85: astore_3
/*   */     //   86: sipush #5837
/*   */     //   89: invokestatic OH0 : (I)Ljava/lang/String;
/*   */     //   92: astore #4
/*   */     //   94: invokespecial <init> : ()V
/*   */     //   97: aload #4
/*   */     //   99: invokevirtual E1 : (Ljava/lang/String;)V
/*   */     //   102: new f/dQ
/*   */     //   105: dup
/*   */     //   106: astore #4
/*   */     //   108: aload_3
/*   */     //   109: aload_2
/*   */     //   110: aload_1
/*   */     //   111: aload #4
/*   */     //   113: dup
/*   */     //   114: sipush #5838
/*   */     //   117: invokestatic OH0 : (I)Ljava/lang/String;
/*   */     //   120: astore #5
/*   */     //   122: invokespecial <init> : ()V
/*   */     //   125: aload #5
/*   */     //   127: invokevirtual E1 : (Ljava/lang/String;)V
/*   */     //   130: ldc 'label-title-small2'
/*   */     //   132: invokevirtual Xu : (Ljava/lang/String;)V
/*   */     //   135: ldc 'label-title-medium'
/*   */     //   137: invokevirtual Xu : (Ljava/lang/String;)V
/*   */     //   140: ldc 'label-title-small2'
/*   */     //   142: invokevirtual Xu : (Ljava/lang/String;)V
/*   */     //   145: ldc 'label-title-smallest'
/*   */     //   147: invokevirtual Xu : (Ljava/lang/String;)V
/*   */     //   150: new f/Ip
/*   */     //   153: dup
/*   */     //   154: dup
/*   */     //   155: dup2
/*   */     //   156: astore #5
/*   */     //   158: invokespecial <init> : ()V
/*   */     //   161: new f/g0
/*   */     //   164: dup
/*   */     //   165: aload #5
/*   */     //   167: invokespecial <init> : (Lf/Ip;)V
/*   */     //   170: invokevirtual rK0 : (Lf/U90;)V
/*   */     //   173: new f/cr0
/*   */     //   176: dup
/*   */     //   177: aload #5
/*   */     //   179: invokespecial <init> : (Lf/Ip;)V
/*   */     //   182: invokevirtual WN : (Lf/U90;)V
/*   */     //   185: getfield Xz0 : Lf/U90;
/*   */     //   188: astore #6
/*   */     //   190: iconst_4
/*   */     //   191: anewarray f/JG0
/*   */     //   194: dup
/*   */     //   195: dup2
/*   */     //   196: astore #7
/*   */     //   198: iconst_0
/*   */     //   199: aload_1
/*   */     //   200: aastore
/*   */     //   201: iconst_1
/*   */     //   202: aload_2
/*   */     //   203: aastore
/*   */     //   204: iconst_2
/*   */     //   205: aload_3
/*   */     //   206: aastore
/*   */     //   207: iconst_3
/*   */     //   208: istore #8
/*   */     //   210: getfield xL0 : Z
/*   */     //   213: ifeq -> 222
/*   */     //   216: aconst_null
/*   */     //   217: astore #9
/*   */     //   219: goto -> 226
/*   */     //   222: aload #4
/*   */     //   224: astore #9
/*   */     //   226: aload_0
/*   */     //   227: aload #5
/*   */     //   229: aload #6
/*   */     //   231: aload #5
/*   */     //   233: aload #7
/*   */     //   235: dup
/*   */     //   236: iload #8
/*   */     //   238: aload #9
/*   */     //   240: aastore
/*   */     //   241: invokevirtual vo0 : ([Lf/JG0;)Lf/U90;
/*   */     //   244: invokevirtual ee0 : (Lf/U90;)Lf/U90;
/*   */     //   247: pop
/*   */     //   248: getfield o30 : Lf/U90;
/*   */     //   251: astore #6
/*   */     //   253: iconst_4
/*   */     //   254: anewarray f/JG0
/*   */     //   257: dup
/*   */     //   258: dup2
/*   */     //   259: astore #7
/*   */     //   261: iconst_0
/*   */     //   262: aload_1
/*   */     //   263: aastore
/*   */     //   264: iconst_1
/*   */     //   265: aload_2
/*   */     //   266: aastore
/*   */     //   267: iconst_2
/*   */     //   268: aload_3
/*   */     //   269: aastore
/*   */     //   270: iconst_3
/*   */     //   271: istore_1
/*   */     //   272: getfield xL0 : Z
/*   */     //   275: ifeq -> 281
/*   */     //   278: aconst_null
/*   */     //   279: astore #4
/*   */     //   281: aload_0
/*   */     //   282: dup
/*   */     //   283: aload #6
/*   */     //   285: aload #5
/*   */     //   287: aload #7
/*   */     //   289: dup
/*   */     //   290: iload_1
/*   */     //   291: aload #4
/*   */     //   293: aastore
/*   */     //   294: invokevirtual AUX : ([Lf/JG0;)Lf/U90;
/*   */     //   297: invokevirtual ee0 : (Lf/U90;)Lf/U90;
/*   */     //   300: pop
/*   */     //   301: getfield CY : Lf/dQ;
/*   */     //   304: astore_1
/*   */     //   305: getfield xL0 : Z
/*   */     //   308: ifeq -> 317
/*   */     //   311: ldc ' '
/*   */     //   313: astore_2
/*   */     //   314: goto -> 357
/*   */     //   317: iconst_2
/*   */     //   318: anewarray java/lang/String
/*   */     //   321: dup
/*   */     //   322: dup
/*   */     //   323: astore_2
/*   */     //   324: new java/lang/StringBuilder
/*   */     //   327: dup
/*   */     //   328: invokespecial <init> : ()V
/*   */     //   331: getstatic f/km.u4 : Lf/R8;
/*   */     //   334: getfield pp0 : S
/*   */     //   337: ldc ''
/*   */     //   339: invokestatic Gl0 : (Ljava/lang/StringBuilder;ILjava/lang/String;)Ljava/lang/String;
/*   */     //   342: iconst_0
/*   */     //   343: swap
/*   */     //   344: aastore
/*   */     //   345: iconst_1
/*   */     //   346: ldc '250'
/*   */     //   348: aastore
/*   */     //   349: sipush #5839
/*   */     //   352: aload_2
/*   */     //   353: invokestatic sB : (I[Ljava/lang/String;)Ljava/lang/String;
/*   */     //   356: astore_2
/*   */     //   357: aload_0
/*   */     //   358: aload_1
/*   */     //   359: aload_2
/*   */     //   360: invokevirtual E1 : (Ljava/lang/String;)V
/*   */     //   363: getfield d60 : [Lf/V50;
/*   */     //   366: dup
/*   */     //   367: astore_1
/*   */     //   368: ifnull -> 1311
/*   */     //   371: aload_1
/*   */     //   372: arraylength
/*   */     //   373: istore_2
/*   */     //   374: iconst_0
/*   */     //   375: istore_3
/*   */     //   376: iload_3
/*   */     //   377: iload_2
/*   */     //   378: if_icmpge -> 1236
/*   */     //   381: aload_0
/*   */     //   382: dup
/*   */     //   383: aload_1
/*   */     //   384: iload_3
/*   */     //   385: aaload
/*   */     //   386: dup
/*   */     //   387: astore #4
/*   */     //   389: <illegal opcode> run : (Lf/K40;Lf/V50;)Ljava/lang/Runnable;
/*   */     //   394: astore #6
/*   */     //   396: getfield xL0 : Z
/*   */     //   399: ifeq -> 489
/*   */     //   402: aload #4
/*   */     //   404: getfield Tb0 : Ljava/lang/String;
/*   */     //   407: dup
/*   */     //   408: astore #7
/*   */     //   410: invokevirtual isEmpty : ()Z
/*   */     //   413: ifeq -> 421
/*   */     //   416: ldc_w '???'
/*   */     //   419: astore #7
/*   */     //   421: aload #7
/*   */     //   423: new f/Un
/*   */     //   426: dup
/*   */     //   427: astore #8
/*   */     //   429: aload #7
/*   */     //   431: invokespecial <init> : (Ljava/lang/String;)V
/*   */     //   434: invokevirtual length : ()I
/*   */     //   437: bipush #7
/*   */     //   439: if_icmple -> 670
/*   */     //   442: aload #8
/*   */     //   444: dup
/*   */     //   445: aload #7
/*   */     //   447: aload #8
/*   */     //   449: new java/lang/StringBuilder
/*   */     //   452: dup
/*   */     //   453: aload #7
/*   */     //   455: swap
/*   */     //   456: invokespecial <init> : ()V
/*   */     //   459: iconst_0
/*   */     //   460: bipush #6
/*   */     //   462: invokevirtual substring : (II)Ljava/lang/String;
/*   */     //   465: invokevirtual append : (Ljava/lang/String;)Ljava/lang/StringBuilder;
/*   */     //   468: ldc_w '...'
/*   */     //   471: invokevirtual append : (Ljava/lang/String;)Ljava/lang/StringBuilder;
/*   */     //   474: invokevirtual toString : ()Ljava/lang/String;
/*   */     //   477: invokevirtual s6 : (Ljava/lang/String;)V
/*   */     //   480: putfield z4 : Ljava/lang/Object;
/*   */     //   483: invokevirtual zn : ()V
/*   */     //   486: goto -> 662
/*   */     //   489: aload #4
/*   */     //   491: new f/Un
/*   */     //   494: astore #8
/*   */     //   496: getfield f4 : I
/*   */     //   499: ifeq -> 512
/*   */     //   502: aload #4
/*   */     //   504: getfield RD : Ljava/lang/String;
/*   */     //   507: astore #7
/*   */     //   509: goto -> 522
/*   */     //   512: aload #4
/*   */     //   514: getfield RD : Ljava/lang/String;
/*   */     //   517: invokestatic LU : (Ljava/lang/String;)Ljava/lang/String;
/*   */     //   520: astore #7
/*   */     //   522: aload #4
/*   */     //   524: aload #8
/*   */     //   526: aload #7
/*   */     //   528: invokespecial <init> : (Ljava/lang/String;)V
/*   */     //   531: getfield f4 : I
/*   */     //   534: ifeq -> 545
/*   */     //   537: aload #4
/*   */     //   539: getfield RD : Ljava/lang/String;
/*   */     //   542: goto -> 553
/*   */     //   545: aload #4
/*   */     //   547: getfield RD : Ljava/lang/String;
/*   */     //   550: invokestatic LU : (Ljava/lang/String;)Ljava/lang/String;
/*   */     //   553: invokevirtual length : ()I
/*   */     //   556: bipush #7
/*   */     //   558: if_icmple -> 670
/*   */     //   561: aload #4
/*   */     //   563: new java/lang/StringBuilder
/*   */     //   566: dup
/*   */     //   567: astore #7
/*   */     //   569: invokespecial <init> : ()V
/*   */     //   572: getfield f4 : I
/*   */     //   575: ifeq -> 586
/*   */     //   578: aload #4
/*   */     //   580: getfield RD : Ljava/lang/String;
/*   */     //   583: goto -> 594
/*   */     //   586: aload #4
/*   */     //   588: getfield RD : Ljava/lang/String;
/*   */     //   591: invokestatic LU : (Ljava/lang/String;)Ljava/lang/String;
/*   */     //   594: iconst_0
/*   */     //   595: bipush #6
/*   */     //   597: invokevirtual substring : (II)Ljava/lang/String;
/*   */     //   600: astore #9
/*   */     //   602: aload #4
/*   */     //   604: aload #8
/*   */     //   606: aload #7
/*   */     //   608: aload #9
/*   */     //   610: invokevirtual append : (Ljava/lang/String;)Ljava/lang/StringBuilder;
/*   */     //   613: ldc_w '...'
/*   */     //   616: invokevirtual append : (Ljava/lang/String;)Ljava/lang/StringBuilder;
/*   */     //   619: invokevirtual toString : ()Ljava/lang/String;
/*   */     //   622: invokevirtual s6 : (Ljava/lang/String;)V
/*   */     //   625: getfield f4 : I
/*   */     //   628: ifeq -> 641
/*   */     //   631: aload #4
/*   */     //   633: getfield RD : Ljava/lang/String;
/*   */     //   636: astore #7
/*   */     //   638: goto -> 651
/*   */     //   641: aload #4
/*   */     //   643: getfield RD : Ljava/lang/String;
/*   */     //   646: invokestatic LU : (Ljava/lang/String;)Ljava/lang/String;
/*   */     //   649: astore #7
/*   */     //   651: aload #8
/*   */     //   653: dup
/*   */     //   654: aload #7
/*   */     //   656: putfield z4 : Ljava/lang/Object;
/*   */     //   659: invokevirtual zn : ()V
/*   */     //   662: aload #8
/*   */     //   664: sipush #150
/*   */     //   667: putfield jl : I
/*   */     //   670: aload #4
/*   */     //   672: aload #8
/*   */     //   674: aload #6
/*   */     //   676: invokevirtual tW : (Ljava/lang/Runnable;)V
/*   */     //   679: new f/Un
/*   */     //   682: astore #7
/*   */     //   684: getfield f4 : I
/*   */     //   687: ifeq -> 700
/*   */     //   690: aload #4
/*   */     //   692: getfield r10 : Ljava/lang/String;
/*   */     //   695: astore #9
/*   */     //   697: goto -> 710
/*   */     //   700: aload #4
/*   */     //   702: getfield r10 : Ljava/lang/String;
/*   */     //   705: invokestatic LU : (Ljava/lang/String;)Ljava/lang/String;
/*   */     //   708: astore #9
/*   */     //   710: aload #4
/*   */     //   712: aload #7
/*   */     //   714: aload #6
/*   */     //   716: aload #7
/*   */     //   718: aload #9
/*   */     //   720: invokespecial <init> : (Ljava/lang/String;)V
/*   */     //   723: invokevirtual tW : (Ljava/lang/Runnable;)V
/*   */     //   726: getfield f4 : I
/*   */     //   729: ifeq -> 740
/*   */     //   732: aload #4
/*   */     //   734: getfield r10 : Ljava/lang/String;
/*   */     //   737: goto -> 748
/*   */     //   740: aload #4
/*   */     //   742: getfield r10 : Ljava/lang/String;
/*   */     //   745: invokestatic LU : (Ljava/lang/String;)Ljava/lang/String;
/*   */     //   748: invokevirtual length : ()I
/*   */     //   751: bipush #12
/*   */     //   753: if_icmple -> 864
/*   */     //   756: aload #4
/*   */     //   758: new java/lang/StringBuilder
/*   */     //   761: dup
/*   */     //   762: astore #9
/*   */     //   764: invokespecial <init> : ()V
/*   */     //   767: getfield f4 : I
/*   */     //   770: ifeq -> 781
/*   */     //   773: aload #4
/*   */     //   775: getfield r10 : Ljava/lang/String;
/*   */     //   778: goto -> 789
/*   */     //   781: aload #4
/*   */     //   783: getfield r10 : Ljava/lang/String;
/*   */     //   786: invokestatic LU : (Ljava/lang/String;)Ljava/lang/String;
/*   */     //   789: iconst_0
/*   */     //   790: bipush #11
/*   */     //   792: invokevirtual substring : (II)Ljava/lang/String;
/*   */     //   795: astore #10
/*   */     //   797: aload #4
/*   */     //   799: aload #7
/*   */     //   801: aload #9
/*   */     //   803: aload #10
/*   */     //   805: invokevirtual append : (Ljava/lang/String;)Ljava/lang/StringBuilder;
/*   */     //   808: ldc_w '...'
/*   */     //   811: invokevirtual append : (Ljava/lang/String;)Ljava/lang/StringBuilder;
/*   */     //   814: invokevirtual toString : ()Ljava/lang/String;
/*   */     //   817: invokevirtual s6 : (Ljava/lang/String;)V
/*   */     //   820: getfield f4 : I
/*   */     //   823: ifeq -> 836
/*   */     //   826: aload #4
/*   */     //   828: getfield r10 : Ljava/lang/String;
/*   */     //   831: astore #9
/*   */     //   833: goto -> 846
/*   */     //   836: aload #4
/*   */     //   838: getfield r10 : Ljava/lang/String;
/*   */     //   841: invokestatic LU : (Ljava/lang/String;)Ljava/lang/String;
/*   */     //   844: astore #9
/*   */     //   846: aload #7
/*   */     //   848: dup
/*   */     //   849: dup
/*   */     //   850: aload #9
/*   */     //   852: putfield z4 : Ljava/lang/Object;
/*   */     //   855: invokevirtual zn : ()V
/*   */     //   858: sipush #150
/*   */     //   861: putfield jl : I
/*   */     //   864: new java/text/SimpleDateFormat
/*   */     //   867: dup
/*   */     //   868: astore #9
/*   */     //   870: ldc_w 'yyyy-MM-dd'
/*   */     //   873: invokespecial <init> : (Ljava/lang/String;)V
/*   */     //   876: new java/util/Date
/*   */     //   879: dup
/*   */     //   880: astore #10
/*   */     //   882: aload #4
/*   */     //   884: aload #10
/*   */     //   886: invokespecial <init> : ()V
/*   */     //   889: getfield Px0 : I
/*   */     //   892: i2l
/*   */     //   893: ldc2_w 1000
/*   */     //   896: lmul
/*   */     //   897: invokevirtual setTime : (J)V
/*   */     //   900: new f/Un
/*   */     //   903: dup
/*   */     //   904: astore #11
/*   */     //   906: aload #6
/*   */     //   908: aload #11
/*   */     //   910: aload #9
/*   */     //   912: aload #10
/*   */     //   914: invokevirtual format : (Ljava/util/Date;)Ljava/lang/String;
/*   */     //   917: invokespecial <init> : (Ljava/lang/String;)V
/*   */     //   920: invokevirtual tW : (Ljava/lang/Runnable;)V
/*   */     //   923: new f/Fy0
/*   */     //   926: dup
/*   */     //   927: dup2
/*   */     //   928: astore #6
/*   */     //   930: invokespecial <init> : ()V
/*   */     //   933: getfield As : Lf/rH;
/*   */     //   936: iconst_1
/*   */     //   937: anewarray f/pe0
/*   */     //   940: dup
/*   */     //   941: invokestatic ZZ : ()Lf/interface;
/*   */     //   944: getfield GI0 : Lf/pe0;
/*   */     //   947: iconst_0
/*   */     //   948: swap
/*   */     //   949: aastore
/*   */     //   950: invokevirtual Pn : ([Lf/pe0;)Lf/JG0;
/*   */     //   953: pop
/*   */     //   954: getfield As : Lf/rH;
/*   */     //   957: astore #9
/*   */     //   959: invokestatic XU : ()Z
/*   */     //   962: ifeq -> 972
/*   */     //   965: bipush #30
/*   */     //   967: istore #10
/*   */     //   969: goto -> 976
/*   */     //   972: bipush #21
/*   */     //   974: istore #10
/*   */     //   976: invokestatic XU : ()Z
/*   */     //   979: ifeq -> 989
/*   */     //   982: bipush #10
/*   */     //   984: istore #12
/*   */     //   986: goto -> 993
/*   */     //   989: bipush #6
/*   */     //   991: istore #12
/*   */     //   993: aload #4
/*   */     //   995: aload #6
/*   */     //   997: aload_0
/*   */     //   998: aload #6
/*   */     //   1000: aload #9
/*   */     //   1002: iload #10
/*   */     //   1004: iload #12
/*   */     //   1006: invokevirtual zT : (II)Lf/JG0;
/*   */     //   1009: pop
/*   */     //   1010: aload #4
/*   */     //   1012: <illegal opcode> run : (Lf/K40;Lf/Fy0;Lf/V50;)Ljava/lang/Runnable;
/*   */     //   1017: invokevirtual tW : (Ljava/lang/Runnable;)V
/*   */     //   1020: getfield NZ : B
/*   */     //   1023: iconst_1
/*   */     //   1024: if_icmpne -> 1031
/*   */     //   1027: iconst_1
/*   */     //   1028: goto -> 1032
/*   */     //   1031: iconst_0
/*   */     //   1032: ifeq -> 1073
/*   */     //   1035: aload_0
/*   */     //   1036: getfield xL0 : Z
/*   */     //   1039: ifne -> 1073
/*   */     //   1042: aload #6
/*   */     //   1044: aload #11
/*   */     //   1046: aload #7
/*   */     //   1048: aload #8
/*   */     //   1050: ldc 'label-title-small2'
/*   */     //   1052: invokevirtual Xu : (Ljava/lang/String;)V
/*   */     //   1055: ldc 'label-title-medium'
/*   */     //   1057: invokevirtual Xu : (Ljava/lang/String;)V
/*   */     //   1060: ldc 'label-title-small2'
/*   */     //   1062: invokevirtual Xu : (Ljava/lang/String;)V
/*   */     //   1065: ldc 'label-title-smallest'
/*   */     //   1067: invokevirtual Xu : (Ljava/lang/String;)V
/*   */     //   1070: goto -> 1105
/*   */     //   1073: aload #6
/*   */     //   1075: aload #11
/*   */     //   1077: aload #7
/*   */     //   1079: aload #8
/*   */     //   1081: ldc_w 'label-value-small2'
/*   */     //   1084: invokevirtual Xu : (Ljava/lang/String;)V
/*   */     //   1087: ldc_w 'label-value-medium'
/*   */     //   1090: invokevirtual Xu : (Ljava/lang/String;)V
/*   */     //   1093: ldc_w 'label-value-small2'
/*   */     //   1096: invokevirtual Xu : (Ljava/lang/String;)V
/*   */     //   1099: ldc_w 'label-value-smallest'
/*   */     //   1102: invokevirtual Xu : (Ljava/lang/String;)V
/*   */     //   1105: aload_0
/*   */     //   1106: aload #5
/*   */     //   1108: getfield Xz0 : Lf/U90;
/*   */     //   1111: astore #4
/*   */     //   1113: iconst_4
/*   */     //   1114: anewarray f/JG0
/*   */     //   1117: dup
/*   */     //   1118: dup2
/*   */     //   1119: astore #9
/*   */     //   1121: iconst_0
/*   */     //   1122: aload #8
/*   */     //   1124: aastore
/*   */     //   1125: iconst_1
/*   */     //   1126: aload #7
/*   */     //   1128: aastore
/*   */     //   1129: iconst_2
/*   */     //   1130: aload #11
/*   */     //   1132: aastore
/*   */     //   1133: iconst_3
/*   */     //   1134: istore #10
/*   */     //   1136: getfield xL0 : Z
/*   */     //   1139: ifeq -> 1148
/*   */     //   1142: aconst_null
/*   */     //   1143: astore #12
/*   */     //   1145: goto -> 1152
/*   */     //   1148: aload #6
/*   */     //   1150: astore #12
/*   */     //   1152: aload_0
/*   */     //   1153: aload #5
/*   */     //   1155: aload #4
/*   */     //   1157: aload #5
/*   */     //   1159: aload #9
/*   */     //   1161: dup
/*   */     //   1162: iload #10
/*   */     //   1164: aload #12
/*   */     //   1166: aastore
/*   */     //   1167: invokevirtual vo0 : ([Lf/JG0;)Lf/U90;
/*   */     //   1170: invokevirtual ee0 : (Lf/U90;)Lf/U90;
/*   */     //   1173: pop
/*   */     //   1174: getfield o30 : Lf/U90;
/*   */     //   1177: astore #4
/*   */     //   1179: iconst_4
/*   */     //   1180: anewarray f/JG0
/*   */     //   1183: dup
/*   */     //   1184: dup2
/*   */     //   1185: astore #9
/*   */     //   1187: iconst_0
/*   */     //   1188: aload #8
/*   */     //   1190: aastore
/*   */     //   1191: iconst_1
/*   */     //   1192: aload #7
/*   */     //   1194: aastore
/*   */     //   1195: iconst_2
/*   */     //   1196: aload #11
/*   */     //   1198: aastore
/*   */     //   1199: iconst_3
/*   */     //   1200: istore #7
/*   */     //   1202: getfield xL0 : Z
/*   */     //   1205: ifeq -> 1211
/*   */     //   1208: aconst_null
/*   */     //   1209: astore #6
/*   */     //   1211: aload #4
/*   */     //   1213: aload #5
/*   */     //   1215: aload #9
/*   */     //   1217: dup
/*   */     //   1218: iload #7
/*   */     //   1220: aload #6
/*   */     //   1222: aastore
/*   */     //   1223: invokevirtual AUX : ([Lf/JG0;)Lf/U90;
/*   */     //   1226: invokevirtual ee0 : (Lf/U90;)Lf/U90;
/*   */     //   1229: pop
/*   */     //   1230: iinc #3, 1
/*   */     //   1233: goto -> 376
/*   */     //   1236: aload_0
/*   */     //   1237: getfield d60 : [Lf/V50;
/*   */     //   1240: arraylength
/*   */     //   1241: ifne -> 1374
/*   */     //   1244: aload #5
/*   */     //   1246: dup
/*   */     //   1247: new f/Un
/*   */     //   1250: dup
/*   */     //   1251: dup
/*   */     //   1252: astore_1
/*   */     //   1253: sipush #1655
/*   */     //   1256: invokestatic OH0 : (I)Ljava/lang/String;
/*   */     //   1259: invokespecial <init> : (Ljava/lang/String;)V
/*   */     //   1262: ldc_w 'label-value-small'
/*   */     //   1265: invokevirtual Xu : (Ljava/lang/String;)V
/*   */     //   1268: getfield Xz0 : Lf/U90;
/*   */     //   1271: aload #5
/*   */     //   1273: iconst_1
/*   */     //   1274: anewarray f/JG0
/*   */     //   1277: dup
/*   */     //   1278: iconst_0
/*   */     //   1279: aload_1
/*   */     //   1280: aastore
/*   */     //   1281: invokevirtual vo0 : ([Lf/JG0;)Lf/U90;
/*   */     //   1284: invokevirtual ee0 : (Lf/U90;)Lf/U90;
/*   */     //   1287: pop
/*   */     //   1288: getfield o30 : Lf/U90;
/*   */     //   1291: aload #5
/*   */     //   1293: iconst_1
/*   */     //   1294: anewarray f/JG0
/*   */     //   1297: dup
/*   */     //   1298: iconst_0
/*   */     //   1299: aload_1
/*   */     //   1300: aastore
/*   */     //   1301: invokevirtual AUX : ([Lf/JG0;)Lf/U90;
/*   */     //   1304: invokevirtual ee0 : (Lf/U90;)Lf/U90;
/*   */     //   1307: pop
/*   */     //   1308: goto -> 1374
/*   */     //   1311: aload #5
/*   */     //   1313: dup
/*   */     //   1314: new f/Un
/*   */     //   1317: dup
/*   */     //   1318: dup
/*   */     //   1319: astore_1
/*   */     //   1320: bipush #55
/*   */     //   1322: invokestatic OH0 : (I)Ljava/lang/String;
/*   */     //   1325: invokespecial <init> : (Ljava/lang/String;)V
/*   */     //   1328: ldc_w 'label-value-small'
/*   */     //   1331: invokevirtual Xu : (Ljava/lang/String;)V
/*   */     //   1334: getfield Xz0 : Lf/U90;
/*   */     //   1337: aload #5
/*   */     //   1339: iconst_1
/*   */     //   1340: anewarray f/JG0
/*   */     //   1343: dup
/*   */     //   1344: iconst_0
/*   */     //   1345: aload_1
/*   */     //   1346: aastore
/*   */     //   1347: invokevirtual vo0 : ([Lf/JG0;)Lf/U90;
/*   */     //   1350: invokevirtual ee0 : (Lf/U90;)Lf/U90;
/*   */     //   1353: pop
/*   */     //   1354: getfield o30 : Lf/U90;
/*   */     //   1357: aload #5
/*   */     //   1359: iconst_1
/*   */     //   1360: anewarray f/JG0
/*   */     //   1363: dup
/*   */     //   1364: iconst_0
/*   */     //   1365: aload_1
/*   */     //   1366: aastore
/*   */     //   1367: invokevirtual AUX : ([Lf/JG0;)Lf/U90;
/*   */     //   1370: invokevirtual ee0 : (Lf/U90;)Lf/U90;
/*   */     //   1373: pop
/*   */     //   1374: aload_0
/*   */     //   1375: getfield jJ : Lf/rS;
/*   */     //   1378: aload #5
/*   */     //   1380: invokevirtual Gz0 : (Lf/JG0;)V
/*   */     //   1383: return
/*   */     // Line number table:
/*   */     //   Java source line number -> byte code offset
/*   */     //   #1	-> 4
/*   */     //   #2	-> 13
/*   */     //   #3	-> 49
/*   */     //   #4	-> 55
/*   */     //   #5	-> 73
/*   */     //   #6	-> 80
/*   */     //   #7	-> 94
/*   */     //   #8	-> 102
/*   */     //   #9	-> 122
/*   */     //   #10	-> 130
/*   */     //   #11	-> 161
/*   */     //   #12	-> 170
/*   */     //   #13	-> 173
/*   */     //   #14	-> 182
/*   */     //   #15	-> 185
/*   */     //   #16	-> 191
/*   */     //   #17	-> 248
/*   */     //   #18	-> 254
/*   */     //   #19	-> 334
/*   */     //   #20	-> 337
/*   */     //   #21	-> 344
/*   */     //   #22	-> 404
/*   */     //   #23	-> 410
/*   */     //   #24	-> 480
/*   */     //   #25	-> 491
/*   */     //   #26	-> 496
/*   */     //   #27	-> 504
/*   */     //   #28	-> 514
/*   */     //   #29	-> 528
/*   */     //   #30	-> 531
/*   */     //   #31	-> 539
/*   */     //   #32	-> 547
/*   */     //   #33	-> 553
/*   */     //   #34	-> 572
/*   */     //   #35	-> 580
/*   */     //   #36	-> 588
/*   */     //   #37	-> 597
/*   */     //   #38	-> 625
/*   */     //   #39	-> 633
/*   */     //   #40	-> 643
/*   */     //   #41	-> 656
/*   */     //   #42	-> 667
/*   */     //   #43	-> 676
/*   */     //   #44	-> 684
/*   */     //   #45	-> 692
/*   */     //   #46	-> 702
/*   */     //   #47	-> 720
/*   */     //   #48	-> 726
/*   */     //   #49	-> 734
/*   */     //   #50	-> 742
/*   */     //   #51	-> 748
/*   */     //   #52	-> 767
/*   */     //   #53	-> 775
/*   */     //   #54	-> 783
/*   */     //   #55	-> 792
/*   */     //   #56	-> 820
/*   */     //   #57	-> 828
/*   */     //   #58	-> 838
/*   */     //   #59	-> 852
/*   */     //   #60	-> 861
/*   */     //   #61	-> 864
/*   */     //   #62	-> 889
/*   */     //   #63	-> 897
/*   */     //   #64	-> 933
/*   */     //   #65	-> 937
/*   */     //   #66	-> 944
/*   */     //   #67	-> 949
/*   */     //   #68	-> 954
/*   */     //   #69	-> 959
/*   */     //   #70	-> 1020
/*   */     //   #71	-> 1036
/*   */     //   #72	-> 1108
/*   */     //   #73	-> 1114
/*   */     //   #74	-> 1174
/*   */     //   #75	-> 1180
/*   */     //   #76	-> 1268
/*   */     //   #77	-> 1274
/*   */     //   #78	-> 1288
/*   */     //   #79	-> 1294
/*   */     //   #80	-> 1334
/*   */     //   #81	-> 1340
/*   */     //   #82	-> 1354
/*   */     //   #83	-> 1360
/*   */   }
/*   */   
/*   */   public final void Vq0(short paramShort) {
/*   */     short s;
/*   */     this.w6 = paramShort;
/*   */     R8 r8 = km.u4;
/*   */     boolean bool = this.xL0;
/*   */     r8.e20.W3(new cOM2(paramShort, bool));
/*   */     Yb yb = this.fb0;
/*   */     if (this.xL0) {
/*   */       s = km.u4.M9;
/*   */     } else {
/*   */       s = km.u4.pp0;
/*   */     } 
/*   */     yb.r1(paramShort, s);
/*   */     this.d60 = null;
/*   */     hI0();
/*   */   } }


/* Location:              /Users/vnnsnnt/Documents/Codespace/JavaWorkspace/RedTrainer/src/main/java/org/trainer/client/PokeMMO.jar!/f/K40.class
 * Java compiler version: 8 (52.0)
 * JD-Core Version:       1.1.3
 */