/* 1 */ package f;public final class kB0 extends VH { private void Em(String paramString, int paramInt) { this.fo
/*   */       
/* 3 */       .sk0(this.Hl.F2.toString().equalsIgnoreCase(paramString)); }
/*   */ 
/*   */   
/*   */   public kB0(String paramString1, String paramString2, Tx paramTx) {
/*   */     // Byte code:
/*   */     //   0: aload_0
/*   */     //   1: dup
/*   */     //   2: dup
/*   */     //   3: aload_1
/*   */     //   4: aload_2
/*   */     //   5: invokevirtual length : ()I
/*   */     //   8: aload_3
/*   */     //   9: invokespecial <init> : (Ljava/lang/String;ILf/Tx;)V
/*   */     //   12: getfield fo : Lf/Un;
/*   */     //   15: iconst_0
/*   */     //   16: invokevirtual sk0 : (Z)V
/*   */     //   19: getfield Hl : Lf/of;
/*   */     //   22: aload_0
/*   */     //   23: aload_2
/*   */     //   24: <illegal opcode> SX : (Lf/kB0;Ljava/lang/String;)Lf/a70;
/*   */     //   29: invokevirtual JD0 : (Lf/a70;)V
/*   */     //   32: return
/*   */   } }


/* Location:              /Users/vnnsnnt/Documents/Codespace/JavaWorkspace/RedTrainer/src/main/java/org/trainer/client/PokeMMO.jar!/f/kB0.class
 * Java compiler version: 8 (52.0)
 * JD-Core Version:       1.1.3
 */