/*    */
package f;

public final class Kf extends Qa0 implements r60 {
    public Vq0 kc;
    public Ip MD0;
    public K40 dA0;
    public K40 fF;
    public Ip bG;
    public of Gr;
    public of cl;
    public of Nv0;
    public Rm default;
    public T1[] WN;
    public Qv0[] Jt;
    public int Ps;
    public of ef;
    public of Vt;
    public of rB;
    public yn0[] sw;
    public Un gk;
    public Un s9;
    public Un sC0;
    public Un tv;
    public of Fw;
    public boolean n80;
    public boolean cS;
    public coM9 hD;

    /*  2 */
    public static int lm0(j40 paramj40) {
        return paramj40.Zs.Tl0;
    }

    private void M00(List paramList) {
        for (Iterator iterator = paramList.iterator(); iterator.hasNext(); ) {
            nE0 nE0;
            if ((nE0 = ((yn0) iterator.next()).ZF0).T7)
                /*  3 */ continue;
            int i = nE0.bz0;
            /*  4 */
            byte b = nE0.Ly;
            /*    */
            /*  6 */
            short s = this.dA0.w6;
            /*  7 */
            km.u4.mS(i, b, null, s, (byte) 2);
            return;
        }
    }

    private void p00(List paramList) {
        for (Iterator iterator = paramList.iterator(); iterator.hasNext(); ) {
            nE0 nE0;
            if ((nE0 = ((yn0) iterator.next()).ZF0).T7) continue;
            int i = nE0.bz0;
            byte b = nE0.Ly;
            short s = this.dA0.w6;
            km.u4.mS(i, b, null, s, (byte) 1);
            return;
        }
    }

    private void X3(ge0 paramge0) {
        if (paramge0.TG0.nm0() != h1.vj) {
            h1.vj = paramge0.TG0.nm0();
            h1.Td();
        }
        Ym0(true);
    }

    private void bW(G9 paramG9) {
        boolean bool;
        List list = KK0();
        if (paramG9.t70 != null) {
            bool = true;
        } else {
            bool = false;
        }
        F7.Yo(JB0.at0(paramG9, this, bool), paramG9);
    }

    public static void Se(T1 paramT1) {
        boolean bool;
        Rc rc = JB0.B4;
        if (paramT1.hC0 > 0) {
            bool = true;
        } else {
            bool = false;
        }
        F7.Yo(JB0.Ww(paramT1, rc, bool), paramT1);
    }

    private void Rt(Un paramUn) {
        int i = paramUn.Kd;
        F7.T1(JB0.qk0(this.Gr), this, i, paramUn.yR());
    }

    private void rD0(List paramList) {
        for (Iterator iterator = paramList.iterator(); iterator.hasNext(); ) {
            nE0 nE0;
            if ((nE0 = ((yn0) iterator.next()).ZF0).T7) continue;
            int i = nE0.bz0;
            km.u4.J80(nE0.Ly, i, this.dA0.w6);
            return;
        }
    }

    public static kt o8(OZ paramOZ, String paramString, int paramInt, kt paramkt) {
        paramString = paramString.substring(0, paramInt);
        this();
        ArrayList arrayList;
        byte b = 0;
        while (b < paramOZ.Fj.size()) {
            boolean bool;
            Object object;
            if ((object = paramOZ.c90(b)) != null) {
                int i = paramString.length();
                bool = object.toString().regionMatches(true, 0, paramString, 0, i);
            } else {
                bool = false;
            }
            if (bool) arrayList.add(paramOZ.Fj.get(b));
            b++;
        }
        return arrayList.isEmpty() ? null : new TW(false, arrayList);
    }

    public Kf(boolean paramBoolean, j40 paramj40) { // Byte code:
        /*    */     //   0: iload_1
        /*    */     //   1: aload_0
        /*    */     //   2: dup
        /*    */     //   3: dup
        /*    */     //   4: dup2
        /*    */     //   5: dup2
        /*    */     //   6: dup2
        /*    */     //   7: dup2
        /*    */     //   8: invokestatic XU : ()Z
        /*    */     //   11: invokespecial <init> : (Z)V
        /*    */     //   14: iconst_0
        /*    */     //   15: putfield Ps : I
        /*    */     //   18: aconst_null
        /*    */     //   19: putfield gk : Lf/Un;
        /*    */     //   22: aconst_null
        /*    */     //   23: putfield s9 : Lf/Un;
        /*    */     //   26: aconst_null
        /*    */     //   27: putfield sC0 : Lf/Un;
        /*    */     //   30: ldc_w 'mail-window'
        /*    */     //   33: invokevirtual Xu : (Ljava/lang/String;)V
        /*    */     //   36: sipush #5827
        /*    */     //   39: invokestatic OH0 : (I)Ljava/lang/String;
        /*    */     //   42: invokevirtual Lo : (Ljava/lang/String;)V
        /*    */     //   45: iconst_1
        /*    */     //   46: invokevirtual EP : (I)V
        /*    */     //   49: <illegal opcode> run : (Lf/Kf;)Ljava/lang/Runnable;
        /*    */     //   54: invokevirtual TG0 : (Ljava/lang/Runnable;)V
        /*    */     //   57: new f/Vq0
        /*    */     //   60: dup
        /*    */     //   61: aload_0
        /*    */     //   62: swap
        /*    */     //   63: dup
        /*    */     //   64: invokespecial <init> : ()V
        /*    */     //   67: putfield kc : Lf/Vq0;
        /*    */     //   70: iconst_0
        /*    */     //   71: invokevirtual T1 : (Z)V
        /*    */     //   74: new f/Ip
        /*    */     //   77: dup
        /*    */     //   78: dup
        /*    */     //   79: aload_0
        /*    */     //   80: swap
        /*    */     //   81: dup
        /*    */     //   82: invokespecial <init> : ()V
        /*    */     //   85: putfield MD0 : Lf/Ip;
        /*    */     //   88: invokevirtual mE0 : ()Lf/g0;
        /*    */     //   91: iconst_1
        /*    */     //   92: anewarray f/U90
        /*    */     //   95: dup
        /*    */     //   96: aload_0
        /*    */     //   97: getfield MD0 : Lf/Ip;
        /*    */     //   100: invokevirtual d7 : ()Lf/cr0;
        /*    */     //   103: bipush #10
        /*    */     //   105: invokevirtual Aq : (I)Lf/U90;
        /*    */     //   108: iconst_1
        /*    */     //   109: anewarray f/JG0
        /*    */     //   112: dup
        /*    */     //   113: aload_0
        /*    */     //   114: getfield kc : Lf/Vq0;
        /*    */     //   117: iconst_0
        /*    */     //   118: swap
        /*    */     //   119: aastore
        /*    */     //   120: invokevirtual Mg : ([Lf/JG0;)Lf/U90;
        /*    */     //   123: iconst_0
        /*    */     //   124: swap
        /*    */     //   125: aastore
        /*    */     //   126: invokevirtual cOM8 : ([Lf/U90;)Lf/U90;
        /*    */     //   129: invokevirtual rK0 : (Lf/U90;)V
        /*    */     //   132: getfield MD0 : Lf/Ip;
        /*    */     //   135: dup
        /*    */     //   136: invokevirtual d7 : ()Lf/cr0;
        /*    */     //   139: iconst_1
        /*    */     //   140: anewarray f/U90
        /*    */     //   143: dup
        /*    */     //   144: aload_0
        /*    */     //   145: getfield MD0 : Lf/Ip;
        /*    */     //   148: iconst_1
        /*    */     //   149: anewarray f/JG0
        /*    */     //   152: dup
        /*    */     //   153: aload_0
        /*    */     //   154: getfield kc : Lf/Vq0;
        /*    */     //   157: iconst_0
        /*    */     //   158: swap
        /*    */     //   159: aastore
        /*    */     //   160: invokevirtual AUX : ([Lf/JG0;)Lf/U90;
        /*    */     //   163: iconst_0
        /*    */     //   164: swap
        /*    */     //   165: aastore
        /*    */     //   166: invokevirtual cOM8 : ([Lf/U90;)Lf/U90;
        /*    */     //   169: invokevirtual WN : (Lf/U90;)V
        /*    */     //   172: ifne -> 194
        /*    */     //   175: invokestatic N2 : ()Lf/js;
        /*    */     //   178: invokevirtual L40 : ()Lf/pA;
        /*    */     //   181: invokevirtual Ol : ()Lf/gO;
        /*    */     //   184: ifnull -> 192
        /*    */     //   187: iconst_1
        /*    */     //   188: istore_1
        /*    */     //   189: goto -> 194
        /*    */     //   192: iconst_0
        /*    */     //   193: istore_1
        /*    */     //   194: aload_0
        /*    */     //   195: dup
        /*    */     //   196: dup
        /*    */     //   197: dup2
        /*    */     //   198: dup2
        /*    */     //   199: dup2
        /*    */     //   200: iload_1
        /*    */     //   201: putfield n80 : Z
        /*    */     //   204: new f/K40
        /*    */     //   207: dup
        /*    */     //   208: aload_0
        /*    */     //   209: iconst_0
        /*    */     //   210: invokespecial <init> : (Lf/Kf;Z)V
        /*    */     //   213: putfield dA0 : Lf/K40;
        /*    */     //   216: new f/K40
        /*    */     //   219: dup
        /*    */     //   220: aload_0
        /*    */     //   221: iconst_1
        /*    */     //   222: invokespecial <init> : (Lf/Kf;Z)V
        /*    */     //   225: putfield fF : Lf/K40;
        /*    */     //   228: invokevirtual IB0 : ()V
        /*    */     //   231: new f/Ip
        /*    */     //   234: dup
        /*    */     //   235: invokespecial <init> : ()V
        /*    */     //   238: putfield bG : Lf/Ip;
        /*    */     //   241: new f/rS
        /*    */     //   244: dup
        /*    */     //   245: dup
        /*    */     //   246: astore_3
        /*    */     //   247: invokespecial <init> : ()V
        /*    */     //   250: ldc_w 'write-mail'
        /*    */     //   253: invokevirtual Xu : (Ljava/lang/String;)V
        /*    */     //   256: new f/dQ
        /*    */     //   259: dup
        /*    */     //   260: dup
        /*    */     //   261: astore #4
        /*    */     //   263: sipush #5828
        /*    */     //   266: invokestatic OH0 : (I)Ljava/lang/String;
        /*    */     //   269: invokespecial <init> : (Ljava/lang/String;)V
        /*    */     //   272: ldc_w 'label-title-small'
        /*    */     //   275: invokevirtual Xu : (Ljava/lang/String;)V
        /*    */     //   278: new f/of
        /*    */     //   281: dup
        /*    */     //   282: aload_0
        /*    */     //   283: swap
        /*    */     //   284: dup
        /*    */     //   285: invokespecial <init> : ()V
        /*    */     //   288: putfield Gr : Lf/of;
        /*    */     //   291: invokevirtual LE : ()V
        /*    */     //   294: getfield Gr : Lf/of;
        /*    */     //   297: aload #4
        /*    */     //   299: invokevirtual Xy : ()Ljava/lang/String;
        /*    */     //   302: pop
        /*    */     //   303: invokevirtual getClass : ()Ljava/lang/Class;
        /*    */     //   306: pop
        /*    */     //   307: getfield Gr : Lf/of;
        /*    */     //   310: bipush #16
        /*    */     //   312: invokevirtual co : (I)V
        /*    */     //   315: getfield Gr : Lf/of;
        /*    */     //   318: invokevirtual vB0 : ()V
        /*    */     //   321: getfield Gr : Lf/of;
        /*    */     //   324: ldc_w '[a-zA-Z]'
        /*    */     //   327: invokevirtual Lpt5 : (Ljava/lang/String;)V
        /*    */     //   330: invokestatic gE0 : ()V
        /*    */     //   333: new f/OZ
        /*    */     //   336: dup
        /*    */     //   337: astore #5
        /*    */     //   339: invokespecial <init> : ()V
        /*    */     //   342: getstatic f/km.u4 : Lf/R8;
        /*    */     //   345: invokevirtual rC0 : ()Lf/Oc0;
        /*    */     //   348: invokevirtual iterator : ()Ljava/util/Iterator;
        /*    */     //   351: astore #6
        /*    */     //   353: aload #6
        /*    */     //   355: invokeinterface hasNext : ()Z
        /*    */     //   360: ifeq -> 386
        /*    */     //   363: aload #5
        /*    */     //   365: aload #6
        /*    */     //   367: invokeinterface next : ()Ljava/lang/Object;
        /*    */     //   372: checkcast f/CD0
        /*    */     //   375: invokeinterface getName : ()Ljava/lang/String;
        /*    */     //   380: invokevirtual i3 : (Ljava/lang/Object;)V
        /*    */     //   383: goto -> 353
        /*    */     //   386: getstatic f/km.u4 : Lf/R8;
        /*    */     //   389: invokevirtual ik0 : ()Lf/mG;
        /*    */     //   392: ifnull -> 459
        /*    */     //   395: getstatic f/km.u4 : Lf/R8;
        /*    */     //   398: invokevirtual ik0 : ()Lf/mG;
        /*    */     //   401: invokevirtual DQ : ()[Lf/ON;
        /*    */     //   404: dup
        /*    */     //   405: astore #6
        /*    */     //   407: arraylength
        /*    */     //   408: istore #7
        /*    */     //   410: iconst_0
        /*    */     //   411: istore #8
        /*    */     //   413: iload #8
        /*    */     //   415: iload #7
        /*    */     //   417: if_icmpge -> 459
        /*    */     //   420: aload #5
        /*    */     //   422: aload #6
        /*    */     //   424: iload #8
        /*    */     //   426: aaload
        /*    */     //   427: dup
        /*    */     //   428: astore #9
        /*    */     //   430: invokeinterface getName : ()Ljava/lang/String;
        /*    */     //   435: invokevirtual on0 : (Ljava/lang/String;)I
        /*    */     //   438: ifge -> 453
        /*    */     //   441: aload #5
        /*    */     //   443: aload #9
        /*    */     //   445: invokeinterface getName : ()Ljava/lang/String;
        /*    */     //   450: invokevirtual i3 : (Ljava/lang/Object;)V
        /*    */     //   453: iinc #8, 1
        /*    */     //   456: goto -> 413
        /*    */     //   459: aload_0
        /*    */     //   460: dup
        /*    */     //   461: dup
        /*    */     //   462: dup2
        /*    */     //   463: dup2
        /*    */     //   464: getfield Gr : Lf/of;
        /*    */     //   467: aload #5
        /*    */     //   469: <illegal opcode> Nj0 : (Lf/OZ;)Lf/CF0;
        /*    */     //   474: invokevirtual Aw0 : (Lf/CF0;)V
        /*    */     //   477: new f/Un
        /*    */     //   480: dup
        /*    */     //   481: astore #5
        /*    */     //   483: aload_0
        /*    */     //   484: aload #5
        /*    */     //   486: dup
        /*    */     //   487: ldc_w '+'
        /*    */     //   490: invokespecial <init> : (Ljava/lang/String;)V
        /*    */     //   493: <illegal opcode> run : (Lf/Kf;Lf/Un;)Ljava/lang/Runnable;
        /*    */     //   498: invokevirtual tW : (Ljava/lang/Runnable;)V
        /*    */     //   501: new f/dQ
        /*    */     //   504: dup
        /*    */     //   505: astore #6
        /*    */     //   507: aload_0
        /*    */     //   508: aload #6
        /*    */     //   510: dup
        /*    */     //   511: sipush #5829
        /*    */     //   514: invokestatic OH0 : (I)Ljava/lang/String;
        /*    */     //   517: invokespecial <init> : (Ljava/lang/String;)V
        /*    */     //   520: ldc_w 'label-title-small'
        /*    */     //   523: invokevirtual Xu : (Ljava/lang/String;)V
        /*    */     //   526: new f/of
        /*    */     //   529: dup
        /*    */     //   530: invokespecial <init> : ()V
        /*    */     //   533: putfield cl : Lf/of;
        /*    */     //   536: invokevirtual Xy : ()Ljava/lang/String;
        /*    */     //   539: pop
        /*    */     //   540: getfield cl : Lf/of;
        /*    */     //   543: bipush #40
        /*    */     //   545: invokevirtual co : (I)V
        /*    */     //   548: new f/dQ
        /*    */     //   551: dup
        /*    */     //   552: astore #7
        /*    */     //   554: aload_0
        /*    */     //   555: aload #7
        /*    */     //   557: dup
        /*    */     //   558: sipush #5830
        /*    */     //   561: invokestatic OH0 : (I)Ljava/lang/String;
        /*    */     //   564: invokespecial <init> : (Ljava/lang/String;)V
        /*    */     //   567: ldc_w 'label-title-small'
        /*    */     //   570: invokevirtual Xu : (Ljava/lang/String;)V
        /*    */     //   573: new f/of
        /*    */     //   576: dup
        /*    */     //   577: invokespecial <init> : ()V
        /*    */     //   580: putfield Nv0 : Lf/of;
        /*    */     //   583: invokevirtual Xy : ()Ljava/lang/String;
        /*    */     //   586: pop
        /*    */     //   587: getfield Nv0 : Lf/of;
        /*    */     //   590: sipush #2000
        /*    */     //   593: invokevirtual co : (I)V
        /*    */     //   596: getfield Nv0 : Lf/of;
        /*    */     //   599: invokevirtual ZW : ()V
        /*    */     //   602: new f/rS
        /*    */     //   605: dup
        /*    */     //   606: astore #8
        /*    */     //   608: aload_0
        /*    */     //   609: getfield Nv0 : Lf/of;
        /*    */     //   612: invokespecial <init> : (Lf/JG0;)V
        /*    */     //   615: new f/dQ
        /*    */     //   618: dup
        /*    */     //   619: dup
        /*    */     //   620: astore #9
        /*    */     //   622: sipush #5831
        /*    */     //   625: invokestatic OH0 : (I)Ljava/lang/String;
        /*    */     //   628: invokespecial <init> : (Ljava/lang/String;)V
        /*    */     //   631: ldc_w 'label-title-small'
        /*    */     //   634: invokevirtual Xu : (Ljava/lang/String;)V
        /*    */     //   637: new f/zT
        /*    */     //   640: dup
        /*    */     //   641: astore #10
        /*    */     //   643: aload_0
        /*    */     //   644: dup
        /*    */     //   645: aload #10
        /*    */     //   647: iconst_0
        /*    */     //   648: ldc_w 2000000000
        /*    */     //   651: iconst_0
        /*    */     //   652: invokespecial <init> : (III)V
        /*    */     //   655: new f/Rm
        /*    */     //   658: dup
        /*    */     //   659: aload #10
        /*    */     //   661: invokespecial <init> : (Lf/zT;)V
        /*    */     //   664: putfield default : Lf/Rm;
        /*    */     //   667: <illegal opcode> run : (Lf/Kf;)Ljava/lang/Runnable;
        /*    */     //   672: invokevirtual Ac0 : (Ljava/lang/Runnable;)V
        /*    */     //   675: getfield default : Lf/Rm;
        /*    */     //   678: invokevirtual VL : ()V
        /*    */     //   681: getfield default : Lf/Rm;
        /*    */     //   684: iload_1
        /*    */     //   685: invokevirtual sk0 : (Z)V
        /*    */     //   688: new f/dQ
        /*    */     //   691: dup
        /*    */     //   692: dup
        /*    */     //   693: astore #10
        /*    */     //   695: sipush #5832
        /*    */     //   698: invokestatic OH0 : (I)Ljava/lang/String;
        /*    */     //   701: invokespecial <init> : (Ljava/lang/String;)V
        /*    */     //   704: ldc_w 'label-title-small'
        /*    */     //   707: invokevirtual Xu : (Ljava/lang/String;)V
        /*    */     //   710: iconst_5
        /*    */     //   711: anewarray f/T1
        /*    */     //   714: putfield WN : [Lf/T1;
        /*    */     //   717: iconst_0
        /*    */     //   718: istore #11
        /*    */     //   720: iload #11
        /*    */     //   722: aload_0
        /*    */     //   723: getfield WN : [Lf/T1;
        /*    */     //   726: arraylength
        /*    */     //   727: if_icmpge -> 801
        /*    */     //   730: iload_1
        /*    */     //   731: new f/T1
        /*    */     //   734: dup
        /*    */     //   735: astore #12
        /*    */     //   737: iload_1
        /*    */     //   738: aload #12
        /*    */     //   740: aload_0
        /*    */     //   741: aload #12
        /*    */     //   743: dup
        /*    */     //   744: dup
        /*    */     //   745: invokespecial <init> : ()V
        /*    */     //   748: <illegal opcode> run : (Lf/T1;)Ljava/lang/Runnable;
        /*    */     //   753: invokevirtual bm0 : (Ljava/lang/Runnable;)V
        /*    */     //   756: <illegal opcode> run : (Lf/Kf;)Ljava/lang/Runnable;
        /*    */     //   761: invokevirtual tW : (Ljava/lang/Runnable;)V
        /*    */     //   764: invokevirtual sk0 : (Z)V
        /*    */     //   767: ifne -> 786
        /*    */     //   770: aload #12
        /*    */     //   772: dup
        /*    */     //   773: sipush #5846
        /*    */     //   776: invokestatic OH0 : (I)Ljava/lang/String;
        /*    */     //   779: invokevirtual Gq0 : (Ljava/lang/Object;)V
        /*    */     //   782: iconst_0
        /*    */     //   783: invokevirtual Pb0 : (I)V
        /*    */     //   786: aload_0
        /*    */     //   787: getfield WN : [Lf/T1;
        /*    */     //   790: iload #11
        /*    */     //   792: aload #12
        /*    */     //   794: aastore
        /*    */     //   795: iinc #11, 1
        /*    */     //   798: goto -> 720
        /*    */     //   801: aload_0
        /*    */     //   802: new f/dQ
        /*    */     //   805: dup
        /*    */     //   806: dup
        /*    */     //   807: astore #11
        /*    */     //   809: sipush #5833
        /*    */     //   812: invokestatic OH0 : (I)Ljava/lang/String;
        /*    */     //   815: invokespecial <init> : (Ljava/lang/String;)V
        /*    */     //   818: ldc_w 'label-title-small'
        /*    */     //   821: invokevirtual Xu : (Ljava/lang/String;)V
        /*    */     //   824: iconst_5
        /*    */     //   825: anewarray f/G9
        /*    */     //   828: putfield Jt : [Lf/Qv0;
        /*    */     //   831: iconst_0
        /*    */     //   832: istore #12
        /*    */     //   834: iload #12
        /*    */     //   836: aload_0
        /*    */     //   837: getfield Jt : [Lf/Qv0;
        /*    */     //   840: arraylength
        /*    */     //   841: if_icmpge -> 933
        /*    */     //   844: iload_1
        /*    */     //   845: new f/G9
        /*    */     //   848: dup
        /*    */     //   849: astore #13
        /*    */     //   851: aload_0
        /*    */     //   852: aload #13
        /*    */     //   854: dup
        /*    */     //   855: aload_0
        /*    */     //   856: aload #13
        /*    */     //   858: dup
        /*    */     //   859: dup2
        /*    */     //   860: iload_1
        /*    */     //   861: aload #13
        /*    */     //   863: dup
        /*    */     //   864: invokespecial <init> : ()V
        /*    */     //   867: invokevirtual dC0 : ()V
        /*    */     //   870: invokevirtual sk0 : (Z)V
        /*    */     //   873: invokevirtual Ws : ()Z
        /*    */     //   876: invokevirtual hC : (Z)V
        /*    */     //   879: iconst_1
        /*    */     //   880: invokevirtual wU : (Z)V
        /*    */     //   883: <illegal opcode> run : (Lf/Kf;)Ljava/lang/Runnable;
        /*    */     //   888: invokevirtual tW : (Ljava/lang/Runnable;)V
        /*    */     //   891: <illegal opcode> run : (Lf/Kf;Lf/G9;)Ljava/lang/Runnable;
        /*    */     //   896: invokevirtual L1 : (Ljava/lang/Runnable;)V
        /*    */     //   899: ifne -> 918
        /*    */     //   902: aload #13
        /*    */     //   904: dup
        /*    */     //   905: sipush #5846
        /*    */     //   908: invokestatic OH0 : (I)Ljava/lang/String;
        /*    */     //   911: invokevirtual Gq0 : (Ljava/lang/Object;)V
        /*    */     //   914: iconst_0
        /*    */     //   915: invokevirtual Pb0 : (I)V
        /*    */     //   918: aload_0
        /*    */     //   919: getfield Jt : [Lf/Qv0;
        /*    */     //   922: iload #12
        /*    */     //   924: aload #13
        /*    */     //   926: aastore
        /*    */     //   927: iinc #12, 1
        /*    */     //   930: goto -> 834
        /*    */     //   933: iload_1
        /*    */     //   934: ifne -> 958
        /*    */     //   937: aload_0
        /*    */     //   938: dup
        /*    */     //   939: getfield default : Lf/Rm;
        /*    */     //   942: sipush #5846
        /*    */     //   945: invokestatic OH0 : (I)Ljava/lang/String;
        /*    */     //   948: invokevirtual Gq0 : (Ljava/lang/Object;)V
        /*    */     //   951: getfield default : Lf/Rm;
        /*    */     //   954: iconst_0
        /*    */     //   955: invokevirtual Pb0 : (I)V
        /*    */     //   958: aload_0
        /*    */     //   959: dup
        /*    */     //   960: aload_3
        /*    */     //   961: aload_0
        /*    */     //   962: dup
        /*    */     //   963: dup
        /*    */     //   964: new f/Un
        /*    */     //   967: dup
        /*    */     //   968: aload_0
        /*    */     //   969: swap
        /*    */     //   970: dup
        /*    */     //   971: sipush #5834
        /*    */     //   974: invokestatic OH0 : (I)Ljava/lang/String;
        /*    */     //   977: invokespecial <init> : (Ljava/lang/String;)V
        /*    */     //   980: putfield tv : Lf/Un;
        /*    */     //   983: getstatic f/et.Wi0 : Lf/et;
        /*    */     //   986: dup
        /*    */     //   987: astore_1
        /*    */     //   988: invokevirtual C70 : (Lf/et;)V
        /*    */     //   991: getfield tv : Lf/Un;
        /*    */     //   994: aload_0
        /*    */     //   995: <illegal opcode> run : (Lf/Kf;)Ljava/lang/Runnable;
        /*    */     //   1000: invokevirtual tW : (Ljava/lang/Runnable;)V
        /*    */     //   1003: new f/Un
        /*    */     //   1006: dup
        /*    */     //   1007: astore #12
        /*    */     //   1009: aload_0
        /*    */     //   1010: aload #12
        /*    */     //   1012: aload_1
        /*    */     //   1013: aload #12
        /*    */     //   1015: sipush #5841
        /*    */     //   1018: invokestatic OH0 : (I)Ljava/lang/String;
        /*    */     //   1021: invokespecial <init> : (Ljava/lang/String;)V
        /*    */     //   1024: invokevirtual C70 : (Lf/et;)V
        /*    */     //   1027: <illegal opcode> run : (Lf/Kf;)Ljava/lang/Runnable;
        /*    */     //   1032: invokevirtual tW : (Ljava/lang/Runnable;)V
        /*    */     //   1035: new f/dQ
        /*    */     //   1038: dup
        /*    */     //   1039: astore_1
        /*    */     //   1040: aload_0
        /*    */     //   1041: aload_1
        /*    */     //   1042: dup
        /*    */     //   1043: sipush #5840
        /*    */     //   1046: invokestatic OH0 : (I)Ljava/lang/String;
        /*    */     //   1049: invokespecial <init> : (Ljava/lang/String;)V
        /*    */     //   1052: ldc_w 'label-title-small'
        /*    */     //   1055: invokevirtual Xu : (Ljava/lang/String;)V
        /*    */     //   1058: new f/of
        /*    */     //   1061: dup
        /*    */     //   1062: invokespecial <init> : ()V
        /*    */     //   1065: putfield Fw : Lf/of;
        /*    */     //   1068: invokevirtual Xy : ()Ljava/lang/String;
        /*    */     //   1071: pop
        /*    */     //   1072: getfield Fw : Lf/of;
        /*    */     //   1075: iconst_0
        /*    */     //   1076: invokevirtual sk0 : (Z)V
        /*    */     //   1079: invokevirtual PR : ()V
        /*    */     //   1082: new f/Ip
        /*    */     //   1085: dup
        /*    */     //   1086: dup
        /*    */     //   1087: dup2
        /*    */     //   1088: dup2
        /*    */     //   1089: astore #13
        /*    */     //   1091: invokespecial <init> : ()V
        /*    */     //   1094: bipush #8
        /*    */     //   1096: anewarray f/U90
        /*    */     //   1099: dup
        /*    */     //   1100: dup
        /*    */     //   1101: astore #14
        /*    */     //   1103: aload #13
        /*    */     //   1105: aload #14
        /*    */     //   1107: aload #13
        /*    */     //   1109: aload #14
        /*    */     //   1111: aload #13
        /*    */     //   1113: aload #14
        /*    */     //   1115: aload #13
        /*    */     //   1117: aload #14
        /*    */     //   1119: aload #13
        /*    */     //   1121: aload #14
        /*    */     //   1123: aload #13
        /*    */     //   1125: aload #14
        /*    */     //   1127: aload #13
        /*    */     //   1129: aload #14
        /*    */     //   1131: aload #13
        /*    */     //   1133: iconst_3
        /*    */     //   1134: anewarray f/JG0
        /*    */     //   1137: dup
        /*    */     //   1138: dup2
        /*    */     //   1139: aload_0
        /*    */     //   1140: swap
        /*    */     //   1141: iconst_0
        /*    */     //   1142: aload #4
        /*    */     //   1144: aastore
        /*    */     //   1145: getfield Gr : Lf/of;
        /*    */     //   1148: iconst_1
        /*    */     //   1149: swap
        /*    */     //   1150: aastore
        /*    */     //   1151: iconst_2
        /*    */     //   1152: aload #5
        /*    */     //   1154: aastore
        /*    */     //   1155: invokevirtual vo0 : ([Lf/JG0;)Lf/U90;
        /*    */     //   1158: iconst_0
        /*    */     //   1159: swap
        /*    */     //   1160: aastore
        /*    */     //   1161: iconst_2
        /*    */     //   1162: anewarray f/JG0
        /*    */     //   1165: dup
        /*    */     //   1166: dup
        /*    */     //   1167: aload_0
        /*    */     //   1168: swap
        /*    */     //   1169: iconst_0
        /*    */     //   1170: aload #6
        /*    */     //   1172: aastore
        /*    */     //   1173: getfield cl : Lf/of;
        /*    */     //   1176: iconst_1
        /*    */     //   1177: swap
        /*    */     //   1178: aastore
        /*    */     //   1179: invokevirtual vo0 : ([Lf/JG0;)Lf/U90;
        /*    */     //   1182: iconst_1
        /*    */     //   1183: swap
        /*    */     //   1184: aastore
        /*    */     //   1185: iconst_2
        /*    */     //   1186: anewarray f/JG0
        /*    */     //   1189: dup
        /*    */     //   1190: dup
        /*    */     //   1191: iconst_0
        /*    */     //   1192: aload #7
        /*    */     //   1194: aastore
        /*    */     //   1195: iconst_1
        /*    */     //   1196: aload #8
        /*    */     //   1198: aastore
        /*    */     //   1199: invokevirtual vo0 : ([Lf/JG0;)Lf/U90;
        /*    */     //   1202: iconst_2
        /*    */     //   1203: swap
        /*    */     //   1204: aastore
        /*    */     //   1205: iconst_2
        /*    */     //   1206: anewarray f/JG0
        /*    */     //   1209: dup
        /*    */     //   1210: dup
        /*    */     //   1211: aload_0
        /*    */     //   1212: swap
        /*    */     //   1213: iconst_0
        /*    */     //   1214: aload #9
        /*    */     //   1216: aastore
        /*    */     //   1217: getfield default : Lf/Rm;
        /*    */     //   1220: iconst_1
        /*    */     //   1221: swap
        /*    */     //   1222: aastore
        /*    */     //   1223: invokevirtual vo0 : ([Lf/JG0;)Lf/U90;
        /*    */     //   1226: iconst_3
        /*    */     //   1227: swap
        /*    */     //   1228: aastore
        /*    */     //   1229: iconst_1
        /*    */     //   1230: anewarray f/JG0
        /*    */     //   1233: dup
        /*    */     //   1234: iconst_0
        /*    */     //   1235: aload #10
        /*    */     //   1237: aastore
        /*    */     //   1238: invokevirtual vo0 : ([Lf/JG0;)Lf/U90;
        /*    */     //   1241: aload_0
        /*    */     //   1242: getfield WN : [Lf/T1;
        /*    */     //   1245: invokevirtual Mg : ([Lf/JG0;)Lf/U90;
        /*    */     //   1248: iconst_4
        /*    */     //   1249: swap
        /*    */     //   1250: aastore
        /*    */     //   1251: iconst_1
        /*    */     //   1252: anewarray f/JG0
        /*    */     //   1255: dup
        /*    */     //   1256: iconst_0
        /*    */     //   1257: aload #11
        /*    */     //   1259: aastore
        /*    */     //   1260: invokevirtual vo0 : ([Lf/JG0;)Lf/U90;
        /*    */     //   1263: aload_0
        /*    */     //   1264: getfield Jt : [Lf/Qv0;
        /*    */     //   1267: invokevirtual Mg : ([Lf/JG0;)Lf/U90;
        /*    */     //   1270: iconst_5
        /*    */     //   1271: swap
        /*    */     //   1272: aastore
        /*    */     //   1273: iconst_2
        /*    */     //   1274: anewarray f/JG0
        /*    */     //   1277: dup
        /*    */     //   1278: dup
        /*    */     //   1279: aload_0
        /*    */     //   1280: swap
        /*    */     //   1281: iconst_0
        /*    */     //   1282: aload_1
        /*    */     //   1283: aastore
        /*    */     //   1284: getfield Fw : Lf/of;
        /*    */     //   1287: iconst_1
        /*    */     //   1288: swap
        /*    */     //   1289: aastore
        /*    */     //   1290: invokevirtual vo0 : ([Lf/JG0;)Lf/U90;
        /*    */     //   1293: bipush #6
        /*    */     //   1295: swap
        /*    */     //   1296: aastore
        /*    */     //   1297: iconst_1
        /*    */     //   1298: anewarray f/JG0
        /*    */     //   1301: dup
        /*    */     //   1302: iconst_0
        /*    */     //   1303: aload #12
        /*    */     //   1305: aastore
        /*    */     //   1306: invokevirtual vo0 : ([Lf/JG0;)Lf/U90;
        /*    */     //   1309: invokevirtual Em0 : ()Lf/U90;
        /*    */     //   1312: aload_0
        /*    */     //   1313: getfield tv : Lf/Un;
        /*    */     //   1316: invokevirtual Ya : (Lf/JG0;)Lf/U90;
        /*    */     //   1319: bipush #7
        /*    */     //   1321: swap
        /*    */     //   1322: aastore
        /*    */     //   1323: invokevirtual Yw0 : ([Lf/U90;)Lf/U90;
        /*    */     //   1326: invokevirtual rK0 : (Lf/U90;)V
        /*    */     //   1329: bipush #8
        /*    */     //   1331: anewarray f/U90
        /*    */     //   1334: dup
        /*    */     //   1335: dup
        /*    */     //   1336: astore #14
        /*    */     //   1338: aload #13
        /*    */     //   1340: aload #14
        /*    */     //   1342: aload #13
        /*    */     //   1344: aload #14
        /*    */     //   1346: aload #13
        /*    */     //   1348: aload #14
        /*    */     //   1350: aload #13
        /*    */     //   1352: aload #14
        /*    */     //   1354: aload #13
        /*    */     //   1356: aload #14
        /*    */     //   1358: aload #13
        /*    */     //   1360: aload #14
        /*    */     //   1362: aload #13
        /*    */     //   1364: aload #14
        /*    */     //   1366: aload #13
        /*    */     //   1368: iconst_3
        /*    */     //   1369: anewarray f/JG0
        /*    */     //   1372: dup
        /*    */     //   1373: dup2
        /*    */     //   1374: aload_0
        /*    */     //   1375: swap
        /*    */     //   1376: iconst_0
        /*    */     //   1377: aload #4
        /*    */     //   1379: aastore
        /*    */     //   1380: getfield Gr : Lf/of;
        /*    */     //   1383: iconst_1
        /*    */     //   1384: swap
        /*    */     //   1385: aastore
        /*    */     //   1386: iconst_2
        /*    */     //   1387: aload #5
        /*    */     //   1389: aastore
        /*    */     //   1390: invokevirtual AUX : ([Lf/JG0;)Lf/U90;
        /*    */     //   1393: iconst_0
        /*    */     //   1394: swap
        /*    */     //   1395: aastore
        /*    */     //   1396: iconst_2
        /*    */     //   1397: anewarray f/JG0
        /*    */     //   1400: dup
        /*    */     //   1401: dup
        /*    */     //   1402: aload_0
        /*    */     //   1403: swap
        /*    */     //   1404: iconst_0
        /*    */     //   1405: aload #6
        /*    */     //   1407: aastore
        /*    */     //   1408: getfield cl : Lf/of;
        /*    */     //   1411: iconst_1
        /*    */     //   1412: swap
        /*    */     //   1413: aastore
        /*    */     //   1414: invokevirtual AUX : ([Lf/JG0;)Lf/U90;
        /*    */     //   1417: iconst_1
        /*    */     //   1418: swap
        /*    */     //   1419: aastore
        /*    */     //   1420: iconst_2
        /*    */     //   1421: anewarray f/JG0
        /*    */     //   1424: dup
        /*    */     //   1425: dup
        /*    */     //   1426: iconst_0
        /*    */     //   1427: aload #7
        /*    */     //   1429: aastore
        /*    */     //   1430: iconst_1
        /*    */     //   1431: aload #8
        /*    */     //   1433: aastore
        /*    */     //   1434: invokevirtual AUX : ([Lf/JG0;)Lf/U90;
        /*    */     //   1437: iconst_2
        /*    */     //   1438: swap
        /*    */     //   1439: aastore
        /*    */     //   1440: iconst_2
        /*    */     //   1441: anewarray f/JG0
        /*    */     //   1444: dup
        /*    */     //   1445: dup
        /*    */     //   1446: aload_0
        /*    */     //   1447: swap
        /*    */     //   1448: iconst_0
        /*    */     //   1449: aload #9
        /*    */     //   1451: aastore
        /*    */     //   1452: getfield default : Lf/Rm;
        /*    */     //   1455: iconst_1
        /*    */     //   1456: swap
        /*    */     //   1457: aastore
        /*    */     //   1458: invokevirtual AUX : ([Lf/JG0;)Lf/U90;
        /*    */     //   1461: iconst_3
        /*    */     //   1462: swap
        /*    */     //   1463: aastore
        /*    */     //   1464: iconst_1
        /*    */     //   1465: anewarray f/JG0
        /*    */     //   1468: dup
        /*    */     //   1469: iconst_0
        /*    */     //   1470: aload #10
        /*    */     //   1472: aastore
        /*    */     //   1473: invokevirtual AUX : ([Lf/JG0;)Lf/U90;
        /*    */     //   1476: aload_0
        /*    */     //   1477: getfield WN : [Lf/T1;
        /*    */     //   1480: invokevirtual Mg : ([Lf/JG0;)Lf/U90;
        /*    */     //   1483: iconst_4
        /*    */     //   1484: swap
        /*    */     //   1485: aastore
        /*    */     //   1486: iconst_1
        /*    */     //   1487: anewarray f/JG0
        /*    */     //   1490: dup
        /*    */     //   1491: iconst_0
        /*    */     //   1492: aload #11
        /*    */     //   1494: aastore
        /*    */     //   1495: invokevirtual AUX : ([Lf/JG0;)Lf/U90;
        /*    */     //   1498: aload_0
        /*    */     //   1499: getfield Jt : [Lf/Qv0;
        /*    */     //   1502: invokevirtual Mg : ([Lf/JG0;)Lf/U90;
        /*    */     //   1505: iconst_5
        /*    */     //   1506: swap
        /*    */     //   1507: aastore
        /*    */     //   1508: iconst_2
        /*    */     //   1509: anewarray f/JG0
        /*    */     //   1512: dup
        /*    */     //   1513: dup
        /*    */     //   1514: aload_0
        /*    */     //   1515: swap
        /*    */     //   1516: iconst_0
        /*    */     //   1517: aload_1
        /*    */     //   1518: aastore
        /*    */     //   1519: getfield Fw : Lf/of;
        /*    */     //   1522: iconst_1
        /*    */     //   1523: swap
        /*    */     //   1524: aastore
        /*    */     //   1525: invokevirtual AUX : ([Lf/JG0;)Lf/U90;
        /*    */     //   1528: bipush #6
        /*    */     //   1530: swap
        /*    */     //   1531: aastore
        /*    */     //   1532: iconst_2
        /*    */     //   1533: anewarray f/JG0
        /*    */     //   1536: dup
        /*    */     //   1537: dup
        /*    */     //   1538: aload_0
        /*    */     //   1539: swap
        /*    */     //   1540: iconst_0
        /*    */     //   1541: aload #12
        /*    */     //   1543: aastore
        /*    */     //   1544: getfield tv : Lf/Un;
        /*    */     //   1547: iconst_1
        /*    */     //   1548: swap
        /*    */     //   1549: aastore
        /*    */     //   1550: invokevirtual AUX : ([Lf/JG0;)Lf/U90;
        /*    */     //   1553: bipush #7
        /*    */     //   1555: swap
        /*    */     //   1556: aastore
        /*    */     //   1557: invokevirtual Gs : ([Lf/U90;)Lf/U90;
        /*    */     //   1560: invokevirtual WN : (Lf/U90;)V
        /*    */     //   1563: invokevirtual Gz0 : (Lf/JG0;)V
        /*    */     //   1566: getfield bG : Lf/Ip;
        /*    */     //   1569: dup
        /*    */     //   1570: invokevirtual mE0 : ()Lf/g0;
        /*    */     //   1573: iconst_1
        /*    */     //   1574: anewarray f/U90
        /*    */     //   1577: dup
        /*    */     //   1578: aload_0
        /*    */     //   1579: getfield bG : Lf/Ip;
        /*    */     //   1582: iconst_1
        /*    */     //   1583: anewarray f/JG0
        /*    */     //   1586: dup
        /*    */     //   1587: iconst_0
        /*    */     //   1588: aload_3
        /*    */     //   1589: aastore
        /*    */     //   1590: invokevirtual vo0 : ([Lf/JG0;)Lf/U90;
        /*    */     //   1593: iconst_0
        /*    */     //   1594: swap
        /*    */     //   1595: aastore
        /*    */     //   1596: invokevirtual cOM8 : ([Lf/U90;)Lf/U90;
        /*    */     //   1599: invokevirtual rK0 : (Lf/U90;)V
        /*    */     //   1602: getfield bG : Lf/Ip;
        /*    */     //   1605: dup
        /*    */     //   1606: astore_1
        /*    */     //   1607: invokevirtual d7 : ()Lf/cr0;
        /*    */     //   1610: astore #4
        /*    */     //   1612: invokestatic XU : ()Z
        /*    */     //   1615: ifeq -> 1624
        /*    */     //   1618: iconst_0
        /*    */     //   1619: istore #5
        /*    */     //   1621: goto -> 1628
        /*    */     //   1624: bipush #30
        /*    */     //   1626: istore #5
        /*    */     //   1628: aload_2
        /*    */     //   1629: aload_0
        /*    */     //   1630: dup
        /*    */     //   1631: dup
        /*    */     //   1632: dup2
        /*    */     //   1633: dup2
        /*    */     //   1634: dup2
        /*    */     //   1635: aload_1
        /*    */     //   1636: aload #4
        /*    */     //   1638: iload #5
        /*    */     //   1640: invokevirtual Aq : (I)Lf/U90;
        /*    */     //   1643: iconst_1
        /*    */     //   1644: anewarray f/U90
        /*    */     //   1647: dup
        /*    */     //   1648: aload_0
        /*    */     //   1649: getfield bG : Lf/Ip;
        /*    */     //   1652: invokevirtual mE0 : ()Lf/g0;
        /*    */     //   1655: aload_3
        /*    */     //   1656: invokevirtual Ya : (Lf/JG0;)Lf/U90;
        /*    */     //   1659: iconst_0
        /*    */     //   1660: swap
        /*    */     //   1661: aastore
        /*    */     //   1662: invokevirtual cOM8 : ([Lf/U90;)Lf/U90;
        /*    */     //   1665: invokevirtual WN : (Lf/U90;)V
        /*    */     //   1668: getfield dA0 : Lf/K40;
        /*    */     //   1671: invokevirtual hI0 : ()V
        /*    */     //   1674: getfield fF : Lf/K40;
        /*    */     //   1677: invokevirtual hI0 : ()V
        /*    */     //   1680: getfield kc : Lf/Vq0;
        /*    */     //   1683: aload_0
        /*    */     //   1684: sipush #5835
        /*    */     //   1687: invokestatic OH0 : (I)Ljava/lang/String;
        /*    */     //   1690: astore_1
        /*    */     //   1691: getfield dA0 : Lf/K40;
        /*    */     //   1694: getfield Am0 : Lf/Ip;
        /*    */     //   1697: aload_1
        /*    */     //   1698: invokevirtual WS : (Lf/JG0;Ljava/lang/String;)Lf/Li0;
        /*    */     //   1701: aload_0
        /*    */     //   1702: <illegal opcode> run : (Lf/Kf;)Ljava/lang/Runnable;
        /*    */     //   1707: invokevirtual Ac0 : (Ljava/lang/Runnable;)V
        /*    */     //   1710: getfield kc : Lf/Vq0;
        /*    */     //   1713: aload_0
        /*    */     //   1714: sipush #5834
        /*    */     //   1717: invokestatic OH0 : (I)Ljava/lang/String;
        /*    */     //   1720: astore_1
        /*    */     //   1721: getfield bG : Lf/Ip;
        /*    */     //   1724: aload_1
        /*    */     //   1725: invokevirtual WS : (Lf/JG0;Ljava/lang/String;)Lf/Li0;
        /*    */     //   1728: aload_0
        /*    */     //   1729: <illegal opcode> run : (Lf/Kf;)Ljava/lang/Runnable;
        /*    */     //   1734: invokevirtual Ac0 : (Ljava/lang/Runnable;)V
        /*    */     //   1737: getfield kc : Lf/Vq0;
        /*    */     //   1740: aload_0
        /*    */     //   1741: sipush #5848
        /*    */     //   1744: invokestatic OH0 : (I)Ljava/lang/String;
        /*    */     //   1747: astore_1
        /*    */     //   1748: getfield fF : Lf/K40;
        /*    */     //   1751: getfield Am0 : Lf/Ip;
        /*    */     //   1754: aload_1
        /*    */     //   1755: invokevirtual WS : (Lf/JG0;Ljava/lang/String;)Lf/Li0;
        /*    */     //   1758: aload_0
        /*    */     //   1759: <illegal opcode> run : (Lf/Kf;)Ljava/lang/Runnable;
        /*    */     //   1764: invokevirtual Ac0 : (Ljava/lang/Runnable;)V
        /*    */     //   1767: getfield MD0 : Lf/Ip;
        /*    */     //   1770: invokevirtual J8 : (Lf/JG0;)V
        /*    */     //   1773: getfield dA0 : Lf/K40;
        /*    */     //   1776: iconst_0
        /*    */     //   1777: invokevirtual Vq0 : (S)V
        /*    */     //   1780: getfield fF : Lf/K40;
        /*    */     //   1783: iconst_0
        /*    */     //   1784: invokevirtual Vq0 : (S)V
        /*    */     //   1787: ifnull -> 1795
        /*    */     //   1790: aload_0
        /*    */     //   1791: aload_2
        /*    */     //   1792: invokevirtual zf0 : (Lf/j40;)V
        /*  7 */     //   1795: return } public final List KK0() { return (List)Arrays.<j40>stream(km.u4.s40(aq0.LI).lPt3()).filter(paramj40 -> (paramj40 != null && !py.Gw0(paramj40, Arrays.<Qv0>stream(this.Jt).map(Qv0::public).filter(Objects::nonNull).toArray(Kf::Ow0)))).sorted(Comparator.comparingInt(Kf::lm0)).collect(Collectors.toList()); } public final void PR() { int i = 100; if (this.default.T8 > 0) i = 400;  this(); V6 v61, v62; this(); T1[] arrayOfT1; int k; byte b; for (k = (arrayOfT1 = this.WN).length, b = 0; b < k; ) { T1 t1; if ((t1 = arrayOfT1[b]).hC0 >= 1) if (!v61.uX(t1.dn0)) { t1.Tm0(null); } else { i += 300; }   b++; }  Qv0[] arrayOfQv0; for (int j = (arrayOfQv0 = this.Jt).length; k < j; ) { Qv0 qv0; if ((qv0 = arrayOfQv0[k]).public() != null) if (!v62.uX((qv0.public()).Jg)) { qv0.zf(null); } else { i += 300; }   k++; }  if (!Bz.uD && km.D70(7)) { i = 0; } else if (!Bz.uD && km.D70(1)) { i -= 100; }  this.Fw
        /*    */
        /*  9 */       .Zh(B40.df("$").append(NumberFormat.getInstance().format(i)).toString());
    }

    public final void Ym0(boolean paramBoolean) { // Byte code:
        /*    */     //   0: aload_0
        /*    */     //   1: getfield Gr : Lf/of;
        /*    */     //   4: getfield F2 : Lf/ak0;
        /*    */     //   7: getfield PH0 : Ljava/lang/StringBuilder;
        /*    */     //   10: invokevirtual length : ()I
        /*    */     //   13: iconst_2
        /*    */     //   14: if_icmplt -> 608
        /*    */     //   17: aload_0
        /*    */     //   18: getfield Gr : Lf/of;
        /*    */     //   21: getfield F2 : Lf/ak0;
        /*    */     //   24: getfield PH0 : Ljava/lang/StringBuilder;
        /*    */     //   27: invokevirtual length : ()I
        /*    */     //   30: bipush #16
        /*    */     //   32: if_icmple -> 38
        /*    */     //   35: goto -> 608
        /*    */     //   38: aload_0
        /*    */     //   39: getfield cl : Lf/of;
        /*    */     //   42: getfield F2 : Lf/ak0;
        /*    */     //   45: getfield PH0 : Ljava/lang/StringBuilder;
        /*    */     //   48: invokevirtual length : ()I
        /*    */     //   51: iconst_1
        /*    */     //   52: if_icmpge -> 66
        /*    */     //   55: aload_0
        /*    */     //   56: getfield cl : Lf/of;
        /*    */     //   59: ldc_w '(No Subject)'
        /*    */     //   62: iconst_0
        /*    */     //   63: invokevirtual Be0 : (Ljava/lang/String;Z)V
        /*    */     //   66: aload_0
        /*    */     //   67: getfield cl : Lf/of;
        /*    */     //   70: getfield F2 : Lf/ak0;
        /*    */     //   73: getfield PH0 : Ljava/lang/StringBuilder;
        /*    */     //   76: invokevirtual length : ()I
        /*    */     //   79: bipush #40
        /*    */     //   81: if_icmple -> 92
        /*    */     //   84: aload_0
        /*    */     //   85: getstatic f/pv0.y40 : Lf/pv0;
        /*    */     //   88: invokevirtual JK0 : (Lf/pv0;)V
        /*    */     //   91: return
        /*    */     //   92: aload_0
        /*    */     //   93: getfield Nv0 : Lf/of;
        /*    */     //   96: getfield F2 : Lf/ak0;
        /*    */     //   99: getfield PH0 : Ljava/lang/StringBuilder;
        /*    */     //   102: invokevirtual length : ()I
        /*    */     //   105: iconst_1
        /*    */     //   106: if_icmplt -> 600
        /*    */     //   109: aload_0
        /*    */     //   110: getfield Nv0 : Lf/of;
        /*    */     //   113: getfield F2 : Lf/ak0;
        /*    */     //   116: getfield PH0 : Ljava/lang/StringBuilder;
        /*    */     //   119: invokevirtual length : ()I
        /*    */     //   122: sipush #2000
        /*    */     //   125: if_icmple -> 131
        /*    */     //   128: goto -> 600
        /*    */     //   131: aload_0
        /*    */     //   132: dup
        /*    */     //   133: getfield tv : Lf/Un;
        /*    */     //   136: iconst_0
        /*    */     //   137: invokevirtual sk0 : (Z)V
        /*    */     //   140: new java/util/ArrayList
        /*    */     //   143: dup
        /*    */     //   144: astore_2
        /*    */     //   145: invokespecial <init> : ()V
        /*    */     //   148: getfield default : Lf/Rm;
        /*    */     //   151: getfield T8 : I
        /*    */     //   154: dup
        /*    */     //   155: istore_3
        /*    */     //   156: ifle -> 178
        /*    */     //   159: aload_2
        /*    */     //   160: new f/z0
        /*    */     //   163: dup
        /*    */     //   164: astore #4
        /*    */     //   166: iconst_2
        /*    */     //   167: iload_3
        /*    */     //   168: iconst_0
        /*    */     //   169: invokespecial <init> : (BIS)V
        /*    */     //   172: aload #4
        /*    */     //   174: invokevirtual add : (Ljava/lang/Object;)Z
        /*    */     //   177: pop
        /*    */     //   178: aload_0
        /*    */     //   179: getfield WN : [Lf/T1;
        /*    */     //   182: dup
        /*    */     //   183: astore_3
        /*    */     //   184: arraylength
        /*    */     //   185: istore #4
        /*    */     //   187: iconst_0
        /*    */     //   188: istore #5
        /*    */     //   190: iload #5
        /*    */     //   192: iload #4
        /*    */     //   194: if_icmpge -> 250
        /*    */     //   197: aload_3
        /*    */     //   198: iload #5
        /*    */     //   200: aaload
        /*    */     //   201: dup
        /*    */     //   202: astore #6
        /*    */     //   204: getfield hC0 : S
        /*    */     //   207: ifle -> 244
        /*    */     //   210: aload_2
        /*    */     //   211: new f/z0
        /*    */     //   214: dup
        /*    */     //   215: astore #7
        /*    */     //   217: aload #6
        /*    */     //   219: dup
        /*    */     //   220: getfield dn0 : I
        /*    */     //   223: istore #6
        /*    */     //   225: getfield op0 : S
        /*    */     //   228: istore #8
        /*    */     //   230: iconst_0
        /*    */     //   231: iload #6
        /*    */     //   233: iload #8
        /*    */     //   235: invokespecial <init> : (BIS)V
        /*    */     //   238: aload #7
        /*    */     //   240: invokevirtual add : (Ljava/lang/Object;)Z
        /*    */     //   243: pop
        /*    */     //   244: iinc #5, 1
        /*    */     //   247: goto -> 190
        /*    */     //   250: aload_0
        /*    */     //   251: getfield Jt : [Lf/Qv0;
        /*    */     //   254: dup
        /*    */     //   255: astore_3
        /*    */     //   256: arraylength
        /*    */     //   257: istore #4
        /*    */     //   259: iconst_0
        /*    */     //   260: istore #5
        /*    */     //   262: iload #5
        /*    */     //   264: iload #4
        /*    */     //   266: if_icmpge -> 311
        /*    */     //   269: aload_3
        /*    */     //   270: iload #5
        /*    */     //   272: aaload
        /*    */     //   273: dup
        /*    */     //   274: astore #6
        /*    */     //   276: invokevirtual public : ()Lf/j40;
        /*    */     //   279: ifnull -> 305
        /*    */     //   282: aload_2
        /*    */     //   283: new f/z0
        /*    */     //   286: dup
        /*    */     //   287: aload #6
        /*    */     //   289: invokevirtual public : ()Lf/j40;
        /*    */     //   292: getfield Jg : I
        /*    */     //   295: iconst_1
        /*    */     //   296: swap
        /*    */     //   297: iconst_0
        /*    */     //   298: invokespecial <init> : (BIS)V
        /*    */     //   301: invokevirtual add : (Ljava/lang/Object;)Z
        /*    */     //   304: pop
        /*    */     //   305: iinc #5, 1
        /*    */     //   308: goto -> 262
        /*    */     //   311: iload_1
        /*    */     //   312: ifne -> 513
        /*    */     //   315: aload_2
        /*    */     //   316: invokevirtual isEmpty : ()Z
        /*    */     //   319: ifne -> 513
        /*    */     //   322: getstatic f/h1.vj : Z
        /*    */     //   325: ifne -> 513
        /*    */     //   328: new f/YA0
        /*    */     //   331: dup
        /*    */     //   332: dup
        /*    */     //   333: astore_1
        /*    */     //   334: invokespecial <init> : ()V
        /*    */     //   337: getfield Dv0 : Lf/SA;
        /*    */     //   340: dup
        /*    */     //   341: dup
        /*    */     //   342: getfield RT : Lf/nJ0;
        /*    */     //   345: ldc_w 5.0
        /*    */     //   348: invokevirtual Xj0 : (F)Lf/nJ0;
        /*    */     //   351: pop
        /*    */     //   352: sipush #5903
        /*    */     //   355: invokestatic OH0 : (I)Ljava/lang/String;
        /*    */     //   358: astore_2
        /*    */     //   359: new f/dQ
        /*    */     //   362: dup
        /*    */     //   363: dup
        /*    */     //   364: aload_2
        /*    */     //   365: swap
        /*    */     //   366: invokespecial <init> : ()V
        /*    */     //   369: invokevirtual E1 : (Ljava/lang/String;)V
        /*    */     //   372: invokevirtual S7 : (Ljava/lang/Object;)Lf/nJ0;
        /*    */     //   375: dup
        /*    */     //   376: iconst_2
        /*    */     //   377: invokestatic valueOf : (I)Ljava/lang/Integer;
        /*    */     //   380: putfield ss : Ljava/lang/Integer;
        /*    */     //   383: getfield Ox : Lf/ZP;
        /*    */     //   386: invokevirtual wP : ()Lf/nJ0;
        /*    */     //   389: pop
        /*    */     //   390: new f/ge0
        /*    */     //   393: dup
        /*    */     //   394: dup2
        /*    */     //   395: astore_2
        /*    */     //   396: invokespecial <init> : ()V
        /*    */     //   399: getstatic f/h1.vj : Z
        /*    */     //   402: istore_3
        /*    */     //   403: getfield TG0 : Lf/protected;
        /*    */     //   406: iload_3
        /*    */     //   407: invokevirtual Fx0 : (Z)V
        /*    */     //   410: new f/dQ
        /*    */     //   413: dup
        /*    */     //   414: astore_3
        /*    */     //   415: aload_2
        /*    */     //   416: aload_3
        /*    */     //   417: dup
        /*    */     //   418: sipush #5904
        /*    */     //   421: invokestatic OH0 : (I)Ljava/lang/String;
        /*    */     //   424: astore #4
        /*    */     //   426: invokespecial <init> : ()V
        /*    */     //   429: aload #4
        /*    */     //   431: invokevirtual E1 : (Ljava/lang/String;)V
        /*    */     //   434: invokevirtual VH : (Lf/JG0;)V
        /*    */     //   437: invokevirtual S7 : (Ljava/lang/Object;)Lf/nJ0;
        /*    */     //   440: getfield Ox : Lf/ZP;
        /*    */     //   443: aload_3
        /*    */     //   444: invokevirtual S7 : (Ljava/lang/Object;)Lf/nJ0;
        /*    */     //   447: pop
        /*    */     //   448: getstatic f/js.vu0 : Lf/js;
        /*    */     //   451: new f/h70
        /*    */     //   454: dup
        /*    */     //   455: aload_0
        /*    */     //   456: swap
        /*    */     //   457: aload_1
        /*    */     //   458: aload_0
        /*    */     //   459: aload_2
        /*    */     //   460: <illegal opcode> run : (Lf/Kf;Lf/ge0;)Ljava/lang/Runnable;
        /*    */     //   465: invokespecial <init> : (Lf/JG0;Ljava/lang/Runnable;)V
        /*    */     //   468: <illegal opcode> run : (Lf/Kf;)Ljava/lang/Runnable;
        /*    */     //   473: invokevirtual Id : (Ljava/lang/Runnable;)Lf/h70;
        /*    */     //   476: dup
        /*    */     //   477: dup2
        /*    */     //   478: iconst_1
        /*    */     //   479: putfield sD0 : Z
        /*    */     //   482: sipush #5834
        /*    */     //   485: invokestatic OH0 : (I)Ljava/lang/String;
        /*    */     //   488: astore_0
        /*    */     //   489: getfield Ak0 : Lf/Un;
        /*    */     //   492: aload_0
        /*    */     //   493: invokevirtual s6 : (Ljava/lang/String;)V
        /*    */     //   496: bipush #53
        /*    */     //   498: invokestatic OH0 : (I)Ljava/lang/String;
        /*    */     //   501: astore_0
        /*    */     //   502: getfield Ek : Lf/Un;
        /*    */     //   505: aload_0
        /*    */     //   506: invokevirtual s6 : (Ljava/lang/String;)V
        /*    */     //   509: invokevirtual uh : (Lf/h70;)V
        /*    */     //   512: return
        /*    */     //   513: aload_0
        /*    */     //   514: aload_2
        /*    */     //   515: aload_0
        /*    */     //   516: dup
        /*    */     //   517: dup
        /*    */     //   518: getstatic f/km.u4 : Lf/R8;
        /*    */     //   521: astore_0
        /*    */     //   522: getfield Gr : Lf/of;
        /*    */     //   525: getfield F2 : Lf/ak0;
        /*    */     //   528: getfield PH0 : Ljava/lang/StringBuilder;
        /*    */     //   531: invokevirtual toString : ()Ljava/lang/String;
        /*    */     //   534: astore_1
        /*    */     //   535: getfield cl : Lf/of;
        /*    */     //   538: getfield F2 : Lf/ak0;
        /*    */     //   541: getfield PH0 : Ljava/lang/StringBuilder;
        /*    */     //   544: invokevirtual toString : ()Ljava/lang/String;
        /*    */     //   547: astore_2
        /*    */     //   548: getfield Nv0 : Lf/of;
        /*    */     //   551: getfield F2 : Lf/ak0;
        /*    */     //   554: getfield PH0 : Ljava/lang/StringBuilder;
        /*    */     //   557: invokevirtual toString : ()Ljava/lang/String;
        /*    */     //   560: astore_3
        /*    */     //   561: iconst_0
        /*    */     //   562: anewarray f/z0
        /*    */     //   565: invokevirtual toArray : ([Ljava/lang/Object;)[Ljava/lang/Object;
        /*    */     //   568: checkcast [Lf/z0;
        /*    */     //   571: astore #4
        /*    */     //   573: aload_0
        /*    */     //   574: getfield e20 : Lf/c4;
        /*    */     //   577: new f/PRn
        /*    */     //   580: dup
        /*    */     //   581: aload_1
        /*    */     //   582: aload_2
        /*    */     //   583: aload_3
        /*    */     //   584: aload #4
        /*    */     //   586: invokespecial <init> : (Ljava/lang/String;Ljava/lang/String;Ljava/lang/String;[Lf/z0;)V
        /*    */     //   589: invokevirtual W3 : (Lf/Bi;)V
        /*    */     //   592: getfield fF : Lf/K40;
        /*    */     //   595: iconst_0
        /*    */     //   596: invokevirtual Vq0 : (S)V
        /*    */     //   599: return
        /*    */     //   600: aload_0
        /*    */     //   601: getstatic f/pv0.Ow0 : Lf/pv0;
        /*    */     //   604: invokevirtual JK0 : (Lf/pv0;)V
        /*    */     //   607: return
        /*    */     //   608: aload_0
        /*    */     //   609: getstatic f/pv0.Gb : Lf/pv0;
        /*    */     //   612: invokevirtual JK0 : (Lf/pv0;)V
        /*    */     //   615: return
        /*    */     // Line number table:
        /*    */     //   Java source line number -> byte code offset
        /*    */     //   #1	-> 4
        /*    */     //   #2	-> 7
        /*    */     //   #3	-> 10
        /*    */     //   #4	-> 18
        /*    */     //   #5	-> 21
        /*    */     //   #6	-> 24
        /*    */     //   #7	-> 27
        /*    */     //   #8	-> 39
        /*    */     //   #9	-> 42
        /*    */     //   #10	-> 45
        /*    */     //   #11	-> 48
        /*    */     //   #12	-> 56
        /*    */     //   #13	-> 59
        /*    */     //   #14	-> 67
        /*    */     //   #15	-> 70
        /*    */     //   #16	-> 73
        /*    */     //   #17	-> 76
        /*    */     //   #18	-> 85
        /*    */     //   #19	-> 96
        /*    */     //   #20	-> 99
        /*    */     //   #21	-> 102
        /*    */     //   #22	-> 110
        /*    */     //   #23	-> 113
        /*    */     //   #24	-> 116
        /*    */     //   #25	-> 119
        /*    */     //   #26	-> 133
        /*    */     //   #27	-> 151
        /*    */     //   #28	-> 160
        /*    */     //   #29	-> 204
        /*    */     //   #30	-> 211
        /*    */     //   #31	-> 220
        /*    */     //   #32	-> 225
        /*    */     //   #33	-> 235
        /*    */     //   #34	-> 292
        /*    */     //   #35	-> 298
        /*    */     //   #36	-> 342
        /*    */     //   #37	-> 348
        /*    */     //   #38	-> 366
        /*    */     //   #39	-> 372
        /*    */     //   #40	-> 380
        /*    */     //   #41	-> 383
        /*    */     //   #42	-> 390
        /*    */     //   #43	-> 403
        /*    */     //   #44	-> 407
        /*    */     //   #45	-> 410
        /*    */     //   #46	-> 426
        /*    */     //   #47	-> 434
        /*    */     //   #48	-> 440
        /*    */     //   #49	-> 448
        /*    */     //   #50	-> 451
        /*    */     //   #51	-> 465
        /*    */     //   #52	-> 468
        /*    */     //   #53	-> 479
        /*    */     //   #54	-> 485
        /*    */     //   #55	-> 489
        /*    */     //   #56	-> 498
        /*    */     //   #57	-> 502
        /*    */     //   #58	-> 509
        /*    */     //   #59	-> 525
        /*    */     //   #60	-> 528
        /*    */     //   #61	-> 531
        /*    */     //   #62	-> 535
        /*    */     //   #63	-> 538
        /*    */     //   #64	-> 541
        /*    */     //   #65	-> 544
        /*    */     //   #66	-> 548
        /*    */     //   #67	-> 551
        /*    */     //   #68	-> 554
        /*    */     //   #69	-> 557
        /*    */     //   #70	-> 562
        /*    */     //   #71	-> 574
        /*    */     //   #72	-> 577
        /*    */     //   #73	-> 592 } public final void IB0() { MJ0(); this.dA0.En(null); this.fF.En(null); if (!km.XU()) mM();  } public final void Eg(V50 paramV50) { // Byte code:
        /*    */     //   0: aload_1
        /*    */     //   1: ifnonnull -> 26
        /*    */     //   4: aload_0
        /*    */     //   5: dup
        /*    */     //   6: iconst_0
        /*    */     //   7: putfield Ps : I
        /*    */     //   10: getstatic f/km.u4 : Lf/R8;
        /*    */     //   13: sipush #5820
        /*    */     //   16: invokestatic OH0 : (I)Ljava/lang/String;
        /*    */     //   19: invokevirtual Pq : (Ljava/lang/String;)V
        /*    */     //   22: invokevirtual IB0 : ()V
        /*    */     //   25: return
        /*    */     //   26: aload_0
        /*    */     //   27: getfield dA0 : Lf/K40;
        /*    */     //   30: getfield d60 : [Lf/V50;
        /*    */     //   33: dup
        /*    */     //   34: astore_2
        /*    */     //   35: ifnull -> 89
        /*    */     //   38: aload_2
        /*    */     //   39: arraylength
        /*    */     //   40: istore_3
        /*    */     //   41: iconst_0
        /*    */     //   42: istore #4
        /*    */     //   44: iload #4
        /*    */     //   46: iload_3
        /*    */     //   47: if_icmpge -> 89
        /*    */     //   50: aload_2
        /*    */     //   51: iload #4
        /*    */     //   53: aaload
        /*    */     //   54: dup
        /*    */     //   55: astore #5
        /*    */     //   57: getfield z70 : I
        /*    */     //   60: aload_1
        /*    */     //   61: getfield z70 : I
        /*    */     //   64: if_icmpne -> 83
        /*    */     //   67: aload_0
        /*    */     //   68: aload #5
        /*    */     //   70: iconst_0
        /*    */     //   71: putfield NZ : B
        /*    */     //   74: getfield dA0 : Lf/K40;
        /*    */     //   77: invokevirtual hI0 : ()V
        /*    */     //   80: goto -> 89
        /*    */     //   83: iinc #4, 1
        /*    */     //   86: goto -> 44
        /*    */     //   89: aload_1
        /*    */     //   90: getfield e9 : I
        /*    */     //   93: getstatic f/km.a3 : Lf/vh0;
        /*    */     //   96: getfield yD : I
        /*    */     //   99: if_icmpeq -> 107
        /*    */     //   102: iconst_1
        /*    */     //   103: istore_2
        /*    */     //   104: goto -> 109
        /*    */     //   107: iconst_0
        /*    */     //   108: istore_2
        /*    */     //   109: iload_2
        /*    */     //   110: aload_0
        /*    */     //   111: dup
        /*    */     //   112: aload_1
        /*    */     //   113: getfield z70 : I
        /*    */     //   116: putfield Ps : I
        /*    */     //   119: new f/of
        /*    */     //   122: dup
        /*    */     //   123: dup
        /*    */     //   124: astore_3
        /*    */     //   125: aconst_null
        /*    */     //   126: invokespecial <init> : (Lf/Sa0;)V
        /*    */     //   129: putfield ef : Lf/of;
        /*    */     //   132: ifeq -> 144
        /*    */     //   135: aload_1
        /*    */     //   136: getfield Tb0 : Ljava/lang/String;
        /*    */     //   139: astore #4
        /*    */     //   141: goto -> 169
        /*    */     //   144: aload_1
        /*    */     //   145: getfield f4 : I
        /*    */     //   148: ifeq -> 160
        /*    */     //   151: aload_1
        /*    */     //   152: getfield RD : Ljava/lang/String;
        /*    */     //   155: astore #4
        /*    */     //   157: goto -> 169
        /*    */     //   160: aload_1
        /*    */     //   161: getfield RD : Ljava/lang/String;
        /*    */     //   164: invokestatic LU : (Ljava/lang/String;)Ljava/lang/String;
        /*    */     //   167: astore #4
        /*    */     //   169: aload_1
        /*    */     //   170: aload_0
        /*    */     //   171: dup
        /*    */     //   172: aload_3
        /*    */     //   173: aload #4
        /*    */     //   175: iconst_0
        /*    */     //   176: invokevirtual Be0 : (Ljava/lang/String;Z)V
        /*    */     //   179: getfield ef : Lf/of;
        /*    */     //   182: iconst_1
        /*    */     //   183: invokevirtual uh : (Z)V
        /*    */     //   186: new f/of
        /*    */     //   189: dup
        /*    */     //   190: dup
        /*    */     //   191: astore_3
        /*    */     //   192: aconst_null
        /*    */     //   193: invokespecial <init> : (Lf/Sa0;)V
        /*    */     //   196: putfield Vt : Lf/of;
        /*    */     //   199: getfield f4 : I
        /*    */     //   202: ifeq -> 214
        /*    */     //   205: aload_1
        /*    */     //   206: getfield r10 : Ljava/lang/String;
        /*    */     //   209: astore #4
        /*    */     //   211: goto -> 223
        /*    */     //   214: aload_1
        /*    */     //   215: getfield r10 : Ljava/lang/String;
        /*    */     //   218: invokestatic LU : (Ljava/lang/String;)Ljava/lang/String;
        /*    */     //   221: astore #4
        /*    */     //   223: aload_1
        /*    */     //   224: dup
        /*    */     //   225: aload_0
        /*    */     //   226: aload_3
        /*    */     //   227: aload #4
        /*    */     //   229: iconst_0
        /*    */     //   230: invokevirtual Be0 : (Ljava/lang/String;Z)V
        /*    */     //   233: getfield Vt : Lf/of;
        /*    */     //   236: iconst_1
        /*    */     //   237: invokevirtual uh : (Z)V
        /*    */     //   240: new java/util/Date
        /*    */     //   243: dup
        /*    */     //   244: aload_1
        /*    */     //   245: swap
        /*    */     //   246: invokespecial <init> : ()V
        /*    */     //   249: getfield Px0 : I
        /*    */     //   252: i2l
        /*    */     //   253: ldc2_w 1000
        /*    */     //   256: lmul
        /*    */     //   257: invokevirtual setTime : (J)V
        /*    */     //   260: getfield Px0 : I
        /*    */     //   263: invokestatic currentTimeMillis : ()J
        /*    */     //   266: ldc2_w 1000
        /*    */     //   269: ldiv
        /*    */     //   270: l2i
        /*    */     //   271: isub
        /*    */     //   272: istore_3
        /*    */     //   273: new f/dQ
        /*    */     //   276: dup
        /*    */     //   277: dup2
        /*    */     //   278: astore #4
        /*    */     //   280: iload_3
        /*    */     //   281: iconst_1
        /*    */     //   282: invokestatic Ya : (II)Ljava/lang/String;
        /*    */     //   285: astore_3
        /*    */     //   286: invokespecial <init> : ()V
        /*    */     //   289: aload_3
        /*    */     //   290: invokevirtual E1 : (Ljava/lang/String;)V
        /*    */     //   293: ldc_w 'label-title-small'
        /*    */     //   296: invokevirtual Xu : (Ljava/lang/String;)V
        /*    */     //   299: new f/dQ
        /*    */     //   302: dup
        /*    */     //   303: dup
        /*    */     //   304: sipush #5830
        /*    */     //   307: invokestatic OH0 : (I)Ljava/lang/String;
        /*    */     //   310: astore_3
        /*    */     //   311: invokespecial <init> : ()V
        /*    */     //   314: aload_3
        /*    */     //   315: invokevirtual E1 : (Ljava/lang/String;)V
        /*    */     //   318: ldc_w 'label-title-small'
        /*    */     //   321: invokevirtual Xu : (Ljava/lang/String;)V
        /*    */     //   324: new f/of
        /*    */     //   327: dup
        /*    */     //   328: dup
        /*    */     //   329: aload_0
        /*    */     //   330: swap
        /*    */     //   331: dup
        /*    */     //   332: aconst_null
        /*    */     //   333: invokespecial <init> : (Lf/Sa0;)V
        /*    */     //   336: putfield rB : Lf/of;
        /*    */     //   339: iconst_1
        /*    */     //   340: putfield GE : Z
        /*    */     //   343: iconst_1
        /*    */     //   344: invokevirtual uh : (Z)V
        /*    */     //   347: new java/util/ArrayList
        /*    */     //   350: dup
        /*    */     //   351: astore_3
        /*    */     //   352: invokespecial <init> : ()V
        /*    */     //   355: aconst_null
        /*    */     //   356: astore #5
        /*    */     //   358: new java/util/ArrayList
        /*    */     //   361: dup
        /*    */     //   362: astore #6
        /*    */     //   364: invokespecial <init> : ()V
        /*    */     //   367: new java/util/ArrayList
        /*    */     //   370: dup
        /*    */     //   371: astore #7
        /*    */     //   373: invokespecial <init> : ()V
        /*    */     //   376: new java/util/ArrayList
        /*    */     //   379: dup
        /*    */     //   380: astore #8
        /*    */     //   382: invokespecial <init> : ()V
        /*    */     //   385: getfield Ml0 : Ljava/util/Map;
        /*    */     //   388: invokeinterface values : ()Ljava/util/Collection;
        /*    */     //   393: invokeinterface iterator : ()Ljava/util/Iterator;
        /*    */     //   398: astore #9
        /*    */     //   400: aload #9
        /*    */     //   402: invokeinterface hasNext : ()Z
        /*    */     //   407: ifeq -> 519
        /*    */     //   410: aload #9
        /*    */     //   412: invokeinterface next : ()Ljava/lang/Object;
        /*    */     //   417: checkcast f/nE0
        /*    */     //   420: dup
        /*    */     //   421: astore #10
        /*    */     //   423: getfield T7 : Z
        /*    */     //   426: ifeq -> 436
        /*    */     //   429: iload_2
        /*    */     //   430: ifne -> 436
        /*    */     //   433: goto -> 400
        /*    */     //   436: aload #10
        /*    */     //   438: aload_3
        /*    */     //   439: new f/yn0
        /*    */     //   442: dup
        /*    */     //   443: astore #11
        /*    */     //   445: aload_0
        /*    */     //   446: aload #10
        /*    */     //   448: iload_2
        /*    */     //   449: invokespecial <init> : (Lf/Kf;Lf/nE0;Z)V
        /*    */     //   452: aload #11
        /*    */     //   454: invokevirtual add : (Ljava/lang/Object;)Z
        /*    */     //   457: pop
        /*    */     //   458: getfield Jf : B
        /*    */     //   461: dup
        /*    */     //   462: istore #10
        /*    */     //   464: ifeq -> 508
        /*    */     //   467: iload #10
        /*    */     //   469: iconst_1
        /*    */     //   470: if_icmpeq -> 497
        /*    */     //   473: iload #10
        /*    */     //   475: iconst_2
        /*    */     //   476: if_icmpeq -> 490
        /*    */     //   479: aload #8
        /*    */     //   481: aload #11
        /*    */     //   483: invokevirtual add : (Ljava/lang/Object;)Z
        /*    */     //   486: pop
        /*    */     //   487: goto -> 400
        /*    */     //   490: aload #11
        /*    */     //   492: astore #5
        /*    */     //   494: goto -> 400
        /*    */     //   497: aload #7
        /*    */     //   499: aload #11
        /*    */     //   501: invokevirtual add : (Ljava/lang/Object;)Z
        /*    */     //   504: pop
        /*    */     //   505: goto -> 400
        /*    */     //   508: aload #6
        /*    */     //   510: aload #11
        /*    */     //   512: invokevirtual add : (Ljava/lang/Object;)Z
        /*    */     //   515: pop
        /*    */     //   516: goto -> 400
        /*    */     //   519: aload_1
        /*    */     //   520: aload_0
        /*    */     //   521: aload_3
        /*    */     //   522: iconst_0
        /*    */     //   523: anewarray f/yn0
        /*    */     //   526: invokevirtual toArray : ([Ljava/lang/Object;)[Ljava/lang/Object;
        /*    */     //   529: checkcast [Lf/yn0;
        /*    */     //   532: putfield sw : [Lf/yn0;
        /*    */     //   535: new f/Un
        /*    */     //   538: dup
        /*    */     //   539: dup
        /*    */     //   540: astore_3
        /*    */     //   541: sipush #5844
        /*    */     //   544: invokestatic OH0 : (I)Ljava/lang/String;
        /*    */     //   547: invokespecial <init> : (Ljava/lang/String;)V
        /*    */     //   550: new f/M50
        /*    */     //   553: dup
        /*    */     //   554: aload_0
        /*    */     //   555: aload_1
        /*    */     //   556: invokespecial <init> : (Lf/Kf;Lf/V50;)V
        /*    */     //   559: invokevirtual tW : (Ljava/lang/Runnable;)V
        /*    */     //   562: getfield f4 : I
        /*    */     //   565: ifle -> 574
        /*    */     //   568: iconst_1
        /*    */     //   569: istore #9
        /*    */     //   571: goto -> 577
        /*    */     //   574: iconst_0
        /*    */     //   575: istore #9
        /*    */     //   577: aload #5
        /*    */     //   579: aload_3
        /*    */     //   580: iload #9
        /*    */     //   582: invokevirtual wI0 : (Z)V
        /*    */     //   585: new f/Ip
        /*    */     //   588: dup
        /*    */     //   589: dup
        /*    */     //   590: dup2
        /*    */     //   591: dup2
        /*    */     //   592: astore #9
        /*    */     //   594: invokespecial <init> : ()V
        /*    */     //   597: invokevirtual GH0 : ()V
        /*    */     //   600: iconst_3
        /*    */     //   601: anewarray f/U90
        /*    */     //   604: dup
        /*    */     //   605: dup
        /*    */     //   606: astore #10
        /*    */     //   608: aload #9
        /*    */     //   610: aload #10
        /*    */     //   612: aload #9
        /*    */     //   614: aload #10
        /*    */     //   616: aload #9
        /*    */     //   618: iconst_2
        /*    */     //   619: anewarray f/JG0
        /*    */     //   622: dup
        /*    */     //   623: dup
        /*    */     //   624: aload_0
        /*    */     //   625: getfield ef : Lf/of;
        /*    */     //   628: iconst_0
        /*    */     //   629: swap
        /*    */     //   630: aastore
        /*    */     //   631: iconst_1
        /*    */     //   632: aload #4
        /*    */     //   634: aastore
        /*    */     //   635: invokevirtual vo0 : ([Lf/JG0;)Lf/U90;
        /*    */     //   638: iconst_0
        /*    */     //   639: swap
        /*    */     //   640: aastore
        /*    */     //   641: iconst_1
        /*    */     //   642: anewarray f/JG0
        /*    */     //   645: dup
        /*    */     //   646: aload_0
        /*    */     //   647: getfield Vt : Lf/of;
        /*    */     //   650: iconst_0
        /*    */     //   651: swap
        /*    */     //   652: aastore
        /*    */     //   653: invokevirtual vo0 : ([Lf/JG0;)Lf/U90;
        /*    */     //   656: iconst_1
        /*    */     //   657: swap
        /*    */     //   658: aastore
        /*    */     //   659: iconst_1
        /*    */     //   660: anewarray f/JG0
        /*    */     //   663: dup
        /*    */     //   664: aload_0
        /*    */     //   665: getfield rB : Lf/of;
        /*    */     //   668: iconst_0
        /*    */     //   669: swap
        /*    */     //   670: aastore
        /*    */     //   671: invokevirtual vo0 : ([Lf/JG0;)Lf/U90;
        /*    */     //   674: iconst_2
        /*    */     //   675: swap
        /*    */     //   676: aastore
        /*    */     //   677: invokevirtual Yw0 : ([Lf/U90;)Lf/U90;
        /*    */     //   680: invokevirtual rK0 : (Lf/U90;)V
        /*    */     //   683: iconst_3
        /*    */     //   684: anewarray f/U90
        /*    */     //   687: dup
        /*    */     //   688: dup
        /*    */     //   689: astore #10
        /*    */     //   691: aload #9
        /*    */     //   693: aload #10
        /*    */     //   695: aload #9
        /*    */     //   697: aload #10
        /*    */     //   699: aload #9
        /*    */     //   701: iconst_2
        /*    */     //   702: anewarray f/JG0
        /*    */     //   705: dup
        /*    */     //   706: dup
        /*    */     //   707: aload_0
        /*    */     //   708: getfield ef : Lf/of;
        /*    */     //   711: iconst_0
        /*    */     //   712: swap
        /*    */     //   713: aastore
        /*    */     //   714: iconst_1
        /*    */     //   715: aload #4
        /*    */     //   717: aastore
        /*    */     //   718: invokevirtual AUX : ([Lf/JG0;)Lf/U90;
        /*    */     //   721: iconst_0
        /*    */     //   722: swap
        /*    */     //   723: aastore
        /*    */     //   724: iconst_1
        /*    */     //   725: anewarray f/JG0
        /*    */     //   728: dup
        /*    */     //   729: aload_0
        /*    */     //   730: getfield Vt : Lf/of;
        /*    */     //   733: iconst_0
        /*    */     //   734: swap
        /*    */     //   735: aastore
        /*    */     //   736: invokevirtual AUX : ([Lf/JG0;)Lf/U90;
        /*    */     //   739: iconst_1
        /*    */     //   740: swap
        /*    */     //   741: aastore
        /*    */     //   742: iconst_1
        /*    */     //   743: anewarray f/JG0
        /*    */     //   746: dup
        /*    */     //   747: aload_0
        /*    */     //   748: getfield rB : Lf/of;
        /*    */     //   751: iconst_0
        /*    */     //   752: swap
        /*    */     //   753: aastore
        /*    */     //   754: invokevirtual AUX : ([Lf/JG0;)Lf/U90;
        /*    */     //   757: iconst_2
        /*    */     //   758: swap
        /*    */     //   759: aastore
        /*    */     //   760: invokevirtual Gs : ([Lf/U90;)Lf/U90;
        /*    */     //   763: invokevirtual WN : (Lf/U90;)V
        /*    */     //   766: ifnull -> 978
        /*    */     //   769: aload #9
        /*    */     //   771: new f/dQ
        /*    */     //   774: dup
        /*    */     //   775: dup2
        /*    */     //   776: astore #4
        /*    */     //   778: sipush #5831
        /*    */     //   781: invokestatic OH0 : (I)Ljava/lang/String;
        /*    */     //   784: astore #10
        /*    */     //   786: invokespecial <init> : ()V
        /*    */     //   789: aload #10
        /*    */     //   791: invokevirtual E1 : (Ljava/lang/String;)V
        /*    */     //   794: ldc_w 'label-title-small'
        /*    */     //   797: invokevirtual Xu : (Ljava/lang/String;)V
        /*    */     //   800: getfield Xz0 : Lf/U90;
        /*    */     //   803: astore #10
        /*    */     //   805: iconst_3
        /*    */     //   806: anewarray f/JG0
        /*    */     //   809: astore #11
        /*    */     //   811: iconst_0
        /*    */     //   812: istore #12
        /*    */     //   814: invokestatic XU : ()Z
        /*    */     //   817: ifne -> 834
        /*    */     //   820: iload_2
        /*    */     //   821: ifne -> 827
        /*    */     //   824: goto -> 834
        /*    */     //   827: aload #4
        /*    */     //   829: astore #13
        /*    */     //   831: goto -> 837
        /*    */     //   834: aconst_null
        /*    */     //   835: astore #13
        /*    */     //   837: iload_2
        /*    */     //   838: aload #11
        /*    */     //   840: aload #5
        /*    */     //   842: aload #11
        /*    */     //   844: iload #12
        /*    */     //   846: aload #13
        /*    */     //   848: aastore
        /*    */     //   849: getfield Tx : Lf/JG0;
        /*    */     //   852: iconst_1
        /*    */     //   853: swap
        /*    */     //   854: aastore
        /*    */     //   855: iconst_2
        /*    */     //   856: istore #12
        /*    */     //   858: ifeq -> 867
        /*    */     //   861: aconst_null
        /*    */     //   862: astore #13
        /*    */     //   864: goto -> 874
        /*    */     //   867: aload #5
        /*    */     //   869: getfield jK : Lf/Un;
        /*    */     //   872: astore #13
        /*    */     //   874: aload #9
        /*    */     //   876: aload #10
        /*    */     //   878: aload #9
        /*    */     //   880: aload #11
        /*    */     //   882: dup
        /*    */     //   883: iload #12
        /*    */     //   885: aload #13
        /*    */     //   887: aastore
        /*    */     //   888: invokevirtual vo0 : ([Lf/JG0;)Lf/U90;
        /*    */     //   891: invokevirtual ee0 : (Lf/U90;)Lf/U90;
        /*    */     //   894: pop
        /*    */     //   895: getfield o30 : Lf/U90;
        /*    */     //   898: astore #10
        /*    */     //   900: iconst_3
        /*    */     //   901: anewarray f/JG0
        /*    */     //   904: astore #11
        /*    */     //   906: iconst_0
        /*    */     //   907: istore #12
        /*    */     //   909: invokestatic XU : ()Z
        /*    */     //   912: ifne -> 919
        /*    */     //   915: iload_2
        /*    */     //   916: ifne -> 922
        /*    */     //   919: aconst_null
        /*    */     //   920: astore #4
        /*    */     //   922: iload_2
        /*    */     //   923: aload #11
        /*    */     //   925: aload #5
        /*    */     //   927: aload #11
        /*    */     //   929: iload #12
        /*    */     //   931: aload #4
        /*    */     //   933: aastore
        /*    */     //   934: getfield Tx : Lf/JG0;
        /*    */     //   937: iconst_1
        /*    */     //   938: swap
        /*    */     //   939: aastore
        /*    */     //   940: iconst_2
        /*    */     //   941: istore #4
        /*    */     //   943: ifeq -> 952
        /*    */     //   946: aconst_null
        /*    */     //   947: astore #5
        /*    */     //   949: goto -> 959
        /*    */     //   952: aload #5
        /*    */     //   954: getfield jK : Lf/Un;
        /*    */     //   957: astore #5
        /*    */     //   959: aload #10
        /*    */     //   961: aload #9
        /*    */     //   963: aload #11
        /*    */     //   965: dup
        /*    */     //   966: iload #4
        /*    */     //   968: aload #5
        /*    */     //   970: aastore
        /*    */     //   971: invokevirtual AUX : ([Lf/JG0;)Lf/U90;
        /*    */     //   974: invokevirtual ee0 : (Lf/U90;)Lf/U90;
        /*    */     //   977: pop
        /*    */     //   978: aload #6
        /*    */     //   980: invokevirtual size : ()I
        /*    */     //   983: ifle -> 1207
        /*    */     //   986: new f/dQ
        /*    */     //   989: dup
        /*    */     //   990: dup2
        /*    */     //   991: astore #4
        /*    */     //   993: sipush #5832
        /*    */     //   996: invokestatic OH0 : (I)Ljava/lang/String;
        /*    */     //   999: astore #5
        /*    */     //   1001: invokespecial <init> : ()V
        /*    */     //   1004: aload #5
        /*    */     //   1006: invokevirtual E1 : (Ljava/lang/String;)V
        /*    */     //   1009: ldc_w 'label-title-small'
        /*    */     //   1012: invokevirtual Xu : (Ljava/lang/String;)V
        /*    */     //   1015: new f/cr0
        /*    */     //   1018: dup
        /*    */     //   1019: astore #5
        /*    */     //   1021: aload #9
        /*    */     //   1023: invokespecial <init> : (Lf/Ip;)V
        /*    */     //   1026: new f/g0
        /*    */     //   1029: dup
        /*    */     //   1030: astore #10
        /*    */     //   1032: aload #9
        /*    */     //   1034: invokespecial <init> : (Lf/Ip;)V
        /*    */     //   1037: invokestatic XU : ()Z
        /*    */     //   1040: ifne -> 1063
        /*    */     //   1043: iload_2
        /*    */     //   1044: ifeq -> 1063
        /*    */     //   1047: aload #10
        /*    */     //   1049: aload #5
        /*    */     //   1051: aload #4
        /*    */     //   1053: invokevirtual Ya : (Lf/JG0;)Lf/U90;
        /*    */     //   1056: pop
        /*    */     //   1057: aload #4
        /*    */     //   1059: invokevirtual Ya : (Lf/JG0;)Lf/U90;
        /*    */     //   1062: pop
        /*    */     //   1063: aload #6
        /*    */     //   1065: invokevirtual iterator : ()Ljava/util/Iterator;
        /*    */     //   1068: astore #4
        /*    */     //   1070: aload #4
        /*    */     //   1072: invokeinterface hasNext : ()Z
        /*    */     //   1077: ifeq -> 1116
        /*    */     //   1080: aload #10
        /*    */     //   1082: aload #5
        /*    */     //   1084: aload #4
        /*    */     //   1086: invokeinterface next : ()Ljava/lang/Object;
        /*    */     //   1091: checkcast f/yn0
        /*    */     //   1094: dup
        /*    */     //   1095: astore #11
        /*    */     //   1097: getfield Tx : Lf/JG0;
        /*    */     //   1100: invokevirtual Ya : (Lf/JG0;)Lf/U90;
        /*    */     //   1103: pop
        /*    */     //   1104: aload #11
        /*    */     //   1106: getfield Tx : Lf/JG0;
        /*    */     //   1109: invokevirtual Ya : (Lf/JG0;)Lf/U90;
        /*    */     //   1112: pop
        /*    */     //   1113: goto -> 1070
        /*    */     //   1116: iload_2
        /*    */     //   1117: aload_0
        /*    */     //   1118: new f/Un
        /*    */     //   1121: dup
        /*    */     //   1122: astore #4
        /*    */     //   1124: aload_0
        /*    */     //   1125: aload #6
        /*    */     //   1127: aload_0
        /*    */     //   1128: aload #4
        /*    */     //   1130: dup
        /*    */     //   1131: sipush #5899
        /*    */     //   1134: invokestatic OH0 : (I)Ljava/lang/String;
        /*    */     //   1137: invokespecial <init> : (Ljava/lang/String;)V
        /*    */     //   1140: putfield gk : Lf/Un;
        /*    */     //   1143: <illegal opcode> run : (Lf/Kf;Ljava/util/List;)Ljava/lang/Runnable;
        /*    */     //   1148: invokevirtual tW : (Ljava/lang/Runnable;)V
        /*    */     //   1151: getfield gk : Lf/Un;
        /*    */     //   1154: ldc_w 'button-small2'
        /*    */     //   1157: invokevirtual Xu : (Ljava/lang/String;)V
        /*    */     //   1160: ifne -> 1186
        /*    */     //   1163: aload #10
        /*    */     //   1165: aload_0
        /*    */     //   1166: aload #5
        /*    */     //   1168: invokevirtual Em0 : ()Lf/U90;
        /*    */     //   1171: aload_0
        /*    */     //   1172: getfield gk : Lf/Un;
        /*    */     //   1175: invokevirtual Ya : (Lf/JG0;)Lf/U90;
        /*    */     //   1178: pop
        /*    */     //   1179: getfield gk : Lf/Un;
        /*    */     //   1182: invokevirtual Ya : (Lf/JG0;)Lf/U90;
        /*    */     //   1185: pop
        /*    */     //   1186: aload #9
        /*    */     //   1188: dup
        /*    */     //   1189: getfield Xz0 : Lf/U90;
        /*    */     //   1192: aload #5
        /*    */     //   1194: invokevirtual ee0 : (Lf/U90;)Lf/U90;
        /*    */     //   1197: pop
        /*    */     //   1198: getfield o30 : Lf/U90;
        /*    */     //   1201: aload #10
        /*    */     //   1203: invokevirtual ee0 : (Lf/U90;)Lf/U90;
        /*    */     //   1206: pop
        /*    */     //   1207: aload #7
        /*    */     //   1209: invokevirtual size : ()I
        /*    */     //   1212: ifle -> 1646
        /*    */     //   1215: new f/dQ
        /*    */     //   1218: dup
        /*    */     //   1219: dup2
        /*    */     //   1220: astore #4
        /*    */     //   1222: sipush #5833
        /*    */     //   1225: invokestatic OH0 : (I)Ljava/lang/String;
        /*    */     //   1228: astore #5
        /*    */     //   1230: invokespecial <init> : ()V
        /*    */     //   1233: aload #5
        /*    */     //   1235: invokevirtual E1 : (Ljava/lang/String;)V
        /*    */     //   1238: ldc_w 'label-title-small'
        /*    */     //   1241: invokevirtual Xu : (Ljava/lang/String;)V
        /*    */     //   1244: new f/cr0
        /*    */     //   1247: dup
        /*    */     //   1248: astore #5
        /*    */     //   1250: aload #9
        /*    */     //   1252: invokespecial <init> : (Lf/Ip;)V
        /*    */     //   1255: new f/g0
        /*    */     //   1258: dup
        /*    */     //   1259: astore #6
        /*    */     //   1261: aload #9
        /*    */     //   1263: invokespecial <init> : (Lf/Ip;)V
        /*    */     //   1266: new f/g0
        /*    */     //   1269: dup
        /*    */     //   1270: astore #10
        /*    */     //   1272: aload #9
        /*    */     //   1274: invokespecial <init> : (Lf/Ip;)V
        /*    */     //   1277: invokestatic XU : ()Z
        /*    */     //   1280: ifne -> 1303
        /*    */     //   1283: iload_2
        /*    */     //   1284: ifeq -> 1303
        /*    */     //   1287: aload #6
        /*    */     //   1289: aload #5
        /*    */     //   1291: aload #4
        /*    */     //   1293: invokevirtual Ya : (Lf/JG0;)Lf/U90;
        /*    */     //   1296: pop
        /*    */     //   1297: aload #4
        /*    */     //   1299: invokevirtual Ya : (Lf/JG0;)Lf/U90;
        /*    */     //   1302: pop
        /*    */     //   1303: aload #7
        /*    */     //   1305: invokevirtual iterator : ()Ljava/util/Iterator;
        /*    */     //   1308: astore #4
        /*    */     //   1310: aload #4
        /*    */     //   1312: invokeinterface hasNext : ()Z
        /*    */     //   1317: ifeq -> 1442
        /*    */     //   1320: aload_0
        /*    */     //   1321: dup
        /*    */     //   1322: aload #10
        /*    */     //   1324: aload #5
        /*    */     //   1326: aload #4
        /*    */     //   1328: invokeinterface next : ()Ljava/lang/Object;
        /*    */     //   1333: checkcast f/yn0
        /*    */     //   1336: dup
        /*    */     //   1337: astore #11
        /*    */     //   1339: getfield Tx : Lf/JG0;
        /*    */     //   1342: invokevirtual Ya : (Lf/JG0;)Lf/U90;
        /*    */     //   1345: pop
        /*    */     //   1346: aload #11
        /*    */     //   1348: getfield Tx : Lf/JG0;
        /*    */     //   1351: invokevirtual Ya : (Lf/JG0;)Lf/U90;
        /*    */     //   1354: pop
        /*    */     //   1355: new f/Un
        /*    */     //   1358: dup
        /*    */     //   1359: astore #11
        /*    */     //   1361: aload_0
        /*    */     //   1362: aload #7
        /*    */     //   1364: aload_0
        /*    */     //   1365: aload #11
        /*    */     //   1367: dup
        /*    */     //   1368: sipush #5897
        /*    */     //   1371: invokestatic OH0 : (I)Ljava/lang/String;
        /*    */     //   1374: invokespecial <init> : (Ljava/lang/String;)V
        /*    */     //   1377: putfield s9 : Lf/Un;
        /*    */     //   1380: <illegal opcode> run : (Lf/Kf;Ljava/util/List;)Ljava/lang/Runnable;
        /*    */     //   1385: invokevirtual tW : (Ljava/lang/Runnable;)V
        /*    */     //   1388: getfield s9 : Lf/Un;
        /*    */     //   1391: ldc_w 'button-small2'
        /*    */     //   1394: invokevirtual Xu : (Ljava/lang/String;)V
        /*    */     //   1397: new f/Un
        /*    */     //   1400: dup
        /*    */     //   1401: astore #11
        /*    */     //   1403: aload_0
        /*    */     //   1404: aload #7
        /*    */     //   1406: aload_0
        /*    */     //   1407: aload #11
        /*    */     //   1409: dup
        /*    */     //   1410: sipush #5898
        /*    */     //   1413: invokestatic OH0 : (I)Ljava/lang/String;
        /*    */     //   1416: invokespecial <init> : (Ljava/lang/String;)V
        /*    */     //   1419: putfield sC0 : Lf/Un;
        /*    */     //   1422: <illegal opcode> run : (Lf/Kf;Ljava/util/List;)Ljava/lang/Runnable;
        /*    */     //   1427: invokevirtual tW : (Ljava/lang/Runnable;)V
        /*    */     //   1430: getfield sC0 : Lf/Un;
        /*    */     //   1433: ldc_w 'button-small2'
        /*    */     //   1436: invokevirtual Xu : (Ljava/lang/String;)V
        /*    */     //   1439: goto -> 1310
        /*    */     //   1442: iload_2
        /*    */     //   1443: aload #6
        /*    */     //   1445: new f/cr0
        /*    */     //   1448: dup
        /*    */     //   1449: aload #9
        /*    */     //   1451: invokespecial <init> : (Lf/Ip;)V
        /*    */     //   1454: invokevirtual Em0 : ()Lf/U90;
        /*    */     //   1457: aload #10
        /*    */     //   1459: invokevirtual ee0 : (Lf/U90;)Lf/U90;
        /*    */     //   1462: invokevirtual Em0 : ()Lf/U90;
        /*    */     //   1465: invokevirtual ee0 : (Lf/U90;)Lf/U90;
        /*    */     //   1468: pop
        /*    */     //   1469: ifne -> 1545
        /*    */     //   1472: invokestatic XU : ()Z
        /*    */     //   1475: ifne -> 1545
        /*    */     //   1478: aload #6
        /*    */     //   1480: aload #9
        /*    */     //   1482: aload #5
        /*    */     //   1484: invokevirtual Em0 : ()Lf/U90;
        /*    */     //   1487: aload #9
        /*    */     //   1489: iconst_2
        /*    */     //   1490: anewarray f/JG0
        /*    */     //   1493: dup
        /*    */     //   1494: dup
        /*    */     //   1495: aload_0
        /*    */     //   1496: swap
        /*    */     //   1497: aload_0
        /*    */     //   1498: getfield s9 : Lf/Un;
        /*    */     //   1501: iconst_0
        /*    */     //   1502: swap
        /*    */     //   1503: aastore
        /*    */     //   1504: getfield sC0 : Lf/Un;
        /*    */     //   1507: iconst_1
        /*    */     //   1508: swap
        /*    */     //   1509: aastore
        /*    */     //   1510: invokevirtual AUX : ([Lf/JG0;)Lf/U90;
        /*    */     //   1513: invokevirtual ee0 : (Lf/U90;)Lf/U90;
        /*    */     //   1516: pop
        /*    */     //   1517: iconst_2
        /*    */     //   1518: anewarray f/JG0
        /*    */     //   1521: dup
        /*    */     //   1522: dup
        /*    */     //   1523: aload_0
        /*    */     //   1524: swap
        /*    */     //   1525: aload_0
        /*    */     //   1526: getfield s9 : Lf/Un;
        /*    */     //   1529: iconst_0
        /*    */     //   1530: swap
        /*    */     //   1531: aastore
        /*    */     //   1532: getfield sC0 : Lf/Un;
        /*    */     //   1535: iconst_1
        /*    */     //   1536: swap
        /*    */     //   1537: aastore
        /*    */     //   1538: invokevirtual vo0 : ([Lf/JG0;)Lf/U90;
        /*    */     //   1541: invokevirtual ee0 : (Lf/U90;)Lf/U90;
        /*    */     //   1544: pop
        /*    */     //   1545: iload_2
        /*    */     //   1546: aload #9
        /*    */     //   1548: dup
        /*    */     //   1549: getfield Xz0 : Lf/U90;
        /*    */     //   1552: aload #5
        /*    */     //   1554: invokevirtual ee0 : (Lf/U90;)Lf/U90;
        /*    */     //   1557: pop
        /*    */     //   1558: getfield o30 : Lf/U90;
        /*    */     //   1561: aload #6
        /*    */     //   1563: invokevirtual ee0 : (Lf/U90;)Lf/U90;
        /*    */     //   1566: pop
        /*    */     //   1567: ifne -> 1646
        /*    */     //   1570: invokestatic XU : ()Z
        /*    */     //   1573: ifeq -> 1646
        /*    */     //   1576: aload #9
        /*    */     //   1578: dup
        /*    */     //   1579: getfield Xz0 : Lf/U90;
        /*    */     //   1582: aload #9
        /*    */     //   1584: iconst_1
        /*    */     //   1585: anewarray f/JG0
        /*    */     //   1588: dup
        /*    */     //   1589: aload_0
        /*    */     //   1590: getfield s9 : Lf/Un;
        /*    */     //   1593: iconst_0
        /*    */     //   1594: swap
        /*    */     //   1595: aastore
        /*    */     //   1596: invokevirtual vo0 : ([Lf/JG0;)Lf/U90;
        /*    */     //   1599: invokevirtual Em0 : ()Lf/U90;
        /*    */     //   1602: aload_0
        /*    */     //   1603: getfield sC0 : Lf/Un;
        /*    */     //   1606: invokevirtual Ya : (Lf/JG0;)Lf/U90;
        /*    */     //   1609: invokevirtual ee0 : (Lf/U90;)Lf/U90;
        /*    */     //   1612: pop
        /*    */     //   1613: getfield o30 : Lf/U90;
        /*    */     //   1616: aload #9
        /*    */     //   1618: iconst_2
        /*    */     //   1619: anewarray f/JG0
        /*    */     //   1622: dup
        /*    */     //   1623: dup
        /*    */     //   1624: aload_0
        /*    */     //   1625: swap
        /*    */     //   1626: aload_0
        /*    */     //   1627: getfield s9 : Lf/Un;
        /*    */     //   1630: iconst_0
        /*    */     //   1631: swap
        /*    */     //   1632: aastore
        /*    */     //   1633: getfield sC0 : Lf/Un;
        /*    */     //   1636: iconst_1
        /*    */     //   1637: swap
        /*    */     //   1638: aastore
        /*    */     //   1639: invokevirtual AUX : ([Lf/JG0;)Lf/U90;
        /*    */     //   1642: invokevirtual ee0 : (Lf/U90;)Lf/U90;
        /*    */     //   1645: pop
        /*    */     //   1646: aload #8
        /*    */     //   1648: invokevirtual iterator : ()Ljava/util/Iterator;
        /*    */     //   1651: astore #4
        /*    */     //   1653: aload #4
        /*    */     //   1655: invokeinterface hasNext : ()Z
        /*    */     //   1660: ifeq -> 1751
        /*    */     //   1663: aload #9
        /*    */     //   1665: dup
        /*    */     //   1666: aload #4
        /*    */     //   1668: invokeinterface next : ()Ljava/lang/Object;
        /*    */     //   1673: checkcast f/yn0
        /*    */     //   1676: astore #5
        /*    */     //   1678: getfield Xz0 : Lf/U90;
        /*    */     //   1681: aload #9
        /*    */     //   1683: iconst_2
        /*    */     //   1684: anewarray f/JG0
        /*    */     //   1687: dup
        /*    */     //   1688: dup
        /*    */     //   1689: aload #5
        /*    */     //   1691: swap
        /*    */     //   1692: aload #5
        /*    */     //   1694: getfield Tx : Lf/JG0;
        /*    */     //   1697: iconst_0
        /*    */     //   1698: swap
        /*    */     //   1699: aastore
        /*    */     //   1700: getfield jK : Lf/Un;
        /*    */     //   1703: iconst_1
        /*    */     //   1704: swap
        /*    */     //   1705: aastore
        /*    */     //   1706: invokevirtual vo0 : ([Lf/JG0;)Lf/U90;
        /*    */     //   1709: invokevirtual ee0 : (Lf/U90;)Lf/U90;
        /*    */     //   1712: pop
        /*    */     //   1713: getfield o30 : Lf/U90;
        /*    */     //   1716: aload #9
        /*    */     //   1718: iconst_2
        /*    */     //   1719: anewarray f/JG0
        /*    */     //   1722: dup
        /*    */     //   1723: dup
        /*    */     //   1724: aload #5
        /*    */     //   1726: swap
        /*    */     //   1727: aload #5
        /*    */     //   1729: getfield Tx : Lf/JG0;
        /*    */     //   1732: iconst_0
        /*    */     //   1733: swap
        /*    */     //   1734: aastore
        /*    */     //   1735: getfield jK : Lf/Un;
        /*    */     //   1738: iconst_1
        /*    */     //   1739: swap
        /*    */     //   1740: aastore
        /*    */     //   1741: invokevirtual AUX : ([Lf/JG0;)Lf/U90;
        /*    */     //   1744: invokevirtual ee0 : (Lf/U90;)Lf/U90;
        /*    */     //   1747: pop
        /*    */     //   1748: goto -> 1653
        /*    */     //   1751: aload_1
        /*    */     //   1752: aload #9
        /*    */     //   1754: getfield Xz0 : Lf/U90;
        /*    */     //   1757: astore #4
        /*    */     //   1759: getfield f4 : I
        /*    */     //   1762: ifeq -> 1794
        /*    */     //   1765: iload_2
        /*    */     //   1766: ifeq -> 1772
        /*    */     //   1769: goto -> 1794
        /*    */     //   1772: aload #9
        /*    */     //   1774: iconst_1
        /*    */     //   1775: anewarray f/JG0
        /*    */     //   1778: dup
        /*    */     //   1779: astore #5
        /*    */     //   1781: iconst_0
        /*    */     //   1782: aload_3
        /*    */     //   1783: aastore
        /*    */     //   1784: aload #5
        /*    */     //   1786: invokevirtual vo0 : ([Lf/JG0;)Lf/U90;
        /*    */     //   1789: astore #5
        /*    */     //   1791: goto -> 1805
        /*    */     //   1794: new f/cr0
        /*    */     //   1797: dup
        /*    */     //   1798: astore #5
        /*    */     //   1800: aload #9
        /*    */     //   1802: invokespecial <init> : (Lf/Ip;)V
        /*    */     //   1805: aload_1
        /*    */     //   1806: aload #9
        /*    */     //   1808: aload #4
        /*    */     //   1810: aload #5
        /*    */     //   1812: invokevirtual ee0 : (Lf/U90;)Lf/U90;
        /*    */     //   1815: pop
        /*    */     //   1816: getfield o30 : Lf/U90;
        /*    */     //   1819: astore #4
        /*    */     //   1821: getfield f4 : I
        /*    */     //   1824: ifeq -> 1855
        /*    */     //   1827: iload_2
        /*    */     //   1828: ifeq -> 1834
        /*    */     //   1831: goto -> 1855
        /*    */     //   1834: aload #9
        /*    */     //   1836: iconst_1
        /*    */     //   1837: anewarray f/JG0
        /*    */     //   1840: dup
        /*    */     //   1841: astore #5
        /*    */     //   1843: iconst_0
        /*    */     //   1844: aload_3
        /*    */     //   1845: aastore
        /*    */     //   1846: aload #5
        /*    */     //   1848: invokevirtual AUX : ([Lf/JG0;)Lf/U90;
        /*    */     //   1851: astore_3
        /*    */     //   1852: goto -> 1865
        /*    */     //   1855: new f/g0
        /*    */     //   1858: dup
        /*    */     //   1859: astore_3
        /*    */     //   1860: aload #9
        /*    */     //   1862: invokespecial <init> : (Lf/Ip;)V
        /*    */     //   1865: aload_1
        /*    */     //   1866: aload #4
        /*    */     //   1868: aload_3
        /*    */     //   1869: invokevirtual ee0 : (Lf/U90;)Lf/U90;
        /*    */     //   1872: pop
        /*    */     //   1873: new f/rS
        /*    */     //   1876: dup
        /*    */     //   1877: dup
        /*    */     //   1878: astore_3
        /*    */     //   1879: aload #9
        /*    */     //   1881: invokespecial <init> : (Lf/JG0;)V
        /*    */     //   1884: ldc_w 'read-mail'
        /*    */     //   1887: invokevirtual Xu : (Ljava/lang/String;)V
        /*    */     //   1890: new f/Ip
        /*    */     //   1893: dup
        /*    */     //   1894: dup2
        /*    */     //   1895: astore #4
        /*    */     //   1897: invokespecial <init> : ()V
        /*    */     //   1900: new f/g0
        /*    */     //   1903: dup
        /*    */     //   1904: aload #4
        /*    */     //   1906: invokespecial <init> : (Lf/Ip;)V
        /*    */     //   1909: iconst_1
        /*    */     //   1910: anewarray f/U90
        /*    */     //   1913: dup
        /*    */     //   1914: aload #4
        /*    */     //   1916: iconst_1
        /*    */     //   1917: anewarray f/JG0
        /*    */     //   1920: dup
        /*    */     //   1921: iconst_0
        /*    */     //   1922: aload_3
        /*    */     //   1923: aastore
        /*    */     //   1924: invokevirtual vo0 : ([Lf/JG0;)Lf/U90;
        /*    */     //   1927: iconst_0
        /*    */     //   1928: swap
        /*    */     //   1929: aastore
        /*    */     //   1930: invokevirtual cOM8 : ([Lf/U90;)Lf/U90;
        /*    */     //   1933: invokevirtual rK0 : (Lf/U90;)V
        /*    */     //   1936: new f/cr0
        /*    */     //   1939: dup
        /*    */     //   1940: aload #4
        /*    */     //   1942: invokespecial <init> : (Lf/Ip;)V
        /*    */     //   1945: iconst_1
        /*    */     //   1946: anewarray f/U90
        /*    */     //   1949: dup
        /*    */     //   1950: aload #4
        /*    */     //   1952: iconst_1
        /*    */     //   1953: anewarray f/JG0
        /*    */     //   1956: dup
        /*    */     //   1957: iconst_0
        /*    */     //   1958: aload_3
        /*    */     //   1959: aastore
        /*    */     //   1960: invokevirtual AUX : ([Lf/JG0;)Lf/U90;
        /*    */     //   1963: iconst_0
        /*    */     //   1964: swap
        /*    */     //   1965: aastore
        /*    */     //   1966: invokevirtual cOM8 : ([Lf/U90;)Lf/U90;
        /*    */     //   1969: invokevirtual WN : (Lf/U90;)V
        /*    */     //   1972: getfield r10 : Ljava/lang/String;
        /*    */     //   1975: dup
        /*    */     //   1976: astore_3
        /*    */     //   1977: invokevirtual length : ()I
        /*    */     //   1980: bipush #10
        /*    */     //   1982: if_icmple -> 2013
        /*    */     //   1985: new java/lang/StringBuilder
        /*    */     //   1988: dup
        /*    */     //   1989: aload_3
        /*    */     //   1990: swap
        /*    */     //   1991: invokespecial <init> : ()V
        /*    */     //   1994: iconst_0
        /*    */     //   1995: bipush #8
        /*    */     //   1997: invokevirtual substring : (II)Ljava/lang/String;
        /*    */     //   2000: invokevirtual append : (Ljava/lang/String;)Ljava/lang/StringBuilder;
        /*    */     //   2003: ldc_w '...'
        /*    */     //   2006: invokevirtual append : (Ljava/lang/String;)Ljava/lang/StringBuilder;
        /*    */     //   2009: invokevirtual toString : ()Ljava/lang/String;
        /*    */     //   2012: astore_3
        /*    */     //   2013: aload_1
        /*    */     //   2014: getfield f4 : I
        /*    */     //   2017: ifeq -> 2028
        /*    */     //   2020: aload_1
        /*    */     //   2021: getfield V9 : Ljava/lang/String;
        /*    */     //   2024: astore_1
        /*    */     //   2025: goto -> 2036
        /*    */     //   2028: aload_1
        /*    */     //   2029: getfield V9 : Ljava/lang/String;
        /*    */     //   2032: invokestatic LU : (Ljava/lang/String;)Ljava/lang/String;
        /*    */     //   2035: astore_1
        /*    */     //   2036: getstatic f/h1.yA0 : Z
        /*    */     //   2039: ifeq -> 2052
        /*    */     //   2042: aload_1
        /*    */     //   2043: aload_3
        /*    */     //   2044: invokestatic jv : (Ljava/lang/String;)Ljava/lang/String;
        /*    */     //   2047: pop
        /*    */     //   2048: invokestatic jv : (Ljava/lang/String;)Ljava/lang/String;
        /*    */     //   2051: astore_1
        /*    */     //   2052: invokestatic bigCJKFontSizes : ()Z
        /*    */     //   2055: ifeq -> 2064
        /*    */     //   2058: bipush #50
        /*    */     //   2060: istore_3
        /*    */     //   2061: goto -> 2067
        /*    */     //   2064: bipush #48
        /*    */     //   2066: istore_3
        /*    */     //   2067: iload_2
        /*    */     //   2068: aload_0
        /*    */     //   2069: aload_1
        /*    */     //   2070: iconst_0
        /*    */     //   2071: istore_1
        /*    */     //   2072: aconst_null
        /*    */     //   2073: iload_3
        /*    */     //   2074: swap
        /*    */     //   2075: iload_1
        /*    */     //   2076: iconst_0
        /*    */     //   2077: invokestatic Qd0 : (Ljava/lang/String;ILjava/lang/String;ZI)Ljava/lang/String;
        /*    */     //   2080: astore_1
        /*    */     //   2081: getfield dA0 : Lf/K40;
        /*    */     //   2084: astore_3
        /*    */     //   2085: ifeq -> 2094
        /*    */     //   2088: aconst_null
        /*    */     //   2089: astore #5
        /*    */     //   2091: goto -> 2098
        /*    */     //   2094: aload #4
        /*    */     //   2096: astore #5
        /*    */     //   2098: iload_2
        /*    */     //   2099: aload_0
        /*    */     //   2100: aload_3
        /*    */     //   2101: aload #5
        /*    */     //   2103: invokevirtual En : (Lf/Ip;)V
        /*    */     //   2106: getfield fF : Lf/K40;
        /*    */     //   2109: astore_2
        /*    */     //   2110: ifeq -> 2116
        /*    */     //   2113: goto -> 2119
        /*    */     //   2116: aconst_null
        /*    */     //   2117: astore #4
        /*    */     //   2119: aload_0
        /*    */     //   2120: dup
        /*    */     //   2121: aload_2
        /*    */     //   2122: aload #4
        /*    */     //   2124: invokevirtual En : (Lf/Ip;)V
        /*    */     //   2127: invokevirtual MJ0 : ()V
        /*    */     //   2130: getfield rB : Lf/of;
        /*    */     //   2133: aload_1
        /*    */     //   2134: iconst_0
        /*    */     //   2135: invokevirtual Be0 : (Ljava/lang/String;Z)V
        /*    */     //   2138: return
        /*    */     // Line number table:
        /*    */     //   Java source line number -> byte code offset
        /*    */     //   #1	-> 57
        /*    */     //   #2	-> 61
        /*    */     //   #3	-> 71
        /*    */     //   #4	-> 74
        /*    */     //   #5	-> 90
        /*    */     //   #6	-> 93
        /*    */     //   #7	-> 96
        /*    */     //   #8	-> 113
        /*    */     //   #9	-> 116
        /*    */     //   #10	-> 126
        /*    */     //   #11	-> 129
        /*    */     //   #12	-> 136
        /*    */     //   #13	-> 145
        /*    */     //   #14	-> 152
        /*    */     //   #15	-> 161
        /*    */     //   #16	-> 176
        /*    */     //   #17	-> 179
        /*    */     //   #18	-> 193
        /*    */     //   #19	-> 196
        /*    */     //   #20	-> 199
        /*    */     //   #21	-> 206
        /*    */     //   #22	-> 215
        /*    */     //   #23	-> 230
        /*    */     //   #24	-> 233
        /*    */     //   #25	-> 249
        /*    */     //   #26	-> 257
        /*    */     //   #27	-> 260
        /*    */     //   #28	-> 263
        /*    */     //   #29	-> 286
        /*    */     //   #30	-> 293
        /*    */     //   #31	-> 311
        /*    */     //   #32	-> 318
        /*    */     //   #33	-> 333
        /*    */     //   #34	-> 336
        /*    */     //   #35	-> 340
        /*    */     //   #36	-> 344
        /*    */     //   #37	-> 385
        /*    */     //   #38	-> 393
        /*    */     //   #39	-> 423
        /*    */     //   #40	-> 439
        /*    */     //   #41	-> 458
        /*    */     //   #42	-> 483
        /*    */     //   #43	-> 562
        /*    */     //   #44	-> 582
        /*    */     //   #45	-> 786
        /*    */     //   #46	-> 794
        /*    */     //   #47	-> 800
        /*    */     //   #48	-> 806
        /*    */     //   #49	-> 895
        /*    */     //   #50	-> 901
        /*    */     //   #51	-> 1001
        /*    */     //   #52	-> 1009
        /*    */     //   #53	-> 1015
        /*    */     //   #54	-> 1026
        /*    */     //   #55	-> 1037
        /*    */     //   #56	-> 1189
        /*    */     //   #57	-> 1194
        /*    */     //   #58	-> 1198
        /*    */     //   #59	-> 1203
        /*    */     //   #60	-> 1230
        /*    */     //   #61	-> 1238
        /*    */     //   #62	-> 1244
        /*    */     //   #63	-> 1255
        /*    */     //   #64	-> 1277
        /*    */     //   #65	-> 1445
        /*    */     //   #66	-> 1454
        /*    */     //   #67	-> 1549
        /*    */     //   #68	-> 1554
        /*    */     //   #69	-> 1558
        /*    */     //   #70	-> 1563
        /*    */     //   #71	-> 1579
        /*    */     //   #72	-> 1585
        /*    */     //   #73	-> 1613
        /*    */     //   #74	-> 1619
        /*    */     //   #75	-> 1678
        /*    */     //   #76	-> 1684
        /*    */     //   #77	-> 1713
        /*    */     //   #78	-> 1719
        /*    */     //   #79	-> 1754
        /*    */     //   #80	-> 1759
        /*    */     //   #81	-> 1775
        /*    */     //   #82	-> 1794
        /*    */     //   #83	-> 1812
        /*    */     //   #84	-> 1816
        /*    */     //   #85	-> 1821
        /*    */     //   #86	-> 1837
        /*    */     //   #87	-> 1855
        /*    */     //   #88	-> 1869
        /*    */     //   #89	-> 1900
        /*    */     //   #90	-> 1910
        /*    */     //   #91	-> 1936
        /*    */     //   #92	-> 1946
        /*    */     //   #93	-> 1972
        /*    */     //   #94	-> 1977
        /*    */     //   #95	-> 2014
        /*    */     //   #96	-> 2021
        /*    */     //   #97	-> 2029
        /*    */     //   #98	-> 2036
        /*    */     //   #99	-> 2077
        /*    */     //   #100	-> 2081
        /*  9 */     //   #101	-> 2135 } public final void JK0(pv0 parampv0) { this.tv.sk0(true); int i; if ((i = parampv0.ordinal()) != 0) { switch (i) { default: return;case 6: VA0.c90(this.Nv0);case 5: VA0.c90(this.cl);case 4: break; }  VA0.c90(this.Gr); }  qb(false); } public final void qb(boolean paramBoolean) { if (paramBoolean && (this.Nv0.F2.length() > 10 || this.cl.F2.length() > 5)) { js.vu0.uh(new h70(Ml0.OH0(5816), new da0(this), this)); } else { this.Gr.Be0("", false); this.cl
        /* 10 */         .Be0("", false);
        /* 11 */
        this.Nv0
/* 12 */.Be0("", false);
        /* 13 */
        this.
        default.l4(0);
        T1[] arrayOfT1;
        int j;
        byte b;
        for (j = (arrayOfT1 = this.WN).length, b = 0; b < j; ) {
            arrayOfT1[b].Tm0(null);
            b++;
        }
        Qv0[] arrayOfQv0;
        for (int i = (arrayOfQv0 = this.Jt).length; j < i; ) {
            this[j].zf(null);
            j++;
        }
        /*    */
    }
    /*    */      }

    /*    */
    /*    */
    /*    */
    public final void IG0() {
        /*    */
        VA0.c90(this);
        /*    */
    }

    /*    */
    /*    */
    public final void d40() {
        /*    */
        super.d40();
        /*    */
        if (km.XU()) {
            /*    */
            QI();
            /*    */
        } else {
            /*    */
            of of1;
            /*    */
            if ((of1 = this.rB) != null)
                /*    */ of1.uh0(0, 150);
            /*    */
        }
        /*    */
        if (this.cS) {
            /*    */
            this.kc.dA0(this.kc.Hf(1));
            /*    */
            this.cS = false;
            /*    */
        }
        /*    */
    }

    /*    */
    /*    */
    public final void zf0(j40 paramj40) {
        /*    */
        boolean bool;
        /*    */
        Qv0[] arrayOfQv0;
        /*    */
        int i;
        /*    */
        byte b;
        /*    */
        for (i = (arrayOfQv0 = this.Jt).length, b = 0; b < i; ) {
            /*    */
            Qv0 qv0;
            /*    */
            if ((qv0 = arrayOfQv0[b]). public () == null){
                /*    */
                qv0.zf(paramj40);
                /*    */
                break;
                /*    */
            }
            /*    */
            b++;
            /*    */
        }
        /*    */
        if (this.kM != 0) {
            /*    */
            bool = true;
            /*    */
        } else {
            /*    */
            bool = false;
            /*    */
        }
        /*    */
        if (bool) {
            /*    */
            this.cS = true;
            /*    */
        } else {
            /*    */
            this.kc.dA0(this.kc.Hf(1));
            /*    */
        }
        /*    */
        BA();
        /*    */
    }

    /*    */
    /*    */
    public final void close() {
        /*    */
        Un un;
        /*    */
        if ((un = this.tv) != null && !this.kN)
            /*    */ return;
        /*    */
        pA pA;
        /*    */
        if ((pA = js.vu0.MH0).dk0 == null && this.QI0 == null)
            /*    */ km.u4.e20.W3(new nC());
        /*    */
        js.vu0.MH0.BI0(null, false, false);
        /*    */
    }
}


/* Location:              /Users/vnnsnnt/Documents/Codespace/JavaWorkspace/RedTrainer/src/main/java/org/trainer/client/PokeMMO.jar!/f/Kf.class
 * Java compiler version: 8 (52.0)
 * JD-Core Version:       1.1.3
 */