/*  1 */ package f;public abstract class kR extends Ar0 { public d70 cr0; public Jp0 n2; public boolean c5; public static void Xw0(ql0 paramql0, Jp0 paramJp0) { boolean bool; paramJp0.Wu("name", null); float f3 = Float.parseFloat(paramJp0.Wu("opacity", "1.0")); if (paramJp0.xT(1, "visible") == 1) { bool = true; } else { bool = false; }  float f1 = paramJp0.r8("offsetx", 0.0F), f2 = paramJp0.r8("offsety", 0.0F); paramql0.ln0 = f3; paramql0
/*  2 */       .CG0 = bool;
/*  3 */     paramql0.FG0 = f1; paramql0.Rj0();
/*  4 */     paramql0.bc = f2; paramql0.Rj0(); } public int Zg0; public pB0 L2; public kR(Xt0 paramXt0) { super(paramXt0); d70 d701; this(); this.cr0 = this; this.c5 = true; } public static RD0 Te0(RD0 paramRD0, String paramString) { this(paramString, "\\/"); StringTokenizer stringTokenizer; RD0 rD0; for (rD0 = paramRD0.wT(); stringTokenizer.hasMoreElements(); rD0 = rD0.f0(str)) { String str; if ((str = stringTokenizer.nextToken()).equals("..")) { rD0 = rD0.wT(); continue; }  }  return rD0; } public static void R3(y9 paramy9, Jp0 paramJp0) { if (paramJp0.Xh0.equals("properties")) for (Hc0 hc0 = paramJp0.LG0("property").r30(); hc0.hasNext(); ) { Color color; Jp0 jp0; String str1 = (jp0 = (Jp0)hc0.next()).Wu("name", null), str3 = jp0.Wu("type", null); String str2; if ((str2 = ((Jp0)hc0.next()).Wu("value", null)) == null) str2 = jp0.MK0;  if (str3 != null) { Integer integer; if (str3.equals("int")) { integer = Integer.valueOf(str2); } else { Float float_; if (str3.equals("float")) { float_ = Float.valueOf((String)integer); } else { Boolean bool; if (str3.equals("bool")) { bool = Boolean.valueOf((String)float_); } else if (str3.equals("color")) { String str = bool.substring(3); color = Color.valueOf(str + bool.substring(1, 3)); }
/*    */               else
/*    */               
/*  7 */               { throw new JU("Wrong type given for property " + str1 + ", given : " + str3 + ", supported : string, bool, int, float, color"); }  }  }  }  paramy9.un.X00(str1, color); }   } public abstract fQ Hf0(RD0 paramRD0, kd0 paramkd0); public final pB0 PRn(RD0 paramRD0, Lv paramLv, np paramnp) { this(); pB0 pB01; int i; this.L2 = pB01; if (paramLv != null) { this.c5 = paramLv.go; } else { this.c5 = true; }  int j = this.n2.xT(0, "width"), k = this.n2.xT(0, "height"), m = this.n2.xT(0, "tilewidth"), n = this.n2.xT(0, "tileheight"), i1 = this.n2.xT(0, "hexsidelength"); String str2 = this.n2.Wu("staggeraxis", null), str3 = this.n2.Wu("staggerindex", null), str4 = this.n2.Wu("backgroundcolor", null); y9 y9 = this.L2.nK0; String str1; if ((str1 = this.n2.Wu("orientation", null)) != null) y9.un.X00("orientation", str1);  Integer integer = Integer.valueOf(j); y9.un.X00("width", integer); integer = Integer.valueOf(k);
/*  8 */     y9.un.X00("height", integer);
/*  9 */     integer = Integer.valueOf(m);
/* 10 */     y9.un.X00("tilewidth", integer);
/* 11 */     integer = Integer.valueOf(n);
/* 12 */     y9.un.X00("tileheight", integer);
/* 13 */     integer = Integer.valueOf(i1);
/* 14 */     y9.un.X00("hexsidelength", integer); if (str2 != null) y9.un.X00("staggeraxis", str2);  if (str3 != null) y9.un.X00("staggerindex", str3);  if (str4 != null) y9.un.X00("backgroundcolor", str4);  this
/* 15 */       .Zg0 = k * n; if (str1 != null && "staggered".equals(str1) && k > 1) { m / 2; int i2 = this.Zg0 / 2; this.Zg0 = n / 2 + i2; }  Jp0 jp0; if ((jp0 = this.n2.cE("properties")) != null)
/*    */     {
/* 17 */       R3(this.L2.nK0, jp0); }  for (Hc0 hc0 = this.n2.LG0("tileset").r30(); hc0.hasNext(); ) { Jp0 jp01; if ((jp01 = (Jp0)hc0.next())
/* 18 */         .Xh0
/* 19 */         .equals("tileset")) { fQ fQ2; RD0 rD0; Jp0 jp03; tv tv; k = jp01.xT(1, "firstgid"); String str = ""; n = 0; i1 = 0; str2 = null; if ((str3 = jp01.Wu("source", null)) != null) { RD0 rD01 = Te0(paramRD0, str3); try { Jp0 jp06; if ((jp06 = (jp03 = this.cr0.g(rD01)).cE("image")) != null) { str = jp06.UI0("source"); n = jp06.xT(0, "width"); i1 = jp06.xT(0, "height"); rD0 = Te0(rD01, str); }  } catch (kN kN) { throw new JU("Error parsing external tileset."); }  } else { Jp0 jp06; if ((jp06 = jp01.cE("image")) != null) { str = jp06.UI0("source"); n = jp06.xT(0, "width"); i1 = jp06.xT(0, "height"); rD0 = Te0(paramRD0, str); jp03 = jp01; } else { jp03 = jp01; }  }  str4 = "name"; Jp0 jp02; f7 f7;
/* 20 */         if (((f7 = jp03.CT) == null || (String)f7.pd0(str4) == null) && (jp02 = jp03.cE(str4)) != null);
/*    */         
/* 22 */         int i2 = jp03.xT(0, "tilewidth"), i3 = jp03.xT(0, "tileheight"), i4 = jp03.xT(0, "spacing"), i5 = jp03.xT(0, "margin"), i6 = 0, i7 = 0; Jp0 jp04; if ((jp04 = jp03.cE("tileoffset")) != null) { i6 = jp04.xT(0, "x"); i7 = jp04.xT(0, "y"); }  this();
/* 23 */         y9 y91 = (new tv()).wo0; Jp0 jp05;
/* 24 */         if ((jp05 = jp03.cE("properties")) != null) R3(y91, jp05);  Integer integer1 = Integer.valueOf(k); y91
/* 25 */           .un
/* 26 */           .X00("firstgid", integer1);
/* 27 */         Ne0(paramRD0, paramnp, tv, fQ3, k, i2, i3, i4, i5, str3, i6, i7, str, n, i1, rD0); this(); fQ fQ3; for (Hc0 hc02 = (fQ3 = jp03.LG0("tile")).r30(); hc02.hasNext(); ) { Jp0 jp06; int i8 = (jp06 = (Jp0)hc02.next()).xT(0, "id") + k; else else;
/* 28 */           if ((else = (else)tv.m0.get(i8)) != null)
/* 29 */           { fQ fQ4; Jp0 jp08; if ((jp08 = jp06.cE("animation")) != null) { fQ fQ5; o0 o0; this(); this(); for (Hc0 hc03 = jp08.LG0("frame").r30(); hc03.hasNext(); )
/*    */               
/* 31 */               { int i9 = Integer.parseInt(jp09.UI0("tileid")) + k;
/*    */                 
/* 33 */                 fQ5.Com3(tv.m0.get(i9));
/*    */                 Jp0 jp09;
/* 35 */                 o0.oU(Integer.parseInt((jp09 = (Jp0)hc03.next()).UI0("duration"))); }  this(o0, fQ5); kp kp; (kp = new kp())
/* 36 */                 .JU = else.getId(); } else { fQ3 = null; }  if (fQ3 != null) { fQ2
/* 37 */                 .Com3(fQ3); fQ4 = fQ3; }
/* 38 */              String str5; if ((str5 = jp06.Wu("terrain", null)) != null) (fQ4.eY())
/* 39 */                 .un
/* 40 */                 .X00("terrain", str5); 
/* 41 */             if ((str5 = jp06.Wu("probability", null)) != null) (fQ4.eY())
/* 42 */                 .un
/* 43 */                 .X00("probability", str5); 
/* 44 */             if ((str5 = jp06.Wu("type", null)) != null) (fQ4.eY())
/* 45 */                 .un
/* 46 */                 .X00("type", str5);  Jp0 jp07;
/* 47 */             if ((jp07 = jp06.cE("properties")) != null) R3(fQ4.eY(), jp07); 
/* 48 */             if ((jp06 = jp06.cE("objectgroup")) != null) for (Hc0 hc03 = jp06.LG0("object").r30(); hc03.hasNext(); ) { jp07 = (Jp0)hc03.next(); pB0 pB02 = this.L2;
/* 49 */                 GC gC = fQ4.Jy0();
/* 50 */                 float f = (fQ4.LPT8()).Vn0;
/* 51 */                 UX(pB02, gC, jp07, f); }   }  }
/* 52 */          for (Hc0 hc01 = fQ2.r30(); hc01.hasNext(); ) {
/* 53 */           kp kp; int i8 = (kp = (kp)hc01.next()).JU;
/* 54 */           tv.m0.tD0(i8, kp);
/*    */         } 
/* 56 */         this.L2.f8
/* 57 */           .GO
/* 58 */           .Com3(tv); }
/*    */        fQ fQ1;
/* 60 */       if ((fQ1 = this.n2.gu0) != null) fQ1
/* 61 */           .Ct(jp01, true);  }  byte b = 0;
/*    */     fQ fQ;
/* 63 */     if ((fQ = this.n2.gu0) == null) { i = 0; }
/* 64 */     else { i = i.Z8; }  while (b < i) {
/*    */       Jp0 jp01; fQ fQ1;
/* 66 */       if ((fQ1 = (jp01 = this.n2).gu0) != null) {
/* 67 */         jp01 = (Jp0)fQ1.get(b);
/*    */ 
/*    */         
/* 70 */         Xm(this.L2, this.L2.TC, jp01, paramRD0, paramnp); b++; continue;
/* 71 */       }  throw new JU(
/* 72 */           B40.df("Element has no children: ")
/* 73 */           .append(jp01.Xh0).toString());
/* 74 */     }  return this.L2; }
/*    */ 
/*    */   
/*    */   public final void Xm(pB0 parampB0, lb paramlb, Jp0 paramJp0, RD0 paramRD0, np paramnp) {
/*    */     // Byte code:
/*    */     //   0: aload_3
/*    */     //   1: getfield Xh0 : Ljava/lang/String;
/*    */     //   4: dup
/*    */     //   5: astore #6
/*    */     //   7: ldc_w 'group'
/*    */     //   10: invokevirtual equals : (Ljava/lang/Object;)Z
/*    */     //   13: ifeq -> 236
/*    */     //   16: aload_3
/*    */     //   17: getfield Xh0 : Ljava/lang/String;
/*    */     //   20: ldc_w 'group'
/*    */     //   23: invokevirtual equals : (Ljava/lang/Object;)Z
/*    */     //   26: ifeq -> 1619
/*    */     //   29: aload_3
/*    */     //   30: new f/si0
/*    */     //   33: dup
/*    */     //   34: dup
/*    */     //   35: astore #6
/*    */     //   37: invokespecial <init> : ()V
/*    */     //   40: aload_3
/*    */     //   41: invokestatic Xw0 : (Lf/ql0;Lf/Jp0;)V
/*    */     //   44: ldc 'properties'
/*    */     //   46: invokevirtual cE : (Ljava/lang/String;)Lf/Jp0;
/*    */     //   49: dup
/*    */     //   50: astore #7
/*    */     //   52: ifnull -> 65
/*    */     //   55: aload #6
/*    */     //   57: getfield HT : Lf/y9;
/*    */     //   60: aload #7
/*    */     //   62: invokestatic R3 : (Lf/y9;Lf/Jp0;)V
/*    */     //   65: aload_3
/*    */     //   66: iconst_0
/*    */     //   67: istore #7
/*    */     //   69: getfield gu0 : Lf/fQ;
/*    */     //   72: dup
/*    */     //   73: astore #8
/*    */     //   75: ifnonnull -> 84
/*    */     //   78: iconst_0
/*    */     //   79: istore #8
/*    */     //   81: goto -> 91
/*    */     //   84: aload #8
/*    */     //   86: getfield Z8 : I
/*    */     //   89: istore #8
/*    */     //   91: iload #7
/*    */     //   93: iload #8
/*    */     //   95: if_icmpge -> 166
/*    */     //   98: aload_3
/*    */     //   99: getfield gu0 : Lf/fQ;
/*    */     //   102: dup
/*    */     //   103: astore #9
/*    */     //   105: ifnull -> 142
/*    */     //   108: aload_0
/*    */     //   109: aload_1
/*    */     //   110: aload #6
/*    */     //   112: aload #9
/*    */     //   114: iload #7
/*    */     //   116: invokevirtual get : (I)Ljava/lang/Object;
/*    */     //   119: checkcast f/Jp0
/*    */     //   122: astore #9
/*    */     //   124: getfield VI : Lf/lb;
/*    */     //   127: aload #9
/*    */     //   129: aload #4
/*    */     //   131: aload #5
/*    */     //   133: invokevirtual Xm : (Lf/pB0;Lf/lb;Lf/Jp0;Lf/RD0;Lf/np;)V
/*    */     //   136: iinc #7, 1
/*    */     //   139: goto -> 91
/*    */     //   142: new f/JU
/*    */     //   145: dup
/*    */     //   146: ldc_w 'Element has no children: '
/*    */     //   149: invokestatic df : (Ljava/lang/String;)Ljava/lang/StringBuilder;
/*    */     //   152: aload_3
/*    */     //   153: getfield Xh0 : Ljava/lang/String;
/*    */     //   156: invokevirtual append : (Ljava/lang/String;)Ljava/lang/StringBuilder;
/*    */     //   159: invokevirtual toString : ()Ljava/lang/String;
/*    */     //   162: invokespecial <init> : (Ljava/lang/String;)V
/*    */     //   165: athrow
/*    */     //   166: aload #6
/*    */     //   168: getfield VI : Lf/lb;
/*    */     //   171: getfield VD0 : Lf/fQ;
/*    */     //   174: invokevirtual r30 : ()Lf/Hc0;
/*    */     //   177: astore_0
/*    */     //   178: aload_0
/*    */     //   179: invokevirtual hasNext : ()Z
/*    */     //   182: ifeq -> 224
/*    */     //   185: aload #6
/*    */     //   187: aload_0
/*    */     //   188: invokevirtual next : ()Ljava/lang/Object;
/*    */     //   191: checkcast f/ql0
/*    */     //   194: dup
/*    */     //   195: astore_1
/*    */     //   196: if_acmpeq -> 208
/*    */     //   199: aload_1
/*    */     //   200: aload #6
/*    */     //   202: putfield T7 : Lf/ql0;
/*    */     //   205: goto -> 178
/*    */     //   208: aload_1
/*    */     //   209: invokevirtual getClass : ()Ljava/lang/Class;
/*    */     //   212: pop
/*    */     //   213: new f/JU
/*    */     //   216: dup
/*    */     //   217: ldc_w 'Can't set self as the parent'
/*    */     //   220: invokespecial <init> : (Ljava/lang/String;)V
/*    */     //   223: athrow
/*    */     //   224: aload_2
/*    */     //   225: getfield VD0 : Lf/fQ;
/*    */     //   228: aload #6
/*    */     //   230: invokevirtual Com3 : (Ljava/lang/Object;)V
/*    */     //   233: goto -> 1619
/*    */     //   236: aload #6
/*    */     //   238: ldc_w 'layer'
/*    */     //   241: invokevirtual equals : (Ljava/lang/Object;)Z
/*    */     //   244: ifeq -> 1239
/*    */     //   247: aload_3
/*    */     //   248: getfield Xh0 : Ljava/lang/String;
/*    */     //   251: ldc_w 'layer'
/*    */     //   254: invokevirtual equals : (Ljava/lang/Object;)Z
/*    */     //   257: ifeq -> 1619
/*    */     //   260: aload_3
/*    */     //   261: aload_1
/*    */     //   262: dup
/*    */     //   263: aload_3
/*    */     //   264: dup
/*    */     //   265: iconst_0
/*    */     //   266: ldc 'width'
/*    */     //   268: invokevirtual xT : (ILjava/lang/String;)I
/*    */     //   271: istore #4
/*    */     //   273: iconst_0
/*    */     //   274: ldc 'height'
/*    */     //   276: invokevirtual xT : (ILjava/lang/String;)I
/*    */     //   279: istore #5
/*    */     //   281: getfield nK0 : Lf/y9;
/*    */     //   284: getfield un : Lf/f7;
/*    */     //   287: ldc 'tilewidth'
/*    */     //   289: invokevirtual pd0 : (Ljava/lang/Object;)Ljava/lang/Object;
/*    */     //   292: checkcast java/lang/Integer
/*    */     //   295: invokevirtual intValue : ()I
/*    */     //   298: istore #6
/*    */     //   300: getfield nK0 : Lf/y9;
/*    */     //   303: getfield un : Lf/f7;
/*    */     //   306: ldc 'tileheight'
/*    */     //   308: invokevirtual pd0 : (Ljava/lang/Object;)Ljava/lang/Object;
/*    */     //   311: checkcast java/lang/Integer
/*    */     //   314: invokevirtual intValue : ()I
/*    */     //   317: istore #7
/*    */     //   319: new f/YN
/*    */     //   322: dup
/*    */     //   323: astore #8
/*    */     //   325: aload_3
/*    */     //   326: aload #8
/*    */     //   328: iload #4
/*    */     //   330: iload #5
/*    */     //   332: iload #6
/*    */     //   334: iload #7
/*    */     //   336: invokespecial <init> : (IIII)V
/*    */     //   339: invokestatic Xw0 : (Lf/ql0;Lf/Jp0;)V
/*    */     //   342: ldc_w 'data'
/*    */     //   345: invokevirtual cE : (Ljava/lang/String;)Lf/Jp0;
/*    */     //   348: dup
/*    */     //   349: astore #6
/*    */     //   351: ldc_w 'encoding'
/*    */     //   354: aconst_null
/*    */     //   355: invokevirtual Wu : (Ljava/lang/String;Ljava/lang/String;)Ljava/lang/String;
/*    */     //   358: dup
/*    */     //   359: astore #7
/*    */     //   361: ifnull -> 1228
/*    */     //   364: aload #7
/*    */     //   366: iload #4
/*    */     //   368: iload #5
/*    */     //   370: imul
/*    */     //   371: newarray int
/*    */     //   373: astore #9
/*    */     //   375: ldc_w 'csv'
/*    */     //   378: invokevirtual equals : (Ljava/lang/Object;)Z
/*    */     //   381: ifeq -> 431
/*    */     //   384: aload #6
/*    */     //   386: getfield MK0 : Ljava/lang/String;
/*    */     //   389: ldc_w ','
/*    */     //   392: invokevirtual split : (Ljava/lang/String;)[Ljava/lang/String;
/*    */     //   395: astore #6
/*    */     //   397: iconst_0
/*    */     //   398: istore #7
/*    */     //   400: iload #7
/*    */     //   402: aload #6
/*    */     //   404: arraylength
/*    */     //   405: if_icmpge -> 763
/*    */     //   408: aload #9
/*    */     //   410: iload #7
/*    */     //   412: aload #6
/*    */     //   414: iload #7
/*    */     //   416: aaload
/*    */     //   417: invokevirtual trim : ()Ljava/lang/String;
/*    */     //   420: invokestatic parseLong : (Ljava/lang/String;)J
/*    */     //   423: l2i
/*    */     //   424: iastore
/*    */     //   425: iinc #7, 1
/*    */     //   428: goto -> 400
/*    */     //   431: aload #7
/*    */     //   433: ldc_w 'base64'
/*    */     //   436: invokevirtual equals : (Ljava/lang/Object;)Z
/*    */     //   439: ifeq -> 1209
/*    */     //   442: aload #6
/*    */     //   444: aconst_null
/*    */     //   445: astore #7
/*    */     //   447: ldc_w 'compression'
/*    */     //   450: aconst_null
/*    */     //   451: invokevirtual Wu : (Ljava/lang/String;Ljava/lang/String;)Ljava/lang/String;
/*    */     //   454: dup
/*    */     //   455: astore #10
/*    */     //   457: aload #6
/*    */     //   459: getfield MK0 : Ljava/lang/String;
/*    */     //   462: invokestatic HI0 : (Ljava/lang/String;)[B
/*    */     //   465: astore #6
/*    */     //   467: ifnonnull -> 488
/*    */     //   470: new java/io/ByteArrayInputStream
/*    */     //   473: dup
/*    */     //   474: astore #10
/*    */     //   476: aload #6
/*    */     //   478: invokespecial <init> : ([B)V
/*    */     //   481: aload #10
/*    */     //   483: astore #7
/*    */     //   485: goto -> 586
/*    */     //   488: aload #10
/*    */     //   490: ldc_w 'gzip'
/*    */     //   493: invokevirtual equals : (Ljava/lang/Object;)Z
/*    */     //   496: ifeq -> 539
/*    */     //   499: new java/io/BufferedInputStream
/*    */     //   502: dup
/*    */     //   503: astore #10
/*    */     //   505: new java/util/zip/GZIPInputStream
/*    */     //   508: dup
/*    */     //   509: astore #11
/*    */     //   511: aload #6
/*    */     //   513: new java/io/ByteArrayInputStream
/*    */     //   516: dup
/*    */     //   517: astore #12
/*    */     //   519: aload #6
/*    */     //   521: invokespecial <init> : ([B)V
/*    */     //   524: arraylength
/*    */     //   525: aload #12
/*    */     //   527: swap
/*    */     //   528: invokespecial <init> : (Ljava/io/InputStream;I)V
/*    */     //   531: aload #11
/*    */     //   533: invokespecial <init> : (Ljava/io/InputStream;)V
/*    */     //   536: goto -> 481
/*    */     //   539: aload #10
/*    */     //   541: ldc_w 'zlib'
/*    */     //   544: invokevirtual equals : (Ljava/lang/Object;)Z
/*    */     //   547: ifeq -> 1131
/*    */     //   550: new java/io/BufferedInputStream
/*    */     //   553: dup
/*    */     //   554: astore #10
/*    */     //   556: new java/util/zip/InflaterInputStream
/*    */     //   559: dup
/*    */     //   560: astore #11
/*    */     //   562: new java/io/ByteArrayInputStream
/*    */     //   565: dup
/*    */     //   566: astore #12
/*    */     //   568: aload #6
/*    */     //   570: invokespecial <init> : ([B)V
/*    */     //   573: aload #12
/*    */     //   575: invokespecial <init> : (Ljava/io/InputStream;)V
/*    */     //   578: aload #11
/*    */     //   580: invokespecial <init> : (Ljava/io/InputStream;)V
/*    */     //   583: goto -> 481
/*    */     //   586: iconst_4
/*    */     //   587: dup
/*    */     //   588: istore #6
/*    */     //   590: newarray byte
/*    */     //   592: astore #10
/*    */     //   594: iconst_0
/*    */     //   595: istore #11
/*    */     //   597: iload #11
/*    */     //   599: iload #5
/*    */     //   601: if_icmpge -> 758
/*    */     //   604: iconst_0
/*    */     //   605: istore #12
/*    */     //   607: iload #12
/*    */     //   609: iload #4
/*    */     //   611: if_icmpge -> 752
/*    */     //   614: aload #7
/*    */     //   616: aload #10
/*    */     //   618: invokevirtual read : ([B)I
/*    */     //   621: istore #13
/*    */     //   623: iload #13
/*    */     //   625: iload #6
/*    */     //   627: if_icmpge -> 668
/*    */     //   630: aload #7
/*    */     //   632: iload #6
/*    */     //   634: iload #13
/*    */     //   636: isub
/*    */     //   637: istore #14
/*    */     //   639: aload #10
/*    */     //   641: iload #13
/*    */     //   643: iload #14
/*    */     //   645: invokevirtual read : ([BII)I
/*    */     //   648: dup
/*    */     //   649: istore #14
/*    */     //   651: iconst_m1
/*    */     //   652: if_icmpne -> 658
/*    */     //   655: goto -> 668
/*    */     //   658: iload #13
/*    */     //   660: iload #14
/*    */     //   662: iadd
/*    */     //   663: istore #13
/*    */     //   665: goto -> 623
/*    */     //   668: iload #13
/*    */     //   670: iload #6
/*    */     //   672: if_icmpne -> 741
/*    */     //   675: aload #9
/*    */     //   677: aload #10
/*    */     //   679: iload #11
/*    */     //   681: iload #4
/*    */     //   683: imul
/*    */     //   684: iload #12
/*    */     //   686: iadd
/*    */     //   687: istore #13
/*    */     //   689: iconst_0
/*    */     //   690: baload
/*    */     //   691: sipush #255
/*    */     //   694: iand
/*    */     //   695: aload #10
/*    */     //   697: iconst_1
/*    */     //   698: baload
/*    */     //   699: sipush #255
/*    */     //   702: iand
/*    */     //   703: bipush #8
/*    */     //   705: ishl
/*    */     //   706: ior
/*    */     //   707: aload #10
/*    */     //   709: iconst_2
/*    */     //   710: baload
/*    */     //   711: sipush #255
/*    */     //   714: iand
/*    */     //   715: bipush #16
/*    */     //   717: ishl
/*    */     //   718: ior
/*    */     //   719: aload #10
/*    */     //   721: iconst_3
/*    */     //   722: baload
/*    */     //   723: sipush #255
/*    */     //   726: iand
/*    */     //   727: bipush #24
/*    */     //   729: ishl
/*    */     //   730: ior
/*    */     //   731: iload #13
/*    */     //   733: swap
/*    */     //   734: iastore
/*    */     //   735: iinc #12, 1
/*    */     //   738: goto -> 607
/*    */     //   741: new f/JU
/*    */     //   744: dup
/*    */     //   745: ldc_w 'Error Reading TMX Layer Data: Premature end of tile data'
/*    */     //   748: invokespecial <init> : (Ljava/lang/String;)V
/*    */     //   751: athrow
/*    */     //   752: iinc #11, 1
/*    */     //   755: goto -> 597
/*    */     //   758: aload #7
/*    */     //   760: invokestatic JC0 : (Ljava/io/Closeable;)V
/*    */     //   763: aload_1
/*    */     //   764: getfield f8 : Lf/bR;
/*    */     //   767: astore_1
/*    */     //   768: iconst_0
/*    */     //   769: istore #6
/*    */     //   771: iload #6
/*    */     //   773: iload #5
/*    */     //   775: if_icmpge -> 1099
/*    */     //   778: iconst_0
/*    */     //   779: istore #7
/*    */     //   781: iload #7
/*    */     //   783: iload #4
/*    */     //   785: if_icmpge -> 1093
/*    */     //   788: aload #9
/*    */     //   790: iload #6
/*    */     //   792: iload #4
/*    */     //   794: imul
/*    */     //   795: iload #7
/*    */     //   797: iadd
/*    */     //   798: iaload
/*    */     //   799: dup
/*    */     //   800: istore #10
/*    */     //   802: ldc_w -2147483648
/*    */     //   805: iand
/*    */     //   806: ifeq -> 815
/*    */     //   809: iconst_1
/*    */     //   810: istore #11
/*    */     //   812: goto -> 818
/*    */     //   815: iconst_0
/*    */     //   816: istore #11
/*    */     //   818: iload #10
/*    */     //   820: ldc_w 1073741824
/*    */     //   823: iand
/*    */     //   824: ifeq -> 833
/*    */     //   827: iconst_1
/*    */     //   828: istore #12
/*    */     //   830: goto -> 836
/*    */     //   833: iconst_0
/*    */     //   834: istore #12
/*    */     //   836: iload #10
/*    */     //   838: ldc_w 536870912
/*    */     //   841: iand
/*    */     //   842: ifeq -> 851
/*    */     //   845: iconst_1
/*    */     //   846: istore #13
/*    */     //   848: goto -> 854
/*    */     //   851: iconst_0
/*    */     //   852: istore #13
/*    */     //   854: aload_1
/*    */     //   855: iload #10
/*    */     //   857: ldc_w 536870911
/*    */     //   860: iand
/*    */     //   861: istore #10
/*    */     //   863: getfield GO : Lf/fQ;
/*    */     //   866: getfield Z8 : I
/*    */     //   869: iconst_1
/*    */     //   870: isub
/*    */     //   871: istore #14
/*    */     //   873: iload #14
/*    */     //   875: iflt -> 916
/*    */     //   878: aload_1
/*    */     //   879: getfield GO : Lf/fQ;
/*    */     //   882: iload #14
/*    */     //   884: invokevirtual get : (I)Ljava/lang/Object;
/*    */     //   887: checkcast f/tv
/*    */     //   890: getfield m0 : Lf/y10;
/*    */     //   893: iload #10
/*    */     //   895: invokevirtual get : (I)Ljava/lang/Object;
/*    */     //   898: checkcast f/else
/*    */     //   901: dup
/*    */     //   902: astore #15
/*    */     //   904: ifnull -> 910
/*    */     //   907: goto -> 919
/*    */     //   910: iinc #14, -1
/*    */     //   913: goto -> 873
/*    */     //   916: aconst_null
/*    */     //   917: astore #15
/*    */     //   919: aload #15
/*    */     //   921: ifnull -> 1087
/*    */     //   924: iload #13
/*    */     //   926: new f/H40
/*    */     //   929: dup
/*    */     //   930: astore #10
/*    */     //   932: invokespecial <init> : ()V
/*    */     //   935: ifeq -> 995
/*    */     //   938: iload #11
/*    */     //   940: ifeq -> 957
/*    */     //   943: iload #12
/*    */     //   945: ifeq -> 957
/*    */     //   948: aload #10
/*    */     //   950: iconst_1
/*    */     //   951: putfield dj0 : Z
/*    */     //   954: goto -> 982
/*    */     //   957: iload #11
/*    */     //   959: ifeq -> 965
/*    */     //   962: goto -> 982
/*    */     //   965: iload #12
/*    */     //   967: ifeq -> 976
/*    */     //   970: iconst_1
/*    */     //   971: istore #11
/*    */     //   973: goto -> 985
/*    */     //   976: aload #10
/*    */     //   978: iconst_1
/*    */     //   979: putfield NI0 : Z
/*    */     //   982: iconst_3
/*    */     //   983: istore #11
/*    */     //   985: aload #10
/*    */     //   987: iload #11
/*    */     //   989: putfield lv : I
/*    */     //   992: goto -> 1008
/*    */     //   995: aload #10
/*    */     //   997: dup
/*    */     //   998: iload #11
/*    */     //   1000: putfield dj0 : Z
/*    */     //   1003: iload #12
/*    */     //   1005: putfield NI0 : Z
/*    */     //   1008: aload_0
/*    */     //   1009: aload #10
/*    */     //   1011: aload #15
/*    */     //   1013: putfield yH : Lf/else;
/*    */     //   1016: getfield c5 : Z
/*    */     //   1019: ifeq -> 1034
/*    */     //   1022: iload #5
/*    */     //   1024: iconst_1
/*    */     //   1025: isub
/*    */     //   1026: iload #6
/*    */     //   1028: isub
/*    */     //   1029: istore #11
/*    */     //   1031: goto -> 1038
/*    */     //   1034: iload #6
/*    */     //   1036: istore #11
/*    */     //   1038: iload #7
/*    */     //   1040: iflt -> 1087
/*    */     //   1043: iload #7
/*    */     //   1045: aload #8
/*    */     //   1047: getfield zt0 : I
/*    */     //   1050: if_icmplt -> 1056
/*    */     //   1053: goto -> 1087
/*    */     //   1056: iload #11
/*    */     //   1058: iflt -> 1087
/*    */     //   1061: iload #11
/*    */     //   1063: aload #8
/*    */     //   1065: getfield mc0 : I
/*    */     //   1068: if_icmplt -> 1074
/*    */     //   1071: goto -> 1087
/*    */     //   1074: aload #8
/*    */     //   1076: getfield aT : [[Lf/H40;
/*    */     //   1079: iload #7
/*    */     //   1081: aaload
/*    */     //   1082: iload #11
/*    */     //   1084: aload #10
/*    */     //   1086: aastore
/*    */     //   1087: iinc #7, 1
/*    */     //   1090: goto -> 781
/*    */     //   1093: iinc #6, 1
/*    */     //   1096: goto -> 771
/*    */     //   1099: aload_3
/*    */     //   1100: ldc 'properties'
/*    */     //   1102: invokevirtual cE : (Ljava/lang/String;)Lf/Jp0;
/*    */     //   1105: dup
/*    */     //   1106: astore_0
/*    */     //   1107: ifnull -> 1119
/*    */     //   1110: aload #8
/*    */     //   1112: getfield HT : Lf/y9;
/*    */     //   1115: aload_0
/*    */     //   1116: invokestatic R3 : (Lf/y9;Lf/Jp0;)V
/*    */     //   1119: aload_2
/*    */     //   1120: getfield VD0 : Lf/fQ;
/*    */     //   1123: aload #8
/*    */     //   1125: invokevirtual Com3 : (Ljava/lang/Object;)V
/*    */     //   1128: goto -> 1619
/*    */     //   1131: new f/JU
/*    */     //   1134: dup
/*    */     //   1135: new java/lang/StringBuilder
/*    */     //   1138: dup
/*    */     //   1139: invokespecial <init> : ()V
/*    */     //   1142: ldc_w 'Unrecognised compression ('
/*    */     //   1145: invokevirtual append : (Ljava/lang/String;)Ljava/lang/StringBuilder;
/*    */     //   1148: aload #10
/*    */     //   1150: invokevirtual append : (Ljava/lang/String;)Ljava/lang/StringBuilder;
/*    */     //   1153: ldc_w ') for TMX Layer Data'
/*    */     //   1156: invokevirtual append : (Ljava/lang/String;)Ljava/lang/StringBuilder;
/*    */     //   1159: invokevirtual toString : ()Ljava/lang/String;
/*    */     //   1162: invokespecial <init> : (Ljava/lang/String;)V
/*    */     //   1165: athrow
/*    */     //   1166: astore_0
/*    */     //   1167: goto -> 1202
/*    */     //   1170: astore_0
/*    */     //   1171: new f/JU
/*    */     //   1174: dup
/*    */     //   1175: new java/lang/StringBuilder
/*    */     //   1178: dup
/*    */     //   1179: invokespecial <init> : ()V
/*    */     //   1182: ldc_w 'Error Reading TMX Layer Data - IOException: '
/*    */     //   1185: invokevirtual append : (Ljava/lang/String;)Ljava/lang/StringBuilder;
/*    */     //   1188: aload_0
/*    */     //   1189: invokevirtual getMessage : ()Ljava/lang/String;
/*    */     //   1192: invokevirtual append : (Ljava/lang/String;)Ljava/lang/StringBuilder;
/*    */     //   1195: invokevirtual toString : ()Ljava/lang/String;
/*    */     //   1198: invokespecial <init> : (Ljava/lang/String;)V
/*    */     //   1201: athrow
/*    */     //   1202: aload_0
/*    */     //   1203: aload #7
/*    */     //   1205: invokestatic JC0 : (Ljava/io/Closeable;)V
/*    */     //   1208: athrow
/*    */     //   1209: new f/JU
/*    */     //   1212: dup
/*    */     //   1213: ldc_w 'Unrecognised encoding ('
/*    */     //   1216: aload #7
/*    */     //   1218: ldc_w ') for TMX Layer Data'
/*    */     //   1221: invokestatic AT : (Ljava/lang/String;Ljava/lang/String;Ljava/lang/String;)Ljava/lang/String;
/*    */     //   1224: invokespecial <init> : (Ljava/lang/String;)V
/*    */     //   1227: athrow
/*    */     //   1228: new f/JU
/*    */     //   1231: dup
/*    */     //   1232: ldc_w 'Unsupported encoding (XML) for TMX Layer Data'
/*    */     //   1235: invokespecial <init> : (Ljava/lang/String;)V
/*    */     //   1238: athrow
/*    */     //   1239: aload #6
/*    */     //   1241: ldc_w 'objectgroup'
/*    */     //   1244: invokevirtual equals : (Ljava/lang/Object;)Z
/*    */     //   1247: ifeq -> 1366
/*    */     //   1250: aload_3
/*    */     //   1251: getfield Xh0 : Ljava/lang/String;
/*    */     //   1254: ldc_w 'objectgroup'
/*    */     //   1257: invokevirtual equals : (Ljava/lang/Object;)Z
/*    */     //   1260: ifeq -> 1619
/*    */     //   1263: aload_3
/*    */     //   1264: new f/ql0
/*    */     //   1267: dup
/*    */     //   1268: dup
/*    */     //   1269: astore #4
/*    */     //   1271: invokespecial <init> : ()V
/*    */     //   1274: aload_3
/*    */     //   1275: invokestatic Xw0 : (Lf/ql0;Lf/Jp0;)V
/*    */     //   1278: ldc 'properties'
/*    */     //   1280: invokevirtual cE : (Ljava/lang/String;)Lf/Jp0;
/*    */     //   1283: dup
/*    */     //   1284: astore #5
/*    */     //   1286: ifnull -> 1299
/*    */     //   1289: aload #4
/*    */     //   1291: getfield HT : Lf/y9;
/*    */     //   1294: aload #5
/*    */     //   1296: invokestatic R3 : (Lf/y9;Lf/Jp0;)V
/*    */     //   1299: aload_3
/*    */     //   1300: ldc_w 'object'
/*    */     //   1303: invokevirtual LG0 : (Ljava/lang/String;)Lf/fQ;
/*    */     //   1306: invokevirtual r30 : ()Lf/Hc0;
/*    */     //   1309: astore_3
/*    */     //   1310: aload_3
/*    */     //   1311: invokevirtual hasNext : ()Z
/*    */     //   1314: ifeq -> 1354
/*    */     //   1317: aload_0
/*    */     //   1318: aload_1
/*    */     //   1319: aload_0
/*    */     //   1320: aload #4
/*    */     //   1322: aload_3
/*    */     //   1323: invokevirtual next : ()Ljava/lang/Object;
/*    */     //   1326: checkcast f/Jp0
/*    */     //   1329: astore #5
/*    */     //   1331: getfield TM : Lf/GC;
/*    */     //   1334: astore #6
/*    */     //   1336: getfield Zg0 : I
/*    */     //   1339: i2f
/*    */     //   1340: fstore #7
/*    */     //   1342: aload #6
/*    */     //   1344: aload #5
/*    */     //   1346: fload #7
/*    */     //   1348: invokevirtual UX : (Lf/pB0;Lf/GC;Lf/Jp0;F)V
/*    */     //   1351: goto -> 1310
/*    */     //   1354: aload_2
/*    */     //   1355: getfield VD0 : Lf/fQ;
/*    */     //   1358: aload #4
/*    */     //   1360: invokevirtual Com3 : (Ljava/lang/Object;)V
/*    */     //   1363: goto -> 1619
/*    */     //   1366: aload #6
/*    */     //   1368: ldc_w 'imagelayer'
/*    */     //   1371: invokevirtual equals : (Ljava/lang/Object;)Z
/*    */     //   1374: ifeq -> 1619
/*    */     //   1377: aload_3
/*    */     //   1378: getfield Xh0 : Ljava/lang/String;
/*    */     //   1381: ldc_w 'imagelayer'
/*    */     //   1384: invokevirtual equals : (Ljava/lang/Object;)Z
/*    */     //   1387: ifeq -> 1619
/*    */     //   1390: aload_3
/*    */     //   1391: ldc 'offsetx'
/*    */     //   1393: astore_1
/*    */     //   1394: getfield CT : Lf/f7;
/*    */     //   1397: dup
/*    */     //   1398: astore #6
/*    */     //   1400: ifnonnull -> 1407
/*    */     //   1403: iconst_0
/*    */     //   1404: goto -> 1413
/*    */     //   1407: aload #6
/*    */     //   1409: aload_1
/*    */     //   1410: invokevirtual GB0 : (Ljava/lang/Object;)Z
/*    */     //   1413: ifeq -> 1432
/*    */     //   1416: aload_3
/*    */     //   1417: ldc 'offsetx'
/*    */     //   1419: ldc_w '0'
/*    */     //   1422: invokevirtual Wu : (Ljava/lang/String;Ljava/lang/String;)Ljava/lang/String;
/*    */     //   1425: invokestatic parseFloat : (Ljava/lang/String;)F
/*    */     //   1428: fstore_1
/*    */     //   1429: goto -> 1446
/*    */     //   1432: aload_3
/*    */     //   1433: ldc_w 'x'
/*    */     //   1436: ldc_w '0'
/*    */     //   1439: invokevirtual Wu : (Ljava/lang/String;Ljava/lang/String;)Ljava/lang/String;
/*    */     //   1442: invokestatic parseFloat : (Ljava/lang/String;)F
/*    */     //   1445: fstore_1
/*    */     //   1446: aload_3
/*    */     //   1447: ldc 'offsety'
/*    */     //   1449: astore #6
/*    */     //   1451: getfield CT : Lf/f7;
/*    */     //   1454: dup
/*    */     //   1455: astore #7
/*    */     //   1457: ifnonnull -> 1464
/*    */     //   1460: iconst_0
/*    */     //   1461: goto -> 1471
/*    */     //   1464: aload #7
/*    */     //   1466: aload #6
/*    */     //   1468: invokevirtual GB0 : (Ljava/lang/Object;)Z
/*    */     //   1471: ifeq -> 1491
/*    */     //   1474: aload_3
/*    */     //   1475: ldc 'offsety'
/*    */     //   1477: ldc_w '0'
/*    */     //   1480: invokevirtual Wu : (Ljava/lang/String;Ljava/lang/String;)Ljava/lang/String;
/*    */     //   1483: invokestatic parseFloat : (Ljava/lang/String;)F
/*    */     //   1486: fstore #6
/*    */     //   1488: goto -> 1506
/*    */     //   1491: aload_3
/*    */     //   1492: ldc_w 'y'
/*    */     //   1495: ldc_w '0'
/*    */     //   1498: invokevirtual Wu : (Ljava/lang/String;Ljava/lang/String;)Ljava/lang/String;
/*    */     //   1501: invokestatic parseFloat : (Ljava/lang/String;)F
/*    */     //   1504: fstore #6
/*    */     //   1506: aload_0
/*    */     //   1507: getfield c5 : Z
/*    */     //   1510: ifeq -> 1523
/*    */     //   1513: aload_0
/*    */     //   1514: getfield Zg0 : I
/*    */     //   1517: i2f
/*    */     //   1518: fload #6
/*    */     //   1520: fsub
/*    */     //   1521: fstore #6
/*    */     //   1523: aload_3
/*    */     //   1524: aconst_null
/*    */     //   1525: astore_0
/*    */     //   1526: ldc_w 'image'
/*    */     //   1529: invokevirtual cE : (Ljava/lang/String;)Lf/Jp0;
/*    */     //   1532: dup
/*    */     //   1533: astore #7
/*    */     //   1535: ifnull -> 1572
/*    */     //   1538: fload #6
/*    */     //   1540: aload #5
/*    */     //   1542: aload #4
/*    */     //   1544: aload #7
/*    */     //   1546: ldc_w 'source'
/*    */     //   1549: invokevirtual UI0 : (Ljava/lang/String;)Ljava/lang/String;
/*    */     //   1552: invokestatic Te0 : (Lf/RD0;Ljava/lang/String;)Lf/RD0;
/*    */     //   1555: invokevirtual rw : ()Ljava/lang/String;
/*    */     //   1558: invokeinterface l70 : (Ljava/lang/String;)Lf/pe0;
/*    */     //   1563: dup
/*    */     //   1564: astore_0
/*    */     //   1565: getfield Vn0 : I
/*    */     //   1568: i2f
/*    */     //   1569: fsub
/*    */     //   1570: fstore #6
/*    */     //   1572: aload_3
/*    */     //   1573: new f/Jv
/*    */     //   1576: dup
/*    */     //   1577: dup
/*    */     //   1578: astore #4
/*    */     //   1580: aload_0
/*    */     //   1581: fload_1
/*    */     //   1582: fload #6
/*    */     //   1584: invokespecial <init> : (Lf/pe0;FF)V
/*    */     //   1587: aload_3
/*    */     //   1588: invokestatic Xw0 : (Lf/ql0;Lf/Jp0;)V
/*    */     //   1591: ldc 'properties'
/*    */     //   1593: invokevirtual cE : (Ljava/lang/String;)Lf/Jp0;
/*    */     //   1596: dup
/*    */     //   1597: astore_0
/*    */     //   1598: ifnull -> 1610
/*    */     //   1601: aload #4
/*    */     //   1603: getfield HT : Lf/y9;
/*    */     //   1606: aload_0
/*    */     //   1607: invokestatic R3 : (Lf/y9;Lf/Jp0;)V
/*    */     //   1610: aload_2
/*    */     //   1611: getfield VD0 : Lf/fQ;
/*    */     //   1614: aload #4
/*    */     //   1616: invokevirtual Com3 : (Ljava/lang/Object;)V
/*    */     //   1619: return
/*    */     // Line number table:
/*    */     //   Java source line number -> byte code offset
/*    */     //   #1	-> 1
/*    */     //   #2	-> 7
/*    */     //   #3	-> 17
/*    */     //   #4	-> 20
/*    */     //   #5	-> 57
/*    */     //   #6	-> 62
/*    */     //   #7	-> 69
/*    */     //   #8	-> 99
/*    */     //   #9	-> 124
/*    */     //   #10	-> 133
/*    */     //   #11	-> 142
/*    */     //   #12	-> 146
/*    */     //   #13	-> 153
/*    */     //   #14	-> 168
/*    */     //   #15	-> 171
/*    */     //   #16	-> 174
/*    */     //   #17	-> 179
/*    */     //   #18	-> 202
/*    */     //   #19	-> 209
/*    */     //   #20	-> 213
/*    */     //   #21	-> 225
/*    */     //   #22	-> 230
/*    */     //   #23	-> 238
/*    */     //   #24	-> 248
/*    */     //   #25	-> 251
/*    */     //   #26	-> 281
/*    */     //   #27	-> 284
/*    */     //   #28	-> 287
/*    */     //   #29	-> 292
/*    */     //   #30	-> 300
/*    */     //   #31	-> 303
/*    */     //   #32	-> 306
/*    */     //   #33	-> 311
/*    */     //   #34	-> 342
/*    */     //   #35	-> 386
/*    */     //   #36	-> 389
/*    */     //   #37	-> 459
/*    */     //   #38	-> 462
/*    */     //   #39	-> 764
/*    */     //   #40	-> 798
/*    */     //   #41	-> 863
/*    */     //   #42	-> 866
/*    */     //   #43	-> 890
/*    */     //   #44	-> 895
/*    */     //   #45	-> 926
/*    */     //   #46	-> 951
/*    */     //   #47	-> 979
/*    */     //   #48	-> 989
/*    */     //   #49	-> 1000
/*    */     //   #50	-> 1005
/*    */     //   #51	-> 1013
/*    */     //   #52	-> 1016
/*    */     //   #53	-> 1047
/*    */     //   #54	-> 1100
/*    */     //   #55	-> 1112
/*    */     //   #56	-> 1116
/*    */     //   #57	-> 1120
/*    */     //   #58	-> 1125
/*    */     //   #59	-> 1131
/*    */     //   #60	-> 1213
/*    */     //   #61	-> 1224
/*    */     //   #62	-> 1241
/*    */     //   #63	-> 1251
/*    */     //   #64	-> 1254
/*    */     //   #65	-> 1291
/*    */     //   #66	-> 1296
/*    */     //   #67	-> 1331
/*    */     //   #68	-> 1336
/*    */     //   #69	-> 1355
/*    */     //   #70	-> 1360
/*    */     //   #71	-> 1368
/*    */     //   #72	-> 1378
/*    */     //   #73	-> 1381
/*    */     //   #74	-> 1394
/*    */     //   #75	-> 1417
/*    */     //   #76	-> 1451
/*    */     //   #77	-> 1475
/*    */     //   #78	-> 1565
/*    */     //   #79	-> 1573
/*    */     //   #80	-> 1603
/*    */     //   #81	-> 1607
/*    */     //   #82	-> 1611
/*    */     //   #83	-> 1616
/*    */     // Exception table:
/*    */     //   from	to	target	type
/*    */     //   447	454	1170	java/io/IOException
/*    */     //   447	454	1166	finally
/*    */     //   457	465	1170	java/io/IOException
/*    */     //   457	465	1166	finally
/*    */     //   470	473	1170	java/io/IOException
/*    */     //   470	473	1166	finally
/*    */     //   476	481	1170	java/io/IOException
/*    */     //   476	481	1166	finally
/*    */     //   488	496	1170	java/io/IOException
/*    */     //   488	496	1166	finally
/*    */     //   499	502	1170	java/io/IOException
/*    */     //   499	502	1166	finally
/*    */     //   505	508	1170	java/io/IOException
/*    */     //   505	508	1166	finally
/*    */     //   511	516	1170	java/io/IOException
/*    */     //   511	516	1166	finally
/*    */     //   519	547	1170	java/io/IOException
/*    */     //   519	547	1166	finally
/*    */     //   550	553	1170	java/io/IOException
/*    */     //   550	553	1166	finally
/*    */     //   556	559	1170	java/io/IOException
/*    */     //   556	559	1166	finally
/*    */     //   562	565	1170	java/io/IOException
/*    */     //   562	565	1166	finally
/*    */     //   568	586	1170	java/io/IOException
/*    */     //   568	586	1166	finally
/*    */     //   590	592	1170	java/io/IOException
/*    */     //   590	592	1166	finally
/*    */     //   614	621	1170	java/io/IOException
/*    */     //   614	621	1166	finally
/*    */     //   639	648	1170	java/io/IOException
/*    */     //   639	648	1166	finally
/*    */     //   689	691	1170	java/io/IOException
/*    */     //   689	691	1166	finally
/*    */     //   695	699	1170	java/io/IOException
/*    */     //   695	699	1166	finally
/*    */     //   707	711	1170	java/io/IOException
/*    */     //   707	711	1166	finally
/*    */     //   719	723	1170	java/io/IOException
/*    */     //   719	723	1166	finally
/*    */     //   731	735	1170	java/io/IOException
/*    */     //   731	735	1166	finally
/*    */     //   741	752	1170	java/io/IOException
/*    */     //   741	752	1166	finally
/*    */     //   1131	1166	1170	java/io/IOException
/*    */     //   1131	1166	1166	finally
/*    */     //   1171	1202	1166	finally
/*    */   }
/*    */   
/*    */   public final void UX(pB0 parampB0, GC paramGC, Jp0 paramJp0, float paramFloat) {
/*    */     // Byte code:
/*    */     //   0: aload_3
/*    */     //   1: getfield Xh0 : Ljava/lang/String;
/*    */     //   4: ldc_w 'object'
/*    */     //   7: invokevirtual equals : (Ljava/lang/Object;)Z
/*    */     //   10: ifeq -> 1026
/*    */     //   13: aload_0
/*    */     //   14: aload_3
/*    */     //   15: aconst_null
/*    */     //   16: astore #5
/*    */     //   18: fconst_1
/*    */     //   19: fstore #6
/*    */     //   21: fconst_1
/*    */     //   22: fstore #7
/*    */     //   24: ldc_w 'x'
/*    */     //   27: fconst_0
/*    */     //   28: invokevirtual r8 : (Ljava/lang/String;F)F
/*    */     //   31: fload #6
/*    */     //   33: fmul
/*    */     //   34: fstore #8
/*    */     //   36: getfield c5 : Z
/*    */     //   39: ifeq -> 56
/*    */     //   42: fload #4
/*    */     //   44: aload_3
/*    */     //   45: ldc_w 'y'
/*    */     //   48: fconst_0
/*    */     //   49: invokevirtual r8 : (Ljava/lang/String;F)F
/*    */     //   52: fsub
/*    */     //   53: goto -> 64
/*    */     //   56: aload_3
/*    */     //   57: ldc_w 'y'
/*    */     //   60: fconst_0
/*    */     //   61: invokevirtual r8 : (Ljava/lang/String;F)F
/*    */     //   64: fload #7
/*    */     //   66: fmul
/*    */     //   67: fstore #4
/*    */     //   69: aload_3
/*    */     //   70: dup
/*    */     //   71: dup
/*    */     //   72: ldc 'width'
/*    */     //   74: fconst_0
/*    */     //   75: invokevirtual r8 : (Ljava/lang/String;F)F
/*    */     //   78: fload #6
/*    */     //   80: fmul
/*    */     //   81: fstore #9
/*    */     //   83: ldc 'height'
/*    */     //   85: fconst_0
/*    */     //   86: invokevirtual r8 : (Ljava/lang/String;F)F
/*    */     //   89: fload #7
/*    */     //   91: fmul
/*    */     //   92: fstore #10
/*    */     //   94: getfield gu0 : Lf/fQ;
/*    */     //   97: dup
/*    */     //   98: astore #11
/*    */     //   100: ifnonnull -> 109
/*    */     //   103: iconst_0
/*    */     //   104: istore #11
/*    */     //   106: goto -> 116
/*    */     //   109: aload #11
/*    */     //   111: getfield Z8 : I
/*    */     //   114: istore #11
/*    */     //   116: iload #11
/*    */     //   118: ifle -> 480
/*    */     //   121: aload_3
/*    */     //   122: ldc_w 'polygon'
/*    */     //   125: invokevirtual cE : (Ljava/lang/String;)Lf/Jp0;
/*    */     //   128: dup
/*    */     //   129: astore #11
/*    */     //   131: ifnull -> 276
/*    */     //   134: aload #11
/*    */     //   136: ldc_w 'points'
/*    */     //   139: invokevirtual UI0 : (Ljava/lang/String;)Ljava/lang/String;
/*    */     //   142: ldc_w ' '
/*    */     //   145: invokevirtual split : (Ljava/lang/String;)[Ljava/lang/String;
/*    */     //   148: dup
/*    */     //   149: astore #5
/*    */     //   151: arraylength
/*    */     //   152: iconst_2
/*    */     //   153: imul
/*    */     //   154: newarray float
/*    */     //   156: astore #11
/*    */     //   158: iconst_0
/*    */     //   159: istore #12
/*    */     //   161: iload #12
/*    */     //   163: aload #5
/*    */     //   165: arraylength
/*    */     //   166: if_icmpge -> 247
/*    */     //   169: aload_0
/*    */     //   170: aload #5
/*    */     //   172: iload #12
/*    */     //   174: aaload
/*    */     //   175: ldc_w ','
/*    */     //   178: invokevirtual split : (Ljava/lang/String;)[Ljava/lang/String;
/*    */     //   181: dup
/*    */     //   182: aload #11
/*    */     //   184: swap
/*    */     //   185: iload #12
/*    */     //   187: iconst_2
/*    */     //   188: imul
/*    */     //   189: istore #13
/*    */     //   191: iconst_0
/*    */     //   192: aaload
/*    */     //   193: invokestatic parseFloat : (Ljava/lang/String;)F
/*    */     //   196: fload #6
/*    */     //   198: fmul
/*    */     //   199: iload #13
/*    */     //   201: swap
/*    */     //   202: fastore
/*    */     //   203: iinc #13, 1
/*    */     //   206: iconst_1
/*    */     //   207: aaload
/*    */     //   208: invokestatic parseFloat : (Ljava/lang/String;)F
/*    */     //   211: fload #7
/*    */     //   213: fmul
/*    */     //   214: fstore #14
/*    */     //   216: getfield c5 : Z
/*    */     //   219: ifeq -> 226
/*    */     //   222: iconst_m1
/*    */     //   223: goto -> 227
/*    */     //   226: iconst_1
/*    */     //   227: i2f
/*    */     //   228: fstore #15
/*    */     //   230: aload #11
/*    */     //   232: fload #14
/*    */     //   234: fload #15
/*    */     //   236: fmul
/*    */     //   237: iload #13
/*    */     //   239: swap
/*    */     //   240: fastore
/*    */     //   241: iinc #12, 1
/*    */     //   244: goto -> 161
/*    */     //   247: new f/tm0
/*    */     //   250: dup
/*    */     //   251: astore #5
/*    */     //   253: aload #11
/*    */     //   255: invokespecial <init> : ([F)V
/*    */     //   258: new f/m00
/*    */     //   261: dup
/*    */     //   262: astore #6
/*    */     //   264: aload #5
/*    */     //   266: invokespecial <init> : (Lf/tm0;)V
/*    */     //   269: aload #6
/*    */     //   271: astore #5
/*    */     //   273: goto -> 480
/*    */     //   276: aload_3
/*    */     //   277: ldc_w 'polyline'
/*    */     //   280: invokevirtual cE : (Ljava/lang/String;)Lf/Jp0;
/*    */     //   283: dup
/*    */     //   284: astore #11
/*    */     //   286: ifnull -> 431
/*    */     //   289: aload #11
/*    */     //   291: ldc_w 'points'
/*    */     //   294: invokevirtual UI0 : (Ljava/lang/String;)Ljava/lang/String;
/*    */     //   297: ldc_w ' '
/*    */     //   300: invokevirtual split : (Ljava/lang/String;)[Ljava/lang/String;
/*    */     //   303: dup
/*    */     //   304: astore #5
/*    */     //   306: arraylength
/*    */     //   307: iconst_2
/*    */     //   308: imul
/*    */     //   309: newarray float
/*    */     //   311: astore #11
/*    */     //   313: iconst_0
/*    */     //   314: istore #12
/*    */     //   316: iload #12
/*    */     //   318: aload #5
/*    */     //   320: arraylength
/*    */     //   321: if_icmpge -> 402
/*    */     //   324: aload_0
/*    */     //   325: aload #5
/*    */     //   327: iload #12
/*    */     //   329: aaload
/*    */     //   330: ldc_w ','
/*    */     //   333: invokevirtual split : (Ljava/lang/String;)[Ljava/lang/String;
/*    */     //   336: dup
/*    */     //   337: aload #11
/*    */     //   339: swap
/*    */     //   340: iload #12
/*    */     //   342: iconst_2
/*    */     //   343: imul
/*    */     //   344: istore #13
/*    */     //   346: iconst_0
/*    */     //   347: aaload
/*    */     //   348: invokestatic parseFloat : (Ljava/lang/String;)F
/*    */     //   351: fload #6
/*    */     //   353: fmul
/*    */     //   354: iload #13
/*    */     //   356: swap
/*    */     //   357: fastore
/*    */     //   358: iinc #13, 1
/*    */     //   361: iconst_1
/*    */     //   362: aaload
/*    */     //   363: invokestatic parseFloat : (Ljava/lang/String;)F
/*    */     //   366: fload #7
/*    */     //   368: fmul
/*    */     //   369: fstore #14
/*    */     //   371: getfield c5 : Z
/*    */     //   374: ifeq -> 381
/*    */     //   377: iconst_m1
/*    */     //   378: goto -> 382
/*    */     //   381: iconst_1
/*    */     //   382: i2f
/*    */     //   383: fstore #15
/*    */     //   385: aload #11
/*    */     //   387: fload #14
/*    */     //   389: fload #15
/*    */     //   391: fmul
/*    */     //   392: iload #13
/*    */     //   394: swap
/*    */     //   395: fastore
/*    */     //   396: iinc #12, 1
/*    */     //   399: goto -> 316
/*    */     //   402: new f/Bg
/*    */     //   405: dup
/*    */     //   406: astore #5
/*    */     //   408: aload #11
/*    */     //   410: invokespecial <init> : ([F)V
/*    */     //   413: new f/SQ
/*    */     //   416: dup
/*    */     //   417: astore #6
/*    */     //   419: aload #5
/*    */     //   421: invokespecial <init> : (Lf/Bg;)V
/*    */     //   424: aload #6
/*    */     //   426: astore #5
/*    */     //   428: goto -> 480
/*    */     //   431: aload_3
/*    */     //   432: ldc_w 'ellipse'
/*    */     //   435: invokevirtual cE : (Ljava/lang/String;)Lf/Jp0;
/*    */     //   438: ifnull -> 480
/*    */     //   441: aload_0
/*    */     //   442: new f/ie
/*    */     //   445: astore #5
/*    */     //   447: getfield c5 : Z
/*    */     //   450: ifeq -> 463
/*    */     //   453: fload #4
/*    */     //   455: fload #10
/*    */     //   457: fsub
/*    */     //   458: fstore #6
/*    */     //   460: goto -> 467
/*    */     //   463: fload #4
/*    */     //   465: fstore #6
/*    */     //   467: aload #5
/*    */     //   469: fload #8
/*    */     //   471: fload #6
/*    */     //   473: fload #9
/*    */     //   475: fload #10
/*    */     //   477: invokespecial <init> : (FFFF)V
/*    */     //   480: aload #5
/*    */     //   482: ifnonnull -> 732
/*    */     //   485: aload_3
/*    */     //   486: ldc_w 'gid'
/*    */     //   489: aconst_null
/*    */     //   490: invokevirtual Wu : (Ljava/lang/String;Ljava/lang/String;)Ljava/lang/String;
/*    */     //   493: dup
/*    */     //   494: astore #5
/*    */     //   496: ifnull -> 696
/*    */     //   499: aload #5
/*    */     //   501: invokestatic parseLong : (Ljava/lang/String;)J
/*    */     //   504: l2i
/*    */     //   505: dup
/*    */     //   506: istore #5
/*    */     //   508: ldc_w -2147483648
/*    */     //   511: iand
/*    */     //   512: ifeq -> 521
/*    */     //   515: iconst_1
/*    */     //   516: istore #6
/*    */     //   518: goto -> 524
/*    */     //   521: iconst_0
/*    */     //   522: istore #6
/*    */     //   524: iload #5
/*    */     //   526: ldc_w 1073741824
/*    */     //   529: iand
/*    */     //   530: ifeq -> 539
/*    */     //   533: iconst_1
/*    */     //   534: istore #7
/*    */     //   536: goto -> 542
/*    */     //   539: iconst_0
/*    */     //   540: istore #7
/*    */     //   542: iload #5
/*    */     //   544: aload_1
/*    */     //   545: getfield f8 : Lf/bR;
/*    */     //   548: astore_1
/*    */     //   549: ldc_w 536870911
/*    */     //   552: iand
/*    */     //   553: istore #11
/*    */     //   555: aload_1
/*    */     //   556: getfield GO : Lf/fQ;
/*    */     //   559: getfield Z8 : I
/*    */     //   562: iconst_1
/*    */     //   563: isub
/*    */     //   564: istore #12
/*    */     //   566: iload #12
/*    */     //   568: iflt -> 609
/*    */     //   571: aload_1
/*    */     //   572: getfield GO : Lf/fQ;
/*    */     //   575: iload #12
/*    */     //   577: invokevirtual get : (I)Ljava/lang/Object;
/*    */     //   580: checkcast f/tv
/*    */     //   583: getfield m0 : Lf/y10;
/*    */     //   586: iload #11
/*    */     //   588: invokevirtual get : (I)Ljava/lang/Object;
/*    */     //   591: checkcast f/else
/*    */     //   594: dup
/*    */     //   595: astore #13
/*    */     //   597: ifnull -> 603
/*    */     //   600: goto -> 612
/*    */     //   603: iinc #12, -1
/*    */     //   606: goto -> 566
/*    */     //   609: aconst_null
/*    */     //   610: astore #13
/*    */     //   612: aload_3
/*    */     //   613: dup
/*    */     //   614: dup
/*    */     //   615: iload #5
/*    */     //   617: new f/M40
/*    */     //   620: dup
/*    */     //   621: dup2
/*    */     //   622: astore #5
/*    */     //   624: aload #13
/*    */     //   626: iload #6
/*    */     //   628: iload #7
/*    */     //   630: invokespecial <init> : (Lf/else;ZZ)V
/*    */     //   633: getfield fx : Lf/pe0;
/*    */     //   636: astore_1
/*    */     //   637: getfield ip0 : Lf/y9;
/*    */     //   640: astore #6
/*    */     //   642: invokestatic valueOf : (I)Ljava/lang/Integer;
/*    */     //   645: astore #7
/*    */     //   647: aload_1
/*    */     //   648: aload #6
/*    */     //   650: getfield un : Lf/f7;
/*    */     //   653: ldc_w 'gid'
/*    */     //   656: aload #7
/*    */     //   658: invokevirtual X00 : (Ljava/lang/Object;Ljava/lang/Object;)Ljava/lang/Object;
/*    */     //   661: pop
/*    */     //   662: getfield H0 : I
/*    */     //   665: i2f
/*    */     //   666: ldc 'width'
/*    */     //   668: swap
/*    */     //   669: invokevirtual r8 : (Ljava/lang/String;F)F
/*    */     //   672: pop
/*    */     //   673: aload_1
/*    */     //   674: getfield Vn0 : I
/*    */     //   677: i2f
/*    */     //   678: ldc 'height'
/*    */     //   680: swap
/*    */     //   681: invokevirtual r8 : (Ljava/lang/String;F)F
/*    */     //   684: pop
/*    */     //   685: ldc_w 'rotation'
/*    */     //   688: fconst_0
/*    */     //   689: invokevirtual r8 : (Ljava/lang/String;F)F
/*    */     //   692: pop
/*    */     //   693: goto -> 732
/*    */     //   696: aload_0
/*    */     //   697: new f/Vo
/*    */     //   700: astore #5
/*    */     //   702: getfield c5 : Z
/*    */     //   705: ifeq -> 717
/*    */     //   708: fload #4
/*    */     //   710: fload #10
/*    */     //   712: fsub
/*    */     //   713: fstore_1
/*    */     //   714: goto -> 720
/*    */     //   717: fload #4
/*    */     //   719: fstore_1
/*    */     //   720: aload #5
/*    */     //   722: fload #8
/*    */     //   724: fload_1
/*    */     //   725: fload #9
/*    */     //   727: fload #10
/*    */     //   729: invokespecial <init> : (FFFF)V
/*    */     //   732: aload_3
/*    */     //   733: dup
/*    */     //   734: ldc 'name'
/*    */     //   736: aconst_null
/*    */     //   737: invokevirtual Wu : (Ljava/lang/String;Ljava/lang/String;)Ljava/lang/String;
/*    */     //   740: pop
/*    */     //   741: ldc_w 'rotation'
/*    */     //   744: aconst_null
/*    */     //   745: invokevirtual Wu : (Ljava/lang/String;Ljava/lang/String;)Ljava/lang/String;
/*    */     //   748: dup
/*    */     //   749: astore_1
/*    */     //   750: ifnull -> 777
/*    */     //   753: aload #5
/*    */     //   755: getfield ip0 : Lf/y9;
/*    */     //   758: aload_1
/*    */     //   759: invokestatic parseFloat : (Ljava/lang/String;)F
/*    */     //   762: invokestatic valueOf : (F)Ljava/lang/Float;
/*    */     //   765: astore_1
/*    */     //   766: getfield un : Lf/f7;
/*    */     //   769: ldc_w 'rotation'
/*    */     //   772: aload_1
/*    */     //   773: invokevirtual X00 : (Ljava/lang/Object;Ljava/lang/Object;)Ljava/lang/Object;
/*    */     //   776: pop
/*    */     //   777: aload_3
/*    */     //   778: ldc 'type'
/*    */     //   780: aconst_null
/*    */     //   781: invokevirtual Wu : (Ljava/lang/String;Ljava/lang/String;)Ljava/lang/String;
/*    */     //   784: dup
/*    */     //   785: astore_1
/*    */     //   786: ifnull -> 804
/*    */     //   789: aload #5
/*    */     //   791: getfield ip0 : Lf/y9;
/*    */     //   794: getfield un : Lf/f7;
/*    */     //   797: ldc 'type'
/*    */     //   799: aload_1
/*    */     //   800: invokevirtual X00 : (Ljava/lang/Object;Ljava/lang/Object;)Ljava/lang/Object;
/*    */     //   803: pop
/*    */     //   804: aload_3
/*    */     //   805: iconst_0
/*    */     //   806: ldc_w 'id'
/*    */     //   809: invokevirtual xT : (ILjava/lang/String;)I
/*    */     //   812: dup
/*    */     //   813: istore_1
/*    */     //   814: ifeq -> 842
/*    */     //   817: iload_1
/*    */     //   818: aload #5
/*    */     //   820: getfield ip0 : Lf/y9;
/*    */     //   823: astore_1
/*    */     //   824: invokestatic valueOf : (I)Ljava/lang/Integer;
/*    */     //   827: astore #6
/*    */     //   829: aload_1
/*    */     //   830: getfield un : Lf/f7;
/*    */     //   833: ldc_w 'id'
/*    */     //   836: aload #6
/*    */     //   838: invokevirtual X00 : (Ljava/lang/Object;Ljava/lang/Object;)Ljava/lang/Object;
/*    */     //   841: pop
/*    */     //   842: aload #5
/*    */     //   844: fload #8
/*    */     //   846: aload #5
/*    */     //   848: getfield ip0 : Lf/y9;
/*    */     //   851: astore_1
/*    */     //   852: invokestatic valueOf : (F)Ljava/lang/Float;
/*    */     //   855: astore #6
/*    */     //   857: aload_1
/*    */     //   858: getfield un : Lf/f7;
/*    */     //   861: ldc_w 'x'
/*    */     //   864: aload #6
/*    */     //   866: invokevirtual X00 : (Ljava/lang/Object;Ljava/lang/Object;)Ljava/lang/Object;
/*    */     //   869: pop
/*    */     //   870: instanceof f/M40
/*    */     //   873: ifeq -> 903
/*    */     //   876: fload #4
/*    */     //   878: aload #5
/*    */     //   880: getfield ip0 : Lf/y9;
/*    */     //   883: astore_0
/*    */     //   884: invokestatic valueOf : (F)Ljava/lang/Float;
/*    */     //   887: astore_1
/*    */     //   888: aload_0
/*    */     //   889: getfield un : Lf/f7;
/*    */     //   892: ldc_w 'y'
/*    */     //   895: aload_1
/*    */     //   896: invokevirtual X00 : (Ljava/lang/Object;Ljava/lang/Object;)Ljava/lang/Object;
/*    */     //   899: pop
/*    */     //   900: goto -> 943
/*    */     //   903: aload_0
/*    */     //   904: aload #5
/*    */     //   906: getfield ip0 : Lf/y9;
/*    */     //   909: astore_0
/*    */     //   910: ldc_w 'y'
/*    */     //   913: astore_1
/*    */     //   914: getfield c5 : Z
/*    */     //   917: ifeq -> 927
/*    */     //   920: fload #4
/*    */     //   922: fload #10
/*    */     //   924: fsub
/*    */     //   925: fstore #4
/*    */     //   927: aload_0
/*    */     //   928: fload #4
/*    */     //   930: invokestatic valueOf : (F)Ljava/lang/Float;
/*    */     //   933: astore_0
/*    */     //   934: getfield un : Lf/f7;
/*    */     //   937: aload_1
/*    */     //   938: aload_0
/*    */     //   939: invokevirtual X00 : (Ljava/lang/Object;Ljava/lang/Object;)Ljava/lang/Object;
/*    */     //   942: pop
/*    */     //   943: aload_3
/*    */     //   944: dup
/*    */     //   945: fload #10
/*    */     //   947: aload #5
/*    */     //   949: fload #9
/*    */     //   951: aload #5
/*    */     //   953: getfield ip0 : Lf/y9;
/*    */     //   956: astore_0
/*    */     //   957: invokestatic valueOf : (F)Ljava/lang/Float;
/*    */     //   960: astore_1
/*    */     //   961: aload_0
/*    */     //   962: getfield un : Lf/f7;
/*    */     //   965: ldc 'width'
/*    */     //   967: aload_1
/*    */     //   968: invokevirtual X00 : (Ljava/lang/Object;Ljava/lang/Object;)Ljava/lang/Object;
/*    */     //   971: pop
/*    */     //   972: getfield ip0 : Lf/y9;
/*    */     //   975: astore_0
/*    */     //   976: invokestatic valueOf : (F)Ljava/lang/Float;
/*    */     //   979: astore_1
/*    */     //   980: aload_0
/*    */     //   981: getfield un : Lf/f7;
/*    */     //   984: ldc 'height'
/*    */     //   986: aload_1
/*    */     //   987: invokevirtual X00 : (Ljava/lang/Object;Ljava/lang/Object;)Ljava/lang/Object;
/*    */     //   990: pop
/*    */     //   991: iconst_1
/*    */     //   992: ldc 'visible'
/*    */     //   994: invokevirtual xT : (ILjava/lang/String;)I
/*    */     //   997: pop
/*    */     //   998: ldc 'properties'
/*    */     //   1000: invokevirtual cE : (Ljava/lang/String;)Lf/Jp0;
/*    */     //   1003: dup
/*    */     //   1004: astore_0
/*    */     //   1005: ifnull -> 1017
/*    */     //   1008: aload #5
/*    */     //   1010: getfield ip0 : Lf/y9;
/*    */     //   1013: aload_0
/*    */     //   1014: invokestatic R3 : (Lf/y9;Lf/Jp0;)V
/*    */     //   1017: aload_2
/*    */     //   1018: getfield e80 : Lf/fQ;
/*    */     //   1021: aload #5
/*    */     //   1023: invokevirtual Com3 : (Ljava/lang/Object;)V
/*    */     //   1026: return
/*    */     // Line number table:
/*    */     //   Java source line number -> byte code offset
/*    */     //   #1	-> 1
/*    */     //   #2	-> 4
/*    */     //   #3	-> 94
/*    */     //   #4	-> 122
/*    */     //   #5	-> 545
/*    */     //   #6	-> 556
/*    */     //   #7	-> 559
/*    */     //   #8	-> 583
/*    */     //   #9	-> 588
/*    */     //   #10	-> 617
/*    */     //   #11	-> 633
/*    */     //   #12	-> 637
/*    */     //   #13	-> 642
/*    */     //   #14	-> 650
/*    */     //   #15	-> 653
/*    */     //   #16	-> 662
/*    */     //   #17	-> 666
/*    */     //   #18	-> 674
/*    */     //   #19	-> 678
/*    */     //   #20	-> 755
/*    */     //   #21	-> 759
/*    */     //   #22	-> 766
/*    */     //   #23	-> 769
/*    */     //   #24	-> 778
/*    */     //   #25	-> 791
/*    */     //   #26	-> 794
/*    */     //   #27	-> 797
/*    */     //   #28	-> 806
/*    */     //   #29	-> 820
/*    */     //   #30	-> 824
/*    */     //   #31	-> 830
/*    */     //   #32	-> 833
/*    */     //   #33	-> 848
/*    */     //   #34	-> 852
/*    */     //   #35	-> 858
/*    */     //   #36	-> 861
/*    */     //   #37	-> 870
/*    */     //   #38	-> 880
/*    */     //   #39	-> 884
/*    */     //   #40	-> 889
/*    */     //   #41	-> 892
/*    */     //   #42	-> 906
/*    */     //   #43	-> 910
/*    */     //   #44	-> 934
/*    */     //   #45	-> 939
/*    */     //   #46	-> 953
/*    */     //   #47	-> 957
/*    */     //   #48	-> 962
/*    */     //   #49	-> 965
/*    */     //   #50	-> 972
/*    */     //   #51	-> 976
/*    */     //   #52	-> 981
/*    */     //   #53	-> 984
/*    */     //   #54	-> 992
/*    */     //   #55	-> 1010
/*    */     //   #56	-> 1014
/*    */     //   #57	-> 1018
/*    */     //   #58	-> 1023
/*    */   }
/*    */   
/*    */   public abstract void Ne0(RD0 paramRD01, np paramnp, tv paramtv, fQ paramfQ, int paramInt1, int paramInt2, int paramInt3, int paramInt4, int paramInt5, String paramString1, int paramInt6, int paramInt7, String paramString2, int paramInt8, int paramInt9, RD0 paramRD02);
/*    */   
/*    */   public final fQ getDependencies(String paramString, RD0 paramRD0, wP paramwP) {
/*    */     this.n2 = this.cr0.g(paramRD0);
/*    */     super();
/*    */     Lv lv;
/*    */     if ((lv = (Lv)paramwP) != null) {
/*    */       ((kd0)paramwP).ER = false;
/*    */       ((kd0)paramwP).Ok0 = lv.Sp;
/*    */       ((kd0)paramwP).Xd0 = lv.j1;
/*    */     } 
/*    */     return Hf0(paramRD0, (kd0)paramwP);
/*    */   } }


/* Location:              /Users/vnnsnnt/Documents/Codespace/JavaWorkspace/RedTrainer/src/main/java/org/trainer/client/PokeMMO.jar!/f/kR.class
 * Java compiler version: 7 (51.0)
 * JD-Core Version:       1.1.3
 */