/*   1 */ package f;public final class Ld extends Wr { public final of yQ; public final Ip pp; public final ge0 N80; public final ge0 QA0; public static void C20(Object paramObject) { km.u4
/*     */ 
/*     */ 
/*     */       
/*   5 */       .lF(B40.df("//moveto2 ").append(((Ws0)(paramObject = paramObject)).he0.bO()).append(" ").append(((Ws0)paramObject).Ga).toString()); }
/*     */   public final ge0 bq0;
/*   7 */   public final ge0 GB; public final ge0 kh; public final ge0 I9; public Ld(h2 paramh2) { dQ dQ1; ge0 ge01; ge0 ge02; ge0 ge03; ge0 ge04; ge0 ge05; ge0 ge06; YA0 yA02; dQ dQ2; dQ dQ3; dQ dQ4; dQ dQ5; dQ dQ6; this(); this.N80 = new ge0(); this(); this.QA0 = new ge0(); this(); this.bq0 = new ge0(); this(); this.GB = new ge0(); this(); this.kh = new ge0(); this(); this.I9 = new ge0(); this(); EP(1); Xu("adminframe-nontab"); Lo("Search"); TG0(() -> paramh2.jf0(this)); this(); this.yQ = of1; of1.LE(); of of1; (of1 = new of()).JD0(paramInt -> tK0()); this("Search"); Un un; (un = new Un()).tW(this::tK0); this(); this.pp = ip; Ip ip; (new Ip()).rK0((ip = new Ip()).mE0()); (new Ip()).WN((new Ip()).d7()); ge01.zs(true); ge02.zs(true); ge03.zs(true); ge04.zs(false); ge05.zs(false); this("ITEMS"); this("MOVES"); this(Ml0.OH0(0)); this("MAPS"); this("DECO"); this("STRINGS"); ge01.tW(this::tK0); ge02.tW(this::tK0); ge03.tW(this::tK0); ge04.tW(this::tK0); ge05.tW(this::tK0); ge06.tW(this::tK0); ge06.zs(false); this(); rS rS; (rS = new rS()).Gz0(ip); this(); (new YA0()).sa0().sg(5.0F); sA.S7(ge01).fA0(this).Kw().zm0(); sA.S7(ge02).fA0(dQ2).Kw().zm0(); sA.S7(ge03).fA0(dQ3).Kw().zm0(); sA.S7(ge04).fA0(dQ4).Kw().zm0(); sA.S7(ge05).fA0(dQ5).Kw().zm0(); SA sA; (sA = (new YA0()).Dv0).S7(ge06).fA0(dQ6).Kw(); YA0 yA01; (yA01 = new YA0()).Dv0.cM().Xj0(5.0F); (yA01 = new YA0()).Dv0.F(45.0F); (yA01 = new YA0()).Dv0.to(5.0F); (yA01 = new YA0()).Dv0.Ty0(5.0F); (yA01 = new YA0()).Dv0.Ve0(5.0F); (yA01 = new YA0()).Dv0.S7(new JG0()).fA0(of1).K4().fA0(un).Ig0(150.0F).zm0(); (yA01 = new YA0()).Dv0.S7(yA02).fu().Xs0().fA0(rS).Yv(Integer.valueOf(2)).Ig0(530.0F).fJ(400.0F).sV(); J8(new YA0()); tK0(); } public static void U60(UD0 paramUD0) { Tx tx = paramUD0::Og0; this("Whats the level, please?", 3, tx); VH vH; (new VH()).Hl.Be0("100", false); pA.Dg0.J8(vH); UB0.Kg0.fN(vH::hy0); } public static void Og0(UD0 paramUD0, String paramString) { km.u4.lF(B40.df("//addmonster ").append(km.u4.Lz.tu).append(" ").append(paramUD0.AP).append(" ").append(paramString).toString()); } public static void Jl(WD paramWD) { Gp0 gp0; if ((gp0 = km.MR) != null) { LV lV; hm0 hm01 = gp0.N0((byte)0, (byte)0), hm02 = gp0.N0((byte)1, (byte)0); O5.AU.getClass(); O5.AU.xa(hm01, paramWD.HA).SK(hm02); this((byte)2, O5.AU.xa(hm01, paramWD.HA)); km.wI0.K7.LW
/*   8 */         .YP
/*   9 */         .add(lV); }  } public static void eV(WD paramWD) { Gp0 gp0; if ((gp0 = km.MR) != null) { LV lV; hm0 hm01 = gp0.N0((byte)1, (byte)0), hm02 = gp0.N0((byte)0, (byte)0); O5.AU.getClass(); O5.AU.xa(hm01, paramWD.HA).SK(hm02); this((byte)2, O5.AU.xa(hm01, paramWD.HA)); km.wI0.K7.LW.YP.add(lV); }  } public static void ls(WD paramWD) { Gp0 gp0; if ((gp0 = km.MR) != null) { LV lV; hm0 hm01 = gp0.N0((byte)0, (byte)0), hm02 = gp0.N0((byte)1, (byte)0); O5.AU.getClass(); O5.AU.xa(hm01, paramWD.HA).SK(hm02); this((byte)0, O5.AU.xa(hm01, paramWD.HA)); km.wI0.K7.LW.YP.add(lV); }  } public static void Zi(WD paramWD) { Gp0 gp0; if ((gp0 = km.MR) != null) { LV lV; hm0 hm01 = gp0.N0((byte)1, (byte)0), hm02 = gp0.N0((byte)0, (byte)0); O5.AU.getClass(); O5.AU.xa(hm01, paramWD.HA).SK(hm02); this((byte)0, O5.AU.xa(hm01, paramWD.HA)); km.wI0.K7.LW.YP.add(lV); }
/*     */      } public static void Ed0(LPT3 paramLPT3) { Tx tx; if (paramLPT3.ID0 > 1 && paramLPT3.Y8 != Hu0.Bm) {
/*     */       VH vH; tx = paramLPT3::t80; this("Heh, how much do you want, cheater?", 3, tx); (new VH()).Hl.Be0("100", false); pA.Dg0.J8(vH);
/*     */       UB0.Kg0.fN(vH::hy0);
/*     */     } else {
/*  14 */       km.u4.lF(B40.df("//createitem ").append(km.u4.Lz.tu).append(" ").append(((LPT3)tx).bj0).append(" 1").toString());
/*     */     }  } public static void t80(LPT3 paramLPT3, String paramString) { km.u4.lF(B40.df("//createitem ").append(km.u4.Lz.tu).append(" ").append(paramLPT3.bj0).append(" ").append(paramString).toString()); }
/*     */   public static Un f80(Object paramObject) { // Byte code:
/*     */     //   0: aload_0
/*     */     //   1: new f/Un
/*     */     //   4: dup
/*     */     //   5: astore_1
/*     */     //   6: ldc_w '▸▸'
/*     */     //   9: invokespecial <init> : (Ljava/lang/String;)V
/*     */     //   12: instanceof f/MZ
/*     */     //   15: ifeq -> 38
/*     */     //   18: aload_1
/*     */     //   19: aload_0
/*     */     //   20: checkcast f/MZ
/*     */     //   23: getfield fA0 : B
/*     */     //   26: aload_0
/*     */     //   27: <illegal opcode> run : (BLjava/lang/Object;)Ljava/lang/Runnable;
/*     */     //   32: invokevirtual tW : (Ljava/lang/Runnable;)V
/*     */     //   35: goto -> 55
/*     */     //   38: aload_0
/*     */     //   39: instanceof f/Ws0
/*     */     //   42: ifeq -> 55
/*     */     //   45: aload_1
/*     */     //   46: aload_0
/*     */     //   47: <illegal opcode> run : (Ljava/lang/Object;)Ljava/lang/Runnable;
/*     */     //   52: invokevirtual tW : (Ljava/lang/Runnable;)V
/*     */     //   55: aload_1
/*     */     //   56: dup
/*     */     //   57: ldc_w 'button-symbol'
/*     */     //   60: invokevirtual Xu : (Ljava/lang/String;)V
/*     */     //   63: areturn }
/*  17 */   public final void tK0() { this.pp.gx(); g0 g0 = Mr.X60(this.pp, this.pp); dQ dQ1 = P6.A("Type"); dQ dQ2 = P6.A("Region"); dQ dQ3 = P6.A("Id"); this(); String str; dQ4.E1("Name"); dQ1.Xu("hr-1"); dQ2.Xu("hr-1"); dQ3.Xu("hr-1"); dQ dQ4; (dQ4 = new dQ()).Xu("hr-5"); Ip ip; (ip = this.pp).getClass(); g0.ee0((new cr0(ip)).Ya(dQ1).Ya(dQ2).Ya(dQ3).Ya(dQ4)); cr0 cr0; (cr0 = V2.Ur(this.pp, this.pp)).ee0(Mr.X60(this.pp, this.pp).Mg(new JG0[] { dQ1, dQ2, dQ3, dQ4 })); int i = 0; 
/*  18 */     try { i = Integer.parseInt(str = LF.Ll0(this.yQ.F2.PH0.toString(), true)); } catch (NumberFormatException numberFormatException) {} if (this.N80
/*  19 */       .TG0
/*  20 */       .nm0())
/*     */     {
/*     */ 
/*     */       
/*  24 */       for (Iterator<LPT3> iterator = Of.eH.cOm7.values().iterator(); iterator.hasNext();)
/*     */       
/*     */       { 
/*  27 */         if (LF.qS(Ml0.OH0((lPT3 = iterator.next()).Iu), str) || lPT3
/*  28 */           .bj0 == i) { Fy0 fy0; ip = null;
/*  29 */           if (km.zg0(8)) { this("▶ ADD"); fy0
/*  30 */               .As
/*     */ 
/*     */ 
/*     */               
/*  34 */               .qt(new U70[] { wm0.y0.SJ0(lPT3.bj0, false) }); (fy0 = new Fy0()).tW(lPT3::Ed0); }
/*  35 */            byte b = lPT3.ux0;
/*     */ 
/*     */           
/*  38 */           String str1 = N.Gl0(new StringBuilder(), lPT3.bj0, "");
/*  39 */           String str2 = Ml0.OH0(lPT3.Iu);
/*  40 */           nR(g0, cr0, "Item", b, str1, str2, fy0); }  }  }  if (this.QA0
/*  41 */       .TG0
/*  42 */       .nm0())
/*  43 */       for (Iterator iterator = yk0.cw().jQ().iterator(); ((DA0)iterator).hasNext();)
/*     */       
/*     */       { 
/*  46 */         if (LF.qS(Ml0.OH0((wD = (WD)((Ke)iterator).q00()).iz), str) || wD
/*  47 */           .HA == i)
/*  48 */         { Un un; dQ dQ7, dQ5 = P6.A("MOVE");
/*  49 */           dQ dQ6 = P6.A("");
/*     */ 
/*     */           
/*  52 */           String str1 = N.Gl0(new StringBuilder(), wD.HA, "");
/*  53 */           this(); (new dQ()).E1(str1);
/*     */           
/*  55 */           String str2 = Ml0.OH0(wD.iz);
/*  56 */           this(); dQ8.E1(str2);
/*  57 */           dQ5.Xu("tr-1"); dQ6.Xu("tr-1"); dQ7.Xu("tr-1"); dQ8.Xu("tr-2"); dQ dQ8;
/*  58 */           (dQ8 = new dQ()).z4 = w50.I6(wD, null); (new dQ()).zn();
/*  59 */           if (O5.AU
/*  60 */             .yG0
/*     */             
/*  62 */             .Fb(wD.HA))
/*  63 */           { this("▸"); un.Xu("button-symbol"); this("◂"); un1.Xu("button-symbol"); un
/*  64 */               .z4 = "Plays the battle animation where player is caster and enemy is target."; un.zn();
/*  65 */             un.jl = 120;
/*  66 */             un1.z4 = "Plays the battle animation where enemy is caster and player is target."; un1.zn();
/*  67 */             un1.jl = 120; Un un1;
/*  68 */             (un1 = new Un()).tW(wD::Zi); (un = new Un()).tW(wD::ls); this("▸"); un2.Xu("button-symbol"); this("◂"); un3.Xu("button-symbol"); Un un3; (un3 = new Un()).tW(wD::eV); Un un2; (un2 = new Un()).tW(wD::Jl);
/*     */             
/*  70 */             U90 u90 = V2.Ur(this.pp, this.pp).Mg(new JG0[] { dQ5, un, un1, un2, un3, dQ7, dQ8 });
/*     */             
/*  72 */             u90 = Mr.X60(this.pp, this.pp).Mg(new JG0[] { dQ5, un, un1, un2, un3, dQ7, dQ8 }); g0.ee0(u90); cr0.ee0(u90); continue; }  g0
/*     */             
/*  74 */             .ee0(V2.Ur(this.pp, this.pp).Mg(new JG0[] { dQ5, un, dQ7, dQ8 }));
/*     */           
/*  76 */           cr0.ee0(Mr.X60(this.pp, this.pp).Mg(new JG0[] { dQ5, un, dQ7, dQ8 })); }  }   if (this.bq0
/*  77 */       .TG0
/*  78 */       .nm0())
/*     */     {
/*     */ 
/*     */       
/*  82 */       for (Iterator<UD0> iterator = (On.v30()).iI0.values().iterator(); iterator.hasNext();) { if (LF.qS((uD0 = iterator.next()).o60(true), str) || uD0
/*  83 */           .AP == i) { Fy0 fy0; ip = null;
/*  84 */           if (km.zg0(8)) { this("▶ ADD"); (fy0 = new Fy0()).tW(uD0::U60); }  String str2 = Ml0.OH0(0);
/*     */           
/*  86 */           String str1 = N.Gl0(new StringBuilder(), uD0.AP, "");
/*  87 */           String str3 = uD0.o60(true); nR(g0, cr0, str2, -1, str1, str3, fy0); }  }  }  if (this.GB
/*  88 */       .TG0
/*  89 */       .nm0())
/*     */     
/*  91 */     { for (Iterator<MZ> iterator = fV.Ca.KF().iterator(); iterator.hasNext();) { if (LF.qS((mZ = iterator.next()).iL0(), str)) { byte b = mZ.fA0; this(); int j = mZ.CoN; StringBuilder stringBuilder; String str1 = (stringBuilder = new StringBuilder()).append(mZ.fA0 * 50 + j).append(".").append(mZ.N0).toString(), str2 = mZ.iL0(); Un un = f80(mZ); nR(g0, cr0, "MAP", b, str1, str2, un); }  }  gD gD; if ((gD = km.mI0.MT) != null)
/*     */       { iy0[] arrayOfIy0; int j;
/*     */         byte b;
/*  94 */         for (j = (arrayOfIy0 = (iy0[])gD.y7.Z6).length, b = 0; b < j; ) { iy0 iy0; if (LF.qS((iy0 = arrayOfIy0[b]).Lr(), str)) { km.mI0.MT.getClass();
/*  95 */             String str1 = N.Gl0(new StringBuilder(), iy0.Ga, "");
/*  96 */             String str2 = iy0.Lr(); Un un = f80(iy0); nR(g0, cr0, "MAP", 3, str1, str2, un); }  b++; }  }  Wo wo; if ((wo = km.mI0.AN) != null)
/*     */       { gb[] arrayOfGb; int j;
/*     */         byte b;
/*  99 */         for (j = (arrayOfGb = (gb[])wo.YP.Z6).length, b = 0; b < j; ) { gb gb; if (LF.qS((gb = arrayOfGb[b]).Lr(), str)) { km.mI0.AN.getClass();
/* 100 */             String str1 = N.Gl0(new StringBuilder(), gb.Ga, "");
/* 101 */             String str2 = gb.Lr(); Un un = f80(gb); nR(g0, cr0, "MAP", 2, str1, str2, un); }  b++; }  }  BE bE; if ((bE = km.mI0.yE) != null)
/*     */       { iy0[] arrayOfIy0; int j;
/*     */         byte b;
/* 104 */         for (j = (arrayOfIy0 = (iy0[])bE.qN.Z6).length, b = 0; b < j; ) { iy0 iy0; if (LF.qS((iy0 = arrayOfIy0[b]).Lr(), str)) { km.mI0.yE.getClass();
/* 105 */             String str1 = N.Gl0(new StringBuilder(), iy0.Ga, "");
/* 106 */             String str2 = iy0.Lr(); Un un = f80(iy0); nR(g0, cr0, "MAP", 4, str1, str2, un); }  b++; }  }  }  if (this.kh
/* 107 */       .TG0
/* 108 */       .nm0())
/*     */     {
/*     */ 
/*     */       
/* 112 */       for (Iterator<lj0> iterator = HQ.Z90.gr.values().iterator(); iterator.hasNext();) { if (LF.qS((lj0 = iterator.next()).s60(), str))
/*     */         
/* 114 */         { String str1 = N.Gl0(new StringBuilder(), lj0.Pu0, "");
/* 115 */           String str2 = lj0.s60();
/* 116 */           nR(g0, cr0, "DECO", 1, str1, str2, null); }  }
/* 117 */        }  if (this.I9
/* 118 */       .TG0
/* 119 */       .nm0())
/*     */     { int[] arrayOfInt;
/* 121 */       Arrays.sort(arrayOfInt = Arrays.copyOf(Ml0.nW.YJ0(), (Ml0.nW.YJ0()).length)); int j; byte b; for (j = (Arrays.copyOf(Ml0.nW.YJ0(), (Ml0.nW.YJ0()).length)).length, b = 0; b < j; ) { int k = arrayOfInt[b]; String str1;
/* 122 */         if ((str1 = (String)Ml0.nW.Z6(k)) == null)
/* 123 */           str1 = XD0.SD0("STRING_", k); 
/* 124 */         if (LF.qS(str1, str) || k == i) { String str2 = k + "";
/* 125 */           nR(g0, cr0, "STRING", -1, str2, str1, null); }  b++; }  }  this
/* 126 */       .pp.rK0(g0); this.pp.WN(cr0); }
/*     */ 
/*     */   
/*     */   public final void nR(g0 paramg0, cr0 paramcr0, String paramString1, int paramInt, String paramString2, String paramString3, Un paramUn) {
/*     */     dQ dQ1 = P6.A(paramString1);
/*     */     dQ dQ4 = P6.A("");
/*     */     if (paramInt != -1) {
/*     */       if (paramInt != 10) {
/*     */         dQ4.E1(Mk0.zd((byte)paramInt));
/*     */       } else {
/*     */         dQ4.E1("Custom");
/*     */       } 
/*     */     } else {
/*     */       dQ4.E1("--");
/*     */     } 
/*     */     dQ dQ2 = P6.A(paramString2);
/*     */     dQ dQ3 = P6.A(paramString3);
/*     */     if (paramString3.length() > 40 && !paramString3.contains("\n")) {
/*     */       dQ3.z4 = paramString3.replace("|br|", "\n");
/*     */       dQ3.zn();
/*     */       dQ3.jl = 200;
/*     */       dQ3.E1(paramString3.substring(0, 40) + " ...");
/*     */     } 
/*     */     dQ1.Xu("tr-1");
/*     */     dQ4.Xu("tr-1");
/*     */     dQ2.Xu("tr-1");
/*     */     dQ3.Xu("tr-4");
/*     */     if (paramUn != null) {
/*     */       paramg0.ee0(V2.Ur(this.pp, this.pp).Mg(new JG0[] { dQ1, dQ4, dQ2, paramUn }).lW(et.Lp, dQ3));
/*     */       paramcr0.ee0(Mr.X60(this.pp, this.pp).Mg(new JG0[] { dQ1, dQ4, dQ2, paramUn, dQ3 }));
/*     */     } else {
/*     */       paramg0.ee0(V2.Ur(this.pp, this.pp).Mg(new JG0[] { dQ1, dQ4, dQ2, dQ3 }));
/*     */       paramcr0.ee0(Mr.X60(this.pp, this.pp).Mg(new JG0[] { dQ1, dQ4, dQ2, dQ3 }));
/*     */     } 
/*     */   } }


/* Location:              /Users/vnnsnnt/Documents/Codespace/JavaWorkspace/RedTrainer/src/main/java/org/trainer/client/PokeMMO.jar!/f/Ld.class
 * Java compiler version: 8 (52.0)
 * JD-Core Version:       1.1.3
 */