/*   */ package f;
/*   */ public final class ld0 extends Qa0 { public final Ip O60; public final Un vs0;
/* 3 */   private void dA0(short paramShort) { String str1 = this.kG.F2.PH0.toString();
/* 4 */     String str2 = "";
/* 5 */     km.u4.e20
/* 6 */       .W3(new zQ(paramShort, this, str2, false)); } public final of kG; public ld0(pA parampA, boolean paramBoolean, short paramShort) { // Byte code:
/*   */     //   0: iload_2
/*   */     //   1: aload_0
/*   */     //   2: dup
/*   */     //   3: iconst_0
/*   */     //   4: iconst_0
/*   */     //   5: invokespecial <init> : (ZZ)V
/*   */     //   8: ldc 'confirm-widget'
/*   */     //   10: invokevirtual Xu : (Ljava/lang/String;)V
/*   */     //   13: new f/Ip
/*   */     //   16: dup
/*   */     //   17: astore_2
/*   */     //   18: aload_0
/*   */     //   19: aload_2
/*   */     //   20: dup
/*   */     //   21: invokespecial <init> : ()V
/*   */     //   24: putfield O60 : Lf/Ip;
/*   */     //   27: ldc 'confirm-panel'
/*   */     //   29: invokevirtual Xu : (Ljava/lang/String;)V
/*   */     //   32: new f/dQ
/*   */     //   35: dup
/*   */     //   36: astore #4
/*   */     //   38: ldc 100002
/*   */     //   40: invokestatic OH0 : (I)Ljava/lang/String;
/*   */     //   43: invokespecial <init> : (Ljava/lang/String;)V
/*   */     //   46: new f/of
/*   */     //   49: dup
/*   */     //   50: astore #5
/*   */     //   52: aload #4
/*   */     //   54: aload #5
/*   */     //   56: aload_0
/*   */     //   57: aload #5
/*   */     //   59: dup
/*   */     //   60: invokespecial <init> : ()V
/*   */     //   63: putfield kG : Lf/of;
/*   */     //   66: invokevirtual LE : ()V
/*   */     //   69: invokevirtual Xy : ()Ljava/lang/String;
/*   */     //   72: pop
/*   */     //   73: bipush #16
/*   */     //   75: invokevirtual co : (I)V
/*   */     //   78: new f/dQ
/*   */     //   81: dup
/*   */     //   82: astore #6
/*   */     //   84: sipush #1053
/*   */     //   87: invokestatic OH0 : (I)Ljava/lang/String;
/*   */     //   90: invokespecial <init> : (Ljava/lang/String;)V
/*   */     //   93: ifeq -> 131
/*   */     //   96: new f/Un
/*   */     //   99: dup
/*   */     //   100: astore #7
/*   */     //   102: aload_0
/*   */     //   103: iload_3
/*   */     //   104: aload_0
/*   */     //   105: aload #7
/*   */     //   107: dup
/*   */     //   108: sipush #2991
/*   */     //   111: invokestatic OH0 : (I)Ljava/lang/String;
/*   */     //   114: invokespecial <init> : (Ljava/lang/String;)V
/*   */     //   117: putfield vs0 : Lf/Un;
/*   */     //   120: <illegal opcode> run : (Lf/ld0;S)Ljava/lang/Runnable;
/*   */     //   125: invokevirtual tW : (Ljava/lang/Runnable;)V
/*   */     //   128: goto -> 163
/*   */     //   131: new f/Un
/*   */     //   134: dup
/*   */     //   135: astore #7
/*   */     //   137: aload_0
/*   */     //   138: aload_1
/*   */     //   139: aload_0
/*   */     //   140: aload #7
/*   */     //   142: dup
/*   */     //   143: bipush #52
/*   */     //   145: invokestatic OH0 : (I)Ljava/lang/String;
/*   */     //   148: invokespecial <init> : (Ljava/lang/String;)V
/*   */     //   151: putfield vs0 : Lf/Un;
/*   */     //   154: iload_3
/*   */     //   155: <illegal opcode> run : (Lf/ld0;Lf/pA;S)Ljava/lang/Runnable;
/*   */     //   160: invokevirtual tW : (Ljava/lang/Runnable;)V
/*   */     //   163: aload_0
/*   */     //   164: aload_2
/*   */     //   165: dup
/*   */     //   166: dup
/*   */     //   167: dup2
/*   */     //   168: new f/Un
/*   */     //   171: dup
/*   */     //   172: astore_3
/*   */     //   173: aload_1
/*   */     //   174: dup
/*   */     //   175: aload_3
/*   */     //   176: bipush #53
/*   */     //   178: invokestatic OH0 : (I)Ljava/lang/String;
/*   */     //   181: invokespecial <init> : (Ljava/lang/String;)V
/*   */     //   184: invokevirtual getClass : ()Ljava/lang/Class;
/*   */     //   187: pop
/*   */     //   188: <illegal opcode> run : (Lf/pA;)Ljava/lang/Runnable;
/*   */     //   193: invokevirtual tW : (Ljava/lang/Runnable;)V
/*   */     //   196: invokevirtual d7 : ()Lf/cr0;
/*   */     //   199: aload #4
/*   */     //   201: invokevirtual Ya : (Lf/JG0;)Lf/U90;
/*   */     //   204: aload_2
/*   */     //   205: invokevirtual mE0 : ()Lf/g0;
/*   */     //   208: iconst_2
/*   */     //   209: anewarray f/JG0
/*   */     //   212: dup
/*   */     //   213: dup
/*   */     //   214: iconst_0
/*   */     //   215: aload #6
/*   */     //   217: aastore
/*   */     //   218: iconst_1
/*   */     //   219: aload #5
/*   */     //   221: aastore
/*   */     //   222: invokevirtual Mg : ([Lf/JG0;)Lf/U90;
/*   */     //   225: invokevirtual ee0 : (Lf/U90;)Lf/U90;
/*   */     //   228: aload_2
/*   */     //   229: invokevirtual d7 : ()Lf/cr0;
/*   */     //   232: iconst_2
/*   */     //   233: anewarray f/JG0
/*   */     //   236: dup
/*   */     //   237: dup
/*   */     //   238: aload_0
/*   */     //   239: getfield vs0 : Lf/Un;
/*   */     //   242: iconst_0
/*   */     //   243: swap
/*   */     //   244: aastore
/*   */     //   245: iconst_1
/*   */     //   246: aload_3
/*   */     //   247: aastore
/*   */     //   248: invokevirtual Mg : ([Lf/JG0;)Lf/U90;
/*   */     //   251: invokevirtual ee0 : (Lf/U90;)Lf/U90;
/*   */     //   254: invokevirtual Em0 : ()Lf/U90;
/*   */     //   257: invokevirtual WN : (Lf/U90;)V
/*   */     //   260: invokevirtual mE0 : ()Lf/g0;
/*   */     //   263: aload #4
/*   */     //   265: invokevirtual Ya : (Lf/JG0;)Lf/U90;
/*   */     //   268: aload_2
/*   */     //   269: invokevirtual d7 : ()Lf/cr0;
/*   */     //   272: iconst_2
/*   */     //   273: anewarray f/JG0
/*   */     //   276: dup
/*   */     //   277: dup
/*   */     //   278: iconst_0
/*   */     //   279: aload #6
/*   */     //   281: aastore
/*   */     //   282: iconst_1
/*   */     //   283: aload #5
/*   */     //   285: aastore
/*   */     //   286: invokevirtual Mg : ([Lf/JG0;)Lf/U90;
/*   */     //   289: invokevirtual ee0 : (Lf/U90;)Lf/U90;
/*   */     //   292: aload_2
/*   */     //   293: invokevirtual mE0 : ()Lf/g0;
/*   */     //   296: aload_0
/*   */     //   297: getfield vs0 : Lf/Un;
/*   */     //   300: invokevirtual Ya : (Lf/JG0;)Lf/U90;
/*   */     //   303: aload_3
/*   */     //   304: invokevirtual Ya : (Lf/JG0;)Lf/U90;
/*   */     //   307: invokevirtual ee0 : (Lf/U90;)Lf/U90;
/*   */     //   310: invokevirtual rK0 : (Lf/U90;)V
/*   */     //   313: invokevirtual J8 : (Lf/JG0;)V
/*   */     //   316: return } private void Rz(pA parampA, short paramShort) { // Byte code:
/*   */     //   0: aload_1
/*   */     //   1: invokevirtual Sc : ()V
/*   */     //   4: getstatic f/js.vu0 : Lf/js;
/*   */     //   7: new f/h70
/*   */     //   10: dup
/*   */     //   11: aload_0
/*   */     //   12: iload_2
/*   */     //   13: ldc 100004
/*   */     //   15: aload_0
/*   */     //   16: getfield kG : Lf/of;
/*   */     //   19: getfield F2 : Lf/ak0;
/*   */     //   22: invokevirtual toString : ()Ljava/lang/String;
/*   */     //   25: invokestatic Go : (ILjava/lang/String;)Ljava/lang/String;
/*   */     //   28: astore_1
/*   */     //   29: <illegal opcode> run : (Lf/ld0;S)Ljava/lang/Runnable;
/*   */     //   34: aload_1
/*   */     //   35: swap
/*   */     //   36: aload_0
/*   */     //   37: invokespecial <init> : (Ljava/lang/String;Ljava/lang/Runnable;Lf/JG0;)V
/*   */     //   40: invokevirtual uh : (Lf/h70;)V
/*   */     //   43: return
/*   */     // Line number table:
/*   */     //   Java source line number -> byte code offset
/*   */     //   #1	-> 4
/*   */     //   #2	-> 7
/*   */     //   #3	-> 19
/*   */     //   #4	-> 22
/* 6 */     //   #5	-> 25 } private void O20(short paramShort) { String str1 = this.kG.F2.PH0.toString(); String str2 = ""; km.u4.e20.W3(new zQ(paramShort, this, str2, true)); }
/*   */ 
/*   */   
/*   */   public final void LM(throws paramthrows) {
/*   */     super.LM(paramthrows);
/*   */     VA0.c90(this.kG);
/*   */   }
/*   */   
/*   */   public final void d40() {
/*   */     super.d40();
/*   */     this.O60.mM();
/*   */     QI();
/*   */     this.O60.js0(et.Wi0);
/*   */   } }


/* Location:              /Users/vnnsnnt/Documents/Codespace/JavaWorkspace/RedTrainer/src/main/java/org/trainer/client/PokeMMO.jar!/f/ld0.class
 * Java compiler version: 8 (52.0)
 * JD-Core Version:       1.1.3
 */