package f;

public final class lr0 implements con {
  public final void ng(Object paramObject, int paramInt, float[] paramArrayOffloat) {
    // Byte code:
    //   0: iload_2
    //   1: aload_1
    //   2: checkcast f/Ui0
    //   5: astore_0
    //   6: tableswitch default -> 52, 1 -> 187, 2 -> 177, 3 -> 160, 4 -> 134, 5 -> 107, 6 -> 81, 7 -> 71, 8 -> 61
    //   52: getstatic f/lr0.QA0 : Z
    //   55: ifeq -> 195
    //   58: goto -> 194
    //   61: aload_0
    //   62: aload_3
    //   63: iconst_0
    //   64: faload
    //   65: invokevirtual t : (F)V
    //   68: goto -> 194
    //   71: aload_0
    //   72: aload_3
    //   73: iconst_0
    //   74: faload
    //   75: invokevirtual yc : (F)V
    //   78: goto -> 194
    //   81: aload_0
    //   82: dup
    //   83: dup
    //   84: aload_3
    //   85: dup
    //   86: iconst_0
    //   87: faload
    //   88: fstore_0
    //   89: iconst_1
    //   90: faload
    //   91: fstore_1
    //   92: fload_0
    //   93: putfield c30 : F
    //   96: fload_1
    //   97: putfield ch0 : F
    //   100: iconst_1
    //   101: putfield eL : Z
    //   104: goto -> 194
    //   107: aload_0
    //   108: dup
    //   109: dup
    //   110: aload_3
    //   111: aload_0
    //   112: getfield c30 : F
    //   115: fstore_0
    //   116: iconst_0
    //   117: faload
    //   118: fstore_1
    //   119: fload_0
    //   120: putfield c30 : F
    //   123: fload_1
    //   124: putfield ch0 : F
    //   127: iconst_1
    //   128: putfield eL : Z
    //   131: goto -> 194
    //   134: aload_0
    //   135: dup
    //   136: dup2
    //   137: aload_3
    //   138: iconst_0
    //   139: faload
    //   140: fstore_0
    //   141: getfield ch0 : F
    //   144: fstore_1
    //   145: fload_0
    //   146: putfield c30 : F
    //   149: fload_1
    //   150: putfield ch0 : F
    //   153: iconst_1
    //   154: putfield eL : Z
    //   157: goto -> 194
    //   160: aload_0
    //   161: aload_3
    //   162: aload_0
    //   163: aload_3
    //   164: iconst_0
    //   165: faload
    //   166: invokevirtual aR : (F)V
    //   169: iconst_1
    //   170: faload
    //   171: invokevirtual Zq0 : (F)V
    //   174: goto -> 194
    //   177: aload_0
    //   178: aload_3
    //   179: iconst_0
    //   180: faload
    //   181: invokevirtual Zq0 : (F)V
    //   184: goto -> 194
    //   187: aload_0
    //   188: aload_3
    //   189: iconst_0
    //   190: faload
    //   191: invokevirtual aR : (F)V
    //   194: return
    //   195: new java/lang/AssertionError
    //   198: dup
    //   199: invokespecial <init> : ()V
    //   202: athrow
    // Line number table:
    //   Java source line number -> byte code offset
    //   #1	-> 52
    //   #2	-> 93
    //   #3	-> 97
    //   #4	-> 112
    //   #5	-> 117
    //   #6	-> 120
    //   #7	-> 139
    //   #8	-> 141
    //   #9	-> 146
    //   #10	-> 165
  }
  
  public final int Uu0(Object paramObject, int paramInt, float[] paramArrayOffloat) {
    // Byte code:
    //   0: iload_2
    //   1: aload_1
    //   2: checkcast f/Ui0
    //   5: astore_0
    //   6: tableswitch default -> 52, 1 -> 173, 2 -> 160, 3 -> 139, 4 -> 126, 5 -> 113, 6 -> 92, 7 -> 79, 8 -> 63
    //   52: getstatic f/lr0.QA0 : Z
    //   55: ifeq -> 185
    //   58: iconst_0
    //   59: istore_0
    //   60: goto -> 183
    //   63: aload_3
    //   64: aload_0
    //   65: getfield Kd0 : Lcom/badlogic/gdx/graphics/Color;
    //   68: getfield a : F
    //   71: iconst_0
    //   72: swap
    //   73: fastore
    //   74: iconst_1
    //   75: istore_0
    //   76: goto -> 183
    //   79: aload_3
    //   80: aload_0
    //   81: getfield FM : F
    //   84: iconst_0
    //   85: swap
    //   86: fastore
    //   87: iconst_1
    //   88: istore_0
    //   89: goto -> 183
    //   92: aload_3
    //   93: aload_0
    //   94: aload_3
    //   95: aload_0
    //   96: getfield c30 : F
    //   99: iconst_0
    //   100: swap
    //   101: fastore
    //   102: getfield ch0 : F
    //   105: iconst_1
    //   106: swap
    //   107: fastore
    //   108: iconst_2
    //   109: istore_0
    //   110: goto -> 183
    //   113: aload_3
    //   114: aload_0
    //   115: getfield ch0 : F
    //   118: iconst_0
    //   119: swap
    //   120: fastore
    //   121: iconst_1
    //   122: istore_0
    //   123: goto -> 183
    //   126: aload_3
    //   127: aload_0
    //   128: getfield c30 : F
    //   131: iconst_0
    //   132: swap
    //   133: fastore
    //   134: iconst_1
    //   135: istore_0
    //   136: goto -> 183
    //   139: aload_3
    //   140: aload_0
    //   141: aload_3
    //   142: aload_0
    //   143: invokevirtual Vw : ()F
    //   146: iconst_0
    //   147: swap
    //   148: fastore
    //   149: invokevirtual UT : ()F
    //   152: iconst_1
    //   153: swap
    //   154: fastore
    //   155: iconst_2
    //   156: istore_0
    //   157: goto -> 183
    //   160: aload_3
    //   161: aload_0
    //   162: invokevirtual UT : ()F
    //   165: iconst_0
    //   166: swap
    //   167: fastore
    //   168: iconst_1
    //   169: istore_0
    //   170: goto -> 183
    //   173: aload_3
    //   174: aload_0
    //   175: invokevirtual Vw : ()F
    //   178: iconst_0
    //   179: swap
    //   180: fastore
    //   181: iconst_1
    //   182: istore_0
    //   183: iload_0
    //   184: ireturn
    //   185: new java/lang/AssertionError
    //   188: dup
    //   189: invokespecial <init> : ()V
    //   192: athrow
    // Line number table:
    //   Java source line number -> byte code offset
    //   #1	-> 52
    //   #2	-> 65
    //   #3	-> 68
    //   #4	-> 81
    //   #5	-> 86
    //   #6	-> 96
    //   #7	-> 101
    //   #8	-> 102
    //   #9	-> 107
    //   #10	-> 115
    //   #11	-> 120
    //   #12	-> 128
    //   #13	-> 133
  }
}


/* Location:              /Users/vnnsnnt/Documents/Codespace/JavaWorkspace/RedTrainer/src/main/java/org/trainer/client/PokeMMO.jar!/f/lr0.class
 * Java compiler version: 8 (52.0)
 * JD-Core Version:       1.1.3
 */