/*   */ package f;public final class Mc extends Wr { public static void n30(eA0 parameA0, int paramInt) {
/* 2 */     jp0 jp0 = (jp0)km.wI0.iJ0;
/*   */     
/* 4 */     if ((jp0
/* 5 */       .ez0 = parameA0.R10[paramInt]) == null) jp0
/* 6 */         .YR(jp0.K60);  jp0.tJ();
/*   */   }
/*   */   
/*   */   public YA0 bA0;
/*   */   public Texture G80;
/*   */   public ge0 Z80;
/*   */   public W1 LPt2;
/*   */   
/*   */   public Mc() {
/*   */     YA0 yA01;
/*   */     YA0 yA02;
/*   */     OZ oZ;
/*   */     Xu("/resizableframe");
/*   */     TG0(this::ra0);
/*   */     this();
/*   */     SA sA = (new YA0()).Dv0;
/*   */     int i;
/*   */     String[] arrayOfString = new String[i = (km.mI0.AN.z40().K0()).length];
/*   */     for (byte b = 0; b < i; b++)
/*   */       arrayOfString[b] = String.valueOf(b); 
/*   */     this((Object[])arrayOfString);
/*   */     (this.LPt2 = new W1(oZ)).Z30(0);
/*   */     this.LPt2.D30(() -> z5());
/*   */     (this.Z80 = new ge0()).zs(true);
/*   */     this.Z80.tW(() -> z5());
/*   */     sA.IR("Config: ").fA0(this.LPt2).zm0();
/*   */     sA.IR("Compress: ").fA0(this.Z80).zm0();
/*   */     (new Un("Reset")).tW(Mc::Rh);
/*   */     sA.S7(new Un("Reset")).Yv(Integer.valueOf(2)).zm0();
/*   */     this();
/*   */     this.bA0 = new YA0();
/*   */     sA.S7(this).Kw().Yv(Integer.valueOf(2)).zm0();
/*   */     this.bA0.Dv0.cM().Xj0(2.0F);
/*   */     z5();
/*   */     yA02.Dv0.Dl0(15.0F);
/*   */     J8(yA02);
/*   */   }
/*   */   
/*   */   public static void Rh() {
/*   */     ((jp0)km.wI0.iJ0).ez0 = null;
/*   */     ((jp0)km.wI0.iJ0).YR(((jp0)km.wI0.iJ0).K60);
/*   */     ((jp0)km.wI0.iJ0).tJ();
/*   */   }
/*   */   
/*   */   public final void z5() {
/*   */     // Byte code:
/*   */     //   0: aload_0
/*   */     //   1: dup
/*   */     //   2: getstatic f/km.mI0 : Lf/P1;
/*   */     //   5: getfield AN : Lf/Wo;
/*   */     //   8: getfield r70 : Lf/FE0;
/*   */     //   11: getfield WE0 : [Lf/eA0;
/*   */     //   14: aload_0
/*   */     //   15: getfield LPt2 : Lf/W1;
/*   */     //   18: getfield Wa0 : Lf/A60;
/*   */     //   21: getfield go : I
/*   */     //   24: aaload
/*   */     //   25: astore_1
/*   */     //   26: getfield bA0 : Lf/YA0;
/*   */     //   29: getfield Dv0 : Lf/SA;
/*   */     //   32: dup
/*   */     //   33: astore_2
/*   */     //   34: invokevirtual kp0 : ()V
/*   */     //   37: getfield G80 : Lcom/badlogic/gdx/graphics/Texture;
/*   */     //   40: dup
/*   */     //   41: astore_3
/*   */     //   42: ifnull -> 49
/*   */     //   45: aload_3
/*   */     //   46: invokevirtual dispose : ()V
/*   */     //   49: aload_1
/*   */     //   50: getfield R10 : [Lf/lw;
/*   */     //   53: arraylength
/*   */     //   54: istore_3
/*   */     //   55: new f/ZH
/*   */     //   58: dup
/*   */     //   59: astore #4
/*   */     //   61: iload_3
/*   */     //   62: getstatic f/Uc.xi0 : Lf/Uc;
/*   */     //   65: iconst_4
/*   */     //   66: swap
/*   */     //   67: invokespecial <init> : (IILf/Uc;)V
/*   */     //   70: iconst_0
/*   */     //   71: istore #5
/*   */     //   73: iload #5
/*   */     //   75: iconst_5
/*   */     //   76: if_icmpge -> 224
/*   */     //   79: iconst_0
/*   */     //   80: istore #6
/*   */     //   82: iload #6
/*   */     //   84: iload_3
/*   */     //   85: if_icmpge -> 218
/*   */     //   88: iload #5
/*   */     //   90: aload_1
/*   */     //   91: getfield R10 : [Lf/lw;
/*   */     //   94: iload #6
/*   */     //   96: aaload
/*   */     //   97: astore #7
/*   */     //   99: aconst_null
/*   */     //   100: astore #8
/*   */     //   102: tableswitch default -> 136, 0 -> 179, 1 -> 169, 2 -> 159, 3 -> 149, 4 -> 139
/*   */     //   136: goto -> 186
/*   */     //   139: aload #7
/*   */     //   141: getfield vX : Lcom/badlogic/gdx/graphics/Color;
/*   */     //   144: astore #8
/*   */     //   146: goto -> 186
/*   */     //   149: aload #7
/*   */     //   151: getfield GB0 : Lcom/badlogic/gdx/graphics/Color;
/*   */     //   154: astore #8
/*   */     //   156: goto -> 186
/*   */     //   159: aload #7
/*   */     //   161: getfield vo0 : Lcom/badlogic/gdx/graphics/Color;
/*   */     //   164: astore #8
/*   */     //   166: goto -> 186
/*   */     //   169: aload #7
/*   */     //   171: getfield Jb0 : Lcom/badlogic/gdx/graphics/Color;
/*   */     //   174: astore #8
/*   */     //   176: goto -> 186
/*   */     //   179: aload #7
/*   */     //   181: getfield Mj : Lcom/badlogic/gdx/graphics/Color;
/*   */     //   184: astore #8
/*   */     //   186: aload #8
/*   */     //   188: ifnull -> 212
/*   */     //   191: aload #4
/*   */     //   193: aload #8
/*   */     //   195: invokestatic rgba8888 : (Lcom/badlogic/gdx/graphics/Color;)I
/*   */     //   198: istore #7
/*   */     //   200: getfield Con : Lcom/badlogic/gdx/graphics/g2d/Gdx2DPixmap;
/*   */     //   203: iload #6
/*   */     //   205: iload #5
/*   */     //   207: iload #7
/*   */     //   209: invokevirtual YO : (III)V
/*   */     //   212: iinc #6, 1
/*   */     //   215: goto -> 82
/*   */     //   218: iinc #5, 1
/*   */     //   221: goto -> 73
/*   */     //   224: aload_2
/*   */     //   225: dup
/*   */     //   226: dup
/*   */     //   227: dup2
/*   */     //   228: dup2
/*   */     //   229: aload #4
/*   */     //   231: aload_0
/*   */     //   232: new com/badlogic/gdx/graphics/Texture
/*   */     //   235: dup
/*   */     //   236: aload #4
/*   */     //   238: invokespecial <init> : (Lf/ZH;)V
/*   */     //   241: putfield G80 : Lcom/badlogic/gdx/graphics/Texture;
/*   */     //   244: invokevirtual dispose : ()V
/*   */     //   247: ldc_w 'Time'
/*   */     //   250: invokevirtual IR : (Ljava/lang/String;)Lf/nJ0;
/*   */     //   253: pop
/*   */     //   254: ldc_w '#'
/*   */     //   257: invokevirtual IR : (Ljava/lang/String;)Lf/nJ0;
/*   */     //   260: pop
/*   */     //   261: ldc_w 'Env'
/*   */     //   264: invokevirtual IR : (Ljava/lang/String;)Lf/nJ0;
/*   */     //   267: pop
/*   */     //   268: ldc_w 'BG'
/*   */     //   271: invokevirtual IR : (Ljava/lang/String;)Lf/nJ0;
/*   */     //   274: pop
/*   */     //   275: ldc_w 'Fog'
/*   */     //   278: invokevirtual IR : (Ljava/lang/String;)Lf/nJ0;
/*   */     //   281: pop
/*   */     //   282: ldc_w 'Win'
/*   */     //   285: invokevirtual IR : (Ljava/lang/String;)Lf/nJ0;
/*   */     //   288: pop
/*   */     //   289: ldc_w 'Win2'
/*   */     //   292: invokevirtual IR : (Ljava/lang/String;)Lf/nJ0;
/*   */     //   295: getfield Ox : Lf/ZP;
/*   */     //   298: invokevirtual wP : ()Lf/nJ0;
/*   */     //   301: pop
/*   */     //   302: iconst_0
/*   */     //   303: istore_3
/*   */     //   304: iconst_0
/*   */     //   305: istore #4
/*   */     //   307: iload #4
/*   */     //   309: bipush #48
/*   */     //   311: if_icmpge -> 523
/*   */     //   314: iload #4
/*   */     //   316: bipush #30
/*   */     //   318: imul
/*   */     //   319: dup
/*   */     //   320: istore #5
/*   */     //   322: invokestatic W70 : (I)I
/*   */     //   325: dup
/*   */     //   326: istore #6
/*   */     //   328: iload_3
/*   */     //   329: if_icmpne -> 348
/*   */     //   332: aload_0
/*   */     //   333: getfield Z80 : Lf/ge0;
/*   */     //   336: getfield TG0 : Lf/protected;
/*   */     //   339: invokevirtual nm0 : ()Z
/*   */     //   342: ifeq -> 348
/*   */     //   345: goto -> 517
/*   */     //   348: aload_2
/*   */     //   349: dup
/*   */     //   350: iload #5
/*   */     //   352: bipush #60
/*   */     //   354: imul
/*   */     //   355: i2l
/*   */     //   356: invokestatic W70 : (J)Ljava/lang/String;
/*   */     //   359: invokevirtual IR : (Ljava/lang/String;)Lf/nJ0;
/*   */     //   362: pop
/*   */     //   363: new java/lang/StringBuilder
/*   */     //   366: dup
/*   */     //   367: invokespecial <init> : ()V
/*   */     //   370: ldc_w 'ID: '
/*   */     //   373: invokevirtual append : (Ljava/lang/String;)Ljava/lang/StringBuilder;
/*   */     //   376: iload #6
/*   */     //   378: invokevirtual append : (I)Ljava/lang/StringBuilder;
/*   */     //   381: invokevirtual toString : ()Ljava/lang/String;
/*   */     //   384: invokevirtual IR : (Ljava/lang/String;)Lf/nJ0;
/*   */     //   387: pop
/*   */     //   388: iconst_0
/*   */     //   389: istore_3
/*   */     //   390: iload_3
/*   */     //   391: iconst_5
/*   */     //   392: if_icmpge -> 473
/*   */     //   395: aload_2
/*   */     //   396: new f/vF0
/*   */     //   399: dup
/*   */     //   400: dup2
/*   */     //   401: dup2
/*   */     //   402: invokespecial <init> : ()V
/*   */     //   405: bipush #32
/*   */     //   407: bipush #16
/*   */     //   409: invokevirtual Cu0 : (II)V
/*   */     //   412: getfield TS : Lf/rH;
/*   */     //   415: iconst_1
/*   */     //   416: anewarray f/pe0
/*   */     //   419: dup
/*   */     //   420: new f/pe0
/*   */     //   423: dup
/*   */     //   424: astore #5
/*   */     //   426: aload_0
/*   */     //   427: getfield G80 : Lcom/badlogic/gdx/graphics/Texture;
/*   */     //   430: iload #6
/*   */     //   432: iload_3
/*   */     //   433: iconst_1
/*   */     //   434: iconst_1
/*   */     //   435: invokespecial <init> : (Lcom/badlogic/gdx/graphics/Texture;IIII)V
/*   */     //   438: iconst_0
/*   */     //   439: aload #5
/*   */     //   441: aastore
/*   */     //   442: invokevirtual Pn : ([Lf/pe0;)Lf/JG0;
/*   */     //   445: pop
/*   */     //   446: getfield TS : Lf/rH;
/*   */     //   449: bipush #32
/*   */     //   451: bipush #16
/*   */     //   453: invokevirtual tL : (II)V
/*   */     //   456: getfield TS : Lf/rH;
/*   */     //   459: iconst_1
/*   */     //   460: putfield xB0 : I
/*   */     //   463: invokevirtual S7 : (Ljava/lang/Object;)Lf/nJ0;
/*   */     //   466: pop
/*   */     //   467: iinc #3, 1
/*   */     //   470: goto -> 390
/*   */     //   473: aload_2
/*   */     //   474: new f/Un
/*   */     //   477: dup
/*   */     //   478: astore_3
/*   */     //   479: aload_1
/*   */     //   480: iload #6
/*   */     //   482: aload_2
/*   */     //   483: aload_3
/*   */     //   484: dup
/*   */     //   485: dup
/*   */     //   486: ldc_w 'Preview'
/*   */     //   489: invokespecial <init> : (Ljava/lang/String;)V
/*   */     //   492: ldc_w 'label'
/*   */     //   495: invokevirtual Xu : (Ljava/lang/String;)V
/*   */     //   498: invokevirtual S7 : (Ljava/lang/Object;)Lf/nJ0;
/*   */     //   501: pop
/*   */     //   502: <illegal opcode> run : (Lf/eA0;I)Ljava/lang/Runnable;
/*   */     //   507: invokevirtual tW : (Ljava/lang/Runnable;)V
/*   */     //   510: invokevirtual wP : ()Lf/nJ0;
/*   */     //   513: pop
/*   */     //   514: iload #6
/*   */     //   516: istore_3
/*   */     //   517: iinc #4, 1
/*   */     //   520: goto -> 307
/*   */     //   523: aload_0
/*   */     //   524: invokevirtual mM : ()V
/*   */     //   527: return
/*   */     // Line number table:
/*   */     //   Java source line number -> byte code offset
/*   */     //   #1	-> 8
/*   */     //   #2	-> 11
/*   */     //   #3	-> 15
/*   */     //   #4	-> 18
/*   */     //   #5	-> 21
/*   */     //   #6	-> 24
/*   */     //   #7	-> 50
/*   */     //   #8	-> 53
/*   */     //   #9	-> 91
/*   */     //   #10	-> 141
/*   */     //   #11	-> 200
/*   */     //   #12	-> 232
/*   */     //   #13	-> 295
/*   */     //   #14	-> 322
/*   */     //   #15	-> 336
/*   */     //   #16	-> 339
/*   */     //   #17	-> 356
/*   */     //   #18	-> 412
/*   */     //   #19	-> 416
/*   */     //   #20	-> 446
/*   */     //   #21	-> 453
/*   */     //   #22	-> 456
/*   */     //   #23	-> 460
/*   */     //   #24	-> 463
/*   */   }
/*   */   
/*   */   public final void ED0(throws paramthrows) {
/*   */     this.G80.dispose();
/*   */   } }


/* Location:              /Users/vnnsnnt/Documents/Codespace/JavaWorkspace/RedTrainer/src/main/java/org/trainer/client/PokeMMO.jar!/f/Mc.class
 * Java compiler version: 8 (52.0)
 * JD-Core Version:       1.1.3
 */