package f;

import java.nio.ByteBuffer;

public abstract class mL extends Kl0 {
  public static final ik Vm = C00.gd(mL.class);
  
  public mL(ByteBuffer paramByteBuffer, c4 paramc4) {
    super(paramc4, paramByteBuffer);
  }
  
  public final GS tl() {
    // Byte code:
    //   0: aload_0
    //   1: dup
    //   2: getfield Ws : Ljava/nio/ByteBuffer;
    //   5: invokevirtual get : ()B
    //   8: istore_1
    //   9: getfield Ws : Ljava/nio/ByteBuffer;
    //   12: invokevirtual get : ()B
    //   15: dup
    //   16: istore_2
    //   17: iconst_0
    //   18: istore_3
    //   19: iconst_0
    //   20: istore #4
    //   22: iconst_1
    //   23: ior
    //   24: dup
    //   25: istore #5
    //   27: iload_2
    //   28: if_icmpne -> 39
    //   31: aload_0
    //   32: getfield Ws : Ljava/nio/ByteBuffer;
    //   35: invokevirtual getInt : ()I
    //   38: istore_3
    //   39: iload_2
    //   40: iconst_2
    //   41: ior
    //   42: dup
    //   43: istore #6
    //   45: iload_2
    //   46: if_icmpne -> 58
    //   49: aload_0
    //   50: getfield Ws : Ljava/nio/ByteBuffer;
    //   53: invokevirtual getInt : ()I
    //   56: istore #4
    //   58: iload_1
    //   59: tableswitch default -> 700, -29 -> 5278, -28 -> 5267, -27 -> 5093, -26 -> 5073, -25 -> 5093, -24 -> 5093, -23 -> 5093, -22 -> 5051, -21 -> 5030, -20 -> 5011, -19 -> 4993, -18 -> 4958, -17 -> 4774, -16 -> 4732, -15 -> 4714, -14 -> 4604, -13 -> 4586, -12 -> 4568, -11 -> 4550, -10 -> 4532, -9 -> 4514, -8 -> 4496, -7 -> 4485, -6 -> 4457, -5 -> 4439, -4 -> 4421, -3 -> 4403, -2 -> 4385, -1 -> 4367, 0 -> 4349, 1 -> 4280, 2 -> 4203, 3 -> 4185, 4 -> 4178, 5 -> 4151, 6 -> 4133, 7 -> 4106, 8 -> 4079, 9 -> 700, 10 -> 4061, 11 -> 4043, 12 -> 4014, 13 -> 3986, 14 -> 3948, 15 -> 3918, 16 -> 3900, 17 -> 700, 18 -> 3882, 19 -> 3864, 20 -> 3853, 21 -> 3835, 22 -> 3817, 23 -> 3764, 24 -> 3714, 25 -> 3689, 26 -> 3671, 27 -> 3644, 28 -> 3591, 29 -> 3570, 30 -> 3543, 31 -> 3383, 32 -> 3365, 33 -> 3347, 34 -> 3336, 35 -> 3309, 36 -> 3291, 37 -> 3280, 38 -> 3269, 39 -> 3251, 40 -> 3240, 41 -> 3183, 42 -> 3165, 43 -> 3105, 44 -> 3087, 45 -> 3069, 46 -> 3044, 47 -> 3026, 48 -> 3008, 49 -> 2990, 50 -> 2965, 51 -> 2856, 52 -> 2838, 53 -> 2820, 54 -> 2795, 55 -> 2770, 56 -> 2718, 57 -> 2700, 58 -> 2682, 59 -> 2664, 60 -> 2611, 61 -> 2567, 62 -> 2526, 63 -> 2515, 64 -> 2497, 65 -> 2472, 66 -> 2454, 67 -> 2443, 68 -> 2418, 69 -> 2384, 70 -> 2366, 71 -> 2348, 72 -> 2337, 73 -> 2319, 74 -> 2298, 75 -> 2273, 76 -> 2190, 77 -> 2172, 78 -> 2154, 79 -> 2136, 80 -> 2118, 81 -> 2000, 82 -> 1982, 83 -> 1957, 84 -> 1930, 85 -> 1912, 86 -> 1861, 87 -> 1850, 88 -> 1839, 89 -> 1797, 90 -> 1779, 91 -> 1761, 92 -> 1731, 93 -> 1687, 94 -> 1669, 95 -> 1651, 96 -> 1633, 97 -> 1577, 98 -> 1533, 99 -> 1515, 100 -> 1454, 101 -> 1358, 102 -> 700, 103 -> 1340, 104 -> 1322, 105 -> 1296, 106 -> 1264, 107 -> 1208, 108 -> 1190, 109 -> 1108, 110 -> 1090, 111 -> 1072, 112 -> 1054, 113 -> 1036, 114 -> 1011, 115 -> 993, 116 -> 975, 117 -> 950, 118 -> 925, 119 -> 907, 120 -> 889, 121 -> 871, 122 -> 843, 123 -> 832, 124 -> 771, 125 -> 760, 126 -> 749, 127 -> 738
    //   700: getstatic f/mL.Vm : Lf/ik;
    //   703: new java/lang/StringBuilder
    //   706: dup
    //   707: iload_1
    //   708: swap
    //   709: invokespecial <init> : ()V
    //   712: invokevirtual append : (I)Ljava/lang/StringBuilder;
    //   715: ldc ''
    //   717: invokevirtual append : (Ljava/lang/String;)Ljava/lang/StringBuilder;
    //   720: invokevirtual toString : ()Ljava/lang/String;
    //   723: new java/lang/RuntimeException
    //   726: dup
    //   727: invokespecial <init> : ()V
    //   730: invokeinterface error : (Ljava/lang/String;Ljava/lang/Throwable;)V
    //   735: goto -> 5341
    //   738: new f/om0
    //   741: dup
    //   742: astore_0
    //   743: invokespecial <init> : ()V
    //   746: goto -> 5343
    //   749: new f/Gd
    //   752: dup
    //   753: astore_0
    //   754: invokespecial <init> : ()V
    //   757: goto -> 5343
    //   760: new f/K90
    //   763: dup
    //   764: astore_0
    //   765: invokespecial <init> : ()V
    //   768: goto -> 5343
    //   771: aload_0
    //   772: getfield Ws : Ljava/nio/ByteBuffer;
    //   775: invokevirtual get : ()B
    //   778: dup
    //   779: istore_1
    //   780: anewarray f/hR
    //   783: astore #7
    //   785: iconst_0
    //   786: istore #8
    //   788: iload #8
    //   790: iload_1
    //   791: if_icmpge -> 819
    //   794: iload #8
    //   796: aload #7
    //   798: iload #8
    //   800: aload_0
    //   801: getfield Ws : Ljava/nio/ByteBuffer;
    //   804: invokevirtual get : ()B
    //   807: invokestatic aU : (B)Lf/hR;
    //   810: aastore
    //   811: iconst_1
    //   812: iadd
    //   813: i2b
    //   814: istore #8
    //   816: goto -> 788
    //   819: new f/Bp
    //   822: dup
    //   823: astore_0
    //   824: aload #7
    //   826: invokespecial <init> : ([Lf/hR;)V
    //   829: goto -> 5343
    //   832: new f/Mf
    //   835: dup
    //   836: astore_0
    //   837: invokespecial <init> : ()V
    //   840: goto -> 5343
    //   843: aload_0
    //   844: getfield Ws : Ljava/nio/ByteBuffer;
    //   847: invokevirtual get : ()B
    //   850: istore_1
    //   851: new f/cY
    //   854: dup
    //   855: astore #7
    //   857: aload_0
    //   858: iload_1
    //   859: invokevirtual ee0 : (I)[B
    //   862: invokespecial <init> : ([B)V
    //   865: aload #7
    //   867: astore_0
    //   868: goto -> 5343
    //   871: new f/Ac0
    //   874: dup
    //   875: astore_1
    //   876: aload_0
    //   877: getfield Ws : Ljava/nio/ByteBuffer;
    //   880: invokevirtual getShort : ()S
    //   883: invokespecial <init> : (S)V
    //   886: goto -> 5088
    //   889: new f/Q30
    //   892: dup
    //   893: astore_1
    //   894: aload_0
    //   895: getfield Ws : Ljava/nio/ByteBuffer;
    //   898: invokevirtual getShort : ()S
    //   901: invokespecial <init> : (S)V
    //   904: goto -> 5088
    //   907: new f/gs0
    //   910: dup
    //   911: astore_1
    //   912: aload_0
    //   913: getfield Ws : Ljava/nio/ByteBuffer;
    //   916: invokevirtual getShort : ()S
    //   919: invokespecial <init> : (S)V
    //   922: goto -> 5088
    //   925: new f/GG0
    //   928: dup
    //   929: astore_1
    //   930: aload_0
    //   931: getfield Ws : Ljava/nio/ByteBuffer;
    //   934: invokevirtual getInt : ()I
    //   937: aload_0
    //   938: getfield Ws : Ljava/nio/ByteBuffer;
    //   941: invokevirtual getShort : ()S
    //   944: invokespecial <init> : (IS)V
    //   947: goto -> 5088
    //   950: new f/IE
    //   953: dup
    //   954: astore_1
    //   955: aload_0
    //   956: dup
    //   957: getfield Ws : Ljava/nio/ByteBuffer;
    //   960: invokevirtual getInt : ()I
    //   963: istore_0
    //   964: invokevirtual au : ()Ljava/lang/String;
    //   967: iload_0
    //   968: swap
    //   969: invokespecial <init> : (ILjava/lang/String;)V
    //   972: goto -> 5088
    //   975: new f/PE0
    //   978: dup
    //   979: astore_1
    //   980: aload_0
    //   981: getfield Ws : Ljava/nio/ByteBuffer;
    //   984: invokevirtual getShort : ()S
    //   987: invokespecial <init> : (S)V
    //   990: goto -> 5088
    //   993: new f/Pq0
    //   996: dup
    //   997: astore_1
    //   998: aload_0
    //   999: getfield Ws : Ljava/nio/ByteBuffer;
    //   1002: invokevirtual getShort : ()S
    //   1005: invokespecial <init> : (S)V
    //   1008: goto -> 5088
    //   1011: new f/DY
    //   1014: dup
    //   1015: astore_1
    //   1016: aload_0
    //   1017: getfield Ws : Ljava/nio/ByteBuffer;
    //   1020: invokevirtual get : ()B
    //   1023: aload_0
    //   1024: getfield Ws : Ljava/nio/ByteBuffer;
    //   1027: invokevirtual getShort : ()S
    //   1030: invokespecial <init> : (BS)V
    //   1033: goto -> 5088
    //   1036: new f/Dv
    //   1039: dup
    //   1040: astore_1
    //   1041: aload_0
    //   1042: getfield Ws : Ljava/nio/ByteBuffer;
    //   1045: invokevirtual getShort : ()S
    //   1048: invokespecial <init> : (S)V
    //   1051: goto -> 5088
    //   1054: new f/PC0
    //   1057: dup
    //   1058: astore_1
    //   1059: aload_0
    //   1060: getfield Ws : Ljava/nio/ByteBuffer;
    //   1063: invokevirtual get : ()B
    //   1066: invokespecial <init> : (B)V
    //   1069: goto -> 5088
    //   1072: new f/Gg0
    //   1075: dup
    //   1076: astore_1
    //   1077: aload_0
    //   1078: getfield Ws : Ljava/nio/ByteBuffer;
    //   1081: invokevirtual get : ()B
    //   1084: invokespecial <init> : (B)V
    //   1087: goto -> 5088
    //   1090: new f/EA
    //   1093: dup
    //   1094: astore_1
    //   1095: aload_0
    //   1096: getfield Ws : Ljava/nio/ByteBuffer;
    //   1099: invokevirtual get : ()B
    //   1102: invokespecial <init> : (B)V
    //   1105: goto -> 5088
    //   1108: new f/Kd0
    //   1111: dup
    //   1112: astore_1
    //   1113: aload_0
    //   1114: dup
    //   1115: dup
    //   1116: getfield Ws : Ljava/nio/ByteBuffer;
    //   1119: invokevirtual getShort : ()S
    //   1122: istore #7
    //   1124: getfield Ws : Ljava/nio/ByteBuffer;
    //   1127: invokevirtual get : ()B
    //   1130: istore #8
    //   1132: invokevirtual au : ()Ljava/lang/String;
    //   1135: astore #9
    //   1137: iload #7
    //   1139: aload_0
    //   1140: dup
    //   1141: dup2
    //   1142: getfield Ws : Ljava/nio/ByteBuffer;
    //   1145: invokevirtual get : ()B
    //   1148: istore_0
    //   1149: getfield Ws : Ljava/nio/ByteBuffer;
    //   1152: invokevirtual get : ()B
    //   1155: istore #7
    //   1157: getfield Ws : Ljava/nio/ByteBuffer;
    //   1160: invokevirtual get : ()B
    //   1163: istore #10
    //   1165: getfield Ws : Ljava/nio/ByteBuffer;
    //   1168: invokevirtual get : ()B
    //   1171: istore #11
    //   1173: iload #8
    //   1175: aload #9
    //   1177: iload_0
    //   1178: iload #7
    //   1180: iload #10
    //   1182: iload #11
    //   1184: invokespecial <init> : (SBLjava/lang/String;BBBB)V
    //   1187: goto -> 5088
    //   1190: new f/uu0
    //   1193: dup
    //   1194: astore_1
    //   1195: aload_0
    //   1196: getfield Ws : Ljava/nio/ByteBuffer;
    //   1199: invokevirtual getShort : ()S
    //   1202: invokespecial <init> : (S)V
    //   1205: goto -> 5088
    //   1208: new f/Vb0
    //   1211: dup
    //   1212: astore_1
    //   1213: aload_0
    //   1214: getfield Ws : Ljava/nio/ByteBuffer;
    //   1217: invokevirtual getShort : ()S
    //   1220: aload_0
    //   1221: dup
    //   1222: dup2
    //   1223: getfield Ws : Ljava/nio/ByteBuffer;
    //   1226: invokevirtual get : ()B
    //   1229: pop
    //   1230: getfield Ws : Ljava/nio/ByteBuffer;
    //   1233: invokevirtual getShort : ()S
    //   1236: istore_0
    //   1237: getfield Ws : Ljava/nio/ByteBuffer;
    //   1240: invokevirtual getShort : ()S
    //   1243: istore #7
    //   1245: getfield Ws : Ljava/nio/ByteBuffer;
    //   1248: invokevirtual getShort : ()S
    //   1251: istore #8
    //   1253: iload_0
    //   1254: iload #7
    //   1256: iload #8
    //   1258: invokespecial <init> : (SSSS)V
    //   1261: goto -> 5088
    //   1264: new f/Lb0
    //   1267: dup
    //   1268: astore_1
    //   1269: aload_0
    //   1270: dup
    //   1271: dup
    //   1272: getfield Ws : Ljava/nio/ByteBuffer;
    //   1275: invokevirtual get : ()B
    //   1278: istore_0
    //   1279: getfield Ws : Ljava/nio/ByteBuffer;
    //   1282: invokevirtual get : ()B
    //   1285: invokevirtual ee0 : (I)[B
    //   1288: iload_0
    //   1289: swap
    //   1290: invokespecial <init> : (B[B)V
    //   1293: goto -> 5088
    //   1296: new f/TK
    //   1299: dup
    //   1300: astore_1
    //   1301: aload_0
    //   1302: dup
    //   1303: getfield Ws : Ljava/nio/ByteBuffer;
    //   1306: invokevirtual getShort : ()S
    //   1309: pop
    //   1310: getfield Ws : Ljava/nio/ByteBuffer;
    //   1313: invokevirtual getShort : ()S
    //   1316: invokespecial <init> : (S)V
    //   1319: goto -> 5088
    //   1322: new f/y2
    //   1325: dup
    //   1326: astore_1
    //   1327: aload_0
    //   1328: getfield Ws : Ljava/nio/ByteBuffer;
    //   1331: invokevirtual get : ()B
    //   1334: invokespecial <init> : (B)V
    //   1337: goto -> 5088
    //   1340: new f/un0
    //   1343: dup
    //   1344: astore_1
    //   1345: aload_0
    //   1346: getfield Ws : Ljava/nio/ByteBuffer;
    //   1349: invokevirtual get : ()B
    //   1352: invokespecial <init> : (B)V
    //   1355: goto -> 5088
    //   1358: aload_0
    //   1359: dup
    //   1360: getfield Ws : Ljava/nio/ByteBuffer;
    //   1363: invokevirtual get : ()B
    //   1366: istore_1
    //   1367: invokevirtual R00 : ()I
    //   1370: dup
    //   1371: istore #7
    //   1373: anewarray [S
    //   1376: astore #8
    //   1378: iconst_0
    //   1379: istore #9
    //   1381: iload #9
    //   1383: iload #7
    //   1385: if_icmpge -> 1440
    //   1388: aload #8
    //   1390: iload #9
    //   1392: aload_0
    //   1393: invokevirtual R00 : ()I
    //   1396: newarray short
    //   1398: aastore
    //   1399: iconst_0
    //   1400: istore #10
    //   1402: iload #10
    //   1404: aload #8
    //   1406: iload #9
    //   1408: aaload
    //   1409: dup
    //   1410: astore #11
    //   1412: arraylength
    //   1413: if_icmpge -> 1434
    //   1416: aload #11
    //   1418: iload #10
    //   1420: aload_0
    //   1421: getfield Ws : Ljava/nio/ByteBuffer;
    //   1424: invokevirtual getShort : ()S
    //   1427: sastore
    //   1428: iinc #10, 1
    //   1431: goto -> 1402
    //   1434: iinc #9, 1
    //   1437: goto -> 1381
    //   1440: new f/Dw0
    //   1443: dup
    //   1444: astore_0
    //   1445: iload_1
    //   1446: aload #8
    //   1448: invokespecial <init> : (B[[S)V
    //   1451: goto -> 5343
    //   1454: aload_0
    //   1455: dup
    //   1456: getfield Ws : Ljava/nio/ByteBuffer;
    //   1459: invokevirtual getShort : ()S
    //   1462: istore_1
    //   1463: invokevirtual R00 : ()I
    //   1466: dup
    //   1467: istore #7
    //   1469: newarray short
    //   1471: astore #8
    //   1473: iconst_0
    //   1474: istore #9
    //   1476: iload #9
    //   1478: iload #7
    //   1480: if_icmpge -> 1501
    //   1483: aload #8
    //   1485: iload #9
    //   1487: aload_0
    //   1488: getfield Ws : Ljava/nio/ByteBuffer;
    //   1491: invokevirtual getShort : ()S
    //   1494: sastore
    //   1495: iinc #9, 1
    //   1498: goto -> 1476
    //   1501: new f/mJ0
    //   1504: dup
    //   1505: astore_0
    //   1506: iload_1
    //   1507: aload #8
    //   1509: invokespecial <init> : (S[S)V
    //   1512: goto -> 5343
    //   1515: new f/zG0
    //   1518: dup
    //   1519: astore_1
    //   1520: aload_0
    //   1521: getfield Ws : Ljava/nio/ByteBuffer;
    //   1524: invokevirtual getShort : ()S
    //   1527: invokespecial <init> : (S)V
    //   1530: goto -> 5088
    //   1533: aload_0
    //   1534: getfield Ws : Ljava/nio/ByteBuffer;
    //   1537: invokevirtual get : ()B
    //   1540: dup
    //   1541: istore_1
    //   1542: new f/Vj0
    //   1545: astore #7
    //   1547: iconst_3
    //   1548: if_icmpne -> 1562
    //   1551: aload_0
    //   1552: getfield Ws : Ljava/nio/ByteBuffer;
    //   1555: invokevirtual getShort : ()S
    //   1558: istore_0
    //   1559: goto -> 1564
    //   1562: iconst_0
    //   1563: istore_0
    //   1564: aload #7
    //   1566: iload_1
    //   1567: iload_0
    //   1568: invokespecial <init> : (BS)V
    //   1571: aload #7
    //   1573: astore_0
    //   1574: goto -> 5343
    //   1577: aload_0
    //   1578: dup
    //   1579: dup
    //   1580: new f/Gb
    //   1583: astore_0
    //   1584: getfield Ws : Ljava/nio/ByteBuffer;
    //   1587: invokevirtual get : ()B
    //   1590: invokestatic kc : (B)Lf/mJ;
    //   1593: astore_1
    //   1594: getfield Ws : Ljava/nio/ByteBuffer;
    //   1597: invokevirtual get : ()B
    //   1600: istore #7
    //   1602: getfield Ws : Ljava/nio/ByteBuffer;
    //   1605: invokevirtual get : ()B
    //   1608: iconst_1
    //   1609: if_icmpne -> 1618
    //   1612: iconst_1
    //   1613: istore #8
    //   1615: goto -> 1621
    //   1618: iconst_0
    //   1619: istore #8
    //   1621: aload_0
    //   1622: aload_1
    //   1623: iload #7
    //   1625: iload #8
    //   1627: invokespecial <init> : (Lf/mJ;BZ)V
    //   1630: goto -> 5343
    //   1633: new f/YJ0
    //   1636: dup
    //   1637: astore_1
    //   1638: aload_0
    //   1639: getfield Ws : Ljava/nio/ByteBuffer;
    //   1642: invokevirtual getShort : ()S
    //   1645: invokespecial <init> : (S)V
    //   1648: goto -> 5088
    //   1651: new f/ed0
    //   1654: dup
    //   1655: astore_1
    //   1656: aload_0
    //   1657: getfield Ws : Ljava/nio/ByteBuffer;
    //   1660: invokevirtual get : ()B
    //   1663: invokespecial <init> : (B)V
    //   1666: goto -> 5088
    //   1669: new f/j1
    //   1672: dup
    //   1673: astore_1
    //   1674: aload_0
    //   1675: getfield Ws : Ljava/nio/ByteBuffer;
    //   1678: invokevirtual get : ()B
    //   1681: invokespecial <init> : (B)V
    //   1684: goto -> 5088
    //   1687: aload_0
    //   1688: getfield Ws : Ljava/nio/ByteBuffer;
    //   1691: invokevirtual get : ()B
    //   1694: dup
    //   1695: istore_1
    //   1696: new f/y90
    //   1699: astore #7
    //   1701: iconst_2
    //   1702: if_icmpne -> 1716
    //   1705: aload_0
    //   1706: getfield Ws : Ljava/nio/ByteBuffer;
    //   1709: invokevirtual getShort : ()S
    //   1712: istore_0
    //   1713: goto -> 1718
    //   1716: iconst_0
    //   1717: istore_0
    //   1718: aload #7
    //   1720: iload_1
    //   1721: iload_0
    //   1722: invokespecial <init> : (BS)V
    //   1725: aload #7
    //   1727: astore_0
    //   1728: goto -> 5343
    //   1731: aload_0
    //   1732: new f/P
    //   1735: astore_0
    //   1736: getfield Ws : Ljava/nio/ByteBuffer;
    //   1739: invokevirtual get : ()B
    //   1742: iconst_1
    //   1743: if_icmpne -> 1751
    //   1746: iconst_1
    //   1747: istore_1
    //   1748: goto -> 1753
    //   1751: iconst_0
    //   1752: istore_1
    //   1753: aload_0
    //   1754: iload_1
    //   1755: invokespecial <init> : (Z)V
    //   1758: goto -> 5343
    //   1761: new f/mz
    //   1764: dup
    //   1765: astore_1
    //   1766: aload_0
    //   1767: getfield Ws : Ljava/nio/ByteBuffer;
    //   1770: invokevirtual getShort : ()S
    //   1773: invokespecial <init> : (S)V
    //   1776: goto -> 5088
    //   1779: new f/PD
    //   1782: dup
    //   1783: astore_1
    //   1784: aload_0
    //   1785: getfield Ws : Ljava/nio/ByteBuffer;
    //   1788: invokevirtual getShort : ()S
    //   1791: invokespecial <init> : (S)V
    //   1794: goto -> 5088
    //   1797: aload_0
    //   1798: dup
    //   1799: new f/LC0
    //   1802: astore_0
    //   1803: getfield Ws : Ljava/nio/ByteBuffer;
    //   1806: invokevirtual getShort : ()S
    //   1809: istore_1
    //   1810: getfield Ws : Ljava/nio/ByteBuffer;
    //   1813: invokevirtual get : ()B
    //   1816: iconst_1
    //   1817: if_icmpne -> 1826
    //   1820: iconst_1
    //   1821: istore #7
    //   1823: goto -> 1829
    //   1826: iconst_0
    //   1827: istore #7
    //   1829: aload_0
    //   1830: iload_1
    //   1831: iload #7
    //   1833: invokespecial <init> : (SZ)V
    //   1836: goto -> 5343
    //   1839: new f/rv0
    //   1842: dup
    //   1843: astore_0
    //   1844: invokespecial <init> : ()V
    //   1847: goto -> 5343
    //   1850: new f/Hb
    //   1853: dup
    //   1854: astore_0
    //   1855: invokespecial <init> : ()V
    //   1858: goto -> 5343
    //   1861: aload_0
    //   1862: getfield Ws : Ljava/nio/ByteBuffer;
    //   1865: invokevirtual get : ()B
    //   1868: dup
    //   1869: istore_1
    //   1870: iconst_4
    //   1871: if_icmpne -> 1900
    //   1874: new f/jy
    //   1877: dup
    //   1878: astore #7
    //   1880: aload_0
    //   1881: getfield Ws : Ljava/nio/ByteBuffer;
    //   1884: invokevirtual get : ()B
    //   1887: invokestatic aU : (B)Lf/hR;
    //   1890: iload_1
    //   1891: invokespecial <init> : (Lf/hR;B)V
    //   1894: aload #7
    //   1896: astore_0
    //   1897: goto -> 5343
    //   1900: new f/jy
    //   1903: dup
    //   1904: astore_0
    //   1905: iload_1
    //   1906: invokespecial <init> : (B)V
    //   1909: goto -> 5343
    //   1912: new f/Is0
    //   1915: dup
    //   1916: astore_1
    //   1917: aload_0
    //   1918: getfield Ws : Ljava/nio/ByteBuffer;
    //   1921: invokevirtual get : ()B
    //   1924: invokespecial <init> : (B)V
    //   1927: goto -> 5088
    //   1930: new f/OH0
    //   1933: dup
    //   1934: astore_1
    //   1935: aload_0
    //   1936: dup
    //   1937: getfield Ws : Ljava/nio/ByteBuffer;
    //   1940: invokevirtual getShort : ()S
    //   1943: istore_0
    //   1944: getfield Ws : Ljava/nio/ByteBuffer;
    //   1947: invokevirtual getInt : ()I
    //   1950: iload_0
    //   1951: invokespecial <init> : (IS)V
    //   1954: goto -> 5088
    //   1957: new f/Vb
    //   1960: dup
    //   1961: astore_1
    //   1962: aload_0
    //   1963: getfield Ws : Ljava/nio/ByteBuffer;
    //   1966: invokevirtual getShort : ()S
    //   1969: aload_0
    //   1970: getfield Ws : Ljava/nio/ByteBuffer;
    //   1973: invokevirtual getShort : ()S
    //   1976: invokespecial <init> : (SS)V
    //   1979: goto -> 5088
    //   1982: new f/vj0
    //   1985: dup
    //   1986: astore_1
    //   1987: aload_0
    //   1988: getfield Ws : Ljava/nio/ByteBuffer;
    //   1991: invokevirtual getShort : ()S
    //   1994: invokespecial <init> : (S)V
    //   1997: goto -> 5088
    //   2000: aload_0
    //   2001: getfield Ws : Ljava/nio/ByteBuffer;
    //   2004: invokevirtual get : ()B
    //   2007: dup
    //   2008: istore_1
    //   2009: ifeq -> 2024
    //   2012: new f/B90
    //   2015: dup
    //   2016: astore_0
    //   2017: iload_1
    //   2018: invokespecial <init> : (B)V
    //   2021: goto -> 5343
    //   2024: aload_0
    //   2025: getfield Ws : Ljava/nio/ByteBuffer;
    //   2028: invokevirtual get : ()B
    //   2031: dup
    //   2032: istore #7
    //   2034: anewarray [B
    //   2037: astore #8
    //   2039: iconst_0
    //   2040: istore #9
    //   2042: iload #9
    //   2044: iload #7
    //   2046: if_icmpge -> 2104
    //   2049: aload #8
    //   2051: iload #9
    //   2053: aload_0
    //   2054: getfield Ws : Ljava/nio/ByteBuffer;
    //   2057: invokevirtual get : ()B
    //   2060: newarray byte
    //   2062: aastore
    //   2063: iconst_0
    //   2064: istore #10
    //   2066: iload #10
    //   2068: aload #8
    //   2070: iload #9
    //   2072: aaload
    //   2073: dup
    //   2074: astore #11
    //   2076: arraylength
    //   2077: if_icmpge -> 2098
    //   2080: aload #11
    //   2082: iload #10
    //   2084: aload_0
    //   2085: getfield Ws : Ljava/nio/ByteBuffer;
    //   2088: invokevirtual get : ()B
    //   2091: bastore
    //   2092: iinc #10, 1
    //   2095: goto -> 2066
    //   2098: iinc #9, 1
    //   2101: goto -> 2042
    //   2104: new f/B90
    //   2107: dup
    //   2108: astore_0
    //   2109: iload_1
    //   2110: aload #8
    //   2112: invokespecial <init> : (B[[B)V
    //   2115: goto -> 5343
    //   2118: new f/Uq0
    //   2121: dup
    //   2122: astore_1
    //   2123: aload_0
    //   2124: getfield Ws : Ljava/nio/ByteBuffer;
    //   2127: invokevirtual get : ()B
    //   2130: invokespecial <init> : (B)V
    //   2133: goto -> 5088
    //   2136: new f/No
    //   2139: dup
    //   2140: astore_1
    //   2141: aload_0
    //   2142: getfield Ws : Ljava/nio/ByteBuffer;
    //   2145: invokevirtual get : ()B
    //   2148: invokespecial <init> : (B)V
    //   2151: goto -> 5088
    //   2154: new f/Zn
    //   2157: dup
    //   2158: astore_1
    //   2159: aload_0
    //   2160: getfield Ws : Ljava/nio/ByteBuffer;
    //   2163: invokevirtual get : ()B
    //   2166: invokespecial <init> : (B)V
    //   2169: goto -> 5088
    //   2172: new f/Xz
    //   2175: dup
    //   2176: astore_1
    //   2177: aload_0
    //   2178: getfield Ws : Ljava/nio/ByteBuffer;
    //   2181: invokevirtual get : ()B
    //   2184: invokespecial <init> : (B)V
    //   2187: goto -> 5088
    //   2190: aload_0
    //   2191: dup
    //   2192: getfield Ws : Ljava/nio/ByteBuffer;
    //   2195: invokevirtual get : ()B
    //   2198: istore_1
    //   2199: getfield Ws : Ljava/nio/ByteBuffer;
    //   2202: invokevirtual get : ()B
    //   2205: dup
    //   2206: istore #7
    //   2208: ifne -> 2247
    //   2211: new f/zG
    //   2214: dup
    //   2215: astore #8
    //   2217: iload_1
    //   2218: aload_0
    //   2219: dup
    //   2220: getfield Ws : Ljava/nio/ByteBuffer;
    //   2223: invokevirtual getShort : ()S
    //   2226: istore_0
    //   2227: getfield Ws : Ljava/nio/ByteBuffer;
    //   2230: invokevirtual getShort : ()S
    //   2233: istore_1
    //   2234: iload #7
    //   2236: iload_0
    //   2237: iload_1
    //   2238: invokespecial <init> : (BBSS)V
    //   2241: aload #8
    //   2243: astore_0
    //   2244: goto -> 5343
    //   2247: new f/zG
    //   2250: dup
    //   2251: astore #8
    //   2253: iload_1
    //   2254: aload_0
    //   2255: getfield Ws : Ljava/nio/ByteBuffer;
    //   2258: invokevirtual getInt : ()I
    //   2261: iload #7
    //   2263: swap
    //   2264: invokespecial <init> : (BBI)V
    //   2267: aload #8
    //   2269: astore_0
    //   2270: goto -> 5343
    //   2273: new f/V
    //   2276: dup
    //   2277: astore_1
    //   2278: aload_0
    //   2279: getfield Ws : Ljava/nio/ByteBuffer;
    //   2282: invokevirtual getShort : ()S
    //   2285: aload_0
    //   2286: getfield Ws : Ljava/nio/ByteBuffer;
    //   2289: invokevirtual getShort : ()S
    //   2292: invokespecial <init> : (SS)V
    //   2295: goto -> 5088
    //   2298: new f/Du0
    //   2301: dup
    //   2302: astore_1
    //   2303: aload_0
    //   2304: getfield Ws : Ljava/nio/ByteBuffer;
    //   2307: invokevirtual get : ()B
    //   2310: invokestatic Jo0 : (B)Lf/CC0;
    //   2313: invokespecial <init> : (Lf/CC0;)V
    //   2316: goto -> 5088
    //   2319: new f/bA0
    //   2322: dup
    //   2323: astore_1
    //   2324: aload_0
    //   2325: getfield Ws : Ljava/nio/ByteBuffer;
    //   2328: invokevirtual getShort : ()S
    //   2331: invokespecial <init> : (S)V
    //   2334: goto -> 5088
    //   2337: new f/zC0
    //   2340: dup
    //   2341: astore_0
    //   2342: invokespecial <init> : ()V
    //   2345: goto -> 5343
    //   2348: new f/Vl0
    //   2351: dup
    //   2352: astore_1
    //   2353: aload_0
    //   2354: getfield Ws : Ljava/nio/ByteBuffer;
    //   2357: invokevirtual getShort : ()S
    //   2360: invokespecial <init> : (S)V
    //   2363: goto -> 5088
    //   2366: new f/z8
    //   2369: dup
    //   2370: astore_1
    //   2371: aload_0
    //   2372: getfield Ws : Ljava/nio/ByteBuffer;
    //   2375: invokevirtual getShort : ()S
    //   2378: invokespecial <init> : (S)V
    //   2381: goto -> 5088
    //   2384: new f/gj
    //   2387: dup
    //   2388: astore_1
    //   2389: aload_0
    //   2390: getfield Ws : Ljava/nio/ByteBuffer;
    //   2393: invokevirtual get : ()B
    //   2396: aload_0
    //   2397: dup
    //   2398: getfield Ws : Ljava/nio/ByteBuffer;
    //   2401: invokevirtual getShort : ()S
    //   2404: istore_0
    //   2405: getfield Ws : Ljava/nio/ByteBuffer;
    //   2408: invokevirtual get : ()B
    //   2411: iload_0
    //   2412: invokespecial <init> : (BBS)V
    //   2415: goto -> 5088
    //   2418: new f/bW
    //   2421: dup
    //   2422: astore_1
    //   2423: aload_0
    //   2424: getfield Ws : Ljava/nio/ByteBuffer;
    //   2427: invokevirtual getShort : ()S
    //   2430: aload_0
    //   2431: getfield Ws : Ljava/nio/ByteBuffer;
    //   2434: invokevirtual getShort : ()S
    //   2437: invokespecial <init> : (SS)V
    //   2440: goto -> 5088
    //   2443: new f/iS
    //   2446: dup
    //   2447: astore_0
    //   2448: invokespecial <init> : ()V
    //   2451: goto -> 5343
    //   2454: new f/ML
    //   2457: dup
    //   2458: astore_1
    //   2459: aload_0
    //   2460: getfield Ws : Ljava/nio/ByteBuffer;
    //   2463: invokevirtual getShort : ()S
    //   2466: invokespecial <init> : (S)V
    //   2469: goto -> 5088
    //   2472: new f/MH0
    //   2475: dup
    //   2476: astore_1
    //   2477: aload_0
    //   2478: getfield Ws : Ljava/nio/ByteBuffer;
    //   2481: invokevirtual getShort : ()S
    //   2484: aload_0
    //   2485: getfield Ws : Ljava/nio/ByteBuffer;
    //   2488: invokevirtual getShort : ()S
    //   2491: invokespecial <init> : (SS)V
    //   2494: goto -> 5088
    //   2497: new f/Ox0
    //   2500: dup
    //   2501: astore_1
    //   2502: aload_0
    //   2503: getfield Ws : Ljava/nio/ByteBuffer;
    //   2506: invokevirtual getShort : ()S
    //   2509: invokespecial <init> : (S)V
    //   2512: goto -> 5088
    //   2515: new f/KP
    //   2518: dup
    //   2519: astore_0
    //   2520: invokespecial <init> : ()V
    //   2523: goto -> 5343
    //   2526: new f/dF0
    //   2529: dup
    //   2530: astore_1
    //   2531: aload_0
    //   2532: getfield Ws : Ljava/nio/ByteBuffer;
    //   2535: invokevirtual get : ()B
    //   2538: invokestatic Gt0 : (B)Lf/Ht0;
    //   2541: aload_0
    //   2542: dup
    //   2543: getfield Ws : Ljava/nio/ByteBuffer;
    //   2546: invokevirtual get : ()B
    //   2549: invokestatic Gt0 : (B)Lf/Ht0;
    //   2552: astore_0
    //   2553: getfield Ws : Ljava/nio/ByteBuffer;
    //   2556: invokevirtual getShort : ()S
    //   2559: aload_0
    //   2560: swap
    //   2561: invokespecial <init> : (Lf/Ht0;Lf/Ht0;S)V
    //   2564: goto -> 5088
    //   2567: aload_0
    //   2568: getfield Ws : Ljava/nio/ByteBuffer;
    //   2571: invokevirtual get : ()B
    //   2574: dup
    //   2575: istore_1
    //   2576: new f/el
    //   2579: astore #7
    //   2581: iconst_1
    //   2582: if_icmpne -> 2596
    //   2585: aload_0
    //   2586: getfield Ws : Ljava/nio/ByteBuffer;
    //   2589: invokevirtual getShort : ()S
    //   2592: istore_0
    //   2593: goto -> 2598
    //   2596: iconst_0
    //   2597: istore_0
    //   2598: aload #7
    //   2600: iload_1
    //   2601: iload_0
    //   2602: invokespecial <init> : (BS)V
    //   2605: aload #7
    //   2607: astore_0
    //   2608: goto -> 5343
    //   2611: aload_0
    //   2612: getfield Ws : Ljava/nio/ByteBuffer;
    //   2615: invokevirtual get : ()B
    //   2618: dup
    //   2619: istore_1
    //   2620: newarray short
    //   2622: astore #7
    //   2624: iconst_0
    //   2625: istore #8
    //   2627: iload #8
    //   2629: iload_1
    //   2630: if_icmpge -> 2651
    //   2633: aload #7
    //   2635: iload #8
    //   2637: aload_0
    //   2638: getfield Ws : Ljava/nio/ByteBuffer;
    //   2641: invokevirtual getShort : ()S
    //   2644: sastore
    //   2645: iinc #8, 1
    //   2648: goto -> 2627
    //   2651: new f/IH0
    //   2654: dup
    //   2655: astore_0
    //   2656: aload #7
    //   2658: invokespecial <init> : ([S)V
    //   2661: goto -> 5343
    //   2664: new f/uz
    //   2667: dup
    //   2668: astore_1
    //   2669: aload_0
    //   2670: getfield Ws : Ljava/nio/ByteBuffer;
    //   2673: invokevirtual get : ()B
    //   2676: invokespecial <init> : (B)V
    //   2679: goto -> 5088
    //   2682: new f/Rs0
    //   2685: dup
    //   2686: astore_1
    //   2687: aload_0
    //   2688: getfield Ws : Ljava/nio/ByteBuffer;
    //   2691: invokevirtual get : ()B
    //   2694: invokespecial <init> : (B)V
    //   2697: goto -> 5088
    //   2700: new f/bX
    //   2703: dup
    //   2704: astore_1
    //   2705: aload_0
    //   2706: getfield Ws : Ljava/nio/ByteBuffer;
    //   2709: invokevirtual getShort : ()S
    //   2712: invokespecial <init> : (S)V
    //   2715: goto -> 5088
    //   2718: new f/e
    //   2721: dup
    //   2722: astore_1
    //   2723: aload_0
    //   2724: getfield Ws : Ljava/nio/ByteBuffer;
    //   2727: invokevirtual getShort : ()S
    //   2730: aload_0
    //   2731: dup
    //   2732: dup
    //   2733: getfield Ws : Ljava/nio/ByteBuffer;
    //   2736: invokevirtual get : ()B
    //   2739: invokestatic aU : (B)Lf/hR;
    //   2742: astore_0
    //   2743: getfield Ws : Ljava/nio/ByteBuffer;
    //   2746: invokevirtual get : ()B
    //   2749: istore #7
    //   2751: getfield Ws : Ljava/nio/ByteBuffer;
    //   2754: invokevirtual get : ()B
    //   2757: istore #8
    //   2759: aload_0
    //   2760: iload #7
    //   2762: iload #8
    //   2764: invokespecial <init> : (SLf/hR;BB)V
    //   2767: goto -> 5088
    //   2770: new f/bz0
    //   2773: dup
    //   2774: astore_1
    //   2775: aload_0
    //   2776: getfield Ws : Ljava/nio/ByteBuffer;
    //   2779: invokevirtual getShort : ()S
    //   2782: aload_0
    //   2783: getfield Ws : Ljava/nio/ByteBuffer;
    //   2786: invokevirtual getShort : ()S
    //   2789: invokespecial <init> : (SS)V
    //   2792: goto -> 5088
    //   2795: new f/dW
    //   2798: dup
    //   2799: astore_1
    //   2800: aload_0
    //   2801: getfield Ws : Ljava/nio/ByteBuffer;
    //   2804: invokevirtual getShort : ()S
    //   2807: aload_0
    //   2808: getfield Ws : Ljava/nio/ByteBuffer;
    //   2811: invokevirtual getShort : ()S
    //   2814: invokespecial <init> : (SS)V
    //   2817: goto -> 5088
    //   2820: new f/OP
    //   2823: dup
    //   2824: astore_1
    //   2825: aload_0
    //   2826: getfield Ws : Ljava/nio/ByteBuffer;
    //   2829: invokevirtual getShort : ()S
    //   2832: invokespecial <init> : (S)V
    //   2835: goto -> 5088
    //   2838: new f/Zt0
    //   2841: dup
    //   2842: astore_1
    //   2843: aload_0
    //   2844: getfield Ws : Ljava/nio/ByteBuffer;
    //   2847: invokevirtual getShort : ()S
    //   2850: invokespecial <init> : (S)V
    //   2853: goto -> 5088
    //   2856: aload_0
    //   2857: getfield Ws : Ljava/nio/ByteBuffer;
    //   2860: invokevirtual get : ()B
    //   2863: dup
    //   2864: istore_1
    //   2865: aload_0
    //   2866: dup
    //   2867: getfield Ws : Ljava/nio/ByteBuffer;
    //   2870: invokevirtual getShort : ()S
    //   2873: istore #7
    //   2875: getfield Ws : Ljava/nio/ByteBuffer;
    //   2878: invokevirtual getInt : ()I
    //   2881: istore #8
    //   2883: iconst_0
    //   2884: istore #9
    //   2886: iconst_0
    //   2887: istore #10
    //   2889: iconst_0
    //   2890: istore #11
    //   2892: iconst_1
    //   2893: iand
    //   2894: ifeq -> 2906
    //   2897: aload_0
    //   2898: getfield Ws : Ljava/nio/ByteBuffer;
    //   2901: invokevirtual getInt : ()I
    //   2904: istore #9
    //   2906: iload_1
    //   2907: iconst_2
    //   2908: iand
    //   2909: ifne -> 2919
    //   2912: iload_1
    //   2913: bipush #8
    //   2915: iand
    //   2916: ifeq -> 2928
    //   2919: aload_0
    //   2920: getfield Ws : Ljava/nio/ByteBuffer;
    //   2923: invokevirtual getShort : ()S
    //   2926: istore #10
    //   2928: iload_1
    //   2929: iconst_4
    //   2930: iand
    //   2931: ifeq -> 2943
    //   2934: aload_0
    //   2935: getfield Ws : Ljava/nio/ByteBuffer;
    //   2938: invokevirtual getShort : ()S
    //   2941: istore #11
    //   2943: new f/Oh0
    //   2946: dup
    //   2947: astore_0
    //   2948: iload_1
    //   2949: iload #7
    //   2951: iload #8
    //   2953: iload #9
    //   2955: iload #10
    //   2957: iload #11
    //   2959: invokespecial <init> : (BSIISS)V
    //   2962: goto -> 5343
    //   2965: new f/Yu0
    //   2968: dup
    //   2969: astore_1
    //   2970: aload_0
    //   2971: getfield Ws : Ljava/nio/ByteBuffer;
    //   2974: invokevirtual get : ()B
    //   2977: aload_0
    //   2978: getfield Ws : Ljava/nio/ByteBuffer;
    //   2981: invokevirtual getShort : ()S
    //   2984: invokespecial <init> : (BS)V
    //   2987: goto -> 5088
    //   2990: new f/pV
    //   2993: dup
    //   2994: astore_1
    //   2995: aload_0
    //   2996: getfield Ws : Ljava/nio/ByteBuffer;
    //   2999: invokevirtual getShort : ()S
    //   3002: invokespecial <init> : (S)V
    //   3005: goto -> 5088
    //   3008: new f/cB
    //   3011: dup
    //   3012: astore_1
    //   3013: aload_0
    //   3014: getfield Ws : Ljava/nio/ByteBuffer;
    //   3017: invokevirtual get : ()B
    //   3020: invokespecial <init> : (B)V
    //   3023: goto -> 5088
    //   3026: new f/AS
    //   3029: dup
    //   3030: astore_1
    //   3031: aload_0
    //   3032: getfield Ws : Ljava/nio/ByteBuffer;
    //   3035: invokevirtual getShort : ()S
    //   3038: invokespecial <init> : (S)V
    //   3041: goto -> 5088
    //   3044: new f/G0
    //   3047: dup
    //   3048: astore_1
    //   3049: aload_0
    //   3050: getfield Ws : Ljava/nio/ByteBuffer;
    //   3053: invokevirtual get : ()B
    //   3056: aload_0
    //   3057: getfield Ws : Ljava/nio/ByteBuffer;
    //   3060: invokevirtual getShort : ()S
    //   3063: invokespecial <init> : (BS)V
    //   3066: goto -> 5088
    //   3069: new f/WH
    //   3072: dup
    //   3073: astore_1
    //   3074: aload_0
    //   3075: getfield Ws : Ljava/nio/ByteBuffer;
    //   3078: invokevirtual get : ()B
    //   3081: invokespecial <init> : (B)V
    //   3084: goto -> 5088
    //   3087: new f/fc0
    //   3090: dup
    //   3091: astore_1
    //   3092: aload_0
    //   3093: getfield Ws : Ljava/nio/ByteBuffer;
    //   3096: invokevirtual get : ()B
    //   3099: invokespecial <init> : (B)V
    //   3102: goto -> 5088
    //   3105: new f/mH0
    //   3108: dup
    //   3109: astore_1
    //   3110: aload_0
    //   3111: dup
    //   3112: getfield Ws : Ljava/nio/ByteBuffer;
    //   3115: invokevirtual getShort : ()S
    //   3118: istore #7
    //   3120: getfield Ws : Ljava/nio/ByteBuffer;
    //   3123: invokevirtual get : ()B
    //   3126: iload #7
    //   3128: aload_0
    //   3129: dup
    //   3130: dup
    //   3131: getfield Ws : Ljava/nio/ByteBuffer;
    //   3134: invokevirtual getShort : ()S
    //   3137: istore_0
    //   3138: getfield Ws : Ljava/nio/ByteBuffer;
    //   3141: invokevirtual getShort : ()S
    //   3144: istore #7
    //   3146: getfield Ws : Ljava/nio/ByteBuffer;
    //   3149: invokevirtual getShort : ()S
    //   3152: istore #8
    //   3154: iload_0
    //   3155: iload #7
    //   3157: iload #8
    //   3159: invokespecial <init> : (BSSSS)V
    //   3162: goto -> 5088
    //   3165: new f/FT
    //   3168: dup
    //   3169: astore_1
    //   3170: aload_0
    //   3171: getfield Ws : Ljava/nio/ByteBuffer;
    //   3174: invokevirtual getShort : ()S
    //   3177: invokespecial <init> : (S)V
    //   3180: goto -> 5088
    //   3183: aload_0
    //   3184: getfield Ws : Ljava/nio/ByteBuffer;
    //   3187: invokevirtual getShort : ()S
    //   3190: dup
    //   3191: istore_1
    //   3192: new f/L
    //   3195: astore #7
    //   3197: sipush #273
    //   3200: if_icmpne -> 3215
    //   3203: aload_0
    //   3204: getfield Ws : Ljava/nio/ByteBuffer;
    //   3207: invokevirtual getInt : ()I
    //   3210: istore #8
    //   3212: goto -> 3218
    //   3215: iconst_0
    //   3216: istore #8
    //   3218: aload #7
    //   3220: iload #8
    //   3222: aload_0
    //   3223: getfield Ws : Ljava/nio/ByteBuffer;
    //   3226: invokevirtual getShort : ()S
    //   3229: iload_1
    //   3230: swap
    //   3231: invokespecial <init> : (ISS)V
    //   3234: aload #7
    //   3236: astore_0
    //   3237: goto -> 5343
    //   3240: new f/Y9
    //   3243: dup
    //   3244: astore_0
    //   3245: invokespecial <init> : ()V
    //   3248: goto -> 5343
    //   3251: new f/tB
    //   3254: dup
    //   3255: astore_1
    //   3256: aload_0
    //   3257: getfield Ws : Ljava/nio/ByteBuffer;
    //   3260: invokevirtual getShort : ()S
    //   3263: invokespecial <init> : (S)V
    //   3266: goto -> 5088
    //   3269: new f/UJ0
    //   3272: dup
    //   3273: astore_0
    //   3274: invokespecial <init> : ()V
    //   3277: goto -> 5343
    //   3280: new f/qo0
    //   3283: dup
    //   3284: astore_0
    //   3285: invokespecial <init> : ()V
    //   3288: goto -> 5343
    //   3291: new f/rc0
    //   3294: dup
    //   3295: astore_1
    //   3296: aload_0
    //   3297: getfield Ws : Ljava/nio/ByteBuffer;
    //   3300: invokevirtual getShort : ()S
    //   3303: invokespecial <init> : (S)V
    //   3306: goto -> 5088
    //   3309: aload_0
    //   3310: new f/lv0
    //   3313: astore_0
    //   3314: invokevirtual R00 : ()I
    //   3317: iconst_1
    //   3318: if_icmpne -> 3326
    //   3321: iconst_1
    //   3322: istore_1
    //   3323: goto -> 3328
    //   3326: iconst_0
    //   3327: istore_1
    //   3328: aload_0
    //   3329: iload_1
    //   3330: invokespecial <init> : (Z)V
    //   3333: goto -> 5343
    //   3336: new f/CA
    //   3339: dup
    //   3340: astore_0
    //   3341: invokespecial <init> : ()V
    //   3344: goto -> 5343
    //   3347: new f/oq0
    //   3350: dup
    //   3351: astore_1
    //   3352: aload_0
    //   3353: getfield Ws : Ljava/nio/ByteBuffer;
    //   3356: invokevirtual getShort : ()S
    //   3359: invokespecial <init> : (S)V
    //   3362: goto -> 5088
    //   3365: new f/WK0
    //   3368: dup
    //   3369: astore_1
    //   3370: aload_0
    //   3371: getfield Ws : Ljava/nio/ByteBuffer;
    //   3374: invokevirtual get : ()B
    //   3377: invokespecial <init> : (B)V
    //   3380: goto -> 5088
    //   3383: aload_0
    //   3384: dup
    //   3385: getfield Ws : Ljava/nio/ByteBuffer;
    //   3388: invokevirtual getShort : ()S
    //   3391: istore_1
    //   3392: getfield Ws : Ljava/nio/ByteBuffer;
    //   3395: invokevirtual get : ()B
    //   3398: istore #7
    //   3400: iconst_4
    //   3401: newarray short
    //   3403: astore #8
    //   3405: iconst_0
    //   3406: istore #9
    //   3408: iload #9
    //   3410: iconst_4
    //   3411: if_icmpge -> 3432
    //   3414: aload #8
    //   3416: iload #9
    //   3418: aload_0
    //   3419: getfield Ws : Ljava/nio/ByteBuffer;
    //   3422: invokevirtual getShort : ()S
    //   3425: sastore
    //   3426: iinc #9, 1
    //   3429: goto -> 3408
    //   3432: aload_0
    //   3433: dup
    //   3434: dup
    //   3435: dup2
    //   3436: getfield Ws : Ljava/nio/ByteBuffer;
    //   3439: invokevirtual getShort : ()S
    //   3442: istore #9
    //   3444: getfield Ws : Ljava/nio/ByteBuffer;
    //   3447: invokevirtual get : ()B
    //   3450: istore #10
    //   3452: getfield Ws : Ljava/nio/ByteBuffer;
    //   3455: invokevirtual get : ()B
    //   3458: istore #11
    //   3460: getfield Ws : Ljava/nio/ByteBuffer;
    //   3463: invokevirtual getInt : ()I
    //   3466: invokestatic ua0 : (I)[B
    //   3469: astore #12
    //   3471: getfield n90 : I
    //   3474: bipush #19
    //   3476: if_icmpge -> 3489
    //   3479: getstatic f/Ht0.P00 : Lf/Ht0;
    //   3482: astore_0
    //   3483: aload_0
    //   3484: astore #13
    //   3486: goto -> 3512
    //   3489: aload_0
    //   3490: dup
    //   3491: getfield Ws : Ljava/nio/ByteBuffer;
    //   3494: invokevirtual get : ()B
    //   3497: invokestatic Gt0 : (B)Lf/Ht0;
    //   3500: astore_0
    //   3501: getfield Ws : Ljava/nio/ByteBuffer;
    //   3504: invokevirtual get : ()B
    //   3507: invokestatic Gt0 : (B)Lf/Ht0;
    //   3510: astore #13
    //   3512: new f/ei0
    //   3515: dup
    //   3516: astore #14
    //   3518: iload_1
    //   3519: iload #7
    //   3521: aload #8
    //   3523: iload #9
    //   3525: iload #10
    //   3527: iload #11
    //   3529: aload #12
    //   3531: aload_0
    //   3532: aload #13
    //   3534: invokespecial <init> : (SB[SSBB[BLf/Ht0;Lf/Ht0;)V
    //   3537: aload #14
    //   3539: astore_0
    //   3540: goto -> 5343
    //   3543: new f/WQ
    //   3546: dup
    //   3547: astore_1
    //   3548: aload_0
    //   3549: dup
    //   3550: getfield Ws : Ljava/nio/ByteBuffer;
    //   3553: invokevirtual getShort : ()S
    //   3556: istore_0
    //   3557: getfield Ws : Ljava/nio/ByteBuffer;
    //   3560: invokevirtual get : ()B
    //   3563: iload_0
    //   3564: invokespecial <init> : (BS)V
    //   3567: goto -> 5088
    //   3570: new f/rD0
    //   3573: dup
    //   3574: astore_1
    //   3575: aload_0
    //   3576: getfield Ws : Ljava/nio/ByteBuffer;
    //   3579: invokevirtual get : ()B
    //   3582: invokestatic Gt0 : (B)Lf/Ht0;
    //   3585: invokespecial <init> : (Lf/Ht0;)V
    //   3588: goto -> 5088
    //   3591: aload_0
    //   3592: dup
    //   3593: dup
    //   3594: new f/s
    //   3597: astore_0
    //   3598: getfield Ws : Ljava/nio/ByteBuffer;
    //   3601: invokevirtual get : ()B
    //   3604: istore_1
    //   3605: getfield Ws : Ljava/nio/ByteBuffer;
    //   3608: invokevirtual get : ()B
    //   3611: istore #7
    //   3613: getfield Ws : Ljava/nio/ByteBuffer;
    //   3616: invokevirtual get : ()B
    //   3619: iconst_1
    //   3620: if_icmpne -> 3629
    //   3623: iconst_1
    //   3624: istore #8
    //   3626: goto -> 3632
    //   3629: iconst_0
    //   3630: istore #8
    //   3632: aload_0
    //   3633: iload_1
    //   3634: iload #7
    //   3636: iload #8
    //   3638: invokespecial <init> : (BBZ)V
    //   3641: goto -> 5343
    //   3644: aload_0
    //   3645: new f/Hs
    //   3648: astore_0
    //   3649: invokevirtual R00 : ()I
    //   3652: iconst_1
    //   3653: if_icmpne -> 3661
    //   3656: iconst_1
    //   3657: istore_1
    //   3658: goto -> 3663
    //   3661: iconst_0
    //   3662: istore_1
    //   3663: aload_0
    //   3664: iload_1
    //   3665: invokespecial <init> : (Z)V
    //   3668: goto -> 5343
    //   3671: new f/Mk
    //   3674: dup
    //   3675: astore_1
    //   3676: aload_0
    //   3677: getfield Ws : Ljava/nio/ByteBuffer;
    //   3680: invokevirtual getShort : ()S
    //   3683: invokespecial <init> : (S)V
    //   3686: goto -> 5088
    //   3689: new f/nj0
    //   3692: dup
    //   3693: astore_1
    //   3694: aload_0
    //   3695: getfield Ws : Ljava/nio/ByteBuffer;
    //   3698: invokevirtual get : ()B
    //   3701: aload_0
    //   3702: getfield Ws : Ljava/nio/ByteBuffer;
    //   3705: invokevirtual get : ()B
    //   3708: invokespecial <init> : (BB)V
    //   3711: goto -> 5088
    //   3714: aload_0
    //   3715: getfield Ws : Ljava/nio/ByteBuffer;
    //   3718: invokevirtual get : ()B
    //   3721: dup
    //   3722: istore_1
    //   3723: aload_0
    //   3724: getfield Ws : Ljava/nio/ByteBuffer;
    //   3727: invokevirtual getShort : ()S
    //   3730: istore #7
    //   3732: iconst_0
    //   3733: istore #8
    //   3735: iconst_1
    //   3736: if_icmpne -> 3748
    //   3739: aload_0
    //   3740: getfield Ws : Ljava/nio/ByteBuffer;
    //   3743: invokevirtual getShort : ()S
    //   3746: istore #8
    //   3748: new f/Fv
    //   3751: dup
    //   3752: astore_0
    //   3753: iload_1
    //   3754: iload #7
    //   3756: iload #8
    //   3758: invokespecial <init> : (BSS)V
    //   3761: goto -> 5343
    //   3764: aload_0
    //   3765: dup
    //   3766: dup
    //   3767: new f/mC0
    //   3770: astore_0
    //   3771: getfield Ws : Ljava/nio/ByteBuffer;
    //   3774: invokevirtual get : ()B
    //   3777: istore_1
    //   3778: getfield Ws : Ljava/nio/ByteBuffer;
    //   3781: invokevirtual getShort : ()S
    //   3784: istore #7
    //   3786: getfield Ws : Ljava/nio/ByteBuffer;
    //   3789: invokevirtual get : ()B
    //   3792: iconst_1
    //   3793: if_icmpne -> 3802
    //   3796: iconst_1
    //   3797: istore #8
    //   3799: goto -> 3805
    //   3802: iconst_0
    //   3803: istore #8
    //   3805: aload_0
    //   3806: iload #7
    //   3808: iload #8
    //   3810: iload_1
    //   3811: invokespecial <init> : (SZB)V
    //   3814: goto -> 5343
    //   3817: new f/Xq
    //   3820: dup
    //   3821: astore_1
    //   3822: aload_0
    //   3823: getfield Ws : Ljava/nio/ByteBuffer;
    //   3826: invokevirtual get : ()B
    //   3829: invokespecial <init> : (B)V
    //   3832: goto -> 5088
    //   3835: new f/Wj
    //   3838: dup
    //   3839: astore_1
    //   3840: aload_0
    //   3841: getfield Ws : Ljava/nio/ByteBuffer;
    //   3844: invokevirtual get : ()B
    //   3847: invokespecial <init> : (B)V
    //   3850: goto -> 5088
    //   3853: new f/V30
    //   3856: dup
    //   3857: astore_0
    //   3858: invokespecial <init> : ()V
    //   3861: goto -> 5343
    //   3864: new f/lz0
    //   3867: dup
    //   3868: astore_1
    //   3869: aload_0
    //   3870: getfield Ws : Ljava/nio/ByteBuffer;
    //   3873: invokevirtual getShort : ()S
    //   3876: invokespecial <init> : (S)V
    //   3879: goto -> 5088
    //   3882: new f/vv
    //   3885: dup
    //   3886: astore_1
    //   3887: aload_0
    //   3888: getfield Ws : Ljava/nio/ByteBuffer;
    //   3891: invokevirtual getShort : ()S
    //   3894: invokespecial <init> : (S)V
    //   3897: goto -> 5088
    //   3900: new f/xr
    //   3903: dup
    //   3904: astore_1
    //   3905: aload_0
    //   3906: getfield Ws : Ljava/nio/ByteBuffer;
    //   3909: invokevirtual get : ()B
    //   3912: invokespecial <init> : (B)V
    //   3915: goto -> 5088
    //   3918: aload_0
    //   3919: new f/up0
    //   3922: astore_0
    //   3923: getfield Ws : Ljava/nio/ByteBuffer;
    //   3926: invokevirtual get : ()B
    //   3929: iconst_1
    //   3930: if_icmpne -> 3938
    //   3933: iconst_1
    //   3934: istore_1
    //   3935: goto -> 3940
    //   3938: iconst_0
    //   3939: istore_1
    //   3940: aload_0
    //   3941: iload_1
    //   3942: invokespecial <init> : (Z)V
    //   3945: goto -> 5343
    //   3948: new f/zf
    //   3951: dup
    //   3952: astore_1
    //   3953: aload_0
    //   3954: getfield Ws : Ljava/nio/ByteBuffer;
    //   3957: invokevirtual getShort : ()S
    //   3960: aload_0
    //   3961: dup
    //   3962: getfield Ws : Ljava/nio/ByteBuffer;
    //   3965: invokevirtual get : ()B
    //   3968: invokestatic kc : (B)Lf/mJ;
    //   3971: astore_0
    //   3972: getfield Ws : Ljava/nio/ByteBuffer;
    //   3975: invokevirtual getShort : ()S
    //   3978: aload_0
    //   3979: swap
    //   3980: invokespecial <init> : (SLf/mJ;S)V
    //   3983: goto -> 5088
    //   3986: new f/GE0
    //   3989: dup
    //   3990: astore_1
    //   3991: aload_0
    //   3992: getfield Ws : Ljava/nio/ByteBuffer;
    //   3995: invokevirtual get : ()B
    //   3998: invokestatic s2 : (B)Lf/Mx;
    //   4001: aload_0
    //   4002: getfield Ws : Ljava/nio/ByteBuffer;
    //   4005: invokevirtual getShort : ()S
    //   4008: invokespecial <init> : (Lf/Mx;S)V
    //   4011: goto -> 5088
    //   4014: new f/ZM
    //   4017: dup
    //   4018: astore_1
    //   4019: aload_0
    //   4020: getfield Ws : Ljava/nio/ByteBuffer;
    //   4023: invokevirtual get : ()B
    //   4026: invokestatic s2 : (B)Lf/Mx;
    //   4029: aload_0
    //   4030: getfield Ws : Ljava/nio/ByteBuffer;
    //   4033: invokevirtual get : ()B
    //   4036: pop
    //   4037: invokespecial <init> : (Lf/Mx;)V
    //   4040: goto -> 5088
    //   4043: new f/Wr0
    //   4046: dup
    //   4047: astore_1
    //   4048: aload_0
    //   4049: getfield Ws : Ljava/nio/ByteBuffer;
    //   4052: invokevirtual get : ()B
    //   4055: invokespecial <init> : (B)V
    //   4058: goto -> 5088
    //   4061: new f/gi0
    //   4064: dup
    //   4065: astore_1
    //   4066: aload_0
    //   4067: getfield Ws : Ljava/nio/ByteBuffer;
    //   4070: invokevirtual get : ()B
    //   4073: invokespecial <init> : (B)V
    //   4076: goto -> 5088
    //   4079: aload_0
    //   4080: new f/DS
    //   4083: astore_0
    //   4084: invokevirtual R00 : ()I
    //   4087: iconst_1
    //   4088: if_icmpne -> 4096
    //   4091: iconst_1
    //   4092: istore_1
    //   4093: goto -> 4098
    //   4096: iconst_0
    //   4097: istore_1
    //   4098: aload_0
    //   4099: iload_1
    //   4100: invokespecial <init> : (Z)V
    //   4103: goto -> 5343
    //   4106: aload_0
    //   4107: new f/bg
    //   4110: astore_0
    //   4111: invokevirtual R00 : ()I
    //   4114: iconst_1
    //   4115: if_icmpne -> 4123
    //   4118: iconst_1
    //   4119: istore_1
    //   4120: goto -> 4125
    //   4123: iconst_0
    //   4124: istore_1
    //   4125: aload_0
    //   4126: iload_1
    //   4127: invokespecial <init> : (Z)V
    //   4130: goto -> 5343
    //   4133: new f/sd
    //   4136: dup
    //   4137: astore_1
    //   4138: aload_0
    //   4139: getfield Ws : Ljava/nio/ByteBuffer;
    //   4142: invokevirtual getShort : ()S
    //   4145: invokespecial <init> : (S)V
    //   4148: goto -> 5088
    //   4151: aload_0
    //   4152: new f/JI0
    //   4155: astore_0
    //   4156: invokevirtual R00 : ()I
    //   4159: iconst_1
    //   4160: if_icmpne -> 4168
    //   4163: iconst_1
    //   4164: istore_1
    //   4165: goto -> 4170
    //   4168: iconst_0
    //   4169: istore_1
    //   4170: aload_0
    //   4171: iload_1
    //   4172: invokespecial <init> : (Z)V
    //   4175: goto -> 5343
    //   4178: getstatic f/tg0.ju0 : Lf/tg0;
    //   4181: astore_0
    //   4182: goto -> 5343
    //   4185: new f/zi
    //   4188: dup
    //   4189: astore_1
    //   4190: aload_0
    //   4191: getfield Ws : Ljava/nio/ByteBuffer;
    //   4194: invokevirtual getShort : ()S
    //   4197: invokespecial <init> : (S)V
    //   4200: goto -> 5088
    //   4203: aload_0
    //   4204: getfield Ws : Ljava/nio/ByteBuffer;
    //   4207: invokevirtual get : ()B
    //   4210: dup
    //   4211: istore_1
    //   4212: aload_0
    //   4213: new f/Qk
    //   4216: astore #7
    //   4218: getfield Ws : Ljava/nio/ByteBuffer;
    //   4221: invokevirtual get : ()B
    //   4224: istore #8
    //   4226: iconst_1
    //   4227: if_icmpne -> 4242
    //   4230: aload_0
    //   4231: getfield Ws : Ljava/nio/ByteBuffer;
    //   4234: invokevirtual getShort : ()S
    //   4237: istore #9
    //   4239: goto -> 4245
    //   4242: iconst_0
    //   4243: istore #9
    //   4245: iload_1
    //   4246: iconst_3
    //   4247: if_icmpne -> 4261
    //   4250: aload_0
    //   4251: getfield Ws : Ljava/nio/ByteBuffer;
    //   4254: invokevirtual getInt : ()I
    //   4257: istore_0
    //   4258: goto -> 4263
    //   4261: iconst_0
    //   4262: istore_0
    //   4263: aload #7
    //   4265: iload_1
    //   4266: iload #8
    //   4268: iload #9
    //   4270: iload_0
    //   4271: invokespecial <init> : (BBSI)V
    //   4274: aload #7
    //   4276: astore_0
    //   4277: goto -> 5343
    //   4280: aload_0
    //   4281: getfield Ws : Ljava/nio/ByteBuffer;
    //   4284: invokevirtual get : ()B
    //   4287: dup
    //   4288: istore_1
    //   4289: sipush #128
    //   4292: iand
    //   4293: ifne -> 4302
    //   4296: iconst_1
    //   4297: istore #7
    //   4299: goto -> 4305
    //   4302: iconst_0
    //   4303: istore #7
    //   4305: iload_1
    //   4306: bipush #127
    //   4308: iand
    //   4309: i2b
    //   4310: invokestatic aU : (B)Lf/hR;
    //   4313: astore_1
    //   4314: new f/Tj
    //   4317: dup
    //   4318: astore #8
    //   4320: aload_1
    //   4321: aload_0
    //   4322: dup
    //   4323: getfield Ws : Ljava/nio/ByteBuffer;
    //   4326: invokevirtual get : ()B
    //   4329: istore_0
    //   4330: getfield Ws : Ljava/nio/ByteBuffer;
    //   4333: invokevirtual get : ()B
    //   4336: iload_0
    //   4337: swap
    //   4338: iload #7
    //   4340: invokespecial <init> : (Lf/hR;BBZ)V
    //   4343: aload #8
    //   4345: astore_0
    //   4346: goto -> 5343
    //   4349: new f/JS
    //   4352: dup
    //   4353: astore_1
    //   4354: aload_0
    //   4355: getfield Ws : Ljava/nio/ByteBuffer;
    //   4358: invokevirtual getShort : ()S
    //   4361: invokespecial <init> : (S)V
    //   4364: goto -> 5088
    //   4367: new f/NV
    //   4370: dup
    //   4371: astore_1
    //   4372: aload_0
    //   4373: getfield Ws : Ljava/nio/ByteBuffer;
    //   4376: invokevirtual getShort : ()S
    //   4379: invokespecial <init> : (S)V
    //   4382: goto -> 5088
    //   4385: new f/Br
    //   4388: dup
    //   4389: astore_1
    //   4390: aload_0
    //   4391: getfield Ws : Ljava/nio/ByteBuffer;
    //   4394: invokevirtual getShort : ()S
    //   4397: invokespecial <init> : (S)V
    //   4400: goto -> 5088
    //   4403: new f/Zg0
    //   4406: dup
    //   4407: astore_1
    //   4408: aload_0
    //   4409: getfield Ws : Ljava/nio/ByteBuffer;
    //   4412: invokevirtual get : ()B
    //   4415: invokespecial <init> : (B)V
    //   4418: goto -> 5088
    //   4421: new f/Ae
    //   4424: dup
    //   4425: astore_1
    //   4426: aload_0
    //   4427: getfield Ws : Ljava/nio/ByteBuffer;
    //   4430: invokevirtual get : ()B
    //   4433: invokespecial <init> : (B)V
    //   4436: goto -> 5088
    //   4439: new f/Ah0
    //   4442: dup
    //   4443: astore_1
    //   4444: aload_0
    //   4445: getfield Ws : Ljava/nio/ByteBuffer;
    //   4448: invokevirtual get : ()B
    //   4451: invokespecial <init> : (B)V
    //   4454: goto -> 5088
    //   4457: new f/KR
    //   4460: dup
    //   4461: astore_1
    //   4462: aload_0
    //   4463: getfield Ws : Ljava/nio/ByteBuffer;
    //   4466: invokevirtual get : ()B
    //   4469: invokestatic Jo0 : (B)Lf/CC0;
    //   4472: aload_0
    //   4473: getfield Ws : Ljava/nio/ByteBuffer;
    //   4476: invokevirtual getShort : ()S
    //   4479: invokespecial <init> : (Lf/CC0;S)V
    //   4482: goto -> 5088
    //   4485: new f/i1
    //   4488: dup
    //   4489: astore_0
    //   4490: invokespecial <init> : ()V
    //   4493: goto -> 5343
    //   4496: new f/SA0
    //   4499: dup
    //   4500: astore_1
    //   4501: aload_0
    //   4502: getfield Ws : Ljava/nio/ByteBuffer;
    //   4505: invokevirtual get : ()B
    //   4508: invokespecial <init> : (B)V
    //   4511: goto -> 5088
    //   4514: new f/FL0
    //   4517: dup
    //   4518: astore_1
    //   4519: aload_0
    //   4520: getfield Ws : Ljava/nio/ByteBuffer;
    //   4523: invokevirtual get : ()B
    //   4526: invokespecial <init> : (B)V
    //   4529: goto -> 5088
    //   4532: new f/Sk0
    //   4535: dup
    //   4536: astore_1
    //   4537: aload_0
    //   4538: getfield Ws : Ljava/nio/ByteBuffer;
    //   4541: invokevirtual get : ()B
    //   4544: invokespecial <init> : (B)V
    //   4547: goto -> 5088
    //   4550: new f/md
    //   4553: dup
    //   4554: astore_1
    //   4555: aload_0
    //   4556: getfield Ws : Ljava/nio/ByteBuffer;
    //   4559: invokevirtual getShort : ()S
    //   4562: invokespecial <init> : (S)V
    //   4565: goto -> 5088
    //   4568: new f/XX
    //   4571: dup
    //   4572: astore_1
    //   4573: aload_0
    //   4574: getfield Ws : Ljava/nio/ByteBuffer;
    //   4577: invokevirtual getShort : ()S
    //   4580: invokespecial <init> : (S)V
    //   4583: goto -> 5088
    //   4586: new f/ws
    //   4589: dup
    //   4590: astore_1
    //   4591: aload_0
    //   4592: getfield Ws : Ljava/nio/ByteBuffer;
    //   4595: invokevirtual getShort : ()S
    //   4598: invokespecial <init> : (S)V
    //   4601: goto -> 5088
    //   4604: aload_0
    //   4605: getfield Ws : Ljava/nio/ByteBuffer;
    //   4608: invokevirtual get : ()B
    //   4611: dup
    //   4612: istore_1
    //   4613: anewarray f/hR
    //   4616: astore #7
    //   4618: iconst_0
    //   4619: istore #8
    //   4621: iload #8
    //   4623: iload_1
    //   4624: if_icmpge -> 4648
    //   4627: aload #7
    //   4629: iload #8
    //   4631: aload_0
    //   4632: getfield Ws : Ljava/nio/ByteBuffer;
    //   4635: invokevirtual get : ()B
    //   4638: invokestatic aU : (B)Lf/hR;
    //   4641: aastore
    //   4642: iinc #8, 1
    //   4645: goto -> 4621
    //   4648: aload_0
    //   4649: dup
    //   4650: getfield Ws : Ljava/nio/ByteBuffer;
    //   4653: invokevirtual get : ()B
    //   4656: istore_1
    //   4657: getfield Ws : Ljava/nio/ByteBuffer;
    //   4660: invokevirtual get : ()B
    //   4663: dup
    //   4664: istore #8
    //   4666: newarray byte
    //   4668: astore #9
    //   4670: iconst_0
    //   4671: istore #10
    //   4673: iload #10
    //   4675: iload #8
    //   4677: if_icmpge -> 4698
    //   4680: aload #9
    //   4682: iload #10
    //   4684: aload_0
    //   4685: getfield Ws : Ljava/nio/ByteBuffer;
    //   4688: invokevirtual get : ()B
    //   4691: bastore
    //   4692: iinc #10, 1
    //   4695: goto -> 4673
    //   4698: new f/yt0
    //   4701: dup
    //   4702: astore_0
    //   4703: aload #7
    //   4705: iload_1
    //   4706: aload #9
    //   4708: invokespecial <init> : ([Lf/hR;B[B)V
    //   4711: goto -> 5343
    //   4714: new f/Bl0
    //   4717: dup
    //   4718: astore_1
    //   4719: aload_0
    //   4720: getfield Ws : Ljava/nio/ByteBuffer;
    //   4723: invokevirtual getShort : ()S
    //   4726: invokespecial <init> : (S)V
    //   4729: goto -> 5088
    //   4732: aload_0
    //   4733: dup
    //   4734: new f/y40
    //   4737: astore_0
    //   4738: getfield Ws : Ljava/nio/ByteBuffer;
    //   4741: invokevirtual get : ()B
    //   4744: istore_1
    //   4745: getfield Ws : Ljava/nio/ByteBuffer;
    //   4748: invokevirtual get : ()B
    //   4751: iconst_1
    //   4752: if_icmpne -> 4761
    //   4755: iconst_1
    //   4756: istore #7
    //   4758: goto -> 4764
    //   4761: iconst_0
    //   4762: istore #7
    //   4764: aload_0
    //   4765: iload_1
    //   4766: iload #7
    //   4768: invokespecial <init> : (BZ)V
    //   4771: goto -> 5343
    //   4774: aload_0
    //   4775: getfield Ws : Ljava/nio/ByteBuffer;
    //   4778: invokevirtual get : ()B
    //   4781: dup
    //   4782: istore_1
    //   4783: bipush #33
    //   4785: if_icmpne -> 4925
    //   4788: aload_0
    //   4789: dup
    //   4790: dup
    //   4791: new f/sk
    //   4794: astore_0
    //   4795: getfield Ws : Ljava/nio/ByteBuffer;
    //   4798: invokevirtual get : ()B
    //   4801: istore #7
    //   4803: getfield Ws : Ljava/nio/ByteBuffer;
    //   4806: invokevirtual getInt : ()I
    //   4809: istore #8
    //   4811: getfield Ws : Ljava/nio/ByteBuffer;
    //   4814: invokevirtual get : ()B
    //   4817: dup
    //   4818: istore #9
    //   4820: ifne -> 4831
    //   4823: getstatic f/hR.ZF : [Lf/hR;
    //   4826: astore #9
    //   4828: goto -> 4911
    //   4831: getstatic f/hR.Gg : Lf/hR;
    //   4834: pop
    //   4835: new java/util/ArrayList
    //   4838: dup
    //   4839: astore #10
    //   4841: invokespecial <init> : ()V
    //   4844: getstatic f/hR.Tt0 : [Lf/hR;
    //   4847: dup
    //   4848: astore #11
    //   4850: arraylength
    //   4851: istore #12
    //   4853: iconst_0
    //   4854: istore #13
    //   4856: iload #13
    //   4858: iload #12
    //   4860: if_icmpge -> 4897
    //   4863: iload #9
    //   4865: aload #11
    //   4867: iload #13
    //   4869: aaload
    //   4870: dup
    //   4871: astore #14
    //   4873: getfield dL : B
    //   4876: iconst_1
    //   4877: swap
    //   4878: ishl
    //   4879: iand
    //   4880: ifeq -> 4891
    //   4883: aload #10
    //   4885: aload #14
    //   4887: invokevirtual add : (Ljava/lang/Object;)Z
    //   4890: pop
    //   4891: iinc #13, 1
    //   4894: goto -> 4856
    //   4897: aload #10
    //   4899: iconst_0
    //   4900: anewarray f/hR
    //   4903: invokevirtual toArray : ([Ljava/lang/Object;)[Ljava/lang/Object;
    //   4906: checkcast [Lf/hR;
    //   4909: astore #9
    //   4911: aload_0
    //   4912: iload_1
    //   4913: iload #7
    //   4915: iload #8
    //   4917: aload #9
    //   4919: invokespecial <init> : (BBI[Lf/hR;)V
    //   4922: goto -> 5343
    //   4925: new f/sk
    //   4928: dup
    //   4929: astore #7
    //   4931: iload_1
    //   4932: aload_0
    //   4933: dup
    //   4934: getfield Ws : Ljava/nio/ByteBuffer;
    //   4937: invokevirtual get : ()B
    //   4940: istore_0
    //   4941: getfield Ws : Ljava/nio/ByteBuffer;
    //   4944: invokevirtual getInt : ()I
    //   4947: iload_0
    //   4948: swap
    //   4949: invokespecial <init> : (BBI)V
    //   4952: aload #7
    //   4954: astore_0
    //   4955: goto -> 5343
    //   4958: new f/ha0
    //   4961: dup
    //   4962: astore_1
    //   4963: aload_0
    //   4964: getfield Ws : Ljava/nio/ByteBuffer;
    //   4967: invokevirtual get : ()B
    //   4970: aload_0
    //   4971: dup
    //   4972: getfield Ws : Ljava/nio/ByteBuffer;
    //   4975: invokevirtual get : ()B
    //   4978: istore_0
    //   4979: getfield Ws : Ljava/nio/ByteBuffer;
    //   4982: invokevirtual get : ()B
    //   4985: iload_0
    //   4986: swap
    //   4987: invokespecial <init> : (BBB)V
    //   4990: goto -> 5088
    //   4993: new f/zW
    //   4996: dup
    //   4997: astore_1
    //   4998: aload_0
    //   4999: getfield Ws : Ljava/nio/ByteBuffer;
    //   5002: invokevirtual get : ()B
    //   5005: invokespecial <init> : (B)V
    //   5008: goto -> 5088
    //   5011: new f/AJ
    //   5014: dup
    //   5015: astore_1
    //   5016: aload_0
    //   5017: getfield Ws : Ljava/nio/ByteBuffer;
    //   5020: invokevirtual get : ()B
    //   5023: pop
    //   5024: invokespecial <init> : ()V
    //   5027: goto -> 5088
    //   5030: new f/RB0
    //   5033: dup
    //   5034: astore_1
    //   5035: aload_0
    //   5036: getfield Ws : Ljava/nio/ByteBuffer;
    //   5039: invokevirtual getInt : ()I
    //   5042: invokestatic ua0 : (I)[B
    //   5045: invokespecial <init> : ([B)V
    //   5048: goto -> 5088
    //   5051: new f/iI0
    //   5054: dup
    //   5055: astore_1
    //   5056: aload_0
    //   5057: invokevirtual au : ()Ljava/lang/String;
    //   5060: aload_0
    //   5061: getfield Ws : Ljava/nio/ByteBuffer;
    //   5064: invokevirtual getInt : ()I
    //   5067: invokespecial <init> : (Ljava/lang/String;I)V
    //   5070: goto -> 5088
    //   5073: new f/h00
    //   5076: dup
    //   5077: astore_1
    //   5078: aload_0
    //   5079: getfield Ws : Ljava/nio/ByteBuffer;
    //   5082: invokevirtual getShort : ()S
    //   5085: invokespecial <init> : (S)V
    //   5088: aload_1
    //   5089: astore_0
    //   5090: goto -> 5343
    //   5093: aload_0
    //   5094: dup
    //   5095: getfield Ws : Ljava/nio/ByteBuffer;
    //   5098: invokevirtual get : ()B
    //   5101: istore #7
    //   5103: getfield Ws : Ljava/nio/ByteBuffer;
    //   5106: invokevirtual get : ()B
    //   5109: dup
    //   5110: dup
    //   5111: istore #8
    //   5113: newarray int
    //   5115: astore #9
    //   5117: newarray short
    //   5119: astore #10
    //   5121: iconst_0
    //   5122: istore #11
    //   5124: iload #11
    //   5126: iload #8
    //   5128: if_icmpge -> 5161
    //   5131: aload #10
    //   5133: iload #11
    //   5135: aload_0
    //   5136: aload #9
    //   5138: iload #11
    //   5140: aload_0
    //   5141: getfield Ws : Ljava/nio/ByteBuffer;
    //   5144: invokevirtual getInt : ()I
    //   5147: iastore
    //   5148: getfield Ws : Ljava/nio/ByteBuffer;
    //   5151: invokevirtual getShort : ()S
    //   5154: sastore
    //   5155: iinc #11, 1
    //   5158: goto -> 5124
    //   5161: iload_1
    //   5162: tableswitch default -> 5196, -27 -> 5250, -26 -> 5196, -25 -> 5233, -24 -> 5216, -23 -> 5199
    //   5196: goto -> 5341
    //   5199: new f/zE
    //   5202: dup
    //   5203: astore_0
    //   5204: iload #7
    //   5206: aload #9
    //   5208: aload #10
    //   5210: invokespecial <init> : (B[I[S)V
    //   5213: goto -> 5343
    //   5216: new f/ID
    //   5219: dup
    //   5220: astore_0
    //   5221: iload #7
    //   5223: aload #9
    //   5225: aload #10
    //   5227: invokespecial <init> : (B[I[S)V
    //   5230: goto -> 5343
    //   5233: new f/j3
    //   5236: dup
    //   5237: astore_0
    //   5238: iload #7
    //   5240: aload #9
    //   5242: aload #10
    //   5244: invokespecial <init> : (B[I[S)V
    //   5247: goto -> 5343
    //   5250: new f/f
    //   5253: dup
    //   5254: astore_0
    //   5255: iload #7
    //   5257: aload #9
    //   5259: aload #10
    //   5261: invokespecial <init> : (B[I[S)V
    //   5264: goto -> 5343
    //   5267: new f/Ks
    //   5270: dup
    //   5271: astore_0
    //   5272: invokespecial <init> : ()V
    //   5275: goto -> 5343
    //   5278: aload_0
    //   5279: dup
    //   5280: dup2
    //   5281: new f/Ec0
    //   5284: astore_0
    //   5285: getfield Ws : Ljava/nio/ByteBuffer;
    //   5288: invokevirtual get : ()B
    //   5291: istore_1
    //   5292: getfield Ws : Ljava/nio/ByteBuffer;
    //   5295: invokevirtual get : ()B
    //   5298: istore #7
    //   5300: getfield Ws : Ljava/nio/ByteBuffer;
    //   5303: invokevirtual get : ()B
    //   5306: istore #8
    //   5308: getfield Ws : Ljava/nio/ByteBuffer;
    //   5311: invokevirtual get : ()B
    //   5314: iconst_1
    //   5315: if_icmpne -> 5324
    //   5318: iconst_1
    //   5319: istore #9
    //   5321: goto -> 5327
    //   5324: iconst_0
    //   5325: istore #9
    //   5327: aload_0
    //   5328: iload_1
    //   5329: iload #7
    //   5331: iload #8
    //   5333: iload #9
    //   5335: invokespecial <init> : (BBBZ)V
    //   5338: goto -> 5343
    //   5341: aconst_null
    //   5342: astore_0
    //   5343: aload_0
    //   5344: ifnonnull -> 5349
    //   5347: aconst_null
    //   5348: areturn
    //   5349: iload #5
    //   5351: aload_0
    //   5352: iload_2
    //   5353: putfield ig : B
    //   5356: iload_2
    //   5357: if_icmpne -> 5370
    //   5360: aload_0
    //   5361: dup
    //   5362: iload_3
    //   5363: putfield pn : I
    //   5366: iconst_1
    //   5367: invokevirtual zb : (B)V
    //   5370: iload #6
    //   5372: iload_2
    //   5373: if_icmpne -> 5387
    //   5376: aload_0
    //   5377: dup
    //   5378: iload #4
    //   5380: putfield b70 : I
    //   5383: iconst_2
    //   5384: invokevirtual zb : (B)V
    //   5387: aload_0
    //   5388: areturn
    // Line number table:
    //   Java source line number -> byte code offset
    //   #1	-> 2
    //   #2	-> 32
    //   #3	-> 700
    //   #4	-> 772
    //   #5	-> 780
    //   #6	-> 801
    //   #7	-> 807
    //   #8	-> 844
    //   #9	-> 851
    //   #10	-> 877
    //   #11	-> 883
    //   #12	-> 895
    //   #13	-> 901
    //   #14	-> 913
    //   #15	-> 919
    //   #16	-> 931
    //   #17	-> 938
    //   #18	-> 944
    //   #19	-> 957
    //   #20	-> 964
    //   #21	-> 981
    //   #22	-> 987
    //   #23	-> 999
    //   #24	-> 1005
    //   #25	-> 1017
    //   #26	-> 1024
    //   #27	-> 1030
    //   #28	-> 1042
    //   #29	-> 1048
    //   #30	-> 1060
    //   #31	-> 1066
    //   #32	-> 1078
    //   #33	-> 1084
    //   #34	-> 1096
    //   #35	-> 1102
    //   #36	-> 1116
    //   #37	-> 1124
    //   #38	-> 1132
    //   #39	-> 1142
    //   #40	-> 1184
    //   #41	-> 1196
    //   #42	-> 1202
    //   #43	-> 1214
    //   #44	-> 1223
    //   #45	-> 1230
    //   #46	-> 1258
    //   #47	-> 1272
    //   #48	-> 1285
    //   #49	-> 1303
    //   #50	-> 1316
    //   #51	-> 1328
    //   #52	-> 1334
    //   #53	-> 1346
    //   #54	-> 1352
    //   #55	-> 1360
    //   #56	-> 1367
    //   #57	-> 1421
    //   #58	-> 1427
    //   #59	-> 1456
    //   #60	-> 1463
    //   #61	-> 1488
    //   #62	-> 1494
    //   #63	-> 1521
    //   #64	-> 1527
    //   #65	-> 1534
    //   #66	-> 1542
    //   #67	-> 1552
    //   #68	-> 1568
    //   #69	-> 1584
    //   #70	-> 1590
    //   #71	-> 1594
    //   #72	-> 1627
    //   #73	-> 1639
    //   #74	-> 1645
    //   #75	-> 1657
    //   #76	-> 1663
    //   #77	-> 1675
    //   #78	-> 1681
    //   #79	-> 1688
    //   #80	-> 1696
    //   #81	-> 1706
    //   #82	-> 1722
    //   #83	-> 1736
    //   #84	-> 1755
    //   #85	-> 1767
    //   #86	-> 1773
    //   #87	-> 1785
    //   #88	-> 1791
    //   #89	-> 1803
    //   #90	-> 1810
    //   #91	-> 1833
    //   #92	-> 1862
    //   #93	-> 1874
    //   #94	-> 1881
    //   #95	-> 1887
    //   #96	-> 1918
    //   #97	-> 1924
    //   #98	-> 1937
    //   #99	-> 1944
    //   #100	-> 1951
    //   #101	-> 1963
    //   #102	-> 1976
    //   #103	-> 1988
    //   #104	-> 1994
    //   #105	-> 2001
    //   #106	-> 2012
    //   #107	-> 2025
    //   #108	-> 2034
    //   #109	-> 2054
    //   #110	-> 2060
    //   #111	-> 2085
    //   #112	-> 2091
    //   #113	-> 2124
    //   #114	-> 2130
    //   #115	-> 2142
    //   #116	-> 2148
    //   #117	-> 2160
    //   #118	-> 2166
    //   #119	-> 2178
    //   #120	-> 2184
    //   #121	-> 2192
    //   #122	-> 2211
    //   #123	-> 2220
    //   #124	-> 2238
    //   #125	-> 2255
    //   #126	-> 2264
    //   #127	-> 2279
    //   #128	-> 2292
    //   #129	-> 2304
    //   #130	-> 2310
    //   #131	-> 2325
    //   #132	-> 2331
    //   #133	-> 2354
    //   #134	-> 2360
    //   #135	-> 2372
    //   #136	-> 2378
    //   #137	-> 2390
    //   #138	-> 2398
    //   #139	-> 2405
    //   #140	-> 2412
    //   #141	-> 2424
    //   #142	-> 2437
    //   #143	-> 2460
    //   #144	-> 2466
    //   #145	-> 2478
    //   #146	-> 2491
    //   #147	-> 2503
    //   #148	-> 2509
    //   #149	-> 2532
    //   #150	-> 2538
    //   #151	-> 2543
    //   #152	-> 2549
    //   #153	-> 2553
    //   #154	-> 2561
    //   #155	-> 2568
    //   #156	-> 2576
    //   #157	-> 2586
    //   #158	-> 2602
    //   #159	-> 2612
    //   #160	-> 2620
    //   #161	-> 2638
    //   #162	-> 2644
    //   #163	-> 2670
    //   #164	-> 2676
    //   #165	-> 2688
    //   #166	-> 2694
    //   #167	-> 2706
    //   #168	-> 2712
    //   #169	-> 2724
    //   #170	-> 2733
    //   #171	-> 2739
    //   #172	-> 2743
    //   #173	-> 2764
    //   #174	-> 2776
    //   #175	-> 2789
    //   #176	-> 2801
    //   #177	-> 2814
    //   #178	-> 2826
    //   #179	-> 2832
    //   #180	-> 2844
    //   #181	-> 2850
    //   #182	-> 2857
    //   #183	-> 2867
    //   #184	-> 2875
    //   #185	-> 2920
    //   #186	-> 2943
    //   #187	-> 2971
    //   #188	-> 2978
    //   #189	-> 2984
    //   #190	-> 2996
    //   #191	-> 3002
    //   #192	-> 3014
    //   #193	-> 3020
    //   #194	-> 3032
    //   #195	-> 3038
    //   #196	-> 3050
    //   #197	-> 3057
    //   #198	-> 3063
    //   #199	-> 3075
    //   #200	-> 3081
    //   #201	-> 3093
    //   #202	-> 3099
    //   #203	-> 3112
    //   #204	-> 3120
    //   #205	-> 3131
    //   #206	-> 3159
    //   #207	-> 3171
    //   #208	-> 3177
    //   #209	-> 3184
    //   #210	-> 3192
    //   #211	-> 3204
    //   #212	-> 3223
    //   #213	-> 3231
    //   #214	-> 3257
    //   #215	-> 3263
    //   #216	-> 3297
    //   #217	-> 3303
    //   #218	-> 3353
    //   #219	-> 3359
    //   #220	-> 3371
    //   #221	-> 3377
    //   #222	-> 3385
    //   #223	-> 3392
    //   #224	-> 3401
    //   #225	-> 3419
    //   #226	-> 3425
    //   #227	-> 3436
    //   #228	-> 3444
    //   #229	-> 3460
    //   #230	-> 3466
    //   #231	-> 3471
    //   #232	-> 3479
    //   #233	-> 3491
    //   #234	-> 3497
    //   #235	-> 3501
    //   #236	-> 3507
    //   #237	-> 3550
    //   #238	-> 3557
    //   #239	-> 3564
    //   #240	-> 3576
    //   #241	-> 3582
    //   #242	-> 3598
    //   #243	-> 3638
    //   #244	-> 3677
    //   #245	-> 3683
    //   #246	-> 3695
    //   #247	-> 3708
    //   #248	-> 3715
    //   #249	-> 3724
    //   #250	-> 3748
    //   #251	-> 3771
    //   #252	-> 3778
    //   #253	-> 3786
    //   #254	-> 3811
    //   #255	-> 3823
    //   #256	-> 3829
    //   #257	-> 3841
    //   #258	-> 3847
    //   #259	-> 3870
    //   #260	-> 3876
    //   #261	-> 3888
    //   #262	-> 3894
    //   #263	-> 3906
    //   #264	-> 3912
    //   #265	-> 3923
    //   #266	-> 3942
    //   #267	-> 3954
    //   #268	-> 3962
    //   #269	-> 3968
    //   #270	-> 3972
    //   #271	-> 3980
    //   #272	-> 3986
    //   #273	-> 3992
    //   #274	-> 3998
    //   #275	-> 4002
    //   #276	-> 4008
    //   #277	-> 4020
    //   #278	-> 4026
    //   #279	-> 4030
    //   #280	-> 4037
    //   #281	-> 4049
    //   #282	-> 4055
    //   #283	-> 4067
    //   #284	-> 4073
    //   #285	-> 4139
    //   #286	-> 4145
    //   #287	-> 4191
    //   #288	-> 4197
    //   #289	-> 4204
    //   #290	-> 4213
    //   #291	-> 4218
    //   #292	-> 4231
    //   #293	-> 4251
    //   #294	-> 4271
    //   #295	-> 4281
    //   #296	-> 4310
    //   #297	-> 4323
    //   #298	-> 4340
    //   #299	-> 4355
    //   #300	-> 4361
    //   #301	-> 4373
    //   #302	-> 4379
    //   #303	-> 4391
    //   #304	-> 4397
    //   #305	-> 4409
    //   #306	-> 4415
    //   #307	-> 4427
    //   #308	-> 4433
    //   #309	-> 4445
    //   #310	-> 4451
    //   #311	-> 4463
    //   #312	-> 4469
    //   #313	-> 4473
    //   #314	-> 4479
    //   #315	-> 4502
    //   #316	-> 4508
    //   #317	-> 4520
    //   #318	-> 4526
    //   #319	-> 4538
    //   #320	-> 4544
    //   #321	-> 4556
    //   #322	-> 4562
    //   #323	-> 4574
    //   #324	-> 4580
    //   #325	-> 4592
    //   #326	-> 4598
    //   #327	-> 4605
    //   #328	-> 4613
    //   #329	-> 4632
    //   #330	-> 4638
    //   #331	-> 4650
    //   #332	-> 4666
    //   #333	-> 4685
    //   #334	-> 4691
    //   #335	-> 4720
    //   #336	-> 4726
    //   #337	-> 4738
    //   #338	-> 4768
    //   #339	-> 4775
    //   #340	-> 4791
    //   #341	-> 4795
    //   #342	-> 4803
    //   #343	-> 4811
    //   #344	-> 4823
    //   #345	-> 4831
    //   #346	-> 4835
    //   #347	-> 4873
    //   #348	-> 4887
    //   #349	-> 4919
    //   #350	-> 4934
    //   #351	-> 4941
    //   #352	-> 4949
    //   #353	-> 4964
    //   #354	-> 4987
    //   #355	-> 4999
    //   #356	-> 5005
    //   #357	-> 5017
    //   #358	-> 5024
    //   #359	-> 5036
    //   #360	-> 5042
    //   #361	-> 5061
    //   #362	-> 5067
    //   #363	-> 5079
    //   #364	-> 5085
    //   #365	-> 5095
    //   #366	-> 5113
    //   #367	-> 5141
    //   #368	-> 5147
    //   #369	-> 5148
    //   #370	-> 5154
    //   #371	-> 5285
    //   #372	-> 5335
    //   #373	-> 5353
    //   #374	-> 5363
    //   #375	-> 5380
  }
}


/* Location:              /Users/vnnsnnt/Documents/Codespace/JavaWorkspace/RedTrainer/src/main/java/org/trainer/client/PokeMMO.jar!/f/mL.class
 * Java compiler version: 8 (52.0)
 * JD-Core Version:       1.1.3
 */