package f;

public final class mO extends ZK0 {
  public final xr0 Zg0(KI paramKI, xr0 paramxr01, xr0 paramxr02, byte paramByte) {
    // Byte code:
    //   0: aload_3
    //   1: ifnull -> 31
    //   4: aload_3
    //   5: invokevirtual T9 : ()Z
    //   8: ifne -> 31
    //   11: aload_2
    //   12: invokevirtual i00 : ()F
    //   15: aload_3
    //   16: invokevirtual i00 : ()F
    //   19: fsub
    //   20: invokestatic abs : (F)F
    //   23: ldc 1.27
    //   25: fcmpg
    //   26: ifge -> 31
    //   29: aload_3
    //   30: areturn
    //   31: aload_2
    //   32: invokevirtual Y00 : ()Z
    //   35: ifeq -> 118
    //   38: aload_1
    //   39: aload_2
    //   40: iload #4
    //   42: iconst_1
    //   43: invokevirtual COm3 : (Lf/xr0;BI)Lf/xr0;
    //   46: dup
    //   47: astore_0
    //   48: iconst_0
    //   49: istore_3
    //   50: ifnull -> 64
    //   53: aload_0
    //   54: invokevirtual Y00 : ()Z
    //   57: ifeq -> 64
    //   60: iconst_1
    //   61: istore_3
    //   62: aload_0
    //   63: astore_2
    //   64: aload_1
    //   65: aload_2
    //   66: invokevirtual j5 : ()Lf/eo;
    //   69: getfield x : F
    //   72: f2i
    //   73: i2s
    //   74: aload_2
    //   75: dup
    //   76: invokevirtual j5 : ()Lf/eo;
    //   79: getfield z : F
    //   82: f2i
    //   83: i2s
    //   84: istore_0
    //   85: invokevirtual j5 : ()Lf/eo;
    //   88: getfield y : F
    //   91: iload_0
    //   92: swap
    //   93: invokevirtual U30 : (SSF)Lf/xr0;
    //   96: dup
    //   97: astore_0
    //   98: ifnonnull -> 103
    //   101: aconst_null
    //   102: areturn
    //   103: iload_3
    //   104: ifeq -> 109
    //   107: aload_0
    //   108: areturn
    //   109: aload_1
    //   110: aload_0
    //   111: iload #4
    //   113: iconst_1
    //   114: invokevirtual COm3 : (Lf/xr0;BI)Lf/xr0;
    //   117: areturn
    //   118: aload_3
    //   119: ifnonnull -> 124
    //   122: aconst_null
    //   123: areturn
    //   124: aload_1
    //   125: aload_2
    //   126: aload_3
    //   127: dup
    //   128: invokevirtual Ka : ()S
    //   131: i2f
    //   132: ldc 0.5
    //   134: fadd
    //   135: fstore_0
    //   136: invokevirtual hA0 : ()S
    //   139: i2f
    //   140: ldc 0.5
    //   142: fadd
    //   143: fstore_1
    //   144: invokevirtual i00 : ()F
    //   147: fstore_2
    //   148: fload_0
    //   149: fload_1
    //   150: fload_2
    //   151: invokevirtual XG0 : (FFF)Lf/xr0;
    //   154: areturn
  }
}


/* Location:              /Users/vnnsnnt/Documents/Codespace/JavaWorkspace/RedTrainer/src/main/java/org/trainer/client/PokeMMO.jar!/f/mO.class
 * Java compiler version: 8 (52.0)
 * JD-Core Version:       1.1.3
 */