package f;

import java.nio.ByteBuffer;

public abstract class mu0 {
  public static final ik WN = C00.gd(mu0.class);
  
  public static boolean Lj() {
    // Byte code:
    //   0: getstatic f/UB0.vj0 : Lf/XG;
    //   3: ldc 'data/data.pak'
    //   5: invokevirtual aP : (Ljava/lang/String;)Lf/hZ;
    //   8: invokevirtual iy0 : ()[B
    //   11: invokestatic HI0 : ([B)[B
    //   14: invokestatic wrap : ([B)Ljava/nio/ByteBuffer;
    //   17: getstatic java/nio/ByteOrder.LITTLE_ENDIAN : Ljava/nio/ByteOrder;
    //   20: invokevirtual order : (Ljava/nio/ByteOrder;)Ljava/nio/ByteBuffer;
    //   23: dup
    //   24: dup2
    //   25: astore_0
    //   26: invokevirtual position : ()I
    //   29: bipush #8
    //   31: iadd
    //   32: invokevirtual position : (I)Ljava/nio/Buffer;
    //   35: pop
    //   36: invokevirtual getInt : ()I
    //   39: istore_1
    //   40: bipush #126
    //   42: iload_1
    //   43: if_icmpeq -> 76
    //   46: getstatic f/mu0.WN : Lf/ik;
    //   49: new java/lang/StringBuilder
    //   52: dup
    //   53: invokespecial <init> : ()V
    //   56: ldc 'Mismatched data.pak version. Expected 126 got '
    //   58: invokevirtual append : (Ljava/lang/String;)Ljava/lang/StringBuilder;
    //   61: iload_1
    //   62: invokevirtual append : (I)Ljava/lang/StringBuilder;
    //   65: invokevirtual toString : ()Ljava/lang/String;
    //   68: invokeinterface error : (Ljava/lang/String;)V
    //   73: goto -> 95
    //   76: aload_0
    //   77: invokevirtual get : ()B
    //   80: istore_1
    //   81: iconst_0
    //   82: istore_2
    //   83: iload_2
    //   84: iload_1
    //   85: if_icmpge -> 105
    //   88: aload_0
    //   89: invokestatic zq : (Ljava/nio/ByteBuffer;)Z
    //   92: ifne -> 99
    //   95: iconst_0
    //   96: goto -> 122
    //   99: iinc #2, 1
    //   102: goto -> 83
    //   105: iconst_1
    //   106: goto -> 122
    //   109: astore_0
    //   110: getstatic f/mu0.WN : Lf/ik;
    //   113: ldc 'Error loading data package'
    //   115: aload_0
    //   116: invokeinterface error : (Ljava/lang/String;Ljava/lang/Throwable;)V
    //   121: iconst_0
    //   122: ireturn
    // Line number table:
    //   Java source line number -> byte code offset
    //   #1	-> 8
    // Exception table:
    //   from	to	target	type
    //   8	23	109	java/lang/Exception
    //   26	29	109	java/lang/Exception
    //   32	35	109	java/lang/Exception
    //   36	39	109	java/lang/Exception
    //   46	80	109	java/lang/Exception
    //   88	92	109	java/lang/Exception
  }
  
  public static boolean zq(ByteBuffer paramByteBuffer) {
    // Byte code:
    //   0: aload_0
    //   1: invokevirtual get : ()B
    //   4: aload_0
    //   5: invokevirtual getInt : ()I
    //   8: istore_1
    //   9: tableswitch default -> 84, 1 -> 2782, 2 -> 2582, 3 -> 2567, 4 -> 2014, 5 -> 1839, 6 -> 1354, 7 -> 1086, 8 -> 995, 9 -> 907, 10 -> 622, 11 -> 509, 12 -> 360, 13 -> 354, 14 -> 235, 15 -> 97
    //   84: aload_0
    //   85: dup
    //   86: invokevirtual position : ()I
    //   89: iload_1
    //   90: iadd
    //   91: invokevirtual position : (I)Ljava/nio/Buffer;
    //   94: pop
    //   95: iconst_1
    //   96: ireturn
    //   97: aload_0
    //   98: getstatic f/di.Dz0 : I
    //   101: pop
    //   102: invokevirtual getShort : ()S
    //   105: istore_1
    //   106: iconst_0
    //   107: istore_2
    //   108: iload_2
    //   109: iload_1
    //   110: if_icmpge -> 233
    //   113: aload_0
    //   114: dup
    //   115: invokevirtual get : ()B
    //   118: istore_3
    //   119: invokevirtual getShort : ()S
    //   122: istore #4
    //   124: getstatic f/G00.Av0 : Lf/G00;
    //   127: getfield Sl : Lf/ak;
    //   130: iload_3
    //   131: invokevirtual Ha0 : (B)Ljava/lang/Object;
    //   134: checkcast f/Le0
    //   137: dup
    //   138: astore_3
    //   139: getfield Gi0 : Lf/Ut0;
    //   142: iload #4
    //   144: invokevirtual Z6 : (I)Ljava/lang/Object;
    //   147: checkcast f/LJ
    //   150: dup
    //   151: astore #5
    //   153: ifnonnull -> 177
    //   156: aload_3
    //   157: new f/Yq0
    //   160: dup
    //   161: astore #5
    //   163: invokespecial <init> : ()V
    //   166: getfield Gi0 : Lf/Ut0;
    //   169: iload #4
    //   171: aload #5
    //   173: invokevirtual A3 : (ILjava/lang/Object;)Ljava/lang/Object;
    //   176: pop
    //   177: aload_0
    //   178: invokevirtual get : ()B
    //   181: dup
    //   182: istore_3
    //   183: iconst_1
    //   184: iand
    //   185: ifeq -> 197
    //   188: aload #5
    //   190: aload_0
    //   191: invokevirtual get : ()B
    //   194: putfield dc : B
    //   197: iload_3
    //   198: iconst_2
    //   199: iand
    //   200: ifeq -> 212
    //   203: aload #5
    //   205: aload_0
    //   206: invokevirtual get : ()B
    //   209: putfield Ap : B
    //   212: iload_3
    //   213: iconst_4
    //   214: iand
    //   215: ifeq -> 227
    //   218: aload #5
    //   220: aload_0
    //   221: invokevirtual get : ()B
    //   224: putfield YB0 : B
    //   227: iinc #2, 1
    //   230: goto -> 108
    //   233: iconst_1
    //   234: ireturn
    //   235: aload_0
    //   236: getstatic f/wh0.zz : I
    //   239: pop
    //   240: invokevirtual getShort : ()S
    //   243: istore_1
    //   244: iconst_0
    //   245: istore_2
    //   246: iload_2
    //   247: iload_1
    //   248: if_icmpge -> 352
    //   251: aload_0
    //   252: invokevirtual get : ()B
    //   255: istore_3
    //   256: getstatic f/Z4.T0 : Lf/Z4;
    //   259: dup
    //   260: astore #4
    //   262: getfield V1 : Lf/ak;
    //   265: iload_3
    //   266: invokevirtual Ha0 : (B)Ljava/lang/Object;
    //   269: checkcast f/ln0
    //   272: dup
    //   273: astore #5
    //   275: ifnonnull -> 300
    //   278: aload #4
    //   280: new f/ln0
    //   283: dup
    //   284: astore #5
    //   286: iload_3
    //   287: invokespecial <init> : (B)V
    //   290: getfield V1 : Lf/ak;
    //   293: iload_3
    //   294: aload #5
    //   296: invokevirtual VF : (BLjava/lang/Object;)Ljava/lang/Object;
    //   299: pop
    //   300: aload_0
    //   301: invokevirtual get : ()B
    //   304: dup
    //   305: istore_3
    //   306: iconst_1
    //   307: iand
    //   308: ifeq -> 320
    //   311: aload #5
    //   313: aload_0
    //   314: invokevirtual get : ()B
    //   317: putfield Im0 : B
    //   320: iload_3
    //   321: iconst_2
    //   322: iand
    //   323: ifeq -> 335
    //   326: aload #5
    //   328: aload_0
    //   329: invokevirtual get : ()B
    //   332: putfield cy : B
    //   335: iload_3
    //   336: iconst_4
    //   337: iand
    //   338: ifeq -> 346
    //   341: aload_0
    //   342: invokevirtual get : ()B
    //   345: pop
    //   346: iinc #2, 1
    //   349: goto -> 246
    //   352: iconst_1
    //   353: ireturn
    //   354: aload_0
    //   355: invokestatic Bx0 : (Ljava/nio/ByteBuffer;)V
    //   358: iconst_1
    //   359: ireturn
    //   360: aload_0
    //   361: invokevirtual getShort : ()S
    //   364: istore_1
    //   365: iconst_0
    //   366: istore_2
    //   367: iload_2
    //   368: iload_1
    //   369: if_icmpge -> 507
    //   372: aload_0
    //   373: dup
    //   374: dup2
    //   375: invokevirtual getShort : ()S
    //   378: istore_3
    //   379: invokevirtual getShort : ()S
    //   382: istore #4
    //   384: invokevirtual getShort : ()S
    //   387: istore #5
    //   389: invokevirtual get : ()B
    //   392: dup
    //   393: istore #6
    //   395: getstatic f/Ni.V10 : [Lf/kc;
    //   398: astore #7
    //   400: ifle -> 472
    //   403: new java/util/ArrayList
    //   406: dup
    //   407: astore #7
    //   409: invokespecial <init> : ()V
    //   412: iconst_0
    //   413: istore #8
    //   415: iload #8
    //   417: iload #6
    //   419: if_icmpge -> 458
    //   422: iload #8
    //   424: aload #7
    //   426: new f/kc
    //   429: dup
    //   430: aload_0
    //   431: dup
    //   432: invokevirtual getShort : ()S
    //   435: istore #8
    //   437: invokevirtual getShort : ()S
    //   440: iload #8
    //   442: swap
    //   443: invokespecial <init> : (SS)V
    //   446: invokevirtual add : (Ljava/lang/Object;)Z
    //   449: pop
    //   450: iconst_1
    //   451: iadd
    //   452: i2s
    //   453: istore #8
    //   455: goto -> 415
    //   458: aload #7
    //   460: iconst_0
    //   461: anewarray f/kc
    //   464: invokevirtual toArray : ([Ljava/lang/Object;)[Ljava/lang/Object;
    //   467: checkcast [Lf/kc;
    //   470: astore #7
    //   472: iload_2
    //   473: getstatic f/bl0.DO : Lf/bl0;
    //   476: new f/Ni
    //   479: dup
    //   480: astore_2
    //   481: iload_3
    //   482: aload #7
    //   484: iload #4
    //   486: iload #5
    //   488: invokespecial <init> : (S[Lf/kc;SS)V
    //   491: getfield Nw0 : Lf/qw0;
    //   494: iload_3
    //   495: aload_2
    //   496: invokevirtual Vh0 : (SLjava/lang/Object;)Ljava/lang/Object;
    //   499: pop
    //   500: iconst_1
    //   501: iadd
    //   502: i2s
    //   503: istore_2
    //   504: goto -> 367
    //   507: iconst_1
    //   508: ireturn
    //   509: aload_0
    //   510: invokevirtual get : ()B
    //   513: istore_1
    //   514: iconst_0
    //   515: istore_2
    //   516: iload_2
    //   517: iload_1
    //   518: if_icmpge -> 620
    //   521: aload_0
    //   522: dup
    //   523: invokevirtual get : ()B
    //   526: istore_3
    //   527: invokevirtual getShort : ()S
    //   530: istore #4
    //   532: iconst_1
    //   533: istore #5
    //   535: iload #5
    //   537: iload #4
    //   539: iconst_1
    //   540: iadd
    //   541: if_icmpge -> 612
    //   544: aload_0
    //   545: invokevirtual getShort : ()S
    //   548: invokestatic v30 : ()Lf/On;
    //   551: swap
    //   552: invokevirtual lpT3 : (S)Lf/UD0;
    //   555: dup
    //   556: astore #6
    //   558: ifnull -> 602
    //   561: iload_3
    //   562: iflt -> 590
    //   565: iload_3
    //   566: aload #6
    //   568: getfield G1 : [S
    //   571: dup
    //   572: astore #7
    //   574: arraylength
    //   575: if_icmplt -> 581
    //   578: goto -> 590
    //   581: aload #7
    //   583: iload_3
    //   584: iload #5
    //   586: sastore
    //   587: goto -> 602
    //   590: aload #6
    //   592: getfield G1 : [S
    //   595: dup
    //   596: arraylength
    //   597: iconst_1
    //   598: isub
    //   599: iload #5
    //   601: sastore
    //   602: iload #5
    //   604: iconst_1
    //   605: iadd
    //   606: i2s
    //   607: istore #5
    //   609: goto -> 535
    //   612: iload_2
    //   613: iconst_1
    //   614: iadd
    //   615: i2b
    //   616: istore_2
    //   617: goto -> 516
    //   620: iconst_1
    //   621: ireturn
    //   622: aload_0
    //   623: invokevirtual getShort : ()S
    //   626: istore_1
    //   627: iconst_0
    //   628: istore_2
    //   629: iload_2
    //   630: iload_1
    //   631: if_icmpge -> 905
    //   634: aload_0
    //   635: invokevirtual getShort : ()S
    //   638: istore_3
    //   639: new f/UD0
    //   642: dup
    //   643: dup
    //   644: astore #4
    //   646: aload_0
    //   647: aload #4
    //   649: dup
    //   650: dup2
    //   651: iload_3
    //   652: invokespecial <init> : (S)V
    //   655: iconst_1
    //   656: putfield lS : Z
    //   659: getstatic f/Ls0.yi : Lf/Ls0;
    //   662: dup
    //   663: astore_3
    //   664: putfield I30 : Lf/Ls0;
    //   667: aload_3
    //   668: putfield LPt6 : Lf/Ls0;
    //   671: invokevirtual get : ()B
    //   674: invokestatic Gt0 : (B)Lf/Ht0;
    //   677: aload_0
    //   678: invokevirtual get : ()B
    //   681: invokestatic Gt0 : (B)Lf/Ht0;
    //   684: astore_3
    //   685: putfield FH : Lf/Ht0;
    //   688: aload_3
    //   689: putfield e6 : Lf/Ht0;
    //   692: getstatic f/hR.ka : [Lf/hR;
    //   695: dup
    //   696: astore_3
    //   697: arraylength
    //   698: istore #5
    //   700: iconst_0
    //   701: istore #6
    //   703: iload #6
    //   705: iload #5
    //   707: if_icmpge -> 830
    //   710: aload_0
    //   711: aload_3
    //   712: iload #6
    //   714: aaload
    //   715: astore #7
    //   717: invokevirtual getShort : ()S
    //   720: istore #8
    //   722: aload #7
    //   724: invokevirtual ordinal : ()I
    //   727: tableswitch default -> 764, 0 -> 817, 1 -> 807, 2 -> 797, 3 -> 787, 4 -> 777, 5 -> 767
    //   764: goto -> 824
    //   767: aload #4
    //   769: iload #8
    //   771: putfield ha0 : I
    //   774: goto -> 824
    //   777: aload #4
    //   779: iload #8
    //   781: putfield j90 : I
    //   784: goto -> 824
    //   787: aload #4
    //   789: iload #8
    //   791: putfield qA0 : I
    //   794: goto -> 824
    //   797: aload #4
    //   799: iload #8
    //   801: putfield UH0 : I
    //   804: goto -> 824
    //   807: aload #4
    //   809: iload #8
    //   811: putfield dv0 : I
    //   814: goto -> 824
    //   817: aload #4
    //   819: iload #8
    //   821: putfield my0 : I
    //   824: iinc #6, 1
    //   827: goto -> 703
    //   830: iconst_0
    //   831: istore_3
    //   832: iload_3
    //   833: iconst_3
    //   834: if_icmpge -> 870
    //   837: iload_3
    //   838: aload_0
    //   839: invokevirtual getShort : ()S
    //   842: istore #5
    //   844: iflt -> 864
    //   847: iload_3
    //   848: iconst_2
    //   849: if_icmple -> 855
    //   852: goto -> 864
    //   855: aload #4
    //   857: getfield Po : [S
    //   860: iload_3
    //   861: iload #5
    //   863: sastore
    //   864: iinc #3, 1
    //   867: goto -> 832
    //   870: aload #4
    //   872: aload_0
    //   873: invokevirtual getShort : ()S
    //   876: putfield FD : I
    //   879: invokestatic v30 : ()Lf/On;
    //   882: getfield iI0 : Ljava/util/HashMap;
    //   885: aload #4
    //   887: getfield AP : S
    //   890: invokestatic valueOf : (S)Ljava/lang/Short;
    //   893: aload #4
    //   895: invokevirtual put : (Ljava/lang/Object;Ljava/lang/Object;)Ljava/lang/Object;
    //   898: pop
    //   899: iinc #2, 1
    //   902: goto -> 629
    //   905: iconst_1
    //   906: ireturn
    //   907: aload_0
    //   908: invokevirtual getShort : ()S
    //   911: istore_1
    //   912: iconst_0
    //   913: istore_2
    //   914: iload_2
    //   915: iload_1
    //   916: if_icmpge -> 993
    //   919: aload_0
    //   920: invokevirtual getShort : ()S
    //   923: istore_3
    //   924: getstatic f/Sg0.Tn : Lf/Sg0;
    //   927: new f/rj
    //   930: dup
    //   931: astore #4
    //   933: iload_3
    //   934: aload_0
    //   935: dup
    //   936: dup
    //   937: dup2
    //   938: invokevirtual get : ()B
    //   941: getstatic f/Gv.ib0 : Lf/ak;
    //   944: swap
    //   945: invokevirtual Ha0 : (B)Ljava/lang/Object;
    //   948: checkcast f/Gv
    //   951: astore #5
    //   953: invokevirtual getInt : ()I
    //   956: pop
    //   957: invokevirtual getShort : ()S
    //   960: pop
    //   961: invokevirtual getFloat : ()F
    //   964: fstore #6
    //   966: invokevirtual getShort : ()S
    //   969: pop
    //   970: aload #5
    //   972: fload #6
    //   974: invokespecial <init> : (SLf/Gv;F)V
    //   977: getfield p90 : Lf/qw0;
    //   980: iload_3
    //   981: aload #4
    //   983: invokevirtual Vh0 : (SLjava/lang/Object;)Ljava/lang/Object;
    //   986: pop
    //   987: iinc #2, 1
    //   990: goto -> 914
    //   993: iconst_1
    //   994: ireturn
    //   995: aload_0
    //   996: invokevirtual getShort : ()S
    //   999: istore_1
    //   1000: iconst_0
    //   1001: istore_2
    //   1002: iload_2
    //   1003: iload_1
    //   1004: if_icmpge -> 1084
    //   1007: aload_0
    //   1008: dup
    //   1009: dup
    //   1010: dup2
    //   1011: dup2
    //   1012: invokevirtual get : ()B
    //   1015: istore_3
    //   1016: invokevirtual get : ()B
    //   1019: istore #4
    //   1021: invokevirtual getInt : ()I
    //   1024: istore #5
    //   1026: invokevirtual getInt : ()I
    //   1029: pop
    //   1030: invokevirtual get : ()B
    //   1033: istore #6
    //   1035: invokevirtual get : ()B
    //   1038: istore #7
    //   1040: invokevirtual getShort : ()S
    //   1043: istore #8
    //   1045: getstatic f/LPT5.tD0 : Lf/LPT5;
    //   1048: new f/iq
    //   1051: dup
    //   1052: astore #9
    //   1054: iload_3
    //   1055: iload #4
    //   1057: iload #5
    //   1059: iload #6
    //   1061: iload #7
    //   1063: iload #8
    //   1065: invokespecial <init> : (BBIBBS)V
    //   1068: getfield EJ0 : Lf/ak;
    //   1071: iload_3
    //   1072: aload #9
    //   1074: invokevirtual VF : (BLjava/lang/Object;)Ljava/lang/Object;
    //   1077: pop
    //   1078: iinc #2, 1
    //   1081: goto -> 1002
    //   1084: iconst_1
    //   1085: ireturn
    //   1086: aload_0
    //   1087: invokevirtual getShort : ()S
    //   1090: istore_1
    //   1091: iconst_0
    //   1092: istore_2
    //   1093: iload_2
    //   1094: iload_1
    //   1095: if_icmpge -> 1352
    //   1098: aload_0
    //   1099: invokevirtual getShort : ()S
    //   1102: istore_3
    //   1103: iconst_5
    //   1104: newarray int
    //   1106: astore #4
    //   1108: iconst_0
    //   1109: istore #5
    //   1111: iload #5
    //   1113: iconst_5
    //   1114: if_icmpge -> 1133
    //   1117: aload #4
    //   1119: aload_0
    //   1120: invokevirtual get : ()B
    //   1123: iload #5
    //   1125: swap
    //   1126: iastore
    //   1127: iinc #5, 1
    //   1130: goto -> 1111
    //   1133: aload_0
    //   1134: dup
    //   1135: dup2
    //   1136: dup2
    //   1137: invokevirtual get : ()B
    //   1140: istore #5
    //   1142: invokevirtual get : ()B
    //   1145: istore #6
    //   1147: invokevirtual getShort : ()S
    //   1150: istore #7
    //   1152: invokevirtual get : ()B
    //   1155: istore #8
    //   1157: invokevirtual get : ()B
    //   1160: istore #9
    //   1162: invokevirtual getShort : ()S
    //   1165: istore #10
    //   1167: getstatic f/Of.eH : Lf/Of;
    //   1170: dup
    //   1171: invokevirtual getClass : ()Ljava/lang/Class;
    //   1174: pop
    //   1175: new java/util/ArrayList
    //   1178: dup
    //   1179: astore #11
    //   1181: invokespecial <init> : ()V
    //   1184: getfield cOm7 : Ljava/util/TreeMap;
    //   1187: invokevirtual values : ()Ljava/util/Collection;
    //   1190: invokeinterface iterator : ()Ljava/util/Iterator;
    //   1195: astore #12
    //   1197: aload #12
    //   1199: invokeinterface hasNext : ()Z
    //   1204: ifeq -> 1269
    //   1207: aload #12
    //   1209: invokeinterface next : ()Ljava/lang/Object;
    //   1214: checkcast f/LPT3
    //   1217: dup
    //   1218: astore #13
    //   1220: getfield bj0 : S
    //   1223: iload_3
    //   1224: if_icmpeq -> 1258
    //   1227: aload #13
    //   1229: getfield YB : S
    //   1232: dup
    //   1233: istore #14
    //   1235: ifle -> 1244
    //   1238: iconst_1
    //   1239: istore #15
    //   1241: goto -> 1247
    //   1244: iconst_0
    //   1245: istore #15
    //   1247: iload #15
    //   1249: ifeq -> 1197
    //   1252: iload #14
    //   1254: iload_3
    //   1255: if_icmpne -> 1197
    //   1258: aload #11
    //   1260: aload #13
    //   1262: invokevirtual add : (Ljava/lang/Object;)Z
    //   1265: pop
    //   1266: goto -> 1197
    //   1269: aload #11
    //   1271: invokevirtual iterator : ()Ljava/util/Iterator;
    //   1274: astore_3
    //   1275: aload_3
    //   1276: invokeinterface hasNext : ()Z
    //   1281: ifeq -> 1346
    //   1284: aload_3
    //   1285: invokeinterface next : ()Ljava/lang/Object;
    //   1290: checkcast f/LPT3
    //   1293: dup
    //   1294: astore #11
    //   1296: iload #10
    //   1298: aload #11
    //   1300: iload #9
    //   1302: aload #11
    //   1304: iload #8
    //   1306: aload #11
    //   1308: iload #7
    //   1310: aload #11
    //   1312: iload #6
    //   1314: aload #11
    //   1316: iload #5
    //   1318: aload #11
    //   1320: aload #4
    //   1322: putfield iI0 : [I
    //   1325: putfield kU : B
    //   1328: putfield Sd0 : B
    //   1331: putfield nk0 : S
    //   1334: putfield ab : B
    //   1337: putfield iY : B
    //   1340: putfield Dw : S
    //   1343: goto -> 1275
    //   1346: iinc #2, 1
    //   1349: goto -> 1093
    //   1352: iconst_1
    //   1353: ireturn
    //   1354: aload_0
    //   1355: invokevirtual getShort : ()S
    //   1358: istore_1
    //   1359: iconst_0
    //   1360: istore_2
    //   1361: iload_2
    //   1362: iload_1
    //   1363: if_icmpge -> 1837
    //   1366: aload_0
    //   1367: dup
    //   1368: invokevirtual getShort : ()S
    //   1371: istore_3
    //   1372: invokevirtual getShort : ()S
    //   1375: istore #4
    //   1377: invokestatic v30 : ()Lf/On;
    //   1380: iload_3
    //   1381: invokevirtual lpT3 : (S)Lf/UD0;
    //   1384: dup
    //   1385: astore #5
    //   1387: ifnonnull -> 1400
    //   1390: new f/UD0
    //   1393: dup
    //   1394: astore #5
    //   1396: iload_3
    //   1397: invokespecial <init> : (S)V
    //   1400: iload #4
    //   1402: iconst_1
    //   1403: iand
    //   1404: ifeq -> 1449
    //   1407: aload #5
    //   1409: dup
    //   1410: aload_0
    //   1411: invokevirtual get : ()B
    //   1414: istore_3
    //   1415: getstatic f/Ls0.a7 : Lf/ak;
    //   1418: dup
    //   1419: aload_0
    //   1420: swap
    //   1421: iload_3
    //   1422: invokevirtual Ha0 : (B)Ljava/lang/Object;
    //   1425: checkcast f/Ls0
    //   1428: astore_3
    //   1429: invokevirtual get : ()B
    //   1432: invokevirtual Ha0 : (B)Ljava/lang/Object;
    //   1435: checkcast f/Ls0
    //   1438: astore #6
    //   1440: aload_3
    //   1441: putfield I30 : Lf/Ls0;
    //   1444: aload #6
    //   1446: putfield LPt6 : Lf/Ls0;
    //   1449: iload #4
    //   1451: iconst_2
    //   1452: iand
    //   1453: ifeq -> 1462
    //   1456: aload #5
    //   1458: iconst_1
    //   1459: putfield lS : Z
    //   1462: iload #4
    //   1464: bipush #64
    //   1466: iand
    //   1467: ifeq -> 1476
    //   1470: aload #5
    //   1472: iconst_1
    //   1473: putfield hL : Z
    //   1476: iload #4
    //   1478: iconst_4
    //   1479: iand
    //   1480: ifeq -> 1638
    //   1483: getstatic f/hR.Tt0 : [Lf/hR;
    //   1486: dup
    //   1487: astore_3
    //   1488: arraylength
    //   1489: istore #6
    //   1491: iconst_0
    //   1492: istore #7
    //   1494: iload #7
    //   1496: iload #6
    //   1498: if_icmpge -> 1638
    //   1501: aload_3
    //   1502: iload #7
    //   1504: aaload
    //   1505: dup
    //   1506: astore #8
    //   1508: getfield NT : Z
    //   1511: ifeq -> 1517
    //   1514: goto -> 1632
    //   1517: aload_0
    //   1518: invokevirtual getShort : ()S
    //   1521: dup
    //   1522: istore #9
    //   1524: iconst_m1
    //   1525: if_icmpeq -> 1632
    //   1528: aload #8
    //   1530: invokevirtual ordinal : ()I
    //   1533: tableswitch default -> 1572, 0 -> 1625, 1 -> 1615, 2 -> 1605, 3 -> 1595, 4 -> 1585, 5 -> 1575
    //   1572: goto -> 1632
    //   1575: aload #5
    //   1577: iload #9
    //   1579: putfield ha0 : I
    //   1582: goto -> 1632
    //   1585: aload #5
    //   1587: iload #9
    //   1589: putfield j90 : I
    //   1592: goto -> 1632
    //   1595: aload #5
    //   1597: iload #9
    //   1599: putfield qA0 : I
    //   1602: goto -> 1632
    //   1605: aload #5
    //   1607: iload #9
    //   1609: putfield UH0 : I
    //   1612: goto -> 1632
    //   1615: aload #5
    //   1617: iload #9
    //   1619: putfield dv0 : I
    //   1622: goto -> 1632
    //   1625: aload #5
    //   1627: iload #9
    //   1629: putfield my0 : I
    //   1632: iinc #7, 1
    //   1635: goto -> 1494
    //   1638: iload #4
    //   1640: bipush #8
    //   1642: iand
    //   1643: ifeq -> 1686
    //   1646: iconst_0
    //   1647: istore_3
    //   1648: iload_3
    //   1649: iconst_3
    //   1650: if_icmpge -> 1686
    //   1653: iload_3
    //   1654: aload_0
    //   1655: invokevirtual getShort : ()S
    //   1658: istore #6
    //   1660: iflt -> 1680
    //   1663: iload_3
    //   1664: iconst_2
    //   1665: if_icmple -> 1671
    //   1668: goto -> 1680
    //   1671: aload #5
    //   1673: getfield Po : [S
    //   1676: iload_3
    //   1677: iload #6
    //   1679: sastore
    //   1680: iinc #3, 1
    //   1683: goto -> 1648
    //   1686: iload #4
    //   1688: bipush #16
    //   1690: iand
    //   1691: ifeq -> 1767
    //   1694: aload #5
    //   1696: aload_0
    //   1697: invokevirtual getShort : ()S
    //   1700: putfield jt : S
    //   1703: getstatic f/hR.Tt0 : [Lf/hR;
    //   1706: dup
    //   1707: astore_3
    //   1708: arraylength
    //   1709: istore #6
    //   1711: iconst_0
    //   1712: istore #7
    //   1714: iload #7
    //   1716: iload #6
    //   1718: if_icmpge -> 1767
    //   1721: aload_3
    //   1722: iload #7
    //   1724: aaload
    //   1725: dup
    //   1726: astore #8
    //   1728: getfield NT : Z
    //   1731: ifeq -> 1737
    //   1734: goto -> 1761
    //   1737: aload #5
    //   1739: getfield HL0 : [B
    //   1742: aload #8
    //   1744: getfield dL : B
    //   1747: dup
    //   1748: aload #5
    //   1750: getfield jt : S
    //   1753: swap
    //   1754: iconst_2
    //   1755: imul
    //   1756: ishr
    //   1757: iconst_3
    //   1758: iand
    //   1759: i2b
    //   1760: bastore
    //   1761: iinc #7, 1
    //   1764: goto -> 1714
    //   1767: iload #4
    //   1769: bipush #32
    //   1771: iand
    //   1772: ifeq -> 1817
    //   1775: aload_0
    //   1776: invokevirtual get : ()B
    //   1779: dup
    //   1780: istore_3
    //   1781: newarray short
    //   1783: astore #6
    //   1785: iconst_0
    //   1786: istore #7
    //   1788: iload #7
    //   1790: iload_3
    //   1791: if_icmpge -> 1810
    //   1794: aload #6
    //   1796: aload_0
    //   1797: invokevirtual getShort : ()S
    //   1800: iload #7
    //   1802: swap
    //   1803: sastore
    //   1804: iinc #7, 1
    //   1807: goto -> 1788
    //   1810: aload #5
    //   1812: aload #6
    //   1814: putfield Ny : [S
    //   1817: iload #4
    //   1819: sipush #128
    //   1822: iand
    //   1823: ifeq -> 1831
    //   1826: aload_0
    //   1827: invokevirtual getShort : ()S
    //   1830: pop
    //   1831: iinc #2, 1
    //   1834: goto -> 1361
    //   1837: iconst_1
    //   1838: ireturn
    //   1839: aload_0
    //   1840: invokevirtual getShort : ()S
    //   1843: istore_1
    //   1844: iconst_0
    //   1845: istore_2
    //   1846: iload_2
    //   1847: iload_1
    //   1848: if_icmpge -> 2012
    //   1851: aload_0
    //   1852: dup
    //   1853: invokevirtual getShort : ()S
    //   1856: istore_3
    //   1857: new f/Jt
    //   1860: dup
    //   1861: astore #4
    //   1863: iload_3
    //   1864: invokespecial <init> : (S)V
    //   1867: invokevirtual getShort : ()S
    //   1870: istore_3
    //   1871: iconst_0
    //   1872: istore #5
    //   1874: iload #5
    //   1876: iload_3
    //   1877: if_icmpge -> 1989
    //   1880: aload #4
    //   1882: new f/Hq
    //   1885: dup
    //   1886: astore #6
    //   1888: aload_0
    //   1889: dup
    //   1890: dup2
    //   1891: dup2
    //   1892: dup2
    //   1893: dup2
    //   1894: invokevirtual get : ()B
    //   1897: istore #7
    //   1899: invokevirtual getShort : ()S
    //   1902: pop
    //   1903: invokevirtual get : ()B
    //   1906: istore #8
    //   1908: invokevirtual get : ()B
    //   1911: getstatic f/pM.m30 : Lf/ak;
    //   1914: swap
    //   1915: invokevirtual Ha0 : (B)Ljava/lang/Object;
    //   1918: checkcast f/pM
    //   1921: astore #9
    //   1923: invokevirtual get : ()B
    //   1926: istore #10
    //   1928: invokevirtual get : ()B
    //   1931: istore #11
    //   1933: invokevirtual get : ()B
    //   1936: istore #12
    //   1938: invokevirtual getShort : ()S
    //   1941: istore #13
    //   1943: invokevirtual get : ()B
    //   1946: istore #14
    //   1948: invokevirtual get : ()B
    //   1951: istore #15
    //   1953: iload #7
    //   1955: iload #8
    //   1957: aload #9
    //   1959: iload #10
    //   1961: iload #11
    //   1963: iload #12
    //   1965: iload #13
    //   1967: iload #14
    //   1969: iload #15
    //   1971: invokespecial <init> : (BBLf/pM;BBBSBB)V
    //   1974: getfield s20 : Ljava/util/ArrayList;
    //   1977: aload #6
    //   1979: invokevirtual add : (Ljava/lang/Object;)Z
    //   1982: pop
    //   1983: iinc #5, 1
    //   1986: goto -> 1874
    //   1989: getstatic f/k50.Gp : Lf/k50;
    //   1992: getfield g90 : Lf/qw0;
    //   1995: aload #4
    //   1997: getfield qg : S
    //   2000: aload #4
    //   2002: invokevirtual Vh0 : (SLjava/lang/Object;)Ljava/lang/Object;
    //   2005: pop
    //   2006: iinc #2, 1
    //   2009: goto -> 1846
    //   2012: iconst_1
    //   2013: ireturn
    //   2014: aload_0
    //   2015: new f/Av
    //   2018: dup
    //   2019: astore_1
    //   2020: aload_0
    //   2021: invokespecial <init> : (Ljava/nio/ByteBuffer;)V
    //   2024: invokevirtual getShort : ()S
    //   2027: istore_2
    //   2028: iconst_0
    //   2029: istore_3
    //   2030: iload_3
    //   2031: iload_2
    //   2032: if_icmpge -> 2565
    //   2035: aload_0
    //   2036: dup
    //   2037: invokevirtual getShort : ()S
    //   2040: istore #4
    //   2042: invokevirtual get : ()B
    //   2045: istore #5
    //   2047: getstatic f/YB0.SH0 : Lf/ak;
    //   2050: dup
    //   2051: astore #6
    //   2053: iload #5
    //   2055: invokevirtual db0 : (B)Z
    //   2058: ifeq -> 2076
    //   2061: aload #6
    //   2063: iload #5
    //   2065: invokevirtual Ha0 : (B)Ljava/lang/Object;
    //   2068: checkcast f/YB0
    //   2071: astore #5
    //   2073: goto -> 2081
    //   2076: getstatic f/YB0.tI0 : Lf/YB0;
    //   2079: astore #5
    //   2081: aload_0
    //   2082: invokevirtual getShort : ()S
    //   2085: istore #6
    //   2087: invokestatic cw : ()Lf/yk0;
    //   2090: iload #4
    //   2092: invokevirtual mP : (S)Lf/WD;
    //   2095: dup
    //   2096: astore #7
    //   2098: ifnonnull -> 2132
    //   2101: new f/WD
    //   2104: dup
    //   2105: astore #7
    //   2107: iload #4
    //   2109: getstatic f/Ht0.P00 : Lf/Ht0;
    //   2112: invokespecial <init> : (SLf/Ht0;)V
    //   2115: invokestatic cw : ()Lf/yk0;
    //   2118: getfield iu : Lf/qw0;
    //   2121: aload #7
    //   2123: getfield HA : S
    //   2126: aload #7
    //   2128: invokevirtual Vh0 : (SLjava/lang/Object;)Ljava/lang/Object;
    //   2131: pop
    //   2132: iload #6
    //   2134: aload #7
    //   2136: aload #5
    //   2138: putfield Iq : Lf/YB0;
    //   2141: iconst_1
    //   2142: iand
    //   2143: ifeq -> 2155
    //   2146: aload #7
    //   2148: aload_0
    //   2149: invokevirtual get : ()B
    //   2152: putfield Jp0 : B
    //   2155: iload #6
    //   2157: iconst_2
    //   2158: iand
    //   2159: ifeq -> 2171
    //   2162: aload #7
    //   2164: aload_0
    //   2165: invokevirtual getShort : ()S
    //   2168: putfield Di0 : S
    //   2171: iload #6
    //   2173: iconst_4
    //   2174: iand
    //   2175: ifeq -> 2187
    //   2178: aload #7
    //   2180: aload_0
    //   2181: invokevirtual get : ()B
    //   2184: putfield nul : B
    //   2187: iload #6
    //   2189: bipush #8
    //   2191: iand
    //   2192: ifeq -> 2207
    //   2195: aload #7
    //   2197: aload_0
    //   2198: invokevirtual get : ()B
    //   2201: invokestatic Gt0 : (B)Lf/Ht0;
    //   2204: putfield wJ0 : Lf/Ht0;
    //   2207: iload #6
    //   2209: bipush #16
    //   2211: iand
    //   2212: ifeq -> 2224
    //   2215: aload #7
    //   2217: aload_0
    //   2218: invokevirtual getShort : ()S
    //   2221: putfield f50 : S
    //   2224: iload #6
    //   2226: bipush #32
    //   2228: iand
    //   2229: ifeq -> 2241
    //   2232: aload #7
    //   2234: aload_0
    //   2235: invokevirtual get : ()B
    //   2238: putfield VT : B
    //   2241: iload #6
    //   2243: bipush #64
    //   2245: iand
    //   2246: ifeq -> 2258
    //   2249: aload #7
    //   2251: aload_0
    //   2252: invokevirtual get : ()B
    //   2255: putfield DD : B
    //   2258: iload #6
    //   2260: sipush #128
    //   2263: iand
    //   2264: ifeq -> 2273
    //   2267: iconst_1
    //   2268: istore #4
    //   2270: goto -> 2276
    //   2273: iconst_0
    //   2274: istore #4
    //   2276: iload #6
    //   2278: aload #7
    //   2280: iload #4
    //   2282: putfield WS : Z
    //   2285: sipush #256
    //   2288: iand
    //   2289: ifeq -> 2301
    //   2292: aload #7
    //   2294: aload_0
    //   2295: invokevirtual get : ()B
    //   2298: putfield XT : B
    //   2301: iload #6
    //   2303: sipush #512
    //   2306: iand
    //   2307: ifeq -> 2460
    //   2310: aload_0
    //   2311: invokevirtual get : ()B
    //   2314: dup
    //   2315: istore #4
    //   2317: anewarray f/hR
    //   2320: astore #5
    //   2322: iconst_0
    //   2323: istore #6
    //   2325: iload #6
    //   2327: iload #4
    //   2329: if_icmpge -> 2350
    //   2332: aload #5
    //   2334: iload #6
    //   2336: aload_0
    //   2337: invokevirtual get : ()B
    //   2340: invokestatic aU : (B)Lf/hR;
    //   2343: aastore
    //   2344: iinc #6, 1
    //   2347: goto -> 2325
    //   2350: aload_0
    //   2351: dup
    //   2352: invokevirtual get : ()B
    //   2355: istore #4
    //   2357: invokevirtual get : ()B
    //   2360: dup
    //   2361: istore #6
    //   2363: anewarray f/hR
    //   2366: astore #8
    //   2368: iconst_0
    //   2369: istore #9
    //   2371: iload #9
    //   2373: iload #6
    //   2375: if_icmpge -> 2396
    //   2378: aload #8
    //   2380: iload #9
    //   2382: aload_0
    //   2383: invokevirtual get : ()B
    //   2386: invokestatic aU : (B)Lf/hR;
    //   2389: aastore
    //   2390: iinc #9, 1
    //   2393: goto -> 2371
    //   2396: aload_0
    //   2397: dup
    //   2398: invokevirtual get : ()B
    //   2401: istore #6
    //   2403: invokevirtual get : ()B
    //   2406: iconst_1
    //   2407: if_icmpne -> 2416
    //   2410: iconst_1
    //   2411: istore #9
    //   2413: goto -> 2419
    //   2416: iconst_0
    //   2417: istore #9
    //   2419: aload #7
    //   2421: dup
    //   2422: dup2
    //   2423: dup2
    //   2424: aload_0
    //   2425: invokevirtual get : ()B
    //   2428: istore #10
    //   2430: aload #5
    //   2432: putfield sK0 : [Lf/hR;
    //   2435: aload #8
    //   2437: putfield pr0 : [Lf/hR;
    //   2440: iload #4
    //   2442: putfield ha : B
    //   2445: iload #6
    //   2447: putfield I80 : B
    //   2450: iload #9
    //   2452: putfield Zo : Z
    //   2455: iload #10
    //   2457: putfield oV : B
    //   2460: aload_0
    //   2461: invokevirtual get : ()B
    //   2464: dup
    //   2465: istore #4
    //   2467: anewarray f/uj
    //   2470: astore #5
    //   2472: iconst_0
    //   2473: istore #6
    //   2475: iload #6
    //   2477: iload #4
    //   2479: if_icmpge -> 2552
    //   2482: aload_0
    //   2483: dup
    //   2484: invokevirtual getInt : ()I
    //   2487: istore #8
    //   2489: invokevirtual get : ()B
    //   2492: dup
    //   2493: istore #9
    //   2495: anewarray f/LPT1
    //   2498: astore #10
    //   2500: iconst_0
    //   2501: istore #11
    //   2503: iload #11
    //   2505: iload #9
    //   2507: if_icmpge -> 2526
    //   2510: aload #10
    //   2512: aload_1
    //   2513: invokevirtual Ac : ()Lf/LPT1;
    //   2516: iload #11
    //   2518: swap
    //   2519: aastore
    //   2520: iinc #11, 1
    //   2523: goto -> 2503
    //   2526: aload #5
    //   2528: new f/uj
    //   2531: dup
    //   2532: astore #9
    //   2534: iload #8
    //   2536: aload #10
    //   2538: invokespecial <init> : (I[Lf/LPT1;)V
    //   2541: iload #6
    //   2543: aload #9
    //   2545: aastore
    //   2546: iinc #6, 1
    //   2549: goto -> 2475
    //   2552: aload #7
    //   2554: aload #5
    //   2556: putfield A2 : [Lf/uj;
    //   2559: iinc #3, 1
    //   2562: goto -> 2030
    //   2565: iconst_1
    //   2566: ireturn
    //   2567: new f/Jn
    //   2570: dup
    //   2571: aload_0
    //   2572: invokespecial <init> : (Ljava/nio/ByteBuffer;)V
    //   2575: aload_0
    //   2576: invokevirtual RH : (Ljava/nio/ByteBuffer;)Z
    //   2579: pop
    //   2580: iconst_1
    //   2581: ireturn
    //   2582: aload_0
    //   2583: invokevirtual getShort : ()S
    //   2586: istore_1
    //   2587: iconst_0
    //   2588: istore_2
    //   2589: iload_2
    //   2590: iload_1
    //   2591: if_icmpge -> 2780
    //   2594: aload_0
    //   2595: dup
    //   2596: dup
    //   2597: invokevirtual getShort : ()S
    //   2600: istore_3
    //   2601: invokevirtual get : ()B
    //   2604: getstatic f/KM.td0 : Lf/ak;
    //   2607: swap
    //   2608: invokevirtual Ha0 : (B)Ljava/lang/Object;
    //   2611: checkcast f/KM
    //   2614: astore #4
    //   2616: invokevirtual getShort : ()S
    //   2619: istore #5
    //   2621: bipush #10
    //   2623: newarray short
    //   2625: astore #6
    //   2627: iconst_0
    //   2628: istore #7
    //   2630: iconst_0
    //   2631: istore #8
    //   2633: iload #8
    //   2635: iload #5
    //   2637: if_icmpge -> 2704
    //   2640: aload_0
    //   2641: invokevirtual getShort : ()S
    //   2644: istore #9
    //   2646: iload #7
    //   2648: iconst_1
    //   2649: iadd
    //   2650: dup
    //   2651: istore #10
    //   2653: aload #6
    //   2655: arraylength
    //   2656: if_icmple -> 2687
    //   2659: aload #6
    //   2661: dup
    //   2662: dup
    //   2663: arraylength
    //   2664: iconst_1
    //   2665: ishl
    //   2666: iload #10
    //   2668: invokestatic max : (II)I
    //   2671: newarray short
    //   2673: astore #6
    //   2675: arraylength
    //   2676: istore #11
    //   2678: iconst_0
    //   2679: aload #6
    //   2681: iconst_0
    //   2682: iload #11
    //   2684: invokestatic arraycopy : (Ljava/lang/Object;ILjava/lang/Object;II)V
    //   2687: aload #6
    //   2689: iload #7
    //   2691: iload #9
    //   2693: sastore
    //   2694: iinc #8, 1
    //   2697: iload #10
    //   2699: istore #7
    //   2701: goto -> 2633
    //   2704: invokestatic v30 : ()Lf/On;
    //   2707: iload_3
    //   2708: invokevirtual lpT3 : (S)Lf/UD0;
    //   2711: dup
    //   2712: astore_3
    //   2713: ifnull -> 2774
    //   2716: iload #7
    //   2718: dup
    //   2719: iconst_0
    //   2720: istore #5
    //   2722: newarray short
    //   2724: astore #8
    //   2726: ifne -> 2732
    //   2729: goto -> 2749
    //   2732: iload #7
    //   2734: ifle -> 2764
    //   2737: aload #6
    //   2739: iload #5
    //   2741: aload #8
    //   2743: iconst_0
    //   2744: iload #7
    //   2746: invokestatic arraycopy : (Ljava/lang/Object;ILjava/lang/Object;II)V
    //   2749: aload_3
    //   2750: getfield Pw0 : [[S
    //   2753: aload #4
    //   2755: getfield vp : B
    //   2758: aload #8
    //   2760: aastore
    //   2761: goto -> 2774
    //   2764: new java/lang/ArrayIndexOutOfBoundsException
    //   2767: dup
    //   2768: iload #5
    //   2770: invokespecial <init> : (I)V
    //   2773: athrow
    //   2774: iinc #2, 1
    //   2777: goto -> 2589
    //   2780: iconst_1
    //   2781: ireturn
    //   2782: aload_0
    //   2783: invokevirtual getShort : ()S
    //   2786: istore_1
    //   2787: iconst_0
    //   2788: istore_2
    //   2789: iload_2
    //   2790: iload_1
    //   2791: if_icmpge -> 2891
    //   2794: aload_0
    //   2795: dup
    //   2796: invokevirtual getShort : ()S
    //   2799: istore_3
    //   2800: invokevirtual get : ()B
    //   2803: sipush #255
    //   2806: iand
    //   2807: istore #4
    //   2809: new java/util/ArrayList
    //   2812: dup
    //   2813: astore #5
    //   2815: invokespecial <init> : ()V
    //   2818: iconst_0
    //   2819: istore #6
    //   2821: iload #6
    //   2823: iload #4
    //   2825: if_icmpge -> 2867
    //   2828: aload #5
    //   2830: aload_0
    //   2831: dup
    //   2832: invokevirtual getShort : ()S
    //   2835: istore #7
    //   2837: invokevirtual get : ()B
    //   2840: istore #8
    //   2842: new f/oC0
    //   2845: dup
    //   2846: astore #9
    //   2848: iload #8
    //   2850: iload #7
    //   2852: invokespecial <init> : (BS)V
    //   2855: aload #9
    //   2857: invokevirtual add : (Ljava/lang/Object;)Z
    //   2860: pop
    //   2861: iinc #6, 1
    //   2864: goto -> 2821
    //   2867: invokestatic v30 : ()Lf/On;
    //   2870: iload_3
    //   2871: invokevirtual lpT3 : (S)Lf/UD0;
    //   2874: dup
    //   2875: astore_3
    //   2876: ifnull -> 2885
    //   2879: aload_3
    //   2880: aload #5
    //   2882: putfield hz0 : Ljava/util/List;
    //   2885: iinc #2, 1
    //   2888: goto -> 2789
    //   2891: iconst_1
    //   2892: ireturn
    // Line number table:
    //   Java source line number -> byte code offset
    //   #1	-> 102
    //   #2	-> 124
    //   #3	-> 127
    //   #4	-> 131
    //   #5	-> 139
    //   #6	-> 144
    //   #7	-> 157
    //   #8	-> 166
    //   #9	-> 178
    //   #10	-> 194
    //   #11	-> 206
    //   #12	-> 209
    //   #13	-> 221
    //   #14	-> 224
    //   #15	-> 236
    //   #16	-> 240
    //   #17	-> 256
    //   #18	-> 262
    //   #19	-> 266
    //   #20	-> 301
    //   #21	-> 317
    //   #22	-> 329
    //   #23	-> 332
    //   #24	-> 342
    //   #25	-> 355
    //   #26	-> 361
    //   #27	-> 473
    //   #28	-> 476
    //   #29	-> 491
    //   #30	-> 496
    //   #31	-> 510
    //   #32	-> 568
    //   #33	-> 623
    //   #34	-> 656
    //   #35	-> 659
    //   #36	-> 664
    //   #37	-> 671
    //   #38	-> 685
    //   #39	-> 692
    //   #40	-> 724
    //   #41	-> 839
    //   #42	-> 857
    //   #43	-> 873
    //   #44	-> 876
    //   #45	-> 879
    //   #46	-> 882
    //   #47	-> 887
    //   #48	-> 890
    //   #49	-> 908
    //   #50	-> 924
    //   #51	-> 927
    //   #52	-> 941
    //   #53	-> 953
    //   #54	-> 977
    //   #55	-> 983
    //   #56	-> 996
    //   #57	-> 1045
    //   #58	-> 1048
    //   #59	-> 1068
    //   #60	-> 1074
    //   #61	-> 1087
    //   #62	-> 1167
    //   #63	-> 1171
    //   #64	-> 1175
    //   #65	-> 1184
    //   #66	-> 1190
    //   #67	-> 1220
    //   #68	-> 1229
    //   #69	-> 1262
    //   #70	-> 1271
    //   #71	-> 1322
    //   #72	-> 1325
    //   #73	-> 1355
    //   #74	-> 1415
    //   #75	-> 1429
    //   #76	-> 1432
    //   #77	-> 1441
    //   #78	-> 1459
    //   #79	-> 1473
    //   #80	-> 1483
    //   #81	-> 1508
    //   #82	-> 1518
    //   #83	-> 1530
    //   #84	-> 1655
    //   #85	-> 1673
    //   #86	-> 1697
    //   #87	-> 1700
    //   #88	-> 1703
    //   #89	-> 1728
    //   #90	-> 1739
    //   #91	-> 1744
    //   #92	-> 1750
    //   #93	-> 1776
    //   #94	-> 1814
    //   #95	-> 1827
    //   #96	-> 1840
    //   #97	-> 1911
    //   #98	-> 1923
    //   #99	-> 1974
    //   #100	-> 1989
    //   #101	-> 1992
    //   #102	-> 1997
    //   #103	-> 2002
    //   #104	-> 2015
    //   #105	-> 2024
    //   #106	-> 2047
    //   #107	-> 2055
    //   #108	-> 2065
    //   #109	-> 2082
    //   #110	-> 2118
    //   #111	-> 2123
    //   #112	-> 2128
    //   #113	-> 2138
    //   #114	-> 2149
    //   #115	-> 2152
    //   #116	-> 2165
    //   #117	-> 2168
    //   #118	-> 2181
    //   #119	-> 2184
    //   #120	-> 2198
    //   #121	-> 2204
    //   #122	-> 2218
    //   #123	-> 2221
    //   #124	-> 2235
    //   #125	-> 2238
    //   #126	-> 2252
    //   #127	-> 2255
    //   #128	-> 2282
    //   #129	-> 2295
    //   #130	-> 2298
    //   #131	-> 2311
    //   #132	-> 2432
    //   #133	-> 2461
    //   #134	-> 2556
    //   #135	-> 2567
    //   #136	-> 2583
    //   #137	-> 2604
    //   #138	-> 2616
    //   #139	-> 2623
    //   #140	-> 2641
    //   #141	-> 2655
    //   #142	-> 2693
    //   #143	-> 2704
    //   #144	-> 2722
    //   #145	-> 2746
    //   #146	-> 2750
    //   #147	-> 2755
    //   #148	-> 2760
    //   #149	-> 2764
    //   #150	-> 2783
    //   #151	-> 2882
  }
}


/* Location:              /Users/vnnsnnt/Documents/Codespace/JavaWorkspace/RedTrainer/src/main/java/org/trainer/client/PokeMMO.jar!/f/mu0.class
 * Java compiler version: 8 (52.0)
 * JD-Core Version:       1.1.3
 */