/*    */ package f;
/*  2 */ public final class n extends Qa0 implements r60 { public final Ip Kt0; public final nE0 r8; public final A30 Ub0; public final Kf HD0; public W1 WB0; private void P0(Kf paramKf, LPT3 paramLPT3, nE0 paramnE0) { Vp0 vp0 = paramLPT3.c3.Hl0;
/*    */     
/*  4 */     this(vp0, paramLPT3.c3.Lk, paramnE0, paramKf); coM9 coM92, coM91;
/*  5 */     if ((coM91 = paramKf.hD) == null) { paramKf
/*  6 */         .hD = coM92; } else { coM91.ra0(); paramKf.hD = coM92; }  paramKf
/*  7 */       .si(coM92, paramKf.Ub());
/*  8 */     ra0(); }
/*    */   public W1 Hv;
/*    */   public W1[] pD0; public WD[] OZ; public ge0[] M60; public Rm[] Ve; public n(nE0 paramnE0, Kf paramKf) { // Byte code:
/*    */     //   0: aload_0
/*    */     //   1: aload_1
/*    */     //   2: aload_0
/*    */     //   3: aload_1
/*    */     //   4: aload_0
/*    */     //   5: aload_2
/*    */     //   6: aload_0
/*    */     //   7: dup
/*    */     //   8: dup2
/*    */     //   9: dup2
/*    */     //   10: iconst_1
/*    */     //   11: iconst_0
/*    */     //   12: invokespecial <init> : (ZZ)V
/*    */     //   15: aconst_null
/*    */     //   16: putfield WB0 : Lf/W1;
/*    */     //   19: aconst_null
/*    */     //   20: putfield Hv : Lf/W1;
/*    */     //   23: iconst_0
/*    */     //   24: anewarray f/W1
/*    */     //   27: putfield pD0 : [Lf/W1;
/*    */     //   30: aconst_null
/*    */     //   31: putfield M60 : [Lf/ge0;
/*    */     //   34: ldc 'confirm-widget'
/*    */     //   36: invokevirtual Xu : (Ljava/lang/String;)V
/*    */     //   39: putfield HD0 : Lf/Kf;
/*    */     //   42: putfield r8 : Lf/nE0;
/*    */     //   45: new f/Ip
/*    */     //   48: dup
/*    */     //   49: dup2
/*    */     //   50: dup2
/*    */     //   51: astore_3
/*    */     //   52: aload_0
/*    */     //   53: aload_3
/*    */     //   54: dup
/*    */     //   55: invokespecial <init> : ()V
/*    */     //   58: putfield Kt0 : Lf/Ip;
/*    */     //   61: ldc 'confirm-panel'
/*    */     //   63: invokevirtual Xu : (Ljava/lang/String;)V
/*    */     //   66: new f/dQ
/*    */     //   69: dup
/*    */     //   70: dup
/*    */     //   71: astore #4
/*    */     //   73: invokespecial <init> : ()V
/*    */     //   76: ldc 'label-title'
/*    */     //   78: invokevirtual E1 : (Ljava/lang/String;)V
/*    */     //   81: iconst_1
/*    */     //   82: anewarray f/JG0
/*    */     //   85: dup
/*    */     //   86: iconst_0
/*    */     //   87: aload #4
/*    */     //   89: aastore
/*    */     //   90: invokevirtual vo0 : ([Lf/JG0;)Lf/U90;
/*    */     //   93: invokevirtual WN : (Lf/U90;)V
/*    */     //   96: iconst_1
/*    */     //   97: anewarray f/JG0
/*    */     //   100: dup
/*    */     //   101: iconst_0
/*    */     //   102: aload #4
/*    */     //   104: aastore
/*    */     //   105: invokevirtual AUX : ([Lf/JG0;)Lf/U90;
/*    */     //   108: invokevirtual rK0 : (Lf/U90;)V
/*    */     //   111: invokevirtual lF0 : ()Lf/A30;
/*    */     //   114: dup
/*    */     //   115: astore #5
/*    */     //   117: putfield Ub0 : Lf/A30;
/*    */     //   120: aload #5
/*    */     //   122: invokevirtual d1 : ()S
/*    */     //   125: ifle -> 1807
/*    */     //   128: aload #5
/*    */     //   130: aload #4
/*    */     //   132: sipush #5613
/*    */     //   135: invokestatic OH0 : (I)Ljava/lang/String;
/*    */     //   138: invokevirtual E1 : (Ljava/lang/String;)V
/*    */     //   141: invokestatic v30 : ()Lf/On;
/*    */     //   144: aload #5
/*    */     //   146: invokevirtual d1 : ()S
/*    */     //   149: invokevirtual lpT3 : (S)Lf/UD0;
/*    */     //   152: astore_1
/*    */     //   153: new java/lang/StringBuilder
/*    */     //   156: dup
/*    */     //   157: astore_2
/*    */     //   158: new java/lang/StringBuilder
/*    */     //   161: dup
/*    */     //   162: astore #4
/*    */     //   164: invokespecial <init> : ()V
/*    */     //   167: bipush #59
/*    */     //   169: aload #4
/*    */     //   171: ldc ' '
/*    */     //   173: invokestatic X9 : (ILjava/lang/StringBuilder;Ljava/lang/String;)Ljava/lang/StringBuilder;
/*    */     //   176: aload #5
/*    */     //   178: invokevirtual Wf : ()B
/*    */     //   181: invokevirtual append : (I)Ljava/lang/StringBuilder;
/*    */     //   184: ldc ' '
/*    */     //   186: invokevirtual append : (Ljava/lang/String;)Ljava/lang/StringBuilder;
/*    */     //   189: invokevirtual toString : ()Ljava/lang/String;
/*    */     //   192: invokespecial <init> : (Ljava/lang/String;)V
/*    */     //   195: invokevirtual Dd0 : ()Z
/*    */     //   198: ifeq -> 228
/*    */     //   201: aload #5
/*    */     //   203: invokevirtual on0 : ()Z
/*    */     //   206: ifeq -> 228
/*    */     //   209: aload_2
/*    */     //   210: sipush #5621
/*    */     //   213: invokestatic OH0 : (I)Ljava/lang/String;
/*    */     //   216: invokevirtual append : (Ljava/lang/String;)Ljava/lang/StringBuilder;
/*    */     //   219: ldc ' '
/*    */     //   221: invokevirtual append : (Ljava/lang/String;)Ljava/lang/StringBuilder;
/*    */     //   224: pop
/*    */     //   225: goto -> 279
/*    */     //   228: aload #5
/*    */     //   230: invokevirtual Dd0 : ()Z
/*    */     //   233: ifeq -> 255
/*    */     //   236: aload_2
/*    */     //   237: sipush #5614
/*    */     //   240: invokestatic OH0 : (I)Ljava/lang/String;
/*    */     //   243: invokevirtual append : (Ljava/lang/String;)Ljava/lang/StringBuilder;
/*    */     //   246: ldc ' '
/*    */     //   248: invokevirtual append : (Ljava/lang/String;)Ljava/lang/StringBuilder;
/*    */     //   251: pop
/*    */     //   252: goto -> 279
/*    */     //   255: aload #5
/*    */     //   257: invokevirtual on0 : ()Z
/*    */     //   260: ifeq -> 279
/*    */     //   263: aload_2
/*    */     //   264: sipush #5615
/*    */     //   267: invokestatic OH0 : (I)Ljava/lang/String;
/*    */     //   270: invokevirtual append : (Ljava/lang/String;)Ljava/lang/StringBuilder;
/*    */     //   273: ldc ' '
/*    */     //   275: invokevirtual append : (Ljava/lang/String;)Ljava/lang/StringBuilder;
/*    */     //   278: pop
/*    */     //   279: aload #5
/*    */     //   281: aload_3
/*    */     //   282: dup
/*    */     //   283: aload_2
/*    */     //   284: aload_1
/*    */     //   285: invokevirtual wp : ()Ljava/lang/String;
/*    */     //   288: invokevirtual append : (Ljava/lang/String;)Ljava/lang/StringBuilder;
/*    */     //   291: pop
/*    */     //   292: new f/dQ
/*    */     //   295: dup
/*    */     //   296: astore_3
/*    */     //   297: aload_2
/*    */     //   298: invokevirtual toString : ()Ljava/lang/String;
/*    */     //   301: invokespecial <init> : (Ljava/lang/String;)V
/*    */     //   304: invokevirtual xh : ()Lf/U90;
/*    */     //   307: aload_3
/*    */     //   308: invokevirtual Ya : (Lf/JG0;)Lf/U90;
/*    */     //   311: pop
/*    */     //   312: invokevirtual iJ0 : ()Lf/U90;
/*    */     //   315: aload_3
/*    */     //   316: invokevirtual Ya : (Lf/JG0;)Lf/U90;
/*    */     //   319: pop
/*    */     //   320: invokevirtual KL0 : ()Z
/*    */     //   323: ifeq -> 497
/*    */     //   326: new f/dQ
/*    */     //   329: dup
/*    */     //   330: astore_2
/*    */     //   331: sipush #8106
/*    */     //   334: invokestatic OH0 : (I)Ljava/lang/String;
/*    */     //   337: invokespecial <init> : (Ljava/lang/String;)V
/*    */     //   340: getstatic f/nV.ko0 : [Lf/nV;
/*    */     //   343: dup
/*    */     //   344: dup
/*    */     //   345: astore_3
/*    */     //   346: arraylength
/*    */     //   347: iconst_1
/*    */     //   348: iadd
/*    */     //   349: anewarray java/lang/String
/*    */     //   352: dup
/*    */     //   353: astore #4
/*    */     //   355: iconst_0
/*    */     //   356: ldc '-'
/*    */     //   358: aastore
/*    */     //   359: arraylength
/*    */     //   360: istore #5
/*    */     //   362: iconst_0
/*    */     //   363: istore #6
/*    */     //   365: iload #6
/*    */     //   367: iload #5
/*    */     //   369: if_icmpge -> 399
/*    */     //   372: aload #4
/*    */     //   374: aload_3
/*    */     //   375: iload #6
/*    */     //   377: aaload
/*    */     //   378: dup
/*    */     //   379: invokevirtual LPt8 : ()B
/*    */     //   382: iconst_1
/*    */     //   383: iadd
/*    */     //   384: istore #7
/*    */     //   386: invokevirtual cK0 : ()Ljava/lang/String;
/*    */     //   389: iload #7
/*    */     //   391: swap
/*    */     //   392: aastore
/*    */     //   393: iinc #6, 1
/*    */     //   396: goto -> 365
/*    */     //   399: aload_0
/*    */     //   400: dup
/*    */     //   401: new f/OZ
/*    */     //   404: dup
/*    */     //   405: astore_3
/*    */     //   406: aload #4
/*    */     //   408: invokespecial <init> : ([Ljava/lang/Object;)V
/*    */     //   411: new f/W1
/*    */     //   414: dup
/*    */     //   415: aload_0
/*    */     //   416: swap
/*    */     //   417: dup
/*    */     //   418: aload_3
/*    */     //   419: invokespecial <init> : (Lf/cQ;)V
/*    */     //   422: putfield WB0 : Lf/W1;
/*    */     //   425: iconst_0
/*    */     //   426: invokevirtual Z30 : (I)V
/*    */     //   429: getfield Kt0 : Lf/Ip;
/*    */     //   432: invokevirtual xh : ()Lf/U90;
/*    */     //   435: aload_0
/*    */     //   436: getfield Kt0 : Lf/Ip;
/*    */     //   439: invokevirtual mE0 : ()Lf/g0;
/*    */     //   442: iconst_2
/*    */     //   443: anewarray f/JG0
/*    */     //   446: dup
/*    */     //   447: dup
/*    */     //   448: aload_0
/*    */     //   449: swap
/*    */     //   450: iconst_0
/*    */     //   451: aload_2
/*    */     //   452: aastore
/*    */     //   453: getfield WB0 : Lf/W1;
/*    */     //   456: iconst_1
/*    */     //   457: swap
/*    */     //   458: aastore
/*    */     //   459: invokevirtual Mg : ([Lf/JG0;)Lf/U90;
/*    */     //   462: invokevirtual ee0 : (Lf/U90;)Lf/U90;
/*    */     //   465: pop
/*    */     //   466: getfield Kt0 : Lf/Ip;
/*    */     //   469: invokevirtual iJ0 : ()Lf/U90;
/*    */     //   472: aload_0
/*    */     //   473: getfield Kt0 : Lf/Ip;
/*    */     //   476: invokevirtual d7 : ()Lf/cr0;
/*    */     //   479: aload_2
/*    */     //   480: invokevirtual Ya : (Lf/JG0;)Lf/U90;
/*    */     //   483: invokevirtual Em0 : ()Lf/U90;
/*    */     //   486: aload_0
/*    */     //   487: getfield WB0 : Lf/W1;
/*    */     //   490: invokevirtual Ya : (Lf/JG0;)Lf/U90;
/*    */     //   493: invokevirtual ee0 : (Lf/U90;)Lf/U90;
/*    */     //   496: pop
/*    */     //   497: aload_0
/*    */     //   498: getfield Ub0 : Lf/A30;
/*    */     //   501: invokevirtual TC : ()Z
/*    */     //   504: ifeq -> 649
/*    */     //   507: aload_0
/*    */     //   508: dup
/*    */     //   509: new f/dQ
/*    */     //   512: dup
/*    */     //   513: astore_2
/*    */     //   514: sipush #8100
/*    */     //   517: invokestatic OH0 : (I)Ljava/lang/String;
/*    */     //   520: invokespecial <init> : (Ljava/lang/String;)V
/*    */     //   523: iconst_3
/*    */     //   524: anewarray java/lang/String
/*    */     //   527: dup
/*    */     //   528: dup2
/*    */     //   529: astore_3
/*    */     //   530: iconst_0
/*    */     //   531: ldc '-'
/*    */     //   533: aastore
/*    */     //   534: sipush #8101
/*    */     //   537: invokestatic OH0 : (I)Ljava/lang/String;
/*    */     //   540: iconst_1
/*    */     //   541: swap
/*    */     //   542: aastore
/*    */     //   543: sipush #8102
/*    */     //   546: invokestatic OH0 : (I)Ljava/lang/String;
/*    */     //   549: iconst_2
/*    */     //   550: swap
/*    */     //   551: aastore
/*    */     //   552: new f/OZ
/*    */     //   555: dup
/*    */     //   556: astore #4
/*    */     //   558: aload_3
/*    */     //   559: invokespecial <init> : ([Ljava/lang/Object;)V
/*    */     //   562: new f/W1
/*    */     //   565: dup
/*    */     //   566: aload_0
/*    */     //   567: swap
/*    */     //   568: dup
/*    */     //   569: aload #4
/*    */     //   571: invokespecial <init> : (Lf/cQ;)V
/*    */     //   574: putfield Hv : Lf/W1;
/*    */     //   577: iconst_0
/*    */     //   578: invokevirtual Z30 : (I)V
/*    */     //   581: getfield Kt0 : Lf/Ip;
/*    */     //   584: invokevirtual xh : ()Lf/U90;
/*    */     //   587: aload_0
/*    */     //   588: getfield Kt0 : Lf/Ip;
/*    */     //   591: invokevirtual mE0 : ()Lf/g0;
/*    */     //   594: iconst_2
/*    */     //   595: anewarray f/JG0
/*    */     //   598: dup
/*    */     //   599: dup
/*    */     //   600: aload_0
/*    */     //   601: swap
/*    */     //   602: iconst_0
/*    */     //   603: aload_2
/*    */     //   604: aastore
/*    */     //   605: getfield Hv : Lf/W1;
/*    */     //   608: iconst_1
/*    */     //   609: swap
/*    */     //   610: aastore
/*    */     //   611: invokevirtual Mg : ([Lf/JG0;)Lf/U90;
/*    */     //   614: invokevirtual ee0 : (Lf/U90;)Lf/U90;
/*    */     //   617: pop
/*    */     //   618: getfield Kt0 : Lf/Ip;
/*    */     //   621: invokevirtual iJ0 : ()Lf/U90;
/*    */     //   624: aload_0
/*    */     //   625: getfield Kt0 : Lf/Ip;
/*    */     //   628: invokevirtual d7 : ()Lf/cr0;
/*    */     //   631: aload_2
/*    */     //   632: invokevirtual Ya : (Lf/JG0;)Lf/U90;
/*    */     //   635: invokevirtual Em0 : ()Lf/U90;
/*    */     //   638: aload_0
/*    */     //   639: getfield Hv : Lf/W1;
/*    */     //   642: invokevirtual Ya : (Lf/JG0;)Lf/U90;
/*    */     //   645: invokevirtual ee0 : (Lf/U90;)Lf/U90;
/*    */     //   648: pop
/*    */     //   649: aload_0
/*    */     //   650: dup
/*    */     //   651: getfield Ub0 : Lf/A30;
/*    */     //   654: invokevirtual Hq : ()B
/*    */     //   657: anewarray f/W1
/*    */     //   660: putfield pD0 : [Lf/W1;
/*    */     //   663: new java/util/ArrayList
/*    */     //   666: dup
/*    */     //   667: dup
/*    */     //   668: astore_2
/*    */     //   669: invokespecial <init> : ()V
/*    */     //   672: invokestatic cw : ()Lf/yk0;
/*    */     //   675: iconst_0
/*    */     //   676: invokevirtual mP : (S)Lf/WD;
/*    */     //   679: invokevirtual add : (Ljava/lang/Object;)Z
/*    */     //   682: pop
/*    */     //   683: invokestatic cw : ()Lf/yk0;
/*    */     //   686: invokevirtual jQ : ()Lf/iL;
/*    */     //   689: invokevirtual iterator : ()Ljava/util/Iterator;
/*    */     //   692: astore_3
/*    */     //   693: aload_3
/*    */     //   694: checkcast f/DA0
/*    */     //   697: invokevirtual hasNext : ()Z
/*    */     //   700: ifeq -> 770
/*    */     //   703: aload_3
/*    */     //   704: checkcast f/Ke
/*    */     //   707: invokevirtual next : ()Ljava/lang/Object;
/*    */     //   710: checkcast f/WD
/*    */     //   713: dup
/*    */     //   714: astore #4
/*    */     //   716: invokevirtual xF0 : ()S
/*    */     //   719: iconst_1
/*    */     //   720: if_icmplt -> 693
/*    */     //   723: aload #4
/*    */     //   725: invokevirtual Pj0 : ()Z
/*    */     //   728: ifeq -> 734
/*    */     //   731: goto -> 693
/*    */     //   734: aload_1
/*    */     //   735: aload_0
/*    */     //   736: aload #4
/*    */     //   738: invokevirtual xF0 : ()S
/*    */     //   741: istore #5
/*    */     //   743: getfield Ub0 : Lf/A30;
/*    */     //   746: invokevirtual Wf : ()B
/*    */     //   749: iload #5
/*    */     //   751: invokevirtual W40 : (BS)Z
/*    */     //   754: ifne -> 760
/*    */     //   757: goto -> 693
/*    */     //   760: aload_2
/*    */     //   761: aload #4
/*    */     //   763: invokevirtual add : (Ljava/lang/Object;)Z
/*    */     //   766: pop
/*    */     //   767: goto -> 693
/*    */     //   770: aload_0
/*    */     //   771: aload_2
/*    */     //   772: dup
/*    */     //   773: getstatic f/WD.Fw0 : Ljava/util/Comparator;
/*    */     //   776: invokestatic sort : (Ljava/util/List;Ljava/util/Comparator;)V
/*    */     //   779: iconst_0
/*    */     //   780: anewarray f/WD
/*    */     //   783: invokevirtual toArray : ([Ljava/lang/Object;)[Ljava/lang/Object;
/*    */     //   786: checkcast [Lf/WD;
/*    */     //   789: putfield OZ : [Lf/WD;
/*    */     //   792: iconst_0
/*    */     //   793: istore_1
/*    */     //   794: iload_1
/*    */     //   795: aload_0
/*    */     //   796: getfield Ub0 : Lf/A30;
/*    */     //   799: invokevirtual Hq : ()B
/*    */     //   802: if_icmpge -> 948
/*    */     //   805: aload_0
/*    */     //   806: dup
/*    */     //   807: dup2
/*    */     //   808: new f/dQ
/*    */     //   811: dup
/*    */     //   812: astore_2
/*    */     //   813: iload_1
/*    */     //   814: iconst_1
/*    */     //   815: iadd
/*    */     //   816: dup
/*    */     //   817: istore_3
/*    */     //   818: invokestatic toString : (I)Ljava/lang/String;
/*    */     //   821: sipush #5616
/*    */     //   824: swap
/*    */     //   825: invokestatic Go : (ILjava/lang/String;)Ljava/lang/String;
/*    */     //   828: invokespecial <init> : (Ljava/lang/String;)V
/*    */     //   831: new f/OZ
/*    */     //   834: dup
/*    */     //   835: astore #4
/*    */     //   837: aload_0
/*    */     //   838: getfield OZ : [Lf/WD;
/*    */     //   841: invokespecial <init> : ([Ljava/lang/Object;)V
/*    */     //   844: getfield pD0 : [Lf/W1;
/*    */     //   847: iload_1
/*    */     //   848: new f/W1
/*    */     //   851: dup
/*    */     //   852: astore #5
/*    */     //   854: aload #4
/*    */     //   856: invokespecial <init> : (Lf/cQ;)V
/*    */     //   859: aload #5
/*    */     //   861: aastore
/*    */     //   862: getfield pD0 : [Lf/W1;
/*    */     //   865: iload_1
/*    */     //   866: aaload
/*    */     //   867: iconst_0
/*    */     //   868: invokevirtual Z30 : (I)V
/*    */     //   871: getfield Kt0 : Lf/Ip;
/*    */     //   874: invokevirtual xh : ()Lf/U90;
/*    */     //   877: aload_0
/*    */     //   878: getfield Kt0 : Lf/Ip;
/*    */     //   881: invokevirtual mE0 : ()Lf/g0;
/*    */     //   884: iconst_2
/*    */     //   885: anewarray f/JG0
/*    */     //   888: dup
/*    */     //   889: dup
/*    */     //   890: aload_0
/*    */     //   891: swap
/*    */     //   892: iconst_0
/*    */     //   893: aload_2
/*    */     //   894: aastore
/*    */     //   895: getfield pD0 : [Lf/W1;
/*    */     //   898: iload_1
/*    */     //   899: aaload
/*    */     //   900: iconst_1
/*    */     //   901: swap
/*    */     //   902: aastore
/*    */     //   903: invokevirtual Mg : ([Lf/JG0;)Lf/U90;
/*    */     //   906: invokevirtual ee0 : (Lf/U90;)Lf/U90;
/*    */     //   909: pop
/*    */     //   910: getfield Kt0 : Lf/Ip;
/*    */     //   913: invokevirtual iJ0 : ()Lf/U90;
/*    */     //   916: aload_0
/*    */     //   917: getfield Kt0 : Lf/Ip;
/*    */     //   920: invokevirtual d7 : ()Lf/cr0;
/*    */     //   923: aload_2
/*    */     //   924: invokevirtual Ya : (Lf/JG0;)Lf/U90;
/*    */     //   927: invokevirtual Em0 : ()Lf/U90;
/*    */     //   930: aload_0
/*    */     //   931: getfield pD0 : [Lf/W1;
/*    */     //   934: iload_1
/*    */     //   935: aaload
/*    */     //   936: invokevirtual Ya : (Lf/JG0;)Lf/U90;
/*    */     //   939: invokevirtual ee0 : (Lf/U90;)Lf/U90;
/*    */     //   942: pop
/*    */     //   943: iload_3
/*    */     //   944: istore_1
/*    */     //   945: goto -> 794
/*    */     //   948: aload_0
/*    */     //   949: getfield Ub0 : Lf/A30;
/*    */     //   952: invokevirtual Sn0 : ()B
/*    */     //   955: ifle -> 1757
/*    */     //   958: aload_0
/*    */     //   959: dup
/*    */     //   960: dup2
/*    */     //   961: new f/dQ
/*    */     //   964: dup
/*    */     //   965: astore_1
/*    */     //   966: aload_0
/*    */     //   967: getfield Ub0 : Lf/A30;
/*    */     //   970: invokevirtual Sn0 : ()B
/*    */     //   973: invokestatic toString : (I)Ljava/lang/String;
/*    */     //   976: sipush #9110
/*    */     //   979: swap
/*    */     //   980: invokestatic Go : (ILjava/lang/String;)Ljava/lang/String;
/*    */     //   983: invokespecial <init> : (Ljava/lang/String;)V
/*    */     //   986: getfield Kt0 : Lf/Ip;
/*    */     //   989: invokevirtual xh : ()Lf/U90;
/*    */     //   992: aload_1
/*    */     //   993: invokevirtual Ya : (Lf/JG0;)Lf/U90;
/*    */     //   996: pop
/*    */     //   997: getfield Kt0 : Lf/Ip;
/*    */     //   1000: invokevirtual iJ0 : ()Lf/U90;
/*    */     //   1003: aload_1
/*    */     //   1004: invokevirtual Ya : (Lf/JG0;)Lf/U90;
/*    */     //   1007: pop
/*    */     //   1008: bipush #6
/*    */     //   1010: anewarray f/ge0
/*    */     //   1013: putfield M60 : [Lf/ge0;
/*    */     //   1016: bipush #6
/*    */     //   1018: anewarray f/dQ
/*    */     //   1021: astore_1
/*    */     //   1022: bipush #6
/*    */     //   1024: anewarray f/Rm
/*    */     //   1027: putfield Ve : [Lf/Rm;
/*    */     //   1030: iconst_0
/*    */     //   1031: istore_2
/*    */     //   1032: iload_2
/*    */     //   1033: getstatic f/hR.Tm0 : [Lf/hR;
/*    */     //   1036: dup
/*    */     //   1037: astore_3
/*    */     //   1038: arraylength
/*    */     //   1039: if_icmpge -> 1160
/*    */     //   1042: aload_0
/*    */     //   1043: dup
/*    */     //   1044: dup
/*    */     //   1045: dup2
/*    */     //   1046: aload_3
/*    */     //   1047: iload_2
/*    */     //   1048: aaload
/*    */     //   1049: astore_3
/*    */     //   1050: new f/dQ
/*    */     //   1053: dup
/*    */     //   1054: astore #4
/*    */     //   1056: aload_1
/*    */     //   1057: iload_2
/*    */     //   1058: aload #4
/*    */     //   1060: aload_3
/*    */     //   1061: invokevirtual toString : ()Ljava/lang/String;
/*    */     //   1064: invokespecial <init> : (Ljava/lang/String;)V
/*    */     //   1067: aload #4
/*    */     //   1069: aastore
/*    */     //   1070: ldc 'label-title'
/*    */     //   1072: invokevirtual Xu : (Ljava/lang/String;)V
/*    */     //   1075: new f/zT
/*    */     //   1078: dup
/*    */     //   1079: astore_3
/*    */     //   1080: iconst_0
/*    */     //   1081: bipush #31
/*    */     //   1083: bipush #31
/*    */     //   1085: invokespecial <init> : (III)V
/*    */     //   1088: getfield Ve : [Lf/Rm;
/*    */     //   1091: iload_2
/*    */     //   1092: new f/Rm
/*    */     //   1095: dup
/*    */     //   1096: astore #4
/*    */     //   1098: aload_3
/*    */     //   1099: invokespecial <init> : (Lf/zT;)V
/*    */     //   1102: aload #4
/*    */     //   1104: aastore
/*    */     //   1105: getfield Ve : [Lf/Rm;
/*    */     //   1108: iload_2
/*    */     //   1109: aaload
/*    */     //   1110: ldc_w 'valueadjuster-small'
/*    */     //   1113: invokevirtual Xu : (Ljava/lang/String;)V
/*    */     //   1116: getfield Ve : [Lf/Rm;
/*    */     //   1119: iload_2
/*    */     //   1120: aaload
/*    */     //   1121: iconst_0
/*    */     //   1122: invokevirtual sk0 : (Z)V
/*    */     //   1125: getfield M60 : [Lf/ge0;
/*    */     //   1128: iload_2
/*    */     //   1129: new f/ge0
/*    */     //   1132: dup
/*    */     //   1133: astore_3
/*    */     //   1134: invokespecial <init> : ()V
/*    */     //   1137: aload_3
/*    */     //   1138: aastore
/*    */     //   1139: getfield M60 : [Lf/ge0;
/*    */     //   1142: iload_2
/*    */     //   1143: aaload
/*    */     //   1144: aload_0
/*    */     //   1145: iload_2
/*    */     //   1146: <illegal opcode> run : (Lf/n;I)Ljava/lang/Runnable;
/*    */     //   1151: invokevirtual tW : (Ljava/lang/Runnable;)V
/*    */     //   1154: iinc #2, 1
/*    */     //   1157: goto -> 1032
/*    */     //   1160: aload_0
/*    */     //   1161: dup
/*    */     //   1162: dup2
/*    */     //   1163: getfield Kt0 : Lf/Ip;
/*    */     //   1166: invokevirtual d7 : ()Lf/cr0;
/*    */     //   1169: aload_0
/*    */     //   1170: getfield Kt0 : Lf/Ip;
/*    */     //   1173: invokevirtual mE0 : ()Lf/g0;
/*    */     //   1176: iconst_3
/*    */     //   1177: anewarray f/JG0
/*    */     //   1180: dup
/*    */     //   1181: dup
/*    */     //   1182: astore_2
/*    */     //   1183: aload_0
/*    */     //   1184: aload_2
/*    */     //   1185: aload_0
/*    */     //   1186: aload_2
/*    */     //   1187: aload_1
/*    */     //   1188: iconst_0
/*    */     //   1189: aaload
/*    */     //   1190: iconst_0
/*    */     //   1191: swap
/*    */     //   1192: aastore
/*    */     //   1193: getfield M60 : [Lf/ge0;
/*    */     //   1196: iconst_0
/*    */     //   1197: aaload
/*    */     //   1198: iconst_1
/*    */     //   1199: swap
/*    */     //   1200: aastore
/*    */     //   1201: getfield Ve : [Lf/Rm;
/*    */     //   1204: iconst_0
/*    */     //   1205: aaload
/*    */     //   1206: iconst_2
/*    */     //   1207: swap
/*    */     //   1208: aastore
/*    */     //   1209: invokevirtual Mg : ([Lf/JG0;)Lf/U90;
/*    */     //   1212: invokevirtual ee0 : (Lf/U90;)Lf/U90;
/*    */     //   1215: aload_0
/*    */     //   1216: getfield Kt0 : Lf/Ip;
/*    */     //   1219: invokevirtual mE0 : ()Lf/g0;
/*    */     //   1222: iconst_3
/*    */     //   1223: anewarray f/JG0
/*    */     //   1226: dup
/*    */     //   1227: dup
/*    */     //   1228: astore_2
/*    */     //   1229: aload_0
/*    */     //   1230: aload_2
/*    */     //   1231: aload_0
/*    */     //   1232: aload_2
/*    */     //   1233: aload_1
/*    */     //   1234: iconst_1
/*    */     //   1235: aaload
/*    */     //   1236: iconst_0
/*    */     //   1237: swap
/*    */     //   1238: aastore
/*    */     //   1239: getfield M60 : [Lf/ge0;
/*    */     //   1242: iconst_1
/*    */     //   1243: aaload
/*    */     //   1244: iconst_1
/*    */     //   1245: swap
/*    */     //   1246: aastore
/*    */     //   1247: getfield Ve : [Lf/Rm;
/*    */     //   1250: iconst_1
/*    */     //   1251: aaload
/*    */     //   1252: iconst_2
/*    */     //   1253: swap
/*    */     //   1254: aastore
/*    */     //   1255: invokevirtual Mg : ([Lf/JG0;)Lf/U90;
/*    */     //   1258: invokevirtual ee0 : (Lf/U90;)Lf/U90;
/*    */     //   1261: aload_0
/*    */     //   1262: getfield Kt0 : Lf/Ip;
/*    */     //   1265: invokevirtual mE0 : ()Lf/g0;
/*    */     //   1268: iconst_3
/*    */     //   1269: anewarray f/JG0
/*    */     //   1272: dup
/*    */     //   1273: dup
/*    */     //   1274: astore_2
/*    */     //   1275: aload_0
/*    */     //   1276: aload_2
/*    */     //   1277: aload_0
/*    */     //   1278: aload_2
/*    */     //   1279: aload_1
/*    */     //   1280: iconst_2
/*    */     //   1281: aaload
/*    */     //   1282: iconst_0
/*    */     //   1283: swap
/*    */     //   1284: aastore
/*    */     //   1285: getfield M60 : [Lf/ge0;
/*    */     //   1288: iconst_2
/*    */     //   1289: aaload
/*    */     //   1290: iconst_1
/*    */     //   1291: swap
/*    */     //   1292: aastore
/*    */     //   1293: getfield Ve : [Lf/Rm;
/*    */     //   1296: iconst_2
/*    */     //   1297: aaload
/*    */     //   1298: iconst_2
/*    */     //   1299: swap
/*    */     //   1300: aastore
/*    */     //   1301: invokevirtual Mg : ([Lf/JG0;)Lf/U90;
/*    */     //   1304: invokevirtual ee0 : (Lf/U90;)Lf/U90;
/*    */     //   1307: aload_0
/*    */     //   1308: getfield Kt0 : Lf/Ip;
/*    */     //   1311: invokevirtual mE0 : ()Lf/g0;
/*    */     //   1314: iconst_3
/*    */     //   1315: anewarray f/JG0
/*    */     //   1318: dup
/*    */     //   1319: dup
/*    */     //   1320: astore_2
/*    */     //   1321: aload_0
/*    */     //   1322: aload_2
/*    */     //   1323: aload_0
/*    */     //   1324: aload_2
/*    */     //   1325: aload_1
/*    */     //   1326: iconst_3
/*    */     //   1327: aaload
/*    */     //   1328: iconst_0
/*    */     //   1329: swap
/*    */     //   1330: aastore
/*    */     //   1331: getfield M60 : [Lf/ge0;
/*    */     //   1334: iconst_3
/*    */     //   1335: aaload
/*    */     //   1336: iconst_1
/*    */     //   1337: swap
/*    */     //   1338: aastore
/*    */     //   1339: getfield Ve : [Lf/Rm;
/*    */     //   1342: iconst_3
/*    */     //   1343: aaload
/*    */     //   1344: iconst_2
/*    */     //   1345: swap
/*    */     //   1346: aastore
/*    */     //   1347: invokevirtual Mg : ([Lf/JG0;)Lf/U90;
/*    */     //   1350: invokevirtual ee0 : (Lf/U90;)Lf/U90;
/*    */     //   1353: aload_0
/*    */     //   1354: getfield Kt0 : Lf/Ip;
/*    */     //   1357: invokevirtual mE0 : ()Lf/g0;
/*    */     //   1360: iconst_3
/*    */     //   1361: anewarray f/JG0
/*    */     //   1364: dup
/*    */     //   1365: dup
/*    */     //   1366: astore_2
/*    */     //   1367: aload_0
/*    */     //   1368: aload_2
/*    */     //   1369: aload_0
/*    */     //   1370: aload_2
/*    */     //   1371: aload_1
/*    */     //   1372: iconst_4
/*    */     //   1373: aaload
/*    */     //   1374: iconst_0
/*    */     //   1375: swap
/*    */     //   1376: aastore
/*    */     //   1377: getfield M60 : [Lf/ge0;
/*    */     //   1380: iconst_4
/*    */     //   1381: aaload
/*    */     //   1382: iconst_1
/*    */     //   1383: swap
/*    */     //   1384: aastore
/*    */     //   1385: getfield Ve : [Lf/Rm;
/*    */     //   1388: iconst_4
/*    */     //   1389: aaload
/*    */     //   1390: iconst_2
/*    */     //   1391: swap
/*    */     //   1392: aastore
/*    */     //   1393: invokevirtual Mg : ([Lf/JG0;)Lf/U90;
/*    */     //   1396: invokevirtual ee0 : (Lf/U90;)Lf/U90;
/*    */     //   1399: aload_0
/*    */     //   1400: getfield Kt0 : Lf/Ip;
/*    */     //   1403: invokevirtual mE0 : ()Lf/g0;
/*    */     //   1406: iconst_3
/*    */     //   1407: anewarray f/JG0
/*    */     //   1410: dup
/*    */     //   1411: dup
/*    */     //   1412: astore_2
/*    */     //   1413: aload_0
/*    */     //   1414: aload_2
/*    */     //   1415: aload_0
/*    */     //   1416: aload_2
/*    */     //   1417: aload_1
/*    */     //   1418: iconst_5
/*    */     //   1419: aaload
/*    */     //   1420: iconst_0
/*    */     //   1421: swap
/*    */     //   1422: aastore
/*    */     //   1423: getfield M60 : [Lf/ge0;
/*    */     //   1426: iconst_5
/*    */     //   1427: aaload
/*    */     //   1428: iconst_1
/*    */     //   1429: swap
/*    */     //   1430: aastore
/*    */     //   1431: getfield Ve : [Lf/Rm;
/*    */     //   1434: iconst_5
/*    */     //   1435: aaload
/*    */     //   1436: iconst_2
/*    */     //   1437: swap
/*    */     //   1438: aastore
/*    */     //   1439: invokevirtual Mg : ([Lf/JG0;)Lf/U90;
/*    */     //   1442: invokevirtual ee0 : (Lf/U90;)Lf/U90;
/*    */     //   1445: astore_2
/*    */     //   1446: getfield Kt0 : Lf/Ip;
/*    */     //   1449: invokevirtual mE0 : ()Lf/g0;
/*    */     //   1452: aload_0
/*    */     //   1453: getfield Kt0 : Lf/Ip;
/*    */     //   1456: invokevirtual d7 : ()Lf/cr0;
/*    */     //   1459: aload_1
/*    */     //   1460: iconst_0
/*    */     //   1461: aaload
/*    */     //   1462: invokevirtual Ya : (Lf/JG0;)Lf/U90;
/*    */     //   1465: invokevirtual Em0 : ()Lf/U90;
/*    */     //   1468: iconst_2
/*    */     //   1469: anewarray f/JG0
/*    */     //   1472: dup
/*    */     //   1473: dup
/*    */     //   1474: aload_0
/*    */     //   1475: swap
/*    */     //   1476: aload_0
/*    */     //   1477: getfield M60 : [Lf/ge0;
/*    */     //   1480: iconst_0
/*    */     //   1481: aaload
/*    */     //   1482: iconst_0
/*    */     //   1483: swap
/*    */     //   1484: aastore
/*    */     //   1485: getfield Ve : [Lf/Rm;
/*    */     //   1488: iconst_0
/*    */     //   1489: aaload
/*    */     //   1490: iconst_1
/*    */     //   1491: swap
/*    */     //   1492: aastore
/*    */     //   1493: invokevirtual Mg : ([Lf/JG0;)Lf/U90;
/*    */     //   1496: invokevirtual ee0 : (Lf/U90;)Lf/U90;
/*    */     //   1499: aload_0
/*    */     //   1500: getfield Kt0 : Lf/Ip;
/*    */     //   1503: invokevirtual d7 : ()Lf/cr0;
/*    */     //   1506: aload_1
/*    */     //   1507: iconst_1
/*    */     //   1508: aaload
/*    */     //   1509: invokevirtual Ya : (Lf/JG0;)Lf/U90;
/*    */     //   1512: invokevirtual Em0 : ()Lf/U90;
/*    */     //   1515: iconst_2
/*    */     //   1516: anewarray f/JG0
/*    */     //   1519: dup
/*    */     //   1520: dup
/*    */     //   1521: aload_0
/*    */     //   1522: swap
/*    */     //   1523: aload_0
/*    */     //   1524: getfield M60 : [Lf/ge0;
/*    */     //   1527: iconst_1
/*    */     //   1528: aaload
/*    */     //   1529: iconst_0
/*    */     //   1530: swap
/*    */     //   1531: aastore
/*    */     //   1532: getfield Ve : [Lf/Rm;
/*    */     //   1535: iconst_1
/*    */     //   1536: aaload
/*    */     //   1537: iconst_1
/*    */     //   1538: swap
/*    */     //   1539: aastore
/*    */     //   1540: invokevirtual Mg : ([Lf/JG0;)Lf/U90;
/*    */     //   1543: invokevirtual ee0 : (Lf/U90;)Lf/U90;
/*    */     //   1546: aload_0
/*    */     //   1547: getfield Kt0 : Lf/Ip;
/*    */     //   1550: invokevirtual d7 : ()Lf/cr0;
/*    */     //   1553: aload_1
/*    */     //   1554: iconst_2
/*    */     //   1555: aaload
/*    */     //   1556: invokevirtual Ya : (Lf/JG0;)Lf/U90;
/*    */     //   1559: invokevirtual Em0 : ()Lf/U90;
/*    */     //   1562: iconst_2
/*    */     //   1563: anewarray f/JG0
/*    */     //   1566: dup
/*    */     //   1567: dup
/*    */     //   1568: aload_0
/*    */     //   1569: swap
/*    */     //   1570: aload_0
/*    */     //   1571: getfield M60 : [Lf/ge0;
/*    */     //   1574: iconst_2
/*    */     //   1575: aaload
/*    */     //   1576: iconst_0
/*    */     //   1577: swap
/*    */     //   1578: aastore
/*    */     //   1579: getfield Ve : [Lf/Rm;
/*    */     //   1582: iconst_2
/*    */     //   1583: aaload
/*    */     //   1584: iconst_1
/*    */     //   1585: swap
/*    */     //   1586: aastore
/*    */     //   1587: invokevirtual Mg : ([Lf/JG0;)Lf/U90;
/*    */     //   1590: invokevirtual ee0 : (Lf/U90;)Lf/U90;
/*    */     //   1593: aload_0
/*    */     //   1594: getfield Kt0 : Lf/Ip;
/*    */     //   1597: invokevirtual d7 : ()Lf/cr0;
/*    */     //   1600: aload_1
/*    */     //   1601: iconst_3
/*    */     //   1602: aaload
/*    */     //   1603: invokevirtual Ya : (Lf/JG0;)Lf/U90;
/*    */     //   1606: invokevirtual Em0 : ()Lf/U90;
/*    */     //   1609: iconst_2
/*    */     //   1610: anewarray f/JG0
/*    */     //   1613: dup
/*    */     //   1614: dup
/*    */     //   1615: aload_0
/*    */     //   1616: swap
/*    */     //   1617: aload_0
/*    */     //   1618: getfield M60 : [Lf/ge0;
/*    */     //   1621: iconst_3
/*    */     //   1622: aaload
/*    */     //   1623: iconst_0
/*    */     //   1624: swap
/*    */     //   1625: aastore
/*    */     //   1626: getfield Ve : [Lf/Rm;
/*    */     //   1629: iconst_3
/*    */     //   1630: aaload
/*    */     //   1631: iconst_1
/*    */     //   1632: swap
/*    */     //   1633: aastore
/*    */     //   1634: invokevirtual Mg : ([Lf/JG0;)Lf/U90;
/*    */     //   1637: invokevirtual ee0 : (Lf/U90;)Lf/U90;
/*    */     //   1640: aload_0
/*    */     //   1641: getfield Kt0 : Lf/Ip;
/*    */     //   1644: invokevirtual d7 : ()Lf/cr0;
/*    */     //   1647: aload_1
/*    */     //   1648: iconst_4
/*    */     //   1649: aaload
/*    */     //   1650: invokevirtual Ya : (Lf/JG0;)Lf/U90;
/*    */     //   1653: invokevirtual Em0 : ()Lf/U90;
/*    */     //   1656: iconst_2
/*    */     //   1657: anewarray f/JG0
/*    */     //   1660: dup
/*    */     //   1661: dup
/*    */     //   1662: aload_0
/*    */     //   1663: swap
/*    */     //   1664: aload_0
/*    */     //   1665: getfield M60 : [Lf/ge0;
/*    */     //   1668: iconst_4
/*    */     //   1669: aaload
/*    */     //   1670: iconst_0
/*    */     //   1671: swap
/*    */     //   1672: aastore
/*    */     //   1673: getfield Ve : [Lf/Rm;
/*    */     //   1676: iconst_4
/*    */     //   1677: aaload
/*    */     //   1678: iconst_1
/*    */     //   1679: swap
/*    */     //   1680: aastore
/*    */     //   1681: invokevirtual Mg : ([Lf/JG0;)Lf/U90;
/*    */     //   1684: invokevirtual ee0 : (Lf/U90;)Lf/U90;
/*    */     //   1687: aload_0
/*    */     //   1688: getfield Kt0 : Lf/Ip;
/*    */     //   1691: invokevirtual d7 : ()Lf/cr0;
/*    */     //   1694: aload_1
/*    */     //   1695: iconst_5
/*    */     //   1696: aaload
/*    */     //   1697: invokevirtual Ya : (Lf/JG0;)Lf/U90;
/*    */     //   1700: invokevirtual Em0 : ()Lf/U90;
/*    */     //   1703: iconst_2
/*    */     //   1704: anewarray f/JG0
/*    */     //   1707: dup
/*    */     //   1708: dup
/*    */     //   1709: aload_0
/*    */     //   1710: swap
/*    */     //   1711: aload_0
/*    */     //   1712: getfield M60 : [Lf/ge0;
/*    */     //   1715: iconst_5
/*    */     //   1716: aaload
/*    */     //   1717: iconst_0
/*    */     //   1718: swap
/*    */     //   1719: aastore
/*    */     //   1720: getfield Ve : [Lf/Rm;
/*    */     //   1723: iconst_5
/*    */     //   1724: aaload
/*    */     //   1725: iconst_1
/*    */     //   1726: swap
/*    */     //   1727: aastore
/*    */     //   1728: invokevirtual Mg : ([Lf/JG0;)Lf/U90;
/*    */     //   1731: invokevirtual ee0 : (Lf/U90;)Lf/U90;
/*    */     //   1734: astore_1
/*    */     //   1735: getfield Kt0 : Lf/Ip;
/*    */     //   1738: invokevirtual xh : ()Lf/U90;
/*    */     //   1741: aload_2
/*    */     //   1742: invokevirtual ee0 : (Lf/U90;)Lf/U90;
/*    */     //   1745: pop
/*    */     //   1746: getfield Kt0 : Lf/Ip;
/*    */     //   1749: invokevirtual iJ0 : ()Lf/U90;
/*    */     //   1752: aload_1
/*    */     //   1753: invokevirtual ee0 : (Lf/U90;)Lf/U90;
/*    */     //   1756: pop
/*    */     //   1757: aload_0
/*    */     //   1758: dup
/*    */     //   1759: new f/Un
/*    */     //   1762: dup
/*    */     //   1763: astore_1
/*    */     //   1764: aload_0
/*    */     //   1765: aload_1
/*    */     //   1766: bipush #52
/*    */     //   1768: invokestatic OH0 : (I)Ljava/lang/String;
/*    */     //   1771: invokespecial <init> : (Ljava/lang/String;)V
/*    */     //   1774: <illegal opcode> run : (Lf/n;)Ljava/lang/Runnable;
/*    */     //   1779: invokevirtual tW : (Ljava/lang/Runnable;)V
/*    */     //   1782: getfield Kt0 : Lf/Ip;
/*    */     //   1785: invokevirtual xh : ()Lf/U90;
/*    */     //   1788: aload_1
/*    */     //   1789: invokevirtual Ya : (Lf/JG0;)Lf/U90;
/*    */     //   1792: pop
/*    */     //   1793: getfield Kt0 : Lf/Ip;
/*    */     //   1796: invokevirtual iJ0 : ()Lf/U90;
/*    */     //   1799: aload_1
/*    */     //   1800: invokevirtual Ya : (Lf/JG0;)Lf/U90;
/*    */     //   1803: pop
/*    */     //   1804: goto -> 2204
/*    */     //   1807: aload #5
/*    */     //   1809: aload #4
/*    */     //   1811: sipush #5588
/*    */     //   1814: invokestatic OH0 : (I)Ljava/lang/String;
/*    */     //   1817: invokevirtual E1 : (Ljava/lang/String;)V
/*    */     //   1820: invokevirtual yE0 : ()I
/*    */     //   1823: ifle -> 1890
/*    */     //   1826: aload_3
/*    */     //   1827: dup
/*    */     //   1828: new f/Un
/*    */     //   1831: dup
/*    */     //   1832: astore #4
/*    */     //   1834: aload_0
/*    */     //   1835: aload #4
/*    */     //   1837: ldc_w '$'
/*    */     //   1840: invokestatic df : (Ljava/lang/String;)Ljava/lang/StringBuilder;
/*    */     //   1843: invokestatic getInstance : ()Ljava/text/NumberFormat;
/*    */     //   1846: aload #5
/*    */     //   1848: invokevirtual yE0 : ()I
/*    */     //   1851: i2l
/*    */     //   1852: invokevirtual format : (J)Ljava/lang/String;
/*    */     //   1855: invokevirtual append : (Ljava/lang/String;)Ljava/lang/StringBuilder;
/*    */     //   1858: invokevirtual toString : ()Ljava/lang/String;
/*    */     //   1861: invokespecial <init> : (Ljava/lang/String;)V
/*    */     //   1864: <illegal opcode> run : (Lf/n;)Ljava/lang/Runnable;
/*    */     //   1869: invokevirtual tW : (Ljava/lang/Runnable;)V
/*    */     //   1872: invokevirtual xh : ()Lf/U90;
/*    */     //   1875: aload #4
/*    */     //   1877: invokevirtual Ya : (Lf/JG0;)Lf/U90;
/*    */     //   1880: pop
/*    */     //   1881: invokevirtual iJ0 : ()Lf/U90;
/*    */     //   1884: aload #4
/*    */     //   1886: invokevirtual Ya : (Lf/JG0;)Lf/U90;
/*    */     //   1889: pop
/*    */     //   1890: aload #5
/*    */     //   1892: invokevirtual gk : ()I
/*    */     //   1895: ifle -> 1977
/*    */     //   1898: aload_3
/*    */     //   1899: dup
/*    */     //   1900: new f/Un
/*    */     //   1903: dup
/*    */     //   1904: astore #4
/*    */     //   1906: aload_0
/*    */     //   1907: aload #4
/*    */     //   1909: new java/lang/StringBuilder
/*    */     //   1912: dup
/*    */     //   1913: invokespecial <init> : ()V
/*    */     //   1916: invokestatic getInstance : ()Ljava/text/NumberFormat;
/*    */     //   1919: aload #5
/*    */     //   1921: invokevirtual gk : ()I
/*    */     //   1924: i2l
/*    */     //   1925: invokevirtual format : (J)Ljava/lang/String;
/*    */     //   1928: invokevirtual append : (Ljava/lang/String;)Ljava/lang/StringBuilder;
/*    */     //   1931: ldc ' '
/*    */     //   1933: invokevirtual append : (Ljava/lang/String;)Ljava/lang/StringBuilder;
/*    */     //   1936: sipush #3002
/*    */     //   1939: invokestatic OH0 : (I)Ljava/lang/String;
/*    */     //   1942: invokevirtual append : (Ljava/lang/String;)Ljava/lang/StringBuilder;
/*    */     //   1945: invokevirtual toString : ()Ljava/lang/String;
/*    */     //   1948: invokespecial <init> : (Ljava/lang/String;)V
/*    */     //   1951: <illegal opcode> run : (Lf/n;)Ljava/lang/Runnable;
/*    */     //   1956: invokevirtual tW : (Ljava/lang/Runnable;)V
/*    */     //   1959: invokevirtual xh : ()Lf/U90;
/*    */     //   1962: aload #4
/*    */     //   1964: invokevirtual Ya : (Lf/JG0;)Lf/U90;
/*    */     //   1967: pop
/*    */     //   1968: invokevirtual iJ0 : ()Lf/U90;
/*    */     //   1971: aload #4
/*    */     //   1973: invokevirtual Ya : (Lf/JG0;)Lf/U90;
/*    */     //   1976: pop
/*    */     //   1977: aload #5
/*    */     //   1979: invokevirtual Kw0 : ()I
/*    */     //   1982: ifle -> 2063
/*    */     //   1985: aload_3
/*    */     //   1986: dup
/*    */     //   1987: new f/Un
/*    */     //   1990: dup
/*    */     //   1991: astore #4
/*    */     //   1993: aload_0
/*    */     //   1994: aload #4
/*    */     //   1996: new java/lang/StringBuilder
/*    */     //   1999: dup
/*    */     //   2000: invokespecial <init> : ()V
/*    */     //   2003: invokestatic getInstance : ()Ljava/text/NumberFormat;
/*    */     //   2006: aload #5
/*    */     //   2008: invokevirtual Kw0 : ()I
/*    */     //   2011: i2l
/*    */     //   2012: invokevirtual format : (J)Ljava/lang/String;
/*    */     //   2015: invokevirtual append : (Ljava/lang/String;)Ljava/lang/StringBuilder;
/*    */     //   2018: ldc ' '
/*    */     //   2020: invokevirtual append : (Ljava/lang/String;)Ljava/lang/StringBuilder;
/*    */     //   2023: bipush #121
/*    */     //   2025: invokestatic OH0 : (I)Ljava/lang/String;
/*    */     //   2028: invokevirtual append : (Ljava/lang/String;)Ljava/lang/StringBuilder;
/*    */     //   2031: invokevirtual toString : ()Ljava/lang/String;
/*    */     //   2034: invokespecial <init> : (Ljava/lang/String;)V
/*    */     //   2037: <illegal opcode> run : (Lf/n;)Ljava/lang/Runnable;
/*    */     //   2042: invokevirtual tW : (Ljava/lang/Runnable;)V
/*    */     //   2045: invokevirtual xh : ()Lf/U90;
/*    */     //   2048: aload #4
/*    */     //   2050: invokevirtual Ya : (Lf/JG0;)Lf/U90;
/*    */     //   2053: pop
/*    */     //   2054: invokevirtual iJ0 : ()Lf/U90;
/*    */     //   2057: aload #4
/*    */     //   2059: invokevirtual Ya : (Lf/JG0;)Lf/U90;
/*    */     //   2062: pop
/*    */     //   2063: aload #5
/*    */     //   2065: invokevirtual tU : ()S
/*    */     //   2068: ifle -> 2204
/*    */     //   2071: new java/lang/StringBuilder
/*    */     //   2074: dup
/*    */     //   2075: dup2
/*    */     //   2076: astore #4
/*    */     //   2078: aload #5
/*    */     //   2080: aload #4
/*    */     //   2082: invokespecial <init> : ()V
/*    */     //   2085: invokestatic b20 : ()Lf/Of;
/*    */     //   2088: aload #5
/*    */     //   2090: invokevirtual tU : ()S
/*    */     //   2093: invokevirtual On0 : (S)Lf/LPT3;
/*    */     //   2096: astore #5
/*    */     //   2098: invokevirtual pQ : ()S
/*    */     //   2101: invokevirtual append : (I)Ljava/lang/StringBuilder;
/*    */     //   2104: pop
/*    */     //   2105: ldc_w 'x '
/*    */     //   2108: invokevirtual append : (Ljava/lang/String;)Ljava/lang/StringBuilder;
/*    */     //   2111: pop
/*    */     //   2112: aload #5
/*    */     //   2114: invokevirtual getName : ()Ljava/lang/String;
/*    */     //   2117: invokevirtual append : (Ljava/lang/String;)Ljava/lang/StringBuilder;
/*    */     //   2120: pop
/*    */     //   2121: aload #5
/*    */     //   2123: new f/Un
/*    */     //   2126: dup
/*    */     //   2127: astore #6
/*    */     //   2129: aload #4
/*    */     //   2131: invokevirtual toString : ()Ljava/lang/String;
/*    */     //   2134: invokespecial <init> : (Ljava/lang/String;)V
/*    */     //   2137: invokevirtual Pd0 : ()Lf/wc;
/*    */     //   2140: ifnull -> 2171
/*    */     //   2143: aload #5
/*    */     //   2145: invokevirtual Pd0 : ()Lf/wc;
/*    */     //   2148: invokevirtual XF0 : ()Z
/*    */     //   2151: ifne -> 2157
/*    */     //   2154: goto -> 2171
/*    */     //   2157: aload_0
/*    */     //   2158: aload_2
/*    */     //   2159: aload #5
/*    */     //   2161: aload_1
/*    */     //   2162: <illegal opcode> run : (Lf/n;Lf/Kf;Lf/LPT3;Lf/nE0;)Ljava/lang/Runnable;
/*    */     //   2167: astore_1
/*    */     //   2168: goto -> 2178
/*    */     //   2171: aload_0
/*    */     //   2172: <illegal opcode> run : (Lf/n;)Ljava/lang/Runnable;
/*    */     //   2177: astore_1
/*    */     //   2178: aload_3
/*    */     //   2179: dup
/*    */     //   2180: aload #6
/*    */     //   2182: aload_1
/*    */     //   2183: invokevirtual tW : (Ljava/lang/Runnable;)V
/*    */     //   2186: invokevirtual xh : ()Lf/U90;
/*    */     //   2189: aload #6
/*    */     //   2191: invokevirtual Ya : (Lf/JG0;)Lf/U90;
/*    */     //   2194: pop
/*    */     //   2195: invokevirtual iJ0 : ()Lf/U90;
/*    */     //   2198: aload #6
/*    */     //   2200: invokevirtual Ya : (Lf/JG0;)Lf/U90;
/*    */     //   2203: pop
/*    */     //   2204: aload_0
/*    */     //   2205: dup
/*    */     //   2206: dup2
/*    */     //   2207: new f/Un
/*    */     //   2210: dup
/*    */     //   2211: astore_1
/*    */     //   2212: aload_0
/*    */     //   2213: aload_1
/*    */     //   2214: bipush #53
/*    */     //   2216: invokestatic OH0 : (I)Ljava/lang/String;
/*    */     //   2219: invokespecial <init> : (Ljava/lang/String;)V
/*    */     //   2222: <illegal opcode> run : (Lf/n;)Ljava/lang/Runnable;
/*    */     //   2227: invokevirtual tW : (Ljava/lang/Runnable;)V
/*    */     //   2230: getfield Kt0 : Lf/Ip;
/*    */     //   2233: invokevirtual xh : ()Lf/U90;
/*    */     //   2236: bipush #25
/*    */     //   2238: invokevirtual Aq : (I)Lf/U90;
/*    */     //   2241: aload_1
/*    */     //   2242: invokevirtual Ya : (Lf/JG0;)Lf/U90;
/*    */     //   2245: pop
/*    */     //   2246: getfield Kt0 : Lf/Ip;
/*    */     //   2249: invokevirtual iJ0 : ()Lf/U90;
/*    */     //   2252: aload_1
/*    */     //   2253: invokevirtual Ya : (Lf/JG0;)Lf/U90;
/*    */     //   2256: pop
/*    */     //   2257: getfield Kt0 : Lf/Ip;
/*    */     //   2260: invokevirtual J8 : (Lf/JG0;)V
/*    */     //   2263: return
/*    */     // Line number table:
/*    */     //   Java source line number -> byte code offset
/*    */     //   #1	-> 171
/*    */     //   #2	-> 178
/*    */     //   #3	-> 1837
/* 10 */     //   #4	-> 1843 } private void kI0(int paramInt) { this.Ve[paramInt].sk0((this.M60[paramInt]).TG0.nm0()); } public final void Bl0() { A30 a30; if ((a30 = this.Ub0).fd < 1) return;  a30 = null; nV nV; if (a30.jJ0 && (nV = nV.Y4((byte)(this.WB0.Wa0.go - 1))) == null) { km.u4.Pq(Ml0.OH0(5618)); return; }  byte b = -1; if (this.Ub0.O00 && (b = (byte)(this.Hv.Wa0.go - 1)) < 0)
/* 11 */     { km.u4.Pq(Ml0.OH0(5623)); return; }  this(); Lw lw; Fm fm; if (this.Ub0
/* 12 */       .Yk0 > 0) { byte b3 = 0; while (b3 < 
/* 13 */         this.Ub0
/* 14 */         .Yk0)
/*    */       { WD wD;
/*    */         
/*    */         short s1;
/* 18 */         if ((wD = this.OZ[(this.pD0[b3]).Wa0.go]) != null && (
/* 19 */           s1 = wD.HA) >= 1 && 
/* 20 */           !lw.Fb(s1)) lw
/*    */             
/* 22 */             .Ye0(wD.HA);  b3++; }  }  byte b1; if (lw
/* 23 */       .ir0 != (
/*    */       
/* 25 */       b1 = this.Ub0.Yk0))
/* 26 */     { km.u4.Pq(Ml0.Go(5619, Integer.toString(b1))); return; }  this(); if (this.Ub0
/* 27 */       .Rt > 0)
/* 28 */     { hR[] arrayOfHR1; int i1; byte b3; for (i1 = (arrayOfHR1 = hR.Tm0).length, b3 = 0; b3 < i1; ) { hR hR = arrayOfHR1[b3];
/*    */         
/* 30 */         if ((this.M60[hR.It0])
/* 31 */           .TG0
/* 32 */           .nm0()) fm
/*    */ 
/*    */ 
/*    */ 
/*    */             
/* 37 */             .ej((byte)(this.Ve[hR.It0]).T8, hR);  b3++; }  }  byte b2; if (fm
/* 38 */       .ir0 != (
/*    */       
/* 40 */       b2 = this.Ub0.Rt))
/* 41 */     { km.u4.Pq(Ml0.Go(5620, Integer.toString(b2))); return; }  Vg0 vg0 = new Vg0(); short[] arrayOfShort = lw.YH();
/*    */     
/* 43 */     hR[] arrayOfHR = new hR[fm.ir0]; Object[] arrayOfObject2; int k;
/* 44 */     for (int j = (arrayOfObject2 = fm.QG0).length; j-- > 0;) { if ((object = arrayOfObject2[j]) != zb0.IM && object != zb0.ET) { int i1 = k + 1; arrayOfHR[k] = (hR)object; k = i1; }  }
/* 45 */      arrayOfHR = arrayOfHR; Object[] arrayOfObject1; byte[] arrayOfByte1, arrayOfByte2;
/*    */     int m;
/* 47 */     for (arrayOfByte1 = new byte[fm.ir0], arrayOfObject1 = fm.QG0, k = (arrayOfByte2 = fm.pC0).length, m = 0; k-- > 0;) { if ((object = arrayOfObject1[k]) != zb0.IM && object != zb0.ET) { int i1 = m + 1; arrayOfByte1[m] = arrayOfByte2[k]; m = i1; }  }
/* 48 */      this(nV, b, arrayOfShort, arrayOfHR, arrayOfByte1);
/* 49 */     int i = this.r8.bz0;
/* 50 */     b = this.r8.Ly;
/*    */ 
/*    */     
/* 53 */     short s = this.HD0.dA0.w6;
/* 54 */     km.u4.mS(i, b, vg0, s, (byte)0);
/* 55 */     ra0(); }
/*    */ 
/*    */   
/*    */   public final void RE(byte paramByte) {
/*    */     this(paramByte);
/*    */     Vg0 vg0;
/*    */     int i = this.r8.bz0;
/*    */     byte b = this.r8.Ly;
/*    */     short s = this.HD0.dA0.w6;
/*    */     km.u4.mS(i, b, vg0, s, (byte)0);
/*    */     ra0();
/*    */   }
/*    */   
/*    */   public final void d40() {
/*    */     super.d40();
/*    */     this.Kt0.mM();
/*    */     QI();
/*    */     this.Kt0.js0(et.Wi0);
/*    */   }
/*    */   
/*    */   public final void jA0() {
/*    */     super.jA0();
/*    */     Kf kf;
/*    */     if ((kf = this.HD0) != null)
/*    */       VA0.c90(this); 
/*    */   } }


/* Location:              /Users/vnnsnnt/Documents/Codespace/JavaWorkspace/RedTrainer/src/main/java/org/trainer/client/PokeMMO.jar!/f/n.class
 * Java compiler version: 8 (52.0)
 * JD-Core Version:       1.1.3
 */