/*  1 */ package f;public class n3 extends Ip { public static final Ll lB0 = Ll.F10("filtered"); public static final Ll qJ = Ll.F10("obey"); public static final pRn BC0 = new pRn(1610612735); public Zq[] f9; public final gO n90; public int Zb; public final void dI0(int paramInt1, int paramInt2) { if (!this.ku0) return;  Zq[] arrayOfZq; int i; byte b; for (i = (arrayOfZq = this.f9).length, b = 0; b < i; ) { Zq zq; if ((zq = arrayOfZq[b]).Kd >= 
/*  2 */         Math.min(this.Mn0, paramInt1) - zq
/*  3 */         .xY && zq
/*  4 */         .Kd <= 
/*  5 */         Math.max(this.Mn0, paramInt1) && zq
/*  6 */         .er0 >= 
/*  7 */         Math.min(this.rA, paramInt2) - zq
/*  8 */         .HC && zq
/*  9 */         .er0 <= 
/* 10 */         Math.max(this.rA, paramInt2)) { zq
/* 11 */           .TG0
/* 12 */           .Fx0(true); } else { zq
/* 13 */           .TG0
/* 14 */           .Fx0(false); }  b++; }  } public int Gg0 = 0; public Consumer Qx0; public boolean dy; public int Mn0; public int rA; public boolean ku0; public n3(gO paramgO, int paramInt) { Xu("dialoglayout"); this.n90 = paramgO; this.Zb = paramInt; a5(); lp0(null); } public void lp0(String[] paramArrayOfString) { if (km.u4.s40(aq0.LI) == null) return;  if (paramArrayOfString != null && paramArrayOfString.length == 1 && paramArrayOfString[0].isEmpty()) paramArrayOfString = null;  short s = (short)(this.Zb * 60); byte b = 0; um0 um0 = um0.Kt0; short s1 = 0; while (s1 < this.f9.length) { j40 j40; if ((j40 = km.u4.s40(aq0.XJ0).ky((short)(s + s1))) != null) { Sa0 sa0; Ll ll; short s2 = j40.Zs.Vf0(); byte b1 = j40.s5(); this.f9[s1].Ax(um0.lb(s2, j40.Zs.da(), b1)[0]); this.f9[s1].zf(j40); km.gE0(); (this.f9[s1]).z4 = rG0.Zs0(j40, false, false, true); this.f9[s1].zn(); (this.f9[s1]).Az0 = "tooltip-markup"; (this.f9[s1]).jl = 300; gO gO3; for (Hc0 hc0 = (gO3 = this.n90).V3.r30(); hc0.hasNext(); )
/* 15 */         { Q90 q90 = j40.Zs;
/*    */           
/* 17 */           if (!((sK)hc0.next()).fy(q90, j40.LPT4)) { boolean bool1 = false; if (bool1) b++;
/*    */             
/* 19 */             (sa0 = (this.f9[s1]).O)
/* 20 */               .gf0(lB0, bool1); ll = qJ;
/*    */ 
/*    */ 
/*    */ 
/*    */ 
/*    */ 
/*    */             
/* 27 */             int j = ((j40.Zs.od <= km.u4.fF0.ry0(km.a3.eA)) ? 1 : 0) ^ 0x1; sa0
/* 28 */               .gf0(ll, j); }  }  if (paramArrayOfString == null && ((gO)ll).V3.Z8 == 0) continue;  boolean bool = sa0.pJ0(paramArrayOfString); continue; }  (this.f9[s1])
/* 29 */         .db0 = null;
/* 30 */       this.f9[s1].Ax(null); this.f9[s1].zf(null); (this.f9[s1])
/* 31 */         .z4 = null;
/* 32 */       this.f9[s1].zn();
/* 33 */       (this.f9[s1])
/* 34 */         .TG0
/* 35 */         .Fx0(false); s1 = (short)(s1 + 1); }  gO gO1 = this.n90;
/* 36 */     int i = this.Zb;
/*    */ 
/*    */ 
/*    */     
/* 40 */     gf gf = (gf)(this.fH[this.LPt7.cm0(i)]).ZX; of of;
/*    */     gO gO2;
/* 42 */     if ((gO2 = this.n90).V3
/* 43 */       .Z8 != 0 || ((of = gO2.ok0) != null && 
/*    */ 
/*    */ 
/*    */       
/* 47 */       !of.F2.PH0.toString().isEmpty())) {  } else {  }  if (false && this != null) { if (b == 0)
/*    */       { I i1; Ja0 ja0;
/* 49 */         this(this); this(ja0, BC0);
/* 50 */         this.db0 = i1; } else if (this
/* 51 */         .db0 != null) { this
/* 52 */           .db0 = null; return; }  } else if (this != null && this.db0 != null) { this.db0 = null;
/*    */       return; }
/*    */      }
/*    */ 
/*    */   
/*    */   public final void cE0(int paramInt1, int paramInt2) {
/*    */     if (!this.ku0)
/*    */       return; 
/*    */     Zq[] arrayOfZq;
/*    */     int i;
/*    */     byte b;
/*    */     for (i = (arrayOfZq = this.f9).length, b = 0; b < i; ) {
/*    */       Zq zq;
/*    */       if ((zq = arrayOfZq[b]).Kd >= Math.min(this.Mn0, paramInt1) - zq.xY && zq.Kd <= Math.max(this.Mn0, paramInt1) && zq.er0 >= Math.min(this.rA, paramInt2) - zq.HC && zq.er0 <= Math.max(this.rA, paramInt2) && zq.public() != null) {
/*    */         zq.Cx0(true);
/*    */       } else {
/*    */         zq.TG0.Fx0(false);
/*    */       } 
/*    */       b++;
/*    */     } 
/*    */     this.ku0 = false;
/*    */   }
/*    */   
/*    */   public void H0(int paramInt) {
/*    */     this.Gg0 = paramInt;
/*    */     Consumer<j40> consumer;
/*    */     if ((consumer = this.Qx0) != null)
/*    */       consumer.accept(this.f9[paramInt].public()); 
/*    */     if (this.dy) {
/*    */       int i = (this.f9[paramInt]).Kd;
/*    */       dI0(i, (this.f9[paramInt]).er0);
/*    */     } 
/*    */     this.f9[paramInt].BA();
/*    */   }
/*    */   
/*    */   public void EX(nY paramnY) {}
/*    */   
/*    */   public final Zq[] t00() {
/*    */     this();
/*    */     ArrayList arrayList;
/*    */     Zq[] arrayOfZq;
/*    */     int i;
/*    */     byte b;
/*    */     for (i = (arrayOfZq = this.f9).length, b = 0; b < i; ) {
/*    */       Zq zq;
/*    */       if ((zq = arrayOfZq[b]).TG0.nm0() && zq.public() != null)
/*    */         add((E)zq); 
/*    */       b++;
/*    */     } 
/*    */     return toArray(new Zq[0]);
/*    */   }
/*    */   
/*    */   public final void d40() {
/*    */     super.d40();
/*    */   }
/*    */   
/*    */   public boolean i2(oa0 paramoa0) {
/*    */     // Byte code:
/*    */     //   0: aload_1
/*    */     //   1: getfield cz0 : I
/*    */     //   4: invokestatic Wm0 : (I)Z
/*    */     //   7: ifeq -> 488
/*    */     //   10: aload_1
/*    */     //   11: invokevirtual oO : ()Z
/*    */     //   14: ifeq -> 488
/*    */     //   17: aload_1
/*    */     //   18: getfield GG0 : I
/*    */     //   21: getstatic f/BM.lc : Lf/BM;
/*    */     //   24: invokestatic J20 : (ILf/BM;)Z
/*    */     //   27: ifeq -> 92
/*    */     //   30: aload_0
/*    */     //   31: getfield n90 : Lf/gO;
/*    */     //   34: getfield U40 : Lf/Qv0;
/*    */     //   37: ifnonnull -> 92
/*    */     //   40: aload_0
/*    */     //   41: invokevirtual t00 : ()[Lf/Zq;
/*    */     //   44: dup
/*    */     //   45: astore_1
/*    */     //   46: arraylength
/*    */     //   47: ifle -> 66
/*    */     //   50: aload_1
/*    */     //   51: invokestatic stream : ([Ljava/lang/Object;)Ljava/util/stream/Stream;
/*    */     //   54: <illegal opcode> accept : ()Ljava/util/function/Consumer;
/*    */     //   59: invokeinterface forEach : (Ljava/util/function/Consumer;)V
/*    */     //   64: iconst_1
/*    */     //   65: ireturn
/*    */     //   66: aload_0
/*    */     //   67: getfield n90 : Lf/gO;
/*    */     //   70: dup
/*    */     //   71: astore_0
/*    */     //   72: getfield fH : [Lf/nJ0;
/*    */     //   75: aload_0
/*    */     //   76: getfield s5 : I
/*    */     //   79: aaload
/*    */     //   80: getfield ZX : Ljava/lang/Object;
/*    */     //   83: checkcast f/JG0
/*    */     //   86: invokestatic c90 : (Lf/JG0;)Z
/*    */     //   89: pop
/*    */     //   90: iconst_1
/*    */     //   91: ireturn
/*    */     //   92: aload_1
/*    */     //   93: getfield GG0 : I
/*    */     //   96: getstatic f/BM.bC : Lf/BM;
/*    */     //   99: invokestatic J20 : (ILf/BM;)Z
/*    */     //   102: ifeq -> 204
/*    */     //   105: aload_0
/*    */     //   106: getfield dy : Z
/*    */     //   109: ifeq -> 170
/*    */     //   112: aload_0
/*    */     //   113: getfield n90 : Lf/gO;
/*    */     //   116: getfield U40 : Lf/Qv0;
/*    */     //   119: ifnull -> 124
/*    */     //   122: iconst_1
/*    */     //   123: ireturn
/*    */     //   124: aload_0
/*    */     //   125: dup
/*    */     //   126: iconst_0
/*    */     //   127: invokevirtual zn0 : (Z)V
/*    */     //   130: invokevirtual M50 : ()Lf/Zq;
/*    */     //   133: astore_1
/*    */     //   134: getstatic f/js.vu0 : Lf/js;
/*    */     //   137: aload_1
/*    */     //   138: dup
/*    */     //   139: aload_0
/*    */     //   140: dup
/*    */     //   141: invokevirtual t00 : ()[Lf/Zq;
/*    */     //   144: astore_0
/*    */     //   145: getfield Zb : I
/*    */     //   148: istore_2
/*    */     //   149: getfield Kd : I
/*    */     //   152: istore_3
/*    */     //   153: getfield er0 : I
/*    */     //   156: istore #4
/*    */     //   158: iconst_0
/*    */     //   159: iload_2
/*    */     //   160: iload_3
/*    */     //   161: aload_1
/*    */     //   162: aload_0
/*    */     //   163: iload #4
/*    */     //   165: invokevirtual jv0 : (ZIILf/Qv0;[Lf/Qv0;I)V
/*    */     //   168: iconst_1
/*    */     //   169: ireturn
/*    */     //   170: aload_0
/*    */     //   171: getfield n90 : Lf/gO;
/*    */     //   174: invokevirtual gO : ()Z
/*    */     //   177: ifeq -> 204
/*    */     //   180: aload_0
/*    */     //   181: getfield n90 : Lf/gO;
/*    */     //   184: getfield U40 : Lf/Qv0;
/*    */     //   187: ifnull -> 192
/*    */     //   190: iconst_1
/*    */     //   191: ireturn
/*    */     //   192: aload_0
/*    */     //   193: dup
/*    */     //   194: getfield dy : Z
/*    */     //   197: iconst_1
/*    */     //   198: ixor
/*    */     //   199: invokevirtual zn0 : (Z)V
/*    */     //   202: iconst_1
/*    */     //   203: ireturn
/*    */     //   204: aload_1
/*    */     //   205: getfield GG0 : I
/*    */     //   208: getstatic f/BM.Oq : Lf/BM;
/*    */     //   211: invokestatic J20 : (ILf/BM;)Z
/*    */     //   214: ifeq -> 247
/*    */     //   217: aload_0
/*    */     //   218: getfield Gg0 : I
/*    */     //   221: iconst_1
/*    */     //   222: isub
/*    */     //   223: dup
/*    */     //   224: aload_0
/*    */     //   225: swap
/*    */     //   226: putfield Gg0 : I
/*    */     //   229: ifge -> 237
/*    */     //   232: aload_0
/*    */     //   233: iconst_0
/*    */     //   234: putfield Gg0 : I
/*    */     //   237: aload_0
/*    */     //   238: dup
/*    */     //   239: getfield Gg0 : I
/*    */     //   242: invokevirtual H0 : (I)V
/*    */     //   245: iconst_1
/*    */     //   246: ireturn
/*    */     //   247: aload_1
/*    */     //   248: getfield GG0 : I
/*    */     //   251: getstatic f/BM.M8 : Lf/BM;
/*    */     //   254: invokestatic J20 : (ILf/BM;)Z
/*    */     //   257: ifeq -> 356
/*    */     //   260: aload_0
/*    */     //   261: getfield Gg0 : I
/*    */     //   264: iconst_1
/*    */     //   265: iadd
/*    */     //   266: dup
/*    */     //   267: istore_1
/*    */     //   268: aload_0
/*    */     //   269: dup
/*    */     //   270: iload_1
/*    */     //   271: putfield Gg0 : I
/*    */     //   274: getfield f9 : [Lf/Zq;
/*    */     //   277: dup
/*    */     //   278: astore_1
/*    */     //   279: arraylength
/*    */     //   280: if_icmplt -> 291
/*    */     //   283: aload_0
/*    */     //   284: aload_1
/*    */     //   285: arraylength
/*    */     //   286: iconst_1
/*    */     //   287: isub
/*    */     //   288: putfield Gg0 : I
/*    */     //   291: aload_0
/*    */     //   292: getfield Gg0 : I
/*    */     //   295: aload_0
/*    */     //   296: invokevirtual Gz0 : ()I
/*    */     //   299: irem
/*    */     //   300: ifne -> 346
/*    */     //   303: aload_0
/*    */     //   304: getfield n90 : Lf/gO;
/*    */     //   307: getfield oP : Lf/NR;
/*    */     //   310: dup
/*    */     //   311: dup
/*    */     //   312: astore_1
/*    */     //   313: invokevirtual getClass : ()Ljava/lang/Class;
/*    */     //   316: pop
/*    */     //   317: invokestatic c90 : (Lf/JG0;)Z
/*    */     //   320: ifeq -> 333
/*    */     //   323: aload_1
/*    */     //   324: dup
/*    */     //   325: iconst_1
/*    */     //   326: putfield rs0 : Z
/*    */     //   329: iconst_1
/*    */     //   330: invokevirtual Op : (Z)V
/*    */     //   333: aload_0
/*    */     //   334: dup
/*    */     //   335: getfield Gg0 : I
/*    */     //   338: iconst_1
/*    */     //   339: isub
/*    */     //   340: putfield Gg0 : I
/*    */     //   343: goto -> 354
/*    */     //   346: aload_0
/*    */     //   347: dup
/*    */     //   348: getfield Gg0 : I
/*    */     //   351: invokevirtual H0 : (I)V
/*    */     //   354: iconst_1
/*    */     //   355: ireturn
/*    */     //   356: aload_1
/*    */     //   357: aload_0
/*    */     //   358: invokevirtual Gz0 : ()I
/*    */     //   361: istore_2
/*    */     //   362: getfield GG0 : I
/*    */     //   365: getstatic f/BM.ni : Lf/BM;
/*    */     //   368: invokestatic J20 : (ILf/BM;)Z
/*    */     //   371: ifeq -> 428
/*    */     //   374: aload_0
/*    */     //   375: getfield Gg0 : I
/*    */     //   378: iload_2
/*    */     //   379: isub
/*    */     //   380: dup
/*    */     //   381: istore_1
/*    */     //   382: aload_0
/*    */     //   383: iload_1
/*    */     //   384: putfield Gg0 : I
/*    */     //   387: ifge -> 421
/*    */     //   390: aload_0
/*    */     //   391: dup
/*    */     //   392: iconst_0
/*    */     //   393: putfield Gg0 : I
/*    */     //   396: getfield n90 : Lf/gO;
/*    */     //   399: dup
/*    */     //   400: astore_0
/*    */     //   401: getfield fH : [Lf/nJ0;
/*    */     //   404: aload_0
/*    */     //   405: getfield s5 : I
/*    */     //   408: aaload
/*    */     //   409: getfield ZX : Ljava/lang/Object;
/*    */     //   412: checkcast f/gf
/*    */     //   415: invokevirtual BA : ()Z
/*    */     //   418: pop
/*    */     //   419: iconst_1
/*    */     //   420: ireturn
/*    */     //   421: aload_0
/*    */     //   422: iload_1
/*    */     //   423: invokevirtual H0 : (I)V
/*    */     //   426: iconst_1
/*    */     //   427: ireturn
/*    */     //   428: aload_1
/*    */     //   429: getfield GG0 : I
/*    */     //   432: getstatic f/BM.N70 : Lf/BM;
/*    */     //   435: invokestatic J20 : (ILf/BM;)Z
/*    */     //   438: ifeq -> 488
/*    */     //   441: aload_0
/*    */     //   442: getfield Gg0 : I
/*    */     //   445: iload_2
/*    */     //   446: iadd
/*    */     //   447: dup
/*    */     //   448: istore_1
/*    */     //   449: aload_0
/*    */     //   450: dup
/*    */     //   451: iload_1
/*    */     //   452: putfield Gg0 : I
/*    */     //   455: getfield f9 : [Lf/Zq;
/*    */     //   458: arraylength
/*    */     //   459: if_icmplt -> 481
/*    */     //   462: aload_0
/*    */     //   463: dup
/*    */     //   464: iload_1
/*    */     //   465: iload_2
/*    */     //   466: isub
/*    */     //   467: putfield Gg0 : I
/*    */     //   470: getfield n90 : Lf/gO;
/*    */     //   473: getfield M50 : Lf/ZE;
/*    */     //   476: invokevirtual Ev0 : ()V
/*    */     //   479: iconst_1
/*    */     //   480: ireturn
/*    */     //   481: aload_0
/*    */     //   482: iload_1
/*    */     //   483: invokevirtual H0 : (I)V
/*    */     //   486: iconst_1
/*    */     //   487: ireturn
/*    */     //   488: aload_1
/*    */     //   489: invokevirtual Cz0 : ()Z
/*    */     //   492: ifeq -> 598
/*    */     //   495: aload_1
/*    */     //   496: invokevirtual Ud : ()Z
/*    */     //   499: ifeq -> 527
/*    */     //   502: aload_0
/*    */     //   503: getfield ku0 : Z
/*    */     //   506: ifeq -> 527
/*    */     //   509: aload_0
/*    */     //   510: aload_1
/*    */     //   511: dup
/*    */     //   512: getfield aK : I
/*    */     //   515: istore_0
/*    */     //   516: getfield gk0 : I
/*    */     //   519: iload_0
/*    */     //   520: swap
/*    */     //   521: invokevirtual cE0 : (II)V
/*    */     //   524: goto -> 596
/*    */     //   527: aload_1
/*    */     //   528: getfield Ua : Z
/*    */     //   531: ifeq -> 596
/*    */     //   534: aload_0
/*    */     //   535: getfield ku0 : Z
/*    */     //   538: ifeq -> 559
/*    */     //   541: aload_0
/*    */     //   542: aload_1
/*    */     //   543: dup
/*    */     //   544: getfield aK : I
/*    */     //   547: istore_0
/*    */     //   548: getfield gk0 : I
/*    */     //   551: iload_0
/*    */     //   552: swap
/*    */     //   553: invokevirtual dI0 : (II)V
/*    */     //   556: goto -> 596
/*    */     //   559: aload_0
/*    */     //   560: instanceof f/jw0
/*    */     //   563: ifne -> 596
/*    */     //   566: aload_0
/*    */     //   567: dup
/*    */     //   568: dup2
/*    */     //   569: aload_1
/*    */     //   570: dup
/*    */     //   571: getfield aK : I
/*    */     //   574: istore_0
/*    */     //   575: getfield gk0 : I
/*    */     //   578: istore_1
/*    */     //   579: iconst_1
/*    */     //   580: putfield ku0 : Z
/*    */     //   583: iload_0
/*    */     //   584: putfield Mn0 : I
/*    */     //   587: iload_1
/*    */     //   588: putfield rA : I
/*    */     //   591: iload_0
/*    */     //   592: iload_1
/*    */     //   593: invokevirtual dI0 : (II)V
/*    */     //   596: iconst_1
/*    */     //   597: ireturn
/*    */     //   598: aload_0
/*    */     //   599: aload_1
/*    */     //   600: invokespecial i2 : (Lf/oa0;)Z
/*    */     //   603: ireturn
/*    */     // Line number table:
/*    */     //   Java source line number -> byte code offset
/*    */     //   #1	-> 1
/*    */     //   #2	-> 4
/*    */     //   #3	-> 11
/*    */     //   #4	-> 18
/*    */     //   #5	-> 21
/*    */     //   #6	-> 31
/*    */     //   #7	-> 34
/*    */     //   #8	-> 41
/*    */     //   #9	-> 72
/*    */     //   #10	-> 76
/*    */     //   #11	-> 79
/*    */     //   #12	-> 80
/*    */     //   #13	-> 83
/*    */     //   #14	-> 93
/*    */     //   #15	-> 96
/*    */     //   #16	-> 116
/*    */     //   #17	-> 127
/*    */     //   #18	-> 134
/*    */     //   #19	-> 141
/*    */     //   #20	-> 149
/*    */     //   #21	-> 153
/*    */     //   #22	-> 165
/*    */     //   #23	-> 184
/*    */     //   #24	-> 194
/*    */     //   #25	-> 205
/*    */     //   #26	-> 208
/*    */     //   #27	-> 239
/*    */     //   #28	-> 248
/*    */     //   #29	-> 251
/*    */     //   #30	-> 307
/*    */     //   #31	-> 313
/*    */     //   #32	-> 317
/*    */     //   #33	-> 330
/*    */     //   #34	-> 335
/*    */     //   #35	-> 348
/*    */     //   #36	-> 358
/*    */     //   #37	-> 362
/*    */     //   #38	-> 365
/*    */     //   #39	-> 401
/*    */     //   #40	-> 405
/*    */     //   #41	-> 409
/*    */     //   #42	-> 412
/*    */     //   #43	-> 415
/*    */     //   #44	-> 423
/*    */     //   #45	-> 429
/*    */     //   #46	-> 432
/*    */     //   #47	-> 473
/*    */     //   #48	-> 476
/*    */     //   #49	-> 483
/*    */     //   #50	-> 489
/*    */     //   #51	-> 512
/*    */     //   #52	-> 516
/*    */     //   #53	-> 521
/*    */     //   #54	-> 528
/*    */     //   #55	-> 535
/*    */     //   #56	-> 544
/*    */     //   #57	-> 548
/*    */     //   #58	-> 553
/*    */     //   #59	-> 571
/*    */     //   #60	-> 575
/*    */     //   #61	-> 580
/*    */     //   #62	-> 600
/*    */   }
/*    */   
/*    */   public Zq[] MY() {
/*    */     return this.f9;
/*    */   }
/*    */   
/*    */   public final void zn0(boolean paramBoolean) {
/*    */     Zq zq = M50();
/*    */     if (!this.dy && paramBoolean) {
/*    */       int i = zq.Kd;
/*    */       int j = zq.er0;
/*    */       this.ku0 = true;
/*    */       this.Mn0 = i;
/*    */       this.rA = j;
/*    */       dI0(i, j);
/*    */     } 
/*    */     if (this.dy && !paramBoolean) {
/*    */       int i = zq.Kd;
/*    */       cE0(i, zq.er0);
/*    */     } 
/*    */     this.dy = paramBoolean;
/*    */     if (zq.p3())
/*    */       zq.O.gf0(Qv0.Co, paramBoolean); 
/*    */   }
/*    */   
/*    */   public final Zq M50() {
/*    */     return MY()[this.Gg0];
/*    */   }
/*    */   
/*    */   public int Gz0() {
/*    */     return 10;
/*    */   }
/*    */   
/*    */   public void a5() {
/*    */     this.f9 = new Zq[60];
/*    */     this(this);
/*    */     hq hq;
/*    */     cr0 cr0;
/*    */     g0 g0;
/*    */     this(this);
/*    */     this(this);
/*    */     Qv0[] arrayOfQv0;
/*    */     int i;
/*    */     short s;
/*    */     for (arrayOfQv0 = new Qv0[10], i = 0, s = 0; s < this.f9.length; ) {
/*    */       Uc0 uc0 = km.u4.s40(aq0.XJ0);
/*    */       this(this.n90, this, uc0, (short)(this.Zb * 60 + s));
/*    */       this.f9[s] = zq;
/*    */       zq.dw0 = hq;
/*    */       Zq zq;
/*    */       (zq = new Zq()).n0 = (() -> H0(paramShort));
/*    */       arrayOfQv0[i] = zq;
/*    */       int j;
/*    */       if ((j = i + 1) % 10 == 0) {
/*    */         i = 0;
/*    */         cr0.ee0((new g0(this)).Mg((JG0[])arrayOfQv0));
/*    */         g0.ee0((new cr0(this)).Mg((JG0[])arrayOfQv0));
/*    */       } else {
/*    */         i = j;
/*    */       } 
/*    */       s = (short)(s + 1);
/*    */     } 
/*    */     rK0((new cr0(this)).cOM8(new U90[] { g0 }));
/*    */     WN((new g0(this)).cOM8(new U90[] { cr0 }));
/*    */   } }


/* Location:              /Users/vnnsnnt/Documents/Codespace/JavaWorkspace/RedTrainer/src/main/java/org/trainer/client/PokeMMO.jar!/f/n3.class
 * Java compiler version: 8 (52.0)
 * JD-Core Version:       1.1.3
 */