/*  1 */ package f;public final class nP implements Hm { public static final byte[] wE0 = new byte[] { 0, 1, 1, 1, 2, 1, 3, 1, 4, 1, 5, 1, 6, 1, 7, 1, 8, 2, 0, 7, 2, 0, 8, 2, 1, 3, 2, 1, 5 }; public nP() { fQ fQ1; this(8); this.WP = this; this(8); this.dd = this; } public static byte[] nu0() { return new byte[] { 1, 1, 2, 3, 4, 3, 5, 3, 6, 1, 0, 7, 7, 3, 8, 3, 9, 9, 3, 11, 11, 12, 13, 14, 3, 15, 11, 10, 16, 16, 17, 18, 16, 3, 19, 19, 20, 21, 19, 3, 22, 22, 3, 21, 21, 24, 3, 25, 3, 26, 3, 27, 21, 23, 28, 29, 29, 28, 30, 31, 32, 3, 33, 34, 34, 33, 13, 35, 15, 3, 34, 34, 12, 36, 37, 3, 15, 34, 10, 16, 3, 36, 36, 12, 3, 38, 3, 3, 36, 10, 39, 39, 3, 40, 40, 3, 13, 13, 12, 3, 41, 3, 15, 13, 10, 42, 42, 3, 43, 43, 3, 28, 3, 44, 44, 3, 45, 45, 3, 47, 47, 48, 49, 50, 3, 51, 52, 53, 47, 46, 54, 55, 55, 54, 56, 57, 58, 3, 59, 60, 60, 59, 49, 61, 52, 3, 60, 60, 48, 62, 63, 3, 51, 52, 53, 60, 46, 54, 3, 62, 62, 48, 3, 64, 3, 51, 3, 53, 62, 46, 65, 65, 3, 66, 66, 3, 49, 49, 48, 3, 67, 3, 51, 52, 53, 49, 46, 68, 68, 3, 69, 69, 3, 70, 70, 3, 8, 8, 71, 8, 3, 72, 72, 73, 72, 3, 3, 3, 0 }; } public static byte[] BH() { return new byte[] { 13, 0, 15, 0, 0, 7, 3, 11, 1, 11, 17, 0, 20, 0, 0, 5, 1, 1, 1, 0, 0, 0, 11, 13, 15, 0, 7, 3, 1, 1, 1, 1, 23, 0, 0, 0, 0, 0, 0, 11, 11, 0, 11, 11, 11, 11, 13, 0, 15, 0, 0, 7, 9, 3, 1, 1, 1, 1, 26, 0, 0, 0, 0, 0, 0, 11, 11, 0, 11, 11, 11, 1, 0, 0 }; } public static String Du(String paramString) { int i = paramString.length(); this(i + 16); Ag ag; for (int j = 0; j < i; ) { char[] arrayOfChar; byte b; int k = j + 1; if ((j = paramString.charAt(j)) != '\\') { ag.yd0(j); j = k; continue; }  if (k == i) break;  j = k + 1;
/*  2 */       if ((k = paramString.charAt(k)) == 117) { arrayOfChar = Character.toChars(Integer.parseInt(paramString.substring(j, j += 4), 16)); int m;
/*  3 */         if ((m = ag.Td0 + arrayOfChar.length) > ag.bF0.length) ag.LpT8(m);  arrayOfChar = ag.bF0; int n = ag.Td0, i1 = arrayOfChar.length; System.arraycopy(arrayOfChar, 0, arrayOfChar, n, i1); ag.Td0 = m; continue; }  if (arrayOfChar != 34 && arrayOfChar != 47 && arrayOfChar != 92) if (arrayOfChar != 98) { if (arrayOfChar != 102) { if (arrayOfChar != 110) { if (arrayOfChar != 114) { if (arrayOfChar == 116) { b = 9; }
/*  4 */                 else { throw new kN("Illegal escaped character: \\" + b); }  } else { b = 13; }  } else { b = 10; }  } else { b = 12; }  } else { b = 8; }   ag
/*  5 */         .yd0(b); }
/*  6 */      return ag.toString(); }
/*    */   public final bM0 lu(InputStreamReader paramInputStreamReader) { char[] arrayOfChar = new char[1024]; int i = 0; try { while (true) { int j; if ((j = paramInputStreamReader.read(arrayOfChar, i, arrayOfChar.length - i)) == -1) { Ui.JC0(paramInputStreamReader); return Tg(arrayOfChar, i); }  if (j == 0) { arrayOfChar = new char[arrayOfChar.length * 2]; j = 0; boolean bool = false; int k = arrayOfChar.length; System.arraycopy(arrayOfChar, j, arrayOfChar, bool, k); continue; }  i += j; }  } catch (IOException iOException) { throw new kN("Error reading input.", this); } finally {} Ui.JC0(paramInputStreamReader); throw this; } public final bM0 PL0(RD0 paramRD0) { try { String str = "UTF-8"; InputStream inputStream = paramRD0.Yc(); try { try { return lu(new InputStreamReader(inputStream, this)); } catch (Exception exception) { throw new kN("Error parsing file: " + paramRD0, this); }  } catch (UnsupportedEncodingException unsupportedEncodingException) { Ui.JC0(inputStream); throw new JU("Error reading file: " + paramRD0, this); }  } catch (Exception exception) { throw new kN("Error reading file: " + paramRD0, this); }  } public final bM0 Tg(char[] paramArrayOfchar, int paramInt) { // Byte code:
/*    */     //   0: iconst_0
/*    */     //   1: istore_3
/*    */     //   2: iconst_4
/*    */     //   3: newarray int
/*    */     //   5: astore #4
/*    */     //   7: iconst_0
/*    */     //   8: istore #5
/*    */     //   10: new f/fQ
/*    */     //   13: dup
/*    */     //   14: astore #6
/*    */     //   16: bipush #8
/*    */     //   18: invokespecial <init> : (I)V
/*    */     //   21: iconst_0
/*    */     //   22: istore #7
/*    */     //   24: iconst_0
/*    */     //   25: istore #8
/*    */     //   27: iconst_0
/*    */     //   28: istore #9
/*    */     //   30: aconst_null
/*    */     //   31: astore #10
/*    */     //   33: iconst_1
/*    */     //   34: istore #11
/*    */     //   36: iconst_0
/*    */     //   37: istore #12
/*    */     //   39: iconst_0
/*    */     //   40: istore #13
/*    */     //   42: iload #13
/*    */     //   44: ifeq -> 68
/*    */     //   47: iload #13
/*    */     //   49: iconst_1
/*    */     //   50: if_icmpeq -> 87
/*    */     //   53: iload #13
/*    */     //   55: iconst_2
/*    */     //   56: if_icmpeq -> 1691
/*    */     //   59: iload #13
/*    */     //   61: iconst_4
/*    */     //   62: if_icmpeq -> 1717
/*    */     //   65: goto -> 2191
/*    */     //   68: iload_3
/*    */     //   69: iload_2
/*    */     //   70: if_icmpne -> 79
/*    */     //   73: iconst_4
/*    */     //   74: istore #13
/*    */     //   76: goto -> 42
/*    */     //   79: iload #11
/*    */     //   81: ifne -> 87
/*    */     //   84: goto -> 1696
/*    */     //   87: getstatic f/nP.kr : [S
/*    */     //   90: iload #11
/*    */     //   92: saload
/*    */     //   93: istore #13
/*    */     //   95: getstatic f/nP.P30 : [S
/*    */     //   98: iload #11
/*    */     //   100: saload
/*    */     //   101: istore #14
/*    */     //   103: getstatic f/nP.vc0 : [B
/*    */     //   106: iload #11
/*    */     //   108: baload
/*    */     //   109: dup
/*    */     //   110: istore #15
/*    */     //   112: ifle -> 224
/*    */     //   115: iload #13
/*    */     //   117: iload #15
/*    */     //   119: iadd
/*    */     //   120: dup
/*    */     //   121: istore #16
/*    */     //   123: iconst_1
/*    */     //   124: isub
/*    */     //   125: istore #17
/*    */     //   127: iload #13
/*    */     //   129: istore #18
/*    */     //   131: iload #17
/*    */     //   133: iload #18
/*    */     //   135: if_icmpge -> 156
/*    */     //   138: iload #14
/*    */     //   140: iload #15
/*    */     //   142: iadd
/*    */     //   143: istore #14
/*    */     //   145: iload #14
/*    */     //   147: iload #16
/*    */     //   149: istore #14
/*    */     //   151: istore #13
/*    */     //   153: goto -> 232
/*    */     //   156: aload_1
/*    */     //   157: iload_3
/*    */     //   158: iload #18
/*    */     //   160: iload #17
/*    */     //   162: iload #18
/*    */     //   164: isub
/*    */     //   165: iconst_1
/*    */     //   166: ishr
/*    */     //   167: iadd
/*    */     //   168: istore #19
/*    */     //   170: caload
/*    */     //   171: dup
/*    */     //   172: istore #20
/*    */     //   174: getstatic f/nP.GX : [C
/*    */     //   177: iload #19
/*    */     //   179: caload
/*    */     //   180: dup
/*    */     //   181: istore #21
/*    */     //   183: if_icmpge -> 195
/*    */     //   186: iload #19
/*    */     //   188: iconst_1
/*    */     //   189: isub
/*    */     //   190: istore #17
/*    */     //   192: goto -> 131
/*    */     //   195: iload #20
/*    */     //   197: iload #21
/*    */     //   199: if_icmple -> 211
/*    */     //   202: iload #19
/*    */     //   204: iconst_1
/*    */     //   205: iadd
/*    */     //   206: istore #18
/*    */     //   208: goto -> 131
/*    */     //   211: iload #19
/*    */     //   213: iload #13
/*    */     //   215: isub
/*    */     //   216: iload #14
/*    */     //   218: iadd
/*    */     //   219: istore #11
/*    */     //   221: goto -> 358
/*    */     //   224: iload #14
/*    */     //   226: iload #13
/*    */     //   228: istore #14
/*    */     //   230: istore #13
/*    */     //   232: getstatic f/nP.cZ : [B
/*    */     //   235: iload #11
/*    */     //   237: baload
/*    */     //   238: dup
/*    */     //   239: istore #11
/*    */     //   241: ifle -> 354
/*    */     //   244: iload #14
/*    */     //   246: iload #11
/*    */     //   248: iconst_1
/*    */     //   249: ishl
/*    */     //   250: iadd
/*    */     //   251: iconst_2
/*    */     //   252: isub
/*    */     //   253: istore #15
/*    */     //   255: iload #14
/*    */     //   257: istore #16
/*    */     //   259: iload #15
/*    */     //   261: iload #16
/*    */     //   263: if_icmpge -> 276
/*    */     //   266: iload #13
/*    */     //   268: iload #11
/*    */     //   270: iadd
/*    */     //   271: istore #11
/*    */     //   273: goto -> 358
/*    */     //   276: aload_1
/*    */     //   277: iload_3
/*    */     //   278: iload #16
/*    */     //   280: iload #15
/*    */     //   282: iload #16
/*    */     //   284: isub
/*    */     //   285: iconst_1
/*    */     //   286: ishr
/*    */     //   287: bipush #-2
/*    */     //   289: iand
/*    */     //   290: iadd
/*    */     //   291: istore #17
/*    */     //   293: caload
/*    */     //   294: dup
/*    */     //   295: istore #18
/*    */     //   297: getstatic f/nP.GX : [C
/*    */     //   300: dup
/*    */     //   301: astore #19
/*    */     //   303: iload #17
/*    */     //   305: caload
/*    */     //   306: if_icmpge -> 318
/*    */     //   309: iload #17
/*    */     //   311: iconst_2
/*    */     //   312: isub
/*    */     //   313: istore #15
/*    */     //   315: goto -> 259
/*    */     //   318: iload #18
/*    */     //   320: aload #19
/*    */     //   322: iload #17
/*    */     //   324: iconst_1
/*    */     //   325: iadd
/*    */     //   326: caload
/*    */     //   327: if_icmple -> 339
/*    */     //   330: iload #17
/*    */     //   332: iconst_2
/*    */     //   333: iadd
/*    */     //   334: istore #16
/*    */     //   336: goto -> 259
/*    */     //   339: iload #13
/*    */     //   341: iload #17
/*    */     //   343: iload #14
/*    */     //   345: isub
/*    */     //   346: iconst_1
/*    */     //   347: ishr
/*    */     //   348: iadd
/*    */     //   349: istore #11
/*    */     //   351: goto -> 358
/*    */     //   354: iload #13
/*    */     //   356: istore #11
/*    */     //   358: getstatic f/nP.Ev0 : [B
/*    */     //   361: iload #11
/*    */     //   363: baload
/*    */     //   364: istore #11
/*    */     //   366: getstatic f/nP.Kf0 : [B
/*    */     //   369: iload #11
/*    */     //   371: baload
/*    */     //   372: istore #13
/*    */     //   374: getstatic f/nP.DW : [B
/*    */     //   377: iload #11
/*    */     //   379: baload
/*    */     //   380: dup
/*    */     //   381: istore #11
/*    */     //   383: ifeq -> 1687
/*    */     //   386: getstatic f/nP.wE0 : [B
/*    */     //   389: iload #11
/*    */     //   391: dup
/*    */     //   392: iconst_1
/*    */     //   393: iadd
/*    */     //   394: istore #11
/*    */     //   396: baload
/*    */     //   397: istore #14
/*    */     //   399: iload #14
/*    */     //   401: dup
/*    */     //   402: iconst_m1
/*    */     //   403: iadd
/*    */     //   404: istore #14
/*    */     //   406: ifle -> 1687
/*    */     //   409: getstatic f/nP.wE0 : [B
/*    */     //   412: iload #11
/*    */     //   414: dup
/*    */     //   415: iconst_1
/*    */     //   416: iadd
/*    */     //   417: istore #11
/*    */     //   419: baload
/*    */     //   420: tableswitch default -> 472, 0 -> 1681, 1 -> 1266, 2 -> 1167, 3 -> 1074, 4 -> 974, 5 -> 894, 6 -> 818, 7 -> 547, 8 -> 475
/*    */     //   472: goto -> 399
/*    */     //   475: iinc #3, 1
/*    */     //   478: iconst_0
/*    */     //   479: istore #5
/*    */     //   481: iload_3
/*    */     //   482: iload #5
/*    */     //   484: istore #7
/*    */     //   486: istore #5
/*    */     //   488: aload_1
/*    */     //   489: iload #5
/*    */     //   491: caload
/*    */     //   492: dup
/*    */     //   493: istore #15
/*    */     //   495: bipush #34
/*    */     //   497: if_icmpeq -> 527
/*    */     //   500: iload #15
/*    */     //   502: bipush #92
/*    */     //   504: if_icmpeq -> 510
/*    */     //   507: goto -> 516
/*    */     //   510: iconst_1
/*    */     //   511: istore #7
/*    */     //   513: iinc #5, 1
/*    */     //   516: iload #5
/*    */     //   518: iconst_1
/*    */     //   519: iadd
/*    */     //   520: dup
/*    */     //   521: istore #5
/*    */     //   523: iload_2
/*    */     //   524: if_icmpne -> 488
/*    */     //   527: iinc #5, -1
/*    */     //   530: iload #5
/*    */     //   532: iload_3
/*    */     //   533: istore #5
/*    */     //   535: istore_3
/*    */     //   536: goto -> 399
/*    */     //   539: astore #10
/*    */     //   541: iload #5
/*    */     //   543: istore_3
/*    */     //   544: goto -> 2191
/*    */     //   547: iload #8
/*    */     //   549: iconst_0
/*    */     //   550: istore #5
/*    */     //   552: iconst_1
/*    */     //   553: istore #7
/*    */     //   555: ifeq -> 660
/*    */     //   558: iload_3
/*    */     //   559: istore #9
/*    */     //   561: aload_1
/*    */     //   562: iload #9
/*    */     //   564: caload
/*    */     //   565: dup
/*    */     //   566: istore #15
/*    */     //   568: bipush #10
/*    */     //   570: if_icmpeq -> 773
/*    */     //   573: iload #15
/*    */     //   575: bipush #13
/*    */     //   577: if_icmpeq -> 773
/*    */     //   580: iload #15
/*    */     //   582: bipush #47
/*    */     //   584: if_icmpeq -> 610
/*    */     //   587: iload #15
/*    */     //   589: bipush #58
/*    */     //   591: if_icmpeq -> 773
/*    */     //   594: iload #15
/*    */     //   596: bipush #92
/*    */     //   598: if_icmpeq -> 604
/*    */     //   601: goto -> 646
/*    */     //   604: iconst_1
/*    */     //   605: istore #5
/*    */     //   607: goto -> 646
/*    */     //   610: iload #9
/*    */     //   612: iconst_1
/*    */     //   613: iadd
/*    */     //   614: dup
/*    */     //   615: istore #15
/*    */     //   617: iload_2
/*    */     //   618: if_icmpne -> 624
/*    */     //   621: goto -> 646
/*    */     //   624: aload_1
/*    */     //   625: iload #15
/*    */     //   627: caload
/*    */     //   628: dup
/*    */     //   629: istore #15
/*    */     //   631: bipush #47
/*    */     //   633: if_icmpeq -> 773
/*    */     //   636: iload #15
/*    */     //   638: bipush #42
/*    */     //   640: if_icmpne -> 646
/*    */     //   643: goto -> 773
/*    */     //   646: iload #9
/*    */     //   648: iconst_1
/*    */     //   649: iadd
/*    */     //   650: dup
/*    */     //   651: istore #9
/*    */     //   653: iload_2
/*    */     //   654: if_icmpne -> 561
/*    */     //   657: goto -> 773
/*    */     //   660: iload_3
/*    */     //   661: istore #9
/*    */     //   663: aload_1
/*    */     //   664: iload #9
/*    */     //   666: caload
/*    */     //   667: dup
/*    */     //   668: istore #15
/*    */     //   670: bipush #10
/*    */     //   672: if_icmpeq -> 773
/*    */     //   675: iload #15
/*    */     //   677: bipush #13
/*    */     //   679: if_icmpeq -> 773
/*    */     //   682: iload #15
/*    */     //   684: bipush #44
/*    */     //   686: if_icmpeq -> 773
/*    */     //   689: iload #15
/*    */     //   691: bipush #47
/*    */     //   693: if_icmpeq -> 726
/*    */     //   696: iload #15
/*    */     //   698: bipush #125
/*    */     //   700: if_icmpeq -> 773
/*    */     //   703: iload #15
/*    */     //   705: bipush #92
/*    */     //   707: if_icmpeq -> 720
/*    */     //   710: iload #15
/*    */     //   712: bipush #93
/*    */     //   714: if_icmpeq -> 773
/*    */     //   717: goto -> 762
/*    */     //   720: iconst_1
/*    */     //   721: istore #5
/*    */     //   723: goto -> 762
/*    */     //   726: iload #9
/*    */     //   728: iconst_1
/*    */     //   729: iadd
/*    */     //   730: dup
/*    */     //   731: istore #15
/*    */     //   733: iload_2
/*    */     //   734: if_icmpne -> 740
/*    */     //   737: goto -> 762
/*    */     //   740: aload_1
/*    */     //   741: iload #15
/*    */     //   743: caload
/*    */     //   744: dup
/*    */     //   745: istore #15
/*    */     //   747: bipush #47
/*    */     //   749: if_icmpeq -> 773
/*    */     //   752: iload #15
/*    */     //   754: bipush #42
/*    */     //   756: if_icmpne -> 762
/*    */     //   759: goto -> 773
/*    */     //   762: iload #9
/*    */     //   764: iconst_1
/*    */     //   765: iadd
/*    */     //   766: dup
/*    */     //   767: istore #9
/*    */     //   769: iload_2
/*    */     //   770: if_icmpne -> 663
/*    */     //   773: aload_1
/*    */     //   774: iload #9
/*    */     //   776: iconst_m1
/*    */     //   777: iadd
/*    */     //   778: dup
/*    */     //   779: istore #9
/*    */     //   781: caload
/*    */     //   782: invokestatic isSpace : (C)Z
/*    */     //   785: ifeq -> 791
/*    */     //   788: goto -> 773
/*    */     //   791: iload #9
/*    */     //   793: iload_3
/*    */     //   794: iload #5
/*    */     //   796: iload #7
/*    */     //   798: istore #9
/*    */     //   800: istore #7
/*    */     //   802: istore #5
/*    */     //   804: istore_3
/*    */     //   805: goto -> 399
/*    */     //   808: astore_3
/*    */     //   809: aload_3
/*    */     //   810: iload #9
/*    */     //   812: istore_3
/*    */     //   813: astore #10
/*    */     //   815: goto -> 2191
/*    */     //   818: aload_1
/*    */     //   819: iload_3
/*    */     //   820: dup
/*    */     //   821: iconst_1
/*    */     //   822: iadd
/*    */     //   823: istore_3
/*    */     //   824: caload
/*    */     //   825: bipush #47
/*    */     //   827: if_icmpne -> 855
/*    */     //   830: iload_3
/*    */     //   831: iload_2
/*    */     //   832: if_icmpeq -> 849
/*    */     //   835: aload_1
/*    */     //   836: iload_3
/*    */     //   837: caload
/*    */     //   838: bipush #10
/*    */     //   840: if_icmpeq -> 849
/*    */     //   843: iinc #3, 1
/*    */     //   846: goto -> 830
/*    */     //   849: iinc #3, -1
/*    */     //   852: goto -> 399
/*    */     //   855: iload_3
/*    */     //   856: iconst_1
/*    */     //   857: iadd
/*    */     //   858: dup
/*    */     //   859: istore #15
/*    */     //   861: iload_2
/*    */     //   862: if_icmpge -> 873
/*    */     //   865: aload_1
/*    */     //   866: iload_3
/*    */     //   867: caload
/*    */     //   868: bipush #42
/*    */     //   870: if_icmpne -> 882
/*    */     //   873: aload_1
/*    */     //   874: iload #15
/*    */     //   876: caload
/*    */     //   877: bipush #47
/*    */     //   879: if_icmpeq -> 888
/*    */     //   882: iload #15
/*    */     //   884: istore_3
/*    */     //   885: goto -> 855
/*    */     //   888: iload #15
/*    */     //   890: istore_3
/*    */     //   891: goto -> 399
/*    */     //   894: aload_0
/*    */     //   895: dup
/*    */     //   896: dup
/*    */     //   897: getfield WP : Lf/fQ;
/*    */     //   900: invokevirtual pop : ()Ljava/lang/Object;
/*    */     //   903: checkcast f/bM0
/*    */     //   906: putfield uw0 : Lf/bM0;
/*    */     //   909: getfield Mb0 : Lf/bM0;
/*    */     //   912: getfield LG : I
/*    */     //   915: ifle -> 926
/*    */     //   918: aload_0
/*    */     //   919: getfield dd : Lf/fQ;
/*    */     //   922: invokevirtual pop : ()Ljava/lang/Object;
/*    */     //   925: pop
/*    */     //   926: aload_0
/*    */     //   927: getfield WP : Lf/fQ;
/*    */     //   930: dup
/*    */     //   931: astore #11
/*    */     //   933: getfield Z8 : I
/*    */     //   936: ifle -> 952
/*    */     //   939: aload #11
/*    */     //   941: invokevirtual peek : ()Ljava/lang/Object;
/*    */     //   944: checkcast f/bM0
/*    */     //   947: astore #11
/*    */     //   949: goto -> 955
/*    */     //   952: aconst_null
/*    */     //   953: astore #11
/*    */     //   955: aload #4
/*    */     //   957: aload_0
/*    */     //   958: aload #11
/*    */     //   960: putfield Mb0 : Lf/bM0;
/*    */     //   963: iload #12
/*    */     //   965: iconst_m1
/*    */     //   966: iadd
/*    */     //   967: dup
/*    */     //   968: istore #11
/*    */     //   970: iaload
/*    */     //   971: goto -> 1151
/*    */     //   974: aload #6
/*    */     //   976: getfield Z8 : I
/*    */     //   979: ifle -> 995
/*    */     //   982: aload #6
/*    */     //   984: invokevirtual pop : ()Ljava/lang/Object;
/*    */     //   987: checkcast java/lang/String
/*    */     //   990: astore #11
/*    */     //   992: goto -> 998
/*    */     //   995: aconst_null
/*    */     //   996: astore #11
/*    */     //   998: iload #12
/*    */     //   1000: aload #4
/*    */     //   1002: aload_0
/*    */     //   1003: aload #11
/*    */     //   1005: invokevirtual To0 : (Ljava/lang/String;)V
/*    */     //   1008: arraylength
/*    */     //   1009: if_icmpne -> 1043
/*    */     //   1012: aload #4
/*    */     //   1014: dup
/*    */     //   1015: dup
/*    */     //   1016: arraylength
/*    */     //   1017: iconst_2
/*    */     //   1018: imul
/*    */     //   1019: newarray int
/*    */     //   1021: astore #4
/*    */     //   1023: iconst_0
/*    */     //   1024: istore #11
/*    */     //   1026: iconst_0
/*    */     //   1027: istore #14
/*    */     //   1029: arraylength
/*    */     //   1030: istore #15
/*    */     //   1032: iload #11
/*    */     //   1034: aload #4
/*    */     //   1036: iload #14
/*    */     //   1038: iload #15
/*    */     //   1040: invokestatic arraycopy : (Ljava/lang/Object;ILjava/lang/Object;II)V
/*    */     //   1043: aload #4
/*    */     //   1045: iload #12
/*    */     //   1047: iconst_1
/*    */     //   1048: iadd
/*    */     //   1049: istore #11
/*    */     //   1051: iload #12
/*    */     //   1053: iload #13
/*    */     //   1055: iastore
/*    */     //   1056: bipush #23
/*    */     //   1058: istore #12
/*    */     //   1060: iconst_2
/*    */     //   1061: istore #13
/*    */     //   1063: iload #12
/*    */     //   1065: iload #11
/*    */     //   1067: istore #12
/*    */     //   1069: istore #11
/*    */     //   1071: goto -> 42
/*    */     //   1074: aload_0
/*    */     //   1075: dup
/*    */     //   1076: dup
/*    */     //   1077: getfield WP : Lf/fQ;
/*    */     //   1080: invokevirtual pop : ()Ljava/lang/Object;
/*    */     //   1083: checkcast f/bM0
/*    */     //   1086: putfield uw0 : Lf/bM0;
/*    */     //   1089: getfield Mb0 : Lf/bM0;
/*    */     //   1092: getfield LG : I
/*    */     //   1095: ifle -> 1106
/*    */     //   1098: aload_0
/*    */     //   1099: getfield dd : Lf/fQ;
/*    */     //   1102: invokevirtual pop : ()Ljava/lang/Object;
/*    */     //   1105: pop
/*    */     //   1106: aload_0
/*    */     //   1107: getfield WP : Lf/fQ;
/*    */     //   1110: dup
/*    */     //   1111: astore #11
/*    */     //   1113: getfield Z8 : I
/*    */     //   1116: ifle -> 1132
/*    */     //   1119: aload #11
/*    */     //   1121: invokevirtual peek : ()Ljava/lang/Object;
/*    */     //   1124: checkcast f/bM0
/*    */     //   1127: astore #11
/*    */     //   1129: goto -> 1135
/*    */     //   1132: aconst_null
/*    */     //   1133: astore #11
/*    */     //   1135: aload #4
/*    */     //   1137: aload_0
/*    */     //   1138: aload #11
/*    */     //   1140: putfield Mb0 : Lf/bM0;
/*    */     //   1143: iload #12
/*    */     //   1145: iconst_m1
/*    */     //   1146: iadd
/*    */     //   1147: dup
/*    */     //   1148: istore #11
/*    */     //   1150: iaload
/*    */     //   1151: istore #12
/*    */     //   1153: iload #12
/*    */     //   1155: iload #11
/*    */     //   1157: istore #12
/*    */     //   1159: istore #11
/*    */     //   1161: iconst_2
/*    */     //   1162: istore #13
/*    */     //   1164: goto -> 42
/*    */     //   1167: aload #6
/*    */     //   1169: getfield Z8 : I
/*    */     //   1172: ifle -> 1188
/*    */     //   1175: aload #6
/*    */     //   1177: invokevirtual pop : ()Ljava/lang/Object;
/*    */     //   1180: checkcast java/lang/String
/*    */     //   1183: astore #11
/*    */     //   1185: goto -> 1191
/*    */     //   1188: aconst_null
/*    */     //   1189: astore #11
/*    */     //   1191: iload #12
/*    */     //   1193: aload #4
/*    */     //   1195: aload_0
/*    */     //   1196: aload #11
/*    */     //   1198: invokevirtual F50 : (Ljava/lang/String;)V
/*    */     //   1201: arraylength
/*    */     //   1202: if_icmpne -> 1236
/*    */     //   1205: aload #4
/*    */     //   1207: dup
/*    */     //   1208: dup
/*    */     //   1209: arraylength
/*    */     //   1210: iconst_2
/*    */     //   1211: imul
/*    */     //   1212: newarray int
/*    */     //   1214: astore #4
/*    */     //   1216: iconst_0
/*    */     //   1217: istore #11
/*    */     //   1219: iconst_0
/*    */     //   1220: istore #14
/*    */     //   1222: arraylength
/*    */     //   1223: istore #15
/*    */     //   1225: iload #11
/*    */     //   1227: aload #4
/*    */     //   1229: iload #14
/*    */     //   1231: iload #15
/*    */     //   1233: invokestatic arraycopy : (Ljava/lang/Object;ILjava/lang/Object;II)V
/*    */     //   1236: aload #4
/*    */     //   1238: iload #12
/*    */     //   1240: iconst_1
/*    */     //   1241: iadd
/*    */     //   1242: istore #11
/*    */     //   1244: iload #12
/*    */     //   1246: iload #13
/*    */     //   1248: iastore
/*    */     //   1249: iconst_5
/*    */     //   1250: istore #12
/*    */     //   1252: iconst_2
/*    */     //   1253: istore #13
/*    */     //   1255: iload #12
/*    */     //   1257: iload #11
/*    */     //   1259: istore #12
/*    */     //   1261: istore #11
/*    */     //   1263: goto -> 42
/*    */     //   1266: iload #7
/*    */     //   1268: new java/lang/String
/*    */     //   1271: dup
/*    */     //   1272: astore #15
/*    */     //   1274: iload_3
/*    */     //   1275: iload #5
/*    */     //   1277: isub
/*    */     //   1278: istore #16
/*    */     //   1280: aload_1
/*    */     //   1281: iload #5
/*    */     //   1283: iload #16
/*    */     //   1285: invokespecial <init> : ([CII)V
/*    */     //   1288: ifeq -> 1298
/*    */     //   1291: aload #15
/*    */     //   1293: invokestatic Du : (Ljava/lang/String;)Ljava/lang/String;
/*    */     //   1296: astore #15
/*    */     //   1298: iload #8
/*    */     //   1300: ifeq -> 1316
/*    */     //   1303: aload #6
/*    */     //   1305: iconst_0
/*    */     //   1306: istore #8
/*    */     //   1308: aload #15
/*    */     //   1310: invokevirtual Com3 : (Ljava/lang/Object;)V
/*    */     //   1313: goto -> 1668
/*    */     //   1316: aload #6
/*    */     //   1318: getfield Z8 : I
/*    */     //   1321: ifle -> 1337
/*    */     //   1324: aload #6
/*    */     //   1326: invokevirtual pop : ()Ljava/lang/Object;
/*    */     //   1329: checkcast java/lang/String
/*    */     //   1332: astore #16
/*    */     //   1334: goto -> 1340
/*    */     //   1337: aconst_null
/*    */     //   1338: astore #16
/*    */     //   1340: iload #9
/*    */     //   1342: ifeq -> 1649
/*    */     //   1345: aload #15
/*    */     //   1347: ldc 'true'
/*    */     //   1349: invokevirtual equals : (Ljava/lang/Object;)Z
/*    */     //   1352: ifeq -> 1380
/*    */     //   1355: aload_0
/*    */     //   1356: iconst_1
/*    */     //   1357: istore #5
/*    */     //   1359: new f/bM0
/*    */     //   1362: dup
/*    */     //   1363: astore #9
/*    */     //   1365: iload #5
/*    */     //   1367: invokespecial <init> : (Z)V
/*    */     //   1370: aload #16
/*    */     //   1372: aload #9
/*    */     //   1374: invokevirtual p30 : (Ljava/lang/String;Lf/bM0;)V
/*    */     //   1377: goto -> 1668
/*    */     //   1380: aload #15
/*    */     //   1382: ldc_w 'false'
/*    */     //   1385: invokevirtual equals : (Ljava/lang/Object;)Z
/*    */     //   1388: ifeq -> 1409
/*    */     //   1391: aload_0
/*    */     //   1392: iconst_0
/*    */     //   1393: istore #5
/*    */     //   1395: new f/bM0
/*    */     //   1398: dup
/*    */     //   1399: astore #9
/*    */     //   1401: iload #5
/*    */     //   1403: invokespecial <init> : (Z)V
/*    */     //   1406: goto -> 1370
/*    */     //   1409: aload #15
/*    */     //   1411: ldc_w 'null'
/*    */     //   1414: invokevirtual equals : (Ljava/lang/Object;)Z
/*    */     //   1417: ifeq -> 1445
/*    */     //   1420: aload_0
/*    */     //   1421: aconst_null
/*    */     //   1422: astore #5
/*    */     //   1424: new f/bM0
/*    */     //   1427: dup
/*    */     //   1428: astore #9
/*    */     //   1430: aload #5
/*    */     //   1432: invokespecial <init> : (Ljava/lang/String;)V
/*    */     //   1435: aload #16
/*    */     //   1437: aload #9
/*    */     //   1439: invokevirtual p30 : (Ljava/lang/String;Lf/bM0;)V
/*    */     //   1442: goto -> 1668
/*    */     //   1445: iconst_0
/*    */     //   1446: istore #9
/*    */     //   1448: iconst_1
/*    */     //   1449: istore #17
/*    */     //   1451: iload #5
/*    */     //   1453: iload_3
/*    */     //   1454: if_icmpge -> 1573
/*    */     //   1457: aload_1
/*    */     //   1458: iload #5
/*    */     //   1460: caload
/*    */     //   1461: dup
/*    */     //   1462: istore #18
/*    */     //   1464: bipush #43
/*    */     //   1466: if_icmpeq -> 1567
/*    */     //   1469: iload #18
/*    */     //   1471: bipush #69
/*    */     //   1473: if_icmpeq -> 1561
/*    */     //   1476: iload #18
/*    */     //   1478: bipush #101
/*    */     //   1480: if_icmpeq -> 1561
/*    */     //   1483: iload #18
/*    */     //   1485: bipush #45
/*    */     //   1487: if_icmpeq -> 1567
/*    */     //   1490: iload #18
/*    */     //   1492: bipush #46
/*    */     //   1494: if_icmpeq -> 1561
/*    */     //   1497: iload #18
/*    */     //   1499: tableswitch default -> 1552, 48 -> 1567, 49 -> 1567, 50 -> 1567, 51 -> 1567, 52 -> 1567, 53 -> 1567, 54 -> 1567, 55 -> 1567, 56 -> 1567, 57 -> 1567
/*    */     //   1552: iconst_0
/*    */     //   1553: istore #9
/*    */     //   1555: iconst_0
/*    */     //   1556: istore #17
/*    */     //   1558: goto -> 1573
/*    */     //   1561: iconst_1
/*    */     //   1562: istore #9
/*    */     //   1564: iconst_0
/*    */     //   1565: istore #17
/*    */     //   1567: iinc #5, 1
/*    */     //   1570: goto -> 1451
/*    */     //   1573: iload #9
/*    */     //   1575: ifeq -> 1613
/*    */     //   1578: aload_0
/*    */     //   1579: aload #15
/*    */     //   1581: invokestatic parseDouble : (Ljava/lang/String;)D
/*    */     //   1584: dstore #17
/*    */     //   1586: new f/bM0
/*    */     //   1589: dup
/*    */     //   1590: astore #5
/*    */     //   1592: dload #17
/*    */     //   1594: aload #15
/*    */     //   1596: invokespecial <init> : (DLjava/lang/String;)V
/*    */     //   1599: aload #16
/*    */     //   1601: aload #5
/*    */     //   1603: invokevirtual p30 : (Ljava/lang/String;Lf/bM0;)V
/*    */     //   1606: goto -> 1668
/*    */     //   1609: pop
/*    */     //   1610: goto -> 1649
/*    */     //   1613: iload #17
/*    */     //   1615: ifeq -> 1649
/*    */     //   1618: aload_0
/*    */     //   1619: aload #15
/*    */     //   1621: invokestatic parseLong : (Ljava/lang/String;)J
/*    */     //   1624: lstore #17
/*    */     //   1626: new f/bM0
/*    */     //   1629: dup
/*    */     //   1630: astore #5
/*    */     //   1632: lload #17
/*    */     //   1634: aload #15
/*    */     //   1636: invokespecial <init> : (JLjava/lang/String;)V
/*    */     //   1639: aload #16
/*    */     //   1641: aload #5
/*    */     //   1643: invokevirtual p30 : (Ljava/lang/String;Lf/bM0;)V
/*    */     //   1646: goto -> 1668
/*    */     //   1649: aload_0
/*    */     //   1650: new f/bM0
/*    */     //   1653: dup
/*    */     //   1654: astore #5
/*    */     //   1656: aload #15
/*    */     //   1658: invokespecial <init> : (Ljava/lang/String;)V
/*    */     //   1661: aload #16
/*    */     //   1663: aload #5
/*    */     //   1665: invokevirtual p30 : (Ljava/lang/String;Lf/bM0;)V
/*    */     //   1668: iconst_0
/*    */     //   1669: istore #5
/*    */     //   1671: iload_3
/*    */     //   1672: iload #5
/*    */     //   1674: istore #9
/*    */     //   1676: istore #5
/*    */     //   1678: goto -> 399
/*    */     //   1681: iconst_1
/*    */     //   1682: istore #8
/*    */     //   1684: goto -> 399
/*    */     //   1687: iload #13
/*    */     //   1689: istore #11
/*    */     //   1691: iload #11
/*    */     //   1693: ifne -> 1702
/*    */     //   1696: iconst_5
/*    */     //   1697: istore #13
/*    */     //   1699: goto -> 42
/*    */     //   1702: iload_3
/*    */     //   1703: iconst_1
/*    */     //   1704: iadd
/*    */     //   1705: dup
/*    */     //   1706: istore_3
/*    */     //   1707: iload_2
/*    */     //   1708: if_icmpeq -> 1717
/*    */     //   1711: iconst_1
/*    */     //   1712: istore #13
/*    */     //   1714: goto -> 42
/*    */     //   1717: iload_3
/*    */     //   1718: iload_2
/*    */     //   1719: if_icmpne -> 2191
/*    */     //   1722: getstatic f/nP.LC0 : [B
/*    */     //   1725: iload #11
/*    */     //   1727: baload
/*    */     //   1728: getstatic f/nP.wE0 : [B
/*    */     //   1731: swap
/*    */     //   1732: dup
/*    */     //   1733: iconst_1
/*    */     //   1734: iadd
/*    */     //   1735: istore #4
/*    */     //   1737: baload
/*    */     //   1738: istore #11
/*    */     //   1740: iload #11
/*    */     //   1742: dup
/*    */     //   1743: iconst_m1
/*    */     //   1744: iadd
/*    */     //   1745: istore #11
/*    */     //   1747: ifle -> 2191
/*    */     //   1750: getstatic f/nP.wE0 : [B
/*    */     //   1753: iload #4
/*    */     //   1755: dup
/*    */     //   1756: iconst_1
/*    */     //   1757: iadd
/*    */     //   1758: istore #4
/*    */     //   1760: baload
/*    */     //   1761: iconst_1
/*    */     //   1762: if_icmpeq -> 1768
/*    */     //   1765: goto -> 1740
/*    */     //   1768: iload #7
/*    */     //   1770: new java/lang/String
/*    */     //   1773: dup
/*    */     //   1774: astore #12
/*    */     //   1776: iload_3
/*    */     //   1777: iload #5
/*    */     //   1779: isub
/*    */     //   1780: istore #13
/*    */     //   1782: aload_1
/*    */     //   1783: iload #5
/*    */     //   1785: iload #13
/*    */     //   1787: invokespecial <init> : ([CII)V
/*    */     //   1790: ifeq -> 1800
/*    */     //   1793: aload #12
/*    */     //   1795: invokestatic Du : (Ljava/lang/String;)Ljava/lang/String;
/*    */     //   1798: astore #12
/*    */     //   1800: iload #8
/*    */     //   1802: ifeq -> 1822
/*    */     //   1805: aload #6
/*    */     //   1807: iconst_0
/*    */     //   1808: istore #5
/*    */     //   1810: aload #12
/*    */     //   1812: invokevirtual Com3 : (Ljava/lang/Object;)V
/*    */     //   1815: iload #5
/*    */     //   1817: istore #8
/*    */     //   1819: goto -> 2176
/*    */     //   1822: aload #6
/*    */     //   1824: getfield Z8 : I
/*    */     //   1827: ifle -> 1843
/*    */     //   1830: aload #6
/*    */     //   1832: invokevirtual pop : ()Ljava/lang/Object;
/*    */     //   1835: checkcast java/lang/String
/*    */     //   1838: astore #13
/*    */     //   1840: goto -> 1846
/*    */     //   1843: aconst_null
/*    */     //   1844: astore #13
/*    */     //   1846: iload #9
/*    */     //   1848: ifeq -> 2157
/*    */     //   1851: aload #12
/*    */     //   1853: ldc 'true'
/*    */     //   1855: invokevirtual equals : (Ljava/lang/Object;)Z
/*    */     //   1858: ifeq -> 1886
/*    */     //   1861: aload_0
/*    */     //   1862: iconst_1
/*    */     //   1863: istore #5
/*    */     //   1865: new f/bM0
/*    */     //   1868: dup
/*    */     //   1869: astore #9
/*    */     //   1871: iload #5
/*    */     //   1873: invokespecial <init> : (Z)V
/*    */     //   1876: aload #13
/*    */     //   1878: aload #9
/*    */     //   1880: invokevirtual p30 : (Ljava/lang/String;Lf/bM0;)V
/*    */     //   1883: goto -> 2176
/*    */     //   1886: aload #12
/*    */     //   1888: ldc_w 'false'
/*    */     //   1891: invokevirtual equals : (Ljava/lang/Object;)Z
/*    */     //   1894: ifeq -> 1915
/*    */     //   1897: aload_0
/*    */     //   1898: iconst_0
/*    */     //   1899: istore #5
/*    */     //   1901: new f/bM0
/*    */     //   1904: dup
/*    */     //   1905: astore #9
/*    */     //   1907: iload #5
/*    */     //   1909: invokespecial <init> : (Z)V
/*    */     //   1912: goto -> 1876
/*    */     //   1915: aload #12
/*    */     //   1917: ldc_w 'null'
/*    */     //   1920: invokevirtual equals : (Ljava/lang/Object;)Z
/*    */     //   1923: ifeq -> 1951
/*    */     //   1926: aload_0
/*    */     //   1927: aconst_null
/*    */     //   1928: astore #5
/*    */     //   1930: new f/bM0
/*    */     //   1933: dup
/*    */     //   1934: astore #9
/*    */     //   1936: aload #5
/*    */     //   1938: invokespecial <init> : (Ljava/lang/String;)V
/*    */     //   1941: aload #13
/*    */     //   1943: aload #9
/*    */     //   1945: invokevirtual p30 : (Ljava/lang/String;Lf/bM0;)V
/*    */     //   1948: goto -> 2176
/*    */     //   1951: iconst_0
/*    */     //   1952: istore #9
/*    */     //   1954: iconst_1
/*    */     //   1955: istore #14
/*    */     //   1957: iload #5
/*    */     //   1959: iload_3
/*    */     //   1960: if_icmpge -> 2081
/*    */     //   1963: aload_1
/*    */     //   1964: iload #5
/*    */     //   1966: caload
/*    */     //   1967: dup
/*    */     //   1968: istore #15
/*    */     //   1970: bipush #43
/*    */     //   1972: if_icmpeq -> 2075
/*    */     //   1975: iload #15
/*    */     //   1977: bipush #69
/*    */     //   1979: if_icmpeq -> 2069
/*    */     //   1982: iload #15
/*    */     //   1984: bipush #101
/*    */     //   1986: if_icmpeq -> 2069
/*    */     //   1989: iload #15
/*    */     //   1991: bipush #45
/*    */     //   1993: if_icmpeq -> 2075
/*    */     //   1996: iload #15
/*    */     //   1998: bipush #46
/*    */     //   2000: if_icmpeq -> 2069
/*    */     //   2003: iload #15
/*    */     //   2005: tableswitch default -> 2060, 48 -> 2075, 49 -> 2075, 50 -> 2075, 51 -> 2075, 52 -> 2075, 53 -> 2075, 54 -> 2075, 55 -> 2075, 56 -> 2075, 57 -> 2075
/*    */     //   2060: iconst_0
/*    */     //   2061: istore #9
/*    */     //   2063: iconst_0
/*    */     //   2064: istore #14
/*    */     //   2066: goto -> 2081
/*    */     //   2069: iconst_1
/*    */     //   2070: istore #9
/*    */     //   2072: iconst_0
/*    */     //   2073: istore #14
/*    */     //   2075: iinc #5, 1
/*    */     //   2078: goto -> 1957
/*    */     //   2081: iload #9
/*    */     //   2083: ifeq -> 2121
/*    */     //   2086: aload_0
/*    */     //   2087: aload #12
/*    */     //   2089: invokestatic parseDouble : (Ljava/lang/String;)D
/*    */     //   2092: dstore #14
/*    */     //   2094: new f/bM0
/*    */     //   2097: dup
/*    */     //   2098: astore #5
/*    */     //   2100: dload #14
/*    */     //   2102: aload #12
/*    */     //   2104: invokespecial <init> : (DLjava/lang/String;)V
/*    */     //   2107: aload #13
/*    */     //   2109: aload #5
/*    */     //   2111: invokevirtual p30 : (Ljava/lang/String;Lf/bM0;)V
/*    */     //   2114: goto -> 2176
/*    */     //   2117: pop
/*    */     //   2118: goto -> 2157
/*    */     //   2121: iload #14
/*    */     //   2123: ifeq -> 2157
/*    */     //   2126: aload_0
/*    */     //   2127: aload #12
/*    */     //   2129: invokestatic parseLong : (Ljava/lang/String;)J
/*    */     //   2132: lstore #14
/*    */     //   2134: new f/bM0
/*    */     //   2137: dup
/*    */     //   2138: astore #5
/*    */     //   2140: lload #14
/*    */     //   2142: aload #12
/*    */     //   2144: invokespecial <init> : (JLjava/lang/String;)V
/*    */     //   2147: aload #13
/*    */     //   2149: aload #5
/*    */     //   2151: invokevirtual p30 : (Ljava/lang/String;Lf/bM0;)V
/*    */     //   2154: goto -> 2176
/*    */     //   2157: aload_0
/*    */     //   2158: new f/bM0
/*    */     //   2161: dup
/*    */     //   2162: astore #5
/*    */     //   2164: aload #12
/*    */     //   2166: invokespecial <init> : (Ljava/lang/String;)V
/*    */     //   2169: aload #13
/*    */     //   2171: aload #5
/*    */     //   2173: invokevirtual p30 : (Ljava/lang/String;Lf/bM0;)V
/*    */     //   2176: iconst_0
/*    */     //   2177: istore #9
/*    */     //   2179: iload_3
/*    */     //   2180: istore #5
/*    */     //   2182: goto -> 1740
/*    */     //   2185: astore #4
/*    */     //   2187: aload #4
/*    */     //   2189: astore #10
/*    */     //   2191: iload_3
/*    */     //   2192: iload_2
/*    */     //   2193: aload_0
/*    */     //   2194: dup
/*    */     //   2195: dup2
/*    */     //   2196: getfield uw0 : Lf/bM0;
/*    */     //   2199: astore #4
/*    */     //   2201: aconst_null
/*    */     //   2202: putfield uw0 : Lf/bM0;
/*    */     //   2205: aconst_null
/*    */     //   2206: putfield Mb0 : Lf/bM0;
/*    */     //   2209: getfield dd : Lf/fQ;
/*    */     //   2212: invokevirtual clear : ()V
/*    */     //   2215: if_icmpge -> 2327
/*    */     //   2218: iconst_1
/*    */     //   2219: istore_0
/*    */     //   2220: iconst_0
/*    */     //   2221: istore #4
/*    */     //   2223: iload #4
/*    */     //   2225: iload_3
/*    */     //   2226: if_icmpge -> 2247
/*    */     //   2229: aload_1
/*    */     //   2230: iload #4
/*    */     //   2232: caload
/*    */     //   2233: bipush #10
/*    */     //   2235: if_icmpne -> 2241
/*    */     //   2238: iinc #0, 1
/*    */     //   2241: iinc #4, 1
/*    */     //   2244: goto -> 2223
/*    */     //   2247: iload_3
/*    */     //   2248: bipush #32
/*    */     //   2250: isub
/*    */     //   2251: iconst_0
/*    */     //   2252: swap
/*    */     //   2253: invokestatic max : (II)I
/*    */     //   2256: istore #4
/*    */     //   2258: new f/kN
/*    */     //   2261: dup
/*    */     //   2262: ldc_w 'Error parsing JSON on line '
/*    */     //   2265: iload_0
/*    */     //   2266: ldc_w ' near: '
/*    */     //   2269: invokestatic DH0 : (Ljava/lang/String;ILjava/lang/String;)Ljava/lang/StringBuilder;
/*    */     //   2272: new java/lang/String
/*    */     //   2275: dup
/*    */     //   2276: aload_1
/*    */     //   2277: iload_3
/*    */     //   2278: iload #4
/*    */     //   2280: isub
/*    */     //   2281: iload #4
/*    */     //   2283: swap
/*    */     //   2284: invokespecial <init> : ([CII)V
/*    */     //   2287: invokevirtual append : (Ljava/lang/String;)Ljava/lang/StringBuilder;
/*    */     //   2290: ldc_w '*ERROR*'
/*    */     //   2293: invokevirtual append : (Ljava/lang/String;)Ljava/lang/StringBuilder;
/*    */     //   2296: new java/lang/String
/*    */     //   2299: dup
/*    */     //   2300: aload_1
/*    */     //   2301: iload_2
/*    */     //   2302: iload_3
/*    */     //   2303: isub
/*    */     //   2304: bipush #64
/*    */     //   2306: swap
/*    */     //   2307: invokestatic min : (II)I
/*    */     //   2310: iload_3
/*    */     //   2311: swap
/*    */     //   2312: invokespecial <init> : ([CII)V
/*    */     //   2315: invokevirtual append : (Ljava/lang/String;)Ljava/lang/StringBuilder;
/*    */     //   2318: invokevirtual toString : ()Ljava/lang/String;
/*    */     //   2321: aload #10
/*    */     //   2323: invokespecial <init> : (Ljava/lang/String;Ljava/lang/Throwable;)V
/*    */     //   2326: athrow
/*    */     //   2327: aload_0
/*    */     //   2328: getfield WP : Lf/fQ;
/*    */     //   2331: dup
/*    */     //   2332: astore_2
/*    */     //   2333: getfield Z8 : I
/*    */     //   2336: ifeq -> 2398
/*    */     //   2339: aload_2
/*    */     //   2340: invokevirtual peek : ()Ljava/lang/Object;
/*    */     //   2343: checkcast f/bM0
/*    */     //   2346: dup
/*    */     //   2347: astore_1
/*    */     //   2348: aload_0
/*    */     //   2349: getfield WP : Lf/fQ;
/*    */     //   2352: invokevirtual clear : ()V
/*    */     //   2355: ifnull -> 2387
/*    */     //   2358: aload_1
/*    */     //   2359: getfield eR : Lf/nc;
/*    */     //   2362: getstatic f/nc.Gg0 : Lf/nc;
/*    */     //   2365: if_acmpne -> 2372
/*    */     //   2368: iconst_1
/*    */     //   2369: goto -> 2373
/*    */     //   2372: iconst_0
/*    */     //   2373: ifeq -> 2387
/*    */     //   2376: new f/kN
/*    */     //   2379: dup
/*    */     //   2380: ldc_w 'Error parsing JSON, unmatched brace.'
/*    */     //   2383: invokespecial <init> : (Ljava/lang/String;)V
/*    */     //   2386: athrow
/*    */     //   2387: new f/kN
/*    */     //   2390: dup
/*    */     //   2391: ldc_w 'Error parsing JSON, unmatched bracket.'
/*    */     //   2394: invokespecial <init> : (Ljava/lang/String;)V
/*    */     //   2397: athrow
/*    */     //   2398: aload #10
/*    */     //   2400: ifnonnull -> 2406
/*    */     //   2403: aload #4
/*    */     //   2405: areturn
/*    */     //   2406: new f/kN
/*    */     //   2409: dup
/*    */     //   2410: ldc_w 'Error parsing JSON: '
/*    */     //   2413: invokestatic df : (Ljava/lang/String;)Ljava/lang/StringBuilder;
/*    */     //   2416: new java/lang/String
/*    */     //   2419: dup
/*    */     //   2420: aload_1
/*    */     //   2421: invokespecial <init> : ([C)V
/*    */     //   2424: invokevirtual append : (Ljava/lang/String;)Ljava/lang/StringBuilder;
/*    */     //   2427: invokevirtual toString : ()Ljava/lang/String;
/*    */     //   2430: aload #10
/*    */     //   2432: invokespecial <init> : (Ljava/lang/String;Ljava/lang/Throwable;)V
/*    */     //   2435: athrow
/*    */     // Line number table:
/*    */     //   Java source line number -> byte code offset
/*    */     //   #1	-> 897
/*    */     //   #2	-> 970
/*    */     //   #3	-> 1077
/*    */     //   #4	-> 1150
/*    */     //   #5	-> 1359
/*    */     //   #6	-> 1382
/*    */     //   #7	-> 1395
/*    */     //   #8	-> 1411
/*    */     //   #9	-> 1424
/*    */     //   #10	-> 1460
/*    */     //   #11	-> 1586
/*    */     //   #12	-> 1621
/*    */     //   #13	-> 1626
/*    */     //   #14	-> 1650
/*    */     //   #15	-> 1722
/*    */     //   #16	-> 1865
/*    */     //   #17	-> 1888
/*    */     //   #18	-> 1901
/*    */     //   #19	-> 1917
/*    */     //   #20	-> 1930
/*    */     //   #21	-> 1966
/*    */     //   #22	-> 2094
/*    */     //   #23	-> 2129
/*    */     //   #24	-> 2134
/*    */     //   #25	-> 2158
/*    */     //   #26	-> 2196
/*    */     //   #27	-> 2262
/*    */     //   #28	-> 2272
/*    */     //   #29	-> 2359
/*    */     //   #30	-> 2376
/*    */     //   #31	-> 2410
/*    */     //   #32	-> 2416
/*    */     // Exception table:
/*    */     //   from	to	target	type
/*    */     //   87	93	2185	java/lang/RuntimeException
/*    */     //   95	101	2185	java/lang/RuntimeException
/*    */     //   103	109	2185	java/lang/RuntimeException
/*    */     //   170	171	2185	java/lang/RuntimeException
/*    */     //   174	180	2185	java/lang/RuntimeException
/*    */     //   232	238	2185	java/lang/RuntimeException
/*    */     //   293	294	2185	java/lang/RuntimeException
/*    */     //   297	300	2185	java/lang/RuntimeException
/*    */     //   303	306	2185	java/lang/RuntimeException
/*    */     //   326	327	2185	java/lang/RuntimeException
/*    */     //   358	364	2185	java/lang/RuntimeException
/*    */     //   366	372	2185	java/lang/RuntimeException
/*    */     //   374	380	2185	java/lang/RuntimeException
/*    */     //   386	389	2185	java/lang/RuntimeException
/*    */     //   396	397	2185	java/lang/RuntimeException
/*    */     //   409	412	2185	java/lang/RuntimeException
/*    */     //   419	420	2185	java/lang/RuntimeException
/*    */     //   488	492	539	java/lang/RuntimeException
/*    */     //   561	565	808	java/lang/RuntimeException
/*    */     //   624	628	808	java/lang/RuntimeException
/*    */     //   663	667	808	java/lang/RuntimeException
/*    */     //   740	744	808	java/lang/RuntimeException
/*    */     //   781	785	808	java/lang/RuntimeException
/*    */     //   824	825	2185	java/lang/RuntimeException
/*    */     //   835	838	2185	java/lang/RuntimeException
/*    */     //   865	868	2185	java/lang/RuntimeException
/*    */     //   873	877	2185	java/lang/RuntimeException
/*    */     //   894	915	2185	java/lang/RuntimeException
/*    */     //   918	925	2185	java/lang/RuntimeException
/*    */     //   926	930	2185	java/lang/RuntimeException
/*    */     //   933	936	2185	java/lang/RuntimeException
/*    */     //   939	947	2185	java/lang/RuntimeException
/*    */     //   955	963	2185	java/lang/RuntimeException
/*    */     //   970	979	2185	java/lang/RuntimeException
/*    */     //   982	990	2185	java/lang/RuntimeException
/*    */     //   998	1009	2185	java/lang/RuntimeException
/*    */     //   1012	1017	2185	java/lang/RuntimeException
/*    */     //   1019	1021	2185	java/lang/RuntimeException
/*    */     //   1029	1030	2185	java/lang/RuntimeException
/*    */     //   1032	1043	2185	java/lang/RuntimeException
/*    */     //   1051	1056	2185	java/lang/RuntimeException
/*    */     //   1074	1095	2185	java/lang/RuntimeException
/*    */     //   1098	1105	2185	java/lang/RuntimeException
/*    */     //   1106	1110	2185	java/lang/RuntimeException
/*    */     //   1113	1116	2185	java/lang/RuntimeException
/*    */     //   1119	1127	2185	java/lang/RuntimeException
/*    */     //   1135	1143	2185	java/lang/RuntimeException
/*    */     //   1150	1151	2185	java/lang/RuntimeException
/*    */     //   1167	1172	2185	java/lang/RuntimeException
/*    */     //   1175	1183	2185	java/lang/RuntimeException
/*    */     //   1191	1202	2185	java/lang/RuntimeException
/*    */     //   1205	1210	2185	java/lang/RuntimeException
/*    */     //   1212	1214	2185	java/lang/RuntimeException
/*    */     //   1222	1223	2185	java/lang/RuntimeException
/*    */     //   1225	1236	2185	java/lang/RuntimeException
/*    */     //   1244	1249	2185	java/lang/RuntimeException
/*    */     //   1266	1271	2185	java/lang/RuntimeException
/*    */     //   1280	1288	2185	java/lang/RuntimeException
/*    */     //   1291	1296	2185	java/lang/RuntimeException
/*    */     //   1308	1321	2185	java/lang/RuntimeException
/*    */     //   1324	1332	2185	java/lang/RuntimeException
/*    */     //   1345	1352	2185	java/lang/RuntimeException
/*    */     //   1359	1362	2185	java/lang/RuntimeException
/*    */     //   1365	1388	2185	java/lang/RuntimeException
/*    */     //   1395	1398	2185	java/lang/RuntimeException
/*    */     //   1401	1417	2185	java/lang/RuntimeException
/*    */     //   1424	1427	2185	java/lang/RuntimeException
/*    */     //   1430	1445	2185	java/lang/RuntimeException
/*    */     //   1457	1461	2185	java/lang/RuntimeException
/*    */     //   1578	1584	1609	java/lang/NumberFormatException
/*    */     //   1578	1584	2185	java/lang/RuntimeException
/*    */     //   1586	1589	1609	java/lang/NumberFormatException
/*    */     //   1586	1589	2185	java/lang/RuntimeException
/*    */     //   1592	1609	1609	java/lang/NumberFormatException
/*    */     //   1592	1609	2185	java/lang/RuntimeException
/*    */     //   1618	1624	1609	java/lang/NumberFormatException
/*    */     //   1618	1624	2185	java/lang/RuntimeException
/*    */     //   1626	1629	1609	java/lang/NumberFormatException
/*    */     //   1626	1629	2185	java/lang/RuntimeException
/*    */     //   1632	1649	1609	java/lang/NumberFormatException
/*    */     //   1632	1649	2185	java/lang/RuntimeException
/*    */     //   1649	1653	2185	java/lang/RuntimeException
/*    */     //   1656	1668	2185	java/lang/RuntimeException
/*    */     //   1722	1731	2185	java/lang/RuntimeException
/*    */     //   1737	1738	2185	java/lang/RuntimeException
/*    */     //   1750	1753	2185	java/lang/RuntimeException
/*    */     //   1760	1761	2185	java/lang/RuntimeException
/*    */     //   1768	1773	2185	java/lang/RuntimeException
/*    */     //   1782	1790	2185	java/lang/RuntimeException
/*    */     //   1793	1798	2185	java/lang/RuntimeException
/*    */     //   1810	1815	2185	java/lang/RuntimeException
/*    */     //   1822	1827	2185	java/lang/RuntimeException
/*    */     //   1830	1838	2185	java/lang/RuntimeException
/*    */     //   1851	1858	2185	java/lang/RuntimeException
/*    */     //   1865	1868	2185	java/lang/RuntimeException
/*    */     //   1871	1894	2185	java/lang/RuntimeException
/*    */     //   1901	1904	2185	java/lang/RuntimeException
/*    */     //   1907	1923	2185	java/lang/RuntimeException
/*    */     //   1930	1933	2185	java/lang/RuntimeException
/*    */     //   1936	1951	2185	java/lang/RuntimeException
/*    */     //   1963	1967	2185	java/lang/RuntimeException
/*    */     //   2086	2092	2117	java/lang/NumberFormatException
/*    */     //   2086	2092	2185	java/lang/RuntimeException
/*    */     //   2094	2097	2117	java/lang/NumberFormatException
/*    */     //   2094	2097	2185	java/lang/RuntimeException
/*    */     //   2100	2117	2117	java/lang/NumberFormatException
/*    */     //   2100	2117	2185	java/lang/RuntimeException
/*    */     //   2126	2132	2117	java/lang/NumberFormatException
/*    */     //   2126	2132	2185	java/lang/RuntimeException
/*    */     //   2134	2137	2117	java/lang/NumberFormatException
/*    */     //   2134	2137	2185	java/lang/RuntimeException
/*    */     //   2140	2157	2117	java/lang/NumberFormatException
/*    */     //   2140	2157	2185	java/lang/RuntimeException
/*    */     //   2157	2161	2185	java/lang/RuntimeException
/*  7 */     //   2164	2176	2185	java/lang/RuntimeException } public final void F50(String paramString) { this(nc.Gg0); bM0 bM01; if (this.Mb0 != null) p30(paramString, bM01);  this.WP.Com3(bM01); this.Mb0 = bM01; } public static final byte[] vc0 = new byte[] { 0, 9, 2, 1, 2, 7, 4, 4, 2, 9, 7, 7, 7, 1, 7, 2, 2, 7, 2, 2, 1, 2, 2, 9, 7, 7, 9, 1, 9, 2, 2, 9, 2, 2, 2, 3, 3, 0, 0 };
/*    */   public final void To0(String paramString) { this(nc.implements); bM0 bM01; if (this.Mb0 != null) p30(paramString, bM01);  this.WP.Com3(bM01); this.Mb0 = bM01; }
/*  9 */   public final void p30(String paramString, bM0 parambM0) { parambM0.as0 = paramString; bM0 bM01; if ((bM01 = this.Mb0) == null) { this.Mb0 = parambM0; this.uw0 = parambM0; } else { if (!bM01.OA0()) { boolean bool; if ((bM01 = this.Mb0).eR == nc.Gg0) { bool = true; } else { bool = false; }  if (bool) parambM0.UC = bM01 = this.Mb0;  this.uw0 = bM01; return; }  parambM0.UC = bM01 = this.Mb0; }  } public static final short[] kr = new short[] { 0, 0, 11, 13, 14, 16, 25, 31, 37, 39, 50, 57, 64, 73, 74, 83, 85, 87, 96, 98, 100, 101, 103, 105, 116, 123, 130, 141, 142, 153, 155, 157, 168, 170, 172, 174, 179, 184, 184 }; public static final char[] GX = new char[] { '\r', ' ', '"', ',', '/', ':', '[', ']', '{', '\t', '\n', '*', '/', '"', '*', '/', '\r', ' ', '"', ',', '/', ':', '}', '\t', '\n', '\r', ' ', '/', ':', '\t', '\n', '\r', ' ', '/', ':', '\t', '\n', '*', '/', '\r', ' ', '"', ',', '/', ':', '[', ']', '{', '\t', '\n', '\t', '\n', '\r', ' ', ',', '/', '}', '\t', '\n', '\r', ' ', ',', '/', '}', '\r', ' ', '"', ',', '/', ':', '}', '\t', '\n', '"', '\r', ' ', '"', ',', '/', ':', '}', '\t', '\n', '*', '/', '*', '/', '\r', ' ', '"', ',', '/', ':', '}', '\t', '\n', '*', '/', '*', '/', '"', '*', '/', '*', '/', '\r', ' ', '"', ',', '/', ':', '[', ']', '{', '\t', '\n', '\t', '\n', '\r', ' ', ',', '/', ']', '\t', '\n', '\r', ' ', ',', '/', ']', '\r', ' ', '"', ',', '/', ':', '[', ']', '{', '\t', '\n', '"', '\r', ' ', '"', ',', '/', ':', '[', ']', '{', '\t', '\n', '*', '/', '*', '/', '\r', ' ', '"', ',', '/', ':', '[', ']', '{', '\t', '\n', '*', '/', '*', '/', '*', '/', '\r', ' ', '/', '\t', '\n', '\r', ' ', '/', '\t', '\n', Character.MIN_VALUE }; public static final byte[] cZ = new byte[] { 0, 1, 0, 0, 0, 1, 1, 1, 0, 1, 0, 0, 1, 0, 1, 0, 0, 1, 0, 0, 0, 0, 0, 1, 0, 0, 1, 0, 1, 0, 0, 1, 0, 0, 0, 1, 1, 0, 0 };
/*    */   
/* 11 */   public static final short[] P30 = new short[] { 0, 0, 11, 14, 16, 19, 28, 34, 40, 43, 54, 62, 70, 79, 81, 90, 93, 96, 105, 108, 111, 113, 116, 119, 130, 138, 146, 157, 159, 170, 173, 176, 187, 190, 193, 196, 201, 206, 207 };
/* 12 */   public static final byte[] Ev0 = nu0();
/* 13 */   public static final byte[] Kf0 = new byte[] { 35, 1, 3, 0, 4, 36, 36, 36, 36, 1, 6, 5, 13, 17, 22, 37, 7, 8, 9, 7, 8, 9, 7, 10, 20, 21, 11, 11, 11, 12, 17, 19, 37, 11, 12, 19, 14, 16, 15, 14, 12, 18, 17, 11, 9, 5, 24, 23, 27, 31, 34, 25, 38, 25, 25, 26, 31, 33, 38, 25, 26, 33, 28, 30, 29, 28, 26, 32, 31, 25, 23, 2, 36, 2 };
/* 14 */   public static final byte[] DW = BH();
/* 15 */   public static final byte[] LC0 = new byte[] { 0, 0, 0, 0, 0, 0, 0, 0, 0, 0, 0, 0, 0, 0, 0, 0, 0, 0, 0, 0, 0, 0, 0, 0, 0, 0, 0, 0, 0, 0, 0, 0, 0, 0, 0, 1, 0, 0, 0 };
/*    */   public final fQ WP;
/*    */   public final fQ dd;
/*    */   public bM0 uw0;
/*    */   public bM0 Mb0; }


/* Location:              /Users/vnnsnnt/Documents/Codespace/JavaWorkspace/RedTrainer/src/main/java/org/trainer/client/PokeMMO.jar!/f/nP.class
 * Java compiler version: 7 (51.0)
 * JD-Core Version:       1.1.3
 */