/*  1 */ package f;public final class NR extends Wr implements fi { public final Qv0[] FB0; public pA Zw0; public Qv0 Hd; public Qv0 k9; public Ip k10; public Fy0 S80; public Fy0 W20; public static void w90(j40 paramj40) { km.u4
/*  2 */       .bA0(paramj40.Jg, (byte)1); } public boolean nN; public boolean CC0; public int Qp0; public boolean rs0; public boolean RJ; public Consumer gp; public NR(pA parampA, boolean paramBoolean) { Fd0 fd0; this.nN = true; this.CC0 = false; this.Qp0 = 0; this.rs0 = false; Lo(""); Xu("monster-party-frame-locked"); (this.k10 = new Ip()).Xu("content"); this.Zw0 = parampA; EP(1); this.RJ = paramBoolean; this.FB0 = new Qv0[6]; this(this, paramBoolean, parampA); Qv0[] arrayOfQv0; for (short s = 0; s < (arrayOfQv0 = this.FB0).length; s = (short)(s + 1)) { Qv0 qv0; this(km.u4.s40(aq0.LI), s, paramBoolean); arrayOfQv0[s] = qv0; this.FB0[s].ay(fd0); if (paramBoolean) if (km.XU()) { this.FB0[s].AL(80, 80); this.FB0[s].zY().zT(4, 0); } else { this.FB0[s].zY().zT(12, 4); }   this.FB0[s].L1(() -> { this.Qp0 = paramShort; Xp(false); }); if (paramBoolean) this.FB0[s].Ou0();  this.k10.J8(this.FB0[s]); }  this("", 12, 12); this.S80 = fy0; Fy0 fy0; (fy0 = new Fy0()).tW(this::E7); (this.W20 = new Fy0("", 12, 12)).Xu("button-move"); this.W20.tW(this::U8); U90 u901 = this.k10.mE0().Mg((JG0[])this.FB0); U90 u902 = this.k10.d7().Mg((JG0[])this.FB0); if (km.Nr() && !paramBoolean) { u902.ee0(this.k10.AUX(new JG0[] { this.S80, this.W20 })); u901.ee0(this.k10.vo0(new JG0[] { this.S80, this.W20 })); }  this.k10.rK0(u901); this.k10.WN(u902); uh0(30, 30); J8(this.k10); } private void Ea0(short paramShort, boolean paramBoolean, j40 paramj40) { // Byte code:
/*    */     //   0: iload_1
/*    */     //   1: iload_2
/*    */     //   2: invokestatic CE0 : (SZ)Z
/*    */     //   5: ifeq -> 44
/*    */     //   8: aload_0
/*    */     //   9: aload_3
/*    */     //   10: getstatic f/js.vu0 : Lf/js;
/*    */     //   13: aload_0
/*    */     //   14: dup
/*    */     //   15: dup
/*    */     //   16: getfield Kd : I
/*    */     //   19: istore_0
/*    */     //   20: getfield er0 : I
/*    */     //   23: istore_2
/*    */     //   24: <illegal opcode> run : (Lf/NR;)Ljava/lang/Runnable;
/*    */     //   29: astore_3
/*    */     //   30: invokevirtual getClass : ()Ljava/lang/Class;
/*    */     //   33: pop
/*    */     //   34: iload_1
/*    */     //   35: iload_0
/*    */     //   36: iload_2
/*    */     //   37: aload_3
/*    */     //   38: invokestatic yC0 : (Lf/JG0;Lf/j40;SIILjava/lang/Runnable;)V
/*    */     //   41: goto -> 123
/*    */     //   44: iload_1
/*    */     //   45: aload_3
/*    */     //   46: getstatic f/km.u4 : Lf/R8;
/*    */     //   49: astore_2
/*    */     //   50: getfield Jg : I
/*    */     //   53: istore_3
/*    */     //   54: iconst_0
/*    */     //   55: istore #4
/*    */     //   57: iconst_0
/*    */     //   58: istore #5
/*    */     //   60: bipush #19
/*    */     //   62: if_icmpne -> 95
/*    */     //   65: aload_2
/*    */     //   66: dup
/*    */     //   67: invokevirtual getClass : ()Ljava/lang/Class;
/*    */     //   70: pop
/*    */     //   71: iconst_1
/*    */     //   72: istore_1
/*    */     //   73: aconst_null
/*    */     //   74: astore_2
/*    */     //   75: getfield YG0 : Lf/js;
/*    */     //   78: getfield MH0 : Lf/pA;
/*    */     //   81: dup
/*    */     //   82: astore_3
/*    */     //   83: ifnull -> 115
/*    */     //   86: aload_3
/*    */     //   87: iload_1
/*    */     //   88: aload_2
/*    */     //   89: invokevirtual U10 : (ZLf/R2;)V
/*    */     //   92: goto -> 115
/*    */     //   95: aload_2
/*    */     //   96: getfield e20 : Lf/c4;
/*    */     //   99: new f/NH
/*    */     //   102: dup
/*    */     //   103: iload_3
/*    */     //   104: iload #4
/*    */     //   106: iload #5
/*    */     //   108: iload_1
/*    */     //   109: invokespecial <init> : (IIIS)V
/*    */     //   112: invokevirtual W3 : (Lf/Bi;)V
/*    */     //   115: aload_0
/*    */     //   116: dup
/*    */     //   117: invokevirtual xf0 : ()V
/*    */     //   120: invokevirtual xI0 : ()V
/*    */     //   123: return
/*    */     // Line number table:
/*    */     //   Java source line number -> byte code offset
/*    */     //   #1	-> 10
/*    */     //   #2	-> 16
/*    */     //   #3	-> 20
/*    */     //   #4	-> 24
/*    */     //   #5	-> 50
/*    */     //   #6	-> 67
/*    */     //   #7	-> 75
/*    */     //   #8	-> 78
/*    */     //   #9	-> 89
/*    */     //   #10	-> 96
/*    */     //   #11	-> 99
/*  2 */     //   #12	-> 117 } public static void default(Qv0 paramQv0) { js js = js.vu0; arrayOfQv0[0] = paramQv0;
/*  3 */     int i = paramQv0.Kd - 174;
/*  4 */     int j = paramQv0.er0;
/*  5 */     js.getClass();
/*    */     Qv0[] arrayOfQv0;
/*  7 */     F7.T1(js.pz(arrayOfQv0 = new Qv0[1], -1), paramQv0, i, j); } private void dq(j40 paramj40) { xf0(); R8 r8 = km.u4; int i = paramj40.Jg; byte b = -1; aq0 aq0 = paramj40.Zs.COm1; this.e20.W3(new zD(i, b, aq0)); } private void HV(j40 paramj40) { UD0 uD0 = paramj40.VP; byte b = paramj40.Zs.Vp; pA pA1; Hy hy; if ((hy = (pA1 = pA.Dg0).yb0) == null) { pA1.RQ(); } else { VA0.c90(hy); }  pA1.yb0.If(b, uD0); xf0(); } private void ga0(j40 paramj40, Qv0 paramQv0) { pA.Dg0.u30(paramQv0, paramj40); xf0(); } public static void Jz(Qv0 paramQv0) { int i = paramQv0.RS(); i = paramQv0.qF() / 2 + i; int j = paramQv0.e3(); j = paramQv0.Hy() / 2 + j; pA.Dg0.dk0.class(paramQv0, Collections.emptyList()); pA.Dg0.dk0.lf0(i, j); } public final kC0 fG(JG0 paramJG0) { if (paramJG0 instanceof kC0) return (kC0)paramJG0;  if ((paramJG0 = paramJG0.fr0) != null) return fG(paramJG0);  return null; } public final void Vp(Qv0 paramQv0) { Qv0 qv0; if (paramQv0 != (qv0 = this.k9)) { if (qv0 != null) { qv0.O.gf0(Qv0.GZ, false); qv0.O.gf0(Qv0.iX, false); }  this.k9 = paramQv0; if (paramQv0 != null) { boolean bool1, bool2, bool3; if (paramQv0 == this.Hd || paramQv0.As.AX()) { bool1 = true; } else { bool1 = false; }  Sa0 sa0 = paramQv0.O; Ll ll2 = Qv0.GZ; if (bool1) { bool3 = true; } else { bool3 = false; }  sa0.gf0(ll2, bool3); Ll ll1 = Qv0.iX; if (!bool1) { bool2 = true; } else { bool2 = false; }  sa0.gf0(this, bool2); }  }  } public final void Op(boolean paramBoolean) { if (this.Qp0 < 0) this.Qp0 = 0;  while (true) { int i; Qv0[] arrayOfQv0; if ((i = this.Qp0) >= (arrayOfQv0 = this.FB0).length || (i > 0 && arrayOfQv0[i].public() == null && !this.RJ)) { this.Qp0--; continue; }  if (paramBoolean) xf0();  if (this.RJ) VA0.c90(this.FB0[this.Qp0]);  Consumer<j40> consumer; if ((consumer = this.gp) != null) consumer.accept(this.FB0[this.Qp0].public());  Qv0 qv0 = this.FB0[this.Qp0]; qv0 = ((NR)super).FB0[((NR)super).Qp0]; String str; if (this.RJ ? (str = "monster-slot-pc-selected").equals(this.cl) : (str = "monster-slot-selected").equals(this.cl)) { Xu(str); cZ(); }  return; }  } public final void U8() { this.CC0 = false; this.CC0 = true; String str; if (this.CC0 ? (str = "monster-party-frame-locked").equals(this.cl) : (str = "monster-party-frame").equals(this.cl)) { Xu(str); cZ(); }  }
/*  8 */   public final void E7() { if (this.nN) { this.nN = false; this.k10.rK0(V2.Ur(this.k10, this.k10).Mg((JG0[])this.FB0).ee0(this.k10.AUX(new JG0[] { this.S80, this.W20 }))); this.k10.WN(Mr.X60(this.k10, this.k10).Mg((JG0[])this.FB0).ee0(this.k10.vo0(new JG0[] { this.S80, this.W20 }))); } else { this.nN = true; this.k10.rK0(Mr.X60(this.k10, this.k10).Mg((JG0[])this.FB0).ee0(this.k10.vo0(new JG0[] { this.S80, this.W20 }))); this.k10.WN(V2.Ur(this.k10, this.k10).Mg((JG0[])this.FB0).ee0(this.k10.AUX(new JG0[] { this.S80, this.W20 }))); }  } public final void EX(nY paramnY) {} public final void d40() { this.k10.mM(); mM(); if (this.Kd + this.xY > km.wI0.dG() - this.xY) { int i = km.wI0.dG() - this.xY; ME(i, this.er0); }  if (this
/*  9 */       .er0 + this
/* 10 */       .HC > 
/* 11 */       km.wI0.k1())
/*    */     {
/*    */ 
/*    */       
/* 15 */       ME(this.Kd, km.wI0.k1() - this.HC); }  super
/* 16 */       .d40(); }
/*    */ 
/*    */   
/*    */   public final void CQ(boolean paramBoolean) {
/*    */     if (paramBoolean && !this.dP)
/*    */       xf0(); 
/*    */     super.CQ(paramBoolean);
/*    */   }
/*    */   
/*    */   public final void xf0() {
/*    */     // Byte code:
/*    */     //   0: getstatic f/P3.lF : Lf/P3;
/*    */     //   3: invokevirtual getClass : ()Ljava/lang/Class;
/*    */     //   6: pop
/*    */     //   7: ldc f/NR
/*    */     //   9: invokestatic XP : (Ljava/lang/Class;)Ljava/util/List;
/*    */     //   12: invokeinterface iterator : ()Ljava/util/Iterator;
/*    */     //   17: astore_0
/*    */     //   18: aload_0
/*    */     //   19: invokeinterface hasNext : ()Z
/*    */     //   24: ifeq -> 622
/*    */     //   27: aload_0
/*    */     //   28: invokeinterface next : ()Ljava/lang/Object;
/*    */     //   33: checkcast f/NR
/*    */     //   36: dup
/*    */     //   37: astore_1
/*    */     //   38: invokevirtual getClass : ()Ljava/lang/Class;
/*    */     //   41: pop
/*    */     //   42: getstatic f/km.u4 : Lf/R8;
/*    */     //   45: dup
/*    */     //   46: astore_2
/*    */     //   47: ifnonnull -> 53
/*    */     //   50: goto -> 18
/*    */     //   53: aload_2
/*    */     //   54: getfield z2 : Lf/Uc0;
/*    */     //   57: astore_2
/*    */     //   58: getstatic f/um0.Kt0 : Lf/um0;
/*    */     //   61: astore_3
/*    */     //   62: iconst_0
/*    */     //   63: istore #4
/*    */     //   65: iload #4
/*    */     //   67: bipush #6
/*    */     //   69: if_icmpge -> 600
/*    */     //   72: aload_2
/*    */     //   73: iload #4
/*    */     //   75: invokevirtual ky : (S)Lf/j40;
/*    */     //   78: dup
/*    */     //   79: astore #5
/*    */     //   81: ifnull -> 457
/*    */     //   84: aload #5
/*    */     //   86: dup
/*    */     //   87: aload_1
/*    */     //   88: dup
/*    */     //   89: getfield FB0 : [Lf/Qv0;
/*    */     //   92: iload #4
/*    */     //   94: aaload
/*    */     //   95: aload_3
/*    */     //   96: aload #5
/*    */     //   98: dup
/*    */     //   99: getfield Zs : Lf/Q90;
/*    */     //   102: invokevirtual Vf0 : ()S
/*    */     //   105: istore #6
/*    */     //   107: invokevirtual s5 : ()B
/*    */     //   110: istore #7
/*    */     //   112: iload #6
/*    */     //   114: aload #5
/*    */     //   116: getfield Zs : Lf/Q90;
/*    */     //   119: invokevirtual da : ()Z
/*    */     //   122: iload #7
/*    */     //   124: invokevirtual lb : (SZB)[Lf/zh0;
/*    */     //   127: iconst_0
/*    */     //   128: aaload
/*    */     //   129: invokevirtual Ax : (Lf/zh0;)V
/*    */     //   132: getfield FB0 : [Lf/Qv0;
/*    */     //   135: iload #4
/*    */     //   137: aaload
/*    */     //   138: aload_2
/*    */     //   139: invokevirtual un : (Lf/Uc0;)V
/*    */     //   142: getfield Zs : Lf/Q90;
/*    */     //   145: getfield Hq0 : S
/*    */     //   148: i2f
/*    */     //   149: aload #5
/*    */     //   151: getfield Fq0 : Lf/Sf;
/*    */     //   154: getstatic f/hR.Gg : Lf/hR;
/*    */     //   157: invokevirtual Mm : (Lf/hR;)S
/*    */     //   160: i2f
/*    */     //   161: fdiv
/*    */     //   162: fstore #6
/*    */     //   164: getfield Zs : Lf/Q90;
/*    */     //   167: getfield u0 : B
/*    */     //   170: ifeq -> 179
/*    */     //   173: iconst_1
/*    */     //   174: istore #7
/*    */     //   176: goto -> 182
/*    */     //   179: iconst_0
/*    */     //   180: istore #7
/*    */     //   182: iload #7
/*    */     //   184: ifeq -> 197
/*    */     //   187: aload_1
/*    */     //   188: getfield FB0 : [Lf/Qv0;
/*    */     //   191: iload #4
/*    */     //   193: aaload
/*    */     //   194: invokevirtual jj : ()V
/*    */     //   197: aload_1
/*    */     //   198: dup
/*    */     //   199: getfield FB0 : [Lf/Qv0;
/*    */     //   202: iload #4
/*    */     //   204: aaload
/*    */     //   205: dup
/*    */     //   206: astore #7
/*    */     //   208: sipush #200
/*    */     //   211: putfield jl : I
/*    */     //   214: getfield RJ : Z
/*    */     //   217: ifeq -> 254
/*    */     //   220: ldc_w 'monster-slot-pc'
/*    */     //   223: dup
/*    */     //   224: astore #6
/*    */     //   226: aload #7
/*    */     //   228: getfield cl : Ljava/lang/String;
/*    */     //   231: invokevirtual equals : (Ljava/lang/Object;)Z
/*    */     //   234: ifeq -> 240
/*    */     //   237: goto -> 432
/*    */     //   240: aload #7
/*    */     //   242: dup
/*    */     //   243: aload #6
/*    */     //   245: invokevirtual Xu : (Ljava/lang/String;)V
/*    */     //   248: invokevirtual cZ : ()V
/*    */     //   251: goto -> 432
/*    */     //   254: aload #5
/*    */     //   256: getfield Zs : Lf/Q90;
/*    */     //   259: invokevirtual YC : ()Z
/*    */     //   262: ifne -> 392
/*    */     //   265: fload #6
/*    */     //   267: f2d
/*    */     //   268: dup2
/*    */     //   269: dstore #7
/*    */     //   271: ldc2_w 0.5
/*    */     //   274: dcmpl
/*    */     //   275: ifle -> 281
/*    */     //   278: goto -> 392
/*    */     //   281: dload #7
/*    */     //   283: ldc2_w 0.2
/*    */     //   286: dcmpl
/*    */     //   287: ifle -> 319
/*    */     //   290: aload_1
/*    */     //   291: getfield FB0 : [Lf/Qv0;
/*    */     //   294: iload #4
/*    */     //   296: aaload
/*    */     //   297: astore #6
/*    */     //   299: ldc_w 'monster-slot-orange'
/*    */     //   302: dup
/*    */     //   303: astore #7
/*    */     //   305: aload #6
/*    */     //   307: getfield cl : Ljava/lang/String;
/*    */     //   310: invokevirtual equals : (Ljava/lang/Object;)Z
/*    */     //   313: ifeq -> 421
/*    */     //   316: goto -> 432
/*    */     //   319: fload #6
/*    */     //   321: fconst_0
/*    */     //   322: fcmpl
/*    */     //   323: dup
/*    */     //   324: istore #6
/*    */     //   326: ifle -> 358
/*    */     //   329: aload_1
/*    */     //   330: getfield FB0 : [Lf/Qv0;
/*    */     //   333: iload #4
/*    */     //   335: aaload
/*    */     //   336: astore #6
/*    */     //   338: ldc_w 'monster-slot-red'
/*    */     //   341: dup
/*    */     //   342: astore #7
/*    */     //   344: aload #6
/*    */     //   346: getfield cl : Ljava/lang/String;
/*    */     //   349: invokevirtual equals : (Ljava/lang/Object;)Z
/*    */     //   352: ifeq -> 421
/*    */     //   355: goto -> 432
/*    */     //   358: iload #6
/*    */     //   360: ifne -> 432
/*    */     //   363: aload_1
/*    */     //   364: getfield FB0 : [Lf/Qv0;
/*    */     //   367: iload #4
/*    */     //   369: aaload
/*    */     //   370: astore #6
/*    */     //   372: ldc_w 'monster-slot-purple'
/*    */     //   375: dup
/*    */     //   376: astore #7
/*    */     //   378: aload #6
/*    */     //   380: getfield cl : Ljava/lang/String;
/*    */     //   383: invokevirtual equals : (Ljava/lang/Object;)Z
/*    */     //   386: ifeq -> 421
/*    */     //   389: goto -> 432
/*    */     //   392: aload_1
/*    */     //   393: getfield FB0 : [Lf/Qv0;
/*    */     //   396: iload #4
/*    */     //   398: aaload
/*    */     //   399: astore #6
/*    */     //   401: ldc_w 'monster-slot'
/*    */     //   404: dup
/*    */     //   405: astore #7
/*    */     //   407: aload #6
/*    */     //   409: getfield cl : Ljava/lang/String;
/*    */     //   412: invokevirtual equals : (Ljava/lang/Object;)Z
/*    */     //   415: ifeq -> 421
/*    */     //   418: goto -> 432
/*    */     //   421: aload #6
/*    */     //   423: dup
/*    */     //   424: aload #7
/*    */     //   426: invokevirtual Xu : (Ljava/lang/String;)V
/*    */     //   429: invokevirtual cZ : ()V
/*    */     //   432: aload_1
/*    */     //   433: getfield FB0 : [Lf/Qv0;
/*    */     //   436: iload #4
/*    */     //   438: aaload
/*    */     //   439: dup
/*    */     //   440: aload #5
/*    */     //   442: iconst_1
/*    */     //   443: iconst_0
/*    */     //   444: iconst_0
/*    */     //   445: invokestatic Zs0 : (Lf/j40;ZZZ)Ljava/lang/String;
/*    */     //   448: putfield z4 : Ljava/lang/Object;
/*    */     //   451: invokevirtual zn : ()V
/*    */     //   454: goto -> 590
/*    */     //   457: aload_1
/*    */     //   458: dup
/*    */     //   459: dup2
/*    */     //   460: getfield FB0 : [Lf/Qv0;
/*    */     //   463: iload #4
/*    */     //   465: aaload
/*    */     //   466: aload_2
/*    */     //   467: invokevirtual un : (Lf/Uc0;)V
/*    */     //   470: getfield FB0 : [Lf/Qv0;
/*    */     //   473: iload #4
/*    */     //   475: aaload
/*    */     //   476: aconst_null
/*    */     //   477: invokevirtual Ax : (Lf/zh0;)V
/*    */     //   480: getfield FB0 : [Lf/Qv0;
/*    */     //   483: iload #4
/*    */     //   485: aaload
/*    */     //   486: aconst_null
/*    */     //   487: invokevirtual zf : (Lf/j40;)V
/*    */     //   490: getfield RJ : Z
/*    */     //   493: ifeq -> 525
/*    */     //   496: aload_1
/*    */     //   497: getfield FB0 : [Lf/Qv0;
/*    */     //   500: iload #4
/*    */     //   502: aaload
/*    */     //   503: astore #5
/*    */     //   505: ldc_w 'monster-slot-pc-empty'
/*    */     //   508: dup
/*    */     //   509: astore #6
/*    */     //   511: aload #5
/*    */     //   513: getfield cl : Ljava/lang/String;
/*    */     //   516: invokevirtual equals : (Ljava/lang/Object;)Z
/*    */     //   519: ifeq -> 554
/*    */     //   522: goto -> 565
/*    */     //   525: aload_1
/*    */     //   526: getfield FB0 : [Lf/Qv0;
/*    */     //   529: iload #4
/*    */     //   531: aaload
/*    */     //   532: astore #5
/*    */     //   534: ldc_w 'monster-slot-empty'
/*    */     //   537: dup
/*    */     //   538: astore #6
/*    */     //   540: aload #5
/*    */     //   542: getfield cl : Ljava/lang/String;
/*    */     //   545: invokevirtual equals : (Ljava/lang/Object;)Z
/*    */     //   548: ifeq -> 554
/*    */     //   551: goto -> 565
/*    */     //   554: aload #5
/*    */     //   556: dup
/*    */     //   557: aload #6
/*    */     //   559: invokevirtual Xu : (Ljava/lang/String;)V
/*    */     //   562: invokevirtual cZ : ()V
/*    */     //   565: aload_1
/*    */     //   566: dup
/*    */     //   567: getfield FB0 : [Lf/Qv0;
/*    */     //   570: iload #4
/*    */     //   572: aaload
/*    */     //   573: dup
/*    */     //   574: aconst_null
/*    */     //   575: putfield z4 : Ljava/lang/Object;
/*    */     //   578: invokevirtual zn : ()V
/*    */     //   581: getfield FB0 : [Lf/Qv0;
/*    */     //   584: iload #4
/*    */     //   586: aaload
/*    */     //   587: invokevirtual jj : ()V
/*    */     //   590: iload #4
/*    */     //   592: iconst_1
/*    */     //   593: iadd
/*    */     //   594: i2s
/*    */     //   595: istore #4
/*    */     //   597: goto -> 65
/*    */     //   600: aload_1
/*    */     //   601: getfield rs0 : Z
/*    */     //   604: ifeq -> 18
/*    */     //   607: aload_1
/*    */     //   608: invokevirtual p3 : ()Z
/*    */     //   611: ifeq -> 18
/*    */     //   614: aload_1
/*    */     //   615: iconst_0
/*    */     //   616: invokevirtual Op : (Z)V
/*    */     //   619: goto -> 18
/*    */     //   622: return
/*    */     // Line number table:
/*    */     //   Java source line number -> byte code offset
/*    */     //   #1	-> 42
/*    */     //   #2	-> 54
/*    */     //   #3	-> 58
/*    */     //   #4	-> 75
/*    */     //   #5	-> 99
/*    */     //   #6	-> 102
/*    */     //   #7	-> 116
/*    */     //   #8	-> 124
/*    */     //   #9	-> 142
/*    */     //   #10	-> 145
/*    */     //   #11	-> 151
/*    */     //   #12	-> 154
/*    */     //   #13	-> 164
/*    */     //   #14	-> 167
/*    */     //   #15	-> 188
/*    */     //   #16	-> 211
/*    */     //   #17	-> 214
/*    */     //   #18	-> 228
/*    */     //   #19	-> 231
/*    */     //   #20	-> 256
/*    */     //   #21	-> 291
/*    */     //   #22	-> 307
/*    */     //   #23	-> 310
/*    */     //   #24	-> 330
/*    */     //   #25	-> 346
/*    */     //   #26	-> 349
/*    */     //   #27	-> 364
/*    */     //   #28	-> 380
/*    */     //   #29	-> 383
/*    */     //   #30	-> 393
/*    */     //   #31	-> 409
/*    */     //   #32	-> 412
/*    */     //   #33	-> 433
/*    */     //   #34	-> 445
/*    */     //   #35	-> 448
/*    */     //   #36	-> 451
/*    */     //   #37	-> 460
/*    */     //   #38	-> 513
/*    */     //   #39	-> 516
/*    */     //   #40	-> 526
/*    */     //   #41	-> 542
/*    */     //   #42	-> 545
/*    */     //   #43	-> 567
/*    */     //   #44	-> 575
/*    */     //   #45	-> 578
/*    */     //   #46	-> 581
/*    */   }
/*    */   
/*    */   public final boolean RE0() {
/*    */     return this.rs0;
/*    */   }
/*    */   
/*    */   public final void To(Consumer paramConsumer) {
/*    */     this.gp = paramConsumer;
/*    */   }
/*    */   
/*    */   public final boolean i2(oa0 paramoa0) {
/*    */     int i;
/*    */     if (!this.rs0)
/*    */       return super.i2(paramoa0); 
/*    */     if (B8.Wm0(paramoa0.cz0) && paramoa0.oO()) {
/*    */       int j;
/*    */       if (h1.J20(j = paramoa0.GG0, BM.ni)) {
/*    */         if ((i = this.Qp0) > 0) {
/*    */           this.Qp0 = i - 1;
/*    */           Op(true);
/*    */         } 
/*    */         return true;
/*    */       } 
/*    */       if (h1.J20(j, BM.N70)) {
/*    */         this.Qp0++;
/*    */         Op(true);
/*    */         return true;
/*    */       } 
/*    */       if (h1.J20(j, BM.bC)) {
/*    */         if (this.RJ && pA.Dg0.dk0.U40 != null)
/*    */           return super.i2(i); 
/*    */         Xp(true);
/*    */         return true;
/*    */       } 
/*    */       if (h1.J20(j, BM.lc) && !this.RJ) {
/*    */         xI0();
/*    */         return true;
/*    */       } 
/*    */     } 
/*    */     return super.i2(i);
/*    */   }
/*    */   
/*    */   public final void Xp(boolean paramBoolean) {
/*    */     // Byte code:
/*    */     //   0: aload_0
/*    */     //   1: getfield FB0 : [Lf/Qv0;
/*    */     //   4: aload_0
/*    */     //   5: getfield Qp0 : I
/*    */     //   8: aaload
/*    */     //   9: dup
/*    */     //   10: astore_2
/*    */     //   11: invokevirtual public : ()Lf/j40;
/*    */     //   14: dup
/*    */     //   15: astore_3
/*    */     //   16: ifnonnull -> 20
/*    */     //   19: return
/*    */     //   20: aload_0
/*    */     //   21: new f/B3
/*    */     //   24: dup
/*    */     //   25: astore #4
/*    */     //   27: invokespecial <init> : ()V
/*    */     //   30: new f/Hk0
/*    */     //   33: dup
/*    */     //   34: astore #5
/*    */     //   36: aload_2
/*    */     //   37: sipush #2317
/*    */     //   40: invokestatic OH0 : (I)Ljava/lang/String;
/*    */     //   43: astore #6
/*    */     //   45: <illegal opcode> run : (Lf/Qv0;)Ljava/lang/Runnable;
/*    */     //   50: aload #6
/*    */     //   52: swap
/*    */     //   53: invokespecial <init> : (Ljava/lang/String;Ljava/lang/Runnable;)V
/*    */     //   56: getfield RJ : Z
/*    */     //   59: ifeq -> 77
/*    */     //   62: iload_1
/*    */     //   63: ifeq -> 77
/*    */     //   66: aload #4
/*    */     //   68: getfield aV : Ljava/util/ArrayList;
/*    */     //   71: aload #5
/*    */     //   73: invokevirtual add : (Ljava/lang/Object;)Z
/*    */     //   76: pop
/*    */     //   77: aload_3
/*    */     //   78: aload #4
/*    */     //   80: dup
/*    */     //   81: new f/Hk0
/*    */     //   84: dup
/*    */     //   85: astore_1
/*    */     //   86: aload_0
/*    */     //   87: aload_3
/*    */     //   88: sipush #1801
/*    */     //   91: invokestatic OH0 : (I)Ljava/lang/String;
/*    */     //   94: astore #5
/*    */     //   96: aload_2
/*    */     //   97: <illegal opcode> run : (Lf/NR;Lf/j40;Lf/Qv0;)Ljava/lang/Runnable;
/*    */     //   102: aload #5
/*    */     //   104: swap
/*    */     //   105: invokespecial <init> : (Ljava/lang/String;Ljava/lang/Runnable;)V
/*    */     //   108: getfield aV : Ljava/util/ArrayList;
/*    */     //   111: aload_1
/*    */     //   112: invokevirtual add : (Ljava/lang/Object;)Z
/*    */     //   115: pop
/*    */     //   116: new f/Hk0
/*    */     //   119: dup
/*    */     //   120: astore_1
/*    */     //   121: aload_0
/*    */     //   122: aload_3
/*    */     //   123: sipush #1729
/*    */     //   126: invokestatic OH0 : (I)Ljava/lang/String;
/*    */     //   129: astore #5
/*    */     //   131: <illegal opcode> run : (Lf/NR;Lf/j40;)Ljava/lang/Runnable;
/*    */     //   136: aload #5
/*    */     //   138: swap
/*    */     //   139: invokespecial <init> : (Ljava/lang/String;Ljava/lang/Runnable;)V
/*    */     //   142: getfield aV : Ljava/util/ArrayList;
/*    */     //   145: aload_1
/*    */     //   146: invokevirtual add : (Ljava/lang/Object;)Z
/*    */     //   149: pop
/*    */     //   150: getstatic f/Of.eH : Lf/Of;
/*    */     //   153: aload_3
/*    */     //   154: getfield Zs : Lf/Q90;
/*    */     //   157: invokevirtual p10 : ()S
/*    */     //   160: invokevirtual On0 : (S)Lf/LPT3;
/*    */     //   163: astore_1
/*    */     //   164: getfield Zs : Lf/Q90;
/*    */     //   167: invokevirtual p10 : ()S
/*    */     //   170: ifle -> 217
/*    */     //   173: aload #4
/*    */     //   175: new f/Hk0
/*    */     //   178: dup
/*    */     //   179: astore #5
/*    */     //   181: aload_0
/*    */     //   182: aload_3
/*    */     //   183: aload_1
/*    */     //   184: getfield Iu : I
/*    */     //   187: invokestatic OH0 : (I)Ljava/lang/String;
/*    */     //   190: sipush #1421
/*    */     //   193: swap
/*    */     //   194: invokestatic Go : (ILjava/lang/String;)Ljava/lang/String;
/*    */     //   197: astore_1
/*    */     //   198: <illegal opcode> run : (Lf/NR;Lf/j40;)Ljava/lang/Runnable;
/*    */     //   203: aload_1
/*    */     //   204: swap
/*    */     //   205: invokespecial <init> : (Ljava/lang/String;Ljava/lang/Runnable;)V
/*    */     //   208: getfield aV : Ljava/util/ArrayList;
/*    */     //   211: aload #5
/*    */     //   213: invokevirtual add : (Ljava/lang/Object;)Z
/*    */     //   216: pop
/*    */     //   217: aload_0
/*    */     //   218: getfield Zw0 : Lf/pA;
/*    */     //   221: getfield dk0 : Lf/gO;
/*    */     //   224: ifnull -> 262
/*    */     //   227: aload #4
/*    */     //   229: new f/Hk0
/*    */     //   232: dup
/*    */     //   233: astore_1
/*    */     //   234: aload_2
/*    */     //   235: sipush #2301
/*    */     //   238: invokestatic OH0 : (I)Ljava/lang/String;
/*    */     //   241: astore #5
/*    */     //   243: <illegal opcode> run : (Lf/Qv0;)Ljava/lang/Runnable;
/*    */     //   248: aload #5
/*    */     //   250: swap
/*    */     //   251: invokespecial <init> : (Ljava/lang/String;Ljava/lang/Runnable;)V
/*    */     //   254: getfield aV : Ljava/util/ArrayList;
/*    */     //   257: aload_1
/*    */     //   258: invokevirtual add : (Ljava/lang/Object;)Z
/*    */     //   261: pop
/*    */     //   262: aload_0
/*    */     //   263: getfield Qp0 : I
/*    */     //   266: ifle -> 304
/*    */     //   269: aload #4
/*    */     //   271: new f/Hk0
/*    */     //   274: dup
/*    */     //   275: astore_1
/*    */     //   276: aload_0
/*    */     //   277: sipush #2303
/*    */     //   280: invokestatic OH0 : (I)Ljava/lang/String;
/*    */     //   283: astore #5
/*    */     //   285: <illegal opcode> run : (Lf/NR;)Ljava/lang/Runnable;
/*    */     //   290: aload #5
/*    */     //   292: swap
/*    */     //   293: invokespecial <init> : (Ljava/lang/String;Ljava/lang/Runnable;)V
/*    */     //   296: getfield aV : Ljava/util/ArrayList;
/*    */     //   299: aload_1
/*    */     //   300: invokevirtual add : (Ljava/lang/Object;)Z
/*    */     //   303: pop
/*    */     //   304: aload_0
/*    */     //   305: getfield Qp0 : I
/*    */     //   308: iconst_1
/*    */     //   309: iadd
/*    */     //   310: dup
/*    */     //   311: istore_1
/*    */     //   312: aload_0
/*    */     //   313: getfield FB0 : [Lf/Qv0;
/*    */     //   316: dup
/*    */     //   317: astore #5
/*    */     //   319: arraylength
/*    */     //   320: if_icmpge -> 368
/*    */     //   323: aload #5
/*    */     //   325: iload_1
/*    */     //   326: aaload
/*    */     //   327: invokevirtual public : ()Lf/j40;
/*    */     //   330: ifnull -> 368
/*    */     //   333: aload #4
/*    */     //   335: new f/Hk0
/*    */     //   338: dup
/*    */     //   339: astore_1
/*    */     //   340: aload_0
/*    */     //   341: sipush #2304
/*    */     //   344: invokestatic OH0 : (I)Ljava/lang/String;
/*    */     //   347: astore #5
/*    */     //   349: <illegal opcode> run : (Lf/NR;)Ljava/lang/Runnable;
/*    */     //   354: aload #5
/*    */     //   356: swap
/*    */     //   357: invokespecial <init> : (Ljava/lang/String;Ljava/lang/Runnable;)V
/*    */     //   360: getfield aV : Ljava/util/ArrayList;
/*    */     //   363: aload_1
/*    */     //   364: invokevirtual add : (Ljava/lang/Object;)Z
/*    */     //   367: pop
/*    */     //   368: aload_0
/*    */     //   369: getfield Qp0 : I
/*    */     //   372: ifle -> 410
/*    */     //   375: aload #4
/*    */     //   377: new f/Hk0
/*    */     //   380: dup
/*    */     //   381: astore_1
/*    */     //   382: aload_0
/*    */     //   383: sipush #2313
/*    */     //   386: invokestatic OH0 : (I)Ljava/lang/String;
/*    */     //   389: astore #5
/*    */     //   391: <illegal opcode> run : (Lf/NR;)Ljava/lang/Runnable;
/*    */     //   396: aload #5
/*    */     //   398: swap
/*    */     //   399: invokespecial <init> : (Ljava/lang/String;Ljava/lang/Runnable;)V
/*    */     //   402: getfield aV : Ljava/util/ArrayList;
/*    */     //   405: aload_1
/*    */     //   406: invokevirtual add : (Ljava/lang/Object;)Z
/*    */     //   409: pop
/*    */     //   410: getstatic f/km.a3 : Lf/vh0;
/*    */     //   413: invokevirtual Jr0 : ()Lf/KI;
/*    */     //   416: dup
/*    */     //   417: astore_1
/*    */     //   418: ifnull -> 433
/*    */     //   421: aload_1
/*    */     //   422: invokevirtual XC : ()Z
/*    */     //   425: ifeq -> 433
/*    */     //   428: iconst_1
/*    */     //   429: istore_1
/*    */     //   430: goto -> 435
/*    */     //   433: iconst_0
/*    */     //   434: istore_1
/*    */     //   435: iconst_0
/*    */     //   436: istore #5
/*    */     //   438: iload #5
/*    */     //   440: iconst_4
/*    */     //   441: if_icmpge -> 523
/*    */     //   444: aload_3
/*    */     //   445: getfield Zs : Lf/Q90;
/*    */     //   448: getfield En0 : [S
/*    */     //   451: iload #5
/*    */     //   453: saload
/*    */     //   454: dup
/*    */     //   455: istore #6
/*    */     //   457: iload_1
/*    */     //   458: invokestatic e6 : (SZ)Z
/*    */     //   461: ifne -> 467
/*    */     //   464: goto -> 517
/*    */     //   467: aload #4
/*    */     //   469: new f/Hk0
/*    */     //   472: dup
/*    */     //   473: astore #7
/*    */     //   475: aload_0
/*    */     //   476: iload #6
/*    */     //   478: dup
/*    */     //   479: ldc_w 110000
/*    */     //   482: iadd
/*    */     //   483: invokestatic OH0 : (I)Ljava/lang/String;
/*    */     //   486: sipush #1422
/*    */     //   489: swap
/*    */     //   490: invokestatic Go : (ILjava/lang/String;)Ljava/lang/String;
/*    */     //   493: astore #6
/*    */     //   495: iload_1
/*    */     //   496: aload_3
/*    */     //   497: <illegal opcode> run : (Lf/NR;SZLf/j40;)Ljava/lang/Runnable;
/*    */     //   502: aload #6
/*    */     //   504: swap
/*    */     //   505: invokespecial <init> : (Ljava/lang/String;Ljava/lang/Runnable;)V
/*    */     //   508: getfield aV : Ljava/util/ArrayList;
/*    */     //   511: aload #7
/*    */     //   513: invokevirtual add : (Ljava/lang/Object;)Z
/*    */     //   516: pop
/*    */     //   517: iinc #5, 1
/*    */     //   520: goto -> 438
/*    */     //   523: getstatic f/km.a3 : Lf/vh0;
/*    */     //   526: getfield Ct : Lf/Jo;
/*    */     //   529: dup
/*    */     //   530: astore_0
/*    */     //   531: ifnull -> 628
/*    */     //   534: aload_0
/*    */     //   535: invokevirtual nX : ()S
/*    */     //   538: aload_3
/*    */     //   539: getfield Zs : Lf/Q90;
/*    */     //   542: getfield Cw0 : S
/*    */     //   545: if_icmpne -> 628
/*    */     //   548: aload_3
/*    */     //   549: aload_0
/*    */     //   550: invokevirtual wo : ()B
/*    */     //   553: istore_0
/*    */     //   554: iconst_0
/*    */     //   555: istore_1
/*    */     //   556: invokevirtual s5 : ()B
/*    */     //   559: iconst_1
/*    */     //   560: if_icmpne -> 567
/*    */     //   563: bipush #32
/*    */     //   565: i2b
/*    */     //   566: istore_1
/*    */     //   567: aload_3
/*    */     //   568: getfield Zs : Lf/Q90;
/*    */     //   571: invokevirtual tm0 : ()Z
/*    */     //   574: ifeq -> 583
/*    */     //   577: iload_1
/*    */     //   578: bipush #64
/*    */     //   580: ior
/*    */     //   581: i2b
/*    */     //   582: istore_1
/*    */     //   583: aload_3
/*    */     //   584: getfield Zs : Lf/Q90;
/*    */     //   587: invokevirtual da : ()Z
/*    */     //   590: ifeq -> 599
/*    */     //   593: iload_1
/*    */     //   594: bipush #-128
/*    */     //   596: ior
/*    */     //   597: i2b
/*    */     //   598: istore_1
/*    */     //   599: iload_0
/*    */     //   600: iload_1
/*    */     //   601: if_icmpne -> 628
/*    */     //   604: new f/Hk0
/*    */     //   607: dup
/*    */     //   608: astore_0
/*    */     //   609: sipush #2256
/*    */     //   612: invokestatic OH0 : (I)Ljava/lang/String;
/*    */     //   615: <illegal opcode> run : ()Ljava/lang/Runnable;
/*    */     //   620: swap
/*    */     //   621: swap
/*    */     //   622: invokespecial <init> : (Ljava/lang/String;Ljava/lang/Runnable;)V
/*    */     //   625: goto -> 732
/*    */     //   628: aload_3
/*    */     //   629: getfield Zs : Lf/Q90;
/*    */     //   632: invokevirtual YC : ()Z
/*    */     //   635: ifne -> 676
/*    */     //   638: aload #4
/*    */     //   640: new f/Hk0
/*    */     //   643: dup
/*    */     //   644: astore_0
/*    */     //   645: aload_3
/*    */     //   646: dup
/*    */     //   647: invokevirtual m : ()Ljava/lang/String;
/*    */     //   650: sipush #2262
/*    */     //   653: swap
/*    */     //   654: invokestatic Go : (ILjava/lang/String;)Ljava/lang/String;
/*    */     //   657: astore_1
/*    */     //   658: <illegal opcode> run : (Lf/j40;)Ljava/lang/Runnable;
/*    */     //   663: aload_1
/*    */     //   664: swap
/*    */     //   665: invokespecial <init> : (Ljava/lang/String;Ljava/lang/Runnable;)V
/*    */     //   668: getfield aV : Ljava/util/ArrayList;
/*    */     //   671: aload_0
/*    */     //   672: invokevirtual add : (Ljava/lang/Object;)Z
/*    */     //   675: pop
/*    */     //   676: new f/Hk0
/*    */     //   679: dup
/*    */     //   680: astore_0
/*    */     //   681: aload_2
/*    */     //   682: new java/lang/StringBuilder
/*    */     //   685: dup
/*    */     //   686: invokespecial <init> : ()V
/*    */     //   689: invokestatic getInstance : ()Ljava/text/NumberFormat;
/*    */     //   692: aload_2
/*    */     //   693: invokevirtual fH0 : ()S
/*    */     //   696: iconst_1
/*    */     //   697: iadd
/*    */     //   698: i2l
/*    */     //   699: invokevirtual format : (J)Ljava/lang/String;
/*    */     //   702: sipush #2263
/*    */     //   705: swap
/*    */     //   706: invokestatic Go : (ILjava/lang/String;)Ljava/lang/String;
/*    */     //   709: invokevirtual append : (Ljava/lang/String;)Ljava/lang/StringBuilder;
/*    */     //   712: ldc_w ' Slot'
/*    */     //   715: invokevirtual append : (Ljava/lang/String;)Ljava/lang/StringBuilder;
/*    */     //   718: invokevirtual toString : ()Ljava/lang/String;
/*    */     //   721: astore_1
/*    */     //   722: <illegal opcode> run : (Lf/Qv0;)Ljava/lang/Runnable;
/*    */     //   727: aload_1
/*    */     //   728: swap
/*    */     //   729: invokespecial <init> : (Ljava/lang/String;Ljava/lang/Runnable;)V
/*    */     //   732: aload #4
/*    */     //   734: dup
/*    */     //   735: getfield aV : Ljava/util/ArrayList;
/*    */     //   738: aload_0
/*    */     //   739: invokevirtual add : (Ljava/lang/Object;)Z
/*    */     //   742: pop
/*    */     //   743: new f/Hk0
/*    */     //   746: dup
/*    */     //   747: astore_0
/*    */     //   748: bipush #53
/*    */     //   750: invokestatic OH0 : (I)Ljava/lang/String;
/*    */     //   753: aconst_null
/*    */     //   754: invokespecial <init> : (Ljava/lang/String;Ljava/lang/Runnable;)V
/*    */     //   757: getfield aV : Ljava/util/ArrayList;
/*    */     //   760: aload_0
/*    */     //   761: invokevirtual add : (Ljava/lang/Object;)Z
/*    */     //   764: pop
/*    */     //   765: getstatic f/h1.Wo : Z
/*    */     //   768: ifeq -> 782
/*    */     //   771: bipush #16
/*    */     //   773: aload #4
/*    */     //   775: aload_2
/*    */     //   776: invokestatic YK0 : (ILf/B3;Lf/Qv0;)V
/*    */     //   779: goto -> 790
/*    */     //   782: bipush #8
/*    */     //   784: aload #4
/*    */     //   786: aload_2
/*    */     //   787: invokestatic YK0 : (ILf/B3;Lf/Qv0;)V
/*    */     //   790: return
/*    */     // Line number table:
/*    */     //   Java source line number -> byte code offset
/*    */     //   #1	-> 68
/*    */     //   #2	-> 81
/*    */     //   #3	-> 108
/*    */     //   #4	-> 116
/*    */     //   #5	-> 142
/*    */     //   #6	-> 150
/*    */     //   #7	-> 154
/*    */     //   #8	-> 157
/*    */     //   #9	-> 164
/*    */     //   #10	-> 167
/*    */     //   #11	-> 184
/*    */     //   #12	-> 194
/*    */     //   #13	-> 208
/*    */     //   #14	-> 218
/*    */     //   #15	-> 221
/*    */     //   #16	-> 229
/*    */     //   #17	-> 254
/*    */     //   #18	-> 263
/*    */     //   #19	-> 296
/*    */     //   #20	-> 305
/*    */     //   #21	-> 360
/*    */     //   #22	-> 369
/*    */     //   #23	-> 402
/*    */     //   #24	-> 410
/*    */     //   #25	-> 445
/*    */     //   #26	-> 448
/*    */     //   #27	-> 453
/*    */     //   #28	-> 458
/*    */     //   #29	-> 508
/*    */     //   #30	-> 523
/*    */     //   #31	-> 526
/*    */     //   #32	-> 535
/*    */     //   #33	-> 539
/*    */     //   #34	-> 542
/*    */     //   #35	-> 550
/*    */     //   #36	-> 556
/*    */     //   #37	-> 568
/*    */     //   #38	-> 571
/*    */     //   #39	-> 584
/*    */     //   #40	-> 587
/*    */     //   #41	-> 604
/*    */     //   #42	-> 629
/*    */     //   #43	-> 640
/*    */     //   #44	-> 668
/*    */     //   #45	-> 676
/*    */     //   #46	-> 735
/*    */     //   #47	-> 743
/*    */     //   #48	-> 757
/*    */     //   #49	-> 765
/*    */   }
/*    */   
/*    */   public final void xI0() {
/*    */     this.rs0 = false;
/*    */     xf0();
/*    */     super.xI0();
/*    */     gO gO;
/*    */     if ((gO = this.Zw0.dk0) != null)
/*    */       VA0.c90(this); 
/*    */   }
/*    */   
/*    */   public final void V90(throws paramthrows) {
/*    */     // Byte code:
/*    */     //   0: getstatic f/km.u4 : Lf/R8;
/*    */     //   3: ifnonnull -> 9
/*    */     //   6: goto -> 79
/*    */     //   9: getstatic f/aq0.Yz0 : [Lf/aq0;
/*    */     //   12: astore_2
/*    */     //   13: iconst_3
/*    */     //   14: istore_3
/*    */     //   15: iconst_0
/*    */     //   16: istore #4
/*    */     //   18: iload #4
/*    */     //   20: iload_3
/*    */     //   21: if_icmpge -> 79
/*    */     //   24: aload_2
/*    */     //   25: iload #4
/*    */     //   27: aaload
/*    */     //   28: getstatic f/km.u4 : Lf/R8;
/*    */     //   31: swap
/*    */     //   32: invokevirtual s40 : (Lf/aq0;)Lf/Uc0;
/*    */     //   35: dup
/*    */     //   36: astore #5
/*    */     //   38: ifnull -> 73
/*    */     //   41: aload #5
/*    */     //   43: getfield ID0 : Z
/*    */     //   46: ifeq -> 61
/*    */     //   49: aload #5
/*    */     //   51: iconst_0
/*    */     //   52: putfield ID0 : Z
/*    */     //   55: iconst_1
/*    */     //   56: istore #5
/*    */     //   58: goto -> 64
/*    */     //   61: iconst_0
/*    */     //   62: istore #5
/*    */     //   64: iload #5
/*    */     //   66: ifeq -> 73
/*    */     //   69: iconst_1
/*    */     //   70: goto -> 80
/*    */     //   73: iinc #4, 1
/*    */     //   76: goto -> 18
/*    */     //   79: iconst_0
/*    */     //   80: ifeq -> 87
/*    */     //   83: aload_0
/*    */     //   84: invokevirtual xf0 : ()V
/*    */     //   87: aload_0
/*    */     //   88: invokevirtual p3 : ()Z
/*    */     //   91: ifne -> 138
/*    */     //   94: aload_0
/*    */     //   95: getfield FB0 : [Lf/Qv0;
/*    */     //   98: dup
/*    */     //   99: astore_2
/*    */     //   100: arraylength
/*    */     //   101: istore_3
/*    */     //   102: iconst_0
/*    */     //   103: istore #4
/*    */     //   105: iload #4
/*    */     //   107: iload_3
/*    */     //   108: if_icmpge -> 138
/*    */     //   111: aload_2
/*    */     //   112: iload #4
/*    */     //   114: aaload
/*    */     //   115: getfield cl : Ljava/lang/String;
/*    */     //   118: ldc_w 'monster-slot-selected'
/*    */     //   121: swap
/*    */     //   122: invokevirtual equals : (Ljava/lang/Object;)Z
/*    */     //   125: ifeq -> 132
/*    */     //   128: aload_0
/*    */     //   129: invokevirtual xf0 : ()V
/*    */     //   132: iinc #4, 1
/*    */     //   135: goto -> 105
/*    */     //   138: aload_0
/*    */     //   139: aload_1
/*    */     //   140: invokespecial V90 : (Lf/throws;)V
/*    */     //   143: return
/*    */     // Line number table:
/*    */     //   Java source line number -> byte code offset
/*    */     //   #1	-> 0
/*    */     //   #2	-> 43
/*    */     //   #3	-> 84
/*    */     //   #4	-> 115
/*    */     //   #5	-> 118
/*    */   }
/*    */   
/*    */   public final void LM(throws paramthrows) {
/*    */     P3.lF.gL(this);
/*    */     xf0();
/*    */   }
/*    */   
/*    */   public final void ED0(throws paramthrows) {
/*    */     synchronized (P3.lF) {
/*    */       ConcurrentHashMap<?, ?> concurrentHashMap;
/*    */       if ((concurrentHashMap = P3.bx).containsKey(NR.class))
/*    */         ((List)concurrentHashMap.get(NR.class)).remove(this); 
/*    */       return;
/*    */     } 
/*    */   } }


/* Location:              /Users/vnnsnnt/Documents/Codespace/JavaWorkspace/RedTrainer/src/main/java/org/trainer/client/PokeMMO.jar!/f/NR.class
 * Java compiler version: 8 (52.0)
 * JD-Core Version:       1.1.3
 */