/*    */ package f;
/*    */ public final class NuL extends Ip { public static final pRn fL0 = new pRn(855638015); public dQ T10; public final wg0 To0; public final Hu0 fL; public final j4 hU; public NK0 kv0; public O0 Th0;
/*    */   public final Ut0 ke0 = new Ut0();
/*    */   public final Ut0 CS = new Ut0();
/*    */   
/*  6 */   public static int je0(Y paramY1, Y paramY2) { WD wD2 = yk0.cw().mP(paramY2.Bp0.kx0); WD wD1; if ((wD1 = yk0.cw().mP(paramY1.Bp0.kx0)) == null || wD2 == null)
/*    */     {
/*    */       
/*  9 */       return 0; }  Ht0 ht0 = wD1.Wt(null, null); return Ht0.Rs0.compare(ht0, wD2.Wt(null, null)); } public ArrayList PO = new ArrayList(); public Ut0 Y60 = new Ut0(); public rS H40; public ArrayList v60 = new ArrayList(); public ArrayList Sj = new ArrayList(); public ArrayList NL = new ArrayList(); public Y[] Hu; public final ck u0; public final Ip Dn; public NuL(wg0 paramwg0, ck paramck, Hu0 paramHu0, Y[] paramArrayOfY) { Xu("dialoglayout"); this.To0 = paramwg0; this.fL = paramHu0; this.Hu = paramArrayOfY; this.u0 = paramck; this.Dn = new Ip(); this.T10 = new dQ(""); this.hU = new j4(this); (new rS()).zG0(2); (new rS()).Gz0(this.T10); (this.H40 = new rS()).zG0(2); FK(); rK0(mE0().cOM8(new U90[] { d7().Mg(new JG0[] { this.H40 }) })); WN(d7().cOM8(new U90[] { mE0().Mg(new JG0[] { this.H40 }) })); } public static void I6(NuL paramNuL, NK0 paramNK0, oa0 paramoa0) { paramNuL.getClass(); pRn pRn1 = pRn.WHITE; xJ0 xJ0; SE0[] arrayOfSE02; int j; byte b; for (j = (arrayOfSE02 = (xJ0 = pA.Dg0.WH).sN).length, b = 0; b < j; ) { SE0 sE0; if ((sE0 = arrayOfSE02[b]).db0 == null) { I i1; Ja0 ja0; this(sE0); this(ja0, pRn.WHITE); sE0.db0 = i1; }  sE0
/* 10 */         .db0
/* 11 */         .sz(pRn1, 100); b++; }  boolean bool = false; SE0[] arrayOfSE01;
/* 12 */     for (int i = (arrayOfSE01 = xJ0.sN).length; j < i; ) { (arrayOfSE01[j])
/* 13 */         .O
/* 14 */         .gf0(JG0.e30, bool); j++; }  if (paramNuL
/* 15 */       .kv0 != null) { paramNuL.Tx(paramoa0); O0 o02; if ((o02 = paramNuL.Th0) != null) { o02.Tm0(paramNK0.pRn()); }
/*    */       else
/* 17 */       { int k = paramoa0.aK;
/*    */         
/* 19 */         JG0 jG0 = js.vu0.Va0(k, paramoa0.gk0); pA pA; wu wu;
/* 20 */         if ((pA = pA.Dg0) != null && (
/* 21 */           wu = pA.TF) != null && wu
/* 22 */           .b00 == jG0
/* 23 */           .fr0) { wu
/* 24 */             .Vw(paramNK0.pRn()); } else { Y y; if ((jG0 = paramNuL.TG0(jG0)) != null && (y = paramNK0.pRn()) != null) { ((kC0)jG0)
/* 25 */               .cv0
/*    */ 
/*    */ 
/*    */ 
/*    */ 
/*    */ 
/*    */ 
/*    */               
/* 33 */               .Be0(((kC0)jG0).cv0.F2.PH0.toString() + "{I:" + y.Lh.Wy + "}", false);
/* 34 */             VA0.c90(((kC0)jG0).cv0); }  }  }  paramNK0 = null; O0 o01;
/* 35 */       if ((o01 = paramNuL.Th0) != null) { if (o01 != null) o01.xJ(false, false);  paramNuL.Th0 = (O0)paramNK0; }  paramNuL
/* 36 */         .kv0 = null; }
/*    */      }
/*    */ 
/*    */   
/*    */   public final JG0 FK() {
/*    */     this.NL.clear();
/*    */     String str;
/*    */     if ((str = LF.Ll0(this.To0.fJ.F2.toString(), true)).isEmpty()) {
/*    */       this.H40.Gz0(Zf(new ArrayList(Arrays.asList((Object[])this.Hu))));
/*    */     } else {
/*    */       Y[] arrayOfY;
/*    */       int i;
/*    */       byte b;
/*    */       for (i = (arrayOfY = this.Hu).length, b = 0; b < i; ) {
/*    */         Y y;
/*    */         if (LF.qS((y = arrayOfY[b]).JG0(), str))
/*    */           this.NL.add(y); 
/*    */         b++;
/*    */       } 
/*    */       Collections.sort(this.NL);
/*    */       this.H40.Gz0(Zf(this.NL));
/*    */     } 
/*    */     return !this.PO.isEmpty() ? this.PO.get(0) : null;
/*    */   }
/*    */   
/*    */   public final void d40() {
/*    */     if (!km.XU()) {
/*    */       uh0(448, 180);
/*    */       kN(10, 10, 10, 10);
/*    */     } 
/*    */     super.d40();
/*    */   }
/*    */   
/*    */   public final void P30(ArrayList paramArrayList1, ArrayList paramArrayList2, Ip paramIp, cr0 paramcr0, g0 paramg0) {
/*    */     if (paramArrayList1.isEmpty())
/*    */       return; 
/*    */     Un[] arrayOfUn = (Un[])paramArrayList1.toArray((Object[])new Un[0]);
/*    */     this.ke0.A3(this.ke0.ir0, this);
/*    */     Y[] arrayOfY = (Y[])paramArrayList2.toArray((Object[])new Y[0]);
/*    */     this.CS.A3(this.CS.ir0, arrayOfY);
/*    */     paramcr0.ee0(paramIp.AUX((JG0[])this));
/*    */     paramg0.ee0(paramIp.vo0((JG0[])this));
/*    */     paramArrayList1.clear();
/*    */     paramArrayList2.clear();
/*    */   }
/*    */   
/*    */   public final void Tx(oa0 paramoa0) {
/*    */     int i = paramoa0.aK;
/*    */     JG0 jG0;
/*    */     pA pA;
/*    */     O0 o0;
/*    */     if (this.kv0 != null && (pA = pA.Dg0) != null && jG0 = pA.Va0(i, paramoa0.gk0) instanceof O0 && ((O0)(jG0 = jG0)).zz0 && jG0 != (o0 = this.Th0)) {
/*    */       if (o0 != null)
/*    */         o0.xJ(false, false); 
/*    */       this.Th0 = (O0)jG0;
/*    */       jG0.xJ(true, true);
/*    */     } 
/*    */   }
/*    */   
/*    */   public final kC0 TG0(JG0 paramJG0) {
/*    */     if (paramJG0 instanceof kC0)
/*    */       return (kC0)paramJG0; 
/*    */     if ((paramJG0 = paramJG0.fr0) != null)
/*    */       return TG0(paramJG0); 
/*    */     return null;
/*    */   }
/*    */   
/*    */   public final Ip Zf(ArrayList paramArrayList) {
/*    */     // Byte code:
/*    */     //   0: aload_0
/*    */     //   1: dup
/*    */     //   2: dup
/*    */     //   3: dup2
/*    */     //   4: dup2
/*    */     //   5: dup2
/*    */     //   6: getfield v60 : Ljava/util/ArrayList;
/*    */     //   9: invokevirtual clear : ()V
/*    */     //   12: getfield Sj : Ljava/util/ArrayList;
/*    */     //   15: invokevirtual clear : ()V
/*    */     //   18: getfield CS : Lf/Ut0;
/*    */     //   21: invokevirtual clear : ()V
/*    */     //   24: getfield PO : Ljava/util/ArrayList;
/*    */     //   27: invokevirtual clear : ()V
/*    */     //   30: getfield ke0 : Lf/Ut0;
/*    */     //   33: invokevirtual clear : ()V
/*    */     //   36: getfield Dn : Lf/Ip;
/*    */     //   39: invokevirtual gx : ()V
/*    */     //   42: getfield Dn : Lf/Ip;
/*    */     //   45: dup
/*    */     //   46: invokestatic Ur : (Lf/Ip;Lf/Ip;)Lf/cr0;
/*    */     //   49: astore_2
/*    */     //   50: getfield Dn : Lf/Ip;
/*    */     //   53: dup
/*    */     //   54: invokestatic X60 : (Lf/Ip;Lf/Ip;)Lf/g0;
/*    */     //   57: astore_3
/*    */     //   58: getstatic f/km.u4 : Lf/R8;
/*    */     //   61: getfield Ld : Lf/P4;
/*    */     //   64: astore #4
/*    */     //   66: iconst_0
/*    */     //   67: istore #5
/*    */     //   69: iconst_0
/*    */     //   70: istore #6
/*    */     //   72: getstatic f/Ht0.P00 : Lf/Ht0;
/*    */     //   75: astore #7
/*    */     //   77: iconst_0
/*    */     //   78: istore #8
/*    */     //   80: getfield fL : Lf/Hu0;
/*    */     //   83: getstatic f/Hu0.JV : Lf/Hu0;
/*    */     //   86: dup
/*    */     //   87: astore #9
/*    */     //   89: if_acmpne -> 98
/*    */     //   92: iconst_2
/*    */     //   93: istore #10
/*    */     //   95: goto -> 102
/*    */     //   98: bipush #11
/*    */     //   100: istore #10
/*    */     //   102: invokestatic XU : ()Z
/*    */     //   105: ifeq -> 111
/*    */     //   108: iconst_1
/*    */     //   109: istore #10
/*    */     //   111: aload_0
/*    */     //   112: new f/Ut0
/*    */     //   115: dup
/*    */     //   116: astore #11
/*    */     //   118: invokespecial <init> : ()V
/*    */     //   121: getfield fL : Lf/Hu0;
/*    */     //   124: aload #9
/*    */     //   126: if_acmpne -> 222
/*    */     //   129: aload_1
/*    */     //   130: dup
/*    */     //   131: <illegal opcode> compare : ()Ljava/util/Comparator;
/*    */     //   136: invokestatic sort : (Ljava/util/List;Ljava/util/Comparator;)V
/*    */     //   139: new java/util/ArrayList
/*    */     //   142: dup
/*    */     //   143: astore #9
/*    */     //   145: invokespecial <init> : ()V
/*    */     //   148: invokevirtual iterator : ()Ljava/util/Iterator;
/*    */     //   151: astore #12
/*    */     //   153: aload #12
/*    */     //   155: invokeinterface hasNext : ()Z
/*    */     //   160: ifeq -> 196
/*    */     //   163: aload #12
/*    */     //   165: invokeinterface next : ()Ljava/lang/Object;
/*    */     //   170: checkcast f/Y
/*    */     //   173: dup
/*    */     //   174: astore #13
/*    */     //   176: getfield Bp0 : Lf/LPT3;
/*    */     //   179: invokevirtual bj : ()Z
/*    */     //   182: ifeq -> 153
/*    */     //   185: aload #9
/*    */     //   187: aload #13
/*    */     //   189: invokevirtual add : (Ljava/lang/Object;)Z
/*    */     //   192: pop
/*    */     //   193: goto -> 153
/*    */     //   196: aload #9
/*    */     //   198: invokevirtual size : ()I
/*    */     //   201: ifle -> 226
/*    */     //   204: aload_1
/*    */     //   205: dup
/*    */     //   206: aload #9
/*    */     //   208: invokevirtual removeAll : (Ljava/util/Collection;)Z
/*    */     //   211: pop
/*    */     //   212: iconst_0
/*    */     //   213: aload #9
/*    */     //   215: invokevirtual addAll : (ILjava/util/Collection;)Z
/*    */     //   218: pop
/*    */     //   219: goto -> 226
/*    */     //   222: aload_1
/*    */     //   223: invokestatic sort : (Ljava/util/List;)V
/*    */     //   226: aload_1
/*    */     //   227: invokevirtual iterator : ()Ljava/util/Iterator;
/*    */     //   230: astore_1
/*    */     //   231: aload_1
/*    */     //   232: invokeinterface hasNext : ()Z
/*    */     //   237: ifeq -> 1318
/*    */     //   240: aload #4
/*    */     //   242: aload_1
/*    */     //   243: invokeinterface next : ()Ljava/lang/Object;
/*    */     //   248: checkcast f/Y
/*    */     //   251: dup
/*    */     //   252: astore #9
/*    */     //   254: getfield Lh : Lf/nH0;
/*    */     //   257: dup
/*    */     //   258: astore #12
/*    */     //   260: getfield Sf0 : S
/*    */     //   263: istore #13
/*    */     //   265: ifnull -> 346
/*    */     //   268: aload #12
/*    */     //   270: getfield Wy : I
/*    */     //   273: istore #12
/*    */     //   275: iconst_0
/*    */     //   276: istore #14
/*    */     //   278: iload #14
/*    */     //   280: aload #4
/*    */     //   282: getfield mR : [[Lf/Rd0;
/*    */     //   285: aload #4
/*    */     //   287: getfield QO : B
/*    */     //   290: aaload
/*    */     //   291: dup
/*    */     //   292: astore #15
/*    */     //   294: arraylength
/*    */     //   295: if_icmpge -> 335
/*    */     //   298: aload #15
/*    */     //   300: iload #14
/*    */     //   302: aaload
/*    */     //   303: dup
/*    */     //   304: astore #15
/*    */     //   306: ifnull -> 329
/*    */     //   309: aload #15
/*    */     //   311: getfield aP : I
/*    */     //   314: iload #12
/*    */     //   316: if_icmpne -> 329
/*    */     //   319: aload #15
/*    */     //   321: getfield Lv : S
/*    */     //   324: istore #12
/*    */     //   326: goto -> 338
/*    */     //   329: iinc #14, 1
/*    */     //   332: goto -> 278
/*    */     //   335: iconst_0
/*    */     //   336: istore #12
/*    */     //   338: iload #13
/*    */     //   340: iload #12
/*    */     //   342: isub
/*    */     //   343: i2s
/*    */     //   344: istore #13
/*    */     //   346: iload #13
/*    */     //   348: iconst_1
/*    */     //   349: if_icmpge -> 355
/*    */     //   352: goto -> 231
/*    */     //   355: aload_0
/*    */     //   356: getfield fL : Lf/Hu0;
/*    */     //   359: getstatic f/Hu0.JV : Lf/Hu0;
/*    */     //   362: dup
/*    */     //   363: astore #12
/*    */     //   365: if_acmpne -> 637
/*    */     //   368: aload #9
/*    */     //   370: getfield Bp0 : Lf/LPT3;
/*    */     //   373: invokevirtual bj : ()Z
/*    */     //   376: ifeq -> 485
/*    */     //   379: iload #8
/*    */     //   381: ifne -> 787
/*    */     //   384: aload_3
/*    */     //   385: aload_0
/*    */     //   386: dup
/*    */     //   387: dup
/*    */     //   388: dup2
/*    */     //   389: getfield v60 : Ljava/util/ArrayList;
/*    */     //   392: astore #5
/*    */     //   394: getfield Sj : Ljava/util/ArrayList;
/*    */     //   397: astore #8
/*    */     //   399: getfield Dn : Lf/Ip;
/*    */     //   402: astore #14
/*    */     //   404: aload #5
/*    */     //   406: aload #8
/*    */     //   408: aload #14
/*    */     //   410: aload_2
/*    */     //   411: aload_3
/*    */     //   412: invokevirtual P30 : (Ljava/util/ArrayList;Ljava/util/ArrayList;Lf/Ip;Lf/cr0;Lf/g0;)V
/*    */     //   415: iconst_0
/*    */     //   416: istore #5
/*    */     //   418: getfield Dn : Lf/Ip;
/*    */     //   421: dup
/*    */     //   422: aload_2
/*    */     //   423: swap
/*    */     //   424: new f/dQ
/*    */     //   427: dup
/*    */     //   428: dup
/*    */     //   429: astore #8
/*    */     //   431: sipush #10798
/*    */     //   434: invokestatic OH0 : (I)Ljava/lang/String;
/*    */     //   437: astore #14
/*    */     //   439: invokespecial <init> : ()V
/*    */     //   442: aload #14
/*    */     //   444: invokevirtual E1 : (Ljava/lang/String;)V
/*    */     //   447: iconst_1
/*    */     //   448: anewarray f/JG0
/*    */     //   451: dup
/*    */     //   452: iconst_0
/*    */     //   453: aload #8
/*    */     //   455: aastore
/*    */     //   456: invokevirtual AUX : ([Lf/JG0;)Lf/U90;
/*    */     //   459: invokevirtual ee0 : (Lf/U90;)Lf/U90;
/*    */     //   462: pop
/*    */     //   463: iconst_1
/*    */     //   464: anewarray f/JG0
/*    */     //   467: dup
/*    */     //   468: iconst_0
/*    */     //   469: aload #8
/*    */     //   471: aastore
/*    */     //   472: invokevirtual vo0 : ([Lf/JG0;)Lf/U90;
/*    */     //   475: invokevirtual ee0 : (Lf/U90;)Lf/U90;
/*    */     //   478: pop
/*    */     //   479: iconst_1
/*    */     //   480: istore #8
/*    */     //   482: goto -> 787
/*    */     //   485: aload #7
/*    */     //   487: invokestatic cw : ()Lf/yk0;
/*    */     //   490: aload #9
/*    */     //   492: getfield Bp0 : Lf/LPT3;
/*    */     //   495: getfield kx0 : S
/*    */     //   498: invokevirtual mP : (S)Lf/WD;
/*    */     //   501: aload #9
/*    */     //   503: getfield Lh : Lf/nH0;
/*    */     //   506: getfield p1 : S
/*    */     //   509: invokestatic toString : (I)Ljava/lang/String;
/*    */     //   512: invokestatic requireNonNull : (Ljava/lang/Object;Ljava/lang/String;)Ljava/lang/Object;
/*    */     //   515: checkcast f/WD
/*    */     //   518: aconst_null
/*    */     //   519: aconst_null
/*    */     //   520: invokevirtual Wt : (Lf/Q90;Lf/Mx;)Lf/Ht0;
/*    */     //   523: dup
/*    */     //   524: astore #14
/*    */     //   526: if_acmpeq -> 787
/*    */     //   529: aload_3
/*    */     //   530: aload_0
/*    */     //   531: dup
/*    */     //   532: dup
/*    */     //   533: dup2
/*    */     //   534: getfield v60 : Ljava/util/ArrayList;
/*    */     //   537: astore #5
/*    */     //   539: getfield Sj : Ljava/util/ArrayList;
/*    */     //   542: astore #7
/*    */     //   544: getfield Dn : Lf/Ip;
/*    */     //   547: astore #15
/*    */     //   549: aload #5
/*    */     //   551: aload #7
/*    */     //   553: aload #15
/*    */     //   555: aload_2
/*    */     //   556: aload_3
/*    */     //   557: invokevirtual P30 : (Ljava/util/ArrayList;Ljava/util/ArrayList;Lf/Ip;Lf/cr0;Lf/g0;)V
/*    */     //   560: iconst_0
/*    */     //   561: istore #5
/*    */     //   563: getfield Dn : Lf/Ip;
/*    */     //   566: dup
/*    */     //   567: aload_2
/*    */     //   568: swap
/*    */     //   569: new f/dQ
/*    */     //   572: dup
/*    */     //   573: dup
/*    */     //   574: astore #7
/*    */     //   576: aload #14
/*    */     //   578: invokevirtual mn0 : ()Ljava/lang/String;
/*    */     //   581: sipush #10799
/*    */     //   584: swap
/*    */     //   585: invokestatic Go : (ILjava/lang/String;)Ljava/lang/String;
/*    */     //   588: astore #15
/*    */     //   590: invokespecial <init> : ()V
/*    */     //   593: aload #15
/*    */     //   595: invokevirtual E1 : (Ljava/lang/String;)V
/*    */     //   598: iconst_1
/*    */     //   599: anewarray f/JG0
/*    */     //   602: dup
/*    */     //   603: iconst_0
/*    */     //   604: aload #7
/*    */     //   606: aastore
/*    */     //   607: invokevirtual AUX : ([Lf/JG0;)Lf/U90;
/*    */     //   610: invokevirtual ee0 : (Lf/U90;)Lf/U90;
/*    */     //   613: pop
/*    */     //   614: iconst_1
/*    */     //   615: anewarray f/JG0
/*    */     //   618: dup
/*    */     //   619: iconst_0
/*    */     //   620: aload #7
/*    */     //   622: aastore
/*    */     //   623: invokevirtual vo0 : ([Lf/JG0;)Lf/U90;
/*    */     //   626: invokevirtual ee0 : (Lf/U90;)Lf/U90;
/*    */     //   629: pop
/*    */     //   630: aload #14
/*    */     //   632: astore #7
/*    */     //   634: goto -> 787
/*    */     //   637: iload #6
/*    */     //   639: aload #9
/*    */     //   641: getfield Bp0 : Lf/LPT3;
/*    */     //   644: invokevirtual wf0 : ()I
/*    */     //   647: if_icmpeq -> 787
/*    */     //   650: aload #9
/*    */     //   652: aload_0
/*    */     //   653: dup
/*    */     //   654: dup2
/*    */     //   655: getfield v60 : Ljava/util/ArrayList;
/*    */     //   658: astore #5
/*    */     //   660: getfield Sj : Ljava/util/ArrayList;
/*    */     //   663: astore #6
/*    */     //   665: getfield Dn : Lf/Ip;
/*    */     //   668: astore #14
/*    */     //   670: aload #5
/*    */     //   672: aload #6
/*    */     //   674: aload #14
/*    */     //   676: aload_2
/*    */     //   677: aload_3
/*    */     //   678: invokevirtual P30 : (Ljava/util/ArrayList;Ljava/util/ArrayList;Lf/Ip;Lf/cr0;Lf/g0;)V
/*    */     //   681: iconst_0
/*    */     //   682: istore #5
/*    */     //   684: getfield Bp0 : Lf/LPT3;
/*    */     //   687: invokevirtual wf0 : ()I
/*    */     //   690: dup
/*    */     //   691: istore #6
/*    */     //   693: aload_0
/*    */     //   694: getfield Dn : Lf/Ip;
/*    */     //   697: astore #14
/*    */     //   699: sipush #10000
/*    */     //   702: iadd
/*    */     //   703: istore #15
/*    */     //   705: getstatic f/Ml0.nW : Lf/Ut0;
/*    */     //   708: iload #15
/*    */     //   710: invokevirtual return : (I)Z
/*    */     //   713: ifeq -> 787
/*    */     //   716: iload #6
/*    */     //   718: sipush #800
/*    */     //   721: if_icmplt -> 727
/*    */     //   724: goto -> 787
/*    */     //   727: aload_3
/*    */     //   728: aload #14
/*    */     //   730: aload_2
/*    */     //   731: aload #14
/*    */     //   733: new f/dQ
/*    */     //   736: dup
/*    */     //   737: dup
/*    */     //   738: astore #14
/*    */     //   740: iload #15
/*    */     //   742: invokestatic OH0 : (I)Ljava/lang/String;
/*    */     //   745: astore #15
/*    */     //   747: invokespecial <init> : ()V
/*    */     //   750: aload #15
/*    */     //   752: invokevirtual E1 : (Ljava/lang/String;)V
/*    */     //   755: iconst_1
/*    */     //   756: anewarray f/JG0
/*    */     //   759: dup
/*    */     //   760: iconst_0
/*    */     //   761: aload #14
/*    */     //   763: aastore
/*    */     //   764: invokevirtual AUX : ([Lf/JG0;)Lf/U90;
/*    */     //   767: invokevirtual ee0 : (Lf/U90;)Lf/U90;
/*    */     //   770: pop
/*    */     //   771: iconst_1
/*    */     //   772: anewarray f/JG0
/*    */     //   775: dup
/*    */     //   776: iconst_0
/*    */     //   777: aload #14
/*    */     //   779: aastore
/*    */     //   780: invokevirtual vo0 : ([Lf/JG0;)Lf/U90;
/*    */     //   783: invokevirtual ee0 : (Lf/U90;)Lf/U90;
/*    */     //   786: pop
/*    */     //   787: aload_0
/*    */     //   788: getfield Y60 : Lf/Ut0;
/*    */     //   791: aload #9
/*    */     //   793: getfield Lh : Lf/nH0;
/*    */     //   796: getfield Wy : I
/*    */     //   799: invokevirtual Z6 : (I)Ljava/lang/Object;
/*    */     //   802: checkcast f/Un
/*    */     //   805: dup
/*    */     //   806: astore #14
/*    */     //   808: ifnonnull -> 1033
/*    */     //   811: aload_0
/*    */     //   812: getfield fL : Lf/Hu0;
/*    */     //   815: aload #12
/*    */     //   817: if_acmpne -> 919
/*    */     //   820: aload #9
/*    */     //   822: new f/Yr
/*    */     //   825: dup
/*    */     //   826: astore #12
/*    */     //   828: aload_0
/*    */     //   829: dup
/*    */     //   830: getfield To0 : Lf/wg0;
/*    */     //   833: astore #14
/*    */     //   835: getfield u0 : Lf/ck;
/*    */     //   838: aload #9
/*    */     //   840: aload #14
/*    */     //   842: invokespecial <init> : (Lf/ck;Lf/Y;Lf/wg0;)V
/*    */     //   845: getfield Bp0 : Lf/LPT3;
/*    */     //   848: getfield kx0 : S
/*    */     //   851: ifle -> 895
/*    */     //   854: aload #12
/*    */     //   856: new java/lang/StringBuilder
/*    */     //   859: dup
/*    */     //   860: iload #13
/*    */     //   862: swap
/*    */     //   863: invokespecial <init> : ()V
/*    */     //   866: invokevirtual append : (I)Ljava/lang/StringBuilder;
/*    */     //   869: ldc_w 'x '
/*    */     //   872: invokevirtual append : (Ljava/lang/String;)Ljava/lang/StringBuilder;
/*    */     //   875: aload #9
/*    */     //   877: getfield Bp0 : Lf/LPT3;
/*    */     //   880: getfield Iu : I
/*    */     //   883: invokestatic OH0 : (I)Ljava/lang/String;
/*    */     //   886: invokevirtual append : (Ljava/lang/String;)Ljava/lang/StringBuilder;
/*    */     //   889: invokevirtual toString : ()Ljava/lang/String;
/*    */     //   892: invokevirtual s6 : (Ljava/lang/String;)V
/*    */     //   895: aload #12
/*    */     //   897: new f/vE
/*    */     //   900: dup
/*    */     //   901: astore #13
/*    */     //   903: aload_0
/*    */     //   904: invokespecial <init> : (Lf/NuL;)V
/*    */     //   907: aload #13
/*    */     //   909: putfield om0 : Lf/vE;
/*    */     //   912: aload #12
/*    */     //   914: astore #14
/*    */     //   916: goto -> 964
/*    */     //   919: new f/mm
/*    */     //   922: dup
/*    */     //   923: astore #12
/*    */     //   925: aload_0
/*    */     //   926: dup
/*    */     //   927: getfield To0 : Lf/wg0;
/*    */     //   930: astore #14
/*    */     //   932: getfield u0 : Lf/ck;
/*    */     //   935: aload #14
/*    */     //   937: swap
/*    */     //   938: aload #9
/*    */     //   940: iload #13
/*    */     //   942: invokespecial <init> : (Lf/wg0;Lf/ck;Lf/Y;S)V
/*    */     //   945: invokestatic XU : ()Z
/*    */     //   948: ifne -> 960
/*    */     //   951: aload #12
/*    */     //   953: aload_0
/*    */     //   954: getfield hU : Lf/j4;
/*    */     //   957: putfield vr0 : Lf/j4;
/*    */     //   960: aload #12
/*    */     //   962: astore #14
/*    */     //   964: invokestatic Nr : ()Z
/*    */     //   967: ifeq -> 1221
/*    */     //   970: aload #9
/*    */     //   972: aload #14
/*    */     //   974: iconst_1
/*    */     //   975: putfield jl : I
/*    */     //   978: getfield Bp0 : Lf/LPT3;
/*    */     //   981: dup
/*    */     //   982: astore #12
/*    */     //   984: getfield c3 : Lf/wc;
/*    */     //   987: ifnull -> 1016
/*    */     //   990: new f/pQ
/*    */     //   993: dup
/*    */     //   994: astore #13
/*    */     //   996: aload #12
/*    */     //   998: aload #9
/*    */     //   1000: getfield Lh : Lf/nH0;
/*    */     //   1003: getfield Nj : B
/*    */     //   1006: iconst_1
/*    */     //   1007: iconst_1
/*    */     //   1008: ldc ''
/*    */     //   1010: invokespecial <init> : (Lf/LPT3;BZZLjava/lang/String;)V
/*    */     //   1013: goto -> 1210
/*    */     //   1016: aload #14
/*    */     //   1018: dup
/*    */     //   1019: aload #12
/*    */     //   1021: invokestatic kh0 : (Lf/LPT3;)Ljava/lang/String;
/*    */     //   1024: putfield z4 : Ljava/lang/Object;
/*    */     //   1027: invokevirtual zn : ()V
/*    */     //   1030: goto -> 1221
/*    */     //   1033: invokestatic XU : ()Z
/*    */     //   1036: ifne -> 1079
/*    */     //   1039: aload #14
/*    */     //   1041: instanceof f/Yr
/*    */     //   1044: ifeq -> 1050
/*    */     //   1047: goto -> 1079
/*    */     //   1050: aload #14
/*    */     //   1052: new java/lang/StringBuilder
/*    */     //   1055: dup
/*    */     //   1056: invokespecial <init> : ()V
/*    */     //   1059: ldc_w 'x'
/*    */     //   1062: invokevirtual append : (Ljava/lang/String;)Ljava/lang/StringBuilder;
/*    */     //   1065: iload #13
/*    */     //   1067: invokevirtual append : (I)Ljava/lang/StringBuilder;
/*    */     //   1070: invokevirtual toString : ()Ljava/lang/String;
/*    */     //   1073: invokevirtual s6 : (Ljava/lang/String;)V
/*    */     //   1076: goto -> 1120
/*    */     //   1079: aload #14
/*    */     //   1081: new java/lang/StringBuilder
/*    */     //   1084: dup
/*    */     //   1085: iload #13
/*    */     //   1087: swap
/*    */     //   1088: invokespecial <init> : ()V
/*    */     //   1091: invokevirtual append : (I)Ljava/lang/StringBuilder;
/*    */     //   1094: ldc_w 'x '
/*    */     //   1097: invokevirtual append : (Ljava/lang/String;)Ljava/lang/StringBuilder;
/*    */     //   1100: aload #9
/*    */     //   1102: getfield Bp0 : Lf/LPT3;
/*    */     //   1105: getfield Iu : I
/*    */     //   1108: invokestatic OH0 : (I)Ljava/lang/String;
/*    */     //   1111: invokevirtual append : (Ljava/lang/String;)Ljava/lang/StringBuilder;
/*    */     //   1114: invokevirtual toString : ()Ljava/lang/String;
/*    */     //   1117: invokevirtual s6 : (Ljava/lang/String;)V
/*    */     //   1120: aload #14
/*    */     //   1122: instanceof f/NK0
/*    */     //   1125: ifeq -> 1167
/*    */     //   1128: aload #14
/*    */     //   1130: checkcast f/NK0
/*    */     //   1133: dup
/*    */     //   1134: astore #12
/*    */     //   1136: invokeinterface pRn : ()Lf/Y;
/*    */     //   1141: getfield Lh : Lf/nH0;
/*    */     //   1144: getfield p1 : S
/*    */     //   1147: aload #9
/*    */     //   1149: getfield Lh : Lf/nH0;
/*    */     //   1152: getfield p1 : S
/*    */     //   1155: if_icmpeq -> 1167
/*    */     //   1158: aload #12
/*    */     //   1160: aload #9
/*    */     //   1162: invokeinterface Tm0 : (Lf/Y;)V
/*    */     //   1167: invokestatic Nr : ()Z
/*    */     //   1170: ifeq -> 1221
/*    */     //   1173: aload #9
/*    */     //   1175: getfield Bp0 : Lf/LPT3;
/*    */     //   1178: dup
/*    */     //   1179: astore #12
/*    */     //   1181: getfield c3 : Lf/wc;
/*    */     //   1184: ifnull -> 1221
/*    */     //   1187: new f/pQ
/*    */     //   1190: dup
/*    */     //   1191: astore #13
/*    */     //   1193: aload #12
/*    */     //   1195: aload #9
/*    */     //   1197: getfield Lh : Lf/nH0;
/*    */     //   1200: getfield Nj : B
/*    */     //   1203: iconst_1
/*    */     //   1204: iconst_1
/*    */     //   1205: ldc ''
/*    */     //   1207: invokespecial <init> : (Lf/LPT3;BZZLjava/lang/String;)V
/*    */     //   1210: aload #14
/*    */     //   1212: dup
/*    */     //   1213: aload #13
/*    */     //   1215: putfield z4 : Ljava/lang/Object;
/*    */     //   1218: invokevirtual zn : ()V
/*    */     //   1221: aload_0
/*    */     //   1222: dup
/*    */     //   1223: dup
/*    */     //   1224: aload #11
/*    */     //   1226: aload #9
/*    */     //   1228: getfield Lh : Lf/nH0;
/*    */     //   1231: getfield Wy : I
/*    */     //   1234: aload #14
/*    */     //   1236: invokevirtual A3 : (ILjava/lang/Object;)Ljava/lang/Object;
/*    */     //   1239: pop
/*    */     //   1240: getfield v60 : Ljava/util/ArrayList;
/*    */     //   1243: aload #14
/*    */     //   1245: invokevirtual add : (Ljava/lang/Object;)Z
/*    */     //   1248: pop
/*    */     //   1249: getfield Sj : Ljava/util/ArrayList;
/*    */     //   1252: aload #9
/*    */     //   1254: invokevirtual add : (Ljava/lang/Object;)Z
/*    */     //   1257: pop
/*    */     //   1258: getfield PO : Ljava/util/ArrayList;
/*    */     //   1261: aload #14
/*    */     //   1263: checkcast f/NK0
/*    */     //   1266: invokevirtual add : (Ljava/lang/Object;)Z
/*    */     //   1269: pop
/*    */     //   1270: iload #5
/*    */     //   1272: iconst_1
/*    */     //   1273: iadd
/*    */     //   1274: dup
/*    */     //   1275: istore #5
/*    */     //   1277: iload #10
/*    */     //   1279: irem
/*    */     //   1280: ifne -> 231
/*    */     //   1283: aload_0
/*    */     //   1284: dup
/*    */     //   1285: dup2
/*    */     //   1286: iconst_0
/*    */     //   1287: istore #5
/*    */     //   1289: getfield v60 : Ljava/util/ArrayList;
/*    */     //   1292: astore #9
/*    */     //   1294: getfield Sj : Ljava/util/ArrayList;
/*    */     //   1297: astore #12
/*    */     //   1299: getfield Dn : Lf/Ip;
/*    */     //   1302: astore #13
/*    */     //   1304: aload #9
/*    */     //   1306: aload #12
/*    */     //   1308: aload #13
/*    */     //   1310: aload_2
/*    */     //   1311: aload_3
/*    */     //   1312: invokevirtual P30 : (Ljava/util/ArrayList;Ljava/util/ArrayList;Lf/Ip;Lf/cr0;Lf/g0;)V
/*    */     //   1315: goto -> 231
/*    */     //   1318: aload_0
/*    */     //   1319: dup
/*    */     //   1320: dup2
/*    */     //   1321: dup2
/*    */     //   1322: dup2
/*    */     //   1323: aload #11
/*    */     //   1325: putfield Y60 : Lf/Ut0;
/*    */     //   1328: getfield v60 : Ljava/util/ArrayList;
/*    */     //   1331: astore_0
/*    */     //   1332: getfield Sj : Ljava/util/ArrayList;
/*    */     //   1335: astore_1
/*    */     //   1336: getfield Dn : Lf/Ip;
/*    */     //   1339: astore #4
/*    */     //   1341: aload_0
/*    */     //   1342: aload_1
/*    */     //   1343: aload #4
/*    */     //   1345: aload_2
/*    */     //   1346: aload_3
/*    */     //   1347: invokevirtual P30 : (Ljava/util/ArrayList;Ljava/util/ArrayList;Lf/Ip;Lf/cr0;Lf/g0;)V
/*    */     //   1350: getfield Dn : Lf/Ip;
/*    */     //   1353: aload_2
/*    */     //   1354: invokevirtual WN : (Lf/U90;)V
/*    */     //   1357: getfield Dn : Lf/Ip;
/*    */     //   1360: aload_3
/*    */     //   1361: invokevirtual rK0 : (Lf/U90;)V
/*    */     //   1364: getfield Dn : Lf/Ip;
/*    */     //   1367: areturn
/*    */     // Line number table:
/*    */     //   Java source line number -> byte code offset
/*    */     //   #1	-> 46
/*    */     //   #2	-> 50
/*    */     //   #3	-> 54
/*    */     //   #4	-> 58
/*    */     //   #5	-> 61
/*    */     //   #6	-> 72
/*    */     //   #7	-> 176
/*    */     //   #8	-> 179
/*    */     //   #9	-> 254
/*    */     //   #10	-> 260
/*    */     //   #11	-> 270
/*    */     //   #12	-> 282
/*    */     //   #13	-> 311
/*    */     //   #14	-> 321
/*    */     //   #15	-> 356
/*    */     //   #16	-> 370
/*    */     //   #17	-> 373
/*    */     //   #18	-> 424
/*    */     //   #19	-> 439
/*    */     //   #20	-> 448
/*    */     //   #21	-> 487
/*    */     //   #22	-> 492
/*    */     //   #23	-> 495
/*    */     //   #24	-> 498
/*    */     //   #25	-> 503
/*    */     //   #26	-> 506
/*    */     //   #27	-> 509
/*    */     //   #28	-> 520
/*    */     //   #29	-> 534
/*    */     //   #30	-> 569
/*    */     //   #31	-> 590
/*    */     //   #32	-> 599
/*    */     //   #33	-> 641
/*    */     //   #34	-> 644
/*    */     //   #35	-> 684
/*    */     //   #36	-> 687
/*    */     //   #37	-> 705
/*    */     //   #38	-> 710
/*    */     //   #39	-> 733
/*    */     //   #40	-> 747
/*    */     //   #41	-> 756
/*    */     //   #42	-> 788
/*    */     //   #43	-> 793
/*    */     //   #44	-> 796
/*    */     //   #45	-> 799
/*    */     //   #46	-> 845
/*    */     //   #47	-> 848
/*    */     //   #48	-> 856
/*    */     //   #49	-> 877
/*    */     //   #50	-> 880
/*    */     //   #51	-> 883
/*    */     //   #52	-> 886
/*    */     //   #53	-> 909
/*    */     //   #54	-> 919
/*    */     //   #55	-> 957
/*    */     //   #56	-> 964
/*    */     //   #57	-> 975
/*    */     //   #58	-> 978
/*    */     //   #59	-> 984
/*    */     //   #60	-> 990
/*    */     //   #61	-> 1000
/*    */     //   #62	-> 1003
/*    */     //   #63	-> 1008
/*    */     //   #64	-> 1021
/*    */     //   #65	-> 1024
/*    */     //   #66	-> 1033
/*    */     //   #67	-> 1102
/*    */     //   #68	-> 1105
/*    */     //   #69	-> 1108
/*    */     //   #70	-> 1111
/*    */     //   #71	-> 1141
/*    */     //   #72	-> 1144
/*    */     //   #73	-> 1149
/*    */     //   #74	-> 1152
/*    */     //   #75	-> 1162
/*    */     //   #76	-> 1175
/*    */     //   #77	-> 1181
/*    */     //   #78	-> 1187
/*    */     //   #79	-> 1197
/*    */     //   #80	-> 1200
/*    */     //   #81	-> 1205
/*    */     //   #82	-> 1215
/*    */     //   #83	-> 1228
/*    */     //   #84	-> 1231
/*    */     //   #85	-> 1236
/*    */   } }


/* Location:              /Users/vnnsnnt/Documents/Codespace/JavaWorkspace/RedTrainer/src/main/java/org/trainer/client/PokeMMO.jar!/f/NuL.class
 * Java compiler version: 8 (52.0)
 * JD-Core Version:       1.1.3
 */