/* 1 */ package f;public final class Od0 extends Kl0 { public final void sM() { this
/* 2 */       .M70 = this.Ws.get(); byte b;
/*   */     short[] arrayOfShort;
/* 4 */     for (this.Ss = this.Ws.get(), this.dS = new short[R00()], b = 0; b < (arrayOfShort = this.dS).length; ) { arrayOfShort[b] = this
/* 5 */         .Ws.getShort();
/* 6 */       b++; }
/*   */      }
/*   */ 
/*   */   
/*   */   public byte M70;
/*   */   public byte Ss;
/*   */   public short[] dS;
/*   */   
/*   */   public Od0(c4 paramc4, ByteBuffer paramByteBuffer) {
/*   */     super(paramc4, paramByteBuffer);
/*   */   }
/*   */   
/*   */   public final void Cx() {
/*   */     // Byte code:
/*   */     //   0: getstatic f/km.wI0 : Lf/Pw;
/*   */     //   3: dup
/*   */     //   4: astore_1
/*   */     //   5: getfield HV : Lf/sH;
/*   */     //   8: ifnull -> 30
/*   */     //   11: getstatic f/A1.L7 : Lf/A1;
/*   */     //   14: new f/RZ
/*   */     //   17: dup
/*   */     //   18: aload_0
/*   */     //   19: invokespecial <init> : (Lf/Od0;)V
/*   */     //   22: ldc2_w 100
/*   */     //   25: invokevirtual ac0 : (Ljava/lang/Runnable;J)Ljava/util/concurrent/ScheduledFuture;
/*   */     //   28: pop
/*   */     //   29: return
/*   */     //   30: aload_0
/*   */     //   31: getfield M70 : B
/*   */     //   34: dup
/*   */     //   35: istore_2
/*   */     //   36: bipush #32
/*   */     //   38: if_icmpeq -> 1419
/*   */     //   41: iload_2
/*   */     //   42: tableswitch default -> 100, 0 -> 1067, 1 -> 921, 2 -> 824, 3 -> 766, 4 -> 573, 5 -> 537, 6 -> 502, 7 -> 253, 8 -> 189, 9 -> 159, 10 -> 135
/*   */     //   100: iload_2
/*   */     //   101: tableswitch default -> 132, 12 -> 1314, 13 -> 1299, 14 -> 1241, 15 -> 1183
/*   */     //   132: goto -> 1430
/*   */     //   135: aload_0
/*   */     //   136: invokevirtual r8 : ()Lf/ro;
/*   */     //   139: aload_0
/*   */     //   140: dup
/*   */     //   141: getfield Ss : B
/*   */     //   144: istore_0
/*   */     //   145: iconst_0
/*   */     //   146: invokevirtual zc : (I)S
/*   */     //   149: iload_0
/*   */     //   150: swap
/*   */     //   151: iconst_0
/*   */     //   152: iconst_0
/*   */     //   153: invokevirtual aUX : (BSSS)V
/*   */     //   156: goto -> 1430
/*   */     //   159: aload_0
/*   */     //   160: invokevirtual r8 : ()Lf/ro;
/*   */     //   163: aload_0
/*   */     //   164: dup
/*   */     //   165: dup
/*   */     //   166: getfield Ss : B
/*   */     //   169: istore_0
/*   */     //   170: iconst_0
/*   */     //   171: invokevirtual zc : (I)S
/*   */     //   174: istore_1
/*   */     //   175: iconst_1
/*   */     //   176: invokevirtual zc : (I)S
/*   */     //   179: istore_2
/*   */     //   180: iload_0
/*   */     //   181: iload_1
/*   */     //   182: iload_2
/*   */     //   183: invokevirtual jt0 : (BSS)V
/*   */     //   186: goto -> 1430
/*   */     //   189: aload_0
/*   */     //   190: invokevirtual r8 : ()Lf/ro;
/*   */     //   193: aload_0
/*   */     //   194: dup
/*   */     //   195: dup
/*   */     //   196: getfield Ss : B
/*   */     //   199: istore_0
/*   */     //   200: iconst_0
/*   */     //   201: invokevirtual zc : (I)S
/*   */     //   204: istore_1
/*   */     //   205: iconst_1
/*   */     //   206: invokevirtual zc : (I)S
/*   */     //   209: pop
/*   */     //   210: checkcast f/R8
/*   */     //   213: dup
/*   */     //   214: astore_2
/*   */     //   215: getfield YG0 : Lf/js;
/*   */     //   218: getfield MH0 : Lf/pA;
/*   */     //   221: dup
/*   */     //   222: astore_3
/*   */     //   223: ifnonnull -> 235
/*   */     //   226: aload_2
/*   */     //   227: iload_0
/*   */     //   228: iconst_0
/*   */     //   229: invokevirtual lx0 : (BB)V
/*   */     //   232: goto -> 1430
/*   */     //   235: aload_3
/*   */     //   236: new f/do0
/*   */     //   239: dup
/*   */     //   240: astore_2
/*   */     //   241: iload_1
/*   */     //   242: iload_0
/*   */     //   243: invokespecial <init> : (IB)V
/*   */     //   246: aload_2
/*   */     //   247: invokevirtual J8 : (Lf/JG0;)V
/*   */     //   250: goto -> 1430
/*   */     //   253: getstatic f/km.a3 : Lf/vh0;
/*   */     //   256: getfield Ct : Lf/Jo;
/*   */     //   259: dup
/*   */     //   260: astore_0
/*   */     //   261: ifnonnull -> 265
/*   */     //   264: return
/*   */     //   265: getstatic f/km.wI0 : Lf/Pw;
/*   */     //   268: getfield iJ0 : Lf/Xi;
/*   */     //   271: dup
/*   */     //   272: astore_1
/*   */     //   273: instanceof f/tg
/*   */     //   276: ifeq -> 322
/*   */     //   279: aload_1
/*   */     //   280: checkcast f/tg
/*   */     //   283: new f/eo
/*   */     //   286: dup
/*   */     //   287: aload_0
/*   */     //   288: getfield HW : Lf/G5;
/*   */     //   291: dup
/*   */     //   292: astore_1
/*   */     //   293: getfield mm : S
/*   */     //   296: i2f
/*   */     //   297: aload_1
/*   */     //   298: getfield Yu0 : S
/*   */     //   301: i2f
/*   */     //   302: fconst_0
/*   */     //   303: swap
/*   */     //   304: invokespecial <init> : (FFF)V
/*   */     //   307: ldc 0.25
/*   */     //   309: invokevirtual uu : (F)Lf/eo;
/*   */     //   312: iconst_1
/*   */     //   313: swap
/*   */     //   314: iconst_0
/*   */     //   315: iconst_0
/*   */     //   316: iconst_0
/*   */     //   317: iconst_0
/*   */     //   318: invokevirtual rS : (BLf/eo;IZZZ)Z
/*   */     //   321: pop
/*   */     //   322: aload_0
/*   */     //   323: dup
/*   */     //   324: getfield pm : Lf/d7;
/*   */     //   327: iconst_1
/*   */     //   328: anewarray f/nl
/*   */     //   331: dup
/*   */     //   332: getstatic f/nl.xr : Lf/nl;
/*   */     //   335: iconst_0
/*   */     //   336: swap
/*   */     //   337: aastore
/*   */     //   338: invokevirtual Kk : ([Lf/nl;)V
/*   */     //   341: getfield HW : Lf/G5;
/*   */     //   344: invokevirtual CJ0 : ()Lf/xr0;
/*   */     //   347: astore_1
/*   */     //   348: iconst_0
/*   */     //   349: istore_2
/*   */     //   350: aload_1
/*   */     //   351: invokevirtual i00 : ()F
/*   */     //   354: ldc -1.0
/*   */     //   356: fcmpl
/*   */     //   357: ifle -> 460
/*   */     //   360: iload_2
/*   */     //   361: iconst_5
/*   */     //   362: if_icmpge -> 460
/*   */     //   365: aconst_null
/*   */     //   366: astore_3
/*   */     //   367: iconst_m1
/*   */     //   368: istore #4
/*   */     //   370: iload #4
/*   */     //   372: iconst_2
/*   */     //   373: if_icmpge -> 445
/*   */     //   376: iconst_m1
/*   */     //   377: istore #5
/*   */     //   379: iload #5
/*   */     //   381: iconst_2
/*   */     //   382: if_icmpge -> 439
/*   */     //   385: aload_1
/*   */     //   386: invokevirtual Q4 : ()Lf/KI;
/*   */     //   389: aload_1
/*   */     //   390: invokevirtual Ka : ()S
/*   */     //   393: iload #4
/*   */     //   395: iadd
/*   */     //   396: aload_1
/*   */     //   397: invokevirtual hA0 : ()S
/*   */     //   400: iload #5
/*   */     //   402: iadd
/*   */     //   403: iconst_0
/*   */     //   404: invokevirtual v50 : (III)Lf/xr0;
/*   */     //   407: dup
/*   */     //   408: astore #6
/*   */     //   410: ifnull -> 433
/*   */     //   413: aload_3
/*   */     //   414: ifnull -> 430
/*   */     //   417: aload #6
/*   */     //   419: invokevirtual i00 : ()F
/*   */     //   422: aload_3
/*   */     //   423: invokevirtual i00 : ()F
/*   */     //   426: fcmpg
/*   */     //   427: ifge -> 433
/*   */     //   430: aload #6
/*   */     //   432: astore_3
/*   */     //   433: iinc #5, 1
/*   */     //   436: goto -> 379
/*   */     //   439: iinc #4, 1
/*   */     //   442: goto -> 370
/*   */     //   445: aload_3
/*   */     //   446: ifnonnull -> 452
/*   */     //   449: goto -> 460
/*   */     //   452: iinc #2, 1
/*   */     //   455: aload_3
/*   */     //   456: astore_1
/*   */     //   457: goto -> 350
/*   */     //   460: aload_0
/*   */     //   461: getfield pm : Lf/d7;
/*   */     //   464: dup
/*   */     //   465: astore_3
/*   */     //   466: new f/Ye
/*   */     //   469: dup
/*   */     //   470: astore #4
/*   */     //   472: aload_0
/*   */     //   473: iload_2
/*   */     //   474: aload_1
/*   */     //   475: invokespecial <init> : (Lf/Jo;ILf/xr0;)V
/*   */     //   478: getfield ew0 : Ljava/util/LinkedList;
/*   */     //   481: dup
/*   */     //   482: astore_2
/*   */     //   483: aload_3
/*   */     //   484: aload_2
/*   */     //   485: monitorenter
/*   */     //   486: getfield ew0 : Ljava/util/LinkedList;
/*   */     //   489: aload #4
/*   */     //   491: invokevirtual add : (Ljava/lang/Object;)Z
/*   */     //   494: pop
/*   */     //   495: monitorexit
/*   */     //   496: return
/*   */     //   497: astore_0
/*   */     //   498: aload_0
/*   */     //   499: aload_2
/*   */     //   500: monitorexit
/*   */     //   501: athrow
/*   */     //   502: aload_1
/*   */     //   503: getfield iJ0 : Lf/Xi;
/*   */     //   506: dup
/*   */     //   507: astore_1
/*   */     //   508: ifnonnull -> 528
/*   */     //   511: getstatic f/UB0.Kg0 : Lf/Q50;
/*   */     //   514: new f/y3
/*   */     //   517: dup
/*   */     //   518: aload_0
/*   */     //   519: invokespecial <init> : (Lf/Od0;)V
/*   */     //   522: invokevirtual fN : (Ljava/lang/Runnable;)V
/*   */     //   525: goto -> 536
/*   */     //   528: aload_1
/*   */     //   529: aload_0
/*   */     //   530: getfield dS : [S
/*   */     //   533: invokevirtual j00 : ([S)V
/*   */     //   536: return
/*   */     //   537: aload_0
/*   */     //   538: invokevirtual r8 : ()Lf/ro;
/*   */     //   541: new f/R2
/*   */     //   544: dup
/*   */     //   545: astore_1
/*   */     //   546: aload_0
/*   */     //   547: invokespecial <init> : (Lf/Od0;)V
/*   */     //   550: iconst_1
/*   */     //   551: istore_0
/*   */     //   552: checkcast f/R8
/*   */     //   555: getfield YG0 : Lf/js;
/*   */     //   558: getfield MH0 : Lf/pA;
/*   */     //   561: dup
/*   */     //   562: astore_2
/*   */     //   563: ifnull -> 572
/*   */     //   566: aload_2
/*   */     //   567: iload_0
/*   */     //   568: aload_1
/*   */     //   569: invokevirtual U10 : (ZLf/R2;)V
/*   */     //   572: return
/*   */     //   573: aload_0
/*   */     //   574: iconst_0
/*   */     //   575: invokevirtual zc : (I)S
/*   */     //   578: i2b
/*   */     //   579: istore_1
/*   */     //   580: getstatic f/hv0.yP : Lf/ak;
/*   */     //   583: dup
/*   */     //   584: astore_2
/*   */     //   585: iload_1
/*   */     //   586: invokevirtual db0 : (B)Z
/*   */     //   589: ifeq -> 603
/*   */     //   592: aload_2
/*   */     //   593: iload_1
/*   */     //   594: invokevirtual Ha0 : (B)Ljava/lang/Object;
/*   */     //   597: checkcast f/hv0
/*   */     //   600: goto -> 606
/*   */     //   603: getstatic f/hv0.V00 : Lf/hv0;
/*   */     //   606: aload_0
/*   */     //   607: iconst_1
/*   */     //   608: invokevirtual zc : (I)S
/*   */     //   611: istore_0
/*   */     //   612: invokevirtual ordinal : ()I
/*   */     //   615: tableswitch default -> 652, 0 -> 755, 1 -> 738, 2 -> 691, 3 -> 674, 4 -> 652, 5 -> 655
/*   */     //   652: goto -> 1430
/*   */     //   655: invokestatic Bp : ()Lf/ud;
/*   */     //   658: getfield wS : Lf/nm0;
/*   */     //   661: dup
/*   */     //   662: iload_0
/*   */     //   663: swap
/*   */     //   664: getfield q50 : I
/*   */     //   667: idiv
/*   */     //   668: putfield Gx0 : I
/*   */     //   671: goto -> 1430
/*   */     //   674: invokestatic Bp : ()Lf/ud;
/*   */     //   677: getfield sC0 : Lf/Mj;
/*   */     //   680: iconst_0
/*   */     //   681: sipush #255
/*   */     //   684: iload_0
/*   */     //   685: invokevirtual gz0 : (III)V
/*   */     //   688: goto -> 1430
/*   */     //   691: invokestatic Bp : ()Lf/ud;
/*   */     //   694: dup
/*   */     //   695: dup2
/*   */     //   696: astore_1
/*   */     //   697: getfield qu : Lf/Mj;
/*   */     //   700: getfield oI : I
/*   */     //   703: aload_1
/*   */     //   704: getfield sC0 : Lf/Mj;
/*   */     //   707: getfield oI : I
/*   */     //   710: invokestatic max : (II)I
/*   */     //   713: istore_1
/*   */     //   714: getfield sC0 : Lf/Mj;
/*   */     //   717: iload_1
/*   */     //   718: iconst_0
/*   */     //   719: iload_0
/*   */     //   720: invokevirtual gz0 : (III)V
/*   */     //   723: getfield qu : Lf/Mj;
/*   */     //   726: dup
/*   */     //   727: iconst_0
/*   */     //   728: putfield oI : I
/*   */     //   731: iconst_0
/*   */     //   732: putfield wB0 : I
/*   */     //   735: goto -> 1430
/*   */     //   738: invokestatic Bp : ()Lf/ud;
/*   */     //   741: getfield qu : Lf/Mj;
/*   */     //   744: iconst_0
/*   */     //   745: sipush #255
/*   */     //   748: iload_0
/*   */     //   749: invokevirtual gz0 : (III)V
/*   */     //   752: goto -> 1430
/*   */     //   755: invokestatic Bp : ()Lf/ud;
/*   */     //   758: iload_0
/*   */     //   759: iconst_1
/*   */     //   760: invokevirtual Xk : (IZ)V
/*   */     //   763: goto -> 1430
/*   */     //   766: aload_0
/*   */     //   767: invokevirtual r8 : ()Lf/ro;
/*   */     //   770: aload_0
/*   */     //   771: dup
/*   */     //   772: getfield Ss : B
/*   */     //   775: istore_0
/*   */     //   776: iconst_0
/*   */     //   777: invokevirtual zc : (I)S
/*   */     //   780: istore_1
/*   */     //   781: checkcast f/R8
/*   */     //   784: dup
/*   */     //   785: astore_2
/*   */     //   786: getfield YG0 : Lf/js;
/*   */     //   789: getfield MH0 : Lf/pA;
/*   */     //   792: dup
/*   */     //   793: astore_3
/*   */     //   794: ifnonnull -> 806
/*   */     //   797: aload_2
/*   */     //   798: iload_0
/*   */     //   799: iconst_0
/*   */     //   800: invokevirtual lx0 : (BB)V
/*   */     //   803: goto -> 1430
/*   */     //   806: aload_3
/*   */     //   807: new f/w60
/*   */     //   810: dup
/*   */     //   811: astore_2
/*   */     //   812: iload_1
/*   */     //   813: iload_0
/*   */     //   814: invokespecial <init> : (IB)V
/*   */     //   817: aload_2
/*   */     //   818: invokevirtual J8 : (Lf/JG0;)V
/*   */     //   821: goto -> 1430
/*   */     //   824: aload_0
/*   */     //   825: dup
/*   */     //   826: iconst_0
/*   */     //   827: invokevirtual zc : (I)S
/*   */     //   830: istore_1
/*   */     //   831: iconst_1
/*   */     //   832: invokevirtual zc : (I)S
/*   */     //   835: istore_2
/*   */     //   836: getstatic f/km.a3 : Lf/vh0;
/*   */     //   839: getfield Ct : Lf/Jo;
/*   */     //   842: dup
/*   */     //   843: astore_3
/*   */     //   844: iconst_0
/*   */     //   845: istore #4
/*   */     //   847: invokevirtual UG : ()Z
/*   */     //   850: ifne -> 896
/*   */     //   853: aload_3
/*   */     //   854: invokevirtual XC : ()Z
/*   */     //   857: ifne -> 896
/*   */     //   860: aload_0
/*   */     //   861: invokevirtual r8 : ()Lf/ro;
/*   */     //   864: iload_1
/*   */     //   865: iload_2
/*   */     //   866: iconst_0
/*   */     //   867: invokevirtual nJ : (SSZ)Z
/*   */     //   870: ifne -> 896
/*   */     //   873: aload_3
/*   */     //   874: sipush #900
/*   */     //   877: istore #4
/*   */     //   879: getfield pm : Lf/d7;
/*   */     //   882: iconst_1
/*   */     //   883: anewarray f/nl
/*   */     //   886: dup
/*   */     //   887: getstatic f/nl.z2 : Lf/nl;
/*   */     //   890: iconst_0
/*   */     //   891: swap
/*   */     //   892: aastore
/*   */     //   893: invokevirtual Kk : ([Lf/nl;)V
/*   */     //   896: getstatic f/A1.L7 : Lf/A1;
/*   */     //   899: iload #4
/*   */     //   901: aload_0
/*   */     //   902: iload_1
/*   */     //   903: iload_2
/*   */     //   904: <illegal opcode> run : (Lf/Od0;SS)Ljava/lang/Runnable;
/*   */     //   909: astore_0
/*   */     //   910: i2l
/*   */     //   911: lstore_1
/*   */     //   912: aload_0
/*   */     //   913: lload_1
/*   */     //   914: invokevirtual ac0 : (Ljava/lang/Runnable;J)Ljava/util/concurrent/ScheduledFuture;
/*   */     //   917: pop
/*   */     //   918: goto -> 1430
/*   */     //   921: aload_0
/*   */     //   922: iconst_0
/*   */     //   923: invokevirtual zc : (I)S
/*   */     //   926: bipush #54
/*   */     //   928: if_icmpeq -> 968
/*   */     //   931: aload_0
/*   */     //   932: iconst_0
/*   */     //   933: istore_1
/*   */     //   934: getfield Ss : B
/*   */     //   937: iconst_m1
/*   */     //   938: if_icmpne -> 944
/*   */     //   941: goto -> 1430
/*   */     //   944: getstatic f/A1.L7 : Lf/A1;
/*   */     //   947: iload_1
/*   */     //   948: new f/Sy
/*   */     //   951: dup
/*   */     //   952: astore_1
/*   */     //   953: aload_0
/*   */     //   954: invokespecial <init> : (Lf/Od0;)V
/*   */     //   957: i2l
/*   */     //   958: lstore_2
/*   */     //   959: aload_1
/*   */     //   960: lload_2
/*   */     //   961: invokevirtual ac0 : (Ljava/lang/Runnable;J)Ljava/util/concurrent/ScheduledFuture;
/*   */     //   964: pop
/*   */     //   965: goto -> 1430
/*   */     //   968: aload_0
/*   */     //   969: dup
/*   */     //   970: dup
/*   */     //   971: iconst_1
/*   */     //   972: invokevirtual zc : (I)S
/*   */     //   975: istore_1
/*   */     //   976: iconst_2
/*   */     //   977: invokevirtual zc : (I)S
/*   */     //   980: istore_2
/*   */     //   981: sipush #600
/*   */     //   984: istore_3
/*   */     //   985: getfield Ss : B
/*   */     //   988: iconst_m1
/*   */     //   989: if_icmpne -> 995
/*   */     //   992: goto -> 1018
/*   */     //   995: getstatic f/A1.L7 : Lf/A1;
/*   */     //   998: iload_3
/*   */     //   999: new f/Sy
/*   */     //   1002: dup
/*   */     //   1003: astore_3
/*   */     //   1004: aload_0
/*   */     //   1005: invokespecial <init> : (Lf/Od0;)V
/*   */     //   1008: i2l
/*   */     //   1009: lstore #4
/*   */     //   1011: aload_3
/*   */     //   1012: lload #4
/*   */     //   1014: invokevirtual ac0 : (Ljava/lang/Runnable;J)Ljava/util/concurrent/ScheduledFuture;
/*   */     //   1017: pop
/*   */     //   1018: aload_0
/*   */     //   1019: new f/dh0
/*   */     //   1022: dup
/*   */     //   1023: astore_0
/*   */     //   1024: invokespecial <init> : ()V
/*   */     //   1027: invokevirtual r8 : ()Lf/ro;
/*   */     //   1030: getfield Qa : Lf/vh0;
/*   */     //   1033: invokevirtual Jr0 : ()Lf/KI;
/*   */     //   1036: dup
/*   */     //   1037: astore_3
/*   */     //   1038: ifnonnull -> 1044
/*   */     //   1041: goto -> 1430
/*   */     //   1044: aload_3
/*   */     //   1045: iload_1
/*   */     //   1046: iload_2
/*   */     //   1047: iconst_0
/*   */     //   1048: invokevirtual v50 : (III)Lf/xr0;
/*   */     //   1051: dup
/*   */     //   1052: astore_1
/*   */     //   1053: ifnonnull -> 1059
/*   */     //   1056: goto -> 1430
/*   */     //   1059: aload_1
/*   */     //   1060: aload_0
/*   */     //   1061: invokevirtual TL0 : (Lf/fZ;)V
/*   */     //   1064: goto -> 1430
/*   */     //   1067: aload_0
/*   */     //   1068: dup
/*   */     //   1069: getstatic f/tr.Jv : Lf/tr;
/*   */     //   1072: dup
/*   */     //   1073: astore_1
/*   */     //   1074: aload_0
/*   */     //   1075: dup
/*   */     //   1076: dup2
/*   */     //   1077: iconst_0
/*   */     //   1078: invokevirtual zc : (I)S
/*   */     //   1081: istore_2
/*   */     //   1082: iconst_1
/*   */     //   1083: invokevirtual zc : (I)S
/*   */     //   1086: istore_3
/*   */     //   1087: iconst_2
/*   */     //   1088: invokevirtual zc : (I)S
/*   */     //   1091: istore #4
/*   */     //   1093: iconst_3
/*   */     //   1094: invokevirtual zc : (I)S
/*   */     //   1097: aload_1
/*   */     //   1098: dup
/*   */     //   1099: iload_2
/*   */     //   1100: aload_1
/*   */     //   1101: iload_3
/*   */     //   1102: aload_1
/*   */     //   1103: dup
/*   */     //   1104: lconst_0
/*   */     //   1105: putfield MD0 : J
/*   */     //   1108: iconst_0
/*   */     //   1109: putfield hn0 : I
/*   */     //   1112: putfield fm : I
/*   */     //   1115: putfield Am : I
/*   */     //   1118: getstatic f/zm0.u20 : J
/*   */     //   1121: iload #4
/*   */     //   1123: bipush #15
/*   */     //   1125: imul
/*   */     //   1126: iconst_4
/*   */     //   1127: imul
/*   */     //   1128: i2l
/*   */     //   1129: ladd
/*   */     //   1130: putfield oZ : J
/*   */     //   1133: bipush #15
/*   */     //   1135: imul
/*   */     //   1136: putfield Ty0 : I
/*   */     //   1139: iconst_2
/*   */     //   1140: invokevirtual zc : (I)S
/*   */     //   1143: bipush #15
/*   */     //   1145: imul
/*   */     //   1146: iconst_4
/*   */     //   1147: imul
/*   */     //   1148: istore_1
/*   */     //   1149: getfield Ss : B
/*   */     //   1152: iconst_m1
/*   */     //   1153: if_icmpne -> 1159
/*   */     //   1156: goto -> 1430
/*   */     //   1159: getstatic f/A1.L7 : Lf/A1;
/*   */     //   1162: iload_1
/*   */     //   1163: new f/Sy
/*   */     //   1166: dup
/*   */     //   1167: astore_1
/*   */     //   1168: aload_0
/*   */     //   1169: invokespecial <init> : (Lf/Od0;)V
/*   */     //   1172: i2l
/*   */     //   1173: lstore_2
/*   */     //   1174: aload_1
/*   */     //   1175: lload_2
/*   */     //   1176: invokevirtual ac0 : (Ljava/lang/Runnable;J)Ljava/util/concurrent/ScheduledFuture;
/*   */     //   1179: pop
/*   */     //   1180: goto -> 1430
/*   */     //   1183: aload_0
/*   */     //   1184: invokevirtual r8 : ()Lf/ro;
/*   */     //   1187: aload_0
/*   */     //   1188: dup
/*   */     //   1189: getfield Ss : B
/*   */     //   1192: istore_0
/*   */     //   1193: iconst_0
/*   */     //   1194: invokevirtual zc : (I)S
/*   */     //   1197: istore_1
/*   */     //   1198: checkcast f/R8
/*   */     //   1201: dup
/*   */     //   1202: astore_2
/*   */     //   1203: getfield YG0 : Lf/js;
/*   */     //   1206: getfield MH0 : Lf/pA;
/*   */     //   1209: dup
/*   */     //   1210: astore_3
/*   */     //   1211: ifnonnull -> 1223
/*   */     //   1214: aload_2
/*   */     //   1215: iload_0
/*   */     //   1216: iconst_0
/*   */     //   1217: invokevirtual lx0 : (BB)V
/*   */     //   1220: goto -> 1430
/*   */     //   1223: aload_3
/*   */     //   1224: new f/UW
/*   */     //   1227: dup
/*   */     //   1228: astore_2
/*   */     //   1229: iload_0
/*   */     //   1230: iload_1
/*   */     //   1231: invokespecial <init> : (BS)V
/*   */     //   1234: aload_2
/*   */     //   1235: invokevirtual J8 : (Lf/JG0;)V
/*   */     //   1238: goto -> 1430
/*   */     //   1241: aload_0
/*   */     //   1242: invokevirtual r8 : ()Lf/ro;
/*   */     //   1245: aload_0
/*   */     //   1246: dup
/*   */     //   1247: getfield Ss : B
/*   */     //   1250: istore_0
/*   */     //   1251: iconst_0
/*   */     //   1252: invokevirtual zc : (I)S
/*   */     //   1255: istore_1
/*   */     //   1256: checkcast f/R8
/*   */     //   1259: dup
/*   */     //   1260: astore_2
/*   */     //   1261: getfield YG0 : Lf/js;
/*   */     //   1264: getfield MH0 : Lf/pA;
/*   */     //   1267: dup
/*   */     //   1268: astore_3
/*   */     //   1269: ifnonnull -> 1281
/*   */     //   1272: aload_2
/*   */     //   1273: iload_0
/*   */     //   1274: iconst_0
/*   */     //   1275: invokevirtual lx0 : (BB)V
/*   */     //   1278: goto -> 1430
/*   */     //   1281: aload_3
/*   */     //   1282: new f/Vf
/*   */     //   1285: dup
/*   */     //   1286: astore_2
/*   */     //   1287: iload_0
/*   */     //   1288: iload_1
/*   */     //   1289: invokespecial <init> : (BS)V
/*   */     //   1292: aload_2
/*   */     //   1293: invokevirtual J8 : (Lf/JG0;)V
/*   */     //   1296: goto -> 1430
/*   */     //   1299: aload_0
/*   */     //   1300: invokevirtual r8 : ()Lf/ro;
/*   */     //   1303: aload_0
/*   */     //   1304: iconst_0
/*   */     //   1305: invokevirtual zc : (I)S
/*   */     //   1308: invokevirtual PC : (S)V
/*   */     //   1311: goto -> 1430
/*   */     //   1314: aload_0
/*   */     //   1315: dup
/*   */     //   1316: iconst_0
/*   */     //   1317: invokevirtual zc : (I)S
/*   */     //   1320: istore_1
/*   */     //   1321: iconst_1
/*   */     //   1322: invokevirtual zc : (I)S
/*   */     //   1325: iconst_1
/*   */     //   1326: if_icmpne -> 1334
/*   */     //   1329: iconst_1
/*   */     //   1330: istore_2
/*   */     //   1331: goto -> 1336
/*   */     //   1334: iconst_0
/*   */     //   1335: istore_2
/*   */     //   1336: aload_0
/*   */     //   1337: iconst_2
/*   */     //   1338: invokevirtual zc : (I)S
/*   */     //   1341: i2b
/*   */     //   1342: istore_3
/*   */     //   1343: getstatic f/km.a3 : Lf/vh0;
/*   */     //   1346: getfield Ct : Lf/Jo;
/*   */     //   1349: dup
/*   */     //   1350: astore #4
/*   */     //   1352: iconst_0
/*   */     //   1353: istore #5
/*   */     //   1355: invokevirtual UG : ()Z
/*   */     //   1358: ifne -> 1393
/*   */     //   1361: aload #4
/*   */     //   1363: invokevirtual XC : ()Z
/*   */     //   1366: ifne -> 1393
/*   */     //   1369: aload #4
/*   */     //   1371: sipush #900
/*   */     //   1374: istore #5
/*   */     //   1376: getfield pm : Lf/d7;
/*   */     //   1379: iconst_1
/*   */     //   1380: anewarray f/nl
/*   */     //   1383: dup
/*   */     //   1384: getstatic f/nl.z2 : Lf/nl;
/*   */     //   1387: iconst_0
/*   */     //   1388: swap
/*   */     //   1389: aastore
/*   */     //   1390: invokevirtual Kk : ([Lf/nl;)V
/*   */     //   1393: getstatic f/A1.L7 : Lf/A1;
/*   */     //   1396: iload #5
/*   */     //   1398: aload_0
/*   */     //   1399: iload_1
/*   */     //   1400: iload_2
/*   */     //   1401: iload_3
/*   */     //   1402: <illegal opcode> run : (Lf/Od0;SZB)Ljava/lang/Runnable;
/*   */     //   1407: astore_0
/*   */     //   1408: i2l
/*   */     //   1409: lstore_1
/*   */     //   1410: aload_0
/*   */     //   1411: lload_1
/*   */     //   1412: invokevirtual ac0 : (Ljava/lang/Runnable;J)Ljava/util/concurrent/ScheduledFuture;
/*   */     //   1415: pop
/*   */     //   1416: goto -> 1430
/*   */     //   1419: aload_0
/*   */     //   1420: invokevirtual r8 : ()Lf/ro;
/*   */     //   1423: aload_0
/*   */     //   1424: getfield Ss : B
/*   */     //   1427: invokevirtual pb0 : (B)V
/*   */     //   1430: return
/*   */     // Line number table:
/*   */     //   Java source line number -> byte code offset
/*   */     //   #1	-> 5
/*   */     //   #2	-> 11
/*   */     //   #3	-> 14
/*   */     //   #4	-> 215
/*   */     //   #5	-> 218
/*   */     //   #6	-> 229
/*   */     //   #7	-> 236
/*   */     //   #8	-> 253
/*   */     //   #9	-> 256
/*   */     //   #10	-> 265
/*   */     //   #11	-> 268
/*   */     //   #12	-> 273
/*   */     //   #13	-> 288
/*   */     //   #14	-> 293
/*   */     //   #15	-> 298
/*   */     //   #16	-> 304
/*   */     //   #17	-> 324
/*   */     //   #18	-> 328
/*   */     //   #19	-> 341
/*   */     //   #20	-> 344
/*   */     //   #21	-> 404
/*   */     //   #22	-> 419
/*   */     //   #23	-> 461
/*   */     //   #24	-> 466
/*   */     //   #25	-> 478
/*   */     //   #26	-> 485
/*   */     //   #27	-> 503
/*   */     //   #28	-> 511
/*   */     //   #29	-> 538
/*   */     //   #30	-> 555
/*   */     //   #31	-> 558
/*   */     //   #32	-> 569
/*   */     //   #33	-> 575
/*   */     //   #34	-> 580
/*   */     //   #35	-> 586
/*   */     //   #36	-> 594
/*   */     //   #37	-> 608
/*   */     //   #38	-> 658
/*   */     //   #39	-> 664
/*   */     //   #40	-> 667
/*   */     //   #41	-> 674
/*   */     //   #42	-> 677
/*   */     //   #43	-> 685
/*   */     //   #44	-> 691
/*   */     //   #45	-> 697
/*   */     //   #46	-> 700
/*   */     //   #47	-> 704
/*   */     //   #48	-> 707
/*   */     //   #49	-> 710
/*   */     //   #50	-> 728
/*   */     //   #51	-> 732
/*   */     //   #52	-> 738
/*   */     //   #53	-> 741
/*   */     //   #54	-> 749
/*   */     //   #55	-> 755
/*   */     //   #56	-> 786
/*   */     //   #57	-> 789
/*   */     //   #58	-> 800
/*   */     //   #59	-> 807
/*   */     //   #60	-> 827
/*   */     //   #61	-> 839
/*   */     //   #62	-> 847
/*   */     //   #63	-> 879
/*   */     //   #64	-> 883
/*   */     //   #65	-> 896
/*   */     //   #66	-> 904
/*   */     //   #67	-> 934
/*   */     //   #68	-> 944
/*   */     //   #69	-> 948
/*   */     //   #70	-> 972
/*   */     //   #71	-> 985
/*   */     //   #72	-> 995
/*   */     //   #73	-> 999
/*   */     //   #74	-> 1019
/*   */     //   #75	-> 1027
/*   */     //   #76	-> 1030
/*   */     //   #77	-> 1033
/*   */     //   #78	-> 1048
/*   */     //   #79	-> 1061
/*   */     //   #80	-> 1069
/*   */     //   #81	-> 1105
/*   */     //   #82	-> 1118
/*   */     //   #83	-> 1130
/*   */     //   #84	-> 1140
/*   */     //   #85	-> 1149
/*   */     //   #86	-> 1159
/*   */     //   #87	-> 1163
/*   */     //   #88	-> 1184
/*   */     //   #89	-> 1203
/*   */     //   #90	-> 1206
/*   */     //   #91	-> 1217
/*   */     //   #92	-> 1224
/*   */     //   #93	-> 1242
/*   */     //   #94	-> 1261
/*   */     //   #95	-> 1264
/*   */     //   #96	-> 1275
/*   */     //   #97	-> 1282
/*   */     //   #98	-> 1300
/*   */     //   #99	-> 1346
/*   */     //   #100	-> 1355
/*   */     //   #101	-> 1376
/*   */     //   #102	-> 1380
/*   */     //   #103	-> 1393
/*   */     //   #104	-> 1402
/*   */     // Exception table:
/*   */     //   from	to	target	type
/*   */     //   486	494	497	finally
/*   */     //   495	496	497	finally
/*   */     //   498	501	497	finally
/*   */   }
/*   */   
/*   */   public final short zc(int paramInt) {
/*   */     short[] arrayOfShort;
/*   */     return (paramInt < 0 || paramInt >= (arrayOfShort = this.dS).length) ? 0 : this[paramInt];
/*   */   } }


/* Location:              /Users/vnnsnnt/Documents/Codespace/JavaWorkspace/RedTrainer/src/main/java/org/trainer/client/PokeMMO.jar!/f/Od0.class
 * Java compiler version: 8 (52.0)
 * JD-Core Version:       1.1.3
 */