/*  1 */ package f;public final class Oe0 extends Wr { public final eo Cn0; public jp0 gv0; public LL D0; public rS s00; public f8 V3; public static void VE(lpt1 paramlpt1, String paramString) { paramlpt1.co0(paramString, false, null); } public T0 Xt; public qo xz; public fQ z10; public JG0 hi0; public Oe0() { LG lG; WE0 wE0; KE0 kE0; Ul ul; IL0 iL0; W1 w1; this.Cn0 = new eo(); this.V3 = new f8(); this.Xt = null; this.z10 = new fQ(); this.hi0 = new JG0(); if (km.wI0.Kh() instanceof jp0) this.gv0 = (jp0)km.wI0.Kh();  if (this.gv0 == null) { if (Mv0() != null) Mv0().jf0(this);  return; }  TG0(this::ra0); (this.D0 = new LL(this.V3)).Xu("/mapview-table"); this(); this.D0.ek(Ob0.class, lG); this(); this.D0.ek(ry0.class, wE0); this(); this.D0.ek(Un.class, kE0); this(); this.D0.ek(vy.class, ul); this(); this.D0.ek(Fy0.class, iL0); this.D0.zs0(); this.D0.Gb0(true); (this.s00 = new rS(this.D0)).Xu("scrollpane"); this.s00.zG0(2); Xu("mapview"); Lo("MapDebugger"); this("Refresh"); Un un; (un = new Un()).tW(() -> d()); this(new OZ((Object[])new String[] { "Spring", "Summer", "Autumn", "Winter" })); (new W1()).Z30(L70.Oj0().fu()); (new W1()).D30(new W1()::JD0); (new Ip()).rK0((new Ip()).AUX(new JG0[] { w1, this.s00, un })); (new Ip()).WN((new Ip()).vo0(new JG0[] { w1, this.s00, un })); J8(new Ip()); d(); this.D0.mM(); } private void IL0(T0 paramT0, lpt1 paramlpt1, int paramInt) { // Byte code:
/*    */     //   0: aload_0
/*    */     //   1: getfield Xt : Lf/T0;
/*    */     //   4: dup
/*    */     //   5: astore #4
/*    */     //   7: ifnull -> 38
/*    */     //   10: aload_0
/*    */     //   11: getfield xz : Lf/qo;
/*    */     //   14: dup
/*    */     //   15: astore #5
/*    */     //   17: ifnull -> 30
/*    */     //   20: aload #4
/*    */     //   22: aload #5
/*    */     //   24: invokevirtual Tz0 : (Lf/dj;)V
/*    */     //   27: goto -> 38
/*    */     //   30: aload #4
/*    */     //   32: getstatic f/qo.A80 : J
/*    */     //   35: invokevirtual Ng0 : (J)V
/*    */     //   38: aload_0
/*    */     //   39: getfield Xt : Lf/T0;
/*    */     //   42: aload_1
/*    */     //   43: if_acmpne -> 57
/*    */     //   46: aload_0
/*    */     //   47: dup
/*    */     //   48: aconst_null
/*    */     //   49: putfield Xt : Lf/T0;
/*    */     //   52: aconst_null
/*    */     //   53: putfield xz : Lf/qo;
/*    */     //   56: return
/*    */     //   57: invokestatic hS : ()Z
/*    */     //   60: ifeq -> 193
/*    */     //   63: aload_2
/*    */     //   64: getfield Cx0 : Lf/Ew;
/*    */     //   67: dup
/*    */     //   68: astore #4
/*    */     //   70: ifnonnull -> 84
/*    */     //   73: getstatic f/js.vu0 : Lf/js;
/*    */     //   76: iconst_m1
/*    */     //   77: ldc_w 'No texture provider found'
/*    */     //   80: invokevirtual Pu : (ILjava/lang/String;)V
/*    */     //   83: return
/*    */     //   84: aload_1
/*    */     //   85: aload_2
/*    */     //   86: aload #4
/*    */     //   88: aload_1
/*    */     //   89: getfield Xy0 : Ljava/lang/String;
/*    */     //   92: invokevirtual Vv0 : (Ljava/lang/String;)I
/*    */     //   95: istore #4
/*    */     //   97: getfield Cx0 : Lf/Ew;
/*    */     //   100: astore #5
/*    */     //   102: getfield Xy0 : Ljava/lang/String;
/*    */     //   105: aload #5
/*    */     //   107: getfield dH : Lf/f7;
/*    */     //   110: swap
/*    */     //   111: invokevirtual pd0 : (Ljava/lang/Object;)Ljava/lang/Object;
/*    */     //   114: checkcast java/lang/Integer
/*    */     //   117: dup
/*    */     //   118: astore #5
/*    */     //   120: ifnonnull -> 129
/*    */     //   123: iconst_m1
/*    */     //   124: istore #5
/*    */     //   126: goto -> 136
/*    */     //   129: aload #5
/*    */     //   131: invokevirtual intValue : ()I
/*    */     //   134: istore #5
/*    */     //   136: iload #4
/*    */     //   138: iflt -> 182
/*    */     //   141: iload #5
/*    */     //   143: ifge -> 149
/*    */     //   146: goto -> 182
/*    */     //   149: iload_3
/*    */     //   150: getstatic f/D.N2 : Lf/D;
/*    */     //   153: astore #6
/*    */     //   155: ifge -> 167
/*    */     //   158: aload_2
/*    */     //   159: getfield jx : I
/*    */     //   162: sipush #1000
/*    */     //   165: iadd
/*    */     //   166: istore_3
/*    */     //   167: aload #6
/*    */     //   169: aload_1
/*    */     //   170: aload_2
/*    */     //   171: iload_3
/*    */     //   172: iload #4
/*    */     //   174: iload #5
/*    */     //   176: invokevirtual kx0 : (Lf/T0;Lf/lpt1;III)V
/*    */     //   179: goto -> 193
/*    */     //   182: getstatic f/js.vu0 : Lf/js;
/*    */     //   185: iconst_m1
/*    */     //   186: ldc_w 'No texture found'
/*    */     //   189: invokevirtual Pu : (ILjava/lang/String;)V
/*    */     //   192: return
/*    */     //   193: aload_1
/*    */     //   194: getstatic f/qo.A80 : J
/*    */     //   197: dup2
/*    */     //   198: lstore_2
/*    */     //   199: invokevirtual gV : (J)Z
/*    */     //   202: ifeq -> 217
/*    */     //   205: aload_0
/*    */     //   206: aload_1
/*    */     //   207: lload_2
/*    */     //   208: invokevirtual cOM1 : (J)Lf/dj;
/*    */     //   211: checkcast f/qo
/*    */     //   214: putfield xz : Lf/qo;
/*    */     //   217: aload_0
/*    */     //   218: aload_1
/*    */     //   219: new f/qo
/*    */     //   222: dup
/*    */     //   223: astore_0
/*    */     //   224: getstatic com/badlogic/gdx/graphics/Color.GREEN : Lcom/badlogic/gdx/graphics/Color;
/*    */     //   227: astore #4
/*    */     //   229: lload_2
/*    */     //   230: aload #4
/*    */     //   232: invokespecial <init> : (JLcom/badlogic/gdx/graphics/Color;)V
/*    */     //   235: aload_0
/*    */     //   236: invokevirtual Tz0 : (Lf/dj;)V
/*    */     //   239: aload_1
/*    */     //   240: putfield Xt : Lf/T0;
/*    */     //   243: return
/*    */     // Line number table:
/*    */     //   Java source line number -> byte code offset
/*    */     //   #1	-> 64
/*    */     //   #2	-> 73
/*    */     //   #3	-> 77
/*    */     //   #4	-> 89
/*    */     //   #5	-> 97
/*    */     //   #6	-> 102
/*    */     //   #7	-> 107
/*    */     //   #8	-> 111
/*    */     //   #9	-> 150
/*    */     //   #10	-> 182
/*    */     //   #11	-> 186
/*    */     //   #12	-> 194
/*    */     //   #13	-> 208
/*  1 */     //   #14	-> 211 } public static void r70(lpt1 paramlpt1, String paramString) { paramlpt1.co0(paramString, false, null); } public static void Pt0(lpt1 paramlpt1, String paramString) { paramlpt1.co0(paramString, false, null); } public static void UV(lpt1 paramlpt1, String paramString) { paramlpt1.co0(paramString, false, null); } private void DY(R70 paramR70) { float f2 = paramR70.xn.dK.x, f3 = paramR70.xn.dK.y, f4 = paramR70.xn.dK.z, f1 = paramR70.xn.dK.x; f2 = paramR70.xn.dK.y; f3 = paramR70.xn.dK.z; (So.k60().L5().PL(Wz0.gq(this.gv0.zf0(), 4, 0.5F).qw0(f2, f3, f4)).PL(Wz0.gq(this.gv0.zf0(), 9, 0.5F).qw0(f1, f2, f3)).Kr().Wz0(2.0F)).C00 = this.gv0.RC; this.gv0
/*    */ 
/*    */ 
/*    */       
/*  5 */       .wI = (So)So.k60().L5().PL(Wz0.gq(this.gv0.zf0(), 4, 0.5F).qw0(f2, f3, f4)).PL(Wz0.gq(this.gv0.zf0(), 9, 0.5F).qw0(f1, f2, f3)).Kr().Wz0(2.0F).mg(km.wI0.pB0); } private void eu(eo parameo) { float f2 = parameo.x, f3 = parameo.y, f4 = parameo.z, f1 = parameo.x; f2 = parameo.y; f3 = parameo.z; (So.k60().L5().PL(Wz0.gq(this.gv0.zf0(), 4, 0.5F).qw0(f2, f3, f4)).PL(Wz0.gq(this.gv0.zf0(), 9, 0.5F).qw0(f1, f2, f3)).Kr().Wz0(2.0F)).C00 = this.gv0.RC; this.gv0.wI = (So)So.k60().L5().PL(Wz0.gq(this.gv0.zf0(), 4, 0.5F).qw0(f2, f3, f4)).PL(Wz0.gq(this.gv0.zf0(), 9, 0.5F).qw0(f1, f2, f3)).Kr().Wz0(2.0F).mg(km.wI0.Ee); } public static void JD0(W1 paramW1) { L70.gq.kX((byte)paramW1.Wa0.go); gb[] arrayOfGb; int i;
/*    */     byte b;
/*  7 */     for (i = (arrayOfGb = (gb[])km.mI0.AN.YP.Z6).length, b = 0; b < i; ) { arrayOfGb[b].Lj0(); b++; }
/*  8 */      Xi xi; if ((xi = km.wI0.iJ0) != null) xi
/*  9 */         .AP();  } public final void mA(Ah paramAh) { // Byte code:
/*    */     //   0: aload_1
/*    */     //   1: ldc_w ''
/*    */     //   4: astore_2
/*    */     //   5: getstatic f/km.a3 : Lf/vh0;
/*    */     //   8: getfield Ct : Lf/Jo;
/*    */     //   11: getfield J : Lf/static;
/*    */     //   14: getfield lpt8 : Lf/eo;
/*    */     //   17: astore_3
/*    */     //   18: getfield K9 : Lf/lpt1;
/*    */     //   21: getfield Of : Lf/Eb;
/*    */     //   24: dup
/*    */     //   25: astore #4
/*    */     //   27: getfield pp0 : Lf/eo;
/*    */     //   30: dup
/*    */     //   31: astore #5
/*    */     //   33: getfield x : F
/*    */     //   36: aload_3
/*    */     //   37: getfield x : F
/*    */     //   40: dup
/*    */     //   41: fstore #6
/*    */     //   43: fcmpg
/*    */     //   44: ifgt -> 120
/*    */     //   47: aload #4
/*    */     //   49: getfield s60 : Lf/eo;
/*    */     //   52: dup
/*    */     //   53: astore #4
/*    */     //   55: getfield x : F
/*    */     //   58: fload #6
/*    */     //   60: fcmpl
/*    */     //   61: iflt -> 120
/*    */     //   64: aload #5
/*    */     //   66: getfield y : F
/*    */     //   69: aload_3
/*    */     //   70: getfield y : F
/*    */     //   73: dup
/*    */     //   74: fstore #6
/*    */     //   76: fcmpg
/*    */     //   77: ifgt -> 120
/*    */     //   80: aload #4
/*    */     //   82: getfield y : F
/*    */     //   85: fload #6
/*    */     //   87: fcmpl
/*    */     //   88: iflt -> 120
/*    */     //   91: aload #5
/*    */     //   93: getfield z : F
/*    */     //   96: aload_3
/*    */     //   97: getfield z : F
/*    */     //   100: dup
/*    */     //   101: fstore_3
/*    */     //   102: fcmpg
/*    */     //   103: ifgt -> 120
/*    */     //   106: aload #4
/*    */     //   108: getfield z : F
/*    */     //   111: fload_3
/*    */     //   112: fcmpl
/*    */     //   113: iflt -> 120
/*    */     //   116: iconst_1
/*    */     //   117: goto -> 121
/*    */     //   120: iconst_0
/*    */     //   121: ifeq -> 128
/*    */     //   124: ldc_w ' (Current)'
/*    */     //   127: astore_2
/*    */     //   128: aload_0
/*    */     //   129: getfield V3 : Lf/f8;
/*    */     //   132: dup
/*    */     //   133: dup
/*    */     //   134: astore_3
/*    */     //   135: aload_1
/*    */     //   136: new java/lang/StringBuilder
/*    */     //   139: dup
/*    */     //   140: aload_1
/*    */     //   141: swap
/*    */     //   142: invokespecial <init> : ()V
/*    */     //   145: getfield K9 : Lf/lpt1;
/*    */     //   148: getfield Zl0 : Ljava/lang/String;
/*    */     //   151: aload_2
/*    */     //   152: invokestatic Vr0 : (Ljava/lang/StringBuilder;Ljava/lang/String;Ljava/lang/String;)Ljava/lang/String;
/*    */     //   155: astore_2
/*    */     //   156: getfield wg0 : Lf/Ws0;
/*    */     //   159: invokevirtual getName : ()Ljava/lang/String;
/*    */     //   162: astore #4
/*    */     //   164: invokevirtual getClass : ()Ljava/lang/Class;
/*    */     //   167: pop
/*    */     //   168: new f/Qd0
/*    */     //   171: dup
/*    */     //   172: astore #5
/*    */     //   174: aload_3
/*    */     //   175: aload_2
/*    */     //   176: aload #4
/*    */     //   178: invokespecial <init> : (Lf/bF0;Ljava/lang/String;Ljava/lang/Object;)V
/*    */     //   181: getfield Ko : Ljava/util/ArrayList;
/*    */     //   184: invokevirtual size : ()I
/*    */     //   187: istore_2
/*    */     //   188: getstatic f/Q00.vz : Z
/*    */     //   191: ifne -> 214
/*    */     //   194: aload_3
/*    */     //   195: aload #5
/*    */     //   197: invokevirtual S7 : (Lf/bF0;)I
/*    */     //   200: ifge -> 206
/*    */     //   203: goto -> 214
/*    */     //   206: new java/lang/AssertionError
/*    */     //   209: dup
/*    */     //   210: invokespecial <init> : ()V
/*    */     //   213: athrow
/*    */     //   214: aload_1
/*    */     //   215: aload #5
/*    */     //   217: aload_1
/*    */     //   218: aload #5
/*    */     //   220: aload_1
/*    */     //   221: aload #5
/*    */     //   223: aload_1
/*    */     //   224: aload #5
/*    */     //   226: aload_1
/*    */     //   227: aload_3
/*    */     //   228: iload_2
/*    */     //   229: aload_3
/*    */     //   230: dup
/*    */     //   231: getfield Ko : Ljava/util/ArrayList;
/*    */     //   234: iload_2
/*    */     //   235: aload #5
/*    */     //   237: invokevirtual add : (ILjava/lang/Object;)V
/*    */     //   240: invokevirtual lpt1 : (ILf/bF0;)V
/*    */     //   243: getfield F40 : I
/*    */     //   246: invokestatic valueOf : (I)Ljava/lang/Integer;
/*    */     //   249: ldc_w 'Tileset: '
/*    */     //   252: swap
/*    */     //   253: invokevirtual Ra0 : (Ljava/lang/String;Ljava/lang/Object;)Lf/Qd0;
/*    */     //   256: pop
/*    */     //   257: getfield aK : I
/*    */     //   260: invokestatic valueOf : (I)Ljava/lang/Integer;
/*    */     //   263: ldc_w 'Footer: '
/*    */     //   266: swap
/*    */     //   267: invokevirtual Ra0 : (Ljava/lang/String;Ljava/lang/Object;)Lf/Qd0;
/*    */     //   270: pop
/*    */     //   271: getfield Kj0 : I
/*    */     //   274: invokestatic valueOf : (I)Ljava/lang/Integer;
/*    */     //   277: ldc_w 'Building ID: '
/*    */     //   280: swap
/*    */     //   281: invokevirtual Ra0 : (Ljava/lang/String;Ljava/lang/Object;)Lf/Qd0;
/*    */     //   284: pop
/*    */     //   285: getfield wg0 : Lf/Ws0;
/*    */     //   288: getfield Ga : S
/*    */     //   291: invokestatic valueOf : (S)Ljava/lang/Short;
/*    */     //   294: ldc_w 'HeaderID: '
/*    */     //   297: swap
/*    */     //   298: invokevirtual Ra0 : (Ljava/lang/String;Ljava/lang/Object;)Lf/Qd0;
/*    */     //   301: dup
/*    */     //   302: astore_2
/*    */     //   303: aload_1
/*    */     //   304: aload_2
/*    */     //   305: aload_1
/*    */     //   306: aload_2
/*    */     //   307: aload_1
/*    */     //   308: aload_2
/*    */     //   309: aload_1
/*    */     //   310: aload_2
/*    */     //   311: aload_1
/*    */     //   312: aload_2
/*    */     //   313: aload_1
/*    */     //   314: aload_2
/*    */     //   315: dup
/*    */     //   316: aload_1
/*    */     //   317: aload_2
/*    */     //   318: aload_1
/*    */     //   319: getfield wg0 : Lf/Ws0;
/*    */     //   322: getfield et : B
/*    */     //   325: invokestatic valueOf : (B)Ljava/lang/Byte;
/*    */     //   328: ldc_w 'Camera'
/*    */     //   331: swap
/*    */     //   332: invokevirtual Ra0 : (Ljava/lang/String;Ljava/lang/Object;)Lf/Qd0;
/*    */     //   335: pop
/*    */     //   336: getfield wg0 : Lf/Ws0;
/*    */     //   339: getfield ZC0 : S
/*    */     //   342: invokestatic valueOf : (S)Ljava/lang/Short;
/*    */     //   345: ldc_w 'Events ID'
/*    */     //   348: swap
/*    */     //   349: invokevirtual Ra0 : (Ljava/lang/String;Ljava/lang/Object;)Lf/Qd0;
/*    */     //   352: pop
/*    */     //   353: new f/eo
/*    */     //   356: dup
/*    */     //   357: astore_3
/*    */     //   358: aload_1
/*    */     //   359: getfield wg0 : Lf/Ws0;
/*    */     //   362: dup
/*    */     //   363: astore #4
/*    */     //   365: getfield Rb0 : I
/*    */     //   368: i2f
/*    */     //   369: aload #4
/*    */     //   371: dup
/*    */     //   372: getfield SE0 : I
/*    */     //   375: i2f
/*    */     //   376: fstore #4
/*    */     //   378: getfield ve : I
/*    */     //   381: i2f
/*    */     //   382: fload #4
/*    */     //   384: swap
/*    */     //   385: invokespecial <init> : (FFF)V
/*    */     //   388: ldc_w 'Fly Pos'
/*    */     //   391: aload_3
/*    */     //   392: invokevirtual Ra0 : (Ljava/lang/String;Ljava/lang/Object;)Lf/Qd0;
/*    */     //   395: pop
/*    */     //   396: getfield wg0 : Lf/Ws0;
/*    */     //   399: invokevirtual WD0 : ()Lf/vF;
/*    */     //   402: ldc_w 'MapType'
/*    */     //   405: swap
/*    */     //   406: invokevirtual Ra0 : (Ljava/lang/String;Ljava/lang/Object;)Lf/Qd0;
/*    */     //   409: pop
/*    */     //   410: getfield wg0 : Lf/Ws0;
/*    */     //   413: getfield Z5 : B
/*    */     //   416: invokestatic valueOf : (B)Ljava/lang/Byte;
/*    */     //   419: ldc_w 'Weather ID'
/*    */     //   422: swap
/*    */     //   423: invokevirtual Ra0 : (Ljava/lang/String;Ljava/lang/Object;)Lf/Qd0;
/*    */     //   426: pop
/*    */     //   427: getfield wg0 : Lf/Ws0;
/*    */     //   430: invokevirtual kJ : ()Z
/*    */     //   433: invokestatic valueOf : (Z)Ljava/lang/Boolean;
/*    */     //   436: ldc_w 'Can Fly'
/*    */     //   439: swap
/*    */     //   440: invokevirtual Ra0 : (Ljava/lang/String;Ljava/lang/Object;)Lf/Qd0;
/*    */     //   443: pop
/*    */     //   444: getfield wg0 : Lf/Ws0;
/*    */     //   447: invokevirtual cOM9 : ()Z
/*    */     //   450: invokestatic valueOf : (Z)Ljava/lang/Boolean;
/*    */     //   453: ldc_w 'Can Escape'
/*    */     //   456: swap
/*    */     //   457: invokevirtual Ra0 : (Ljava/lang/String;Ljava/lang/Object;)Lf/Qd0;
/*    */     //   460: pop
/*    */     //   461: getfield wg0 : Lf/Ws0;
/*    */     //   464: getfield d8 : B
/*    */     //   467: sipush #255
/*    */     //   470: iand
/*    */     //   471: invokestatic valueOf : (I)Ljava/lang/Integer;
/*    */     //   474: ldc_w 'NameID: '
/*    */     //   477: swap
/*    */     //   478: invokevirtual Ra0 : (Ljava/lang/String;Ljava/lang/Object;)Lf/Qd0;
/*    */     //   481: pop
/*    */     //   482: getfield wg0 : Lf/Ws0;
/*    */     //   485: getfield F70 : S
/*    */     //   488: invokestatic valueOf : (S)Ljava/lang/Short;
/*    */     //   491: ldc_w 'Matrix: '
/*    */     //   494: swap
/*    */     //   495: invokevirtual Ra0 : (Ljava/lang/String;Ljava/lang/Object;)Lf/Qd0;
/*    */     //   498: pop
/*    */     //   499: getfield wg0 : Lf/Ws0;
/*    */     //   502: getfield cC0 : Lf/eA0;
/*    */     //   505: dup
/*    */     //   506: astore_3
/*    */     //   507: ifnull -> 526
/*    */     //   510: aload_2
/*    */     //   511: aload_3
/*    */     //   512: getfield HQ : I
/*    */     //   515: invokestatic valueOf : (I)Ljava/lang/Integer;
/*    */     //   518: ldc_w 'Lightning'
/*    */     //   521: swap
/*    */     //   522: invokevirtual Ra0 : (Ljava/lang/String;Ljava/lang/Object;)Lf/Qd0;
/*    */     //   525: pop
/*    */     //   526: aload_1
/*    */     //   527: aload_0
/*    */     //   528: aload_1
/*    */     //   529: dup
/*    */     //   530: getfield K9 : Lf/lpt1;
/*    */     //   533: astore_2
/*    */     //   534: getfield F40 : I
/*    */     //   537: aload_2
/*    */     //   538: swap
/*    */     //   539: aload #5
/*    */     //   541: invokevirtual s : (Lf/lpt1;ILf/Qd0;)V
/*    */     //   544: getfield W7 : Lf/fQ;
/*    */     //   547: getfield Z8 : I
/*    */     //   550: dup
/*    */     //   551: istore_2
/*    */     //   552: ifle -> 659
/*    */     //   555: aload_1
/*    */     //   556: aload #5
/*    */     //   558: iload_2
/*    */     //   559: invokestatic valueOf : (I)Ljava/lang/Integer;
/*    */     //   562: ldc_w 'Buildings'
/*    */     //   565: swap
/*    */     //   566: invokevirtual Ra0 : (Ljava/lang/String;Ljava/lang/Object;)Lf/Qd0;
/*    */     //   569: astore_1
/*    */     //   570: getfield W7 : Lf/fQ;
/*    */     //   573: invokevirtual r30 : ()Lf/Hc0;
/*    */     //   576: astore_2
/*    */     //   577: aload_2
/*    */     //   578: invokevirtual hasNext : ()Z
/*    */     //   581: ifeq -> 659
/*    */     //   584: aload_0
/*    */     //   585: aload_1
/*    */     //   586: aload_2
/*    */     //   587: invokevirtual next : ()Ljava/lang/Object;
/*    */     //   590: checkcast f/lpt1
/*    */     //   593: dup
/*    */     //   594: dup
/*    */     //   595: astore_3
/*    */     //   596: new f/eo
/*    */     //   599: dup
/*    */     //   600: astore #4
/*    */     //   602: invokespecial <init> : ()V
/*    */     //   605: getfield mh : Lcom/badlogic/gdx/math/Matrix4;
/*    */     //   608: aload #4
/*    */     //   610: invokevirtual on0 : (Lf/eo;)Lf/eo;
/*    */     //   613: pop
/*    */     //   614: new f/Un
/*    */     //   617: dup
/*    */     //   618: astore #5
/*    */     //   620: aload_0
/*    */     //   621: aload #4
/*    */     //   623: aload #5
/*    */     //   625: ldc_w 'View'
/*    */     //   628: invokespecial <init> : (Ljava/lang/String;)V
/*    */     //   631: <illegal opcode> run : (Lf/Oe0;Lf/eo;)Ljava/lang/Runnable;
/*    */     //   636: invokevirtual tW : (Ljava/lang/Runnable;)V
/*    */     //   639: getfield Zl0 : Ljava/lang/String;
/*    */     //   642: aload #5
/*    */     //   644: invokevirtual Ra0 : (Ljava/lang/String;Ljava/lang/Object;)Lf/Qd0;
/*    */     //   647: astore #4
/*    */     //   649: aload_3
/*    */     //   650: iconst_m1
/*    */     //   651: aload #4
/*    */     //   653: invokevirtual s : (Lf/lpt1;ILf/Qd0;)V
/*    */     //   656: goto -> 577
/*    */     //   659: return
/*    */     // Line number table:
/*    */     //   Java source line number -> byte code offset
/*    */     //   #1	-> 8
/*    */     //   #2	-> 11
/*    */     //   #3	-> 14
/*    */     //   #4	-> 18
/*    */     //   #5	-> 27
/*    */     //   #6	-> 33
/*    */     //   #7	-> 124
/*    */     //   #8	-> 152
/*    */     //   #9	-> 156
/*    */     //   #10	-> 168
/*    */     //   #11	-> 181
/*    */     //   #12	-> 188
/*    */     //   #13	-> 243
/*    */     //   #14	-> 502
/*  9 */     //   #15	-> 512 } public final void d() { if (this.gv0 == null) return;  this.D0.Gb0(false); f81.Ko.clear(); byte b = 0; f8 f81; int i; JJ0[] arrayOfJJ0; if ((i = (f81 = this.V3).Ko.size()) > 0 && (arrayOfJJ0 = f81.PU) != null) { int j; byte b1; for (j = arrayOfJJ0.length, b1 = 0; b1 < j; ) { LL lL; IG iG; if ((iG = (IG)gy0.Hr0((gy0[])(lL = (arrayOfJJ0[b1]).J1).Xw, f81)) != null) { int k, m, n = (m = (k = lL.RM(f81) + 1) + b) + i; XJ0 xJ0; if ((xJ0 = iG.cD0) != null) { boolean bool; if ((bool = LL.kw) || xJ0.NW == f81.Ko.size() + i) { m = iG.cD0.at(b) + k; k = iG.cD0.at(n = b + i) + k;
/* 10 */               int i1 = iG.cD0.NW;
/* 11 */               int[] arrayOfInt = iG.cD0.mE0; iG.cD0.yE(0, i1, arrayOfInt); i1 = iG.cD0.NW - i; arrayOfInt = iG.cD0.mE0; n = i1 - b; System.arraycopy(arrayOfInt, n, arrayOfInt, b, n); iG.cD0.NW = i1; iG.cD0.em0(0, i1);
/* 12 */               if (bool || iG.cD0
/* 13 */                 .NW == f81
/* 14 */                 .Ko.size())
/* 15 */               { n = k; } else { throw new AssertionError(); }  } else { throw new AssertionError(); }  }  if (iG.z4 != null) { for (k = 0; k < i; ) { lL.x7(iG.z4[b + k]); k++; }
/* 16 */              if ((k = f81.Ko.size()) > 0)
/* 17 */             { System.arraycopy(iG.z4, 0, arrayOfIG, 0, b); k = b + i; int i1 = k - b; System.arraycopy(iG.z4, k, arrayOfIG, b, i1); IG[] arrayOfIG = new IG[k]; } else { iG.z4 = null; }  }  if (lL.bi(iG)) lL.KS(m, n - m);  }  b1++; }  }  this
/* 18 */       .D0.Gb0(true);
/*    */     
/* 20 */     for (Hc0 hc0 = this.gv0.wN.r30(); hc0.hasNext(); mA((Ah)hc0.next())); } public final void ED0(throws paramthrows) { for (Hc0 hc0 = this.z10.r30(); hc0.hasNext(); ) { K0 k0 = (K0)hc0.next(); this.hi0.jf0(k0.cC); }  this.z10.clear(); js.vu0.jf0(this.hi0); }
/* 21 */   public final void V90(throws paramthrows) { this.hi0.Xg0(km.wI0.dG(), km.wI0.k1()); this.hi0.ME(0, 0); js.vu0.Af(this.hi0); for (Hc0 hc0 = this.z10.r30(); hc0.hasNext(); ) { K0 k0; (k0 = (K0)hc0.next()).getClass(); Ur0 ur0 = km.wI0.fi0; float f3 = k0.Lx0.i00() * 0.25F + 0.1F; ((K0)hc0.next()).c30.Cn0.TG0(k0.Lx0.Ka() * 0.25F + 0.1F, f3, k0.Lx0.hA0() * 0.25F + 0.05F); if (D.hS()) { f3 = -ur0.G80; float f6 = ur0.Cn0; float f7 = ur0.QQ; float f9 = ur0.o6; k0.c30.gv0.zf0().jf0(k0.c30.Cn0, f3, f6, f7, f9); } else { k0.c30.gv0.zf0().w8(k0.c30.Cn0); }
/* 22 */        eo eo2 = k0.c30.Cn0;
/*    */       
/* 24 */       float f1 = ur0.G80, f2 = ur0.Cn0, f4 = ur0.QQ, f5 = ur0.o6; ur0.Xe.jf0(eo2, f1, f2, f4, f5); eo eo1;
/* 25 */       k0.cC
/*    */ 
/*    */         
/* 28 */         .ME((int)(eo1 = k0.c30.Cn0).x, (int)eo1.y);
/* 29 */       k0.cC.Xg0(120, 20); k0.cC.mM(); }  super
/* 30 */       .V90(paramthrows); }
/*    */ 
/*    */   
/*    */   public final void m6(zP paramzP, Qd0 paramQd0) {
/*    */     // Byte code:
/*    */     //   0: aload_1
/*    */     //   1: getfield cq : Lf/fQ;
/*    */     //   4: invokevirtual r30 : ()Lf/Hc0;
/*    */     //   7: astore_1
/*    */     //   8: aload_1
/*    */     //   9: invokevirtual hasNext : ()Z
/*    */     //   12: ifeq -> 151
/*    */     //   15: aload_1
/*    */     //   16: invokevirtual next : ()Ljava/lang/Object;
/*    */     //   19: checkcast f/zP
/*    */     //   22: dup
/*    */     //   23: astore_3
/*    */     //   24: new f/Un
/*    */     //   27: dup
/*    */     //   28: astore #4
/*    */     //   30: ldc_w 'View'
/*    */     //   33: invokespecial <init> : (Ljava/lang/String;)V
/*    */     //   36: new f/Un
/*    */     //   39: dup
/*    */     //   40: astore #5
/*    */     //   42: ldc_w 'Toggle Visibility'
/*    */     //   45: invokespecial <init> : (Ljava/lang/String;)V
/*    */     //   48: new f/vy
/*    */     //   51: dup
/*    */     //   52: dup
/*    */     //   53: astore #6
/*    */     //   55: iconst_2
/*    */     //   56: anewarray f/JG0
/*    */     //   59: dup
/*    */     //   60: dup
/*    */     //   61: iconst_0
/*    */     //   62: aload #4
/*    */     //   64: aastore
/*    */     //   65: iconst_1
/*    */     //   66: aload #5
/*    */     //   68: aastore
/*    */     //   69: invokespecial <init> : ([Lf/JG0;)V
/*    */     //   72: fconst_1
/*    */     //   73: putfield ne : F
/*    */     //   76: getfield zx0 : Lf/fQ;
/*    */     //   79: invokevirtual r30 : ()Lf/Hc0;
/*    */     //   82: astore #7
/*    */     //   84: aload #7
/*    */     //   86: invokevirtual hasNext : ()Z
/*    */     //   89: ifeq -> 122
/*    */     //   92: aload #4
/*    */     //   94: aload_0
/*    */     //   95: aload #7
/*    */     //   97: invokevirtual next : ()Ljava/lang/Object;
/*    */     //   100: checkcast f/R70
/*    */     //   103: dup
/*    */     //   104: getfield xn : Lf/COM6;
/*    */     //   107: getfield Dr : I
/*    */     //   110: pop
/*    */     //   111: <illegal opcode> run : (Lf/Oe0;Lf/R70;)Ljava/lang/Runnable;
/*    */     //   116: invokevirtual tW : (Ljava/lang/Runnable;)V
/*    */     //   119: goto -> 84
/*    */     //   122: aload_0
/*    */     //   123: aload_3
/*    */     //   124: aload_2
/*    */     //   125: aload_3
/*    */     //   126: aload #5
/*    */     //   128: aload_3
/*    */     //   129: <illegal opcode> run : (Lf/zP;)Ljava/lang/Runnable;
/*    */     //   134: invokevirtual tW : (Ljava/lang/Runnable;)V
/*    */     //   137: getfield v30 : Ljava/lang/String;
/*    */     //   140: aload #6
/*    */     //   142: invokevirtual Ra0 : (Ljava/lang/String;Ljava/lang/Object;)Lf/Qd0;
/*    */     //   145: invokevirtual m6 : (Lf/zP;Lf/Qd0;)V
/*    */     //   148: goto -> 8
/*    */     //   151: return
/*    */     // Line number table:
/*    */     //   Java source line number -> byte code offset
/*    */     //   #1	-> 1
/*    */     //   #2	-> 4
/*    */     //   #3	-> 9
/*    */     //   #4	-> 73
/*    */     //   #5	-> 76
/*    */   }
/*    */   
/*    */   public final void s(lpt1 paramlpt1, int paramInt, Qd0 paramQd0) {
/*    */     // Byte code:
/*    */     //   0: aload_1
/*    */     //   1: aload_3
/*    */     //   2: aload_1
/*    */     //   3: aload_3
/*    */     //   4: aload_1
/*    */     //   5: aload_3
/*    */     //   6: aload_1
/*    */     //   7: aload_3
/*    */     //   8: aload_1
/*    */     //   9: getfield jx : I
/*    */     //   12: invokestatic valueOf : (I)Ljava/lang/Integer;
/*    */     //   15: ldc_w 'Building ID'
/*    */     //   18: swap
/*    */     //   19: invokevirtual Ra0 : (Ljava/lang/String;Ljava/lang/Object;)Lf/Qd0;
/*    */     //   22: pop
/*    */     //   23: getfield bv : Z
/*    */     //   26: invokestatic valueOf : (Z)Ljava/lang/Boolean;
/*    */     //   29: ldc_w 'Is Exterior'
/*    */     //   32: swap
/*    */     //   33: invokevirtual Ra0 : (Ljava/lang/String;Ljava/lang/Object;)Lf/Qd0;
/*    */     //   36: pop
/*    */     //   37: getfield mh : Lcom/badlogic/gdx/math/Matrix4;
/*    */     //   40: new f/eo
/*    */     //   43: dup
/*    */     //   44: invokespecial <init> : ()V
/*    */     //   47: invokevirtual on0 : (Lf/eo;)Lf/eo;
/*    */     //   50: ldc_w 'Position'
/*    */     //   53: swap
/*    */     //   54: invokevirtual Ra0 : (Ljava/lang/String;Ljava/lang/Object;)Lf/Qd0;
/*    */     //   57: pop
/*    */     //   58: getfield lz : Lf/fQ;
/*    */     //   61: getfield Z8 : I
/*    */     //   64: invokestatic valueOf : (I)Ljava/lang/Integer;
/*    */     //   67: ldc_w 'Animations'
/*    */     //   70: swap
/*    */     //   71: invokevirtual Ra0 : (Ljava/lang/String;Ljava/lang/Object;)Lf/Qd0;
/*    */     //   74: astore #4
/*    */     //   76: getfield hI : Ljava/util/HashMap;
/*    */     //   79: dup
/*    */     //   80: astore #5
/*    */     //   82: ifnull -> 177
/*    */     //   85: aload_1
/*    */     //   86: aload #4
/*    */     //   88: aload #5
/*    */     //   90: invokevirtual size : ()I
/*    */     //   93: invokestatic valueOf : (I)Ljava/lang/Integer;
/*    */     //   96: ldc_w 'Material'
/*    */     //   99: swap
/*    */     //   100: invokevirtual Ra0 : (Ljava/lang/String;Ljava/lang/Object;)Lf/Qd0;
/*    */     //   103: astore #5
/*    */     //   105: getfield hI : Ljava/util/HashMap;
/*    */     //   108: invokevirtual keySet : ()Ljava/util/Set;
/*    */     //   111: invokeinterface iterator : ()Ljava/util/Iterator;
/*    */     //   116: astore #6
/*    */     //   118: aload #6
/*    */     //   120: invokeinterface hasNext : ()Z
/*    */     //   125: ifeq -> 177
/*    */     //   128: aload #5
/*    */     //   130: aload #6
/*    */     //   132: invokeinterface next : ()Ljava/lang/Object;
/*    */     //   137: checkcast java/lang/String
/*    */     //   140: dup
/*    */     //   141: astore #7
/*    */     //   143: new f/Un
/*    */     //   146: dup
/*    */     //   147: astore #8
/*    */     //   149: aload_1
/*    */     //   150: aload #7
/*    */     //   152: aload #8
/*    */     //   154: ldc_w 'Play'
/*    */     //   157: invokespecial <init> : (Ljava/lang/String;)V
/*    */     //   160: <illegal opcode> run : (Lf/lpt1;Ljava/lang/String;)Ljava/lang/Runnable;
/*    */     //   165: invokevirtual tW : (Ljava/lang/Runnable;)V
/*    */     //   168: aload #8
/*    */     //   170: invokevirtual Ra0 : (Ljava/lang/String;Ljava/lang/Object;)Lf/Qd0;
/*    */     //   173: pop
/*    */     //   174: goto -> 118
/*    */     //   177: aload_1
/*    */     //   178: getfield Cv0 : Ljava/util/HashMap;
/*    */     //   181: dup
/*    */     //   182: astore #5
/*    */     //   184: ifnull -> 279
/*    */     //   187: aload_1
/*    */     //   188: aload #4
/*    */     //   190: aload #5
/*    */     //   192: invokevirtual size : ()I
/*    */     //   195: invokestatic valueOf : (I)Ljava/lang/Integer;
/*    */     //   198: ldc_w 'Texture'
/*    */     //   201: swap
/*    */     //   202: invokevirtual Ra0 : (Ljava/lang/String;Ljava/lang/Object;)Lf/Qd0;
/*    */     //   205: astore #5
/*    */     //   207: getfield Cv0 : Ljava/util/HashMap;
/*    */     //   210: invokevirtual keySet : ()Ljava/util/Set;
/*    */     //   213: invokeinterface iterator : ()Ljava/util/Iterator;
/*    */     //   218: astore #6
/*    */     //   220: aload #6
/*    */     //   222: invokeinterface hasNext : ()Z
/*    */     //   227: ifeq -> 279
/*    */     //   230: aload #5
/*    */     //   232: aload #6
/*    */     //   234: invokeinterface next : ()Ljava/lang/Object;
/*    */     //   239: checkcast java/lang/String
/*    */     //   242: dup
/*    */     //   243: astore #7
/*    */     //   245: new f/Un
/*    */     //   248: dup
/*    */     //   249: astore #8
/*    */     //   251: aload_1
/*    */     //   252: aload #7
/*    */     //   254: aload #8
/*    */     //   256: ldc_w 'Play'
/*    */     //   259: invokespecial <init> : (Ljava/lang/String;)V
/*    */     //   262: <illegal opcode> run : (Lf/lpt1;Ljava/lang/String;)Ljava/lang/Runnable;
/*    */     //   267: invokevirtual tW : (Ljava/lang/Runnable;)V
/*    */     //   270: aload #8
/*    */     //   272: invokevirtual Ra0 : (Ljava/lang/String;Ljava/lang/Object;)Lf/Qd0;
/*    */     //   275: pop
/*    */     //   276: goto -> 220
/*    */     //   279: aload_1
/*    */     //   280: getfield Eo : Ljava/util/HashMap;
/*    */     //   283: dup
/*    */     //   284: astore #5
/*    */     //   286: ifnull -> 381
/*    */     //   289: aload_1
/*    */     //   290: aload #4
/*    */     //   292: aload #5
/*    */     //   294: invokevirtual size : ()I
/*    */     //   297: invokestatic valueOf : (I)Ljava/lang/Integer;
/*    */     //   300: ldc_w 'UV'
/*    */     //   303: swap
/*    */     //   304: invokevirtual Ra0 : (Ljava/lang/String;Ljava/lang/Object;)Lf/Qd0;
/*    */     //   307: astore #5
/*    */     //   309: getfield Eo : Ljava/util/HashMap;
/*    */     //   312: invokevirtual keySet : ()Ljava/util/Set;
/*    */     //   315: invokeinterface iterator : ()Ljava/util/Iterator;
/*    */     //   320: astore #6
/*    */     //   322: aload #6
/*    */     //   324: invokeinterface hasNext : ()Z
/*    */     //   329: ifeq -> 381
/*    */     //   332: aload #5
/*    */     //   334: aload #6
/*    */     //   336: invokeinterface next : ()Ljava/lang/Object;
/*    */     //   341: checkcast java/lang/String
/*    */     //   344: dup
/*    */     //   345: astore #7
/*    */     //   347: new f/Un
/*    */     //   350: dup
/*    */     //   351: astore #8
/*    */     //   353: aload_1
/*    */     //   354: aload #7
/*    */     //   356: aload #8
/*    */     //   358: ldc_w 'Play'
/*    */     //   361: invokespecial <init> : (Ljava/lang/String;)V
/*    */     //   364: <illegal opcode> run : (Lf/lpt1;Ljava/lang/String;)Ljava/lang/Runnable;
/*    */     //   369: invokevirtual tW : (Ljava/lang/Runnable;)V
/*    */     //   372: aload #8
/*    */     //   374: invokevirtual Ra0 : (Ljava/lang/String;Ljava/lang/Object;)Lf/Qd0;
/*    */     //   377: pop
/*    */     //   378: goto -> 322
/*    */     //   381: aload_1
/*    */     //   382: getfield lz : Lf/fQ;
/*    */     //   385: invokevirtual r30 : ()Lf/Hc0;
/*    */     //   388: astore #5
/*    */     //   390: aload #5
/*    */     //   392: invokevirtual hasNext : ()Z
/*    */     //   395: ifeq -> 445
/*    */     //   398: aload #4
/*    */     //   400: aload #5
/*    */     //   402: invokevirtual next : ()Ljava/lang/Object;
/*    */     //   405: checkcast java/lang/String
/*    */     //   408: dup
/*    */     //   409: astore #6
/*    */     //   411: new f/Un
/*    */     //   414: dup
/*    */     //   415: astore #7
/*    */     //   417: aload_1
/*    */     //   418: aload #6
/*    */     //   420: aload #7
/*    */     //   422: ldc_w 'Play'
/*    */     //   425: invokespecial <init> : (Ljava/lang/String;)V
/*    */     //   428: <illegal opcode> run : (Lf/lpt1;Ljava/lang/String;)Ljava/lang/Runnable;
/*    */     //   433: invokevirtual tW : (Ljava/lang/Runnable;)V
/*    */     //   436: aload #7
/*    */     //   438: invokevirtual Ra0 : (Ljava/lang/String;Ljava/lang/Object;)Lf/Qd0;
/*    */     //   441: pop
/*    */     //   442: goto -> 390
/*    */     //   445: aload_1
/*    */     //   446: aload_3
/*    */     //   447: aload_1
/*    */     //   448: getfield vC0 : Lf/fQ;
/*    */     //   451: getfield Z8 : I
/*    */     //   454: invokestatic valueOf : (I)Ljava/lang/Integer;
/*    */     //   457: ldc_w 'Nodes'
/*    */     //   460: swap
/*    */     //   461: invokevirtual Ra0 : (Ljava/lang/String;Ljava/lang/Object;)Lf/Qd0;
/*    */     //   464: astore #4
/*    */     //   466: getfield vC0 : Lf/fQ;
/*    */     //   469: invokevirtual r30 : ()Lf/Hc0;
/*    */     //   472: astore #5
/*    */     //   474: aload #5
/*    */     //   476: invokevirtual hasNext : ()Z
/*    */     //   479: ifeq -> 520
/*    */     //   482: aload_0
/*    */     //   483: aload #4
/*    */     //   485: aload #5
/*    */     //   487: invokevirtual next : ()Ljava/lang/Object;
/*    */     //   490: checkcast f/zP
/*    */     //   493: dup
/*    */     //   494: dup
/*    */     //   495: astore #6
/*    */     //   497: getfield v30 : Ljava/lang/String;
/*    */     //   500: astore #7
/*    */     //   502: getfield z7 : Lf/eo;
/*    */     //   505: aload #7
/*    */     //   507: swap
/*    */     //   508: invokevirtual Ra0 : (Ljava/lang/String;Ljava/lang/Object;)Lf/Qd0;
/*    */     //   511: aload #6
/*    */     //   513: swap
/*    */     //   514: invokevirtual m6 : (Lf/zP;Lf/Qd0;)V
/*    */     //   517: goto -> 474
/*    */     //   520: aload_1
/*    */     //   521: aload_3
/*    */     //   522: aload_1
/*    */     //   523: getfield xl0 : Lf/fQ;
/*    */     //   526: getfield Z8 : I
/*    */     //   529: invokestatic valueOf : (I)Ljava/lang/Integer;
/*    */     //   532: ldc_w 'Materials'
/*    */     //   535: swap
/*    */     //   536: invokevirtual Ra0 : (Ljava/lang/String;Ljava/lang/Object;)Lf/Qd0;
/*    */     //   539: astore_3
/*    */     //   540: getfield xl0 : Lf/fQ;
/*    */     //   543: invokevirtual r30 : ()Lf/Hc0;
/*    */     //   546: astore #4
/*    */     //   548: aload #4
/*    */     //   550: invokevirtual hasNext : ()Z
/*    */     //   553: ifeq -> 989
/*    */     //   556: aload_1
/*    */     //   557: aload #4
/*    */     //   559: invokevirtual next : ()Ljava/lang/Object;
/*    */     //   562: checkcast f/T0
/*    */     //   565: astore #5
/*    */     //   567: new f/Fy0
/*    */     //   570: dup
/*    */     //   571: dup
/*    */     //   572: astore #6
/*    */     //   574: invokespecial <init> : ()V
/*    */     //   577: ldc_w 'spritebutton'
/*    */     //   580: invokevirtual Xu : (Ljava/lang/String;)V
/*    */     //   583: getfield Cx0 : Lf/Ew;
/*    */     //   586: dup
/*    */     //   587: astore #7
/*    */     //   589: ifnull -> 672
/*    */     //   592: aload #7
/*    */     //   594: aload #5
/*    */     //   596: getfield Xy0 : Ljava/lang/String;
/*    */     //   599: astore #7
/*    */     //   601: getfield W60 : Lf/f7;
/*    */     //   604: aload #7
/*    */     //   606: invokevirtual pd0 : (Ljava/lang/Object;)Ljava/lang/Object;
/*    */     //   609: checkcast com/badlogic/gdx/graphics/Texture
/*    */     //   612: dup
/*    */     //   613: astore #7
/*    */     //   615: ifnull -> 672
/*    */     //   618: aload #6
/*    */     //   620: dup
/*    */     //   621: dup2
/*    */     //   622: getfield As : Lf/rH;
/*    */     //   625: iconst_1
/*    */     //   626: anewarray com/badlogic/gdx/graphics/Texture
/*    */     //   629: dup
/*    */     //   630: iconst_0
/*    */     //   631: aload #7
/*    */     //   633: aastore
/*    */     //   634: invokevirtual Yo : ([Lcom/badlogic/gdx/graphics/Texture;)V
/*    */     //   637: getfield As : Lf/rH;
/*    */     //   640: bipush #32
/*    */     //   642: bipush #32
/*    */     //   644: invokevirtual tL : (II)V
/*    */     //   647: getfield As : Lf/rH;
/*    */     //   650: getstatic f/et.Wi0 : Lf/et;
/*    */     //   653: invokevirtual uE0 : (Lf/et;)V
/*    */     //   656: getfield As : Lf/rH;
/*    */     //   659: dup
/*    */     //   660: getfield Tn : I
/*    */     //   663: iconst_2
/*    */     //   664: iadd
/*    */     //   665: bipush #8
/*    */     //   667: swap
/*    */     //   668: invokevirtual zT : (II)Lf/JG0;
/*    */     //   671: pop
/*    */     //   672: aload #5
/*    */     //   674: aload_3
/*    */     //   675: aload #5
/*    */     //   677: aload #6
/*    */     //   679: aload_0
/*    */     //   680: aload #5
/*    */     //   682: new f/Un
/*    */     //   685: ldc_w 'View'
/*    */     //   688: invokespecial <init> : (Ljava/lang/String;)V
/*    */     //   691: aload_1
/*    */     //   692: iload_2
/*    */     //   693: <illegal opcode> run : (Lf/Oe0;Lf/T0;Lf/lpt1;I)Ljava/lang/Runnable;
/*    */     //   698: invokevirtual tW : (Ljava/lang/Runnable;)V
/*    */     //   701: getfield Xy0 : Ljava/lang/String;
/*    */     //   704: aload #6
/*    */     //   706: invokevirtual Ra0 : (Ljava/lang/String;Ljava/lang/Object;)Lf/Qd0;
/*    */     //   709: astore #5
/*    */     //   711: getfield ra0 : Lf/fQ;
/*    */     //   714: invokevirtual r30 : ()Lf/Hc0;
/*    */     //   717: astore #6
/*    */     //   719: aload #6
/*    */     //   721: invokevirtual hasNext : ()Z
/*    */     //   724: ifeq -> 548
/*    */     //   727: aload #6
/*    */     //   729: invokevirtual next : ()Ljava/lang/Object;
/*    */     //   732: checkcast f/dj
/*    */     //   735: dup
/*    */     //   736: astore #7
/*    */     //   738: aload #5
/*    */     //   740: ldc_w 'Attr'
/*    */     //   743: aload #7
/*    */     //   745: invokevirtual Ra0 : (Ljava/lang/String;Ljava/lang/Object;)Lf/Qd0;
/*    */     //   748: astore #8
/*    */     //   750: getfield tL : J
/*    */     //   753: dup2
/*    */     //   754: lstore #9
/*    */     //   756: getstatic f/Xf0.xZ : J
/*    */     //   759: lcmp
/*    */     //   760: ifne -> 839
/*    */     //   763: aload #7
/*    */     //   765: checkcast f/Xf0
/*    */     //   768: getfield S90 : I
/*    */     //   771: dup
/*    */     //   772: istore #7
/*    */     //   774: ldc_w 'GL_NONE'
/*    */     //   777: astore #9
/*    */     //   779: sipush #1028
/*    */     //   782: if_icmpeq -> 820
/*    */     //   785: iload #7
/*    */     //   787: sipush #1029
/*    */     //   790: if_icmpeq -> 812
/*    */     //   793: iload #7
/*    */     //   795: sipush #1032
/*    */     //   798: if_icmpeq -> 804
/*    */     //   801: goto -> 825
/*    */     //   804: ldc_w 'GL_FRONT_AND_BACK'
/*    */     //   807: astore #9
/*    */     //   809: goto -> 825
/*    */     //   812: ldc_w 'GL_BACK'
/*    */     //   815: astore #9
/*    */     //   817: goto -> 825
/*    */     //   820: ldc_w 'GL_FRONT'
/*    */     //   823: astore #9
/*    */     //   825: aload #8
/*    */     //   827: ldc_w 'CullMode'
/*    */     //   830: aload #9
/*    */     //   832: invokevirtual Ra0 : (Ljava/lang/String;Ljava/lang/Object;)Lf/Qd0;
/*    */     //   835: pop
/*    */     //   836: goto -> 719
/*    */     //   839: lload #9
/*    */     //   841: getstatic f/IF.kA0 : J
/*    */     //   844: lcmp
/*    */     //   845: ifne -> 926
/*    */     //   848: aload #7
/*    */     //   850: checkcast f/IF
/*    */     //   853: getfield Q5 : I
/*    */     //   856: ldc_w ''
/*    */     //   859: astore #7
/*    */     //   861: tableswitch default -> 888, 513 -> 907, 514 -> 899, 515 -> 891
/*    */     //   888: goto -> 912
/*    */     //   891: ldc_w 'GL_LEQUAL'
/*    */     //   894: astore #7
/*    */     //   896: goto -> 912
/*    */     //   899: ldc_w 'GL_EQUAL'
/*    */     //   902: astore #7
/*    */     //   904: goto -> 912
/*    */     //   907: ldc_w 'GL_LESS'
/*    */     //   910: astore #7
/*    */     //   912: aload #8
/*    */     //   914: ldc_w 'DepthFunc'
/*    */     //   917: aload #7
/*    */     //   919: invokevirtual Ra0 : (Ljava/lang/String;Ljava/lang/Object;)Lf/Qd0;
/*    */     //   922: pop
/*    */     //   923: goto -> 719
/*    */     //   926: lload #9
/*    */     //   928: getstatic f/qo.iu0 : J
/*    */     //   931: lcmp
/*    */     //   932: ifne -> 956
/*    */     //   935: aload #8
/*    */     //   937: aload #7
/*    */     //   939: checkcast f/qo
/*    */     //   942: getfield vF0 : Lcom/badlogic/gdx/graphics/Color;
/*    */     //   945: ldc_w 'Color'
/*    */     //   948: swap
/*    */     //   949: invokevirtual Ra0 : (Ljava/lang/String;Ljava/lang/Object;)Lf/Qd0;
/*    */     //   952: pop
/*    */     //   953: goto -> 719
/*    */     //   956: lload #9
/*    */     //   958: getstatic f/zc.U7 : J
/*    */     //   961: lcmp
/*    */     //   962: ifne -> 719
/*    */     //   965: aload #8
/*    */     //   967: aload #7
/*    */     //   969: checkcast f/zc
/*    */     //   972: getfield yg0 : F
/*    */     //   975: invokestatic valueOf : (F)Ljava/lang/Float;
/*    */     //   978: ldc_w 'Opacity'
/*    */     //   981: swap
/*    */     //   982: invokevirtual Ra0 : (Ljava/lang/String;Ljava/lang/Object;)Lf/Qd0;
/*    */     //   985: pop
/*    */     //   986: goto -> 719
/*    */     //   989: return
/*    */     // Line number table:
/*    */     //   Java source line number -> byte code offset
/*    */     //   #1	-> 583
/*    */     //   #2	-> 596
/*    */     //   #3	-> 601
/*    */     //   #4	-> 622
/*    */     //   #5	-> 626
/*    */     //   #6	-> 637
/*    */     //   #7	-> 644
/*    */     //   #8	-> 647
/*    */     //   #9	-> 650
/*    */     //   #10	-> 656
/*    */     //   #11	-> 660
/*    */     //   #12	-> 668
/*    */     //   #13	-> 711
/*    */     //   #14	-> 721
/*    */     //   #15	-> 750
/*    */   } }


/* Location:              /Users/vnnsnnt/Documents/Codespace/JavaWorkspace/RedTrainer/src/main/java/org/trainer/client/PokeMMO.jar!/f/Oe0.class
 * Java compiler version: 8 (52.0)
 * JD-Core Version:       1.1.3
 */