/* 1 */ package f;public class oF0 implements iq0 { public final int Vv(ZH paramZH, int paramInt1, int paramInt2, boolean paramBoolean1, boolean paramBoolean2) { int i, j; boolean bool; int[] arrayOfInt = new int[4]; if (paramBoolean2) { i = paramInt1; } else { i = paramInt2; }  if (paramBoolean2)
/* 2 */     { j = paramZH.Con.ju; }
/*   */     else
/* 4 */     { j = paramZH.Con.Og0; }  if (paramBoolean1) { bool = true; } else { bool = false; }  while (i != j) { if (paramBoolean2) { paramInt1 = i; } else { paramInt2 = i; }
/*   */       
/* 6 */       int m = paramZH.Con.Fl(paramInt1, paramInt2);
/* 7 */       this.Mr.set(m); Color color; int n = (int)((color = this.Mr).r * 255.0F); arrayOfInt[0] = n; int i1 = (int)(color.g * 255.0F); arrayOfInt[1] = i1; int i2 = (int)(color.b * 255.0F); arrayOfInt[2] = i2; arrayOfInt[3] = k; int k; if ((k = (int)(color.a * 255.0F)) == bool) return i;  if (!paramBoolean1 && (n != 0 || i1 != 0 || i2 != 0 || k != 255)) System.out.println(paramInt1 + "  " + paramInt2 + " " + arrayOfInt + " ");  i++; }  return 0; }
/*   */ 
/*   */   
/*   */   public static Pattern bE0 = Pattern.compile("(.+)_(\\d+)$");
/*   */   public boolean GH0;
/*   */   public boolean d;
/*   */   public int ts0;
/*   */   public int WW;
/*   */   public Uc ah0;
/*   */   public int yw0;
/*   */   public boolean p80;
/*   */   public boolean Yn;
/*   */   public boolean Pf;
/*   */   public Color LS;
/*   */   public final fQ dA;
/*   */   public eB0 g8;
/*   */   public Color Mr;
/*   */   
/*   */   public oF0(int paramInt1, int paramInt2, Uc paramUc, int paramInt3, boolean paramBoolean) {
/*   */     this();
/*   */     eV eV;
/*   */     this(paramInt1, paramInt2, paramUc, paramInt3, paramBoolean, false, false, this);
/*   */   }
/*   */   
/*   */   public oF0(int paramInt1, int paramInt2, Uc paramUc, int paramInt3, boolean paramBoolean, eB0 parameB0) {
/*   */     this(paramInt1, paramInt2, paramUc, paramInt3, paramBoolean, false, false, parameB0);
/*   */   }
/*   */   
/*   */   public oF0(int paramInt1, int paramInt2, Uc paramUc, int paramInt3, boolean paramBoolean1, boolean paramBoolean2, boolean paramBoolean3, eB0 parameB0) {
/*   */     Color color2;
/*   */     fQ fQ1;
/*   */     Color color1;
/*   */     this(0.0F, 0.0F, 0.0F, 0.0F);
/*   */     this.LS = this;
/*   */     this();
/*   */     this.dA = this;
/*   */     this();
/*   */     this.Mr = this;
/*   */     this.ts0 = paramInt1;
/*   */     this.WW = paramInt2;
/*   */     this.ah0 = paramUc;
/*   */     this.yw0 = paramInt3;
/*   */     this.p80 = paramBoolean1;
/*   */     this.Yn = paramBoolean2;
/*   */     this.Pf = paramBoolean3;
/*   */     this.g8 = parameB0;
/*   */   }
/*   */   
/*   */   public synchronized cx0 EI0(String paramString, ZH paramZH) {
/*   */     // Byte code:
/*   */     //   0: aload_0
/*   */     //   1: getfield d : Z
/*   */     //   4: ifeq -> 9
/*   */     //   7: aconst_null
/*   */     //   8: areturn
/*   */     //   9: aload_1
/*   */     //   10: ifnull -> 88
/*   */     //   13: aload_0
/*   */     //   14: dup
/*   */     //   15: monitorenter
/*   */     //   16: getfield dA : Lf/fQ;
/*   */     //   19: invokevirtual r30 : ()Lf/Hc0;
/*   */     //   22: astore_3
/*   */     //   23: aload_3
/*   */     //   24: invokevirtual hasNext : ()Z
/*   */     //   27: ifeq -> 58
/*   */     //   30: aload_3
/*   */     //   31: invokevirtual next : ()Ljava/lang/Object;
/*   */     //   34: checkcast f/jk0
/*   */     //   37: getfield XF : Lf/Nn;
/*   */     //   40: aload_1
/*   */     //   41: invokevirtual pd0 : (Ljava/lang/Object;)Ljava/lang/Object;
/*   */     //   44: checkcast f/cx0
/*   */     //   47: dup
/*   */     //   48: astore #4
/*   */     //   50: ifnull -> 23
/*   */     //   53: aload_0
/*   */     //   54: monitorexit
/*   */     //   55: goto -> 63
/*   */     //   58: aload_0
/*   */     //   59: aconst_null
/*   */     //   60: astore #4
/*   */     //   62: monitorexit
/*   */     //   63: aload #4
/*   */     //   65: ifnonnull -> 71
/*   */     //   68: goto -> 88
/*   */     //   71: new f/JU
/*   */     //   74: dup
/*   */     //   75: ldc 'Pixmap has already been packed with name: '
/*   */     //   77: aload_1
/*   */     //   78: invokestatic tF0 : (Ljava/lang/String;Ljava/lang/String;)Ljava/lang/String;
/*   */     //   81: invokespecial <init> : (Ljava/lang/String;)V
/*   */     //   84: athrow
/*   */     //   85: aload_0
/*   */     //   86: monitorexit
/*   */     //   87: athrow
/*   */     //   88: aload_1
/*   */     //   89: aconst_null
/*   */     //   90: astore_3
/*   */     //   91: ifnull -> 747
/*   */     //   94: aload_1
/*   */     //   95: ldc '.9'
/*   */     //   97: invokevirtual endsWith : (Ljava/lang/String;)Z
/*   */     //   100: ifeq -> 747
/*   */     //   103: aload_0
/*   */     //   104: aload_2
/*   */     //   105: new f/B60
/*   */     //   108: dup
/*   */     //   109: astore_3
/*   */     //   110: aload_2
/*   */     //   111: getfield Con : Lcom/badlogic/gdx/graphics/g2d/Gdx2DPixmap;
/*   */     //   114: dup
/*   */     //   115: getfield ju : I
/*   */     //   118: iconst_2
/*   */     //   119: isub
/*   */     //   120: istore #4
/*   */     //   122: getfield Og0 : I
/*   */     //   125: iconst_2
/*   */     //   126: isub
/*   */     //   127: istore #5
/*   */     //   129: iconst_0
/*   */     //   130: iconst_0
/*   */     //   131: iload #4
/*   */     //   133: iload #5
/*   */     //   135: invokespecial <init> : (IIII)V
/*   */     //   138: new f/ZH
/*   */     //   141: dup
/*   */     //   142: dup
/*   */     //   143: astore #4
/*   */     //   145: aload_2
/*   */     //   146: dup
/*   */     //   147: getfield Con : Lcom/badlogic/gdx/graphics/g2d/Gdx2DPixmap;
/*   */     //   150: dup
/*   */     //   151: getfield ju : I
/*   */     //   154: iconst_2
/*   */     //   155: isub
/*   */     //   156: istore #5
/*   */     //   158: getfield Og0 : I
/*   */     //   161: iconst_2
/*   */     //   162: isub
/*   */     //   163: istore #6
/*   */     //   165: invokevirtual TU : ()Lf/Uc;
/*   */     //   168: astore #7
/*   */     //   170: iload #5
/*   */     //   172: iload #6
/*   */     //   174: aload #7
/*   */     //   176: invokespecial <init> : (IILf/Uc;)V
/*   */     //   179: getstatic f/y1.Zj : Lf/y1;
/*   */     //   182: invokevirtual r1 : (Lf/y1;)V
/*   */     //   185: iconst_1
/*   */     //   186: iconst_0
/*   */     //   187: iconst_1
/*   */     //   188: iconst_1
/*   */     //   189: invokevirtual Vv : (Lf/ZH;IIZZ)I
/*   */     //   192: dup
/*   */     //   193: istore #5
/*   */     //   195: aload_0
/*   */     //   196: aload_2
/*   */     //   197: aload_0
/*   */     //   198: aload_2
/*   */     //   199: aload_0
/*   */     //   200: aload_2
/*   */     //   201: aload_0
/*   */     //   202: aload_2
/*   */     //   203: aload_0
/*   */     //   204: aload_2
/*   */     //   205: iload #5
/*   */     //   207: iconst_0
/*   */     //   208: iconst_0
/*   */     //   209: iconst_1
/*   */     //   210: invokevirtual Vv : (Lf/ZH;IIZZ)I
/*   */     //   213: istore #6
/*   */     //   215: iconst_0
/*   */     //   216: iconst_1
/*   */     //   217: iconst_1
/*   */     //   218: iconst_0
/*   */     //   219: invokevirtual Vv : (Lf/ZH;IIZZ)I
/*   */     //   222: istore #7
/*   */     //   224: iconst_0
/*   */     //   225: iload #7
/*   */     //   227: iconst_0
/*   */     //   228: iconst_0
/*   */     //   229: invokevirtual Vv : (Lf/ZH;IIZZ)I
/*   */     //   232: istore #8
/*   */     //   234: iload #6
/*   */     //   236: iconst_1
/*   */     //   237: iadd
/*   */     //   238: iconst_0
/*   */     //   239: iconst_1
/*   */     //   240: iconst_1
/*   */     //   241: invokevirtual Vv : (Lf/ZH;IIZZ)I
/*   */     //   244: pop
/*   */     //   245: iload #8
/*   */     //   247: iconst_1
/*   */     //   248: iadd
/*   */     //   249: iconst_0
/*   */     //   250: swap
/*   */     //   251: iconst_1
/*   */     //   252: iconst_0
/*   */     //   253: invokevirtual Vv : (Lf/ZH;IIZZ)I
/*   */     //   256: pop
/*   */     //   257: ifne -> 281
/*   */     //   260: iload #6
/*   */     //   262: ifne -> 281
/*   */     //   265: iload #7
/*   */     //   267: ifne -> 281
/*   */     //   270: iload #8
/*   */     //   272: ifne -> 281
/*   */     //   275: aconst_null
/*   */     //   276: astore #5
/*   */     //   278: goto -> 385
/*   */     //   281: iload #5
/*   */     //   283: ifeq -> 308
/*   */     //   286: aload_2
/*   */     //   287: iinc #5, -1
/*   */     //   290: getfield Con : Lcom/badlogic/gdx/graphics/g2d/Gdx2DPixmap;
/*   */     //   293: getfield ju : I
/*   */     //   296: iconst_2
/*   */     //   297: isub
/*   */     //   298: iload #6
/*   */     //   300: iconst_1
/*   */     //   301: isub
/*   */     //   302: isub
/*   */     //   303: istore #6
/*   */     //   305: goto -> 319
/*   */     //   308: aload_2
/*   */     //   309: getfield Con : Lcom/badlogic/gdx/graphics/g2d/Gdx2DPixmap;
/*   */     //   312: getfield ju : I
/*   */     //   315: iconst_2
/*   */     //   316: isub
/*   */     //   317: istore #6
/*   */     //   319: iload #7
/*   */     //   321: ifeq -> 346
/*   */     //   324: aload_2
/*   */     //   325: iinc #7, -1
/*   */     //   328: getfield Con : Lcom/badlogic/gdx/graphics/g2d/Gdx2DPixmap;
/*   */     //   331: getfield Og0 : I
/*   */     //   334: iconst_2
/*   */     //   335: isub
/*   */     //   336: iload #8
/*   */     //   338: iconst_1
/*   */     //   339: isub
/*   */     //   340: isub
/*   */     //   341: istore #8
/*   */     //   343: goto -> 357
/*   */     //   346: aload_2
/*   */     //   347: getfield Con : Lcom/badlogic/gdx/graphics/g2d/Gdx2DPixmap;
/*   */     //   350: getfield Og0 : I
/*   */     //   353: iconst_2
/*   */     //   354: isub
/*   */     //   355: istore #8
/*   */     //   357: iconst_4
/*   */     //   358: newarray int
/*   */     //   360: dup
/*   */     //   361: dup
/*   */     //   362: dup2
/*   */     //   363: astore #9
/*   */     //   365: iconst_0
/*   */     //   366: iload #5
/*   */     //   368: iastore
/*   */     //   369: iconst_1
/*   */     //   370: iload #6
/*   */     //   372: iastore
/*   */     //   373: iconst_2
/*   */     //   374: iload #7
/*   */     //   376: iastore
/*   */     //   377: iconst_3
/*   */     //   378: iload #8
/*   */     //   380: iastore
/*   */     //   381: aload #9
/*   */     //   383: astore #5
/*   */     //   385: aload_0
/*   */     //   386: aload_2
/*   */     //   387: dup
/*   */     //   388: aload_3
/*   */     //   389: aload #5
/*   */     //   391: putfield wh0 : [I
/*   */     //   394: getfield Con : Lcom/badlogic/gdx/graphics/g2d/Gdx2DPixmap;
/*   */     //   397: dup
/*   */     //   398: getfield Og0 : I
/*   */     //   401: iconst_1
/*   */     //   402: isub
/*   */     //   403: istore #6
/*   */     //   405: getfield ju : I
/*   */     //   408: iconst_1
/*   */     //   409: isub
/*   */     //   410: istore #7
/*   */     //   412: iconst_1
/*   */     //   413: iload #6
/*   */     //   415: iconst_1
/*   */     //   416: iconst_1
/*   */     //   417: invokevirtual Vv : (Lf/ZH;IIZZ)I
/*   */     //   420: dup
/*   */     //   421: istore #8
/*   */     //   423: aload_0
/*   */     //   424: aload_2
/*   */     //   425: iload #7
/*   */     //   427: iconst_1
/*   */     //   428: iconst_1
/*   */     //   429: iconst_0
/*   */     //   430: invokevirtual Vv : (Lf/ZH;IIZZ)I
/*   */     //   433: istore #9
/*   */     //   435: iconst_0
/*   */     //   436: istore #10
/*   */     //   438: iconst_0
/*   */     //   439: istore #11
/*   */     //   441: ifeq -> 460
/*   */     //   444: aload_0
/*   */     //   445: iload #8
/*   */     //   447: iconst_1
/*   */     //   448: iadd
/*   */     //   449: aload_2
/*   */     //   450: swap
/*   */     //   451: iload #6
/*   */     //   453: iconst_0
/*   */     //   454: iconst_1
/*   */     //   455: invokevirtual Vv : (Lf/ZH;IIZZ)I
/*   */     //   458: istore #10
/*   */     //   460: iload #9
/*   */     //   462: ifeq -> 481
/*   */     //   465: aload_0
/*   */     //   466: aload_2
/*   */     //   467: iload #9
/*   */     //   469: iconst_1
/*   */     //   470: iadd
/*   */     //   471: iload #7
/*   */     //   473: swap
/*   */     //   474: iconst_0
/*   */     //   475: iconst_0
/*   */     //   476: invokevirtual Vv : (Lf/ZH;IIZZ)I
/*   */     //   479: istore #11
/*   */     //   481: iload #8
/*   */     //   483: aload_0
/*   */     //   484: dup
/*   */     //   485: iload #10
/*   */     //   487: iconst_1
/*   */     //   488: iadd
/*   */     //   489: aload_2
/*   */     //   490: swap
/*   */     //   491: iload #6
/*   */     //   493: iconst_1
/*   */     //   494: iconst_1
/*   */     //   495: invokevirtual Vv : (Lf/ZH;IIZZ)I
/*   */     //   498: pop
/*   */     //   499: aload_2
/*   */     //   500: iload #11
/*   */     //   502: iconst_1
/*   */     //   503: iadd
/*   */     //   504: iload #7
/*   */     //   506: swap
/*   */     //   507: iconst_1
/*   */     //   508: iconst_0
/*   */     //   509: invokevirtual Vv : (Lf/ZH;IIZZ)I
/*   */     //   512: pop
/*   */     //   513: ifne -> 534
/*   */     //   516: iload #10
/*   */     //   518: ifne -> 534
/*   */     //   521: iload #9
/*   */     //   523: ifne -> 534
/*   */     //   526: iload #11
/*   */     //   528: ifne -> 534
/*   */     //   531: goto -> 687
/*   */     //   534: iload #8
/*   */     //   536: ifne -> 553
/*   */     //   539: iload #10
/*   */     //   541: ifne -> 553
/*   */     //   544: iconst_m1
/*   */     //   545: istore #8
/*   */     //   547: iconst_m1
/*   */     //   548: istore #6
/*   */     //   550: goto -> 591
/*   */     //   553: iload #8
/*   */     //   555: ifle -> 580
/*   */     //   558: aload_2
/*   */     //   559: iinc #8, -1
/*   */     //   562: getfield Con : Lcom/badlogic/gdx/graphics/g2d/Gdx2DPixmap;
/*   */     //   565: getfield ju : I
/*   */     //   568: iconst_2
/*   */     //   569: isub
/*   */     //   570: iload #10
/*   */     //   572: iconst_1
/*   */     //   573: isub
/*   */     //   574: isub
/*   */     //   575: istore #6
/*   */     //   577: goto -> 591
/*   */     //   580: aload_2
/*   */     //   581: getfield Con : Lcom/badlogic/gdx/graphics/g2d/Gdx2DPixmap;
/*   */     //   584: getfield ju : I
/*   */     //   587: iconst_2
/*   */     //   588: isub
/*   */     //   589: istore #6
/*   */     //   591: iload #9
/*   */     //   593: ifne -> 610
/*   */     //   596: iload #11
/*   */     //   598: ifne -> 610
/*   */     //   601: iconst_m1
/*   */     //   602: istore #9
/*   */     //   604: iconst_m1
/*   */     //   605: istore #7
/*   */     //   607: goto -> 648
/*   */     //   610: iload #9
/*   */     //   612: ifle -> 637
/*   */     //   615: aload_2
/*   */     //   616: iinc #9, -1
/*   */     //   619: getfield Con : Lcom/badlogic/gdx/graphics/g2d/Gdx2DPixmap;
/*   */     //   622: getfield Og0 : I
/*   */     //   625: iconst_2
/*   */     //   626: isub
/*   */     //   627: iload #11
/*   */     //   629: iconst_1
/*   */     //   630: isub
/*   */     //   631: isub
/*   */     //   632: istore #7
/*   */     //   634: goto -> 648
/*   */     //   637: aload_2
/*   */     //   638: getfield Con : Lcom/badlogic/gdx/graphics/g2d/Gdx2DPixmap;
/*   */     //   641: getfield Og0 : I
/*   */     //   644: iconst_2
/*   */     //   645: isub
/*   */     //   646: istore #7
/*   */     //   648: aload #5
/*   */     //   650: iconst_4
/*   */     //   651: newarray int
/*   */     //   653: dup
/*   */     //   654: dup
/*   */     //   655: dup2
/*   */     //   656: astore #10
/*   */     //   658: iconst_0
/*   */     //   659: iload #8
/*   */     //   661: iastore
/*   */     //   662: iconst_1
/*   */     //   663: iload #6
/*   */     //   665: iastore
/*   */     //   666: iconst_2
/*   */     //   667: iload #9
/*   */     //   669: iastore
/*   */     //   670: iconst_3
/*   */     //   671: iload #7
/*   */     //   673: iastore
/*   */     //   674: ifnull -> 690
/*   */     //   677: aload #10
/*   */     //   679: aload #5
/*   */     //   681: invokestatic equals : ([I[I)Z
/*   */     //   684: ifeq -> 690
/*   */     //   687: aconst_null
/*   */     //   688: astore #10
/*   */     //   690: aload_1
/*   */     //   691: aload #4
/*   */     //   693: aload_2
/*   */     //   694: aload_3
/*   */     //   695: aload #10
/*   */     //   697: putfield pc : [I
/*   */     //   700: getfield Con : Lcom/badlogic/gdx/graphics/g2d/Gdx2DPixmap;
/*   */     //   703: dup
/*   */     //   704: dup
/*   */     //   705: astore_1
/*   */     //   706: getfield ju : I
/*   */     //   709: iconst_1
/*   */     //   710: isub
/*   */     //   711: istore_2
/*   */     //   712: getfield Og0 : I
/*   */     //   715: iconst_1
/*   */     //   716: isub
/*   */     //   717: istore #5
/*   */     //   719: getfield Con : Lcom/badlogic/gdx/graphics/g2d/Gdx2DPixmap;
/*   */     //   722: aload_1
/*   */     //   723: iconst_1
/*   */     //   724: iconst_1
/*   */     //   725: iconst_0
/*   */     //   726: iconst_0
/*   */     //   727: iload_2
/*   */     //   728: iload #5
/*   */     //   730: invokevirtual nM : (Lcom/badlogic/gdx/graphics/g2d/Gdx2DPixmap;IIIIII)V
/*   */     //   733: ldc '\.'
/*   */     //   735: invokevirtual split : (Ljava/lang/String;)[Ljava/lang/String;
/*   */     //   738: iconst_0
/*   */     //   739: aaload
/*   */     //   740: astore_1
/*   */     //   741: aload #4
/*   */     //   743: astore_2
/*   */     //   744: goto -> 1207
/*   */     //   747: aload_0
/*   */     //   748: getfield Yn : Z
/*   */     //   751: ifne -> 803
/*   */     //   754: aload_0
/*   */     //   755: getfield Pf : Z
/*   */     //   758: ifeq -> 764
/*   */     //   761: goto -> 803
/*   */     //   764: new f/B60
/*   */     //   767: dup
/*   */     //   768: astore #4
/*   */     //   770: aload_2
/*   */     //   771: getfield Con : Lcom/badlogic/gdx/graphics/g2d/Gdx2DPixmap;
/*   */     //   774: dup
/*   */     //   775: getfield ju : I
/*   */     //   778: istore #5
/*   */     //   780: getfield Og0 : I
/*   */     //   783: istore #6
/*   */     //   785: iconst_0
/*   */     //   786: iconst_0
/*   */     //   787: iload #5
/*   */     //   789: iload #6
/*   */     //   791: invokespecial <init> : (IIII)V
/*   */     //   794: aload #4
/*   */     //   796: aload_3
/*   */     //   797: astore #4
/*   */     //   799: astore_3
/*   */     //   800: goto -> 1207
/*   */     //   803: aload_0
/*   */     //   804: aload_2
/*   */     //   805: getfield Con : Lcom/badlogic/gdx/graphics/g2d/Gdx2DPixmap;
/*   */     //   808: dup
/*   */     //   809: getfield ju : I
/*   */     //   812: istore_3
/*   */     //   813: getfield Og0 : I
/*   */     //   816: istore #4
/*   */     //   818: iconst_0
/*   */     //   819: istore #5
/*   */     //   821: getfield Pf : Z
/*   */     //   824: ifeq -> 968
/*   */     //   827: iconst_0
/*   */     //   828: istore #6
/*   */     //   830: iload #6
/*   */     //   832: aload_2
/*   */     //   833: getfield Con : Lcom/badlogic/gdx/graphics/g2d/Gdx2DPixmap;
/*   */     //   836: getfield Og0 : I
/*   */     //   839: if_icmpge -> 894
/*   */     //   842: iconst_0
/*   */     //   843: istore #7
/*   */     //   845: iload #7
/*   */     //   847: aload_2
/*   */     //   848: getfield Con : Lcom/badlogic/gdx/graphics/g2d/Gdx2DPixmap;
/*   */     //   851: dup
/*   */     //   852: astore #8
/*   */     //   854: getfield ju : I
/*   */     //   857: if_icmpge -> 885
/*   */     //   860: aload #8
/*   */     //   862: iload #7
/*   */     //   864: iload #6
/*   */     //   866: invokevirtual Fl : (II)I
/*   */     //   869: sipush #255
/*   */     //   872: iand
/*   */     //   873: ifle -> 879
/*   */     //   876: goto -> 894
/*   */     //   879: iinc #7, 1
/*   */     //   882: goto -> 845
/*   */     //   885: iinc #5, 1
/*   */     //   888: iinc #6, 1
/*   */     //   891: goto -> 830
/*   */     //   894: aload_2
/*   */     //   895: getfield Con : Lcom/badlogic/gdx/graphics/g2d/Gdx2DPixmap;
/*   */     //   898: getfield Og0 : I
/*   */     //   901: istore #6
/*   */     //   903: iload #4
/*   */     //   905: istore #7
/*   */     //   907: iload #6
/*   */     //   909: iconst_m1
/*   */     //   910: iadd
/*   */     //   911: dup
/*   */     //   912: istore #6
/*   */     //   914: iload #5
/*   */     //   916: if_icmplt -> 972
/*   */     //   919: iconst_0
/*   */     //   920: istore #8
/*   */     //   922: iload #8
/*   */     //   924: aload_2
/*   */     //   925: getfield Con : Lcom/badlogic/gdx/graphics/g2d/Gdx2DPixmap;
/*   */     //   928: dup
/*   */     //   929: astore #9
/*   */     //   931: getfield ju : I
/*   */     //   934: if_icmpge -> 962
/*   */     //   937: aload #9
/*   */     //   939: iload #8
/*   */     //   941: iload #6
/*   */     //   943: invokevirtual Fl : (II)I
/*   */     //   946: sipush #255
/*   */     //   949: iand
/*   */     //   950: ifle -> 956
/*   */     //   953: goto -> 972
/*   */     //   956: iinc #8, 1
/*   */     //   959: goto -> 922
/*   */     //   962: iinc #7, -1
/*   */     //   965: goto -> 907
/*   */     //   968: iload #4
/*   */     //   970: istore #7
/*   */     //   972: aload_0
/*   */     //   973: aload_2
/*   */     //   974: iconst_0
/*   */     //   975: istore #6
/*   */     //   977: getfield Con : Lcom/badlogic/gdx/graphics/g2d/Gdx2DPixmap;
/*   */     //   980: getfield ju : I
/*   */     //   983: istore #8
/*   */     //   985: getfield Yn : Z
/*   */     //   988: ifeq -> 1118
/*   */     //   991: iconst_0
/*   */     //   992: istore #9
/*   */     //   994: iload #9
/*   */     //   996: aload_2
/*   */     //   997: getfield Con : Lcom/badlogic/gdx/graphics/g2d/Gdx2DPixmap;
/*   */     //   1000: getfield ju : I
/*   */     //   1003: if_icmpge -> 1053
/*   */     //   1006: iload #5
/*   */     //   1008: istore #10
/*   */     //   1010: iload #10
/*   */     //   1012: iload #7
/*   */     //   1014: if_icmpge -> 1044
/*   */     //   1017: aload_2
/*   */     //   1018: getfield Con : Lcom/badlogic/gdx/graphics/g2d/Gdx2DPixmap;
/*   */     //   1021: iload #9
/*   */     //   1023: iload #10
/*   */     //   1025: invokevirtual Fl : (II)I
/*   */     //   1028: sipush #255
/*   */     //   1031: iand
/*   */     //   1032: ifle -> 1038
/*   */     //   1035: goto -> 1053
/*   */     //   1038: iinc #10, 1
/*   */     //   1041: goto -> 1010
/*   */     //   1044: iinc #6, 1
/*   */     //   1047: iinc #9, 1
/*   */     //   1050: goto -> 994
/*   */     //   1053: aload_2
/*   */     //   1054: getfield Con : Lcom/badlogic/gdx/graphics/g2d/Gdx2DPixmap;
/*   */     //   1057: getfield ju : I
/*   */     //   1060: istore #9
/*   */     //   1062: iload #9
/*   */     //   1064: iconst_m1
/*   */     //   1065: iadd
/*   */     //   1066: dup
/*   */     //   1067: istore #9
/*   */     //   1069: iload #6
/*   */     //   1071: if_icmplt -> 1118
/*   */     //   1074: iload #5
/*   */     //   1076: istore #10
/*   */     //   1078: iload #10
/*   */     //   1080: iload #7
/*   */     //   1082: if_icmpge -> 1112
/*   */     //   1085: aload_2
/*   */     //   1086: getfield Con : Lcom/badlogic/gdx/graphics/g2d/Gdx2DPixmap;
/*   */     //   1089: iload #9
/*   */     //   1091: iload #10
/*   */     //   1093: invokevirtual Fl : (II)I
/*   */     //   1096: sipush #255
/*   */     //   1099: iand
/*   */     //   1100: ifle -> 1106
/*   */     //   1103: goto -> 1118
/*   */     //   1106: iinc #10, 1
/*   */     //   1109: goto -> 1078
/*   */     //   1112: iinc #8, -1
/*   */     //   1115: goto -> 1062
/*   */     //   1118: iload #7
/*   */     //   1120: iload #5
/*   */     //   1122: iload #8
/*   */     //   1124: iload #6
/*   */     //   1126: isub
/*   */     //   1127: istore #7
/*   */     //   1129: isub
/*   */     //   1130: istore #8
/*   */     //   1132: new f/ZH
/*   */     //   1135: dup
/*   */     //   1136: dup2
/*   */     //   1137: astore #9
/*   */     //   1139: iload #7
/*   */     //   1141: aload_2
/*   */     //   1142: invokevirtual TU : ()Lf/Uc;
/*   */     //   1145: iload #8
/*   */     //   1147: swap
/*   */     //   1148: invokespecial <init> : (IILf/Uc;)V
/*   */     //   1151: getstatic f/y1.Zj : Lf/y1;
/*   */     //   1154: invokevirtual r1 : (Lf/y1;)V
/*   */     //   1157: getfield Con : Lcom/badlogic/gdx/graphics/g2d/Gdx2DPixmap;
/*   */     //   1160: aload_2
/*   */     //   1161: getfield Con : Lcom/badlogic/gdx/graphics/g2d/Gdx2DPixmap;
/*   */     //   1164: iload #6
/*   */     //   1166: iload #5
/*   */     //   1168: iconst_0
/*   */     //   1169: iconst_0
/*   */     //   1170: iload #7
/*   */     //   1172: iload #8
/*   */     //   1174: invokevirtual nM : (Lcom/badlogic/gdx/graphics/g2d/Gdx2DPixmap;IIIIII)V
/*   */     //   1177: new f/B60
/*   */     //   1180: dup
/*   */     //   1181: astore_2
/*   */     //   1182: iconst_0
/*   */     //   1183: iconst_0
/*   */     //   1184: iload #7
/*   */     //   1186: iload #8
/*   */     //   1188: iload #6
/*   */     //   1190: iload #5
/*   */     //   1192: iload_3
/*   */     //   1193: iload #4
/*   */     //   1195: invokespecial <init> : (IIIIIIII)V
/*   */     //   1198: aload_2
/*   */     //   1199: aload #9
/*   */     //   1201: aload #9
/*   */     //   1203: astore #4
/*   */     //   1205: astore_2
/*   */     //   1206: astore_3
/*   */     //   1207: aload_3
/*   */     //   1208: getfield af : F
/*   */     //   1211: aload_0
/*   */     //   1212: getfield ts0 : I
/*   */     //   1215: i2f
/*   */     //   1216: fcmpl
/*   */     //   1217: ifgt -> 1692
/*   */     //   1220: aload_3
/*   */     //   1221: getfield sf0 : F
/*   */     //   1224: aload_0
/*   */     //   1225: getfield WW : I
/*   */     //   1228: i2f
/*   */     //   1229: fcmpl
/*   */     //   1230: ifle -> 1236
/*   */     //   1233: goto -> 1692
/*   */     //   1236: aload_1
/*   */     //   1237: aload_0
/*   */     //   1238: getfield g8 : Lf/eB0;
/*   */     //   1241: aload_0
/*   */     //   1242: aload_3
/*   */     //   1243: invokeinterface sF0 : (Lf/oF0;Lf/cx0;)Lf/jk0;
/*   */     //   1248: astore #5
/*   */     //   1250: ifnull -> 1272
/*   */     //   1253: aload #5
/*   */     //   1255: dup
/*   */     //   1256: getfield XF : Lf/Nn;
/*   */     //   1259: aload_1
/*   */     //   1260: aload_3
/*   */     //   1261: invokevirtual X00 : (Ljava/lang/Object;Ljava/lang/Object;)Ljava/lang/Object;
/*   */     //   1264: pop
/*   */     //   1265: getfield r60 : Lf/fQ;
/*   */     //   1268: aload_1
/*   */     //   1269: invokevirtual Com3 : (Ljava/lang/Object;)V
/*   */     //   1272: aload_0
/*   */     //   1273: aload_3
/*   */     //   1274: dup
/*   */     //   1275: dup2
/*   */     //   1276: getfield dA : F
/*   */     //   1279: f2i
/*   */     //   1280: istore_1
/*   */     //   1281: getfield zA0 : F
/*   */     //   1284: f2i
/*   */     //   1285: istore #6
/*   */     //   1287: getfield af : F
/*   */     //   1290: f2i
/*   */     //   1291: istore #7
/*   */     //   1293: getfield sf0 : F
/*   */     //   1296: f2i
/*   */     //   1297: istore #8
/*   */     //   1299: getfield GH0 : Z
/*   */     //   1302: ifeq -> 1391
/*   */     //   1305: aload_0
/*   */     //   1306: getfield p80 : Z
/*   */     //   1309: ifne -> 1391
/*   */     //   1312: aload #5
/*   */     //   1314: getfield MO : Lcom/badlogic/gdx/graphics/Texture;
/*   */     //   1317: dup
/*   */     //   1318: astore #9
/*   */     //   1320: ifnull -> 1391
/*   */     //   1323: aload #5
/*   */     //   1325: getfield as : Z
/*   */     //   1328: ifne -> 1391
/*   */     //   1331: aload #9
/*   */     //   1333: invokevirtual bind : ()V
/*   */     //   1336: getstatic f/UB0.go : Lf/hj0;
/*   */     //   1339: aload_2
/*   */     //   1340: dup
/*   */     //   1341: dup
/*   */     //   1342: aload #5
/*   */     //   1344: getfield MO : Lcom/badlogic/gdx/graphics/Texture;
/*   */     //   1347: getfield glTarget : I
/*   */     //   1350: istore #9
/*   */     //   1352: invokevirtual qf : ()I
/*   */     //   1355: istore #10
/*   */     //   1357: invokevirtual i5 : ()I
/*   */     //   1360: istore #11
/*   */     //   1362: invokevirtual tp0 : ()Ljava/nio/ByteBuffer;
/*   */     //   1365: astore #12
/*   */     //   1367: iload #9
/*   */     //   1369: iconst_0
/*   */     //   1370: iload_1
/*   */     //   1371: iload #6
/*   */     //   1373: iload #7
/*   */     //   1375: iload #8
/*   */     //   1377: iload #10
/*   */     //   1379: iload #11
/*   */     //   1381: aload #12
/*   */     //   1383: invokeinterface glTexSubImage2D : (IIIIIIIILjava/nio/Buffer;)V
/*   */     //   1388: goto -> 1397
/*   */     //   1391: aload #5
/*   */     //   1393: iconst_1
/*   */     //   1394: putfield as : Z
/*   */     //   1397: aload_0
/*   */     //   1398: aload #5
/*   */     //   1400: getfield Af0 : Lf/ZH;
/*   */     //   1403: aload_2
/*   */     //   1404: iload_1
/*   */     //   1405: iload #6
/*   */     //   1407: invokevirtual fL : (Lf/ZH;II)V
/*   */     //   1410: getfield p80 : Z
/*   */     //   1413: ifeq -> 1680
/*   */     //   1416: aload #5
/*   */     //   1418: dup
/*   */     //   1419: dup
/*   */     //   1420: dup2
/*   */     //   1421: iload #6
/*   */     //   1423: iload #8
/*   */     //   1425: aload_2
/*   */     //   1426: getfield Con : Lcom/badlogic/gdx/graphics/g2d/Gdx2DPixmap;
/*   */     //   1429: dup
/*   */     //   1430: dup
/*   */     //   1431: astore_0
/*   */     //   1432: getfield ju : I
/*   */     //   1435: istore #9
/*   */     //   1437: getfield Og0 : I
/*   */     //   1440: dup
/*   */     //   1441: istore #10
/*   */     //   1443: aload #5
/*   */     //   1445: iload_1
/*   */     //   1446: iload #7
/*   */     //   1448: iload #9
/*   */     //   1450: aload #5
/*   */     //   1452: iload #6
/*   */     //   1454: iload_1
/*   */     //   1455: aload #5
/*   */     //   1457: getfield Af0 : Lf/ZH;
/*   */     //   1460: astore #5
/*   */     //   1462: iconst_1
/*   */     //   1463: isub
/*   */     //   1464: istore #11
/*   */     //   1466: iconst_1
/*   */     //   1467: isub
/*   */     //   1468: istore #12
/*   */     //   1470: aload #5
/*   */     //   1472: getfield Con : Lcom/badlogic/gdx/graphics/g2d/Gdx2DPixmap;
/*   */     //   1475: aload_0
/*   */     //   1476: iconst_0
/*   */     //   1477: iconst_0
/*   */     //   1478: iconst_1
/*   */     //   1479: iconst_1
/*   */     //   1480: iload #11
/*   */     //   1482: iload #12
/*   */     //   1484: iconst_1
/*   */     //   1485: iconst_1
/*   */     //   1486: invokevirtual fj : (Lcom/badlogic/gdx/graphics/g2d/Gdx2DPixmap;IIIIIIII)V
/*   */     //   1489: getfield Af0 : Lf/ZH;
/*   */     //   1492: astore_0
/*   */     //   1493: iconst_1
/*   */     //   1494: isub
/*   */     //   1495: istore #5
/*   */     //   1497: iadd
/*   */     //   1498: istore #13
/*   */     //   1500: aload_0
/*   */     //   1501: getfield Con : Lcom/badlogic/gdx/graphics/g2d/Gdx2DPixmap;
/*   */     //   1504: aload_2
/*   */     //   1505: getfield Con : Lcom/badlogic/gdx/graphics/g2d/Gdx2DPixmap;
/*   */     //   1508: iload #5
/*   */     //   1510: iconst_0
/*   */     //   1511: iconst_1
/*   */     //   1512: iconst_1
/*   */     //   1513: iload #13
/*   */     //   1515: iload #12
/*   */     //   1517: iconst_1
/*   */     //   1518: iconst_1
/*   */     //   1519: invokevirtual fj : (Lcom/badlogic/gdx/graphics/g2d/Gdx2DPixmap;IIIIIIII)V
/*   */     //   1522: getfield Af0 : Lf/ZH;
/*   */     //   1525: astore_0
/*   */     //   1526: iconst_1
/*   */     //   1527: isub
/*   */     //   1528: istore #14
/*   */     //   1530: iadd
/*   */     //   1531: istore #15
/*   */     //   1533: aload_0
/*   */     //   1534: getfield Con : Lcom/badlogic/gdx/graphics/g2d/Gdx2DPixmap;
/*   */     //   1537: aload_2
/*   */     //   1538: getfield Con : Lcom/badlogic/gdx/graphics/g2d/Gdx2DPixmap;
/*   */     //   1541: iconst_0
/*   */     //   1542: iload #14
/*   */     //   1544: iconst_1
/*   */     //   1545: iconst_1
/*   */     //   1546: iload #11
/*   */     //   1548: iload #15
/*   */     //   1550: iconst_1
/*   */     //   1551: iconst_1
/*   */     //   1552: invokevirtual fj : (Lcom/badlogic/gdx/graphics/g2d/Gdx2DPixmap;IIIIIIII)V
/*   */     //   1555: getfield Af0 : Lf/ZH;
/*   */     //   1558: getfield Con : Lcom/badlogic/gdx/graphics/g2d/Gdx2DPixmap;
/*   */     //   1561: aload_2
/*   */     //   1562: getfield Con : Lcom/badlogic/gdx/graphics/g2d/Gdx2DPixmap;
/*   */     //   1565: iload #5
/*   */     //   1567: iload #14
/*   */     //   1569: iconst_1
/*   */     //   1570: iconst_1
/*   */     //   1571: iload #13
/*   */     //   1573: iload #15
/*   */     //   1575: iconst_1
/*   */     //   1576: iconst_1
/*   */     //   1577: invokevirtual fj : (Lcom/badlogic/gdx/graphics/g2d/Gdx2DPixmap;IIIIIIII)V
/*   */     //   1580: getfield Af0 : Lf/ZH;
/*   */     //   1583: getfield Con : Lcom/badlogic/gdx/graphics/g2d/Gdx2DPixmap;
/*   */     //   1586: aload_2
/*   */     //   1587: getfield Con : Lcom/badlogic/gdx/graphics/g2d/Gdx2DPixmap;
/*   */     //   1590: iconst_0
/*   */     //   1591: iconst_0
/*   */     //   1592: iload #9
/*   */     //   1594: iconst_1
/*   */     //   1595: iload_1
/*   */     //   1596: iload #12
/*   */     //   1598: iload #7
/*   */     //   1600: iconst_1
/*   */     //   1601: invokevirtual fj : (Lcom/badlogic/gdx/graphics/g2d/Gdx2DPixmap;IIIIIIII)V
/*   */     //   1604: getfield Af0 : Lf/ZH;
/*   */     //   1607: getfield Con : Lcom/badlogic/gdx/graphics/g2d/Gdx2DPixmap;
/*   */     //   1610: aload_2
/*   */     //   1611: getfield Con : Lcom/badlogic/gdx/graphics/g2d/Gdx2DPixmap;
/*   */     //   1614: iconst_0
/*   */     //   1615: iload #14
/*   */     //   1617: iload #9
/*   */     //   1619: iconst_1
/*   */     //   1620: iload_1
/*   */     //   1621: iload #15
/*   */     //   1623: iload #7
/*   */     //   1625: iconst_1
/*   */     //   1626: invokevirtual fj : (Lcom/badlogic/gdx/graphics/g2d/Gdx2DPixmap;IIIIIIII)V
/*   */     //   1629: getfield Af0 : Lf/ZH;
/*   */     //   1632: getfield Con : Lcom/badlogic/gdx/graphics/g2d/Gdx2DPixmap;
/*   */     //   1635: aload_2
/*   */     //   1636: getfield Con : Lcom/badlogic/gdx/graphics/g2d/Gdx2DPixmap;
/*   */     //   1639: iconst_0
/*   */     //   1640: iconst_0
/*   */     //   1641: iconst_1
/*   */     //   1642: iload #10
/*   */     //   1644: iload #11
/*   */     //   1646: iload #6
/*   */     //   1648: iconst_1
/*   */     //   1649: iload #8
/*   */     //   1651: invokevirtual fj : (Lcom/badlogic/gdx/graphics/g2d/Gdx2DPixmap;IIIIIIII)V
/*   */     //   1654: getfield Af0 : Lf/ZH;
/*   */     //   1657: getfield Con : Lcom/badlogic/gdx/graphics/g2d/Gdx2DPixmap;
/*   */     //   1660: aload_2
/*   */     //   1661: getfield Con : Lcom/badlogic/gdx/graphics/g2d/Gdx2DPixmap;
/*   */     //   1664: iload #5
/*   */     //   1666: iconst_0
/*   */     //   1667: iconst_1
/*   */     //   1668: iload #10
/*   */     //   1670: iload #13
/*   */     //   1672: iload #6
/*   */     //   1674: iconst_1
/*   */     //   1675: iload #8
/*   */     //   1677: invokevirtual fj : (Lcom/badlogic/gdx/graphics/g2d/Gdx2DPixmap;IIIIIIII)V
/*   */     //   1680: aload #4
/*   */     //   1682: ifnull -> 1690
/*   */     //   1685: aload #4
/*   */     //   1687: invokevirtual dispose : ()V
/*   */     //   1690: aload_3
/*   */     //   1691: areturn
/*   */     //   1692: aload_1
/*   */     //   1693: ifnonnull -> 1707
/*   */     //   1696: new f/JU
/*   */     //   1699: dup
/*   */     //   1700: ldc_w 'Page size too small for pixmap.'
/*   */     //   1703: invokespecial <init> : (Ljava/lang/String;)V
/*   */     //   1706: athrow
/*   */     //   1707: new f/JU
/*   */     //   1710: dup
/*   */     //   1711: ldc_w 'Page size too small for pixmap: '
/*   */     //   1714: aload_1
/*   */     //   1715: invokestatic tF0 : (Ljava/lang/String;Ljava/lang/String;)Ljava/lang/String;
/*   */     //   1718: invokespecial <init> : (Ljava/lang/String;)V
/*   */     //   1721: athrow
/*   */     // Line number table:
/*   */     //   Java source line number -> byte code offset
/*   */     //   #1	-> 16
/*   */     //   #2	-> 71
/*   */     //   #3	-> 75
/*   */     //   #4	-> 81
/*   */     //   #5	-> 111
/*   */     //   #6	-> 115
/*   */     //   #7	-> 122
/*   */     //   #8	-> 135
/*   */     //   #9	-> 147
/*   */     //   #10	-> 151
/*   */     //   #11	-> 158
/*   */     //   #12	-> 165
/*   */     //   #13	-> 189
/*   */     //   #14	-> 290
/*   */     //   #15	-> 293
/*   */     //   #16	-> 309
/*   */     //   #17	-> 312
/*   */     //   #18	-> 328
/*   */     //   #19	-> 331
/*   */     //   #20	-> 347
/*   */     //   #21	-> 350
/*   */     //   #22	-> 358
/*   */     //   #23	-> 391
/*   */     //   #24	-> 394
/*   */     //   #25	-> 398
/*   */     //   #26	-> 405
/*   */     //   #27	-> 417
/*   */     //   #28	-> 562
/*   */     //   #29	-> 565
/*   */     //   #30	-> 581
/*   */     //   #31	-> 584
/*   */     //   #32	-> 619
/*   */     //   #33	-> 622
/*   */     //   #34	-> 638
/*   */     //   #35	-> 641
/*   */     //   #36	-> 651
/*   */     //   #37	-> 697
/*   */     //   #38	-> 700
/*   */     //   #39	-> 706
/*   */     //   #40	-> 712
/*   */     //   #41	-> 719
/*   */     //   #42	-> 733
/*   */     //   #43	-> 771
/*   */     //   #44	-> 775
/*   */     //   #45	-> 780
/*   */     //   #46	-> 791
/*   */     //   #47	-> 805
/*   */     //   #48	-> 809
/*   */     //   #49	-> 813
/*   */     //   #50	-> 821
/*   */     //   #51	-> 833
/*   */     //   #52	-> 836
/*   */     //   #53	-> 848
/*   */     //   #54	-> 854
/*   */     //   #55	-> 866
/*   */     //   #56	-> 895
/*   */     //   #57	-> 898
/*   */     //   #58	-> 925
/*   */     //   #59	-> 931
/*   */     //   #60	-> 943
/*   */     //   #61	-> 977
/*   */     //   #62	-> 980
/*   */     //   #63	-> 985
/*   */     //   #64	-> 997
/*   */     //   #65	-> 1000
/*   */     //   #66	-> 1018
/*   */     //   #67	-> 1054
/*   */     //   #68	-> 1057
/*   */     //   #69	-> 1086
/*   */     //   #70	-> 1132
/*   */     //   #71	-> 1157
/*   */     //   #72	-> 1177
/*   */     //   #73	-> 1208
/*   */     //   #74	-> 1212
/*   */     //   #75	-> 1221
/*   */     //   #76	-> 1225
/*   */     //   #77	-> 1426
/*   */     //   #78	-> 1432
/*   */     //   #79	-> 1437
/*   */     //   #80	-> 1457
/*   */     //   #81	-> 1472
/*   */     //   #82	-> 1486
/*   */     //   #83	-> 1489
/*   */     //   #84	-> 1501
/*   */     //   #85	-> 1505
/*   */     //   #86	-> 1522
/*   */     //   #87	-> 1534
/*   */     //   #88	-> 1538
/*   */     //   #89	-> 1555
/*   */     //   #90	-> 1558
/*   */     //   #91	-> 1562
/*   */     //   #92	-> 1580
/*   */     //   #93	-> 1583
/*   */     //   #94	-> 1587
/*   */     //   #95	-> 1604
/*   */     //   #96	-> 1607
/*   */     //   #97	-> 1611
/*   */     //   #98	-> 1629
/*   */     //   #99	-> 1632
/*   */     //   #100	-> 1636
/*   */     //   #101	-> 1654
/*   */     //   #102	-> 1657
/*   */     //   #103	-> 1661
/*   */     //   #104	-> 1687
/*   */     //   #105	-> 1711
/*   */     //   #106	-> 1718
/*   */     // Exception table:
/*   */     //   from	to	target	type
/*   */     //   16	22	85	finally
/*   */     //   23	27	85	finally
/*   */     //   30	47	85	finally
/*   */   }
/*   */   
/*   */   public synchronized void dispose() {
/*   */     Hc0 hc0 = this.dA.r30();
/*   */     while (hc0.hasNext()) {
/*   */       jk0 jk0;
/*   */       if ((jk0 = (jk0)hc0.next()).MO == null)
/*   */         jk0.Af0.dispose(); 
/*   */     } 
/*   */     this.d = true;
/*   */   }
/*   */   
/*   */   public final Color k50() {
/*   */     return this.LS;
/*   */   }
/*   */   
/*   */   public final synchronized COm1 aN(cu0 paramcu01, cu0 paramcu02) {
/*   */     // Byte code:
/*   */     //   0: aload_0
/*   */     //   1: dup
/*   */     //   2: dup2
/*   */     //   3: new f/COm1
/*   */     //   6: dup
/*   */     //   7: astore_3
/*   */     //   8: invokespecial <init> : ()V
/*   */     //   11: monitorenter
/*   */     //   12: monitorenter
/*   */     //   13: monitorenter
/*   */     //   14: iconst_0
/*   */     //   15: istore #4
/*   */     //   17: getfield dA : Lf/fQ;
/*   */     //   20: invokevirtual r30 : ()Lf/Hc0;
/*   */     //   23: astore #5
/*   */     //   25: aload #5
/*   */     //   27: invokevirtual hasNext : ()Z
/*   */     //   30: ifeq -> 138
/*   */     //   33: aload #5
/*   */     //   35: invokevirtual next : ()Ljava/lang/Object;
/*   */     //   38: checkcast f/jk0
/*   */     //   41: dup
/*   */     //   42: astore #6
/*   */     //   44: getfield MO : Lcom/badlogic/gdx/graphics/Texture;
/*   */     //   47: dup
/*   */     //   48: astore #7
/*   */     //   50: ifnull -> 76
/*   */     //   53: aload #6
/*   */     //   55: getfield as : Z
/*   */     //   58: ifne -> 64
/*   */     //   61: goto -> 25
/*   */     //   64: aload #7
/*   */     //   66: dup
/*   */     //   67: invokevirtual getTextureData : ()Lf/Bu0;
/*   */     //   70: invokevirtual load : (Lf/Bu0;)V
/*   */     //   73: goto -> 129
/*   */     //   76: new f/yi0
/*   */     //   79: dup
/*   */     //   80: astore #7
/*   */     //   82: aload_1
/*   */     //   83: aload #6
/*   */     //   85: aload #7
/*   */     //   87: dup
/*   */     //   88: aload #6
/*   */     //   90: new f/AB
/*   */     //   93: dup
/*   */     //   94: astore #7
/*   */     //   96: aload #6
/*   */     //   98: getfield Af0 : Lf/ZH;
/*   */     //   101: dup
/*   */     //   102: astore #8
/*   */     //   104: invokevirtual TU : ()Lf/Uc;
/*   */     //   107: aload #8
/*   */     //   109: swap
/*   */     //   110: iload #4
/*   */     //   112: iconst_0
/*   */     //   113: iconst_1
/*   */     //   114: invokespecial <init> : (Lf/ZH;Lf/Uc;ZZZ)V
/*   */     //   117: aload #7
/*   */     //   119: invokespecial <init> : (Lf/jk0;Lf/AB;)V
/*   */     //   122: putfield MO : Lcom/badlogic/gdx/graphics/Texture;
/*   */     //   125: aload_2
/*   */     //   126: invokevirtual setFilter : (Lf/cu0;Lf/cu0;)V
/*   */     //   129: aload #6
/*   */     //   131: iconst_0
/*   */     //   132: putfield as : Z
/*   */     //   135: goto -> 25
/*   */     //   138: aload_0
/*   */     //   139: dup
/*   */     //   140: monitorexit
/*   */     //   141: getfield dA : Lf/fQ;
/*   */     //   144: invokevirtual r30 : ()Lf/Hc0;
/*   */     //   147: astore_1
/*   */     //   148: aload_1
/*   */     //   149: invokevirtual hasNext : ()Z
/*   */     //   152: ifeq -> 471
/*   */     //   155: aload_1
/*   */     //   156: invokevirtual next : ()Ljava/lang/Object;
/*   */     //   159: checkcast f/jk0
/*   */     //   162: dup
/*   */     //   163: astore_2
/*   */     //   164: getfield r60 : Lf/fQ;
/*   */     //   167: dup
/*   */     //   168: astore #4
/*   */     //   170: getfield Z8 : I
/*   */     //   173: ifle -> 148
/*   */     //   176: aload #4
/*   */     //   178: invokevirtual r30 : ()Lf/Hc0;
/*   */     //   181: astore #4
/*   */     //   183: aload #4
/*   */     //   185: invokevirtual hasNext : ()Z
/*   */     //   188: ifeq -> 450
/*   */     //   191: aload_2
/*   */     //   192: aload #4
/*   */     //   194: invokevirtual next : ()Ljava/lang/Object;
/*   */     //   197: checkcast java/lang/String
/*   */     //   200: astore #5
/*   */     //   202: getfield XF : Lf/Nn;
/*   */     //   205: aload #5
/*   */     //   207: invokevirtual pd0 : (Ljava/lang/Object;)Ljava/lang/Object;
/*   */     //   210: checkcast f/B60
/*   */     //   213: dup
/*   */     //   214: astore #6
/*   */     //   216: new f/P70
/*   */     //   219: dup
/*   */     //   220: astore #7
/*   */     //   222: aload_2
/*   */     //   223: getfield MO : Lcom/badlogic/gdx/graphics/Texture;
/*   */     //   226: aload #6
/*   */     //   228: dup
/*   */     //   229: dup2
/*   */     //   230: getfield dA : F
/*   */     //   233: f2i
/*   */     //   234: istore #8
/*   */     //   236: getfield zA0 : F
/*   */     //   239: f2i
/*   */     //   240: istore #9
/*   */     //   242: getfield af : F
/*   */     //   245: f2i
/*   */     //   246: istore #10
/*   */     //   248: getfield sf0 : F
/*   */     //   251: f2i
/*   */     //   252: istore #11
/*   */     //   254: iload #8
/*   */     //   256: iload #9
/*   */     //   258: iload #10
/*   */     //   260: iload #11
/*   */     //   262: invokespecial <init> : (Lcom/badlogic/gdx/graphics/Texture;IIII)V
/*   */     //   265: getfield wh0 : [I
/*   */     //   268: dup
/*   */     //   269: astore #8
/*   */     //   271: ifnull -> 330
/*   */     //   274: aload #7
/*   */     //   276: dup
/*   */     //   277: iconst_2
/*   */     //   278: anewarray java/lang/String
/*   */     //   281: dup
/*   */     //   282: dup
/*   */     //   283: astore #9
/*   */     //   285: iconst_0
/*   */     //   286: ldc_w 'split'
/*   */     //   289: swap
/*   */     //   290: swap
/*   */     //   291: aastore
/*   */     //   292: iconst_1
/*   */     //   293: ldc_w 'pad'
/*   */     //   296: swap
/*   */     //   297: swap
/*   */     //   298: aastore
/*   */     //   299: aload #9
/*   */     //   301: putfield S00 : [Ljava/lang/String;
/*   */     //   304: iconst_2
/*   */     //   305: anewarray [I
/*   */     //   308: dup
/*   */     //   309: astore #9
/*   */     //   311: aload #6
/*   */     //   313: aload #9
/*   */     //   315: iconst_0
/*   */     //   316: aload #8
/*   */     //   318: aastore
/*   */     //   319: getfield pc : [I
/*   */     //   322: iconst_1
/*   */     //   323: swap
/*   */     //   324: aastore
/*   */     //   325: aload #9
/*   */     //   327: putfield cs0 : [[I
/*   */     //   330: iconst_m1
/*   */     //   331: istore #8
/*   */     //   333: getstatic f/oF0.bE0 : Ljava/util/regex/Pattern;
/*   */     //   336: aload #5
/*   */     //   338: invokevirtual matcher : (Ljava/lang/CharSequence;)Ljava/util/regex/Matcher;
/*   */     //   341: dup
/*   */     //   342: astore #9
/*   */     //   344: invokevirtual matches : ()Z
/*   */     //   347: ifeq -> 368
/*   */     //   350: aload #9
/*   */     //   352: dup
/*   */     //   353: iconst_1
/*   */     //   354: invokevirtual group : (I)Ljava/lang/String;
/*   */     //   357: astore #5
/*   */     //   359: iconst_2
/*   */     //   360: invokevirtual group : (I)Ljava/lang/String;
/*   */     //   363: invokestatic parseInt : (Ljava/lang/String;)I
/*   */     //   366: istore #8
/*   */     //   368: aload_3
/*   */     //   369: aload #7
/*   */     //   371: dup
/*   */     //   372: aload #6
/*   */     //   374: aload #7
/*   */     //   376: aload #6
/*   */     //   378: aload #7
/*   */     //   380: aload #6
/*   */     //   382: aload #7
/*   */     //   384: iload #8
/*   */     //   386: aload #7
/*   */     //   388: aload #5
/*   */     //   390: putfield Pk : Ljava/lang/String;
/*   */     //   393: putfield IC : I
/*   */     //   396: getfield vV : I
/*   */     //   399: i2f
/*   */     //   400: putfield rd : F
/*   */     //   403: getfield zs0 : I
/*   */     //   406: dup
/*   */     //   407: istore #5
/*   */     //   409: i2f
/*   */     //   410: aload #6
/*   */     //   412: getfield sf0 : F
/*   */     //   415: fsub
/*   */     //   416: aload #6
/*   */     //   418: getfield WD : I
/*   */     //   421: i2f
/*   */     //   422: fsub
/*   */     //   423: f2i
/*   */     //   424: i2f
/*   */     //   425: putfield jh0 : F
/*   */     //   428: getfield Kt0 : I
/*   */     //   431: putfield H3 : I
/*   */     //   434: iload #5
/*   */     //   436: putfield gp0 : I
/*   */     //   439: getfield ui0 : Lf/fQ;
/*   */     //   442: aload #7
/*   */     //   444: invokevirtual Com3 : (Ljava/lang/Object;)V
/*   */     //   447: goto -> 183
/*   */     //   450: aload_3
/*   */     //   451: aload_2
/*   */     //   452: getfield r60 : Lf/fQ;
/*   */     //   455: invokevirtual clear : ()V
/*   */     //   458: getfield ws : Lf/MG;
/*   */     //   461: aload_2
/*   */     //   462: getfield MO : Lcom/badlogic/gdx/graphics/Texture;
/*   */     //   465: invokevirtual GV : (Ljava/lang/Object;)V
/*   */     //   468: goto -> 148
/*   */     //   471: aload_3
/*   */     //   472: aload_0
/*   */     //   473: dup
/*   */     //   474: monitorexit
/*   */     //   475: monitorexit
/*   */     //   476: areturn
/*   */     //   477: aload_0
/*   */     //   478: monitorexit
/*   */     //   479: athrow
/*   */     //   480: astore_1
/*   */     //   481: aload_1
/*   */     //   482: aload_0
/*   */     //   483: monitorexit
/*   */     //   484: athrow
/*   */     //   485: aload_0
/*   */     //   486: monitorexit
/*   */     //   487: athrow
/*   */     // Line number table:
/*   */     //   Java source line number -> byte code offset
/*   */     //   #1	-> 12
/*   */     //   #2	-> 13
/*   */     //   #3	-> 17
/*   */     //   #4	-> 44
/*   */     //   #5	-> 55
/*   */     //   #6	-> 141
/*   */     //   #7	-> 439
/*   */     //   #8	-> 444
/*   */     //   #9	-> 458
/*   */     //   #10	-> 462
/*   */     // Exception table:
/*   */     //   from	to	target	type
/*   */     //   12	13	485	finally
/*   */     //   13	14	480	finally
/*   */     //   17	23	477	finally
/*   */     //   25	30	477	finally
/*   */     //   33	41	477	finally
/*   */     //   44	47	477	finally
/*   */     //   53	58	477	finally
/*   */     //   64	79	477	finally
/*   */     //   82	93	477	finally
/*   */     //   96	101	477	finally
/*   */     //   104	138	477	finally
/*   */     //   138	147	480	finally
/*   */     //   148	152	480	finally
/*   */     //   155	162	480	finally
/*   */     //   164	167	480	finally
/*   */     //   170	173	480	finally
/*   */     //   176	181	480	finally
/*   */     //   183	188	480	finally
/*   */     //   191	200	480	finally
/*   */     //   202	213	480	finally
/*   */     //   216	219	480	finally
/*   */     //   222	233	480	finally
/*   */     //   236	239	480	finally
/*   */     //   242	245	480	finally
/*   */     //   248	251	480	finally
/*   */     //   254	268	480	finally
/*   */     //   274	281	480	finally
/*   */     //   286	292	480	finally
/*   */     //   293	308	480	finally
/*   */     //   311	330	480	finally
/*   */     //   333	341	480	finally
/*   */     //   344	347	480	finally
/*   */     //   350	357	480	finally
/*   */     //   359	366	480	finally
/*   */     //   368	399	480	finally
/*   */     //   400	406	480	finally
/*   */     //   410	415	480	finally
/*   */     //   416	421	480	finally
/*   */     //   425	471	480	finally
/*   */     //   471	475	485	finally
/*   */     //   477	480	480	finally
/*   */     //   481	485	485	finally
/*   */   }
/*   */   
/*   */   public final synchronized void LK(fQ paramfQ, cu0 paramcu01, cu0 paramcu02) {
/*   */     // Byte code:
/*   */     //   0: aload_0
/*   */     //   1: dup
/*   */     //   2: monitorenter
/*   */     //   3: iconst_0
/*   */     //   4: istore #4
/*   */     //   6: getfield dA : Lf/fQ;
/*   */     //   9: invokevirtual r30 : ()Lf/Hc0;
/*   */     //   12: astore #5
/*   */     //   14: aload #5
/*   */     //   16: invokevirtual hasNext : ()Z
/*   */     //   19: ifeq -> 127
/*   */     //   22: aload #5
/*   */     //   24: invokevirtual next : ()Ljava/lang/Object;
/*   */     //   27: checkcast f/jk0
/*   */     //   30: dup
/*   */     //   31: astore #6
/*   */     //   33: getfield MO : Lcom/badlogic/gdx/graphics/Texture;
/*   */     //   36: dup
/*   */     //   37: astore #7
/*   */     //   39: ifnull -> 65
/*   */     //   42: aload #6
/*   */     //   44: getfield as : Z
/*   */     //   47: ifne -> 53
/*   */     //   50: goto -> 14
/*   */     //   53: aload #7
/*   */     //   55: dup
/*   */     //   56: invokevirtual getTextureData : ()Lf/Bu0;
/*   */     //   59: invokevirtual load : (Lf/Bu0;)V
/*   */     //   62: goto -> 118
/*   */     //   65: new f/yi0
/*   */     //   68: dup
/*   */     //   69: astore #7
/*   */     //   71: aload_2
/*   */     //   72: aload #6
/*   */     //   74: aload #7
/*   */     //   76: dup
/*   */     //   77: aload #6
/*   */     //   79: new f/AB
/*   */     //   82: dup
/*   */     //   83: astore #7
/*   */     //   85: aload #6
/*   */     //   87: getfield Af0 : Lf/ZH;
/*   */     //   90: dup
/*   */     //   91: astore #8
/*   */     //   93: invokevirtual TU : ()Lf/Uc;
/*   */     //   96: aload #8
/*   */     //   98: swap
/*   */     //   99: iload #4
/*   */     //   101: iconst_0
/*   */     //   102: iconst_1
/*   */     //   103: invokespecial <init> : (Lf/ZH;Lf/Uc;ZZZ)V
/*   */     //   106: aload #7
/*   */     //   108: invokespecial <init> : (Lf/jk0;Lf/AB;)V
/*   */     //   111: putfield MO : Lcom/badlogic/gdx/graphics/Texture;
/*   */     //   114: aload_3
/*   */     //   115: invokevirtual setFilter : (Lf/cu0;Lf/cu0;)V
/*   */     //   118: aload #6
/*   */     //   120: iconst_0
/*   */     //   121: putfield as : Z
/*   */     //   124: goto -> 14
/*   */     //   127: aload_0
/*   */     //   128: monitorexit
/*   */     //   129: aload_1
/*   */     //   130: getfield Z8 : I
/*   */     //   133: dup
/*   */     //   134: istore_2
/*   */     //   135: aload_0
/*   */     //   136: getfield dA : Lf/fQ;
/*   */     //   139: dup
/*   */     //   140: astore_3
/*   */     //   141: getfield Z8 : I
/*   */     //   144: if_icmpge -> 172
/*   */     //   147: aload_1
/*   */     //   148: new f/pe0
/*   */     //   151: dup
/*   */     //   152: aload_3
/*   */     //   153: iload_2
/*   */     //   154: invokevirtual get : (I)Ljava/lang/Object;
/*   */     //   157: checkcast f/jk0
/*   */     //   160: getfield MO : Lcom/badlogic/gdx/graphics/Texture;
/*   */     //   163: invokespecial <init> : (Lcom/badlogic/gdx/graphics/Texture;)V
/*   */     //   166: invokevirtual Com3 : (Ljava/lang/Object;)V
/*   */     //   169: goto -> 129
/*   */     //   172: return
/*   */     //   173: aload_0
/*   */     //   174: monitorexit
/*   */     //   175: athrow
/*   */     // Line number table:
/*   */     //   Java source line number -> byte code offset
/*   */     //   #1	-> 6
/*   */     //   #2	-> 33
/*   */     //   #3	-> 44
/*   */     //   #4	-> 130
/*   */     // Exception table:
/*   */     //   from	to	target	type
/*   */     //   6	12	173	finally
/*   */     //   14	19	173	finally
/*   */     //   22	30	173	finally
/*   */     //   33	36	173	finally
/*   */     //   42	47	173	finally
/*   */     //   53	68	173	finally
/*   */     //   71	82	173	finally
/*   */     //   85	90	173	finally
/*   */     //   93	127	173	finally
/*   */   } }


/* Location:              /Users/vnnsnnt/Documents/Codespace/JavaWorkspace/RedTrainer/src/main/java/org/trainer/client/PokeMMO.jar!/f/oF0.class
 * Java compiler version: 7 (51.0)
 * JD-Core Version:       1.1.3
 */