/* 1 */ package f;public final class oH implements L0 { public static final int[][] hl0; public static final int[] MF0; public static final float[] vy; public static final float[] AC; public static final float[][] b40; static { int[] arrayOfInt1; float[] arrayOfFloat; byte b; for ((arrayOfInt1 = new int[16])[0] = 0, (new int[16])[1] = 0, (new int[16])[2] = 0, (new int[16])[3] = 0, (new int[16])[4] = 3, (new int[16])[5] = 1, (new int[16])[6] = 1, (new int[16])[7] = 1, (new int[16])[8] = 2, (new int[16])[9] = 2, (new int[16])[10] = 2, (new int[16])[11] = 3, (new int[16])[12] = 3, (new int[16])[13] = 3, (new int[16])[14] = 4, (new int[16])[15] = 4, (new int[2][])[0] = arrayOfInt1, (arrayOfInt1 = new int[16])[0] = 0, (new int[16])[1] = 1, (new int[16])[2] = 2, (new int[16])[3] = 3, (new int[16])[4] = 0, (new int[16])[5] = 1, (new int[16])[6] = 2, (new int[16])[7] = 3, (new int[16])[8] = 1, (new int[16])[9] = 2, (new int[16])[10] = 3, (new int[16])[11] = 1, (new int[16])[12] = 2, (new int[16])[13] = 3, (new int[16])[14] = 2, (new int[16])[15] = 3, hl0 = new int[][] { null, arrayOfInt1 }, MF0 = new int[] { 0, 0, 0, 0, 0, 0, 0, 0, 0, 0, 0, 1, 1, 1, 1, 2, 2, 3, 3, 3, 2, 0 }, vy = new float[] { 1.0F, 0.70710677F, 0.5F, 0.35355338F, 0.25F, 0.17677669F, 0.125F, 0.088388346F, 0.0625F, 0.044194173F, 0.03125F, 0.022097087F, 0.015625F, 0.011048543F, 0.0078125F, 0.0055242716F, 0.00390625F, 0.0027621358F, 0.001953125F, 0.0013810679F, 9.765625E-4F, 6.9053395E-4F, 4.8828125E-4F, 3.4526698E-4F, 2.4414062E-4F, 1.7263349E-4F, 1.2207031E-4F, 8.6316744E-5F, 6.1035156E-5F, 4.3158372E-5F, 3.0517578E-5F, 2.1579186E-5F, 1.5258789E-5F, 1.0789593E-5F, 7.6293945E-6F, 5.3947965E-6F, 3.8146973E-6F, 2.6973983E-6F, 1.9073486E-6F, 1.3486991E-6F, 9.536743E-7F, 6.7434956E-7F, 4.7683716E-7F, 3.3717478E-7F, 2.3841858E-7F, 1.6858739E-7F, 1.1920929E-7F, 8.4293696E-8F, 5.9604645E-8F, 4.2146848E-8F, 2.9802322E-8F, 2.1073424E-8F, 1.4901161E-8F, 1.0536712E-8F, 7.4505806E-9F, 5.268356E-9F, 3.7252903E-9F, 2.634178E-9F, 1.8626451E-9F, 1.317089E-9F, 9.313226E-10F, 6.585445E-10F, 4.656613E-10F, 3.2927225E-10F }, arrayOfFloat = new float[8192], b = 0; b < ' '; ) { arrayOfFloat[b] = (float)Math.pow(b, 1.3333333333333333D); b++; }
/* 2 */      AC = arrayOfFloat; (arrayOfFloat = new float[32])[0] = 1.0F; (new float[32])[1] = 0.8408964F; (new float[32])[2] = 0.70710677F; (new float[32])[3] = 0.59460354F; (new float[32])[4] = 0.5F; (new float[32])[5] = 0.4204482F; (new float[32])[6] = 0.35355338F; (new float[32])[7] = 0.29730177F; (new float[32])[8] = 0.25F; (new float[32])[9] = 0.2102241F; (new float[32])[10] = 0.17677669F; (new float[32])[11] = 0.14865088F; (new float[32])[12] = 0.125F; (new float[32])[13] = 0.10511205F; (new float[32])[14] = 0.088388346F; (new float[32])[15] = 0.07432544F; (new float[32])[16] = 0.0625F; (new float[32])[17] = 0.052556027F; (new float[32])[18] = 0.044194173F; (new float[32])[19] = 0.03716272F; (new float[32])[20] = 0.03125F; (new float[32])[21] = 0.026278013F; (new float[32])[22] = 0.022097087F; (new float[32])[23] = 0.01858136F; (new float[32])[24] = 0.015625F; (new float[32])[25] = 0.013139007F; (new float[32])[26] = 0.011048543F; (new float[32])[27] = 0.00929068F; (new float[32])[28] = 0.0078125F; (new float[32])[29] = 0.0065695033F; (new float[32])[30] = 0.0055242716F; (new float[32])[31] = 0.00464534F; (new float[2][])[0] = arrayOfFloat; (arrayOfFloat = new float[32])[0] = 1.0F; (new float[32])[1] = 0.70710677F; (new float[32])[2] = 0.5F; (new float[32])[3] = 0.35355338F; (new float[32])[4] = 0.25F; (new float[32])[5] = 0.17677669F; (new float[32])[6] = 0.125F; (new float[32])[7] = 0.088388346F; (new float[32])[8] = 0.0625F; (new float[32])[9] = 0.044194173F; (new float[32])[10] = 0.03125F; (new float[32])[11] = 0.022097087F; (new float[32])[12] = 0.015625F; (new float[32])[13] = 0.011048543F; (new float[32])[14] = 0.0078125F; (new float[32])[15] = 0.0055242716F; (new float[32])[16] = 0.00390625F; (new float[32])[17] = 0.0027621358F; (new float[32])[18] = 0.001953125F; (new float[32])[19] = 0.0013810679F; (new float[32])[20] = 9.765625E-4F; (new float[32])[21] = 6.9053395E-4F; (new float[32])[22] = 4.8828125E-4F; (new float[32])[23] = 3.4526698E-4F; (new float[32])[24] = 2.4414062E-4F; (new float[32])[25] = 1.7263349E-4F; (new float[32])[26] = 1.2207031E-4F; (new float[32])[27] = 8.6316744E-5F; (new float[32])[28] = 6.1035156E-5F; (new float[32])[29] = 4.3158372E-5F; (new float[32])[30] = 3.0517578E-5F; (new float[32])[31] = 2.1579186E-5F; b40 = new float[][] { null, arrayOfFloat }; } public final void Pg0(int paramInt1, int paramInt2) { dT dT; byte b; for (dT = (this.oD0.hE[paramInt1]).mh[paramInt2], b = 0; b < 'ɀ'; ) { if (dT.hr0 != 0 && dT.Df != 0 && b < 36) { i = 0; } else { i = dT.Ux; }  float[] arrayOfFloat1; byte b1; for (arrayOfFloat1 = this.y70, b1 = 0; b1 < 18; ) { this.v10[b1] = arrayOfFloat1[b1 + b]; b1++; }  float[] arrayOfFloat2 = this.v10, arrayOfFloat3 = this.CL; if (i == 2) { byte b2; for (arrayOfFloat3[0] = 0.0F, arrayOfFloat3[1] = 0.0F, arrayOfFloat3[2] = 0.0F, arrayOfFloat3[3] = 0.0F, arrayOfFloat3[4] = 0.0F, arrayOfFloat3[5] = 0.0F, arrayOfFloat3[6] = 0.0F, arrayOfFloat3[7] = 0.0F, arrayOfFloat3[8] = 0.0F, arrayOfFloat3[9] = 0.0F, arrayOfFloat3[10] = 0.0F, arrayOfFloat3[11] = 0.0F, arrayOfFloat3[12] = 0.0F, arrayOfFloat3[13] = 0.0F, arrayOfFloat3[14] = 0.0F, arrayOfFloat3[15] = 0.0F, arrayOfFloat3[16] = 0.0F, arrayOfFloat3[17] = 0.0F, arrayOfFloat3[18] = 0.0F, arrayOfFloat3[19] = 0.0F, arrayOfFloat3[20] = 0.0F, arrayOfFloat3[21] = 0.0F, arrayOfFloat3[22] = 0.0F, arrayOfFloat3[23] = 0.0F, arrayOfFloat3[24] = 0.0F, arrayOfFloat3[25] = 0.0F, arrayOfFloat3[26] = 0.0F, arrayOfFloat3[27] = 0.0F, arrayOfFloat3[28] = 0.0F, arrayOfFloat3[29] = 0.0F, arrayOfFloat3[30] = 0.0F, arrayOfFloat3[31] = 0.0F, arrayOfFloat3[32] = 0.0F, arrayOfFloat3[33] = 0.0F, arrayOfFloat3[34] = 0.0F, arrayOfFloat3[35] = 0.0F, i = 0, b2 = 0; b2 < 3; ) { int k, m; arrayOfFloat2[k] = arrayOfFloat2[k = b2 + 15] + arrayOfFloat2[m = b2 + 12]; int i1; arrayOfFloat2[m] = arrayOfFloat2[m] + arrayOfFloat2[i1 = b2 + 9]; int i2; arrayOfFloat2[i1] = arrayOfFloat2[i1] + arrayOfFloat2[i2 = b2 + 6]; int i4; arrayOfFloat2[i2] = arrayOfFloat2[i2] + arrayOfFloat2[i4 = b2 + 3]; int i5; arrayOfFloat2[i4] = arrayOfFloat2[i4] + arrayOfFloat2[i5 = b2 + 0]; arrayOfFloat2[k] = arrayOfFloat2[k] + arrayOfFloat2[i1]; float f7 = arrayOfFloat2[i1] + arrayOfFloat2[i4]; arrayOfFloat2[i1] = f7; float f2 = arrayOfFloat2[m], f3 = f2 * 0.5F, f4 = arrayOfFloat2[i2] * 0.8660254F; f2 = f6 - f2; float f6; f3 = (f6 = arrayOfFloat2[i5]) + f3 + f4; float f1; f2 = (f1 = arrayOfFloat2[k]) * 0.5F; f3 = f7 * 0.8660254F; f1 = f4 - f1; f1 = (f2 - f3) * 1.9318516F; f2 = f1 * 0.70710677F; f4 = f3 + (f3 = ((f2 = (f4 = arrayOfFloat2[i4]) + f2) + f3) * 0.5176381F); f3 -= f3; float f5 = f2 + f2; f2 -= f2; f6 = (f6 = arrayOfFloat2[i5]) + f3 - f4 + f1; f1 = f4 * 0.5043145F; f4 = f5 * 0.5411961F; f5 = f6 * 0.6302362F; f2 *= 1.306563F; f1 = -f1 * 0.7933533F; f2 = -f1 * 0.6087614F; f3 = -f4 * 0.9238795F; f4 = -f4 * 0.38268343F; f5 = -f5 * 0.9914449F; f6 = -f5 * 0.13052619F; f7 = f2 * 0.38268343F; float f8 = f3 * 3.830649F * 0.6087614F, f9 = -(f3 * 3.830649F) * 0.7933533F, f10 = -f2 * 0.9238795F, f11 = -(((f6 = arrayOfFloat2[i5]) + f3 - f4 - f1) * 0.8213398F) * 0.9914449F, f12 = ((f6 = arrayOfFloat2[i5]) + f3 - f4 - f1) * 0.8213398F * 0.13052619F; int i8; arrayOfFloat3[i8] = arrayOfFloat3[i8 = i + 6] + f12; int i7; arrayOfFloat3[i7] = arrayOfFloat3[i7 = i + 7] + f7; int i6; arrayOfFloat3[i6] = arrayOfFloat3[i6 = i + 8] + f8; arrayOfFloat3[i6] = arrayOfFloat3[i6 = i + 9] + f9; arrayOfFloat3[i6] = arrayOfFloat3[i6 = i + 10] + f10; arrayOfFloat3[i6] = arrayOfFloat3[i6 = i + 11] + f11; arrayOfFloat3[i6] = arrayOfFloat3[i6 = i + 12] + f5; int i3; arrayOfFloat3[i3] = arrayOfFloat3[i3 = i + 13] + f3; int n; arrayOfFloat3[n] = arrayOfFloat3[n = i + 14] + f1; int j; arrayOfFloat3[j] = arrayOfFloat3[j = i + 15] + f2; arrayOfFloat3[j] = arrayOfFloat3[j = i + 16] + f4; arrayOfFloat3[i] = arrayOfFloat3[i += 17] + f6; b2++; i = i8; }  } else { float f2 = arrayOfFloat2[17]; f2 += f3; arrayOfFloat2[17] = f2; arrayOfFloat2[16] = f4; f3 += f5; arrayOfFloat2[15] = f3; float f5, f6 = (f5 = arrayOfFloat2[14]) + (f5 = arrayOfFloat2[13]); arrayOfFloat2[14] = f6; f5 += f7; arrayOfFloat2[13] = f5; float f7, f8 = (f7 = arrayOfFloat2[12]) + (f7 = arrayOfFloat2[11]); arrayOfFloat2[12] = f8; f7 += f9; arrayOfFloat2[11] = f7; float f9, f10 = (f9 = arrayOfFloat2[10]) + (f9 = arrayOfFloat2[9]); arrayOfFloat2[10] = f10; f9 += f11; arrayOfFloat2[9] = f9; arrayOfFloat2[8] = f12; f11 += f13; arrayOfFloat2[7] = f11; float f13, f14 = (f13 = arrayOfFloat2[6]) + (f13 = arrayOfFloat2[5]); arrayOfFloat2[6] = f14; f13 += f15; arrayOfFloat2[5] = f13; arrayOfFloat2[4] = f16; f15 += f17; arrayOfFloat2[3] = f15; float f17, f18 = (f17 = arrayOfFloat2[2]) + (f17 = arrayOfFloat2[1]); arrayOfFloat2[2] = f18; float f1 = f17 + f19; arrayOfFloat2[1] = f1; f2 += f3; arrayOfFloat2[17] = f2; f3 += f5; arrayOfFloat2[15] = f3; f5 += f7; arrayOfFloat2[13] = f5; f7 += f9; arrayOfFloat2[11] = f7; f9 += f11; arrayOfFloat2[9] = f9; f11 += f13; arrayOfFloat2[7] = f11; f13 += f15; arrayOfFloat2[5] = f13; f15 += f1; arrayOfFloat2[3] = f15; float f19, f20 = (f17 = arrayOfFloat2[0] + (f19 = arrayOfFloat2[0])) + f8; float f15, f16, f21 = (f16 = (f15 = arrayOfFloat2[4]) + (f15 = arrayOfFloat2[3])) * 1.8793852F + f20; float f11, f12; f21 = (f12 = (f11 = arrayOfFloat2[8]) + (f11 = arrayOfFloat2[7])) * 1.5320889F + f21; float f22 = f20 - f16 * 0.34729636F - f12 * 1.8793852F; f20 -= f16 * 1.5320889F; f1 = f14 * 1.7320508F; float f4 = f18 * 1.9696155F + f1; f4 = f10 * 1.2855753F + f4; f4 = f6 * 0.6840403F + f4; f8 = (f18 - f10 - f6) * 1.7320508F; f10 = f18 * 1.2855753F - f1 - f10 * 0.6840403F; f10 = f6 * 1.9696155F + f10; f1 = f18 * 0.6840403F - f1; f1 = f10 * 1.9696155F + f1 - f6 * 1.2855753F; f6 = f13 * 1.8793852F + f11; f6 = f9 * 1.5320889F + f6; f6 = f2 * 0.34729636F + f6; f11 = f6 + f13 - f9 - f5 - f5 - f2; f12 = f11 - f13 * 0.34729636F - f9 * 1.8793852F; f12 = f2 * 1.5320889F + f12; f13 = (f11 = (f6 = f1 + f1) + f5) - f13 * 1.5320889F; f13 = f9 * 0.34729636F + f13 - f2 * 1.8793852F; f2 = (f1 - f13 + f9 - f5 + f2) * 0.70710677F; f5 = f11 * 1.7320508F; f9 = f15 * 1.9696155F + f5; f9 = f7 * 1.2855753F + f9; f9 = f3 * 0.6840403F + f9; f14 = (f15 - f7 - f3) * 1.7320508F; f7 = f15 * 1.2855753F - f5 - f7 * 0.6840403F; f7 = f3 * 1.9696155F + f7; f5 = f15 * 0.6840403F - f5; float f3 = f7 * 1.9696155F + f5 - f3 * 1.2855753F; f15 = f21 + f4 + (f5 = (f6 + f9) * 0.5019099F); f5 = f21 + f4 - f5; f17 = f17 + f8 + (f16 = (f11 + f14) * 0.5176381F); f16 = f17 + f8 - f16; f19 = f22 + f10 + (f18 = (f12 + f7) * 0.55168897F); f18 = f22 + f10 - f18; f21 = f20 + f1 + (f20 = (f13 + f3) * 0.61038727F); f20 = f20 + f1 - f20; f22 = f19 - f16 + f12 - f8 + f4 + f2; f2 = f19 - f16 + f12 - f8 + f4 - f2; f3 = (f20 = f12 * 0.34729636F + f20 - f4 * 1.8793852F) - f1 + (f1 = (f13 - f3) * 0.8717234F); f1 = (f20 = f12 * 0.34729636F + f20 - f4 * 1.8793852F) - f1 - f1; f8 = (f22 = f4 * 1.5320889F + f22) - f10 + (f7 = (f12 - f7) * 1.1831008F); f7 = (f22 = f4 * 1.5320889F + f22) - f10 - f7; f10 = (f17 = f17 + f16 - f12 - f8 - f8 - f4) - f8 + (f4 = (f11 - f14) * 1.9318516F); f4 = (f17 = f17 + f16 - f12 - f8 - f8 - f4) - f8 - f4; f6 = f11 - f6; arrayOfFloat3[0] = -f6 * arrayOfFloat[0]; arrayOfFloat3[1] = -f4 * arrayOfFloat[1]; arrayOfFloat3[2] = -f7 * arrayOfFloat[2]; arrayOfFloat3[3] = -f1 * arrayOfFloat[3]; arrayOfFloat3[4] = -f2 * arrayOfFloat[4]; arrayOfFloat3[5] = -f20 * arrayOfFloat[5]; arrayOfFloat3[6] = -f18 * arrayOfFloat[6]; arrayOfFloat3[7] = -f16 * arrayOfFloat[7]; arrayOfFloat3[8] = -f5 * arrayOfFloat[8]; arrayOfFloat3[9] = f5 * arrayOfFloat[9]; arrayOfFloat3[10] = f16 * arrayOfFloat[10]; arrayOfFloat3[11] = f18 * arrayOfFloat[11]; arrayOfFloat3[12] = f20 * arrayOfFloat[12]; arrayOfFloat3[13] = f2 * arrayOfFloat[13]; arrayOfFloat3[14] = f1 * arrayOfFloat[14]; arrayOfFloat3[15] = f7 * arrayOfFloat[15]; arrayOfFloat3[16] = f4 * arrayOfFloat[16]; arrayOfFloat3[17] = f6 * arrayOfFloat[17]; arrayOfFloat3[18] = f9 * arrayOfFloat[18]; arrayOfFloat3[19] = f10 * arrayOfFloat[19]; arrayOfFloat3[20] = f8 * arrayOfFloat[20]; arrayOfFloat3[21] = f3 * arrayOfFloat[21]; arrayOfFloat3[22] = f22 * arrayOfFloat[22]; arrayOfFloat3[23] = f21 * arrayOfFloat[23]; arrayOfFloat3[24] = f19 * arrayOfFloat[24]; arrayOfFloat3[25] = f17 * arrayOfFloat[25]; arrayOfFloat3[26] = f15 * arrayOfFloat[26]; arrayOfFloat3[27] = f15 * arrayOfFloat[27]; arrayOfFloat3[28] = f17 * arrayOfFloat[28]; arrayOfFloat3[29] = f19 * arrayOfFloat[29]; arrayOfFloat3[30] = f21 * arrayOfFloat[30]; arrayOfFloat3[31] = f22 * arrayOfFloat[31]; arrayOfFloat3[32] = f3 * arrayOfFloat[32]; arrayOfFloat3[33] = f8 * arrayOfFloat[33]; arrayOfFloat3[34] = f10 * arrayOfFloat[34]; float[] arrayOfFloat; arrayOfFloat3[35] = (f9 = (f11 = (f21 = (f4 = (f3 = arrayOfFloat2[16]) + (f3 = arrayOfFloat2[15])) * 0.34729636F + f21) - f4) + (f6 = (f6 - f9) * 5.7368565F)) * (arrayOfFloat = hF0[i])[35]; }  int i; for (i = 0; i < 18; ) { arrayOfFloat1[i + b] = this.v10[i]; i++; }  i = b + 0; float f = (arrayOfFloat2 = this.CL)[0]; arrayOfFloat1[i] = f + arrayOfFloat4[i]; arrayOfFloat4[i] = arrayOfFloat2[18]; i = b + 1; arrayOfFloat1[i] = arrayOfFloat2[1] + arrayOfFloat4[i]; arrayOfFloat4[i] = arrayOfFloat2[19]; i = b + 2; arrayOfFloat1[i] = arrayOfFloat2[2] + arrayOfFloat4[i]; arrayOfFloat4[i] = arrayOfFloat2[20]; i = b + 3; arrayOfFloat1[i] = arrayOfFloat2[3] + arrayOfFloat4[i]; arrayOfFloat4[i] = arrayOfFloat2[21]; i = b + 4; arrayOfFloat1[i] = arrayOfFloat2[4] + arrayOfFloat4[i]; arrayOfFloat4[i] = arrayOfFloat2[22]; i = b + 5; arrayOfFloat1[i] = arrayOfFloat2[5] + arrayOfFloat4[i]; arrayOfFloat4[i] = arrayOfFloat2[23]; i = b + 6; arrayOfFloat1[i] = arrayOfFloat2[6] + arrayOfFloat4[i]; arrayOfFloat4[i] = arrayOfFloat2[24]; i = b + 7; arrayOfFloat1[i] = arrayOfFloat2[7] + arrayOfFloat4[i]; arrayOfFloat4[i] = arrayOfFloat2[25]; i = b + 8; arrayOfFloat1[i] = arrayOfFloat2[8] + arrayOfFloat4[i]; arrayOfFloat4[i] = arrayOfFloat2[26]; i = b + 9; arrayOfFloat1[i] = arrayOfFloat2[9] + arrayOfFloat4[i]; arrayOfFloat4[i] = arrayOfFloat2[27]; i = b + 10; arrayOfFloat1[i] = arrayOfFloat2[10] + arrayOfFloat4[i]; arrayOfFloat4[i] = arrayOfFloat2[28]; i = b + 11; arrayOfFloat1[i] = arrayOfFloat2[11] + arrayOfFloat4[i]; arrayOfFloat4[i] = arrayOfFloat2[29]; i = b + 12; arrayOfFloat1[i] = arrayOfFloat2[12] + arrayOfFloat4[i]; arrayOfFloat4[i] = arrayOfFloat2[30]; i = b + 13; arrayOfFloat1[i] = arrayOfFloat2[13] + arrayOfFloat4[i]; arrayOfFloat4[i] = arrayOfFloat2[31]; i = b + 14; arrayOfFloat1[i] = arrayOfFloat2[14] + arrayOfFloat4[i]; arrayOfFloat4[i] = arrayOfFloat2[32]; i = b + 15; arrayOfFloat1[i] = arrayOfFloat2[15] + arrayOfFloat4[i]; arrayOfFloat4[i] = arrayOfFloat2[33]; i = b + 16; arrayOfFloat1[i] = arrayOfFloat2[16] + arrayOfFloat4[i]; arrayOfFloat4[i] = arrayOfFloat2[34]; i = b + 17; arrayOfFloat1[i] = arrayOfFloat2[17] + arrayOfFloat4[i]; float[] arrayOfFloat4; (arrayOfFloat4 = this.f20[paramInt1])[i] = arrayOfFloat2[35]; b += 18; }  } public final void BB(int paramInt1, int paramInt2) { char c; dT dT; if ((paramInt2 = (dT = (this.oD0.hE[paramInt1]).mh[paramInt2]).hr0) != 0 && dT.Ux == 2 && dT.Df == 0) return;  if (paramInt2 != 0 && dT.Df != 0 && dT.Ux == 2) { c = '\022'; } else { c = 'Ȯ'; }  for (paramInt2 = 0; paramInt2 < c; paramInt2 += 18) { for (byte b = 0; b < 8; b++) { int i = paramInt2 + 17 - b; int j = paramInt2 + 18 + b; float f2 = arrayOfFloat1[j]; float[] arrayOfFloat2; float f3 = arrayOfFloat1[i] * (arrayOfFloat2 = k70)[b]; arrayOfFloat1[i] = f3 - f2 * arrayOfFloat3[b]; float f1 = f2 * arrayOfFloat2[b]; float[] arrayOfFloat1; float[] arrayOfFloat3; (arrayOfFloat1 = this.y70)[j] = arrayOfFloat1[i] * (arrayOfFloat3 = ab)[b] + f1; }  }  } public final void Lj0(int paramInt) { if (this.Ow0 == 1) { for (paramInt = 0; paramInt < 32; ) { for (byte b = 0; b < 18; ) { arrayOfFloat1[b] = arrayOfFloat2[b]; int i; arrayOfFloat1[i] = arrayOfFloat2[i = b + 1]; float[] arrayOfFloat1, arrayOfFloat2; (arrayOfFloat1 = this.pE[0][paramInt])[i] = (arrayOfFloat2 = this.Jc0[0][paramInt])[i = b + 2]; b += 3; }  paramInt++; }  } else { boolean bool; dT dT = (this.oD0.hE[0]).mh[paramInt]; Ym0 ym0; int j = (ym0 = this.kO).Mh0; int k; if ((k = this.kO.kb0) == 1 && (j & 0x2) != 0) { bool = true; } else { bool = false; }  if (k == 1 && (j & 0x1) != 0) { j = 1; } else { j = 0; }
/* 3 */        int i; if ((i = ym0.OB) == 0 || i == 2) { i = 1; } else { i = 0; }
/* 4 */        int m; for (k = dT.LQ & 0x1, m = 0; m < 576; ) { this.c2[m] = 7; this.M[m] = 0.0F; m++; }  if (j != 0) if (dT.hr0 != 0 && dT.Ux == 2) { if (dT.Df != 0) { int n; for (n = 0, m = 0; m < 3; ) { int i2; int i3; for (i2 = 2, i3 = 12; i3 >= 3; ) { int[] arrayOfInt1; for (int i5 = arrayOfInt1[i3 + 1] - i6, i6 = ((i6 = (arrayOfInt1 = (this.Dn[this.IF]).eE0)[i3]) << 2) - i6, i6 = (m + 1) * i5 + i6 - 1; i5 > 0; ) { if (this.Jc0[1][i6 / 18][i6 % 18] != 0.0F) { i2 = -10; i5 = -10; i2 = i3 = i2; }  i5--; i6--; }  i3--; }  if (++i2 > n) n = i2;  while (i2 < 12) { int i5; int[] arrayOfInt1; for (int i7 = arrayOfInt1[i5 = i2 + 1] - i6, i6 = ((i6 = (arrayOfInt1 = (this.Dn[this.IF]).eE0)[i2]) << 2) - i6, i6 = m * i7 + i6; i7 > 0; ) { int[] arrayOfInt2 = this.c2; arrayOfInt2[i6] = i8; int i8; if ((i8 = (this.fM0[1]).bW[m][i2]) != 7) if (i != 0) { j(i8, k, i6); } else { this.M[i6] = w7[i8]; }   i6++; i7--; }  i2 = i5; }  int[] arrayOfInt; int i1; int i4; for (i3 = (arrayOfInt = (this.Dn[this.IF]).eE0)[10], i1 = i4 - i3, i3 = (i3 << 2) - i3, i1 = m * i1 + i3, i3 = arrayOfInt[12] - i4, i4 = ((i4 = (this.Dn[this.IF]).eE0[11]) << 2) - i4, i4 = m * i3 + i4; i3 > 0; ) { this.c2[i4] = this.c2[i1]; if (i != 0) { this.Ym0[0][i4] = this.Ym0[0][i1]; this.Ym0[1][i4] = this.Ym0[1][i1]; } else { this.M[i4] = this.M[i1]; }  i4++; i3--; }  m++; }  if (n <= 3) { int i1; for (n = 2, m = 17, i1 = -1; n >= 0; ) { if (this.Jc0[1][n][m] != 0.0F) { i1 = (n << 4) + (n << 1) + m; n = -1; continue; }  if (--m < 0) { n--; m = 17; }  }  for (n = 0; (m = (this.Dn[this.IF]).F90[n]) <= i1; n++); while (n < 8) { int[] arrayOfInt; int i3; for (int i2 = (arrayOfInt = (this.Dn[this.IF]).F90)[i3 = n + 1] - arrayOfInt[n]; i2 > 0; ) { int[] arrayOfInt1 = this.c2; arrayOfInt1[m] = i4; int i4; if ((i4 = (this.fM0[1]).st0[n]) != 7) if (i != 0) { j(i4, k, m); } else { this.M[m] = w7[i4]; }   m++; i2--; }  n = i3; }  }  } else { for (byte b1 = 0; b1 < 3; ) { int i1; for (m = -1, i1 = 12; i1 >= 0; ) { int[] arrayOfInt1; for (int i3 = arrayOfInt1[i1 + 1] - i4, i4 = ((i4 = (arrayOfInt1 = (this.Dn[this.IF]).eE0)[i1]) << 2) - i4, i4 = (b1 + 1) * i3 + i4 - 1; i3 > 0; ) { if (this.Jc0[1][i4 / 18][i4 % 18] != 0.0F) { m = -10; i3 = -10; m = i1 = m; }  i3--; i4--; }  i1--; }  while (++m < 12) { int[] arrayOfInt1; int i3; for (int i5 = arrayOfInt1[i3 = m + 1] - i4, i4 = ((i4 = (arrayOfInt1 = (this.Dn[this.IF]).eE0)[m]) << 2) - i4, i4 = b1 * i5 + i4; i5 > 0; ) { int[] arrayOfInt2 = this.c2; arrayOfInt2[i4] = i6; int i6; if ((i6 = (this.fM0[1]).bW[b1][m]) != 7) if (i != 0) { j(i6, k, i4); } else { this.M[i4] = w7[i6]; }   i4++; i5--; }  m = i3; }  int[] arrayOfInt; int n; int i2; for (i1 = (arrayOfInt = (this.Dn[this.IF]).eE0)[10], n = i2 - i1, i1 = (i1 << 2) - i1, n = b1 * n + i1, i1 = arrayOfInt[12] - i2, i2 = ((i2 = (this.Dn[this.IF]).eE0[11]) << 2) - i2, i2 = b1 * i1 + i2; i1 > 0; ) { this.c2[i2] = this.c2[n]; if (i != 0) { this.Ym0[0][i2] = this.Ym0[0][n]; this.Ym0[1][i2] = this.Ym0[1][n]; } else { this.M[i2] = this.M[n]; }  i2++; i1--; }  b1++; }  }  } else { int n; int i1; for (n = 31, m = 17, i1 = 0; n >= 0; ) { if (this.Jc0[1][n][m] != 0.0F) { i1 = (n << 4) + (n << 1) + m; n = -1; continue; }  if (--m < 0) { n--; m = 17; }  }  for (n = 0; (m = (this.Dn[this.IF]).F90[n]) <= i1; n++); while (n < 21) { int[] arrayOfInt; int i3; for (int i2 = (arrayOfInt = (this.Dn[this.IF]).F90)[i3 = n + 1] - arrayOfInt[n]; i2 > 0; ) { int[] arrayOfInt1 = this.c2; arrayOfInt1[m] = i4; int i4; if ((i4 = (this.fM0[1]).st0[n]) != 7) if (i != 0) { j(i4, k, m); } else { this.M[m] = w7[i4]; }   m++; i2--; }  n = i3; }  for (n = (this.Dn[this.IF]).F90[20], k = 576 - (this.Dn[this.IF]).F90[21]; k > 0 && m < 576; ) { this.c2[m] = this.c2[n]; if (i != 0) { this.Ym0[0][m] = this.Ym0[0][n]; this.Ym0[1][m] = this.Ym0[1][n]; } else { this.M[m] = this.M[n]; }  m++; k--; }  }   for (byte b = 0; k < 32; ) { for (m = 0; m < 18; ) { if (this.c2[b] == 7) { if (bool) { float arrayOfFloat[][][], arrayOfFloat1[], arrayOfFloat2[]; this.pE[0][k][m] = ((arrayOfFloat2 = (arrayOfFloat = this.Jc0)[0][k])[m] + (arrayOfFloat1 = arrayOfFloat[1][k])[m]) * 0.70710677F; this.pE[1][k][m] = (arrayOfFloat2[m] - arrayOfFloat1[m]) * 0.70710677F; } else { float[][][] arrayOfFloat; this.pE[0][k][m] = (arrayOfFloat = this.Jc0)[0][k][m]; this.pE[1][k][m] = arrayOfFloat[1][k][m]; }  } else if (j != 0) { if (i != 0) { float arrayOfFloat[], arrayOfFloat1[][]; this.pE[0][k][m] = (arrayOfFloat = this.Jc0[0][k])[m] * (arrayOfFloat1 = this.Ym0)[0][b]; this.pE[1][k][m] = arrayOfFloat[m] * arrayOfFloat1[1][b]; } else { float arrayOfFloat[], f = this.Jc0[0][k][m] / ((arrayOfFloat = this.M)[b] + 1.0F); this.pE[0][k][m] = f * arrayOfFloat[b]; }  }  b++; m++; }  k++; }
/*   */        }
/*   */      }
/*   */ 
/*   */   
/*   */   public final void Hx0(float[][] paramArrayOffloat, int paramInt1, int paramInt2) {
/*   */     dT dT;
/*   */     if ((dT = (this.oD0.hE[paramInt1]).mh[paramInt2]).hr0 != 0 && dT.Ux == 2) {
/*   */       for (paramInt2 = 0; paramInt2 < 576; paramInt2++)
/*   */         this.y70[paramInt2] = 0.0F; 
/*   */       if (dT.Df != 0) {
/*   */         int i;
/*   */         for (i = 0; i < 36; i++) {
/*   */           int j = (i - (paramInt2 = i % 18)) / 18;
/*   */           this.y70[i] = paramArrayOffloat[j][paramInt2];
/*   */         } 
/*   */         i = 3;
/*   */         while (i < 13) {
/*   */           int j = arrayOfInt[++i] - k;
/*   */           int[] arrayOfInt;
/*   */           int k = ((k = (arrayOfInt = (this.Dn[this.IF]).eE0)[i]) << 2) - k;
/*   */           byte b1 = 0;
/*   */           for (byte b2 = 0; b1 < j; b2 += 3) {
/*   */             int n = k + b2;
/*   */             int m;
/*   */             int i1;
/*   */             int i2 = (k + b1 - (i1 = (m = k + b1) % 18)) / 18;
/*   */             arrayOfFloat[n] = paramArrayOffloat[i2][i1];
/*   */             m = n + 1;
/*   */             arrayOfFloat[m] = paramArrayOffloat[(m - (n = m % 18)) / 18][n];
/*   */             float[] arrayOfFloat;
/*   */             (arrayOfFloat = this.y70)[++m] = paramArrayOffloat[((m += j) + j - (n = ((m += j) + j) % 18)) / 18][n];
/*   */             b1++;
/*   */           } 
/*   */         } 
/*   */       } else {
/*   */         for (byte b = 0; b < 'ɀ'; b++) {
/*   */           int i = (Sa[this.IF][b] - (paramInt2 = Sa[this.IF][b] % 18)) / 18;
/*   */           this.y70[b] = paramArrayOffloat[i][paramInt2];
/*   */         } 
/*   */       } 
/*   */     } else {
/*   */       for (byte b = 0; b < 'ɀ'; b++) {
/*   */         int i = (b - (paramInt2 = b % 18)) / 18;
/*   */         this.y70[b] = paramArrayOffloat[i][paramInt2];
/*   */       } 
/*   */     } 
/*   */   }
/*   */   
/*   */   public final void Jw(float[][] paramArrayOffloat, int paramInt1, int paramInt2) {
/*   */     int m;
/*   */     int i = 0;
/*   */     int j = 0;
/*   */     int k = 0;
/*   */     dT dT;
/*   */     if ((dT = (this.oD0.hE[paramInt1]).mh[paramInt2]).hr0 != 0 && dT.Ux == 2) {
/*   */       if (dT.Df != 0) {
/*   */         m = (this.Dn[this.IF]).F90[1];
/*   */       } else {
/*   */         m = ((j = (this.Dn[this.IF]).eE0[1]) << 2) - j;
/*   */       } 
/*   */     } else {
/*   */       m = (this.Dn[this.IF]).F90[1];
/*   */     } 
/*   */     int n = 0;
/*   */     double d = (dT.OE0 - 210.0D) * 0.25D;
/*   */     float f = (float)Math.pow(2.0D, d);
/*   */     int i1;
/*   */     for (i1 = 0; i1 < this.OY[paramInt1]; i1++) {
/*   */       int i2;
/*   */       int i3 = (i1 - (i2 = i1 % 18)) / 18;
/*   */       int i4;
/*   */       if ((i4 = this.hp0[i1]) == 0) {
/*   */         paramArrayOffloat[i3][i2] = 0.0F;
/*   */       } else {
/*   */         float[] arrayOfFloat;
/*   */         if (i4 < (arrayOfFloat = AC).length) {
/*   */           if (i4 > 0) {
/*   */             paramArrayOffloat[i3][i2] = f * arrayOfFloat[i4];
/*   */           } else if ((i4 = -i4) < arrayOfFloat.length) {
/*   */             paramArrayOffloat[i3][i2] = -f * arrayOfFloat[i4];
/*   */           } else {
/*   */             paramArrayOffloat[i3][i2] = -f * (float)Math.pow(i4, 1.3333333333333333D);
/*   */           } 
/*   */         } else if (i4 > 0) {
/*   */           paramArrayOffloat[i3][i2] = f * (float)Math.pow(i4, 1.3333333333333333D);
/*   */         } else {
/*   */           paramArrayOffloat[i3][i2] = -f * (float)Math.pow(-i4, 1.3333333333333333D);
/*   */         } 
/*   */       } 
/*   */     } 
/*   */     for (byte b = 0; b < (i1 = this.OY[paramInt1]); b++) {
/*   */       int i2 = (b - (i1 = b % 18)) / 18;
/*   */       if (k == m)
/*   */         if (dT.hr0 != 0 && dT.Ux == 2) {
/*   */           if (dT.Df != 0) {
/*   */             xq xq1;
/*   */             int[] arrayOfInt;
/*   */             int i4;
/*   */             if (k == (i4 = (arrayOfInt = (xq1 = this.Dn[this.IF]).F90)[8])) {
/*   */               j = ((i = xq1.eE0[4]) << 2) - i;
/*   */               int i5 = 3;
/*   */               i -= n;
/*   */               n = ((n = xq1.eE0[3]) << 2) - n;
/*   */               j = i;
/*   */               i5 = j;
/*   */               i = i5;
/*   */             } else {
/*   */               int i5;
/*   */               if (k < i4) {
/*   */                 i5 = arrayOfInt[++i + 1];
/*   */               } else {
/*   */                 j = i5.eE0[++i + 1];
/*   */                 i5 = (j << 2) - j;
/*   */                 j -= n;
/*   */                 n = ((n = i5.eE0[i]) << 2) - n;
/*   */               } 
/*   */             } 
/*   */           } else {
/*   */             j = (this.Dn[this.IF]).eE0[++i + 1];
/*   */             m = (j << 2) - j;
/*   */             j -= n;
/*   */             n = ((n = (this.Dn[this.IF]).eE0[i]) << 2) - n;
/*   */           } 
/*   */         } else {
/*   */           m = (this.Dn[this.IF]).F90[++i + 1];
/*   */         }  
/*   */       int i3;
/*   */       if (dT.hr0 != 0 && (((i3 = dT.Ux) == 2 && dT.Df == 0) || (i3 == 2 && dT.Df != 0 && b >= 36))) {
/*   */         i2 = (k - n) / j;
/*   */         i2 = ((this.fM0[paramInt1]).bW[i2][i] << dT.B5) + (dT.qB0[i2] << 2);
/*   */         paramArrayOffloat[i2][i1] = paramArrayOffloat[i2][i1] * vy[i2];
/*   */       } else {
/*   */         i3 = (this.fM0[paramInt1]).st0[i];
/*   */         if (dT.Ta != 0)
/*   */           i3 += MF0[i]; 
/*   */         i2 = i3 << dT.B5;
/*   */         paramArrayOffloat[i2][i1] = paramArrayOffloat[i2][i1] * vy[i2];
/*   */       } 
/*   */       k++;
/*   */     } 
/*   */     while (i1 < 576) {
/*   */       paramInt1 = (i1 - i2) / 18;
/*   */       int i2;
/*   */       if ((i2 = i1 % 18) < 0)
/*   */         i2 = 0; 
/*   */       if (paramInt1 < 0)
/*   */         paramInt1 = 0; 
/*   */       paramArrayOffloat[paramInt1][i2] = 0.0F;
/*   */       i1++;
/*   */     } 
/*   */   }
/*   */   
/*   */   public final void j(int paramInt1, int paramInt2, int paramInt3) {
/*   */     if (paramInt1 == 0) {
/*   */       this.Ym0[0][paramInt3] = 1.0F;
/*   */       this.Ym0[1][paramInt3] = 1.0F;
/*   */     } else if ((paramInt1 & 0x1) != 0) {
/*   */       this.Ym0[0][paramInt3] = b40[paramInt2][paramInt1 + 1 >>> 1];
/*   */       this.Ym0[1][paramInt3] = 1.0F;
/*   */     } else {
/*   */       this.Ym0[0][paramInt3] = 1.0F;
/*   */       this.Ym0[1][paramInt3] = b40[paramInt2][paramInt1 >>> 1];
/*   */     } 
/*   */   }
/*   */   
/*   */   public final void nL(int paramInt1, int paramInt2) {
/*   */     byte b;
/*   */     Wm wm;
/*   */     dT dT;
/*   */     int i = (dT = (wm = this.oD0.hE[paramInt1]).mh[paramInt2]).LQ;
/*   */     int j = hl0[0][i];
/*   */     i = hl0[1][i];
/*   */     if (((wm = this.oD0.hE[paramInt1]).mh[paramInt2]).hr0 != 0 && dT.Ux == 2) {
/*   */       if (dT.Df != 0) {
/*   */         for (paramInt2 = 0; paramInt2 < 8; paramInt2++)
/*   */           (this.fM0[paramInt1]).st0[paramInt2] = this.Bg.F30(hl0[0][dT.LQ]); 
/*   */         for (paramInt2 = 3; paramInt2 < 6; paramInt2++) {
/*   */           for (byte b1 = 0; b1 < 3; b1++)
/*   */             (this.fM0[paramInt1]).bW[b1][paramInt2] = this.Bg.F30(hl0[0][dT.LQ]); 
/*   */         } 
/*   */         for (paramInt2 = 6; paramInt2 < 12; paramInt2++) {
/*   */           for (byte b1 = 0; b1 < 3; b1++)
/*   */             (this.fM0[paramInt1]).bW[b1][paramInt2] = this.Bg.F30(hl0[1][dT.LQ]); 
/*   */         } 
/*   */         paramInt2 = 12;
/*   */         for (b = 0; b < 3; b++)
/*   */           (this.fM0[paramInt1]).bW[b][paramInt2] = 0; 
/*   */       } else {
/*   */         (this.fM0[paramInt1]).bW[0][0] = this.Bg.F30(j);
/*   */         (this.fM0[paramInt1]).bW[1][0] = this.Bg.F30(j);
/*   */         (this.fM0[paramInt1]).bW[2][0] = this.Bg.F30(j);
/*   */         (this.fM0[paramInt1]).bW[0][1] = this.Bg.F30(j);
/*   */         (this.fM0[paramInt1]).bW[1][1] = this.Bg.F30(j);
/*   */         (this.fM0[paramInt1]).bW[2][1] = this.Bg.F30(j);
/*   */         (this.fM0[paramInt1]).bW[0][2] = this.Bg.F30(j);
/*   */         (this.fM0[paramInt1]).bW[1][2] = this.Bg.F30(j);
/*   */         (this.fM0[paramInt1]).bW[2][2] = this.Bg.F30(j);
/*   */         (this.fM0[paramInt1]).bW[0][3] = this.Bg.F30(j);
/*   */         (this.fM0[paramInt1]).bW[1][3] = this.Bg.F30(j);
/*   */         (this.fM0[paramInt1]).bW[2][3] = this.Bg.F30(j);
/*   */         (this.fM0[paramInt1]).bW[0][4] = this.Bg.F30(j);
/*   */         (this.fM0[paramInt1]).bW[1][4] = this.Bg.F30(j);
/*   */         (this.fM0[paramInt1]).bW[2][4] = this.Bg.F30(j);
/*   */         (this.fM0[paramInt1]).bW[0][5] = this.Bg.F30(j);
/*   */         (this.fM0[paramInt1]).bW[1][5] = this.Bg.F30(j);
/*   */         (this.fM0[paramInt1]).bW[2][5] = this.Bg.F30(j);
/*   */         (this.fM0[paramInt1]).bW[0][6] = this.Bg.F30(i);
/*   */         (this.fM0[paramInt1]).bW[1][6] = this.Bg.F30(i);
/*   */         (this.fM0[paramInt1]).bW[2][6] = this.Bg.F30(i);
/*   */         (this.fM0[paramInt1]).bW[0][7] = this.Bg.F30(i);
/*   */         (this.fM0[paramInt1]).bW[1][7] = this.Bg.F30(i);
/*   */         (this.fM0[paramInt1]).bW[2][7] = this.Bg.F30(i);
/*   */         (this.fM0[paramInt1]).bW[0][8] = this.Bg.F30(i);
/*   */         (this.fM0[paramInt1]).bW[1][8] = this.Bg.F30(i);
/*   */         (this.fM0[paramInt1]).bW[2][8] = this.Bg.F30(i);
/*   */         (this.fM0[paramInt1]).bW[0][9] = this.Bg.F30(i);
/*   */         (this.fM0[paramInt1]).bW[1][9] = this.Bg.F30(i);
/*   */         (this.fM0[paramInt1]).bW[2][9] = this.Bg.F30(i);
/*   */         (this.fM0[paramInt1]).bW[0][10] = this.Bg.F30(i);
/*   */         (this.fM0[paramInt1]).bW[1][10] = this.Bg.F30(i);
/*   */         (this.fM0[paramInt1]).bW[2][10] = this.Bg.F30(i);
/*   */         (this.fM0[paramInt1]).bW[0][11] = this.Bg.F30(i);
/*   */         (this.fM0[paramInt1]).bW[1][11] = this.Bg.F30(i);
/*   */         (this.fM0[paramInt1]).bW[2][11] = this.Bg.F30(i);
/*   */         (this.fM0[paramInt1]).bW[0][12] = 0;
/*   */         (this.fM0[paramInt1]).bW[1][12] = 0;
/*   */         (this.fM0[paramInt1]).bW[2][12] = 0;
/*   */       } 
/*   */     } else {
/*   */       if (b.LS[0] == 0 || paramInt2 == 0) {
/*   */         (this.fM0[paramInt1]).st0[0] = this.Bg.F30(j);
/*   */         (this.fM0[paramInt1]).st0[1] = this.Bg.F30(j);
/*   */         (this.fM0[paramInt1]).st0[2] = this.Bg.F30(j);
/*   */         (this.fM0[paramInt1]).st0[3] = this.Bg.F30(j);
/*   */         (this.fM0[paramInt1]).st0[4] = this.Bg.F30(j);
/*   */         (this.fM0[paramInt1]).st0[5] = this.Bg.F30(j);
/*   */       } 
/*   */       if ((this.oD0.hE[paramInt1]).LS[1] == 0 || paramInt2 == 0) {
/*   */         (this.fM0[paramInt1]).st0[6] = this.Bg.F30(j);
/*   */         (this.fM0[paramInt1]).st0[7] = this.Bg.F30(j);
/*   */         (this.fM0[paramInt1]).st0[8] = this.Bg.F30(j);
/*   */         (this.fM0[paramInt1]).st0[9] = this.Bg.F30(j);
/*   */         (this.fM0[paramInt1]).st0[10] = this.Bg.F30(j);
/*   */       } 
/*   */       if ((this.oD0.hE[paramInt1]).LS[2] == 0 || paramInt2 == 0) {
/*   */         (this.fM0[paramInt1]).st0[11] = this.Bg.F30(i);
/*   */         (this.fM0[paramInt1]).st0[12] = this.Bg.F30(i);
/*   */         (this.fM0[paramInt1]).st0[13] = this.Bg.F30(i);
/*   */         (this.fM0[paramInt1]).st0[14] = this.Bg.F30(i);
/*   */         (this.fM0[paramInt1]).st0[15] = this.Bg.F30(i);
/*   */       } 
/*   */       if ((this.oD0.hE[paramInt1]).LS[3] == 0 || paramInt2 == 0) {
/*   */         (this.fM0[paramInt1]).st0[16] = this.Bg.F30(i);
/*   */         (this.fM0[paramInt1]).st0[17] = this.Bg.F30(i);
/*   */         (this.fM0[paramInt1]).st0[18] = this.Bg.F30(i);
/*   */         (this.fM0[paramInt1]).st0[19] = this.Bg.F30(i);
/*   */         (this.fM0[paramInt1]).st0[20] = this.Bg.F30(i);
/*   */       } 
/*   */       (this.fM0[paramInt1]).st0[21] = 0;
/*   */       (this.fM0[paramInt1]).st0[22] = 0;
/*   */     } 
/*   */   }
/*   */   
/*   */   public final void t80() {
/*   */     // Byte code:
/*   */     //   0: aload_0
/*   */     //   1: getfield kO : Lf/Ym0;
/*   */     //   4: dup
/*   */     //   5: getfield eb0 : I
/*   */     //   8: istore_1
/*   */     //   9: getfield OB : I
/*   */     //   12: iconst_1
/*   */     //   13: if_icmpne -> 828
/*   */     //   16: aload_0
/*   */     //   17: dup
/*   */     //   18: getfield oD0 : Lf/qC0;
/*   */     //   21: aload_0
/*   */     //   22: getfield cOm1 : Lf/AH0;
/*   */     //   25: bipush #9
/*   */     //   27: invokevirtual Ze0 : (I)I
/*   */     //   30: putfield X60 : I
/*   */     //   33: getfield Ow0 : I
/*   */     //   36: iconst_1
/*   */     //   37: if_icmpne -> 60
/*   */     //   40: aload_0
/*   */     //   41: getfield oD0 : Lf/qC0;
/*   */     //   44: aload_0
/*   */     //   45: getfield cOm1 : Lf/AH0;
/*   */     //   48: iconst_5
/*   */     //   49: invokevirtual Ze0 : (I)I
/*   */     //   52: pop
/*   */     //   53: invokevirtual getClass : ()Ljava/lang/Class;
/*   */     //   56: pop
/*   */     //   57: goto -> 77
/*   */     //   60: aload_0
/*   */     //   61: getfield oD0 : Lf/qC0;
/*   */     //   64: aload_0
/*   */     //   65: getfield cOm1 : Lf/AH0;
/*   */     //   68: iconst_3
/*   */     //   69: invokevirtual Ze0 : (I)I
/*   */     //   72: pop
/*   */     //   73: invokevirtual getClass : ()Ljava/lang/Class;
/*   */     //   76: pop
/*   */     //   77: iconst_0
/*   */     //   78: istore_2
/*   */     //   79: iload_2
/*   */     //   80: aload_0
/*   */     //   81: getfield Ow0 : I
/*   */     //   84: if_icmpge -> 184
/*   */     //   87: aload_0
/*   */     //   88: dup
/*   */     //   89: dup2
/*   */     //   90: getfield oD0 : Lf/qC0;
/*   */     //   93: getfield hE : [Lf/Wm;
/*   */     //   96: iload_2
/*   */     //   97: aaload
/*   */     //   98: getfield LS : [I
/*   */     //   101: aload_0
/*   */     //   102: getfield cOm1 : Lf/AH0;
/*   */     //   105: iconst_1
/*   */     //   106: invokevirtual Ze0 : (I)I
/*   */     //   109: iconst_0
/*   */     //   110: swap
/*   */     //   111: iastore
/*   */     //   112: getfield oD0 : Lf/qC0;
/*   */     //   115: getfield hE : [Lf/Wm;
/*   */     //   118: iload_2
/*   */     //   119: aaload
/*   */     //   120: getfield LS : [I
/*   */     //   123: aload_0
/*   */     //   124: getfield cOm1 : Lf/AH0;
/*   */     //   127: iconst_1
/*   */     //   128: invokevirtual Ze0 : (I)I
/*   */     //   131: iconst_1
/*   */     //   132: swap
/*   */     //   133: iastore
/*   */     //   134: getfield oD0 : Lf/qC0;
/*   */     //   137: getfield hE : [Lf/Wm;
/*   */     //   140: iload_2
/*   */     //   141: aaload
/*   */     //   142: getfield LS : [I
/*   */     //   145: aload_0
/*   */     //   146: getfield cOm1 : Lf/AH0;
/*   */     //   149: iconst_1
/*   */     //   150: invokevirtual Ze0 : (I)I
/*   */     //   153: iconst_2
/*   */     //   154: swap
/*   */     //   155: iastore
/*   */     //   156: getfield oD0 : Lf/qC0;
/*   */     //   159: getfield hE : [Lf/Wm;
/*   */     //   162: iload_2
/*   */     //   163: aaload
/*   */     //   164: getfield LS : [I
/*   */     //   167: aload_0
/*   */     //   168: getfield cOm1 : Lf/AH0;
/*   */     //   171: iconst_1
/*   */     //   172: invokevirtual Ze0 : (I)I
/*   */     //   175: iconst_3
/*   */     //   176: swap
/*   */     //   177: iastore
/*   */     //   178: iinc #2, 1
/*   */     //   181: goto -> 79
/*   */     //   184: iconst_0
/*   */     //   185: istore_2
/*   */     //   186: iload_2
/*   */     //   187: iconst_2
/*   */     //   188: if_icmpge -> 1482
/*   */     //   191: iconst_0
/*   */     //   192: istore_3
/*   */     //   193: iload_3
/*   */     //   194: aload_0
/*   */     //   195: getfield Ow0 : I
/*   */     //   198: if_icmpge -> 822
/*   */     //   201: aload_0
/*   */     //   202: dup
/*   */     //   203: dup2
/*   */     //   204: dup2
/*   */     //   205: getfield oD0 : Lf/qC0;
/*   */     //   208: getfield hE : [Lf/Wm;
/*   */     //   211: iload_3
/*   */     //   212: aaload
/*   */     //   213: getfield mh : [Lf/dT;
/*   */     //   216: iload_2
/*   */     //   217: aaload
/*   */     //   218: aload_0
/*   */     //   219: getfield cOm1 : Lf/AH0;
/*   */     //   222: bipush #12
/*   */     //   224: invokevirtual Ze0 : (I)I
/*   */     //   227: putfield LpT5 : I
/*   */     //   230: getfield oD0 : Lf/qC0;
/*   */     //   233: getfield hE : [Lf/Wm;
/*   */     //   236: iload_3
/*   */     //   237: aaload
/*   */     //   238: getfield mh : [Lf/dT;
/*   */     //   241: iload_2
/*   */     //   242: aaload
/*   */     //   243: aload_0
/*   */     //   244: getfield cOm1 : Lf/AH0;
/*   */     //   247: bipush #9
/*   */     //   249: invokevirtual Ze0 : (I)I
/*   */     //   252: putfield Lo0 : I
/*   */     //   255: getfield oD0 : Lf/qC0;
/*   */     //   258: getfield hE : [Lf/Wm;
/*   */     //   261: iload_3
/*   */     //   262: aaload
/*   */     //   263: getfield mh : [Lf/dT;
/*   */     //   266: iload_2
/*   */     //   267: aaload
/*   */     //   268: aload_0
/*   */     //   269: getfield cOm1 : Lf/AH0;
/*   */     //   272: bipush #8
/*   */     //   274: invokevirtual Ze0 : (I)I
/*   */     //   277: putfield OE0 : I
/*   */     //   280: getfield oD0 : Lf/qC0;
/*   */     //   283: getfield hE : [Lf/Wm;
/*   */     //   286: iload_3
/*   */     //   287: aaload
/*   */     //   288: getfield mh : [Lf/dT;
/*   */     //   291: iload_2
/*   */     //   292: aaload
/*   */     //   293: aload_0
/*   */     //   294: getfield cOm1 : Lf/AH0;
/*   */     //   297: iconst_4
/*   */     //   298: invokevirtual Ze0 : (I)I
/*   */     //   301: putfield LQ : I
/*   */     //   304: getfield oD0 : Lf/qC0;
/*   */     //   307: getfield hE : [Lf/Wm;
/*   */     //   310: iload_3
/*   */     //   311: aaload
/*   */     //   312: getfield mh : [Lf/dT;
/*   */     //   315: iload_2
/*   */     //   316: aaload
/*   */     //   317: aload_0
/*   */     //   318: getfield cOm1 : Lf/AH0;
/*   */     //   321: iconst_1
/*   */     //   322: invokevirtual Ze0 : (I)I
/*   */     //   325: putfield hr0 : I
/*   */     //   328: getfield oD0 : Lf/qC0;
/*   */     //   331: getfield hE : [Lf/Wm;
/*   */     //   334: iload_3
/*   */     //   335: aaload
/*   */     //   336: getfield mh : [Lf/dT;
/*   */     //   339: iload_2
/*   */     //   340: aaload
/*   */     //   341: dup
/*   */     //   342: astore #4
/*   */     //   344: getfield hr0 : I
/*   */     //   347: ifeq -> 602
/*   */     //   350: aload_0
/*   */     //   351: dup
/*   */     //   352: dup
/*   */     //   353: dup2
/*   */     //   354: dup2
/*   */     //   355: aload #4
/*   */     //   357: aload_0
/*   */     //   358: getfield cOm1 : Lf/AH0;
/*   */     //   361: iconst_2
/*   */     //   362: invokevirtual Ze0 : (I)I
/*   */     //   365: putfield Ux : I
/*   */     //   368: getfield oD0 : Lf/qC0;
/*   */     //   371: getfield hE : [Lf/Wm;
/*   */     //   374: iload_3
/*   */     //   375: aaload
/*   */     //   376: getfield mh : [Lf/dT;
/*   */     //   379: iload_2
/*   */     //   380: aaload
/*   */     //   381: aload_0
/*   */     //   382: getfield cOm1 : Lf/AH0;
/*   */     //   385: iconst_1
/*   */     //   386: invokevirtual Ze0 : (I)I
/*   */     //   389: putfield Df : I
/*   */     //   392: getfield oD0 : Lf/qC0;
/*   */     //   395: getfield hE : [Lf/Wm;
/*   */     //   398: iload_3
/*   */     //   399: aaload
/*   */     //   400: getfield mh : [Lf/dT;
/*   */     //   403: iload_2
/*   */     //   404: aaload
/*   */     //   405: getfield hL0 : [I
/*   */     //   408: aload_0
/*   */     //   409: getfield cOm1 : Lf/AH0;
/*   */     //   412: iconst_5
/*   */     //   413: invokevirtual Ze0 : (I)I
/*   */     //   416: iconst_0
/*   */     //   417: swap
/*   */     //   418: iastore
/*   */     //   419: getfield oD0 : Lf/qC0;
/*   */     //   422: getfield hE : [Lf/Wm;
/*   */     //   425: iload_3
/*   */     //   426: aaload
/*   */     //   427: getfield mh : [Lf/dT;
/*   */     //   430: iload_2
/*   */     //   431: aaload
/*   */     //   432: getfield hL0 : [I
/*   */     //   435: aload_0
/*   */     //   436: getfield cOm1 : Lf/AH0;
/*   */     //   439: iconst_5
/*   */     //   440: invokevirtual Ze0 : (I)I
/*   */     //   443: iconst_1
/*   */     //   444: swap
/*   */     //   445: iastore
/*   */     //   446: getfield oD0 : Lf/qC0;
/*   */     //   449: getfield hE : [Lf/Wm;
/*   */     //   452: iload_3
/*   */     //   453: aaload
/*   */     //   454: getfield mh : [Lf/dT;
/*   */     //   457: iload_2
/*   */     //   458: aaload
/*   */     //   459: getfield qB0 : [I
/*   */     //   462: aload_0
/*   */     //   463: getfield cOm1 : Lf/AH0;
/*   */     //   466: iconst_3
/*   */     //   467: invokevirtual Ze0 : (I)I
/*   */     //   470: iconst_0
/*   */     //   471: swap
/*   */     //   472: iastore
/*   */     //   473: getfield oD0 : Lf/qC0;
/*   */     //   476: getfield hE : [Lf/Wm;
/*   */     //   479: iload_3
/*   */     //   480: aaload
/*   */     //   481: getfield mh : [Lf/dT;
/*   */     //   484: iload_2
/*   */     //   485: aaload
/*   */     //   486: getfield qB0 : [I
/*   */     //   489: aload_0
/*   */     //   490: getfield cOm1 : Lf/AH0;
/*   */     //   493: iconst_3
/*   */     //   494: invokevirtual Ze0 : (I)I
/*   */     //   497: iconst_1
/*   */     //   498: swap
/*   */     //   499: iastore
/*   */     //   500: getfield oD0 : Lf/qC0;
/*   */     //   503: getfield hE : [Lf/Wm;
/*   */     //   506: iload_3
/*   */     //   507: aaload
/*   */     //   508: getfield mh : [Lf/dT;
/*   */     //   511: iload_2
/*   */     //   512: aaload
/*   */     //   513: getfield qB0 : [I
/*   */     //   516: aload_0
/*   */     //   517: getfield cOm1 : Lf/AH0;
/*   */     //   520: iconst_3
/*   */     //   521: invokevirtual Ze0 : (I)I
/*   */     //   524: iconst_2
/*   */     //   525: swap
/*   */     //   526: iastore
/*   */     //   527: getfield oD0 : Lf/qC0;
/*   */     //   530: getfield hE : [Lf/Wm;
/*   */     //   533: iload_3
/*   */     //   534: aaload
/*   */     //   535: getfield mh : [Lf/dT;
/*   */     //   538: iload_2
/*   */     //   539: aaload
/*   */     //   540: dup
/*   */     //   541: astore #4
/*   */     //   543: getfield Ux : I
/*   */     //   546: dup
/*   */     //   547: istore #5
/*   */     //   549: ifne -> 555
/*   */     //   552: goto -> 1482
/*   */     //   555: iload #5
/*   */     //   557: iconst_2
/*   */     //   558: if_icmpne -> 579
/*   */     //   561: aload #4
/*   */     //   563: getfield Df : I
/*   */     //   566: ifne -> 579
/*   */     //   569: aload #4
/*   */     //   571: bipush #8
/*   */     //   573: putfield re0 : I
/*   */     //   576: goto -> 586
/*   */     //   579: aload #4
/*   */     //   581: bipush #7
/*   */     //   583: putfield re0 : I
/*   */     //   586: aload #4
/*   */     //   588: dup
/*   */     //   589: getfield re0 : I
/*   */     //   592: bipush #20
/*   */     //   594: swap
/*   */     //   595: isub
/*   */     //   596: putfield Cz : I
/*   */     //   599: goto -> 741
/*   */     //   602: aload_0
/*   */     //   603: dup
/*   */     //   604: dup
/*   */     //   605: dup2
/*   */     //   606: aload #4
/*   */     //   608: getfield hL0 : [I
/*   */     //   611: aload_0
/*   */     //   612: getfield cOm1 : Lf/AH0;
/*   */     //   615: iconst_5
/*   */     //   616: invokevirtual Ze0 : (I)I
/*   */     //   619: iconst_0
/*   */     //   620: swap
/*   */     //   621: iastore
/*   */     //   622: getfield oD0 : Lf/qC0;
/*   */     //   625: getfield hE : [Lf/Wm;
/*   */     //   628: iload_3
/*   */     //   629: aaload
/*   */     //   630: getfield mh : [Lf/dT;
/*   */     //   633: iload_2
/*   */     //   634: aaload
/*   */     //   635: getfield hL0 : [I
/*   */     //   638: aload_0
/*   */     //   639: getfield cOm1 : Lf/AH0;
/*   */     //   642: iconst_5
/*   */     //   643: invokevirtual Ze0 : (I)I
/*   */     //   646: iconst_1
/*   */     //   647: swap
/*   */     //   648: iastore
/*   */     //   649: getfield oD0 : Lf/qC0;
/*   */     //   652: getfield hE : [Lf/Wm;
/*   */     //   655: iload_3
/*   */     //   656: aaload
/*   */     //   657: getfield mh : [Lf/dT;
/*   */     //   660: iload_2
/*   */     //   661: aaload
/*   */     //   662: getfield hL0 : [I
/*   */     //   665: aload_0
/*   */     //   666: getfield cOm1 : Lf/AH0;
/*   */     //   669: iconst_5
/*   */     //   670: invokevirtual Ze0 : (I)I
/*   */     //   673: iconst_2
/*   */     //   674: swap
/*   */     //   675: iastore
/*   */     //   676: getfield oD0 : Lf/qC0;
/*   */     //   679: getfield hE : [Lf/Wm;
/*   */     //   682: iload_3
/*   */     //   683: aaload
/*   */     //   684: getfield mh : [Lf/dT;
/*   */     //   687: iload_2
/*   */     //   688: aaload
/*   */     //   689: aload_0
/*   */     //   690: getfield cOm1 : Lf/AH0;
/*   */     //   693: iconst_4
/*   */     //   694: invokevirtual Ze0 : (I)I
/*   */     //   697: putfield re0 : I
/*   */     //   700: getfield oD0 : Lf/qC0;
/*   */     //   703: getfield hE : [Lf/Wm;
/*   */     //   706: iload_3
/*   */     //   707: aaload
/*   */     //   708: getfield mh : [Lf/dT;
/*   */     //   711: iload_2
/*   */     //   712: aaload
/*   */     //   713: aload_0
/*   */     //   714: getfield cOm1 : Lf/AH0;
/*   */     //   717: iconst_3
/*   */     //   718: invokevirtual Ze0 : (I)I
/*   */     //   721: putfield Cz : I
/*   */     //   724: getfield oD0 : Lf/qC0;
/*   */     //   727: getfield hE : [Lf/Wm;
/*   */     //   730: iload_3
/*   */     //   731: aaload
/*   */     //   732: getfield mh : [Lf/dT;
/*   */     //   735: iload_2
/*   */     //   736: aaload
/*   */     //   737: iconst_0
/*   */     //   738: putfield Ux : I
/*   */     //   741: aload_0
/*   */     //   742: dup
/*   */     //   743: dup
/*   */     //   744: getfield oD0 : Lf/qC0;
/*   */     //   747: getfield hE : [Lf/Wm;
/*   */     //   750: iload_3
/*   */     //   751: aaload
/*   */     //   752: getfield mh : [Lf/dT;
/*   */     //   755: iload_2
/*   */     //   756: aaload
/*   */     //   757: aload_0
/*   */     //   758: getfield cOm1 : Lf/AH0;
/*   */     //   761: iconst_1
/*   */     //   762: invokevirtual Ze0 : (I)I
/*   */     //   765: putfield Ta : I
/*   */     //   768: getfield oD0 : Lf/qC0;
/*   */     //   771: getfield hE : [Lf/Wm;
/*   */     //   774: iload_3
/*   */     //   775: aaload
/*   */     //   776: getfield mh : [Lf/dT;
/*   */     //   779: iload_2
/*   */     //   780: aaload
/*   */     //   781: aload_0
/*   */     //   782: getfield cOm1 : Lf/AH0;
/*   */     //   785: iconst_1
/*   */     //   786: invokevirtual Ze0 : (I)I
/*   */     //   789: putfield B5 : I
/*   */     //   792: getfield oD0 : Lf/qC0;
/*   */     //   795: getfield hE : [Lf/Wm;
/*   */     //   798: iload_3
/*   */     //   799: aaload
/*   */     //   800: getfield mh : [Lf/dT;
/*   */     //   803: iload_2
/*   */     //   804: aaload
/*   */     //   805: aload_0
/*   */     //   806: getfield cOm1 : Lf/AH0;
/*   */     //   809: iconst_1
/*   */     //   810: invokevirtual Ze0 : (I)I
/*   */     //   813: putfield nD : I
/*   */     //   816: iinc #3, 1
/*   */     //   819: goto -> 193
/*   */     //   822: iinc #2, 1
/*   */     //   825: goto -> 186
/*   */     //   828: aload_0
/*   */     //   829: dup
/*   */     //   830: getfield oD0 : Lf/qC0;
/*   */     //   833: aload_0
/*   */     //   834: getfield cOm1 : Lf/AH0;
/*   */     //   837: bipush #8
/*   */     //   839: invokevirtual Ze0 : (I)I
/*   */     //   842: putfield X60 : I
/*   */     //   845: getfield Ow0 : I
/*   */     //   848: iconst_1
/*   */     //   849: if_icmpne -> 872
/*   */     //   852: aload_0
/*   */     //   853: getfield oD0 : Lf/qC0;
/*   */     //   856: aload_0
/*   */     //   857: getfield cOm1 : Lf/AH0;
/*   */     //   860: iconst_1
/*   */     //   861: invokevirtual Ze0 : (I)I
/*   */     //   864: pop
/*   */     //   865: invokevirtual getClass : ()Ljava/lang/Class;
/*   */     //   868: pop
/*   */     //   869: goto -> 889
/*   */     //   872: aload_0
/*   */     //   873: getfield oD0 : Lf/qC0;
/*   */     //   876: aload_0
/*   */     //   877: getfield cOm1 : Lf/AH0;
/*   */     //   880: iconst_2
/*   */     //   881: invokevirtual Ze0 : (I)I
/*   */     //   884: pop
/*   */     //   885: invokevirtual getClass : ()Ljava/lang/Class;
/*   */     //   888: pop
/*   */     //   889: iconst_0
/*   */     //   890: istore_2
/*   */     //   891: iload_2
/*   */     //   892: aload_0
/*   */     //   893: getfield Ow0 : I
/*   */     //   896: if_icmpge -> 1482
/*   */     //   899: aload_0
/*   */     //   900: dup
/*   */     //   901: dup2
/*   */     //   902: dup2
/*   */     //   903: getfield oD0 : Lf/qC0;
/*   */     //   906: getfield hE : [Lf/Wm;
/*   */     //   909: iload_2
/*   */     //   910: aaload
/*   */     //   911: getfield mh : [Lf/dT;
/*   */     //   914: iconst_0
/*   */     //   915: aaload
/*   */     //   916: aload_0
/*   */     //   917: getfield cOm1 : Lf/AH0;
/*   */     //   920: bipush #12
/*   */     //   922: invokevirtual Ze0 : (I)I
/*   */     //   925: putfield LpT5 : I
/*   */     //   928: getfield oD0 : Lf/qC0;
/*   */     //   931: getfield hE : [Lf/Wm;
/*   */     //   934: iload_2
/*   */     //   935: aaload
/*   */     //   936: getfield mh : [Lf/dT;
/*   */     //   939: iconst_0
/*   */     //   940: aaload
/*   */     //   941: aload_0
/*   */     //   942: getfield cOm1 : Lf/AH0;
/*   */     //   945: bipush #9
/*   */     //   947: invokevirtual Ze0 : (I)I
/*   */     //   950: putfield Lo0 : I
/*   */     //   953: getfield oD0 : Lf/qC0;
/*   */     //   956: getfield hE : [Lf/Wm;
/*   */     //   959: iload_2
/*   */     //   960: aaload
/*   */     //   961: getfield mh : [Lf/dT;
/*   */     //   964: iconst_0
/*   */     //   965: aaload
/*   */     //   966: aload_0
/*   */     //   967: getfield cOm1 : Lf/AH0;
/*   */     //   970: bipush #8
/*   */     //   972: invokevirtual Ze0 : (I)I
/*   */     //   975: putfield OE0 : I
/*   */     //   978: getfield oD0 : Lf/qC0;
/*   */     //   981: getfield hE : [Lf/Wm;
/*   */     //   984: iload_2
/*   */     //   985: aaload
/*   */     //   986: getfield mh : [Lf/dT;
/*   */     //   989: iconst_0
/*   */     //   990: aaload
/*   */     //   991: aload_0
/*   */     //   992: getfield cOm1 : Lf/AH0;
/*   */     //   995: bipush #9
/*   */     //   997: invokevirtual Ze0 : (I)I
/*   */     //   1000: putfield LQ : I
/*   */     //   1003: getfield oD0 : Lf/qC0;
/*   */     //   1006: getfield hE : [Lf/Wm;
/*   */     //   1009: iload_2
/*   */     //   1010: aaload
/*   */     //   1011: getfield mh : [Lf/dT;
/*   */     //   1014: iconst_0
/*   */     //   1015: aaload
/*   */     //   1016: aload_0
/*   */     //   1017: getfield cOm1 : Lf/AH0;
/*   */     //   1020: iconst_1
/*   */     //   1021: invokevirtual Ze0 : (I)I
/*   */     //   1024: putfield hr0 : I
/*   */     //   1027: getfield oD0 : Lf/qC0;
/*   */     //   1030: getfield hE : [Lf/Wm;
/*   */     //   1033: iload_2
/*   */     //   1034: aaload
/*   */     //   1035: getfield mh : [Lf/dT;
/*   */     //   1038: iconst_0
/*   */     //   1039: aaload
/*   */     //   1040: dup
/*   */     //   1041: astore_3
/*   */     //   1042: getfield hr0 : I
/*   */     //   1045: ifeq -> 1288
/*   */     //   1048: aload_0
/*   */     //   1049: dup
/*   */     //   1050: dup
/*   */     //   1051: dup2
/*   */     //   1052: dup2
/*   */     //   1053: aload_3
/*   */     //   1054: aload_0
/*   */     //   1055: getfield cOm1 : Lf/AH0;
/*   */     //   1058: iconst_2
/*   */     //   1059: invokevirtual Ze0 : (I)I
/*   */     //   1062: putfield Ux : I
/*   */     //   1065: getfield oD0 : Lf/qC0;
/*   */     //   1068: getfield hE : [Lf/Wm;
/*   */     //   1071: iload_2
/*   */     //   1072: aaload
/*   */     //   1073: getfield mh : [Lf/dT;
/*   */     //   1076: iconst_0
/*   */     //   1077: aaload
/*   */     //   1078: aload_0
/*   */     //   1079: getfield cOm1 : Lf/AH0;
/*   */     //   1082: iconst_1
/*   */     //   1083: invokevirtual Ze0 : (I)I
/*   */     //   1086: putfield Df : I
/*   */     //   1089: getfield oD0 : Lf/qC0;
/*   */     //   1092: getfield hE : [Lf/Wm;
/*   */     //   1095: iload_2
/*   */     //   1096: aaload
/*   */     //   1097: getfield mh : [Lf/dT;
/*   */     //   1100: iconst_0
/*   */     //   1101: aaload
/*   */     //   1102: getfield hL0 : [I
/*   */     //   1105: aload_0
/*   */     //   1106: getfield cOm1 : Lf/AH0;
/*   */     //   1109: iconst_5
/*   */     //   1110: invokevirtual Ze0 : (I)I
/*   */     //   1113: iconst_0
/*   */     //   1114: swap
/*   */     //   1115: iastore
/*   */     //   1116: getfield oD0 : Lf/qC0;
/*   */     //   1119: getfield hE : [Lf/Wm;
/*   */     //   1122: iload_2
/*   */     //   1123: aaload
/*   */     //   1124: getfield mh : [Lf/dT;
/*   */     //   1127: iconst_0
/*   */     //   1128: aaload
/*   */     //   1129: getfield hL0 : [I
/*   */     //   1132: aload_0
/*   */     //   1133: getfield cOm1 : Lf/AH0;
/*   */     //   1136: iconst_5
/*   */     //   1137: invokevirtual Ze0 : (I)I
/*   */     //   1140: iconst_1
/*   */     //   1141: swap
/*   */     //   1142: iastore
/*   */     //   1143: getfield oD0 : Lf/qC0;
/*   */     //   1146: getfield hE : [Lf/Wm;
/*   */     //   1149: iload_2
/*   */     //   1150: aaload
/*   */     //   1151: getfield mh : [Lf/dT;
/*   */     //   1154: iconst_0
/*   */     //   1155: aaload
/*   */     //   1156: getfield qB0 : [I
/*   */     //   1159: aload_0
/*   */     //   1160: getfield cOm1 : Lf/AH0;
/*   */     //   1163: iconst_3
/*   */     //   1164: invokevirtual Ze0 : (I)I
/*   */     //   1167: iconst_0
/*   */     //   1168: swap
/*   */     //   1169: iastore
/*   */     //   1170: getfield oD0 : Lf/qC0;
/*   */     //   1173: getfield hE : [Lf/Wm;
/*   */     //   1176: iload_2
/*   */     //   1177: aaload
/*   */     //   1178: getfield mh : [Lf/dT;
/*   */     //   1181: iconst_0
/*   */     //   1182: aaload
/*   */     //   1183: getfield qB0 : [I
/*   */     //   1186: aload_0
/*   */     //   1187: getfield cOm1 : Lf/AH0;
/*   */     //   1190: iconst_3
/*   */     //   1191: invokevirtual Ze0 : (I)I
/*   */     //   1194: iconst_1
/*   */     //   1195: swap
/*   */     //   1196: iastore
/*   */     //   1197: getfield oD0 : Lf/qC0;
/*   */     //   1200: getfield hE : [Lf/Wm;
/*   */     //   1203: iload_2
/*   */     //   1204: aaload
/*   */     //   1205: getfield mh : [Lf/dT;
/*   */     //   1208: iconst_0
/*   */     //   1209: aaload
/*   */     //   1210: getfield qB0 : [I
/*   */     //   1213: aload_0
/*   */     //   1214: getfield cOm1 : Lf/AH0;
/*   */     //   1217: iconst_3
/*   */     //   1218: invokevirtual Ze0 : (I)I
/*   */     //   1221: iconst_2
/*   */     //   1222: swap
/*   */     //   1223: iastore
/*   */     //   1224: getfield oD0 : Lf/qC0;
/*   */     //   1227: getfield hE : [Lf/Wm;
/*   */     //   1230: iload_2
/*   */     //   1231: aaload
/*   */     //   1232: getfield mh : [Lf/dT;
/*   */     //   1235: iconst_0
/*   */     //   1236: aaload
/*   */     //   1237: dup
/*   */     //   1238: astore_3
/*   */     //   1239: getfield Ux : I
/*   */     //   1242: dup
/*   */     //   1243: istore #4
/*   */     //   1245: ifne -> 1251
/*   */     //   1248: goto -> 1482
/*   */     //   1251: iload #4
/*   */     //   1253: iconst_2
/*   */     //   1254: if_icmpne -> 1273
/*   */     //   1257: aload_3
/*   */     //   1258: getfield Df : I
/*   */     //   1261: ifne -> 1273
/*   */     //   1264: aload_3
/*   */     //   1265: bipush #8
/*   */     //   1267: putfield re0 : I
/*   */     //   1270: goto -> 1426
/*   */     //   1273: aload_3
/*   */     //   1274: dup
/*   */     //   1275: bipush #7
/*   */     //   1277: putfield re0 : I
/*   */     //   1280: bipush #13
/*   */     //   1282: putfield Cz : I
/*   */     //   1285: goto -> 1426
/*   */     //   1288: aload_0
/*   */     //   1289: dup
/*   */     //   1290: dup
/*   */     //   1291: dup2
/*   */     //   1292: aload_3
/*   */     //   1293: getfield hL0 : [I
/*   */     //   1296: aload_0
/*   */     //   1297: getfield cOm1 : Lf/AH0;
/*   */     //   1300: iconst_5
/*   */     //   1301: invokevirtual Ze0 : (I)I
/*   */     //   1304: iconst_0
/*   */     //   1305: swap
/*   */     //   1306: iastore
/*   */     //   1307: getfield oD0 : Lf/qC0;
/*   */     //   1310: getfield hE : [Lf/Wm;
/*   */     //   1313: iload_2
/*   */     //   1314: aaload
/*   */     //   1315: getfield mh : [Lf/dT;
/*   */     //   1318: iconst_0
/*   */     //   1319: aaload
/*   */     //   1320: getfield hL0 : [I
/*   */     //   1323: aload_0
/*   */     //   1324: getfield cOm1 : Lf/AH0;
/*   */     //   1327: iconst_5
/*   */     //   1328: invokevirtual Ze0 : (I)I
/*   */     //   1331: iconst_1
/*   */     //   1332: swap
/*   */     //   1333: iastore
/*   */     //   1334: getfield oD0 : Lf/qC0;
/*   */     //   1337: getfield hE : [Lf/Wm;
/*   */     //   1340: iload_2
/*   */     //   1341: aaload
/*   */     //   1342: getfield mh : [Lf/dT;
/*   */     //   1345: iconst_0
/*   */     //   1346: aaload
/*   */     //   1347: getfield hL0 : [I
/*   */     //   1350: aload_0
/*   */     //   1351: getfield cOm1 : Lf/AH0;
/*   */     //   1354: iconst_5
/*   */     //   1355: invokevirtual Ze0 : (I)I
/*   */     //   1358: iconst_2
/*   */     //   1359: swap
/*   */     //   1360: iastore
/*   */     //   1361: getfield oD0 : Lf/qC0;
/*   */     //   1364: getfield hE : [Lf/Wm;
/*   */     //   1367: iload_2
/*   */     //   1368: aaload
/*   */     //   1369: getfield mh : [Lf/dT;
/*   */     //   1372: iconst_0
/*   */     //   1373: aaload
/*   */     //   1374: aload_0
/*   */     //   1375: getfield cOm1 : Lf/AH0;
/*   */     //   1378: iconst_4
/*   */     //   1379: invokevirtual Ze0 : (I)I
/*   */     //   1382: putfield re0 : I
/*   */     //   1385: getfield oD0 : Lf/qC0;
/*   */     //   1388: getfield hE : [Lf/Wm;
/*   */     //   1391: iload_2
/*   */     //   1392: aaload
/*   */     //   1393: getfield mh : [Lf/dT;
/*   */     //   1396: iconst_0
/*   */     //   1397: aaload
/*   */     //   1398: aload_0
/*   */     //   1399: getfield cOm1 : Lf/AH0;
/*   */     //   1402: iconst_3
/*   */     //   1403: invokevirtual Ze0 : (I)I
/*   */     //   1406: putfield Cz : I
/*   */     //   1409: getfield oD0 : Lf/qC0;
/*   */     //   1412: getfield hE : [Lf/Wm;
/*   */     //   1415: iload_2
/*   */     //   1416: aaload
/*   */     //   1417: getfield mh : [Lf/dT;
/*   */     //   1420: iconst_0
/*   */     //   1421: aaload
/*   */     //   1422: iconst_0
/*   */     //   1423: putfield Ux : I
/*   */     //   1426: aload_0
/*   */     //   1427: dup
/*   */     //   1428: getfield oD0 : Lf/qC0;
/*   */     //   1431: getfield hE : [Lf/Wm;
/*   */     //   1434: iload_2
/*   */     //   1435: aaload
/*   */     //   1436: getfield mh : [Lf/dT;
/*   */     //   1439: iconst_0
/*   */     //   1440: aaload
/*   */     //   1441: aload_0
/*   */     //   1442: getfield cOm1 : Lf/AH0;
/*   */     //   1445: iconst_1
/*   */     //   1446: invokevirtual Ze0 : (I)I
/*   */     //   1449: putfield B5 : I
/*   */     //   1452: getfield oD0 : Lf/qC0;
/*   */     //   1455: getfield hE : [Lf/Wm;
/*   */     //   1458: iload_2
/*   */     //   1459: aaload
/*   */     //   1460: getfield mh : [Lf/dT;
/*   */     //   1463: iconst_0
/*   */     //   1464: aaload
/*   */     //   1465: aload_0
/*   */     //   1466: getfield cOm1 : Lf/AH0;
/*   */     //   1469: iconst_1
/*   */     //   1470: invokevirtual Ze0 : (I)I
/*   */     //   1473: putfield nD : I
/*   */     //   1476: iinc #2, 1
/*   */     //   1479: goto -> 891
/*   */     //   1482: iconst_0
/*   */     //   1483: istore_2
/*   */     //   1484: iload_2
/*   */     //   1485: iload_1
/*   */     //   1486: if_icmpge -> 1672
/*   */     //   1489: aload_0
/*   */     //   1490: getfield Bg : Lf/CC;
/*   */     //   1493: dup
/*   */     //   1494: dup
/*   */     //   1495: astore_3
/*   */     //   1496: aload_0
/*   */     //   1497: getfield cOm1 : Lf/AH0;
/*   */     //   1500: bipush #8
/*   */     //   1502: invokevirtual Ze0 : (I)I
/*   */     //   1505: istore #4
/*   */     //   1507: getfield B5 : I
/*   */     //   1510: istore #5
/*   */     //   1512: getfield UZ : [I
/*   */     //   1515: dup
/*   */     //   1516: astore #6
/*   */     //   1518: iload #4
/*   */     //   1520: aload #6
/*   */     //   1522: iload #4
/*   */     //   1524: aload #6
/*   */     //   1526: iload #4
/*   */     //   1528: aload #6
/*   */     //   1530: iload #4
/*   */     //   1532: aload #6
/*   */     //   1534: iload #4
/*   */     //   1536: aload #6
/*   */     //   1538: iload #4
/*   */     //   1540: aload #6
/*   */     //   1542: iload #5
/*   */     //   1544: iload #4
/*   */     //   1546: iinc #5, 1
/*   */     //   1549: sipush #128
/*   */     //   1552: iand
/*   */     //   1553: iastore
/*   */     //   1554: iload #5
/*   */     //   1556: iconst_1
/*   */     //   1557: iadd
/*   */     //   1558: istore #7
/*   */     //   1560: bipush #64
/*   */     //   1562: iand
/*   */     //   1563: iload #5
/*   */     //   1565: swap
/*   */     //   1566: iastore
/*   */     //   1567: iload #7
/*   */     //   1569: iconst_1
/*   */     //   1570: iadd
/*   */     //   1571: istore #5
/*   */     //   1573: bipush #32
/*   */     //   1575: iand
/*   */     //   1576: iload #7
/*   */     //   1578: swap
/*   */     //   1579: iastore
/*   */     //   1580: iload #5
/*   */     //   1582: iconst_1
/*   */     //   1583: iadd
/*   */     //   1584: istore #7
/*   */     //   1586: bipush #16
/*   */     //   1588: iand
/*   */     //   1589: iload #5
/*   */     //   1591: swap
/*   */     //   1592: iastore
/*   */     //   1593: iload #7
/*   */     //   1595: iconst_1
/*   */     //   1596: iadd
/*   */     //   1597: istore #5
/*   */     //   1599: bipush #8
/*   */     //   1601: iand
/*   */     //   1602: iload #7
/*   */     //   1604: swap
/*   */     //   1605: iastore
/*   */     //   1606: iload #5
/*   */     //   1608: iconst_1
/*   */     //   1609: iadd
/*   */     //   1610: istore #7
/*   */     //   1612: iconst_4
/*   */     //   1613: iand
/*   */     //   1614: iload #5
/*   */     //   1616: swap
/*   */     //   1617: iastore
/*   */     //   1618: iload #7
/*   */     //   1620: iconst_1
/*   */     //   1621: iadd
/*   */     //   1622: istore #5
/*   */     //   1624: iconst_2
/*   */     //   1625: iand
/*   */     //   1626: iload #7
/*   */     //   1628: swap
/*   */     //   1629: iastore
/*   */     //   1630: iload #5
/*   */     //   1632: iconst_1
/*   */     //   1633: iadd
/*   */     //   1634: dup
/*   */     //   1635: istore #7
/*   */     //   1637: aload #6
/*   */     //   1639: iload #5
/*   */     //   1641: iload #4
/*   */     //   1643: iconst_1
/*   */     //   1644: iand
/*   */     //   1645: iastore
/*   */     //   1646: ldc_w 32768
/*   */     //   1649: if_icmpne -> 1660
/*   */     //   1652: aload_3
/*   */     //   1653: iconst_0
/*   */     //   1654: putfield B5 : I
/*   */     //   1657: goto -> 1666
/*   */     //   1660: aload_3
/*   */     //   1661: iload #7
/*   */     //   1663: putfield B5 : I
/*   */     //   1666: iinc #2, 1
/*   */     //   1669: goto -> 1484
/*   */     //   1672: aload_0
/*   */     //   1673: getfield Bg : Lf/CC;
/*   */     //   1676: dup
/*   */     //   1677: astore_2
/*   */     //   1678: getfield br : I
/*   */     //   1681: dup
/*   */     //   1682: iconst_3
/*   */     //   1683: iushr
/*   */     //   1684: istore_3
/*   */     //   1685: bipush #7
/*   */     //   1687: iand
/*   */     //   1688: dup
/*   */     //   1689: istore #4
/*   */     //   1691: ifeq -> 1707
/*   */     //   1694: aload_2
/*   */     //   1695: bipush #8
/*   */     //   1697: iload #4
/*   */     //   1699: isub
/*   */     //   1700: invokevirtual F30 : (I)I
/*   */     //   1703: pop
/*   */     //   1704: iinc #3, 1
/*   */     //   1707: aload_0
/*   */     //   1708: getfield lPt7 : I
/*   */     //   1711: dup
/*   */     //   1712: istore_2
/*   */     //   1713: iload_3
/*   */     //   1714: isub
/*   */     //   1715: aload_0
/*   */     //   1716: getfield oD0 : Lf/qC0;
/*   */     //   1719: getfield X60 : I
/*   */     //   1722: isub
/*   */     //   1723: dup
/*   */     //   1724: istore #4
/*   */     //   1726: aload_0
/*   */     //   1727: iload_2
/*   */     //   1728: iload_1
/*   */     //   1729: iadd
/*   */     //   1730: dup
/*   */     //   1731: istore_1
/*   */     //   1732: putfield lPt7 : I
/*   */     //   1735: ifge -> 1741
/*   */     //   1738: goto -> 3884
/*   */     //   1741: iload_3
/*   */     //   1742: sipush #4096
/*   */     //   1745: if_icmple -> 1800
/*   */     //   1748: aload_0
/*   */     //   1749: dup
/*   */     //   1750: iload_1
/*   */     //   1751: sipush #4096
/*   */     //   1754: isub
/*   */     //   1755: putfield lPt7 : I
/*   */     //   1758: getfield Bg : Lf/CC;
/*   */     //   1761: dup
/*   */     //   1762: dup2
/*   */     //   1763: astore_1
/*   */     //   1764: getfield br : I
/*   */     //   1767: ldc_w 32768
/*   */     //   1770: isub
/*   */     //   1771: putfield br : I
/*   */     //   1774: getfield vP : I
/*   */     //   1777: ldc_w 32768
/*   */     //   1780: isub
/*   */     //   1781: dup
/*   */     //   1782: istore_2
/*   */     //   1783: aload_1
/*   */     //   1784: iload_2
/*   */     //   1785: putfield vP : I
/*   */     //   1788: ifge -> 1800
/*   */     //   1791: aload_1
/*   */     //   1792: iload_2
/*   */     //   1793: ldc_w 32768
/*   */     //   1796: iadd
/*   */     //   1797: putfield vP : I
/*   */     //   1800: iload #4
/*   */     //   1802: ifle -> 1821
/*   */     //   1805: aload_0
/*   */     //   1806: getfield Bg : Lf/CC;
/*   */     //   1809: bipush #8
/*   */     //   1811: invokevirtual F30 : (I)I
/*   */     //   1814: pop
/*   */     //   1815: iinc #4, -1
/*   */     //   1818: goto -> 1800
/*   */     //   1821: iconst_0
/*   */     //   1822: istore_1
/*   */     //   1823: iload_1
/*   */     //   1824: aload_0
/*   */     //   1825: getfield S70 : I
/*   */     //   1828: if_icmpge -> 3884
/*   */     //   1831: iconst_0
/*   */     //   1832: istore_2
/*   */     //   1833: iload_2
/*   */     //   1834: aload_0
/*   */     //   1835: getfield Ow0 : I
/*   */     //   1838: if_icmpge -> 3427
/*   */     //   1841: aload_0
/*   */     //   1842: dup
/*   */     //   1843: dup
/*   */     //   1844: getfield Bg : Lf/CC;
/*   */     //   1847: getfield br : I
/*   */     //   1850: putfield uS : I
/*   */     //   1853: getfield kO : Lf/Ym0;
/*   */     //   1856: dup
/*   */     //   1857: astore_3
/*   */     //   1858: getfield OB : I
/*   */     //   1861: iconst_1
/*   */     //   1862: if_icmpne -> 1874
/*   */     //   1865: aload_0
/*   */     //   1866: iload_2
/*   */     //   1867: iload_1
/*   */     //   1868: invokevirtual nL : (II)V
/*   */     //   1871: goto -> 2717
/*   */     //   1874: aload_0
/*   */     //   1875: iconst_0
/*   */     //   1876: istore #4
/*   */     //   1878: getfield oD0 : Lf/qC0;
/*   */     //   1881: getfield hE : [Lf/Wm;
/*   */     //   1884: iload_2
/*   */     //   1885: aaload
/*   */     //   1886: getfield mh : [Lf/dT;
/*   */     //   1889: iload_1
/*   */     //   1890: aaload
/*   */     //   1891: dup
/*   */     //   1892: dup
/*   */     //   1893: astore #5
/*   */     //   1895: aload_3
/*   */     //   1896: getfield Mh0 : I
/*   */     //   1899: istore_3
/*   */     //   1900: iconst_0
/*   */     //   1901: istore #6
/*   */     //   1903: getfield LQ : I
/*   */     //   1906: istore #7
/*   */     //   1908: getfield Ux : I
/*   */     //   1911: iconst_2
/*   */     //   1912: if_icmpne -> 1944
/*   */     //   1915: aload #5
/*   */     //   1917: getfield Df : I
/*   */     //   1920: dup
/*   */     //   1921: istore #8
/*   */     //   1923: ifne -> 1932
/*   */     //   1926: iconst_1
/*   */     //   1927: istore #8
/*   */     //   1929: goto -> 1947
/*   */     //   1932: iload #8
/*   */     //   1934: iconst_1
/*   */     //   1935: if_icmpne -> 1944
/*   */     //   1938: iconst_2
/*   */     //   1939: istore #8
/*   */     //   1941: goto -> 1947
/*   */     //   1944: iconst_0
/*   */     //   1945: istore #8
/*   */     //   1947: iload_3
/*   */     //   1948: iconst_1
/*   */     //   1949: if_icmpeq -> 1957
/*   */     //   1952: iload_3
/*   */     //   1953: iconst_3
/*   */     //   1954: if_icmpne -> 1962
/*   */     //   1957: iload_2
/*   */     //   1958: iconst_1
/*   */     //   1959: if_icmpeq -> 2141
/*   */     //   1962: iload #7
/*   */     //   1964: sipush #400
/*   */     //   1967: if_icmpge -> 2028
/*   */     //   1970: aload #5
/*   */     //   1972: aload_0
/*   */     //   1973: getfield H2 : [I
/*   */     //   1976: dup
/*   */     //   1977: astore #6
/*   */     //   1979: iload #7
/*   */     //   1981: aload #6
/*   */     //   1983: iload #7
/*   */     //   1985: aload #6
/*   */     //   1987: iload #7
/*   */     //   1989: iconst_4
/*   */     //   1990: iushr
/*   */     //   1991: dup
/*   */     //   1992: aload #6
/*   */     //   1994: swap
/*   */     //   1995: iconst_5
/*   */     //   1996: idiv
/*   */     //   1997: iconst_0
/*   */     //   1998: swap
/*   */     //   1999: iastore
/*   */     //   2000: iconst_5
/*   */     //   2001: irem
/*   */     //   2002: iconst_1
/*   */     //   2003: swap
/*   */     //   2004: iastore
/*   */     //   2005: bipush #15
/*   */     //   2007: iand
/*   */     //   2008: iconst_2
/*   */     //   2009: iushr
/*   */     //   2010: iconst_2
/*   */     //   2011: swap
/*   */     //   2012: iastore
/*   */     //   2013: iconst_3
/*   */     //   2014: iand
/*   */     //   2015: iconst_3
/*   */     //   2016: swap
/*   */     //   2017: iastore
/*   */     //   2018: iconst_0
/*   */     //   2019: putfield Ta : I
/*   */     //   2022: iconst_0
/*   */     //   2023: istore #6
/*   */     //   2025: goto -> 2141
/*   */     //   2028: iload #7
/*   */     //   2030: sipush #500
/*   */     //   2033: if_icmpge -> 2090
/*   */     //   2036: aload #5
/*   */     //   2038: aload_0
/*   */     //   2039: getfield H2 : [I
/*   */     //   2042: dup
/*   */     //   2043: dup
/*   */     //   2044: astore #6
/*   */     //   2046: iload #7
/*   */     //   2048: sipush #400
/*   */     //   2051: isub
/*   */     //   2052: dup
/*   */     //   2053: aload #6
/*   */     //   2055: swap
/*   */     //   2056: iconst_2
/*   */     //   2057: iushr
/*   */     //   2058: dup
/*   */     //   2059: aload #6
/*   */     //   2061: swap
/*   */     //   2062: iconst_5
/*   */     //   2063: idiv
/*   */     //   2064: iconst_0
/*   */     //   2065: swap
/*   */     //   2066: iastore
/*   */     //   2067: iconst_5
/*   */     //   2068: irem
/*   */     //   2069: iconst_1
/*   */     //   2070: swap
/*   */     //   2071: iastore
/*   */     //   2072: iconst_3
/*   */     //   2073: iand
/*   */     //   2074: iconst_2
/*   */     //   2075: swap
/*   */     //   2076: iastore
/*   */     //   2077: iconst_3
/*   */     //   2078: iconst_0
/*   */     //   2079: iastore
/*   */     //   2080: iconst_0
/*   */     //   2081: putfield Ta : I
/*   */     //   2084: iconst_1
/*   */     //   2085: istore #6
/*   */     //   2087: goto -> 2141
/*   */     //   2090: iload #7
/*   */     //   2092: sipush #512
/*   */     //   2095: if_icmpge -> 2141
/*   */     //   2098: aload #5
/*   */     //   2100: aload_0
/*   */     //   2101: getfield H2 : [I
/*   */     //   2104: dup
/*   */     //   2105: dup2
/*   */     //   2106: astore #6
/*   */     //   2108: iload #7
/*   */     //   2110: sipush #500
/*   */     //   2113: isub
/*   */     //   2114: dup
/*   */     //   2115: aload #6
/*   */     //   2117: swap
/*   */     //   2118: iconst_3
/*   */     //   2119: idiv
/*   */     //   2120: iconst_0
/*   */     //   2121: swap
/*   */     //   2122: iastore
/*   */     //   2123: iconst_3
/*   */     //   2124: irem
/*   */     //   2125: iconst_1
/*   */     //   2126: swap
/*   */     //   2127: iastore
/*   */     //   2128: iconst_2
/*   */     //   2129: iconst_0
/*   */     //   2130: iastore
/*   */     //   2131: iconst_3
/*   */     //   2132: iconst_0
/*   */     //   2133: iastore
/*   */     //   2134: iconst_1
/*   */     //   2135: putfield Ta : I
/*   */     //   2138: iconst_2
/*   */     //   2139: istore #6
/*   */     //   2141: iload_3
/*   */     //   2142: iconst_1
/*   */     //   2143: if_icmpeq -> 2151
/*   */     //   2146: iload_3
/*   */     //   2147: iconst_3
/*   */     //   2148: if_icmpne -> 2333
/*   */     //   2151: iload_2
/*   */     //   2152: iconst_1
/*   */     //   2153: if_icmpne -> 2333
/*   */     //   2156: iload #7
/*   */     //   2158: iconst_1
/*   */     //   2159: iushr
/*   */     //   2160: dup
/*   */     //   2161: istore_3
/*   */     //   2162: sipush #180
/*   */     //   2165: if_icmpge -> 2220
/*   */     //   2168: aload #5
/*   */     //   2170: aload_0
/*   */     //   2171: getfield H2 : [I
/*   */     //   2174: dup
/*   */     //   2175: dup
/*   */     //   2176: astore #6
/*   */     //   2178: iload_3
/*   */     //   2179: aload #6
/*   */     //   2181: iload_3
/*   */     //   2182: bipush #36
/*   */     //   2184: idiv
/*   */     //   2185: iconst_0
/*   */     //   2186: swap
/*   */     //   2187: iastore
/*   */     //   2188: bipush #36
/*   */     //   2190: irem
/*   */     //   2191: dup
/*   */     //   2192: aload #6
/*   */     //   2194: swap
/*   */     //   2195: bipush #6
/*   */     //   2197: idiv
/*   */     //   2198: iconst_1
/*   */     //   2199: swap
/*   */     //   2200: iastore
/*   */     //   2201: bipush #6
/*   */     //   2203: irem
/*   */     //   2204: iconst_2
/*   */     //   2205: swap
/*   */     //   2206: iastore
/*   */     //   2207: iconst_3
/*   */     //   2208: iconst_0
/*   */     //   2209: iastore
/*   */     //   2210: iconst_0
/*   */     //   2211: putfield Ta : I
/*   */     //   2214: iconst_3
/*   */     //   2215: istore #6
/*   */     //   2217: goto -> 2333
/*   */     //   2220: iload_3
/*   */     //   2221: sipush #244
/*   */     //   2224: if_icmpge -> 2284
/*   */     //   2227: aload #5
/*   */     //   2229: aload_0
/*   */     //   2230: getfield H2 : [I
/*   */     //   2233: dup
/*   */     //   2234: dup
/*   */     //   2235: astore #6
/*   */     //   2237: iload_3
/*   */     //   2238: sipush #180
/*   */     //   2241: isub
/*   */     //   2242: dup
/*   */     //   2243: istore_3
/*   */     //   2244: aload #6
/*   */     //   2246: iload_3
/*   */     //   2247: aload #6
/*   */     //   2249: iload_3
/*   */     //   2250: bipush #63
/*   */     //   2252: iand
/*   */     //   2253: iconst_4
/*   */     //   2254: iushr
/*   */     //   2255: iconst_0
/*   */     //   2256: swap
/*   */     //   2257: iastore
/*   */     //   2258: bipush #15
/*   */     //   2260: iand
/*   */     //   2261: iconst_2
/*   */     //   2262: iushr
/*   */     //   2263: iconst_1
/*   */     //   2264: swap
/*   */     //   2265: iastore
/*   */     //   2266: iconst_3
/*   */     //   2267: iand
/*   */     //   2268: iconst_2
/*   */     //   2269: swap
/*   */     //   2270: iastore
/*   */     //   2271: iconst_3
/*   */     //   2272: iconst_0
/*   */     //   2273: iastore
/*   */     //   2274: iconst_0
/*   */     //   2275: putfield Ta : I
/*   */     //   2278: iconst_4
/*   */     //   2279: istore #6
/*   */     //   2281: goto -> 2333
/*   */     //   2284: iload_3
/*   */     //   2285: sipush #255
/*   */     //   2288: if_icmpge -> 2333
/*   */     //   2291: aload #5
/*   */     //   2293: aload_0
/*   */     //   2294: getfield H2 : [I
/*   */     //   2297: dup
/*   */     //   2298: dup2
/*   */     //   2299: astore #6
/*   */     //   2301: iload_3
/*   */     //   2302: sipush #244
/*   */     //   2305: isub
/*   */     //   2306: dup
/*   */     //   2307: aload #6
/*   */     //   2309: swap
/*   */     //   2310: iconst_3
/*   */     //   2311: idiv
/*   */     //   2312: iconst_0
/*   */     //   2313: swap
/*   */     //   2314: iastore
/*   */     //   2315: iconst_3
/*   */     //   2316: irem
/*   */     //   2317: iconst_1
/*   */     //   2318: swap
/*   */     //   2319: iastore
/*   */     //   2320: iconst_2
/*   */     //   2321: iconst_0
/*   */     //   2322: iastore
/*   */     //   2323: iconst_3
/*   */     //   2324: iconst_0
/*   */     //   2325: iastore
/*   */     //   2326: iconst_0
/*   */     //   2327: putfield Ta : I
/*   */     //   2330: iconst_5
/*   */     //   2331: istore #6
/*   */     //   2333: iconst_0
/*   */     //   2334: istore_3
/*   */     //   2335: iload_3
/*   */     //   2336: bipush #45
/*   */     //   2338: if_icmpge -> 2354
/*   */     //   2341: aload_0
/*   */     //   2342: getfield final : [I
/*   */     //   2345: iload_3
/*   */     //   2346: iconst_0
/*   */     //   2347: iastore
/*   */     //   2348: iinc #3, 1
/*   */     //   2351: goto -> 2335
/*   */     //   2354: iconst_0
/*   */     //   2355: istore_3
/*   */     //   2356: iconst_0
/*   */     //   2357: istore #7
/*   */     //   2359: iload #7
/*   */     //   2361: iconst_4
/*   */     //   2362: if_icmpge -> 2442
/*   */     //   2365: iconst_0
/*   */     //   2366: istore #9
/*   */     //   2368: iload #9
/*   */     //   2370: getstatic f/oH.wA : [[[I
/*   */     //   2373: iload #6
/*   */     //   2375: aaload
/*   */     //   2376: iload #8
/*   */     //   2378: aaload
/*   */     //   2379: iload #7
/*   */     //   2381: iaload
/*   */     //   2382: if_icmpge -> 2436
/*   */     //   2385: aload_0
/*   */     //   2386: dup
/*   */     //   2387: getfield final : [I
/*   */     //   2390: astore #10
/*   */     //   2392: getfield H2 : [I
/*   */     //   2395: iload #7
/*   */     //   2397: iaload
/*   */     //   2398: dup
/*   */     //   2399: istore #11
/*   */     //   2401: ifne -> 2410
/*   */     //   2404: iconst_0
/*   */     //   2405: istore #11
/*   */     //   2407: goto -> 2421
/*   */     //   2410: aload_0
/*   */     //   2411: getfield Bg : Lf/CC;
/*   */     //   2414: iload #11
/*   */     //   2416: invokevirtual F30 : (I)I
/*   */     //   2419: istore #11
/*   */     //   2421: aload #10
/*   */     //   2423: iload_3
/*   */     //   2424: iload #11
/*   */     //   2426: iastore
/*   */     //   2427: iinc #3, 1
/*   */     //   2430: iinc #9, 1
/*   */     //   2433: goto -> 2368
/*   */     //   2436: iinc #7, 1
/*   */     //   2439: goto -> 2359
/*   */     //   2442: aload #5
/*   */     //   2444: getfield hr0 : I
/*   */     //   2447: ifeq -> 2664
/*   */     //   2450: aload #5
/*   */     //   2452: getfield Ux : I
/*   */     //   2455: iconst_2
/*   */     //   2456: if_icmpne -> 2664
/*   */     //   2459: aload #5
/*   */     //   2461: getfield Df : I
/*   */     //   2464: ifeq -> 2583
/*   */     //   2467: iconst_0
/*   */     //   2468: istore_3
/*   */     //   2469: iload_3
/*   */     //   2470: bipush #8
/*   */     //   2472: if_icmpge -> 2502
/*   */     //   2475: aload_0
/*   */     //   2476: getfield fM0 : [Lf/C60;
/*   */     //   2479: iload_2
/*   */     //   2480: aaload
/*   */     //   2481: getfield st0 : [I
/*   */     //   2484: iload_3
/*   */     //   2485: aload_0
/*   */     //   2486: getfield final : [I
/*   */     //   2489: iload #4
/*   */     //   2491: iaload
/*   */     //   2492: iastore
/*   */     //   2493: iinc #4, 1
/*   */     //   2496: iinc #3, 1
/*   */     //   2499: goto -> 2469
/*   */     //   2502: iconst_3
/*   */     //   2503: istore_3
/*   */     //   2504: iload_3
/*   */     //   2505: bipush #12
/*   */     //   2507: if_icmpge -> 2555
/*   */     //   2510: iconst_0
/*   */     //   2511: istore #5
/*   */     //   2513: iload #5
/*   */     //   2515: iconst_3
/*   */     //   2516: if_icmpge -> 2549
/*   */     //   2519: aload_0
/*   */     //   2520: getfield fM0 : [Lf/C60;
/*   */     //   2523: iload_2
/*   */     //   2524: aaload
/*   */     //   2525: getfield bW : [[I
/*   */     //   2528: iload #5
/*   */     //   2530: aaload
/*   */     //   2531: iload_3
/*   */     //   2532: aload_0
/*   */     //   2533: getfield final : [I
/*   */     //   2536: iload #4
/*   */     //   2538: iaload
/*   */     //   2539: iastore
/*   */     //   2540: iinc #4, 1
/*   */     //   2543: iinc #5, 1
/*   */     //   2546: goto -> 2513
/*   */     //   2549: iinc #3, 1
/*   */     //   2552: goto -> 2504
/*   */     //   2555: iconst_0
/*   */     //   2556: istore_3
/*   */     //   2557: iload_3
/*   */     //   2558: iconst_3
/*   */     //   2559: if_icmpge -> 2717
/*   */     //   2562: aload_0
/*   */     //   2563: getfield fM0 : [Lf/C60;
/*   */     //   2566: iload_2
/*   */     //   2567: aaload
/*   */     //   2568: getfield bW : [[I
/*   */     //   2571: iload_3
/*   */     //   2572: aaload
/*   */     //   2573: bipush #12
/*   */     //   2575: iconst_0
/*   */     //   2576: iastore
/*   */     //   2577: iinc #3, 1
/*   */     //   2580: goto -> 2557
/*   */     //   2583: iconst_0
/*   */     //   2584: istore_3
/*   */     //   2585: iload_3
/*   */     //   2586: bipush #12
/*   */     //   2588: if_icmpge -> 2636
/*   */     //   2591: iconst_0
/*   */     //   2592: istore #5
/*   */     //   2594: iload #5
/*   */     //   2596: iconst_3
/*   */     //   2597: if_icmpge -> 2630
/*   */     //   2600: aload_0
/*   */     //   2601: getfield fM0 : [Lf/C60;
/*   */     //   2604: iload_2
/*   */     //   2605: aaload
/*   */     //   2606: getfield bW : [[I
/*   */     //   2609: iload #5
/*   */     //   2611: aaload
/*   */     //   2612: iload_3
/*   */     //   2613: aload_0
/*   */     //   2614: getfield final : [I
/*   */     //   2617: iload #4
/*   */     //   2619: iaload
/*   */     //   2620: iastore
/*   */     //   2621: iinc #4, 1
/*   */     //   2624: iinc #5, 1
/*   */     //   2627: goto -> 2594
/*   */     //   2630: iinc #3, 1
/*   */     //   2633: goto -> 2585
/*   */     //   2636: iconst_0
/*   */     //   2637: istore_3
/*   */     //   2638: iload_3
/*   */     //   2639: iconst_3
/*   */     //   2640: if_icmpge -> 2717
/*   */     //   2643: aload_0
/*   */     //   2644: getfield fM0 : [Lf/C60;
/*   */     //   2647: iload_2
/*   */     //   2648: aaload
/*   */     //   2649: getfield bW : [[I
/*   */     //   2652: iload_3
/*   */     //   2653: aaload
/*   */     //   2654: bipush #12
/*   */     //   2656: iconst_0
/*   */     //   2657: iastore
/*   */     //   2658: iinc #3, 1
/*   */     //   2661: goto -> 2638
/*   */     //   2664: iconst_0
/*   */     //   2665: istore_3
/*   */     //   2666: iload_3
/*   */     //   2667: bipush #21
/*   */     //   2669: if_icmpge -> 2699
/*   */     //   2672: aload_0
/*   */     //   2673: getfield fM0 : [Lf/C60;
/*   */     //   2676: iload_2
/*   */     //   2677: aaload
/*   */     //   2678: getfield st0 : [I
/*   */     //   2681: iload_3
/*   */     //   2682: aload_0
/*   */     //   2683: getfield final : [I
/*   */     //   2686: iload #4
/*   */     //   2688: iaload
/*   */     //   2689: iastore
/*   */     //   2690: iinc #4, 1
/*   */     //   2693: iinc #3, 1
/*   */     //   2696: goto -> 2666
/*   */     //   2699: aload_0
/*   */     //   2700: getfield fM0 : [Lf/C60;
/*   */     //   2703: iload_2
/*   */     //   2704: aaload
/*   */     //   2705: getfield st0 : [I
/*   */     //   2708: dup
/*   */     //   2709: bipush #21
/*   */     //   2711: iconst_0
/*   */     //   2712: iastore
/*   */     //   2713: bipush #22
/*   */     //   2715: iconst_0
/*   */     //   2716: iastore
/*   */     //   2717: aload_0
/*   */     //   2718: dup
/*   */     //   2719: dup
/*   */     //   2720: dup2
/*   */     //   2721: getfield Fj0 : [I
/*   */     //   2724: iconst_0
/*   */     //   2725: iconst_0
/*   */     //   2726: iastore
/*   */     //   2727: getfield d0 : [I
/*   */     //   2730: iconst_0
/*   */     //   2731: iconst_0
/*   */     //   2732: iastore
/*   */     //   2733: getfield cp0 : [I
/*   */     //   2736: iconst_0
/*   */     //   2737: iconst_0
/*   */     //   2738: iastore
/*   */     //   2739: getfield Gh0 : [I
/*   */     //   2742: iconst_0
/*   */     //   2743: iconst_0
/*   */     //   2744: iastore
/*   */     //   2745: getfield uS : I
/*   */     //   2748: aload_0
/*   */     //   2749: getfield oD0 : Lf/qC0;
/*   */     //   2752: getfield hE : [Lf/Wm;
/*   */     //   2755: iload_2
/*   */     //   2756: aaload
/*   */     //   2757: getfield mh : [Lf/dT;
/*   */     //   2760: iload_1
/*   */     //   2761: aaload
/*   */     //   2762: dup
/*   */     //   2763: astore_3
/*   */     //   2764: getfield LpT5 : I
/*   */     //   2767: iadd
/*   */     //   2768: istore #4
/*   */     //   2770: aload_3
/*   */     //   2771: getfield hr0 : I
/*   */     //   2774: ifeq -> 2811
/*   */     //   2777: aload_3
/*   */     //   2778: getfield Ux : I
/*   */     //   2781: iconst_2
/*   */     //   2782: if_icmpne -> 2811
/*   */     //   2785: aload_0
/*   */     //   2786: getfield IF : I
/*   */     //   2789: bipush #8
/*   */     //   2791: if_icmpne -> 2800
/*   */     //   2794: bipush #72
/*   */     //   2796: istore_3
/*   */     //   2797: goto -> 2803
/*   */     //   2800: bipush #36
/*   */     //   2802: istore_3
/*   */     //   2803: sipush #576
/*   */     //   2806: istore #5
/*   */     //   2808: goto -> 2870
/*   */     //   2811: aload_3
/*   */     //   2812: getfield re0 : I
/*   */     //   2815: iconst_1
/*   */     //   2816: iadd
/*   */     //   2817: dup
/*   */     //   2818: istore #5
/*   */     //   2820: aload_3
/*   */     //   2821: getfield Cz : I
/*   */     //   2824: iadd
/*   */     //   2825: iconst_1
/*   */     //   2826: iadd
/*   */     //   2827: dup
/*   */     //   2828: istore_3
/*   */     //   2829: aload_0
/*   */     //   2830: getfield Dn : [Lf/xq;
/*   */     //   2833: aload_0
/*   */     //   2834: getfield IF : I
/*   */     //   2837: aaload
/*   */     //   2838: getfield F90 : [I
/*   */     //   2841: dup
/*   */     //   2842: astore #6
/*   */     //   2844: arraylength
/*   */     //   2845: iconst_1
/*   */     //   2846: isub
/*   */     //   2847: if_icmple -> 2853
/*   */     //   2850: bipush #22
/*   */     //   2852: istore_3
/*   */     //   2853: aload #6
/*   */     //   2855: dup
/*   */     //   2856: iload #5
/*   */     //   2858: iaload
/*   */     //   2859: istore #5
/*   */     //   2861: iload_3
/*   */     //   2862: iaload
/*   */     //   2863: istore_3
/*   */     //   2864: iload #5
/*   */     //   2866: iload_3
/*   */     //   2867: istore #5
/*   */     //   2869: istore_3
/*   */     //   2870: iconst_0
/*   */     //   2871: istore #6
/*   */     //   2873: iconst_0
/*   */     //   2874: istore #7
/*   */     //   2876: iload #7
/*   */     //   2878: aload_0
/*   */     //   2879: getfield oD0 : Lf/qC0;
/*   */     //   2882: getfield hE : [Lf/Wm;
/*   */     //   2885: iload_2
/*   */     //   2886: aaload
/*   */     //   2887: getfield mh : [Lf/dT;
/*   */     //   2890: iload_1
/*   */     //   2891: aaload
/*   */     //   2892: dup
/*   */     //   2893: astore #8
/*   */     //   2895: getfield Lo0 : I
/*   */     //   2898: iconst_1
/*   */     //   2899: ishl
/*   */     //   2900: if_icmpge -> 3068
/*   */     //   2903: iload #7
/*   */     //   2905: iload_3
/*   */     //   2906: if_icmpge -> 2925
/*   */     //   2909: getstatic f/sz.TM : [Lf/sz;
/*   */     //   2912: aload #8
/*   */     //   2914: getfield hL0 : [I
/*   */     //   2917: iconst_0
/*   */     //   2918: iaload
/*   */     //   2919: aaload
/*   */     //   2920: astore #8
/*   */     //   2922: goto -> 2961
/*   */     //   2925: iload #7
/*   */     //   2927: iload #5
/*   */     //   2929: if_icmpge -> 2948
/*   */     //   2932: getstatic f/sz.TM : [Lf/sz;
/*   */     //   2935: aload #8
/*   */     //   2937: getfield hL0 : [I
/*   */     //   2940: iconst_1
/*   */     //   2941: iaload
/*   */     //   2942: aaload
/*   */     //   2943: astore #8
/*   */     //   2945: goto -> 2961
/*   */     //   2948: getstatic f/sz.TM : [Lf/sz;
/*   */     //   2951: aload #8
/*   */     //   2953: getfield hL0 : [I
/*   */     //   2956: iconst_2
/*   */     //   2957: iaload
/*   */     //   2958: aaload
/*   */     //   2959: astore #8
/*   */     //   2961: aload_0
/*   */     //   2962: dup
/*   */     //   2963: aload #8
/*   */     //   2965: aload_0
/*   */     //   2966: dup
/*   */     //   2967: dup
/*   */     //   2968: dup2
/*   */     //   2969: getfield Fj0 : [I
/*   */     //   2972: astore #8
/*   */     //   2974: getfield d0 : [I
/*   */     //   2977: astore #9
/*   */     //   2979: getfield cp0 : [I
/*   */     //   2982: astore #10
/*   */     //   2984: getfield Gh0 : [I
/*   */     //   2987: astore #11
/*   */     //   2989: getfield Bg : Lf/CC;
/*   */     //   2992: astore #12
/*   */     //   2994: aload #8
/*   */     //   2996: aload #9
/*   */     //   2998: aload #10
/*   */     //   3000: aload #11
/*   */     //   3002: aload #12
/*   */     //   3004: invokestatic mm : (Lf/sz;[I[I[I[ILf/CC;)V
/*   */     //   3007: getfield hp0 : [I
/*   */     //   3010: dup
/*   */     //   3011: astore #8
/*   */     //   3013: aload_0
/*   */     //   3014: iload #6
/*   */     //   3016: iconst_1
/*   */     //   3017: iadd
/*   */     //   3018: istore #9
/*   */     //   3020: getfield Fj0 : [I
/*   */     //   3023: dup
/*   */     //   3024: astore #10
/*   */     //   3026: iconst_0
/*   */     //   3027: iaload
/*   */     //   3028: iload #6
/*   */     //   3030: swap
/*   */     //   3031: iastore
/*   */     //   3032: iload #9
/*   */     //   3034: iconst_1
/*   */     //   3035: iadd
/*   */     //   3036: istore #6
/*   */     //   3038: getfield d0 : [I
/*   */     //   3041: dup
/*   */     //   3042: astore #11
/*   */     //   3044: aload #10
/*   */     //   3046: aload #8
/*   */     //   3048: aload #11
/*   */     //   3050: iconst_0
/*   */     //   3051: iaload
/*   */     //   3052: iload #9
/*   */     //   3054: swap
/*   */     //   3055: iastore
/*   */     //   3056: iconst_0
/*   */     //   3057: iaload
/*   */     //   3058: pop
/*   */     //   3059: iconst_0
/*   */     //   3060: iaload
/*   */     //   3061: pop
/*   */     //   3062: iinc #7, 2
/*   */     //   3065: goto -> 2876
/*   */     //   3068: aload_0
/*   */     //   3069: getstatic f/sz.TM : [Lf/sz;
/*   */     //   3072: aload #8
/*   */     //   3074: getfield nD : I
/*   */     //   3077: bipush #32
/*   */     //   3079: iadd
/*   */     //   3080: aaload
/*   */     //   3081: astore_3
/*   */     //   3082: getfield Bg : Lf/CC;
/*   */     //   3085: getfield br : I
/*   */     //   3088: dup
/*   */     //   3089: istore #5
/*   */     //   3091: iload #4
/*   */     //   3093: if_icmpge -> 3263
/*   */     //   3096: iload #6
/*   */     //   3098: sipush #576
/*   */     //   3101: if_icmpge -> 3263
/*   */     //   3104: aload_0
/*   */     //   3105: dup
/*   */     //   3106: dup
/*   */     //   3107: aload_3
/*   */     //   3108: aload_0
/*   */     //   3109: dup
/*   */     //   3110: dup
/*   */     //   3111: dup2
/*   */     //   3112: getfield Fj0 : [I
/*   */     //   3115: astore #5
/*   */     //   3117: getfield d0 : [I
/*   */     //   3120: astore #7
/*   */     //   3122: getfield cp0 : [I
/*   */     //   3125: astore #8
/*   */     //   3127: getfield Gh0 : [I
/*   */     //   3130: astore #9
/*   */     //   3132: getfield Bg : Lf/CC;
/*   */     //   3135: astore #10
/*   */     //   3137: aload #5
/*   */     //   3139: aload #7
/*   */     //   3141: aload #8
/*   */     //   3143: aload #9
/*   */     //   3145: aload #10
/*   */     //   3147: invokestatic mm : (Lf/sz;[I[I[I[ILf/CC;)V
/*   */     //   3150: getfield hp0 : [I
/*   */     //   3153: dup
/*   */     //   3154: astore #5
/*   */     //   3156: aload_0
/*   */     //   3157: aload #5
/*   */     //   3159: aload_0
/*   */     //   3160: aload #5
/*   */     //   3162: aload_0
/*   */     //   3163: iload #6
/*   */     //   3165: iconst_1
/*   */     //   3166: iadd
/*   */     //   3167: istore #7
/*   */     //   3169: getfield cp0 : [I
/*   */     //   3172: dup
/*   */     //   3173: astore #8
/*   */     //   3175: iconst_0
/*   */     //   3176: iaload
/*   */     //   3177: iload #6
/*   */     //   3179: swap
/*   */     //   3180: iastore
/*   */     //   3181: iload #7
/*   */     //   3183: iconst_1
/*   */     //   3184: iadd
/*   */     //   3185: istore #6
/*   */     //   3187: getfield Gh0 : [I
/*   */     //   3190: dup
/*   */     //   3191: astore #9
/*   */     //   3193: iconst_0
/*   */     //   3194: iaload
/*   */     //   3195: iload #7
/*   */     //   3197: swap
/*   */     //   3198: iastore
/*   */     //   3199: iload #6
/*   */     //   3201: iconst_1
/*   */     //   3202: iadd
/*   */     //   3203: istore #7
/*   */     //   3205: getfield Fj0 : [I
/*   */     //   3208: dup
/*   */     //   3209: astore #10
/*   */     //   3211: iconst_0
/*   */     //   3212: iaload
/*   */     //   3213: iload #6
/*   */     //   3215: swap
/*   */     //   3216: iastore
/*   */     //   3217: iload #7
/*   */     //   3219: iconst_1
/*   */     //   3220: iadd
/*   */     //   3221: istore #6
/*   */     //   3223: getfield d0 : [I
/*   */     //   3226: dup
/*   */     //   3227: astore #11
/*   */     //   3229: aload #10
/*   */     //   3231: aload #9
/*   */     //   3233: aload #8
/*   */     //   3235: aload #5
/*   */     //   3237: aload #11
/*   */     //   3239: iconst_0
/*   */     //   3240: iaload
/*   */     //   3241: iload #7
/*   */     //   3243: swap
/*   */     //   3244: iastore
/*   */     //   3245: iconst_0
/*   */     //   3246: iaload
/*   */     //   3247: pop
/*   */     //   3248: iconst_0
/*   */     //   3249: iaload
/*   */     //   3250: pop
/*   */     //   3251: iconst_0
/*   */     //   3252: iaload
/*   */     //   3253: pop
/*   */     //   3254: iconst_0
/*   */     //   3255: iaload
/*   */     //   3256: pop
/*   */     //   3257: getfield Bg : Lf/CC;
/*   */     //   3260: goto -> 3085
/*   */     //   3263: iload #5
/*   */     //   3265: iload #4
/*   */     //   3267: if_icmple -> 3324
/*   */     //   3270: aload_0
/*   */     //   3271: getfield Bg : Lf/CC;
/*   */     //   3274: dup
/*   */     //   3275: dup2
/*   */     //   3276: astore_3
/*   */     //   3277: iload #5
/*   */     //   3279: iload #4
/*   */     //   3281: isub
/*   */     //   3282: istore #5
/*   */     //   3284: getfield br : I
/*   */     //   3287: iload #5
/*   */     //   3289: isub
/*   */     //   3290: putfield br : I
/*   */     //   3293: getfield vP : I
/*   */     //   3296: iload #5
/*   */     //   3298: isub
/*   */     //   3299: dup
/*   */     //   3300: istore #5
/*   */     //   3302: aload_3
/*   */     //   3303: iload #5
/*   */     //   3305: putfield vP : I
/*   */     //   3308: ifge -> 3321
/*   */     //   3311: aload_3
/*   */     //   3312: iload #5
/*   */     //   3314: ldc_w 32768
/*   */     //   3317: iadd
/*   */     //   3318: putfield vP : I
/*   */     //   3321: iinc #6, -4
/*   */     //   3324: aload_0
/*   */     //   3325: getfield Bg : Lf/CC;
/*   */     //   3328: dup
/*   */     //   3329: astore_3
/*   */     //   3330: getfield br : I
/*   */     //   3333: dup
/*   */     //   3334: istore #5
/*   */     //   3336: iload #4
/*   */     //   3338: if_icmpge -> 3351
/*   */     //   3341: aload_3
/*   */     //   3342: iload #4
/*   */     //   3344: iload #5
/*   */     //   3346: isub
/*   */     //   3347: invokevirtual F30 : (I)I
/*   */     //   3350: pop
/*   */     //   3351: iload #6
/*   */     //   3353: sipush #576
/*   */     //   3356: if_icmpge -> 3370
/*   */     //   3359: aload_0
/*   */     //   3360: getfield OY : [I
/*   */     //   3363: iload_2
/*   */     //   3364: iload #6
/*   */     //   3366: iastore
/*   */     //   3367: goto -> 3379
/*   */     //   3370: aload_0
/*   */     //   3371: getfield OY : [I
/*   */     //   3374: iload_2
/*   */     //   3375: sipush #576
/*   */     //   3378: iastore
/*   */     //   3379: iload #6
/*   */     //   3381: ifge -> 3387
/*   */     //   3384: iconst_0
/*   */     //   3385: istore #6
/*   */     //   3387: iload #6
/*   */     //   3389: sipush #576
/*   */     //   3392: if_icmpge -> 3409
/*   */     //   3395: aload_0
/*   */     //   3396: getfield hp0 : [I
/*   */     //   3399: iload #6
/*   */     //   3401: iconst_0
/*   */     //   3402: iastore
/*   */     //   3403: iinc #6, 1
/*   */     //   3406: goto -> 3387
/*   */     //   3409: aload_0
/*   */     //   3410: dup
/*   */     //   3411: getfield Jc0 : [[[F
/*   */     //   3414: iload_2
/*   */     //   3415: aaload
/*   */     //   3416: iload_2
/*   */     //   3417: iload_1
/*   */     //   3418: invokevirtual Jw : ([[FII)V
/*   */     //   3421: iinc #2, 1
/*   */     //   3424: goto -> 1833
/*   */     //   3427: aload_0
/*   */     //   3428: dup
/*   */     //   3429: iload_1
/*   */     //   3430: invokevirtual Lj0 : (I)V
/*   */     //   3433: getfield Fl : I
/*   */     //   3436: iconst_3
/*   */     //   3437: if_icmpne -> 3550
/*   */     //   3440: aload_0
/*   */     //   3441: getfield Ow0 : I
/*   */     //   3444: iconst_1
/*   */     //   3445: if_icmple -> 3550
/*   */     //   3448: iconst_0
/*   */     //   3449: istore_2
/*   */     //   3450: iload_2
/*   */     //   3451: bipush #18
/*   */     //   3453: if_icmpge -> 3550
/*   */     //   3456: iconst_0
/*   */     //   3457: istore_3
/*   */     //   3458: iload_3
/*   */     //   3459: bipush #18
/*   */     //   3461: if_icmpge -> 3544
/*   */     //   3464: aload_0
/*   */     //   3465: getfield pE : [[[F
/*   */     //   3468: dup
/*   */     //   3469: astore #4
/*   */     //   3471: iconst_0
/*   */     //   3472: aaload
/*   */     //   3473: iload_2
/*   */     //   3474: aaload
/*   */     //   3475: dup
/*   */     //   3476: dup2
/*   */     //   3477: dup2
/*   */     //   3478: iload_3
/*   */     //   3479: swap
/*   */     //   3480: iload_3
/*   */     //   3481: faload
/*   */     //   3482: aload #4
/*   */     //   3484: iconst_1
/*   */     //   3485: aaload
/*   */     //   3486: iload_2
/*   */     //   3487: aaload
/*   */     //   3488: dup
/*   */     //   3489: astore #4
/*   */     //   3491: iload_3
/*   */     //   3492: faload
/*   */     //   3493: fadd
/*   */     //   3494: ldc 0.5
/*   */     //   3496: fmul
/*   */     //   3497: fastore
/*   */     //   3498: iload_3
/*   */     //   3499: iconst_1
/*   */     //   3500: iadd
/*   */     //   3501: dup
/*   */     //   3502: istore #5
/*   */     //   3504: faload
/*   */     //   3505: aload #4
/*   */     //   3507: iload #5
/*   */     //   3509: faload
/*   */     //   3510: fadd
/*   */     //   3511: ldc 0.5
/*   */     //   3513: fmul
/*   */     //   3514: iload #5
/*   */     //   3516: swap
/*   */     //   3517: fastore
/*   */     //   3518: iload_3
/*   */     //   3519: iconst_2
/*   */     //   3520: iadd
/*   */     //   3521: dup
/*   */     //   3522: istore #5
/*   */     //   3524: faload
/*   */     //   3525: aload #4
/*   */     //   3527: iload #5
/*   */     //   3529: faload
/*   */     //   3530: fadd
/*   */     //   3531: ldc 0.5
/*   */     //   3533: fmul
/*   */     //   3534: iload #5
/*   */     //   3536: swap
/*   */     //   3537: fastore
/*   */     //   3538: iinc #3, 3
/*   */     //   3541: goto -> 3458
/*   */     //   3544: iinc #2, 1
/*   */     //   3547: goto -> 3450
/*   */     //   3550: aload_0
/*   */     //   3551: getfield HH0 : I
/*   */     //   3554: istore_2
/*   */     //   3555: iload_2
/*   */     //   3556: aload_0
/*   */     //   3557: getfield Lr0 : I
/*   */     //   3560: if_icmpgt -> 3878
/*   */     //   3563: aload_0
/*   */     //   3564: iload_2
/*   */     //   3565: aload_0
/*   */     //   3566: iload_2
/*   */     //   3567: aload_0
/*   */     //   3568: dup
/*   */     //   3569: getfield pE : [[[F
/*   */     //   3572: iload_2
/*   */     //   3573: aaload
/*   */     //   3574: iload_2
/*   */     //   3575: iload_1
/*   */     //   3576: invokevirtual Hx0 : ([[FII)V
/*   */     //   3579: iload_1
/*   */     //   3580: invokevirtual BB : (II)V
/*   */     //   3583: iload_1
/*   */     //   3584: invokevirtual Pg0 : (II)V
/*   */     //   3587: bipush #18
/*   */     //   3589: istore_3
/*   */     //   3590: iload_3
/*   */     //   3591: sipush #576
/*   */     //   3594: if_icmpge -> 3637
/*   */     //   3597: iconst_1
/*   */     //   3598: istore #4
/*   */     //   3600: iload #4
/*   */     //   3602: bipush #18
/*   */     //   3604: if_icmpge -> 3631
/*   */     //   3607: aload_0
/*   */     //   3608: getfield y70 : [F
/*   */     //   3611: dup
/*   */     //   3612: iload_3
/*   */     //   3613: iload #4
/*   */     //   3615: iadd
/*   */     //   3616: dup
/*   */     //   3617: istore #5
/*   */     //   3619: faload
/*   */     //   3620: fneg
/*   */     //   3621: iload #5
/*   */     //   3623: swap
/*   */     //   3624: fastore
/*   */     //   3625: iinc #4, 2
/*   */     //   3628: goto -> 3600
/*   */     //   3631: iinc #3, 36
/*   */     //   3634: goto -> 3590
/*   */     //   3637: iload_2
/*   */     //   3638: ifeq -> 3762
/*   */     //   3641: aload_0
/*   */     //   3642: getfield Fl : I
/*   */     //   3645: iconst_2
/*   */     //   3646: if_icmpne -> 3652
/*   */     //   3649: goto -> 3762
/*   */     //   3652: iconst_0
/*   */     //   3653: istore_3
/*   */     //   3654: iload_3
/*   */     //   3655: bipush #18
/*   */     //   3657: if_icmpge -> 3872
/*   */     //   3660: iconst_0
/*   */     //   3661: istore #4
/*   */     //   3663: iconst_0
/*   */     //   3664: istore #5
/*   */     //   3666: iload #5
/*   */     //   3668: sipush #576
/*   */     //   3671: if_icmpge -> 3699
/*   */     //   3674: aload_0
/*   */     //   3675: getfield Aa0 : [F
/*   */     //   3678: iload #4
/*   */     //   3680: aload_0
/*   */     //   3681: getfield y70 : [F
/*   */     //   3684: iload #5
/*   */     //   3686: iload_3
/*   */     //   3687: iadd
/*   */     //   3688: faload
/*   */     //   3689: fastore
/*   */     //   3690: iinc #4, 1
/*   */     //   3693: iinc #5, 18
/*   */     //   3696: goto -> 3666
/*   */     //   3699: aload_0
/*   */     //   3700: dup
/*   */     //   3701: getfield sD0 : Lf/Va;
/*   */     //   3704: astore #4
/*   */     //   3706: getfield Aa0 : [F
/*   */     //   3709: astore #5
/*   */     //   3711: bipush #31
/*   */     //   3713: istore #6
/*   */     //   3715: iload #6
/*   */     //   3717: iflt -> 3739
/*   */     //   3720: aload #4
/*   */     //   3722: getfield z0 : [F
/*   */     //   3725: iload #6
/*   */     //   3727: aload #5
/*   */     //   3729: iload #6
/*   */     //   3731: faload
/*   */     //   3732: fastore
/*   */     //   3733: iinc #6, -1
/*   */     //   3736: goto -> 3715
/*   */     //   3739: aload_0
/*   */     //   3740: aload #4
/*   */     //   3742: invokevirtual getClass : ()Ljava/lang/Class;
/*   */     //   3745: pop
/*   */     //   3746: getfield sD0 : Lf/Va;
/*   */     //   3749: aload_0
/*   */     //   3750: getfield Tn : Lf/qR;
/*   */     //   3753: invokevirtual yv0 : (Lf/qR;)V
/*   */     //   3756: iinc #3, 1
/*   */     //   3759: goto -> 3654
/*   */     //   3762: iconst_0
/*   */     //   3763: istore_3
/*   */     //   3764: iload_3
/*   */     //   3765: bipush #18
/*   */     //   3767: if_icmpge -> 3872
/*   */     //   3770: iconst_0
/*   */     //   3771: istore #4
/*   */     //   3773: iconst_0
/*   */     //   3774: istore #5
/*   */     //   3776: iload #5
/*   */     //   3778: sipush #576
/*   */     //   3781: if_icmpge -> 3809
/*   */     //   3784: aload_0
/*   */     //   3785: getfield Cc0 : [F
/*   */     //   3788: iload #4
/*   */     //   3790: aload_0
/*   */     //   3791: getfield y70 : [F
/*   */     //   3794: iload #5
/*   */     //   3796: iload_3
/*   */     //   3797: iadd
/*   */     //   3798: faload
/*   */     //   3799: fastore
/*   */     //   3800: iinc #4, 1
/*   */     //   3803: iinc #5, 18
/*   */     //   3806: goto -> 3776
/*   */     //   3809: aload_0
/*   */     //   3810: dup
/*   */     //   3811: getfield aZ : Lf/Va;
/*   */     //   3814: astore #4
/*   */     //   3816: getfield Cc0 : [F
/*   */     //   3819: astore #5
/*   */     //   3821: bipush #31
/*   */     //   3823: istore #6
/*   */     //   3825: iload #6
/*   */     //   3827: iflt -> 3849
/*   */     //   3830: aload #4
/*   */     //   3832: getfield z0 : [F
/*   */     //   3835: iload #6
/*   */     //   3837: aload #5
/*   */     //   3839: iload #6
/*   */     //   3841: faload
/*   */     //   3842: fastore
/*   */     //   3843: iinc #6, -1
/*   */     //   3846: goto -> 3825
/*   */     //   3849: aload_0
/*   */     //   3850: aload #4
/*   */     //   3852: invokevirtual getClass : ()Ljava/lang/Class;
/*   */     //   3855: pop
/*   */     //   3856: getfield aZ : Lf/Va;
/*   */     //   3859: aload_0
/*   */     //   3860: getfield Tn : Lf/qR;
/*   */     //   3863: invokevirtual yv0 : (Lf/qR;)V
/*   */     //   3866: iinc #3, 1
/*   */     //   3869: goto -> 3764
/*   */     //   3872: iinc #2, 1
/*   */     //   3875: goto -> 3555
/*   */     //   3878: iinc #1, 1
/*   */     //   3881: goto -> 1823
/*   */     //   3884: return
/*   */     // Line number table:
/*   */     //   Java source line number -> byte code offset
/*   */     //   #1	-> 1
/*   */     //   #2	-> 5
/*   */     //   #3	-> 9
/*   */     //   #4	-> 18
/*   */     //   #5	-> 1490
/*   */     //   #6	-> 1507
/*   */     //   #7	-> 1512
/*   */     //   #8	-> 1673
/*   */     //   #9	-> 1678
/*   */     //   #10	-> 1700
/*   */     //   #11	-> 1764
/*   */     //   #12	-> 1771
/*   */     //   #13	-> 1806
/*   */     //   #14	-> 1847
/*   */     //   #15	-> 1850
/*   */     //   #16	-> 1858
/*   */     //   #17	-> 1868
/*   */     //   #18	-> 1878
/*   */     //   #19	-> 1896
/*   */     //   #20	-> 1903
/*   */     //   #21	-> 2444
/*   */     //   #22	-> 2721
/*   */     //   #23	-> 3085
/*   */     //   #24	-> 3112
/*   */     //   #25	-> 3284
/*   */     //   #26	-> 3290
/*   */     //   #27	-> 3325
/*   */     //   #28	-> 3330
/*   */     //   #29	-> 3347
/*   */     //   #30	-> 3411
/*   */     //   #31	-> 3465
/*   */     //   #32	-> 3551
/*   */     //   #33	-> 3722
/*   */     //   #34	-> 3731
/*   */     //   #35	-> 3742
/*   */     //   #36	-> 3832
/*   */     //   #37	-> 3841
/*   */     //   #38	-> 3852
/*   */   }
/*   */   
/*   */   public static final float[] w7 = new float[] { 
/*   */       0.0F, 0.2679492F, 0.57735026F, 1.0F, 1.7320508F, 3.732051F, 9.9999998E10F, -3.732051F, -1.7320508F, -1.0F, 
/*   */       -0.57735026F, -0.2679492F, 0.0F, 0.2679492F, 0.57735026F, 1.0F };
/*   */   public static int[][] Sa;
/*   */   public static final float[] k70 = new float[] { 0.8574929F, 0.881742F, 0.94962865F, 0.9833146F, 0.9955178F, 0.9991606F, 0.9998992F, 0.99999315F };
/*   */   public static final float[] ab = new float[] { -0.51449573F, -0.47173196F, -0.31337744F, -0.1819132F, -0.09457419F, -0.040965583F, -0.014198569F, -0.0036999746F };
/*   */   public static final float[][] hF0;
/*   */   public static final int[][][] wA;
/*   */   public int[] final;
/*   */   public int[] hp0;
/*   */   public float[][][] Jc0;
/*   */   public float[][][] pE;
/*   */   public float[] y70;
/*   */   public float[][] f20;
/*   */   public float[][] Ym0;
/*   */   public int[] OY;
/*   */   public AH0 cOm1;
/*   */   public Ym0 kO;
/*   */   public Va aZ;
/*   */   public Va sD0;
/*   */   public qR Tn;
/*   */   public int Fl;
/*   */   public CC Bg;
/*   */   public qC0 oD0;
/*   */   public C60[] o40;
/*   */   public C60[] fM0;
/*   */   public int S70;
/*   */   public int lPt7;
/*   */   public int uS;
/*   */   public int Ow0;
/*   */   public int HH0;
/*   */   public int Lr0;
/*   */   public int IF;
/*   */   public float[] Cc0;
/*   */   public float[] Aa0;
/*   */   public final int[] H2;
/*   */   public int[] Fj0;
/*   */   public int[] d0;
/*   */   public int[] cp0;
/*   */   public int[] Gh0;
/*   */   public int[] c2;
/*   */   public float[] M;
/*   */   public float[] v10;
/*   */   public float[] CL;
/*   */   public xq[] Dn;
/*   */   
/*   */   static {
/*   */     (arrayOfFloat = new float[36])[0] = -0.016141215F;
/*   */     (new float[36])[1] = -0.05360318F;
/*   */     (new float[36])[2] = -0.100707136F;
/*   */     (new float[36])[3] = -0.16280818F;
/*   */     (new float[36])[4] = -0.5F;
/*   */     (new float[36])[5] = -0.38388735F;
/*   */     (new float[36])[6] = -0.6206114F;
/*   */     (new float[36])[7] = -1.1659756F;
/*   */     (new float[36])[8] = -3.8720753F;
/*   */     (new float[36])[9] = -4.225629F;
/*   */     (new float[36])[10] = -1.519529F;
/*   */     (new float[36])[11] = -0.97416484F;
/*   */     (new float[36])[12] = -0.73744076F;
/*   */     (new float[36])[13] = -1.2071068F;
/*   */     (new float[36])[14] = -0.5163616F;
/*   */     (new float[36])[15] = -0.45426053F;
/*   */     (new float[36])[16] = -0.40715656F;
/*   */     (new float[36])[17] = -0.3696946F;
/*   */     (new float[36])[18] = -0.3387627F;
/*   */     (new float[36])[19] = -0.31242222F;
/*   */     (new float[36])[20] = -0.28939587F;
/*   */     (new float[36])[21] = -0.26880082F;
/*   */     (new float[36])[22] = -0.5F;
/*   */     (new float[36])[23] = -0.23251417F;
/*   */     (new float[36])[24] = -0.21596715F;
/*   */     (new float[36])[25] = -0.20004979F;
/*   */     (new float[36])[26] = -0.18449493F;
/*   */     (new float[36])[27] = -0.16905846F;
/*   */     (new float[36])[28] = -0.15350361F;
/*   */     (new float[36])[29] = -0.13758625F;
/*   */     (new float[36])[30] = -0.12103922F;
/*   */     (new float[36])[31] = -0.20710678F;
/*   */     (new float[36])[32] = -0.084752575F;
/*   */     (new float[36])[33] = -0.06415752F;
/*   */     (new float[36])[34] = -0.041131172F;
/*   */     (new float[36])[35] = -0.014790705F;
/*   */     (new float[4][])[0] = arrayOfFloat;
/*   */     (arrayOfFloat = new float[36])[0] = -0.016141215F;
/*   */     (new float[36])[1] = -0.05360318F;
/*   */     (new float[36])[2] = -0.100707136F;
/*   */     (new float[36])[3] = -0.16280818F;
/*   */     (new float[36])[4] = -0.5F;
/*   */     (new float[36])[5] = -0.38388735F;
/*   */     (new float[36])[6] = -0.6206114F;
/*   */     (new float[36])[7] = -1.1659756F;
/*   */     (new float[36])[8] = -3.8720753F;
/*   */     (new float[36])[9] = -4.225629F;
/*   */     (new float[36])[10] = -1.519529F;
/*   */     (new float[36])[11] = -0.97416484F;
/*   */     (new float[36])[12] = -0.73744076F;
/*   */     (new float[36])[13] = -1.2071068F;
/*   */     (new float[36])[14] = -0.5163616F;
/*   */     (new float[36])[15] = -0.45426053F;
/*   */     (new float[36])[16] = -0.40715656F;
/*   */     (new float[36])[17] = -0.3696946F;
/*   */     (new float[36])[18] = -0.33908543F;
/*   */     (new float[36])[19] = -0.3151181F;
/*   */     (new float[36])[20] = -0.29642227F;
/*   */     (new float[36])[21] = -0.28184548F;
/*   */     (new float[36])[22] = -0.5411961F;
/*   */     (new float[36])[23] = -0.2621323F;
/*   */     (new float[36])[24] = -0.25387916F;
/*   */     (new float[36])[25] = -0.2329629F;
/*   */     (new float[36])[26] = -0.19852729F;
/*   */     (new float[36])[27] = -0.15233535F;
/*   */     (new float[36])[28] = -0.0964964F;
/*   */     (new float[36])[29] = -0.03342383F;
/*   */     (new float[36])[30] = 0.0F;
/*   */     (new float[36])[31] = 0.0F;
/*   */     (new float[36])[32] = 0.0F;
/*   */     (new float[36])[33] = 0.0F;
/*   */     (new float[36])[34] = 0.0F;
/*   */     (new float[36])[35] = 0.0F;
/*   */     (new float[4][])[1] = arrayOfFloat;
/*   */     (arrayOfFloat = new float[36])[0] = -0.0483008F;
/*   */     (new float[36])[1] = -0.15715657F;
/*   */     (new float[36])[2] = -0.28325045F;
/*   */     (new float[36])[3] = -0.42953748F;
/*   */     (new float[36])[4] = -1.2071068F;
/*   */     (new float[36])[5] = -0.8242648F;
/*   */     (new float[36])[6] = -1.1451749F;
/*   */     (new float[36])[7] = -1.769529F;
/*   */     (new float[36])[8] = -4.5470223F;
/*   */     (new float[36])[9] = -3.489053F;
/*   */     (new float[36])[10] = -0.7329629F;
/*   */     (new float[36])[11] = -0.15076515F;
/*   */     (new float[36])[12] = 0.0F;
/*   */     (new float[36])[13] = 0.0F;
/*   */     (new float[36])[14] = 0.0F;
/*   */     (new float[36])[15] = 0.0F;
/*   */     (new float[36])[16] = 0.0F;
/*   */     (new float[36])[17] = 0.0F;
/*   */     (new float[36])[18] = 0.0F;
/*   */     (new float[36])[19] = 0.0F;
/*   */     (new float[36])[20] = 0.0F;
/*   */     (new float[36])[21] = 0.0F;
/*   */     (new float[36])[22] = 0.0F;
/*   */     (new float[36])[23] = 0.0F;
/*   */     (new float[36])[24] = 0.0F;
/*   */     (new float[36])[25] = 0.0F;
/*   */     (new float[36])[26] = 0.0F;
/*   */     (new float[36])[27] = 0.0F;
/*   */     (new float[36])[28] = 0.0F;
/*   */     (new float[36])[29] = 0.0F;
/*   */     (new float[36])[30] = 0.0F;
/*   */     (new float[36])[31] = 0.0F;
/*   */     (new float[36])[32] = 0.0F;
/*   */     (new float[36])[33] = 0.0F;
/*   */     (new float[36])[34] = 0.0F;
/*   */     (new float[36])[35] = 0.0F;
/*   */     (new float[4][])[2] = arrayOfFloat;
/*   */     (arrayOfFloat = new float[36])[0] = 0.0F;
/*   */     (new float[36])[1] = 0.0F;
/*   */     (new float[36])[2] = 0.0F;
/*   */     (new float[36])[3] = 0.0F;
/*   */     (new float[36])[4] = 0.0F;
/*   */     (new float[36])[5] = 0.0F;
/*   */     (new float[36])[6] = -0.15076514F;
/*   */     (new float[36])[7] = -0.7329629F;
/*   */     (new float[36])[8] = -3.489053F;
/*   */     (new float[36])[9] = -4.5470223F;
/*   */     (new float[36])[10] = -1.769529F;
/*   */     (new float[36])[11] = -1.1451749F;
/*   */     (new float[36])[12] = -0.8313774F;
/*   */     (new float[36])[13] = -1.306563F;
/*   */     (new float[36])[14] = -0.54142016F;
/*   */     (new float[36])[15] = -0.46528974F;
/*   */     (new float[36])[16] = -0.4106699F;
/*   */     (new float[36])[17] = -0.3700468F;
/*   */     (new float[36])[18] = -0.3387627F;
/*   */     (new float[36])[19] = -0.31242222F;
/*   */     (new float[36])[20] = -0.28939587F;
/*   */     (new float[36])[21] = -0.26880082F;
/*   */     (new float[36])[22] = -0.5F;
/*   */     (new float[36])[23] = -0.23251417F;
/*   */     (new float[36])[24] = -0.21596715F;
/*   */     (new float[36])[25] = -0.20004979F;
/*   */     (new float[36])[26] = -0.18449493F;
/*   */     (new float[36])[27] = -0.16905846F;
/*   */     (new float[36])[28] = -0.15350361F;
/*   */     (new float[36])[29] = -0.13758625F;
/*   */     (new float[36])[30] = -0.12103922F;
/*   */     (new float[36])[31] = -0.20710678F;
/*   */     (new float[36])[32] = -0.084752575F;
/*   */     (new float[36])[33] = -0.06415752F;
/*   */     (new float[36])[34] = -0.041131172F;
/*   */     (new float[36])[35] = -0.014790705F;
/*   */     hF0 = new float[][] { null, null, null, arrayOfFloat };
/*   */     int[] arrayOfInt2;
/*   */     (arrayOfInt2 = new int[4])[0] = 6;
/*   */     (new int[4])[1] = 5;
/*   */     (new int[4])[2] = 5;
/*   */     (new int[4])[3] = 5;
/*   */     int[][] arrayOfInt;
/*   */     (arrayOfInt = new int[3][])[0] = arrayOfInt2;
/*   */     (arrayOfInt2 = new int[4])[0] = 9;
/*   */     (new int[4])[1] = 9;
/*   */     (new int[4])[2] = 9;
/*   */     (new int[4])[3] = 9;
/*   */     (new int[3][])[1] = arrayOfInt2;
/*   */     (arrayOfInt2 = new int[4])[0] = 6;
/*   */     (new int[4])[1] = 9;
/*   */     (new int[4])[2] = 9;
/*   */     (new int[4])[3] = 9;
/*   */     (new int[3][])[2] = arrayOfInt2;
/*   */     (new int[6][][])[0] = arrayOfInt;
/*   */     (arrayOfInt2 = new int[4])[0] = 6;
/*   */     (new int[4])[1] = 5;
/*   */     (new int[4])[2] = 7;
/*   */     (new int[4])[3] = 3;
/*   */     (arrayOfInt = new int[3][])[0] = arrayOfInt2;
/*   */     (arrayOfInt2 = new int[4])[0] = 9;
/*   */     (new int[4])[1] = 9;
/*   */     (new int[4])[2] = 12;
/*   */     (new int[4])[3] = 6;
/*   */     (new int[3][])[1] = arrayOfInt2;
/*   */     (arrayOfInt2 = new int[4])[0] = 6;
/*   */     (new int[4])[1] = 9;
/*   */     (new int[4])[2] = 12;
/*   */     (new int[4])[3] = 6;
/*   */     (new int[3][])[2] = arrayOfInt2;
/*   */     (new int[6][][])[1] = arrayOfInt;
/*   */     (arrayOfInt2 = new int[4])[0] = 11;
/*   */     (new int[4])[1] = 10;
/*   */     (new int[4])[2] = 0;
/*   */     (new int[4])[3] = 0;
/*   */     (arrayOfInt = new int[3][])[0] = arrayOfInt2;
/*   */     (arrayOfInt2 = new int[4])[0] = 18;
/*   */     (new int[4])[1] = 18;
/*   */     (new int[4])[2] = 0;
/*   */     (new int[4])[3] = 0;
/*   */     (new int[3][])[1] = arrayOfInt2;
/*   */     (arrayOfInt2 = new int[4])[0] = 15;
/*   */     (new int[4])[1] = 18;
/*   */     (new int[4])[2] = 0;
/*   */     (new int[4])[3] = 0;
/*   */     (new int[3][])[2] = arrayOfInt2;
/*   */     (new int[6][][])[2] = arrayOfInt;
/*   */     (arrayOfInt2 = new int[4])[0] = 7;
/*   */     (new int[4])[1] = 7;
/*   */     (new int[4])[2] = 7;
/*   */     (new int[4])[3] = 0;
/*   */     (arrayOfInt = new int[3][])[0] = arrayOfInt2;
/*   */     (arrayOfInt2 = new int[4])[0] = 12;
/*   */     (new int[4])[1] = 12;
/*   */     (new int[4])[2] = 12;
/*   */     (new int[4])[3] = 0;
/*   */     (new int[3][])[1] = arrayOfInt2;
/*   */     (arrayOfInt2 = new int[4])[0] = 6;
/*   */     (new int[4])[1] = 15;
/*   */     (new int[4])[2] = 12;
/*   */     (new int[4])[3] = 0;
/*   */     (new int[3][])[2] = arrayOfInt2;
/*   */     (new int[6][][])[3] = arrayOfInt;
/*   */     (arrayOfInt2 = new int[4])[0] = 6;
/*   */     (new int[4])[1] = 6;
/*   */     (new int[4])[2] = 6;
/*   */     (new int[4])[3] = 3;
/*   */     (arrayOfInt = new int[3][])[0] = arrayOfInt2;
/*   */     (arrayOfInt2 = new int[4])[0] = 12;
/*   */     (new int[4])[1] = 9;
/*   */     (new int[4])[2] = 9;
/*   */     (new int[4])[3] = 6;
/*   */     (new int[3][])[1] = arrayOfInt2;
/*   */     (arrayOfInt2 = new int[4])[0] = 6;
/*   */     (new int[4])[1] = 12;
/*   */     (new int[4])[2] = 9;
/*   */     (new int[4])[3] = 6;
/*   */     (new int[3][])[2] = arrayOfInt2;
/*   */     (new int[6][][])[4] = arrayOfInt;
/*   */     (arrayOfInt2 = new int[4])[0] = 8;
/*   */     (new int[4])[1] = 8;
/*   */     (new int[4])[2] = 5;
/*   */     (new int[4])[3] = 0;
/*   */     (arrayOfInt = new int[3][])[0] = arrayOfInt2;
/*   */     (arrayOfInt2 = new int[4])[0] = 15;
/*   */     (new int[4])[1] = 12;
/*   */     (new int[4])[2] = 9;
/*   */     (new int[4])[3] = 0;
/*   */     (new int[3][])[1] = arrayOfInt2;
/*   */     (arrayOfInt2 = new int[4])[0] = 6;
/*   */     (new int[4])[1] = 18;
/*   */     (new int[4])[2] = 9;
/*   */     (new int[4])[3] = 0;
/*   */     (new int[3][])[2] = arrayOfInt2;
/*   */     wA = new int[][][] { null, null, null, null, null, arrayOfInt };
/*   */   }
/*   */   
/*   */   public static int[] en0(int[] paramArrayOfint) {
/*   */     int i = 0;
/*   */     int[] arrayOfInt = new int[576];
/*   */     int j = 0;
/*   */     while (j < 13) {
/*   */       int k = paramArrayOfint[j];
/*   */       int m = paramArrayOfint[++j];
/*   */       for (byte b = 0; b < 3; b++) {
/*   */         for (int n = k; n < m; n++)
/*   */           arrayOfInt[n * 3 + b] = i++; 
/*   */       } 
/*   */     } 
/*   */     return arrayOfInt;
/*   */   }
/*   */   
/*   */   public oH(AH0 paramAH0, Ym0 paramYm0, Va paramVa1, Va paramVa2, qR paramqR) {
/*   */     // Byte code:
/*   */     //   0: aload_0
/*   */     //   1: dup
/*   */     //   2: dup2
/*   */     //   3: dup2
/*   */     //   4: dup2
/*   */     //   5: dup2
/*   */     //   6: dup2
/*   */     //   7: dup2
/*   */     //   8: dup2
/*   */     //   9: dup2
/*   */     //   10: dup2
/*   */     //   11: dup2
/*   */     //   12: iconst_0
/*   */     //   13: istore #6
/*   */     //   15: invokespecial <init> : ()V
/*   */     //   18: bipush #32
/*   */     //   20: newarray float
/*   */     //   22: putfield Cc0 : [F
/*   */     //   25: bipush #32
/*   */     //   27: newarray float
/*   */     //   29: putfield Aa0 : [F
/*   */     //   32: iconst_4
/*   */     //   33: newarray int
/*   */     //   35: putfield H2 : [I
/*   */     //   38: iconst_1
/*   */     //   39: newarray int
/*   */     //   41: dup
/*   */     //   42: iconst_0
/*   */     //   43: iconst_0
/*   */     //   44: iastore
/*   */     //   45: putfield Fj0 : [I
/*   */     //   48: iconst_1
/*   */     //   49: newarray int
/*   */     //   51: dup
/*   */     //   52: iconst_0
/*   */     //   53: iconst_0
/*   */     //   54: iastore
/*   */     //   55: putfield d0 : [I
/*   */     //   58: iconst_1
/*   */     //   59: newarray int
/*   */     //   61: dup
/*   */     //   62: iconst_0
/*   */     //   63: iconst_0
/*   */     //   64: iastore
/*   */     //   65: putfield cp0 : [I
/*   */     //   68: iconst_1
/*   */     //   69: newarray int
/*   */     //   71: dup
/*   */     //   72: iconst_0
/*   */     //   73: iconst_0
/*   */     //   74: iastore
/*   */     //   75: putfield Gh0 : [I
/*   */     //   78: sipush #576
/*   */     //   81: newarray int
/*   */     //   83: putfield c2 : [I
/*   */     //   86: sipush #576
/*   */     //   89: newarray float
/*   */     //   91: putfield M : [F
/*   */     //   94: bipush #18
/*   */     //   96: newarray float
/*   */     //   98: putfield v10 : [F
/*   */     //   101: bipush #36
/*   */     //   103: newarray float
/*   */     //   105: putfield CL : [F
/*   */     //   108: invokestatic Ig0 : ()V
/*   */     //   111: sipush #580
/*   */     //   114: newarray int
/*   */     //   116: putfield hp0 : [I
/*   */     //   119: iconst_2
/*   */     //   120: bipush #32
/*   */     //   122: bipush #18
/*   */     //   124: multianewarray[[[F 3
/*   */     //   128: putfield Jc0 : [[[F
/*   */     //   131: iconst_2
/*   */     //   132: bipush #32
/*   */     //   134: bipush #18
/*   */     //   136: multianewarray[[[F 3
/*   */     //   140: putfield pE : [[[F
/*   */     //   143: sipush #576
/*   */     //   146: newarray float
/*   */     //   148: putfield y70 : [F
/*   */     //   151: iconst_2
/*   */     //   152: sipush #576
/*   */     //   155: multianewarray[[F 2
/*   */     //   159: putfield f20 : [[F
/*   */     //   162: iconst_2
/*   */     //   163: sipush #576
/*   */     //   166: multianewarray[[F 2
/*   */     //   170: putfield Ym0 : [[F
/*   */     //   173: iconst_2
/*   */     //   174: newarray int
/*   */     //   176: putfield OY : [I
/*   */     //   179: iconst_2
/*   */     //   180: anewarray f/C60
/*   */     //   183: dup
/*   */     //   184: aload_0
/*   */     //   185: swap
/*   */     //   186: putfield o40 : [Lf/C60;
/*   */     //   189: new f/C60
/*   */     //   192: dup
/*   */     //   193: astore #7
/*   */     //   195: invokespecial <init> : ()V
/*   */     //   198: iconst_0
/*   */     //   199: aload #7
/*   */     //   201: aastore
/*   */     //   202: getfield o40 : [Lf/C60;
/*   */     //   205: new f/C60
/*   */     //   208: dup
/*   */     //   209: astore #7
/*   */     //   211: invokespecial <init> : ()V
/*   */     //   214: iconst_1
/*   */     //   215: aload #7
/*   */     //   217: aastore
/*   */     //   218: getfield o40 : [Lf/C60;
/*   */     //   221: putfield fM0 : [Lf/C60;
/*   */     //   224: bipush #9
/*   */     //   226: anewarray f/xq
/*   */     //   229: dup
/*   */     //   230: dup2
/*   */     //   231: dup2
/*   */     //   232: dup2
/*   */     //   233: dup2
/*   */     //   234: aload_0
/*   */     //   235: swap
/*   */     //   236: putfield Dn : [Lf/xq;
/*   */     //   239: bipush #23
/*   */     //   241: newarray int
/*   */     //   243: dup
/*   */     //   244: dup2
/*   */     //   245: dup2
/*   */     //   246: dup2
/*   */     //   247: dup2
/*   */     //   248: dup2
/*   */     //   249: dup2
/*   */     //   250: dup2
/*   */     //   251: dup2
/*   */     //   252: dup2
/*   */     //   253: dup2
/*   */     //   254: dup2
/*   */     //   255: astore #7
/*   */     //   257: iconst_0
/*   */     //   258: iconst_0
/*   */     //   259: iastore
/*   */     //   260: iconst_1
/*   */     //   261: bipush #6
/*   */     //   263: iastore
/*   */     //   264: iconst_2
/*   */     //   265: bipush #12
/*   */     //   267: iastore
/*   */     //   268: iconst_3
/*   */     //   269: bipush #18
/*   */     //   271: iastore
/*   */     //   272: iconst_4
/*   */     //   273: bipush #24
/*   */     //   275: iastore
/*   */     //   276: iconst_5
/*   */     //   277: bipush #30
/*   */     //   279: iastore
/*   */     //   280: bipush #6
/*   */     //   282: bipush #36
/*   */     //   284: iastore
/*   */     //   285: bipush #7
/*   */     //   287: bipush #44
/*   */     //   289: iastore
/*   */     //   290: bipush #8
/*   */     //   292: bipush #54
/*   */     //   294: iastore
/*   */     //   295: bipush #9
/*   */     //   297: bipush #66
/*   */     //   299: iastore
/*   */     //   300: bipush #10
/*   */     //   302: bipush #80
/*   */     //   304: iastore
/*   */     //   305: bipush #11
/*   */     //   307: bipush #96
/*   */     //   309: iastore
/*   */     //   310: bipush #12
/*   */     //   312: bipush #116
/*   */     //   314: iastore
/*   */     //   315: bipush #13
/*   */     //   317: sipush #140
/*   */     //   320: iastore
/*   */     //   321: bipush #14
/*   */     //   323: sipush #168
/*   */     //   326: iastore
/*   */     //   327: bipush #15
/*   */     //   329: sipush #200
/*   */     //   332: iastore
/*   */     //   333: bipush #16
/*   */     //   335: sipush #238
/*   */     //   338: iastore
/*   */     //   339: bipush #17
/*   */     //   341: sipush #284
/*   */     //   344: iastore
/*   */     //   345: bipush #18
/*   */     //   347: sipush #336
/*   */     //   350: iastore
/*   */     //   351: bipush #19
/*   */     //   353: sipush #396
/*   */     //   356: iastore
/*   */     //   357: bipush #20
/*   */     //   359: sipush #464
/*   */     //   362: iastore
/*   */     //   363: bipush #21
/*   */     //   365: sipush #522
/*   */     //   368: iastore
/*   */     //   369: bipush #22
/*   */     //   371: sipush #576
/*   */     //   374: iastore
/*   */     //   375: bipush #14
/*   */     //   377: newarray int
/*   */     //   379: dup
/*   */     //   380: dup
/*   */     //   381: dup2
/*   */     //   382: dup2
/*   */     //   383: dup2
/*   */     //   384: dup2
/*   */     //   385: dup2
/*   */     //   386: dup2
/*   */     //   387: astore #8
/*   */     //   389: iconst_0
/*   */     //   390: iconst_0
/*   */     //   391: iastore
/*   */     //   392: iconst_1
/*   */     //   393: iconst_4
/*   */     //   394: iastore
/*   */     //   395: iconst_2
/*   */     //   396: bipush #8
/*   */     //   398: iastore
/*   */     //   399: iconst_3
/*   */     //   400: bipush #12
/*   */     //   402: iastore
/*   */     //   403: iconst_4
/*   */     //   404: bipush #18
/*   */     //   406: iastore
/*   */     //   407: iconst_5
/*   */     //   408: bipush #24
/*   */     //   410: iastore
/*   */     //   411: bipush #6
/*   */     //   413: bipush #32
/*   */     //   415: iastore
/*   */     //   416: bipush #7
/*   */     //   418: bipush #42
/*   */     //   420: iastore
/*   */     //   421: bipush #8
/*   */     //   423: bipush #56
/*   */     //   425: iastore
/*   */     //   426: bipush #9
/*   */     //   428: bipush #74
/*   */     //   430: iastore
/*   */     //   431: bipush #10
/*   */     //   433: bipush #100
/*   */     //   435: iastore
/*   */     //   436: bipush #11
/*   */     //   438: sipush #132
/*   */     //   441: iastore
/*   */     //   442: bipush #12
/*   */     //   444: sipush #174
/*   */     //   447: iastore
/*   */     //   448: bipush #13
/*   */     //   450: sipush #192
/*   */     //   453: iastore
/*   */     //   454: bipush #23
/*   */     //   456: newarray int
/*   */     //   458: dup
/*   */     //   459: dup2
/*   */     //   460: dup2
/*   */     //   461: dup2
/*   */     //   462: dup2
/*   */     //   463: dup2
/*   */     //   464: dup2
/*   */     //   465: dup2
/*   */     //   466: dup2
/*   */     //   467: dup2
/*   */     //   468: dup2
/*   */     //   469: dup2
/*   */     //   470: astore #9
/*   */     //   472: iconst_0
/*   */     //   473: iconst_0
/*   */     //   474: iastore
/*   */     //   475: iconst_1
/*   */     //   476: bipush #6
/*   */     //   478: iastore
/*   */     //   479: iconst_2
/*   */     //   480: bipush #12
/*   */     //   482: iastore
/*   */     //   483: iconst_3
/*   */     //   484: bipush #18
/*   */     //   486: iastore
/*   */     //   487: iconst_4
/*   */     //   488: bipush #24
/*   */     //   490: iastore
/*   */     //   491: iconst_5
/*   */     //   492: bipush #30
/*   */     //   494: iastore
/*   */     //   495: bipush #6
/*   */     //   497: bipush #36
/*   */     //   499: iastore
/*   */     //   500: bipush #7
/*   */     //   502: bipush #44
/*   */     //   504: iastore
/*   */     //   505: bipush #8
/*   */     //   507: bipush #54
/*   */     //   509: iastore
/*   */     //   510: bipush #9
/*   */     //   512: bipush #66
/*   */     //   514: iastore
/*   */     //   515: bipush #10
/*   */     //   517: bipush #80
/*   */     //   519: iastore
/*   */     //   520: bipush #11
/*   */     //   522: bipush #96
/*   */     //   524: iastore
/*   */     //   525: bipush #12
/*   */     //   527: bipush #114
/*   */     //   529: iastore
/*   */     //   530: bipush #13
/*   */     //   532: sipush #136
/*   */     //   535: iastore
/*   */     //   536: bipush #14
/*   */     //   538: sipush #162
/*   */     //   541: iastore
/*   */     //   542: bipush #15
/*   */     //   544: sipush #194
/*   */     //   547: iastore
/*   */     //   548: bipush #16
/*   */     //   550: sipush #232
/*   */     //   553: iastore
/*   */     //   554: bipush #17
/*   */     //   556: sipush #278
/*   */     //   559: iastore
/*   */     //   560: bipush #18
/*   */     //   562: sipush #330
/*   */     //   565: iastore
/*   */     //   566: bipush #19
/*   */     //   568: sipush #394
/*   */     //   571: iastore
/*   */     //   572: bipush #20
/*   */     //   574: sipush #464
/*   */     //   577: iastore
/*   */     //   578: bipush #21
/*   */     //   580: sipush #540
/*   */     //   583: iastore
/*   */     //   584: bipush #22
/*   */     //   586: sipush #576
/*   */     //   589: iastore
/*   */     //   590: bipush #14
/*   */     //   592: newarray int
/*   */     //   594: dup
/*   */     //   595: dup
/*   */     //   596: dup2
/*   */     //   597: dup2
/*   */     //   598: dup2
/*   */     //   599: dup2
/*   */     //   600: dup2
/*   */     //   601: dup2
/*   */     //   602: astore #10
/*   */     //   604: iconst_0
/*   */     //   605: iconst_0
/*   */     //   606: iastore
/*   */     //   607: iconst_1
/*   */     //   608: iconst_4
/*   */     //   609: iastore
/*   */     //   610: iconst_2
/*   */     //   611: bipush #8
/*   */     //   613: iastore
/*   */     //   614: iconst_3
/*   */     //   615: bipush #12
/*   */     //   617: iastore
/*   */     //   618: iconst_4
/*   */     //   619: bipush #18
/*   */     //   621: iastore
/*   */     //   622: iconst_5
/*   */     //   623: bipush #26
/*   */     //   625: iastore
/*   */     //   626: bipush #6
/*   */     //   628: bipush #36
/*   */     //   630: iastore
/*   */     //   631: bipush #7
/*   */     //   633: bipush #48
/*   */     //   635: iastore
/*   */     //   636: bipush #8
/*   */     //   638: bipush #62
/*   */     //   640: iastore
/*   */     //   641: bipush #9
/*   */     //   643: bipush #80
/*   */     //   645: iastore
/*   */     //   646: bipush #10
/*   */     //   648: bipush #104
/*   */     //   650: iastore
/*   */     //   651: bipush #11
/*   */     //   653: sipush #136
/*   */     //   656: iastore
/*   */     //   657: bipush #12
/*   */     //   659: sipush #180
/*   */     //   662: iastore
/*   */     //   663: bipush #13
/*   */     //   665: sipush #192
/*   */     //   668: iastore
/*   */     //   669: bipush #23
/*   */     //   671: newarray int
/*   */     //   673: dup
/*   */     //   674: dup2
/*   */     //   675: dup2
/*   */     //   676: dup2
/*   */     //   677: dup2
/*   */     //   678: dup2
/*   */     //   679: dup2
/*   */     //   680: dup2
/*   */     //   681: dup2
/*   */     //   682: dup2
/*   */     //   683: dup2
/*   */     //   684: dup2
/*   */     //   685: astore #11
/*   */     //   687: iconst_0
/*   */     //   688: iconst_0
/*   */     //   689: iastore
/*   */     //   690: iconst_1
/*   */     //   691: bipush #6
/*   */     //   693: iastore
/*   */     //   694: iconst_2
/*   */     //   695: bipush #12
/*   */     //   697: iastore
/*   */     //   698: iconst_3
/*   */     //   699: bipush #18
/*   */     //   701: iastore
/*   */     //   702: iconst_4
/*   */     //   703: bipush #24
/*   */     //   705: iastore
/*   */     //   706: iconst_5
/*   */     //   707: bipush #30
/*   */     //   709: iastore
/*   */     //   710: bipush #6
/*   */     //   712: bipush #36
/*   */     //   714: iastore
/*   */     //   715: bipush #7
/*   */     //   717: bipush #44
/*   */     //   719: iastore
/*   */     //   720: bipush #8
/*   */     //   722: bipush #54
/*   */     //   724: iastore
/*   */     //   725: bipush #9
/*   */     //   727: bipush #66
/*   */     //   729: iastore
/*   */     //   730: bipush #10
/*   */     //   732: bipush #80
/*   */     //   734: iastore
/*   */     //   735: bipush #11
/*   */     //   737: bipush #96
/*   */     //   739: iastore
/*   */     //   740: bipush #12
/*   */     //   742: bipush #116
/*   */     //   744: iastore
/*   */     //   745: bipush #13
/*   */     //   747: sipush #140
/*   */     //   750: iastore
/*   */     //   751: bipush #14
/*   */     //   753: sipush #168
/*   */     //   756: iastore
/*   */     //   757: bipush #15
/*   */     //   759: sipush #200
/*   */     //   762: iastore
/*   */     //   763: bipush #16
/*   */     //   765: sipush #238
/*   */     //   768: iastore
/*   */     //   769: bipush #17
/*   */     //   771: sipush #284
/*   */     //   774: iastore
/*   */     //   775: bipush #18
/*   */     //   777: sipush #336
/*   */     //   780: iastore
/*   */     //   781: bipush #19
/*   */     //   783: sipush #396
/*   */     //   786: iastore
/*   */     //   787: bipush #20
/*   */     //   789: sipush #464
/*   */     //   792: iastore
/*   */     //   793: bipush #21
/*   */     //   795: sipush #522
/*   */     //   798: iastore
/*   */     //   799: bipush #22
/*   */     //   801: sipush #576
/*   */     //   804: iastore
/*   */     //   805: bipush #14
/*   */     //   807: newarray int
/*   */     //   809: dup
/*   */     //   810: dup
/*   */     //   811: dup2
/*   */     //   812: dup2
/*   */     //   813: dup2
/*   */     //   814: dup2
/*   */     //   815: dup2
/*   */     //   816: dup2
/*   */     //   817: astore #12
/*   */     //   819: iconst_0
/*   */     //   820: iconst_0
/*   */     //   821: iastore
/*   */     //   822: iconst_1
/*   */     //   823: iconst_4
/*   */     //   824: iastore
/*   */     //   825: iconst_2
/*   */     //   826: bipush #8
/*   */     //   828: iastore
/*   */     //   829: iconst_3
/*   */     //   830: bipush #12
/*   */     //   832: iastore
/*   */     //   833: iconst_4
/*   */     //   834: bipush #18
/*   */     //   836: iastore
/*   */     //   837: iconst_5
/*   */     //   838: bipush #26
/*   */     //   840: iastore
/*   */     //   841: bipush #6
/*   */     //   843: bipush #36
/*   */     //   845: iastore
/*   */     //   846: bipush #7
/*   */     //   848: bipush #48
/*   */     //   850: iastore
/*   */     //   851: bipush #8
/*   */     //   853: bipush #62
/*   */     //   855: iastore
/*   */     //   856: bipush #9
/*   */     //   858: bipush #80
/*   */     //   860: iastore
/*   */     //   861: bipush #10
/*   */     //   863: bipush #104
/*   */     //   865: iastore
/*   */     //   866: bipush #11
/*   */     //   868: sipush #134
/*   */     //   871: iastore
/*   */     //   872: bipush #12
/*   */     //   874: sipush #174
/*   */     //   877: iastore
/*   */     //   878: bipush #13
/*   */     //   880: sipush #192
/*   */     //   883: iastore
/*   */     //   884: bipush #23
/*   */     //   886: newarray int
/*   */     //   888: dup
/*   */     //   889: dup2
/*   */     //   890: dup2
/*   */     //   891: dup2
/*   */     //   892: dup2
/*   */     //   893: dup2
/*   */     //   894: dup2
/*   */     //   895: dup2
/*   */     //   896: dup2
/*   */     //   897: dup2
/*   */     //   898: dup2
/*   */     //   899: dup2
/*   */     //   900: astore #13
/*   */     //   902: iconst_0
/*   */     //   903: iconst_0
/*   */     //   904: iastore
/*   */     //   905: iconst_1
/*   */     //   906: iconst_4
/*   */     //   907: iastore
/*   */     //   908: iconst_2
/*   */     //   909: bipush #8
/*   */     //   911: iastore
/*   */     //   912: iconst_3
/*   */     //   913: bipush #12
/*   */     //   915: iastore
/*   */     //   916: iconst_4
/*   */     //   917: bipush #16
/*   */     //   919: iastore
/*   */     //   920: iconst_5
/*   */     //   921: bipush #20
/*   */     //   923: iastore
/*   */     //   924: bipush #6
/*   */     //   926: bipush #24
/*   */     //   928: iastore
/*   */     //   929: bipush #7
/*   */     //   931: bipush #30
/*   */     //   933: iastore
/*   */     //   934: bipush #8
/*   */     //   936: bipush #36
/*   */     //   938: iastore
/*   */     //   939: bipush #9
/*   */     //   941: bipush #44
/*   */     //   943: iastore
/*   */     //   944: bipush #10
/*   */     //   946: bipush #52
/*   */     //   948: iastore
/*   */     //   949: bipush #11
/*   */     //   951: bipush #62
/*   */     //   953: iastore
/*   */     //   954: bipush #12
/*   */     //   956: bipush #74
/*   */     //   958: iastore
/*   */     //   959: bipush #13
/*   */     //   961: bipush #90
/*   */     //   963: iastore
/*   */     //   964: bipush #14
/*   */     //   966: bipush #110
/*   */     //   968: iastore
/*   */     //   969: bipush #15
/*   */     //   971: sipush #134
/*   */     //   974: iastore
/*   */     //   975: bipush #16
/*   */     //   977: sipush #162
/*   */     //   980: iastore
/*   */     //   981: bipush #17
/*   */     //   983: sipush #196
/*   */     //   986: iastore
/*   */     //   987: bipush #18
/*   */     //   989: sipush #238
/*   */     //   992: iastore
/*   */     //   993: bipush #19
/*   */     //   995: sipush #288
/*   */     //   998: iastore
/*   */     //   999: bipush #20
/*   */     //   1001: sipush #342
/*   */     //   1004: iastore
/*   */     //   1005: bipush #21
/*   */     //   1007: sipush #418
/*   */     //   1010: iastore
/*   */     //   1011: bipush #22
/*   */     //   1013: sipush #576
/*   */     //   1016: iastore
/*   */     //   1017: bipush #14
/*   */     //   1019: newarray int
/*   */     //   1021: dup
/*   */     //   1022: dup
/*   */     //   1023: dup2
/*   */     //   1024: dup2
/*   */     //   1025: dup2
/*   */     //   1026: dup2
/*   */     //   1027: dup2
/*   */     //   1028: dup2
/*   */     //   1029: astore #14
/*   */     //   1031: iconst_0
/*   */     //   1032: iconst_0
/*   */     //   1033: iastore
/*   */     //   1034: iconst_1
/*   */     //   1035: iconst_4
/*   */     //   1036: iastore
/*   */     //   1037: iconst_2
/*   */     //   1038: bipush #8
/*   */     //   1040: iastore
/*   */     //   1041: iconst_3
/*   */     //   1042: bipush #12
/*   */     //   1044: iastore
/*   */     //   1045: iconst_4
/*   */     //   1046: bipush #16
/*   */     //   1048: iastore
/*   */     //   1049: iconst_5
/*   */     //   1050: bipush #22
/*   */     //   1052: iastore
/*   */     //   1053: bipush #6
/*   */     //   1055: bipush #30
/*   */     //   1057: iastore
/*   */     //   1058: bipush #7
/*   */     //   1060: bipush #40
/*   */     //   1062: iastore
/*   */     //   1063: bipush #8
/*   */     //   1065: bipush #52
/*   */     //   1067: iastore
/*   */     //   1068: bipush #9
/*   */     //   1070: bipush #66
/*   */     //   1072: iastore
/*   */     //   1073: bipush #10
/*   */     //   1075: bipush #84
/*   */     //   1077: iastore
/*   */     //   1078: bipush #11
/*   */     //   1080: bipush #106
/*   */     //   1082: iastore
/*   */     //   1083: bipush #12
/*   */     //   1085: sipush #136
/*   */     //   1088: iastore
/*   */     //   1089: bipush #13
/*   */     //   1091: sipush #192
/*   */     //   1094: iastore
/*   */     //   1095: bipush #23
/*   */     //   1097: newarray int
/*   */     //   1099: dup
/*   */     //   1100: dup2
/*   */     //   1101: dup2
/*   */     //   1102: dup2
/*   */     //   1103: dup2
/*   */     //   1104: dup2
/*   */     //   1105: dup2
/*   */     //   1106: dup2
/*   */     //   1107: dup2
/*   */     //   1108: dup2
/*   */     //   1109: dup2
/*   */     //   1110: dup2
/*   */     //   1111: astore #15
/*   */     //   1113: iconst_0
/*   */     //   1114: iconst_0
/*   */     //   1115: iastore
/*   */     //   1116: iconst_1
/*   */     //   1117: iconst_4
/*   */     //   1118: iastore
/*   */     //   1119: iconst_2
/*   */     //   1120: bipush #8
/*   */     //   1122: iastore
/*   */     //   1123: iconst_3
/*   */     //   1124: bipush #12
/*   */     //   1126: iastore
/*   */     //   1127: iconst_4
/*   */     //   1128: bipush #16
/*   */     //   1130: iastore
/*   */     //   1131: iconst_5
/*   */     //   1132: bipush #20
/*   */     //   1134: iastore
/*   */     //   1135: bipush #6
/*   */     //   1137: bipush #24
/*   */     //   1139: iastore
/*   */     //   1140: bipush #7
/*   */     //   1142: bipush #30
/*   */     //   1144: iastore
/*   */     //   1145: bipush #8
/*   */     //   1147: bipush #36
/*   */     //   1149: iastore
/*   */     //   1150: bipush #9
/*   */     //   1152: bipush #42
/*   */     //   1154: iastore
/*   */     //   1155: bipush #10
/*   */     //   1157: bipush #50
/*   */     //   1159: iastore
/*   */     //   1160: bipush #11
/*   */     //   1162: bipush #60
/*   */     //   1164: iastore
/*   */     //   1165: bipush #12
/*   */     //   1167: bipush #72
/*   */     //   1169: iastore
/*   */     //   1170: bipush #13
/*   */     //   1172: bipush #88
/*   */     //   1174: iastore
/*   */     //   1175: bipush #14
/*   */     //   1177: bipush #106
/*   */     //   1179: iastore
/*   */     //   1180: bipush #15
/*   */     //   1182: sipush #128
/*   */     //   1185: iastore
/*   */     //   1186: bipush #16
/*   */     //   1188: sipush #156
/*   */     //   1191: iastore
/*   */     //   1192: bipush #17
/*   */     //   1194: sipush #190
/*   */     //   1197: iastore
/*   */     //   1198: bipush #18
/*   */     //   1200: sipush #230
/*   */     //   1203: iastore
/*   */     //   1204: bipush #19
/*   */     //   1206: sipush #276
/*   */     //   1209: iastore
/*   */     //   1210: bipush #20
/*   */     //   1212: sipush #330
/*   */     //   1215: iastore
/*   */     //   1216: bipush #21
/*   */     //   1218: sipush #384
/*   */     //   1221: iastore
/*   */     //   1222: bipush #22
/*   */     //   1224: sipush #576
/*   */     //   1227: iastore
/*   */     //   1228: bipush #14
/*   */     //   1230: newarray int
/*   */     //   1232: dup
/*   */     //   1233: dup
/*   */     //   1234: dup2
/*   */     //   1235: dup2
/*   */     //   1236: dup2
/*   */     //   1237: dup2
/*   */     //   1238: dup2
/*   */     //   1239: dup2
/*   */     //   1240: astore #16
/*   */     //   1242: iconst_0
/*   */     //   1243: iconst_0
/*   */     //   1244: iastore
/*   */     //   1245: iconst_1
/*   */     //   1246: iconst_4
/*   */     //   1247: iastore
/*   */     //   1248: iconst_2
/*   */     //   1249: bipush #8
/*   */     //   1251: iastore
/*   */     //   1252: iconst_3
/*   */     //   1253: bipush #12
/*   */     //   1255: iastore
/*   */     //   1256: iconst_4
/*   */     //   1257: bipush #16
/*   */     //   1259: iastore
/*   */     //   1260: iconst_5
/*   */     //   1261: bipush #22
/*   */     //   1263: iastore
/*   */     //   1264: bipush #6
/*   */     //   1266: bipush #28
/*   */     //   1268: iastore
/*   */     //   1269: bipush #7
/*   */     //   1271: bipush #38
/*   */     //   1273: iastore
/*   */     //   1274: bipush #8
/*   */     //   1276: bipush #50
/*   */     //   1278: iastore
/*   */     //   1279: bipush #9
/*   */     //   1281: bipush #64
/*   */     //   1283: iastore
/*   */     //   1284: bipush #10
/*   */     //   1286: bipush #80
/*   */     //   1288: iastore
/*   */     //   1289: bipush #11
/*   */     //   1291: bipush #100
/*   */     //   1293: iastore
/*   */     //   1294: bipush #12
/*   */     //   1296: bipush #126
/*   */     //   1298: iastore
/*   */     //   1299: bipush #13
/*   */     //   1301: sipush #192
/*   */     //   1304: iastore
/*   */     //   1305: bipush #23
/*   */     //   1307: newarray int
/*   */     //   1309: dup
/*   */     //   1310: dup2
/*   */     //   1311: dup2
/*   */     //   1312: dup2
/*   */     //   1313: dup2
/*   */     //   1314: dup2
/*   */     //   1315: dup2
/*   */     //   1316: dup2
/*   */     //   1317: dup2
/*   */     //   1318: dup2
/*   */     //   1319: dup2
/*   */     //   1320: dup2
/*   */     //   1321: astore #17
/*   */     //   1323: iconst_0
/*   */     //   1324: iconst_0
/*   */     //   1325: iastore
/*   */     //   1326: iconst_1
/*   */     //   1327: iconst_4
/*   */     //   1328: iastore
/*   */     //   1329: iconst_2
/*   */     //   1330: bipush #8
/*   */     //   1332: iastore
/*   */     //   1333: iconst_3
/*   */     //   1334: bipush #12
/*   */     //   1336: iastore
/*   */     //   1337: iconst_4
/*   */     //   1338: bipush #16
/*   */     //   1340: iastore
/*   */     //   1341: iconst_5
/*   */     //   1342: bipush #20
/*   */     //   1344: iastore
/*   */     //   1345: bipush #6
/*   */     //   1347: bipush #24
/*   */     //   1349: iastore
/*   */     //   1350: bipush #7
/*   */     //   1352: bipush #30
/*   */     //   1354: iastore
/*   */     //   1355: bipush #8
/*   */     //   1357: bipush #36
/*   */     //   1359: iastore
/*   */     //   1360: bipush #9
/*   */     //   1362: bipush #44
/*   */     //   1364: iastore
/*   */     //   1365: bipush #10
/*   */     //   1367: bipush #54
/*   */     //   1369: iastore
/*   */     //   1370: bipush #11
/*   */     //   1372: bipush #66
/*   */     //   1374: iastore
/*   */     //   1375: bipush #12
/*   */     //   1377: bipush #82
/*   */     //   1379: iastore
/*   */     //   1380: bipush #13
/*   */     //   1382: bipush #102
/*   */     //   1384: iastore
/*   */     //   1385: bipush #14
/*   */     //   1387: bipush #126
/*   */     //   1389: iastore
/*   */     //   1390: bipush #15
/*   */     //   1392: sipush #156
/*   */     //   1395: iastore
/*   */     //   1396: bipush #16
/*   */     //   1398: sipush #194
/*   */     //   1401: iastore
/*   */     //   1402: bipush #17
/*   */     //   1404: sipush #240
/*   */     //   1407: iastore
/*   */     //   1408: bipush #18
/*   */     //   1410: sipush #296
/*   */     //   1413: iastore
/*   */     //   1414: bipush #19
/*   */     //   1416: sipush #364
/*   */     //   1419: iastore
/*   */     //   1420: bipush #20
/*   */     //   1422: sipush #448
/*   */     //   1425: iastore
/*   */     //   1426: bipush #21
/*   */     //   1428: sipush #550
/*   */     //   1431: iastore
/*   */     //   1432: bipush #22
/*   */     //   1434: sipush #576
/*   */     //   1437: iastore
/*   */     //   1438: bipush #14
/*   */     //   1440: newarray int
/*   */     //   1442: dup
/*   */     //   1443: dup
/*   */     //   1444: dup2
/*   */     //   1445: dup2
/*   */     //   1446: dup2
/*   */     //   1447: dup2
/*   */     //   1448: dup2
/*   */     //   1449: dup2
/*   */     //   1450: astore #18
/*   */     //   1452: iconst_0
/*   */     //   1453: iconst_0
/*   */     //   1454: iastore
/*   */     //   1455: iconst_1
/*   */     //   1456: iconst_4
/*   */     //   1457: iastore
/*   */     //   1458: iconst_2
/*   */     //   1459: bipush #8
/*   */     //   1461: iastore
/*   */     //   1462: iconst_3
/*   */     //   1463: bipush #12
/*   */     //   1465: iastore
/*   */     //   1466: iconst_4
/*   */     //   1467: bipush #16
/*   */     //   1469: iastore
/*   */     //   1470: iconst_5
/*   */     //   1471: bipush #22
/*   */     //   1473: iastore
/*   */     //   1474: bipush #6
/*   */     //   1476: bipush #30
/*   */     //   1478: iastore
/*   */     //   1479: bipush #7
/*   */     //   1481: bipush #42
/*   */     //   1483: iastore
/*   */     //   1484: bipush #8
/*   */     //   1486: bipush #58
/*   */     //   1488: iastore
/*   */     //   1489: bipush #9
/*   */     //   1491: bipush #78
/*   */     //   1493: iastore
/*   */     //   1494: bipush #10
/*   */     //   1496: bipush #104
/*   */     //   1498: iastore
/*   */     //   1499: bipush #11
/*   */     //   1501: sipush #138
/*   */     //   1504: iastore
/*   */     //   1505: bipush #12
/*   */     //   1507: sipush #180
/*   */     //   1510: iastore
/*   */     //   1511: bipush #13
/*   */     //   1513: sipush #192
/*   */     //   1516: iastore
/*   */     //   1517: bipush #23
/*   */     //   1519: newarray int
/*   */     //   1521: dup
/*   */     //   1522: dup2
/*   */     //   1523: dup2
/*   */     //   1524: dup2
/*   */     //   1525: dup2
/*   */     //   1526: dup2
/*   */     //   1527: dup2
/*   */     //   1528: dup2
/*   */     //   1529: dup2
/*   */     //   1530: dup2
/*   */     //   1531: dup2
/*   */     //   1532: dup2
/*   */     //   1533: astore #19
/*   */     //   1535: iconst_0
/*   */     //   1536: iconst_0
/*   */     //   1537: iastore
/*   */     //   1538: iconst_1
/*   */     //   1539: bipush #6
/*   */     //   1541: iastore
/*   */     //   1542: iconst_2
/*   */     //   1543: bipush #12
/*   */     //   1545: iastore
/*   */     //   1546: iconst_3
/*   */     //   1547: bipush #18
/*   */     //   1549: iastore
/*   */     //   1550: iconst_4
/*   */     //   1551: bipush #24
/*   */     //   1553: iastore
/*   */     //   1554: iconst_5
/*   */     //   1555: bipush #30
/*   */     //   1557: iastore
/*   */     //   1558: bipush #6
/*   */     //   1560: bipush #36
/*   */     //   1562: iastore
/*   */     //   1563: bipush #7
/*   */     //   1565: bipush #44
/*   */     //   1567: iastore
/*   */     //   1568: bipush #8
/*   */     //   1570: bipush #54
/*   */     //   1572: iastore
/*   */     //   1573: bipush #9
/*   */     //   1575: bipush #66
/*   */     //   1577: iastore
/*   */     //   1578: bipush #10
/*   */     //   1580: bipush #80
/*   */     //   1582: iastore
/*   */     //   1583: bipush #11
/*   */     //   1585: bipush #96
/*   */     //   1587: iastore
/*   */     //   1588: bipush #12
/*   */     //   1590: bipush #116
/*   */     //   1592: iastore
/*   */     //   1593: bipush #13
/*   */     //   1595: sipush #140
/*   */     //   1598: iastore
/*   */     //   1599: bipush #14
/*   */     //   1601: sipush #168
/*   */     //   1604: iastore
/*   */     //   1605: bipush #15
/*   */     //   1607: sipush #200
/*   */     //   1610: iastore
/*   */     //   1611: bipush #16
/*   */     //   1613: sipush #238
/*   */     //   1616: iastore
/*   */     //   1617: bipush #17
/*   */     //   1619: sipush #284
/*   */     //   1622: iastore
/*   */     //   1623: bipush #18
/*   */     //   1625: sipush #336
/*   */     //   1628: iastore
/*   */     //   1629: bipush #19
/*   */     //   1631: sipush #396
/*   */     //   1634: iastore
/*   */     //   1635: bipush #20
/*   */     //   1637: sipush #464
/*   */     //   1640: iastore
/*   */     //   1641: bipush #21
/*   */     //   1643: sipush #522
/*   */     //   1646: iastore
/*   */     //   1647: bipush #22
/*   */     //   1649: sipush #576
/*   */     //   1652: iastore
/*   */     //   1653: bipush #14
/*   */     //   1655: newarray int
/*   */     //   1657: dup
/*   */     //   1658: dup
/*   */     //   1659: dup2
/*   */     //   1660: dup2
/*   */     //   1661: dup2
/*   */     //   1662: dup2
/*   */     //   1663: dup2
/*   */     //   1664: dup2
/*   */     //   1665: astore #20
/*   */     //   1667: iconst_0
/*   */     //   1668: iconst_0
/*   */     //   1669: iastore
/*   */     //   1670: iconst_1
/*   */     //   1671: iconst_4
/*   */     //   1672: iastore
/*   */     //   1673: iconst_2
/*   */     //   1674: bipush #8
/*   */     //   1676: iastore
/*   */     //   1677: iconst_3
/*   */     //   1678: bipush #12
/*   */     //   1680: iastore
/*   */     //   1681: iconst_4
/*   */     //   1682: bipush #18
/*   */     //   1684: iastore
/*   */     //   1685: iconst_5
/*   */     //   1686: bipush #26
/*   */     //   1688: iastore
/*   */     //   1689: bipush #6
/*   */     //   1691: bipush #36
/*   */     //   1693: iastore
/*   */     //   1694: bipush #7
/*   */     //   1696: bipush #48
/*   */     //   1698: iastore
/*   */     //   1699: bipush #8
/*   */     //   1701: bipush #62
/*   */     //   1703: iastore
/*   */     //   1704: bipush #9
/*   */     //   1706: bipush #80
/*   */     //   1708: iastore
/*   */     //   1709: bipush #10
/*   */     //   1711: bipush #104
/*   */     //   1713: iastore
/*   */     //   1714: bipush #11
/*   */     //   1716: sipush #134
/*   */     //   1719: iastore
/*   */     //   1720: bipush #12
/*   */     //   1722: sipush #174
/*   */     //   1725: iastore
/*   */     //   1726: bipush #13
/*   */     //   1728: sipush #192
/*   */     //   1731: iastore
/*   */     //   1732: bipush #23
/*   */     //   1734: newarray int
/*   */     //   1736: dup
/*   */     //   1737: dup2
/*   */     //   1738: dup2
/*   */     //   1739: dup2
/*   */     //   1740: dup2
/*   */     //   1741: dup2
/*   */     //   1742: dup2
/*   */     //   1743: dup2
/*   */     //   1744: dup2
/*   */     //   1745: dup2
/*   */     //   1746: dup2
/*   */     //   1747: dup2
/*   */     //   1748: astore #21
/*   */     //   1750: iconst_0
/*   */     //   1751: iconst_0
/*   */     //   1752: iastore
/*   */     //   1753: iconst_1
/*   */     //   1754: bipush #6
/*   */     //   1756: iastore
/*   */     //   1757: iconst_2
/*   */     //   1758: bipush #12
/*   */     //   1760: iastore
/*   */     //   1761: iconst_3
/*   */     //   1762: bipush #18
/*   */     //   1764: iastore
/*   */     //   1765: iconst_4
/*   */     //   1766: bipush #24
/*   */     //   1768: iastore
/*   */     //   1769: iconst_5
/*   */     //   1770: bipush #30
/*   */     //   1772: iastore
/*   */     //   1773: bipush #6
/*   */     //   1775: bipush #36
/*   */     //   1777: iastore
/*   */     //   1778: bipush #7
/*   */     //   1780: bipush #44
/*   */     //   1782: iastore
/*   */     //   1783: bipush #8
/*   */     //   1785: bipush #54
/*   */     //   1787: iastore
/*   */     //   1788: bipush #9
/*   */     //   1790: bipush #66
/*   */     //   1792: iastore
/*   */     //   1793: bipush #10
/*   */     //   1795: bipush #80
/*   */     //   1797: iastore
/*   */     //   1798: bipush #11
/*   */     //   1800: bipush #96
/*   */     //   1802: iastore
/*   */     //   1803: bipush #12
/*   */     //   1805: bipush #116
/*   */     //   1807: iastore
/*   */     //   1808: bipush #13
/*   */     //   1810: sipush #140
/*   */     //   1813: iastore
/*   */     //   1814: bipush #14
/*   */     //   1816: sipush #168
/*   */     //   1819: iastore
/*   */     //   1820: bipush #15
/*   */     //   1822: sipush #200
/*   */     //   1825: iastore
/*   */     //   1826: bipush #16
/*   */     //   1828: sipush #238
/*   */     //   1831: iastore
/*   */     //   1832: bipush #17
/*   */     //   1834: sipush #284
/*   */     //   1837: iastore
/*   */     //   1838: bipush #18
/*   */     //   1840: sipush #336
/*   */     //   1843: iastore
/*   */     //   1844: bipush #19
/*   */     //   1846: sipush #396
/*   */     //   1849: iastore
/*   */     //   1850: bipush #20
/*   */     //   1852: sipush #464
/*   */     //   1855: iastore
/*   */     //   1856: bipush #21
/*   */     //   1858: sipush #522
/*   */     //   1861: iastore
/*   */     //   1862: bipush #22
/*   */     //   1864: sipush #576
/*   */     //   1867: iastore
/*   */     //   1868: bipush #14
/*   */     //   1870: newarray int
/*   */     //   1872: dup
/*   */     //   1873: dup
/*   */     //   1874: dup2
/*   */     //   1875: dup2
/*   */     //   1876: dup2
/*   */     //   1877: dup2
/*   */     //   1878: dup2
/*   */     //   1879: dup2
/*   */     //   1880: astore #22
/*   */     //   1882: iconst_0
/*   */     //   1883: iconst_0
/*   */     //   1884: iastore
/*   */     //   1885: iconst_1
/*   */     //   1886: iconst_4
/*   */     //   1887: iastore
/*   */     //   1888: iconst_2
/*   */     //   1889: bipush #8
/*   */     //   1891: iastore
/*   */     //   1892: iconst_3
/*   */     //   1893: bipush #12
/*   */     //   1895: iastore
/*   */     //   1896: iconst_4
/*   */     //   1897: bipush #18
/*   */     //   1899: iastore
/*   */     //   1900: iconst_5
/*   */     //   1901: bipush #26
/*   */     //   1903: iastore
/*   */     //   1904: bipush #6
/*   */     //   1906: bipush #36
/*   */     //   1908: iastore
/*   */     //   1909: bipush #7
/*   */     //   1911: bipush #48
/*   */     //   1913: iastore
/*   */     //   1914: bipush #8
/*   */     //   1916: bipush #62
/*   */     //   1918: iastore
/*   */     //   1919: bipush #9
/*   */     //   1921: bipush #80
/*   */     //   1923: iastore
/*   */     //   1924: bipush #10
/*   */     //   1926: bipush #104
/*   */     //   1928: iastore
/*   */     //   1929: bipush #11
/*   */     //   1931: sipush #134
/*   */     //   1934: iastore
/*   */     //   1935: bipush #12
/*   */     //   1937: sipush #174
/*   */     //   1940: iastore
/*   */     //   1941: bipush #13
/*   */     //   1943: sipush #192
/*   */     //   1946: iastore
/*   */     //   1947: bipush #23
/*   */     //   1949: newarray int
/*   */     //   1951: dup
/*   */     //   1952: dup2
/*   */     //   1953: dup2
/*   */     //   1954: dup2
/*   */     //   1955: dup2
/*   */     //   1956: dup2
/*   */     //   1957: dup2
/*   */     //   1958: dup2
/*   */     //   1959: dup2
/*   */     //   1960: dup2
/*   */     //   1961: dup2
/*   */     //   1962: dup2
/*   */     //   1963: astore #23
/*   */     //   1965: iconst_0
/*   */     //   1966: iconst_0
/*   */     //   1967: iastore
/*   */     //   1968: iconst_1
/*   */     //   1969: bipush #12
/*   */     //   1971: iastore
/*   */     //   1972: iconst_2
/*   */     //   1973: bipush #24
/*   */     //   1975: iastore
/*   */     //   1976: iconst_3
/*   */     //   1977: bipush #36
/*   */     //   1979: iastore
/*   */     //   1980: iconst_4
/*   */     //   1981: bipush #48
/*   */     //   1983: iastore
/*   */     //   1984: iconst_5
/*   */     //   1985: bipush #60
/*   */     //   1987: iastore
/*   */     //   1988: bipush #6
/*   */     //   1990: bipush #72
/*   */     //   1992: iastore
/*   */     //   1993: bipush #7
/*   */     //   1995: bipush #88
/*   */     //   1997: iastore
/*   */     //   1998: bipush #8
/*   */     //   2000: bipush #108
/*   */     //   2002: iastore
/*   */     //   2003: bipush #9
/*   */     //   2005: sipush #132
/*   */     //   2008: iastore
/*   */     //   2009: bipush #10
/*   */     //   2011: sipush #160
/*   */     //   2014: iastore
/*   */     //   2015: bipush #11
/*   */     //   2017: sipush #192
/*   */     //   2020: iastore
/*   */     //   2021: bipush #12
/*   */     //   2023: sipush #232
/*   */     //   2026: iastore
/*   */     //   2027: bipush #13
/*   */     //   2029: sipush #280
/*   */     //   2032: iastore
/*   */     //   2033: bipush #14
/*   */     //   2035: sipush #336
/*   */     //   2038: iastore
/*   */     //   2039: bipush #15
/*   */     //   2041: sipush #400
/*   */     //   2044: iastore
/*   */     //   2045: bipush #16
/*   */     //   2047: sipush #476
/*   */     //   2050: iastore
/*   */     //   2051: bipush #17
/*   */     //   2053: sipush #566
/*   */     //   2056: iastore
/*   */     //   2057: bipush #18
/*   */     //   2059: sipush #568
/*   */     //   2062: iastore
/*   */     //   2063: bipush #19
/*   */     //   2065: sipush #570
/*   */     //   2068: iastore
/*   */     //   2069: bipush #20
/*   */     //   2071: sipush #572
/*   */     //   2074: iastore
/*   */     //   2075: bipush #21
/*   */     //   2077: sipush #574
/*   */     //   2080: iastore
/*   */     //   2081: bipush #22
/*   */     //   2083: sipush #576
/*   */     //   2086: iastore
/*   */     //   2087: bipush #14
/*   */     //   2089: newarray int
/*   */     //   2091: dup
/*   */     //   2092: dup
/*   */     //   2093: dup2
/*   */     //   2094: dup2
/*   */     //   2095: dup2
/*   */     //   2096: dup2
/*   */     //   2097: dup2
/*   */     //   2098: dup2
/*   */     //   2099: astore #24
/*   */     //   2101: iconst_0
/*   */     //   2102: iconst_0
/*   */     //   2103: iastore
/*   */     //   2104: iconst_1
/*   */     //   2105: bipush #8
/*   */     //   2107: iastore
/*   */     //   2108: iconst_2
/*   */     //   2109: bipush #16
/*   */     //   2111: iastore
/*   */     //   2112: iconst_3
/*   */     //   2113: bipush #24
/*   */     //   2115: iastore
/*   */     //   2116: iconst_4
/*   */     //   2117: bipush #36
/*   */     //   2119: iastore
/*   */     //   2120: iconst_5
/*   */     //   2121: bipush #52
/*   */     //   2123: iastore
/*   */     //   2124: bipush #6
/*   */     //   2126: bipush #72
/*   */     //   2128: iastore
/*   */     //   2129: bipush #7
/*   */     //   2131: bipush #96
/*   */     //   2133: iastore
/*   */     //   2134: bipush #8
/*   */     //   2136: bipush #124
/*   */     //   2138: iastore
/*   */     //   2139: bipush #9
/*   */     //   2141: sipush #160
/*   */     //   2144: iastore
/*   */     //   2145: bipush #10
/*   */     //   2147: sipush #162
/*   */     //   2150: iastore
/*   */     //   2151: bipush #11
/*   */     //   2153: sipush #164
/*   */     //   2156: iastore
/*   */     //   2157: bipush #12
/*   */     //   2159: sipush #166
/*   */     //   2162: iastore
/*   */     //   2163: bipush #13
/*   */     //   2165: sipush #192
/*   */     //   2168: iastore
/*   */     //   2169: new f/xq
/*   */     //   2172: dup
/*   */     //   2173: astore #25
/*   */     //   2175: aload #7
/*   */     //   2177: aload #8
/*   */     //   2179: invokespecial <init> : ([I[I)V
/*   */     //   2182: iconst_0
/*   */     //   2183: aload #25
/*   */     //   2185: aastore
/*   */     //   2186: new f/xq
/*   */     //   2189: dup
/*   */     //   2190: astore #7
/*   */     //   2192: aload #9
/*   */     //   2194: aload #10
/*   */     //   2196: invokespecial <init> : ([I[I)V
/*   */     //   2199: iconst_1
/*   */     //   2200: aload #7
/*   */     //   2202: aastore
/*   */     //   2203: new f/xq
/*   */     //   2206: dup
/*   */     //   2207: astore #7
/*   */     //   2209: aload #11
/*   */     //   2211: aload #12
/*   */     //   2213: invokespecial <init> : ([I[I)V
/*   */     //   2216: iconst_2
/*   */     //   2217: aload #7
/*   */     //   2219: aastore
/*   */     //   2220: new f/xq
/*   */     //   2223: dup
/*   */     //   2224: astore #7
/*   */     //   2226: aload #13
/*   */     //   2228: aload #14
/*   */     //   2230: invokespecial <init> : ([I[I)V
/*   */     //   2233: iconst_3
/*   */     //   2234: aload #7
/*   */     //   2236: aastore
/*   */     //   2237: new f/xq
/*   */     //   2240: dup
/*   */     //   2241: astore #7
/*   */     //   2243: aload #15
/*   */     //   2245: aload #16
/*   */     //   2247: invokespecial <init> : ([I[I)V
/*   */     //   2250: iconst_4
/*   */     //   2251: aload #7
/*   */     //   2253: aastore
/*   */     //   2254: new f/xq
/*   */     //   2257: dup
/*   */     //   2258: astore #7
/*   */     //   2260: aload #17
/*   */     //   2262: aload #18
/*   */     //   2264: invokespecial <init> : ([I[I)V
/*   */     //   2267: iconst_5
/*   */     //   2268: aload #7
/*   */     //   2270: aastore
/*   */     //   2271: new f/xq
/*   */     //   2274: dup
/*   */     //   2275: astore #7
/*   */     //   2277: aload #19
/*   */     //   2279: aload #20
/*   */     //   2281: invokespecial <init> : ([I[I)V
/*   */     //   2284: bipush #6
/*   */     //   2286: aload #7
/*   */     //   2288: aastore
/*   */     //   2289: new f/xq
/*   */     //   2292: dup
/*   */     //   2293: astore #7
/*   */     //   2295: aload #21
/*   */     //   2297: aload #22
/*   */     //   2299: invokespecial <init> : ([I[I)V
/*   */     //   2302: bipush #7
/*   */     //   2304: aload #7
/*   */     //   2306: aastore
/*   */     //   2307: new f/xq
/*   */     //   2310: dup
/*   */     //   2311: astore #7
/*   */     //   2313: aload #23
/*   */     //   2315: aload #24
/*   */     //   2317: invokespecial <init> : ([I[I)V
/*   */     //   2320: bipush #8
/*   */     //   2322: aload #7
/*   */     //   2324: aastore
/*   */     //   2325: getstatic f/oH.Sa : [[I
/*   */     //   2328: ifnonnull -> 2374
/*   */     //   2331: bipush #9
/*   */     //   2333: anewarray [I
/*   */     //   2336: putstatic f/oH.Sa : [[I
/*   */     //   2339: iconst_0
/*   */     //   2340: istore #7
/*   */     //   2342: iload #7
/*   */     //   2344: bipush #9
/*   */     //   2346: if_icmpge -> 2374
/*   */     //   2349: getstatic f/oH.Sa : [[I
/*   */     //   2352: iload #7
/*   */     //   2354: aload_0
/*   */     //   2355: getfield Dn : [Lf/xq;
/*   */     //   2358: iload #7
/*   */     //   2360: aaload
/*   */     //   2361: getfield eE0 : [I
/*   */     //   2364: invokestatic en0 : ([I)[I
/*   */     //   2367: aastore
/*   */     //   2368: iinc #7, 1
/*   */     //   2371: goto -> 2342
/*   */     //   2374: aload_2
/*   */     //   2375: aload_0
/*   */     //   2376: dup
/*   */     //   2377: iload #6
/*   */     //   2379: aload_0
/*   */     //   2380: aload #5
/*   */     //   2382: aload_0
/*   */     //   2383: aload #4
/*   */     //   2385: aload_0
/*   */     //   2386: aload_3
/*   */     //   2387: aload_0
/*   */     //   2388: aload_2
/*   */     //   2389: aload_0
/*   */     //   2390: aload_1
/*   */     //   2391: aload_0
/*   */     //   2392: bipush #54
/*   */     //   2394: newarray int
/*   */     //   2396: putfield final : [I
/*   */     //   2399: putfield cOm1 : Lf/AH0;
/*   */     //   2402: putfield kO : Lf/Ym0;
/*   */     //   2405: putfield aZ : Lf/Va;
/*   */     //   2408: putfield sD0 : Lf/Va;
/*   */     //   2411: putfield Tn : Lf/qR;
/*   */     //   2414: putfield Fl : I
/*   */     //   2417: iconst_0
/*   */     //   2418: putfield lPt7 : I
/*   */     //   2421: invokevirtual Kb : ()I
/*   */     //   2424: iconst_3
/*   */     //   2425: if_icmpne -> 2433
/*   */     //   2428: iconst_1
/*   */     //   2429: istore_1
/*   */     //   2430: goto -> 2435
/*   */     //   2433: iconst_2
/*   */     //   2434: istore_1
/*   */     //   2435: aload_0
/*   */     //   2436: dup
/*   */     //   2437: iload_1
/*   */     //   2438: putfield Ow0 : I
/*   */     //   2441: getfield kO : Lf/Ym0;
/*   */     //   2444: invokevirtual y9 : ()I
/*   */     //   2447: iconst_1
/*   */     //   2448: if_icmpne -> 2456
/*   */     //   2451: iconst_2
/*   */     //   2452: istore_1
/*   */     //   2453: goto -> 2458
/*   */     //   2456: iconst_1
/*   */     //   2457: istore_1
/*   */     //   2458: aload_0
/*   */     //   2459: dup
/*   */     //   2460: dup
/*   */     //   2461: iload_1
/*   */     //   2462: putfield S70 : I
/*   */     //   2465: getfield kO : Lf/Ym0;
/*   */     //   2468: invokevirtual Gc0 : ()I
/*   */     //   2471: istore_1
/*   */     //   2472: getfield kO : Lf/Ym0;
/*   */     //   2475: invokevirtual y9 : ()I
/*   */     //   2478: iconst_1
/*   */     //   2479: if_icmpne -> 2487
/*   */     //   2482: iconst_3
/*   */     //   2483: istore_2
/*   */     //   2484: goto -> 2506
/*   */     //   2487: aload_0
/*   */     //   2488: getfield kO : Lf/Ym0;
/*   */     //   2491: invokevirtual y9 : ()I
/*   */     //   2494: iconst_2
/*   */     //   2495: if_icmpne -> 2504
/*   */     //   2498: bipush #6
/*   */     //   2500: istore_2
/*   */     //   2501: goto -> 2506
/*   */     //   2504: iconst_0
/*   */     //   2505: istore_2
/*   */     //   2506: aload_0
/*   */     //   2507: dup
/*   */     //   2508: iload_1
/*   */     //   2509: iload_2
/*   */     //   2510: iadd
/*   */     //   2511: putfield IF : I
/*   */     //   2514: getfield Ow0 : I
/*   */     //   2517: iconst_2
/*   */     //   2518: if_icmpne -> 2567
/*   */     //   2521: aload_0
/*   */     //   2522: getfield Fl : I
/*   */     //   2525: dup
/*   */     //   2526: istore_1
/*   */     //   2527: iconst_1
/*   */     //   2528: if_icmpeq -> 2567
/*   */     //   2531: iload_1
/*   */     //   2532: iconst_2
/*   */     //   2533: if_icmpeq -> 2554
/*   */     //   2536: iload_1
/*   */     //   2537: iconst_3
/*   */     //   2538: if_icmpeq -> 2567
/*   */     //   2541: aload_0
/*   */     //   2542: dup
/*   */     //   2543: iconst_0
/*   */     //   2544: putfield HH0 : I
/*   */     //   2547: iconst_1
/*   */     //   2548: putfield Lr0 : I
/*   */     //   2551: goto -> 2577
/*   */     //   2554: aload_0
/*   */     //   2555: dup
/*   */     //   2556: iconst_1
/*   */     //   2557: putfield Lr0 : I
/*   */     //   2560: iconst_1
/*   */     //   2561: putfield HH0 : I
/*   */     //   2564: goto -> 2577
/*   */     //   2567: aload_0
/*   */     //   2568: dup
/*   */     //   2569: iconst_0
/*   */     //   2570: putfield Lr0 : I
/*   */     //   2573: iconst_0
/*   */     //   2574: putfield HH0 : I
/*   */     //   2577: iconst_0
/*   */     //   2578: istore_1
/*   */     //   2579: iload_1
/*   */     //   2580: iconst_2
/*   */     //   2581: if_icmpge -> 2614
/*   */     //   2584: iconst_0
/*   */     //   2585: istore_2
/*   */     //   2586: iload_2
/*   */     //   2587: sipush #576
/*   */     //   2590: if_icmpge -> 2608
/*   */     //   2593: aload_0
/*   */     //   2594: getfield f20 : [[F
/*   */     //   2597: iload_1
/*   */     //   2598: aaload
/*   */     //   2599: iload_2
/*   */     //   2600: fconst_0
/*   */     //   2601: fastore
/*   */     //   2602: iinc #2, 1
/*   */     //   2605: goto -> 2586
/*   */     //   2608: iinc #1, 1
/*   */     //   2611: goto -> 2579
/*   */     //   2614: aload_0
/*   */     //   2615: dup
/*   */     //   2616: dup
/*   */     //   2617: getfield OY : [I
/*   */     //   2620: dup
/*   */     //   2621: iconst_1
/*   */     //   2622: sipush #576
/*   */     //   2625: iastore
/*   */     //   2626: iconst_0
/*   */     //   2627: sipush #576
/*   */     //   2630: iastore
/*   */     //   2631: new f/CC
/*   */     //   2634: dup
/*   */     //   2635: astore_0
/*   */     //   2636: invokespecial <init> : ()V
/*   */     //   2639: aload_0
/*   */     //   2640: putfield Bg : Lf/CC;
/*   */     //   2643: new f/qC0
/*   */     //   2646: dup
/*   */     //   2647: astore_0
/*   */     //   2648: invokespecial <init> : ()V
/*   */     //   2651: aload_0
/*   */     //   2652: putfield oD0 : Lf/qC0;
/*   */     //   2655: return
/*   */   } }


/* Location:              /Users/vnnsnnt/Documents/Codespace/JavaWorkspace/RedTrainer/src/main/java/org/trainer/client/PokeMMO.jar!/f/oH.class
 * Java compiler version: 6 (50.0)
 * JD-Core Version:       1.1.3
 */