/*  1 */ package f;public final class Pe0 { public static final Locale lu0 = new Locale("", "", ""); public Locale AuX; public static Pe0 Qr0(RD0 paramRD0, String paramString, Locale paramLocale) { if (paramRD0 != null && paramLocale != null) { Pe0 pe02, pe01 = null; Locale locale = paramLocale; do { ArrayList<Locale> arrayList; String str1 = locale.getLanguage(), str2 = locale.getCountry(); this(4); if (locale.getVariant().length() > 0) arrayList.add(locale);  if (str2.length() > 0) { Locale locale2; if (arrayList.isEmpty()) { locale2 = locale; } else { this(str1, str2); }  arrayList.add(locale2); }  if (str1.length() > 0) { Locale locale2; if (arrayList.isEmpty()) { locale2 = locale; } else { this(str1); }  arrayList.add(locale2); }  Locale locale1; arrayList.add(locale1 = lu0);
/*  2 */         if ((pe02 = A1(paramRD0, paramString, arrayList, 0, pe01)) != null) {
/*    */           boolean bool; Locale locale2;
/*  4 */           if (!(bool = (locale2 = pe02.AuX).equals(locale1)) || locale2.equals(paramLocale) || (arrayList.size() == 1 && locale2.equals(arrayList.get(0)))) break;  if (bool && pe01 == null) pe01 = pe02; 
/*  5 */         }  if (!locale.equals(locale = Locale.getDefault())) continue;  locale = null; } while (locale != null); if (pe02 == null) if (pe01 != null) { pe02 = pe01; }
/*  6 */         else { throw new MissingResourceException(
/*  7 */               B40.df("Can't find bundle for base file handle ")
/*  8 */               .append(paramRD0.rw()).append(", locale ").append(paramLocale).toString(), paramRD0 + "_" + paramLocale, ""); }   return pe02; }  throw null; } public static Pe0 A1(RD0 paramRD0, String paramString, ArrayList<Locale> paramArrayList, int paramInt, Pe0 paramPe0) { InputStreamReader inputStreamReader; Locale locale = paramArrayList.get(paramInt); Pe0 pe0 = null; if (paramInt != paramArrayList.size() - 1) { pe0 = A1(paramRD0, paramString, paramArrayList, ++paramInt, paramPe0); } else if (paramPe0 != null && locale.equals(lu0)) { return paramPe0; }  paramRD0 = null; paramArrayList = null; try { RD0 rD0; try { (rD0 = Zp0(paramRD0, locale)).Yc().close(); } catch (Exception exception) {} if (false) { Pe0 pe01; this(); InputStream inputStream = rD0.Yc(); try { InputStreamReader inputStreamReader1; this(inputStream, paramString); try { (pe01 = new Pe0()).kX(inputStreamReader1); } catch (IOException iOException) {  } finally { pe01 = null; }  } catch (UnsupportedEncodingException unsupportedEncodingException) { Ui.JC0(inputStream); throw new JU("Error reading file: " + rD0, unsupportedEncodingException); }  }  } catch (IOException iOException) {  } finally {} Ui.JC0(inputStreamReader); if (paramRD0 != null) ((Pe0)paramRD0)
/*  9 */         .AuX = locale; 
/* 10 */     return (Pe0)((paramRD0 != null) ? paramRD0 : pe0); }
/*    */ 
/*    */   
/*    */   public static RD0 Zp0(RD0 paramRD0, Locale paramLocale) {
/*    */     // Byte code:
/*    */     //   0: aload_1
/*    */     //   1: new f/Ag
/*    */     //   4: dup
/*    */     //   5: astore_2
/*    */     //   6: aload_0
/*    */     //   7: getfield ml : Ljava/io/File;
/*    */     //   10: invokevirtual getName : ()Ljava/lang/String;
/*    */     //   13: invokespecial <init> : (Ljava/lang/String;)V
/*    */     //   16: getstatic f/Pe0.lu0 : Ljava/util/Locale;
/*    */     //   19: invokevirtual equals : (Ljava/lang/Object;)Z
/*    */     //   22: ifne -> 142
/*    */     //   25: aload_1
/*    */     //   26: dup
/*    */     //   27: dup
/*    */     //   28: invokevirtual getLanguage : ()Ljava/lang/String;
/*    */     //   31: astore_1
/*    */     //   32: invokevirtual getCountry : ()Ljava/lang/String;
/*    */     //   35: astore_3
/*    */     //   36: invokevirtual getVariant : ()Ljava/lang/String;
/*    */     //   39: astore #4
/*    */     //   41: ldc ''
/*    */     //   43: aload_1
/*    */     //   44: invokevirtual equals : (Ljava/lang/Object;)Z
/*    */     //   47: ldc ''
/*    */     //   49: aload_3
/*    */     //   50: invokevirtual equals : (Ljava/lang/Object;)Z
/*    */     //   53: istore #5
/*    */     //   55: ldc ''
/*    */     //   57: aload #4
/*    */     //   59: invokevirtual equals : (Ljava/lang/Object;)Z
/*    */     //   62: istore #6
/*    */     //   64: ifeq -> 77
/*    */     //   67: iload #5
/*    */     //   69: ifeq -> 77
/*    */     //   72: iload #6
/*    */     //   74: ifne -> 142
/*    */     //   77: iload #6
/*    */     //   79: aload_2
/*    */     //   80: bipush #95
/*    */     //   82: invokevirtual yd0 : (C)V
/*    */     //   85: ifne -> 119
/*    */     //   88: aload_2
/*    */     //   89: aload #4
/*    */     //   91: aload_2
/*    */     //   92: dup
/*    */     //   93: aload_3
/*    */     //   94: aload_2
/*    */     //   95: dup
/*    */     //   96: aload_1
/*    */     //   97: invokevirtual V9 : (Ljava/lang/String;)V
/*    */     //   100: bipush #95
/*    */     //   102: invokevirtual yd0 : (C)V
/*    */     //   105: invokevirtual V9 : (Ljava/lang/String;)V
/*    */     //   108: bipush #95
/*    */     //   110: invokevirtual yd0 : (C)V
/*    */     //   113: invokevirtual V9 : (Ljava/lang/String;)V
/*    */     //   116: goto -> 142
/*    */     //   119: iload #5
/*    */     //   121: ifne -> 137
/*    */     //   124: aload_2
/*    */     //   125: aload_3
/*    */     //   126: aload_2
/*    */     //   127: dup
/*    */     //   128: aload_1
/*    */     //   129: invokevirtual V9 : (Ljava/lang/String;)V
/*    */     //   132: bipush #95
/*    */     //   134: goto -> 110
/*    */     //   137: aload_2
/*    */     //   138: aload_1
/*    */     //   139: invokevirtual V9 : (Ljava/lang/String;)V
/*    */     //   142: aload_0
/*    */     //   143: aload_2
/*    */     //   144: dup
/*    */     //   145: ldc '.properties'
/*    */     //   147: invokevirtual V9 : (Ljava/lang/String;)V
/*    */     //   150: invokevirtual toString : ()Ljava/lang/String;
/*    */     //   153: invokevirtual rB0 : (Ljava/lang/String;)Lf/RD0;
/*    */     //   156: areturn
/*    */     // Line number table:
/*    */     //   Java source line number -> byte code offset
/*    */     //   #1	-> 7
/*    */     //   #2	-> 10
/*    */     //   #3	-> 13
/*    */     //   #4	-> 82
/*    */     //   #5	-> 97
/*    */     //   #6	-> 102
/*    */     //   #7	-> 105
/*    */     //   #8	-> 110
/*    */     //   #9	-> 113
/*    */     //   #10	-> 129
/*    */     //   #11	-> 139
/*    */     //   #12	-> 145
/*    */     //   #13	-> 147
/*    */     //   #14	-> 150
/*    */   }
/*    */   
/*    */   public final void kX(InputStreamReader paramInputStreamReader) {
/*    */     // Byte code:
/*    */     //   0: new f/f7
/*    */     //   3: dup
/*    */     //   4: astore_0
/*    */     //   5: invokespecial <init> : ()V
/*    */     //   8: iconst_0
/*    */     //   9: istore_2
/*    */     //   10: iconst_0
/*    */     //   11: istore_3
/*    */     //   12: iconst_0
/*    */     //   13: istore #4
/*    */     //   15: bipush #40
/*    */     //   17: newarray char
/*    */     //   19: astore #5
/*    */     //   21: iconst_0
/*    */     //   22: istore #6
/*    */     //   24: iconst_m1
/*    */     //   25: istore #7
/*    */     //   27: iconst_1
/*    */     //   28: istore #8
/*    */     //   30: new java/io/BufferedReader
/*    */     //   33: dup
/*    */     //   34: astore #9
/*    */     //   36: aload_1
/*    */     //   37: invokespecial <init> : (Ljava/io/Reader;)V
/*    */     //   40: aload #9
/*    */     //   42: invokevirtual read : ()I
/*    */     //   45: dup
/*    */     //   46: istore_1
/*    */     //   47: iconst_m1
/*    */     //   48: if_icmpne -> 141
/*    */     //   51: iload_2
/*    */     //   52: iconst_2
/*    */     //   53: if_icmpne -> 75
/*    */     //   56: iload #4
/*    */     //   58: iconst_4
/*    */     //   59: if_icmple -> 65
/*    */     //   62: goto -> 75
/*    */     //   65: new java/lang/IllegalArgumentException
/*    */     //   68: dup
/*    */     //   69: ldc 'Invalid Unicode sequence: expected format \uxxxx'
/*    */     //   71: invokespecial <init> : (Ljava/lang/String;)V
/*    */     //   74: athrow
/*    */     //   75: iload #7
/*    */     //   77: iconst_m1
/*    */     //   78: if_icmpne -> 90
/*    */     //   81: iload #6
/*    */     //   83: ifle -> 90
/*    */     //   86: iload #6
/*    */     //   88: istore #7
/*    */     //   90: iload #7
/*    */     //   92: iflt -> 140
/*    */     //   95: iload_2
/*    */     //   96: new java/lang/String
/*    */     //   99: dup
/*    */     //   100: dup
/*    */     //   101: aload #5
/*    */     //   103: iconst_0
/*    */     //   104: iload #6
/*    */     //   106: invokespecial <init> : ([CII)V
/*    */     //   109: iconst_0
/*    */     //   110: iload #7
/*    */     //   112: invokevirtual substring : (II)Ljava/lang/String;
/*    */     //   115: astore_1
/*    */     //   116: iload #7
/*    */     //   118: invokevirtual substring : (I)Ljava/lang/String;
/*    */     //   121: astore_2
/*    */     //   122: iconst_1
/*    */     //   123: if_icmpne -> 133
/*    */     //   126: aload_2
/*    */     //   127: ldc ' '
/*    */     //   129: invokestatic tF0 : (Ljava/lang/String;Ljava/lang/String;)Ljava/lang/String;
/*    */     //   132: astore_2
/*    */     //   133: aload_0
/*    */     //   134: aload_1
/*    */     //   135: aload_2
/*    */     //   136: invokevirtual X00 : (Ljava/lang/Object;Ljava/lang/Object;)Ljava/lang/Object;
/*    */     //   139: pop
/*    */     //   140: return
/*    */     //   141: iload #6
/*    */     //   143: aload #5
/*    */     //   145: iload_1
/*    */     //   146: i2c
/*    */     //   147: istore_1
/*    */     //   148: arraylength
/*    */     //   149: if_icmpne -> 171
/*    */     //   152: aload #5
/*    */     //   154: dup
/*    */     //   155: arraylength
/*    */     //   156: iconst_2
/*    */     //   157: imul
/*    */     //   158: newarray char
/*    */     //   160: astore #5
/*    */     //   162: iconst_0
/*    */     //   163: aload #5
/*    */     //   165: iconst_0
/*    */     //   166: iload #6
/*    */     //   168: invokestatic arraycopy : (Ljava/lang/Object;ILjava/lang/Object;II)V
/*    */     //   171: iload_2
/*    */     //   172: iconst_2
/*    */     //   173: if_icmpne -> 261
/*    */     //   176: iload_1
/*    */     //   177: bipush #16
/*    */     //   179: invokestatic digit : (CI)I
/*    */     //   182: dup
/*    */     //   183: istore #10
/*    */     //   185: iflt -> 209
/*    */     //   188: iload_3
/*    */     //   189: iconst_4
/*    */     //   190: ishl
/*    */     //   191: iload #10
/*    */     //   193: iadd
/*    */     //   194: istore_3
/*    */     //   195: iload #4
/*    */     //   197: iconst_1
/*    */     //   198: iadd
/*    */     //   199: dup
/*    */     //   200: istore #4
/*    */     //   202: iconst_4
/*    */     //   203: if_icmpge -> 215
/*    */     //   206: goto -> 40
/*    */     //   209: iload #4
/*    */     //   211: iconst_4
/*    */     //   212: if_icmple -> 251
/*    */     //   215: iload_1
/*    */     //   216: aload #5
/*    */     //   218: iload_3
/*    */     //   219: iconst_0
/*    */     //   220: istore_2
/*    */     //   221: iload #6
/*    */     //   223: iconst_1
/*    */     //   224: iadd
/*    */     //   225: istore #10
/*    */     //   227: i2c
/*    */     //   228: iload #6
/*    */     //   230: swap
/*    */     //   231: castore
/*    */     //   232: bipush #10
/*    */     //   234: if_icmpeq -> 244
/*    */     //   237: iload #10
/*    */     //   239: istore #6
/*    */     //   241: goto -> 40
/*    */     //   244: iload #10
/*    */     //   246: istore #6
/*    */     //   248: goto -> 261
/*    */     //   251: new java/lang/IllegalArgumentException
/*    */     //   254: dup
/*    */     //   255: ldc 'Invalid Unicode sequence: illegal character'
/*    */     //   257: invokespecial <init> : (Ljava/lang/String;)V
/*    */     //   260: athrow
/*    */     //   261: iload_2
/*    */     //   262: iconst_1
/*    */     //   263: if_icmpne -> 365
/*    */     //   266: iload_1
/*    */     //   267: iconst_0
/*    */     //   268: istore_2
/*    */     //   269: bipush #10
/*    */     //   271: if_icmpeq -> 571
/*    */     //   274: iload_1
/*    */     //   275: bipush #13
/*    */     //   277: if_icmpeq -> 360
/*    */     //   280: iload_1
/*    */     //   281: bipush #98
/*    */     //   283: if_icmpeq -> 354
/*    */     //   286: iload_1
/*    */     //   287: bipush #102
/*    */     //   289: if_icmpeq -> 348
/*    */     //   292: iload_1
/*    */     //   293: bipush #110
/*    */     //   295: if_icmpeq -> 342
/*    */     //   298: iload_1
/*    */     //   299: bipush #114
/*    */     //   301: if_icmpeq -> 336
/*    */     //   304: iload_1
/*    */     //   305: bipush #116
/*    */     //   307: if_icmpeq -> 330
/*    */     //   310: iload_1
/*    */     //   311: bipush #117
/*    */     //   313: if_icmpeq -> 319
/*    */     //   316: goto -> 533
/*    */     //   319: iconst_2
/*    */     //   320: istore_2
/*    */     //   321: iconst_0
/*    */     //   322: istore #4
/*    */     //   324: iload #4
/*    */     //   326: istore_3
/*    */     //   327: goto -> 40
/*    */     //   330: bipush #9
/*    */     //   332: istore_1
/*    */     //   333: goto -> 533
/*    */     //   336: bipush #13
/*    */     //   338: istore_1
/*    */     //   339: goto -> 533
/*    */     //   342: bipush #10
/*    */     //   344: istore_1
/*    */     //   345: goto -> 533
/*    */     //   348: bipush #12
/*    */     //   350: istore_1
/*    */     //   351: goto -> 533
/*    */     //   354: bipush #8
/*    */     //   356: istore_1
/*    */     //   357: goto -> 533
/*    */     //   360: iconst_3
/*    */     //   361: istore_2
/*    */     //   362: goto -> 40
/*    */     //   365: iload_1
/*    */     //   366: bipush #10
/*    */     //   368: if_icmpeq -> 566
/*    */     //   371: iload_1
/*    */     //   372: bipush #13
/*    */     //   374: if_icmpeq -> 576
/*    */     //   377: iload_1
/*    */     //   378: bipush #33
/*    */     //   380: if_icmpeq -> 439
/*    */     //   383: iload_1
/*    */     //   384: bipush #35
/*    */     //   386: if_icmpeq -> 439
/*    */     //   389: iload_1
/*    */     //   390: bipush #58
/*    */     //   392: if_icmpeq -> 424
/*    */     //   395: iload_1
/*    */     //   396: bipush #61
/*    */     //   398: if_icmpeq -> 424
/*    */     //   401: iload_1
/*    */     //   402: bipush #92
/*    */     //   404: if_icmpeq -> 410
/*    */     //   407: goto -> 476
/*    */     //   410: iload_2
/*    */     //   411: iconst_4
/*    */     //   412: if_icmpne -> 419
/*    */     //   415: iload #6
/*    */     //   417: istore #7
/*    */     //   419: iconst_1
/*    */     //   420: istore_2
/*    */     //   421: goto -> 40
/*    */     //   424: iload #7
/*    */     //   426: iconst_m1
/*    */     //   427: if_icmpne -> 476
/*    */     //   430: iconst_0
/*    */     //   431: istore_2
/*    */     //   432: iload #6
/*    */     //   434: istore #7
/*    */     //   436: goto -> 40
/*    */     //   439: iload #8
/*    */     //   441: ifeq -> 476
/*    */     //   444: aload #9
/*    */     //   446: invokevirtual read : ()I
/*    */     //   449: dup
/*    */     //   450: istore_1
/*    */     //   451: iconst_m1
/*    */     //   452: if_icmpne -> 458
/*    */     //   455: goto -> 40
/*    */     //   458: iload_1
/*    */     //   459: i2c
/*    */     //   460: dup
/*    */     //   461: istore_1
/*    */     //   462: bipush #13
/*    */     //   464: if_icmpeq -> 40
/*    */     //   467: iload_1
/*    */     //   468: bipush #10
/*    */     //   470: if_icmpne -> 444
/*    */     //   473: goto -> 40
/*    */     //   476: iload_1
/*    */     //   477: invokestatic isSpace : (C)Z
/*    */     //   480: ifeq -> 521
/*    */     //   483: iload_2
/*    */     //   484: iconst_3
/*    */     //   485: if_icmpne -> 490
/*    */     //   488: iconst_5
/*    */     //   489: istore_2
/*    */     //   490: iload #6
/*    */     //   492: ifeq -> 40
/*    */     //   495: iload #6
/*    */     //   497: iload #7
/*    */     //   499: if_icmpeq -> 40
/*    */     //   502: iload_2
/*    */     //   503: iconst_5
/*    */     //   504: if_icmpne -> 510
/*    */     //   507: goto -> 40
/*    */     //   510: iload #7
/*    */     //   512: iconst_m1
/*    */     //   513: if_icmpne -> 521
/*    */     //   516: iconst_4
/*    */     //   517: istore_2
/*    */     //   518: goto -> 40
/*    */     //   521: iload_2
/*    */     //   522: iconst_5
/*    */     //   523: if_icmpeq -> 531
/*    */     //   526: iload_2
/*    */     //   527: iconst_3
/*    */     //   528: if_icmpne -> 533
/*    */     //   531: iconst_0
/*    */     //   532: istore_2
/*    */     //   533: iload_2
/*    */     //   534: iconst_0
/*    */     //   535: istore #8
/*    */     //   537: iconst_4
/*    */     //   538: if_icmpne -> 547
/*    */     //   541: iconst_0
/*    */     //   542: istore_2
/*    */     //   543: iload #6
/*    */     //   545: istore #7
/*    */     //   547: aload #5
/*    */     //   549: iload #6
/*    */     //   551: iconst_1
/*    */     //   552: iadd
/*    */     //   553: istore #10
/*    */     //   555: iload #6
/*    */     //   557: iload_1
/*    */     //   558: castore
/*    */     //   559: iload #10
/*    */     //   561: istore #6
/*    */     //   563: goto -> 40
/*    */     //   566: iload_2
/*    */     //   567: iconst_3
/*    */     //   568: if_icmpne -> 576
/*    */     //   571: iconst_5
/*    */     //   572: istore_2
/*    */     //   573: goto -> 40
/*    */     //   576: iload #6
/*    */     //   578: iconst_0
/*    */     //   579: istore_2
/*    */     //   580: iconst_1
/*    */     //   581: istore #8
/*    */     //   583: ifgt -> 596
/*    */     //   586: iload #6
/*    */     //   588: ifne -> 638
/*    */     //   591: iload #7
/*    */     //   593: ifne -> 638
/*    */     //   596: iload #7
/*    */     //   598: iconst_m1
/*    */     //   599: if_icmpne -> 606
/*    */     //   602: iload #6
/*    */     //   604: istore #7
/*    */     //   606: aload_0
/*    */     //   607: new java/lang/String
/*    */     //   610: dup
/*    */     //   611: dup
/*    */     //   612: aload #5
/*    */     //   614: iconst_0
/*    */     //   615: iload #6
/*    */     //   617: invokespecial <init> : ([CII)V
/*    */     //   620: iconst_0
/*    */     //   621: iload #7
/*    */     //   623: invokevirtual substring : (II)Ljava/lang/String;
/*    */     //   626: astore_1
/*    */     //   627: iload #7
/*    */     //   629: invokevirtual substring : (I)Ljava/lang/String;
/*    */     //   632: aload_1
/*    */     //   633: swap
/*    */     //   634: invokevirtual X00 : (Ljava/lang/Object;Ljava/lang/Object;)Ljava/lang/Object;
/*    */     //   637: pop
/*    */     //   638: iconst_m1
/*    */     //   639: istore #7
/*    */     //   641: iconst_0
/*    */     //   642: istore #6
/*    */     //   644: goto -> 40
/*    */     // Line number table:
/*    */     //   Java source line number -> byte code offset
/*    */     //   #1	-> 17
/*    */     //   #2	-> 127
/*    */     //   #3	-> 136
/*    */   } }


/* Location:              /Users/vnnsnnt/Documents/Codespace/JavaWorkspace/RedTrainer/src/main/java/org/trainer/client/PokeMMO.jar!/f/Pe0.class
 * Java compiler version: 7 (51.0)
 * JD-Core Version:       1.1.3
 */