/*   */ package f;public final class Pp0 { public int wk; public final String toString() {
/* 2 */     return B40.df("version:").append(new Integer(this.wk)).append(", channels:").append(new Integer(this.V0)).append(", rate:").append(new Integer(this.ce)).append(", bitrate:").append(new Integer(this.n40)).append(",").append(new Integer(this.N30)).append(",").append(new Integer(this.Ww0)).toString();
/*   */   }
/*   */   
/*   */   public int V0;
/*   */   public int ce;
/*   */   
/*   */   public int n40;
/*   */   public int N30;
/*   */   public int Ww0;
/*   */   public int[] OF = new int[2];
/*   */   public int Cw;
/*   */   public int b60;
/*   */   public int MT;
/*   */   public int IN;
/*   */   public int xs0;
/*   */   public int K3;
/*   */   public ag[] tb = null;
/*   */   public int[] t9 = null;
/*   */   public Object[] jE0 = null;
/*   */   public int[] gL = null;
/*   */   public Object[] fN = null;
/*   */   public int[] ur0 = null;
/*   */   public Object[] q9 = null;
/*   */   public int[] tw0 = null;
/*   */   public Object[] Or = null;
/*   */   public Y8[] EU = null;
/*   */   
/*   */   static {
/*   */     "vorbis".getBytes();
/*   */   }
/*   */   
/*   */   public final void It0() {
/*   */     byte b;
/*   */     for (b = 0; b < this.Cw; b++)
/*   */       this.tb[b] = null; 
/*   */     this.tb = null;
/*   */     for (b = 0; b < this.b60; b++) {
/*   */       this.jE0[b];
/*   */       PM.M40[this.t9[b]].getClass();
/*   */     } 
/*   */     this.jE0 = null;
/*   */     for (b = 0; b < this.MT; b++) {
/*   */       this.fN[b];
/*   */       Lx.e70[this.gL[b]].getClass();
/*   */     } 
/*   */     this.fN = null;
/*   */     for (b = 0; b < this.IN; b++) {
/*   */       this.q9[b];
/*   */       Ty.Wu[this.ur0[b]].Qk0();
/*   */     } 
/*   */     this.q9 = null;
/*   */     for (b = 0; b < this.xs0; b++) {
/*   */       this.Or[b];
/*   */       BI0.Da0[this.tw0[b]].getClass();
/*   */     } 
/*   */     this.Or = null;
/*   */     for (b = 0; b < this.K3; b++) {
/*   */       Y8[] arrayOfY8;
/*   */       if ((arrayOfY8 = this.EU)[b] != null)
/*   */         arrayOfY8[b] = null; 
/*   */     } 
/*   */     this.EU = null;
/*   */   }
/*   */   
/*   */   public final int bW(O50 paramO50, lc paramlc) {
/*   */     // Byte code:
/*   */     //   0: aload_2
/*   */     //   1: new f/E7
/*   */     //   4: dup
/*   */     //   5: astore_3
/*   */     //   6: invokespecial <init> : ()V
/*   */     //   9: ifnull -> 2491
/*   */     //   12: aload_3
/*   */     //   13: dup
/*   */     //   14: dup2
/*   */     //   15: dup2
/*   */     //   16: aload_2
/*   */     //   17: dup
/*   */     //   18: dup
/*   */     //   19: getfield ME : [B
/*   */     //   22: astore #4
/*   */     //   24: getfield XD0 : I
/*   */     //   27: istore #5
/*   */     //   29: getfield W80 : I
/*   */     //   32: istore #6
/*   */     //   34: iload #5
/*   */     //   36: putfield UG : I
/*   */     //   39: aload #4
/*   */     //   41: putfield qJ0 : [B
/*   */     //   44: iconst_0
/*   */     //   45: putfield m60 : I
/*   */     //   48: iconst_0
/*   */     //   49: putfield SJ : I
/*   */     //   52: iload #6
/*   */     //   54: putfield zk : I
/*   */     //   57: bipush #6
/*   */     //   59: newarray byte
/*   */     //   61: astore #4
/*   */     //   63: bipush #8
/*   */     //   65: invokevirtual else : (I)I
/*   */     //   68: istore #5
/*   */     //   70: bipush #6
/*   */     //   72: istore #6
/*   */     //   74: iconst_0
/*   */     //   75: istore #7
/*   */     //   77: iload #6
/*   */     //   79: dup
/*   */     //   80: iconst_m1
/*   */     //   81: iadd
/*   */     //   82: istore #6
/*   */     //   84: ifeq -> 105
/*   */     //   87: aload #4
/*   */     //   89: iload #7
/*   */     //   91: aload_3
/*   */     //   92: iinc #7, 1
/*   */     //   95: bipush #8
/*   */     //   97: invokevirtual else : (I)I
/*   */     //   100: i2b
/*   */     //   101: bastore
/*   */     //   102: goto -> 77
/*   */     //   105: aload #4
/*   */     //   107: iconst_0
/*   */     //   108: baload
/*   */     //   109: bipush #118
/*   */     //   111: if_icmpne -> 2489
/*   */     //   114: aload #4
/*   */     //   116: iconst_1
/*   */     //   117: baload
/*   */     //   118: bipush #111
/*   */     //   120: if_icmpne -> 2489
/*   */     //   123: aload #4
/*   */     //   125: iconst_2
/*   */     //   126: baload
/*   */     //   127: bipush #114
/*   */     //   129: if_icmpne -> 2489
/*   */     //   132: aload #4
/*   */     //   134: iconst_3
/*   */     //   135: baload
/*   */     //   136: bipush #98
/*   */     //   138: if_icmpne -> 2489
/*   */     //   141: aload #4
/*   */     //   143: iconst_4
/*   */     //   144: baload
/*   */     //   145: bipush #105
/*   */     //   147: if_icmpne -> 2489
/*   */     //   150: aload #4
/*   */     //   152: iconst_5
/*   */     //   153: baload
/*   */     //   154: bipush #115
/*   */     //   156: if_icmpeq -> 162
/*   */     //   159: goto -> 2489
/*   */     //   162: iload #5
/*   */     //   164: iconst_1
/*   */     //   165: if_icmpeq -> 2313
/*   */     //   168: iload #5
/*   */     //   170: iconst_3
/*   */     //   171: if_icmpeq -> 2109
/*   */     //   174: iload #5
/*   */     //   176: iconst_5
/*   */     //   177: if_icmpeq -> 183
/*   */     //   180: goto -> 2491
/*   */     //   183: aload_0
/*   */     //   184: getfield ce : I
/*   */     //   187: ifeq -> 2107
/*   */     //   190: aload_1
/*   */     //   191: getfield EB0 : [B
/*   */     //   194: ifnonnull -> 200
/*   */     //   197: goto -> 2107
/*   */     //   200: aload_0
/*   */     //   201: dup
/*   */     //   202: aload_3
/*   */     //   203: bipush #8
/*   */     //   205: invokevirtual else : (I)I
/*   */     //   208: iconst_1
/*   */     //   209: iadd
/*   */     //   210: dup
/*   */     //   211: istore_1
/*   */     //   212: putfield K3 : I
/*   */     //   215: getfield EU : [Lf/Y8;
/*   */     //   218: dup
/*   */     //   219: astore_2
/*   */     //   220: ifnull -> 229
/*   */     //   223: aload_2
/*   */     //   224: arraylength
/*   */     //   225: iload_1
/*   */     //   226: if_icmpeq -> 237
/*   */     //   229: aload_0
/*   */     //   230: iload_1
/*   */     //   231: anewarray f/Y8
/*   */     //   234: putfield EU : [Lf/Y8;
/*   */     //   237: iconst_0
/*   */     //   238: istore_1
/*   */     //   239: iload_1
/*   */     //   240: aload_0
/*   */     //   241: getfield K3 : I
/*   */     //   244: if_icmpge -> 724
/*   */     //   247: aload_3
/*   */     //   248: aload_0
/*   */     //   249: getfield EU : [Lf/Y8;
/*   */     //   252: iload_1
/*   */     //   253: new f/Y8
/*   */     //   256: dup
/*   */     //   257: astore_2
/*   */     //   258: invokespecial <init> : ()V
/*   */     //   261: aload_2
/*   */     //   262: aastore
/*   */     //   263: bipush #24
/*   */     //   265: invokevirtual else : (I)I
/*   */     //   268: ldc 5653314
/*   */     //   270: if_icmpeq -> 276
/*   */     //   273: goto -> 707
/*   */     //   276: aload_3
/*   */     //   277: aload_2
/*   */     //   278: aload_3
/*   */     //   279: bipush #16
/*   */     //   281: invokevirtual else : (I)I
/*   */     //   284: putfield ME0 : I
/*   */     //   287: bipush #24
/*   */     //   289: invokevirtual else : (I)I
/*   */     //   292: dup
/*   */     //   293: aload_2
/*   */     //   294: swap
/*   */     //   295: putfield T20 : I
/*   */     //   298: iconst_m1
/*   */     //   299: if_icmpne -> 305
/*   */     //   302: goto -> 707
/*   */     //   305: aload_3
/*   */     //   306: iconst_1
/*   */     //   307: invokevirtual else : (I)I
/*   */     //   310: dup
/*   */     //   311: istore #4
/*   */     //   313: ifeq -> 415
/*   */     //   316: iload #4
/*   */     //   318: iconst_1
/*   */     //   319: if_icmpeq -> 325
/*   */     //   322: goto -> 707
/*   */     //   325: aload_2
/*   */     //   326: dup
/*   */     //   327: aload_3
/*   */     //   328: iconst_5
/*   */     //   329: invokevirtual else : (I)I
/*   */     //   332: iconst_1
/*   */     //   333: iadd
/*   */     //   334: istore #4
/*   */     //   336: getfield T20 : I
/*   */     //   339: newarray int
/*   */     //   341: putfield Me : [I
/*   */     //   344: iconst_0
/*   */     //   345: istore #5
/*   */     //   347: iload #5
/*   */     //   349: aload_2
/*   */     //   350: getfield T20 : I
/*   */     //   353: dup
/*   */     //   354: istore #6
/*   */     //   356: if_icmpge -> 540
/*   */     //   359: aload_3
/*   */     //   360: iload #6
/*   */     //   362: iload #5
/*   */     //   364: isub
/*   */     //   365: invokestatic TV : (I)I
/*   */     //   368: invokevirtual else : (I)I
/*   */     //   371: dup
/*   */     //   372: istore #6
/*   */     //   374: iconst_m1
/*   */     //   375: if_icmpne -> 381
/*   */     //   378: goto -> 707
/*   */     //   381: iconst_0
/*   */     //   382: istore #7
/*   */     //   384: iload #7
/*   */     //   386: iload #6
/*   */     //   388: if_icmpge -> 409
/*   */     //   391: aload_2
/*   */     //   392: getfield Me : [I
/*   */     //   395: iload #5
/*   */     //   397: iload #4
/*   */     //   399: iastore
/*   */     //   400: iinc #7, 1
/*   */     //   403: iinc #5, 1
/*   */     //   406: goto -> 384
/*   */     //   409: iinc #4, 1
/*   */     //   412: goto -> 347
/*   */     //   415: aload_3
/*   */     //   416: aload_2
/*   */     //   417: dup
/*   */     //   418: getfield T20 : I
/*   */     //   421: newarray int
/*   */     //   423: putfield Me : [I
/*   */     //   426: iconst_1
/*   */     //   427: invokevirtual else : (I)I
/*   */     //   430: ifeq -> 496
/*   */     //   433: iconst_0
/*   */     //   434: istore #4
/*   */     //   436: iload #4
/*   */     //   438: aload_2
/*   */     //   439: getfield T20 : I
/*   */     //   442: if_icmpge -> 540
/*   */     //   445: aload_3
/*   */     //   446: iconst_1
/*   */     //   447: invokevirtual else : (I)I
/*   */     //   450: ifeq -> 482
/*   */     //   453: aload_3
/*   */     //   454: iconst_5
/*   */     //   455: invokevirtual else : (I)I
/*   */     //   458: dup
/*   */     //   459: istore #5
/*   */     //   461: iconst_m1
/*   */     //   462: if_icmpne -> 468
/*   */     //   465: goto -> 707
/*   */     //   468: aload_2
/*   */     //   469: getfield Me : [I
/*   */     //   472: iload #4
/*   */     //   474: iload #5
/*   */     //   476: iconst_1
/*   */     //   477: iadd
/*   */     //   478: iastore
/*   */     //   479: goto -> 490
/*   */     //   482: aload_2
/*   */     //   483: getfield Me : [I
/*   */     //   486: iload #4
/*   */     //   488: iconst_0
/*   */     //   489: iastore
/*   */     //   490: iinc #4, 1
/*   */     //   493: goto -> 436
/*   */     //   496: iconst_0
/*   */     //   497: istore #4
/*   */     //   499: iload #4
/*   */     //   501: aload_2
/*   */     //   502: getfield T20 : I
/*   */     //   505: if_icmpge -> 540
/*   */     //   508: aload_3
/*   */     //   509: iconst_5
/*   */     //   510: invokevirtual else : (I)I
/*   */     //   513: dup
/*   */     //   514: istore #5
/*   */     //   516: iconst_m1
/*   */     //   517: if_icmpne -> 523
/*   */     //   520: goto -> 707
/*   */     //   523: aload_2
/*   */     //   524: getfield Me : [I
/*   */     //   527: iload #4
/*   */     //   529: iload #5
/*   */     //   531: iconst_1
/*   */     //   532: iadd
/*   */     //   533: iastore
/*   */     //   534: iinc #4, 1
/*   */     //   537: goto -> 499
/*   */     //   540: aload_3
/*   */     //   541: iconst_4
/*   */     //   542: invokevirtual else : (I)I
/*   */     //   545: dup
/*   */     //   546: istore #4
/*   */     //   548: aload_2
/*   */     //   549: iload #4
/*   */     //   551: putfield qo0 : I
/*   */     //   554: ifeq -> 711
/*   */     //   557: iload #4
/*   */     //   559: iconst_1
/*   */     //   560: if_icmpeq -> 572
/*   */     //   563: iload #4
/*   */     //   565: iconst_2
/*   */     //   566: if_icmpeq -> 572
/*   */     //   569: goto -> 707
/*   */     //   572: aload_2
/*   */     //   573: dup
/*   */     //   574: aload_3
/*   */     //   575: aload_2
/*   */     //   576: aload_3
/*   */     //   577: aload_2
/*   */     //   578: aload_3
/*   */     //   579: aload_2
/*   */     //   580: aload_3
/*   */     //   581: bipush #32
/*   */     //   583: invokevirtual else : (I)I
/*   */     //   586: putfield Gv : I
/*   */     //   589: bipush #32
/*   */     //   591: invokevirtual else : (I)I
/*   */     //   594: putfield SM : I
/*   */     //   597: iconst_4
/*   */     //   598: invokevirtual else : (I)I
/*   */     //   601: iconst_1
/*   */     //   602: iadd
/*   */     //   603: putfield RY : I
/*   */     //   606: iconst_1
/*   */     //   607: invokevirtual else : (I)I
/*   */     //   610: putfield Wl : I
/*   */     //   613: iconst_0
/*   */     //   614: istore #4
/*   */     //   616: getfield qo0 : I
/*   */     //   619: dup
/*   */     //   620: istore #5
/*   */     //   622: iconst_1
/*   */     //   623: if_icmpeq -> 649
/*   */     //   626: iload #5
/*   */     //   628: iconst_2
/*   */     //   629: if_icmpeq -> 635
/*   */     //   632: goto -> 655
/*   */     //   635: aload_2
/*   */     //   636: getfield T20 : I
/*   */     //   639: aload_2
/*   */     //   640: getfield ME0 : I
/*   */     //   643: imul
/*   */     //   644: istore #4
/*   */     //   646: goto -> 655
/*   */     //   649: aload_2
/*   */     //   650: invokevirtual M0 : ()I
/*   */     //   653: istore #4
/*   */     //   655: aload_2
/*   */     //   656: iload #4
/*   */     //   658: newarray int
/*   */     //   660: putfield Ng : [I
/*   */     //   663: iconst_0
/*   */     //   664: istore #5
/*   */     //   666: iload #5
/*   */     //   668: iload #4
/*   */     //   670: if_icmpge -> 694
/*   */     //   673: aload_2
/*   */     //   674: getfield Ng : [I
/*   */     //   677: iload #5
/*   */     //   679: aload_3
/*   */     //   680: aload_2
/*   */     //   681: getfield RY : I
/*   */     //   684: invokevirtual else : (I)I
/*   */     //   687: iastore
/*   */     //   688: iinc #5, 1
/*   */     //   691: goto -> 666
/*   */     //   694: aload_2
/*   */     //   695: getfield Ng : [I
/*   */     //   698: iload #4
/*   */     //   700: iconst_1
/*   */     //   701: isub
/*   */     //   702: iaload
/*   */     //   703: iconst_m1
/*   */     //   704: if_icmpne -> 711
/*   */     //   707: iconst_m1
/*   */     //   708: goto -> 712
/*   */     //   711: iconst_0
/*   */     //   712: ifeq -> 718
/*   */     //   715: goto -> 2097
/*   */     //   718: iinc #1, 1
/*   */     //   721: goto -> 239
/*   */     //   724: aload_0
/*   */     //   725: dup
/*   */     //   726: aload_3
/*   */     //   727: bipush #6
/*   */     //   729: invokevirtual else : (I)I
/*   */     //   732: iconst_1
/*   */     //   733: iadd
/*   */     //   734: dup
/*   */     //   735: istore_1
/*   */     //   736: putfield MT : I
/*   */     //   739: getfield gL : [I
/*   */     //   742: dup
/*   */     //   743: astore_2
/*   */     //   744: ifnull -> 753
/*   */     //   747: aload_2
/*   */     //   748: arraylength
/*   */     //   749: iload_1
/*   */     //   750: if_icmpeq -> 760
/*   */     //   753: aload_0
/*   */     //   754: iload_1
/*   */     //   755: newarray int
/*   */     //   757: putfield gL : [I
/*   */     //   760: aload_0
/*   */     //   761: getfield fN : [Ljava/lang/Object;
/*   */     //   764: dup
/*   */     //   765: astore_2
/*   */     //   766: ifnull -> 775
/*   */     //   769: aload_2
/*   */     //   770: arraylength
/*   */     //   771: iload_1
/*   */     //   772: if_icmpeq -> 783
/*   */     //   775: aload_0
/*   */     //   776: iload_1
/*   */     //   777: anewarray java/lang/Object
/*   */     //   780: putfield fN : [Ljava/lang/Object;
/*   */     //   783: iconst_0
/*   */     //   784: istore_1
/*   */     //   785: iload_1
/*   */     //   786: aload_0
/*   */     //   787: getfield MT : I
/*   */     //   790: if_icmpge -> 859
/*   */     //   793: aload_0
/*   */     //   794: dup
/*   */     //   795: getfield gL : [I
/*   */     //   798: iload_1
/*   */     //   799: aload_3
/*   */     //   800: bipush #16
/*   */     //   802: invokevirtual else : (I)I
/*   */     //   805: iastore
/*   */     //   806: getfield gL : [I
/*   */     //   809: iload_1
/*   */     //   810: iaload
/*   */     //   811: dup
/*   */     //   812: istore_2
/*   */     //   813: iflt -> 2097
/*   */     //   816: iload_2
/*   */     //   817: iconst_1
/*   */     //   818: if_icmplt -> 824
/*   */     //   821: goto -> 2097
/*   */     //   824: aload_0
/*   */     //   825: dup
/*   */     //   826: getfield fN : [Ljava/lang/Object;
/*   */     //   829: iload_1
/*   */     //   830: getstatic f/Lx.e70 : [Lf/Lx;
/*   */     //   833: iload_2
/*   */     //   834: aaload
/*   */     //   835: invokevirtual getClass : ()Ljava/lang/Class;
/*   */     //   838: pop
/*   */     //   839: ldc ''
/*   */     //   841: aastore
/*   */     //   842: getfield fN : [Ljava/lang/Object;
/*   */     //   845: iload_1
/*   */     //   846: aaload
/*   */     //   847: ifnonnull -> 853
/*   */     //   850: goto -> 2097
/*   */     //   853: iinc #1, 1
/*   */     //   856: goto -> 785
/*   */     //   859: aload_0
/*   */     //   860: dup
/*   */     //   861: aload_3
/*   */     //   862: bipush #6
/*   */     //   864: invokevirtual else : (I)I
/*   */     //   867: iconst_1
/*   */     //   868: iadd
/*   */     //   869: dup
/*   */     //   870: istore_1
/*   */     //   871: putfield IN : I
/*   */     //   874: getfield ur0 : [I
/*   */     //   877: dup
/*   */     //   878: astore_2
/*   */     //   879: ifnull -> 888
/*   */     //   882: aload_2
/*   */     //   883: arraylength
/*   */     //   884: iload_1
/*   */     //   885: if_icmpeq -> 895
/*   */     //   888: aload_0
/*   */     //   889: iload_1
/*   */     //   890: newarray int
/*   */     //   892: putfield ur0 : [I
/*   */     //   895: aload_0
/*   */     //   896: getfield q9 : [Ljava/lang/Object;
/*   */     //   899: dup
/*   */     //   900: astore_2
/*   */     //   901: ifnull -> 910
/*   */     //   904: aload_2
/*   */     //   905: arraylength
/*   */     //   906: iload_1
/*   */     //   907: if_icmpeq -> 918
/*   */     //   910: aload_0
/*   */     //   911: iload_1
/*   */     //   912: anewarray java/lang/Object
/*   */     //   915: putfield q9 : [Ljava/lang/Object;
/*   */     //   918: iconst_0
/*   */     //   919: istore_1
/*   */     //   920: iload_1
/*   */     //   921: aload_0
/*   */     //   922: getfield IN : I
/*   */     //   925: if_icmpge -> 993
/*   */     //   928: aload_0
/*   */     //   929: dup
/*   */     //   930: getfield ur0 : [I
/*   */     //   933: iload_1
/*   */     //   934: aload_3
/*   */     //   935: bipush #16
/*   */     //   937: invokevirtual else : (I)I
/*   */     //   940: iastore
/*   */     //   941: getfield ur0 : [I
/*   */     //   944: iload_1
/*   */     //   945: iaload
/*   */     //   946: dup
/*   */     //   947: istore_2
/*   */     //   948: iflt -> 2097
/*   */     //   951: iload_2
/*   */     //   952: iconst_2
/*   */     //   953: if_icmplt -> 959
/*   */     //   956: goto -> 2097
/*   */     //   959: aload_0
/*   */     //   960: dup
/*   */     //   961: getfield q9 : [Ljava/lang/Object;
/*   */     //   964: iload_1
/*   */     //   965: getstatic f/Ty.Wu : [Lf/Ty;
/*   */     //   968: iload_2
/*   */     //   969: aaload
/*   */     //   970: aload_0
/*   */     //   971: aload_3
/*   */     //   972: invokevirtual I9 : (Lf/Pp0;Lf/E7;)Ljava/lang/Object;
/*   */     //   975: aastore
/*   */     //   976: getfield q9 : [Ljava/lang/Object;
/*   */     //   979: iload_1
/*   */     //   980: aaload
/*   */     //   981: ifnonnull -> 987
/*   */     //   984: goto -> 2097
/*   */     //   987: iinc #1, 1
/*   */     //   990: goto -> 920
/*   */     //   993: aload_0
/*   */     //   994: dup
/*   */     //   995: aload_3
/*   */     //   996: bipush #6
/*   */     //   998: invokevirtual else : (I)I
/*   */     //   1001: iconst_1
/*   */     //   1002: iadd
/*   */     //   1003: dup
/*   */     //   1004: istore_1
/*   */     //   1005: putfield xs0 : I
/*   */     //   1008: getfield tw0 : [I
/*   */     //   1011: dup
/*   */     //   1012: astore_2
/*   */     //   1013: ifnull -> 1022
/*   */     //   1016: aload_2
/*   */     //   1017: arraylength
/*   */     //   1018: iload_1
/*   */     //   1019: if_icmpeq -> 1029
/*   */     //   1022: aload_0
/*   */     //   1023: iload_1
/*   */     //   1024: newarray int
/*   */     //   1026: putfield tw0 : [I
/*   */     //   1029: aload_0
/*   */     //   1030: getfield Or : [Ljava/lang/Object;
/*   */     //   1033: dup
/*   */     //   1034: astore_2
/*   */     //   1035: ifnull -> 1044
/*   */     //   1038: aload_2
/*   */     //   1039: arraylength
/*   */     //   1040: iload_1
/*   */     //   1041: if_icmpeq -> 1052
/*   */     //   1044: aload_0
/*   */     //   1045: iload_1
/*   */     //   1046: anewarray java/lang/Object
/*   */     //   1049: putfield Or : [Ljava/lang/Object;
/*   */     //   1052: iconst_0
/*   */     //   1053: istore_1
/*   */     //   1054: iload_1
/*   */     //   1055: aload_0
/*   */     //   1056: getfield xs0 : I
/*   */     //   1059: if_icmpge -> 1372
/*   */     //   1062: aload_0
/*   */     //   1063: dup
/*   */     //   1064: getfield tw0 : [I
/*   */     //   1067: iload_1
/*   */     //   1068: aload_3
/*   */     //   1069: bipush #16
/*   */     //   1071: invokevirtual else : (I)I
/*   */     //   1074: iastore
/*   */     //   1075: getfield tw0 : [I
/*   */     //   1078: iload_1
/*   */     //   1079: iaload
/*   */     //   1080: dup
/*   */     //   1081: istore_2
/*   */     //   1082: iflt -> 2097
/*   */     //   1085: iload_2
/*   */     //   1086: iconst_3
/*   */     //   1087: if_icmplt -> 1093
/*   */     //   1090: goto -> 2097
/*   */     //   1093: aload_0
/*   */     //   1094: getfield Or : [Ljava/lang/Object;
/*   */     //   1097: astore #4
/*   */     //   1099: getstatic f/BI0.Da0 : [Lf/BI0;
/*   */     //   1102: iload_2
/*   */     //   1103: aaload
/*   */     //   1104: checkcast f/e90
/*   */     //   1107: invokevirtual getClass : ()Ljava/lang/Class;
/*   */     //   1110: pop
/*   */     //   1111: iconst_0
/*   */     //   1112: istore_2
/*   */     //   1113: new f/bC
/*   */     //   1116: dup
/*   */     //   1117: astore #5
/*   */     //   1119: aload_3
/*   */     //   1120: aload #5
/*   */     //   1122: aload_3
/*   */     //   1123: aload #5
/*   */     //   1125: aload_3
/*   */     //   1126: aload #5
/*   */     //   1128: aload_3
/*   */     //   1129: aload #5
/*   */     //   1131: aload_3
/*   */     //   1132: aload #5
/*   */     //   1134: invokespecial <init> : ()V
/*   */     //   1137: bipush #24
/*   */     //   1139: invokevirtual else : (I)I
/*   */     //   1142: putfield Oi : I
/*   */     //   1145: bipush #24
/*   */     //   1147: invokevirtual else : (I)I
/*   */     //   1150: putfield vK : I
/*   */     //   1153: bipush #24
/*   */     //   1155: invokevirtual else : (I)I
/*   */     //   1158: iconst_1
/*   */     //   1159: iadd
/*   */     //   1160: putfield bF : I
/*   */     //   1163: bipush #6
/*   */     //   1165: invokevirtual else : (I)I
/*   */     //   1168: iconst_1
/*   */     //   1169: iadd
/*   */     //   1170: putfield LPT3 : I
/*   */     //   1173: bipush #8
/*   */     //   1175: invokevirtual else : (I)I
/*   */     //   1178: putfield XX : I
/*   */     //   1181: iconst_0
/*   */     //   1182: istore #6
/*   */     //   1184: iload #6
/*   */     //   1186: aload #5
/*   */     //   1188: getfield LPT3 : I
/*   */     //   1191: if_icmpge -> 1268
/*   */     //   1194: aload_3
/*   */     //   1195: dup
/*   */     //   1196: iconst_3
/*   */     //   1197: invokevirtual else : (I)I
/*   */     //   1200: istore #7
/*   */     //   1202: iconst_1
/*   */     //   1203: invokevirtual else : (I)I
/*   */     //   1206: ifeq -> 1221
/*   */     //   1209: iload #7
/*   */     //   1211: aload_3
/*   */     //   1212: iconst_5
/*   */     //   1213: invokevirtual else : (I)I
/*   */     //   1216: iconst_3
/*   */     //   1217: ishl
/*   */     //   1218: ior
/*   */     //   1219: istore #7
/*   */     //   1221: aload #5
/*   */     //   1223: getfield k7 : [I
/*   */     //   1226: iload #6
/*   */     //   1228: iload #7
/*   */     //   1230: iastore
/*   */     //   1231: iconst_0
/*   */     //   1232: istore #8
/*   */     //   1234: iload #7
/*   */     //   1236: ifeq -> 1257
/*   */     //   1239: iload #7
/*   */     //   1241: iload #8
/*   */     //   1243: iload #7
/*   */     //   1245: iconst_1
/*   */     //   1246: iand
/*   */     //   1247: iadd
/*   */     //   1248: istore #8
/*   */     //   1250: iconst_1
/*   */     //   1251: iushr
/*   */     //   1252: istore #7
/*   */     //   1254: goto -> 1234
/*   */     //   1257: iload_2
/*   */     //   1258: iload #8
/*   */     //   1260: iadd
/*   */     //   1261: istore_2
/*   */     //   1262: iinc #6, 1
/*   */     //   1265: goto -> 1184
/*   */     //   1268: iconst_0
/*   */     //   1269: istore #6
/*   */     //   1271: iload #6
/*   */     //   1273: iload_2
/*   */     //   1274: if_icmpge -> 1297
/*   */     //   1277: aload #5
/*   */     //   1279: getfield Nt0 : [I
/*   */     //   1282: iload #6
/*   */     //   1284: aload_3
/*   */     //   1285: bipush #8
/*   */     //   1287: invokevirtual else : (I)I
/*   */     //   1290: iastore
/*   */     //   1291: iinc #6, 1
/*   */     //   1294: goto -> 1271
/*   */     //   1297: aload #5
/*   */     //   1299: getfield XX : I
/*   */     //   1302: aload_0
/*   */     //   1303: getfield K3 : I
/*   */     //   1306: if_icmplt -> 1312
/*   */     //   1309: goto -> 1336
/*   */     //   1312: iconst_0
/*   */     //   1313: istore #6
/*   */     //   1315: iload #6
/*   */     //   1317: iload_2
/*   */     //   1318: if_icmpge -> 1348
/*   */     //   1321: aload #5
/*   */     //   1323: getfield Nt0 : [I
/*   */     //   1326: iload #6
/*   */     //   1328: iaload
/*   */     //   1329: aload_0
/*   */     //   1330: getfield K3 : I
/*   */     //   1333: if_icmplt -> 1342
/*   */     //   1336: aconst_null
/*   */     //   1337: astore #5
/*   */     //   1339: goto -> 1348
/*   */     //   1342: iinc #6, 1
/*   */     //   1345: goto -> 1315
/*   */     //   1348: aload_0
/*   */     //   1349: aload #4
/*   */     //   1351: iload_1
/*   */     //   1352: aload #5
/*   */     //   1354: aastore
/*   */     //   1355: getfield Or : [Ljava/lang/Object;
/*   */     //   1358: iload_1
/*   */     //   1359: aaload
/*   */     //   1360: ifnonnull -> 1366
/*   */     //   1363: goto -> 2097
/*   */     //   1366: iinc #1, 1
/*   */     //   1369: goto -> 1054
/*   */     //   1372: aload_0
/*   */     //   1373: dup
/*   */     //   1374: aload_3
/*   */     //   1375: bipush #6
/*   */     //   1377: invokevirtual else : (I)I
/*   */     //   1380: iconst_1
/*   */     //   1381: iadd
/*   */     //   1382: dup
/*   */     //   1383: istore_1
/*   */     //   1384: putfield b60 : I
/*   */     //   1387: getfield t9 : [I
/*   */     //   1390: dup
/*   */     //   1391: astore_2
/*   */     //   1392: ifnull -> 1401
/*   */     //   1395: aload_2
/*   */     //   1396: arraylength
/*   */     //   1397: iload_1
/*   */     //   1398: if_icmpeq -> 1408
/*   */     //   1401: aload_0
/*   */     //   1402: iload_1
/*   */     //   1403: newarray int
/*   */     //   1405: putfield t9 : [I
/*   */     //   1408: aload_0
/*   */     //   1409: getfield jE0 : [Ljava/lang/Object;
/*   */     //   1412: dup
/*   */     //   1413: astore_2
/*   */     //   1414: ifnull -> 1423
/*   */     //   1417: aload_2
/*   */     //   1418: arraylength
/*   */     //   1419: iload_1
/*   */     //   1420: if_icmpeq -> 1431
/*   */     //   1423: aload_0
/*   */     //   1424: iload_1
/*   */     //   1425: anewarray java/lang/Object
/*   */     //   1428: putfield jE0 : [Ljava/lang/Object;
/*   */     //   1431: iconst_0
/*   */     //   1432: istore_1
/*   */     //   1433: iload_1
/*   */     //   1434: aload_0
/*   */     //   1435: getfield b60 : I
/*   */     //   1438: if_icmpge -> 1925
/*   */     //   1441: aload_0
/*   */     //   1442: dup
/*   */     //   1443: getfield t9 : [I
/*   */     //   1446: iload_1
/*   */     //   1447: aload_3
/*   */     //   1448: bipush #16
/*   */     //   1450: invokevirtual else : (I)I
/*   */     //   1453: iastore
/*   */     //   1454: getfield t9 : [I
/*   */     //   1457: iload_1
/*   */     //   1458: iaload
/*   */     //   1459: dup
/*   */     //   1460: istore_2
/*   */     //   1461: iflt -> 2097
/*   */     //   1464: iload_2
/*   */     //   1465: iconst_1
/*   */     //   1466: if_icmplt -> 1472
/*   */     //   1469: goto -> 2097
/*   */     //   1472: aload_3
/*   */     //   1473: aload_0
/*   */     //   1474: getfield jE0 : [Ljava/lang/Object;
/*   */     //   1477: astore #4
/*   */     //   1479: getstatic f/PM.M40 : [Lf/PM;
/*   */     //   1482: iload_2
/*   */     //   1483: aaload
/*   */     //   1484: checkcast f/jl
/*   */     //   1487: invokevirtual getClass : ()Ljava/lang/Class;
/*   */     //   1490: pop
/*   */     //   1491: new f/r70
/*   */     //   1494: dup
/*   */     //   1495: astore_2
/*   */     //   1496: invokespecial <init> : ()V
/*   */     //   1499: iconst_1
/*   */     //   1500: invokevirtual else : (I)I
/*   */     //   1503: ifeq -> 1520
/*   */     //   1506: aload_2
/*   */     //   1507: aload_3
/*   */     //   1508: iconst_4
/*   */     //   1509: invokevirtual else : (I)I
/*   */     //   1512: iconst_1
/*   */     //   1513: iadd
/*   */     //   1514: putfield W : I
/*   */     //   1517: goto -> 1525
/*   */     //   1520: aload_2
/*   */     //   1521: iconst_1
/*   */     //   1522: putfield W : I
/*   */     //   1525: aload_3
/*   */     //   1526: iconst_1
/*   */     //   1527: invokevirtual else : (I)I
/*   */     //   1530: ifeq -> 1698
/*   */     //   1533: aload_2
/*   */     //   1534: aload_3
/*   */     //   1535: bipush #8
/*   */     //   1537: invokevirtual else : (I)I
/*   */     //   1540: iconst_1
/*   */     //   1541: iadd
/*   */     //   1542: putfield js : I
/*   */     //   1545: iconst_0
/*   */     //   1546: istore #5
/*   */     //   1548: iload #5
/*   */     //   1550: aload_2
/*   */     //   1551: getfield js : I
/*   */     //   1554: if_icmpge -> 1698
/*   */     //   1557: aload_0
/*   */     //   1558: aload_2
/*   */     //   1559: getfield Dt0 : [I
/*   */     //   1562: astore #6
/*   */     //   1564: getfield V0 : I
/*   */     //   1567: istore #7
/*   */     //   1569: iconst_0
/*   */     //   1570: istore #8
/*   */     //   1572: iload #7
/*   */     //   1574: iconst_1
/*   */     //   1575: if_icmple -> 1590
/*   */     //   1578: iload #7
/*   */     //   1580: iinc #8, 1
/*   */     //   1583: iconst_1
/*   */     //   1584: iushr
/*   */     //   1585: istore #7
/*   */     //   1587: goto -> 1572
/*   */     //   1590: aload_0
/*   */     //   1591: aload_2
/*   */     //   1592: aload #6
/*   */     //   1594: aload_3
/*   */     //   1595: iload #8
/*   */     //   1597: invokevirtual else : (I)I
/*   */     //   1600: istore #6
/*   */     //   1602: iload #5
/*   */     //   1604: iload #6
/*   */     //   1606: iastore
/*   */     //   1607: getfield ot0 : [I
/*   */     //   1610: astore #7
/*   */     //   1612: getfield V0 : I
/*   */     //   1615: istore #8
/*   */     //   1617: iconst_0
/*   */     //   1618: istore #9
/*   */     //   1620: iload #8
/*   */     //   1622: iconst_1
/*   */     //   1623: if_icmple -> 1638
/*   */     //   1626: iload #8
/*   */     //   1628: iinc #9, 1
/*   */     //   1631: iconst_1
/*   */     //   1632: iushr
/*   */     //   1633: istore #8
/*   */     //   1635: goto -> 1620
/*   */     //   1638: iload #6
/*   */     //   1640: aload #7
/*   */     //   1642: aload_3
/*   */     //   1643: iload #9
/*   */     //   1645: invokevirtual else : (I)I
/*   */     //   1648: istore #7
/*   */     //   1650: iload #5
/*   */     //   1652: iload #7
/*   */     //   1654: iastore
/*   */     //   1655: iflt -> 1863
/*   */     //   1658: iload #7
/*   */     //   1660: iflt -> 1863
/*   */     //   1663: iload #6
/*   */     //   1665: iload #7
/*   */     //   1667: if_icmpeq -> 1863
/*   */     //   1670: iload #6
/*   */     //   1672: aload_0
/*   */     //   1673: getfield V0 : I
/*   */     //   1676: dup
/*   */     //   1677: istore #6
/*   */     //   1679: if_icmpge -> 1863
/*   */     //   1682: iload #7
/*   */     //   1684: iload #6
/*   */     //   1686: if_icmplt -> 1692
/*   */     //   1689: goto -> 1863
/*   */     //   1692: iinc #5, 1
/*   */     //   1695: goto -> 1548
/*   */     //   1698: aload_3
/*   */     //   1699: iconst_2
/*   */     //   1700: invokevirtual else : (I)I
/*   */     //   1703: ifle -> 1709
/*   */     //   1706: goto -> 1863
/*   */     //   1709: aload_2
/*   */     //   1710: getfield W : I
/*   */     //   1713: iconst_1
/*   */     //   1714: if_icmple -> 1764
/*   */     //   1717: iconst_0
/*   */     //   1718: istore #5
/*   */     //   1720: iload #5
/*   */     //   1722: aload_0
/*   */     //   1723: getfield V0 : I
/*   */     //   1726: if_icmpge -> 1764
/*   */     //   1729: aload_2
/*   */     //   1730: dup
/*   */     //   1731: getfield Dt : [I
/*   */     //   1734: iload #5
/*   */     //   1736: aload_3
/*   */     //   1737: iconst_4
/*   */     //   1738: invokevirtual else : (I)I
/*   */     //   1741: iastore
/*   */     //   1742: getfield Dt : [I
/*   */     //   1745: iload #5
/*   */     //   1747: iaload
/*   */     //   1748: aload_2
/*   */     //   1749: getfield W : I
/*   */     //   1752: if_icmplt -> 1758
/*   */     //   1755: goto -> 1863
/*   */     //   1758: iinc #5, 1
/*   */     //   1761: goto -> 1720
/*   */     //   1764: iconst_0
/*   */     //   1765: istore #5
/*   */     //   1767: iload #5
/*   */     //   1769: aload_2
/*   */     //   1770: getfield W : I
/*   */     //   1773: if_icmpge -> 1902
/*   */     //   1776: aload_2
/*   */     //   1777: dup
/*   */     //   1778: getfield NE : [I
/*   */     //   1781: iload #5
/*   */     //   1783: aload_3
/*   */     //   1784: bipush #8
/*   */     //   1786: invokevirtual else : (I)I
/*   */     //   1789: iastore
/*   */     //   1790: getfield NE : [I
/*   */     //   1793: iload #5
/*   */     //   1795: iaload
/*   */     //   1796: aload_0
/*   */     //   1797: getfield MT : I
/*   */     //   1800: if_icmplt -> 1806
/*   */     //   1803: goto -> 1863
/*   */     //   1806: aload_2
/*   */     //   1807: dup
/*   */     //   1808: getfield sd : [I
/*   */     //   1811: iload #5
/*   */     //   1813: aload_3
/*   */     //   1814: bipush #8
/*   */     //   1816: invokevirtual else : (I)I
/*   */     //   1819: iastore
/*   */     //   1820: getfield sd : [I
/*   */     //   1823: iload #5
/*   */     //   1825: iaload
/*   */     //   1826: aload_0
/*   */     //   1827: getfield IN : I
/*   */     //   1830: if_icmplt -> 1836
/*   */     //   1833: goto -> 1863
/*   */     //   1836: aload_2
/*   */     //   1837: dup
/*   */     //   1838: getfield mZ : [I
/*   */     //   1841: iload #5
/*   */     //   1843: aload_3
/*   */     //   1844: bipush #8
/*   */     //   1846: invokevirtual else : (I)I
/*   */     //   1849: iastore
/*   */     //   1850: getfield mZ : [I
/*   */     //   1853: iload #5
/*   */     //   1855: iaload
/*   */     //   1856: aload_0
/*   */     //   1857: getfield xs0 : I
/*   */     //   1860: if_icmplt -> 1896
/*   */     //   1863: aload_2
/*   */     //   1864: dup
/*   */     //   1865: dup2
/*   */     //   1866: dup2
/*   */     //   1867: aconst_null
/*   */     //   1868: putfield Dt : [I
/*   */     //   1871: aconst_null
/*   */     //   1872: putfield NE : [I
/*   */     //   1875: aconst_null
/*   */     //   1876: putfield sd : [I
/*   */     //   1879: aconst_null
/*   */     //   1880: putfield mZ : [I
/*   */     //   1883: aconst_null
/*   */     //   1884: putfield Dt0 : [I
/*   */     //   1887: aconst_null
/*   */     //   1888: putfield ot0 : [I
/*   */     //   1891: aconst_null
/*   */     //   1892: astore_2
/*   */     //   1893: goto -> 1902
/*   */     //   1896: iinc #5, 1
/*   */     //   1899: goto -> 1767
/*   */     //   1902: aload_0
/*   */     //   1903: aload #4
/*   */     //   1905: iload_1
/*   */     //   1906: aload_2
/*   */     //   1907: aastore
/*   */     //   1908: getfield jE0 : [Ljava/lang/Object;
/*   */     //   1911: iload_1
/*   */     //   1912: aaload
/*   */     //   1913: ifnonnull -> 1919
/*   */     //   1916: goto -> 2097
/*   */     //   1919: iinc #1, 1
/*   */     //   1922: goto -> 1433
/*   */     //   1925: aload_0
/*   */     //   1926: dup
/*   */     //   1927: aload_3
/*   */     //   1928: bipush #6
/*   */     //   1930: invokevirtual else : (I)I
/*   */     //   1933: iconst_1
/*   */     //   1934: iadd
/*   */     //   1935: dup
/*   */     //   1936: istore_1
/*   */     //   1937: putfield Cw : I
/*   */     //   1940: getfield tb : [Lf/ag;
/*   */     //   1943: dup
/*   */     //   1944: astore_2
/*   */     //   1945: ifnull -> 1954
/*   */     //   1948: aload_2
/*   */     //   1949: arraylength
/*   */     //   1950: iload_1
/*   */     //   1951: if_icmpeq -> 1962
/*   */     //   1954: aload_0
/*   */     //   1955: iload_1
/*   */     //   1956: anewarray f/ag
/*   */     //   1959: putfield tb : [Lf/ag;
/*   */     //   1962: iconst_0
/*   */     //   1963: istore_1
/*   */     //   1964: iload_1
/*   */     //   1965: aload_0
/*   */     //   1966: getfield Cw : I
/*   */     //   1969: if_icmpge -> 2088
/*   */     //   1972: aload_0
/*   */     //   1973: dup
/*   */     //   1974: dup
/*   */     //   1975: dup2
/*   */     //   1976: getfield tb : [Lf/ag;
/*   */     //   1979: astore_2
/*   */     //   1980: new f/ag
/*   */     //   1983: dup
/*   */     //   1984: astore #4
/*   */     //   1986: aload_3
/*   */     //   1987: aload_2
/*   */     //   1988: iload_1
/*   */     //   1989: aload #4
/*   */     //   1991: invokespecial <init> : ()V
/*   */     //   1994: aload #4
/*   */     //   1996: aastore
/*   */     //   1997: iconst_1
/*   */     //   1998: invokevirtual else : (I)I
/*   */     //   2001: putfield OZ : I
/*   */     //   2004: getfield tb : [Lf/ag;
/*   */     //   2007: iload_1
/*   */     //   2008: aaload
/*   */     //   2009: aload_3
/*   */     //   2010: bipush #16
/*   */     //   2012: invokevirtual else : (I)I
/*   */     //   2015: putfield A60 : I
/*   */     //   2018: getfield tb : [Lf/ag;
/*   */     //   2021: iload_1
/*   */     //   2022: aaload
/*   */     //   2023: aload_3
/*   */     //   2024: bipush #16
/*   */     //   2026: invokevirtual else : (I)I
/*   */     //   2029: putfield pt0 : I
/*   */     //   2032: getfield tb : [Lf/ag;
/*   */     //   2035: iload_1
/*   */     //   2036: aaload
/*   */     //   2037: aload_3
/*   */     //   2038: bipush #8
/*   */     //   2040: invokevirtual else : (I)I
/*   */     //   2043: putfield xL0 : I
/*   */     //   2046: getfield tb : [Lf/ag;
/*   */     //   2049: iload_1
/*   */     //   2050: aaload
/*   */     //   2051: dup
/*   */     //   2052: astore_2
/*   */     //   2053: getfield A60 : I
/*   */     //   2056: iconst_1
/*   */     //   2057: if_icmpge -> 2097
/*   */     //   2060: aload_2
/*   */     //   2061: getfield pt0 : I
/*   */     //   2064: iconst_1
/*   */     //   2065: if_icmpge -> 2097
/*   */     //   2068: aload_2
/*   */     //   2069: getfield xL0 : I
/*   */     //   2072: aload_0
/*   */     //   2073: getfield b60 : I
/*   */     //   2076: if_icmplt -> 2082
/*   */     //   2079: goto -> 2097
/*   */     //   2082: iinc #1, 1
/*   */     //   2085: goto -> 1964
/*   */     //   2088: aload_3
/*   */     //   2089: iconst_1
/*   */     //   2090: invokevirtual else : (I)I
/*   */     //   2093: iconst_1
/*   */     //   2094: if_icmpeq -> 2105
/*   */     //   2097: aload_0
/*   */     //   2098: invokevirtual It0 : ()V
/*   */     //   2101: iconst_m1
/*   */     //   2102: goto -> 2106
/*   */     //   2105: iconst_0
/*   */     //   2106: ireturn
/*   */     //   2107: iconst_m1
/*   */     //   2108: ireturn
/*   */     //   2109: aload_0
/*   */     //   2110: getfield ce : I
/*   */     //   2113: ifne -> 2118
/*   */     //   2116: iconst_m1
/*   */     //   2117: ireturn
/*   */     //   2118: aload_3
/*   */     //   2119: aload_1
/*   */     //   2120: invokevirtual getClass : ()Ljava/lang/Class;
/*   */     //   2123: pop
/*   */     //   2124: bipush #32
/*   */     //   2126: invokevirtual else : (I)I
/*   */     //   2129: dup
/*   */     //   2130: istore_0
/*   */     //   2131: ifge -> 2137
/*   */     //   2134: goto -> 2303
/*   */     //   2137: aload_1
/*   */     //   2138: iload_0
/*   */     //   2139: iconst_1
/*   */     //   2140: iadd
/*   */     //   2141: newarray byte
/*   */     //   2143: dup
/*   */     //   2144: astore_2
/*   */     //   2145: putfield EB0 : [B
/*   */     //   2148: iconst_0
/*   */     //   2149: istore #4
/*   */     //   2151: iload_0
/*   */     //   2152: dup
/*   */     //   2153: iconst_m1
/*   */     //   2154: iadd
/*   */     //   2155: istore_0
/*   */     //   2156: ifeq -> 2176
/*   */     //   2159: aload_2
/*   */     //   2160: iload #4
/*   */     //   2162: aload_3
/*   */     //   2163: iinc #4, 1
/*   */     //   2166: bipush #8
/*   */     //   2168: invokevirtual else : (I)I
/*   */     //   2171: i2b
/*   */     //   2172: bastore
/*   */     //   2173: goto -> 2151
/*   */     //   2176: aload_3
/*   */     //   2177: bipush #32
/*   */     //   2179: invokevirtual else : (I)I
/*   */     //   2182: dup
/*   */     //   2183: istore_0
/*   */     //   2184: aload_1
/*   */     //   2185: iload_0
/*   */     //   2186: putfield WO : I
/*   */     //   2189: ifge -> 2195
/*   */     //   2192: goto -> 2303
/*   */     //   2195: aload_1
/*   */     //   2196: dup
/*   */     //   2197: iload_0
/*   */     //   2198: iconst_1
/*   */     //   2199: iadd
/*   */     //   2200: dup
/*   */     //   2201: istore_0
/*   */     //   2202: anewarray [B
/*   */     //   2205: putfield az : [[B
/*   */     //   2208: iload_0
/*   */     //   2209: newarray int
/*   */     //   2211: putfield Cs : [I
/*   */     //   2214: iconst_0
/*   */     //   2215: istore_0
/*   */     //   2216: iload_0
/*   */     //   2217: aload_1
/*   */     //   2218: getfield WO : I
/*   */     //   2221: if_icmpge -> 2294
/*   */     //   2224: aload_3
/*   */     //   2225: bipush #32
/*   */     //   2227: invokevirtual else : (I)I
/*   */     //   2230: dup
/*   */     //   2231: istore_2
/*   */     //   2232: ifge -> 2238
/*   */     //   2235: goto -> 2303
/*   */     //   2238: aload_1
/*   */     //   2239: dup
/*   */     //   2240: getfield Cs : [I
/*   */     //   2243: iload_0
/*   */     //   2244: iload_2
/*   */     //   2245: iastore
/*   */     //   2246: getfield az : [[B
/*   */     //   2249: iload_0
/*   */     //   2250: iload_2
/*   */     //   2251: iconst_1
/*   */     //   2252: iadd
/*   */     //   2253: newarray byte
/*   */     //   2255: dup
/*   */     //   2256: astore #4
/*   */     //   2258: aastore
/*   */     //   2259: iconst_0
/*   */     //   2260: istore #5
/*   */     //   2262: iload_2
/*   */     //   2263: dup
/*   */     //   2264: iconst_m1
/*   */     //   2265: iadd
/*   */     //   2266: istore_2
/*   */     //   2267: ifeq -> 2288
/*   */     //   2270: aload #4
/*   */     //   2272: iload #5
/*   */     //   2274: aload_3
/*   */     //   2275: iinc #5, 1
/*   */     //   2278: bipush #8
/*   */     //   2280: invokevirtual else : (I)I
/*   */     //   2283: i2b
/*   */     //   2284: bastore
/*   */     //   2285: goto -> 2262
/*   */     //   2288: iinc #0, 1
/*   */     //   2291: goto -> 2216
/*   */     //   2294: aload_3
/*   */     //   2295: iconst_1
/*   */     //   2296: invokevirtual else : (I)I
/*   */     //   2299: iconst_1
/*   */     //   2300: if_icmpeq -> 2311
/*   */     //   2303: aload_1
/*   */     //   2304: invokevirtual HZ : ()V
/*   */     //   2307: iconst_m1
/*   */     //   2308: goto -> 2312
/*   */     //   2311: iconst_0
/*   */     //   2312: ireturn
/*   */     //   2313: aload_2
/*   */     //   2314: getfield Tj : I
/*   */     //   2317: ifne -> 2322
/*   */     //   2320: iconst_m1
/*   */     //   2321: ireturn
/*   */     //   2322: aload_0
/*   */     //   2323: getfield ce : I
/*   */     //   2326: ifeq -> 2331
/*   */     //   2329: iconst_m1
/*   */     //   2330: ireturn
/*   */     //   2331: aload_3
/*   */     //   2332: bipush #32
/*   */     //   2334: invokevirtual else : (I)I
/*   */     //   2337: dup
/*   */     //   2338: aload_0
/*   */     //   2339: swap
/*   */     //   2340: putfield wk : I
/*   */     //   2343: ifeq -> 2350
/*   */     //   2346: iconst_m1
/*   */     //   2347: goto -> 2488
/*   */     //   2350: aload_0
/*   */     //   2351: dup
/*   */     //   2352: dup2
/*   */     //   2353: aload_3
/*   */     //   2354: aload_0
/*   */     //   2355: aload_3
/*   */     //   2356: aload_0
/*   */     //   2357: aload_3
/*   */     //   2358: aload_0
/*   */     //   2359: aload_3
/*   */     //   2360: aload_0
/*   */     //   2361: aload_3
/*   */     //   2362: bipush #8
/*   */     //   2364: invokevirtual else : (I)I
/*   */     //   2367: putfield V0 : I
/*   */     //   2370: bipush #32
/*   */     //   2372: invokevirtual else : (I)I
/*   */     //   2375: putfield ce : I
/*   */     //   2378: bipush #32
/*   */     //   2380: invokevirtual else : (I)I
/*   */     //   2383: putfield n40 : I
/*   */     //   2386: bipush #32
/*   */     //   2388: invokevirtual else : (I)I
/*   */     //   2391: putfield N30 : I
/*   */     //   2394: bipush #32
/*   */     //   2396: invokevirtual else : (I)I
/*   */     //   2399: putfield Ww0 : I
/*   */     //   2402: getfield OF : [I
/*   */     //   2405: aload_3
/*   */     //   2406: iconst_4
/*   */     //   2407: invokevirtual else : (I)I
/*   */     //   2410: iconst_1
/*   */     //   2411: swap
/*   */     //   2412: ishl
/*   */     //   2413: iconst_0
/*   */     //   2414: swap
/*   */     //   2415: iastore
/*   */     //   2416: getfield OF : [I
/*   */     //   2419: aload_3
/*   */     //   2420: iconst_4
/*   */     //   2421: invokevirtual else : (I)I
/*   */     //   2424: iconst_1
/*   */     //   2425: swap
/*   */     //   2426: ishl
/*   */     //   2427: iconst_1
/*   */     //   2428: swap
/*   */     //   2429: iastore
/*   */     //   2430: getfield ce : I
/*   */     //   2433: iconst_1
/*   */     //   2434: if_icmplt -> 2483
/*   */     //   2437: aload_0
/*   */     //   2438: getfield V0 : I
/*   */     //   2441: iconst_1
/*   */     //   2442: if_icmplt -> 2483
/*   */     //   2445: aload_0
/*   */     //   2446: getfield OF : [I
/*   */     //   2449: dup
/*   */     //   2450: astore_1
/*   */     //   2451: iconst_0
/*   */     //   2452: iaload
/*   */     //   2453: dup
/*   */     //   2454: istore_2
/*   */     //   2455: bipush #8
/*   */     //   2457: if_icmplt -> 2483
/*   */     //   2460: aload_1
/*   */     //   2461: iconst_1
/*   */     //   2462: iaload
/*   */     //   2463: iload_2
/*   */     //   2464: if_icmplt -> 2483
/*   */     //   2467: aload_3
/*   */     //   2468: iconst_1
/*   */     //   2469: invokevirtual else : (I)I
/*   */     //   2472: iconst_1
/*   */     //   2473: if_icmpeq -> 2479
/*   */     //   2476: goto -> 2483
/*   */     //   2479: iconst_0
/*   */     //   2480: goto -> 2488
/*   */     //   2483: aload_0
/*   */     //   2484: invokevirtual It0 : ()V
/*   */     //   2487: iconst_m1
/*   */     //   2488: ireturn
/*   */     //   2489: iconst_m1
/*   */     //   2490: ireturn
/*   */     //   2491: iconst_m1
/*   */     //   2492: ireturn
/*   */     // Line number table:
/*   */     //   Java source line number -> byte code offset
/*   */     //   #1	-> 36
/*   */     //   #2	-> 59
/*   */     //   #3	-> 97
/*   */     //   #4	-> 108
/*   */     //   #5	-> 205
/*   */     //   #6	-> 265
/*   */     //   #7	-> 729
/*   */     //   #8	-> 1113
/*   */     //   #9	-> 1354
/*   */     //   #10	-> 1491
/*   */     //   #11	-> 1868
/*   */     //   #12	-> 1907
/*   */     //   #13	-> 2110
/*   */     //   #14	-> 2126
/*   */     //   #15	-> 2168
/*   */     //   #16	-> 2179
/*   */     //   #17	-> 2280
/*   */     //   #18	-> 2296
/*   */     //   #19	-> 2314
/*   */     //   #20	-> 2334
/*   */   } }


/* Location:              /Users/vnnsnnt/Documents/Codespace/JavaWorkspace/RedTrainer/src/main/java/org/trainer/client/PokeMMO.jar!/f/Pp0.class
 * Java compiler version: 6 (50.0)
 * JD-Core Version:       1.1.3
 */