package f;

public final class pR implements a70 {
  public pR(mk parammk) {}
  
  public final void SX(int paramInt) {
    // Byte code:
    //   0: iload_1
    //   1: bipush #66
    //   3: if_icmpne -> 253
    //   6: aload_0
    //   7: getfield MS : Lf/mk;
    //   10: getfield Nx : Lf/jF;
    //   13: getfield F2 : Lf/ak0;
    //   16: getfield PH0 : Ljava/lang/StringBuilder;
    //   19: invokevirtual toString : ()Ljava/lang/String;
    //   22: dup
    //   23: astore_1
    //   24: invokevirtual length : ()I
    //   27: ifle -> 442
    //   30: aload_1
    //   31: aload_0
    //   32: getfield MS : Lf/mk;
    //   35: getfield Nx : Lf/jF;
    //   38: ldc ''
    //   40: iconst_0
    //   41: invokevirtual Be0 : (Ljava/lang/String;Z)V
    //   44: ldc ' '
    //   46: invokevirtual split : (Ljava/lang/String;)[Ljava/lang/String;
    //   49: dup
    //   50: astore_2
    //   51: arraylength
    //   52: ifne -> 56
    //   55: return
    //   56: aload_0
    //   57: getfield MS : Lf/mk;
    //   60: getfield vc0 : Ljava/util/ArrayList;
    //   63: invokevirtual size : ()I
    //   66: ifeq -> 95
    //   69: aload_0
    //   70: getfield MS : Lf/mk;
    //   73: getfield vc0 : Ljava/util/ArrayList;
    //   76: dup
    //   77: invokevirtual size : ()I
    //   80: iconst_1
    //   81: isub
    //   82: invokevirtual get : (I)Ljava/lang/Object;
    //   85: checkcast java/lang/String
    //   88: aload_1
    //   89: invokevirtual equals : (Ljava/lang/Object;)Z
    //   92: ifne -> 107
    //   95: aload_0
    //   96: getfield MS : Lf/mk;
    //   99: getfield vc0 : Ljava/util/ArrayList;
    //   102: aload_1
    //   103: invokevirtual add : (Ljava/lang/Object;)Z
    //   106: pop
    //   107: aload_0
    //   108: getfield MS : Lf/mk;
    //   111: dup
    //   112: getfield vc0 : Ljava/util/ArrayList;
    //   115: invokevirtual size : ()I
    //   118: putfield R0 : I
    //   121: getstatic f/PO.mC0 : Lf/PO;
    //   124: getfield kA0 : Ljava/util/ArrayList;
    //   127: invokevirtual iterator : ()Ljava/util/Iterator;
    //   130: astore_3
    //   131: aload_3
    //   132: invokeinterface hasNext : ()Z
    //   137: ifeq -> 213
    //   140: aload_3
    //   141: invokeinterface next : ()Ljava/lang/Object;
    //   146: checkcast f/UA
    //   149: dup
    //   150: astore #4
    //   152: getfield Y60 : Z
    //   155: ifeq -> 170
    //   158: aload_1
    //   159: aload #4
    //   161: getfield Rp0 : Ljava/lang/String;
    //   164: invokestatic M60 : (Ljava/lang/String;Ljava/lang/String;)Z
    //   167: ifne -> 190
    //   170: aload #4
    //   172: getfield Y60 : Z
    //   175: ifne -> 205
    //   178: aload_1
    //   179: aload #4
    //   181: getfield Rp0 : Ljava/lang/String;
    //   184: invokevirtual equalsIgnoreCase : (Ljava/lang/String;)Z
    //   187: ifeq -> 205
    //   190: aload #4
    //   192: aload_1
    //   193: ldc ' '
    //   195: invokevirtual split : (Ljava/lang/String;)[Ljava/lang/String;
    //   198: invokevirtual Vt : ([Ljava/lang/String;)V
    //   201: iconst_1
    //   202: goto -> 206
    //   205: iconst_0
    //   206: ifeq -> 131
    //   209: iconst_1
    //   210: goto -> 214
    //   213: iconst_0
    //   214: ifeq -> 218
    //   217: return
    //   218: aload_0
    //   219: getfield MS : Lf/mk;
    //   222: dup
    //   223: dup2
    //   224: astore_0
    //   225: ldc 'Command '
    //   227: invokestatic df : (Ljava/lang/String;)Ljava/lang/StringBuilder;
    //   230: aload_2
    //   231: iconst_0
    //   232: aaload
    //   233: ldc ' not found'
    //   235: invokestatic Vr0 : (Ljava/lang/StringBuilder;Ljava/lang/String;Ljava/lang/String;)Ljava/lang/String;
    //   238: astore_1
    //   239: monitorenter
    //   240: aload_1
    //   241: ldc 'default'
    //   243: invokevirtual r10 : (Ljava/lang/String;Ljava/lang/String;)V
    //   246: monitorexit
    //   247: goto -> 442
    //   250: aload_0
    //   251: monitorexit
    //   252: athrow
    //   253: iload_1
    //   254: bipush #19
    //   256: if_icmpne -> 304
    //   259: aload_0
    //   260: getfield MS : Lf/mk;
    //   263: dup
    //   264: astore_1
    //   265: getfield R0 : I
    //   268: dup
    //   269: istore_2
    //   270: ifle -> 442
    //   273: aload_0
    //   274: aload_1
    //   275: dup
    //   276: iload_2
    //   277: iconst_1
    //   278: isub
    //   279: dup
    //   280: istore_1
    //   281: putfield R0 : I
    //   284: getfield vc0 : Ljava/util/ArrayList;
    //   287: iload_1
    //   288: invokevirtual get : (I)Ljava/lang/Object;
    //   291: checkcast java/lang/String
    //   294: astore_1
    //   295: getfield MS : Lf/mk;
    //   298: getfield Nx : Lf/jF;
    //   301: goto -> 365
    //   304: iload_1
    //   305: bipush #20
    //   307: if_icmpne -> 387
    //   310: aload_0
    //   311: getfield MS : Lf/mk;
    //   314: dup
    //   315: astore_1
    //   316: getfield R0 : I
    //   319: aload_1
    //   320: getfield vc0 : Ljava/util/ArrayList;
    //   323: invokevirtual size : ()I
    //   326: iconst_1
    //   327: isub
    //   328: if_icmpge -> 442
    //   331: aload_0
    //   332: dup
    //   333: getfield MS : Lf/mk;
    //   336: dup
    //   337: dup
    //   338: getfield R0 : I
    //   341: iconst_1
    //   342: iadd
    //   343: dup
    //   344: istore_1
    //   345: putfield R0 : I
    //   348: getfield vc0 : Ljava/util/ArrayList;
    //   351: iload_1
    //   352: invokevirtual get : (I)Ljava/lang/Object;
    //   355: checkcast java/lang/String
    //   358: astore_1
    //   359: getfield MS : Lf/mk;
    //   362: getfield Nx : Lf/jF;
    //   365: aload_1
    //   366: iconst_0
    //   367: invokevirtual Be0 : (Ljava/lang/String;Z)V
    //   370: aload_0
    //   371: getfield MS : Lf/mk;
    //   374: getfield Nx : Lf/jF;
    //   377: aload_1
    //   378: invokevirtual length : ()I
    //   381: invokevirtual H20 : (I)V
    //   384: goto -> 442
    //   387: iload_1
    //   388: bipush #92
    //   390: if_icmpne -> 416
    //   393: aload_0
    //   394: getfield MS : Lf/mk;
    //   397: getfield jY : Lf/rS;
    //   400: dup
    //   401: getfield PB : Lf/Ja;
    //   404: getfield Ny0 : I
    //   407: bipush #60
    //   409: isub
    //   410: invokevirtual rt : (I)V
    //   413: goto -> 442
    //   416: iload_1
    //   417: bipush #93
    //   419: if_icmpne -> 442
    //   422: aload_0
    //   423: getfield MS : Lf/mk;
    //   426: getfield jY : Lf/rS;
    //   429: dup
    //   430: getfield PB : Lf/Ja;
    //   433: getfield Ny0 : I
    //   436: bipush #60
    //   438: iadd
    //   439: invokevirtual rt : (I)V
    //   442: return
    // Line number table:
    //   Java source line number -> byte code offset
    //   #1	-> 10
    //   #2	-> 13
    //   #3	-> 16
    //   #4	-> 19
    //   #5	-> 24
    //   #6	-> 35
    //   #7	-> 38
    //   #8	-> 44
    //   #9	-> 60
    //   #10	-> 63
    //   #11	-> 73
    //   #12	-> 77
    //   #13	-> 99
    //   #14	-> 103
    //   #15	-> 112
    //   #16	-> 115
    //   #17	-> 118
    //   #18	-> 121
    //   #19	-> 124
    //   #20	-> 127
    //   #21	-> 152
    //   #22	-> 161
    //   #23	-> 219
    //   #24	-> 225
    //   #25	-> 232
    //   #26	-> 233
    //   #27	-> 239
    //   #28	-> 241
    //   #29	-> 260
    //   #30	-> 265
    //   #31	-> 281
    //   #32	-> 284
    //   #33	-> 288
    //   #34	-> 298
    //   #35	-> 311
    //   #36	-> 316
    //   #37	-> 320
    //   #38	-> 323
    //   #39	-> 338
    //   #40	-> 348
    //   #41	-> 352
    //   #42	-> 362
    //   #43	-> 367
    //   #44	-> 371
    //   #45	-> 374
    //   #46	-> 378
    //   #47	-> 397
    //   #48	-> 401
    //   #49	-> 404
    //   #50	-> 410
    //   #51	-> 426
    //   #52	-> 430
    //   #53	-> 433
    //   #54	-> 439
    // Exception table:
    //   from	to	target	type
    //   240	246	250	finally
  }
}


/* Location:              /Users/vnnsnnt/Documents/Codespace/JavaWorkspace/RedTrainer/src/main/java/org/trainer/client/PokeMMO.jar!/f/pR.class
 * Java compiler version: 8 (52.0)
 * JD-Core Version:       1.1.3
 */