package f;

import java.util.ArrayList;

public final class py0 extends Con {
  public static final ik a30 = C00.gd(py0.class);
  
  public final ArrayList Du;
  
  public py0(String paramString, gL0 paramgL0) {
    super(paramString, paramgL0);
    ArrayList arrayList;
    this();
    this.Du = this;
  }
  
  public final void ok0() {
    // Byte code:
    //   0: aload_0
    //   1: dup
    //   2: dup
    //   3: getfield hr0 : Ljava/nio/channels/spi/AbstractSelector;
    //   6: aload_0
    //   7: getfield j8 : I
    //   10: i2l
    //   11: invokevirtual select : (J)I
    //   14: istore_1
    //   15: getfield Du : Ljava/util/ArrayList;
    //   18: dup
    //   19: astore_2
    //   20: monitorenter
    //   21: getfield Du : Ljava/util/ArrayList;
    //   24: invokevirtual iterator : ()Ljava/util/Iterator;
    //   27: astore_3
    //   28: aload_3
    //   29: invokeinterface hasNext : ()Z
    //   34: ifeq -> 53
    //   37: aload_0
    //   38: aload_3
    //   39: invokeinterface next : ()Ljava/lang/Object;
    //   44: checkcast f/LPt3
    //   47: invokevirtual dX : (Lf/LPt3;)V
    //   50: goto -> 28
    //   53: iload_1
    //   54: aload_2
    //   55: aload_0
    //   56: getfield Du : Ljava/util/ArrayList;
    //   59: invokevirtual clear : ()V
    //   62: monitorexit
    //   63: ifeq -> 239
    //   66: aload_0
    //   67: getfield hr0 : Ljava/nio/channels/spi/AbstractSelector;
    //   70: invokevirtual selectedKeys : ()Ljava/util/Set;
    //   73: invokeinterface iterator : ()Ljava/util/Iterator;
    //   78: astore_1
    //   79: aload_1
    //   80: invokeinterface hasNext : ()Z
    //   85: ifeq -> 239
    //   88: aload_1
    //   89: dup
    //   90: invokeinterface next : ()Ljava/lang/Object;
    //   95: checkcast java/nio/channels/SelectionKey
    //   98: astore_2
    //   99: invokeinterface remove : ()V
    //   104: aload_2
    //   105: invokevirtual isValid : ()Z
    //   108: ifne -> 132
    //   111: aload_2
    //   112: invokevirtual attachment : ()Ljava/lang/Object;
    //   115: ifnull -> 79
    //   118: aload_0
    //   119: aload_2
    //   120: invokevirtual attachment : ()Ljava/lang/Object;
    //   123: checkcast f/LPt3
    //   126: invokevirtual dX : (Lf/LPt3;)V
    //   129: goto -> 79
    //   132: aload_2
    //   133: invokevirtual readyOps : ()I
    //   136: dup
    //   137: istore_3
    //   138: iconst_1
    //   139: if_icmpeq -> 231
    //   142: iload_3
    //   143: iconst_4
    //   144: if_icmpeq -> 223
    //   147: iload_3
    //   148: iconst_5
    //   149: if_icmpeq -> 211
    //   152: iload_3
    //   153: bipush #16
    //   155: if_icmpeq -> 204
    //   158: iload_3
    //   159: bipush #17
    //   161: if_icmpeq -> 190
    //   164: getstatic f/py0.a30 : Lf/ik;
    //   167: ldc 'Unsupported readyOps '
    //   169: invokestatic df : (Ljava/lang/String;)Ljava/lang/StringBuilder;
    //   172: aload_2
    //   173: invokevirtual readyOps : ()I
    //   176: invokevirtual append : (I)Ljava/lang/StringBuilder;
    //   179: invokevirtual toString : ()Ljava/lang/String;
    //   182: invokeinterface info : (Ljava/lang/String;)V
    //   187: goto -> 79
    //   190: aload_2
    //   191: dup
    //   192: invokestatic kp0 : (Ljava/nio/channels/SelectionKey;)V
    //   195: invokevirtual isValid : ()Z
    //   198: ifeq -> 79
    //   201: goto -> 231
    //   204: aload_2
    //   205: invokestatic kp0 : (Ljava/nio/channels/SelectionKey;)V
    //   208: goto -> 79
    //   211: aload_2
    //   212: aload_0
    //   213: aload_2
    //   214: invokevirtual ad : (Ljava/nio/channels/SelectionKey;)V
    //   217: invokevirtual isValid : ()Z
    //   220: ifeq -> 79
    //   223: aload_0
    //   224: aload_2
    //   225: invokevirtual prn : (Ljava/nio/channels/SelectionKey;)V
    //   228: goto -> 79
    //   231: aload_0
    //   232: aload_2
    //   233: invokevirtual ad : (Ljava/nio/channels/SelectionKey;)V
    //   236: goto -> 79
    //   239: return
    //   240: astore_0
    //   241: aload_0
    //   242: aload_2
    //   243: monitorexit
    //   244: athrow
    // Line number table:
    //   Java source line number -> byte code offset
    //   #1	-> 15
    //   #2	-> 67
    //   #3	-> 167
    //   #4	-> 173
    //   #5	-> 243
    // Exception table:
    //   from	to	target	type
    //   21	27	240	finally
    //   28	34	240	finally
    //   37	63	240	finally
    //   241	244	240	finally
  }
  
  public final void xl(LPt3 paramLPt3) {
    ArrayList arrayList;
    /* monitor enter ClassFileLocalVariableReferenceExpression{type=ObjectType{java/util/ArrayList}, name=null} */
    try {
      return;
    } finally {
      this = null;
      /* monitor exit ClassFileLocalVariableReferenceExpression{type=ObjectType{java/util/ArrayList}, name=null} */
    } 
  }
}


/* Location:              /Users/vnnsnnt/Documents/Codespace/JavaWorkspace/RedTrainer/src/main/java/org/trainer/client/PokeMMO.jar!/f/py0.class
 * Java compiler version: 8 (52.0)
 * JD-Core Version:       1.1.3
 */