/* 1 */ package f;public final class qO extends Ij implements r60 { public final j40 y10; public Ip WJ; public final Y MG; public G9 qQ; public Un m5; public Un qv0; private void abstract(j40 paramj40) { if (this.zA0 < 0) return;  arrayOfString[0] = paramj40.m(); arrayOfString[1] = Ml0.OH0(this.Oz + 210000); String[] arrayOfString; (arrayOfString = new String[3])[2] = Ml0.OH0(this.h2[this.zA0] + 210000); String str = Ml0.sB(8591, arrayOfString); js.vu0
/* 2 */       .uh(new h70(str, this::hD, this)); } public final StringBuilder pH0; public final dQ Yv; public final int[] h2; public int Oz; public int zA0; public qO(Y paramY, j40 paramj40) { // Byte code:
/*   */     //   0: aload_2
/*   */     //   1: dup
/*   */     //   2: aload_0
/*   */     //   3: aload_1
/*   */     //   4: aload_0
/*   */     //   5: aload_2
/*   */     //   6: aload_0
/*   */     //   7: dup
/*   */     //   8: dup2
/*   */     //   9: dup2
/*   */     //   10: invokespecial <init> : ()V
/*   */     //   13: new java/lang/StringBuilder
/*   */     //   16: dup
/*   */     //   17: invokespecial <init> : ()V
/*   */     //   20: putfield pH0 : Ljava/lang/StringBuilder;
/*   */     //   23: new f/dQ
/*   */     //   26: dup
/*   */     //   27: ldc ''
/*   */     //   29: invokespecial <init> : (Ljava/lang/String;)V
/*   */     //   32: putfield Yv : Lf/dQ;
/*   */     //   35: iconst_m1
/*   */     //   36: putfield zA0 : I
/*   */     //   39: <illegal opcode> run : (Lf/qO;)Ljava/lang/Runnable;
/*   */     //   44: invokevirtual TG0 : (Ljava/lang/Runnable;)V
/*   */     //   47: putfield y10 : Lf/j40;
/*   */     //   50: putfield MG : Lf/Y;
/*   */     //   53: invokevirtual h60 : ()Lf/UD0;
/*   */     //   56: invokevirtual S60 : ()[S
/*   */     //   59: astore_1
/*   */     //   60: iconst_0
/*   */     //   61: istore_3
/*   */     //   62: invokevirtual eC : ()Lf/Q90;
/*   */     //   65: invokevirtual iL : ()Z
/*   */     //   68: ifeq -> 78
/*   */     //   71: aload_1
/*   */     //   72: arraylength
/*   */     //   73: istore #4
/*   */     //   75: goto -> 84
/*   */     //   78: aload_1
/*   */     //   79: arraylength
/*   */     //   80: iconst_1
/*   */     //   81: isub
/*   */     //   82: istore #4
/*   */     //   84: aload_0
/*   */     //   85: iload_3
/*   */     //   86: iload #4
/*   */     //   88: invokestatic range : (II)Ljava/util/stream/IntStream;
/*   */     //   91: aload_1
/*   */     //   92: <illegal opcode> applyAsInt : ([S)Ljava/util/function/IntUnaryOperator;
/*   */     //   97: invokeinterface map : (Ljava/util/function/IntUnaryOperator;)Ljava/util/stream/IntStream;
/*   */     //   102: invokeinterface distinct : ()Ljava/util/stream/IntStream;
/*   */     //   107: <illegal opcode> test : ()Ljava/util/function/IntPredicate;
/*   */     //   112: invokeinterface filter : (Ljava/util/function/IntPredicate;)Ljava/util/stream/IntStream;
/*   */     //   117: invokeinterface toArray : ()[I
/*   */     //   122: dup
/*   */     //   123: astore_3
/*   */     //   124: putfield h2 : [I
/*   */     //   127: aload_3
/*   */     //   128: arraylength
/*   */     //   129: iconst_1
/*   */     //   130: if_icmpgt -> 150
/*   */     //   133: aload_0
/*   */     //   134: getstatic f/km.u4 : Lf/R8;
/*   */     //   137: sipush #6005
/*   */     //   140: invokestatic OH0 : (I)Ljava/lang/String;
/*   */     //   143: invokevirtual Pq : (Ljava/lang/String;)V
/*   */     //   146: invokevirtual close : ()V
/*   */     //   149: return
/*   */     //   150: aload_3
/*   */     //   151: arraylength
/*   */     //   152: anewarray f/Un
/*   */     //   155: astore_3
/*   */     //   156: iconst_0
/*   */     //   157: istore #4
/*   */     //   159: iload #4
/*   */     //   161: aload_0
/*   */     //   162: getfield h2 : [I
/*   */     //   165: arraylength
/*   */     //   166: if_icmpge -> 216
/*   */     //   169: new f/Un
/*   */     //   172: dup
/*   */     //   173: astore #5
/*   */     //   175: aload_0
/*   */     //   176: iload #4
/*   */     //   178: aload_3
/*   */     //   179: iload #4
/*   */     //   181: aload #5
/*   */     //   183: aload_0
/*   */     //   184: getfield h2 : [I
/*   */     //   187: iload #4
/*   */     //   189: iaload
/*   */     //   190: ldc 210000
/*   */     //   192: iadd
/*   */     //   193: invokestatic OH0 : (I)Ljava/lang/String;
/*   */     //   196: invokespecial <init> : (Ljava/lang/String;)V
/*   */     //   199: aload #5
/*   */     //   201: aastore
/*   */     //   202: <illegal opcode> run : (Lf/qO;I)Ljava/lang/Runnable;
/*   */     //   207: invokevirtual tW : (Ljava/lang/Runnable;)V
/*   */     //   210: iinc #4, 1
/*   */     //   213: goto -> 159
/*   */     //   216: aload_0
/*   */     //   217: aload_1
/*   */     //   218: aload_2
/*   */     //   219: invokevirtual eC : ()Lf/Q90;
/*   */     //   222: invokevirtual M7 : ()B
/*   */     //   225: saload
/*   */     //   226: putfield Oz : I
/*   */     //   229: invokestatic XU : ()Z
/*   */     //   232: ifeq -> 244
/*   */     //   235: aload_0
/*   */     //   236: ldc 'mysterious-gem'
/*   */     //   238: invokevirtual Xu : (Ljava/lang/String;)V
/*   */     //   241: goto -> 259
/*   */     //   244: aload_0
/*   */     //   245: dup
/*   */     //   246: ldc 'seed-plant-dialog'
/*   */     //   248: invokevirtual Xu : (Ljava/lang/String;)V
/*   */     //   251: ldc 100031
/*   */     //   253: invokestatic OH0 : (I)Ljava/lang/String;
/*   */     //   256: invokevirtual Lo : (Ljava/lang/String;)V
/*   */     //   259: aload_0
/*   */     //   260: dup
/*   */     //   261: dup2
/*   */     //   262: dup2
/*   */     //   263: dup2
/*   */     //   264: dup2
/*   */     //   265: dup2
/*   */     //   266: new f/Ip
/*   */     //   269: dup
/*   */     //   270: invokespecial <init> : ()V
/*   */     //   273: putfield WJ : Lf/Ip;
/*   */     //   276: new f/G9
/*   */     //   279: dup
/*   */     //   280: astore_1
/*   */     //   281: aload_2
/*   */     //   282: aload_0
/*   */     //   283: aload_1
/*   */     //   284: dup
/*   */     //   285: invokespecial <init> : ()V
/*   */     //   288: putfield qQ : Lf/G9;
/*   */     //   291: invokevirtual zf : (Lf/j40;)V
/*   */     //   294: getfield qQ : Lf/G9;
/*   */     //   297: iconst_0
/*   */     //   298: invokevirtual hC : (Z)V
/*   */     //   301: getfield qQ : Lf/G9;
/*   */     //   304: aload_2
/*   */     //   305: invokestatic M5 : (Lf/j40;)Ljava/lang/String;
/*   */     //   308: invokevirtual Gq0 : (Ljava/lang/Object;)V
/*   */     //   311: new f/dQ
/*   */     //   314: dup
/*   */     //   315: astore_1
/*   */     //   316: aload_2
/*   */     //   317: invokevirtual m : ()Ljava/lang/String;
/*   */     //   320: sipush #8590
/*   */     //   323: swap
/*   */     //   324: invokestatic Go : (ILjava/lang/String;)Ljava/lang/String;
/*   */     //   327: invokespecial <init> : (Ljava/lang/String;)V
/*   */     //   330: new f/Un
/*   */     //   333: dup
/*   */     //   334: bipush #60
/*   */     //   336: invokestatic OH0 : (I)Ljava/lang/String;
/*   */     //   339: invokespecial <init> : (Ljava/lang/String;)V
/*   */     //   342: putfield m5 : Lf/Un;
/*   */     //   345: new f/Un
/*   */     //   348: dup
/*   */     //   349: bipush #53
/*   */     //   351: invokestatic OH0 : (I)Ljava/lang/String;
/*   */     //   354: invokespecial <init> : (Ljava/lang/String;)V
/*   */     //   357: putfield qv0 : Lf/Un;
/*   */     //   360: getfield m5 : Lf/Un;
/*   */     //   363: aload_0
/*   */     //   364: aload_2
/*   */     //   365: <illegal opcode> run : (Lf/qO;Lf/j40;)Ljava/lang/Runnable;
/*   */     //   370: invokevirtual tW : (Ljava/lang/Runnable;)V
/*   */     //   373: getfield m5 : Lf/Un;
/*   */     //   376: iconst_0
/*   */     //   377: invokevirtual sk0 : (Z)V
/*   */     //   380: getfield qv0 : Lf/Un;
/*   */     //   383: aload_0
/*   */     //   384: <illegal opcode> run : (Lf/qO;)Ljava/lang/Runnable;
/*   */     //   389: invokevirtual tW : (Ljava/lang/Runnable;)V
/*   */     //   392: getfield WJ : Lf/Ip;
/*   */     //   395: dup
/*   */     //   396: astore_2
/*   */     //   397: aload_0
/*   */     //   398: dup
/*   */     //   399: dup
/*   */     //   400: aload_2
/*   */     //   401: invokevirtual d7 : ()Lf/cr0;
/*   */     //   404: bipush #15
/*   */     //   406: invokevirtual Aq : (I)Lf/U90;
/*   */     //   409: astore_2
/*   */     //   410: getfield WJ : Lf/Ip;
/*   */     //   413: invokevirtual mE0 : ()Lf/g0;
/*   */     //   416: iconst_1
/*   */     //   417: anewarray f/JG0
/*   */     //   420: dup
/*   */     //   421: aload_0
/*   */     //   422: getfield qQ : Lf/G9;
/*   */     //   425: iconst_0
/*   */     //   426: swap
/*   */     //   427: aastore
/*   */     //   428: aload_2
/*   */     //   429: bipush #15
/*   */     //   431: invokestatic aj0 : (Lf/g0;[Lf/JG0;Lf/U90;I)Lf/U90;
/*   */     //   434: astore_2
/*   */     //   435: getfield WJ : Lf/Ip;
/*   */     //   438: invokevirtual mE0 : ()Lf/g0;
/*   */     //   441: iconst_1
/*   */     //   442: anewarray f/JG0
/*   */     //   445: dup
/*   */     //   446: iconst_0
/*   */     //   447: aload_1
/*   */     //   448: aastore
/*   */     //   449: aload_2
/*   */     //   450: bipush #15
/*   */     //   452: invokestatic aj0 : (Lf/g0;[Lf/JG0;Lf/U90;I)Lf/U90;
/*   */     //   455: aload_0
/*   */     //   456: getfield WJ : Lf/Ip;
/*   */     //   459: invokevirtual mE0 : ()Lf/g0;
/*   */     //   462: aload_3
/*   */     //   463: invokevirtual Mg : ([Lf/JG0;)Lf/U90;
/*   */     //   466: invokevirtual ee0 : (Lf/U90;)Lf/U90;
/*   */     //   469: bipush #15
/*   */     //   471: invokevirtual Aq : (I)Lf/U90;
/*   */     //   474: astore_2
/*   */     //   475: getfield WJ : Lf/Ip;
/*   */     //   478: invokevirtual mE0 : ()Lf/g0;
/*   */     //   481: iconst_1
/*   */     //   482: anewarray f/JG0
/*   */     //   485: dup
/*   */     //   486: aload_0
/*   */     //   487: getfield Yv : Lf/dQ;
/*   */     //   490: iconst_0
/*   */     //   491: swap
/*   */     //   492: aastore
/*   */     //   493: aload_2
/*   */     //   494: bipush #15
/*   */     //   496: invokestatic aj0 : (Lf/g0;[Lf/JG0;Lf/U90;I)Lf/U90;
/*   */     //   499: aload_0
/*   */     //   500: getfield WJ : Lf/Ip;
/*   */     //   503: invokevirtual d7 : ()Lf/cr0;
/*   */     //   506: iconst_2
/*   */     //   507: anewarray f/JG0
/*   */     //   510: dup
/*   */     //   511: dup
/*   */     //   512: aload_0
/*   */     //   513: swap
/*   */     //   514: aload_0
/*   */     //   515: getfield m5 : Lf/Un;
/*   */     //   518: iconst_0
/*   */     //   519: swap
/*   */     //   520: aastore
/*   */     //   521: getfield qv0 : Lf/Un;
/*   */     //   524: iconst_1
/*   */     //   525: swap
/*   */     //   526: aastore
/*   */     //   527: invokevirtual Mg : ([Lf/JG0;)Lf/U90;
/*   */     //   530: invokevirtual ee0 : (Lf/U90;)Lf/U90;
/*   */     //   533: invokevirtual Em0 : ()Lf/U90;
/*   */     //   536: invokevirtual WN : (Lf/U90;)V
/*   */     //   539: getfield WJ : Lf/Ip;
/*   */     //   542: dup
/*   */     //   543: invokevirtual mE0 : ()Lf/g0;
/*   */     //   546: aload_0
/*   */     //   547: getfield WJ : Lf/Ip;
/*   */     //   550: invokevirtual d7 : ()Lf/cr0;
/*   */     //   553: invokevirtual Em0 : ()Lf/U90;
/*   */     //   556: aload_0
/*   */     //   557: getfield qQ : Lf/G9;
/*   */     //   560: invokevirtual Ya : (Lf/JG0;)Lf/U90;
/*   */     //   563: invokevirtual Em0 : ()Lf/U90;
/*   */     //   566: invokevirtual ee0 : (Lf/U90;)Lf/U90;
/*   */     //   569: aload_0
/*   */     //   570: getfield WJ : Lf/Ip;
/*   */     //   573: invokevirtual d7 : ()Lf/cr0;
/*   */     //   576: invokevirtual Em0 : ()Lf/U90;
/*   */     //   579: iconst_1
/*   */     //   580: anewarray f/JG0
/*   */     //   583: dup
/*   */     //   584: iconst_0
/*   */     //   585: aload_1
/*   */     //   586: aastore
/*   */     //   587: invokevirtual Mg : ([Lf/JG0;)Lf/U90;
/*   */     //   590: invokevirtual Em0 : ()Lf/U90;
/*   */     //   593: invokevirtual ee0 : (Lf/U90;)Lf/U90;
/*   */     //   596: aload_0
/*   */     //   597: getfield WJ : Lf/Ip;
/*   */     //   600: invokevirtual d7 : ()Lf/cr0;
/*   */     //   603: invokevirtual Em0 : ()Lf/U90;
/*   */     //   606: aload_3
/*   */     //   607: invokevirtual Mg : ([Lf/JG0;)Lf/U90;
/*   */     //   610: invokevirtual Em0 : ()Lf/U90;
/*   */     //   613: invokevirtual ee0 : (Lf/U90;)Lf/U90;
/*   */     //   616: aload_0
/*   */     //   617: getfield WJ : Lf/Ip;
/*   */     //   620: invokevirtual d7 : ()Lf/cr0;
/*   */     //   623: invokevirtual Em0 : ()Lf/U90;
/*   */     //   626: iconst_1
/*   */     //   627: anewarray f/JG0
/*   */     //   630: dup
/*   */     //   631: aload_0
/*   */     //   632: getfield Yv : Lf/dQ;
/*   */     //   635: iconst_0
/*   */     //   636: swap
/*   */     //   637: aastore
/*   */     //   638: invokevirtual Mg : ([Lf/JG0;)Lf/U90;
/*   */     //   641: invokevirtual Em0 : ()Lf/U90;
/*   */     //   644: invokevirtual ee0 : (Lf/U90;)Lf/U90;
/*   */     //   647: aload_0
/*   */     //   648: getfield WJ : Lf/Ip;
/*   */     //   651: invokevirtual mE0 : ()Lf/g0;
/*   */     //   654: aload_0
/*   */     //   655: getfield m5 : Lf/Un;
/*   */     //   658: invokevirtual Ya : (Lf/JG0;)Lf/U90;
/*   */     //   661: aload_0
/*   */     //   662: getfield qv0 : Lf/Un;
/*   */     //   665: invokevirtual Ya : (Lf/JG0;)Lf/U90;
/*   */     //   668: invokevirtual ee0 : (Lf/U90;)Lf/U90;
/*   */     //   671: invokevirtual rK0 : (Lf/U90;)V
/*   */     //   674: getfield WJ : Lf/Ip;
/*   */     //   677: invokevirtual J8 : (Lf/JG0;)V
/*   */     //   680: return
/*   */     // Line number table:
/*   */     //   Java source line number -> byte code offset
/*   */     //   #1	-> 431
/*   */     //   #2	-> 435
/*   */     //   #3	-> 452
/*   */     //   #4	-> 456
/*   */     //   #5	-> 496
/* 2 */     //   #6	-> 500 } public final void close() { pA pA; qO qO1; if ((qO1 = (pA = pA.Dg0).Tq0) != null) { qO1
/* 3 */         .ra0(); this.Tq0 = null; }
/*   */      }
/*   */ 
/*   */   
/*   */   private void hJ(int paramInt) {
/*   */     this.zA0 = paramInt;
/*   */     this.pH0.setLength(0);
/*   */     if ((paramInt = this.h2[paramInt]) == this.Oz) {
/*   */       this.pH0.append(Ml0.OH0(paramInt + 220000));
/*   */       this.pH0.append("\n\n");
/*   */       arrayOfString[0] = this.y10.m();
/*   */       String[] arrayOfString;
/*   */       (arrayOfString = new String[2])[1] = Ml0.OH0(paramInt + 210000);
/*   */       this.pH0.append(Ml0.sB(8592, arrayOfString));
/*   */       this.m5.sk0(false);
/*   */       this.Yv.E1(this.pH0.toString());
/*   */     } else {
/*   */       this.pH0.append(Ml0.OH0(paramInt + 220000));
/*   */       this.m5.sk0(true);
/*   */       this.Yv.E1(this.pH0.toString());
/*   */     } 
/*   */   }
/*   */   
/*   */   public final void d40() {
/*   */     if (km.XU()) {
/*   */       QI();
/*   */       this.WJ.js0(et.Wi0);
/*   */       this.WJ.Tm(500, 520);
/*   */     } else {
/*   */       super.d40();
/*   */       mM();
/*   */       qB0(et.Wi0);
/*   */     } 
/*   */   }
/*   */   
/*   */   public final void hD() {
/*   */     // Byte code:
/*   */     //   0: aload_0
/*   */     //   1: dup
/*   */     //   2: getstatic f/km.u4 : Lf/R8;
/*   */     //   5: astore_1
/*   */     //   6: getfield MG : Lf/Y;
/*   */     //   9: getfield Lh : Lf/nH0;
/*   */     //   12: dup
/*   */     //   13: getfield p1 : S
/*   */     //   16: istore_2
/*   */     //   17: getfield Wy : I
/*   */     //   20: istore_3
/*   */     //   21: getfield y10 : Lf/j40;
/*   */     //   24: dup
/*   */     //   25: getfield Jg : I
/*   */     //   28: istore #4
/*   */     //   30: iconst_1
/*   */     //   31: istore #5
/*   */     //   33: getfield LPT4 : Lf/UD0;
/*   */     //   36: getfield Po : [S
/*   */     //   39: dup
/*   */     //   40: astore #6
/*   */     //   42: aload_0
/*   */     //   43: getfield h2 : [I
/*   */     //   46: aload_0
/*   */     //   47: getfield zA0 : I
/*   */     //   50: iaload
/*   */     //   51: i2s
/*   */     //   52: istore_0
/*   */     //   53: iconst_0
/*   */     //   54: istore #7
/*   */     //   56: ifnull -> 95
/*   */     //   59: aload #6
/*   */     //   61: arraylength
/*   */     //   62: iconst_1
/*   */     //   63: if_icmpge -> 69
/*   */     //   66: goto -> 95
/*   */     //   69: iload #7
/*   */     //   71: aload #6
/*   */     //   73: arraylength
/*   */     //   74: if_icmpge -> 95
/*   */     //   77: iload_0
/*   */     //   78: aload #6
/*   */     //   80: iload #7
/*   */     //   82: saload
/*   */     //   83: if_icmpne -> 89
/*   */     //   86: goto -> 98
/*   */     //   89: iinc #7, 1
/*   */     //   92: goto -> 69
/*   */     //   95: iconst_m1
/*   */     //   96: istore #7
/*   */     //   98: aload_1
/*   */     //   99: iload #7
/*   */     //   101: i2b
/*   */     //   102: istore_0
/*   */     //   103: iload_2
/*   */     //   104: iload_3
/*   */     //   105: iload #4
/*   */     //   107: iload #5
/*   */     //   109: iload_0
/*   */     //   110: invokevirtual tq0 : (SIISB)V
/*   */     //   113: getstatic f/pA.Dg0 : Lf/pA;
/*   */     //   116: dup
/*   */     //   117: astore_0
/*   */     //   118: getfield Tq0 : Lf/qO;
/*   */     //   121: dup
/*   */     //   122: astore_1
/*   */     //   123: ifnull -> 136
/*   */     //   126: aload_0
/*   */     //   127: aload_1
/*   */     //   128: invokevirtual ra0 : ()Z
/*   */     //   131: pop
/*   */     //   132: aconst_null
/*   */     //   133: putfield Tq0 : Lf/qO;
/*   */     //   136: return
/*   */     // Line number table:
/*   */     //   Java source line number -> byte code offset
/*   */     //   #1	-> 9
/*   */     //   #2	-> 13
/*   */     //   #3	-> 17
/*   */     //   #4	-> 21
/*   */     //   #5	-> 25
/*   */     //   #6	-> 33
/*   */     //   #7	-> 36
/*   */     //   #8	-> 43
/*   */     //   #9	-> 61
/*   */     //   #10	-> 110
/*   */     //   #11	-> 113
/*   */     //   #12	-> 118
/*   */     //   #13	-> 128
/*   */   } }


/* Location:              /Users/vnnsnnt/Documents/Codespace/JavaWorkspace/RedTrainer/src/main/java/org/trainer/client/PokeMMO.jar!/f/qO.class
 * Java compiler version: 8 (52.0)
 * JD-Core Version:       1.1.3
 */