/*  1 */ package f;public final class qt0 extends Wr implements r60 { public final Tl0 nf0; public rS M6; public Ip ad0; public int MY; public int mH0; public final void d40() { this.ad0.uh0(186, 10); this.ad0.mM(); this.ad0.lu0 = new db(0, 0); this.ad0
/*  2 */       .h20(); int i; Iterator iterator;
/*  3 */     for (i = this.le0.size() * 30 + 30, iterator = this.Lu.iterator(); iterator.hasNext();) i += ((dQ)iterator.next())
/*  4 */         .HC;  if (i > 250) i = 250;  this
/*  5 */       .M6.uh0(210, i); this.M6.mM(); this.M6
/*  6 */       .kN(7, 7, 7, 7);
/*  7 */     uh0(200, 1); mM(); super.d40(); } public uQ w0; public int os; public ArrayList le0; public ArrayList Lu; public qt0(Tl0 paramTl0) { rS rS1; this.MY = 0; this.mH0 = 0; this.w0 = null; this.os = -1; this.le0 = new ArrayList(); this.Lu = new ArrayList(); this.nf0 = paramTl0; Xu("base-frame-padded"); (new Ip()).rK0((this.ad0 = new Ip()).mE0()); this.ad0.WN(this.ad0.d7()); this(this.ad0); this.M6 = new rS(); J8(rS1); Tl0(); } public final void Tl0() { // Byte code:
/*    */     //   0: aload_0
/*    */     //   1: dup
/*    */     //   2: dup2
/*    */     //   3: dup2
/*    */     //   4: ldc ''
/*    */     //   6: astore_1
/*    */     //   7: iconst_0
/*    */     //   8: putfield mH0 : I
/*    */     //   11: getfield le0 : Ljava/util/ArrayList;
/*    */     //   14: invokevirtual clear : ()V
/*    */     //   17: getfield Lu : Ljava/util/ArrayList;
/*    */     //   20: invokevirtual clear : ()V
/*    */     //   23: getfield ad0 : Lf/Ip;
/*    */     //   26: getfield o30 : Lf/U90;
/*    */     //   29: invokevirtual Hb : ()V
/*    */     //   32: getfield ad0 : Lf/Ip;
/*    */     //   35: getfield Xz0 : Lf/U90;
/*    */     //   38: invokevirtual Hb : ()V
/*    */     //   41: getfield MY : I
/*    */     //   44: dup
/*    */     //   45: istore_2
/*    */     //   46: ifne -> 113
/*    */     //   49: aload_0
/*    */     //   50: getstatic f/s10.hU : Lf/s10;
/*    */     //   53: dup
/*    */     //   54: astore_2
/*    */     //   55: aload_0
/*    */     //   56: aload_2
/*    */     //   57: aload_0
/*    */     //   58: aload_2
/*    */     //   59: iconst_1
/*    */     //   60: iconst_5
/*    */     //   61: iconst_0
/*    */     //   62: invokevirtual vG0 : (BBI)Ljava/lang/String;
/*    */     //   65: iconst_1
/*    */     //   66: swap
/*    */     //   67: invokevirtual IJ : (ILjava/lang/String;)Lf/Un;
/*    */     //   70: pop
/*    */     //   71: iconst_1
/*    */     //   72: iconst_5
/*    */     //   73: iconst_1
/*    */     //   74: invokevirtual vG0 : (BBI)Ljava/lang/String;
/*    */     //   77: iconst_2
/*    */     //   78: swap
/*    */     //   79: invokevirtual IJ : (ILjava/lang/String;)Lf/Un;
/*    */     //   82: pop
/*    */     //   83: iconst_1
/*    */     //   84: iconst_5
/*    */     //   85: iconst_2
/*    */     //   86: invokevirtual vG0 : (BBI)Ljava/lang/String;
/*    */     //   89: new f/as
/*    */     //   92: dup
/*    */     //   93: invokespecial <init> : ()V
/*    */     //   96: invokevirtual yI : (Ljava/lang/String;Ljava/lang/Runnable;)Lf/Un;
/*    */     //   99: pop
/*    */     //   100: iconst_0
/*    */     //   101: putstatic f/ro.l10 : B
/*    */     //   104: getstatic f/wJ0.Nf0 : Lf/wJ0;
/*    */     //   107: invokevirtual dz : ()V
/*    */     //   110: goto -> 1188
/*    */     //   113: iload_2
/*    */     //   114: iconst_1
/*    */     //   115: if_icmpne -> 232
/*    */     //   118: aload_0
/*    */     //   119: dup
/*    */     //   120: dup2
/*    */     //   121: getstatic f/s10.hU : Lf/s10;
/*    */     //   124: iconst_1
/*    */     //   125: iconst_5
/*    */     //   126: iconst_0
/*    */     //   127: invokevirtual vG0 : (BBI)Ljava/lang/String;
/*    */     //   130: astore_1
/*    */     //   131: ldc 270250
/*    */     //   133: invokestatic OH0 : (I)Ljava/lang/String;
/*    */     //   136: bipush #100
/*    */     //   138: swap
/*    */     //   139: invokevirtual IJ : (ILjava/lang/String;)Lf/Un;
/*    */     //   142: dup
/*    */     //   143: ldc 270255
/*    */     //   145: invokestatic OH0 : (I)Ljava/lang/String;
/*    */     //   148: putfield z4 : Ljava/lang/Object;
/*    */     //   151: invokevirtual zn : ()V
/*    */     //   154: ldc 270251
/*    */     //   156: invokestatic OH0 : (I)Ljava/lang/String;
/*    */     //   159: new f/oi
/*    */     //   162: dup
/*    */     //   163: aload_0
/*    */     //   164: invokespecial <init> : (Lf/qt0;)V
/*    */     //   167: invokevirtual yI : (Ljava/lang/String;Ljava/lang/Runnable;)Lf/Un;
/*    */     //   170: dup
/*    */     //   171: ldc 270256
/*    */     //   173: invokestatic OH0 : (I)Ljava/lang/String;
/*    */     //   176: putfield z4 : Ljava/lang/Object;
/*    */     //   179: invokevirtual zn : ()V
/*    */     //   182: ldc 270252
/*    */     //   184: invokestatic OH0 : (I)Ljava/lang/String;
/*    */     //   187: bipush #102
/*    */     //   189: swap
/*    */     //   190: invokevirtual IJ : (ILjava/lang/String;)Lf/Un;
/*    */     //   193: dup
/*    */     //   194: ldc 270257
/*    */     //   196: invokestatic OH0 : (I)Ljava/lang/String;
/*    */     //   199: putfield z4 : Ljava/lang/Object;
/*    */     //   202: invokevirtual zn : ()V
/*    */     //   205: ldc 270253
/*    */     //   207: invokestatic OH0 : (I)Ljava/lang/String;
/*    */     //   210: iconst_0
/*    */     //   211: swap
/*    */     //   212: invokevirtual IJ : (ILjava/lang/String;)Lf/Un;
/*    */     //   215: astore_2
/*    */     //   216: ldc 270258
/*    */     //   218: invokestatic OH0 : (I)Ljava/lang/String;
/*    */     //   221: ldc '|br|'
/*    */     //   223: ldc '\\n'
/*    */     //   225: invokevirtual replace : (Ljava/lang/CharSequence;Ljava/lang/CharSequence;)Ljava/lang/String;
/*    */     //   228: astore_3
/*    */     //   229: goto -> 1179
/*    */     //   232: iload_2
/*    */     //   233: iconst_2
/*    */     //   234: if_icmpne -> 305
/*    */     //   237: aload_0
/*    */     //   238: dup
/*    */     //   239: dup2
/*    */     //   240: getstatic f/qf0.Qb0 : [Lf/LPT1;
/*    */     //   243: ldc 271017642
/*    */     //   245: swap
/*    */     //   246: invokestatic Sz : (I[Lf/LPT1;)Ljava/lang/String;
/*    */     //   249: invokevirtual qc0 : (Ljava/lang/String;)V
/*    */     //   252: bipush #50
/*    */     //   254: invokestatic OH0 : (I)Ljava/lang/String;
/*    */     //   257: invokevirtual toUpperCase : ()Ljava/lang/String;
/*    */     //   260: new f/sL0
/*    */     //   263: dup
/*    */     //   264: invokespecial <init> : ()V
/*    */     //   267: invokevirtual yI : (Ljava/lang/String;Ljava/lang/Runnable;)Lf/Un;
/*    */     //   270: pop
/*    */     //   271: iconst_1
/*    */     //   272: putfield mH0 : I
/*    */     //   275: bipush #51
/*    */     //   277: invokestatic OH0 : (I)Ljava/lang/String;
/*    */     //   280: invokevirtual toUpperCase : ()Ljava/lang/String;
/*    */     //   283: iconst_0
/*    */     //   284: swap
/*    */     //   285: invokevirtual IJ : (ILjava/lang/String;)Lf/Un;
/*    */     //   288: astore_2
/*    */     //   289: ldc 270258
/*    */     //   291: invokestatic OH0 : (I)Ljava/lang/String;
/*    */     //   294: ldc '|br|'
/*    */     //   296: ldc '\\n'
/*    */     //   298: invokevirtual replace : (Ljava/lang/CharSequence;Ljava/lang/CharSequence;)Ljava/lang/String;
/*    */     //   301: astore_3
/*    */     //   302: goto -> 1179
/*    */     //   305: iload_2
/*    */     //   306: iconst_3
/*    */     //   307: if_icmpne -> 408
/*    */     //   310: aload_0
/*    */     //   311: dup
/*    */     //   312: dup
/*    */     //   313: dup2
/*    */     //   314: iconst_1
/*    */     //   315: newarray byte
/*    */     //   317: dup
/*    */     //   318: astore_2
/*    */     //   319: iconst_0
/*    */     //   320: iconst_2
/*    */     //   321: bastore
/*    */     //   322: iconst_1
/*    */     //   323: anewarray java/lang/String
/*    */     //   326: dup
/*    */     //   327: astore_3
/*    */     //   328: aload_0
/*    */     //   329: getfield w0 : Lf/uQ;
/*    */     //   332: getfield L1 : Lf/lj0;
/*    */     //   335: invokevirtual s60 : ()Ljava/lang/String;
/*    */     //   338: iconst_0
/*    */     //   339: swap
/*    */     //   340: aastore
/*    */     //   341: ldc 270309
/*    */     //   343: aload_2
/*    */     //   344: aload_3
/*    */     //   345: invokestatic Nq0 : (I[B[Ljava/lang/String;)Ljava/lang/String;
/*    */     //   348: invokevirtual qc0 : (Ljava/lang/String;)V
/*    */     //   351: bipush #50
/*    */     //   353: invokestatic OH0 : (I)Ljava/lang/String;
/*    */     //   356: invokevirtual toUpperCase : ()Ljava/lang/String;
/*    */     //   359: new f/Xd
/*    */     //   362: dup
/*    */     //   363: aload_0
/*    */     //   364: invokespecial <init> : (Lf/qt0;)V
/*    */     //   367: invokevirtual yI : (Ljava/lang/String;Ljava/lang/Runnable;)Lf/Un;
/*    */     //   370: pop
/*    */     //   371: iconst_1
/*    */     //   372: putfield mH0 : I
/*    */     //   375: bipush #51
/*    */     //   377: invokestatic OH0 : (I)Ljava/lang/String;
/*    */     //   380: invokevirtual toUpperCase : ()Ljava/lang/String;
/*    */     //   383: astore_2
/*    */     //   384: getfield os : I
/*    */     //   387: aload_2
/*    */     //   388: invokevirtual IJ : (ILjava/lang/String;)Lf/Un;
/*    */     //   391: astore_2
/*    */     //   392: ldc 270258
/*    */     //   394: invokestatic OH0 : (I)Ljava/lang/String;
/*    */     //   397: ldc '|br|'
/*    */     //   399: ldc '\\n'
/*    */     //   401: invokevirtual replace : (Ljava/lang/CharSequence;Ljava/lang/CharSequence;)Ljava/lang/String;
/*    */     //   404: astore_3
/*    */     //   405: goto -> 1179
/*    */     //   408: iload_2
/*    */     //   409: bipush #100
/*    */     //   411: if_icmpeq -> 1016
/*    */     //   414: iload_2
/*    */     //   415: bipush #102
/*    */     //   417: if_icmpne -> 423
/*    */     //   420: goto -> 1016
/*    */     //   423: iload_2
/*    */     //   424: sipush #1000
/*    */     //   427: if_icmplt -> 437
/*    */     //   430: iload_2
/*    */     //   431: sipush #1010
/*    */     //   434: if_icmple -> 451
/*    */     //   437: iload_2
/*    */     //   438: sipush #1020
/*    */     //   441: if_icmplt -> 1188
/*    */     //   444: iload_2
/*    */     //   445: sipush #1030
/*    */     //   448: if_icmpgt -> 1188
/*    */     //   451: iload_2
/*    */     //   452: dup
/*    */     //   453: sipush #1000
/*    */     //   456: isub
/*    */     //   457: istore_1
/*    */     //   458: bipush #100
/*    */     //   460: istore_3
/*    */     //   461: sipush #1020
/*    */     //   464: if_icmplt -> 483
/*    */     //   467: iload_2
/*    */     //   468: sipush #1030
/*    */     //   471: if_icmpgt -> 483
/*    */     //   474: iload_2
/*    */     //   475: sipush #1020
/*    */     //   478: isub
/*    */     //   479: istore_1
/*    */     //   480: bipush #102
/*    */     //   482: istore_3
/*    */     //   483: iload_1
/*    */     //   484: getstatic f/km.u4 : Lf/R8;
/*    */     //   487: getstatic f/CJ.ST : Lf/CJ;
/*    */     //   490: invokevirtual Y40 : (Lf/CJ;)Lf/hP;
/*    */     //   493: astore_2
/*    */     //   494: ldc 270200
/*    */     //   496: iadd
/*    */     //   497: invokestatic OH0 : (I)Ljava/lang/String;
/*    */     //   500: astore #4
/*    */     //   502: new f/qw0
/*    */     //   505: dup
/*    */     //   506: astore #5
/*    */     //   508: invokespecial <init> : ()V
/*    */     //   511: getstatic f/Tl0.yY : [Lf/Tl0;
/*    */     //   514: dup
/*    */     //   515: astore #6
/*    */     //   517: arraylength
/*    */     //   518: istore #7
/*    */     //   520: iconst_0
/*    */     //   521: istore #8
/*    */     //   523: iload #8
/*    */     //   525: iload #7
/*    */     //   527: if_icmpge -> 670
/*    */     //   530: aload #6
/*    */     //   532: iload #8
/*    */     //   534: aaload
/*    */     //   535: getstatic f/km.u4 : Lf/R8;
/*    */     //   538: getfield YS : [Lf/Dm0;
/*    */     //   541: swap
/*    */     //   542: getfield uQ : B
/*    */     //   545: aaload
/*    */     //   546: dup
/*    */     //   547: astore #9
/*    */     //   549: ifnonnull -> 555
/*    */     //   552: goto -> 658
/*    */     //   555: aload #9
/*    */     //   557: dup
/*    */     //   558: monitorenter
/*    */     //   559: invokevirtual CoN : ()Ljava/util/List;
/*    */     //   562: iconst_0
/*    */     //   563: anewarray f/mq
/*    */     //   566: astore #10
/*    */     //   568: checkcast java/util/ArrayList
/*    */     //   571: aload #10
/*    */     //   573: invokevirtual toArray : ([Ljava/lang/Object;)[Ljava/lang/Object;
/*    */     //   576: checkcast [Lf/mq;
/*    */     //   579: dup
/*    */     //   580: astore #10
/*    */     //   582: aload #9
/*    */     //   584: monitorexit
/*    */     //   585: arraylength
/*    */     //   586: istore #9
/*    */     //   588: iconst_0
/*    */     //   589: istore #11
/*    */     //   591: iload #11
/*    */     //   593: iload #9
/*    */     //   595: if_icmpge -> 658
/*    */     //   598: aload #5
/*    */     //   600: aload #10
/*    */     //   602: iload #11
/*    */     //   604: aaload
/*    */     //   605: dup
/*    */     //   606: astore #12
/*    */     //   608: getfield Ol : S
/*    */     //   611: invokevirtual Z90 : (S)Ljava/lang/Object;
/*    */     //   614: checkcast java/util/concurrent/atomic/AtomicInteger
/*    */     //   617: dup
/*    */     //   618: astore #13
/*    */     //   620: ifnonnull -> 646
/*    */     //   623: aload #5
/*    */     //   625: aload #12
/*    */     //   627: new java/util/concurrent/atomic/AtomicInteger
/*    */     //   630: dup
/*    */     //   631: astore #13
/*    */     //   633: iconst_0
/*    */     //   634: invokespecial <init> : (I)V
/*    */     //   637: getfield Ol : S
/*    */     //   640: aload #13
/*    */     //   642: invokevirtual Vh0 : (SLjava/lang/Object;)Ljava/lang/Object;
/*    */     //   645: pop
/*    */     //   646: aload #13
/*    */     //   648: invokevirtual incrementAndGet : ()I
/*    */     //   651: pop
/*    */     //   652: iinc #11, 1
/*    */     //   655: goto -> 591
/*    */     //   658: iinc #8, 1
/*    */     //   661: goto -> 523
/*    */     //   664: astore_0
/*    */     //   665: aload_0
/*    */     //   666: aload #9
/*    */     //   668: monitorexit
/*    */     //   669: athrow
/*    */     //   670: aload_2
/*    */     //   671: dup
/*    */     //   672: dup
/*    */     //   673: getfield p20 : Ljava/util/HashMap;
/*    */     //   676: dup
/*    */     //   677: astore_2
/*    */     //   678: monitorenter
/*    */     //   679: getfield p20 : Ljava/util/HashMap;
/*    */     //   682: invokevirtual size : ()I
/*    */     //   685: anewarray f/uQ
/*    */     //   688: astore #6
/*    */     //   690: getfield p20 : Ljava/util/HashMap;
/*    */     //   693: invokevirtual values : ()Ljava/util/Collection;
/*    */     //   696: aload #6
/*    */     //   698: invokeinterface toArray : ([Ljava/lang/Object;)[Ljava/lang/Object;
/*    */     //   703: checkcast [Lf/uQ;
/*    */     //   706: dup
/*    */     //   707: dup
/*    */     //   708: astore #6
/*    */     //   710: aload_2
/*    */     //   711: monitorexit
/*    */     //   712: invokestatic asList : ([Ljava/lang/Object;)Ljava/util/List;
/*    */     //   715: new f/vM
/*    */     //   718: dup
/*    */     //   719: invokespecial <init> : ()V
/*    */     //   722: invokestatic sort : (Ljava/util/List;Ljava/util/Comparator;)V
/*    */     //   725: arraylength
/*    */     //   726: istore_2
/*    */     //   727: iconst_0
/*    */     //   728: istore #7
/*    */     //   730: iload #7
/*    */     //   732: iload_2
/*    */     //   733: if_icmpge -> 956
/*    */     //   736: aload #5
/*    */     //   738: aload #6
/*    */     //   740: iload #7
/*    */     //   742: aaload
/*    */     //   743: dup
/*    */     //   744: astore #8
/*    */     //   746: iconst_0
/*    */     //   747: istore #9
/*    */     //   749: getfield wj : Lf/Xm;
/*    */     //   752: getfield eS : S
/*    */     //   755: invokevirtual Z90 : (S)Ljava/lang/Object;
/*    */     //   758: checkcast java/util/concurrent/atomic/AtomicInteger
/*    */     //   761: dup
/*    */     //   762: astore #10
/*    */     //   764: ifnull -> 814
/*    */     //   767: aload #10
/*    */     //   769: iconst_1
/*    */     //   770: istore #9
/*    */     //   772: invokevirtual decrementAndGet : ()I
/*    */     //   775: iconst_1
/*    */     //   776: if_icmpge -> 814
/*    */     //   779: aload #5
/*    */     //   781: aload #8
/*    */     //   783: getfield wj : Lf/Xm;
/*    */     //   786: getfield eS : S
/*    */     //   789: invokevirtual kc0 : (S)I
/*    */     //   792: dup
/*    */     //   793: istore #10
/*    */     //   795: iflt -> 814
/*    */     //   798: aload #5
/*    */     //   800: iload #10
/*    */     //   802: aload #5
/*    */     //   804: getfield TH0 : [Ljava/lang/Object;
/*    */     //   807: iload #10
/*    */     //   809: aaload
/*    */     //   810: pop
/*    */     //   811: invokevirtual Id : (I)V
/*    */     //   814: aload #8
/*    */     //   816: getfield L1 : Lf/lj0;
/*    */     //   819: getfield kq0 : B
/*    */     //   822: iload_1
/*    */     //   823: if_icmpne -> 950
/*    */     //   826: iload #9
/*    */     //   828: new java/lang/StringBuilder
/*    */     //   831: dup
/*    */     //   832: aload #8
/*    */     //   834: swap
/*    */     //   835: invokespecial <init> : ()V
/*    */     //   838: getfield L1 : Lf/lj0;
/*    */     //   841: invokevirtual s60 : ()Ljava/lang/String;
/*    */     //   844: invokevirtual append : (Ljava/lang/String;)Ljava/lang/StringBuilder;
/*    */     //   847: astore #10
/*    */     //   849: ifeq -> 860
/*    */     //   852: ldc_w ' - PLACED'
/*    */     //   855: astore #11
/*    */     //   857: goto -> 864
/*    */     //   860: ldc ''
/*    */     //   862: astore #11
/*    */     //   864: aload #8
/*    */     //   866: aload_0
/*    */     //   867: aload #10
/*    */     //   869: aload #11
/*    */     //   871: invokevirtual append : (Ljava/lang/String;)Ljava/lang/StringBuilder;
/*    */     //   874: invokevirtual toString : ()Ljava/lang/String;
/*    */     //   877: new f/hg
/*    */     //   880: dup
/*    */     //   881: aload_0
/*    */     //   882: iload_3
/*    */     //   883: iload #9
/*    */     //   885: aload #8
/*    */     //   887: invokespecial <init> : (Lf/qt0;IZLf/uQ;)V
/*    */     //   890: invokevirtual yI : (Ljava/lang/String;Ljava/lang/Runnable;)Lf/Un;
/*    */     //   893: astore #8
/*    */     //   895: getfield L1 : Lf/lj0;
/*    */     //   898: dup
/*    */     //   899: astore #9
/*    */     //   901: getfield vh : Z
/*    */     //   904: ifne -> 918
/*    */     //   907: sipush #1451
/*    */     //   910: invokestatic OH0 : (I)Ljava/lang/String;
/*    */     //   913: astore #9
/*    */     //   915: goto -> 932
/*    */     //   918: aload #9
/*    */     //   920: getfield Pu0 : S
/*    */     //   923: ldc_w 295000
/*    */     //   926: iadd
/*    */     //   927: invokestatic OH0 : (I)Ljava/lang/String;
/*    */     //   930: astore #9
/*    */     //   932: aload #8
/*    */     //   934: dup
/*    */     //   935: aload #9
/*    */     //   937: ldc '|br|'
/*    */     //   939: ldc '\\n'
/*    */     //   941: invokevirtual replace : (Ljava/lang/CharSequence;Ljava/lang/CharSequence;)Ljava/lang/String;
/*    */     //   944: putfield z4 : Ljava/lang/Object;
/*    */     //   947: invokevirtual zn : ()V
/*    */     //   950: iinc #7, 1
/*    */     //   953: goto -> 730
/*    */     //   956: aload_0
/*    */     //   957: getfield le0 : Ljava/util/ArrayList;
/*    */     //   960: invokevirtual isEmpty : ()Z
/*    */     //   963: ifeq -> 976
/*    */     //   966: aload_0
/*    */     //   967: ldc_w 270312
/*    */     //   970: invokestatic OH0 : (I)Ljava/lang/String;
/*    */     //   973: invokevirtual qc0 : (Ljava/lang/String;)V
/*    */     //   976: aload_0
/*    */     //   977: iload_3
/*    */     //   978: ldc 270253
/*    */     //   980: invokestatic OH0 : (I)Ljava/lang/String;
/*    */     //   983: invokevirtual IJ : (ILjava/lang/String;)Lf/Un;
/*    */     //   986: dup
/*    */     //   987: ldc 270258
/*    */     //   989: invokestatic OH0 : (I)Ljava/lang/String;
/*    */     //   992: ldc '|br|'
/*    */     //   994: ldc '\\n'
/*    */     //   996: invokevirtual replace : (Ljava/lang/CharSequence;Ljava/lang/CharSequence;)Ljava/lang/String;
/*    */     //   999: putfield z4 : Ljava/lang/Object;
/*    */     //   1002: invokevirtual zn : ()V
/*    */     //   1005: aload #4
/*    */     //   1007: astore_1
/*    */     //   1008: goto -> 1188
/*    */     //   1011: astore_0
/*    */     //   1012: aload_0
/*    */     //   1013: aload_2
/*    */     //   1014: monitorexit
/*    */     //   1015: athrow
/*    */     //   1016: iload_2
/*    */     //   1017: bipush #100
/*    */     //   1019: if_icmpne -> 1031
/*    */     //   1022: ldc 270250
/*    */     //   1024: invokestatic OH0 : (I)Ljava/lang/String;
/*    */     //   1027: astore_1
/*    */     //   1028: goto -> 1037
/*    */     //   1031: ldc 270252
/*    */     //   1033: invokestatic OH0 : (I)Ljava/lang/String;
/*    */     //   1036: astore_1
/*    */     //   1037: aload_0
/*    */     //   1038: getstatic f/km.u4 : Lf/R8;
/*    */     //   1041: getstatic f/CJ.ST : Lf/CJ;
/*    */     //   1044: invokevirtual Y40 : (Lf/CJ;)Lf/hP;
/*    */     //   1047: astore_2
/*    */     //   1048: iconst_2
/*    */     //   1049: anewarray java/lang/String
/*    */     //   1052: dup
/*    */     //   1053: dup
/*    */     //   1054: astore_3
/*    */     //   1055: new java/lang/StringBuilder
/*    */     //   1058: dup
/*    */     //   1059: aload_2
/*    */     //   1060: swap
/*    */     //   1061: invokespecial <init> : ()V
/*    */     //   1064: getfield p20 : Ljava/util/HashMap;
/*    */     //   1067: invokevirtual size : ()I
/*    */     //   1070: invokevirtual append : (I)Ljava/lang/StringBuilder;
/*    */     //   1073: ldc ''
/*    */     //   1075: invokevirtual append : (Ljava/lang/String;)Ljava/lang/StringBuilder;
/*    */     //   1078: invokevirtual toString : ()Ljava/lang/String;
/*    */     //   1081: iconst_0
/*    */     //   1082: swap
/*    */     //   1083: aastore
/*    */     //   1084: new java/lang/StringBuilder
/*    */     //   1087: dup
/*    */     //   1088: invokespecial <init> : ()V
/*    */     //   1091: bipush #80
/*    */     //   1093: invokevirtual append : (I)Ljava/lang/StringBuilder;
/*    */     //   1096: ldc ''
/*    */     //   1098: invokevirtual append : (Ljava/lang/String;)Ljava/lang/StringBuilder;
/*    */     //   1101: invokevirtual toString : ()Ljava/lang/String;
/*    */     //   1104: iconst_1
/*    */     //   1105: swap
/*    */     //   1106: aastore
/*    */     //   1107: sipush #6754
/*    */     //   1110: aload_3
/*    */     //   1111: invokestatic sB : (I[Ljava/lang/String;)Ljava/lang/String;
/*    */     //   1114: invokevirtual qc0 : (Ljava/lang/String;)V
/*    */     //   1117: iconst_0
/*    */     //   1118: istore_2
/*    */     //   1119: iload_2
/*    */     //   1120: bipush #8
/*    */     //   1122: if_icmpge -> 1154
/*    */     //   1125: aload_0
/*    */     //   1126: dup
/*    */     //   1127: iload_2
/*    */     //   1128: ldc 270200
/*    */     //   1130: iadd
/*    */     //   1131: invokestatic OH0 : (I)Ljava/lang/String;
/*    */     //   1134: astore_3
/*    */     //   1135: getfield MY : I
/*    */     //   1138: bipush #10
/*    */     //   1140: imul
/*    */     //   1141: iload_2
/*    */     //   1142: iadd
/*    */     //   1143: aload_3
/*    */     //   1144: invokevirtual IJ : (ILjava/lang/String;)Lf/Un;
/*    */     //   1147: pop
/*    */     //   1148: iinc #2, 1
/*    */     //   1151: goto -> 1119
/*    */     //   1154: aload_0
/*    */     //   1155: ldc 270253
/*    */     //   1157: invokestatic OH0 : (I)Ljava/lang/String;
/*    */     //   1160: iconst_1
/*    */     //   1161: swap
/*    */     //   1162: invokevirtual IJ : (ILjava/lang/String;)Lf/Un;
/*    */     //   1165: astore_2
/*    */     //   1166: ldc 270258
/*    */     //   1168: invokestatic OH0 : (I)Ljava/lang/String;
/*    */     //   1171: ldc '|br|'
/*    */     //   1173: ldc '\\n'
/*    */     //   1175: invokevirtual replace : (Ljava/lang/CharSequence;Ljava/lang/CharSequence;)Ljava/lang/String;
/*    */     //   1178: astore_3
/*    */     //   1179: aload_2
/*    */     //   1180: dup
/*    */     //   1181: aload_3
/*    */     //   1182: putfield z4 : Ljava/lang/Object;
/*    */     //   1185: invokevirtual zn : ()V
/*    */     //   1188: aload_0
/*    */     //   1189: dup
/*    */     //   1190: dup
/*    */     //   1191: dup2
/*    */     //   1192: aload_1
/*    */     //   1193: invokevirtual Lo : (Ljava/lang/String;)V
/*    */     //   1196: getfield ad0 : Lf/Ip;
/*    */     //   1199: invokevirtual mM : ()V
/*    */     //   1202: invokevirtual mM : ()V
/*    */     //   1205: invokevirtual d40 : ()V
/*    */     //   1208: getfield mH0 : I
/*    */     //   1211: aload_0
/*    */     //   1212: getfield le0 : Ljava/util/ArrayList;
/*    */     //   1215: invokevirtual size : ()I
/*    */     //   1218: if_icmplt -> 1234
/*    */     //   1221: aload_0
/*    */     //   1222: dup
/*    */     //   1223: getfield le0 : Ljava/util/ArrayList;
/*    */     //   1226: invokevirtual size : ()I
/*    */     //   1229: iconst_1
/*    */     //   1230: isub
/*    */     //   1231: putfield mH0 : I
/*    */     //   1234: aload_0
/*    */     //   1235: getfield mH0 : I
/*    */     //   1238: ifge -> 1246
/*    */     //   1241: aload_0
/*    */     //   1242: iconst_0
/*    */     //   1243: putfield mH0 : I
/*    */     //   1246: aload_0
/*    */     //   1247: getfield mH0 : I
/*    */     //   1250: aload_0
/*    */     //   1251: getfield le0 : Ljava/util/ArrayList;
/*    */     //   1254: invokevirtual size : ()I
/*    */     //   1257: if_icmplt -> 1265
/*    */     //   1260: aconst_null
/*    */     //   1261: astore_1
/*    */     //   1262: goto -> 1280
/*    */     //   1265: aload_0
/*    */     //   1266: getfield le0 : Ljava/util/ArrayList;
/*    */     //   1269: aload_0
/*    */     //   1270: getfield mH0 : I
/*    */     //   1273: invokevirtual get : (I)Ljava/lang/Object;
/*    */     //   1276: checkcast f/Un
/*    */     //   1279: astore_1
/*    */     //   1280: aload_1
/*    */     //   1281: ifnull -> 1303
/*    */     //   1284: aload_0
/*    */     //   1285: aload_1
/*    */     //   1286: invokestatic c90 : (Lf/JG0;)Z
/*    */     //   1289: pop
/*    */     //   1290: getfield M6 : Lf/rS;
/*    */     //   1293: dup
/*    */     //   1294: astore_0
/*    */     //   1295: ifnull -> 1303
/*    */     //   1298: aload_0
/*    */     //   1299: aload_1
/*    */     //   1300: invokevirtual ai : (Lf/JG0;)V
/*    */     //   1303: return
/*    */     // Line number table:
/*    */     //   Java source line number -> byte code offset
/*    */     //   #1	-> 8
/*    */     //   #2	-> 26
/*    */     //   #3	-> 29
/*    */     //   #4	-> 35
/*    */     //   #5	-> 38
/*    */     //   #6	-> 41
/*    */     //   #7	-> 50
/*    */     //   #8	-> 62
/*    */     //   #9	-> 104
/*    */     //   #10	-> 107
/*    */     //   #11	-> 121
/*    */     //   #12	-> 127
/*    */     //   #13	-> 148
/*    */     //   #14	-> 156
/*    */     //   #15	-> 176
/*    */     //   #16	-> 184
/*    */     //   #17	-> 199
/*    */     //   #18	-> 207
/*    */     //   #19	-> 240
/*    */     //   #20	-> 249
/*    */     //   #21	-> 332
/*    */     //   #22	-> 335
/*    */     //   #23	-> 538
/*    */     //   #24	-> 542
/*    */     //   #25	-> 545
/*    */     //   #26	-> 558
/*    */     //   #27	-> 585
/*    */     //   #28	-> 608
/*    */     //   #29	-> 611
/*    */     //   #30	-> 637
/*    */     //   #31	-> 642
/*    */     //   #32	-> 668
/*    */     //   #33	-> 673
/*    */     //   #34	-> 712
/*    */     //   #35	-> 749
/*    */     //   #36	-> 752
/*    */     //   #37	-> 755
/*    */     //   #38	-> 783
/*    */     //   #39	-> 786
/*    */     //   #40	-> 789
/*    */     //   #41	-> 816
/*    */     //   #42	-> 819
/*    */     //   #43	-> 828
/*    */     //   #44	-> 838
/*    */     //   #45	-> 841
/*    */     //   #46	-> 895
/*    */     //   #47	-> 901
/*    */     //   #48	-> 910
/*    */     //   #49	-> 937
/*    */     //   #50	-> 944
/*    */     //   #51	-> 957
/*    */     //   #52	-> 999
/*    */     //   #53	-> 1014
/*    */     //   #54	-> 1024
/*    */     //   #55	-> 1064
/*    */     //   #56	-> 1070
/*    */     //   #57	-> 1182
/*    */     //   #58	-> 1193
/*    */     //   #59	-> 1208
/*    */     //   #60	-> 1286
/*    */     // Exception table:
/*    */     //   from	to	target	type
/*    */     //   559	566	664	finally
/*    */     //   568	579	664	finally
/*    */     //   582	585	664	finally
/*    */     //   665	669	664	finally
/*    */     //   679	688	1011	finally
/*    */     //   690	706	1011	finally
/*    */     //   710	712	1011	finally
/*  7 */     //   1012	1015	1011	finally } public final Un IJ(int paramInt, String paramString) { this(paramString); un.tW(new Kn0(this, paramInt)); this.ad0.Xz0.Ya(un); this.ad0.o30.Ya(un); this.le0.add(un); Un un; return un = new Un(); } public final Un yI(String paramString, Runnable paramRunnable) { this(paramString); un.tW(paramRunnable); this.ad0.Xz0.Ya(un); this.ad0.o30.Ya(un); this.le0.add(un); Un un; return un = new Un(); } public final void qc0(String paramString) { this(paramString); Ro0 ro0; (new Ro0()).g40 = 180; (new Ro0()).C70(et.Wi0); Ip ip; (ip = this.ad0).Xz0.ee0((new cr0(ip)).Em0().Ya(this).Em0()); (ip = this.ad0).o30.ee0(ip.AUX(new JG0[] { this })); this.Lu.add(this); } public final void LM(throws paramthrows) { Un un; if (this.mH0 >= this.le0.size()) this.mH0 = this.le0.size() - 1;  if (this.mH0 < 0) this.mH0 = 0;  if (this.mH0 >= this.le0.size()) { paramthrows = null; } else { un = this.le0.get(this.mH0); }  VA0.c90(un); rS rS1; if (un != null && (rS1 = this.M6) != null) ai(un);  } public final boolean i2(oa0 paramoa0) { Un un1; Un un2; if (B8.Wm0(paramoa0.cz0) && paramoa0.oO()) { rS rS1; int i; if (h1.J20(i = paramoa0.GG0, BM.ni)) { this.mH0 = j; int j; if ((j = this.mH0 - 1) >= this.le0.size()) this.mH0 = this.le0.size() - 1;  if (this.mH0 < 0) this.mH0 = 0;  if (this.mH0 >= this.le0.size()) { un2 = null; } else { un2 = this.le0.get(this.mH0); }  VA0.c90(un2); if (un2 != null && (rS1 = this.M6) != null) ai(un2);  return true; }
/*  8 */        if (h1.J20(i, BM.N70)) { ((qt0)super).mH0 = j; int j; if ((j = ((qt0)super).mH0 + 1) >= ((qt0)super)
/*  9 */           .le0.size()) ((qt0)super).mH0 = ((qt0)super).le0.size() - 1;  if (((qt0)super).mH0 < 0) ((qt0)super).mH0 = 0;  if (((qt0)super).mH0 >= ((qt0)super).le0.size()) { un2 = null; } else { un2 = ((qt0)super).le0.get(((qt0)super).mH0); }
/* 10 */          VA0.c90(un2); if (un2 != null && (rS1 = ((qt0)super).M6) != null) ai(un2);  return true; }
/* 11 */        if (h1.J20(i, BM.bC)) { if (((qt0)super)
/* 12 */           .mH0 >= ((qt0)super).le0.size()) ((qt0)super).mH0 = ((qt0)super).le0.size() - 1;  if (((qt0)super).mH0 < 0) ((qt0)super).mH0 = 0;  if (((qt0)super).mH0 >= ((qt0)super).le0.size()) { rS1 = null; } else { un1 = ((qt0)super).le0.get(((qt0)super).mH0); }  if (this != null)
/*    */         {
/*    */           
/* 15 */           hm.Fz0(this.TG0.oh0); }  return true; }
/* 16 */        if (h1.J20(i, BM.lc))
/*    */       
/*    */       { 
/* 19 */         try { hm.Fz0(((Un)((qt0)super).le0.get(((qt0)super).le0.size() - 1)).TG0.oh0); } catch (Exception exception) {} return true; }  }
/* 20 */      return super.i2((oa0)un2); }
/*    */    }


/* Location:              /Users/vnnsnnt/Documents/Codespace/JavaWorkspace/RedTrainer/src/main/java/org/trainer/client/PokeMMO.jar!/f/qt0.class
 * Java compiler version: 8 (52.0)
 * JD-Core Version:       1.1.3
 */