/*   1 */ package f;public class Qv0 extends Fy0 implements Comparable { public static final Ll MZ = Ll.F10("dragActive"); public static final Ll GZ = Ll.F10("dropOk"); public static final Ll iX = Ll.F10("dropBlocked"); public static final Ll Jh0 = Ll.F10("filtered"); public static final Ll FA0 = Ll.F10("obey"); public static final Ll mk0 = Ll.F10("multiselect"); public static final Ll Co = Ll.F10("multiselectActive"); public static final Ll Bv0 = Ll.F10("battlebox"); public ab0 dw0; public boolean I20; public short A90; public Uc0 MQ; public LpT3 ee; public VA Iw; public VA Kx0; public VA sk0; public final void Cx0(boolean paramBoolean) { if (public() != null) this.TG0
/*   2 */         .Fx0(paramBoolean);  } public VA OR; public VA mG0; public VA Ld; public Dm Kb; public UN uE0; public boolean ZF = true; public boolean FO = false; public Runnable n0; public int r6; public int jo; public Qv0 Ba0; public boolean dr; public boolean oj0; public boolean Ia; public long Jl0 = 0L; public Qv0(Uc0 paramUc0, short paramShort, boolean paramBoolean) { this(paramUc0, paramShort, b1, b2); byte b1; byte b2; this.oj0 = paramBoolean; } public Qv0(Uc0 paramUc0, short paramShort, int paramInt1, int paramInt2) { super(paramInt1, paramInt2); rH rH = zY(); if (paramUc0.s20() == aq0.dy) { paramInt2 = 5; } else { paramInt2 = 4; }  rH.zT(paramInt2, -4); if (km.XU()) { int i; if ((i = paramUc0.s20().ordinal()) != 1) { if (i == 2) { AL(76, 76); zY().Ii0(2.0F); zY().zT(2, 2); }  } else { AL(100, 100); zY().Ii0(2.0F); zY().zT(14, 8); this.uE0 = new UN(); }  }  Xu("monster-slot"); this.MQ = paramUc0; this.A90 = paramShort; this.ee = new LpT3(this); (this.Kb = new Dm(this)).Nu(1.0F); this.Kb.Xu("slot-health-progressbar"); this.Iw = new VA(this, 16, 16); this.OR = new VA(this, 16, 16); this.mG0 = new VA(this, 16, 16); this.Ld = new VA(this, 16, 16); this.sk0 = new VA(this, 16, 16); this.Kx0 = new VA(this, 16, 16); this.sk0.ZH0().sm(new zh0[] { h90.Kw0().ol() }); if (km.XU()) { this.sk0.Cu0(17, 14); this.sk0.ZH0().tL(17, 14); this.Kx0.ZH0().tL(15, 15); this.OR.ZH0().Ii0(1.5F); this.mG0.ZH0().Ii0(1.5F); this.Ld.ZH0().Ii0(1.5F); this.Iw.ZH0().Ii0(1.5F); } else { this.sk0.ZH0().tL(13, 10); }  this.sk0.wI0(false); J8(this.Iw); J8(this.sk0); J8(this.Kx0); J8(this.OR); J8(this.Ld); J8(this.mG0); j40 j40 = public(); if (paramUc0.s20().tT() && km.Nr() && j40 != null && !j40.Q00()) J8(this.Kb);  this.ee.Xu("label-dark"); J8(this.ee); this.pz = true; } public final void Ax(zh0 paramzh0) { this.As.sm(new zh0[] { paramzh0 }); } public void zf(j40 paramj40) { un(this.MQ); } public void un(Uc0 paramUc0) { this.MQ = paramUc0; j40 j40; if ((j40 = public()) != null) MJ0();  aq0 aq0; if ((aq0 = paramUc0.Nul) == aq0.dy) { if (j40 != null) { this.sk0
/*     */           
/*   4 */           .wI0(j40.Zs.BM());
/*   5 */         if (j40.Zs
/*   6 */           .tm0()) { this.OR
/*   7 */             .TS
/*     */ 
/*     */             
/*  10 */             .Pn(new pe0[] { interface.ZZ().yI0(j40.Zs.Gf()) }); } else { this.OR
/*  11 */             .TS
/*  12 */             .H(); }
/*  13 */          if (j40.Zs
/*  14 */           .wH.length > 
/*  15 */           0) { this.mG0
/*  16 */             .TS
/*     */ 
/*     */             
/*  19 */             .Pn(new pe0[] { (interface.ZZ()).oX }); } else { this.mG0
/*  20 */             .TS
/*  21 */             .H(); }  }  } else if (aq0
/*  22 */       .cOM1) { if (j40 != null) { boolean bool; this
/*  23 */           .sk0
/*     */           
/*  25 */           .wI0(j40.Zs.BM());
/*  26 */         if (j40.Zs
/*  27 */           .u0 != 0) { bool = true; } else { bool = false; }  if (bool)
/*  28 */         { this.Kx0
/*  29 */             .TS
/*     */ 
/*     */ 
/*     */ 
/*     */             
/*  34 */             .Pn(new pe0[] { interface.ZZ().vn0(Q90.Ft(j40.Zs.u0)) }); } else { this.Kx0
/*  35 */             .TS
/*  36 */             .H(); }  if (this.oj0) if (j40
/*  37 */             .Zs.YC())
/*  38 */           { this.Iw
/*  39 */               .TS
/*  40 */               .H(); this.OR
/*  41 */               .TS
/*  42 */               .H(); this.mG0
/*  43 */               .TS
/*  44 */               .H(); this.Ld
/*  45 */               .TS
/*  46 */               .H(); this.ee.E1(""); this.sk0.wI0(false); } else { if (j40.s5() >= 0)
/*     */             
/*  48 */             { interface interface = interface.ZZ();
/*     */ 
/*     */               
/*  51 */               this.Iw.TS.Pn(new pe0[] { interface.ar0[j40.s5()] }); } else { this.Iw
/*  52 */                 .TS
/*  53 */                 .H(); }  if (j40
/*  54 */               .Zs
/*  55 */               .tm0()) { this.OR
/*  56 */                 .TS
/*     */ 
/*     */                 
/*  59 */                 .Pn(new pe0[] { interface.ZZ().yI0(j40.Zs.Gf()) }); } else { this.OR
/*  60 */                 .TS
/*  61 */                 .H(); }
/*  62 */              if (j40.Zs
/*  63 */               .wH.length > 
/*  64 */               0) { this.mG0
/*  65 */                 .TS
/*     */ 
/*     */                 
/*  68 */                 .Pn(new pe0[] { (interface.ZZ()).oX }); } else { this.mG0
/*  69 */                 .TS
/*  70 */                 .H(); }  if (j40
/*  71 */               .Zs
/*  72 */               .iL()) { this.Ld
/*  73 */                 .TS
/*     */ 
/*     */                 
/*  76 */                 .Pn(new pe0[] { (interface.ZZ()).n30 }); } else { this.Ld
/*  77 */                 .TS
/*  78 */                 .H(); }  if (km.XU()) this.ee
/*     */ 
/*     */                 
/*  81 */                 .E1(String.valueOf(j40.Zs.od));  this.sk0
/*     */               
/*  83 */               .wI0(j40.Zs.BM()); }
/*     */         
/*     */ 
/*     */         
/*  87 */         float f = j40.Zs.Hq0 / j40.Fq0.Mm(hR.Gg); if (this.uE0 != null)
/*  88 */         { this.As
/*  89 */             .O3 = null; double d; if ((d = f) > 0.5D || j40
/*  90 */             .Zs.YC())
/*     */           
/*     */           { 
/*     */ 
/*     */             
/*  95 */             this.uE0.M6.set(785150431); } else if (d > 0.2D) { this.uE0.M6.set(-207875361); } else { int i; if ((i = f cmp 0.0F) > 0) { this.uE0.M6.set(-414434081); } else if (i == 0) { this.uE0.M6.set(-1688619297); f = 1.0E-5F; this.As.O3 = new pRn(-1325400065); }  }  this.uE0
/*  96 */             .zE = f;
/*  97 */           this.uE0.bK(); }
/*  98 */         else if (j40.Zs
/*  99 */           .Hq0 > 0 && f < 0.13F) { f = 0.13F; }  this
/* 100 */           .Kb.Nu(f); this.Kb
/*     */           
/* 102 */           .wI0(j40.Zs.YC() ^ true); if (km.Nr() && 
/*     */           
/* 104 */           !j40.Zs.YC() && ID(this.Kb) < 0 && !this.dr) { Dm dm = this.Kb;
/* 105 */           si(dm, Ub()); }  }
/* 106 */       else { this.Iw
/* 107 */           .TS
/* 108 */           .H(); this.Ld
/* 109 */           .TS
/* 110 */           .H(); this.mG0
/* 111 */           .TS
/* 112 */           .H(); this.OR
/* 113 */           .TS
/* 114 */           .H(); this.ee.E1(""); this.sk0.wI0(false); if (km.Nr()) jf0(this.Kb);  }
/*     */        }
/*     */     
/* 117 */     hm.Fz0(this.TG0.oh0); this
/* 118 */       .O
/* 119 */       .gf0(Jh0, false); this.O.gf0(FA0, false);
/* 120 */     this.O
/* 121 */       .gf0(Bv0, false); UN uN; if (j40 == null && (uN = this.uE0) != null) { this
/* 122 */         .zE = 1.0E-4F;
/* 123 */       bK(); }
/*     */      }
/*     */ 
/*     */   
/*     */   public void jj() {
/*     */     j40 j40;
/*     */     if ((j40 = public()) != null) {
/*     */       boolean bool;
/*     */       if (j40.Zs.u0 != 0) {
/*     */         bool = true;
/*     */       } else {
/*     */         bool = false;
/*     */       } 
/*     */       if (bool) {
/*     */         this.Kx0.TS.Pn(new pe0[] { interface.ZZ().vn0(Q90.Ft(j40.Zs.u0)) });
/*     */         return;
/*     */       } 
/*     */     } 
/*     */     this.Kx0.TS.H();
/*     */   }
/*     */   
/*     */   public short fH0() {
/*     */     return this.A90;
/*     */   }
/*     */   
/*     */   public j40 public() {
/*     */     return this.MQ.ky(this.A90);
/*     */   }
/*     */   
/*     */   public final void Xw(nY paramnY) {
/*     */     super.Xw(paramnY);
/*     */     pe0 pe0;
/*     */     mX mX;
/*     */     if (km.XU() && this.uE0 != null && (mX = ((q80)paramnY).w2("radial-progress")) != null && (pe0 = mX.LPT8()) != null) {
/*     */       this.XF0 = pe0;
/*     */       float f1 = pe0.mP;
/*     */       float f2 = pe0.WT;
/*     */       float f3 = pe0.zV;
/*     */       this.NU = f3 - f1;
/*     */       UN uN;
/*     */       (uN = this.uE0).sx0 = pe0.bh0 - f2;
/*     */     } 
/*     */   }
/*     */   
/*     */   public aq0 lK() {
/*     */     return this.MQ.Nul;
/*     */   }
/*     */   
/*     */   public boolean i2(oa0 paramoa0) {
/*     */     // Byte code:
/*     */     //   0: aload_1
/*     */     //   1: invokevirtual Cz0 : ()Z
/*     */     //   4: ifeq -> 111
/*     */     //   7: aload_0
/*     */     //   8: getfield Ia : Z
/*     */     //   11: ifeq -> 65
/*     */     //   14: aload_1
/*     */     //   15: invokevirtual Ud : ()Z
/*     */     //   18: ifeq -> 46
/*     */     //   21: aload_0
/*     */     //   22: getfield dw0 : Lf/ab0;
/*     */     //   25: dup
/*     */     //   26: astore_2
/*     */     //   27: ifnull -> 38
/*     */     //   30: aload_2
/*     */     //   31: aload_0
/*     */     //   32: aload_1
/*     */     //   33: invokeinterface Cj0 : (Lf/Qv0;Lf/oa0;)V
/*     */     //   38: aload_0
/*     */     //   39: iconst_0
/*     */     //   40: putfield Ia : Z
/*     */     //   43: goto -> 63
/*     */     //   46: aload_0
/*     */     //   47: getfield dw0 : Lf/ab0;
/*     */     //   50: dup
/*     */     //   51: astore_2
/*     */     //   52: ifnull -> 63
/*     */     //   55: aload_2
/*     */     //   56: aload_0
/*     */     //   57: aload_1
/*     */     //   58: invokeinterface pN : (Lf/Qv0;Lf/oa0;)V
/*     */     //   63: iconst_1
/*     */     //   64: ireturn
/*     */     //   65: aload_1
/*     */     //   66: getfield Ua : Z
/*     */     //   69: ifeq -> 96
/*     */     //   72: aload_0
/*     */     //   73: dup
/*     */     //   74: iconst_1
/*     */     //   75: putfield Ia : Z
/*     */     //   78: getfield dw0 : Lf/ab0;
/*     */     //   81: dup
/*     */     //   82: astore_2
/*     */     //   83: ifnull -> 94
/*     */     //   86: aload_2
/*     */     //   87: aload_0
/*     */     //   88: aload_1
/*     */     //   89: invokeinterface qm : (Lf/Qv0;Lf/oa0;)V
/*     */     //   94: iconst_1
/*     */     //   95: ireturn
/*     */     //   96: aload_1
/*     */     //   97: getfield cz0 : I
/*     */     //   100: iconst_4
/*     */     //   101: if_icmpne -> 109
/*     */     //   104: aload_0
/*     */     //   105: aload_1
/*     */     //   106: invokevirtual F4 : (Lf/oa0;)V
/*     */     //   109: iconst_1
/*     */     //   110: ireturn
/*     */     //   111: aload_1
/*     */     //   112: getfield cz0 : I
/*     */     //   115: invokestatic Pg : (I)Z
/*     */     //   118: ifeq -> 134
/*     */     //   121: aload_1
/*     */     //   122: getfield kB0 : I
/*     */     //   125: ifeq -> 134
/*     */     //   128: aload_0
/*     */     //   129: aload_1
/*     */     //   130: invokespecial i2 : (Lf/oa0;)Z
/*     */     //   133: ireturn
/*     */     //   134: aload_1
/*     */     //   135: getfield GG0 : I
/*     */     //   138: getstatic f/BM.bC : Lf/BM;
/*     */     //   141: invokestatic J20 : (ILf/BM;)Z
/*     */     //   144: ifeq -> 384
/*     */     //   147: getstatic f/pA.Dg0 : Lf/pA;
/*     */     //   150: getfield dk0 : Lf/gO;
/*     */     //   153: dup
/*     */     //   154: astore_2
/*     */     //   155: ifnull -> 384
/*     */     //   158: aload_1
/*     */     //   159: getfield cz0 : I
/*     */     //   162: bipush #10
/*     */     //   164: if_icmpne -> 172
/*     */     //   167: iconst_1
/*     */     //   168: istore_3
/*     */     //   169: goto -> 174
/*     */     //   172: iconst_0
/*     */     //   173: istore_3
/*     */     //   174: iload_3
/*     */     //   175: ifeq -> 221
/*     */     //   178: aload_2
/*     */     //   179: getfield U40 : Lf/Qv0;
/*     */     //   182: ifnonnull -> 221
/*     */     //   185: aload_0
/*     */     //   186: getfield Jl0 : J
/*     */     //   189: dup2
/*     */     //   190: lstore_2
/*     */     //   191: lconst_0
/*     */     //   192: lcmp
/*     */     //   193: ifne -> 198
/*     */     //   196: iconst_1
/*     */     //   197: ireturn
/*     */     //   198: invokestatic currentTimeMillis : ()J
/*     */     //   201: lload_2
/*     */     //   202: lsub
/*     */     //   203: ldc2_w 500
/*     */     //   206: lcmp
/*     */     //   207: ifge -> 214
/*     */     //   210: aload_0
/*     */     //   211: invokevirtual GO : ()V
/*     */     //   214: aload_0
/*     */     //   215: lconst_0
/*     */     //   216: putfield Jl0 : J
/*     */     //   219: iconst_1
/*     */     //   220: ireturn
/*     */     //   221: aload_1
/*     */     //   222: invokevirtual oO : ()Z
/*     */     //   225: ifeq -> 292
/*     */     //   228: aload_1
/*     */     //   229: getfield cz0 : I
/*     */     //   232: bipush #9
/*     */     //   234: if_icmpne -> 249
/*     */     //   237: aload_1
/*     */     //   238: getfield sj : Z
/*     */     //   241: ifeq -> 249
/*     */     //   244: iconst_1
/*     */     //   245: istore_3
/*     */     //   246: goto -> 251
/*     */     //   249: iconst_0
/*     */     //   250: istore_3
/*     */     //   251: iload_3
/*     */     //   252: ifne -> 292
/*     */     //   255: aload_2
/*     */     //   256: getfield U40 : Lf/Qv0;
/*     */     //   259: ifnonnull -> 292
/*     */     //   262: aload_0
/*     */     //   263: invokestatic currentTimeMillis : ()J
/*     */     //   266: putfield Jl0 : J
/*     */     //   269: new f/KU
/*     */     //   272: dup
/*     */     //   273: astore_1
/*     */     //   274: aload_0
/*     */     //   275: aload_2
/*     */     //   276: invokespecial <init> : (Lf/Qv0;Lf/gO;)V
/*     */     //   279: invokestatic k6 : ()Lf/HC;
/*     */     //   282: aload_1
/*     */     //   283: ldc_w 0.5
/*     */     //   286: invokevirtual S : (Lf/oo;F)Lf/oo;
/*     */     //   289: pop
/*     */     //   290: iconst_1
/*     */     //   291: ireturn
/*     */     //   292: aload_1
/*     */     //   293: invokevirtual oO : ()Z
/*     */     //   296: ifne -> 319
/*     */     //   299: aload_1
/*     */     //   300: getfield cz0 : I
/*     */     //   303: bipush #10
/*     */     //   305: if_icmpne -> 313
/*     */     //   308: iconst_1
/*     */     //   309: istore_3
/*     */     //   310: goto -> 315
/*     */     //   313: iconst_0
/*     */     //   314: istore_3
/*     */     //   315: iload_3
/*     */     //   316: ifeq -> 384
/*     */     //   319: aload_1
/*     */     //   320: getfield cz0 : I
/*     */     //   323: bipush #9
/*     */     //   325: if_icmpne -> 340
/*     */     //   328: aload_1
/*     */     //   329: getfield sj : Z
/*     */     //   332: ifeq -> 340
/*     */     //   335: iconst_1
/*     */     //   336: istore_3
/*     */     //   337: goto -> 342
/*     */     //   340: iconst_0
/*     */     //   341: istore_3
/*     */     //   342: iload_3
/*     */     //   343: ifne -> 384
/*     */     //   346: aload_2
/*     */     //   347: aload_0
/*     */     //   348: dup
/*     */     //   349: dup2
/*     */     //   350: lconst_0
/*     */     //   351: putfield Jl0 : J
/*     */     //   354: invokevirtual RS : ()I
/*     */     //   357: istore_1
/*     */     //   358: invokevirtual qF : ()I
/*     */     //   361: iconst_2
/*     */     //   362: idiv
/*     */     //   363: iload_1
/*     */     //   364: iadd
/*     */     //   365: istore_1
/*     */     //   366: invokevirtual e3 : ()I
/*     */     //   369: istore_2
/*     */     //   370: iload_1
/*     */     //   371: aload_0
/*     */     //   372: invokevirtual Hy : ()I
/*     */     //   375: iconst_2
/*     */     //   376: idiv
/*     */     //   377: iload_2
/*     */     //   378: iadd
/*     */     //   379: invokevirtual wL0 : (II)V
/*     */     //   382: iconst_1
/*     */     //   383: ireturn
/*     */     //   384: aload_0
/*     */     //   385: aload_1
/*     */     //   386: invokespecial i2 : (Lf/oa0;)Z
/*     */     //   389: ireturn
/*     */     // Line number table:
/*     */     //   Java source line number -> byte code offset
/*     */     //   #1	-> 66
/*     */     //   #2	-> 75
/*     */     //   #3	-> 97
/*     */     //   #4	-> 106
/*     */     //   #5	-> 112
/*     */     //   #6	-> 122
/*     */     //   #7	-> 130
/*     */     //   #8	-> 135
/*     */     //   #9	-> 138
/*     */     //   #10	-> 147
/*     */     //   #11	-> 150
/*     */     //   #12	-> 159
/*     */     //   #13	-> 179
/*     */     //   #14	-> 186
/*     */     //   #15	-> 198
/*     */     //   #16	-> 211
/*     */     //   #17	-> 229
/*     */     //   #18	-> 256
/*     */     //   #19	-> 263
/*     */     //   #20	-> 266
/*     */     //   #21	-> 279
/*     */     //   #22	-> 293
/*     */     //   #23	-> 300
/*     */     //   #24	-> 320
/*     */     //   #25	-> 351
/*     */   }
/*     */   
/*     */   public void F4(oa0 paramoa0) {
/*     */     // Byte code:
/*     */     //   0: aload_1
/*     */     //   1: aload_0
/*     */     //   2: getstatic f/pA.Dg0 : Lf/pA;
/*     */     //   5: dup
/*     */     //   6: dup2
/*     */     //   7: dup2
/*     */     //   8: astore_2
/*     */     //   9: getfield cl : Lf/GV;
/*     */     //   12: astore_3
/*     */     //   13: getfield QI0 : Lf/A;
/*     */     //   16: astore #4
/*     */     //   18: getfield dk0 : Lf/gO;
/*     */     //   21: astore #5
/*     */     //   23: getfield M20 : Lf/Zr;
/*     */     //   26: astore #6
/*     */     //   28: getfield AL : Lf/Kf;
/*     */     //   31: astore #7
/*     */     //   33: getfield MQ : Lf/Uc0;
/*     */     //   36: getfield Nul : Lf/aq0;
/*     */     //   39: astore #8
/*     */     //   41: getfield vl : I
/*     */     //   44: dup
/*     */     //   45: istore #9
/*     */     //   47: ifne -> 401
/*     */     //   50: aload_1
/*     */     //   51: getfield com8 : I
/*     */     //   54: bipush #36
/*     */     //   56: iand
/*     */     //   57: ifeq -> 340
/*     */     //   60: aload #8
/*     */     //   62: getstatic f/aq0.LI : Lf/aq0;
/*     */     //   65: dup
/*     */     //   66: astore_1
/*     */     //   67: if_acmpne -> 161
/*     */     //   70: aload_3
/*     */     //   71: ifnull -> 161
/*     */     //   74: aload_3
/*     */     //   75: aload_0
/*     */     //   76: invokevirtual public : ()Lf/j40;
/*     */     //   79: astore_0
/*     */     //   80: getfield TG0 : [Lf/Qv0;
/*     */     //   83: iconst_0
/*     */     //   84: aaload
/*     */     //   85: invokevirtual public : ()Lf/j40;
/*     */     //   88: ifnonnull -> 120
/*     */     //   91: aload_3
/*     */     //   92: iconst_0
/*     */     //   93: dup
/*     */     //   94: istore_1
/*     */     //   95: iconst_1
/*     */     //   96: aload_0
/*     */     //   97: invokevirtual Cb : (SZLf/j40;)Z
/*     */     //   100: ifeq -> 440
/*     */     //   103: aload_3
/*     */     //   104: dup
/*     */     //   105: getfield TG0 : [Lf/Qv0;
/*     */     //   108: iload_1
/*     */     //   109: aaload
/*     */     //   110: aload_0
/*     */     //   111: invokevirtual zf : (Lf/j40;)V
/*     */     //   114: invokevirtual update : ()V
/*     */     //   117: goto -> 440
/*     */     //   120: aload_3
/*     */     //   121: getfield TG0 : [Lf/Qv0;
/*     */     //   124: iconst_2
/*     */     //   125: aaload
/*     */     //   126: invokevirtual public : ()Lf/j40;
/*     */     //   129: ifnonnull -> 440
/*     */     //   132: aload_3
/*     */     //   133: iconst_2
/*     */     //   134: dup
/*     */     //   135: istore_1
/*     */     //   136: iconst_1
/*     */     //   137: aload_0
/*     */     //   138: invokevirtual Cb : (SZLf/j40;)Z
/*     */     //   141: ifeq -> 440
/*     */     //   144: aload_3
/*     */     //   145: dup
/*     */     //   146: getfield TG0 : [Lf/Qv0;
/*     */     //   149: iload_1
/*     */     //   150: aaload
/*     */     //   151: aload_0
/*     */     //   152: invokevirtual zf : (Lf/j40;)V
/*     */     //   155: invokevirtual update : ()V
/*     */     //   158: goto -> 440
/*     */     //   161: aload #8
/*     */     //   163: getfield cOM1 : Z
/*     */     //   166: dup
/*     */     //   167: istore_2
/*     */     //   168: ifeq -> 206
/*     */     //   171: aload #5
/*     */     //   173: ifnull -> 206
/*     */     //   176: aload #5
/*     */     //   178: dup
/*     */     //   179: invokevirtual e8 : ()Lf/n3;
/*     */     //   182: getfield Zb : I
/*     */     //   185: iconst_0
/*     */     //   186: invokevirtual lg : (II)Lf/Zq;
/*     */     //   189: dup
/*     */     //   190: astore_1
/*     */     //   191: ifnonnull -> 195
/*     */     //   194: return
/*     */     //   195: getstatic f/km.u4 : Lf/R8;
/*     */     //   198: aload_0
/*     */     //   199: aload_1
/*     */     //   200: invokevirtual lO : (Lf/Qv0;Lf/Qv0;)V
/*     */     //   203: goto -> 440
/*     */     //   206: iload_2
/*     */     //   207: ifeq -> 275
/*     */     //   210: aload #6
/*     */     //   212: ifnull -> 275
/*     */     //   215: aload #6
/*     */     //   217: getfield wC0 : [[Lf/Qv0;
/*     */     //   220: iconst_0
/*     */     //   221: aaload
/*     */     //   222: dup
/*     */     //   223: astore_1
/*     */     //   224: arraylength
/*     */     //   225: istore_2
/*     */     //   226: iconst_0
/*     */     //   227: istore_3
/*     */     //   228: iload_3
/*     */     //   229: iload_2
/*     */     //   230: if_icmpge -> 254
/*     */     //   233: aload_1
/*     */     //   234: iload_3
/*     */     //   235: aaload
/*     */     //   236: dup
/*     */     //   237: astore #4
/*     */     //   239: invokevirtual public : ()Lf/j40;
/*     */     //   242: ifnonnull -> 248
/*     */     //   245: goto -> 257
/*     */     //   248: iinc #3, 1
/*     */     //   251: goto -> 228
/*     */     //   254: aconst_null
/*     */     //   255: astore #4
/*     */     //   257: aload #4
/*     */     //   259: ifnonnull -> 263
/*     */     //   262: return
/*     */     //   263: getstatic f/km.u4 : Lf/R8;
/*     */     //   266: aload_0
/*     */     //   267: aload #4
/*     */     //   269: invokevirtual lO : (Lf/Qv0;Lf/Qv0;)V
/*     */     //   272: goto -> 440
/*     */     //   275: aload #8
/*     */     //   277: aload_1
/*     */     //   278: if_acmpne -> 440
/*     */     //   281: aload #4
/*     */     //   283: ifnull -> 323
/*     */     //   286: aload #4
/*     */     //   288: dup
/*     */     //   289: dup
/*     */     //   290: aload_0
/*     */     //   291: invokevirtual public : ()Lf/j40;
/*     */     //   294: astore_0
/*     */     //   295: getfield bk : Lf/Gn0;
/*     */     //   298: aload_0
/*     */     //   299: invokevirtual zf : (Lf/j40;)V
/*     */     //   302: getfield sr : Lf/Vq0;
/*     */     //   305: dup
/*     */     //   306: iconst_3
/*     */     //   307: invokevirtual Hf : (I)Lf/Li0;
/*     */     //   310: invokevirtual dA0 : (Lf/Li0;)V
/*     */     //   313: getfield bk : Lf/Gn0;
/*     */     //   316: invokestatic c90 : (Lf/JG0;)Z
/*     */     //   319: pop
/*     */     //   320: goto -> 440
/*     */     //   323: aload #7
/*     */     //   325: ifnull -> 440
/*     */     //   328: aload #7
/*     */     //   330: aload_0
/*     */     //   331: invokevirtual public : ()Lf/j40;
/*     */     //   334: invokevirtual zf0 : (Lf/j40;)V
/*     */     //   337: goto -> 440
/*     */     //   340: aload_1
/*     */     //   341: getfield Ua : Z
/*     */     //   344: ifne -> 440
/*     */     //   347: invokestatic XU : ()Z
/*     */     //   350: ifeq -> 383
/*     */     //   353: aload #8
/*     */     //   355: getstatic f/aq0.dy : Lf/aq0;
/*     */     //   358: if_acmpne -> 383
/*     */     //   361: aload_0
/*     */     //   362: invokevirtual public : ()Lf/j40;
/*     */     //   365: ifnull -> 383
/*     */     //   368: getstatic f/pA.Dg0 : Lf/pA;
/*     */     //   371: aload_0
/*     */     //   372: invokevirtual public : ()Lf/j40;
/*     */     //   375: aconst_null
/*     */     //   376: swap
/*     */     //   377: invokevirtual u30 : (Lf/JG0;Lf/j40;)V
/*     */     //   380: goto -> 440
/*     */     //   383: aload_0
/*     */     //   384: getfield n0 : Ljava/lang/Runnable;
/*     */     //   387: dup
/*     */     //   388: astore_0
/*     */     //   389: ifnull -> 440
/*     */     //   392: aload_0
/*     */     //   393: invokeinterface run : ()V
/*     */     //   398: goto -> 440
/*     */     //   401: iload #9
/*     */     //   403: iconst_1
/*     */     //   404: if_icmpne -> 440
/*     */     //   407: aload_1
/*     */     //   408: getfield com8 : I
/*     */     //   411: bipush #36
/*     */     //   413: iand
/*     */     //   414: ifeq -> 430
/*     */     //   417: aload_2
/*     */     //   418: aload_0
/*     */     //   419: invokevirtual public : ()Lf/j40;
/*     */     //   422: aload_0
/*     */     //   423: swap
/*     */     //   424: invokevirtual u30 : (Lf/JG0;Lf/j40;)V
/*     */     //   427: goto -> 440
/*     */     //   430: aload_2
/*     */     //   431: aload_0
/*     */     //   432: invokevirtual public : ()Lf/j40;
/*     */     //   435: aconst_null
/*     */     //   436: swap
/*     */     //   437: invokevirtual u30 : (Lf/JG0;Lf/j40;)V
/*     */     //   440: return
/*     */     // Line number table:
/*     */     //   Java source line number -> byte code offset
/*     */     //   #1	-> 2
/*     */     //   #2	-> 9
/*     */     //   #3	-> 13
/*     */     //   #4	-> 18
/*     */     //   #5	-> 23
/*     */     //   #6	-> 28
/*     */     //   #7	-> 33
/*     */     //   #8	-> 36
/*     */     //   #9	-> 41
/*     */     //   #10	-> 51
/*     */     //   #11	-> 62
/*     */     //   #12	-> 80
/*     */     //   #13	-> 97
/*     */     //   #14	-> 121
/*     */     //   #15	-> 138
/*     */     //   #16	-> 163
/*     */     //   #17	-> 179
/*     */     //   #18	-> 182
/*     */     //   #19	-> 186
/*     */     //   #20	-> 195
/*     */     //   #21	-> 217
/*     */     //   #22	-> 263
/*     */     //   #23	-> 295
/*     */     //   #24	-> 331
/*     */     //   #25	-> 341
/*     */     //   #26	-> 347
/*     */     //   #27	-> 368
/*     */     //   #28	-> 372
/*     */     //   #29	-> 408
/*     */     //   #30	-> 419
/*     */   }
/*     */   
/*     */   public final void L1(Runnable paramRunnable) {
/*     */     this.n0 = paramRunnable;
/*     */   }
/*     */   
/*     */   public void d40() {
/*     */     // Byte code:
/*     */     //   0: aload_0
/*     */     //   1: getfield MQ : Lf/Uc0;
/*     */     //   4: getfield Nul : Lf/aq0;
/*     */     //   7: getstatic f/aq0.XJ0 : Lf/aq0;
/*     */     //   10: if_acmpne -> 18
/*     */     //   13: aload_0
/*     */     //   14: invokespecial d40 : ()V
/*     */     //   17: return
/*     */     //   18: invokestatic Nr : ()Z
/*     */     //   21: ifeq -> 523
/*     */     //   24: aload_0
/*     */     //   25: dup
/*     */     //   26: dup2
/*     */     //   27: getfield ee : Lf/LpT3;
/*     */     //   30: aload_0
/*     */     //   31: getfield Kd : I
/*     */     //   34: iconst_4
/*     */     //   35: iadd
/*     */     //   36: aload_0
/*     */     //   37: getfield er0 : I
/*     */     //   40: bipush #36
/*     */     //   42: iadd
/*     */     //   43: invokevirtual ME : (II)Z
/*     */     //   46: pop
/*     */     //   47: getfield Kb : Lf/Dm;
/*     */     //   50: bipush #40
/*     */     //   52: bipush #8
/*     */     //   54: invokevirtual Tm : (II)Z
/*     */     //   57: pop
/*     */     //   58: getfield Kb : Lf/Dm;
/*     */     //   61: aload_0
/*     */     //   62: getfield Kd : I
/*     */     //   65: iconst_2
/*     */     //   66: iadd
/*     */     //   67: aload_0
/*     */     //   68: getfield er0 : I
/*     */     //   71: bipush #30
/*     */     //   73: iadd
/*     */     //   74: invokevirtual ME : (II)Z
/*     */     //   77: pop
/*     */     //   78: getfield oj0 : Z
/*     */     //   81: ifne -> 189
/*     */     //   84: aload_0
/*     */     //   85: iconst_1
/*     */     //   86: istore_1
/*     */     //   87: getfield Iw : Lf/VA;
/*     */     //   90: getfield TS : Lf/rH;
/*     */     //   93: invokevirtual e00 : ()I
/*     */     //   96: ifle -> 122
/*     */     //   99: aload_0
/*     */     //   100: getfield Iw : Lf/VA;
/*     */     //   103: aload_0
/*     */     //   104: getfield Kd : I
/*     */     //   107: iconst_1
/*     */     //   108: iadd
/*     */     //   109: aload_0
/*     */     //   110: getfield er0 : I
/*     */     //   113: iconst_2
/*     */     //   114: iadd
/*     */     //   115: invokevirtual ME : (II)Z
/*     */     //   118: pop
/*     */     //   119: bipush #15
/*     */     //   121: istore_1
/*     */     //   122: aload_0
/*     */     //   123: invokevirtual public : ()Lf/j40;
/*     */     //   126: ifnull -> 167
/*     */     //   129: aload_0
/*     */     //   130: invokevirtual public : ()Lf/j40;
/*     */     //   133: getfield Zs : Lf/Q90;
/*     */     //   136: invokevirtual tm0 : ()Z
/*     */     //   139: ifeq -> 167
/*     */     //   142: aload_0
/*     */     //   143: getfield OR : Lf/VA;
/*     */     //   146: aload_0
/*     */     //   147: getfield Kd : I
/*     */     //   150: iload_1
/*     */     //   151: iadd
/*     */     //   152: iconst_1
/*     */     //   153: iadd
/*     */     //   154: aload_0
/*     */     //   155: getfield er0 : I
/*     */     //   158: iconst_1
/*     */     //   159: iadd
/*     */     //   160: invokevirtual ME : (II)Z
/*     */     //   163: pop
/*     */     //   164: iinc #1, 14
/*     */     //   167: aload_0
/*     */     //   168: getfield mG0 : Lf/VA;
/*     */     //   171: aload_0
/*     */     //   172: getfield Kd : I
/*     */     //   175: iload_1
/*     */     //   176: iadd
/*     */     //   177: iconst_1
/*     */     //   178: iadd
/*     */     //   179: aload_0
/*     */     //   180: getfield er0 : I
/*     */     //   183: iconst_1
/*     */     //   184: iadd
/*     */     //   185: invokevirtual ME : (II)Z
/*     */     //   188: pop
/*     */     //   189: aload_0
/*     */     //   190: getfield oj0 : Z
/*     */     //   193: ifeq -> 372
/*     */     //   196: aload_0
/*     */     //   197: dup
/*     */     //   198: dup
/*     */     //   199: getfield OR : Lf/VA;
/*     */     //   202: aload_0
/*     */     //   203: getfield Kd : I
/*     */     //   206: iconst_1
/*     */     //   207: iadd
/*     */     //   208: aload_0
/*     */     //   209: getfield er0 : I
/*     */     //   212: iconst_1
/*     */     //   213: iadd
/*     */     //   214: invokevirtual ME : (II)Z
/*     */     //   217: pop
/*     */     //   218: getfield OR : Lf/VA;
/*     */     //   221: getfield TS : Lf/rH;
/*     */     //   224: iconst_0
/*     */     //   225: iconst_0
/*     */     //   226: invokevirtual zT : (II)Lf/JG0;
/*     */     //   229: pop
/*     */     //   230: getfield OR : Lf/VA;
/*     */     //   233: getfield TS : Lf/rH;
/*     */     //   236: invokevirtual cA : ()I
/*     */     //   239: aload_0
/*     */     //   240: dup
/*     */     //   241: dup
/*     */     //   242: getfield mG0 : Lf/VA;
/*     */     //   245: astore_1
/*     */     //   246: getfield Kd : I
/*     */     //   249: iconst_1
/*     */     //   250: iadd
/*     */     //   251: istore_2
/*     */     //   252: getfield er0 : I
/*     */     //   255: iconst_1
/*     */     //   256: iadd
/*     */     //   257: istore_3
/*     */     //   258: ifne -> 267
/*     */     //   261: iconst_0
/*     */     //   262: istore #4
/*     */     //   264: goto -> 271
/*     */     //   267: bipush #12
/*     */     //   269: istore #4
/*     */     //   271: aload_0
/*     */     //   272: dup
/*     */     //   273: dup
/*     */     //   274: aload_1
/*     */     //   275: iload_2
/*     */     //   276: iload_3
/*     */     //   277: iload #4
/*     */     //   279: iadd
/*     */     //   280: invokevirtual ME : (II)Z
/*     */     //   283: pop
/*     */     //   284: getfield Iw : Lf/VA;
/*     */     //   287: aload_0
/*     */     //   288: getfield Kd : I
/*     */     //   291: iconst_1
/*     */     //   292: iadd
/*     */     //   293: aload_0
/*     */     //   294: invokevirtual mD : ()I
/*     */     //   297: aload_0
/*     */     //   298: getfield Iw : Lf/VA;
/*     */     //   301: getfield TS : Lf/rH;
/*     */     //   304: invokevirtual cA : ()I
/*     */     //   307: isub
/*     */     //   308: invokevirtual ME : (II)Z
/*     */     //   311: pop
/*     */     //   312: getfield Ld : Lf/VA;
/*     */     //   315: getfield TS : Lf/rH;
/*     */     //   318: aload_0
/*     */     //   319: getfield xY : I
/*     */     //   322: bipush #17
/*     */     //   324: isub
/*     */     //   325: iconst_2
/*     */     //   326: invokevirtual zT : (II)Lf/JG0;
/*     */     //   329: pop
/*     */     //   330: getfield Ld : Lf/VA;
/*     */     //   333: getfield TS : Lf/rH;
/*     */     //   336: invokevirtual cA : ()I
/*     */     //   339: dup
/*     */     //   340: istore_1
/*     */     //   341: aload_0
/*     */     //   342: dup
/*     */     //   343: getfield sk0 : Lf/VA;
/*     */     //   346: getfield TS : Lf/rH;
/*     */     //   349: astore_2
/*     */     //   350: getfield xY : I
/*     */     //   353: bipush #15
/*     */     //   355: isub
/*     */     //   356: istore_3
/*     */     //   357: ifne -> 362
/*     */     //   360: iconst_2
/*     */     //   361: istore_1
/*     */     //   362: aload_2
/*     */     //   363: iload_3
/*     */     //   364: iload_1
/*     */     //   365: invokevirtual zT : (II)Lf/JG0;
/*     */     //   368: pop
/*     */     //   369: goto -> 1075
/*     */     //   372: aload_0
/*     */     //   373: getfield MQ : Lf/Uc0;
/*     */     //   376: getfield Nul : Lf/aq0;
/*     */     //   379: getstatic f/aq0.dy : Lf/aq0;
/*     */     //   382: if_acmpne -> 477
/*     */     //   385: aload_0
/*     */     //   386: dup
/*     */     //   387: dup
/*     */     //   388: getfield OR : Lf/VA;
/*     */     //   391: aload_0
/*     */     //   392: getfield Kd : I
/*     */     //   395: bipush #50
/*     */     //   397: iadd
/*     */     //   398: aload_0
/*     */     //   399: getfield er0 : I
/*     */     //   402: iconst_1
/*     */     //   403: iadd
/*     */     //   404: invokevirtual ME : (II)Z
/*     */     //   407: pop
/*     */     //   408: getfield mG0 : Lf/VA;
/*     */     //   411: astore_1
/*     */     //   412: getfield OR : Lf/VA;
/*     */     //   415: dup
/*     */     //   416: dup
/*     */     //   417: getfield Kd : I
/*     */     //   420: istore_2
/*     */     //   421: getfield er0 : I
/*     */     //   424: istore_3
/*     */     //   425: getfield TS : Lf/rH;
/*     */     //   428: invokevirtual cA : ()I
/*     */     //   431: ifle -> 441
/*     */     //   434: bipush #13
/*     */     //   436: istore #4
/*     */     //   438: goto -> 444
/*     */     //   441: iconst_0
/*     */     //   442: istore #4
/*     */     //   444: aload_0
/*     */     //   445: dup
/*     */     //   446: dup
/*     */     //   447: aload_1
/*     */     //   448: iload_2
/*     */     //   449: iload_3
/*     */     //   450: iload #4
/*     */     //   452: iadd
/*     */     //   453: invokevirtual ME : (II)Z
/*     */     //   456: pop
/*     */     //   457: getfield sk0 : Lf/VA;
/*     */     //   460: astore_1
/*     */     //   461: getfield Kd : I
/*     */     //   464: bipush #38
/*     */     //   466: iadd
/*     */     //   467: istore_2
/*     */     //   468: getfield er0 : I
/*     */     //   471: iconst_5
/*     */     //   472: iadd
/*     */     //   473: istore_3
/*     */     //   474: goto -> 1068
/*     */     //   477: aload_0
/*     */     //   478: dup
/*     */     //   479: dup
/*     */     //   480: getfield sk0 : Lf/VA;
/*     */     //   483: aload_0
/*     */     //   484: getfield Kd : I
/*     */     //   487: bipush #30
/*     */     //   489: iadd
/*     */     //   490: aload_0
/*     */     //   491: getfield er0 : I
/*     */     //   494: bipush #18
/*     */     //   496: iadd
/*     */     //   497: invokevirtual ME : (II)Z
/*     */     //   500: pop
/*     */     //   501: getfield Kx0 : Lf/VA;
/*     */     //   504: astore_1
/*     */     //   505: getfield sk0 : Lf/VA;
/*     */     //   508: dup
/*     */     //   509: getfield Kd : I
/*     */     //   512: istore_2
/*     */     //   513: getfield er0 : I
/*     */     //   516: bipush #15
/*     */     //   518: isub
/*     */     //   519: istore_3
/*     */     //   520: goto -> 1068
/*     */     //   523: invokestatic XU : ()Z
/*     */     //   526: ifeq -> 1075
/*     */     //   529: aload_0
/*     */     //   530: dup
/*     */     //   531: dup2
/*     */     //   532: getfield ee : Lf/LpT3;
/*     */     //   535: invokevirtual mM : ()V
/*     */     //   538: getfield ee : Lf/LpT3;
/*     */     //   541: dup
/*     */     //   542: aload_0
/*     */     //   543: dup
/*     */     //   544: getfield Kd : I
/*     */     //   547: istore_1
/*     */     //   548: getfield xY : I
/*     */     //   551: swap
/*     */     //   552: getfield xY : I
/*     */     //   555: isub
/*     */     //   556: iload_1
/*     */     //   557: iadd
/*     */     //   558: bipush #6
/*     */     //   560: isub
/*     */     //   561: aload_0
/*     */     //   562: invokevirtual mD : ()I
/*     */     //   565: aload_0
/*     */     //   566: getfield ee : Lf/LpT3;
/*     */     //   569: invokevirtual Hy : ()I
/*     */     //   572: isub
/*     */     //   573: iconst_2
/*     */     //   574: isub
/*     */     //   575: invokevirtual ME : (II)Z
/*     */     //   578: pop
/*     */     //   579: getfield Kb : Lf/Dm;
/*     */     //   582: astore_1
/*     */     //   583: getfield As : Lf/rH;
/*     */     //   586: getfield V1 : F
/*     */     //   589: fconst_1
/*     */     //   590: fcmpl
/*     */     //   591: ifle -> 600
/*     */     //   594: bipush #72
/*     */     //   596: istore_2
/*     */     //   597: goto -> 603
/*     */     //   600: bipush #40
/*     */     //   602: istore_2
/*     */     //   603: aload_0
/*     */     //   604: dup
/*     */     //   605: dup2
/*     */     //   606: aload_1
/*     */     //   607: iload_2
/*     */     //   608: bipush #8
/*     */     //   610: invokevirtual Tm : (II)Z
/*     */     //   613: pop
/*     */     //   614: getfield Kb : Lf/Dm;
/*     */     //   617: aload_0
/*     */     //   618: getfield Kd : I
/*     */     //   621: iconst_4
/*     */     //   622: iadd
/*     */     //   623: aload_0
/*     */     //   624: getfield er0 : I
/*     */     //   627: bipush #65
/*     */     //   629: iadd
/*     */     //   630: invokevirtual ME : (II)Z
/*     */     //   633: pop
/*     */     //   634: getfield Iw : Lf/VA;
/*     */     //   637: aload_0
/*     */     //   638: getfield Kd : I
/*     */     //   641: iconst_2
/*     */     //   642: iadd
/*     */     //   643: aload_0
/*     */     //   644: invokevirtual mD : ()I
/*     */     //   647: aload_0
/*     */     //   648: getfield Iw : Lf/VA;
/*     */     //   651: getfield TS : Lf/rH;
/*     */     //   654: invokevirtual cA : ()I
/*     */     //   657: isub
/*     */     //   658: invokevirtual ME : (II)Z
/*     */     //   661: pop
/*     */     //   662: iconst_1
/*     */     //   663: istore_1
/*     */     //   664: getfield OR : Lf/VA;
/*     */     //   667: aload_0
/*     */     //   668: getfield Kd : I
/*     */     //   671: iconst_1
/*     */     //   672: iadd
/*     */     //   673: aload_0
/*     */     //   674: getfield er0 : I
/*     */     //   677: iconst_1
/*     */     //   678: iadd
/*     */     //   679: invokevirtual ME : (II)Z
/*     */     //   682: pop
/*     */     //   683: getfield OR : Lf/VA;
/*     */     //   686: getfield TS : Lf/rH;
/*     */     //   689: invokevirtual cA : ()I
/*     */     //   692: ifle -> 710
/*     */     //   695: aload_0
/*     */     //   696: getfield OR : Lf/VA;
/*     */     //   699: getfield TS : Lf/rH;
/*     */     //   702: invokevirtual cA : ()I
/*     */     //   705: iconst_3
/*     */     //   706: isub
/*     */     //   707: iload_1
/*     */     //   708: iadd
/*     */     //   709: istore_1
/*     */     //   710: aload_0
/*     */     //   711: dup
/*     */     //   712: dup
/*     */     //   713: getfield mG0 : Lf/VA;
/*     */     //   716: aload_0
/*     */     //   717: getfield Kd : I
/*     */     //   720: iconst_1
/*     */     //   721: iadd
/*     */     //   722: aload_0
/*     */     //   723: getfield er0 : I
/*     */     //   726: iload_1
/*     */     //   727: iadd
/*     */     //   728: invokevirtual ME : (II)Z
/*     */     //   731: pop
/*     */     //   732: getfield Ld : Lf/VA;
/*     */     //   735: aload_0
/*     */     //   736: dup
/*     */     //   737: invokevirtual m40 : ()I
/*     */     //   740: aload_0
/*     */     //   741: getfield Ld : Lf/VA;
/*     */     //   744: getfield TS : Lf/rH;
/*     */     //   747: invokevirtual e00 : ()I
/*     */     //   750: isub
/*     */     //   751: iconst_1
/*     */     //   752: isub
/*     */     //   753: istore_1
/*     */     //   754: getfield er0 : I
/*     */     //   757: iload_1
/*     */     //   758: swap
/*     */     //   759: invokevirtual ME : (II)Z
/*     */     //   762: pop
/*     */     //   763: getfield uE0 : Lf/UN;
/*     */     //   766: dup
/*     */     //   767: astore_1
/*     */     //   768: ifnull -> 851
/*     */     //   771: aload_1
/*     */     //   772: aload_0
/*     */     //   773: dup
/*     */     //   774: getfield Kd : I
/*     */     //   777: istore_2
/*     */     //   778: getfield er0 : I
/*     */     //   781: istore_3
/*     */     //   782: bipush #100
/*     */     //   784: istore #4
/*     */     //   786: bipush #100
/*     */     //   788: istore #5
/*     */     //   790: getfield rq : I
/*     */     //   793: iload_2
/*     */     //   794: if_icmpne -> 826
/*     */     //   797: aload_1
/*     */     //   798: getfield Lm : I
/*     */     //   801: iload_3
/*     */     //   802: if_icmpne -> 826
/*     */     //   805: aload_1
/*     */     //   806: getfield eY : I
/*     */     //   809: iload #4
/*     */     //   811: if_icmpne -> 826
/*     */     //   814: aload_1
/*     */     //   815: getfield ue0 : I
/*     */     //   818: iload #5
/*     */     //   820: if_icmpne -> 826
/*     */     //   823: goto -> 851
/*     */     //   826: aload_1
/*     */     //   827: dup
/*     */     //   828: dup
/*     */     //   829: dup2
/*     */     //   830: iload_2
/*     */     //   831: putfield rq : I
/*     */     //   834: iload_3
/*     */     //   835: putfield Lm : I
/*     */     //   838: iload #4
/*     */     //   840: putfield eY : I
/*     */     //   843: iload #5
/*     */     //   845: putfield ue0 : I
/*     */     //   848: invokevirtual bK : ()V
/*     */     //   851: aload_0
/*     */     //   852: getfield MQ : Lf/Uc0;
/*     */     //   855: getfield Nul : Lf/aq0;
/*     */     //   858: invokestatic requireNonNull : (Ljava/lang/Object;)Ljava/lang/Object;
/*     */     //   861: getstatic f/aq0.dy : Lf/aq0;
/*     */     //   864: if_acmpne -> 961
/*     */     //   867: aload_0
/*     */     //   868: dup
/*     */     //   869: dup
/*     */     //   870: getfield OR : Lf/VA;
/*     */     //   873: aload_0
/*     */     //   874: getfield Kd : I
/*     */     //   877: bipush #45
/*     */     //   879: iadd
/*     */     //   880: aload_0
/*     */     //   881: getfield er0 : I
/*     */     //   884: bipush #11
/*     */     //   886: iadd
/*     */     //   887: invokevirtual ME : (II)Z
/*     */     //   890: pop
/*     */     //   891: getfield mG0 : Lf/VA;
/*     */     //   894: astore_1
/*     */     //   895: getfield OR : Lf/VA;
/*     */     //   898: dup
/*     */     //   899: dup
/*     */     //   900: getfield Kd : I
/*     */     //   903: istore_2
/*     */     //   904: getfield er0 : I
/*     */     //   907: istore_3
/*     */     //   908: getfield TS : Lf/rH;
/*     */     //   911: invokevirtual cA : ()I
/*     */     //   914: ifle -> 924
/*     */     //   917: bipush #16
/*     */     //   919: istore #4
/*     */     //   921: goto -> 927
/*     */     //   924: iconst_0
/*     */     //   925: istore #4
/*     */     //   927: aload_0
/*     */     //   928: dup
/*     */     //   929: dup
/*     */     //   930: aload_1
/*     */     //   931: iload_2
/*     */     //   932: iload_3
/*     */     //   933: iload #4
/*     */     //   935: iadd
/*     */     //   936: invokevirtual ME : (II)Z
/*     */     //   939: pop
/*     */     //   940: getfield sk0 : Lf/VA;
/*     */     //   943: astore_1
/*     */     //   944: getfield Kd : I
/*     */     //   947: bipush #16
/*     */     //   949: iadd
/*     */     //   950: istore_2
/*     */     //   951: getfield er0 : I
/*     */     //   954: bipush #14
/*     */     //   956: iadd
/*     */     //   957: istore_3
/*     */     //   958: goto -> 1038
/*     */     //   961: aload_0
/*     */     //   962: getfield oj0 : Z
/*     */     //   965: ifeq -> 1017
/*     */     //   968: aload_0
/*     */     //   969: getfield sk0 : Lf/VA;
/*     */     //   972: aload_0
/*     */     //   973: dup
/*     */     //   974: invokevirtual m40 : ()I
/*     */     //   977: aload_0
/*     */     //   978: getfield sk0 : Lf/VA;
/*     */     //   981: getfield TS : Lf/rH;
/*     */     //   984: invokevirtual e00 : ()I
/*     */     //   987: isub
/*     */     //   988: iconst_4
/*     */     //   989: isub
/*     */     //   990: istore_1
/*     */     //   991: invokevirtual e3 : ()I
/*     */     //   994: istore_2
/*     */     //   995: iload_1
/*     */     //   996: aload_0
/*     */     //   997: getfield Ld : Lf/VA;
/*     */     //   1000: getfield TS : Lf/rH;
/*     */     //   1003: invokevirtual cA : ()I
/*     */     //   1006: iload_2
/*     */     //   1007: iadd
/*     */     //   1008: iconst_5
/*     */     //   1009: iadd
/*     */     //   1010: invokevirtual ME : (II)Z
/*     */     //   1013: pop
/*     */     //   1014: goto -> 1045
/*     */     //   1017: aload_0
/*     */     //   1018: dup
/*     */     //   1019: dup
/*     */     //   1020: getfield sk0 : Lf/VA;
/*     */     //   1023: astore_1
/*     */     //   1024: getfield Kd : I
/*     */     //   1027: bipush #33
/*     */     //   1029: iadd
/*     */     //   1030: istore_2
/*     */     //   1031: getfield er0 : I
/*     */     //   1034: bipush #20
/*     */     //   1036: iadd
/*     */     //   1037: istore_3
/*     */     //   1038: aload_1
/*     */     //   1039: iload_2
/*     */     //   1040: iload_3
/*     */     //   1041: invokevirtual ME : (II)Z
/*     */     //   1044: pop
/*     */     //   1045: aload_0
/*     */     //   1046: dup
/*     */     //   1047: getfield Kx0 : Lf/VA;
/*     */     //   1050: astore_1
/*     */     //   1051: getfield sk0 : Lf/VA;
/*     */     //   1054: dup
/*     */     //   1055: getfield Kd : I
/*     */     //   1058: bipush #17
/*     */     //   1060: iadd
/*     */     //   1061: istore_2
/*     */     //   1062: getfield er0 : I
/*     */     //   1065: iconst_1
/*     */     //   1066: isub
/*     */     //   1067: istore_3
/*     */     //   1068: aload_1
/*     */     //   1069: iload_2
/*     */     //   1070: iload_3
/*     */     //   1071: invokevirtual ME : (II)Z
/*     */     //   1074: pop
/*     */     //   1075: aload_0
/*     */     //   1076: invokespecial d40 : ()V
/*     */     //   1079: return
/*     */     // Line number table:
/*     */     //   Java source line number -> byte code offset
/*     */     //   #1	-> 4
/*     */     //   #2	-> 7
/*     */     //   #3	-> 31
/*     */     //   #4	-> 37
/*     */     //   #5	-> 43
/*     */     //   #6	-> 47
/*     */     //   #7	-> 62
/*     */     //   #8	-> 68
/*     */     //   #9	-> 74
/*     */     //   #10	-> 78
/*     */     //   #11	-> 90
/*     */     //   #12	-> 93
/*     */     //   #13	-> 104
/*     */     //   #14	-> 110
/*     */     //   #15	-> 115
/*     */     //   #16	-> 123
/*     */     //   #17	-> 133
/*     */     //   #18	-> 136
/*     */     //   #19	-> 147
/*     */     //   #20	-> 155
/*     */     //   #21	-> 160
/*     */     //   #22	-> 168
/*     */     //   #23	-> 172
/*     */     //   #24	-> 180
/*     */     //   #25	-> 185
/*     */     //   #26	-> 190
/*     */     //   #27	-> 203
/*     */     //   #28	-> 209
/*     */     //   #29	-> 214
/*     */     //   #30	-> 218
/*     */     //   #31	-> 221
/*     */     //   #32	-> 226
/*     */     //   #33	-> 233
/*     */     //   #34	-> 236
/*     */     //   #35	-> 246
/*     */     //   #36	-> 252
/*     */     //   #37	-> 280
/*     */     //   #38	-> 284
/*     */     //   #39	-> 288
/*     */     //   #40	-> 294
/*     */     //   #41	-> 301
/*     */     //   #42	-> 304
/*     */     //   #43	-> 308
/*     */     //   #44	-> 312
/*     */     //   #45	-> 315
/*     */     //   #46	-> 319
/*     */     //   #47	-> 326
/*     */     //   #48	-> 333
/*     */     //   #49	-> 336
/*     */     //   #50	-> 346
/*     */     //   #51	-> 350
/*     */     //   #52	-> 365
/*     */     //   #53	-> 376
/*     */     //   #54	-> 379
/*     */     //   #55	-> 392
/*     */     //   #56	-> 399
/*     */     //   #57	-> 404
/*     */     //   #58	-> 408
/*     */     //   #59	-> 417
/*     */     //   #60	-> 421
/*     */     //   #61	-> 425
/*     */     //   #62	-> 428
/*     */     //   #63	-> 453
/*     */     //   #64	-> 457
/*     */     //   #65	-> 461
/*     */     //   #66	-> 468
/*     */     //   #67	-> 480
/*     */     //   #68	-> 484
/*     */     //   #69	-> 491
/*     */     //   #70	-> 497
/*     */     //   #71	-> 501
/*     */     //   #72	-> 509
/*     */     //   #73	-> 513
/*     */     //   #74	-> 523
/*     */     //   #75	-> 544
/*     */     //   #76	-> 548
/*     */     //   #77	-> 552
/*     */     //   #78	-> 562
/*     */     //   #79	-> 575
/*     */     //   #80	-> 579
/*     */     //   #81	-> 583
/*     */     //   #82	-> 586
/*     */     //   #83	-> 610
/*     */     //   #84	-> 618
/*     */     //   #85	-> 624
/*     */     //   #86	-> 630
/*     */     //   #87	-> 634
/*     */     //   #88	-> 638
/*     */     //   #89	-> 644
/*     */     //   #90	-> 651
/*     */     //   #91	-> 654
/*     */     //   #92	-> 658
/*     */     //   #93	-> 664
/*     */     //   #94	-> 668
/*     */     //   #95	-> 674
/*     */     //   #96	-> 679
/*     */     //   #97	-> 683
/*     */     //   #98	-> 686
/*     */     //   #99	-> 689
/*     */     //   #100	-> 699
/*     */     //   #101	-> 702
/*     */     //   #102	-> 717
/*     */     //   #103	-> 723
/*     */     //   #104	-> 728
/*     */     //   #105	-> 732
/*     */     //   #106	-> 744
/*     */     //   #107	-> 747
/*     */     //   #108	-> 754
/*     */     //   #109	-> 759
/*     */     //   #110	-> 763
/*     */     //   #111	-> 774
/*     */     //   #112	-> 778
/*     */     //   #113	-> 790
/*     */     //   #114	-> 852
/*     */     //   #115	-> 855
/*     */     //   #116	-> 858
/*     */     //   #117	-> 874
/*     */     //   #118	-> 881
/*     */     //   #119	-> 887
/*     */     //   #120	-> 891
/*     */     //   #121	-> 900
/*     */     //   #122	-> 904
/*     */     //   #123	-> 908
/*     */     //   #124	-> 911
/*     */     //   #125	-> 936
/*     */     //   #126	-> 940
/*     */     //   #127	-> 944
/*     */     //   #128	-> 951
/*     */     //   #129	-> 962
/*     */     //   #130	-> 981
/*     */     //   #131	-> 984
/*     */     //   #132	-> 1000
/*     */     //   #133	-> 1003
/*     */     //   #134	-> 1010
/*     */     //   #135	-> 1020
/*     */     //   #136	-> 1024
/*     */     //   #137	-> 1031
/*     */     //   #138	-> 1041
/*     */     //   #139	-> 1047
/*     */     //   #140	-> 1055
/*     */     //   #141	-> 1062
/*     */     //   #142	-> 1071
/*     */     //   #143	-> 1076
/*     */   }
/*     */   
/*     */   public final void yV(throws paramthrows) {
/*     */     UN uN;
/*     */     if ((uN = this.uE0) != null) {
/*     */       int i = this.Kd;
/*     */       int j = this.er0;
/*     */       byte b1 = 100, b2 = 100;
/*     */       if (uN.rq != i || uN.Lm != j || uN.eY != b1 || uN.ue0 != b2) {
/*     */         uN.rq = i;
/*     */         uN.Lm = j;
/*     */         uN.eY = b1;
/*     */         uN.ue0 = b2;
/*     */         uN.bK();
/*     */       } 
/*     */       JX jX = km.wI0.C50;
/*     */       pe0 pe0;
/*     */       if ((pe0 = (uN = this.uE0).XF0) != null) {
/*     */         Texture texture = pe0.G3;
/*     */         float[] arrayOfFloat = uN.cG;
/*     */         int k = uN.JS;
/*     */         jX.xu(texture, arrayOfFloat, k);
/*     */       } 
/*     */     } 
/*     */     this.en = cL();
/*     */     super.yV(paramthrows);
/*     */   }
/*     */   
/*     */   public boolean cL() {
/*     */     return this.I20 ^ true;
/*     */   }
/*     */   
/*     */   public final void Ve(throws paramthrows, int paramInt1, int paramInt2, int paramInt3) {
/*     */     if (this.I20 && this.MQ.Nul.va0)
/*     */       this.As.sG0(paramInt1, paramInt2); 
/*     */   }
/*     */   
/*     */   public final void hC(boolean paramBoolean) {
/*     */     this.ZF = paramBoolean;
/*     */   }
/*     */   
/*     */   public boolean y1() {
/*     */     return this.FO;
/*     */   }
/*     */   
/*     */   public void GO() {
/*     */     Qv0[] arrayOfQv0;
/*     */     (arrayOfQv0 = new Qv0[1])[0] = this;
/*     */     int i = this.A90 / 60;
/*     */     int j = this.Kd;
/*     */     int k = this.er0;
/*     */     js.vu0.jv0(false, i, j, this, arrayOfQv0, k);
/*     */   }
/*     */   
/*     */   public final void wU(boolean paramBoolean) {
/*     */     this.FO = paramBoolean;
/*     */   }
/*     */   
/*     */   public final int compareTo(Object paramObject) {
/*     */     this = (Qv0)paramObject;
/*     */     return Integer.compare(fH0(), fH0());
/*     */   }
/*     */   
/*     */   public final void ay(Fd0 paramFd0) {
/*     */     this.dw0 = paramFd0;
/*     */   }
/*     */   
/*     */   public final void Ou0() {
/*     */     this.dr = true;
/*     */     Dm dm;
/*     */     if ((dm = this.Kb).fr0 != null)
/*     */       jf0(dm); 
/*     */     this.uE0 = null;
/*     */   } }


/* Location:              /Users/vnnsnnt/Documents/Codespace/JavaWorkspace/RedTrainer/src/main/java/org/trainer/client/PokeMMO.jar!/f/Qv0.class
 * Java compiler version: 8 (52.0)
 * JD-Core Version:       1.1.3
 */