/* 1 */ package f;public final class R3 implements qd0 { public final void HD(Me paramMe, CharSequence paramCharSequence) { boolean bool = false; int i = paramCharSequence.length();
/* 2 */     Color color = paramMe.Ca.Yb;
/* 3 */     bq0(paramMe, paramCharSequence, bool, i, color, 0.0F, 8, false, null); }
/*   */ 
/*   */   
/*   */   public static final Lc f70 = Lp0.vu0(zj.class);
/*   */   public static final o0 Ax = new o0(4);
/*   */   public final fQ m0;
/*   */   public final o0 eN;
/*   */   public int w6;
/*   */   public float e20;
/*   */   public float Df0;
/*   */   
/*   */   public R3() {
/*   */     fQ fQ1;
/*   */     o0 o01;
/*   */     this(1);
/*   */     this.m0 = this;
/*   */     this(2);
/*   */     this.eN = this;
/*   */   }
/*   */   
/*   */   public R3(Me paramMe, CharSequence paramCharSequence) {
/*   */     fQ fQ1;
/*   */     o0 o01;
/*   */     this(1);
/*   */     this.m0 = this;
/*   */     this(2);
/*   */     this.eN = this;
/*   */     HD(paramMe, paramCharSequence);
/*   */   }
/*   */   
/*   */   public R3(Me paramMe, CharSequence paramCharSequence, Color paramColor, float paramFloat, int paramInt, boolean paramBoolean) {
/*   */     fQ fQ1;
/*   */     o0 o01;
/*   */     this(1);
/*   */     this.m0 = this;
/*   */     this(2);
/*   */     this.eN = this;
/*   */     H2(paramMe, paramCharSequence, paramColor, paramFloat, paramInt, paramBoolean);
/*   */   }
/*   */   
/*   */   public R3(Me paramMe, CharSequence paramCharSequence, int paramInt1, int paramInt2, Color paramColor, float paramFloat, int paramInt3, boolean paramBoolean, String paramString) {
/*   */     fQ fQ1;
/*   */     o0 o01;
/*   */     this(1);
/*   */     this.m0 = this;
/*   */     this(2);
/*   */     this.eN = this;
/*   */     bq0(paramMe, paramCharSequence, paramInt1, paramInt2, paramColor, paramFloat, paramInt3, paramBoolean, paramString);
/*   */   }
/*   */   
/*   */   public final void H2(Me paramMe, CharSequence paramCharSequence, Color paramColor, float paramFloat, int paramInt, boolean paramBoolean) {
/*   */     int i = paramCharSequence.length();
/*   */     bq0(paramMe, paramCharSequence, 0, i, paramColor, paramFloat, paramInt, paramBoolean, null);
/*   */   }
/*   */   
/*   */   public final void bq0(Me paramMe, CharSequence paramCharSequence, int paramInt1, int paramInt2, Color paramColor, float paramFloat, int paramInt3, boolean paramBoolean, String paramString) {
/*   */     // Byte code:
/*   */     //   0: iload_3
/*   */     //   1: aload_1
/*   */     //   2: aload_0
/*   */     //   3: invokevirtual reset : ()V
/*   */     //   6: getfield XO : Lf/vQ;
/*   */     //   9: astore_1
/*   */     //   10: iload #4
/*   */     //   12: if_icmpne -> 24
/*   */     //   15: aload_0
/*   */     //   16: aload_1
/*   */     //   17: getfield Y5 : F
/*   */     //   20: putfield Df0 : F
/*   */     //   23: return
/*   */     //   24: iload #8
/*   */     //   26: ifeq -> 43
/*   */     //   29: fload #6
/*   */     //   31: aload_1
/*   */     //   32: getfield kw : F
/*   */     //   35: ldc 3.0
/*   */     //   37: fmul
/*   */     //   38: invokestatic max : (FF)F
/*   */     //   41: fstore #6
/*   */     //   43: iload #8
/*   */     //   45: ifne -> 62
/*   */     //   48: aload #9
/*   */     //   50: ifnull -> 56
/*   */     //   53: goto -> 62
/*   */     //   56: iconst_0
/*   */     //   57: istore #8
/*   */     //   59: goto -> 65
/*   */     //   62: iconst_1
/*   */     //   63: istore #8
/*   */     //   65: aload_0
/*   */     //   66: aload #5
/*   */     //   68: invokevirtual toIntBits : ()I
/*   */     //   71: istore #5
/*   */     //   73: getfield eN : Lf/o0;
/*   */     //   76: dup
/*   */     //   77: dup
/*   */     //   78: astore #10
/*   */     //   80: iconst_0
/*   */     //   81: istore #11
/*   */     //   83: getfield Ky : [I
/*   */     //   86: astore #12
/*   */     //   88: getfield mG0 : I
/*   */     //   91: dup
/*   */     //   92: istore #13
/*   */     //   94: iconst_1
/*   */     //   95: iadd
/*   */     //   96: aload #12
/*   */     //   98: arraylength
/*   */     //   99: if_icmplt -> 122
/*   */     //   102: aload #10
/*   */     //   104: iload #13
/*   */     //   106: i2f
/*   */     //   107: ldc 1.75
/*   */     //   109: fmul
/*   */     //   110: f2i
/*   */     //   111: bipush #8
/*   */     //   113: swap
/*   */     //   114: invokestatic max : (II)I
/*   */     //   117: invokevirtual YK0 : (I)[I
/*   */     //   120: astore #12
/*   */     //   122: aload_1
/*   */     //   123: aload #10
/*   */     //   125: dup
/*   */     //   126: getfield mG0 : I
/*   */     //   129: dup
/*   */     //   130: istore #10
/*   */     //   132: aload #12
/*   */     //   134: iload #10
/*   */     //   136: aload #12
/*   */     //   138: iload #10
/*   */     //   140: iload #11
/*   */     //   142: iastore
/*   */     //   143: iconst_1
/*   */     //   144: iadd
/*   */     //   145: iload #5
/*   */     //   147: iastore
/*   */     //   148: iconst_2
/*   */     //   149: iadd
/*   */     //   150: putfield mG0 : I
/*   */     //   153: getfield Zp : Z
/*   */     //   156: dup
/*   */     //   157: istore #10
/*   */     //   159: ifeq -> 170
/*   */     //   162: getstatic f/R3.Ax : Lf/o0;
/*   */     //   165: iload #5
/*   */     //   167: invokevirtual oU : (I)V
/*   */     //   170: aload_1
/*   */     //   171: iconst_0
/*   */     //   172: istore #11
/*   */     //   174: fconst_0
/*   */     //   175: fstore #12
/*   */     //   177: getfield DD : F
/*   */     //   180: fstore #13
/*   */     //   182: aconst_null
/*   */     //   183: astore #14
/*   */     //   185: aconst_null
/*   */     //   186: astore #15
/*   */     //   188: iload_3
/*   */     //   189: iload #5
/*   */     //   191: iload #11
/*   */     //   193: iload #5
/*   */     //   195: fload #12
/*   */     //   197: aload #14
/*   */     //   199: aload #15
/*   */     //   201: astore #17
/*   */     //   203: astore #16
/*   */     //   205: fstore #15
/*   */     //   207: istore #12
/*   */     //   209: istore #14
/*   */     //   211: istore #11
/*   */     //   213: istore #5
/*   */     //   215: iload_3
/*   */     //   216: iconst_0
/*   */     //   217: istore #18
/*   */     //   219: iload #4
/*   */     //   221: if_icmpne -> 258
/*   */     //   224: iload #5
/*   */     //   226: iload #4
/*   */     //   228: if_icmpne -> 234
/*   */     //   231: goto -> 1837
/*   */     //   234: iconst_1
/*   */     //   235: istore #14
/*   */     //   237: iload #11
/*   */     //   239: iload #4
/*   */     //   241: iload #14
/*   */     //   243: iload #18
/*   */     //   245: iload_3
/*   */     //   246: istore #11
/*   */     //   248: istore #19
/*   */     //   250: istore #18
/*   */     //   252: istore_3
/*   */     //   253: istore #14
/*   */     //   255: goto -> 747
/*   */     //   258: aload_2
/*   */     //   259: iload_3
/*   */     //   260: iconst_1
/*   */     //   261: iadd
/*   */     //   262: istore #19
/*   */     //   264: iload_3
/*   */     //   265: invokeinterface charAt : (I)C
/*   */     //   270: dup
/*   */     //   271: istore_3
/*   */     //   272: bipush #10
/*   */     //   274: if_icmpeq -> 723
/*   */     //   277: iload_3
/*   */     //   278: bipush #91
/*   */     //   280: if_icmpeq -> 286
/*   */     //   283: goto -> 717
/*   */     //   286: iload #10
/*   */     //   288: ifeq -> 717
/*   */     //   291: iload #19
/*   */     //   293: iload #4
/*   */     //   295: if_icmpne -> 301
/*   */     //   298: goto -> 618
/*   */     //   301: aload_2
/*   */     //   302: iload #19
/*   */     //   304: invokeinterface charAt : (I)C
/*   */     //   309: dup
/*   */     //   310: istore_3
/*   */     //   311: bipush #35
/*   */     //   313: if_icmpeq -> 452
/*   */     //   316: iload_3
/*   */     //   317: bipush #91
/*   */     //   319: if_icmpeq -> 446
/*   */     //   322: iload_3
/*   */     //   323: bipush #93
/*   */     //   325: if_icmpeq -> 409
/*   */     //   328: iload #19
/*   */     //   330: iconst_1
/*   */     //   331: iadd
/*   */     //   332: istore_3
/*   */     //   333: iload_3
/*   */     //   334: iload #4
/*   */     //   336: if_icmpge -> 618
/*   */     //   339: aload_2
/*   */     //   340: iload_3
/*   */     //   341: invokeinterface charAt : (I)C
/*   */     //   346: bipush #93
/*   */     //   348: if_icmpeq -> 357
/*   */     //   351: iinc #3, 1
/*   */     //   354: goto -> 333
/*   */     //   357: aload_2
/*   */     //   358: iload #19
/*   */     //   360: iload_3
/*   */     //   361: invokeinterface subSequence : (II)Ljava/lang/CharSequence;
/*   */     //   366: invokeinterface toString : ()Ljava/lang/String;
/*   */     //   371: getstatic f/GT.dU : Lf/f7;
/*   */     //   374: swap
/*   */     //   375: invokevirtual pd0 : (Ljava/lang/Object;)Ljava/lang/Object;
/*   */     //   378: checkcast com/badlogic/gdx/graphics/Color
/*   */     //   381: dup
/*   */     //   382: astore #20
/*   */     //   384: ifnonnull -> 390
/*   */     //   387: goto -> 618
/*   */     //   390: iload_3
/*   */     //   391: iload #19
/*   */     //   393: getstatic f/R3.Ax : Lf/o0;
/*   */     //   396: aload #20
/*   */     //   398: invokevirtual toIntBits : ()I
/*   */     //   401: invokevirtual oU : (I)V
/*   */     //   404: isub
/*   */     //   405: istore_3
/*   */     //   406: goto -> 620
/*   */     //   409: getstatic f/R3.Ax : Lf/o0;
/*   */     //   412: dup
/*   */     //   413: astore_3
/*   */     //   414: getfield mG0 : I
/*   */     //   417: dup
/*   */     //   418: istore #20
/*   */     //   420: iconst_1
/*   */     //   421: if_icmple -> 441
/*   */     //   424: aload_3
/*   */     //   425: getfield Ky : [I
/*   */     //   428: aload_3
/*   */     //   429: iload #20
/*   */     //   431: iconst_1
/*   */     //   432: isub
/*   */     //   433: dup
/*   */     //   434: istore_3
/*   */     //   435: putfield mG0 : I
/*   */     //   438: iload_3
/*   */     //   439: iaload
/*   */     //   440: pop
/*   */     //   441: iconst_0
/*   */     //   442: istore_3
/*   */     //   443: goto -> 620
/*   */     //   446: bipush #-2
/*   */     //   448: istore_3
/*   */     //   449: goto -> 620
/*   */     //   452: iconst_0
/*   */     //   453: istore_3
/*   */     //   454: iload #19
/*   */     //   456: iconst_1
/*   */     //   457: iadd
/*   */     //   458: istore #20
/*   */     //   460: iload #20
/*   */     //   462: iload #4
/*   */     //   464: if_icmpge -> 618
/*   */     //   467: aload_2
/*   */     //   468: iload #20
/*   */     //   470: invokeinterface charAt : (I)C
/*   */     //   475: dup
/*   */     //   476: istore #21
/*   */     //   478: bipush #93
/*   */     //   480: if_icmpne -> 548
/*   */     //   483: iload #20
/*   */     //   485: iload #19
/*   */     //   487: iconst_2
/*   */     //   488: iadd
/*   */     //   489: if_icmplt -> 618
/*   */     //   492: iload #20
/*   */     //   494: iload #19
/*   */     //   496: bipush #9
/*   */     //   498: iadd
/*   */     //   499: if_icmple -> 505
/*   */     //   502: goto -> 618
/*   */     //   505: iload #20
/*   */     //   507: iload #19
/*   */     //   509: isub
/*   */     //   510: dup
/*   */     //   511: istore #20
/*   */     //   513: bipush #8
/*   */     //   515: if_icmpge -> 532
/*   */     //   518: iload_3
/*   */     //   519: bipush #9
/*   */     //   521: iload #20
/*   */     //   523: isub
/*   */     //   524: iconst_2
/*   */     //   525: ishl
/*   */     //   526: ishl
/*   */     //   527: sipush #255
/*   */     //   530: ior
/*   */     //   531: istore_3
/*   */     //   532: getstatic f/R3.Ax : Lf/o0;
/*   */     //   535: iload_3
/*   */     //   536: invokestatic reverseBytes : (I)I
/*   */     //   539: invokevirtual oU : (I)V
/*   */     //   542: iload #20
/*   */     //   544: istore_3
/*   */     //   545: goto -> 620
/*   */     //   548: iload #21
/*   */     //   550: iload_3
/*   */     //   551: iconst_4
/*   */     //   552: ishl
/*   */     //   553: iload #21
/*   */     //   555: iadd
/*   */     //   556: istore_3
/*   */     //   557: bipush #48
/*   */     //   559: if_icmplt -> 575
/*   */     //   562: iload #21
/*   */     //   564: bipush #57
/*   */     //   566: if_icmpgt -> 575
/*   */     //   569: iinc #3, -48
/*   */     //   572: goto -> 612
/*   */     //   575: iload #21
/*   */     //   577: bipush #65
/*   */     //   579: if_icmplt -> 595
/*   */     //   582: iload #21
/*   */     //   584: bipush #70
/*   */     //   586: if_icmpgt -> 595
/*   */     //   589: iinc #3, -55
/*   */     //   592: goto -> 612
/*   */     //   595: iload #21
/*   */     //   597: bipush #97
/*   */     //   599: if_icmplt -> 618
/*   */     //   602: iload #21
/*   */     //   604: bipush #102
/*   */     //   606: if_icmpgt -> 618
/*   */     //   609: iinc #3, -87
/*   */     //   612: iinc #20, 1
/*   */     //   615: goto -> 460
/*   */     //   618: iconst_m1
/*   */     //   619: istore_3
/*   */     //   620: iload_3
/*   */     //   621: iflt -> 703
/*   */     //   624: iload_3
/*   */     //   625: iload #19
/*   */     //   627: iconst_1
/*   */     //   628: isub
/*   */     //   629: istore_3
/*   */     //   630: iconst_1
/*   */     //   631: iadd
/*   */     //   632: iload #19
/*   */     //   634: iadd
/*   */     //   635: dup
/*   */     //   636: istore #19
/*   */     //   638: iload #4
/*   */     //   640: if_icmpne -> 665
/*   */     //   643: iconst_1
/*   */     //   644: istore #14
/*   */     //   646: iload #11
/*   */     //   648: iload #14
/*   */     //   650: iload #18
/*   */     //   652: iload #19
/*   */     //   654: istore #11
/*   */     //   656: istore #19
/*   */     //   658: istore #18
/*   */     //   660: istore #14
/*   */     //   662: goto -> 747
/*   */     //   665: getstatic f/R3.Ax : Lf/o0;
/*   */     //   668: dup
/*   */     //   669: astore #11
/*   */     //   671: getfield Ky : [I
/*   */     //   674: aload #11
/*   */     //   676: getfield mG0 : I
/*   */     //   679: iconst_1
/*   */     //   680: isub
/*   */     //   681: iaload
/*   */     //   682: istore #11
/*   */     //   684: iload #11
/*   */     //   686: iload #14
/*   */     //   688: iload #18
/*   */     //   690: iload #19
/*   */     //   692: istore #11
/*   */     //   694: istore #19
/*   */     //   696: istore #18
/*   */     //   698: istore #14
/*   */     //   700: goto -> 747
/*   */     //   703: iload_3
/*   */     //   704: bipush #-2
/*   */     //   706: if_icmpne -> 717
/*   */     //   709: iload #19
/*   */     //   711: iconst_1
/*   */     //   712: iadd
/*   */     //   713: istore_3
/*   */     //   714: goto -> 215
/*   */     //   717: iload #19
/*   */     //   719: istore_3
/*   */     //   720: goto -> 215
/*   */     //   723: iload #19
/*   */     //   725: iconst_1
/*   */     //   726: isub
/*   */     //   727: istore_3
/*   */     //   728: iconst_1
/*   */     //   729: istore #18
/*   */     //   731: iload #11
/*   */     //   733: iload #14
/*   */     //   735: iload #18
/*   */     //   737: iload #19
/*   */     //   739: istore #11
/*   */     //   741: istore #19
/*   */     //   743: istore #18
/*   */     //   745: istore #14
/*   */     //   747: iload #14
/*   */     //   749: iload #12
/*   */     //   751: aload_0
/*   */     //   752: dup
/*   */     //   753: aload_1
/*   */     //   754: getstatic f/R3.f70 : Lf/Lc;
/*   */     //   757: dup
/*   */     //   758: astore #20
/*   */     //   760: invokevirtual obtain : ()Ljava/lang/Object;
/*   */     //   763: checkcast f/zj
/*   */     //   766: dup
/*   */     //   767: dup
/*   */     //   768: astore #21
/*   */     //   770: fload #15
/*   */     //   772: aload #21
/*   */     //   774: fconst_0
/*   */     //   775: putfield x0 : F
/*   */     //   778: putfield FI : F
/*   */     //   781: aload_2
/*   */     //   782: iload #5
/*   */     //   784: iload_3
/*   */     //   785: aload #17
/*   */     //   787: invokevirtual t30 : (Lf/zj;Ljava/lang/CharSequence;IILf/Jk0;)V
/*   */     //   790: getfield w6 : I
/*   */     //   793: aload #21
/*   */     //   795: getfield Pb : Lf/fQ;
/*   */     //   798: getfield Z8 : I
/*   */     //   801: iadd
/*   */     //   802: putfield w6 : I
/*   */     //   805: if_icmpeq -> 871
/*   */     //   808: aload_0
/*   */     //   809: getfield eN : Lf/o0;
/*   */     //   812: dup
/*   */     //   813: getfield mG0 : I
/*   */     //   816: iconst_2
/*   */     //   817: isub
/*   */     //   818: invokevirtual Vl : (I)I
/*   */     //   821: aload_0
/*   */     //   822: getfield w6 : I
/*   */     //   825: dup
/*   */     //   826: istore #12
/*   */     //   828: if_icmpne -> 849
/*   */     //   831: aload_0
/*   */     //   832: getfield eN : Lf/o0;
/*   */     //   835: dup
/*   */     //   836: getfield mG0 : I
/*   */     //   839: iconst_1
/*   */     //   840: isub
/*   */     //   841: iload #14
/*   */     //   843: invokevirtual X60 : (II)V
/*   */     //   846: goto -> 867
/*   */     //   849: aload_0
/*   */     //   850: dup
/*   */     //   851: getfield eN : Lf/o0;
/*   */     //   854: iload #12
/*   */     //   856: invokevirtual oU : (I)V
/*   */     //   859: getfield eN : Lf/o0;
/*   */     //   862: iload #14
/*   */     //   864: invokevirtual oU : (I)V
/*   */     //   867: iload #14
/*   */     //   869: istore #12
/*   */     //   871: aload #21
/*   */     //   873: getfield Pb : Lf/fQ;
/*   */     //   876: dup
/*   */     //   877: astore #22
/*   */     //   879: getfield Z8 : I
/*   */     //   882: ifne -> 900
/*   */     //   885: aload #16
/*   */     //   887: aload #20
/*   */     //   889: aload #21
/*   */     //   891: invokevirtual free : (Ljava/lang/Object;)V
/*   */     //   894: ifnonnull -> 1019
/*   */     //   897: goto -> 3350
/*   */     //   900: aload #16
/*   */     //   902: ifnonnull -> 921
/*   */     //   905: aload_0
/*   */     //   906: getfield m0 : Lf/fQ;
/*   */     //   909: aload #21
/*   */     //   911: invokevirtual Com3 : (Ljava/lang/Object;)V
/*   */     //   914: aload #21
/*   */     //   916: astore #16
/*   */     //   918: goto -> 1019
/*   */     //   921: aload #16
/*   */     //   923: dup
/*   */     //   924: getfield Pb : Lf/fQ;
/*   */     //   927: dup
/*   */     //   928: astore #17
/*   */     //   930: aload #22
/*   */     //   932: dup
/*   */     //   933: aload #17
/*   */     //   935: invokevirtual getClass : ()Ljava/lang/Class;
/*   */     //   938: pop
/*   */     //   939: getfield Uq0 : [Ljava/lang/Object;
/*   */     //   942: astore #17
/*   */     //   944: getfield Z8 : I
/*   */     //   947: istore #22
/*   */     //   949: aload #17
/*   */     //   951: iconst_0
/*   */     //   952: iload #22
/*   */     //   954: invokevirtual tu0 : ([Ljava/lang/Object;II)V
/*   */     //   957: getfield Qd0 : Lf/G3;
/*   */     //   960: dup
/*   */     //   961: astore #17
/*   */     //   963: getfield NB0 : I
/*   */     //   966: dup
/*   */     //   967: istore #22
/*   */     //   969: ifle -> 976
/*   */     //   972: iconst_1
/*   */     //   973: goto -> 977
/*   */     //   976: iconst_0
/*   */     //   977: ifeq -> 989
/*   */     //   980: aload #17
/*   */     //   982: iload #22
/*   */     //   984: iconst_1
/*   */     //   985: isub
/*   */     //   986: putfield NB0 : I
/*   */     //   989: aload #20
/*   */     //   991: aload #17
/*   */     //   993: aload #21
/*   */     //   995: getfield Qd0 : Lf/G3;
/*   */     //   998: dup
/*   */     //   999: getfield By0 : [F
/*   */     //   1002: astore #17
/*   */     //   1004: getfield NB0 : I
/*   */     //   1007: iconst_0
/*   */     //   1008: swap
/*   */     //   1009: aload #17
/*   */     //   1011: invokevirtual p : (II[F)V
/*   */     //   1014: aload #21
/*   */     //   1016: invokevirtual free : (Ljava/lang/Object;)V
/*   */     //   1019: iload #19
/*   */     //   1021: ifne -> 1048
/*   */     //   1024: iload #18
/*   */     //   1026: ifeq -> 1032
/*   */     //   1029: goto -> 1048
/*   */     //   1032: aload #16
/*   */     //   1034: getfield Pb : Lf/fQ;
/*   */     //   1037: invokevirtual peek : ()Ljava/lang/Object;
/*   */     //   1040: checkcast f/Jk0
/*   */     //   1043: astore #17
/*   */     //   1045: goto -> 1109
/*   */     //   1048: aload #16
/*   */     //   1050: dup
/*   */     //   1051: getfield Pb : Lf/fQ;
/*   */     //   1054: invokevirtual peek : ()Ljava/lang/Object;
/*   */     //   1057: checkcast f/Jk0
/*   */     //   1060: dup
/*   */     //   1061: astore #17
/*   */     //   1063: invokevirtual getClass : ()Ljava/lang/Class;
/*   */     //   1066: pop
/*   */     //   1067: getfield Qd0 : Lf/G3;
/*   */     //   1070: dup
/*   */     //   1071: astore #20
/*   */     //   1073: getfield By0 : [F
/*   */     //   1076: aload #20
/*   */     //   1078: getfield NB0 : I
/*   */     //   1081: iconst_1
/*   */     //   1082: isub
/*   */     //   1083: aload #17
/*   */     //   1085: getfield zq : I
/*   */     //   1088: aload #17
/*   */     //   1090: getfield eJ : I
/*   */     //   1093: iadd
/*   */     //   1094: i2f
/*   */     //   1095: aload_1
/*   */     //   1096: getfield gu0 : F
/*   */     //   1099: fmul
/*   */     //   1100: aload_1
/*   */     //   1101: getfield of : F
/*   */     //   1104: fsub
/*   */     //   1105: fastore
/*   */     //   1106: aconst_null
/*   */     //   1107: astore #17
/*   */     //   1109: iload #8
/*   */     //   1111: ifeq -> 3350
/*   */     //   1114: aload #16
/*   */     //   1116: getfield Pb : Lf/fQ;
/*   */     //   1119: getfield Z8 : I
/*   */     //   1122: ifne -> 1128
/*   */     //   1125: goto -> 3350
/*   */     //   1128: iload #19
/*   */     //   1130: ifne -> 1138
/*   */     //   1133: iload #18
/*   */     //   1135: ifeq -> 3350
/*   */     //   1138: aload #16
/*   */     //   1140: getfield Qd0 : Lf/G3;
/*   */     //   1143: dup
/*   */     //   1144: astore #20
/*   */     //   1146: getfield NB0 : I
/*   */     //   1149: ifeq -> 3339
/*   */     //   1152: aload #20
/*   */     //   1154: dup
/*   */     //   1155: getfield By0 : [F
/*   */     //   1158: iconst_0
/*   */     //   1159: faload
/*   */     //   1160: fstore #20
/*   */     //   1162: iconst_1
/*   */     //   1163: invokevirtual cON : (I)F
/*   */     //   1166: fload #20
/*   */     //   1168: fadd
/*   */     //   1169: fstore #20
/*   */     //   1171: iconst_2
/*   */     //   1172: istore #21
/*   */     //   1174: iload #21
/*   */     //   1176: aload #16
/*   */     //   1178: getfield Qd0 : Lf/G3;
/*   */     //   1181: getfield NB0 : I
/*   */     //   1184: if_icmpge -> 3350
/*   */     //   1187: aload #16
/*   */     //   1189: getfield Pb : Lf/fQ;
/*   */     //   1192: iload #21
/*   */     //   1194: iconst_1
/*   */     //   1195: isub
/*   */     //   1196: dup
/*   */     //   1197: istore #22
/*   */     //   1199: invokevirtual get : (I)Ljava/lang/Object;
/*   */     //   1202: checkcast f/Jk0
/*   */     //   1205: dup
/*   */     //   1206: astore #23
/*   */     //   1208: getfield zq : I
/*   */     //   1211: aload #23
/*   */     //   1213: getfield eJ : I
/*   */     //   1216: iadd
/*   */     //   1217: i2f
/*   */     //   1218: aload_1
/*   */     //   1219: getfield gu0 : F
/*   */     //   1222: fmul
/*   */     //   1223: aload_1
/*   */     //   1224: getfield of : F
/*   */     //   1227: fsub
/*   */     //   1228: fload #20
/*   */     //   1230: fadd
/*   */     //   1231: ldc_w 1.0E-4
/*   */     //   1234: fsub
/*   */     //   1235: fload #6
/*   */     //   1237: fcmpg
/*   */     //   1238: ifgt -> 1260
/*   */     //   1241: fload #20
/*   */     //   1243: aload #16
/*   */     //   1245: getfield Qd0 : Lf/G3;
/*   */     //   1248: getfield By0 : [F
/*   */     //   1251: iload #21
/*   */     //   1253: faload
/*   */     //   1254: fadd
/*   */     //   1255: fstore #20
/*   */     //   1257: goto -> 3322
/*   */     //   1260: aload #9
/*   */     //   1262: ifnull -> 2155
/*   */     //   1265: aload_1
/*   */     //   1266: aload #9
/*   */     //   1268: aload #16
/*   */     //   1270: getfield Pb : Lf/fQ;
/*   */     //   1273: getfield Z8 : I
/*   */     //   1276: istore_2
/*   */     //   1277: getstatic f/R3.f70 : Lf/Lc;
/*   */     //   1280: invokevirtual obtain : ()Ljava/lang/Object;
/*   */     //   1283: checkcast f/zj
/*   */     //   1286: astore_3
/*   */     //   1287: invokevirtual length : ()I
/*   */     //   1290: istore #4
/*   */     //   1292: aload_3
/*   */     //   1293: aload #9
/*   */     //   1295: iconst_0
/*   */     //   1296: iload #4
/*   */     //   1298: aconst_null
/*   */     //   1299: invokevirtual t30 : (Lf/zj;Ljava/lang/CharSequence;IILf/Jk0;)V
/*   */     //   1302: aload_3
/*   */     //   1303: fconst_0
/*   */     //   1304: fstore #4
/*   */     //   1306: getfield Qd0 : Lf/G3;
/*   */     //   1309: getfield NB0 : I
/*   */     //   1312: ifle -> 1404
/*   */     //   1315: aload_3
/*   */     //   1316: dup
/*   */     //   1317: getfield Pb : Lf/fQ;
/*   */     //   1320: invokevirtual peek : ()Ljava/lang/Object;
/*   */     //   1323: checkcast f/Jk0
/*   */     //   1326: dup
/*   */     //   1327: astore #5
/*   */     //   1329: invokevirtual getClass : ()Ljava/lang/Class;
/*   */     //   1332: pop
/*   */     //   1333: getfield Qd0 : Lf/G3;
/*   */     //   1336: dup
/*   */     //   1337: astore #8
/*   */     //   1339: getfield By0 : [F
/*   */     //   1342: dup
/*   */     //   1343: astore #11
/*   */     //   1345: aload #8
/*   */     //   1347: getfield NB0 : I
/*   */     //   1350: dup
/*   */     //   1351: istore #8
/*   */     //   1353: iconst_1
/*   */     //   1354: isub
/*   */     //   1355: aload #5
/*   */     //   1357: getfield zq : I
/*   */     //   1360: aload #5
/*   */     //   1362: getfield eJ : I
/*   */     //   1365: iadd
/*   */     //   1366: i2f
/*   */     //   1367: aload_1
/*   */     //   1368: getfield gu0 : F
/*   */     //   1371: fmul
/*   */     //   1372: aload_1
/*   */     //   1373: getfield of : F
/*   */     //   1376: fsub
/*   */     //   1377: fastore
/*   */     //   1378: iconst_1
/*   */     //   1379: istore #5
/*   */     //   1381: iload #5
/*   */     //   1383: iload #8
/*   */     //   1385: if_icmpge -> 1404
/*   */     //   1388: fload #4
/*   */     //   1390: aload #11
/*   */     //   1392: iload #5
/*   */     //   1394: faload
/*   */     //   1395: fadd
/*   */     //   1396: fstore #4
/*   */     //   1398: iinc #5, 1
/*   */     //   1401: goto -> 1381
/*   */     //   1404: aload #16
/*   */     //   1406: dup
/*   */     //   1407: fload #6
/*   */     //   1409: fload #4
/*   */     //   1411: fsub
/*   */     //   1412: fstore #4
/*   */     //   1414: iconst_0
/*   */     //   1415: istore #5
/*   */     //   1417: getfield x0 : F
/*   */     //   1420: fstore #8
/*   */     //   1422: getfield Qd0 : Lf/G3;
/*   */     //   1425: getfield By0 : [F
/*   */     //   1428: astore #11
/*   */     //   1430: iload #5
/*   */     //   1432: aload #16
/*   */     //   1434: getfield Qd0 : Lf/G3;
/*   */     //   1437: getfield NB0 : I
/*   */     //   1440: if_icmpge -> 1469
/*   */     //   1443: fload #8
/*   */     //   1445: aload #11
/*   */     //   1447: iload #5
/*   */     //   1449: faload
/*   */     //   1450: fadd
/*   */     //   1451: dup
/*   */     //   1452: fstore #8
/*   */     //   1454: fload #4
/*   */     //   1456: fcmpl
/*   */     //   1457: ifle -> 1463
/*   */     //   1460: goto -> 1469
/*   */     //   1463: iinc #5, 1
/*   */     //   1466: goto -> 1430
/*   */     //   1469: iload #5
/*   */     //   1471: iconst_1
/*   */     //   1472: if_icmple -> 1685
/*   */     //   1475: aload #16
/*   */     //   1477: dup
/*   */     //   1478: getfield Pb : Lf/fQ;
/*   */     //   1481: iload #5
/*   */     //   1483: iconst_1
/*   */     //   1484: isub
/*   */     //   1485: invokevirtual pL0 : (I)V
/*   */     //   1488: getfield Qd0 : Lf/G3;
/*   */     //   1491: dup
/*   */     //   1492: astore #4
/*   */     //   1494: getfield NB0 : I
/*   */     //   1497: iload #5
/*   */     //   1499: if_icmple -> 1509
/*   */     //   1502: aload #4
/*   */     //   1504: iload #5
/*   */     //   1506: putfield NB0 : I
/*   */     //   1509: aload_3
/*   */     //   1510: aload #16
/*   */     //   1512: dup
/*   */     //   1513: getfield Pb : Lf/fQ;
/*   */     //   1516: invokevirtual peek : ()Ljava/lang/Object;
/*   */     //   1519: checkcast f/Jk0
/*   */     //   1522: dup
/*   */     //   1523: astore #4
/*   */     //   1525: invokevirtual getClass : ()Ljava/lang/Class;
/*   */     //   1528: pop
/*   */     //   1529: getfield Qd0 : Lf/G3;
/*   */     //   1532: dup
/*   */     //   1533: astore #5
/*   */     //   1535: getfield By0 : [F
/*   */     //   1538: aload #5
/*   */     //   1540: getfield NB0 : I
/*   */     //   1543: iconst_1
/*   */     //   1544: isub
/*   */     //   1545: aload #4
/*   */     //   1547: getfield zq : I
/*   */     //   1550: aload #4
/*   */     //   1552: getfield eJ : I
/*   */     //   1555: iadd
/*   */     //   1556: i2f
/*   */     //   1557: aload_1
/*   */     //   1558: getfield gu0 : F
/*   */     //   1561: fmul
/*   */     //   1562: aload_1
/*   */     //   1563: getfield of : F
/*   */     //   1566: fsub
/*   */     //   1567: fastore
/*   */     //   1568: getfield Qd0 : Lf/G3;
/*   */     //   1571: dup
/*   */     //   1572: astore #4
/*   */     //   1574: getfield NB0 : I
/*   */     //   1577: dup
/*   */     //   1578: istore #8
/*   */     //   1580: ifle -> 1723
/*   */     //   1583: iload #8
/*   */     //   1585: iconst_1
/*   */     //   1586: isub
/*   */     //   1587: dup
/*   */     //   1588: istore #8
/*   */     //   1590: aload #5
/*   */     //   1592: iconst_1
/*   */     //   1593: istore #11
/*   */     //   1595: invokevirtual getClass : ()Ljava/lang/Class;
/*   */     //   1598: pop
/*   */     //   1599: iload #11
/*   */     //   1601: iadd
/*   */     //   1602: aload #4
/*   */     //   1604: getfield NB0 : I
/*   */     //   1607: if_icmpgt -> 1631
/*   */     //   1610: aload #5
/*   */     //   1612: aload #4
/*   */     //   1614: getfield By0 : [F
/*   */     //   1617: astore #4
/*   */     //   1619: iload #11
/*   */     //   1621: iload #8
/*   */     //   1623: aload #4
/*   */     //   1625: invokevirtual p : (II[F)V
/*   */     //   1628: goto -> 1723
/*   */     //   1631: new java/lang/IllegalArgumentException
/*   */     //   1634: dup
/*   */     //   1635: new java/lang/StringBuilder
/*   */     //   1638: dup
/*   */     //   1639: invokespecial <init> : ()V
/*   */     //   1642: ldc_w 'offset + length must be <= size: '
/*   */     //   1645: invokevirtual append : (Ljava/lang/String;)Ljava/lang/StringBuilder;
/*   */     //   1648: iload #11
/*   */     //   1650: invokevirtual append : (I)Ljava/lang/StringBuilder;
/*   */     //   1653: ldc_w ' + '
/*   */     //   1656: invokevirtual append : (Ljava/lang/String;)Ljava/lang/StringBuilder;
/*   */     //   1659: iload #8
/*   */     //   1661: invokevirtual append : (I)Ljava/lang/StringBuilder;
/*   */     //   1664: ldc_w ' <= '
/*   */     //   1667: invokevirtual append : (Ljava/lang/String;)Ljava/lang/StringBuilder;
/*   */     //   1670: aload #4
/*   */     //   1672: getfield NB0 : I
/*   */     //   1675: invokevirtual append : (I)Ljava/lang/StringBuilder;
/*   */     //   1678: invokevirtual toString : ()Ljava/lang/String;
/*   */     //   1681: invokespecial <init> : (Ljava/lang/String;)V
/*   */     //   1684: athrow
/*   */     //   1685: aload #16
/*   */     //   1687: dup
/*   */     //   1688: getfield Pb : Lf/fQ;
/*   */     //   1691: invokevirtual clear : ()V
/*   */     //   1694: getfield Qd0 : Lf/G3;
/*   */     //   1697: dup
/*   */     //   1698: aload_3
/*   */     //   1699: swap
/*   */     //   1700: iconst_0
/*   */     //   1701: putfield NB0 : I
/*   */     //   1704: getfield Qd0 : Lf/G3;
/*   */     //   1707: dup
/*   */     //   1708: getfield By0 : [F
/*   */     //   1711: astore #4
/*   */     //   1713: getfield NB0 : I
/*   */     //   1716: iconst_0
/*   */     //   1717: swap
/*   */     //   1718: aload #4
/*   */     //   1720: invokevirtual p : (II[F)V
/*   */     //   1723: iload_2
/*   */     //   1724: aload #16
/*   */     //   1726: getfield Pb : Lf/fQ;
/*   */     //   1729: getfield Z8 : I
/*   */     //   1732: isub
/*   */     //   1733: dup
/*   */     //   1734: istore_2
/*   */     //   1735: ifle -> 1802
/*   */     //   1738: aload_1
/*   */     //   1739: aload_0
/*   */     //   1740: dup
/*   */     //   1741: getfield w6 : I
/*   */     //   1744: iload_2
/*   */     //   1745: isub
/*   */     //   1746: putfield w6 : I
/*   */     //   1749: getfield Zp : Z
/*   */     //   1752: ifeq -> 1802
/*   */     //   1755: aload_0
/*   */     //   1756: getfield eN : Lf/o0;
/*   */     //   1759: dup
/*   */     //   1760: astore_2
/*   */     //   1761: getfield mG0 : I
/*   */     //   1764: dup
/*   */     //   1765: istore #4
/*   */     //   1767: iconst_2
/*   */     //   1768: if_icmple -> 1802
/*   */     //   1771: aload_2
/*   */     //   1772: iload #4
/*   */     //   1774: iconst_2
/*   */     //   1775: isub
/*   */     //   1776: invokevirtual Vl : (I)I
/*   */     //   1779: aload_0
/*   */     //   1780: getfield w6 : I
/*   */     //   1783: if_icmplt -> 1802
/*   */     //   1786: aload_0
/*   */     //   1787: getfield eN : Lf/o0;
/*   */     //   1790: dup
/*   */     //   1791: getfield mG0 : I
/*   */     //   1794: iconst_2
/*   */     //   1795: isub
/*   */     //   1796: putfield mG0 : I
/*   */     //   1799: goto -> 1755
/*   */     //   1802: aload_0
/*   */     //   1803: aload #9
/*   */     //   1805: aload_0
/*   */     //   1806: aload #16
/*   */     //   1808: getfield Pb : Lf/fQ;
/*   */     //   1811: aload_3
/*   */     //   1812: getfield Pb : Lf/fQ;
/*   */     //   1815: invokevirtual OG0 : (Lf/fQ;)V
/*   */     //   1818: getfield w6 : I
/*   */     //   1821: istore_2
/*   */     //   1822: invokevirtual length : ()I
/*   */     //   1825: iload_2
/*   */     //   1826: iadd
/*   */     //   1827: putfield w6 : I
/*   */     //   1830: getstatic f/R3.f70 : Lf/Lc;
/*   */     //   1833: aload_3
/*   */     //   1834: invokevirtual free : (Ljava/lang/Object;)V
/*   */     //   1837: aload_0
/*   */     //   1838: dup
/*   */     //   1839: fload #15
/*   */     //   1841: aload_1
/*   */     //   1842: getfield Y5 : F
/*   */     //   1845: fstore_2
/*   */     //   1846: invokestatic abs : (F)F
/*   */     //   1849: fload_2
/*   */     //   1850: fadd
/*   */     //   1851: putfield Df0 : F
/*   */     //   1854: fconst_0
/*   */     //   1855: fstore_2
/*   */     //   1856: getfield m0 : Lf/fQ;
/*   */     //   1859: dup
/*   */     //   1860: getfield Uq0 : [Ljava/lang/Object;
/*   */     //   1863: astore_3
/*   */     //   1864: iconst_0
/*   */     //   1865: istore #4
/*   */     //   1867: getfield Z8 : I
/*   */     //   1870: istore #5
/*   */     //   1872: iload #4
/*   */     //   1874: iload #5
/*   */     //   1876: if_icmpge -> 2034
/*   */     //   1879: aload_3
/*   */     //   1880: iload #4
/*   */     //   1882: aaload
/*   */     //   1883: checkcast f/zj
/*   */     //   1886: dup
/*   */     //   1887: dup2
/*   */     //   1888: astore #8
/*   */     //   1890: getfield Qd0 : Lf/G3;
/*   */     //   1893: getfield By0 : [F
/*   */     //   1896: astore #9
/*   */     //   1898: getfield x0 : F
/*   */     //   1901: aload #9
/*   */     //   1903: iconst_0
/*   */     //   1904: faload
/*   */     //   1905: fadd
/*   */     //   1906: fstore #11
/*   */     //   1908: fconst_0
/*   */     //   1909: fstore #12
/*   */     //   1911: getfield Pb : Lf/fQ;
/*   */     //   1914: dup
/*   */     //   1915: getfield Uq0 : [Ljava/lang/Object;
/*   */     //   1918: astore #13
/*   */     //   1920: iconst_0
/*   */     //   1921: istore #14
/*   */     //   1923: getfield Z8 : I
/*   */     //   1926: istore #15
/*   */     //   1928: iload #14
/*   */     //   1930: iload #15
/*   */     //   1932: if_icmpge -> 1994
/*   */     //   1935: fload #11
/*   */     //   1937: aload #9
/*   */     //   1939: fload #12
/*   */     //   1941: aload #13
/*   */     //   1943: iload #14
/*   */     //   1945: aaload
/*   */     //   1946: checkcast f/Jk0
/*   */     //   1949: dup
/*   */     //   1950: astore #12
/*   */     //   1952: getfield zq : I
/*   */     //   1955: aload #12
/*   */     //   1957: getfield eJ : I
/*   */     //   1960: iadd
/*   */     //   1961: i2f
/*   */     //   1962: aload_1
/*   */     //   1963: getfield gu0 : F
/*   */     //   1966: fmul
/*   */     //   1967: aload_1
/*   */     //   1968: getfield of : F
/*   */     //   1971: fsub
/*   */     //   1972: fload #11
/*   */     //   1974: fadd
/*   */     //   1975: invokestatic max : (FF)F
/*   */     //   1978: fstore #12
/*   */     //   1980: iload #14
/*   */     //   1982: iconst_1
/*   */     //   1983: iadd
/*   */     //   1984: dup
/*   */     //   1985: istore #14
/*   */     //   1987: faload
/*   */     //   1988: fadd
/*   */     //   1989: fstore #11
/*   */     //   1991: goto -> 1928
/*   */     //   1994: fload_2
/*   */     //   1995: aload #8
/*   */     //   1997: fload #11
/*   */     //   1999: fload #12
/*   */     //   2001: invokestatic max : (FF)F
/*   */     //   2004: fstore_2
/*   */     //   2005: getfield x0 : F
/*   */     //   2008: dup
/*   */     //   2009: fstore #9
/*   */     //   2011: aload #8
/*   */     //   2013: fload_2
/*   */     //   2014: fload #9
/*   */     //   2016: fsub
/*   */     //   2017: dup
/*   */     //   2018: fstore_2
/*   */     //   2019: putfield F00 : F
/*   */     //   2022: fload_2
/*   */     //   2023: fadd
/*   */     //   2024: invokestatic max : (FF)F
/*   */     //   2027: fstore_2
/*   */     //   2028: iinc #4, 1
/*   */     //   2031: goto -> 1872
/*   */     //   2034: iload #7
/*   */     //   2036: aload_0
/*   */     //   2037: fload_2
/*   */     //   2038: putfield e20 : F
/*   */     //   2041: bipush #8
/*   */     //   2043: iand
/*   */     //   2044: ifne -> 2142
/*   */     //   2047: iload #7
/*   */     //   2049: iconst_1
/*   */     //   2050: iand
/*   */     //   2051: ifeq -> 2059
/*   */     //   2054: iconst_1
/*   */     //   2055: istore_1
/*   */     //   2056: goto -> 2061
/*   */     //   2059: iconst_0
/*   */     //   2060: istore_1
/*   */     //   2061: aload_0
/*   */     //   2062: getfield m0 : Lf/fQ;
/*   */     //   2065: dup
/*   */     //   2066: getfield Uq0 : [Ljava/lang/Object;
/*   */     //   2069: astore_0
/*   */     //   2070: iconst_0
/*   */     //   2071: istore_2
/*   */     //   2072: getfield Z8 : I
/*   */     //   2075: istore_3
/*   */     //   2076: iload_2
/*   */     //   2077: iload_3
/*   */     //   2078: if_icmpge -> 2142
/*   */     //   2081: iload_1
/*   */     //   2082: aload_0
/*   */     //   2083: iload_2
/*   */     //   2084: aaload
/*   */     //   2085: checkcast f/zj
/*   */     //   2088: dup
/*   */     //   2089: astore #4
/*   */     //   2091: getfield x0 : F
/*   */     //   2094: fstore #5
/*   */     //   2096: ifeq -> 2116
/*   */     //   2099: fload #6
/*   */     //   2101: aload #4
/*   */     //   2103: getfield F00 : F
/*   */     //   2106: fsub
/*   */     //   2107: ldc_w 0.5
/*   */     //   2110: fmul
/*   */     //   2111: fstore #7
/*   */     //   2113: goto -> 2126
/*   */     //   2116: fload #6
/*   */     //   2118: aload #4
/*   */     //   2120: getfield F00 : F
/*   */     //   2123: fsub
/*   */     //   2124: fstore #7
/*   */     //   2126: aload #4
/*   */     //   2128: fload #5
/*   */     //   2130: fload #7
/*   */     //   2132: fadd
/*   */     //   2133: putfield x0 : F
/*   */     //   2136: iinc #2, 1
/*   */     //   2139: goto -> 2076
/*   */     //   2142: iload #10
/*   */     //   2144: ifeq -> 2154
/*   */     //   2147: getstatic f/R3.Ax : Lf/o0;
/*   */     //   2150: iconst_0
/*   */     //   2151: putfield mG0 : I
/*   */     //   2154: return
/*   */     //   2155: aload #16
/*   */     //   2157: getfield Pb : Lf/fQ;
/*   */     //   2160: getfield Uq0 : [Ljava/lang/Object;
/*   */     //   2163: dup
/*   */     //   2164: astore #20
/*   */     //   2166: iload #22
/*   */     //   2168: aaload
/*   */     //   2169: checkcast f/Jk0
/*   */     //   2172: getfield xU : I
/*   */     //   2175: i2c
/*   */     //   2176: dup
/*   */     //   2177: istore #21
/*   */     //   2179: bipush #9
/*   */     //   2181: if_icmpeq -> 2209
/*   */     //   2184: iload #21
/*   */     //   2186: bipush #10
/*   */     //   2188: if_icmpeq -> 2209
/*   */     //   2191: iload #21
/*   */     //   2193: bipush #13
/*   */     //   2195: if_icmpeq -> 2209
/*   */     //   2198: iload #21
/*   */     //   2200: bipush #32
/*   */     //   2202: if_icmpeq -> 2209
/*   */     //   2205: iconst_0
/*   */     //   2206: goto -> 2210
/*   */     //   2209: iconst_1
/*   */     //   2210: ifeq -> 2220
/*   */     //   2213: iload #22
/*   */     //   2215: istore #20
/*   */     //   2217: goto -> 2296
/*   */     //   2220: iload #22
/*   */     //   2222: istore #21
/*   */     //   2224: iload #21
/*   */     //   2226: ifle -> 2293
/*   */     //   2229: aload #20
/*   */     //   2231: iload #21
/*   */     //   2233: aaload
/*   */     //   2234: checkcast f/Jk0
/*   */     //   2237: getfield xU : I
/*   */     //   2240: i2c
/*   */     //   2241: dup
/*   */     //   2242: istore #23
/*   */     //   2244: bipush #9
/*   */     //   2246: if_icmpeq -> 2274
/*   */     //   2249: iload #23
/*   */     //   2251: bipush #10
/*   */     //   2253: if_icmpeq -> 2274
/*   */     //   2256: iload #23
/*   */     //   2258: bipush #13
/*   */     //   2260: if_icmpeq -> 2274
/*   */     //   2263: iload #23
/*   */     //   2265: bipush #32
/*   */     //   2267: if_icmpeq -> 2274
/*   */     //   2270: iconst_0
/*   */     //   2271: goto -> 2275
/*   */     //   2274: iconst_1
/*   */     //   2275: ifne -> 2284
/*   */     //   2278: iinc #21, -1
/*   */     //   2281: goto -> 2224
/*   */     //   2284: iload #21
/*   */     //   2286: iconst_1
/*   */     //   2287: iadd
/*   */     //   2288: istore #20
/*   */     //   2290: goto -> 2296
/*   */     //   2293: iconst_0
/*   */     //   2294: istore #20
/*   */     //   2296: iload #20
/*   */     //   2298: ifne -> 2311
/*   */     //   2301: aload #16
/*   */     //   2303: getfield x0 : F
/*   */     //   2306: fconst_0
/*   */     //   2307: fcmpl
/*   */     //   2308: ifeq -> 2331
/*   */     //   2311: iload #20
/*   */     //   2313: aload #16
/*   */     //   2315: getfield Pb : Lf/fQ;
/*   */     //   2318: getfield Z8 : I
/*   */     //   2321: if_icmplt -> 2327
/*   */     //   2324: goto -> 2331
/*   */     //   2327: iload #20
/*   */     //   2329: istore #22
/*   */     //   2331: aload #16
/*   */     //   2333: dup
/*   */     //   2334: getfield Pb : Lf/fQ;
/*   */     //   2337: dup
/*   */     //   2338: astore #20
/*   */     //   2340: getfield Z8 : I
/*   */     //   2343: istore #21
/*   */     //   2345: getfield Qd0 : Lf/G3;
/*   */     //   2348: astore #23
/*   */     //   2350: iload #22
/*   */     //   2352: istore #24
/*   */     //   2354: iload #24
/*   */     //   2356: ifle -> 2421
/*   */     //   2359: aload #20
/*   */     //   2361: iload #24
/*   */     //   2363: iconst_1
/*   */     //   2364: isub
/*   */     //   2365: invokevirtual get : (I)Ljava/lang/Object;
/*   */     //   2368: checkcast f/Jk0
/*   */     //   2371: getfield xU : I
/*   */     //   2374: i2c
/*   */     //   2375: dup
/*   */     //   2376: istore #25
/*   */     //   2378: bipush #9
/*   */     //   2380: if_icmpeq -> 2408
/*   */     //   2383: iload #25
/*   */     //   2385: bipush #10
/*   */     //   2387: if_icmpeq -> 2408
/*   */     //   2390: iload #25
/*   */     //   2392: bipush #13
/*   */     //   2394: if_icmpeq -> 2408
/*   */     //   2397: iload #25
/*   */     //   2399: bipush #32
/*   */     //   2401: if_icmpeq -> 2408
/*   */     //   2404: iconst_0
/*   */     //   2405: goto -> 2409
/*   */     //   2408: iconst_1
/*   */     //   2409: ifne -> 2415
/*   */     //   2412: goto -> 2421
/*   */     //   2415: iinc #24, -1
/*   */     //   2418: goto -> 2354
/*   */     //   2421: iload #22
/*   */     //   2423: iload #21
/*   */     //   2425: if_icmpge -> 2488
/*   */     //   2428: aload #20
/*   */     //   2430: iload #22
/*   */     //   2432: invokevirtual get : (I)Ljava/lang/Object;
/*   */     //   2435: checkcast f/Jk0
/*   */     //   2438: getfield xU : I
/*   */     //   2441: i2c
/*   */     //   2442: dup
/*   */     //   2443: istore #25
/*   */     //   2445: bipush #9
/*   */     //   2447: if_icmpeq -> 2475
/*   */     //   2450: iload #25
/*   */     //   2452: bipush #10
/*   */     //   2454: if_icmpeq -> 2475
/*   */     //   2457: iload #25
/*   */     //   2459: bipush #13
/*   */     //   2461: if_icmpeq -> 2475
/*   */     //   2464: iload #25
/*   */     //   2466: bipush #32
/*   */     //   2468: if_icmpeq -> 2475
/*   */     //   2471: iconst_0
/*   */     //   2472: goto -> 2476
/*   */     //   2475: iconst_1
/*   */     //   2476: ifne -> 2482
/*   */     //   2479: goto -> 2488
/*   */     //   2482: iinc #22, 1
/*   */     //   2485: goto -> 2421
/*   */     //   2488: iload #22
/*   */     //   2490: aconst_null
/*   */     //   2491: astore #25
/*   */     //   2493: iload #21
/*   */     //   2495: if_icmpge -> 2985
/*   */     //   2498: getstatic f/R3.f70 : Lf/Lc;
/*   */     //   2501: invokevirtual obtain : ()Ljava/lang/Object;
/*   */     //   2504: checkcast f/zj
/*   */     //   2507: dup
/*   */     //   2508: dup
/*   */     //   2509: astore #25
/*   */     //   2511: aload #20
/*   */     //   2513: aload #16
/*   */     //   2515: aload #20
/*   */     //   2517: iload #22
/*   */     //   2519: aload #25
/*   */     //   2521: getfield Pb : Lf/fQ;
/*   */     //   2524: dup
/*   */     //   2525: astore #26
/*   */     //   2527: aload #20
/*   */     //   2529: iconst_0
/*   */     //   2530: iload #24
/*   */     //   2532: invokevirtual wV : (Lf/fQ;II)V
/*   */     //   2535: iconst_1
/*   */     //   2536: isub
/*   */     //   2537: dup
/*   */     //   2538: istore #27
/*   */     //   2540: invokevirtual il : (I)V
/*   */     //   2543: aload #26
/*   */     //   2545: putfield Pb : Lf/fQ;
/*   */     //   2548: putfield Pb : Lf/fQ;
/*   */     //   2551: getfield Qd0 : Lf/G3;
/*   */     //   2554: astore #26
/*   */     //   2556: iload #24
/*   */     //   2558: iconst_1
/*   */     //   2559: iadd
/*   */     //   2560: dup
/*   */     //   2561: istore #28
/*   */     //   2563: aload #26
/*   */     //   2565: iconst_0
/*   */     //   2566: istore #29
/*   */     //   2568: invokevirtual getClass : ()Ljava/lang/Class;
/*   */     //   2571: pop
/*   */     //   2572: iload #29
/*   */     //   2574: iadd
/*   */     //   2575: aload #23
/*   */     //   2577: getfield NB0 : I
/*   */     //   2580: if_icmpgt -> 2931
/*   */     //   2583: iload #22
/*   */     //   2585: aload #23
/*   */     //   2587: aload #26
/*   */     //   2589: aload #23
/*   */     //   2591: getfield By0 : [F
/*   */     //   2594: astore #30
/*   */     //   2596: iload #29
/*   */     //   2598: iload #28
/*   */     //   2600: aload #30
/*   */     //   2602: invokevirtual p : (II[F)V
/*   */     //   2605: iconst_1
/*   */     //   2606: istore #28
/*   */     //   2608: getfield NB0 : I
/*   */     //   2611: dup
/*   */     //   2612: istore #29
/*   */     //   2614: if_icmpge -> 2901
/*   */     //   2617: iload #28
/*   */     //   2619: iload #22
/*   */     //   2621: if_icmpgt -> 2880
/*   */     //   2624: aload #23
/*   */     //   2626: iload #29
/*   */     //   2628: iload #27
/*   */     //   2630: iconst_1
/*   */     //   2631: iadd
/*   */     //   2632: dup
/*   */     //   2633: istore #27
/*   */     //   2635: isub
/*   */     //   2636: istore #30
/*   */     //   2638: getfield bK0 : Z
/*   */     //   2641: ifeq -> 2676
/*   */     //   2644: aload #23
/*   */     //   2646: getfield By0 : [F
/*   */     //   2649: dup
/*   */     //   2650: iload #29
/*   */     //   2652: iload #27
/*   */     //   2654: iload #28
/*   */     //   2656: iadd
/*   */     //   2657: dup
/*   */     //   2658: istore #22
/*   */     //   2660: isub
/*   */     //   2661: istore #27
/*   */     //   2663: iload #22
/*   */     //   2665: swap
/*   */     //   2666: iload #28
/*   */     //   2668: iload #27
/*   */     //   2670: invokestatic arraycopy : (Ljava/lang/Object;ILjava/lang/Object;II)V
/*   */     //   2673: goto -> 2713
/*   */     //   2676: aload #23
/*   */     //   2678: iload #30
/*   */     //   2680: iload #22
/*   */     //   2682: iconst_1
/*   */     //   2683: iadd
/*   */     //   2684: invokestatic max : (II)I
/*   */     //   2687: istore #22
/*   */     //   2689: getfield By0 : [F
/*   */     //   2692: dup
/*   */     //   2693: astore #27
/*   */     //   2695: iload #22
/*   */     //   2697: iload #29
/*   */     //   2699: iload #22
/*   */     //   2701: isub
/*   */     //   2702: istore #22
/*   */     //   2704: aload #27
/*   */     //   2706: iload #28
/*   */     //   2708: iload #22
/*   */     //   2710: invokestatic arraycopy : (Ljava/lang/Object;ILjava/lang/Object;II)V
/*   */     //   2713: aload_1
/*   */     //   2714: aload_0
/*   */     //   2715: dup
/*   */     //   2716: iload #21
/*   */     //   2718: aload #16
/*   */     //   2720: aload #25
/*   */     //   2722: aload #23
/*   */     //   2724: aload #16
/*   */     //   2726: aload #26
/*   */     //   2728: aload #23
/*   */     //   2730: dup
/*   */     //   2731: iload #30
/*   */     //   2733: putfield NB0 : I
/*   */     //   2736: getfield By0 : [F
/*   */     //   2739: aload #20
/*   */     //   2741: invokevirtual first : ()Ljava/lang/Object;
/*   */     //   2744: checkcast f/Jk0
/*   */     //   2747: getfield eJ : I
/*   */     //   2750: ineg
/*   */     //   2751: i2f
/*   */     //   2752: aload_1
/*   */     //   2753: getfield gu0 : F
/*   */     //   2756: fmul
/*   */     //   2757: aload_1
/*   */     //   2758: getfield SC : F
/*   */     //   2761: fsub
/*   */     //   2762: iconst_0
/*   */     //   2763: swap
/*   */     //   2764: fastore
/*   */     //   2765: putfield Qd0 : Lf/G3;
/*   */     //   2768: putfield Qd0 : Lf/G3;
/*   */     //   2771: getfield Pb : Lf/fQ;
/*   */     //   2774: getfield Z8 : I
/*   */     //   2777: aload #25
/*   */     //   2779: getfield Pb : Lf/fQ;
/*   */     //   2782: getfield Z8 : I
/*   */     //   2785: istore #20
/*   */     //   2787: isub
/*   */     //   2788: iload #20
/*   */     //   2790: isub
/*   */     //   2791: istore #21
/*   */     //   2793: getfield w6 : I
/*   */     //   2796: iload #21
/*   */     //   2798: isub
/*   */     //   2799: dup
/*   */     //   2800: istore #22
/*   */     //   2802: putfield w6 : I
/*   */     //   2805: getfield Zp : Z
/*   */     //   2808: ifeq -> 3153
/*   */     //   2811: iload #21
/*   */     //   2813: ifle -> 3153
/*   */     //   2816: aload_0
/*   */     //   2817: iload #22
/*   */     //   2819: iload #20
/*   */     //   2821: isub
/*   */     //   2822: istore #20
/*   */     //   2824: getfield eN : Lf/o0;
/*   */     //   2827: getfield mG0 : I
/*   */     //   2830: iconst_2
/*   */     //   2831: isub
/*   */     //   2832: istore #22
/*   */     //   2834: iload #22
/*   */     //   2836: iconst_2
/*   */     //   2837: if_icmplt -> 3153
/*   */     //   2840: aload_0
/*   */     //   2841: getfield eN : Lf/o0;
/*   */     //   2844: iload #22
/*   */     //   2846: invokevirtual Vl : (I)I
/*   */     //   2849: dup
/*   */     //   2850: istore #23
/*   */     //   2852: iload #20
/*   */     //   2854: if_icmpgt -> 2860
/*   */     //   2857: goto -> 3153
/*   */     //   2860: aload_0
/*   */     //   2861: getfield eN : Lf/o0;
/*   */     //   2864: iload #22
/*   */     //   2866: iload #23
/*   */     //   2868: iload #21
/*   */     //   2870: isub
/*   */     //   2871: invokevirtual X60 : (II)V
/*   */     //   2874: iinc #22, -2
/*   */     //   2877: goto -> 2834
/*   */     //   2880: new java/lang/IndexOutOfBoundsException
/*   */     //   2883: dup
/*   */     //   2884: ldc_w 'start can't be > end: '
/*   */     //   2887: iload #28
/*   */     //   2889: ldc_w ' > '
/*   */     //   2892: iload #22
/*   */     //   2894: invokestatic KK : (Ljava/lang/String;ILjava/lang/String;I)Ljava/lang/String;
/*   */     //   2897: invokespecial <init> : (Ljava/lang/String;)V
/*   */     //   2900: athrow
/*   */     //   2901: new java/lang/IndexOutOfBoundsException
/*   */     //   2904: dup
/*   */     //   2905: ldc_w 'end can't be >= size: '
/*   */     //   2908: iload #22
/*   */     //   2910: ldc_w ' >= '
/*   */     //   2913: invokestatic DH0 : (Ljava/lang/String;ILjava/lang/String;)Ljava/lang/StringBuilder;
/*   */     //   2916: aload #23
/*   */     //   2918: getfield NB0 : I
/*   */     //   2921: invokevirtual append : (I)Ljava/lang/StringBuilder;
/*   */     //   2924: invokevirtual toString : ()Ljava/lang/String;
/*   */     //   2927: invokespecial <init> : (Ljava/lang/String;)V
/*   */     //   2930: athrow
/*   */     //   2931: new java/lang/IllegalArgumentException
/*   */     //   2934: dup
/*   */     //   2935: new java/lang/StringBuilder
/*   */     //   2938: dup
/*   */     //   2939: invokespecial <init> : ()V
/*   */     //   2942: ldc_w 'offset + length must be <= size: '
/*   */     //   2945: invokevirtual append : (Ljava/lang/String;)Ljava/lang/StringBuilder;
/*   */     //   2948: iload #29
/*   */     //   2950: invokevirtual append : (I)Ljava/lang/StringBuilder;
/*   */     //   2953: ldc_w ' + '
/*   */     //   2956: invokevirtual append : (Ljava/lang/String;)Ljava/lang/StringBuilder;
/*   */     //   2959: iload #28
/*   */     //   2961: invokevirtual append : (I)Ljava/lang/StringBuilder;
/*   */     //   2964: ldc_w ' <= '
/*   */     //   2967: invokevirtual append : (Ljava/lang/String;)Ljava/lang/StringBuilder;
/*   */     //   2970: aload #23
/*   */     //   2972: getfield NB0 : I
/*   */     //   2975: invokevirtual append : (I)Ljava/lang/StringBuilder;
/*   */     //   2978: invokevirtual toString : ()Ljava/lang/String;
/*   */     //   2981: invokespecial <init> : (Ljava/lang/String;)V
/*   */     //   2984: athrow
/*   */     //   2985: aload #23
/*   */     //   2987: aload #20
/*   */     //   2989: iload #24
/*   */     //   2991: invokevirtual pL0 : (I)V
/*   */     //   2994: iload #24
/*   */     //   2996: iconst_1
/*   */     //   2997: iadd
/*   */     //   2998: istore #20
/*   */     //   3000: getfield NB0 : I
/*   */     //   3003: iload #20
/*   */     //   3005: if_icmple -> 3015
/*   */     //   3008: aload #23
/*   */     //   3010: iload #20
/*   */     //   3012: putfield NB0 : I
/*   */     //   3015: iload #22
/*   */     //   3017: iload #24
/*   */     //   3019: isub
/*   */     //   3020: dup
/*   */     //   3021: istore #20
/*   */     //   3023: ifle -> 3153
/*   */     //   3026: aload_1
/*   */     //   3027: aload_0
/*   */     //   3028: dup
/*   */     //   3029: getfield w6 : I
/*   */     //   3032: iload #20
/*   */     //   3034: isub
/*   */     //   3035: putfield w6 : I
/*   */     //   3038: getfield Zp : Z
/*   */     //   3041: ifeq -> 3153
/*   */     //   3044: aload_0
/*   */     //   3045: getfield eN : Lf/o0;
/*   */     //   3048: dup
/*   */     //   3049: getfield mG0 : I
/*   */     //   3052: iconst_2
/*   */     //   3053: isub
/*   */     //   3054: invokevirtual Vl : (I)I
/*   */     //   3057: aload_0
/*   */     //   3058: getfield w6 : I
/*   */     //   3061: if_icmple -> 3153
/*   */     //   3064: aload_0
/*   */     //   3065: getfield eN : Lf/o0;
/*   */     //   3068: dup
/*   */     //   3069: astore #20
/*   */     //   3071: getfield Ky : [I
/*   */     //   3074: aload #20
/*   */     //   3076: getfield mG0 : I
/*   */     //   3079: iconst_1
/*   */     //   3080: isub
/*   */     //   3081: iaload
/*   */     //   3082: istore #20
/*   */     //   3084: aload_0
/*   */     //   3085: getfield eN : Lf/o0;
/*   */     //   3088: dup
/*   */     //   3089: getfield mG0 : I
/*   */     //   3092: iconst_2
/*   */     //   3093: isub
/*   */     //   3094: invokevirtual Vl : (I)I
/*   */     //   3097: aload_0
/*   */     //   3098: getfield w6 : I
/*   */     //   3101: dup
/*   */     //   3102: istore #21
/*   */     //   3104: if_icmple -> 3123
/*   */     //   3107: aload_0
/*   */     //   3108: getfield eN : Lf/o0;
/*   */     //   3111: dup
/*   */     //   3112: getfield mG0 : I
/*   */     //   3115: iconst_2
/*   */     //   3116: isub
/*   */     //   3117: putfield mG0 : I
/*   */     //   3120: goto -> 3084
/*   */     //   3123: aload_0
/*   */     //   3124: dup
/*   */     //   3125: getfield eN : Lf/o0;
/*   */     //   3128: dup
/*   */     //   3129: getfield mG0 : I
/*   */     //   3132: iconst_2
/*   */     //   3133: isub
/*   */     //   3134: iload #21
/*   */     //   3136: invokevirtual X60 : (II)V
/*   */     //   3139: getfield eN : Lf/o0;
/*   */     //   3142: dup
/*   */     //   3143: getfield mG0 : I
/*   */     //   3146: iconst_1
/*   */     //   3147: isub
/*   */     //   3148: iload #20
/*   */     //   3150: invokevirtual X60 : (II)V
/*   */     //   3153: aload #25
/*   */     //   3155: astore #20
/*   */     //   3157: iload #24
/*   */     //   3159: ifne -> 3181
/*   */     //   3162: aload_0
/*   */     //   3163: getstatic f/R3.f70 : Lf/Lc;
/*   */     //   3166: aload #16
/*   */     //   3168: invokevirtual free : (Ljava/lang/Object;)V
/*   */     //   3171: getfield m0 : Lf/fQ;
/*   */     //   3174: invokevirtual pop : ()Ljava/lang/Object;
/*   */     //   3177: pop
/*   */     //   3178: goto -> 3239
/*   */     //   3181: aload #16
/*   */     //   3183: dup
/*   */     //   3184: getfield Pb : Lf/fQ;
/*   */     //   3187: invokevirtual peek : ()Ljava/lang/Object;
/*   */     //   3190: checkcast f/Jk0
/*   */     //   3193: dup
/*   */     //   3194: astore #16
/*   */     //   3196: invokevirtual getClass : ()Ljava/lang/Class;
/*   */     //   3199: pop
/*   */     //   3200: getfield Qd0 : Lf/G3;
/*   */     //   3203: dup
/*   */     //   3204: astore #21
/*   */     //   3206: getfield By0 : [F
/*   */     //   3209: aload #21
/*   */     //   3211: getfield NB0 : I
/*   */     //   3214: iconst_1
/*   */     //   3215: isub
/*   */     //   3216: aload #16
/*   */     //   3218: getfield zq : I
/*   */     //   3221: aload #16
/*   */     //   3223: getfield eJ : I
/*   */     //   3226: iadd
/*   */     //   3227: i2f
/*   */     //   3228: aload_1
/*   */     //   3229: getfield gu0 : F
/*   */     //   3232: fmul
/*   */     //   3233: aload_1
/*   */     //   3234: getfield of : F
/*   */     //   3237: fsub
/*   */     //   3238: fastore
/*   */     //   3239: aload #20
/*   */     //   3241: ifnonnull -> 3251
/*   */     //   3244: aload #20
/*   */     //   3246: astore #16
/*   */     //   3248: goto -> 3350
/*   */     //   3251: aload #20
/*   */     //   3253: dup
/*   */     //   3254: dup
/*   */     //   3255: fload #15
/*   */     //   3257: fload #13
/*   */     //   3259: aload_0
/*   */     //   3260: getfield m0 : Lf/fQ;
/*   */     //   3263: aload #20
/*   */     //   3265: invokevirtual Com3 : (Ljava/lang/Object;)V
/*   */     //   3268: fadd
/*   */     //   3269: fstore #15
/*   */     //   3271: fconst_0
/*   */     //   3272: putfield x0 : F
/*   */     //   3275: fload #15
/*   */     //   3277: putfield FI : F
/*   */     //   3280: getfield Qd0 : Lf/G3;
/*   */     //   3283: dup
/*   */     //   3284: astore #16
/*   */     //   3286: getfield NB0 : I
/*   */     //   3289: ifeq -> 3328
/*   */     //   3292: aload #16
/*   */     //   3294: dup
/*   */     //   3295: getfield By0 : [F
/*   */     //   3298: iconst_0
/*   */     //   3299: faload
/*   */     //   3300: fstore #16
/*   */     //   3302: iconst_1
/*   */     //   3303: invokevirtual cON : (I)F
/*   */     //   3306: fload #16
/*   */     //   3308: fadd
/*   */     //   3309: fstore #16
/*   */     //   3311: iconst_1
/*   */     //   3312: istore #21
/*   */     //   3314: aload #20
/*   */     //   3316: fload #16
/*   */     //   3318: fstore #20
/*   */     //   3320: astore #16
/*   */     //   3322: iinc #21, 1
/*   */     //   3325: goto -> 1174
/*   */     //   3328: new java/lang/IllegalStateException
/*   */     //   3331: dup
/*   */     //   3332: ldc_w 'Array is empty.'
/*   */     //   3335: invokespecial <init> : (Ljava/lang/String;)V
/*   */     //   3338: athrow
/*   */     //   3339: new java/lang/IllegalStateException
/*   */     //   3342: dup
/*   */     //   3343: ldc_w 'Array is empty.'
/*   */     //   3346: invokespecial <init> : (Ljava/lang/String;)V
/*   */     //   3349: athrow
/*   */     //   3350: iload #19
/*   */     //   3352: ifeq -> 3411
/*   */     //   3355: iload_3
/*   */     //   3356: aconst_null
/*   */     //   3357: astore_3
/*   */     //   3358: aconst_null
/*   */     //   3359: astore #16
/*   */     //   3361: iload #5
/*   */     //   3363: if_icmpne -> 3391
/*   */     //   3366: fload #13
/*   */     //   3368: aload_1
/*   */     //   3369: getfield nu : F
/*   */     //   3372: fmul
/*   */     //   3373: fload #15
/*   */     //   3375: fadd
/*   */     //   3376: fstore #5
/*   */     //   3378: aload_3
/*   */     //   3379: aload #16
/*   */     //   3381: fload #5
/*   */     //   3383: fstore_3
/*   */     //   3384: astore #15
/*   */     //   3386: astore #5
/*   */     //   3388: goto -> 3422
/*   */     //   3391: fload #15
/*   */     //   3393: fload #13
/*   */     //   3395: fadd
/*   */     //   3396: fstore #5
/*   */     //   3398: aload_3
/*   */     //   3399: aload #16
/*   */     //   3401: fload #5
/*   */     //   3403: fstore_3
/*   */     //   3404: astore #15
/*   */     //   3406: astore #5
/*   */     //   3408: goto -> 3422
/*   */     //   3411: aload #16
/*   */     //   3413: aload #17
/*   */     //   3415: fload #15
/*   */     //   3417: fstore_3
/*   */     //   3418: astore #15
/*   */     //   3420: astore #5
/*   */     //   3422: iload #11
/*   */     //   3424: iload #11
/*   */     //   3426: iload #14
/*   */     //   3428: iload #18
/*   */     //   3430: fload_3
/*   */     //   3431: aload #5
/*   */     //   3433: aload #15
/*   */     //   3435: astore #17
/*   */     //   3437: astore #16
/*   */     //   3439: fstore #15
/*   */     //   3441: istore #14
/*   */     //   3443: istore #11
/*   */     //   3445: istore #5
/*   */     //   3447: istore_3
/*   */     //   3448: goto -> 215
/*   */     // Line number table:
/*   */     //   Java source line number -> byte code offset
/*   */     //   #1	-> 83
/*   */     //   #2	-> 88
/*   */     //   #3	-> 153
/*   */     //   #4	-> 304
/*   */     //   #5	-> 371
/*   */     //   #6	-> 393
/*   */     //   #7	-> 425
/*   */     //   #8	-> 470
/*   */     //   #9	-> 665
/*   */     //   #10	-> 671
/*   */     //   #11	-> 676
/*   */     //   #12	-> 754
/*   */     //   #13	-> 924
/*   */     //   #14	-> 939
/*   */     //   #15	-> 957
/*   */     //   #16	-> 963
/*   */     //   #17	-> 986
/*   */     //   #18	-> 999
/*   */     //   #19	-> 1016
/*   */     //   #20	-> 1051
/*   */     //   #21	-> 1085
/*   */     //   #22	-> 1105
/*   */     //   #23	-> 1116
/*   */     //   #24	-> 1146
/*   */     //   #25	-> 1155
/*   */     //   #26	-> 1163
/*   */     //   #27	-> 1208
/*   */     //   #28	-> 1245
/*   */     //   #29	-> 1270
/*   */     //   #30	-> 1317
/*   */     //   #31	-> 1357
/*   */     //   #32	-> 1377
/*   */     //   #33	-> 1394
/*   */     //   #34	-> 1494
/*   */     //   #35	-> 1506
/*   */     //   #36	-> 1513
/*   */     //   #37	-> 1547
/*   */     //   #38	-> 1567
/*   */     //   #39	-> 1568
/*   */     //   #40	-> 1604
/*   */     //   #41	-> 1688
/*   */     //   #42	-> 1701
/*   */     //   #43	-> 1704
/*   */     //   #44	-> 1708
/*   */     //   #45	-> 1726
/*   */     //   #46	-> 1842
/*   */     //   #47	-> 1856
/*   */     //   #48	-> 1952
/*   */     //   #49	-> 1975
/*   */     //   #50	-> 2062
/*   */     //   #51	-> 2147
/*   */     //   #52	-> 2151
/*   */     //   #53	-> 2157
/*   */     //   #54	-> 2160
/*   */     //   #55	-> 2303
/*   */     //   #56	-> 2334
/*   */     //   #57	-> 2577
/*   */     //   #58	-> 2608
/*   */     //   #59	-> 2736
/*   */     //   #60	-> 2741
/*   */     //   #61	-> 2764
/*   */     //   #62	-> 2880
/*   */     //   #63	-> 2884
/*   */     //   #64	-> 2897
/*   */     //   #65	-> 2905
/*   */     //   #66	-> 2918
/*   */     //   #67	-> 2931
/*   */     //   #68	-> 2991
/*   */     //   #69	-> 3000
/*   */     //   #70	-> 3012
/*   */     //   #71	-> 3029
/*   */     //   #72	-> 3071
/*   */     //   #73	-> 3076
/*   */     //   #74	-> 3085
/*   */     //   #75	-> 3184
/*   */     //   #76	-> 3218
/*   */     //   #77	-> 3238
/*   */     //   #78	-> 3260
/*   */     //   #79	-> 3286
/*   */     //   #80	-> 3295
/*   */     //   #81	-> 3303
/*   */     //   #82	-> 3328
/*   */     //   #83	-> 3369
/*   */   }
/*   */   
/*   */   public final void reset() {
/*   */     f70.freeAll(this.m0);
/*   */     this.m0.clear();
/*   */     this.eN.mG0 = 0;
/*   */     this.w6 = 0;
/*   */     this.e20 = 0.0F;
/*   */     this.Df0 = 0.0F;
/*   */   }
/*   */   
/*   */   public final String toString() {
/*   */     if (this.m0.Z8 == 0)
/*   */       return ""; 
/*   */     this(128);
/*   */     stringBuilder.append(this.e20);
/*   */     stringBuilder.append('x');
/*   */     StringBuilder stringBuilder;
/*   */     (stringBuilder = new StringBuilder()).append(this.Df0);
/*   */     (new StringBuilder()).append('\n');
/*   */     byte b = 0;
/*   */     int i = this.m0.Z8;
/*   */     while (b < i) {
/*   */       stringBuilder.append(((zj)this.m0.get(b)).toString());
/*   */       stringBuilder.append('\n');
/*   */       b++;
/*   */     } 
/*   */     stringBuilder.setLength(stringBuilder.length() - 1);
/*   */     return stringBuilder.toString();
/*   */   } }


/* Location:              /Users/vnnsnnt/Documents/Codespace/JavaWorkspace/RedTrainer/src/main/java/org/trainer/client/PokeMMO.jar!/f/R3.class
 * Java compiler version: 7 (51.0)
 * JD-Core Version:       1.1.3
 */