/*    */ package f;public final class R8 extends ro { public js YG0; public R8(P10 paramP10, int paramInt, byte[] paramArrayOfbyte) { super(paramP10, paramInt, paramArrayOfbyte); } private void Ll0(qa0 paramqa0) { // Byte code:
/*    */     //   0: aload_0
/*    */     //   1: getfield YG0 : Lf/js;
/*    */     //   4: getfield MH0 : Lf/pA;
/*    */     //   7: getfield aV : Lf/ep;
/*    */     //   10: dup
/*    */     //   11: astore_0
/*    */     //   12: invokevirtual getClass : ()Ljava/lang/Class;
/*    */     //   15: pop
/*    */     //   16: new f/rS
/*    */     //   19: dup
/*    */     //   20: dup
/*    */     //   21: astore_2
/*    */     //   22: aconst_null
/*    */     //   23: invokespecial <init> : (Lf/JG0;)V
/*    */     //   26: ldc 'stats'
/*    */     //   28: invokevirtual Xu : (Ljava/lang/String;)V
/*    */     //   31: new f/Ip
/*    */     //   34: dup
/*    */     //   35: dup2
/*    */     //   36: dup2
/*    */     //   37: astore_3
/*    */     //   38: invokespecial <init> : ()V
/*    */     //   41: iconst_1
/*    */     //   42: anewarray f/JG0
/*    */     //   45: dup
/*    */     //   46: iconst_0
/*    */     //   47: aload_2
/*    */     //   48: aastore
/*    */     //   49: invokevirtual AUX : ([Lf/JG0;)Lf/U90;
/*    */     //   52: invokevirtual rK0 : (Lf/U90;)V
/*    */     //   55: iconst_1
/*    */     //   56: anewarray f/JG0
/*    */     //   59: dup
/*    */     //   60: iconst_0
/*    */     //   61: aload_2
/*    */     //   62: aastore
/*    */     //   63: invokevirtual vo0 : ([Lf/JG0;)Lf/U90;
/*    */     //   66: invokevirtual WN : (Lf/U90;)V
/*    */     //   69: new f/Ip
/*    */     //   72: dup
/*    */     //   73: dup2
/*    */     //   74: astore #4
/*    */     //   76: invokespecial <init> : ()V
/*    */     //   79: new f/g0
/*    */     //   82: dup
/*    */     //   83: aload #4
/*    */     //   85: invokespecial <init> : (Lf/Ip;)V
/*    */     //   88: invokevirtual rK0 : (Lf/U90;)V
/*    */     //   91: new f/cr0
/*    */     //   94: dup
/*    */     //   95: aload #4
/*    */     //   97: invokespecial <init> : (Lf/Ip;)V
/*    */     //   100: invokevirtual WN : (Lf/U90;)V
/*    */     //   103: sipush #9159
/*    */     //   106: invokestatic OH0 : (I)Ljava/lang/String;
/*    */     //   109: aload_1
/*    */     //   110: invokevirtual P8 : ()Ljava/lang/String;
/*    */     //   113: aload #4
/*    */     //   115: invokestatic GA0 : (Ljava/lang/String;Ljava/lang/String;Lf/Ip;)V
/*    */     //   118: iconst_1
/*    */     //   119: invokestatic D70 : (I)Z
/*    */     //   122: ifeq -> 159
/*    */     //   125: sipush #9160
/*    */     //   128: invokestatic OH0 : (I)Ljava/lang/String;
/*    */     //   131: new java/lang/StringBuilder
/*    */     //   134: dup
/*    */     //   135: aload_1
/*    */     //   136: swap
/*    */     //   137: invokespecial <init> : ()V
/*    */     //   140: getfield Mg0 : I
/*    */     //   143: invokevirtual append : (I)Ljava/lang/StringBuilder;
/*    */     //   146: ldc ''
/*    */     //   148: invokevirtual append : (Ljava/lang/String;)Ljava/lang/StringBuilder;
/*    */     //   151: invokevirtual toString : ()Ljava/lang/String;
/*    */     //   154: aload #4
/*    */     //   156: invokestatic GA0 : (Ljava/lang/String;Ljava/lang/String;Lf/Ip;)V
/*    */     //   159: aload_1
/*    */     //   160: sipush #9161
/*    */     //   163: invokestatic OH0 : (I)Ljava/lang/String;
/*    */     //   166: aload_1
/*    */     //   167: getfield U0 : B
/*    */     //   170: sipush #9225
/*    */     //   173: iadd
/*    */     //   174: invokestatic OH0 : (I)Ljava/lang/String;
/*    */     //   177: aload #4
/*    */     //   179: invokestatic GA0 : (Ljava/lang/String;Ljava/lang/String;Lf/Ip;)V
/*    */     //   182: sipush #9162
/*    */     //   185: invokestatic OH0 : (I)Ljava/lang/String;
/*    */     //   188: aload_1
/*    */     //   189: getfield KX : S
/*    */     //   192: invokestatic toString : (I)Ljava/lang/String;
/*    */     //   195: sipush #9174
/*    */     //   198: swap
/*    */     //   199: invokestatic Go : (ILjava/lang/String;)Ljava/lang/String;
/*    */     //   202: aload #4
/*    */     //   204: invokestatic GA0 : (Ljava/lang/String;Ljava/lang/String;Lf/Ip;)V
/*    */     //   207: sipush #9163
/*    */     //   210: invokestatic OH0 : (I)Ljava/lang/String;
/*    */     //   213: astore #5
/*    */     //   215: new java/lang/StringBuilder
/*    */     //   218: dup
/*    */     //   219: astore #6
/*    */     //   221: invokespecial <init> : ()V
/*    */     //   224: getfield Lm : [Lf/DO;
/*    */     //   227: dup
/*    */     //   228: astore #7
/*    */     //   230: arraylength
/*    */     //   231: istore #8
/*    */     //   233: iconst_0
/*    */     //   234: istore #9
/*    */     //   236: iload #9
/*    */     //   238: iload #8
/*    */     //   240: if_icmpge -> 286
/*    */     //   243: aload #6
/*    */     //   245: aload #7
/*    */     //   247: iload #9
/*    */     //   249: aaload
/*    */     //   250: astore #10
/*    */     //   252: invokevirtual length : ()I
/*    */     //   255: ifle -> 266
/*    */     //   258: aload #6
/*    */     //   260: ldc ', '
/*    */     //   262: invokevirtual append : (Ljava/lang/String;)Ljava/lang/StringBuilder;
/*    */     //   265: pop
/*    */     //   266: aload #6
/*    */     //   268: aload #10
/*    */     //   270: getfield mt0 : I
/*    */     //   273: invokestatic OH0 : (I)Ljava/lang/String;
/*    */     //   276: invokevirtual append : (Ljava/lang/String;)Ljava/lang/StringBuilder;
/*    */     //   279: pop
/*    */     //   280: iinc #9, 1
/*    */     //   283: goto -> 236
/*    */     //   286: aload #6
/*    */     //   288: invokevirtual length : ()I
/*    */     //   291: ifne -> 302
/*    */     //   294: aload #6
/*    */     //   296: ldc '???'
/*    */     //   298: invokevirtual append : (Ljava/lang/String;)Ljava/lang/StringBuilder;
/*    */     //   301: pop
/*    */     //   302: aload_1
/*    */     //   303: dup
/*    */     //   304: aload #5
/*    */     //   306: aload #6
/*    */     //   308: invokevirtual toString : ()Ljava/lang/String;
/*    */     //   311: aload #4
/*    */     //   313: invokestatic GA0 : (Ljava/lang/String;Ljava/lang/String;Lf/Ip;)V
/*    */     //   316: sipush #9172
/*    */     //   319: invokestatic OH0 : (I)Ljava/lang/String;
/*    */     //   322: aload_1
/*    */     //   323: getfield fH0 : Lf/ky;
/*    */     //   326: getfield Pa0 : I
/*    */     //   329: invokestatic OH0 : (I)Ljava/lang/String;
/*    */     //   332: aload #4
/*    */     //   334: invokestatic GA0 : (Ljava/lang/String;Ljava/lang/String;Lf/Ip;)V
/*    */     //   337: sipush #9164
/*    */     //   340: invokestatic OH0 : (I)Ljava/lang/String;
/*    */     //   343: getstatic f/ep.zC0 : Ljava/text/SimpleDateFormat;
/*    */     //   346: aload_1
/*    */     //   347: getfield Gr : J
/*    */     //   350: invokestatic valueOf : (J)Ljava/lang/Long;
/*    */     //   353: invokevirtual format : (Ljava/lang/Object;)Ljava/lang/String;
/*    */     //   356: aload #4
/*    */     //   358: invokestatic GA0 : (Ljava/lang/String;Ljava/lang/String;Lf/Ip;)V
/*    */     //   361: sipush #9165
/*    */     //   364: invokestatic OH0 : (I)Ljava/lang/String;
/*    */     //   367: aload_1
/*    */     //   368: getfield yw : B
/*    */     //   371: sipush #9200
/*    */     //   374: iadd
/*    */     //   375: invokestatic OH0 : (I)Ljava/lang/String;
/*    */     //   378: aload #4
/*    */     //   380: invokestatic GA0 : (Ljava/lang/String;Ljava/lang/String;Lf/Ip;)V
/*    */     //   383: sipush #9166
/*    */     //   386: invokestatic OH0 : (I)Ljava/lang/String;
/*    */     //   389: aload_1
/*    */     //   390: invokevirtual MU : ()Ljava/lang/String;
/*    */     //   393: aload #4
/*    */     //   395: invokestatic GA0 : (Ljava/lang/String;Ljava/lang/String;Lf/Ip;)V
/*    */     //   398: new java/lang/StringBuilder
/*    */     //   401: dup
/*    */     //   402: astore #5
/*    */     //   404: invokespecial <init> : ()V
/*    */     //   407: getfield Lm : [Lf/DO;
/*    */     //   410: invokestatic Qd : ([Lf/DO;)Lf/DO;
/*    */     //   413: astore #6
/*    */     //   415: getfield b20 : B
/*    */     //   418: dup
/*    */     //   419: istore #7
/*    */     //   421: iconst_1
/*    */     //   422: if_icmpne -> 429
/*    */     //   425: iconst_1
/*    */     //   426: goto -> 433
/*    */     //   429: aload_1
/*    */     //   430: getfield pR : Z
/*    */     //   433: ifeq -> 536
/*    */     //   436: aload #6
/*    */     //   438: ifnull -> 536
/*    */     //   441: iload #7
/*    */     //   443: sipush #9181
/*    */     //   446: istore #7
/*    */     //   448: iconst_2
/*    */     //   449: anewarray java/lang/String
/*    */     //   452: astore #8
/*    */     //   454: iconst_1
/*    */     //   455: if_icmpne -> 465
/*    */     //   458: aload_1
/*    */     //   459: getfield KX : S
/*    */     //   462: goto -> 472
/*    */     //   465: aload_1
/*    */     //   466: getfield KX : S
/*    */     //   469: iconst_4
/*    */     //   470: idiv
/*    */     //   471: i2s
/*    */     //   472: invokestatic toString : (I)Ljava/lang/String;
/*    */     //   475: astore #9
/*    */     //   477: aload_1
/*    */     //   478: aload #8
/*    */     //   480: iconst_0
/*    */     //   481: aload #9
/*    */     //   483: aastore
/*    */     //   484: iconst_1
/*    */     //   485: istore #9
/*    */     //   487: getfield fH0 : Lf/ky;
/*    */     //   490: getstatic f/ky.ag0 : Lf/ky;
/*    */     //   493: if_acmpne -> 507
/*    */     //   496: sipush #5756
/*    */     //   499: invokestatic OH0 : (I)Ljava/lang/String;
/*    */     //   502: astore #6
/*    */     //   504: goto -> 517
/*    */     //   507: aload #6
/*    */     //   509: getfield mt0 : I
/*    */     //   512: invokestatic OH0 : (I)Ljava/lang/String;
/*    */     //   515: astore #6
/*    */     //   517: aload #5
/*    */     //   519: iload #7
/*    */     //   521: aload #8
/*    */     //   523: dup
/*    */     //   524: iload #9
/*    */     //   526: aload #6
/*    */     //   528: aastore
/*    */     //   529: invokestatic sB : (I[Ljava/lang/String;)Ljava/lang/String;
/*    */     //   532: invokevirtual append : (Ljava/lang/String;)Ljava/lang/StringBuilder;
/*    */     //   535: pop
/*    */     //   536: aload_1
/*    */     //   537: getfield Q40 : Z
/*    */     //   540: ifeq -> 571
/*    */     //   543: aload #5
/*    */     //   545: invokevirtual length : ()I
/*    */     //   548: ifle -> 559
/*    */     //   551: aload #5
/*    */     //   553: ldc '\\n'
/*    */     //   555: invokevirtual append : (Ljava/lang/String;)Ljava/lang/StringBuilder;
/*    */     //   558: pop
/*    */     //   559: aload #5
/*    */     //   561: sipush #9182
/*    */     //   564: invokestatic OH0 : (I)Ljava/lang/String;
/*    */     //   567: invokevirtual append : (Ljava/lang/String;)Ljava/lang/StringBuilder;
/*    */     //   570: pop
/*    */     //   571: aload #5
/*    */     //   573: invokevirtual length : ()I
/*    */     //   576: ifle -> 595
/*    */     //   579: sipush #9180
/*    */     //   582: invokestatic OH0 : (I)Ljava/lang/String;
/*    */     //   585: aload #5
/*    */     //   587: invokevirtual toString : ()Ljava/lang/String;
/*    */     //   590: aload #4
/*    */     //   592: invokestatic GA0 : (Ljava/lang/String;Ljava/lang/String;Lf/Ip;)V
/*    */     //   595: aload_1
/*    */     //   596: getfield Xe : [Lf/oU;
/*    */     //   599: dup
/*    */     //   600: astore #5
/*    */     //   602: arraylength
/*    */     //   603: ifne -> 625
/*    */     //   606: sipush #9167
/*    */     //   609: invokestatic OH0 : (I)Ljava/lang/String;
/*    */     //   612: bipush #83
/*    */     //   614: invokestatic OH0 : (I)Ljava/lang/String;
/*    */     //   617: aload #4
/*    */     //   619: invokestatic GA0 : (Ljava/lang/String;Ljava/lang/String;Lf/Ip;)V
/*    */     //   622: goto -> 958
/*    */     //   625: aload #5
/*    */     //   627: iconst_0
/*    */     //   628: istore #6
/*    */     //   630: arraylength
/*    */     //   631: istore #7
/*    */     //   633: iconst_0
/*    */     //   634: istore #8
/*    */     //   636: iload #8
/*    */     //   638: iload #7
/*    */     //   640: if_icmpge -> 958
/*    */     //   643: aload #5
/*    */     //   645: iload #8
/*    */     //   647: aaload
/*    */     //   648: dup
/*    */     //   649: astore #9
/*    */     //   651: ifnonnull -> 657
/*    */     //   654: goto -> 952
/*    */     //   657: aload #9
/*    */     //   659: new f/dQ
/*    */     //   662: dup
/*    */     //   663: astore #10
/*    */     //   665: iload #6
/*    */     //   667: aload #10
/*    */     //   669: dup
/*    */     //   670: dup
/*    */     //   671: sipush #9167
/*    */     //   674: invokestatic OH0 : (I)Ljava/lang/String;
/*    */     //   677: astore #6
/*    */     //   679: invokespecial <init> : ()V
/*    */     //   682: aload #6
/*    */     //   684: invokevirtual E1 : (Ljava/lang/String;)V
/*    */     //   687: ldc_w 'label-title'
/*    */     //   690: invokevirtual Xu : (Ljava/lang/String;)V
/*    */     //   693: iconst_1
/*    */     //   694: ixor
/*    */     //   695: invokevirtual wI0 : (Z)V
/*    */     //   698: iconst_1
/*    */     //   699: istore #6
/*    */     //   701: new f/dQ
/*    */     //   704: astore #11
/*    */     //   706: getfield A60 : B
/*    */     //   709: dup
/*    */     //   710: istore #12
/*    */     //   712: ifeq -> 739
/*    */     //   715: iload #12
/*    */     //   717: iconst_1
/*    */     //   718: if_icmpeq -> 728
/*    */     //   721: ldc '???'
/*    */     //   723: astore #12
/*    */     //   725: goto -> 747
/*    */     //   728: sipush #5596
/*    */     //   731: invokestatic OH0 : (I)Ljava/lang/String;
/*    */     //   734: astore #12
/*    */     //   736: goto -> 747
/*    */     //   739: sipush #5595
/*    */     //   742: invokestatic OH0 : (I)Ljava/lang/String;
/*    */     //   745: astore #12
/*    */     //   747: aload #11
/*    */     //   749: dup
/*    */     //   750: aload #12
/*    */     //   752: aload #11
/*    */     //   754: invokespecial <init> : ()V
/*    */     //   757: invokevirtual E1 : (Ljava/lang/String;)V
/*    */     //   760: ldc_w 'label-name-value'
/*    */     //   763: invokevirtual Xu : (Ljava/lang/String;)V
/*    */     //   766: invokestatic XU : ()Z
/*    */     //   769: ifeq -> 812
/*    */     //   772: new f/VP
/*    */     //   775: dup
/*    */     //   776: dup2
/*    */     //   777: astore #12
/*    */     //   779: aload #9
/*    */     //   781: getfield Vm0 : Lf/FV;
/*    */     //   784: astore #13
/*    */     //   786: bipush #48
/*    */     //   788: bipush #48
/*    */     //   790: aload #13
/*    */     //   792: invokespecial <init> : (IILf/FV;)V
/*    */     //   795: getfield X70 : Lf/Dn0;
/*    */     //   798: iconst_2
/*    */     //   799: putfield Dd : I
/*    */     //   802: bipush #-34
/*    */     //   804: bipush #-31
/*    */     //   806: invokevirtual nx : (II)V
/*    */     //   809: goto -> 834
/*    */     //   812: new f/VP
/*    */     //   815: dup
/*    */     //   816: astore #12
/*    */     //   818: aload #9
/*    */     //   820: getfield Vm0 : Lf/FV;
/*    */     //   823: astore #13
/*    */     //   825: bipush #24
/*    */     //   827: bipush #24
/*    */     //   829: aload #13
/*    */     //   831: invokespecial <init> : (IILf/FV;)V
/*    */     //   834: aload #4
/*    */     //   836: dup
/*    */     //   837: new f/dQ
/*    */     //   840: dup
/*    */     //   841: dup2
/*    */     //   842: astore #13
/*    */     //   844: aload #9
/*    */     //   846: getfield Vm0 : Lf/FV;
/*    */     //   849: getfield Pb : Ljava/lang/String;
/*    */     //   852: astore #9
/*    */     //   854: invokespecial <init> : ()V
/*    */     //   857: aload #9
/*    */     //   859: invokevirtual E1 : (Ljava/lang/String;)V
/*    */     //   862: ldc_w 'label-name-icon-value'
/*    */     //   865: invokevirtual Xu : (Ljava/lang/String;)V
/*    */     //   868: getfield Xz0 : Lf/U90;
/*    */     //   871: new f/cr0
/*    */     //   874: dup
/*    */     //   875: aload #4
/*    */     //   877: invokespecial <init> : (Lf/Ip;)V
/*    */     //   880: iconst_4
/*    */     //   881: anewarray f/JG0
/*    */     //   884: dup
/*    */     //   885: dup
/*    */     //   886: dup2
/*    */     //   887: iconst_0
/*    */     //   888: aload #10
/*    */     //   890: aastore
/*    */     //   891: iconst_1
/*    */     //   892: aload #12
/*    */     //   894: aastore
/*    */     //   895: iconst_2
/*    */     //   896: aload #13
/*    */     //   898: aastore
/*    */     //   899: iconst_3
/*    */     //   900: aload #11
/*    */     //   902: aastore
/*    */     //   903: invokevirtual Mg : ([Lf/JG0;)Lf/U90;
/*    */     //   906: invokevirtual ee0 : (Lf/U90;)Lf/U90;
/*    */     //   909: pop
/*    */     //   910: getfield o30 : Lf/U90;
/*    */     //   913: new f/g0
/*    */     //   916: dup
/*    */     //   917: aload #4
/*    */     //   919: invokespecial <init> : (Lf/Ip;)V
/*    */     //   922: iconst_4
/*    */     //   923: anewarray f/JG0
/*    */     //   926: dup
/*    */     //   927: dup
/*    */     //   928: dup2
/*    */     //   929: iconst_0
/*    */     //   930: aload #10
/*    */     //   932: aastore
/*    */     //   933: iconst_1
/*    */     //   934: aload #12
/*    */     //   936: aastore
/*    */     //   937: iconst_2
/*    */     //   938: aload #13
/*    */     //   940: aastore
/*    */     //   941: iconst_3
/*    */     //   942: aload #11
/*    */     //   944: aastore
/*    */     //   945: invokevirtual Mg : ([Lf/JG0;)Lf/U90;
/*    */     //   948: invokevirtual ee0 : (Lf/U90;)Lf/U90;
/*    */     //   951: pop
/*    */     //   952: iinc #8, 1
/*    */     //   955: goto -> 636
/*    */     //   958: aload_1
/*    */     //   959: getfield Br0 : Ljava/util/HashMap;
/*    */     //   962: invokevirtual values : ()Ljava/util/Collection;
/*    */     //   965: invokeinterface size : ()I
/*    */     //   970: ifne -> 990
/*    */     //   973: sipush #9168
/*    */     //   976: invokestatic OH0 : (I)Ljava/lang/String;
/*    */     //   979: ldc_w '--'
/*    */     //   982: aload #4
/*    */     //   984: invokestatic GA0 : (Ljava/lang/String;Ljava/lang/String;Lf/Ip;)V
/*    */     //   987: goto -> 1372
/*    */     //   990: iconst_0
/*    */     //   991: istore #5
/*    */     //   993: new java/util/ArrayList
/*    */     //   996: dup
/*    */     //   997: dup
/*    */     //   998: aload_1
/*    */     //   999: getfield Br0 : Ljava/util/HashMap;
/*    */     //   1002: invokevirtual values : ()Ljava/util/Collection;
/*    */     //   1005: invokespecial <init> : (Ljava/util/Collection;)V
/*    */     //   1008: getstatic f/A30.I80 : Lf/Jc;
/*    */     //   1011: invokestatic sort : (Ljava/util/List;Ljava/util/Comparator;)V
/*    */     //   1014: iconst_m1
/*    */     //   1015: istore #6
/*    */     //   1017: invokevirtual iterator : ()Ljava/util/Iterator;
/*    */     //   1020: astore #7
/*    */     //   1022: aload #7
/*    */     //   1024: invokeinterface hasNext : ()Z
/*    */     //   1029: ifeq -> 1372
/*    */     //   1032: aload #7
/*    */     //   1034: invokeinterface next : ()Ljava/lang/Object;
/*    */     //   1039: checkcast f/A30
/*    */     //   1042: dup
/*    */     //   1043: astore #8
/*    */     //   1045: ifnonnull -> 1051
/*    */     //   1048: goto -> 1022
/*    */     //   1051: aload #8
/*    */     //   1053: new f/dQ
/*    */     //   1056: dup
/*    */     //   1057: astore #9
/*    */     //   1059: iload #5
/*    */     //   1061: aload #9
/*    */     //   1063: dup
/*    */     //   1064: dup
/*    */     //   1065: sipush #9168
/*    */     //   1068: invokestatic OH0 : (I)Ljava/lang/String;
/*    */     //   1071: astore #5
/*    */     //   1073: invokespecial <init> : ()V
/*    */     //   1076: aload #5
/*    */     //   1078: invokevirtual E1 : (Ljava/lang/String;)V
/*    */     //   1081: ldc_w 'label-title'
/*    */     //   1084: invokevirtual Xu : (Ljava/lang/String;)V
/*    */     //   1087: iconst_1
/*    */     //   1088: ixor
/*    */     //   1089: invokevirtual wI0 : (Z)V
/*    */     //   1092: iconst_1
/*    */     //   1093: istore #5
/*    */     //   1095: new f/dQ
/*    */     //   1098: astore #10
/*    */     //   1100: getfield COm5 : B
/*    */     //   1103: tableswitch default -> 1140, 1 -> 1187, 2 -> 1179, 3 -> 1171, 4 -> 1163, 5 -> 1155, 6 -> 1147
/*    */     //   1140: ldc '???'
/*    */     //   1142: astore #11
/*    */     //   1144: goto -> 1192
/*    */     //   1147: ldc_w '#17 - 32'
/*    */     //   1150: astore #11
/*    */     //   1152: goto -> 1192
/*    */     //   1155: ldc_w '#9 - 16'
/*    */     //   1158: astore #11
/*    */     //   1160: goto -> 1192
/*    */     //   1163: ldc_w '#5 - 8'
/*    */     //   1166: astore #11
/*    */     //   1168: goto -> 1192
/*    */     //   1171: ldc_w '#3 - 4'
/*    */     //   1174: astore #11
/*    */     //   1176: goto -> 1192
/*    */     //   1179: ldc_w '#2'
/*    */     //   1182: astore #11
/*    */     //   1184: goto -> 1192
/*    */     //   1187: ldc_w '#1'
/*    */     //   1190: astore #11
/*    */     //   1192: iload #6
/*    */     //   1194: aload #8
/*    */     //   1196: aload #10
/*    */     //   1198: dup
/*    */     //   1199: aload #11
/*    */     //   1201: aload #10
/*    */     //   1203: invokespecial <init> : ()V
/*    */     //   1206: invokevirtual E1 : (Ljava/lang/String;)V
/*    */     //   1209: ldc_w 'label-value-smallest'
/*    */     //   1212: invokevirtual Xu : (Ljava/lang/String;)V
/*    */     //   1215: getfield COm5 : B
/*    */     //   1218: if_icmpeq -> 1227
/*    */     //   1221: iconst_1
/*    */     //   1222: istore #6
/*    */     //   1224: goto -> 1230
/*    */     //   1227: iconst_0
/*    */     //   1228: istore #6
/*    */     //   1230: aload #4
/*    */     //   1232: dup
/*    */     //   1233: aload #8
/*    */     //   1235: aload #10
/*    */     //   1237: iload #6
/*    */     //   1239: invokevirtual wI0 : (Z)V
/*    */     //   1242: getfield COm5 : B
/*    */     //   1245: istore #6
/*    */     //   1247: new f/dQ
/*    */     //   1250: dup
/*    */     //   1251: dup
/*    */     //   1252: dup2
/*    */     //   1253: astore #11
/*    */     //   1255: aload #8
/*    */     //   1257: aload_1
/*    */     //   1258: dup
/*    */     //   1259: getfield KX : S
/*    */     //   1262: istore #8
/*    */     //   1264: getfield rq : I
/*    */     //   1267: iload #8
/*    */     //   1269: swap
/*    */     //   1270: invokestatic e0 : (Lf/A30;SI)Ljava/lang/String;
/*    */     //   1273: astore #8
/*    */     //   1275: invokespecial <init> : ()V
/*    */     //   1278: aload #8
/*    */     //   1280: invokevirtual E1 : (Ljava/lang/String;)V
/*    */     //   1283: ldc_w 'label-name-icon-value'
/*    */     //   1286: invokevirtual Xu : (Ljava/lang/String;)V
/*    */     //   1289: ldc_w 'label-value-large'
/*    */     //   1292: invokevirtual Xu : (Ljava/lang/String;)V
/*    */     //   1295: getfield Xz0 : Lf/U90;
/*    */     //   1298: new f/cr0
/*    */     //   1301: dup
/*    */     //   1302: aload #4
/*    */     //   1304: invokespecial <init> : (Lf/Ip;)V
/*    */     //   1307: iconst_3
/*    */     //   1308: anewarray f/JG0
/*    */     //   1311: dup
/*    */     //   1312: dup2
/*    */     //   1313: iconst_0
/*    */     //   1314: aload #9
/*    */     //   1316: aastore
/*    */     //   1317: iconst_1
/*    */     //   1318: aload #10
/*    */     //   1320: aastore
/*    */     //   1321: iconst_2
/*    */     //   1322: aload #11
/*    */     //   1324: aastore
/*    */     //   1325: invokevirtual Mg : ([Lf/JG0;)Lf/U90;
/*    */     //   1328: invokevirtual ee0 : (Lf/U90;)Lf/U90;
/*    */     //   1331: pop
/*    */     //   1332: getfield o30 : Lf/U90;
/*    */     //   1335: new f/g0
/*    */     //   1338: dup
/*    */     //   1339: aload #4
/*    */     //   1341: invokespecial <init> : (Lf/Ip;)V
/*    */     //   1344: iconst_3
/*    */     //   1345: anewarray f/JG0
/*    */     //   1348: dup
/*    */     //   1349: dup2
/*    */     //   1350: iconst_0
/*    */     //   1351: aload #9
/*    */     //   1353: aastore
/*    */     //   1354: iconst_1
/*    */     //   1355: aload #10
/*    */     //   1357: aastore
/*    */     //   1358: iconst_2
/*    */     //   1359: aload #11
/*    */     //   1361: aastore
/*    */     //   1362: invokevirtual Mg : ([Lf/JG0;)Lf/U90;
/*    */     //   1365: invokevirtual ee0 : (Lf/U90;)Lf/U90;
/*    */     //   1368: pop
/*    */     //   1369: goto -> 1022
/*    */     //   1372: aload_1
/*    */     //   1373: iconst_m1
/*    */     //   1374: istore #5
/*    */     //   1376: getfield KX : S
/*    */     //   1379: dup
/*    */     //   1380: istore #6
/*    */     //   1382: iconst_1
/*    */     //   1383: isub
/*    */     //   1384: i2s
/*    */     //   1385: istore #7
/*    */     //   1387: iconst_0
/*    */     //   1388: istore #8
/*    */     //   1390: iload #6
/*    */     //   1392: istore #9
/*    */     //   1394: iload #9
/*    */     //   1396: iconst_2
/*    */     //   1397: idiv
/*    */     //   1398: dup
/*    */     //   1399: istore #9
/*    */     //   1401: ifle -> 1419
/*    */     //   1404: iload #9
/*    */     //   1406: iload #8
/*    */     //   1408: iconst_1
/*    */     //   1409: iadd
/*    */     //   1410: i2s
/*    */     //   1411: istore #8
/*    */     //   1413: i2s
/*    */     //   1414: istore #9
/*    */     //   1416: goto -> 1394
/*    */     //   1419: iconst_0
/*    */     //   1420: istore #9
/*    */     //   1422: iload #9
/*    */     //   1424: iload #7
/*    */     //   1426: if_icmpge -> 2873
/*    */     //   1429: iload #9
/*    */     //   1431: iload #6
/*    */     //   1433: invokestatic f1 : (SS)S
/*    */     //   1436: dup
/*    */     //   1437: istore #10
/*    */     //   1439: iload #5
/*    */     //   1441: if_icmpeq -> 1618
/*    */     //   1444: ldc ''
/*    */     //   1446: astore #5
/*    */     //   1448: iload #10
/*    */     //   1450: iconst_1
/*    */     //   1451: iadd
/*    */     //   1452: dup
/*    */     //   1453: istore #11
/*    */     //   1455: iload #8
/*    */     //   1457: if_icmpne -> 1468
/*    */     //   1460: sipush #9170
/*    */     //   1463: invokestatic OH0 : (I)Ljava/lang/String;
/*    */     //   1466: astore #5
/*    */     //   1468: iload #10
/*    */     //   1470: iconst_2
/*    */     //   1471: iadd
/*    */     //   1472: iload #8
/*    */     //   1474: if_icmpne -> 1485
/*    */     //   1477: sipush #9171
/*    */     //   1480: invokestatic OH0 : (I)Ljava/lang/String;
/*    */     //   1483: astore #5
/*    */     //   1485: iload #10
/*    */     //   1487: aload #4
/*    */     //   1489: new f/dQ
/*    */     //   1492: dup
/*    */     //   1493: dup2
/*    */     //   1494: astore #12
/*    */     //   1496: iconst_2
/*    */     //   1497: anewarray java/lang/String
/*    */     //   1500: dup
/*    */     //   1501: dup
/*    */     //   1502: astore #13
/*    */     //   1504: new java/lang/StringBuilder
/*    */     //   1507: dup
/*    */     //   1508: iload #11
/*    */     //   1510: swap
/*    */     //   1511: invokespecial <init> : ()V
/*    */     //   1514: invokevirtual append : (I)Ljava/lang/StringBuilder;
/*    */     //   1517: ldc ''
/*    */     //   1519: invokevirtual append : (Ljava/lang/String;)Ljava/lang/StringBuilder;
/*    */     //   1522: invokevirtual toString : ()Ljava/lang/String;
/*    */     //   1525: iconst_0
/*    */     //   1526: swap
/*    */     //   1527: aastore
/*    */     //   1528: iconst_1
/*    */     //   1529: aload #5
/*    */     //   1531: aastore
/*    */     //   1532: sipush #9169
/*    */     //   1535: aload #13
/*    */     //   1537: invokestatic sB : (I[Ljava/lang/String;)Ljava/lang/String;
/*    */     //   1540: astore #5
/*    */     //   1542: invokespecial <init> : ()V
/*    */     //   1545: aload #5
/*    */     //   1547: invokevirtual E1 : (Ljava/lang/String;)V
/*    */     //   1550: ldc_w 'label-title'
/*    */     //   1553: invokevirtual Xu : (Ljava/lang/String;)V
/*    */     //   1556: getfield Xz0 : Lf/U90;
/*    */     //   1559: aload #4
/*    */     //   1561: iconst_1
/*    */     //   1562: anewarray f/JG0
/*    */     //   1565: dup
/*    */     //   1566: iconst_0
/*    */     //   1567: aload #12
/*    */     //   1569: aastore
/*    */     //   1570: invokevirtual vo0 : ([Lf/JG0;)Lf/U90;
/*    */     //   1573: invokevirtual ee0 : (Lf/U90;)Lf/U90;
/*    */     //   1576: pop
/*    */     //   1577: ifle -> 1591
/*    */     //   1580: aload #4
/*    */     //   1582: getfield o30 : Lf/U90;
/*    */     //   1585: bipush #20
/*    */     //   1587: invokevirtual Aq : (I)Lf/U90;
/*    */     //   1590: pop
/*    */     //   1591: aload #4
/*    */     //   1593: getfield o30 : Lf/U90;
/*    */     //   1596: aload #4
/*    */     //   1598: iconst_1
/*    */     //   1599: anewarray f/JG0
/*    */     //   1602: dup
/*    */     //   1603: iconst_0
/*    */     //   1604: aload #12
/*    */     //   1606: aastore
/*    */     //   1607: invokevirtual AUX : ([Lf/JG0;)Lf/U90;
/*    */     //   1610: invokevirtual ee0 : (Lf/U90;)Lf/U90;
/*    */     //   1613: pop
/*    */     //   1614: iload #10
/*    */     //   1616: istore #5
/*    */     //   1618: aload_1
/*    */     //   1619: iload #9
/*    */     //   1621: invokevirtual rv : (S)Lf/nD0;
/*    */     //   1624: dup
/*    */     //   1625: astore #10
/*    */     //   1627: ifnonnull -> 1636
/*    */     //   1630: aconst_null
/*    */     //   1631: astore #10
/*    */     //   1633: goto -> 1807
/*    */     //   1636: aload_1
/*    */     //   1637: getfield Q40 : Z
/*    */     //   1640: ifne -> 1800
/*    */     //   1643: aload_1
/*    */     //   1644: iconst_2
/*    */     //   1645: anewarray f/jc
/*    */     //   1648: astore #10
/*    */     //   1650: getfield KX : S
/*    */     //   1653: istore #11
/*    */     //   1655: iconst_0
/*    */     //   1656: istore #12
/*    */     //   1658: iconst_0
/*    */     //   1659: istore #13
/*    */     //   1661: iload #12
/*    */     //   1663: iload #13
/*    */     //   1665: istore #12
/*    */     //   1667: istore #13
/*    */     //   1669: iload #11
/*    */     //   1671: iconst_2
/*    */     //   1672: idiv
/*    */     //   1673: dup
/*    */     //   1674: istore #11
/*    */     //   1676: ifle -> 1706
/*    */     //   1679: iload #13
/*    */     //   1681: iload #11
/*    */     //   1683: iadd
/*    */     //   1684: dup
/*    */     //   1685: istore #14
/*    */     //   1687: iload #9
/*    */     //   1689: if_icmple -> 1695
/*    */     //   1692: goto -> 1706
/*    */     //   1695: iload #14
/*    */     //   1697: iload #13
/*    */     //   1699: istore #12
/*    */     //   1701: istore #13
/*    */     //   1703: goto -> 1669
/*    */     //   1706: iload #9
/*    */     //   1708: aload_1
/*    */     //   1709: getfield KX : S
/*    */     //   1712: iconst_2
/*    */     //   1713: idiv
/*    */     //   1714: if_icmpge -> 1754
/*    */     //   1717: aload #10
/*    */     //   1719: aload_1
/*    */     //   1720: getfield gb : [Lf/jc;
/*    */     //   1723: dup
/*    */     //   1724: astore #11
/*    */     //   1726: iload #9
/*    */     //   1728: iconst_2
/*    */     //   1729: imul
/*    */     //   1730: dup
/*    */     //   1731: istore #12
/*    */     //   1733: aload #10
/*    */     //   1735: aload #11
/*    */     //   1737: iload #12
/*    */     //   1739: iconst_0
/*    */     //   1740: iadd
/*    */     //   1741: aaload
/*    */     //   1742: iconst_0
/*    */     //   1743: swap
/*    */     //   1744: aastore
/*    */     //   1745: iconst_1
/*    */     //   1746: iadd
/*    */     //   1747: aaload
/*    */     //   1748: iconst_1
/*    */     //   1749: swap
/*    */     //   1750: aastore
/*    */     //   1751: goto -> 1807
/*    */     //   1754: aload #10
/*    */     //   1756: aload_1
/*    */     //   1757: iload #9
/*    */     //   1759: iconst_2
/*    */     //   1760: imul
/*    */     //   1761: iload #13
/*    */     //   1763: irem
/*    */     //   1764: iload #12
/*    */     //   1766: iadd
/*    */     //   1767: i2s
/*    */     //   1768: dup
/*    */     //   1769: istore #11
/*    */     //   1771: aload #10
/*    */     //   1773: aload_1
/*    */     //   1774: iload #11
/*    */     //   1776: invokevirtual rv : (S)Lf/nD0;
/*    */     //   1779: getfield Q0 : Lf/jc;
/*    */     //   1782: iconst_0
/*    */     //   1783: swap
/*    */     //   1784: aastore
/*    */     //   1785: iconst_1
/*    */     //   1786: iadd
/*    */     //   1787: i2s
/*    */     //   1788: invokevirtual rv : (S)Lf/nD0;
/*    */     //   1791: getfield Q0 : Lf/jc;
/*    */     //   1794: iconst_1
/*    */     //   1795: swap
/*    */     //   1796: aastore
/*    */     //   1797: goto -> 1807
/*    */     //   1800: aload #10
/*    */     //   1802: getfield xn : [Lf/jc;
/*    */     //   1805: astore #10
/*    */     //   1807: iconst_2
/*    */     //   1808: dup
/*    */     //   1809: istore #11
/*    */     //   1811: anewarray f/dQ
/*    */     //   1814: astore #12
/*    */     //   1816: iconst_3
/*    */     //   1817: anewarray f/dQ
/*    */     //   1820: astore #13
/*    */     //   1822: iconst_0
/*    */     //   1823: istore #14
/*    */     //   1825: iload #14
/*    */     //   1827: iload #11
/*    */     //   1829: if_icmpge -> 2123
/*    */     //   1832: aload_1
/*    */     //   1833: iload #9
/*    */     //   1835: invokevirtual rv : (S)Lf/nD0;
/*    */     //   1838: getfield HR : B
/*    */     //   1841: ifne -> 1884
/*    */     //   1844: aload #13
/*    */     //   1846: ldc '???'
/*    */     //   1848: invokestatic A : (Ljava/lang/String;)Lf/dQ;
/*    */     //   1851: dup
/*    */     //   1852: astore #15
/*    */     //   1854: aload #12
/*    */     //   1856: iload #14
/*    */     //   1858: aload #15
/*    */     //   1860: aastore
/*    */     //   1861: ldc_w 'label-name-icon-value'
/*    */     //   1864: invokevirtual Xu : (Ljava/lang/String;)V
/*    */     //   1867: new f/dQ
/*    */     //   1870: dup
/*    */     //   1871: astore #15
/*    */     //   1873: invokespecial <init> : ()V
/*    */     //   1876: iload #14
/*    */     //   1878: aload #15
/*    */     //   1880: aastore
/*    */     //   1881: goto -> 2117
/*    */     //   1884: aload #10
/*    */     //   1886: new f/dQ
/*    */     //   1889: astore #15
/*    */     //   1891: iload #14
/*    */     //   1893: aaload
/*    */     //   1894: dup
/*    */     //   1895: astore #16
/*    */     //   1897: ifnonnull -> 1907
/*    */     //   1900: ldc '???'
/*    */     //   1902: astore #16
/*    */     //   1904: goto -> 1917
/*    */     //   1907: aload #16
/*    */     //   1909: getfield jb : Lf/FV;
/*    */     //   1912: getfield Pb : Ljava/lang/String;
/*    */     //   1915: astore #16
/*    */     //   1917: aload #10
/*    */     //   1919: iload #14
/*    */     //   1921: aload #15
/*    */     //   1923: aload #12
/*    */     //   1925: iload #14
/*    */     //   1927: aload #15
/*    */     //   1929: aload #16
/*    */     //   1931: aload #15
/*    */     //   1933: invokespecial <init> : ()V
/*    */     //   1936: invokevirtual E1 : (Ljava/lang/String;)V
/*    */     //   1939: aload #15
/*    */     //   1941: aastore
/*    */     //   1942: ldc_w 'label-name-icon-value'
/*    */     //   1945: invokevirtual Xu : (Ljava/lang/String;)V
/*    */     //   1948: aaload
/*    */     //   1949: ifnull -> 2090
/*    */     //   1952: invokestatic XU : ()Z
/*    */     //   1955: ifeq -> 2032
/*    */     //   1958: aload #10
/*    */     //   1960: new f/VP
/*    */     //   1963: astore #15
/*    */     //   1965: bipush #48
/*    */     //   1967: istore #16
/*    */     //   1969: bipush #48
/*    */     //   1971: istore #17
/*    */     //   1973: iload #14
/*    */     //   1975: aaload
/*    */     //   1976: dup
/*    */     //   1977: astore #18
/*    */     //   1979: ifnonnull -> 1988
/*    */     //   1982: aconst_null
/*    */     //   1983: astore #18
/*    */     //   1985: goto -> 1995
/*    */     //   1988: aload #18
/*    */     //   1990: getfield jb : Lf/FV;
/*    */     //   1993: astore #18
/*    */     //   1995: aload #13
/*    */     //   1997: iload #14
/*    */     //   1999: aload #15
/*    */     //   2001: dup
/*    */     //   2002: dup
/*    */     //   2003: iload #16
/*    */     //   2005: iload #17
/*    */     //   2007: aload #18
/*    */     //   2009: invokespecial <init> : (IILf/FV;)V
/*    */     //   2012: getfield X70 : Lf/Dn0;
/*    */     //   2015: iconst_2
/*    */     //   2016: putfield Dd : I
/*    */     //   2019: bipush #-34
/*    */     //   2021: bipush #-31
/*    */     //   2023: invokevirtual nx : (II)V
/*    */     //   2026: aload #15
/*    */     //   2028: aastore
/*    */     //   2029: goto -> 2106
/*    */     //   2032: aload #10
/*    */     //   2034: new f/VP
/*    */     //   2037: astore #15
/*    */     //   2039: bipush #24
/*    */     //   2041: istore #16
/*    */     //   2043: bipush #24
/*    */     //   2045: istore #17
/*    */     //   2047: iload #14
/*    */     //   2049: aaload
/*    */     //   2050: dup
/*    */     //   2051: astore #18
/*    */     //   2053: ifnonnull -> 2062
/*    */     //   2056: aconst_null
/*    */     //   2057: astore #18
/*    */     //   2059: goto -> 2069
/*    */     //   2062: aload #18
/*    */     //   2064: getfield jb : Lf/FV;
/*    */     //   2067: astore #18
/*    */     //   2069: aload #13
/*    */     //   2071: aload #15
/*    */     //   2073: iload #16
/*    */     //   2075: iload #17
/*    */     //   2077: aload #18
/*    */     //   2079: invokespecial <init> : (IILf/FV;)V
/*    */     //   2082: iload #14
/*    */     //   2084: aload #15
/*    */     //   2086: aastore
/*    */     //   2087: goto -> 2106
/*    */     //   2090: aload #13
/*    */     //   2092: new f/dQ
/*    */     //   2095: dup
/*    */     //   2096: astore #15
/*    */     //   2098: invokespecial <init> : ()V
/*    */     //   2101: iload #14
/*    */     //   2103: aload #15
/*    */     //   2105: aastore
/*    */     //   2106: aload #13
/*    */     //   2108: iload #14
/*    */     //   2110: aaload
/*    */     //   2111: ldc_w 'label-value-icon'
/*    */     //   2114: invokevirtual Xu : (Ljava/lang/String;)V
/*    */     //   2117: iinc #14, 1
/*    */     //   2120: goto -> 1825
/*    */     //   2123: aload_1
/*    */     //   2124: new f/dQ
/*    */     //   2127: dup
/*    */     //   2128: dup2
/*    */     //   2129: astore #10
/*    */     //   2131: sipush #5024
/*    */     //   2134: invokestatic OH0 : (I)Ljava/lang/String;
/*    */     //   2137: astore #11
/*    */     //   2139: invokespecial <init> : ()V
/*    */     //   2142: aload #11
/*    */     //   2144: invokevirtual E1 : (Ljava/lang/String;)V
/*    */     //   2147: ldc_w 'label-value-smallest'
/*    */     //   2150: invokevirtual Xu : (Ljava/lang/String;)V
/*    */     //   2153: iload #9
/*    */     //   2155: invokevirtual rv : (S)Lf/nD0;
/*    */     //   2158: dup
/*    */     //   2159: astore #11
/*    */     //   2161: getfield Q0 : Lf/jc;
/*    */     //   2164: dup
/*    */     //   2165: astore #14
/*    */     //   2167: ifnonnull -> 2199
/*    */     //   2170: aload_1
/*    */     //   2171: iload #9
/*    */     //   2173: invokevirtual rv : (S)Lf/nD0;
/*    */     //   2176: getfield d5 : I
/*    */     //   2179: iflt -> 2199
/*    */     //   2182: aload_1
/*    */     //   2183: aload #11
/*    */     //   2185: getfield d5 : I
/*    */     //   2188: i2s
/*    */     //   2189: istore #14
/*    */     //   2191: getfield gb : [Lf/jc;
/*    */     //   2194: iload #14
/*    */     //   2196: aaload
/*    */     //   2197: astore #14
/*    */     //   2199: aload #11
/*    */     //   2201: aload #13
/*    */     //   2203: new f/dQ
/*    */     //   2206: dup
/*    */     //   2207: dup
/*    */     //   2208: astore #15
/*    */     //   2210: invokespecial <init> : ()V
/*    */     //   2213: new f/Un
/*    */     //   2216: dup
/*    */     //   2217: astore #16
/*    */     //   2219: invokespecial <init> : ()V
/*    */     //   2222: ldc_w 'label-name-value'
/*    */     //   2225: invokevirtual Xu : (Ljava/lang/String;)V
/*    */     //   2228: ldc ''
/*    */     //   2230: invokestatic A : (Ljava/lang/String;)Lf/dQ;
/*    */     //   2233: iconst_2
/*    */     //   2234: swap
/*    */     //   2235: aastore
/*    */     //   2236: getfield HR : B
/*    */     //   2239: tableswitch default -> 2268, 0 -> 2623, 1 -> 2591, 2 -> 2292, 3 -> 2271
/*    */     //   2268: goto -> 2630
/*    */     //   2271: aload #15
/*    */     //   2273: dup
/*    */     //   2274: dup
/*    */     //   2275: sipush #9176
/*    */     //   2278: invokestatic OH0 : (I)Ljava/lang/String;
/*    */     //   2281: putfield z4 : Ljava/lang/Object;
/*    */     //   2284: invokevirtual zn : ()V
/*    */     //   2287: bipush #100
/*    */     //   2289: putfield jl : I
/*    */     //   2292: aload #14
/*    */     //   2294: sipush #9177
/*    */     //   2297: istore #17
/*    */     //   2299: ifnonnull -> 2309
/*    */     //   2302: ldc '???'
/*    */     //   2304: astore #18
/*    */     //   2306: goto -> 2319
/*    */     //   2309: aload #14
/*    */     //   2311: getfield jb : Lf/FV;
/*    */     //   2314: getfield Pb : Ljava/lang/String;
/*    */     //   2317: astore #18
/*    */     //   2319: aload #14
/*    */     //   2321: aload #16
/*    */     //   2323: dup
/*    */     //   2324: iload #17
/*    */     //   2326: aload #18
/*    */     //   2328: invokestatic Go : (ILjava/lang/String;)Ljava/lang/String;
/*    */     //   2331: invokevirtual s6 : (Ljava/lang/String;)V
/*    */     //   2334: ldc_w 'label-name-value-button'
/*    */     //   2337: invokevirtual Xu : (Ljava/lang/String;)V
/*    */     //   2340: sipush #9177
/*    */     //   2343: istore #17
/*    */     //   2345: ifnonnull -> 2355
/*    */     //   2348: ldc '???'
/*    */     //   2350: astore #18
/*    */     //   2352: goto -> 2365
/*    */     //   2355: aload #14
/*    */     //   2357: getfield jb : Lf/FV;
/*    */     //   2360: getfield Pb : Ljava/lang/String;
/*    */     //   2363: astore #18
/*    */     //   2365: aload #15
/*    */     //   2367: iload #17
/*    */     //   2369: aload #18
/*    */     //   2371: invokestatic Go : (ILjava/lang/String;)Ljava/lang/String;
/*    */     //   2374: invokevirtual E1 : (Ljava/lang/String;)V
/*    */     //   2377: invokestatic XU : ()Z
/*    */     //   2380: ifeq -> 2450
/*    */     //   2383: aload #14
/*    */     //   2385: new f/VP
/*    */     //   2388: astore #17
/*    */     //   2390: bipush #48
/*    */     //   2392: istore #18
/*    */     //   2394: bipush #48
/*    */     //   2396: istore #19
/*    */     //   2398: ifnonnull -> 2407
/*    */     //   2401: aconst_null
/*    */     //   2402: astore #20
/*    */     //   2404: goto -> 2414
/*    */     //   2407: aload #14
/*    */     //   2409: getfield jb : Lf/FV;
/*    */     //   2412: astore #20
/*    */     //   2414: aload #13
/*    */     //   2416: aload #17
/*    */     //   2418: dup
/*    */     //   2419: dup
/*    */     //   2420: iload #18
/*    */     //   2422: iload #19
/*    */     //   2424: aload #20
/*    */     //   2426: invokespecial <init> : (IILf/FV;)V
/*    */     //   2429: getfield X70 : Lf/Dn0;
/*    */     //   2432: iconst_2
/*    */     //   2433: putfield Dd : I
/*    */     //   2436: bipush #-34
/*    */     //   2438: bipush #-31
/*    */     //   2440: invokevirtual nx : (II)V
/*    */     //   2443: iconst_2
/*    */     //   2444: aload #17
/*    */     //   2446: aastore
/*    */     //   2447: goto -> 2503
/*    */     //   2450: aload #14
/*    */     //   2452: iconst_2
/*    */     //   2453: istore #17
/*    */     //   2455: new f/VP
/*    */     //   2458: astore #18
/*    */     //   2460: bipush #24
/*    */     //   2462: istore #19
/*    */     //   2464: bipush #24
/*    */     //   2466: istore #20
/*    */     //   2468: ifnull -> 2482
/*    */     //   2471: aload #14
/*    */     //   2473: getfield jb : Lf/FV;
/*    */     //   2476: dup
/*    */     //   2477: astore #21
/*    */     //   2479: ifnonnull -> 2485
/*    */     //   2482: aconst_null
/*    */     //   2483: astore #21
/*    */     //   2485: aload #13
/*    */     //   2487: aload #18
/*    */     //   2489: iload #19
/*    */     //   2491: iload #20
/*    */     //   2493: aload #21
/*    */     //   2495: invokespecial <init> : (IILf/FV;)V
/*    */     //   2498: iload #17
/*    */     //   2500: aload #18
/*    */     //   2502: aastore
/*    */     //   2503: aload #14
/*    */     //   2505: aload #13
/*    */     //   2507: iconst_2
/*    */     //   2508: aaload
/*    */     //   2509: astore #17
/*    */     //   2511: ifnull -> 2528
/*    */     //   2514: aload #14
/*    */     //   2516: getfield jb : Lf/FV;
/*    */     //   2519: ifnull -> 2528
/*    */     //   2522: iconst_1
/*    */     //   2523: istore #18
/*    */     //   2525: goto -> 2531
/*    */     //   2528: iconst_0
/*    */     //   2529: istore #18
/*    */     //   2531: aload #11
/*    */     //   2533: aload #17
/*    */     //   2535: iload #18
/*    */     //   2537: invokevirtual wI0 : (Z)V
/*    */     //   2540: getfield HR : B
/*    */     //   2543: iconst_3
/*    */     //   2544: if_icmpne -> 2630
/*    */     //   2547: aload #14
/*    */     //   2549: ifnonnull -> 2630
/*    */     //   2552: aload #15
/*    */     //   2554: dup
/*    */     //   2555: dup
/*    */     //   2556: aload #16
/*    */     //   2558: sipush #9178
/*    */     //   2561: invokestatic OH0 : (I)Ljava/lang/String;
/*    */     //   2564: invokevirtual s6 : (Ljava/lang/String;)V
/*    */     //   2567: sipush #9178
/*    */     //   2570: invokestatic OH0 : (I)Ljava/lang/String;
/*    */     //   2573: invokevirtual E1 : (Ljava/lang/String;)V
/*    */     //   2576: sipush #9179
/*    */     //   2579: invokestatic OH0 : (I)Ljava/lang/String;
/*    */     //   2582: putfield z4 : Ljava/lang/Object;
/*    */     //   2585: invokevirtual zn : ()V
/*    */     //   2588: goto -> 2630
/*    */     //   2591: aload #16
/*    */     //   2593: dup
/*    */     //   2594: aload #15
/*    */     //   2596: sipush #9175
/*    */     //   2599: invokestatic OH0 : (I)Ljava/lang/String;
/*    */     //   2602: invokevirtual E1 : (Ljava/lang/String;)V
/*    */     //   2605: sipush #9175
/*    */     //   2608: invokestatic OH0 : (I)Ljava/lang/String;
/*    */     //   2611: invokevirtual s6 : (Ljava/lang/String;)V
/*    */     //   2614: ldc_w 'label-name-value-button'
/*    */     //   2617: invokevirtual Xu : (Ljava/lang/String;)V
/*    */     //   2620: goto -> 2630
/*    */     //   2623: aload #15
/*    */     //   2625: ldc ''
/*    */     //   2627: invokevirtual E1 : (Ljava/lang/String;)V
/*    */     //   2630: aload #11
/*    */     //   2632: getfield HR : B
/*    */     //   2635: dup
/*    */     //   2636: istore #14
/*    */     //   2638: iconst_2
/*    */     //   2639: if_icmpne -> 2672
/*    */     //   2642: aload #11
/*    */     //   2644: getfield Bv0 : I
/*    */     //   2647: ifle -> 2672
/*    */     //   2650: aload #16
/*    */     //   2652: new f/Ff
/*    */     //   2655: dup
/*    */     //   2656: astore #14
/*    */     //   2658: aload_0
/*    */     //   2659: aload #11
/*    */     //   2661: invokespecial <init> : (Lf/ep;Lf/nD0;)V
/*    */     //   2664: aload #14
/*    */     //   2666: invokevirtual tW : (Ljava/lang/Runnable;)V
/*    */     //   2669: goto -> 2698
/*    */     //   2672: iload #14
/*    */     //   2674: iconst_1
/*    */     //   2675: if_icmpne -> 2702
/*    */     //   2678: aload #16
/*    */     //   2680: new f/CB0
/*    */     //   2683: dup
/*    */     //   2684: astore #14
/*    */     //   2686: aload_0
/*    */     //   2687: aload_1
/*    */     //   2688: aload #11
/*    */     //   2690: invokespecial <init> : (Lf/ep;Lf/qa0;Lf/nD0;)V
/*    */     //   2693: aload #14
/*    */     //   2695: invokevirtual tW : (Ljava/lang/Runnable;)V
/*    */     //   2698: aload #16
/*    */     //   2700: astore #15
/*    */     //   2702: iload #9
/*    */     //   2704: aload #4
/*    */     //   2706: dup
/*    */     //   2707: aload #13
/*    */     //   2709: iconst_2
/*    */     //   2710: aaload
/*    */     //   2711: ldc_w 'label-value-icon'
/*    */     //   2714: invokevirtual Xu : (Ljava/lang/String;)V
/*    */     //   2717: getfield Xz0 : Lf/U90;
/*    */     //   2720: aload #4
/*    */     //   2722: bipush #7
/*    */     //   2724: anewarray f/JG0
/*    */     //   2727: dup
/*    */     //   2728: dup2
/*    */     //   2729: astore #9
/*    */     //   2731: aload #13
/*    */     //   2733: aload #9
/*    */     //   2735: aload #12
/*    */     //   2737: aload #9
/*    */     //   2739: aload #13
/*    */     //   2741: aload #9
/*    */     //   2743: dup
/*    */     //   2744: aload #12
/*    */     //   2746: aload #9
/*    */     //   2748: aload #13
/*    */     //   2750: iconst_0
/*    */     //   2751: aaload
/*    */     //   2752: iconst_0
/*    */     //   2753: swap
/*    */     //   2754: aastore
/*    */     //   2755: iconst_0
/*    */     //   2756: aaload
/*    */     //   2757: iconst_1
/*    */     //   2758: swap
/*    */     //   2759: aastore
/*    */     //   2760: iconst_2
/*    */     //   2761: aload #10
/*    */     //   2763: aastore
/*    */     //   2764: iconst_1
/*    */     //   2765: aaload
/*    */     //   2766: iconst_3
/*    */     //   2767: swap
/*    */     //   2768: aastore
/*    */     //   2769: iconst_1
/*    */     //   2770: aaload
/*    */     //   2771: iconst_4
/*    */     //   2772: swap
/*    */     //   2773: aastore
/*    */     //   2774: iconst_2
/*    */     //   2775: aaload
/*    */     //   2776: iconst_5
/*    */     //   2777: swap
/*    */     //   2778: aastore
/*    */     //   2779: bipush #6
/*    */     //   2781: aload #15
/*    */     //   2783: aastore
/*    */     //   2784: invokevirtual vo0 : ([Lf/JG0;)Lf/U90;
/*    */     //   2787: invokevirtual ee0 : (Lf/U90;)Lf/U90;
/*    */     //   2790: pop
/*    */     //   2791: getfield o30 : Lf/U90;
/*    */     //   2794: aload #4
/*    */     //   2796: bipush #7
/*    */     //   2798: anewarray f/JG0
/*    */     //   2801: dup
/*    */     //   2802: dup2
/*    */     //   2803: astore #9
/*    */     //   2805: aload #13
/*    */     //   2807: aload #9
/*    */     //   2809: aload #12
/*    */     //   2811: aload #9
/*    */     //   2813: aload #13
/*    */     //   2815: aload #9
/*    */     //   2817: dup
/*    */     //   2818: aload #12
/*    */     //   2820: aload #9
/*    */     //   2822: aload #13
/*    */     //   2824: iconst_0
/*    */     //   2825: aaload
/*    */     //   2826: iconst_0
/*    */     //   2827: swap
/*    */     //   2828: aastore
/*    */     //   2829: iconst_0
/*    */     //   2830: aaload
/*    */     //   2831: iconst_1
/*    */     //   2832: swap
/*    */     //   2833: aastore
/*    */     //   2834: iconst_2
/*    */     //   2835: aload #10
/*    */     //   2837: aastore
/*    */     //   2838: iconst_1
/*    */     //   2839: aaload
/*    */     //   2840: iconst_3
/*    */     //   2841: swap
/*    */     //   2842: aastore
/*    */     //   2843: iconst_1
/*    */     //   2844: aaload
/*    */     //   2845: iconst_4
/*    */     //   2846: swap
/*    */     //   2847: aastore
/*    */     //   2848: iconst_2
/*    */     //   2849: aaload
/*    */     //   2850: iconst_5
/*    */     //   2851: swap
/*    */     //   2852: aastore
/*    */     //   2853: bipush #6
/*    */     //   2855: aload #15
/*    */     //   2857: aastore
/*    */     //   2858: invokevirtual AUX : ([Lf/JG0;)Lf/U90;
/*    */     //   2861: invokevirtual ee0 : (Lf/U90;)Lf/U90;
/*    */     //   2864: pop
/*    */     //   2865: iconst_1
/*    */     //   2866: iadd
/*    */     //   2867: i2s
/*    */     //   2868: istore #9
/*    */     //   2870: goto -> 1422
/*    */     //   2873: aload_0
/*    */     //   2874: dup
/*    */     //   2875: aload_2
/*    */     //   2876: aload #4
/*    */     //   2878: invokevirtual Gz0 : (Lf/JG0;)V
/*    */     //   2881: getfield bw : Lf/Vq0;
/*    */     //   2884: aload_3
/*    */     //   2885: aload_1
/*    */     //   2886: invokevirtual P8 : ()Ljava/lang/String;
/*    */     //   2889: invokevirtual WS : (Lf/JG0;Ljava/lang/String;)Lf/Li0;
/*    */     //   2892: dup
/*    */     //   2893: astore_1
/*    */     //   2894: new f/I80
/*    */     //   2897: dup
/*    */     //   2898: aload_0
/*    */     //   2899: aload_1
/*    */     //   2900: invokespecial <init> : (Lf/ep;Lf/Li0;)V
/*    */     //   2903: invokevirtual Ac0 : (Ljava/lang/Runnable;)V
/*    */     //   2906: getfield bw : Lf/Vq0;
/*    */     //   2909: aload_1
/*    */     //   2910: invokevirtual dA0 : (Lf/Li0;)V
/*    */     //   2913: return
/*    */     // Line number table:
/*    */     //   Java source line number -> byte code offset
/*    */     //   #1	-> 4
/*    */     //   #2	-> 7
/*    */     //   #3	-> 12
/*    */     //   #4	-> 16
/*    */     //   #5	-> 23
/*    */     //   #6	-> 26
/*    */     //   #7	-> 79
/*    */     //   #8	-> 88
/*    */     //   #9	-> 91
/*    */     //   #10	-> 100
/*    */     //   #11	-> 119
/*    */     //   #12	-> 128
/*    */     //   #13	-> 140
/*    */     //   #14	-> 143
/*    */     //   #15	-> 167
/*    */     //   #16	-> 179
/*    */     //   #17	-> 189
/*    */     //   #18	-> 192
/*    */     //   #19	-> 215
/*    */     //   #20	-> 224
/*    */     //   #21	-> 230
/*    */     //   #22	-> 270
/*    */     //   #23	-> 273
/*    */     //   #24	-> 313
/*    */     //   #25	-> 323
/*    */     //   #26	-> 326
/*    */     //   #27	-> 329
/*    */     //   #28	-> 347
/*    */     //   #29	-> 350
/*    */     //   #30	-> 368
/*    */     //   #31	-> 380
/*    */     //   #32	-> 407
/*    */     //   #33	-> 415
/*    */     //   #34	-> 449
/*    */     //   #35	-> 459
/*    */     //   #36	-> 472
/*    */     //   #37	-> 487
/*    */     //   #38	-> 490
/*    */     //   #39	-> 509
/*    */     //   #40	-> 512
/*    */     //   #41	-> 528
/*    */     //   #42	-> 537
/*    */     //   #43	-> 545
/*    */     //   #44	-> 596
/*    */     //   #45	-> 602
/*    */     //   #46	-> 679
/*    */     //   #47	-> 687
/*    */     //   #48	-> 706
/*    */     //   #49	-> 754
/*    */     //   #50	-> 760
/*    */     //   #51	-> 781
/*    */     //   #52	-> 792
/*    */     //   #53	-> 795
/*    */     //   #54	-> 799
/*    */     //   #55	-> 806
/*    */     //   #56	-> 820
/*    */     //   #57	-> 831
/*    */     //   #58	-> 846
/*    */     //   #59	-> 849
/*    */     //   #60	-> 854
/*    */     //   #61	-> 862
/*    */     //   #62	-> 868
/*    */     //   #63	-> 871
/*    */     //   #64	-> 881
/*    */     //   #65	-> 910
/*    */     //   #66	-> 913
/*    */     //   #67	-> 923
/*    */     //   #68	-> 959
/*    */     //   #69	-> 965
/*    */     //   #70	-> 999
/*    */     //   #71	-> 1005
/*    */     //   #72	-> 1073
/*    */     //   #73	-> 1081
/*    */     //   #74	-> 1100
/*    */     //   #75	-> 1203
/*    */     //   #76	-> 1209
/*    */     //   #77	-> 1215
/*    */     //   #78	-> 1239
/*    */     //   #79	-> 1242
/*    */     //   #80	-> 1247
/*    */     //   #81	-> 1259
/*    */     //   #82	-> 1264
/*    */     //   #83	-> 1270
/*    */     //   #84	-> 1275
/*    */     //   #85	-> 1283
/*    */     //   #86	-> 1295
/*    */     //   #87	-> 1298
/*    */     //   #88	-> 1308
/*    */     //   #89	-> 1332
/*    */     //   #90	-> 1335
/*    */     //   #91	-> 1345
/*    */     //   #92	-> 1376
/*    */     //   #93	-> 1397
/*    */     //   #94	-> 1433
/*    */     //   #95	-> 1542
/*    */     //   #96	-> 1550
/*    */     //   #97	-> 1556
/*    */     //   #98	-> 1562
/*    */     //   #99	-> 1582
/*    */     //   #100	-> 1587
/*    */     //   #101	-> 1593
/*    */     //   #102	-> 1599
/*    */     //   #103	-> 1621
/*    */     //   #104	-> 1645
/*    */     //   #105	-> 1650
/*    */     //   #106	-> 1672
/*    */     //   #107	-> 1709
/*    */     //   #108	-> 1713
/*    */     //   #109	-> 1779
/*    */     //   #110	-> 1784
/*    */     //   #111	-> 1791
/*    */     //   #112	-> 1796
/*    */     //   #113	-> 1802
/*    */     //   #114	-> 1811
/*    */     //   #115	-> 1838
/*    */     //   #116	-> 1846
/*    */     //   #117	-> 1860
/*    */     //   #118	-> 1909
/*    */     //   #119	-> 1912
/*    */     //   #120	-> 1933
/*    */     //   #121	-> 1941
/*    */     //   #122	-> 1990
/*    */     //   #123	-> 2009
/*    */     //   #124	-> 2012
/*    */     //   #125	-> 2016
/*    */     //   #126	-> 2023
/*    */     //   #127	-> 2064
/*    */     //   #128	-> 2079
/*    */     //   #129	-> 2139
/*    */     //   #130	-> 2147
/*    */     //   #131	-> 2161
/*    */     //   #132	-> 2173
/*    */     //   #133	-> 2176
/*    */     //   #134	-> 2185
/*    */     //   #135	-> 2191
/*    */     //   #136	-> 2203
/*    */     //   #137	-> 2228
/*    */     //   #138	-> 2235
/*    */     //   #139	-> 2236
/*    */     //   #140	-> 2278
/*    */     //   #141	-> 2281
/*    */     //   #142	-> 2289
/*    */     //   #143	-> 2302
/*    */     //   #144	-> 2311
/*    */     //   #145	-> 2314
/*    */     //   #146	-> 2328
/*    */     //   #147	-> 2357
/*    */     //   #148	-> 2360
/*    */     //   #149	-> 2371
/*    */     //   #150	-> 2409
/*    */     //   #151	-> 2426
/*    */     //   #152	-> 2429
/*    */     //   #153	-> 2433
/*    */     //   #154	-> 2440
/*    */     //   #155	-> 2473
/*    */     //   #156	-> 2495
/*    */     //   #157	-> 2516
/*    */     //   #158	-> 2537
/*    */     //   #159	-> 2540
/*    */     //   #160	-> 2561
/*    */     //   #161	-> 2582
/*    */     //   #162	-> 2599
/*    */     //   #163	-> 2632
/*    */     //   #164	-> 2644
/*    */     //   #165	-> 2652
/*    */     //   #166	-> 2717
/*    */     //   #167	-> 2724
/*    */     //   #168	-> 2791
/*    */     //   #169	-> 2798 } private void qQ(int paramInt1, wQ paramwQ, String paramString, Xv0 paramXv0, int paramInt2) { // Byte code:
/*    */     //   0: aload_0
/*    */     //   1: getfield YG0 : Lf/js;
/*    */     //   4: dup
/*    */     //   5: dup2
/*    */     //   6: astore_0
/*    */     //   7: invokevirtual getClass : ()Ljava/lang/Class;
/*    */     //   10: pop
/*    */     //   11: new f/EW
/*    */     //   14: dup
/*    */     //   15: astore #6
/*    */     //   17: iload_1
/*    */     //   18: aload_2
/*    */     //   19: aload_3
/*    */     //   20: aload #4
/*    */     //   22: iload #5
/*    */     //   24: invokespecial <init> : (ILf/wQ;Ljava/lang/String;Lf/Xv0;I)V
/*    */     //   27: getfield tr0 : Ljava/util/ArrayList;
/*    */     //   30: aload #6
/*    */     //   32: invokevirtual add : (Ljava/lang/Object;)Z
/*    */     //   35: pop
/*    */     //   36: ldc_w f/EW
/*    */     //   39: astore_1
/*    */     //   40: getfield Li0 : Lf/d10;
/*    */     //   43: dup
/*    */     //   44: astore_2
/*    */     //   45: ifnull -> 112
/*    */     //   48: aload_0
/*    */     //   49: aload_2
/*    */     //   50: invokevirtual Jv0 : ()[Ljava/lang/Object;
/*    */     //   53: checkcast [Lf/JG0;
/*    */     //   56: astore_2
/*    */     //   57: iconst_0
/*    */     //   58: istore_3
/*    */     //   59: getfield Li0 : Lf/d10;
/*    */     //   62: getfield Z8 : I
/*    */     //   65: istore #4
/*    */     //   67: iload_3
/*    */     //   68: iload #4
/*    */     //   70: if_icmpge -> 105
/*    */     //   73: aload_2
/*    */     //   74: iload_3
/*    */     //   75: aaload
/*    */     //   76: invokevirtual getClass : ()Ljava/lang/Class;
/*    */     //   79: aload_1
/*    */     //   80: invokevirtual isAssignableFrom : (Ljava/lang/Class;)Z
/*    */     //   83: ifeq -> 99
/*    */     //   86: aload_2
/*    */     //   87: iload_3
/*    */     //   88: aload_0
/*    */     //   89: getfield Li0 : Lf/d10;
/*    */     //   92: invokevirtual At0 : ()V
/*    */     //   95: aaload
/*    */     //   96: goto -> 113
/*    */     //   99: iinc #3, 1
/*    */     //   102: goto -> 67
/*    */     //   105: aload_0
/*    */     //   106: getfield Li0 : Lf/d10;
/*    */     //   109: invokevirtual At0 : ()V
/*    */     //   112: aconst_null
/*    */     //   113: ifnonnull -> 133
/*    */     //   116: aload_0
/*    */     //   117: dup
/*    */     //   118: dup
/*    */     //   119: invokevirtual Ub : ()I
/*    */     //   122: aload #6
/*    */     //   124: swap
/*    */     //   125: invokevirtual si : (Lf/JG0;I)V
/*    */     //   128: aload #6
/*    */     //   130: invokevirtual Af : (Lf/JG0;)V
/*    */     //   133: return
/*    */     // Line number table:
/*    */     //   Java source line number -> byte code offset
/*    */     //   #1	-> 11
/*    */     //   #2	-> 36
/*    */     //   #3	-> 40
/*    */     //   #4	-> 119
/*    */     //   #5	-> 130 } private void BV(String paramString) { this.YG0.DJ(paramString, null); } private void Je0(String paramString) { this.YG0.Pu(-1, paramString); } public final void ps0(short paramShort1, int paramInt1, int paramInt2, short paramShort2, byte paramByte1, byte paramByte2, boolean paramBoolean) { // Byte code:
/*    */     //   0: aload_0
/*    */     //   1: invokevirtual NR : ()Z
/*    */     //   4: ifne -> 2426
/*    */     //   7: aload_0
/*    */     //   8: getfield tN : Z
/*    */     //   11: ifne -> 2426
/*    */     //   14: getstatic f/km.kH0 : Lf/Qz0;
/*    */     //   17: invokevirtual xy0 : ()Z
/*    */     //   20: ifne -> 2426
/*    */     //   23: iload #7
/*    */     //   25: ifne -> 44
/*    */     //   28: aload_0
/*    */     //   29: getfield zl : Lf/Z;
/*    */     //   32: getfield CB0 : Lf/e2;
/*    */     //   35: invokevirtual Po0 : ()Z
/*    */     //   38: ifne -> 44
/*    */     //   41: goto -> 2426
/*    */     //   44: iload_1
/*    */     //   45: sipush #372
/*    */     //   48: if_icmpne -> 228
/*    */     //   51: iload_3
/*    */     //   52: iconst_1
/*    */     //   53: if_icmplt -> 87
/*    */     //   56: iload #4
/*    */     //   58: iconst_1
/*    */     //   59: if_icmpge -> 65
/*    */     //   62: goto -> 87
/*    */     //   65: aload_0
/*    */     //   66: getfield e20 : Lf/c4;
/*    */     //   69: new f/eE0
/*    */     //   72: dup
/*    */     //   73: iload_1
/*    */     //   74: iload_3
/*    */     //   75: iload #4
/*    */     //   77: iload #5
/*    */     //   79: iconst_0
/*    */     //   80: invokespecial <init> : (SISBB)V
/*    */     //   83: invokevirtual W3 : (Lf/Bi;)V
/*    */     //   86: return
/*    */     //   87: aload_0
/*    */     //   88: getstatic f/yM.r4 : Lf/yM;
/*    */     //   91: pop
/*    */     //   92: getfield Fe : [Lf/zr0;
/*    */     //   95: iconst_1
/*    */     //   96: aaload
/*    */     //   97: invokevirtual ro0 : ()[Lf/Y;
/*    */     //   100: dup
/*    */     //   101: astore #7
/*    */     //   103: arraylength
/*    */     //   104: istore #8
/*    */     //   106: iconst_0
/*    */     //   107: istore #9
/*    */     //   109: iload #9
/*    */     //   111: iload #8
/*    */     //   113: if_icmpge -> 228
/*    */     //   116: aload #7
/*    */     //   118: iload #9
/*    */     //   120: aaload
/*    */     //   121: dup
/*    */     //   122: astore #10
/*    */     //   124: getfield Lh : Lf/nH0;
/*    */     //   127: dup
/*    */     //   128: astore #11
/*    */     //   130: getfield Wy : I
/*    */     //   133: dup
/*    */     //   134: istore #12
/*    */     //   136: iload_3
/*    */     //   137: if_icmpne -> 222
/*    */     //   140: aload #11
/*    */     //   142: getfield Sf0 : S
/*    */     //   145: iconst_1
/*    */     //   146: if_icmpne -> 174
/*    */     //   149: aload_0
/*    */     //   150: getfield e20 : Lf/c4;
/*    */     //   153: new f/eE0
/*    */     //   156: dup
/*    */     //   157: sipush #372
/*    */     //   160: iload #12
/*    */     //   162: iconst_1
/*    */     //   163: iconst_m1
/*    */     //   164: iconst_0
/*    */     //   165: invokespecial <init> : (SISBB)V
/*    */     //   168: invokevirtual W3 : (Lf/Bi;)V
/*    */     //   171: goto -> 221
/*    */     //   174: aload_0
/*    */     //   175: getfield YG0 : Lf/js;
/*    */     //   178: getfield MH0 : Lf/pA;
/*    */     //   181: dup
/*    */     //   182: astore_0
/*    */     //   183: getfield lPt8 : Lf/wX;
/*    */     //   186: dup
/*    */     //   187: astore_1
/*    */     //   188: ifnull -> 201
/*    */     //   191: aload_0
/*    */     //   192: aload_1
/*    */     //   193: invokevirtual ra0 : ()Z
/*    */     //   196: pop
/*    */     //   197: aconst_null
/*    */     //   198: putfield lPt8 : Lf/wX;
/*    */     //   201: aload_0
/*    */     //   202: dup
/*    */     //   203: new f/wX
/*    */     //   206: dup
/*    */     //   207: astore_0
/*    */     //   208: aload #10
/*    */     //   210: invokespecial <init> : (Lf/Y;)V
/*    */     //   213: aload_0
/*    */     //   214: putfield lPt8 : Lf/wX;
/*    */     //   217: aload_0
/*    */     //   218: invokevirtual J8 : (Lf/JG0;)V
/*    */     //   221: return
/*    */     //   222: iinc #9, 1
/*    */     //   225: goto -> 109
/*    */     //   228: aload_0
/*    */     //   229: getstatic f/km.u4 : Lf/R8;
/*    */     //   232: getfield jG0 : Lf/yM;
/*    */     //   235: dup
/*    */     //   236: astore #7
/*    */     //   238: invokevirtual gN : (Lf/yM;)Lf/zr0;
/*    */     //   241: iconst_m1
/*    */     //   242: iload_1
/*    */     //   243: iconst_1
/*    */     //   244: invokevirtual vH0 : (BSS)Z
/*    */     //   247: ifne -> 263
/*    */     //   250: getstatic f/km.kH0 : Lf/Qz0;
/*    */     //   253: sipush #6003
/*    */     //   256: invokestatic OH0 : (I)Ljava/lang/String;
/*    */     //   259: invokevirtual jN : (Ljava/lang/String;)V
/*    */     //   262: return
/*    */     //   263: iload_1
/*    */     //   264: dup
/*    */     //   265: invokestatic l90 : (S)S
/*    */     //   268: istore #8
/*    */     //   270: sipush #361
/*    */     //   273: if_icmpeq -> 2403
/*    */     //   276: iload_1
/*    */     //   277: sipush #1181
/*    */     //   280: if_icmpeq -> 2403
/*    */     //   283: iload_1
/*    */     //   284: sipush #5442
/*    */     //   287: if_icmpeq -> 2403
/*    */     //   290: iload_1
/*    */     //   291: sipush #8442
/*    */     //   294: if_icmpeq -> 2403
/*    */     //   297: iload_1
/*    */     //   298: sipush #9442
/*    */     //   301: if_icmpne -> 307
/*    */     //   304: goto -> 2403
/*    */     //   307: iload_1
/*    */     //   308: sipush #260
/*    */     //   311: if_icmpeq -> 2365
/*    */     //   314: iload_1
/*    */     //   315: sipush #8444
/*    */     //   318: if_icmpne -> 324
/*    */     //   321: goto -> 2365
/*    */     //   324: iload #8
/*    */     //   326: sipush #1001
/*    */     //   329: if_icmpne -> 378
/*    */     //   332: aload_0
/*    */     //   333: getfield YG0 : Lf/js;
/*    */     //   336: getfield MH0 : Lf/pA;
/*    */     //   339: dup
/*    */     //   340: astore_0
/*    */     //   341: iconst_0
/*    */     //   342: istore_2
/*    */     //   343: getfield SM : Lf/ld0;
/*    */     //   346: ifnull -> 356
/*    */     //   349: aload_0
/*    */     //   350: invokevirtual Sc : ()V
/*    */     //   353: goto -> 377
/*    */     //   356: aload_0
/*    */     //   357: dup
/*    */     //   358: new f/ld0
/*    */     //   361: dup
/*    */     //   362: astore_3
/*    */     //   363: aload_0
/*    */     //   364: iload_2
/*    */     //   365: iload_1
/*    */     //   366: invokespecial <init> : (Lf/pA;ZS)V
/*    */     //   369: aload_3
/*    */     //   370: putfield SM : Lf/ld0;
/*    */     //   373: aload_3
/*    */     //   374: invokevirtual J8 : (Lf/JG0;)V
/*    */     //   377: return
/*    */     //   378: iload #8
/*    */     //   380: sipush #1004
/*    */     //   383: if_icmpne -> 499
/*    */     //   386: getstatic f/km.u4 : Lf/R8;
/*    */     //   389: getfield Wn0 : Lf/mG;
/*    */     //   392: dup
/*    */     //   393: astore_2
/*    */     //   394: ifnonnull -> 413
/*    */     //   397: aload_0
/*    */     //   398: sipush #2616
/*    */     //   401: invokestatic OH0 : (I)Ljava/lang/String;
/*    */     //   404: getstatic f/ZY.ih : Lf/ZY;
/*    */     //   407: swap
/*    */     //   408: swap
/*    */     //   409: invokevirtual oD : (Ljava/lang/String;Lf/ZY;)V
/*    */     //   412: return
/*    */     //   413: aload_2
/*    */     //   414: getstatic f/km.a3 : Lf/vh0;
/*    */     //   417: getfield yD : I
/*    */     //   420: invokevirtual Ic0 : (I)Lf/jv;
/*    */     //   423: getstatic f/jv.Qq0 : Lf/jv;
/*    */     //   426: if_acmpeq -> 445
/*    */     //   429: aload_0
/*    */     //   430: sipush #2614
/*    */     //   433: invokestatic OH0 : (I)Ljava/lang/String;
/*    */     //   436: getstatic f/ZY.ih : Lf/ZY;
/*    */     //   439: swap
/*    */     //   440: swap
/*    */     //   441: invokevirtual oD : (Ljava/lang/String;Lf/ZY;)V
/*    */     //   444: return
/*    */     //   445: aload_0
/*    */     //   446: getfield YG0 : Lf/js;
/*    */     //   449: getfield MH0 : Lf/pA;
/*    */     //   452: dup
/*    */     //   453: astore_0
/*    */     //   454: iconst_0
/*    */     //   455: istore_2
/*    */     //   456: getfield hJ : Lf/rg;
/*    */     //   459: dup
/*    */     //   460: astore_3
/*    */     //   461: ifnull -> 477
/*    */     //   464: aload_0
/*    */     //   465: aload_3
/*    */     //   466: invokevirtual ra0 : ()Z
/*    */     //   469: pop
/*    */     //   470: aconst_null
/*    */     //   471: putfield hJ : Lf/rg;
/*    */     //   474: goto -> 498
/*    */     //   477: aload_0
/*    */     //   478: dup
/*    */     //   479: new f/rg
/*    */     //   482: dup
/*    */     //   483: astore_3
/*    */     //   484: aload_0
/*    */     //   485: iload_2
/*    */     //   486: iload_1
/*    */     //   487: invokespecial <init> : (Lf/pA;ZS)V
/*    */     //   490: aload_3
/*    */     //   491: putfield hJ : Lf/rg;
/*    */     //   494: aload_3
/*    */     //   495: invokevirtual J8 : (Lf/JG0;)V
/*    */     //   498: return
/*    */     //   499: iload #8
/*    */     //   501: sipush #1003
/*    */     //   504: if_icmpeq -> 2314
/*    */     //   507: iload #8
/*    */     //   509: sipush #1103
/*    */     //   512: if_icmpne -> 518
/*    */     //   515: goto -> 2314
/*    */     //   518: iload_1
/*    */     //   519: sipush #1050
/*    */     //   522: if_icmplt -> 577
/*    */     //   525: iload_1
/*    */     //   526: sipush #1065
/*    */     //   529: if_icmpgt -> 577
/*    */     //   532: iload_3
/*    */     //   533: iconst_1
/*    */     //   534: if_icmpge -> 577
/*    */     //   537: aload_0
/*    */     //   538: getfield Fe : [Lf/zr0;
/*    */     //   541: aload #7
/*    */     //   543: getfield Xv0 : B
/*    */     //   546: aaload
/*    */     //   547: iload_1
/*    */     //   548: invokevirtual C8 : (S)Lf/Y;
/*    */     //   551: dup
/*    */     //   552: astore #9
/*    */     //   554: ifnull -> 577
/*    */     //   557: aload_0
/*    */     //   558: getfield YG0 : Lf/js;
/*    */     //   561: getfield MH0 : Lf/pA;
/*    */     //   564: new f/aC0
/*    */     //   567: dup
/*    */     //   568: aload #9
/*    */     //   570: invokespecial <init> : (Lf/Y;)V
/*    */     //   573: invokevirtual J8 : (Lf/JG0;)V
/*    */     //   576: return
/*    */     //   577: iload_1
/*    */     //   578: sipush #1028
/*    */     //   581: if_icmpeq -> 591
/*    */     //   584: iload_1
/*    */     //   585: sipush #1029
/*    */     //   588: if_icmpne -> 687
/*    */     //   591: iload_3
/*    */     //   592: iconst_1
/*    */     //   593: if_icmplt -> 602
/*    */     //   596: iload #4
/*    */     //   598: iconst_1
/*    */     //   599: if_icmpge -> 687
/*    */     //   602: aload_0
/*    */     //   603: getfield Fe : [Lf/zr0;
/*    */     //   606: aload #7
/*    */     //   608: getfield Xv0 : B
/*    */     //   611: aaload
/*    */     //   612: iload_1
/*    */     //   613: invokevirtual C8 : (S)Lf/Y;
/*    */     //   616: dup
/*    */     //   617: astore #9
/*    */     //   619: ifnull -> 687
/*    */     //   622: aload_0
/*    */     //   623: getfield YG0 : Lf/js;
/*    */     //   626: getfield MH0 : Lf/pA;
/*    */     //   629: dup
/*    */     //   630: astore_0
/*    */     //   631: getfield fw : Lf/BH;
/*    */     //   634: dup
/*    */     //   635: astore_1
/*    */     //   636: ifnull -> 665
/*    */     //   639: aload_1
/*    */     //   640: getfield fc0 : Lf/wW;
/*    */     //   643: getstatic f/km.u4 : Lf/R8;
/*    */     //   646: getstatic f/yM.r4 : Lf/yM;
/*    */     //   649: pop
/*    */     //   650: getfield Fe : [Lf/zr0;
/*    */     //   653: iconst_1
/*    */     //   654: aaload
/*    */     //   655: iload_3
/*    */     //   656: invokevirtual u60 : (I)Lf/Y;
/*    */     //   659: invokevirtual Tm0 : (Lf/Y;)V
/*    */     //   662: goto -> 686
/*    */     //   665: aload_0
/*    */     //   666: dup
/*    */     //   667: new f/BH
/*    */     //   670: dup
/*    */     //   671: astore_0
/*    */     //   672: aload #9
/*    */     //   674: iload_3
/*    */     //   675: invokespecial <init> : (Lf/Y;I)V
/*    */     //   678: aload_0
/*    */     //   679: putfield fw : Lf/BH;
/*    */     //   682: aload_0
/*    */     //   683: invokevirtual J8 : (Lf/JG0;)V
/*    */     //   686: return
/*    */     //   687: iload_1
/*    */     //   688: sipush #1270
/*    */     //   691: if_icmpne -> 790
/*    */     //   694: iload_3
/*    */     //   695: iconst_1
/*    */     //   696: if_icmplt -> 705
/*    */     //   699: iload #4
/*    */     //   701: iconst_1
/*    */     //   702: if_icmpge -> 790
/*    */     //   705: aload_0
/*    */     //   706: getfield Fe : [Lf/zr0;
/*    */     //   709: aload #7
/*    */     //   711: getfield Xv0 : B
/*    */     //   714: aaload
/*    */     //   715: iload_1
/*    */     //   716: invokevirtual C8 : (S)Lf/Y;
/*    */     //   719: dup
/*    */     //   720: astore #9
/*    */     //   722: ifnull -> 790
/*    */     //   725: aload_0
/*    */     //   726: getfield YG0 : Lf/js;
/*    */     //   729: getfield MH0 : Lf/pA;
/*    */     //   732: dup
/*    */     //   733: astore_0
/*    */     //   734: getfield L60 : Lf/Ea0;
/*    */     //   737: dup
/*    */     //   738: astore_1
/*    */     //   739: ifnull -> 768
/*    */     //   742: aload_1
/*    */     //   743: getfield d50 : Lf/ju0;
/*    */     //   746: getstatic f/km.u4 : Lf/R8;
/*    */     //   749: getstatic f/yM.r4 : Lf/yM;
/*    */     //   752: pop
/*    */     //   753: getfield Fe : [Lf/zr0;
/*    */     //   756: iconst_1
/*    */     //   757: aaload
/*    */     //   758: iload_3
/*    */     //   759: invokevirtual u60 : (I)Lf/Y;
/*    */     //   762: invokevirtual Tm0 : (Lf/Y;)V
/*    */     //   765: goto -> 789
/*    */     //   768: aload_0
/*    */     //   769: dup
/*    */     //   770: new f/Ea0
/*    */     //   773: dup
/*    */     //   774: astore_0
/*    */     //   775: aload #9
/*    */     //   777: iload_3
/*    */     //   778: invokespecial <init> : (Lf/Y;I)V
/*    */     //   781: aload_0
/*    */     //   782: putfield L60 : Lf/Ea0;
/*    */     //   785: aload_0
/*    */     //   786: invokevirtual J8 : (Lf/JG0;)V
/*    */     //   789: return
/*    */     //   790: iload_1
/*    */     //   791: sipush #1535
/*    */     //   794: if_icmpne -> 939
/*    */     //   797: iload_3
/*    */     //   798: iconst_1
/*    */     //   799: if_icmpge -> 939
/*    */     //   802: aload_0
/*    */     //   803: getfield Fe : [Lf/zr0;
/*    */     //   806: aload #7
/*    */     //   808: getfield Xv0 : B
/*    */     //   811: aaload
/*    */     //   812: iload_1
/*    */     //   813: invokevirtual C8 : (S)Lf/Y;
/*    */     //   816: dup
/*    */     //   817: astore #9
/*    */     //   819: ifnull -> 939
/*    */     //   822: aload_0
/*    */     //   823: getfield z2 : Lf/Uc0;
/*    */     //   826: iload_3
/*    */     //   827: invokevirtual de0 : (I)Lf/j40;
/*    */     //   830: dup
/*    */     //   831: astore_1
/*    */     //   832: ifnull -> 938
/*    */     //   835: aload_0
/*    */     //   836: getfield YG0 : Lf/js;
/*    */     //   839: getfield MH0 : Lf/pA;
/*    */     //   842: dup
/*    */     //   843: astore_0
/*    */     //   844: aload_1
/*    */     //   845: getfield Zs : Lf/Q90;
/*    */     //   848: astore_1
/*    */     //   849: getfield vx0 : Lf/Bx0;
/*    */     //   852: dup
/*    */     //   853: astore_2
/*    */     //   854: ifnull -> 867
/*    */     //   857: aload_0
/*    */     //   858: aload_2
/*    */     //   859: invokevirtual ra0 : ()Z
/*    */     //   862: pop
/*    */     //   863: aconst_null
/*    */     //   864: putfield vx0 : Lf/Bx0;
/*    */     //   867: aload_0
/*    */     //   868: dup
/*    */     //   869: dup2
/*    */     //   870: new f/Bx0
/*    */     //   873: dup
/*    */     //   874: dup
/*    */     //   875: astore_2
/*    */     //   876: aload #9
/*    */     //   878: aload_1
/*    */     //   879: invokespecial <init> : (Lf/Y;Lf/Q90;)V
/*    */     //   882: putfield vx0 : Lf/Bx0;
/*    */     //   885: aload_2
/*    */     //   886: invokevirtual J8 : (Lf/JG0;)V
/*    */     //   889: getfield vx0 : Lf/Bx0;
/*    */     //   892: invokevirtual mM : ()V
/*    */     //   895: getfield vx0 : Lf/Bx0;
/*    */     //   898: getstatic f/km.wI0 : Lf/Pw;
/*    */     //   901: invokevirtual dG : ()I
/*    */     //   904: iconst_2
/*    */     //   905: idiv
/*    */     //   906: aload_0
/*    */     //   907: getfield vx0 : Lf/Bx0;
/*    */     //   910: getfield xY : I
/*    */     //   913: iconst_2
/*    */     //   914: idiv
/*    */     //   915: isub
/*    */     //   916: getstatic f/km.wI0 : Lf/Pw;
/*    */     //   919: invokevirtual k1 : ()I
/*    */     //   922: iconst_2
/*    */     //   923: idiv
/*    */     //   924: aload_0
/*    */     //   925: getfield vx0 : Lf/Bx0;
/*    */     //   928: getfield HC : I
/*    */     //   931: iconst_2
/*    */     //   932: idiv
/*    */     //   933: isub
/*    */     //   934: invokevirtual ME : (II)Z
/*    */     //   937: pop
/*    */     //   938: return
/*    */     //   939: getstatic f/Of.eH : Lf/Of;
/*    */     //   942: dup
/*    */     //   943: astore #9
/*    */     //   945: iload_1
/*    */     //   946: invokevirtual On0 : (S)Lf/LPT3;
/*    */     //   949: getfield z20 : B
/*    */     //   952: ifle -> 1092
/*    */     //   955: aload_0
/*    */     //   956: getfield Fe : [Lf/zr0;
/*    */     //   959: aload #7
/*    */     //   961: getfield Xv0 : B
/*    */     //   964: aaload
/*    */     //   965: iload_1
/*    */     //   966: invokevirtual C8 : (S)Lf/Y;
/*    */     //   969: dup
/*    */     //   970: astore #10
/*    */     //   972: ifnull -> 1092
/*    */     //   975: aload_0
/*    */     //   976: getfield z2 : Lf/Uc0;
/*    */     //   979: iload_3
/*    */     //   980: invokevirtual de0 : (I)Lf/j40;
/*    */     //   983: dup
/*    */     //   984: astore_1
/*    */     //   985: ifnull -> 1091
/*    */     //   988: aload_0
/*    */     //   989: getfield YG0 : Lf/js;
/*    */     //   992: getfield MH0 : Lf/pA;
/*    */     //   995: dup
/*    */     //   996: astore_0
/*    */     //   997: aload_1
/*    */     //   998: getfield Zs : Lf/Q90;
/*    */     //   1001: astore_1
/*    */     //   1002: getfield fJ0 : Lf/AH;
/*    */     //   1005: dup
/*    */     //   1006: astore_2
/*    */     //   1007: ifnull -> 1020
/*    */     //   1010: aload_0
/*    */     //   1011: aload_2
/*    */     //   1012: invokevirtual ra0 : ()Z
/*    */     //   1015: pop
/*    */     //   1016: aconst_null
/*    */     //   1017: putfield fJ0 : Lf/AH;
/*    */     //   1020: aload_0
/*    */     //   1021: dup
/*    */     //   1022: dup2
/*    */     //   1023: new f/AH
/*    */     //   1026: dup
/*    */     //   1027: dup
/*    */     //   1028: astore_2
/*    */     //   1029: aload #10
/*    */     //   1031: aload_1
/*    */     //   1032: invokespecial <init> : (Lf/Y;Lf/Q90;)V
/*    */     //   1035: putfield fJ0 : Lf/AH;
/*    */     //   1038: aload_2
/*    */     //   1039: invokevirtual J8 : (Lf/JG0;)V
/*    */     //   1042: getfield fJ0 : Lf/AH;
/*    */     //   1045: invokevirtual mM : ()V
/*    */     //   1048: getfield fJ0 : Lf/AH;
/*    */     //   1051: getstatic f/km.wI0 : Lf/Pw;
/*    */     //   1054: invokevirtual dG : ()I
/*    */     //   1057: iconst_2
/*    */     //   1058: idiv
/*    */     //   1059: aload_0
/*    */     //   1060: getfield fJ0 : Lf/AH;
/*    */     //   1063: getfield xY : I
/*    */     //   1066: iconst_2
/*    */     //   1067: idiv
/*    */     //   1068: isub
/*    */     //   1069: getstatic f/km.wI0 : Lf/Pw;
/*    */     //   1072: invokevirtual k1 : ()I
/*    */     //   1075: iconst_2
/*    */     //   1076: idiv
/*    */     //   1077: aload_0
/*    */     //   1078: getfield fJ0 : Lf/AH;
/*    */     //   1081: getfield HC : I
/*    */     //   1084: iconst_2
/*    */     //   1085: idiv
/*    */     //   1086: isub
/*    */     //   1087: invokevirtual ME : (II)Z
/*    */     //   1090: pop
/*    */     //   1091: return
/*    */     //   1092: iload_1
/*    */     //   1093: sipush #1422
/*    */     //   1096: if_icmpne -> 1158
/*    */     //   1099: aload_0
/*    */     //   1100: getfield Fe : [Lf/zr0;
/*    */     //   1103: aload #7
/*    */     //   1105: getfield Xv0 : B
/*    */     //   1108: aaload
/*    */     //   1109: iload_1
/*    */     //   1110: invokevirtual C8 : (S)Lf/Y;
/*    */     //   1113: dup
/*    */     //   1114: astore #10
/*    */     //   1116: ifnull -> 1158
/*    */     //   1119: aload_0
/*    */     //   1120: getfield YG0 : Lf/js;
/*    */     //   1123: getfield MH0 : Lf/pA;
/*    */     //   1126: dup
/*    */     //   1127: astore_0
/*    */     //   1128: getfield A0 : Lf/bZ;
/*    */     //   1131: ifnull -> 1137
/*    */     //   1134: goto -> 1157
/*    */     //   1137: aload_0
/*    */     //   1138: dup
/*    */     //   1139: new f/bZ
/*    */     //   1142: dup
/*    */     //   1143: astore_0
/*    */     //   1144: aload #10
/*    */     //   1146: invokespecial <init> : (Lf/Y;)V
/*    */     //   1149: aload_0
/*    */     //   1150: putfield A0 : Lf/bZ;
/*    */     //   1153: aload_0
/*    */     //   1154: invokevirtual J8 : (Lf/JG0;)V
/*    */     //   1157: return
/*    */     //   1158: iload #8
/*    */     //   1160: sipush #1018
/*    */     //   1163: if_icmpne -> 1273
/*    */     //   1166: iload #5
/*    */     //   1168: iconst_m1
/*    */     //   1169: if_icmpgt -> 1273
/*    */     //   1172: aload_0
/*    */     //   1173: getfield Fe : [Lf/zr0;
/*    */     //   1176: aload #7
/*    */     //   1178: getfield Xv0 : B
/*    */     //   1181: aaload
/*    */     //   1182: iload_1
/*    */     //   1183: invokevirtual C8 : (S)Lf/Y;
/*    */     //   1186: dup
/*    */     //   1187: astore #10
/*    */     //   1189: ifnull -> 1273
/*    */     //   1192: aload_0
/*    */     //   1193: getfield z2 : Lf/Uc0;
/*    */     //   1196: iload_3
/*    */     //   1197: invokevirtual de0 : (I)Lf/j40;
/*    */     //   1200: dup
/*    */     //   1201: astore_1
/*    */     //   1202: ifnull -> 1272
/*    */     //   1205: aload_0
/*    */     //   1206: getfield YG0 : Lf/js;
/*    */     //   1209: getfield MH0 : Lf/pA;
/*    */     //   1212: dup
/*    */     //   1213: astore_0
/*    */     //   1214: getfield Tq0 : Lf/qO;
/*    */     //   1217: ifnull -> 1223
/*    */     //   1220: goto -> 1272
/*    */     //   1223: aload_0
/*    */     //   1224: new f/qO
/*    */     //   1227: dup
/*    */     //   1228: dup
/*    */     //   1229: astore_2
/*    */     //   1230: aload #10
/*    */     //   1232: aload_1
/*    */     //   1233: invokespecial <init> : (Lf/Y;Lf/j40;)V
/*    */     //   1236: putfield Tq0 : Lf/qO;
/*    */     //   1239: aload_2
/*    */     //   1240: getfield qQ : Lf/G9;
/*    */     //   1243: ifnull -> 1250
/*    */     //   1246: iconst_1
/*    */     //   1247: goto -> 1251
/*    */     //   1250: iconst_0
/*    */     //   1251: ifeq -> 1262
/*    */     //   1254: aload_0
/*    */     //   1255: aload_2
/*    */     //   1256: invokevirtual J8 : (Lf/JG0;)V
/*    */     //   1259: goto -> 1272
/*    */     //   1262: aload_0
/*    */     //   1263: aload_2
/*    */     //   1264: invokevirtual ra0 : ()Z
/*    */     //   1267: pop
/*    */     //   1268: aconst_null
/*    */     //   1269: putfield Tq0 : Lf/qO;
/*    */     //   1272: return
/*    */     //   1273: iload #8
/*    */     //   1275: aload #9
/*    */     //   1277: iload_1
/*    */     //   1278: invokevirtual On0 : (S)Lf/LPT3;
/*    */     //   1281: astore #9
/*    */     //   1283: sipush #5548
/*    */     //   1286: if_icmplt -> 1431
/*    */     //   1289: iload #8
/*    */     //   1291: sipush #5564
/*    */     //   1294: if_icmpgt -> 1431
/*    */     //   1297: iload #4
/*    */     //   1299: iconst_1
/*    */     //   1300: if_icmpge -> 1431
/*    */     //   1303: aload_0
/*    */     //   1304: getstatic f/aq0.LI : Lf/aq0;
/*    */     //   1307: invokevirtual s40 : (Lf/aq0;)Lf/Uc0;
/*    */     //   1310: iload_3
/*    */     //   1311: invokevirtual de0 : (I)Lf/j40;
/*    */     //   1314: dup
/*    */     //   1315: astore #4
/*    */     //   1317: iload #8
/*    */     //   1319: invokestatic nt : (S)Lf/Ht0;
/*    */     //   1322: astore #5
/*    */     //   1324: ifnull -> 1430
/*    */     //   1327: aload #5
/*    */     //   1329: ifnonnull -> 1335
/*    */     //   1332: goto -> 1430
/*    */     //   1335: aload_0
/*    */     //   1336: iconst_5
/*    */     //   1337: anewarray java/lang/String
/*    */     //   1340: dup
/*    */     //   1341: astore #6
/*    */     //   1343: aload #5
/*    */     //   1345: aload #6
/*    */     //   1347: dup
/*    */     //   1348: aload #4
/*    */     //   1350: aload #6
/*    */     //   1352: aload #9
/*    */     //   1354: aload #6
/*    */     //   1356: bipush #40
/*    */     //   1358: invokestatic toString : (I)Ljava/lang/String;
/*    */     //   1361: iconst_0
/*    */     //   1362: swap
/*    */     //   1363: aastore
/*    */     //   1364: getfield Iu : I
/*    */     //   1367: invokestatic OH0 : (I)Ljava/lang/String;
/*    */     //   1370: iconst_1
/*    */     //   1371: swap
/*    */     //   1372: aastore
/*    */     //   1373: invokevirtual m : ()Ljava/lang/String;
/*    */     //   1376: iconst_2
/*    */     //   1377: swap
/*    */     //   1378: aastore
/*    */     //   1379: ldc_w 110237
/*    */     //   1382: invokestatic OH0 : (I)Ljava/lang/String;
/*    */     //   1385: iconst_3
/*    */     //   1386: swap
/*    */     //   1387: aastore
/*    */     //   1388: invokevirtual mn0 : ()Ljava/lang/String;
/*    */     //   1391: iconst_4
/*    */     //   1392: swap
/*    */     //   1393: aastore
/*    */     //   1394: sipush #2545
/*    */     //   1397: aload #6
/*    */     //   1399: invokestatic sB : (I[Ljava/lang/String;)Ljava/lang/String;
/*    */     //   1402: astore #4
/*    */     //   1404: getfield YG0 : Lf/js;
/*    */     //   1407: new f/h70
/*    */     //   1410: dup
/*    */     //   1411: aload #4
/*    */     //   1413: aload_0
/*    */     //   1414: iload_1
/*    */     //   1415: iload_2
/*    */     //   1416: iload_3
/*    */     //   1417: <illegal opcode> run : (Lf/R8;SII)Ljava/lang/Runnable;
/*    */     //   1422: aconst_null
/*    */     //   1423: invokespecial <init> : (Ljava/lang/String;Ljava/lang/Runnable;Lf/JG0;)V
/*    */     //   1426: invokevirtual uh : (Lf/h70;)V
/*    */     //   1429: return
/*    */     //   1430: return
/*    */     //   1431: iload_1
/*    */     //   1432: sipush #1540
/*    */     //   1435: if_icmpne -> 1446
/*    */     //   1438: getstatic f/pA.Dg0 : Lf/pA;
/*    */     //   1441: iconst_1
/*    */     //   1442: invokevirtual WW : (Z)V
/*    */     //   1445: return
/*    */     //   1446: aload #9
/*    */     //   1448: getfield c3 : Lf/wc;
/*    */     //   1451: dup
/*    */     //   1452: astore #8
/*    */     //   1454: ifnull -> 1890
/*    */     //   1457: aload_0
/*    */     //   1458: iconst_0
/*    */     //   1459: istore #6
/*    */     //   1461: aconst_null
/*    */     //   1462: astore #9
/*    */     //   1464: aconst_null
/*    */     //   1465: astore #10
/*    */     //   1467: getfield Fe : [Lf/zr0;
/*    */     //   1470: aload #7
/*    */     //   1472: getfield Xv0 : B
/*    */     //   1475: aaload
/*    */     //   1476: invokevirtual ro0 : ()[Lf/Y;
/*    */     //   1479: dup
/*    */     //   1480: astore #7
/*    */     //   1482: arraylength
/*    */     //   1483: istore #11
/*    */     //   1485: iconst_0
/*    */     //   1486: istore #12
/*    */     //   1488: iload #12
/*    */     //   1490: iload #11
/*    */     //   1492: if_icmpge -> 1549
/*    */     //   1495: aload #7
/*    */     //   1497: iload #12
/*    */     //   1499: aaload
/*    */     //   1500: dup
/*    */     //   1501: astore #13
/*    */     //   1503: getfield Lh : Lf/nH0;
/*    */     //   1506: dup
/*    */     //   1507: astore #14
/*    */     //   1509: getfield p1 : S
/*    */     //   1512: iload_1
/*    */     //   1513: if_icmpne -> 1543
/*    */     //   1516: aload #14
/*    */     //   1518: iinc #6, 1
/*    */     //   1521: getfield Wy : I
/*    */     //   1524: iload_2
/*    */     //   1525: if_icmpne -> 1539
/*    */     //   1528: aload #13
/*    */     //   1530: aload #13
/*    */     //   1532: astore #10
/*    */     //   1534: astore #9
/*    */     //   1536: goto -> 1543
/*    */     //   1539: aload #13
/*    */     //   1541: astore #10
/*    */     //   1543: iinc #12, 1
/*    */     //   1546: goto -> 1488
/*    */     //   1549: aload #9
/*    */     //   1551: ifnull -> 1560
/*    */     //   1554: aload #9
/*    */     //   1556: astore_2
/*    */     //   1557: goto -> 1563
/*    */     //   1560: aload #10
/*    */     //   1562: astore_2
/*    */     //   1563: aload_2
/*    */     //   1564: iconst_0
/*    */     //   1565: istore #7
/*    */     //   1567: iconst_0
/*    */     //   1568: istore #11
/*    */     //   1570: ifnull -> 1725
/*    */     //   1573: aload_0
/*    */     //   1574: getfield Qa : Lf/vh0;
/*    */     //   1577: getfield Ct : Lf/Jo;
/*    */     //   1580: dup
/*    */     //   1581: astore #12
/*    */     //   1583: ifnull -> 1725
/*    */     //   1586: aload #12
/*    */     //   1588: getfield lB0 : Lf/OE0;
/*    */     //   1591: aload #8
/*    */     //   1593: getfield Hl0 : Lf/Vp0;
/*    */     //   1596: invokevirtual JM : (Lf/Vp0;)S
/*    */     //   1599: aload #8
/*    */     //   1601: getfield Lk : S
/*    */     //   1604: if_icmpne -> 1641
/*    */     //   1607: aload #12
/*    */     //   1609: getfield lB0 : Lf/OE0;
/*    */     //   1612: aload #8
/*    */     //   1614: getfield Hl0 : Lf/Vp0;
/*    */     //   1617: invokevirtual F00 : (Lf/Vp0;)Lf/UX;
/*    */     //   1620: aload_2
/*    */     //   1621: getfield Lh : Lf/nH0;
/*    */     //   1624: getfield Nj : B
/*    */     //   1627: invokestatic Er : (B)Lf/UX;
/*    */     //   1630: if_acmpne -> 1641
/*    */     //   1633: iconst_1
/*    */     //   1634: istore_2
/*    */     //   1635: iload_2
/*    */     //   1636: istore #7
/*    */     //   1638: goto -> 1646
/*    */     //   1641: iconst_0
/*    */     //   1642: istore_2
/*    */     //   1643: iload_2
/*    */     //   1644: istore #7
/*    */     //   1646: aload #8
/*    */     //   1648: ldc_w 32768
/*    */     //   1651: invokevirtual l9 : (I)Z
/*    */     //   1654: ifeq -> 1725
/*    */     //   1657: aload #12
/*    */     //   1659: getfield lB0 : Lf/OE0;
/*    */     //   1662: aload #8
/*    */     //   1664: getfield Hl0 : Lf/Vp0;
/*    */     //   1667: invokevirtual JM : (Lf/Vp0;)S
/*    */     //   1670: aload #8
/*    */     //   1672: getfield Lk : S
/*    */     //   1675: if_icmpne -> 1682
/*    */     //   1678: iconst_1
/*    */     //   1679: goto -> 1683
/*    */     //   1682: iconst_0
/*    */     //   1683: iload #11
/*    */     //   1685: ior
/*    */     //   1686: istore_2
/*    */     //   1687: aload #12
/*    */     //   1689: getfield lB0 : Lf/OE0;
/*    */     //   1692: aload #8
/*    */     //   1694: getfield Hl0 : Lf/Vp0;
/*    */     //   1697: invokevirtual JM : (Lf/Vp0;)S
/*    */     //   1700: aload #8
/*    */     //   1702: getfield Lk : S
/*    */     //   1705: iconst_1
/*    */     //   1706: iadd
/*    */     //   1707: if_icmpne -> 1716
/*    */     //   1710: iconst_1
/*    */     //   1711: istore #11
/*    */     //   1713: goto -> 1719
/*    */     //   1716: iconst_0
/*    */     //   1717: istore #11
/*    */     //   1719: iload_2
/*    */     //   1720: iload #11
/*    */     //   1722: ior
/*    */     //   1723: istore #11
/*    */     //   1725: aload #9
/*    */     //   1727: ifnonnull -> 1736
/*    */     //   1730: iload #6
/*    */     //   1732: iconst_1
/*    */     //   1733: if_icmpgt -> 1742
/*    */     //   1736: iload #6
/*    */     //   1738: iconst_1
/*    */     //   1739: if_icmpge -> 1758
/*    */     //   1742: aload_0
/*    */     //   1743: getfield YG0 : Lf/js;
/*    */     //   1746: iconst_0
/*    */     //   1747: iconst_1
/*    */     //   1748: iconst_0
/*    */     //   1749: iconst_0
/*    */     //   1750: iconst_0
/*    */     //   1751: iconst_0
/*    */     //   1752: invokevirtual h4 : (IZZZZZ)V
/*    */     //   1755: goto -> 1889
/*    */     //   1758: aload #9
/*    */     //   1760: ifnonnull -> 1767
/*    */     //   1763: aload #10
/*    */     //   1765: astore #9
/*    */     //   1767: aload #9
/*    */     //   1769: ifnull -> 1889
/*    */     //   1772: iload #7
/*    */     //   1774: ifne -> 1805
/*    */     //   1777: aload_0
/*    */     //   1778: aload #9
/*    */     //   1780: getfield Bp0 : Lf/LPT3;
/*    */     //   1783: getfield c3 : Lf/wc;
/*    */     //   1786: getfield Hl0 : Lf/Vp0;
/*    */     //   1789: getfield gw0 : B
/*    */     //   1792: aload #9
/*    */     //   1794: getfield Lh : Lf/nH0;
/*    */     //   1797: getfield Wy : I
/*    */     //   1800: iconst_m1
/*    */     //   1801: iconst_0
/*    */     //   1802: invokevirtual OI : (BISZ)V
/*    */     //   1805: aload #8
/*    */     //   1807: getfield is : I
/*    */     //   1810: sipush #16384
/*    */     //   1813: iand
/*    */     //   1814: ifeq -> 1821
/*    */     //   1817: iconst_1
/*    */     //   1818: goto -> 1822
/*    */     //   1821: iconst_0
/*    */     //   1822: ifne -> 1868
/*    */     //   1825: aload #8
/*    */     //   1827: getfield Hl0 : Lf/Vp0;
/*    */     //   1830: getstatic f/Vp0.c6 : Lf/Vp0;
/*    */     //   1833: if_acmpne -> 1863
/*    */     //   1836: iload #7
/*    */     //   1838: ifne -> 1868
/*    */     //   1841: getstatic f/km.u4 : Lf/R8;
/*    */     //   1844: getfield Lz : Lf/fH0;
/*    */     //   1847: getfield Z60 : B
/*    */     //   1850: iconst_2
/*    */     //   1851: iand
/*    */     //   1852: ifeq -> 1859
/*    */     //   1855: iconst_1
/*    */     //   1856: goto -> 1860
/*    */     //   1859: iconst_0
/*    */     //   1860: ifeq -> 1868
/*    */     //   1863: iload #11
/*    */     //   1865: ifeq -> 1889
/*    */     //   1868: aload_0
/*    */     //   1869: getfield e20 : Lf/c4;
/*    */     //   1872: new f/eE0
/*    */     //   1875: dup
/*    */     //   1876: iload_1
/*    */     //   1877: iload_3
/*    */     //   1878: iload #4
/*    */     //   1880: iload #5
/*    */     //   1882: iconst_0
/*    */     //   1883: invokespecial <init> : (SISBB)V
/*    */     //   1886: invokevirtual W3 : (Lf/Bi;)V
/*    */     //   1889: return
/*    */     //   1890: iload_1
/*    */     //   1891: sipush #262
/*    */     //   1894: if_icmpeq -> 2028
/*    */     //   1897: iload_1
/*    */     //   1898: sipush #263
/*    */     //   1901: if_icmpeq -> 2028
/*    */     //   1904: iload_1
/*    */     //   1905: sipush #264
/*    */     //   1908: if_icmpeq -> 2028
/*    */     //   1911: iload_1
/*    */     //   1912: sipush #5445
/*    */     //   1915: if_icmpeq -> 2028
/*    */     //   1918: iload_1
/*    */     //   1919: sipush #5446
/*    */     //   1922: if_icmpeq -> 2028
/*    */     //   1925: iload_1
/*    */     //   1926: sipush #5447
/*    */     //   1929: if_icmpeq -> 2028
/*    */     //   1932: iload_1
/*    */     //   1933: sipush #8445
/*    */     //   1936: if_icmpeq -> 2028
/*    */     //   1939: iload_1
/*    */     //   1940: sipush #8446
/*    */     //   1943: if_icmpeq -> 2028
/*    */     //   1946: iload_1
/*    */     //   1947: sipush #8447
/*    */     //   1950: if_icmpeq -> 2028
/*    */     //   1953: iload_1
/*    */     //   1954: sipush #9445
/*    */     //   1957: if_icmpeq -> 2028
/*    */     //   1960: iload_1
/*    */     //   1961: sipush #9446
/*    */     //   1964: if_icmpeq -> 2028
/*    */     //   1967: iload_1
/*    */     //   1968: sipush #9447
/*    */     //   1971: if_icmpne -> 1977
/*    */     //   1974: goto -> 2028
/*    */     //   1977: aload #9
/*    */     //   1979: getfield EA : Z
/*    */     //   1982: ifeq -> 2005
/*    */     //   1985: iload #4
/*    */     //   1987: iconst_1
/*    */     //   1988: if_icmpge -> 2005
/*    */     //   1991: getstatic f/pA.Dg0 : Lf/pA;
/*    */     //   1994: aconst_null
/*    */     //   1995: iload_2
/*    */     //   1996: aconst_null
/*    */     //   1997: iload #5
/*    */     //   1999: invokevirtual Nr : (Lf/Bf;ILf/j40;B)V
/*    */     //   2002: goto -> 2027
/*    */     //   2005: aload_0
/*    */     //   2006: getfield e20 : Lf/c4;
/*    */     //   2009: new f/eE0
/*    */     //   2012: dup
/*    */     //   2013: iload_1
/*    */     //   2014: iload_3
/*    */     //   2015: iload #4
/*    */     //   2017: iload #5
/*    */     //   2019: iload #6
/*    */     //   2021: invokespecial <init> : (SISBB)V
/*    */     //   2024: invokevirtual W3 : (Lf/Bi;)V
/*    */     //   2027: return
/*    */     //   2028: getstatic f/km.MR : Lf/Gp0;
/*    */     //   2031: ifnull -> 2035
/*    */     //   2034: return
/*    */     //   2035: getstatic f/km.a3 : Lf/vh0;
/*    */     //   2038: getfield Ct : Lf/Jo;
/*    */     //   2041: dup
/*    */     //   2042: astore_2
/*    */     //   2043: ifnonnull -> 2047
/*    */     //   2046: return
/*    */     //   2047: aload_0
/*    */     //   2048: getfield Qa : Lf/vh0;
/*    */     //   2051: getfield Ct : Lf/Jo;
/*    */     //   2054: dup
/*    */     //   2055: astore #6
/*    */     //   2057: ifnonnull -> 2066
/*    */     //   2060: iconst_0
/*    */     //   2061: istore #6
/*    */     //   2063: goto -> 2075
/*    */     //   2066: aload #6
/*    */     //   2068: bipush #-128
/*    */     //   2070: invokevirtual so0 : (B)Z
/*    */     //   2073: istore #6
/*    */     //   2075: iload #6
/*    */     //   2077: ifeq -> 2091
/*    */     //   2080: aload_0
/*    */     //   2081: sipush #6002
/*    */     //   2084: invokestatic OH0 : (I)Ljava/lang/String;
/*    */     //   2087: invokevirtual Pq : (Ljava/lang/String;)V
/*    */     //   2090: return
/*    */     //   2091: aload_0
/*    */     //   2092: getfield Fe : [Lf/zr0;
/*    */     //   2095: aload #7
/*    */     //   2097: getfield Xv0 : B
/*    */     //   2100: aaload
/*    */     //   2101: getstatic f/km.a3 : Lf/vh0;
/*    */     //   2104: getfield eA : B
/*    */     //   2107: iload_1
/*    */     //   2108: iconst_1
/*    */     //   2109: invokevirtual vH0 : (BSS)Z
/*    */     //   2112: ifne -> 2131
/*    */     //   2115: aload_0
/*    */     //   2116: getfield YG0 : Lf/js;
/*    */     //   2119: sipush #6003
/*    */     //   2122: invokestatic OH0 : (I)Ljava/lang/String;
/*    */     //   2125: iconst_m1
/*    */     //   2126: swap
/*    */     //   2127: invokevirtual Pu : (ILjava/lang/String;)V
/*    */     //   2130: return
/*    */     //   2131: getstatic f/km.a3 : Lf/vh0;
/*    */     //   2134: aload_2
/*    */     //   2135: getfield HW : Lf/G5;
/*    */     //   2138: dup
/*    */     //   2139: dup
/*    */     //   2140: getfield FB : B
/*    */     //   2143: istore #6
/*    */     //   2145: getfield kD0 : B
/*    */     //   2148: istore #7
/*    */     //   2150: getfield vu0 : B
/*    */     //   2153: istore #8
/*    */     //   2155: iload #6
/*    */     //   2157: iload #7
/*    */     //   2159: iload #8
/*    */     //   2161: invokevirtual COm8 : (BBB)Lf/KI;
/*    */     //   2164: dup
/*    */     //   2165: astore #6
/*    */     //   2167: ifnonnull -> 2171
/*    */     //   2170: return
/*    */     //   2171: aload #6
/*    */     //   2173: aload_2
/*    */     //   2174: getfield HW : Lf/G5;
/*    */     //   2177: invokevirtual CJ0 : ()Lf/xr0;
/*    */     //   2180: dup
/*    */     //   2181: astore #6
/*    */     //   2183: aload_2
/*    */     //   2184: getfield HW : Lf/G5;
/*    */     //   2187: getfield g50 : B
/*    */     //   2190: iconst_1
/*    */     //   2191: invokevirtual COm3 : (Lf/xr0;BI)Lf/xr0;
/*    */     //   2194: dup
/*    */     //   2195: astore #7
/*    */     //   2197: ifnull -> 2286
/*    */     //   2200: aload #6
/*    */     //   2202: ifnull -> 2286
/*    */     //   2205: aload #6
/*    */     //   2207: aload_2
/*    */     //   2208: getfield HW : Lf/G5;
/*    */     //   2211: getfield Qf0 : B
/*    */     //   2214: invokevirtual a5 : (B)Z
/*    */     //   2217: ifeq -> 2286
/*    */     //   2220: aload #7
/*    */     //   2222: invokevirtual WS : ()Z
/*    */     //   2225: ifeq -> 2286
/*    */     //   2228: aload #6
/*    */     //   2230: invokevirtual i00 : ()F
/*    */     //   2233: aload #7
/*    */     //   2235: invokevirtual i00 : ()F
/*    */     //   2238: fsub
/*    */     //   2239: invokestatic abs : (F)F
/*    */     //   2242: fconst_1
/*    */     //   2243: fcmpl
/*    */     //   2244: ifle -> 2250
/*    */     //   2247: goto -> 2286
/*    */     //   2250: aload_0
/*    */     //   2251: getfield e20 : Lf/c4;
/*    */     //   2254: new f/eE0
/*    */     //   2257: dup
/*    */     //   2258: iload_1
/*    */     //   2259: iload_3
/*    */     //   2260: iload #4
/*    */     //   2262: iload #5
/*    */     //   2264: iconst_0
/*    */     //   2265: invokespecial <init> : (SISBB)V
/*    */     //   2268: invokevirtual W3 : (Lf/Bi;)V
/*    */     //   2271: getstatic f/km.wI0 : Lf/Pw;
/*    */     //   2274: new f/gC
/*    */     //   2277: dup
/*    */     //   2278: aload_2
/*    */     //   2279: invokespecial <init> : (Lf/Jo;)V
/*    */     //   2282: putfield HV : Lf/sH;
/*    */     //   2285: return
/*    */     //   2286: getstatic f/km.MR : Lf/Gp0;
/*    */     //   2289: ifnull -> 2303
/*    */     //   2292: aload_0
/*    */     //   2293: sipush #6002
/*    */     //   2296: invokestatic OH0 : (I)Ljava/lang/String;
/*    */     //   2299: invokevirtual Pq : (Ljava/lang/String;)V
/*    */     //   2302: return
/*    */     //   2303: aload_0
/*    */     //   2304: sipush #6002
/*    */     //   2307: invokestatic OH0 : (I)Ljava/lang/String;
/*    */     //   2310: invokevirtual Pq : (Ljava/lang/String;)V
/*    */     //   2313: return
/*    */     //   2314: iload_1
/*    */     //   2315: aload_0
/*    */     //   2316: getfield YG0 : Lf/js;
/*    */     //   2319: astore_1
/*    */     //   2320: iconst_1
/*    */     //   2321: istore_2
/*    */     //   2322: iconst_1
/*    */     //   2323: istore_3
/*    */     //   2324: iconst_0
/*    */     //   2325: istore #4
/*    */     //   2327: iconst_0
/*    */     //   2328: istore #5
/*    */     //   2330: sipush #1103
/*    */     //   2333: if_icmpne -> 2342
/*    */     //   2336: iconst_1
/*    */     //   2337: istore #6
/*    */     //   2339: goto -> 2345
/*    */     //   2342: iconst_0
/*    */     //   2343: istore #6
/*    */     //   2345: aload_1
/*    */     //   2346: aload_0
/*    */     //   2347: getfield Lz : Lf/fH0;
/*    */     //   2350: getfield OU : I
/*    */     //   2353: iload_2
/*    */     //   2354: iload_3
/*    */     //   2355: iload #4
/*    */     //   2357: iload #5
/*    */     //   2359: iload #6
/*    */     //   2361: invokevirtual h4 : (IZZZZZ)V
/*    */     //   2364: return
/*    */     //   2365: aload_0
/*    */     //   2366: new java/lang/StringBuilder
/*    */     //   2369: dup
/*    */     //   2370: aload_0
/*    */     //   2371: swap
/*    */     //   2372: invokespecial <init> : ()V
/*    */     //   2375: getfield Lz : Lf/fH0;
/*    */     //   2378: getfield aY : S
/*    */     //   2381: invokevirtual append : (I)Ljava/lang/StringBuilder;
/*    */     //   2384: ldc ''
/*    */     //   2386: invokevirtual append : (Ljava/lang/String;)Ljava/lang/StringBuilder;
/*    */     //   2389: invokevirtual toString : ()Ljava/lang/String;
/*    */     //   2392: sipush #6042
/*    */     //   2395: swap
/*    */     //   2396: invokestatic Go : (ILjava/lang/String;)Ljava/lang/String;
/*    */     //   2399: invokevirtual Pq : (Ljava/lang/String;)V
/*    */     //   2402: return
/*    */     //   2403: aload_0
/*    */     //   2404: iconst_1
/*    */     //   2405: istore_0
/*    */     //   2406: aconst_null
/*    */     //   2407: astore_1
/*    */     //   2408: getfield YG0 : Lf/js;
/*    */     //   2411: getfield MH0 : Lf/pA;
/*    */     //   2414: dup
/*    */     //   2415: astore_2
/*    */     //   2416: ifnull -> 2425
/*    */     //   2419: aload_2
/*    */     //   2420: iload_0
/*    */     //   2421: aload_1
/*    */     //   2422: invokevirtual U10 : (ZLf/R2;)V
/*    */     //   2425: return
/*    */     //   2426: return
/*    */     // Line number table:
/*    */     //   Java source line number -> byte code offset
/*    */     //   #1	-> 8
/*    */     //   #2	-> 14
/*    */     //   #3	-> 32
/*    */     //   #4	-> 35
/*    */     //   #5	-> 80
/*    */     //   #6	-> 83
/*    */     //   #7	-> 92
/*    */     //   #8	-> 96
/*    */     //   #9	-> 97
/*    */     //   #10	-> 124
/*    */     //   #11	-> 130
/*    */     //   #12	-> 142
/*    */     //   #13	-> 150
/*    */     //   #14	-> 165
/*    */     //   #15	-> 168
/*    */     //   #16	-> 178
/*    */     //   #17	-> 183
/*    */     //   #18	-> 193
/*    */     //   #19	-> 203
/*    */     //   #20	-> 229
/*    */     //   #21	-> 232
/*    */     //   #22	-> 238
/*    */     //   #23	-> 244
/*    */     //   #24	-> 250
/*    */     //   #25	-> 336
/*    */     //   #26	-> 343
/*    */     //   #27	-> 350
/*    */     //   #28	-> 386
/*    */     //   #29	-> 389
/*    */     //   #30	-> 401
/*    */     //   #31	-> 417
/*    */     //   #32	-> 420
/*    */     //   #33	-> 449
/*    */     //   #34	-> 456
/*    */     //   #35	-> 466
/*    */     //   #36	-> 479
/*    */     //   #37	-> 538
/*    */     //   #38	-> 543
/*    */     //   #39	-> 546
/*    */     //   #40	-> 548
/*    */     //   #41	-> 561
/*    */     //   #42	-> 564
/*    */     //   #43	-> 603
/*    */     //   #44	-> 608
/*    */     //   #45	-> 611
/*    */     //   #46	-> 613
/*    */     //   #47	-> 626
/*    */     //   #48	-> 631
/*    */     //   #49	-> 640
/*    */     //   #50	-> 643
/*    */     //   #51	-> 650
/*    */     //   #52	-> 654
/*    */     //   #53	-> 656
/*    */     //   #54	-> 706
/*    */     //   #55	-> 711
/*    */     //   #56	-> 714
/*    */     //   #57	-> 716
/*    */     //   #58	-> 729
/*    */     //   #59	-> 734
/*    */     //   #60	-> 743
/*    */     //   #61	-> 746
/*    */     //   #62	-> 753
/*    */     //   #63	-> 757
/*    */     //   #64	-> 759
/*    */     //   #65	-> 803
/*    */     //   #66	-> 808
/*    */     //   #67	-> 811
/*    */     //   #68	-> 813
/*    */     //   #69	-> 823
/*    */     //   #70	-> 827
/*    */     //   #71	-> 839
/*    */     //   #72	-> 845
/*    */     //   #73	-> 849
/*    */     //   #74	-> 859
/*    */     //   #75	-> 870
/*    */     //   #76	-> 910
/*    */     //   #77	-> 914
/*    */     //   #78	-> 928
/*    */     //   #79	-> 932
/*    */     //   #80	-> 934
/*    */     //   #81	-> 939
/*    */     //   #82	-> 946
/*    */     //   #83	-> 949
/*    */     //   #84	-> 956
/*    */     //   #85	-> 961
/*    */     //   #86	-> 964
/*    */     //   #87	-> 966
/*    */     //   #88	-> 976
/*    */     //   #89	-> 980
/*    */     //   #90	-> 992
/*    */     //   #91	-> 998
/*    */     //   #92	-> 1002
/*    */     //   #93	-> 1012
/*    */     //   #94	-> 1023
/*    */     //   #95	-> 1063
/*    */     //   #96	-> 1067
/*    */     //   #97	-> 1081
/*    */     //   #98	-> 1085
/*    */     //   #99	-> 1087
/*    */     //   #100	-> 1100
/*    */     //   #101	-> 1105
/*    */     //   #102	-> 1108
/*    */     //   #103	-> 1110
/*    */     //   #104	-> 1123
/*    */     //   #105	-> 1128
/*    */     //   #106	-> 1139
/*    */     //   #107	-> 1173
/*    */     //   #108	-> 1178
/*    */     //   #109	-> 1181
/*    */     //   #110	-> 1183
/*    */     //   #111	-> 1193
/*    */     //   #112	-> 1197
/*    */     //   #113	-> 1209
/*    */     //   #114	-> 1214
/*    */     //   #115	-> 1224
/*    */     //   #116	-> 1240
/*    */     //   #117	-> 1256
/*    */     //   #118	-> 1264
/*    */     //   #119	-> 1278
/*    */     //   #120	-> 1364
/*    */     //   #121	-> 1372
/*    */     //   #122	-> 1438
/*    */     //   #123	-> 1442
/*    */     //   #124	-> 1448
/*    */     //   #125	-> 1467
/*    */     //   #126	-> 1472
/*    */     //   #127	-> 1475
/*    */     //   #128	-> 1476
/*    */     //   #129	-> 1503
/*    */     //   #130	-> 1509
/*    */     //   #131	-> 1521
/*    */     //   #132	-> 1574
/*    */     //   #133	-> 1577
/*    */     //   #134	-> 1588
/*    */     //   #135	-> 1593
/*    */     //   #136	-> 1596
/*    */     //   #137	-> 1601
/*    */     //   #138	-> 1609
/*    */     //   #139	-> 1614
/*    */     //   #140	-> 1617
/*    */     //   #141	-> 1621
/*    */     //   #142	-> 1624
/*    */     //   #143	-> 1627
/*    */     //   #144	-> 1659
/*    */     //   #145	-> 1664
/*    */     //   #146	-> 1667
/*    */     //   #147	-> 1672
/*    */     //   #148	-> 1689
/*    */     //   #149	-> 1694
/*    */     //   #150	-> 1697
/*    */     //   #151	-> 1702
/*    */     //   #152	-> 1743
/*    */     //   #153	-> 1780
/*    */     //   #154	-> 1783
/*    */     //   #155	-> 1786
/*    */     //   #156	-> 1789
/*    */     //   #157	-> 1794
/*    */     //   #158	-> 1797
/*    */     //   #159	-> 1802
/*    */     //   #160	-> 1807
/*    */     //   #161	-> 1827
/*    */     //   #162	-> 1830
/*    */     //   #163	-> 1844
/*    */     //   #164	-> 1847
/*    */     //   #165	-> 1869
/*    */     //   #166	-> 1883
/*    */     //   #167	-> 1886
/*    */     //   #168	-> 1979
/*    */     //   #169	-> 1991
/*    */     //   #170	-> 1999
/*    */     //   #171	-> 2038
/*    */     //   #172	-> 2048
/*    */     //   #173	-> 2051
/*    */     //   #174	-> 2070
/*    */     //   #175	-> 2084
/*    */     //   #176	-> 2092
/*    */     //   #177	-> 2097
/*    */     //   #178	-> 2100
/*    */     //   #179	-> 2101
/*    */     //   #180	-> 2104
/*    */     //   #181	-> 2109
/*    */     //   #182	-> 2127
/*    */     //   #183	-> 2131
/*    */     //   #184	-> 2135
/*    */     //   #185	-> 2140
/*    */     //   #186	-> 2145
/*    */     //   #187	-> 2150
/*    */     //   #188	-> 2161
/*    */     //   #189	-> 2174
/*    */     //   #190	-> 2177
/*    */     //   #191	-> 2184
/*    */     //   #192	-> 2187
/*    */     //   #193	-> 2191
/*    */     //   #194	-> 2208
/*    */     //   #195	-> 2211
/*    */     //   #196	-> 2214
/*    */     //   #197	-> 2265
/*    */     //   #198	-> 2268
/*    */     //   #199	-> 2282
/*    */     //   #200	-> 2286
/*    */     //   #201	-> 2350
/*    */     //   #202	-> 2361
/*    */     //   #203	-> 2375
/*    */     //   #204	-> 2378
/*    */     //   #205	-> 2381
/*    */     //   #206	-> 2408
/*    */     //   #207	-> 2411
/*    */     //   #208	-> 2422 } public final void Pq(String paramString) { // Byte code:
/*    */     //   0: aload_0
/*    */     //   1: getstatic f/UB0.Kg0 : Lf/Q50;
/*    */     //   4: aload_0
/*    */     //   5: aload_1
/*    */     //   6: <illegal opcode> run : (Lf/R8;Ljava/lang/String;)Ljava/lang/Runnable;
/*    */     //   11: invokevirtual fN : (Ljava/lang/Runnable;)V
/*    */     //   14: new f/Mv0
/*    */     //   17: dup
/*    */     //   18: getstatic f/ZY.ih : Lf/ZY;
/*    */     //   21: iconst_0
/*    */     //   22: ldc ''
/*    */     //   24: aconst_null
/*    */     //   25: iconst_0
/*    */     //   26: aload_1
/*    */     //   27: invokespecial <init> : (Lf/ZY;ILjava/lang/String;Lf/Xv0;BLjava/lang/String;)V
/*    */     //   30: invokevirtual Sg : (Lf/Mv0;)Z
/*    */     //   33: pop
/*    */     //   34: return
/*    */     // Line number table:
/*    */     //   Java source line number -> byte code offset
/*  1 */     //   #1	-> 14 } private void qq0(Mv0 paramMv0) { pA pA; if ((pA = this.YG0.MH0) == null || pA
/*  2 */       .TF == null) return;  if (pA != null && 
/*  3 */       !pA.dP && paramMv0
/*  4 */       .LT > 0 && paramMv0
/*  5 */       .interface == 
/*  6 */       ZY.Nd0) pA.wI0(true);  if (paramMv0
/*  7 */       .r6 > 0 && 
/*    */ 
/*    */       
/* 10 */       !h1.Jx0().contains(paramMv0.RA)) {
/* 11 */       int i = paramMv0.r6;
/*    */       
/* 13 */       km.si0.uB(i, paramMv0.IQ);
/* 14 */     }  this.YG0.MH0
/* 15 */       .TF
/* 16 */       .Ew0(paramMv0, false); } public final void b00(String paramString) { // Byte code:
/*    */     //   0: getstatic f/UB0.Kg0 : Lf/Q50;
/*    */     //   3: aload_0
/*    */     //   4: aload_1
/*    */     //   5: <illegal opcode> run : (Lf/R8;Ljava/lang/String;)Ljava/lang/Runnable;
/*    */     //   10: invokevirtual fN : (Ljava/lang/Runnable;)V
/*    */     //   13: return } public final void jH0(int paramInt1, wQ paramwQ, String paramString, Xv0 paramXv0, int paramInt2) { // Byte code:
/*    */     //   0: getstatic f/UB0.Kg0 : Lf/Q50;
/*    */     //   3: aload_0
/*    */     //   4: iload_1
/*    */     //   5: aload_2
/*    */     //   6: aload_3
/*    */     //   7: aload #4
/*    */     //   9: iload #5
/*    */     //   11: <illegal opcode> run : (Lf/R8;ILf/wQ;Ljava/lang/String;Lf/Xv0;I)Ljava/lang/Runnable;
/*    */     //   16: invokevirtual fN : (Ljava/lang/Runnable;)V
/*    */     //   19: return } public final boolean Sg(Mv0 paramMv0) { // Byte code:
/*    */     //   0: aload_1
/*    */     //   1: getfield r6 : I
/*    */     //   4: dup
/*    */     //   5: istore_2
/*    */     //   6: ifle -> 30
/*    */     //   9: aload_0
/*    */     //   10: getfield qH0 : Lf/QK0;
/*    */     //   13: getfield aux : Ljava/util/HashMap;
/*    */     //   16: iload_2
/*    */     //   17: invokestatic valueOf : (I)Ljava/lang/Integer;
/*    */     //   20: invokevirtual containsKey : (Ljava/lang/Object;)Z
/*    */     //   23: ifeq -> 30
/*    */     //   26: iconst_0
/*    */     //   27: goto -> 38
/*    */     //   30: getstatic f/Jd.qp0 : Lf/Jd;
/*    */     //   33: aload_1
/*    */     //   34: invokevirtual vo : (Lf/Mv0;)V
/*    */     //   37: iconst_1
/*    */     //   38: ifne -> 43
/*    */     //   41: iconst_0
/*    */     //   42: ireturn
/*    */     //   43: aload_1
/*    */     //   44: getfield interface : Lf/ZY;
/*    */     //   47: getstatic f/ZY.Nd0 : Lf/ZY;
/*    */     //   50: if_acmpne -> 101
/*    */     //   53: aload_0
/*    */     //   54: getfield YG0 : Lf/js;
/*    */     //   57: getfield MH0 : Lf/pA;
/*    */     //   60: dup
/*    */     //   61: astore_2
/*    */     //   62: ifnull -> 101
/*    */     //   65: aload_2
/*    */     //   66: aload_1
/*    */     //   67: getfield mq : Ljava/lang/String;
/*    */     //   70: astore_2
/*    */     //   71: getfield zR : Ljava/util/HashMap;
/*    */     //   74: aload_2
/*    */     //   75: invokevirtual get : (Ljava/lang/Object;)Ljava/lang/Object;
/*    */     //   78: checkcast f/kC0
/*    */     //   81: dup
/*    */     //   82: astore_2
/*    */     //   83: ifnull -> 101
/*    */     //   86: getstatic f/UB0.Kg0 : Lf/Q50;
/*    */     //   89: new f/B0
/*    */     //   92: dup
/*    */     //   93: aload_2
/*    */     //   94: aload_1
/*    */     //   95: invokespecial <init> : (Lf/kC0;Lf/Mv0;)V
/*    */     //   98: invokevirtual fN : (Ljava/lang/Runnable;)V
/*    */     //   101: getstatic f/UB0.Kg0 : Lf/Q50;
/*    */     //   104: aload_0
/*    */     //   105: aload_1
/*    */     //   106: <illegal opcode> run : (Lf/R8;Lf/Mv0;)Ljava/lang/Runnable;
/*    */     //   111: invokevirtual fN : (Ljava/lang/Runnable;)V
/*    */     //   114: iconst_1
/*    */     //   115: ireturn
/*    */     // Line number table:
/*    */     //   Java source line number -> byte code offset
/*    */     //   #1	-> 1
/*    */     //   #2	-> 10
/*    */     //   #3	-> 13
/*    */     //   #4	-> 17
/*    */     //   #5	-> 30
/*    */     //   #6	-> 34
/*    */     //   #7	-> 44
/*    */     //   #8	-> 47
/*    */     //   #9	-> 57
/*    */     //   #10	-> 67
/*    */     //   #11	-> 71
/*    */     //   #12	-> 86
/* 16 */     //   #13	-> 101 } public final void ow() { pA pA; if ((pA = this.YG0.MH0) == null) return;  UB0.Kg0.fN(new g50(this)); } public final void Wp() { short[][][] arrayOfShort; int i; byte b; label101: for (i = (arrayOfShort = ro.H70).length, b = 0; b < i; ) { short[][] arrayOfShort1 = arrayOfShort[b]; zr0 zr0; byte b1; if ((zr0 = this.Fe[1]) != null && (b1 = km.a3.eA) >= 0 && b1 < arrayOfShort1.length) { short s; byte b2; short[] arrayOfShort2; for (s = 0, b2 = 0; b2 < (arrayOfShort2 = arrayOfShort1[b1]).length; ) { if (zr0.vH0(b1, arrayOfShort2[b2], (short)1)) { s = arrayOfShort1[b1][b2]; break; }  b2++; }  pA pA; xJ0 xJ0; if (s != 0 && (pA = this.YG0.MH0) != null && (xJ0 = pA.WH) != null) { boolean bool; b1 = 0; b2 = 0; while (b2 < arrayOfShort1.length) { short[] arrayOfShort3; for (byte b3 = 0; b3 < (arrayOfShort3 = arrayOfShort1[b2]).length; ) { bool = b1 | xJ0.Rj(arrayOfShort3[b3], s); b3++; }  b2 = (byte)(b2 + 1); }  if (!bool) { HashSet<Short> hashSet; this(); try { String[] arrayOfString; int j; byte b4; for (j = (arrayOfString = EC.uA.split(",")).length, b4 = 0; b4 < j; ) { hashSet.add(Short.valueOf(Short.parseShort(arrayOfString[b4]))); b4++; }  } catch (Exception exception) {} if (!hashSet.contains(Short.valueOf(s))) { byte b4; SE0[] arrayOfSE0; for (b4 = 0; b4 < (arrayOfSE0 = xJ0.sN).length; ) { if ((arrayOfSE0[b4]).hC0 == s) continue label101;  b4 = (byte)(b4 + 1); }  for (b4 = 0; b4 < (arrayOfSE0 = xJ0.sN).length && b4 < 6; ) { SE0 sE0; if ((sE0 = arrayOfSE0[b4]).hC0 < 1) { sE0.Kh(0, s, true); break; }  b4 = (byte)(b4 + 1); }  }  byte b3 = 0; while (b3 < arrayOfShort1.length) { short[] arrayOfShort3; for (byte b4 = 0; b4 < (arrayOfShort3 = arrayOfShort1[b3]).length; ) { StringBuffer stringBuffer; HashSet<Short> hashSet1; short s1 = arrayOfShort3[b4];
/* 17 */                 this(); try { String[] arrayOfString; int j; byte b5; for (j = (arrayOfString = EC.uA.split(",")).length, b5 = 0; b5 < j; ) { hashSet1.add(Short.valueOf(Short.parseShort(arrayOfString[b5]))); b5++; }  } catch (Exception exception) {} hashSet1
/* 18 */                   .add(Short.valueOf(s1)); this(); for (Iterator<Short> iterator = hashSet1.iterator(); iterator.hasNext(); ) { short s2 = ((Short)iterator.next()).shortValue(); if (stringBuffer.length() > 0) stringBuffer.append(",");  stringBuffer.append(s2); }  EC.uA = stringBuffer.toString(); EC.WD0 = true; b4++; }  b3 = (byte)(b3 + 1); }  }  }  }  b++; }  } public final void rG(byte paramByte, ky paramky, DO paramDO, Gu0 paramGu0) { EZ eZ; (eZ = EZ.G3).getClass(); if (paramky != null && paramDO != null) { Iterator iterator; Map map; if ((map = (Map)eZ.FC0.get(Byte.valueOf(paramByte))) == null) { EnumMap<Enum, Object> enumMap; Byte byte_ = Byte.valueOf(paramByte); this((Class)ky.class); ky[] arrayOfKy; byte b1, b2; for (arrayOfKy = ky.jG, b1 = 4, b2 = 0; b2 < b1; ) { EnumMap<Enum, Object> enumMap1; ky ky1 = arrayOfKy[b2]; this((Class)DO.class); enumMap.put(ky1, enumMap1); b2++; }  eZ.FC0.put(byte_, enumMap); map = enumMap; }  Gu0 gu0; if ((gu0 = (Gu0)((Map)map.get(paramky)).get(paramDO)) != null) { qw0 qw0; (qw0 = paramGu0.y70).getClass(); for (iterator = (new iL(qw0)).iterator(); ((DA0)iterator).hasNext(); ) { yG0 yG0 = (yG0)((Ke)iterator).q00(); gu0.y70.Vh0(yG0.Vo, yG0); }  } else { ((Map<DO, Gu0>)iterator.get(paramky)).put(paramDO, paramGu0); }  }  pA pA; if ((pA = this.YG0.MH0) == null) return;  VF0 vF0; if ((vF0 = this.L90) == null) return;  jd jd = this.cF; if ((paramByte == 0 || paramByte == this.RA) && (paramky == null || paramky == this.p2.Ud0) && (paramDO == null || paramDO == 
/* 19 */       this.p2
/* 20 */       .aU)) { if (this
/* 21 */         .Ou0 == null) { this
/* 22 */           .Ou0 = paramGu0; }
/* 23 */       else { qw0 qw0; (qw0 = paramGu0.y70)
/* 24 */           .getClass();
/*    */         
/* 26 */         for (Iterator iterator = (new iL(qw0)).iterator(); ((DA0)iterator).hasNext(); ) { yG0 yG0 = (yG0)((Ke)iterator).q00(); this.Ou0
/* 27 */             .y70
/*    */             
/* 29 */             .Vh0(yG0.Vo, yG0); }  }  this
/* 30 */         .UK.qs0(oc(false)); }
/*    */      }
/*    */ 
/*    */   
/*    */   public final void jr(Xv0 paramXv0, ZY paramZY, boolean paramBoolean1, boolean paramBoolean2) {
/*    */     h1.Bb = true;
/*    */     h1.qc = paramXv0.uz0;
/*    */     h1.Td();
/*    */     if (paramXv0 != null && !paramBoolean2) {
/*    */       char c = 'ា';
/*    */       Pq(Ml0.Go((paramBoolean1 ? 2 : 0) + c, paramXv0.w));
/*    */     } 
/*    */     if (paramZY != null && !paramBoolean2) {
/*    */       char c = 'ិ';
/*    */       Pq(Ml0.Go((paramBoolean1 ? 2 : 0) + c, Ml0.OH0(paramZY.UR)));
/*    */     } 
/*    */     pA pA;
/*    */     if ((pA = this.YG0.MH0) == null)
/*    */       return; 
/*    */     wu wu;
/*    */     if ((wu = this.TF) == null)
/*    */       return; 
/*    */     Xu("chatframe");
/*    */     cZ();
/*    */     Ui0(h1.JF);
/*    */     jw();
/*    */     if (paramZY != null)
/*    */       ec(paramZY); 
/*    */   }
/*    */   
/*    */   public final void W0(j40 paramj40) {
/*    */     pA pA;
/*    */     if ((pA = this.YG0.MH0) == null)
/*    */       return; 
/*    */     if (paramj40 != null && this.rB0.Z6(paramj40.Jg) != null)
/*    */       UB0.Kg0.fN(new Av0(this, paramj40)); 
/*    */   }
/*    */   
/*    */   public final void TD(qa0 paramqa0) {
/*    */     // Byte code:
/*    */     //   0: aload_0
/*    */     //   1: dup
/*    */     //   2: aconst_null
/*    */     //   3: putfield II : Lf/qa0;
/*    */     //   6: getfield YG0 : Lf/js;
/*    */     //   9: getfield MH0 : Lf/pA;
/*    */     //   12: dup
/*    */     //   13: astore_2
/*    */     //   14: ifnull -> 37
/*    */     //   17: aload_2
/*    */     //   18: getfield aV : Lf/ep;
/*    */     //   21: ifnull -> 37
/*    */     //   24: getstatic f/UB0.Kg0 : Lf/Q50;
/*    */     //   27: aload_0
/*    */     //   28: aload_1
/*    */     //   29: <illegal opcode> run : (Lf/R8;Lf/qa0;)Ljava/lang/Runnable;
/*    */     //   34: invokevirtual fN : (Ljava/lang/Runnable;)V
/*    */     //   37: return
/*    */     // Line number table:
/*    */     //   Java source line number -> byte code offset
/*    */     //   #1	-> 3
/*    */     //   #2	-> 6
/*    */     //   #3	-> 9
/*    */     //   #4	-> 18
/*    */     //   #5	-> 24
/*    */   }
/*    */   
/*    */   public final void tS(Kl0 paramKl0) {
/*    */     // Byte code:
/*    */     //   0: aload_1
/*    */     //   1: instanceof f/b8
/*    */     //   4: ifeq -> 138
/*    */     //   7: aload_1
/*    */     //   8: checkcast f/b8
/*    */     //   11: dup
/*    */     //   12: astore_1
/*    */     //   13: getfield AG0 : B
/*    */     //   16: ifeq -> 22
/*    */     //   19: goto -> 930
/*    */     //   22: aload_0
/*    */     //   23: aload_1
/*    */     //   24: dup
/*    */     //   25: dup
/*    */     //   26: getfield S3 : Ljava/lang/String;
/*    */     //   29: astore_0
/*    */     //   30: getfield ot : Ljava/lang/String;
/*    */     //   33: astore_1
/*    */     //   34: getfield gB : I
/*    */     //   37: istore_2
/*    */     //   38: getstatic f/eo0.AG0 : Ljava/util/ArrayList;
/*    */     //   41: pop
/*    */     //   42: new f/pk
/*    */     //   45: dup
/*    */     //   46: astore_3
/*    */     //   47: iload_2
/*    */     //   48: aload_3
/*    */     //   49: aload_1
/*    */     //   50: aload_3
/*    */     //   51: aload_0
/*    */     //   52: aload_3
/*    */     //   53: invokespecial <init> : ()V
/*    */     //   56: putfield Qk0 : Ljava/lang/String;
/*    */     //   59: putfield at : Ljava/lang/String;
/*    */     //   62: putfield Gs0 : I
/*    */     //   65: getstatic f/eo0.AG0 : Ljava/util/ArrayList;
/*    */     //   68: aload_3
/*    */     //   69: invokevirtual add : (Ljava/lang/Object;)Z
/*    */     //   72: pop
/*    */     //   73: getfield YG0 : Lf/js;
/*    */     //   76: getfield MH0 : Lf/pA;
/*    */     //   79: dup
/*    */     //   80: astore_0
/*    */     //   81: ifnull -> 930
/*    */     //   84: aload_0
/*    */     //   85: getfield OU : Lf/h2;
/*    */     //   88: getfield Ku0 : Lf/yb0;
/*    */     //   91: dup
/*    */     //   92: astore_0
/*    */     //   93: ifnonnull -> 101
/*    */     //   96: aconst_null
/*    */     //   97: astore_1
/*    */     //   98: goto -> 106
/*    */     //   101: aload_0
/*    */     //   102: getfield mg0 : Lf/eo0;
/*    */     //   105: astore_1
/*    */     //   106: aload_1
/*    */     //   107: ifnull -> 930
/*    */     //   110: aload_0
/*    */     //   111: ifnonnull -> 119
/*    */     //   114: aconst_null
/*    */     //   115: astore_0
/*    */     //   116: goto -> 124
/*    */     //   119: aload_0
/*    */     //   120: getfield mg0 : Lf/eo0;
/*    */     //   123: astore_0
/*    */     //   124: aload_0
/*    */     //   125: getfield dP : Lf/Wv0;
/*    */     //   128: aload_0
/*    */     //   129: getfield Vk : Lf/S90;
/*    */     //   132: invokevirtual jA : (Lf/NO;)V
/*    */     //   135: goto -> 930
/*    */     //   138: aload_1
/*    */     //   139: instanceof f/id0
/*    */     //   142: ifeq -> 550
/*    */     //   145: aload_1
/*    */     //   146: checkcast f/id0
/*    */     //   149: dup
/*    */     //   150: astore_1
/*    */     //   151: getfield h9 : I
/*    */     //   154: invokestatic yE : (I)I
/*    */     //   157: tableswitch default -> 200, 1 -> 455, 2 -> 363, 3 -> 200, 4 -> 247, 5 -> 237, 6 -> 226, 7 -> 203
/*    */     //   200: goto -> 930
/*    */     //   203: aload_0
/*    */     //   204: getfield YG0 : Lf/js;
/*    */     //   207: getfield MH0 : Lf/pA;
/*    */     //   210: getfield OU : Lf/h2;
/*    */     //   213: getfield GL : Lf/YE;
/*    */     //   216: aload_1
/*    */     //   217: getfield cN : [Lf/es;
/*    */     //   220: invokevirtual P80 : ([Lf/es;)V
/*    */     //   223: goto -> 930
/*    */     //   226: aload_0
/*    */     //   227: aload_1
/*    */     //   228: getfield ey : Ljava/lang/String;
/*    */     //   231: invokevirtual Pq : (Ljava/lang/String;)V
/*    */     //   234: goto -> 930
/*    */     //   237: aload_0
/*    */     //   238: ldc_w 'Insufficient privileges to use this command.'
/*    */     //   241: invokevirtual Pq : (Ljava/lang/String;)V
/*    */     //   244: goto -> 930
/*    */     //   247: aload_0
/*    */     //   248: getfield YG0 : Lf/js;
/*    */     //   251: getfield MH0 : Lf/pA;
/*    */     //   254: getfield OU : Lf/h2;
/*    */     //   257: getfield fk : Lf/lO;
/*    */     //   260: dup
/*    */     //   261: astore_0
/*    */     //   262: ifnull -> 930
/*    */     //   265: aload_0
/*    */     //   266: aload_1
/*    */     //   267: dup
/*    */     //   268: dup
/*    */     //   269: dup2
/*    */     //   270: dup2
/*    */     //   271: dup2
/*    */     //   272: dup2
/*    */     //   273: dup2
/*    */     //   274: getfield a00 : B
/*    */     //   277: istore_0
/*    */     //   278: getfield Xg0 : S
/*    */     //   281: istore_1
/*    */     //   282: getfield f70 : S
/*    */     //   285: istore_2
/*    */     //   286: getfield cOM1 : S
/*    */     //   289: istore_3
/*    */     //   290: getfield Dv0 : B
/*    */     //   293: istore #4
/*    */     //   295: getfield pH0 : I
/*    */     //   298: istore #5
/*    */     //   300: getfield Tv : Z
/*    */     //   303: istore #6
/*    */     //   305: getfield ZJ0 : Z
/*    */     //   308: istore #7
/*    */     //   310: getfield rx0 : B
/*    */     //   313: istore #8
/*    */     //   315: getfield u3 : B
/*    */     //   318: istore #9
/*    */     //   320: getfield IE : B
/*    */     //   323: istore #10
/*    */     //   325: getfield ic0 : [B
/*    */     //   328: astore #11
/*    */     //   330: getfield iN : [B
/*    */     //   333: astore #12
/*    */     //   335: iload_0
/*    */     //   336: iload_1
/*    */     //   337: iload_2
/*    */     //   338: iload_3
/*    */     //   339: iload #4
/*    */     //   341: iload #5
/*    */     //   343: iload #6
/*    */     //   345: iload #7
/*    */     //   347: iload #8
/*    */     //   349: iload #9
/*    */     //   351: iload #10
/*    */     //   353: aload #11
/*    */     //   355: aload #12
/*    */     //   357: invokevirtual HY : (BSSSBIZZBBB[B[B)V
/*    */     //   360: goto -> 930
/*    */     //   363: aload_1
/*    */     //   364: aload_0
/*    */     //   365: getfield YG0 : Lf/js;
/*    */     //   368: getfield MH0 : Lf/pA;
/*    */     //   371: getfield OU : Lf/h2;
/*    */     //   374: getfield SW : Lf/N1;
/*    */     //   377: getfield iy0 : Lf/K6;
/*    */     //   380: astore_0
/*    */     //   381: getfield Tz0 : I
/*    */     //   384: istore_1
/*    */     //   385: aload_0
/*    */     //   386: iconst_m1
/*    */     //   387: istore_2
/*    */     //   388: iconst_0
/*    */     //   389: istore_3
/*    */     //   390: getfield Fo0 : Ljava/util/ArrayList;
/*    */     //   393: invokevirtual iterator : ()Ljava/util/Iterator;
/*    */     //   396: astore #4
/*    */     //   398: aload #4
/*    */     //   400: invokeinterface hasNext : ()Z
/*    */     //   405: ifeq -> 433
/*    */     //   408: aload #4
/*    */     //   410: invokeinterface next : ()Ljava/lang/Object;
/*    */     //   415: checkcast f/Um0
/*    */     //   418: getfield xZ : I
/*    */     //   421: iload_1
/*    */     //   422: if_icmpne -> 427
/*    */     //   425: iload_3
/*    */     //   426: istore_2
/*    */     //   427: iinc #3, 1
/*    */     //   430: goto -> 398
/*    */     //   433: iload_2
/*    */     //   434: iflt -> 930
/*    */     //   437: getstatic f/UB0.Kg0 : Lf/Q50;
/*    */     //   440: new f/rd0
/*    */     //   443: dup
/*    */     //   444: aload_0
/*    */     //   445: iload_2
/*    */     //   446: invokespecial <init> : (Lf/K6;I)V
/*    */     //   449: invokevirtual fN : (Ljava/lang/Runnable;)V
/*    */     //   452: goto -> 930
/*    */     //   455: aload_0
/*    */     //   456: getfield YG0 : Lf/js;
/*    */     //   459: getfield MH0 : Lf/pA;
/*    */     //   462: getfield OU : Lf/h2;
/*    */     //   465: getfield SW : Lf/N1;
/*    */     //   468: getfield iy0 : Lf/K6;
/*    */     //   471: dup
/*    */     //   472: astore_0
/*    */     //   473: aload_1
/*    */     //   474: dup
/*    */     //   475: dup2
/*    */     //   476: getfield Tz0 : I
/*    */     //   479: istore_1
/*    */     //   480: getfield Bk0 : Ljava/lang/String;
/*    */     //   483: astore_2
/*    */     //   484: getfield SN : I
/*    */     //   487: istore_3
/*    */     //   488: getfield ey : Ljava/lang/String;
/*    */     //   491: astore #4
/*    */     //   493: invokevirtual getClass : ()Ljava/lang/Class;
/*    */     //   496: pop
/*    */     //   497: new f/Um0
/*    */     //   500: dup
/*    */     //   501: astore #5
/*    */     //   503: aload #4
/*    */     //   505: aload #5
/*    */     //   507: iload_3
/*    */     //   508: aload #5
/*    */     //   510: aload_2
/*    */     //   511: aload #5
/*    */     //   513: iload_1
/*    */     //   514: aload #5
/*    */     //   516: invokespecial <init> : ()V
/*    */     //   519: putfield xZ : I
/*    */     //   522: putfield W70 : Ljava/lang/String;
/*    */     //   525: putfield Zb0 : I
/*    */     //   528: putfield Zf : Ljava/lang/String;
/*    */     //   531: getstatic f/UB0.Kg0 : Lf/Q50;
/*    */     //   534: new f/zI0
/*    */     //   537: dup
/*    */     //   538: aload_0
/*    */     //   539: aload #5
/*    */     //   541: invokespecial <init> : (Lf/K6;Lf/Um0;)V
/*    */     //   544: invokevirtual fN : (Ljava/lang/Runnable;)V
/*    */     //   547: goto -> 930
/*    */     //   550: aload_1
/*    */     //   551: instanceof f/ew
/*    */     //   554: ifeq -> 790
/*    */     //   557: aload_1
/*    */     //   558: checkcast f/ew
/*    */     //   561: dup
/*    */     //   562: astore_1
/*    */     //   563: getfield sd : Z
/*    */     //   566: ifeq -> 780
/*    */     //   569: aload_0
/*    */     //   570: getfield YG0 : Lf/js;
/*    */     //   573: getfield MH0 : Lf/pA;
/*    */     //   576: getfield OU : Lf/h2;
/*    */     //   579: dup
/*    */     //   580: astore_2
/*    */     //   581: new f/N1
/*    */     //   584: dup
/*    */     //   585: dup
/*    */     //   586: astore_3
/*    */     //   587: aload_1
/*    */     //   588: dup
/*    */     //   589: dup
/*    */     //   590: dup2
/*    */     //   591: dup2
/*    */     //   592: dup2
/*    */     //   593: dup2
/*    */     //   594: dup2
/*    */     //   595: aload_0
/*    */     //   596: getfield YG0 : Lf/js;
/*    */     //   599: getfield MH0 : Lf/pA;
/*    */     //   602: getfield OU : Lf/h2;
/*    */     //   605: astore_0
/*    */     //   606: getfield tq0 : Lf/fH0;
/*    */     //   609: astore_1
/*    */     //   610: getfield Wz0 : B
/*    */     //   613: istore #4
/*    */     //   615: getfield qw : B
/*    */     //   618: istore #5
/*    */     //   620: getfield Nw0 : B
/*    */     //   623: istore #6
/*    */     //   625: getfield or0 : B
/*    */     //   628: istore #7
/*    */     //   630: getfield Su : Ljava/lang/String;
/*    */     //   633: astore #8
/*    */     //   635: getfield Zl0 : J
/*    */     //   638: lstore #9
/*    */     //   640: getfield eB0 : I
/*    */     //   643: istore #11
/*    */     //   645: getfield do : Ljava/lang/String;
/*    */     //   648: astore #12
/*    */     //   650: getfield y10 : Ljava/lang/String;
/*    */     //   653: astore #13
/*    */     //   655: getfield coM4 : Ljava/lang/String;
/*    */     //   658: astore #14
/*    */     //   660: getfield Pj : Ljava/lang/String;
/*    */     //   663: astore #15
/*    */     //   665: getfield QI : [Lf/ph0;
/*    */     //   668: astore #16
/*    */     //   670: aload_0
/*    */     //   671: aload_1
/*    */     //   672: iload #4
/*    */     //   674: iload #5
/*    */     //   676: iload #6
/*    */     //   678: iload #7
/*    */     //   680: aload #8
/*    */     //   682: lload #9
/*    */     //   684: iload #11
/*    */     //   686: aload #12
/*    */     //   688: aload #13
/*    */     //   690: aload #14
/*    */     //   692: aload #15
/*    */     //   694: aload #16
/*    */     //   696: invokespecial <init> : (Lf/h2;Lf/fH0;BBBBLjava/lang/String;JILjava/lang/String;Ljava/lang/String;Ljava/lang/String;Ljava/lang/String;[Lf/ph0;)V
/*    */     //   699: invokevirtual ID : (Lf/JG0;)I
/*    */     //   702: dup
/*    */     //   703: istore_0
/*    */     //   704: ifle -> 713
/*    */     //   707: aload_2
/*    */     //   708: iload_0
/*    */     //   709: invokevirtual fG0 : (I)Lf/JG0;
/*    */     //   712: pop
/*    */     //   713: aload_2
/*    */     //   714: getfield SW : Lf/N1;
/*    */     //   717: dup
/*    */     //   718: astore_0
/*    */     //   719: ifnull -> 728
/*    */     //   722: aload_2
/*    */     //   723: aload_0
/*    */     //   724: invokevirtual jf0 : (Lf/JG0;)Z
/*    */     //   727: pop
/*    */     //   728: aload_2
/*    */     //   729: aload_3
/*    */     //   730: dup
/*    */     //   731: dup
/*    */     //   732: aload_2
/*    */     //   733: aload_3
/*    */     //   734: invokevirtual J8 : (Lf/JG0;)V
/*    */     //   737: invokevirtual mM : ()V
/*    */     //   740: getstatic f/km.wI0 : Lf/Pw;
/*    */     //   743: invokevirtual dG : ()I
/*    */     //   746: iconst_2
/*    */     //   747: idiv
/*    */     //   748: aload_3
/*    */     //   749: getfield xY : I
/*    */     //   752: iconst_2
/*    */     //   753: idiv
/*    */     //   754: isub
/*    */     //   755: getstatic f/km.wI0 : Lf/Pw;
/*    */     //   758: invokevirtual k1 : ()I
/*    */     //   761: iconst_2
/*    */     //   762: idiv
/*    */     //   763: aload_3
/*    */     //   764: getfield HC : I
/*    */     //   767: iconst_2
/*    */     //   768: idiv
/*    */     //   769: isub
/*    */     //   770: invokevirtual ME : (II)Z
/*    */     //   773: pop
/*    */     //   774: putfield SW : Lf/N1;
/*    */     //   777: goto -> 930
/*    */     //   780: aload_0
/*    */     //   781: ldc_w 'No such player.'
/*    */     //   784: invokevirtual Pq : (Ljava/lang/String;)V
/*    */     //   787: goto -> 930
/*    */     //   790: aload_1
/*    */     //   791: instanceof f/yR
/*    */     //   794: ifeq -> 930
/*    */     //   797: aload_0
/*    */     //   798: aload_1
/*    */     //   799: checkcast f/yR
/*    */     //   802: astore_0
/*    */     //   803: getfield YG0 : Lf/js;
/*    */     //   806: getfield MH0 : Lf/pA;
/*    */     //   809: dup
/*    */     //   810: astore_1
/*    */     //   811: ifnull -> 930
/*    */     //   814: aload_1
/*    */     //   815: getfield OU : Lf/h2;
/*    */     //   818: dup
/*    */     //   819: astore_1
/*    */     //   820: ifnull -> 930
/*    */     //   823: aload_1
/*    */     //   824: aload_0
/*    */     //   825: getfield FF : [Lf/v20;
/*    */     //   828: astore_0
/*    */     //   829: getfield VX : Lf/kK0;
/*    */     //   832: dup
/*    */     //   833: astore_1
/*    */     //   834: ifnull -> 930
/*    */     //   837: aload_1
/*    */     //   838: getfield r0 : Lf/G7;
/*    */     //   841: dup
/*    */     //   842: dup
/*    */     //   843: astore_1
/*    */     //   844: aload_0
/*    */     //   845: aload_1
/*    */     //   846: aload_0
/*    */     //   847: putfield Jn0 : [Lf/v20;
/*    */     //   850: invokestatic asList : ([Ljava/lang/Object;)Ljava/util/List;
/*    */     //   853: invokestatic sort : (Ljava/util/List;)V
/*    */     //   856: getfield Jn0 : [Lf/v20;
/*    */     //   859: arraylength
/*    */     //   860: anewarray f/Un
/*    */     //   863: putfield PA : [Lf/Un;
/*    */     //   866: iconst_0
/*    */     //   867: istore_0
/*    */     //   868: iload_0
/*    */     //   869: aload_1
/*    */     //   870: getfield Jn0 : [Lf/v20;
/*    */     //   873: arraylength
/*    */     //   874: if_icmpge -> 919
/*    */     //   877: aload_1
/*    */     //   878: dup
/*    */     //   879: getfield PA : [Lf/Un;
/*    */     //   882: iload_0
/*    */     //   883: new f/Un
/*    */     //   886: dup
/*    */     //   887: astore_2
/*    */     //   888: ldc_w 'Inspect Player'
/*    */     //   891: invokespecial <init> : (Ljava/lang/String;)V
/*    */     //   894: aload_2
/*    */     //   895: aastore
/*    */     //   896: getfield PA : [Lf/Un;
/*    */     //   899: iload_0
/*    */     //   900: aaload
/*    */     //   901: new f/Y60
/*    */     //   904: dup
/*    */     //   905: aload_1
/*    */     //   906: iload_0
/*    */     //   907: invokespecial <init> : (Lf/G7;I)V
/*    */     //   910: invokevirtual tW : (Ljava/lang/Runnable;)V
/*    */     //   913: iinc #0, 1
/*    */     //   916: goto -> 868
/*    */     //   919: aload_1
/*    */     //   920: getfield gL0 : Lf/Wv0;
/*    */     //   923: aload_1
/*    */     //   924: getfield zG : Lf/X50;
/*    */     //   927: invokevirtual jA : (Lf/NO;)V
/*    */     //   930: return
/*    */     // Line number table:
/*    */     //   Java source line number -> byte code offset
/*    */     //   #1	-> 42
/*    */     //   #2	-> 53
/*    */     //   #3	-> 56
/*    */     //   #4	-> 59
/*    */     //   #5	-> 62
/*    */     //   #6	-> 65
/*    */     //   #7	-> 73
/*    */     //   #8	-> 76
/*    */     //   #9	-> 85
/*    */     //   #10	-> 88
/*    */     //   #11	-> 102
/*    */     //   #12	-> 120
/*    */     //   #13	-> 125
/*    */     //   #14	-> 129
/*    */     //   #15	-> 139
/*    */     //   #16	-> 207
/*    */     //   #17	-> 210
/*    */     //   #18	-> 213
/*    */     //   #19	-> 217
/*    */     //   #20	-> 251
/*    */     //   #21	-> 254
/*    */     //   #22	-> 257
/*    */     //   #23	-> 274
/*    */     //   #24	-> 368
/*    */     //   #25	-> 371
/*    */     //   #26	-> 374
/*    */     //   #27	-> 377
/*    */     //   #28	-> 381
/*    */     //   #29	-> 390
/*    */     //   #30	-> 393
/*    */     //   #31	-> 456
/*    */     //   #32	-> 459
/*    */     //   #33	-> 462
/*    */     //   #34	-> 465
/*    */     //   #35	-> 468
/*    */     //   #36	-> 476
/*    */     //   #37	-> 497
/*    */     //   #38	-> 551
/*    */     //   #39	-> 573
/*    */     //   #40	-> 576
/*    */     //   #41	-> 581
/*    */     //   #42	-> 599
/*    */     //   #43	-> 602
/*    */     //   #44	-> 606
/*    */     //   #45	-> 699
/*    */     //   #46	-> 709
/*    */     //   #47	-> 734
/*    */     //   #48	-> 749
/*    */     //   #49	-> 753
/*    */     //   #50	-> 764
/*    */     //   #51	-> 768
/*    */     //   #52	-> 770
/*    */     //   #53	-> 774
/*    */     //   #54	-> 781
/*    */     //   #55	-> 806
/*    */     //   #56	-> 815
/*    */     //   #57	-> 825
/*    */     //   #58	-> 829
/*    */     //   #59	-> 838
/*    */     //   #60	-> 847
/*    */     //   #61	-> 850
/*    */   }
/*    */   
/*    */   public final void PC(short paramShort) {
/*    */     UB0.Kg0.fN(paramShort::dg0);
/*    */   } }


/* Location:              /Users/vnnsnnt/Documents/Codespace/JavaWorkspace/RedTrainer/src/main/java/org/trainer/client/PokeMMO.jar!/f/R8.class
 * Java compiler version: 8 (52.0)
 * JD-Core Version:       1.1.3
 */