/*    */ package f;public final class r9 extends P2 { public static ik pk0; public static eG0 hm; public static HashSet eS; public String[] GA0; public B4 a4 = null; public boolean N10 = false; public final boolean U50; public final boolean h80 = q00.Sk; static { // Byte code:
/*    */     //   0: getstatic f/eG0.Vc : Lf/eG0;
/*    */     //   3: dup
/*    */     //   4: astore_0
/*    */     //   5: putstatic f/r9.hm : Lf/eG0;
/*    */     //   8: invokestatic getenv : ()Ljava/util/Map;
/*    */     //   11: ldc 'POKEMMO_IS_SNAPPED'
/*    */     //   13: invokeinterface containsKey : (Ljava/lang/Object;)Z
/*    */     //   18: ifeq -> 33
/*    */     //   21: getstatic f/q00.Sk : Z
/*    */     //   24: ifeq -> 33
/*    */     //   27: getstatic f/eG0.fw0 : Lf/eG0;
/*    */     //   30: putstatic f/r9.hm : Lf/eG0;
/*    */     //   33: getstatic f/r9.hm : Lf/eG0;
/*    */     //   36: dup
/*    */     //   37: astore_1
/*    */     //   38: aload_0
/*    */     //   39: if_acmpeq -> 272
/*    */     //   42: getstatic f/eG0.Cf : Ljava/util/EnumMap;
/*    */     //   45: aload_1
/*    */     //   46: invokevirtual get : (Ljava/lang/Object;)Ljava/lang/Object;
/*    */     //   49: checkcast [Lf/PX;
/*    */     //   52: dup
/*    */     //   53: astore_0
/*    */     //   54: arraylength
/*    */     //   55: ifle -> 272
/*    */     //   58: aload_0
/*    */     //   59: new java/util/HashSet
/*    */     //   62: dup
/*    */     //   63: invokespecial <init> : ()V
/*    */     //   66: putstatic f/r9.eS : Ljava/util/HashSet;
/*    */     //   69: arraylength
/*    */     //   70: istore_1
/*    */     //   71: iconst_0
/*    */     //   72: istore_2
/*    */     //   73: iload_2
/*    */     //   74: iload_1
/*    */     //   75: if_icmpge -> 272
/*    */     //   78: aload_0
/*    */     //   79: iload_2
/*    */     //   80: aaload
/*    */     //   81: astore_3
/*    */     //   82: getstatic f/r9.hm : Lf/eG0;
/*    */     //   85: getstatic f/eG0.fw0 : Lf/eG0;
/*    */     //   88: if_acmpne -> 250
/*    */     //   91: aload_3
/*    */     //   92: getstatic f/PX.Oc : Lf/PX;
/*    */     //   95: if_acmpne -> 167
/*    */     //   98: iconst_3
/*    */     //   99: anewarray java/lang/String
/*    */     //   102: dup
/*    */     //   103: dup2
/*    */     //   104: astore #4
/*    */     //   106: iconst_0
/*    */     //   107: ldc 'snapctl'
/*    */     //   109: aastore
/*    */     //   110: iconst_1
/*    */     //   111: ldc 'is-connected'
/*    */     //   113: aastore
/*    */     //   114: iconst_2
/*    */     //   115: ldc 'joystick'
/*    */     //   117: aastore
/*    */     //   118: invokestatic getRuntime : ()Ljava/lang/Runtime;
/*    */     //   121: aload #4
/*    */     //   123: invokevirtual exec : ([Ljava/lang/String;)Ljava/lang/Process;
/*    */     //   126: dup
/*    */     //   127: ldc2_w 2500
/*    */     //   130: getstatic java/util/concurrent/TimeUnit.MILLISECONDS : Ljava/util/concurrent/TimeUnit;
/*    */     //   133: invokevirtual waitFor : (JLjava/util/concurrent/TimeUnit;)Z
/*    */     //   136: pop
/*    */     //   137: invokevirtual exitValue : ()I
/*    */     //   140: ifne -> 250
/*    */     //   143: iconst_1
/*    */     //   144: istore #4
/*    */     //   146: goto -> 253
/*    */     //   149: invokevirtual printStackTrace : ()V
/*    */     //   152: iconst_0
/*    */     //   153: istore #4
/*    */     //   155: goto -> 253
/*    */     //   158: invokevirtual printStackTrace : ()V
/*    */     //   161: iconst_0
/*    */     //   162: istore #4
/*    */     //   164: goto -> 253
/*    */     //   167: aload_3
/*    */     //   168: getstatic f/PX.vr : Lf/PX;
/*    */     //   171: if_acmpne -> 240
/*    */     //   174: iconst_3
/*    */     //   175: anewarray java/lang/String
/*    */     //   178: dup
/*    */     //   179: dup2
/*    */     //   180: astore #4
/*    */     //   182: iconst_0
/*    */     //   183: ldc 'snapctl'
/*    */     //   185: aastore
/*    */     //   186: iconst_1
/*    */     //   187: ldc 'is-connected'
/*    */     //   189: aastore
/*    */     //   190: iconst_2
/*    */     //   191: ldc 'removable-media'
/*    */     //   193: aastore
/*    */     //   194: invokestatic getRuntime : ()Ljava/lang/Runtime;
/*    */     //   197: aload #4
/*    */     //   199: invokevirtual exec : ([Ljava/lang/String;)Ljava/lang/Process;
/*    */     //   202: dup
/*    */     //   203: ldc2_w 2500
/*    */     //   206: getstatic java/util/concurrent/TimeUnit.MILLISECONDS : Ljava/util/concurrent/TimeUnit;
/*    */     //   209: invokevirtual waitFor : (JLjava/util/concurrent/TimeUnit;)Z
/*    */     //   212: pop
/*    */     //   213: invokevirtual exitValue : ()I
/*    */     //   216: ifne -> 250
/*    */     //   219: goto -> 143
/*    */     //   222: invokevirtual printStackTrace : ()V
/*    */     //   225: iconst_0
/*    */     //   226: istore #4
/*    */     //   228: goto -> 253
/*    */     //   231: invokevirtual printStackTrace : ()V
/*    */     //   234: iconst_0
/*    */     //   235: istore #4
/*    */     //   237: goto -> 253
/*    */     //   240: new java/lang/UnsupportedOperationException
/*    */     //   243: dup
/*    */     //   244: ldc 'Unsupported permission type test requested'
/*    */     //   246: invokespecial <init> : (Ljava/lang/String;)V
/*    */     //   249: athrow
/*    */     //   250: iconst_0
/*    */     //   251: istore #4
/*    */     //   253: iload #4
/*    */     //   255: ifeq -> 266
/*    */     //   258: getstatic f/r9.eS : Ljava/util/HashSet;
/*    */     //   261: aload_3
/*    */     //   262: invokevirtual add : (Ljava/lang/Object;)Z
/*    */     //   265: pop
/*    */     //   266: iinc #2, 1
/*    */     //   269: goto -> 73
/*    */     //   272: return
/*    */     // Line number table:
/*    */     //   Java source line number -> byte code offset
/*    */     //   #1	-> 42
/*    */     //   #2	-> 54
/*    */     //   #3	-> 82
/*    */     //   #4	-> 118
/*    */     //   #5	-> 168
/*    */     //   #6	-> 194
/*    */     //   #7	-> 240
/*    */     //   #8	-> 258
/*    */     // Exception table:
/*    */     //   from	to	target	type
/*    */     //   118	126	158	java/io/IOException
/*    */     //   130	136	149	java/lang/InterruptedException
/*    */     //   194	202	231	java/io/IOException
/*  1 */     //   206	212	222	java/lang/InterruptedException } public r9() { pk0 = C00.gd(r9.class); pk0.info(hm.V7()); HashSet hashSet; if (hm != eG0.Vc && (hashSet = eS) != null) pk0.info("- Has permissions: " + Arrays.toString(hashSet.toArray((Object[])new PX[0])));  if (q00.Ar) { this.U50 = false; } else { boolean bool; if (Desktop.isDesktopSupported() && Desktop.getDesktop().isSupported(Desktop.Action.OPEN)) { bool = true; } else { bool = false; }  this.U50 = bool; }  } private void Wg(File paramFile) { String str = paramFile.getAbsolutePath(); if (this.h80) { (new ProcessBuilder(new String[0])).inheritIO(); (new ProcessBuilder(new String[0])).command(new String[] { "xdg-open", this }); try { (new ProcessBuilder(new String[0])).start(); } catch (IOException iOException) { pk0.error("Failed to start xdg-open", this);
/*  2 */         js.vu0
/*    */           
/*  4 */           .Pu(-1, Ml0.OH0(84)); }  }  } public final void pz() { if (!h1.PF0) return;  if (!gm.ym) return;  if (this.N10) return;  if (!q00.PG) return;  if (!Bz.uD) { B4 b4; if (km.a40()) return;  this(); (new B4()).sY(new Ax0(this, b4)); long l = System.currentTimeMillis(); try { (new B4()).st(new int[0]); } catch (Exception exception) {} if ((l = System.currentTimeMillis() - l) > 500L) { pk0.error("Disabling discord rich presence because connect took " + l + " ms."); this.N10 = true; }  return; }  } public final void xK() { // Byte code:
/*    */     //   0: aload_0
/*    */     //   1: getfield a4 : Lf/B4;
/*    */     //   4: ifnonnull -> 19
/*    */     //   7: aload_0
/*    */     //   8: dup
/*    */     //   9: invokevirtual pz : ()V
/*    */     //   12: getfield a4 : Lf/B4;
/*    */     //   15: ifnonnull -> 19
/*    */     //   18: return
/*    */     //   19: invokestatic currentTimeMillis : ()J
/*    */     //   22: lstore_1
/*    */     //   23: getstatic f/h1.PF0 : Z
/*    */     //   26: ifeq -> 255
/*    */     //   29: invokestatic a40 : ()Z
/*    */     //   32: ifeq -> 38
/*    */     //   35: goto -> 255
/*    */     //   38: new f/K7
/*    */     //   41: dup
/*    */     //   42: dup
/*    */     //   43: astore_3
/*    */     //   44: invokespecial <init> : ()V
/*    */     //   47: invokevirtual so : ()V
/*    */     //   50: getstatic f/km.a3 : Lf/vh0;
/*    */     //   53: dup
/*    */     //   54: astore #4
/*    */     //   56: ifnull -> 80
/*    */     //   59: aload #4
/*    */     //   61: invokevirtual Jr0 : ()Lf/KI;
/*    */     //   64: ifnull -> 80
/*    */     //   67: aload_3
/*    */     //   68: getstatic f/km.a3 : Lf/vh0;
/*    */     //   71: invokevirtual Jr0 : ()Lf/KI;
/*    */     //   74: invokevirtual xc0 : ()Ljava/lang/String;
/*    */     //   77: invokevirtual Yw : (Ljava/lang/String;)V
/*    */     //   80: iconst_0
/*    */     //   81: istore #4
/*    */     //   83: getstatic f/km.MR : Lf/Gp0;
/*    */     //   86: dup
/*    */     //   87: astore #5
/*    */     //   89: ifnull -> 201
/*    */     //   92: aload #5
/*    */     //   94: invokevirtual Zo : ()Lf/ky;
/*    */     //   97: getstatic f/ky.JH0 : Lf/ky;
/*    */     //   100: if_acmpeq -> 201
/*    */     //   103: getstatic f/km.MR : Lf/Gp0;
/*    */     //   106: invokevirtual sQ : ()Z
/*    */     //   109: ifeq -> 125
/*    */     //   112: aload_3
/*    */     //   113: sipush #6502
/*    */     //   116: invokestatic OH0 : (I)Ljava/lang/String;
/*    */     //   119: invokevirtual y6 : (Ljava/lang/String;)V
/*    */     //   122: goto -> 174
/*    */     //   125: getstatic f/km.MR : Lf/Gp0;
/*    */     //   128: invokevirtual RM : ()Z
/*    */     //   131: ifeq -> 144
/*    */     //   134: aload_3
/*    */     //   135: sipush #6503
/*    */     //   138: invokestatic OH0 : (I)Ljava/lang/String;
/*    */     //   141: goto -> 119
/*    */     //   144: getstatic f/km.MR : Lf/Gp0;
/*    */     //   147: invokevirtual yx0 : ()Z
/*    */     //   150: ifeq -> 177
/*    */     //   153: aload_3
/*    */     //   154: sipush #6504
/*    */     //   157: getstatic f/km.MR : Lf/Gp0;
/*    */     //   160: invokevirtual QK : ()S
/*    */     //   163: <illegal opcode> makeConcatWithConstants : (S)Ljava/lang/String;
/*    */     //   168: invokestatic Go : (ILjava/lang/String;)Ljava/lang/String;
/*    */     //   171: goto -> 119
/*    */     //   174: iconst_1
/*    */     //   175: istore #4
/*    */     //   177: iload #4
/*    */     //   179: ifeq -> 201
/*    */     //   182: aload_3
/*    */     //   183: getstatic f/km.MR : Lf/Gp0;
/*    */     //   186: invokevirtual Fy : ()J
/*    */     //   189: invokestatic ofEpochMilli : (J)Ljava/time/Instant;
/*    */     //   192: getstatic java/time/ZoneOffset.UTC : Ljava/time/ZoneOffset;
/*    */     //   195: invokestatic ofInstant : (Ljava/time/Instant;Ljava/time/ZoneId;)Ljava/time/OffsetDateTime;
/*    */     //   198: invokevirtual XF : (Ljava/time/OffsetDateTime;)V
/*    */     //   201: iload #4
/*    */     //   203: ifne -> 241
/*    */     //   206: getstatic f/km.u4 : Lf/R8;
/*    */     //   209: ifnull -> 241
/*    */     //   212: aload_3
/*    */     //   213: dup
/*    */     //   214: sipush #6501
/*    */     //   217: invokestatic OH0 : (I)Ljava/lang/String;
/*    */     //   220: invokevirtual y6 : (Ljava/lang/String;)V
/*    */     //   223: getstatic f/km.u4 : Lf/R8;
/*    */     //   226: invokevirtual l5 : ()J
/*    */     //   229: invokestatic ofEpochMilli : (J)Ljava/time/Instant;
/*    */     //   232: getstatic java/time/ZoneOffset.UTC : Ljava/time/ZoneOffset;
/*    */     //   235: invokestatic ofInstant : (Ljava/time/Instant;Ljava/time/ZoneId;)Ljava/time/OffsetDateTime;
/*    */     //   238: invokevirtual XF : (Ljava/time/OffsetDateTime;)V
/*    */     //   241: aload_0
/*    */     //   242: getfield a4 : Lf/B4;
/*    */     //   245: aload_3
/*    */     //   246: invokevirtual Ii : ()Lf/wq;
/*    */     //   249: invokevirtual cz : (Lf/wq;)V
/*    */     //   252: goto -> 279
/*    */     //   255: aload_0
/*    */     //   256: getfield a4 : Lf/B4;
/*    */     //   259: dup
/*    */     //   260: astore_1
/*    */     //   261: ifnull -> 277
/*    */     //   264: aload_0
/*    */     //   265: aload_1
/*    */     //   266: invokevirtual close : ()V
/*    */     //   269: aconst_null
/*    */     //   270: putfield a4 : Lf/B4;
/*    */     //   273: goto -> 277
/*    */     //   276: pop
/*    */     //   277: return
/*    */     //   278: pop
/*    */     //   279: invokestatic currentTimeMillis : ()J
/*    */     //   282: lload_1
/*    */     //   283: lsub
/*    */     //   284: dup2
/*    */     //   285: lstore_1
/*    */     //   286: ldc2_w 500
/*    */     //   289: lcmp
/*    */     //   290: ifle -> 334
/*    */     //   293: aload_0
/*    */     //   294: dup
/*    */     //   295: getstatic f/r9.pk0 : Lf/ik;
/*    */     //   298: lload_1
/*    */     //   299: <illegal opcode> makeConcatWithConstants : (J)Ljava/lang/String;
/*    */     //   304: invokeinterface error : (Ljava/lang/String;)V
/*    */     //   309: iconst_1
/*    */     //   310: putfield N10 : Z
/*    */     //   313: getfield a4 : Lf/B4;
/*    */     //   316: dup
/*    */     //   317: astore_1
/*    */     //   318: ifnull -> 334
/*    */     //   321: aload_0
/*    */     //   322: aload_1
/*    */     //   323: invokevirtual close : ()V
/*    */     //   326: aconst_null
/*    */     //   327: putfield a4 : Lf/B4;
/*    */     //   330: goto -> 334
/*    */     //   333: pop
/*    */     //   334: return
/*    */     // Line number table:
/*    */     //   Java source line number -> byte code offset
/*    */     //   #1	-> 256
/*    */     //   #2	-> 279
/*    */     //   #3	-> 313
/*    */     // Exception table:
/*    */     //   from	to	target	type
/*    */     //   23	26	278	java/lang/Exception
/*    */     //   29	32	278	java/lang/Exception
/*    */     //   38	41	278	java/lang/Exception
/*    */     //   44	53	278	java/lang/Exception
/*    */     //   59	64	278	java/lang/Exception
/*    */     //   67	80	278	java/lang/Exception
/*    */     //   83	86	278	java/lang/Exception
/*    */     //   92	100	278	java/lang/Exception
/*    */     //   103	109	278	java/lang/Exception
/*    */     //   112	131	278	java/lang/Exception
/*    */     //   134	150	278	java/lang/Exception
/*    */     //   157	174	278	java/lang/Exception
/*    */     //   182	201	278	java/lang/Exception
/*    */     //   206	209	278	java/lang/Exception
/*    */     //   212	255	278	java/lang/Exception
/*    */     //   255	259	276	java/lang/Exception
/*    */     //   264	276	276	java/lang/Exception
/*    */     //   313	316	333	java/lang/Exception
/*  4 */     //   321	333	333	java/lang/Exception } public final boolean Ba() { this("./data/themes"); LP lP; File file; ArrayList<String> arrayList; if (!(new File()).exists()) { lP = LP.Od0; km.f70.iJ0("Error", "/data/themes folder does not exist. Please redownload the client.", this, null, false); return false; }  boolean bool = false; this(); File[] arrayOfFile; int j; byte b; for (j = (arrayOfFile = file.listFiles()).length, b = 0; b < j; ) { File file1; if ((file1 = arrayOfFile[b]).isDirectory() && !"default-dark".equalsIgnoreCase(file1.getName())) { File[] arrayOfFile1; int k; byte b1; for (k = (arrayOfFile1 = file1.listFiles()).length, b1 = 0; b1 < k; ) { if (arrayOfFile1[b1].getName().equalsIgnoreCase("theme.xml")) { if (file1.getName().equals(h1.MW)) bool = true;  arrayList.add(file1.getName()); }  b1++; }  }  b++; }  ((r9)super).GA0 = arrayList.<String>toArray(new String[0]); int i; if (h1.wT < (i = Pa0.vH0)) { h1.wT = i; if (!"default".equals(h1.MW) && !"android".equals(h1.MW)) { h1.MW = "default"; h1.x1 = true; h1.Gh0 = true; }  }  if (!bool)
/*  5 */       h1.MW = "default";  super.pz(); try { (new q00()).fG("mmo"); return true; } catch (Exception exception) { LP lP1 = LP.Od0; km.f70
/*  6 */         .iJ0("Error", "Failed to load core libraries. Please redownload the client.", lP1, null, false);
/*  7 */       pk0.error("Failed to load core libraries.", this); return false; }  } public final void bn() { if (yG.lK() != yG.HD0) { UB0.Kg0.EM(); return; }  try { String str; if ((str = System.getProperty("java.home")) != null && !isEmpty()) { StringBuilder stringBuilder; this(); (new StringBuilder()).append(System.getProperty("java.home") + System.getProperty("java.home") + "bin" + File.separator + "javaw "); Iterator<String> iterator = ManagementFactory.getRuntimeMXBean().getInputArguments().iterator(); while (iterator.hasNext()) append((String)iterator.next() + " ");  append("-cp ").append(ManagementFactory.getRuntimeMXBean().getClassPath()).append(" "); append(Client.class.getName()).append(" "); try { Runtime.getRuntime().exec(toString()); } catch (Exception exception) {} } else { throw new RuntimeException("Invalid java.home"); }  } catch (Exception exception) { pk0.error("Error attempting auto restart.", this); }  UB0.Kg0.EM(); } public final String[] DX() { return this.GA0; } public final boolean ar(PC paramPC, String... paramVarArgs) { // Byte code:
/*    */     //   0: invokestatic ak : ()Z
/*    */     //   3: ifeq -> 141
/*    */     //   6: aload_2
/*    */     //   7: invokestatic stackPush : ()Lorg/lwjgl/system/MemoryStack;
/*    */     //   10: dup
/*    */     //   11: astore_0
/*    */     //   12: aload_2
/*    */     //   13: arraylength
/*    */     //   14: invokevirtual mallocPointer : (I)Lorg/lwjgl/PointerBuffer;
/*    */     //   17: astore_3
/*    */     //   18: arraylength
/*    */     //   19: istore #4
/*    */     //   21: iconst_0
/*    */     //   22: istore #5
/*    */     //   24: iload #5
/*    */     //   26: iload #4
/*    */     //   28: if_icmpge -> 55
/*    */     //   31: aload_3
/*    */     //   32: aload_0
/*    */     //   33: aload_2
/*    */     //   34: iload #5
/*    */     //   36: aaload
/*    */     //   37: <illegal opcode> makeConcatWithConstants : (Ljava/lang/String;)Ljava/lang/String;
/*    */     //   42: invokevirtual UTF8 : (Ljava/lang/CharSequence;)Ljava/nio/ByteBuffer;
/*    */     //   45: invokevirtual put : (Ljava/nio/ByteBuffer;)Lorg/lwjgl/PointerBuffer;
/*    */     //   48: pop
/*    */     //   49: iinc #5, 1
/*    */     //   52: goto -> 24
/*    */     //   55: aload_3
/*    */     //   56: invokevirtual flip : ()Lorg/lwjgl/system/CustomBuffer;
/*    */     //   59: pop
/*    */     //   60: ldc_w ''
/*    */     //   63: ldc_w ''
/*    */     //   66: aload_3
/*    */     //   67: ldc_w ''
/*    */     //   70: iconst_0
/*    */     //   71: invokestatic tinyfd_openFileDialog : (Ljava/lang/CharSequence;Ljava/lang/CharSequence;Lorg/lwjgl/PointerBuffer;Ljava/lang/CharSequence;Z)Ljava/lang/String;
/*    */     //   74: dup
/*    */     //   75: astore_3
/*    */     //   76: ifnonnull -> 100
/*    */     //   79: invokestatic N2 : ()Lf/js;
/*    */     //   82: ifnull -> 113
/*    */     //   85: invokestatic N2 : ()Lf/js;
/*    */     //   88: sipush #1085
/*    */     //   91: invokestatic OH0 : (I)Ljava/lang/String;
/*    */     //   94: invokevirtual ln0 : (Ljava/lang/String;)V
/*    */     //   97: goto -> 113
/*    */     //   100: getstatic f/UB0.Kg0 : Lf/Q50;
/*    */     //   103: aload_1
/*    */     //   104: aload_3
/*    */     //   105: <illegal opcode> run : (Lf/PC;Ljava/lang/String;)Ljava/lang/Runnable;
/*    */     //   110: invokevirtual fN : (Ljava/lang/Runnable;)V
/*    */     //   113: iconst_1
/*    */     //   114: aload_0
/*    */     //   115: invokevirtual close : ()V
/*    */     //   118: ireturn
/*    */     //   119: astore_3
/*    */     //   120: aload_0
/*    */     //   121: ifnull -> 136
/*    */     //   124: aload_0
/*    */     //   125: invokevirtual close : ()V
/*    */     //   128: goto -> 136
/*    */     //   131: aload_3
/*    */     //   132: swap
/*    */     //   133: invokevirtual addSuppressed : (Ljava/lang/Throwable;)V
/*    */     //   136: aload_3
/*    */     //   137: athrow
/*    */     //   138: invokevirtual printStackTrace : ()V
/*    */     //   141: aload_2
/*    */     //   142: new javax/swing/JFileChooser
/*    */     //   145: dup
/*    */     //   146: dup
/*    */     //   147: dup2
/*    */     //   148: astore_0
/*    */     //   149: invokespecial <init> : ()V
/*    */     //   152: new java/io/File
/*    */     //   155: dup
/*    */     //   156: ldc_w '.'
/*    */     //   159: invokespecial <init> : (Ljava/lang/String;)V
/*    */     //   162: invokevirtual setCurrentDirectory : (Ljava/io/File;)V
/*    */     //   165: new java/io/File
/*    */     //   168: dup
/*    */     //   169: ldc_w ''
/*    */     //   172: invokespecial <init> : (Ljava/lang/String;)V
/*    */     //   175: invokevirtual setSelectedFile : (Ljava/io/File;)V
/*    */     //   178: iconst_0
/*    */     //   179: invokevirtual setFileSelectionMode : (I)V
/*    */     //   182: arraylength
/*    */     //   183: ifeq -> 205
/*    */     //   186: aload_0
/*    */     //   187: new javax/swing/filechooser/FileNameExtensionFilter
/*    */     //   190: dup
/*    */     //   191: ldc_w ', '
/*    */     //   194: aload_2
/*    */     //   195: invokestatic join : (Ljava/lang/CharSequence;[Ljava/lang/CharSequence;)Ljava/lang/String;
/*    */     //   198: aload_2
/*    */     //   199: invokespecial <init> : (Ljava/lang/String;[Ljava/lang/String;)V
/*    */     //   202: invokevirtual setFileFilter : (Ljavax/swing/filechooser/FileFilter;)V
/*    */     //   205: aload_0
/*    */     //   206: aconst_null
/*    */     //   207: invokevirtual showOpenDialog : (Ljava/awt/Component;)I
/*    */     //   210: ifne -> 254
/*    */     //   213: aload_0
/*    */     //   214: invokevirtual getSelectedFile : ()Ljava/io/File;
/*    */     //   217: ifnonnull -> 241
/*    */     //   220: invokestatic N2 : ()Lf/js;
/*    */     //   223: ifnull -> 254
/*    */     //   226: invokestatic N2 : ()Lf/js;
/*    */     //   229: sipush #1085
/*    */     //   232: invokestatic OH0 : (I)Ljava/lang/String;
/*    */     //   235: invokevirtual ln0 : (Ljava/lang/String;)V
/*    */     //   238: goto -> 254
/*    */     //   241: getstatic f/UB0.Kg0 : Lf/Q50;
/*    */     //   244: aload_1
/*    */     //   245: aload_0
/*    */     //   246: <illegal opcode> run : (Lf/PC;Ljavax/swing/JFileChooser;)Ljava/lang/Runnable;
/*    */     //   251: invokevirtual fN : (Ljava/lang/Runnable;)V
/*    */     //   254: iconst_1
/*    */     //   255: ireturn
/*    */     // Exception table:
/*    */     //   from	to	target	type
/*    */     //   6	10	138	java/lang/Exception
/*    */     //   12	17	119	finally
/*    */     //   18	19	119	finally
/*    */     //   31	48	119	finally
/*    */     //   55	59	119	finally
/*    */     //   60	74	119	finally
/*    */     //   79	82	119	finally
/*    */     //   85	113	119	finally
/*    */     //   114	118	138	java/lang/Exception
/*    */     //   124	131	131	finally
/*    */     //   131	138	138	java/lang/Exception } public final void sK0(File paramFile) { // Byte code:
/*    */     //   0: getstatic f/q00.Ar : Z
/*    */     //   3: ifeq -> 18
/*    */     //   6: getstatic f/UB0.LL0 : Lf/wv0;
/*    */     //   9: aload_1
/*    */     //   10: invokevirtual getPath : ()Ljava/lang/String;
/*    */     //   13: invokevirtual Zq : (Ljava/lang/String;)Z
/*    */     //   16: pop
/*    */     //   17: return
/*    */     //   18: aload_0
/*    */     //   19: getfield U50 : Z
/*    */     //   22: ifeq -> 62
/*    */     //   25: invokestatic getDesktop : ()Ljava/awt/Desktop;
/*    */     //   28: aload_1
/*    */     //   29: invokevirtual open : (Ljava/io/File;)V
/*    */     //   32: return
/*    */     //   33: astore_2
/*    */     //   34: aload_0
/*    */     //   35: getfield h80 : Z
/*    */     //   38: ifne -> 62
/*    */     //   41: invokestatic N2 : ()Lf/js;
/*    */     //   44: ifnull -> 62
/*    */     //   47: aload_2
/*    */     //   48: invokevirtual printStackTrace : ()V
/*    */     //   51: invokestatic N2 : ()Lf/js;
/*    */     //   54: bipush #84
/*    */     //   56: invokestatic OH0 : (I)Ljava/lang/String;
/*    */     //   59: invokevirtual ln0 : (Ljava/lang/String;)V
/*    */     //   62: aload_0
/*    */     //   63: getfield h80 : Z
/*    */     //   66: ifeq -> 86
/*    */     //   69: new java/lang/Thread
/*    */     //   72: dup
/*    */     //   73: aload_0
/*    */     //   74: aload_1
/*    */     //   75: <illegal opcode> run : (Lf/r9;Ljava/io/File;)Ljava/lang/Runnable;
/*    */     //   80: invokespecial <init> : (Ljava/lang/Runnable;)V
/*    */     //   83: invokevirtual start : ()V
/*    */     //   86: return
/*    */     // Exception table:
/*    */     //   from	to	target	type
/*  7 */     //   25	32	33	java/lang/Exception } public final p50[] Tb0(pE0 parampE0) { try { HashSet<?> hashSet; if (!(hashSet = Ro.yl0()).isEmpty()) { ArrayList arrayList; if (size() < 5) { boolean bool = true; km.u4.p10 = km.u4.p10 | bool; }  this(); for (Iterator<E> iterator = iterator(); iterator.hasNext();) { if (parampE0.G10((p50 = (p50)iterator.next()).I1)) add((E)p50);  }  return toArray(new p50[0]); }  throw new RuntimeException(); } catch (Exception exception) { p50 p50; byte[] arrayOfByte; (arrayOfByte = new byte[16])[0] = -77; (new byte[16])[1] = -19; (new byte[16])[2] = -65; (new byte[16])[3] = -92; (new byte[16])[4] = -76; (new byte[16])[5] = 103; (new byte[16])[6] = 34; (new byte[16])[7] = -107; (new byte[16])[8] = 100; (new byte[16])[9] = -77; (new byte[16])[10] = -57; (new byte[16])[11] = -83; (new byte[16])[12] = -35; (new byte[16])[13] = -69; (new byte[16])[14] = 25; (new byte[16])[15] = Byte.MIN_VALUE; this((byte)-1, arrayOfByte); return new p50[] { this }; }  } public final void Hf0() { A1 a1 = A1.L7; this.nc.execute(() -> xK()); } public final void Q7(boolean paramBoolean) { if (paramBoolean) { GLFW.glfwMaximizeWindow(UB0.M60.AW.ne0); } else { GLFW.glfwRestoreWindow(UB0.M60.AW.ne0); }  } public final void GY() { int j = UB0.M60.dL(); int i; if ((i = UB0.M60.fG0()) < 128 || j < 128) return;  byte b; if ((b = h1.c20) == 0) { b = 0; try {  } finally { Exception exception = null; }  if (b != 0) return;  } else if (b == 1 && (fa.Dp()).length > 1) { jn jn = UB0.M60.wf(); if (h1.c20 == 1 && jn != null) { this(); stringBuilder.append(jn.Vz0); stringBuilder.append(","); stringBuilder.append(jn.TT); stringBuilder.append(","); StringBuilder stringBuilder; (stringBuilder = new StringBuilder()).append(jn.YH); h1.LA0 = (new StringBuilder()).toString(); h1.Td(); }  }  if (h1.tR != i || h1.wd0 != j) { h1.tR = i; h1.wd0 = j; h1.Gh0 = true; }  } public final boolean Wf(String paramString) { pk0.info("Setting clipboard contents"); if (MF.yl0()) { pk0.info("Setting clipboard contents glfw"); GLFW.glfwSetClipboardString(UB0.M60.rz().hy0(), paramString); return true; }  if (q00.Ar) return false;  pk0.info("Setting clipboard contents awt"); try { StringSelection stringSelection; this(paramString); Toolkit.getDefaultToolkit().getSystemClipboard().setContents(this, null); return true; } catch (Exception exception) { return false; }  }
/*  8 */   public final void LY(byte paramByte) { int i; if (paramByte == 0) { int[][] arrayOfInt1 = new int[4][1], arrayOfInt2 = new int[4][1]; try { int[] arrayOfInt3 = this[0], arrayOfInt4 = this[1], arrayOfInt5 = this[2], arrayOfInt6 = this[3]; GLFW.glfwGetMonitorWorkarea(((ba)UB0.M60.wf()).Jr, arrayOfInt3, arrayOfInt4, arrayOfInt5, arrayOfInt6); arrayOfInt3 = arrayOfInt2[0]; arrayOfInt4 = arrayOfInt2[1]; arrayOfInt5 = arrayOfInt2[2]; arrayOfInt6 = arrayOfInt2[3]; } finally { arrayOfInt1 = null;
/*  9 */         pk0.info("Failed to retrieve monitor information", (Throwable)this); }  } else if (i == 2) { int[][] arrayOfInt = new int[4][1];
/*    */       
/* 11 */       try { int[] arrayOfInt1 = this[0], arrayOfInt2 = this[1], arrayOfInt3 = this[2], arrayOfInt4 = this[3]; GLFW.glfwGetMonitorWorkarea(((ba)UB0.M60.wf()).Jr, arrayOfInt1, arrayOfInt2, arrayOfInt3, arrayOfInt4);
/*    */         MJ0 mJ0;
/* 13 */         int k = (mJ0 = UB0.M60.AW).kl(), m = UB0.M60.AW.Ye(); int n; if (UB0.M60.AW.kl() < (n = this[0][0])) k = n;  if (mJ0.Ye() < (n = this[1][0])) m = n;  if (UB0.M60.fG0() + mJ0.kl() > (n = this[0][0] + this[2][0]) && (k = n - UB0.M60.fG0()) < 0) k = 0;  }
/* 14 */       finally { arrayOfInt = null;
/* 15 */         pk0.info("Failed to retrieve monitor information", (Throwable)this); }
/*    */        }
/*    */      }
/*    */ 
/*    */   
/*    */   public final boolean wG0(PX paramPX) {
/*    */     HashSet hashSet;
/*    */     return ((hashSet = eS) == null) ? true : contains(paramPX);
/*    */   }
/*    */   
/*    */   public final String MK(PX paramPX) {
/*    */     if (hm == eG0.fw0) {
/*    */       if (paramPX == PX.Oc)
/*    */         return Ml0.OH0(1372); 
/*    */       if (paramPX == PX.vr)
/*    */         return Ml0.OH0(1371); 
/*    */     } 
/*    */     return "";
/*    */   }
/*    */   
/*    */   public final boolean Nb0() {
/*    */     return ANGLELoader.isCompatible();
/*    */   }
/*    */   
/*    */   public final byte[] Ml() {
/*    */     // Byte code:
/*    */     //   0: aconst_null
/*    */     //   1: astore_0
/*    */     //   2: getstatic f/q00.PG : Z
/*    */     //   5: ifne -> 297
/*    */     //   8: getstatic f/q00.Ar : Z
/*    */     //   11: ifeq -> 17
/*    */     //   14: goto -> 297
/*    */     //   17: getstatic f/q00.Sk : Z
/*    */     //   20: ifeq -> 303
/*    */     //   23: getstatic f/UB0.vj0 : Lf/XG;
/*    */     //   26: bipush #15
/*    */     //   28: newarray byte
/*    */     //   30: dup
/*    */     //   31: dup2
/*    */     //   32: dup2
/*    */     //   33: dup2
/*    */     //   34: dup2
/*    */     //   35: dup2
/*    */     //   36: dup2
/*    */     //   37: dup2
/*    */     //   38: astore_1
/*    */     //   39: iconst_0
/*    */     //   40: bipush #47
/*    */     //   42: bastore
/*    */     //   43: iconst_1
/*    */     //   44: bipush #101
/*    */     //   46: bastore
/*    */     //   47: iconst_2
/*    */     //   48: bipush #116
/*    */     //   50: bastore
/*    */     //   51: iconst_3
/*    */     //   52: bipush #99
/*    */     //   54: bastore
/*    */     //   55: iconst_4
/*    */     //   56: bipush #47
/*    */     //   58: bastore
/*    */     //   59: iconst_5
/*    */     //   60: bipush #109
/*    */     //   62: bastore
/*    */     //   63: bipush #6
/*    */     //   65: bipush #97
/*    */     //   67: bastore
/*    */     //   68: bipush #7
/*    */     //   70: bipush #99
/*    */     //   72: bastore
/*    */     //   73: bipush #8
/*    */     //   75: bipush #104
/*    */     //   77: bastore
/*    */     //   78: bipush #9
/*    */     //   80: bipush #105
/*    */     //   82: bastore
/*    */     //   83: bipush #10
/*    */     //   85: bipush #110
/*    */     //   87: bastore
/*    */     //   88: bipush #11
/*    */     //   90: bipush #101
/*    */     //   92: bastore
/*    */     //   93: bipush #12
/*    */     //   95: bipush #45
/*    */     //   97: bastore
/*    */     //   98: bipush #13
/*    */     //   100: bipush #105
/*    */     //   102: bastore
/*    */     //   103: bipush #14
/*    */     //   105: bipush #100
/*    */     //   107: bastore
/*    */     //   108: new java/lang/String
/*    */     //   111: dup
/*    */     //   112: aload_1
/*    */     //   113: invokespecial <init> : ([B)V
/*    */     //   116: invokevirtual lPT1 : (Ljava/lang/String;)Lf/hZ;
/*    */     //   119: invokevirtual mM : ()Ljava/lang/String;
/*    */     //   122: astore_0
/*    */     //   123: goto -> 127
/*    */     //   126: pop
/*    */     //   127: aload_0
/*    */     //   128: ifnull -> 140
/*    */     //   131: aload_0
/*    */     //   132: invokevirtual length : ()I
/*    */     //   135: bipush #10
/*    */     //   137: if_icmpge -> 303
/*    */     //   140: getstatic f/UB0.vj0 : Lf/XG;
/*    */     //   143: bipush #24
/*    */     //   145: newarray byte
/*    */     //   147: dup
/*    */     //   148: dup
/*    */     //   149: dup2
/*    */     //   150: dup2
/*    */     //   151: dup2
/*    */     //   152: dup2
/*    */     //   153: dup2
/*    */     //   154: dup2
/*    */     //   155: dup2
/*    */     //   156: dup2
/*    */     //   157: dup2
/*    */     //   158: dup2
/*    */     //   159: dup2
/*    */     //   160: astore_1
/*    */     //   161: iconst_0
/*    */     //   162: bipush #47
/*    */     //   164: bastore
/*    */     //   165: iconst_1
/*    */     //   166: bipush #118
/*    */     //   168: bastore
/*    */     //   169: iconst_2
/*    */     //   170: bipush #97
/*    */     //   172: bastore
/*    */     //   173: iconst_3
/*    */     //   174: bipush #114
/*    */     //   176: bastore
/*    */     //   177: iconst_4
/*    */     //   178: bipush #47
/*    */     //   180: bastore
/*    */     //   181: iconst_5
/*    */     //   182: bipush #108
/*    */     //   184: bastore
/*    */     //   185: bipush #6
/*    */     //   187: bipush #105
/*    */     //   189: bastore
/*    */     //   190: bipush #7
/*    */     //   192: bipush #98
/*    */     //   194: bastore
/*    */     //   195: bipush #8
/*    */     //   197: bipush #47
/*    */     //   199: bastore
/*    */     //   200: bipush #9
/*    */     //   202: bipush #100
/*    */     //   204: bastore
/*    */     //   205: bipush #10
/*    */     //   207: bipush #98
/*    */     //   209: bastore
/*    */     //   210: bipush #11
/*    */     //   212: bipush #117
/*    */     //   214: bastore
/*    */     //   215: bipush #12
/*    */     //   217: bipush #115
/*    */     //   219: bastore
/*    */     //   220: bipush #13
/*    */     //   222: bipush #47
/*    */     //   224: bastore
/*    */     //   225: bipush #14
/*    */     //   227: bipush #109
/*    */     //   229: bastore
/*    */     //   230: bipush #15
/*    */     //   232: bipush #97
/*    */     //   234: bastore
/*    */     //   235: bipush #16
/*    */     //   237: bipush #99
/*    */     //   239: bastore
/*    */     //   240: bipush #17
/*    */     //   242: bipush #104
/*    */     //   244: bastore
/*    */     //   245: bipush #18
/*    */     //   247: bipush #105
/*    */     //   249: bastore
/*    */     //   250: bipush #19
/*    */     //   252: bipush #110
/*    */     //   254: bastore
/*    */     //   255: bipush #20
/*    */     //   257: bipush #101
/*    */     //   259: bastore
/*    */     //   260: bipush #21
/*    */     //   262: bipush #45
/*    */     //   264: bastore
/*    */     //   265: bipush #22
/*    */     //   267: bipush #105
/*    */     //   269: bastore
/*    */     //   270: bipush #23
/*    */     //   272: bipush #100
/*    */     //   274: bastore
/*    */     //   275: new java/lang/String
/*    */     //   278: dup
/*    */     //   279: aload_1
/*    */     //   280: invokespecial <init> : ([B)V
/*    */     //   283: invokevirtual lPT1 : (Ljava/lang/String;)Lf/hZ;
/*    */     //   286: invokevirtual mM : ()Ljava/lang/String;
/*    */     //   289: astore_0
/*    */     //   290: goto -> 303
/*    */     //   293: pop
/*    */     //   294: goto -> 303
/*    */     //   297: invokestatic cz0 : ()Ljava/lang/String;
/*    */     //   300: goto -> 289
/*    */     //   303: aload_0
/*    */     //   304: ifnull -> 312
/*    */     //   307: aload_0
/*    */     //   308: invokevirtual trim : ()Ljava/lang/String;
/*    */     //   311: astore_0
/*    */     //   312: aload_0
/*    */     //   313: ifnull -> 325
/*    */     //   316: aload_0
/*    */     //   317: invokevirtual length : ()I
/*    */     //   320: bipush #10
/*    */     //   322: if_icmpge -> 724
/*    */     //   325: invokestatic getenv : ()Ljava/util/Map;
/*    */     //   328: dup
/*    */     //   329: bipush #7
/*    */     //   331: newarray byte
/*    */     //   333: dup
/*    */     //   334: dup2
/*    */     //   335: dup2
/*    */     //   336: dup2
/*    */     //   337: astore_0
/*    */     //   338: iconst_0
/*    */     //   339: bipush #111
/*    */     //   341: bastore
/*    */     //   342: iconst_1
/*    */     //   343: bipush #115
/*    */     //   345: bastore
/*    */     //   346: iconst_2
/*    */     //   347: bipush #46
/*    */     //   349: bastore
/*    */     //   350: iconst_3
/*    */     //   351: bipush #110
/*    */     //   353: bastore
/*    */     //   354: iconst_4
/*    */     //   355: bipush #97
/*    */     //   357: bastore
/*    */     //   358: iconst_5
/*    */     //   359: bipush #109
/*    */     //   361: bastore
/*    */     //   362: bipush #6
/*    */     //   364: bipush #101
/*    */     //   366: bastore
/*    */     //   367: new java/lang/String
/*    */     //   370: dup
/*    */     //   371: aload_0
/*    */     //   372: invokespecial <init> : ([B)V
/*    */     //   375: invokestatic getProperty : (Ljava/lang/String;)Ljava/lang/String;
/*    */     //   378: astore_0
/*    */     //   379: bipush #7
/*    */     //   381: newarray byte
/*    */     //   383: dup
/*    */     //   384: dup2
/*    */     //   385: dup2
/*    */     //   386: dup2
/*    */     //   387: astore_1
/*    */     //   388: iconst_0
/*    */     //   389: bipush #111
/*    */     //   391: bastore
/*    */     //   392: iconst_1
/*    */     //   393: bipush #115
/*    */     //   395: bastore
/*    */     //   396: iconst_2
/*    */     //   397: bipush #46
/*    */     //   399: bastore
/*    */     //   400: iconst_3
/*    */     //   401: bipush #97
/*    */     //   403: bastore
/*    */     //   404: iconst_4
/*    */     //   405: bipush #114
/*    */     //   407: bastore
/*    */     //   408: iconst_5
/*    */     //   409: bipush #99
/*    */     //   411: bastore
/*    */     //   412: bipush #6
/*    */     //   414: bipush #104
/*    */     //   416: bastore
/*    */     //   417: new java/lang/String
/*    */     //   420: dup
/*    */     //   421: aload_1
/*    */     //   422: invokespecial <init> : ([B)V
/*    */     //   425: invokestatic getProperty : (Ljava/lang/String;)Ljava/lang/String;
/*    */     //   428: astore_1
/*    */     //   429: invokestatic getDefault : ()Ljava/util/Locale;
/*    */     //   432: invokevirtual toString : ()Ljava/lang/String;
/*    */     //   435: astore_2
/*    */     //   436: bipush #20
/*    */     //   438: newarray byte
/*    */     //   440: dup
/*    */     //   441: dup
/*    */     //   442: dup2
/*    */     //   443: dup2
/*    */     //   444: dup2
/*    */     //   445: dup2
/*    */     //   446: dup2
/*    */     //   447: dup2
/*    */     //   448: dup2
/*    */     //   449: dup2
/*    */     //   450: dup2
/*    */     //   451: astore_3
/*    */     //   452: iconst_0
/*    */     //   453: bipush #80
/*    */     //   455: bastore
/*    */     //   456: iconst_1
/*    */     //   457: bipush #82
/*    */     //   459: bastore
/*    */     //   460: iconst_2
/*    */     //   461: bipush #79
/*    */     //   463: bastore
/*    */     //   464: iconst_3
/*    */     //   465: bipush #67
/*    */     //   467: bastore
/*    */     //   468: iconst_4
/*    */     //   469: bipush #69
/*    */     //   471: bastore
/*    */     //   472: iconst_5
/*    */     //   473: bipush #83
/*    */     //   475: bastore
/*    */     //   476: bipush #6
/*    */     //   478: bipush #83
/*    */     //   480: bastore
/*    */     //   481: bipush #7
/*    */     //   483: bipush #79
/*    */     //   485: bastore
/*    */     //   486: bipush #8
/*    */     //   488: bipush #82
/*    */     //   490: bastore
/*    */     //   491: bipush #9
/*    */     //   493: bipush #95
/*    */     //   495: bastore
/*    */     //   496: bipush #10
/*    */     //   498: bipush #73
/*    */     //   500: bastore
/*    */     //   501: bipush #11
/*    */     //   503: bipush #68
/*    */     //   505: bastore
/*    */     //   506: bipush #12
/*    */     //   508: bipush #69
/*    */     //   510: bastore
/*    */     //   511: bipush #13
/*    */     //   513: bipush #78
/*    */     //   515: bastore
/*    */     //   516: bipush #14
/*    */     //   518: bipush #84
/*    */     //   520: bastore
/*    */     //   521: bipush #15
/*    */     //   523: bipush #73
/*    */     //   525: bastore
/*    */     //   526: bipush #16
/*    */     //   528: bipush #70
/*    */     //   530: bastore
/*    */     //   531: bipush #17
/*    */     //   533: bipush #73
/*    */     //   535: bastore
/*    */     //   536: bipush #18
/*    */     //   538: bipush #69
/*    */     //   540: bastore
/*    */     //   541: bipush #19
/*    */     //   543: bipush #82
/*    */     //   545: bastore
/*    */     //   546: new java/lang/String
/*    */     //   549: dup
/*    */     //   550: aload_3
/*    */     //   551: invokespecial <init> : ([B)V
/*    */     //   554: invokeinterface get : (Ljava/lang/Object;)Ljava/lang/Object;
/*    */     //   559: checkcast java/lang/String
/*    */     //   562: astore_3
/*    */     //   563: bipush #20
/*    */     //   565: newarray byte
/*    */     //   567: dup
/*    */     //   568: dup
/*    */     //   569: dup2
/*    */     //   570: dup2
/*    */     //   571: dup2
/*    */     //   572: dup2
/*    */     //   573: dup2
/*    */     //   574: dup2
/*    */     //   575: dup2
/*    */     //   576: dup2
/*    */     //   577: dup2
/*    */     //   578: astore #4
/*    */     //   580: iconst_0
/*    */     //   581: bipush #78
/*    */     //   583: bastore
/*    */     //   584: iconst_1
/*    */     //   585: bipush #85
/*    */     //   587: bastore
/*    */     //   588: iconst_2
/*    */     //   589: bipush #77
/*    */     //   591: bastore
/*    */     //   592: iconst_3
/*    */     //   593: bipush #66
/*    */     //   595: bastore
/*    */     //   596: iconst_4
/*    */     //   597: bipush #69
/*    */     //   599: bastore
/*    */     //   600: iconst_5
/*    */     //   601: bipush #82
/*    */     //   603: bastore
/*    */     //   604: bipush #6
/*    */     //   606: bipush #95
/*    */     //   608: bastore
/*    */     //   609: bipush #7
/*    */     //   611: bipush #79
/*    */     //   613: bastore
/*    */     //   614: bipush #8
/*    */     //   616: bipush #70
/*    */     //   618: bastore
/*    */     //   619: bipush #9
/*    */     //   621: bipush #95
/*    */     //   623: bastore
/*    */     //   624: bipush #10
/*    */     //   626: bipush #80
/*    */     //   628: bastore
/*    */     //   629: bipush #11
/*    */     //   631: bipush #82
/*    */     //   633: bastore
/*    */     //   634: bipush #12
/*    */     //   636: bipush #79
/*    */     //   638: bastore
/*    */     //   639: bipush #13
/*    */     //   641: bipush #67
/*    */     //   643: bastore
/*    */     //   644: bipush #14
/*    */     //   646: bipush #69
/*    */     //   648: bastore
/*    */     //   649: bipush #15
/*    */     //   651: bipush #83
/*    */     //   653: bastore
/*    */     //   654: bipush #16
/*    */     //   656: bipush #83
/*    */     //   658: bastore
/*    */     //   659: bipush #17
/*    */     //   661: bipush #79
/*    */     //   663: bastore
/*    */     //   664: bipush #18
/*    */     //   666: bipush #82
/*    */     //   668: bastore
/*    */     //   669: bipush #19
/*    */     //   671: bipush #83
/*    */     //   673: bastore
/*    */     //   674: new java/lang/String
/*    */     //   677: dup
/*    */     //   678: aload #4
/*    */     //   680: invokespecial <init> : ([B)V
/*    */     //   683: invokeinterface get : (Ljava/lang/Object;)Ljava/lang/Object;
/*    */     //   688: checkcast java/lang/String
/*    */     //   691: astore #4
/*    */     //   693: ldc_w ''
/*    */     //   696: astore #5
/*    */     //   698: invokestatic getLocalHost : ()Ljava/net/InetAddress;
/*    */     //   701: invokevirtual getHostName : ()Ljava/lang/String;
/*    */     //   704: astore #5
/*    */     //   706: goto -> 710
/*    */     //   709: pop
/*    */     //   710: aload_0
/*    */     //   711: aload_1
/*    */     //   712: aload_2
/*    */     //   713: aload #5
/*    */     //   715: aload_3
/*    */     //   716: aload #4
/*    */     //   718: <illegal opcode> makeConcatWithConstants : (Ljava/lang/String;Ljava/lang/String;Ljava/lang/String;Ljava/lang/String;Ljava/lang/String;Ljava/lang/String;)Ljava/lang/String;
/*    */     //   723: astore_0
/*    */     //   724: bipush #7
/*    */     //   726: newarray byte
/*    */     //   728: dup
/*    */     //   729: dup2
/*    */     //   730: dup2
/*    */     //   731: dup2
/*    */     //   732: astore_1
/*    */     //   733: iconst_0
/*    */     //   734: bipush #83
/*    */     //   736: bastore
/*    */     //   737: iconst_1
/*    */     //   738: bipush #72
/*    */     //   740: bastore
/*    */     //   741: iconst_2
/*    */     //   742: bipush #65
/*    */     //   744: bastore
/*    */     //   745: iconst_3
/*    */     //   746: bipush #45
/*    */     //   748: bastore
/*    */     //   749: iconst_4
/*    */     //   750: bipush #50
/*    */     //   752: bastore
/*    */     //   753: iconst_5
/*    */     //   754: bipush #53
/*    */     //   756: bastore
/*    */     //   757: bipush #6
/*    */     //   759: bipush #54
/*    */     //   761: bastore
/*    */     //   762: new java/lang/String
/*    */     //   765: dup
/*    */     //   766: aload_1
/*    */     //   767: invokespecial <init> : ([B)V
/*    */     //   770: invokestatic getInstance : (Ljava/lang/String;)Ljava/security/MessageDigest;
/*    */     //   773: aload_0
/*    */     //   774: invokevirtual getBytes : ()[B
/*    */     //   777: invokevirtual digest : ([B)[B
/*    */     //   780: areturn
/*    */     //   781: invokevirtual printStackTrace : ()V
/*    */     //   784: iconst_0
/*    */     //   785: newarray byte
/*    */     //   787: areturn
/*    */     // Line number table:
/*    */     //   Java source line number -> byte code offset
/*    */     //   #1	-> 108
/*    */     //   #2	-> 116
/*    */     //   #3	-> 275
/*    */     //   #4	-> 283
/*    */     //   #5	-> 367
/*    */     //   #6	-> 375
/*    */     //   #7	-> 417
/*    */     //   #8	-> 425
/*    */     //   #9	-> 546
/*    */     //   #10	-> 554
/*    */     //   #11	-> 674
/*    */     //   #12	-> 683
/*    */     //   #13	-> 762
/*    */     //   #14	-> 770
/*    */     // Exception table:
/*    */     //   from	to	target	type
/*    */     //   2	5	293	java/lang/Exception
/*    */     //   8	11	293	java/lang/Exception
/*    */     //   17	20	293	java/lang/Exception
/*    */     //   23	30	126	java/lang/Exception
/*    */     //   39	122	126	java/lang/Exception
/*    */     //   131	135	293	java/lang/Exception
/*    */     //   140	147	293	java/lang/Exception
/*    */     //   161	289	293	java/lang/Exception
/*    */     //   297	303	293	java/lang/Exception
/*    */     //   698	704	709	java/net/UnknownHostException
/*    */     //   724	728	781	java/lang/Exception
/*    */     //   733	780	781	java/lang/Exception
/*    */   }
/*    */   
/*    */   public final boolean Qz(File paramFile) {
/*    */     int i = 10000;
/*    */     byte b = 10;
/*    */     try {
/*    */       FileChannel fileChannel;
/*    */       try {
/*    */         return true;
/*    */       } finally {
/*    */         Exception exception = null;
/*    */         if (fileChannel != null)
/*    */           try {
/*    */             fileChannel.close();
/*    */           } finally {} 
/*    */       } 
/*    */     } finally {
/*    */       Exception exception = null;
/*    */       pk0.error("Couldn't acquire file lock", this);
/*    */     } 
/*    */   } }


/* Location:              /Users/vnnsnnt/Documents/Codespace/JavaWorkspace/RedTrainer/src/main/java/org/trainer/client/PokeMMO.jar!/f/r9.class
 * Java compiler version: 17 (61.0)
 * JD-Core Version:       1.1.3
 */