/* 1 */ package f;public final class rg extends JG0 { public final Ip BZ; public final Un yr0; public static void QT(pA parampA) { rg rg1; if ((rg1 = parampA.hJ) != null) { rg1
/* 2 */         .ra0(); parampA.hJ = null; }  }
/*   */   public final of x30; public final of bd; public rg(pA parampA, boolean paramBoolean, short paramShort) { // Byte code:
/*   */     //   0: iload_2
/*   */     //   1: aload_0
/*   */     //   2: dup
/*   */     //   3: dup
/*   */     //   4: invokespecial <init> : ()V
/*   */     //   7: ldc 'confirm-widget'
/*   */     //   9: invokevirtual Xu : (Ljava/lang/String;)V
/*   */     //   12: new f/Ip
/*   */     //   15: dup
/*   */     //   16: astore_2
/*   */     //   17: aload_0
/*   */     //   18: aload_2
/*   */     //   19: dup
/*   */     //   20: invokespecial <init> : ()V
/*   */     //   23: putfield BZ : Lf/Ip;
/*   */     //   26: ldc 'confirm-panel'
/*   */     //   28: invokevirtual Xu : (Ljava/lang/String;)V
/*   */     //   31: new f/dQ
/*   */     //   34: dup
/*   */     //   35: astore #4
/*   */     //   37: ldc 100011
/*   */     //   39: invokestatic OH0 : (I)Ljava/lang/String;
/*   */     //   42: invokespecial <init> : (Ljava/lang/String;)V
/*   */     //   45: new f/of
/*   */     //   48: dup
/*   */     //   49: dup
/*   */     //   50: astore #5
/*   */     //   52: invokespecial <init> : ()V
/*   */     //   55: putfield x30 : Lf/of;
/*   */     //   58: new f/of
/*   */     //   61: dup
/*   */     //   62: dup2
/*   */     //   63: astore #6
/*   */     //   65: aload #5
/*   */     //   67: dup
/*   */     //   68: dup
/*   */     //   69: aload_0
/*   */     //   70: aload #6
/*   */     //   72: dup
/*   */     //   73: invokespecial <init> : ()V
/*   */     //   76: putfield bd : Lf/of;
/*   */     //   79: bipush #16
/*   */     //   81: invokevirtual co : (I)V
/*   */     //   84: ldc '[a-zA-Z脌脕脗脙脛脜脝脟脠脡脢脣脤脥脦脧脨脩脪脫脭脮脰脴脵脷脹脺脻脼脽脿谩芒茫盲氓忙莽猫茅锚毛矛铆卯茂冒帽貌贸么玫枚酶霉煤没眉媒镁每]'
/*   */     //   86: invokevirtual Lpt5 : (Ljava/lang/String;)V
/*   */     //   89: invokevirtual LE : ()V
/*   */     //   92: iconst_4
/*   */     //   93: invokevirtual co : (I)V
/*   */     //   96: ldc '[a-zA-Z脌脕脗脙脛脜脝脟脠脡脢脣脤脥脦脧脨脩脪脫脭脮脰脴脵脷脹脺脻脼脽脿谩芒茫盲氓忙莽猫茅锚毛矛铆卯茂冒帽貌贸么玫枚酶霉煤没眉媒镁每]'
/*   */     //   98: invokevirtual Lpt5 : (Ljava/lang/String;)V
/*   */     //   101: invokevirtual LE : ()V
/*   */     //   104: new f/dQ
/*   */     //   107: dup
/*   */     //   108: astore #7
/*   */     //   110: sipush #2729
/*   */     //   113: invokestatic OH0 : (I)Ljava/lang/String;
/*   */     //   116: invokespecial <init> : (Ljava/lang/String;)V
/*   */     //   119: new f/dQ
/*   */     //   122: dup
/*   */     //   123: astore #8
/*   */     //   125: aload #7
/*   */     //   127: aload #8
/*   */     //   129: sipush #2730
/*   */     //   132: invokestatic OH0 : (I)Ljava/lang/String;
/*   */     //   135: invokespecial <init> : (Ljava/lang/String;)V
/*   */     //   138: invokevirtual Xy : ()Ljava/lang/String;
/*   */     //   141: pop
/*   */     //   142: invokevirtual Xy : ()Ljava/lang/String;
/*   */     //   145: pop
/*   */     //   146: ifeq -> 184
/*   */     //   149: new f/Un
/*   */     //   152: dup
/*   */     //   153: astore #9
/*   */     //   155: aload_0
/*   */     //   156: iload_3
/*   */     //   157: aload_0
/*   */     //   158: aload #9
/*   */     //   160: dup
/*   */     //   161: sipush #2991
/*   */     //   164: invokestatic OH0 : (I)Ljava/lang/String;
/*   */     //   167: invokespecial <init> : (Ljava/lang/String;)V
/*   */     //   170: putfield yr0 : Lf/Un;
/*   */     //   173: <illegal opcode> run : (Lf/rg;S)Ljava/lang/Runnable;
/*   */     //   178: invokevirtual tW : (Ljava/lang/Runnable;)V
/*   */     //   181: goto -> 216
/*   */     //   184: new f/Un
/*   */     //   187: dup
/*   */     //   188: astore #9
/*   */     //   190: aload_0
/*   */     //   191: aload_1
/*   */     //   192: aload_0
/*   */     //   193: aload #9
/*   */     //   195: dup
/*   */     //   196: bipush #52
/*   */     //   198: invokestatic OH0 : (I)Ljava/lang/String;
/*   */     //   201: invokespecial <init> : (Ljava/lang/String;)V
/*   */     //   204: putfield yr0 : Lf/Un;
/*   */     //   207: iload_3
/*   */     //   208: <illegal opcode> run : (Lf/rg;Lf/pA;S)Ljava/lang/Runnable;
/*   */     //   213: invokevirtual tW : (Ljava/lang/Runnable;)V
/*   */     //   216: aload_0
/*   */     //   217: aload_2
/*   */     //   218: dup
/*   */     //   219: dup
/*   */     //   220: dup2
/*   */     //   221: new f/Un
/*   */     //   224: dup
/*   */     //   225: astore_3
/*   */     //   226: aload_1
/*   */     //   227: aload_3
/*   */     //   228: bipush #53
/*   */     //   230: invokestatic OH0 : (I)Ljava/lang/String;
/*   */     //   233: invokespecial <init> : (Ljava/lang/String;)V
/*   */     //   236: <illegal opcode> run : (Lf/pA;)Ljava/lang/Runnable;
/*   */     //   241: invokevirtual tW : (Ljava/lang/Runnable;)V
/*   */     //   244: invokevirtual d7 : ()Lf/cr0;
/*   */     //   247: aload #4
/*   */     //   249: invokevirtual Ya : (Lf/JG0;)Lf/U90;
/*   */     //   252: aload_2
/*   */     //   253: invokevirtual mE0 : ()Lf/g0;
/*   */     //   256: iconst_2
/*   */     //   257: anewarray f/JG0
/*   */     //   260: dup
/*   */     //   261: dup
/*   */     //   262: iconst_0
/*   */     //   263: aload #7
/*   */     //   265: aastore
/*   */     //   266: iconst_1
/*   */     //   267: aload #5
/*   */     //   269: aastore
/*   */     //   270: invokevirtual Mg : ([Lf/JG0;)Lf/U90;
/*   */     //   273: invokevirtual ee0 : (Lf/U90;)Lf/U90;
/*   */     //   276: aload_2
/*   */     //   277: invokevirtual mE0 : ()Lf/g0;
/*   */     //   280: iconst_2
/*   */     //   281: anewarray f/JG0
/*   */     //   284: dup
/*   */     //   285: dup
/*   */     //   286: iconst_0
/*   */     //   287: aload #8
/*   */     //   289: aastore
/*   */     //   290: iconst_1
/*   */     //   291: aload #6
/*   */     //   293: aastore
/*   */     //   294: invokevirtual Mg : ([Lf/JG0;)Lf/U90;
/*   */     //   297: invokevirtual ee0 : (Lf/U90;)Lf/U90;
/*   */     //   300: aload_2
/*   */     //   301: invokevirtual d7 : ()Lf/cr0;
/*   */     //   304: iconst_2
/*   */     //   305: anewarray f/JG0
/*   */     //   308: dup
/*   */     //   309: dup
/*   */     //   310: aload_0
/*   */     //   311: getfield yr0 : Lf/Un;
/*   */     //   314: iconst_0
/*   */     //   315: swap
/*   */     //   316: aastore
/*   */     //   317: iconst_1
/*   */     //   318: aload_3
/*   */     //   319: aastore
/*   */     //   320: invokevirtual Mg : ([Lf/JG0;)Lf/U90;
/*   */     //   323: invokevirtual ee0 : (Lf/U90;)Lf/U90;
/*   */     //   326: invokevirtual Em0 : ()Lf/U90;
/*   */     //   329: invokevirtual WN : (Lf/U90;)V
/*   */     //   332: invokevirtual mE0 : ()Lf/g0;
/*   */     //   335: aload #4
/*   */     //   337: invokevirtual Ya : (Lf/JG0;)Lf/U90;
/*   */     //   340: aload_2
/*   */     //   341: invokevirtual d7 : ()Lf/cr0;
/*   */     //   344: iconst_2
/*   */     //   345: anewarray f/JG0
/*   */     //   348: dup
/*   */     //   349: dup
/*   */     //   350: iconst_0
/*   */     //   351: aload #7
/*   */     //   353: aastore
/*   */     //   354: iconst_1
/*   */     //   355: aload #5
/*   */     //   357: aastore
/*   */     //   358: invokevirtual Mg : ([Lf/JG0;)Lf/U90;
/*   */     //   361: invokevirtual ee0 : (Lf/U90;)Lf/U90;
/*   */     //   364: aload_2
/*   */     //   365: invokevirtual d7 : ()Lf/cr0;
/*   */     //   368: iconst_2
/*   */     //   369: anewarray f/JG0
/*   */     //   372: dup
/*   */     //   373: dup
/*   */     //   374: iconst_0
/*   */     //   375: aload #8
/*   */     //   377: aastore
/*   */     //   378: iconst_1
/*   */     //   379: aload #6
/*   */     //   381: aastore
/*   */     //   382: invokevirtual Mg : ([Lf/JG0;)Lf/U90;
/*   */     //   385: invokevirtual ee0 : (Lf/U90;)Lf/U90;
/*   */     //   388: aload_2
/*   */     //   389: invokevirtual mE0 : ()Lf/g0;
/*   */     //   392: aload_0
/*   */     //   393: getfield yr0 : Lf/Un;
/*   */     //   396: invokevirtual Ya : (Lf/JG0;)Lf/U90;
/*   */     //   399: aload_3
/*   */     //   400: invokevirtual Ya : (Lf/JG0;)Lf/U90;
/*   */     //   403: invokevirtual ee0 : (Lf/U90;)Lf/U90;
/*   */     //   406: invokevirtual rK0 : (Lf/U90;)V
/*   */     //   409: invokevirtual J8 : (Lf/JG0;)V
/*   */     //   412: return } private void DI0(pA parampA, short paramShort) { // Byte code:
/*   */     //   0: aload_1
/*   */     //   1: getfield hJ : Lf/rg;
/*   */     //   4: dup
/*   */     //   5: astore_3
/*   */     //   6: ifnull -> 19
/*   */     //   9: aload_1
/*   */     //   10: aload_3
/*   */     //   11: invokevirtual ra0 : ()Z
/*   */     //   14: pop
/*   */     //   15: aconst_null
/*   */     //   16: putfield hJ : Lf/rg;
/*   */     //   19: getstatic f/js.vu0 : Lf/js;
/*   */     //   22: new f/h70
/*   */     //   25: dup
/*   */     //   26: aload_0
/*   */     //   27: iload_2
/*   */     //   28: ldc 100013
/*   */     //   30: iconst_2
/*   */     //   31: anewarray java/lang/String
/*   */     //   34: dup
/*   */     //   35: dup
/*   */     //   36: iconst_0
/*   */     //   37: aload_0
/*   */     //   38: getfield x30 : Lf/of;
/*   */     //   41: getfield F2 : Lf/ak0;
/*   */     //   44: getfield PH0 : Ljava/lang/StringBuilder;
/*   */     //   47: invokevirtual toString : ()Ljava/lang/String;
/*   */     //   50: aastore
/*   */     //   51: iconst_1
/*   */     //   52: aload_0
/*   */     //   53: getfield bd : Lf/of;
/*   */     //   56: getfield F2 : Lf/ak0;
/*   */     //   59: getfield PH0 : Ljava/lang/StringBuilder;
/*   */     //   62: invokevirtual toString : ()Ljava/lang/String;
/*   */     //   65: aastore
/*   */     //   66: invokestatic sB : (I[Ljava/lang/String;)Ljava/lang/String;
/*   */     //   69: astore_1
/*   */     //   70: <illegal opcode> run : (Lf/rg;S)Ljava/lang/Runnable;
/*   */     //   75: aload_1
/*   */     //   76: swap
/*   */     //   77: aload_0
/*   */     //   78: invokespecial <init> : (Ljava/lang/String;Ljava/lang/Runnable;Lf/JG0;)V
/*   */     //   81: invokevirtual uh : (Lf/h70;)V
/*   */     //   84: return
/*   */     // Line number table:
/*   */     //   Java source line number -> byte code offset
/*   */     //   #1	-> 1
/*   */     //   #2	-> 11
/*   */     //   #3	-> 19
/*   */     //   #4	-> 22
/*   */     //   #5	-> 41
/*   */     //   #6	-> 44
/*   */     //   #7	-> 47
/*   */     //   #8	-> 50
/*   */     //   #9	-> 56
/*   */     //   #10	-> 59
/*   */     //   #11	-> 62
/* 3 */     //   #12	-> 65 } private void qa0(short paramShort) { String str1 = this.x30.F2.PH0.toString();
/*   */ 
/*   */ 
/*   */     
/* 7 */     String str2 = this.bd.F2.PH0.toString();
/* 8 */     km.u4.e20
/* 9 */       .W3(new zQ(paramShort, this, str2, false)); } private void R90(short paramShort) { String str1 = this.x30.F2.PH0.toString(); String str2 = this.bd.F2.PH0.toString(); km.u4.e20.W3(new zQ(paramShort, this, str2, true)); }
/*   */ 
/*   */   
/*   */   public final void LM(throws paramthrows) {
/*   */     VA0.c90(this.x30);
/*   */   }
/*   */   
/*   */   public final void d40() {
/*   */     this.BZ.mM();
/*   */     QI();
/*   */     this.BZ.js0(et.Wi0);
/*   */   } }


/* Location:              /Users/vnnsnnt/Documents/Codespace/JavaWorkspace/RedTrainer/src/main/java/org/trainer/client/PokeMMO.jar!/f/rg.class
 * Java compiler version: 8 (52.0)
 * JD-Core Version:       1.1.3
 */