/*   1 */ package f;public abstract class rG0 { public static String Zs0(j40 paramj40, boolean paramBoolean1, boolean paramBoolean2, boolean paramBoolean3) { if (paramj40 == null) return "";  if (paramj40.Zs.YC())
/*   2 */       return paramj40.m();  if (paramBoolean1)
/*     */     {
/*     */ 
/*     */ 
/*     */ 
/*     */ 
/*     */ 
/*     */ 
/*     */ 
/*     */       
/*  12 */       return pv.X9(1809, pv.X9(1840, (new StringBuilder()).append(paramj40.m()).append("\n"), " ").append(paramj40.Zs.od).append("\n"), " ").append(paramj40.Zs.Hq0).append(" / ").append(paramj40.Fq0.Mm(hR.Gg)).toString();
/*     */     }
/*     */     
/*  15 */     LPT3 lPT3 = Of.eH.On0(paramj40.Zs.p10()); this(); String str1; StringBuilder stringBuilder1; String str2; this(); (new StringBuilder())
/*     */ 
/*     */ 
/*     */       
/*  19 */       .append(pv.X9(59, stringBuilder2, " ").append(paramj40.Zs.od).append(" ").append(paramj40.m()).toString());
/*  20 */     StringBuilder stringBuilder2 = pv.X9(1804, (new StringBuilder()).append("\n"), " ");
/*  21 */     if (paramj40.rG() == paramj40.OH()) { Ht0 ht0 = paramj40.rG(); } else { str2 = paramj40.rG() + " / " + paramj40.OH(); }  stringBuilder1.append(stringBuilder2.append(str2).toString()); stringBuilder1
/*     */ 
/*     */       
/*  24 */       .append(pv.X9(1807, (new StringBuilder()).append("\n"), " ").append(paramj40.Zs.lG()).toString());
/*     */ 
/*     */     
/*     */     hR hR1;
/*     */ 
/*     */     
/*  30 */     stringBuilder1.append(pv.X9(1809, (new StringBuilder()).append("\n"), " ").append(paramj40.Zs.Hq0).append(" / ").append(paramj40.Fq0.Mm(hR1 = hR.Gg)).toString());
/*     */     
/*  32 */     stringBuilder1.append(pv.X9(1824, (new StringBuilder()).append("\n"), " ").append(Ml0.OH0(paramj40.rX() + 210000)).toString());
/*     */ 
/*     */ 
/*     */     
/*  36 */     stringBuilder1.append(pv.X9(1805, (new StringBuilder()).append("\n"), " ").append(paramj40.Zs.k0.cK0()).toString()); this();
/*     */ 
/*     */ 
/*     */ 
/*     */ 
/*     */ 
/*     */     
/*     */     hR hR2, hR3, hR4, hR5, hR6;
/*     */ 
/*     */ 
/*     */ 
/*     */ 
/*     */     
/*  49 */     String str3 = pv.X9(1849, stringBuilder2, " ").append(paramj40.Zs.Hc(hR1)).append("/").append(paramj40.Zs.Hc(hR2 = hR.zh)).append("/").append(paramj40.Zs.Hc(hR3 = hR.kq)).append("/").append(paramj40.Zs.Hc(hR4 = hR.Xx)).append("/").append(paramj40.Zs.Hc(hR5 = hR.PE0)).append("/").append(paramj40.Zs.Hc(hR6 = hR.s5)).toString(); if (paramBoolean3)
/*  50 */       str3 = str3.replace("31", "[#6fb76f]31[]").replaceAll("([^0-9])0", "$1[#ff6666]0[]").replaceAll("^0/", "[#ff6666]0[]/");  stringBuilder1
/*  51 */       .append("\n" + str3);
/*     */ 
/*     */ 
/*     */ 
/*     */ 
/*     */ 
/*     */ 
/*     */ 
/*     */ 
/*     */ 
/*     */ 
/*     */ 
/*     */     
/*  64 */     stringBuilder1.append(pv.X9(1800, (new StringBuilder()).append("\n"), " ").append(paramj40.Zs.Uu0(hR1)).append("/").append(paramj40.Zs.Uu0(hR2)).append("/").append(paramj40.Zs.Uu0(hR3)).append("/").append(paramj40.Zs.Uu0(hR4)).append("/").append(paramj40.Zs.Uu0(hR5)).append("/").append(paramj40.Zs.Uu0(hR6)).toString());
/*  65 */     if (paramj40.Zs
/*  66 */       .p10() > 0)
/*     */     
/*     */     { 
/*     */       
/*  70 */       str1 = pv.X9(1842, B40.df("\n\n"), " ").append(Ml0.OH0(lPT3.Iu)).toString(); } else { str1 = ""; }  stringBuilder1.append(str1); stringBuilder1.append("\n\n" + Ml0.OH0(1843)); byte b; for (b = 0; b < 4; )
/*  71 */     { String str; StringBuilder stringBuilder = B40.df("\n");
/*  72 */       if (yk0.cw()
/*     */ 
/*     */ 
/*     */         
/*  76 */         .mP(paramj40.Zs.En0[b]) == null) { str = "-";
/*     */          }
/*     */       
/*     */       else
/*     */       
/*     */       { 
/*  82 */         str = Ml0.OH0((yk0.cw().mP(paramj40.Zs.En0[b])).iz); }  stringBuilder1
/*  83 */         .append(stringBuilder.append(str).toString()); b++; }  if (paramBoolean2 && paramj40
/*  84 */       .Zs
/*  85 */       .MN()) { stringBuilder1
/*     */         
/*  87 */         .append(B40.df("\n\n").append(Ml0.OH0(1864)).toString()); b = 0; short[] arrayOfShort; while (b < (
/*     */         
/*  89 */         arrayOfShort = paramj40.Zs.AY).length)
/*  90 */       { if (arrayOfShort[b] >= 
/*  91 */           1 && 
/*  92 */           yk0.cw()
/*     */ 
/*     */ 
/*     */           
/*  96 */           .mP(paramj40.Zs.AY[b]) != null) { stringBuilder1.append("\n"); stringBuilder1
/*     */ 
/*     */ 
/*     */ 
/*     */ 
/*     */ 
/*     */             
/* 103 */             .append(Ml0.OH0((yk0.cw().mP(paramj40.Zs.AY[b])).iz)); }  b++; }  }  return stringBuilder1.toString(); }
/*     */ 
/*     */   
/*     */   public static final DecimalFormat J2;
/*     */   
/*     */   public static String Vc(WD paramWD, Q90 paramQ90, LPT3 paramLPT3, boolean paramBoolean) {
/*     */     // Byte code:
/*     */     //   0: invokestatic bigCJKFontSizes : ()Z
/*     */     //   3: ifeq -> 13
/*     */     //   6: bipush #22
/*     */     //   8: istore #4
/*     */     //   10: goto -> 17
/*     */     //   13: bipush #38
/*     */     //   15: istore #4
/*     */     //   17: aload_0
/*     */     //   18: ifnonnull -> 24
/*     */     //   21: ldc ''
/*     */     //   23: areturn
/*     */     //   24: iload_3
/*     */     //   25: new java/lang/StringBuilder
/*     */     //   28: dup
/*     */     //   29: astore_3
/*     */     //   30: invokespecial <init> : ()V
/*     */     //   33: ifeq -> 53
/*     */     //   36: aload_3
/*     */     //   37: aload_0
/*     */     //   38: getfield iz : I
/*     */     //   41: invokestatic OH0 : (I)Ljava/lang/String;
/*     */     //   44: invokevirtual append : (Ljava/lang/String;)Ljava/lang/StringBuilder;
/*     */     //   47: ldc '\\n\\n'
/*     */     //   49: invokevirtual append : (Ljava/lang/String;)Ljava/lang/StringBuilder;
/*     */     //   52: pop
/*     */     //   53: aload_0
/*     */     //   54: aload_3
/*     */     //   55: dup
/*     */     //   56: dup
/*     */     //   57: iload #4
/*     */     //   59: aload_0
/*     */     //   60: getfield hR : I
/*     */     //   63: invokestatic OH0 : (I)Ljava/lang/String;
/*     */     //   66: ldc '|br|'
/*     */     //   68: ldc '\\n'
/*     */     //   70: invokevirtual replace : (Ljava/lang/CharSequence;Ljava/lang/CharSequence;)Ljava/lang/String;
/*     */     //   73: invokestatic JF : (ILjava/lang/String;)Ljava/lang/String;
/*     */     //   76: invokevirtual append : (Ljava/lang/String;)Ljava/lang/StringBuilder;
/*     */     //   79: pop
/*     */     //   80: ldc '\\n\\n'
/*     */     //   82: invokevirtual append : (Ljava/lang/String;)Ljava/lang/StringBuilder;
/*     */     //   85: pop
/*     */     //   86: sipush #1850
/*     */     //   89: invokestatic OH0 : (I)Ljava/lang/String;
/*     */     //   92: invokevirtual append : (Ljava/lang/String;)Ljava/lang/StringBuilder;
/*     */     //   95: ldc ' '
/*     */     //   97: invokevirtual append : (Ljava/lang/String;)Ljava/lang/StringBuilder;
/*     */     //   100: pop
/*     */     //   101: getfield HA : S
/*     */     //   104: lookupswitch default -> 172, 363 -> 238, 374 -> 228, 484 -> 218, 518 -> 175, 519 -> 175, 520 -> 175, 535 -> 218
/*     */     //   172: goto -> 248
/*     */     //   175: aload_0
/*     */     //   176: getfield Di0 : S
/*     */     //   179: ifne -> 189
/*     */     //   182: ldc '---'
/*     */     //   184: astore #5
/*     */     //   186: goto -> 208
/*     */     //   189: new java/lang/StringBuilder
/*     */     //   192: dup
/*     */     //   193: aload_0
/*     */     //   194: swap
/*     */     //   195: invokespecial <init> : ()V
/*     */     //   198: getfield Di0 : S
/*     */     //   201: ldc ' - 150'
/*     */     //   203: invokestatic Gl0 : (Ljava/lang/StringBuilder;ILjava/lang/String;)Ljava/lang/String;
/*     */     //   206: astore #5
/*     */     //   208: aload_3
/*     */     //   209: aload #5
/*     */     //   211: invokevirtual append : (Ljava/lang/String;)Ljava/lang/StringBuilder;
/*     */     //   214: pop
/*     */     //   215: goto -> 295
/*     */     //   218: aload_3
/*     */     //   219: ldc '40 - 120'
/*     */     //   221: invokevirtual append : (Ljava/lang/String;)Ljava/lang/StringBuilder;
/*     */     //   224: pop
/*     */     //   225: goto -> 295
/*     */     //   228: aload_3
/*     */     //   229: ldc '10 - 130'
/*     */     //   231: invokevirtual append : (Ljava/lang/String;)Ljava/lang/StringBuilder;
/*     */     //   234: pop
/*     */     //   235: goto -> 295
/*     */     //   238: aload_3
/*     */     //   239: ldc '80 - 100'
/*     */     //   241: invokevirtual append : (Ljava/lang/String;)Ljava/lang/StringBuilder;
/*     */     //   244: pop
/*     */     //   245: goto -> 295
/*     */     //   248: aload_0
/*     */     //   249: getfield Di0 : S
/*     */     //   252: dup
/*     */     //   253: istore #5
/*     */     //   255: ifne -> 268
/*     */     //   258: aload_3
/*     */     //   259: ldc '---'
/*     */     //   261: invokevirtual append : (Ljava/lang/String;)Ljava/lang/StringBuilder;
/*     */     //   264: pop
/*     */     //   265: goto -> 295
/*     */     //   268: iload #5
/*     */     //   270: iconst_1
/*     */     //   271: if_icmpne -> 288
/*     */     //   274: aload_3
/*     */     //   275: sipush #1867
/*     */     //   278: invokestatic OH0 : (I)Ljava/lang/String;
/*     */     //   281: invokevirtual append : (Ljava/lang/String;)Ljava/lang/StringBuilder;
/*     */     //   284: pop
/*     */     //   285: goto -> 295
/*     */     //   288: aload_3
/*     */     //   289: iload #5
/*     */     //   291: invokevirtual append : (I)Ljava/lang/StringBuilder;
/*     */     //   294: pop
/*     */     //   295: aload_0
/*     */     //   296: aload_3
/*     */     //   297: dup
/*     */     //   298: ldc '\\n'
/*     */     //   300: invokevirtual append : (Ljava/lang/String;)Ljava/lang/StringBuilder;
/*     */     //   303: pop
/*     */     //   304: sipush #1851
/*     */     //   307: invokestatic OH0 : (I)Ljava/lang/String;
/*     */     //   310: invokevirtual append : (Ljava/lang/String;)Ljava/lang/StringBuilder;
/*     */     //   313: ldc ' '
/*     */     //   315: invokevirtual append : (Ljava/lang/String;)Ljava/lang/StringBuilder;
/*     */     //   318: pop
/*     */     //   319: getfield Jp0 : B
/*     */     //   322: dup
/*     */     //   323: istore #5
/*     */     //   325: ifeq -> 348
/*     */     //   328: iload #5
/*     */     //   330: bipush #101
/*     */     //   332: if_icmpne -> 338
/*     */     //   335: goto -> 348
/*     */     //   338: iload #5
/*     */     //   340: invokestatic toString : (I)Ljava/lang/String;
/*     */     //   343: astore #5
/*     */     //   345: goto -> 352
/*     */     //   348: ldc '---'
/*     */     //   350: astore #5
/*     */     //   352: aload_0
/*     */     //   353: aload_3
/*     */     //   354: dup
/*     */     //   355: dup
/*     */     //   356: aload #5
/*     */     //   358: invokevirtual append : (Ljava/lang/String;)Ljava/lang/StringBuilder;
/*     */     //   361: pop
/*     */     //   362: ldc '\\n'
/*     */     //   364: invokevirtual append : (Ljava/lang/String;)Ljava/lang/StringBuilder;
/*     */     //   367: pop
/*     */     //   368: sipush #1852
/*     */     //   371: invokestatic OH0 : (I)Ljava/lang/String;
/*     */     //   374: invokevirtual append : (Ljava/lang/String;)Ljava/lang/StringBuilder;
/*     */     //   377: ldc ' '
/*     */     //   379: invokevirtual append : (Ljava/lang/String;)Ljava/lang/StringBuilder;
/*     */     //   382: pop
/*     */     //   383: getfield HA : S
/*     */     //   386: sipush #165
/*     */     //   389: if_icmpne -> 400
/*     */     //   392: ldc_w '∞'
/*     */     //   395: astore #5
/*     */     //   397: goto -> 409
/*     */     //   400: aload_0
/*     */     //   401: getfield nul : B
/*     */     //   404: invokestatic valueOf : (B)Ljava/lang/Byte;
/*     */     //   407: astore #5
/*     */     //   409: aload_0
/*     */     //   410: aload_3
/*     */     //   411: dup
/*     */     //   412: dup
/*     */     //   413: aload #5
/*     */     //   415: invokevirtual append : (Ljava/lang/Object;)Ljava/lang/StringBuilder;
/*     */     //   418: pop
/*     */     //   419: ldc '\\n'
/*     */     //   421: invokevirtual append : (Ljava/lang/String;)Ljava/lang/StringBuilder;
/*     */     //   424: pop
/*     */     //   425: sipush #1861
/*     */     //   428: invokestatic OH0 : (I)Ljava/lang/String;
/*     */     //   431: invokevirtual append : (Ljava/lang/String;)Ljava/lang/StringBuilder;
/*     */     //   434: ldc ' '
/*     */     //   436: invokevirtual append : (Ljava/lang/String;)Ljava/lang/StringBuilder;
/*     */     //   439: pop
/*     */     //   440: getfield VT : B
/*     */     //   443: dup
/*     */     //   444: istore #5
/*     */     //   446: ifne -> 463
/*     */     //   449: aload_3
/*     */     //   450: sipush #1862
/*     */     //   453: invokestatic OH0 : (I)Ljava/lang/String;
/*     */     //   456: invokevirtual append : (Ljava/lang/String;)Ljava/lang/StringBuilder;
/*     */     //   459: pop
/*     */     //   460: goto -> 485
/*     */     //   463: iload #5
/*     */     //   465: ifle -> 476
/*     */     //   468: aload_3
/*     */     //   469: ldc_w '+'
/*     */     //   472: invokevirtual append : (Ljava/lang/String;)Ljava/lang/StringBuilder;
/*     */     //   475: pop
/*     */     //   476: aload_3
/*     */     //   477: aload_0
/*     */     //   478: getfield VT : B
/*     */     //   481: invokevirtual append : (I)Ljava/lang/StringBuilder;
/*     */     //   484: pop
/*     */     //   485: aload_0
/*     */     //   486: aload_3
/*     */     //   487: dup
/*     */     //   488: ldc '\\n'
/*     */     //   490: invokevirtual append : (Ljava/lang/String;)Ljava/lang/StringBuilder;
/*     */     //   493: pop
/*     */     //   494: sipush #3300
/*     */     //   497: invokestatic OH0 : (I)Ljava/lang/String;
/*     */     //   500: invokevirtual append : (Ljava/lang/String;)Ljava/lang/StringBuilder;
/*     */     //   503: ldc ' '
/*     */     //   505: invokevirtual append : (Ljava/lang/String;)Ljava/lang/StringBuilder;
/*     */     //   508: pop
/*     */     //   509: getfield DD : B
/*     */     //   512: ifne -> 539
/*     */     //   515: aload_0
/*     */     //   516: sipush #2048
/*     */     //   519: invokevirtual Ve0 : (S)Z
/*     */     //   522: ifne -> 539
/*     */     //   525: aload_3
/*     */     //   526: sipush #3349
/*     */     //   529: invokestatic OH0 : (I)Ljava/lang/String;
/*     */     //   532: invokevirtual append : (Ljava/lang/String;)Ljava/lang/StringBuilder;
/*     */     //   535: pop
/*     */     //   536: goto -> 555
/*     */     //   539: aload_3
/*     */     //   540: aload_0
/*     */     //   541: getfield DD : B
/*     */     //   544: sipush #3350
/*     */     //   547: iadd
/*     */     //   548: invokestatic OH0 : (I)Ljava/lang/String;
/*     */     //   551: invokevirtual append : (Ljava/lang/String;)Ljava/lang/StringBuilder;
/*     */     //   554: pop
/*     */     //   555: aload_0
/*     */     //   556: aload_3
/*     */     //   557: ldc '\\n'
/*     */     //   559: invokevirtual append : (Ljava/lang/String;)Ljava/lang/StringBuilder;
/*     */     //   562: pop
/*     */     //   563: getfield HA : S
/*     */     //   566: dup
/*     */     //   567: istore #5
/*     */     //   569: sipush #518
/*     */     //   572: if_icmpeq -> 1321
/*     */     //   575: iload #5
/*     */     //   577: sipush #519
/*     */     //   580: if_icmpeq -> 1321
/*     */     //   583: iload #5
/*     */     //   585: sipush #520
/*     */     //   588: if_icmpne -> 594
/*     */     //   591: goto -> 1321
/*     */     //   594: aload_1
/*     */     //   595: ifnull -> 1778
/*     */     //   598: aload_2
/*     */     //   599: ifnull -> 1202
/*     */     //   602: iload #5
/*     */     //   604: sipush #374
/*     */     //   607: if_icmpne -> 1031
/*     */     //   610: aload_2
/*     */     //   611: getfield Is : S
/*     */     //   614: dup
/*     */     //   615: istore #5
/*     */     //   617: ifgt -> 666
/*     */     //   620: aload_2
/*     */     //   621: getfield uL : Z
/*     */     //   624: ifeq -> 630
/*     */     //   627: goto -> 666
/*     */     //   630: aload_3
/*     */     //   631: dup
/*     */     //   632: aload_2
/*     */     //   633: aload_3
/*     */     //   634: ldc '\\n'
/*     */     //   636: invokevirtual append : (Ljava/lang/String;)Ljava/lang/StringBuilder;
/*     */     //   639: pop
/*     */     //   640: getfield Iu : I
/*     */     //   643: invokestatic OH0 : (I)Ljava/lang/String;
/*     */     //   646: sipush #3517
/*     */     //   649: swap
/*     */     //   650: invokestatic Go : (ILjava/lang/String;)Ljava/lang/String;
/*     */     //   653: invokevirtual append : (Ljava/lang/String;)Ljava/lang/StringBuilder;
/*     */     //   656: pop
/*     */     //   657: ldc '\\n'
/*     */     //   659: invokevirtual append : (Ljava/lang/String;)Ljava/lang/StringBuilder;
/*     */     //   662: pop
/*     */     //   663: goto -> 1202
/*     */     //   666: iload #5
/*     */     //   668: iconst_1
/*     */     //   669: if_icmpge -> 676
/*     */     //   672: bipush #10
/*     */     //   674: istore #5
/*     */     //   676: aload_2
/*     */     //   677: aload_3
/*     */     //   678: iload #5
/*     */     //   680: aload_3
/*     */     //   681: dup
/*     */     //   682: dup2
/*     */     //   683: aload_2
/*     */     //   684: aload_3
/*     */     //   685: ldc '\\n'
/*     */     //   687: invokevirtual append : (Ljava/lang/String;)Ljava/lang/StringBuilder;
/*     */     //   690: pop
/*     */     //   691: getfield Iu : I
/*     */     //   694: invokestatic OH0 : (I)Ljava/lang/String;
/*     */     //   697: sipush #3515
/*     */     //   700: swap
/*     */     //   701: invokestatic Go : (ILjava/lang/String;)Ljava/lang/String;
/*     */     //   704: invokevirtual append : (Ljava/lang/String;)Ljava/lang/StringBuilder;
/*     */     //   707: pop
/*     */     //   708: ldc_w '\\n▶ '
/*     */     //   711: invokevirtual append : (Ljava/lang/String;)Ljava/lang/StringBuilder;
/*     */     //   714: pop
/*     */     //   715: sipush #1850
/*     */     //   718: invokestatic OH0 : (I)Ljava/lang/String;
/*     */     //   721: invokevirtual append : (Ljava/lang/String;)Ljava/lang/StringBuilder;
/*     */     //   724: pop
/*     */     //   725: ldc ' '
/*     */     //   727: invokevirtual append : (Ljava/lang/String;)Ljava/lang/StringBuilder;
/*     */     //   730: pop
/*     */     //   731: invokestatic toString : (I)Ljava/lang/String;
/*     */     //   734: invokevirtual append : (Ljava/lang/String;)Ljava/lang/StringBuilder;
/*     */     //   737: pop
/*     */     //   738: getfield uL : Z
/*     */     //   741: ifeq -> 771
/*     */     //   744: aload_3
/*     */     //   745: aload_2
/*     */     //   746: aload_3
/*     */     //   747: ldc_w '\\n▶ '
/*     */     //   750: invokevirtual append : (Ljava/lang/String;)Ljava/lang/StringBuilder;
/*     */     //   753: pop
/*     */     //   754: getfield Iu : I
/*     */     //   757: invokestatic OH0 : (I)Ljava/lang/String;
/*     */     //   760: sipush #3516
/*     */     //   763: swap
/*     */     //   764: invokestatic Go : (ILjava/lang/String;)Ljava/lang/String;
/*     */     //   767: invokevirtual append : (Ljava/lang/String;)Ljava/lang/StringBuilder;
/*     */     //   770: pop
/*     */     //   771: aload_2
/*     */     //   772: getfield bj0 : S
/*     */     //   775: invokestatic l90 : (S)S
/*     */     //   778: lookupswitch default -> 852, 5214 -> 1002, 5219 -> 980, 5221 -> 955, 5236 -> 930, 5245 -> 905, 5272 -> 880, 5273 -> 855, 5327 -> 955
/*     */     //   852: goto -> 1021
/*     */     //   855: aload_3
/*     */     //   856: dup
/*     */     //   857: ldc_w '\\n▶ '
/*     */     //   860: invokevirtual append : (Ljava/lang/String;)Ljava/lang/StringBuilder;
/*     */     //   863: pop
/*     */     //   864: sipush #3501
/*     */     //   867: ldc_w '100'
/*     */     //   870: invokestatic Go : (ILjava/lang/String;)Ljava/lang/String;
/*     */     //   873: invokevirtual append : (Ljava/lang/String;)Ljava/lang/StringBuilder;
/*     */     //   876: pop
/*     */     //   877: goto -> 1021
/*     */     //   880: aload_3
/*     */     //   881: dup
/*     */     //   882: ldc_w '\\n▶ '
/*     */     //   885: invokevirtual append : (Ljava/lang/String;)Ljava/lang/StringBuilder;
/*     */     //   888: pop
/*     */     //   889: sipush #3505
/*     */     //   892: ldc_w '100'
/*     */     //   895: invokestatic Go : (ILjava/lang/String;)Ljava/lang/String;
/*     */     //   898: invokevirtual append : (Ljava/lang/String;)Ljava/lang/StringBuilder;
/*     */     //   901: pop
/*     */     //   902: goto -> 1021
/*     */     //   905: aload_3
/*     */     //   906: dup
/*     */     //   907: ldc_w '\\n▶ '
/*     */     //   910: invokevirtual append : (Ljava/lang/String;)Ljava/lang/StringBuilder;
/*     */     //   913: pop
/*     */     //   914: sipush #3504
/*     */     //   917: ldc_w '100'
/*     */     //   920: invokestatic Go : (ILjava/lang/String;)Ljava/lang/String;
/*     */     //   923: invokevirtual append : (Ljava/lang/String;)Ljava/lang/StringBuilder;
/*     */     //   926: pop
/*     */     //   927: goto -> 1021
/*     */     //   930: aload_3
/*     */     //   931: dup
/*     */     //   932: ldc_w '\\n▶ '
/*     */     //   935: invokevirtual append : (Ljava/lang/String;)Ljava/lang/StringBuilder;
/*     */     //   938: pop
/*     */     //   939: sipush #3502
/*     */     //   942: ldc_w '100'
/*     */     //   945: invokestatic Go : (ILjava/lang/String;)Ljava/lang/String;
/*     */     //   948: invokevirtual append : (Ljava/lang/String;)Ljava/lang/StringBuilder;
/*     */     //   951: pop
/*     */     //   952: goto -> 1021
/*     */     //   955: aload_3
/*     */     //   956: dup
/*     */     //   957: ldc_w '\\n▶ '
/*     */     //   960: invokevirtual append : (Ljava/lang/String;)Ljava/lang/StringBuilder;
/*     */     //   963: pop
/*     */     //   964: sipush #3500
/*     */     //   967: ldc_w '100'
/*     */     //   970: invokestatic Go : (ILjava/lang/String;)Ljava/lang/String;
/*     */     //   973: invokevirtual append : (Ljava/lang/String;)Ljava/lang/StringBuilder;
/*     */     //   976: pop
/*     */     //   977: goto -> 1021
/*     */     //   980: aload_3
/*     */     //   981: dup
/*     */     //   982: ldc_w '\\n▶ '
/*     */     //   985: invokevirtual append : (Ljava/lang/String;)Ljava/lang/StringBuilder;
/*     */     //   988: pop
/*     */     //   989: sipush #3513
/*     */     //   992: invokestatic OH0 : (I)Ljava/lang/String;
/*     */     //   995: invokevirtual append : (Ljava/lang/String;)Ljava/lang/StringBuilder;
/*     */     //   998: pop
/*     */     //   999: goto -> 1021
/*     */     //   1002: aload_3
/*     */     //   1003: dup
/*     */     //   1004: ldc_w '\\n▶ '
/*     */     //   1007: invokevirtual append : (Ljava/lang/String;)Ljava/lang/StringBuilder;
/*     */     //   1010: pop
/*     */     //   1011: sipush #3514
/*     */     //   1014: invokestatic OH0 : (I)Ljava/lang/String;
/*     */     //   1017: invokevirtual append : (Ljava/lang/String;)Ljava/lang/StringBuilder;
/*     */     //   1020: pop
/*     */     //   1021: aload_3
/*     */     //   1022: ldc '\\n'
/*     */     //   1024: invokevirtual append : (Ljava/lang/String;)Ljava/lang/StringBuilder;
/*     */     //   1027: pop
/*     */     //   1028: goto -> 1202
/*     */     //   1031: iload #5
/*     */     //   1033: sipush #363
/*     */     //   1036: if_icmpne -> 1202
/*     */     //   1039: aload_2
/*     */     //   1040: getfield de0 : Lf/Ht0;
/*     */     //   1043: getstatic f/Ht0.P00 : Lf/Ht0;
/*     */     //   1046: if_acmpeq -> 1176
/*     */     //   1049: aload_2
/*     */     //   1050: getfield m20 : B
/*     */     //   1053: ifle -> 1176
/*     */     //   1056: aload_3
/*     */     //   1057: aload_2
/*     */     //   1058: aload_3
/*     */     //   1059: dup
/*     */     //   1060: aload_2
/*     */     //   1061: aload_3
/*     */     //   1062: dup
/*     */     //   1063: aload_2
/*     */     //   1064: aload_3
/*     */     //   1065: dup
/*     */     //   1066: dup2
/*     */     //   1067: aload_2
/*     */     //   1068: aload_3
/*     */     //   1069: ldc '\\n'
/*     */     //   1071: invokevirtual append : (Ljava/lang/String;)Ljava/lang/StringBuilder;
/*     */     //   1074: pop
/*     */     //   1075: getfield Iu : I
/*     */     //   1078: invokestatic OH0 : (I)Ljava/lang/String;
/*     */     //   1081: sipush #3515
/*     */     //   1084: swap
/*     */     //   1085: invokestatic Go : (ILjava/lang/String;)Ljava/lang/String;
/*     */     //   1088: invokevirtual append : (Ljava/lang/String;)Ljava/lang/StringBuilder;
/*     */     //   1091: pop
/*     */     //   1092: ldc_w '\\n▶ '
/*     */     //   1095: invokevirtual append : (Ljava/lang/String;)Ljava/lang/StringBuilder;
/*     */     //   1098: pop
/*     */     //   1099: sipush #1850
/*     */     //   1102: invokestatic OH0 : (I)Ljava/lang/String;
/*     */     //   1105: invokevirtual append : (Ljava/lang/String;)Ljava/lang/StringBuilder;
/*     */     //   1108: pop
/*     */     //   1109: ldc ' '
/*     */     //   1111: invokevirtual append : (Ljava/lang/String;)Ljava/lang/StringBuilder;
/*     */     //   1114: pop
/*     */     //   1115: getfield m20 : B
/*     */     //   1118: invokestatic toString : (I)Ljava/lang/String;
/*     */     //   1121: invokevirtual append : (Ljava/lang/String;)Ljava/lang/StringBuilder;
/*     */     //   1124: pop
/*     */     //   1125: ldc_w '\\n▶ '
/*     */     //   1128: invokevirtual append : (Ljava/lang/String;)Ljava/lang/StringBuilder;
/*     */     //   1131: pop
/*     */     //   1132: getfield Iu : I
/*     */     //   1135: invokestatic OH0 : (I)Ljava/lang/String;
/*     */     //   1138: sipush #3516
/*     */     //   1141: swap
/*     */     //   1142: invokestatic Go : (ILjava/lang/String;)Ljava/lang/String;
/*     */     //   1145: invokevirtual append : (Ljava/lang/String;)Ljava/lang/StringBuilder;
/*     */     //   1148: pop
/*     */     //   1149: ldc_w '\\n▶ '
/*     */     //   1152: invokevirtual append : (Ljava/lang/String;)Ljava/lang/StringBuilder;
/*     */     //   1155: pop
/*     */     //   1156: getfield de0 : Lf/Ht0;
/*     */     //   1159: invokevirtual mn0 : ()Ljava/lang/String;
/*     */     //   1162: sipush #3518
/*     */     //   1165: swap
/*     */     //   1166: invokestatic Go : (ILjava/lang/String;)Ljava/lang/String;
/*     */     //   1169: invokevirtual append : (Ljava/lang/String;)Ljava/lang/StringBuilder;
/*     */     //   1172: pop
/*     */     //   1173: goto -> 1202
/*     */     //   1176: aload_3
/*     */     //   1177: aload_2
/*     */     //   1178: aload_3
/*     */     //   1179: ldc '\\n'
/*     */     //   1181: invokevirtual append : (Ljava/lang/String;)Ljava/lang/StringBuilder;
/*     */     //   1184: pop
/*     */     //   1185: getfield Iu : I
/*     */     //   1188: invokestatic OH0 : (I)Ljava/lang/String;
/*     */     //   1191: sipush #3517
/*     */     //   1194: swap
/*     */     //   1195: invokestatic Go : (ILjava/lang/String;)Ljava/lang/String;
/*     */     //   1198: invokevirtual append : (Ljava/lang/String;)Ljava/lang/StringBuilder;
/*     */     //   1201: pop
/*     */     //   1202: invokestatic v30 : ()Lf/On;
/*     */     //   1205: aload_1
/*     */     //   1206: getfield Cw0 : S
/*     */     //   1209: invokevirtual lpT3 : (S)Lf/UD0;
/*     */     //   1212: astore_2
/*     */     //   1213: invokestatic v30 : ()Lf/On;
/*     */     //   1216: aload_2
/*     */     //   1217: getfield TL : S
/*     */     //   1220: aload_1
/*     */     //   1221: getfield Vp : B
/*     */     //   1224: iadd
/*     */     //   1225: iconst_1
/*     */     //   1226: isub
/*     */     //   1227: i2s
/*     */     //   1228: invokevirtual lpT3 : (S)Lf/UD0;
/*     */     //   1231: dup
/*     */     //   1232: astore #5
/*     */     //   1234: ifnull -> 1240
/*     */     //   1237: aload #5
/*     */     //   1239: astore_2
/*     */     //   1240: aload_0
/*     */     //   1241: getfield Di0 : S
/*     */     //   1244: ifle -> 1778
/*     */     //   1247: aload_2
/*     */     //   1248: aload_1
/*     */     //   1249: aload_0
/*     */     //   1250: aload_1
/*     */     //   1251: aconst_null
/*     */     //   1252: invokevirtual Wt : (Lf/Q90;Lf/Mx;)Lf/Ht0;
/*     */     //   1255: astore_1
/*     */     //   1256: getfield Vp : B
/*     */     //   1259: dup
/*     */     //   1260: istore #5
/*     */     //   1262: invokevirtual Sl0 : (B)Lf/Ht0;
/*     */     //   1265: aload_1
/*     */     //   1266: if_acmpeq -> 1286
/*     */     //   1269: aload_2
/*     */     //   1270: iload #5
/*     */     //   1272: invokevirtual pf0 : (B)Lf/Ht0;
/*     */     //   1275: aload_1
/*     */     //   1276: if_acmpne -> 1282
/*     */     //   1279: goto -> 1286
/*     */     //   1282: iconst_0
/*     */     //   1283: goto -> 1287
/*     */     //   1286: iconst_1
/*     */     //   1287: ifeq -> 1778
/*     */     //   1290: aload_3
/*     */     //   1291: iload #4
/*     */     //   1293: aload_3
/*     */     //   1294: ldc_w '\\n▶ '
/*     */     //   1297: invokevirtual append : (Ljava/lang/String;)Ljava/lang/StringBuilder;
/*     */     //   1300: pop
/*     */     //   1301: sipush #3511
/*     */     //   1304: invokestatic OH0 : (I)Ljava/lang/String;
/*     */     //   1307: ldc_w '\\n   '
/*     */     //   1310: iconst_1
/*     */     //   1311: invokestatic oF : (ILjava/lang/String;Ljava/lang/String;Z)Ljava/lang/String;
/*     */     //   1314: invokevirtual append : (Ljava/lang/String;)Ljava/lang/StringBuilder;
/*     */     //   1317: pop
/*     */     //   1318: goto -> 1778
/*     */     //   1321: aload_0
/*     */     //   1322: aload_3
/*     */     //   1323: iload #4
/*     */     //   1325: aload_3
/*     */     //   1326: ldc_w '\\n▶ '
/*     */     //   1329: invokevirtual append : (Ljava/lang/String;)Ljava/lang/StringBuilder;
/*     */     //   1332: pop
/*     */     //   1333: ldc_w 200432
/*     */     //   1336: invokestatic OH0 : (I)Ljava/lang/String;
/*     */     //   1339: ldc_w '\\n   '
/*     */     //   1342: iconst_1
/*     */     //   1343: invokestatic oF : (ILjava/lang/String;Ljava/lang/String;Z)Ljava/lang/String;
/*     */     //   1346: invokevirtual append : (Ljava/lang/String;)Ljava/lang/StringBuilder;
/*     */     //   1349: pop
/*     */     //   1350: getfield HA : S
/*     */     //   1353: tableswitch default -> 1380, 518 -> 1611, 519 -> 1497, 520 -> 1383
/*     */     //   1380: goto -> 1722
/*     */     //   1383: aload_3
/*     */     //   1384: dup
/*     */     //   1385: ldc_w '\\n  •'
/*     */     //   1388: invokestatic df : (Ljava/lang/String;)Ljava/lang/StringBuilder;
/*     */     //   1391: iload #4
/*     */     //   1393: new java/lang/StringBuilder
/*     */     //   1396: dup
/*     */     //   1397: astore_1
/*     */     //   1398: invokespecial <init> : ()V
/*     */     //   1401: ldc_w 110519
/*     */     //   1404: aload_1
/*     */     //   1405: ldc_w ': '
/*     */     //   1408: invokestatic X9 : (ILjava/lang/StringBuilder;Ljava/lang/String;)Ljava/lang/StringBuilder;
/*     */     //   1411: ldc_w 200434
/*     */     //   1414: invokestatic OH0 : (I)Ljava/lang/String;
/*     */     //   1417: invokevirtual append : (Ljava/lang/String;)Ljava/lang/StringBuilder;
/*     */     //   1420: invokevirtual toString : ()Ljava/lang/String;
/*     */     //   1423: invokestatic JF : (ILjava/lang/String;)Ljava/lang/String;
/*     */     //   1426: invokevirtual append : (Ljava/lang/String;)Ljava/lang/StringBuilder;
/*     */     //   1429: invokevirtual toString : ()Ljava/lang/String;
/*     */     //   1432: invokevirtual append : (Ljava/lang/String;)Ljava/lang/StringBuilder;
/*     */     //   1435: pop
/*     */     //   1436: new java/lang/StringBuilder
/*     */     //   1439: dup
/*     */     //   1440: invokespecial <init> : ()V
/*     */     //   1443: ldc_w '\\n  •'
/*     */     //   1446: invokevirtual append : (Ljava/lang/String;)Ljava/lang/StringBuilder;
/*     */     //   1449: iload #4
/*     */     //   1451: new java/lang/StringBuilder
/*     */     //   1454: dup
/*     */     //   1455: astore_1
/*     */     //   1456: invokespecial <init> : ()V
/*     */     //   1459: ldc_w 110518
/*     */     //   1462: aload_1
/*     */     //   1463: ldc_w ': '
/*     */     //   1466: invokestatic X9 : (ILjava/lang/StringBuilder;Ljava/lang/String;)Ljava/lang/StringBuilder;
/*     */     //   1469: ldc_w 200433
/*     */     //   1472: invokestatic OH0 : (I)Ljava/lang/String;
/*     */     //   1475: invokevirtual append : (Ljava/lang/String;)Ljava/lang/StringBuilder;
/*     */     //   1478: invokevirtual toString : ()Ljava/lang/String;
/*     */     //   1481: invokestatic JF : (ILjava/lang/String;)Ljava/lang/String;
/*     */     //   1484: invokevirtual append : (Ljava/lang/String;)Ljava/lang/StringBuilder;
/*     */     //   1487: invokevirtual toString : ()Ljava/lang/String;
/*     */     //   1490: invokevirtual append : (Ljava/lang/String;)Ljava/lang/StringBuilder;
/*     */     //   1493: pop
/*     */     //   1494: goto -> 1722
/*     */     //   1497: aload_3
/*     */     //   1498: dup
/*     */     //   1499: ldc_w '\\n  •'
/*     */     //   1502: invokestatic df : (Ljava/lang/String;)Ljava/lang/StringBuilder;
/*     */     //   1505: iload #4
/*     */     //   1507: new java/lang/StringBuilder
/*     */     //   1510: dup
/*     */     //   1511: astore_1
/*     */     //   1512: invokespecial <init> : ()V
/*     */     //   1515: ldc_w 110518
/*     */     //   1518: aload_1
/*     */     //   1519: ldc_w ': '
/*     */     //   1522: invokestatic X9 : (ILjava/lang/StringBuilder;Ljava/lang/String;)Ljava/lang/StringBuilder;
/*     */     //   1525: ldc_w 200435
/*     */     //   1528: invokestatic OH0 : (I)Ljava/lang/String;
/*     */     //   1531: invokevirtual append : (Ljava/lang/String;)Ljava/lang/StringBuilder;
/*     */     //   1534: invokevirtual toString : ()Ljava/lang/String;
/*     */     //   1537: invokestatic JF : (ILjava/lang/String;)Ljava/lang/String;
/*     */     //   1540: invokevirtual append : (Ljava/lang/String;)Ljava/lang/StringBuilder;
/*     */     //   1543: invokevirtual toString : ()Ljava/lang/String;
/*     */     //   1546: invokevirtual append : (Ljava/lang/String;)Ljava/lang/StringBuilder;
/*     */     //   1549: pop
/*     */     //   1550: new java/lang/StringBuilder
/*     */     //   1553: dup
/*     */     //   1554: invokespecial <init> : ()V
/*     */     //   1557: ldc_w '\\n  •'
/*     */     //   1560: invokevirtual append : (Ljava/lang/String;)Ljava/lang/StringBuilder;
/*     */     //   1563: iload #4
/*     */     //   1565: new java/lang/StringBuilder
/*     */     //   1568: dup
/*     */     //   1569: astore_1
/*     */     //   1570: invokespecial <init> : ()V
/*     */     //   1573: ldc_w 110520
/*     */     //   1576: aload_1
/*     */     //   1577: ldc_w ': '
/*     */     //   1580: invokestatic X9 : (ILjava/lang/StringBuilder;Ljava/lang/String;)Ljava/lang/StringBuilder;
/*     */     //   1583: ldc_w 200434
/*     */     //   1586: invokestatic OH0 : (I)Ljava/lang/String;
/*     */     //   1589: invokevirtual append : (Ljava/lang/String;)Ljava/lang/StringBuilder;
/*     */     //   1592: invokevirtual toString : ()Ljava/lang/String;
/*     */     //   1595: invokestatic JF : (ILjava/lang/String;)Ljava/lang/String;
/*     */     //   1598: invokevirtual append : (Ljava/lang/String;)Ljava/lang/StringBuilder;
/*     */     //   1601: invokevirtual toString : ()Ljava/lang/String;
/*     */     //   1604: invokevirtual append : (Ljava/lang/String;)Ljava/lang/StringBuilder;
/*     */     //   1607: pop
/*     */     //   1608: goto -> 1722
/*     */     //   1611: aload_3
/*     */     //   1612: dup
/*     */     //   1613: ldc_w '\\n  •'
/*     */     //   1616: invokestatic df : (Ljava/lang/String;)Ljava/lang/StringBuilder;
/*     */     //   1619: iload #4
/*     */     //   1621: new java/lang/StringBuilder
/*     */     //   1624: dup
/*     */     //   1625: astore_1
/*     */     //   1626: invokespecial <init> : ()V
/*     */     //   1629: ldc_w 110519
/*     */     //   1632: aload_1
/*     */     //   1633: ldc_w ': '
/*     */     //   1636: invokestatic X9 : (ILjava/lang/StringBuilder;Ljava/lang/String;)Ljava/lang/StringBuilder;
/*     */     //   1639: ldc_w 200435
/*     */     //   1642: invokestatic OH0 : (I)Ljava/lang/String;
/*     */     //   1645: invokevirtual append : (Ljava/lang/String;)Ljava/lang/StringBuilder;
/*     */     //   1648: invokevirtual toString : ()Ljava/lang/String;
/*     */     //   1651: invokestatic JF : (ILjava/lang/String;)Ljava/lang/String;
/*     */     //   1654: invokevirtual append : (Ljava/lang/String;)Ljava/lang/StringBuilder;
/*     */     //   1657: invokevirtual toString : ()Ljava/lang/String;
/*     */     //   1660: invokevirtual append : (Ljava/lang/String;)Ljava/lang/StringBuilder;
/*     */     //   1663: pop
/*     */     //   1664: new java/lang/StringBuilder
/*     */     //   1667: dup
/*     */     //   1668: invokespecial <init> : ()V
/*     */     //   1671: ldc_w '\\n  •'
/*     */     //   1674: invokevirtual append : (Ljava/lang/String;)Ljava/lang/StringBuilder;
/*     */     //   1677: iload #4
/*     */     //   1679: new java/lang/StringBuilder
/*     */     //   1682: dup
/*     */     //   1683: astore_1
/*     */     //   1684: invokespecial <init> : ()V
/*     */     //   1687: ldc_w 110520
/*     */     //   1690: aload_1
/*     */     //   1691: ldc_w ': '
/*     */     //   1694: invokestatic X9 : (ILjava/lang/StringBuilder;Ljava/lang/String;)Ljava/lang/StringBuilder;
/*     */     //   1697: ldc_w 200433
/*     */     //   1700: invokestatic OH0 : (I)Ljava/lang/String;
/*     */     //   1703: invokevirtual append : (Ljava/lang/String;)Ljava/lang/StringBuilder;
/*     */     //   1706: invokevirtual toString : ()Ljava/lang/String;
/*     */     //   1709: invokestatic JF : (ILjava/lang/String;)Ljava/lang/String;
/*     */     //   1712: invokevirtual append : (Ljava/lang/String;)Ljava/lang/StringBuilder;
/*     */     //   1715: invokevirtual toString : ()Ljava/lang/String;
/*     */     //   1718: invokevirtual append : (Ljava/lang/String;)Ljava/lang/StringBuilder;
/*     */     //   1721: pop
/*     */     //   1722: aload_3
/*     */     //   1723: iload #4
/*     */     //   1725: aload_3
/*     */     //   1726: dup
/*     */     //   1727: iload #4
/*     */     //   1729: aload_3
/*     */     //   1730: ldc_w '\\n▶ '
/*     */     //   1733: invokevirtual append : (Ljava/lang/String;)Ljava/lang/StringBuilder;
/*     */     //   1736: pop
/*     */     //   1737: sipush #3512
/*     */     //   1740: invokestatic OH0 : (I)Ljava/lang/String;
/*     */     //   1743: ldc_w '\\n   '
/*     */     //   1746: iconst_1
/*     */     //   1747: invokestatic oF : (ILjava/lang/String;Ljava/lang/String;Z)Ljava/lang/String;
/*     */     //   1750: invokevirtual append : (Ljava/lang/String;)Ljava/lang/StringBuilder;
/*     */     //   1753: pop
/*     */     //   1754: ldc_w '\\n▶ '
/*     */     //   1757: invokevirtual append : (Ljava/lang/String;)Ljava/lang/StringBuilder;
/*     */     //   1760: pop
/*     */     //   1761: sipush #3408
/*     */     //   1764: invokestatic OH0 : (I)Ljava/lang/String;
/*     */     //   1767: ldc_w '\\n   '
/*     */     //   1770: iconst_1
/*     */     //   1771: invokestatic oF : (ILjava/lang/String;Ljava/lang/String;Z)Ljava/lang/String;
/*     */     //   1774: invokevirtual append : (Ljava/lang/String;)Ljava/lang/StringBuilder;
/*     */     //   1777: pop
/*     */     //   1778: aload_0
/*     */     //   1779: getfield XT : B
/*     */     //   1782: dup
/*     */     //   1783: istore_1
/*     */     //   1784: ifle -> 1892
/*     */     //   1787: iload_1
/*     */     //   1788: iconst_3
/*     */     //   1789: if_icmplt -> 1817
/*     */     //   1792: aload_3
/*     */     //   1793: dup
/*     */     //   1794: ldc_w '\\n▶ '
/*     */     //   1797: invokevirtual append : (Ljava/lang/String;)Ljava/lang/StringBuilder;
/*     */     //   1800: pop
/*     */     //   1801: sipush #3520
/*     */     //   1804: ldc_w '100'
/*     */     //   1807: invokestatic Go : (ILjava/lang/String;)Ljava/lang/String;
/*     */     //   1810: invokevirtual append : (Ljava/lang/String;)Ljava/lang/StringBuilder;
/*     */     //   1813: pop
/*     */     //   1814: goto -> 1892
/*     */     //   1817: aload_3
/*     */     //   1818: dup
/*     */     //   1819: dup2
/*     */     //   1820: ldc_w '\\n▶ '
/*     */     //   1823: invokevirtual append : (Ljava/lang/String;)Ljava/lang/StringBuilder;
/*     */     //   1826: pop
/*     */     //   1827: getstatic f/rG0.J2 : Ljava/text/DecimalFormat;
/*     */     //   1830: getstatic f/sH0.cx0 : [I
/*     */     //   1833: iload_1
/*     */     //   1834: iaload
/*     */     //   1835: i2d
/*     */     //   1836: ldc2_w 100.0
/*     */     //   1839: ddiv
/*     */     //   1840: invokevirtual format : (D)Ljava/lang/String;
/*     */     //   1843: sipush #3520
/*     */     //   1846: swap
/*     */     //   1847: invokestatic Go : (ILjava/lang/String;)Ljava/lang/String;
/*     */     //   1850: invokevirtual append : (Ljava/lang/String;)Ljava/lang/StringBuilder;
/*     */     //   1853: pop
/*     */     //   1854: ldc_w '\\n▶ '
/*     */     //   1857: invokevirtual append : (Ljava/lang/String;)Ljava/lang/StringBuilder;
/*     */     //   1860: pop
/*     */     //   1861: new java/lang/StringBuilder
/*     */     //   1864: dup
/*     */     //   1865: invokespecial <init> : ()V
/*     */     //   1868: ldc_w '+'
/*     */     //   1871: invokevirtual append : (Ljava/lang/String;)Ljava/lang/StringBuilder;
/*     */     //   1874: iload_1
/*     */     //   1875: invokevirtual append : (I)Ljava/lang/StringBuilder;
/*     */     //   1878: invokevirtual toString : ()Ljava/lang/String;
/*     */     //   1881: sipush #3519
/*     */     //   1884: swap
/*     */     //   1885: invokestatic Go : (ILjava/lang/String;)Ljava/lang/String;
/*     */     //   1888: invokevirtual append : (Ljava/lang/String;)Ljava/lang/StringBuilder;
/*     */     //   1891: pop
/*     */     //   1892: aload_0
/*     */     //   1893: getfield oV : B
/*     */     //   1896: dup
/*     */     //   1897: istore_1
/*     */     //   1898: ifle -> 2446
/*     */     //   1901: aload_0
/*     */     //   1902: dup
/*     */     //   1903: aload_3
/*     */     //   1904: ldc_w '\\n▶ '
/*     */     //   1907: invokevirtual append : (Ljava/lang/String;)Ljava/lang/StringBuilder;
/*     */     //   1910: pop
/*     */     //   1911: getfield ha : B
/*     */     //   1914: istore_2
/*     */     //   1915: getfield Zo : Z
/*     */     //   1918: ifne -> 2056
/*     */     //   1921: aload_0
/*     */     //   1922: getfield DD : B
/*     */     //   1925: bipush #7
/*     */     //   1927: if_icmpne -> 1933
/*     */     //   1930: goto -> 2056
/*     */     //   1933: iload_2
/*     */     //   1934: ifle -> 1995
/*     */     //   1937: aload_3
/*     */     //   1938: iload #4
/*     */     //   1940: iconst_3
/*     */     //   1941: anewarray java/lang/String
/*     */     //   1944: dup
/*     */     //   1945: astore #5
/*     */     //   1947: iload_2
/*     */     //   1948: aload #5
/*     */     //   1950: aload_0
/*     */     //   1951: aload #5
/*     */     //   1953: iload_1
/*     */     //   1954: invokestatic toString : (B)Ljava/lang/String;
/*     */     //   1957: iconst_0
/*     */     //   1958: swap
/*     */     //   1959: aastore
/*     */     //   1960: getfield sK0 : [Lf/hR;
/*     */     //   1963: invokestatic sW : ([Lf/hR;)Ljava/lang/String;
/*     */     //   1966: iconst_1
/*     */     //   1967: swap
/*     */     //   1968: aastore
/*     */     //   1969: invokestatic toString : (B)Ljava/lang/String;
/*     */     //   1972: iconst_2
/*     */     //   1973: swap
/*     */     //   1974: aastore
/*     */     //   1975: sipush #3546
/*     */     //   1978: aload #5
/*     */     //   1980: invokestatic sB : (I[Ljava/lang/String;)Ljava/lang/String;
/*     */     //   1983: aconst_null
/*     */     //   1984: iconst_1
/*     */     //   1985: invokestatic oF : (ILjava/lang/String;Ljava/lang/String;Z)Ljava/lang/String;
/*     */     //   1988: invokevirtual append : (Ljava/lang/String;)Ljava/lang/StringBuilder;
/*     */     //   1991: pop
/*     */     //   1992: goto -> 2176
/*     */     //   1995: aload_3
/*     */     //   1996: iload #4
/*     */     //   1998: iconst_3
/*     */     //   1999: anewarray java/lang/String
/*     */     //   2002: dup
/*     */     //   2003: astore #5
/*     */     //   2005: iload_2
/*     */     //   2006: aload #5
/*     */     //   2008: aload_0
/*     */     //   2009: aload #5
/*     */     //   2011: iload_1
/*     */     //   2012: invokestatic toString : (B)Ljava/lang/String;
/*     */     //   2015: iconst_0
/*     */     //   2016: swap
/*     */     //   2017: aastore
/*     */     //   2018: getfield sK0 : [Lf/hR;
/*     */     //   2021: invokestatic sW : ([Lf/hR;)Ljava/lang/String;
/*     */     //   2024: iconst_1
/*     */     //   2025: swap
/*     */     //   2026: aastore
/*     */     //   2027: iconst_m1
/*     */     //   2028: imul
/*     */     //   2029: i2b
/*     */     //   2030: invokestatic toString : (B)Ljava/lang/String;
/*     */     //   2033: iconst_2
/*     */     //   2034: swap
/*     */     //   2035: aastore
/*     */     //   2036: sipush #3548
/*     */     //   2039: aload #5
/*     */     //   2041: invokestatic sB : (I[Ljava/lang/String;)Ljava/lang/String;
/*     */     //   2044: aconst_null
/*     */     //   2045: iconst_1
/*     */     //   2046: invokestatic oF : (ILjava/lang/String;Ljava/lang/String;Z)Ljava/lang/String;
/*     */     //   2049: invokevirtual append : (Ljava/lang/String;)Ljava/lang/StringBuilder;
/*     */     //   2052: pop
/*     */     //   2053: goto -> 2176
/*     */     //   2056: iload_2
/*     */     //   2057: ifle -> 2118
/*     */     //   2060: aload_3
/*     */     //   2061: iload #4
/*     */     //   2063: iconst_3
/*     */     //   2064: anewarray java/lang/String
/*     */     //   2067: dup
/*     */     //   2068: astore #5
/*     */     //   2070: iload_2
/*     */     //   2071: aload #5
/*     */     //   2073: aload_0
/*     */     //   2074: aload #5
/*     */     //   2076: iload_1
/*     */     //   2077: invokestatic toString : (B)Ljava/lang/String;
/*     */     //   2080: iconst_0
/*     */     //   2081: swap
/*     */     //   2082: aastore
/*     */     //   2083: getfield sK0 : [Lf/hR;
/*     */     //   2086: invokestatic sW : ([Lf/hR;)Ljava/lang/String;
/*     */     //   2089: iconst_1
/*     */     //   2090: swap
/*     */     //   2091: aastore
/*     */     //   2092: invokestatic toString : (B)Ljava/lang/String;
/*     */     //   2095: iconst_2
/*     */     //   2096: swap
/*     */     //   2097: aastore
/*     */     //   2098: sipush #3545
/*     */     //   2101: aload #5
/*     */     //   2103: invokestatic sB : (I[Ljava/lang/String;)Ljava/lang/String;
/*     */     //   2106: aconst_null
/*     */     //   2107: iconst_1
/*     */     //   2108: invokestatic oF : (ILjava/lang/String;Ljava/lang/String;Z)Ljava/lang/String;
/*     */     //   2111: invokevirtual append : (Ljava/lang/String;)Ljava/lang/StringBuilder;
/*     */     //   2114: pop
/*     */     //   2115: goto -> 2176
/*     */     //   2118: aload_3
/*     */     //   2119: iload #4
/*     */     //   2121: iconst_3
/*     */     //   2122: anewarray java/lang/String
/*     */     //   2125: dup
/*     */     //   2126: astore #5
/*     */     //   2128: iload_2
/*     */     //   2129: aload #5
/*     */     //   2131: aload_0
/*     */     //   2132: aload #5
/*     */     //   2134: iload_1
/*     */     //   2135: invokestatic toString : (B)Ljava/lang/String;
/*     */     //   2138: iconst_0
/*     */     //   2139: swap
/*     */     //   2140: aastore
/*     */     //   2141: getfield sK0 : [Lf/hR;
/*     */     //   2144: invokestatic sW : ([Lf/hR;)Ljava/lang/String;
/*     */     //   2147: iconst_1
/*     */     //   2148: swap
/*     */     //   2149: aastore
/*     */     //   2150: iconst_m1
/*     */     //   2151: imul
/*     */     //   2152: i2b
/*     */     //   2153: invokestatic toString : (B)Ljava/lang/String;
/*     */     //   2156: iconst_2
/*     */     //   2157: swap
/*     */     //   2158: aastore
/*     */     //   2159: sipush #3547
/*     */     //   2162: aload #5
/*     */     //   2164: invokestatic sB : (I[Ljava/lang/String;)Ljava/lang/String;
/*     */     //   2167: aconst_null
/*     */     //   2168: iconst_1
/*     */     //   2169: invokestatic oF : (ILjava/lang/String;Ljava/lang/String;Z)Ljava/lang/String;
/*     */     //   2172: invokevirtual append : (Ljava/lang/String;)Ljava/lang/StringBuilder;
/*     */     //   2175: pop
/*     */     //   2176: aload_0
/*     */     //   2177: getfield pr0 : [Lf/hR;
/*     */     //   2180: dup
/*     */     //   2181: astore_2
/*     */     //   2182: arraylength
/*     */     //   2183: ifle -> 2446
/*     */     //   2186: aload_0
/*     */     //   2187: dup
/*     */     //   2188: aload_3
/*     */     //   2189: ldc_w '\\n▶ '
/*     */     //   2192: invokevirtual append : (Ljava/lang/String;)Ljava/lang/StringBuilder;
/*     */     //   2195: pop
/*     */     //   2196: getfield I80 : B
/*     */     //   2199: istore #5
/*     */     //   2201: getfield DD : B
/*     */     //   2204: bipush #7
/*     */     //   2206: if_icmpne -> 2329
/*     */     //   2209: iload #5
/*     */     //   2211: ifle -> 2270
/*     */     //   2214: aload_3
/*     */     //   2215: iload #4
/*     */     //   2217: iconst_3
/*     */     //   2218: anewarray java/lang/String
/*     */     //   2221: dup
/*     */     //   2222: astore #6
/*     */     //   2224: iload #5
/*     */     //   2226: aload #6
/*     */     //   2228: aload_2
/*     */     //   2229: aload #6
/*     */     //   2231: iload_1
/*     */     //   2232: invokestatic toString : (B)Ljava/lang/String;
/*     */     //   2235: iconst_0
/*     */     //   2236: swap
/*     */     //   2237: aastore
/*     */     //   2238: invokestatic sW : ([Lf/hR;)Ljava/lang/String;
/*     */     //   2241: iconst_1
/*     */     //   2242: swap
/*     */     //   2243: aastore
/*     */     //   2244: invokestatic toString : (B)Ljava/lang/String;
/*     */     //   2247: iconst_2
/*     */     //   2248: swap
/*     */     //   2249: aastore
/*     */     //   2250: sipush #3545
/*     */     //   2253: aload #6
/*     */     //   2255: invokestatic sB : (I[Ljava/lang/String;)Ljava/lang/String;
/*     */     //   2258: aconst_null
/*     */     //   2259: iconst_1
/*     */     //   2260: invokestatic oF : (ILjava/lang/String;Ljava/lang/String;Z)Ljava/lang/String;
/*     */     //   2263: invokevirtual append : (Ljava/lang/String;)Ljava/lang/StringBuilder;
/*     */     //   2266: pop
/*     */     //   2267: goto -> 2446
/*     */     //   2270: aload_3
/*     */     //   2271: iload #4
/*     */     //   2273: iconst_3
/*     */     //   2274: anewarray java/lang/String
/*     */     //   2277: dup
/*     */     //   2278: astore #6
/*     */     //   2280: iload #5
/*     */     //   2282: aload #6
/*     */     //   2284: aload_2
/*     */     //   2285: aload #6
/*     */     //   2287: iload_1
/*     */     //   2288: invokestatic toString : (B)Ljava/lang/String;
/*     */     //   2291: iconst_0
/*     */     //   2292: swap
/*     */     //   2293: aastore
/*     */     //   2294: invokestatic sW : ([Lf/hR;)Ljava/lang/String;
/*     */     //   2297: iconst_1
/*     */     //   2298: swap
/*     */     //   2299: aastore
/*     */     //   2300: iconst_m1
/*     */     //   2301: imul
/*     */     //   2302: i2b
/*     */     //   2303: invokestatic toString : (B)Ljava/lang/String;
/*     */     //   2306: iconst_2
/*     */     //   2307: swap
/*     */     //   2308: aastore
/*     */     //   2309: sipush #3547
/*     */     //   2312: aload #6
/*     */     //   2314: invokestatic sB : (I[Ljava/lang/String;)Ljava/lang/String;
/*     */     //   2317: aconst_null
/*     */     //   2318: iconst_1
/*     */     //   2319: invokestatic oF : (ILjava/lang/String;Ljava/lang/String;Z)Ljava/lang/String;
/*     */     //   2322: invokevirtual append : (Ljava/lang/String;)Ljava/lang/StringBuilder;
/*     */     //   2325: pop
/*     */     //   2326: goto -> 2446
/*     */     //   2329: iload #5
/*     */     //   2331: ifle -> 2390
/*     */     //   2334: aload_3
/*     */     //   2335: iload #4
/*     */     //   2337: iconst_3
/*     */     //   2338: anewarray java/lang/String
/*     */     //   2341: dup
/*     */     //   2342: astore #6
/*     */     //   2344: iload #5
/*     */     //   2346: aload #6
/*     */     //   2348: aload_2
/*     */     //   2349: aload #6
/*     */     //   2351: iload_1
/*     */     //   2352: invokestatic toString : (B)Ljava/lang/String;
/*     */     //   2355: iconst_0
/*     */     //   2356: swap
/*     */     //   2357: aastore
/*     */     //   2358: invokestatic sW : ([Lf/hR;)Ljava/lang/String;
/*     */     //   2361: iconst_1
/*     */     //   2362: swap
/*     */     //   2363: aastore
/*     */     //   2364: invokestatic toString : (B)Ljava/lang/String;
/*     */     //   2367: iconst_2
/*     */     //   2368: swap
/*     */     //   2369: aastore
/*     */     //   2370: sipush #3546
/*     */     //   2373: aload #6
/*     */     //   2375: invokestatic sB : (I[Ljava/lang/String;)Ljava/lang/String;
/*     */     //   2378: aconst_null
/*     */     //   2379: iconst_1
/*     */     //   2380: invokestatic oF : (ILjava/lang/String;Ljava/lang/String;Z)Ljava/lang/String;
/*     */     //   2383: invokevirtual append : (Ljava/lang/String;)Ljava/lang/StringBuilder;
/*     */     //   2386: pop
/*     */     //   2387: goto -> 2446
/*     */     //   2390: aload_3
/*     */     //   2391: iload #4
/*     */     //   2393: iconst_3
/*     */     //   2394: anewarray java/lang/String
/*     */     //   2397: dup
/*     */     //   2398: astore #6
/*     */     //   2400: iload #5
/*     */     //   2402: aload #6
/*     */     //   2404: aload_2
/*     */     //   2405: aload #6
/*     */     //   2407: iload_1
/*     */     //   2408: invokestatic toString : (B)Ljava/lang/String;
/*     */     //   2411: iconst_0
/*     */     //   2412: swap
/*     */     //   2413: aastore
/*     */     //   2414: invokestatic sW : ([Lf/hR;)Ljava/lang/String;
/*     */     //   2417: iconst_1
/*     */     //   2418: swap
/*     */     //   2419: aastore
/*     */     //   2420: iconst_m1
/*     */     //   2421: imul
/*     */     //   2422: i2b
/*     */     //   2423: invokestatic toString : (B)Ljava/lang/String;
/*     */     //   2426: iconst_2
/*     */     //   2427: swap
/*     */     //   2428: aastore
/*     */     //   2429: sipush #3548
/*     */     //   2432: aload #6
/*     */     //   2434: invokestatic sB : (I[Ljava/lang/String;)Ljava/lang/String;
/*     */     //   2437: aconst_null
/*     */     //   2438: iconst_1
/*     */     //   2439: invokestatic oF : (ILjava/lang/String;Ljava/lang/String;Z)Ljava/lang/String;
/*     */     //   2442: invokevirtual append : (Ljava/lang/String;)Ljava/lang/StringBuilder;
/*     */     //   2445: pop
/*     */     //   2446: aload_0
/*     */     //   2447: getfield A2 : [Lf/uj;
/*     */     //   2450: dup
/*     */     //   2451: astore_1
/*     */     //   2452: arraylength
/*     */     //   2453: istore_2
/*     */     //   2454: iconst_0
/*     */     //   2455: istore #5
/*     */     //   2457: iload #5
/*     */     //   2459: iload_2
/*     */     //   2460: if_icmpge -> 2508
/*     */     //   2463: aload_3
/*     */     //   2464: iload #4
/*     */     //   2466: aload_3
/*     */     //   2467: aload_1
/*     */     //   2468: iload #5
/*     */     //   2470: aaload
/*     */     //   2471: astore #6
/*     */     //   2473: ldc_w '\\n▶ '
/*     */     //   2476: invokevirtual append : (Ljava/lang/String;)Ljava/lang/StringBuilder;
/*     */     //   2479: pop
/*     */     //   2480: aload #6
/*     */     //   2482: getfield Cz : I
/*     */     //   2485: aload #6
/*     */     //   2487: getfield gO : [Lf/LPT1;
/*     */     //   2490: invokestatic Sz : (I[Lf/LPT1;)Ljava/lang/String;
/*     */     //   2493: aconst_null
/*     */     //   2494: iconst_1
/*     */     //   2495: invokestatic oF : (ILjava/lang/String;Ljava/lang/String;Z)Ljava/lang/String;
/*     */     //   2498: invokevirtual append : (Ljava/lang/String;)Ljava/lang/StringBuilder;
/*     */     //   2501: pop
/*     */     //   2502: iinc #5, 1
/*     */     //   2505: goto -> 2457
/*     */     //   2508: getstatic f/km.a3 : Lf/vh0;
/*     */     //   2511: astore_1
/*     */     //   2512: invokestatic XU : ()Z
/*     */     //   2515: ifne -> 2583
/*     */     //   2518: aload_1
/*     */     //   2519: ifnull -> 2583
/*     */     //   2522: aload_1
/*     */     //   2523: getfield Ct : Lf/Jo;
/*     */     //   2526: dup
/*     */     //   2527: astore_1
/*     */     //   2528: ifnull -> 2583
/*     */     //   2531: aload_1
/*     */     //   2532: getfield HW : Lf/G5;
/*     */     //   2535: getfield FB : B
/*     */     //   2538: iconst_1
/*     */     //   2539: if_icmpne -> 2583
/*     */     //   2542: getstatic f/km.wI0 : Lf/Pw;
/*     */     //   2545: getfield K7 : Lf/Wl;
/*     */     //   2548: ifnull -> 2566
/*     */     //   2551: getstatic f/km.MR : Lf/Gp0;
/*     */     //   2554: dup
/*     */     //   2555: astore_1
/*     */     //   2556: ifnull -> 2583
/*     */     //   2559: aload_1
/*     */     //   2560: invokevirtual sQ : ()Z
/*     */     //   2563: ifeq -> 2583
/*     */     //   2566: aload_3
/*     */     //   2567: aload_0
/*     */     //   2568: aload_3
/*     */     //   2569: ldc_w '\\n--------------------\\n'
/*     */     //   2572: invokevirtual append : (Ljava/lang/String;)Ljava/lang/StringBuilder;
/*     */     //   2575: pop
/*     */     //   2576: invokestatic mx : (Lf/WD;)Ljava/lang/String;
/*     */     //   2579: invokevirtual append : (Ljava/lang/String;)Ljava/lang/StringBuilder;
/*     */     //   2582: pop
/*     */     //   2583: aload_3
/*     */     //   2584: invokevirtual toString : ()Ljava/lang/String;
/*     */     //   2587: areturn
/*     */     // Line number table:
/*     */     //   Java source line number -> byte code offset
/*     */     //   #1	-> 38
/*     */     //   #2	-> 44
/*     */     //   #3	-> 60
/*     */     //   #4	-> 66
/*     */     //   #5	-> 101
/*     */     //   #6	-> 176
/*     */     //   #7	-> 182
/*     */     //   #8	-> 198
/*     */     //   #9	-> 201
/*     */     //   #10	-> 211
/*     */     //   #11	-> 249
/*     */     //   #12	-> 259
/*     */     //   #13	-> 319
/*     */     //   #14	-> 340
/*     */     //   #15	-> 383
/*     */     //   #16	-> 392
/*     */     //   #17	-> 401
/*     */     //   #18	-> 404
/*     */     //   #19	-> 440
/*     */     //   #20	-> 453
/*     */     //   #21	-> 478
/*     */     //   #22	-> 481
/*     */     //   #23	-> 509
/*     */     //   #24	-> 519
/*     */     //   #25	-> 529
/*     */     //   #26	-> 541
/*     */     //   #27	-> 548
/*     */     //   #28	-> 563
/*     */     //   #29	-> 611
/*     */     //   #30	-> 621
/*     */     //   #31	-> 634
/*     */     //   #32	-> 640
/*     */     //   #33	-> 650
/*     */     //   #34	-> 691
/*     */     //   #35	-> 701
/*     */     //   #36	-> 738
/*     */     //   #37	-> 747
/*     */     //   #38	-> 754
/*     */     //   #39	-> 764
/*     */     //   #40	-> 772
/*     */     //   #41	-> 775
/*     */     //   #42	-> 1040
/*     */     //   #43	-> 1043
/*     */     //   #44	-> 1050
/*     */     //   #45	-> 1069
/*     */     //   #46	-> 1075
/*     */     //   #47	-> 1085
/*     */     //   #48	-> 1115
/*     */     //   #49	-> 1118
/*     */     //   #50	-> 1132
/*     */     //   #51	-> 1142
/*     */     //   #52	-> 1156
/*     */     //   #53	-> 1159
/*     */     //   #54	-> 1185
/*     */     //   #55	-> 1195
/*     */     //   #56	-> 1206
/*     */     //   #57	-> 1209
/*     */     //   #58	-> 1217
/*     */     //   #59	-> 1221
/*     */     //   #60	-> 1228
/*     */     //   #61	-> 1241
/*     */     //   #62	-> 1252
/*     */     //   #63	-> 1256
/*     */     //   #64	-> 1262
/*     */     //   #65	-> 1294
/*     */     //   #66	-> 1350
/*     */     //   #67	-> 1385
/*     */     //   #68	-> 1393
/*     */     //   #69	-> 1405
/*     */     //   #70	-> 1414
/*     */     //   #71	-> 1463
/*     */     //   #72	-> 1472
/*     */     //   #73	-> 1499
/*     */     //   #74	-> 1507
/*     */     //   #75	-> 1519
/*     */     //   #76	-> 1528
/*     */     //   #77	-> 1577
/*     */     //   #78	-> 1586
/*     */     //   #79	-> 1613
/*     */     //   #80	-> 1621
/*     */     //   #81	-> 1633
/*     */     //   #82	-> 1642
/*     */     //   #83	-> 1691
/*     */     //   #84	-> 1700
/*     */     //   #85	-> 1779
/*     */     //   #86	-> 1794
/*     */     //   #87	-> 1893
/*     */     //   #88	-> 1904
/*     */     //   #89	-> 1911
/*     */     //   #90	-> 1915
/*     */     //   #91	-> 1922
/*     */     //   #92	-> 1941
/*     */     //   #93	-> 1960
/*     */     //   #94	-> 1963
/*     */     //   #95	-> 2018
/*     */     //   #96	-> 2021
/*     */     //   #97	-> 2083
/*     */     //   #98	-> 2086
/*     */     //   #99	-> 2141
/*     */     //   #100	-> 2144
/*     */     //   #101	-> 2177
/*     */     //   #102	-> 2182
/*     */     //   #103	-> 2196
/*     */     //   #104	-> 2201
/*     */     //   #105	-> 2218
/*     */     //   #106	-> 2447
/*     */     //   #107	-> 2452
/*     */     //   #108	-> 2482
/*     */     //   #109	-> 2487
/*     */     //   #110	-> 2490
/*     */     //   #111	-> 2523
/*     */     //   #112	-> 2532
/*     */     //   #113	-> 2535
/*     */     //   #114	-> 2542
/*     */     //   #115	-> 2545
/*     */     //   #116	-> 2551
/*     */   }
/*     */   
/*     */   public static String oV(WD paramWD) {
/*     */     if (paramWD == null)
/*     */       return ""; 
/*     */     this();
/*     */     StringBuilder stringBuilder;
/*     */     (new StringBuilder()).append(Ml0.OH0(1850)).append(" ");
/*     */     if (paramWD.HA == 374) {
/*     */       stringBuilder.append("10 - 130");
/*     */     } else {
/*     */       String str1;
/*     */       short s;
/*     */       if ((s = paramWD.Di0) == 0) {
/*     */         str1 = "-";
/*     */       } else {
/*     */         str1 = Integer.toString(str1);
/*     */       } 
/*     */       stringBuilder.append(str1);
/*     */     } 
/*     */     stringBuilder.append(" | ");
/*     */     stringBuilder.append(Ml0.OH0(1857)).append(" ");
/*     */     byte b;
/*     */     if ((b = paramWD.Jp0) == 0 || b == 101) {
/*     */       str = "-";
/*     */       stringBuilder.append(str);
/*     */       return stringBuilder.toString();
/*     */     } 
/*     */     String str = Integer.toString(str);
/*     */     stringBuilder.append(str);
/*     */     return stringBuilder.toString();
/*     */   }
/*     */   
/*     */   public static String mx(WD paramWD) {
/*     */     if (paramWD == null)
/*     */       return ""; 
/*     */     if (paramWD.EE0() == null || paramWD.EE0().aU() == null)
/*     */       return Ml0.OH0(7005); 
/*     */     if (t90.bigCJKFontSizes()) {
/*     */       b1 = 22;
/*     */     } else {
/*     */       b1 = 38;
/*     */     } 
/*     */     this();
/*     */     String str1, str2;
/*     */     stringBuilder2.append(Ml0.OH0(1863));
/*     */     stringBuilder2.append("\n\n");
/*     */     stringBuilder2.append(Ml0.OH0((paramWD.EE0()).CA0.QN()));
/*     */     stringBuilder2.append("\n");
/*     */     StringBuilder stringBuilder2;
/*     */     (stringBuilder2 = new StringBuilder()).append(cS.JF(b1, Ml0.OH0((paramWD.EE0().aU()).aF + 310200).replace("|br|", "\n")));
/*     */     (new StringBuilder()).append("\n\n");
/*     */     this();
/*     */     StringBuilder stringBuilder3 = pv.X9(1865, stringBuilder3, " ");
/*     */     byte b1;
/*     */     if ((b1 = (paramWD.EE0().aU()).Im0) > 0) {
/*     */       str2 = Byte.toString(b1);
/*     */     } else {
/*     */       str2 = "--";
/*     */     } 
/*     */     stringBuilder2.append(stringBuilder3.append(str2).toString());
/*     */     stringBuilder2.append("\n");
/*     */     this();
/*     */     StringBuilder stringBuilder1 = pv.X9(1866, stringBuilder1, " ");
/*     */     byte b;
/*     */     if ((b = (paramWD.EE0().aU()).cy) > 0) {
/*     */       str1 = Byte.toString(b);
/*     */     } else {
/*     */       str1 = "--";
/*     */     } 
/*     */     stringBuilder2.append(stringBuilder1.append(str1).toString());
/*     */     return stringBuilder2.toString();
/*     */   }
/*     */   
/*     */   public static String kh0(LPT3 paramLPT3) {
/*     */     return Qb0(paramLPT3, true, false);
/*     */   }
/*     */   
/*     */   public static String Qb0(LPT3 paramLPT3, boolean paramBoolean1, boolean paramBoolean2) {
/*     */     // Byte code:
/*     */     //   0: invokestatic XU : ()Z
/*     */     //   3: ifeq -> 12
/*     */     //   6: bipush #38
/*     */     //   8: istore_3
/*     */     //   9: goto -> 15
/*     */     //   12: bipush #45
/*     */     //   14: istore_3
/*     */     //   15: aload_0
/*     */     //   16: getfield ux0 : B
/*     */     //   19: invokestatic n80 : (B)Z
/*     */     //   22: ifeq -> 41
/*     */     //   25: aload_0
/*     */     //   26: iload_3
/*     */     //   27: invokevirtual Ey0 : (I)Ljava/lang/String;
/*     */     //   30: ldc '|br|'
/*     */     //   32: ldc '\\n'
/*     */     //   34: invokevirtual replace : (Ljava/lang/CharSequence;Ljava/lang/CharSequence;)Ljava/lang/String;
/*     */     //   37: astore_3
/*     */     //   38: goto -> 47
/*     */     //   41: aload_0
/*     */     //   42: iload_3
/*     */     //   43: invokevirtual Ey0 : (I)Ljava/lang/String;
/*     */     //   46: astore_3
/*     */     //   47: aload_0
/*     */     //   48: getfield Y8 : Lf/Hu0;
/*     */     //   51: getstatic f/Hu0.JV : Lf/Hu0;
/*     */     //   54: if_acmpne -> 97
/*     */     //   57: aload_0
/*     */     //   58: getfield kx0 : S
/*     */     //   61: ifle -> 97
/*     */     //   64: aload_0
/*     */     //   65: getfield wC0 : I
/*     */     //   68: iconst_1
/*     */     //   69: if_icmpge -> 97
/*     */     //   72: invokestatic cw : ()Lf/yk0;
/*     */     //   75: aload_0
/*     */     //   76: getfield kx0 : S
/*     */     //   79: invokevirtual mP : (S)Lf/WD;
/*     */     //   82: dup
/*     */     //   83: astore #4
/*     */     //   85: ifnull -> 97
/*     */     //   88: aload #4
/*     */     //   90: aconst_null
/*     */     //   91: aconst_null
/*     */     //   92: iconst_0
/*     */     //   93: invokestatic Vc : (Lf/WD;Lf/Q90;Lf/LPT3;Z)Ljava/lang/String;
/*     */     //   96: astore_3
/*     */     //   97: iload_2
/*     */     //   98: ifeq -> 182
/*     */     //   101: aload_0
/*     */     //   102: new java/lang/StringBuilder
/*     */     //   105: dup
/*     */     //   106: astore #4
/*     */     //   108: invokespecial <init> : ()V
/*     */     //   111: getfield Pa0 : S
/*     */     //   114: ifle -> 152
/*     */     //   117: aload #4
/*     */     //   119: dup
/*     */     //   120: aload_0
/*     */     //   121: getfield Rv0 : Z
/*     */     //   124: sipush #1426
/*     */     //   127: iadd
/*     */     //   128: invokestatic getInstance : ()Ljava/text/NumberFormat;
/*     */     //   131: aload_0
/*     */     //   132: getfield Pa0 : S
/*     */     //   135: i2l
/*     */     //   136: invokevirtual format : (J)Ljava/lang/String;
/*     */     //   139: invokestatic Go : (ILjava/lang/String;)Ljava/lang/String;
/*     */     //   142: invokevirtual append : (Ljava/lang/String;)Ljava/lang/StringBuilder;
/*     */     //   145: pop
/*     */     //   146: ldc '\\n'
/*     */     //   148: invokevirtual append : (Ljava/lang/String;)Ljava/lang/StringBuilder;
/*     */     //   151: pop
/*     */     //   152: aload_0
/*     */     //   153: getfield xp0 : B
/*     */     //   156: iconst_m1
/*     */     //   157: if_icmpne -> 188
/*     */     //   160: aload #4
/*     */     //   162: dup
/*     */     //   163: sipush #3523
/*     */     //   166: invokestatic OH0 : (I)Ljava/lang/String;
/*     */     //   169: invokevirtual append : (Ljava/lang/String;)Ljava/lang/StringBuilder;
/*     */     //   172: pop
/*     */     //   173: ldc '\\n'
/*     */     //   175: invokevirtual append : (Ljava/lang/String;)Ljava/lang/StringBuilder;
/*     */     //   178: pop
/*     */     //   179: goto -> 188
/*     */     //   182: aload_0
/*     */     //   183: invokestatic iw : (Lf/LPT3;)Ljava/lang/StringBuilder;
/*     */     //   186: astore #4
/*     */     //   188: iload_1
/*     */     //   189: new java/lang/StringBuilder
/*     */     //   192: dup
/*     */     //   193: astore_1
/*     */     //   194: invokespecial <init> : ()V
/*     */     //   197: ifeq -> 296
/*     */     //   200: aload_1
/*     */     //   201: aload_0
/*     */     //   202: getfield Iu : I
/*     */     //   205: invokestatic OH0 : (I)Ljava/lang/String;
/*     */     //   208: invokevirtual append : (Ljava/lang/String;)Ljava/lang/StringBuilder;
/*     */     //   211: pop
/*     */     //   212: iconst_3
/*     */     //   213: invokestatic D70 : (I)Z
/*     */     //   216: ifeq -> 289
/*     */     //   219: aload_0
/*     */     //   220: aload_1
/*     */     //   221: ldc_w ' ('
/*     */     //   224: invokevirtual append : (Ljava/lang/String;)Ljava/lang/StringBuilder;
/*     */     //   227: aload_0
/*     */     //   228: getfield bj0 : S
/*     */     //   231: invokevirtual append : (I)Ljava/lang/StringBuilder;
/*     */     //   234: pop
/*     */     //   235: getfield ux0 : B
/*     */     //   238: iflt -> 281
/*     */     //   241: aload_0
/*     */     //   242: aload_1
/*     */     //   243: ldc ' '
/*     */     //   245: invokevirtual append : (Ljava/lang/String;)Ljava/lang/StringBuilder;
/*     */     //   248: pop
/*     */     //   249: getfield ux0 : B
/*     */     //   252: dup
/*     */     //   253: istore #5
/*     */     //   255: bipush #10
/*     */     //   257: if_icmpne -> 271
/*     */     //   260: aload_1
/*     */     //   261: ldc_w 'Custom'
/*     */     //   264: invokevirtual append : (Ljava/lang/String;)Ljava/lang/StringBuilder;
/*     */     //   267: pop
/*     */     //   268: goto -> 281
/*     */     //   271: aload_1
/*     */     //   272: iload #5
/*     */     //   274: invokestatic zd : (B)Ljava/lang/String;
/*     */     //   277: invokevirtual append : (Ljava/lang/String;)Ljava/lang/StringBuilder;
/*     */     //   280: pop
/*     */     //   281: aload_1
/*     */     //   282: ldc_w ')'
/*     */     //   285: invokevirtual append : (Ljava/lang/String;)Ljava/lang/StringBuilder;
/*     */     //   288: pop
/*     */     //   289: aload_1
/*     */     //   290: ldc '\\n'
/*     */     //   292: invokevirtual append : (Ljava/lang/String;)Ljava/lang/StringBuilder;
/*     */     //   295: pop
/*     */     //   296: aload #4
/*     */     //   298: invokevirtual length : ()I
/*     */     //   301: ifle -> 329
/*     */     //   304: aload_0
/*     */     //   305: getfield Y8 : Lf/Hu0;
/*     */     //   308: getstatic f/Hu0.w2 : Lf/Hu0;
/*     */     //   311: if_acmpeq -> 322
/*     */     //   314: aload_1
/*     */     //   315: ldc_w '--------\\n'
/*     */     //   318: invokevirtual append : (Ljava/lang/String;)Ljava/lang/StringBuilder;
/*     */     //   321: pop
/*     */     //   322: aload_1
/*     */     //   323: aload #4
/*     */     //   325: invokevirtual append : (Ljava/lang/CharSequence;)Ljava/lang/StringBuilder;
/*     */     //   328: pop
/*     */     //   329: iload_2
/*     */     //   330: ifne -> 393
/*     */     //   333: aload_0
/*     */     //   334: invokestatic FK0 : (Lf/LPT3;)Ljava/lang/String;
/*     */     //   337: dup
/*     */     //   338: astore #4
/*     */     //   340: invokevirtual isEmpty : ()Z
/*     */     //   343: ifne -> 368
/*     */     //   346: aload_1
/*     */     //   347: dup
/*     */     //   348: dup
/*     */     //   349: ldc_w '--------\\n'
/*     */     //   352: invokevirtual append : (Ljava/lang/String;)Ljava/lang/StringBuilder;
/*     */     //   355: pop
/*     */     //   356: aload #4
/*     */     //   358: invokevirtual append : (Ljava/lang/String;)Ljava/lang/StringBuilder;
/*     */     //   361: pop
/*     */     //   362: ldc '\\n'
/*     */     //   364: invokevirtual append : (Ljava/lang/String;)Ljava/lang/StringBuilder;
/*     */     //   367: pop
/*     */     //   368: aload_0
/*     */     //   369: invokevirtual lF0 : ()Z
/*     */     //   372: ifeq -> 393
/*     */     //   375: aload_1
/*     */     //   376: aload_0
/*     */     //   377: aload_1
/*     */     //   378: ldc_w '--------\\n'
/*     */     //   381: invokevirtual append : (Ljava/lang/String;)Ljava/lang/StringBuilder;
/*     */     //   384: pop
/*     */     //   385: iconst_1
/*     */     //   386: invokestatic LJ : (Lf/LPT3;Z)Ljava/lang/String;
/*     */     //   389: invokevirtual append : (Ljava/lang/String;)Ljava/lang/StringBuilder;
/*     */     //   392: pop
/*     */     //   393: aload_0
/*     */     //   394: getfield KU : B
/*     */     //   397: iconst_m1
/*     */     //   398: if_icmple -> 955
/*     */     //   401: aload_0
/*     */     //   402: aload_1
/*     */     //   403: ldc_w '--------\\n'
/*     */     //   406: invokevirtual append : (Ljava/lang/String;)Ljava/lang/StringBuilder;
/*     */     //   409: pop
/*     */     //   410: new java/lang/StringBuilder
/*     */     //   413: dup
/*     */     //   414: astore #4
/*     */     //   416: invokespecial <init> : ()V
/*     */     //   419: getfield KU : B
/*     */     //   422: dup
/*     */     //   423: istore #5
/*     */     //   425: ifeq -> 490
/*     */     //   428: iload #5
/*     */     //   430: iconst_1
/*     */     //   431: if_icmpeq -> 482
/*     */     //   434: iload #5
/*     */     //   436: iconst_2
/*     */     //   437: if_icmpeq -> 474
/*     */     //   440: iload #5
/*     */     //   442: iconst_4
/*     */     //   443: if_icmpeq -> 466
/*     */     //   446: iload #5
/*     */     //   448: bipush #11
/*     */     //   450: if_icmpeq -> 474
/*     */     //   453: iload #5
/*     */     //   455: bipush #15
/*     */     //   457: if_icmpeq -> 482
/*     */     //   460: dconst_1
/*     */     //   461: dstore #6
/*     */     //   463: goto -> 495
/*     */     //   466: ldc2_w 0.75
/*     */     //   469: dstore #6
/*     */     //   471: goto -> 495
/*     */     //   474: ldc2_w 1.5
/*     */     //   477: dstore #6
/*     */     //   479: goto -> 495
/*     */     //   482: ldc2_w 2.0
/*     */     //   485: dstore #6
/*     */     //   487: goto -> 495
/*     */     //   490: ldc2_w 255.0
/*     */     //   493: dstore #6
/*     */     //   495: iload #5
/*     */     //   497: tableswitch default -> 612, 0 -> 682, 1 -> 674, 2 -> 666, 3 -> 612, 4 -> 658, 5 -> 650, 6 -> 650, 7 -> 642, 8 -> 634, 9 -> 642, 10 -> 674, 11 -> 666, 12 -> 634, 13 -> 612, 14 -> 626, 15 -> 674, 16 -> 642, 17 -> 642, 18 -> 642, 19 -> 642, 20 -> 618, 21 -> 634, 22 -> 642, 23 -> 612, 24 -> 642
/*     */     //   612: dconst_1
/*     */     //   613: dstore #8
/*     */     //   615: goto -> 687
/*     */     //   618: ldc2_w 8.0
/*     */     //   621: dstore #8
/*     */     //   623: goto -> 687
/*     */     //   626: ldc2_w 5.0
/*     */     //   629: dstore #8
/*     */     //   631: goto -> 687
/*     */     //   634: ldc2_w 2.5
/*     */     //   637: dstore #8
/*     */     //   639: goto -> 687
/*     */     //   642: ldc2_w 4.0
/*     */     //   645: dstore #8
/*     */     //   647: goto -> 687
/*     */     //   650: ldc2_w 3.5
/*     */     //   653: dstore #8
/*     */     //   655: goto -> 687
/*     */     //   658: ldc2_w 3.0
/*     */     //   661: dstore #8
/*     */     //   663: goto -> 687
/*     */     //   666: ldc2_w 1.5
/*     */     //   669: dstore #8
/*     */     //   671: goto -> 687
/*     */     //   674: ldc2_w 2.0
/*     */     //   677: dstore #8
/*     */     //   679: goto -> 687
/*     */     //   682: ldc2_w 255.0
/*     */     //   685: dstore #8
/*     */     //   687: dload #6
/*     */     //   689: dconst_0
/*     */     //   690: dcmpl
/*     */     //   691: ifne -> 708
/*     */     //   694: dload #8
/*     */     //   696: dconst_0
/*     */     //   697: dcmpl
/*     */     //   698: ifne -> 708
/*     */     //   701: ldc ''
/*     */     //   703: astore #4
/*     */     //   705: goto -> 948
/*     */     //   708: dload #6
/*     */     //   710: dload #8
/*     */     //   712: dcmpl
/*     */     //   713: ifne -> 788
/*     */     //   716: dload #6
/*     */     //   718: ldc2_w 255.0
/*     */     //   721: dcmpl
/*     */     //   722: iflt -> 747
/*     */     //   725: aload #4
/*     */     //   727: sipush #1444
/*     */     //   730: invokestatic OH0 : (I)Ljava/lang/String;
/*     */     //   733: sipush #1440
/*     */     //   736: swap
/*     */     //   737: invokestatic Go : (ILjava/lang/String;)Ljava/lang/String;
/*     */     //   740: invokevirtual append : (Ljava/lang/String;)Ljava/lang/StringBuilder;
/*     */     //   743: pop
/*     */     //   744: goto -> 934
/*     */     //   747: aload #4
/*     */     //   749: new java/lang/StringBuilder
/*     */     //   752: dup
/*     */     //   753: astore #5
/*     */     //   755: dload #6
/*     */     //   757: aload #5
/*     */     //   759: invokespecial <init> : ()V
/*     */     //   762: invokevirtual append : (D)Ljava/lang/StringBuilder;
/*     */     //   765: ldc_w 'x'
/*     */     //   768: invokevirtual append : (Ljava/lang/String;)Ljava/lang/StringBuilder;
/*     */     //   771: invokevirtual toString : ()Ljava/lang/String;
/*     */     //   774: sipush #1440
/*     */     //   777: swap
/*     */     //   778: invokestatic Go : (ILjava/lang/String;)Ljava/lang/String;
/*     */     //   781: invokevirtual append : (Ljava/lang/String;)Ljava/lang/StringBuilder;
/*     */     //   784: pop
/*     */     //   785: goto -> 934
/*     */     //   788: dload #6
/*     */     //   790: ldc2_w -2.0
/*     */     //   793: dcmpl
/*     */     //   794: ifne -> 819
/*     */     //   797: aload #4
/*     */     //   799: sipush #1443
/*     */     //   802: invokestatic OH0 : (I)Ljava/lang/String;
/*     */     //   805: sipush #1441
/*     */     //   808: swap
/*     */     //   809: invokestatic Go : (ILjava/lang/String;)Ljava/lang/String;
/*     */     //   812: invokevirtual append : (Ljava/lang/String;)Ljava/lang/StringBuilder;
/*     */     //   815: pop
/*     */     //   816: goto -> 857
/*     */     //   819: aload #4
/*     */     //   821: new java/lang/StringBuilder
/*     */     //   824: dup
/*     */     //   825: astore #5
/*     */     //   827: dload #6
/*     */     //   829: aload #5
/*     */     //   831: invokespecial <init> : ()V
/*     */     //   834: invokevirtual append : (D)Ljava/lang/StringBuilder;
/*     */     //   837: ldc_w 'x'
/*     */     //   840: invokevirtual append : (Ljava/lang/String;)Ljava/lang/StringBuilder;
/*     */     //   843: invokevirtual toString : ()Ljava/lang/String;
/*     */     //   846: sipush #1441
/*     */     //   849: swap
/*     */     //   850: invokestatic Go : (ILjava/lang/String;)Ljava/lang/String;
/*     */     //   853: invokevirtual append : (Ljava/lang/String;)Ljava/lang/StringBuilder;
/*     */     //   856: pop
/*     */     //   857: dload #8
/*     */     //   859: aload #4
/*     */     //   861: ldc '\\n'
/*     */     //   863: invokevirtual append : (Ljava/lang/String;)Ljava/lang/StringBuilder;
/*     */     //   866: pop
/*     */     //   867: ldc2_w -2.0
/*     */     //   870: dcmpl
/*     */     //   871: ifne -> 896
/*     */     //   874: aload #4
/*     */     //   876: sipush #1443
/*     */     //   879: invokestatic OH0 : (I)Ljava/lang/String;
/*     */     //   882: sipush #1442
/*     */     //   885: swap
/*     */     //   886: invokestatic Go : (ILjava/lang/String;)Ljava/lang/String;
/*     */     //   889: invokevirtual append : (Ljava/lang/String;)Ljava/lang/StringBuilder;
/*     */     //   892: pop
/*     */     //   893: goto -> 934
/*     */     //   896: aload #4
/*     */     //   898: new java/lang/StringBuilder
/*     */     //   901: dup
/*     */     //   902: astore #5
/*     */     //   904: dload #8
/*     */     //   906: aload #5
/*     */     //   908: invokespecial <init> : ()V
/*     */     //   911: invokevirtual append : (D)Ljava/lang/StringBuilder;
/*     */     //   914: ldc_w 'x'
/*     */     //   917: invokevirtual append : (Ljava/lang/String;)Ljava/lang/StringBuilder;
/*     */     //   920: invokevirtual toString : ()Ljava/lang/String;
/*     */     //   923: sipush #1442
/*     */     //   926: swap
/*     */     //   927: invokestatic Go : (ILjava/lang/String;)Ljava/lang/String;
/*     */     //   930: invokevirtual append : (Ljava/lang/String;)Ljava/lang/StringBuilder;
/*     */     //   933: pop
/*     */     //   934: aload #4
/*     */     //   936: dup
/*     */     //   937: ldc '\\n'
/*     */     //   939: invokevirtual append : (Ljava/lang/String;)Ljava/lang/StringBuilder;
/*     */     //   942: pop
/*     */     //   943: invokevirtual toString : ()Ljava/lang/String;
/*     */     //   946: astore #4
/*     */     //   948: aload_1
/*     */     //   949: aload #4
/*     */     //   951: invokevirtual append : (Ljava/lang/String;)Ljava/lang/StringBuilder;
/*     */     //   954: pop
/*     */     //   955: aload_3
/*     */     //   956: invokevirtual length : ()I
/*     */     //   959: ifle -> 993
/*     */     //   962: aload_0
/*     */     //   963: getfield Y8 : Lf/Hu0;
/*     */     //   966: getstatic f/Hu0.w2 : Lf/Hu0;
/*     */     //   969: if_acmpeq -> 993
/*     */     //   972: aload_1
/*     */     //   973: invokevirtual length : ()I
/*     */     //   976: ifle -> 987
/*     */     //   979: aload_1
/*     */     //   980: ldc_w '--------\\n'
/*     */     //   983: invokevirtual append : (Ljava/lang/String;)Ljava/lang/StringBuilder;
/*     */     //   986: pop
/*     */     //   987: aload_1
/*     */     //   988: aload_3
/*     */     //   989: invokevirtual append : (Ljava/lang/String;)Ljava/lang/StringBuilder;
/*     */     //   992: pop
/*     */     //   993: iload_2
/*     */     //   994: ifne -> 1038
/*     */     //   997: aload_0
/*     */     //   998: invokevirtual lF0 : ()Z
/*     */     //   1001: ifeq -> 1038
/*     */     //   1004: aload_0
/*     */     //   1005: getfield bj0 : S
/*     */     //   1008: sipush #1446
/*     */     //   1011: if_icmpeq -> 1038
/*     */     //   1014: aload_1
/*     */     //   1015: dup
/*     */     //   1016: ldc_w '\\n--------\\n'
/*     */     //   1019: invokevirtual append : (Ljava/lang/String;)Ljava/lang/StringBuilder;
/*     */     //   1022: pop
/*     */     //   1023: ldc_w 100150
/*     */     //   1026: invokestatic OH0 : (I)Ljava/lang/String;
/*     */     //   1029: invokevirtual append : (Ljava/lang/String;)Ljava/lang/StringBuilder;
/*     */     //   1032: ldc '\\n'
/*     */     //   1034: invokevirtual append : (Ljava/lang/String;)Ljava/lang/StringBuilder;
/*     */     //   1037: pop
/*     */     //   1038: aload_1
/*     */     //   1039: invokevirtual toString : ()Ljava/lang/String;
/*     */     //   1042: invokevirtual trim : ()Ljava/lang/String;
/*     */     //   1045: areturn
/*     */     // Line number table:
/*     */     //   Java source line number -> byte code offset
/*     */     //   #1	-> 16
/*     */     //   #2	-> 19
/*     */     //   #3	-> 48
/*     */     //   #4	-> 51
/*     */     //   #5	-> 58
/*     */     //   #6	-> 65
/*     */     //   #7	-> 72
/*     */     //   #8	-> 76
/*     */     //   #9	-> 79
/*     */     //   #10	-> 102
/*     */     //   #11	-> 111
/*     */     //   #12	-> 121
/*     */     //   #13	-> 128
/*     */     //   #14	-> 132
/*     */     //   #15	-> 136
/*     */     //   #16	-> 153
/*     */     //   #17	-> 166
/*     */     //   #18	-> 183
/*     */     //   #19	-> 202
/*     */     //   #20	-> 208
/*     */     //   #21	-> 228
/*     */     //   #22	-> 231
/*     */     //   #23	-> 235
/*     */     //   #24	-> 243
/*     */     //   #25	-> 249
/*     */     //   #26	-> 261
/*     */     //   #27	-> 305
/*     */     //   #28	-> 308
/*     */     //   #29	-> 394
/*     */     //   #30	-> 403
/*     */     //   #31	-> 410
/*     */     //   #32	-> 419
/*     */     //   #33	-> 701
/*     */     //   #34	-> 951
/*     */     //   #35	-> 963
/*     */     //   #36	-> 966
/*     */     //   #37	-> 1005
/*     */     //   #38	-> 1016
/*     */   }
/*     */   
/*     */   public static String LJ(LPT3 paramLPT3, boolean paramBoolean) {
/*     */     if (!paramLPT3.lF0())
/*     */       return ""; 
/*     */     if (paramLPT3.bj0 == 1446)
/*     */       paramBoolean = false; 
/*     */     this();
/*     */     StringBuilder stringBuilder;
/*     */     if (paramBoolean) {
/*     */       int[] arrayOfInt = paramLPT3.iI0;
/*     */       boolean bool = false;
/*     */       byte b = 0;
/*     */       while (b < arrayOfInt.length) {
/*     */         if (arrayOfInt[b] >= 1) {
/*     */           byte b1;
/*     */           if (bool)
/*     */             stringBuilder.append(", "); 
/*     */           bool = true;
/*     */           int k = b * 2 + 100100;
/*     */           if (arrayOfInt[b] > 9) {
/*     */             b1 = 1;
/*     */           } else {
/*     */             b1 = 0;
/*     */           } 
/*     */           stringBuilder.append(Ml0.OH0(k + b1));
/*     */         } 
/*     */         b++;
/*     */       } 
/*     */       stringBuilder.append("\n");
/*     */     } 
/*     */     int i = paramLPT3.nk0 / 60;
/*     */     float f = paramLPT3.Dw / 60.0F;
/*     */     (new DecimalFormat()).setMaximumFractionDigits(2);
/*     */     String str = (new DecimalFormat()).format(f);
/*     */     int j = 100120;
/*     */     stringBuilder.append(Ml0.OH0(paramLPT3.Sd0 + j));
/*     */     stringBuilder.append(" ");
/*     */     stringBuilder.append(Ml0.Go(100119, i + "")).append("\n");
/*     */     i = 100125;
/*     */     stringBuilder.append(Ml0.OH0(paramLPT3.ab + i)).append("\n");
/*     */     i = 100130;
/*     */     stringBuilder.append(Ml0.OH0(paramLPT3.iY + i));
/*     */     stringBuilder.append(" ");
/*     */     stringBuilder.append(Ml0.Go(100119, str)).append("\n");
/*     */     return stringBuilder.toString();
/*     */   }
/*     */   
/*     */   public static StringBuilder iw(LPT3 paramLPT3) {
/*     */     // Byte code:
/*     */     //   0: invokestatic bigCJKFontSizes : ()Z
/*     */     //   3: ifeq -> 12
/*     */     //   6: bipush #22
/*     */     //   8: istore_1
/*     */     //   9: goto -> 15
/*     */     //   12: bipush #45
/*     */     //   14: istore_1
/*     */     //   15: aload_0
/*     */     //   16: new java/lang/StringBuilder
/*     */     //   19: dup
/*     */     //   20: astore_2
/*     */     //   21: invokespecial <init> : ()V
/*     */     //   24: invokestatic w0 : (Lf/LPT3;)Ljava/lang/StringBuilder;
/*     */     //   27: dup
/*     */     //   28: astore_3
/*     */     //   29: invokevirtual length : ()I
/*     */     //   32: ifle -> 41
/*     */     //   35: aload_2
/*     */     //   36: aload_3
/*     */     //   37: invokevirtual append : (Ljava/lang/CharSequence;)Ljava/lang/StringBuilder;
/*     */     //   40: pop
/*     */     //   41: aload_0
/*     */     //   42: getfield yq0 : [Lf/uj;
/*     */     //   45: dup
/*     */     //   46: astore_3
/*     */     //   47: arraylength
/*     */     //   48: istore #4
/*     */     //   50: iconst_0
/*     */     //   51: istore #5
/*     */     //   53: iload #5
/*     */     //   55: iload #4
/*     */     //   57: if_icmpge -> 103
/*     */     //   60: aload_2
/*     */     //   61: aload_3
/*     */     //   62: iload #5
/*     */     //   64: aaload
/*     */     //   65: dup
/*     */     //   66: astore #6
/*     */     //   68: getfield Cz : I
/*     */     //   71: aload #6
/*     */     //   73: getfield gO : [Lf/LPT1;
/*     */     //   76: invokestatic Sz : (I[Lf/LPT1;)Ljava/lang/String;
/*     */     //   79: iload_1
/*     */     //   80: aconst_null
/*     */     //   81: iconst_1
/*     */     //   82: swap
/*     */     //   83: swap
/*     */     //   84: iconst_0
/*     */     //   85: invokestatic Qd0 : (Ljava/lang/String;ILjava/lang/String;ZI)Ljava/lang/String;
/*     */     //   88: invokevirtual append : (Ljava/lang/String;)Ljava/lang/StringBuilder;
/*     */     //   91: ldc '\\n'
/*     */     //   93: invokevirtual append : (Ljava/lang/String;)Ljava/lang/StringBuilder;
/*     */     //   96: pop
/*     */     //   97: iinc #5, 1
/*     */     //   100: goto -> 53
/*     */     //   103: aload_0
/*     */     //   104: getfield Y8 : Lf/Hu0;
/*     */     //   107: getstatic f/Hu0.Bm : Lf/Hu0;
/*     */     //   110: dup
/*     */     //   111: astore_3
/*     */     //   112: if_acmpeq -> 211
/*     */     //   115: aload_0
/*     */     //   116: getfield ph0 : I
/*     */     //   119: ifeq -> 174
/*     */     //   122: aload_0
/*     */     //   123: getfield TA0 : Z
/*     */     //   126: ifeq -> 174
/*     */     //   129: aload_2
/*     */     //   130: invokestatic getInstance : ()Ljava/text/NumberFormat;
/*     */     //   133: aload_0
/*     */     //   134: getfield ph0 : I
/*     */     //   137: i2l
/*     */     //   138: invokevirtual format : (J)Ljava/lang/String;
/*     */     //   141: sipush #1926
/*     */     //   144: swap
/*     */     //   145: invokestatic Go : (ILjava/lang/String;)Ljava/lang/String;
/*     */     //   148: invokevirtual append : (Ljava/lang/String;)Ljava/lang/StringBuilder;
/*     */     //   151: pop
/*     */     //   152: iconst_3
/*     */     //   153: invokestatic D70 : (I)Z
/*     */     //   156: ifeq -> 167
/*     */     //   159: aload_2
/*     */     //   160: ldc_w ' (Mart Item)'
/*     */     //   163: invokevirtual append : (Ljava/lang/String;)Ljava/lang/StringBuilder;
/*     */     //   166: pop
/*     */     //   167: aload_2
/*     */     //   168: ldc '\\n'
/*     */     //   170: invokevirtual append : (Ljava/lang/String;)Ljava/lang/StringBuilder;
/*     */     //   173: pop
/*     */     //   174: aload_0
/*     */     //   175: invokevirtual coM8 : ()I
/*     */     //   178: ifeq -> 211
/*     */     //   181: aload_2
/*     */     //   182: dup
/*     */     //   183: invokestatic getInstance : ()Ljava/text/NumberFormat;
/*     */     //   186: aload_0
/*     */     //   187: invokevirtual coM8 : ()I
/*     */     //   190: i2l
/*     */     //   191: invokevirtual format : (J)Ljava/lang/String;
/*     */     //   194: sipush #1930
/*     */     //   197: swap
/*     */     //   198: invokestatic Go : (ILjava/lang/String;)Ljava/lang/String;
/*     */     //   201: invokevirtual append : (Ljava/lang/String;)Ljava/lang/StringBuilder;
/*     */     //   204: pop
/*     */     //   205: ldc '\\n'
/*     */     //   207: invokevirtual append : (Ljava/lang/String;)Ljava/lang/StringBuilder;
/*     */     //   210: pop
/*     */     //   211: aload_0
/*     */     //   212: invokevirtual vx : ()Z
/*     */     //   215: ifne -> 236
/*     */     //   218: aload_2
/*     */     //   219: dup
/*     */     //   220: sipush #1425
/*     */     //   223: invokestatic OH0 : (I)Ljava/lang/String;
/*     */     //   226: invokevirtual append : (Ljava/lang/String;)Ljava/lang/StringBuilder;
/*     */     //   229: pop
/*     */     //   230: ldc '\\n'
/*     */     //   232: invokevirtual append : (Ljava/lang/String;)Ljava/lang/StringBuilder;
/*     */     //   235: pop
/*     */     //   236: aload_0
/*     */     //   237: getfield IK0 : Z
/*     */     //   240: ifeq -> 261
/*     */     //   243: aload_2
/*     */     //   244: dup
/*     */     //   245: sipush #1447
/*     */     //   248: invokestatic OH0 : (I)Ljava/lang/String;
/*     */     //   251: invokevirtual append : (Ljava/lang/String;)Ljava/lang/StringBuilder;
/*     */     //   254: pop
/*     */     //   255: ldc '\\n'
/*     */     //   257: invokevirtual append : (Ljava/lang/String;)Ljava/lang/StringBuilder;
/*     */     //   260: pop
/*     */     //   261: aload_0
/*     */     //   262: getfield kd : Z
/*     */     //   265: ifne -> 286
/*     */     //   268: aload_2
/*     */     //   269: dup
/*     */     //   270: sipush #1436
/*     */     //   273: invokestatic OH0 : (I)Ljava/lang/String;
/*     */     //   276: invokevirtual append : (Ljava/lang/String;)Ljava/lang/StringBuilder;
/*     */     //   279: pop
/*     */     //   280: ldc '\\n'
/*     */     //   282: invokevirtual append : (Ljava/lang/String;)Ljava/lang/StringBuilder;
/*     */     //   285: pop
/*     */     //   286: aload_0
/*     */     //   287: iconst_0
/*     */     //   288: invokevirtual rg0 : (Z)Z
/*     */     //   291: ifne -> 312
/*     */     //   294: aload_2
/*     */     //   295: dup
/*     */     //   296: sipush #1445
/*     */     //   299: invokestatic OH0 : (I)Ljava/lang/String;
/*     */     //   302: invokevirtual append : (Ljava/lang/String;)Ljava/lang/StringBuilder;
/*     */     //   305: pop
/*     */     //   306: ldc '\\n'
/*     */     //   308: invokevirtual append : (Ljava/lang/String;)Ljava/lang/StringBuilder;
/*     */     //   311: pop
/*     */     //   312: aload_0
/*     */     //   313: getfield GK : S
/*     */     //   316: iconst_m1
/*     */     //   317: if_icmple -> 324
/*     */     //   320: iconst_1
/*     */     //   321: goto -> 325
/*     */     //   324: iconst_0
/*     */     //   325: ifeq -> 346
/*     */     //   328: aload_2
/*     */     //   329: dup
/*     */     //   330: sipush #1429
/*     */     //   333: invokestatic OH0 : (I)Ljava/lang/String;
/*     */     //   336: invokevirtual append : (Ljava/lang/String;)Ljava/lang/StringBuilder;
/*     */     //   339: pop
/*     */     //   340: ldc '\\n'
/*     */     //   342: invokevirtual append : (Ljava/lang/String;)Ljava/lang/StringBuilder;
/*     */     //   345: pop
/*     */     //   346: aload_0
/*     */     //   347: getfield Ap0 : Lf/m9;
/*     */     //   350: getstatic f/m9.Bt0 : Lf/m9;
/*     */     //   353: if_acmpeq -> 374
/*     */     //   356: aload_2
/*     */     //   357: dup
/*     */     //   358: ldc_w 16777252
/*     */     //   361: invokestatic OH0 : (I)Ljava/lang/String;
/*     */     //   364: invokevirtual append : (Ljava/lang/String;)Ljava/lang/StringBuilder;
/*     */     //   367: pop
/*     */     //   368: ldc '\\n'
/*     */     //   370: invokevirtual append : (Ljava/lang/String;)Ljava/lang/StringBuilder;
/*     */     //   373: pop
/*     */     //   374: aload_0
/*     */     //   375: getfield Y8 : Lf/Hu0;
/*     */     //   378: dup
/*     */     //   379: astore #4
/*     */     //   381: getstatic f/Hu0.w2 : Lf/Hu0;
/*     */     //   384: if_acmpeq -> 1018
/*     */     //   387: aload #4
/*     */     //   389: aload_3
/*     */     //   390: if_acmpeq -> 1018
/*     */     //   393: aload_0
/*     */     //   394: getfield lh : I
/*     */     //   397: ifle -> 430
/*     */     //   400: aload_2
/*     */     //   401: dup
/*     */     //   402: invokestatic getInstance : ()Ljava/text/NumberFormat;
/*     */     //   405: aload_0
/*     */     //   406: getfield lh : I
/*     */     //   409: i2l
/*     */     //   410: invokevirtual format : (J)Ljava/lang/String;
/*     */     //   413: ldc_w 101421
/*     */     //   416: swap
/*     */     //   417: invokestatic Go : (ILjava/lang/String;)Ljava/lang/String;
/*     */     //   420: invokevirtual append : (Ljava/lang/String;)Ljava/lang/StringBuilder;
/*     */     //   423: pop
/*     */     //   424: ldc '\\n'
/*     */     //   426: invokevirtual append : (Ljava/lang/String;)Ljava/lang/StringBuilder;
/*     */     //   429: pop
/*     */     //   430: aload_0
/*     */     //   431: new java/lang/StringBuilder
/*     */     //   434: dup
/*     */     //   435: astore_3
/*     */     //   436: invokespecial <init> : ()V
/*     */     //   439: getfield Pa0 : S
/*     */     //   442: ifle -> 479
/*     */     //   445: aload_3
/*     */     //   446: dup
/*     */     //   447: aload_0
/*     */     //   448: getfield Rv0 : Z
/*     */     //   451: sipush #1426
/*     */     //   454: iadd
/*     */     //   455: invokestatic getInstance : ()Ljava/text/NumberFormat;
/*     */     //   458: aload_0
/*     */     //   459: getfield Pa0 : S
/*     */     //   462: i2l
/*     */     //   463: invokevirtual format : (J)Ljava/lang/String;
/*     */     //   466: invokestatic Go : (ILjava/lang/String;)Ljava/lang/String;
/*     */     //   469: invokevirtual append : (Ljava/lang/String;)Ljava/lang/StringBuilder;
/*     */     //   472: pop
/*     */     //   473: ldc '\\n'
/*     */     //   475: invokevirtual append : (Ljava/lang/String;)Ljava/lang/StringBuilder;
/*     */     //   478: pop
/*     */     //   479: aload_0
/*     */     //   480: getfield xp0 : B
/*     */     //   483: iconst_m1
/*     */     //   484: if_icmpne -> 505
/*     */     //   487: aload_3
/*     */     //   488: dup
/*     */     //   489: sipush #3523
/*     */     //   492: invokestatic OH0 : (I)Ljava/lang/String;
/*     */     //   495: invokevirtual append : (Ljava/lang/String;)Ljava/lang/StringBuilder;
/*     */     //   498: pop
/*     */     //   499: ldc '\\n'
/*     */     //   501: invokevirtual append : (Ljava/lang/String;)Ljava/lang/StringBuilder;
/*     */     //   504: pop
/*     */     //   505: aload_3
/*     */     //   506: invokevirtual length : ()I
/*     */     //   509: ifle -> 518
/*     */     //   512: aload_2
/*     */     //   513: aload_3
/*     */     //   514: invokevirtual append : (Ljava/lang/CharSequence;)Ljava/lang/StringBuilder;
/*     */     //   517: pop
/*     */     //   518: aload_0
/*     */     //   519: getfield el : Lf/hR;
/*     */     //   522: dup
/*     */     //   523: astore_3
/*     */     //   524: ifnull -> 629
/*     */     //   527: aload_0
/*     */     //   528: getfield lA : S
/*     */     //   531: ifeq -> 629
/*     */     //   534: aload_0
/*     */     //   535: sipush #1428
/*     */     //   538: istore #4
/*     */     //   540: iconst_2
/*     */     //   541: anewarray java/lang/String
/*     */     //   544: dup
/*     */     //   545: astore #5
/*     */     //   547: aload_3
/*     */     //   548: invokevirtual toString : ()Ljava/lang/String;
/*     */     //   551: iconst_0
/*     */     //   552: swap
/*     */     //   553: aastore
/*     */     //   554: iconst_1
/*     */     //   555: istore_3
/*     */     //   556: new java/lang/StringBuilder
/*     */     //   559: dup
/*     */     //   560: astore #6
/*     */     //   562: invokespecial <init> : ()V
/*     */     //   565: getfield lA : S
/*     */     //   568: ifle -> 579
/*     */     //   571: ldc_w '+'
/*     */     //   574: astore #7
/*     */     //   576: goto -> 583
/*     */     //   579: ldc ''
/*     */     //   581: astore #7
/*     */     //   583: aload_2
/*     */     //   584: dup
/*     */     //   585: iload #4
/*     */     //   587: aload #5
/*     */     //   589: dup
/*     */     //   590: iload_3
/*     */     //   591: aload #6
/*     */     //   593: aload #7
/*     */     //   595: invokevirtual append : (Ljava/lang/String;)Ljava/lang/StringBuilder;
/*     */     //   598: invokestatic getInstance : ()Ljava/text/NumberFormat;
/*     */     //   601: aload_0
/*     */     //   602: getfield lA : S
/*     */     //   605: i2l
/*     */     //   606: invokevirtual format : (J)Ljava/lang/String;
/*     */     //   609: invokevirtual append : (Ljava/lang/String;)Ljava/lang/StringBuilder;
/*     */     //   612: invokevirtual toString : ()Ljava/lang/String;
/*     */     //   615: aastore
/*     */     //   616: invokestatic sB : (I[Ljava/lang/String;)Ljava/lang/String;
/*     */     //   619: invokevirtual append : (Ljava/lang/String;)Ljava/lang/StringBuilder;
/*     */     //   622: pop
/*     */     //   623: ldc '\\n'
/*     */     //   625: invokevirtual append : (Ljava/lang/String;)Ljava/lang/StringBuilder;
/*     */     //   628: pop
/*     */     //   629: aload_0
/*     */     //   630: getfield bj0 : S
/*     */     //   633: invokestatic l90 : (S)S
/*     */     //   636: dup
/*     */     //   637: istore_3
/*     */     //   638: sipush #5548
/*     */     //   641: if_icmplt -> 677
/*     */     //   644: iload_3
/*     */     //   645: sipush #5564
/*     */     //   648: if_icmpgt -> 677
/*     */     //   651: aload_2
/*     */     //   652: dup
/*     */     //   653: iload_3
/*     */     //   654: invokestatic nt : (S)Lf/Ht0;
/*     */     //   657: invokevirtual toString : ()Ljava/lang/String;
/*     */     //   660: sipush #1433
/*     */     //   663: swap
/*     */     //   664: invokestatic Go : (ILjava/lang/String;)Ljava/lang/String;
/*     */     //   667: invokevirtual append : (Ljava/lang/String;)Ljava/lang/StringBuilder;
/*     */     //   670: pop
/*     */     //   671: ldc '\\n'
/*     */     //   673: invokevirtual append : (Ljava/lang/String;)Ljava/lang/StringBuilder;
/*     */     //   676: pop
/*     */     //   677: iload_3
/*     */     //   678: bipush #121
/*     */     //   680: if_icmplt -> 690
/*     */     //   683: iload_3
/*     */     //   684: sipush #132
/*     */     //   687: if_icmple -> 732
/*     */     //   690: iload_3
/*     */     //   691: sipush #5137
/*     */     //   694: if_icmplt -> 704
/*     */     //   697: iload_3
/*     */     //   698: sipush #5148
/*     */     //   701: if_icmple -> 732
/*     */     //   704: iload_3
/*     */     //   705: sipush #8137
/*     */     //   708: if_icmplt -> 718
/*     */     //   711: iload_3
/*     */     //   712: sipush #8148
/*     */     //   715: if_icmple -> 732
/*     */     //   718: iload_3
/*     */     //   719: sipush #9137
/*     */     //   722: if_icmplt -> 750
/*     */     //   725: iload_3
/*     */     //   726: sipush #9148
/*     */     //   729: if_icmpgt -> 750
/*     */     //   732: aload_2
/*     */     //   733: dup
/*     */     //   734: sipush #1434
/*     */     //   737: invokestatic OH0 : (I)Ljava/lang/String;
/*     */     //   740: invokevirtual append : (Ljava/lang/String;)Ljava/lang/StringBuilder;
/*     */     //   743: pop
/*     */     //   744: ldc '\\n'
/*     */     //   746: invokevirtual append : (Ljava/lang/String;)Ljava/lang/StringBuilder;
/*     */     //   749: pop
/*     */     //   750: aload_0
/*     */     //   751: getfield KD0 : S
/*     */     //   754: dup
/*     */     //   755: istore_3
/*     */     //   756: ifeq -> 879
/*     */     //   759: iload_3
/*     */     //   760: ifle -> 793
/*     */     //   763: iload_3
/*     */     //   764: bipush #10
/*     */     //   766: if_icmpge -> 775
/*     */     //   769: sipush #1453
/*     */     //   772: goto -> 820
/*     */     //   775: iload_3
/*     */     //   776: bipush #20
/*     */     //   778: if_icmpge -> 787
/*     */     //   781: sipush #1454
/*     */     //   784: goto -> 820
/*     */     //   787: sipush #1455
/*     */     //   790: goto -> 820
/*     */     //   793: iload_3
/*     */     //   794: bipush #-10
/*     */     //   796: if_icmple -> 805
/*     */     //   799: sipush #1456
/*     */     //   802: goto -> 820
/*     */     //   805: iload_3
/*     */     //   806: bipush #-20
/*     */     //   808: if_icmple -> 817
/*     */     //   811: sipush #1457
/*     */     //   814: goto -> 820
/*     */     //   817: sipush #1458
/*     */     //   820: invokestatic OH0 : (I)Ljava/lang/String;
/*     */     //   823: astore_3
/*     */     //   824: aload_0
/*     */     //   825: aload_2
/*     */     //   826: dup
/*     */     //   827: aload_3
/*     */     //   828: invokevirtual append : (Ljava/lang/String;)Ljava/lang/StringBuilder;
/*     */     //   831: pop
/*     */     //   832: ldc '\\n'
/*     */     //   834: invokevirtual append : (Ljava/lang/String;)Ljava/lang/StringBuilder;
/*     */     //   837: pop
/*     */     //   838: getfield h3 : Lf/XZ;
/*     */     //   841: dup
/*     */     //   842: astore_3
/*     */     //   843: getstatic f/XZ.Sn0 : Lf/XZ;
/*     */     //   846: if_acmpeq -> 879
/*     */     //   849: aload_2
/*     */     //   850: dup
/*     */     //   851: iload_1
/*     */     //   852: aload_3
/*     */     //   853: invokevirtual V40 : ()I
/*     */     //   856: invokestatic OH0 : (I)Ljava/lang/String;
/*     */     //   859: sipush #1459
/*     */     //   862: swap
/*     */     //   863: invokestatic Go : (ILjava/lang/String;)Ljava/lang/String;
/*     */     //   866: invokestatic JF : (ILjava/lang/String;)Ljava/lang/String;
/*     */     //   869: invokevirtual append : (Ljava/lang/String;)Ljava/lang/StringBuilder;
/*     */     //   872: pop
/*     */     //   873: ldc '\\n'
/*     */     //   875: invokevirtual append : (Ljava/lang/String;)Ljava/lang/StringBuilder;
/*     */     //   878: pop
/*     */     //   879: aload_0
/*     */     //   880: getfield t5 : Lf/Uj;
/*     */     //   883: dup
/*     */     //   884: astore_0
/*     */     //   885: getstatic f/Uj.Lt : Lf/Uj;
/*     */     //   888: if_acmpeq -> 1018
/*     */     //   891: aload_2
/*     */     //   892: invokevirtual length : ()I
/*     */     //   895: ifle -> 905
/*     */     //   898: aload_2
/*     */     //   899: ldc '\\n'
/*     */     //   901: invokevirtual append : (Ljava/lang/String;)Ljava/lang/StringBuilder;
/*     */     //   904: pop
/*     */     //   905: getstatic f/km.u4 : Lf/R8;
/*     */     //   908: dup
/*     */     //   909: getfield kw0 : Lf/ak;
/*     */     //   912: dup
/*     */     //   913: astore_1
/*     */     //   914: monitorenter
/*     */     //   915: getfield kw0 : Lf/ak;
/*     */     //   918: aload_0
/*     */     //   919: getfield D : B
/*     */     //   922: invokevirtual Ha0 : (B)Ljava/lang/Object;
/*     */     //   925: checkcast f/Cj
/*     */     //   928: dup
/*     */     //   929: astore_3
/*     */     //   930: aload_1
/*     */     //   931: monitorexit
/*     */     //   932: ifnull -> 989
/*     */     //   935: aload_3
/*     */     //   936: getfield lpT3 : Lf/v30;
/*     */     //   939: getstatic f/v30.Z6 : Lf/v30;
/*     */     //   942: if_acmpne -> 989
/*     */     //   945: aload_2
/*     */     //   946: aload_3
/*     */     //   947: invokestatic currentTimeMillis : ()J
/*     */     //   950: ldc2_w 1000
/*     */     //   953: ldiv
/*     */     //   954: l2i
/*     */     //   955: istore_0
/*     */     //   956: getfield COM2 : I
/*     */     //   959: iload_0
/*     */     //   960: aload_3
/*     */     //   961: getfield vt0 : I
/*     */     //   964: isub
/*     */     //   965: isub
/*     */     //   966: iconst_1
/*     */     //   967: invokestatic da0 : (IZ)Ljava/lang/String;
/*     */     //   970: sipush #1461
/*     */     //   973: swap
/*     */     //   974: invokestatic Go : (ILjava/lang/String;)Ljava/lang/String;
/*     */     //   977: invokevirtual append : (Ljava/lang/String;)Ljava/lang/StringBuilder;
/*     */     //   980: ldc '\\n'
/*     */     //   982: invokevirtual append : (Ljava/lang/String;)Ljava/lang/StringBuilder;
/*     */     //   985: pop
/*     */     //   986: goto -> 1018
/*     */     //   989: aload_2
/*     */     //   990: aload_0
/*     */     //   991: invokevirtual toString : ()Ljava/lang/String;
/*     */     //   994: sipush #1449
/*     */     //   997: swap
/*     */     //   998: invokestatic Go : (ILjava/lang/String;)Ljava/lang/String;
/*     */     //   1001: invokevirtual append : (Ljava/lang/String;)Ljava/lang/StringBuilder;
/*     */     //   1004: ldc '\\n'
/*     */     //   1006: invokevirtual append : (Ljava/lang/String;)Ljava/lang/StringBuilder;
/*     */     //   1009: pop
/*     */     //   1010: goto -> 1018
/*     */     //   1013: astore_0
/*     */     //   1014: aload_0
/*     */     //   1015: aload_1
/*     */     //   1016: monitorexit
/*     */     //   1017: athrow
/*     */     //   1018: aload_2
/*     */     //   1019: areturn
/*     */     // Line number table:
/*     */     //   Java source line number -> byte code offset
/*     */     //   #1	-> 42
/*     */     //   #2	-> 47
/*     */     //   #3	-> 68
/*     */     //   #4	-> 73
/*     */     //   #5	-> 76
/*     */     //   #6	-> 85
/*     */     //   #7	-> 88
/*     */     //   #8	-> 104
/*     */     //   #9	-> 107
/*     */     //   #10	-> 116
/*     */     //   #11	-> 123
/*     */     //   #12	-> 130
/*     */     //   #13	-> 134
/*     */     //   #14	-> 138
/*     */     //   #15	-> 237
/*     */     //   #16	-> 248
/*     */     //   #17	-> 262
/*     */     //   #18	-> 273
/*     */     //   #19	-> 313
/*     */     //   #20	-> 333
/*     */     //   #21	-> 347
/*     */     //   #22	-> 350
/*     */     //   #23	-> 375
/*     */     //   #24	-> 381
/*     */     //   #25	-> 394
/*     */     //   #26	-> 402
/*     */     //   #27	-> 406
/*     */     //   #28	-> 410
/*     */     //   #29	-> 431
/*     */     //   #30	-> 439
/*     */     //   #31	-> 448
/*     */     //   #32	-> 455
/*     */     //   #33	-> 459
/*     */     //   #34	-> 463
/*     */     //   #35	-> 480
/*     */     //   #36	-> 492
/*     */     //   #37	-> 506
/*     */     //   #38	-> 519
/*     */     //   #39	-> 528
/*     */     //   #40	-> 541
/*     */     //   #41	-> 565
/*     */     //   #42	-> 571
/*     */     //   #43	-> 602
/*     */     //   #44	-> 606
/*     */     //   #45	-> 630
/*     */     //   #46	-> 633
/*     */     //   #47	-> 751
/*     */     //   #48	-> 820
/*     */     //   #49	-> 838
/*     */     //   #50	-> 843
/*     */     //   #51	-> 880
/*     */     //   #52	-> 885
/*     */     //   #53	-> 909
/*     */     //   #54	-> 914
/*     */     //   #55	-> 919
/*     */     //   #56	-> 922
/*     */     //   #57	-> 936
/*     */     //   #58	-> 939
/*     */     //   #59	-> 947
/*     */     //   #60	-> 967
/*     */     //   #61	-> 974
/*     */     //   #62	-> 1016
/*     */     // Exception table:
/*     */     //   from	to	target	type
/*     */     //   915	928	1013	finally
/*     */     //   930	932	1013	finally
/*     */     //   1014	1017	1013	finally
/*     */   }
/*     */   
/*     */   public static StringBuilder w0(LPT3 paramLPT3) {
/*     */     // Byte code:
/*     */     //   0: aload_0
/*     */     //   1: dup
/*     */     //   2: new java/lang/StringBuilder
/*     */     //   5: dup
/*     */     //   6: astore_1
/*     */     //   7: invokespecial <init> : ()V
/*     */     //   10: getfield wg0 : Lf/v7;
/*     */     //   13: astore_2
/*     */     //   14: getfield Y8 : Lf/Hu0;
/*     */     //   17: getstatic f/Hu0.w2 : Lf/Hu0;
/*     */     //   20: if_acmpeq -> 192
/*     */     //   23: aload_2
/*     */     //   24: invokevirtual ordinal : ()I
/*     */     //   27: tableswitch default -> 84, 1 -> 176, 2 -> 84, 3 -> 87, 4 -> 157, 5 -> 84, 6 -> 87, 7 -> 84, 8 -> 138, 9 -> 176, 10 -> 176, 11 -> 176
/*     */     //   84: goto -> 192
/*     */     //   87: aload_0
/*     */     //   88: getfield sw : Lf/Uj;
/*     */     //   91: dup
/*     */     //   92: astore_3
/*     */     //   93: ifnull -> 119
/*     */     //   96: aload_1
/*     */     //   97: sipush #19964
/*     */     //   100: aload_3
/*     */     //   101: invokevirtual toString : ()Ljava/lang/String;
/*     */     //   104: invokestatic Go : (ILjava/lang/String;)Ljava/lang/String;
/*     */     //   107: invokevirtual append : (Ljava/lang/String;)Ljava/lang/StringBuilder;
/*     */     //   110: ldc '\\n'
/*     */     //   112: invokevirtual append : (Ljava/lang/String;)Ljava/lang/StringBuilder;
/*     */     //   115: pop
/*     */     //   116: goto -> 192
/*     */     //   119: aload_1
/*     */     //   120: sipush #19954
/*     */     //   123: invokestatic OH0 : (I)Ljava/lang/String;
/*     */     //   126: invokevirtual append : (Ljava/lang/String;)Ljava/lang/StringBuilder;
/*     */     //   129: ldc '\\n'
/*     */     //   131: invokevirtual append : (Ljava/lang/String;)Ljava/lang/StringBuilder;
/*     */     //   134: pop
/*     */     //   135: goto -> 192
/*     */     //   138: aload_1
/*     */     //   139: sipush #19958
/*     */     //   142: invokestatic OH0 : (I)Ljava/lang/String;
/*     */     //   145: invokevirtual append : (Ljava/lang/String;)Ljava/lang/StringBuilder;
/*     */     //   148: ldc '\\n'
/*     */     //   150: invokevirtual append : (Ljava/lang/String;)Ljava/lang/StringBuilder;
/*     */     //   153: pop
/*     */     //   154: goto -> 192
/*     */     //   157: aload_1
/*     */     //   158: sipush #19953
/*     */     //   161: invokestatic OH0 : (I)Ljava/lang/String;
/*     */     //   164: invokevirtual append : (Ljava/lang/String;)Ljava/lang/StringBuilder;
/*     */     //   167: ldc '\\n'
/*     */     //   169: invokevirtual append : (Ljava/lang/String;)Ljava/lang/StringBuilder;
/*     */     //   172: pop
/*     */     //   173: goto -> 192
/*     */     //   176: aload_1
/*     */     //   177: sipush #19956
/*     */     //   180: invokestatic OH0 : (I)Ljava/lang/String;
/*     */     //   183: invokevirtual append : (Ljava/lang/String;)Ljava/lang/StringBuilder;
/*     */     //   186: ldc '\\n'
/*     */     //   188: invokevirtual append : (Ljava/lang/String;)Ljava/lang/StringBuilder;
/*     */     //   191: pop
/*     */     //   192: aload_0
/*     */     //   193: getfield BU : Ljava/time/YearMonth;
/*     */     //   196: dup
/*     */     //   197: astore_3
/*     */     //   198: ifnull -> 417
/*     */     //   201: aload_3
/*     */     //   202: invokevirtual getYear : ()I
/*     */     //   205: sipush #2010
/*     */     //   208: if_icmplt -> 417
/*     */     //   211: aload_2
/*     */     //   212: getstatic f/v7.c0 : Lf/v7;
/*     */     //   215: if_acmpeq -> 353
/*     */     //   218: aload_2
/*     */     //   219: getstatic f/v7.bX : Lf/v7;
/*     */     //   222: if_acmpne -> 228
/*     */     //   225: goto -> 353
/*     */     //   228: aload_2
/*     */     //   229: getstatic f/v7.fx0 : Lf/v7;
/*     */     //   232: if_acmpeq -> 299
/*     */     //   235: aload_2
/*     */     //   236: getstatic f/v7.cv : Lf/v7;
/*     */     //   239: if_acmpne -> 245
/*     */     //   242: goto -> 299
/*     */     //   245: aload_1
/*     */     //   246: sipush #19960
/*     */     //   249: iconst_2
/*     */     //   250: anewarray java/lang/String
/*     */     //   253: dup
/*     */     //   254: dup
/*     */     //   255: aload_3
/*     */     //   256: swap
/*     */     //   257: iconst_0
/*     */     //   258: aload_3
/*     */     //   259: invokevirtual getMonth : ()Ljava/time/Month;
/*     */     //   262: getstatic java/time/format/TextStyle.FULL : Ljava/time/format/TextStyle;
/*     */     //   265: getstatic f/cE.eo0 : Lf/cE;
/*     */     //   268: getfield Dr : Ljava/util/Locale;
/*     */     //   271: invokevirtual getDisplayName : (Ljava/time/format/TextStyle;Ljava/util/Locale;)Ljava/lang/String;
/*     */     //   274: aastore
/*     */     //   275: invokevirtual getYear : ()I
/*     */     //   278: invokestatic toString : (I)Ljava/lang/String;
/*     */     //   281: iconst_1
/*     */     //   282: swap
/*     */     //   283: aastore
/*     */     //   284: invokestatic sB : (I[Ljava/lang/String;)Ljava/lang/String;
/*     */     //   287: invokevirtual append : (Ljava/lang/String;)Ljava/lang/StringBuilder;
/*     */     //   290: ldc '\\n'
/*     */     //   292: invokevirtual append : (Ljava/lang/String;)Ljava/lang/StringBuilder;
/*     */     //   295: pop
/*     */     //   296: goto -> 417
/*     */     //   299: aload_1
/*     */     //   300: sipush #19961
/*     */     //   303: iconst_2
/*     */     //   304: anewarray java/lang/String
/*     */     //   307: dup
/*     */     //   308: dup
/*     */     //   309: aload_3
/*     */     //   310: swap
/*     */     //   311: iconst_0
/*     */     //   312: aload_3
/*     */     //   313: invokevirtual getMonth : ()Ljava/time/Month;
/*     */     //   316: getstatic java/time/format/TextStyle.FULL : Ljava/time/format/TextStyle;
/*     */     //   319: getstatic f/cE.eo0 : Lf/cE;
/*     */     //   322: getfield Dr : Ljava/util/Locale;
/*     */     //   325: invokevirtual getDisplayName : (Ljava/time/format/TextStyle;Ljava/util/Locale;)Ljava/lang/String;
/*     */     //   328: aastore
/*     */     //   329: invokevirtual getYear : ()I
/*     */     //   332: invokestatic toString : (I)Ljava/lang/String;
/*     */     //   335: iconst_1
/*     */     //   336: swap
/*     */     //   337: aastore
/*     */     //   338: invokestatic sB : (I[Ljava/lang/String;)Ljava/lang/String;
/*     */     //   341: invokevirtual append : (Ljava/lang/String;)Ljava/lang/StringBuilder;
/*     */     //   344: ldc '\\n'
/*     */     //   346: invokevirtual append : (Ljava/lang/String;)Ljava/lang/StringBuilder;
/*     */     //   349: pop
/*     */     //   350: goto -> 417
/*     */     //   353: aload_0
/*     */     //   354: getfield sw : Lf/Uj;
/*     */     //   357: dup
/*     */     //   358: astore #4
/*     */     //   360: ifnull -> 409
/*     */     //   363: aload_1
/*     */     //   364: sipush #19962
/*     */     //   367: iconst_2
/*     */     //   368: anewarray java/lang/String
/*     */     //   371: dup
/*     */     //   372: dup
/*     */     //   373: aload_3
/*     */     //   374: swap
/*     */     //   375: aload #4
/*     */     //   377: iconst_0
/*     */     //   378: istore_3
/*     */     //   379: invokevirtual toString : ()Ljava/lang/String;
/*     */     //   382: iload_3
/*     */     //   383: swap
/*     */     //   384: aastore
/*     */     //   385: invokevirtual getYear : ()I
/*     */     //   388: invokestatic toString : (I)Ljava/lang/String;
/*     */     //   391: iconst_1
/*     */     //   392: swap
/*     */     //   393: aastore
/*     */     //   394: invokestatic sB : (I[Ljava/lang/String;)Ljava/lang/String;
/*     */     //   397: invokevirtual append : (Ljava/lang/String;)Ljava/lang/StringBuilder;
/*     */     //   400: ldc '\\n'
/*     */     //   402: invokevirtual append : (Ljava/lang/String;)Ljava/lang/StringBuilder;
/*     */     //   405: pop
/*     */     //   406: goto -> 417
/*     */     //   409: aload_1
/*     */     //   410: ldc_w 'SEASONAL_EVENT_ERR'
/*     */     //   413: invokevirtual append : (Ljava/lang/String;)Ljava/lang/StringBuilder;
/*     */     //   416: pop
/*     */     //   417: aload_2
/*     */     //   418: getstatic f/v7.bX : Lf/v7;
/*     */     //   421: if_acmpne -> 453
/*     */     //   424: aload_0
/*     */     //   425: getfield ge : Lf/yL;
/*     */     //   428: dup
/*     */     //   429: astore_0
/*     */     //   430: ifnull -> 453
/*     */     //   433: aload_1
/*     */     //   434: sipush #19963
/*     */     //   437: aload_0
/*     */     //   438: invokevirtual toString : ()Ljava/lang/String;
/*     */     //   441: invokestatic Go : (ILjava/lang/String;)Ljava/lang/String;
/*     */     //   444: invokevirtual append : (Ljava/lang/String;)Ljava/lang/StringBuilder;
/*     */     //   447: ldc '\\n'
/*     */     //   449: invokevirtual append : (Ljava/lang/String;)Ljava/lang/StringBuilder;
/*     */     //   452: pop
/*     */     //   453: aload_1
/*     */     //   454: areturn
/*     */     // Line number table:
/*     */     //   Java source line number -> byte code offset
/*     */     //   #1	-> 10
/*     */     //   #2	-> 14
/*     */     //   #3	-> 17
/*     */     //   #4	-> 88
/*     */     //   #5	-> 101
/*     */     //   #6	-> 193
/*     */     //   #7	-> 202
/*     */     //   #8	-> 265
/*     */     //   #9	-> 268
/*     */     //   #10	-> 271
/*     */     //   #11	-> 319
/*     */     //   #12	-> 322
/*     */     //   #13	-> 325
/*     */     //   #14	-> 354
/*     */     //   #15	-> 368
/*     */     //   #16	-> 425
/*     */     //   #17	-> 438
/*     */   }
/*     */   
/*     */   public static String FK0(LPT3 paramLPT3) {
/*     */     short s = dx.l90(paramLPT3.bj0);
/*     */     if (!paramLPT3.co0() || s == 1422 || s == 1446 || (s >= 1447 && s <= 1471))
/*     */       return ""; 
/*     */     this();
/*     */     StringBuilder stringBuilder;
/*     */     (new StringBuilder()).append(Ml0.OH0(1446));
/*     */     UD0[] arrayOfUD0;
/*     */     if ((arrayOfUD0 = (UD0[])Arrays.<UD0>stream(paramLPT3.ia0).map(UD0::Fk0).distinct().sorted(Comparator.comparingInt(UD0::Uf)).toArray(rG0::vK0)).length > 5) {
/*     */       byte b1;
/*     */       StringBuilder stringBuilder1;
/*     */       if (t90.bigCJKFontSizes()) {
/*     */         b1 = 22;
/*     */       } else {
/*     */         b1 = 38;
/*     */       } 
/*     */       this();
/*     */       for (byte b2 = 0; b2 < arrayOfUD0.length; ) {
/*     */         UD0 uD0 = arrayOfUD0[b2];
/*     */         if (b2 == 0) {
/*     */           stringBuilder1.append("• ");
/*     */         } else {
/*     */           stringBuilder1.append(", ");
/*     */         } 
/*     */         stringBuilder1.append(uD0.o60(false));
/*     */         b2++;
/*     */       } 
/*     */       stringBuilder.append("\n").append(cS.JF(b1, stringBuilder1.toString()));
/*     */     } else {
/*     */       int i;
/*     */       byte b;
/*     */       for (i = arrayOfUD0.length, b = 0; b < i; ) {
/*     */         UD0 uD0 = arrayOfUD0[b];
/*     */         if (stringBuilder.length() > 0)
/*     */           stringBuilder.append("\n"); 
/*     */         stringBuilder.append("• ").append(uD0.o60(false));
/*     */         b++;
/*     */       } 
/*     */     } 
/*     */     return stringBuilder.toString();
/*     */   }
/*     */   
/*     */   public static String Vk(UD0 paramUD0) {
/*     */     this("");
/*     */     stringBuilder.append(Ml0.OH0(paramUD0.zq0(0) + 210000));
/*     */     stringBuilder.append("\n------\n");
/*     */     StringBuilder stringBuilder;
/*     */     (stringBuilder = new StringBuilder()).append(Ml0.OH0(paramUD0.zq0(0) + 220000));
/*     */     if (paramUD0.zq0(0) != paramUD0.zq0(1) && paramUD0.zq0(1) > 0) {
/*     */       stringBuilder.append("\n\n\n");
/*     */       stringBuilder.append(Ml0.OH0(paramUD0.zq0(1) + 210000));
/*     */       stringBuilder.append("\n------\n");
/*     */       stringBuilder.append(Ml0.OH0(paramUD0.zq0(1) + 220000));
/*     */     } 
/*     */     return stringBuilder.toString();
/*     */   }
/*     */   
/*     */   public static final String Ef0(Gp0 paramGp0, cOm4 paramcOm4) {
/*     */     return P70(paramGp0, paramcOm4, false);
/*     */   }
/*     */   
/*     */   public static String P70(Gp0 paramGp0, cOm4 paramcOm4, boolean paramBoolean) {
/*     */     // Byte code:
/*     */     //   0: aload_1
/*     */     //   1: ifnull -> 1388
/*     */     //   4: aload_1
/*     */     //   5: invokevirtual LF : ()Z
/*     */     //   8: ifne -> 14
/*     */     //   11: goto -> 1388
/*     */     //   14: aload_1
/*     */     //   15: getfield gc : Lf/jd0;
/*     */     //   18: dup
/*     */     //   19: astore_3
/*     */     //   20: ifnull -> 31
/*     */     //   23: aload_3
/*     */     //   24: invokevirtual AL : ()Z
/*     */     //   27: istore_3
/*     */     //   28: goto -> 47
/*     */     //   31: aload_1
/*     */     //   32: getfield k60 : B
/*     */     //   35: bipush #-2
/*     */     //   37: if_icmpne -> 45
/*     */     //   40: iconst_1
/*     */     //   41: istore_3
/*     */     //   42: goto -> 47
/*     */     //   45: iconst_0
/*     */     //   46: istore_3
/*     */     //   47: aload_1
/*     */     //   48: ldc ''
/*     */     //   50: astore #4
/*     */     //   52: ldc ''
/*     */     //   54: astore #5
/*     */     //   56: new java/lang/StringBuilder
/*     */     //   59: dup
/*     */     //   60: astore #6
/*     */     //   62: ldc ''
/*     */     //   64: invokespecial <init> : (Ljava/lang/String;)V
/*     */     //   67: getfield gc : Lf/jd0;
/*     */     //   70: dup
/*     */     //   71: astore #7
/*     */     //   73: ifnull -> 82
/*     */     //   76: iconst_1
/*     */     //   77: istore #8
/*     */     //   79: goto -> 85
/*     */     //   82: iconst_0
/*     */     //   83: istore #8
/*     */     //   85: iload #8
/*     */     //   87: ifne -> 172
/*     */     //   90: aload_1
/*     */     //   91: getfield dm0 : Lf/QZ;
/*     */     //   94: instanceof f/Yu
/*     */     //   97: ifne -> 172
/*     */     //   100: iload_3
/*     */     //   101: bipush #59
/*     */     //   103: invokestatic OH0 : (I)Ljava/lang/String;
/*     */     //   106: astore_0
/*     */     //   107: ldc_w '???'
/*     */     //   110: astore_1
/*     */     //   111: ldc_w '???'
/*     */     //   114: astore_2
/*     */     //   115: ifeq -> 128
/*     */     //   118: sipush #5211
/*     */     //   121: invokestatic OH0 : (I)Ljava/lang/String;
/*     */     //   124: astore_3
/*     */     //   125: goto -> 132
/*     */     //   128: ldc_w '???%'
/*     */     //   131: astore_3
/*     */     //   132: aload #6
/*     */     //   134: dup
/*     */     //   135: aload_0
/*     */     //   136: invokevirtual append : (Ljava/lang/String;)Ljava/lang/StringBuilder;
/*     */     //   139: ldc ' '
/*     */     //   141: invokevirtual append : (Ljava/lang/String;)Ljava/lang/StringBuilder;
/*     */     //   144: aload_2
/*     */     //   145: invokevirtual append : (Ljava/lang/String;)Ljava/lang/StringBuilder;
/*     */     //   148: ldc ' '
/*     */     //   150: invokevirtual append : (Ljava/lang/String;)Ljava/lang/StringBuilder;
/*     */     //   153: aload_1
/*     */     //   154: invokevirtual append : (Ljava/lang/String;)Ljava/lang/StringBuilder;
/*     */     //   157: ldc_w ' - '
/*     */     //   160: invokevirtual append : (Ljava/lang/String;)Ljava/lang/StringBuilder;
/*     */     //   163: aload_3
/*     */     //   164: invokevirtual append : (Ljava/lang/String;)Ljava/lang/StringBuilder;
/*     */     //   167: pop
/*     */     //   168: invokevirtual toString : ()Ljava/lang/String;
/*     */     //   171: areturn
/*     */     //   172: aload #7
/*     */     //   174: ifnonnull -> 180
/*     */     //   177: ldc ''
/*     */     //   179: areturn
/*     */     //   180: iload_2
/*     */     //   181: aconst_null
/*     */     //   182: astore_1
/*     */     //   183: ifne -> 328
/*     */     //   186: aload_0
/*     */     //   187: aload #7
/*     */     //   189: getfield ta : Lf/Q90;
/*     */     //   192: getfield q10 : I
/*     */     //   195: invokevirtual fa : (I)Lf/hm0;
/*     */     //   198: dup
/*     */     //   199: astore_1
/*     */     //   200: ifnull -> 328
/*     */     //   203: aload_1
/*     */     //   204: getfield BC : S
/*     */     //   207: iconst_m1
/*     */     //   208: if_icmpeq -> 215
/*     */     //   211: iconst_1
/*     */     //   212: goto -> 216
/*     */     //   215: iconst_0
/*     */     //   216: ifeq -> 231
/*     */     //   219: aload_1
/*     */     //   220: invokevirtual D90 : ()S
/*     */     //   223: ldc 210000
/*     */     //   225: iadd
/*     */     //   226: invokestatic OH0 : (I)Ljava/lang/String;
/*     */     //   229: astore #4
/*     */     //   231: aload_1
/*     */     //   232: getfield lPt1 : Lf/Ht0;
/*     */     //   235: getstatic f/Ht0.P00 : Lf/Ht0;
/*     */     //   238: dup
/*     */     //   239: astore_2
/*     */     //   240: if_acmpne -> 258
/*     */     //   243: aload_1
/*     */     //   244: getfield se : Lf/Ht0;
/*     */     //   247: aload_2
/*     */     //   248: if_acmpeq -> 254
/*     */     //   251: goto -> 258
/*     */     //   254: iconst_0
/*     */     //   255: goto -> 259
/*     */     //   258: iconst_1
/*     */     //   259: ifeq -> 328
/*     */     //   262: aload_1
/*     */     //   263: invokevirtual VA0 : ()Lf/Ht0;
/*     */     //   266: aload_1
/*     */     //   267: invokevirtual qH0 : ()Lf/Ht0;
/*     */     //   270: if_acmpne -> 292
/*     */     //   273: aload_1
/*     */     //   274: invokevirtual VA0 : ()Lf/Ht0;
/*     */     //   277: invokevirtual mn0 : ()Ljava/lang/String;
/*     */     //   280: sipush #7006
/*     */     //   283: swap
/*     */     //   284: invokestatic Go : (ILjava/lang/String;)Ljava/lang/String;
/*     */     //   287: astore #5
/*     */     //   289: goto -> 328
/*     */     //   292: iconst_2
/*     */     //   293: anewarray java/lang/String
/*     */     //   296: dup
/*     */     //   297: astore_2
/*     */     //   298: aload_1
/*     */     //   299: aload_2
/*     */     //   300: aload_1
/*     */     //   301: invokevirtual VA0 : ()Lf/Ht0;
/*     */     //   304: invokevirtual mn0 : ()Ljava/lang/String;
/*     */     //   307: iconst_0
/*     */     //   308: swap
/*     */     //   309: aastore
/*     */     //   310: invokevirtual qH0 : ()Lf/Ht0;
/*     */     //   313: invokevirtual mn0 : ()Ljava/lang/String;
/*     */     //   316: iconst_1
/*     */     //   317: swap
/*     */     //   318: aastore
/*     */     //   319: sipush #7007
/*     */     //   322: aload_2
/*     */     //   323: invokestatic sB : (I[Ljava/lang/String;)Ljava/lang/String;
/*     */     //   326: astore #5
/*     */     //   328: aload_1
/*     */     //   329: ifnull -> 340
/*     */     //   332: aload_1
/*     */     //   333: invokevirtual Hk : ()B
/*     */     //   336: istore_2
/*     */     //   337: goto -> 349
/*     */     //   340: aload #7
/*     */     //   342: getfield ta : Lf/Q90;
/*     */     //   345: getfield od : B
/*     */     //   348: istore_2
/*     */     //   349: aload_1
/*     */     //   350: ifnull -> 362
/*     */     //   353: aload_1
/*     */     //   354: invokevirtual Jx : ()S
/*     */     //   357: istore #8
/*     */     //   359: goto -> 372
/*     */     //   362: aload #7
/*     */     //   364: getfield ta : Lf/Q90;
/*     */     //   367: getfield Cw0 : S
/*     */     //   370: istore #8
/*     */     //   372: iload_3
/*     */     //   373: iload_2
/*     */     //   374: iload #8
/*     */     //   376: bipush #59
/*     */     //   378: invokestatic OH0 : (I)Ljava/lang/String;
/*     */     //   381: astore_2
/*     */     //   382: ldc_w 150000
/*     */     //   385: iadd
/*     */     //   386: invokestatic OH0 : (I)Ljava/lang/String;
/*     */     //   389: astore #8
/*     */     //   391: invokestatic toString : (I)Ljava/lang/String;
/*     */     //   394: astore #9
/*     */     //   396: ifeq -> 410
/*     */     //   399: sipush #5211
/*     */     //   402: invokestatic OH0 : (I)Ljava/lang/String;
/*     */     //   405: astore #10
/*     */     //   407: goto -> 448
/*     */     //   410: new java/lang/StringBuilder
/*     */     //   413: dup
/*     */     //   414: aload #7
/*     */     //   416: swap
/*     */     //   417: invokespecial <init> : ()V
/*     */     //   420: getfield ta : Lf/Q90;
/*     */     //   423: getfield Hq0 : S
/*     */     //   426: aload #7
/*     */     //   428: getfield hp0 : S
/*     */     //   431: invokestatic ri : (II)D
/*     */     //   434: invokevirtual append : (D)Ljava/lang/StringBuilder;
/*     */     //   437: ldc_w '%'
/*     */     //   440: invokevirtual append : (Ljava/lang/String;)Ljava/lang/StringBuilder;
/*     */     //   443: invokevirtual toString : ()Ljava/lang/String;
/*     */     //   446: astore #10
/*     */     //   448: iload_3
/*     */     //   449: aload #6
/*     */     //   451: aload_2
/*     */     //   452: invokevirtual append : (Ljava/lang/String;)Ljava/lang/StringBuilder;
/*     */     //   455: ldc ' '
/*     */     //   457: invokevirtual append : (Ljava/lang/String;)Ljava/lang/StringBuilder;
/*     */     //   460: aload #9
/*     */     //   462: invokevirtual append : (Ljava/lang/String;)Ljava/lang/StringBuilder;
/*     */     //   465: ldc ' '
/*     */     //   467: invokevirtual append : (Ljava/lang/String;)Ljava/lang/StringBuilder;
/*     */     //   470: aload #8
/*     */     //   472: invokevirtual append : (Ljava/lang/String;)Ljava/lang/StringBuilder;
/*     */     //   475: ldc_w ' - '
/*     */     //   478: invokevirtual append : (Ljava/lang/String;)Ljava/lang/StringBuilder;
/*     */     //   481: aload #10
/*     */     //   483: invokevirtual append : (Ljava/lang/String;)Ljava/lang/StringBuilder;
/*     */     //   486: pop
/*     */     //   487: ifne -> 1382
/*     */     //   490: aload #7
/*     */     //   492: invokevirtual AL : ()Z
/*     */     //   495: ifne -> 524
/*     */     //   498: aload #7
/*     */     //   500: getfield ta : Lf/Q90;
/*     */     //   503: getfield u0 : B
/*     */     //   506: ifeq -> 514
/*     */     //   509: iconst_1
/*     */     //   510: istore_2
/*     */     //   511: goto -> 516
/*     */     //   514: iconst_0
/*     */     //   515: istore_2
/*     */     //   516: iload_2
/*     */     //   517: ifeq -> 524
/*     */     //   520: iconst_1
/*     */     //   521: goto -> 525
/*     */     //   524: iconst_0
/*     */     //   525: ifeq -> 690
/*     */     //   528: aload #7
/*     */     //   530: invokevirtual K : ()B
/*     */     //   533: dup
/*     */     //   534: istore_2
/*     */     //   535: bipush #-128
/*     */     //   537: if_icmpeq -> 673
/*     */     //   540: iload_2
/*     */     //   541: bipush #16
/*     */     //   543: if_icmpeq -> 653
/*     */     //   546: iload_2
/*     */     //   547: bipush #32
/*     */     //   549: if_icmpeq -> 633
/*     */     //   552: iload_2
/*     */     //   553: bipush #64
/*     */     //   555: if_icmpeq -> 613
/*     */     //   558: iload_2
/*     */     //   559: bipush #7
/*     */     //   561: if_icmpeq -> 593
/*     */     //   564: iload_2
/*     */     //   565: bipush #8
/*     */     //   567: if_icmpeq -> 573
/*     */     //   570: goto -> 690
/*     */     //   573: aload #6
/*     */     //   575: ldc '\\n'
/*     */     //   577: invokevirtual append : (Ljava/lang/String;)Ljava/lang/StringBuilder;
/*     */     //   580: sipush #5221
/*     */     //   583: invokestatic OH0 : (I)Ljava/lang/String;
/*     */     //   586: invokevirtual append : (Ljava/lang/String;)Ljava/lang/StringBuilder;
/*     */     //   589: pop
/*     */     //   590: goto -> 690
/*     */     //   593: aload #6
/*     */     //   595: ldc '\\n'
/*     */     //   597: invokevirtual append : (Ljava/lang/String;)Ljava/lang/StringBuilder;
/*     */     //   600: sipush #5220
/*     */     //   603: invokestatic OH0 : (I)Ljava/lang/String;
/*     */     //   606: invokevirtual append : (Ljava/lang/String;)Ljava/lang/StringBuilder;
/*     */     //   609: pop
/*     */     //   610: goto -> 690
/*     */     //   613: aload #6
/*     */     //   615: ldc '\\n'
/*     */     //   617: invokevirtual append : (Ljava/lang/String;)Ljava/lang/StringBuilder;
/*     */     //   620: sipush #5224
/*     */     //   623: invokestatic OH0 : (I)Ljava/lang/String;
/*     */     //   626: invokevirtual append : (Ljava/lang/String;)Ljava/lang/StringBuilder;
/*     */     //   629: pop
/*     */     //   630: goto -> 690
/*     */     //   633: aload #6
/*     */     //   635: ldc '\\n'
/*     */     //   637: invokevirtual append : (Ljava/lang/String;)Ljava/lang/StringBuilder;
/*     */     //   640: sipush #5223
/*     */     //   643: invokestatic OH0 : (I)Ljava/lang/String;
/*     */     //   646: invokevirtual append : (Ljava/lang/String;)Ljava/lang/StringBuilder;
/*     */     //   649: pop
/*     */     //   650: goto -> 690
/*     */     //   653: aload #6
/*     */     //   655: ldc '\\n'
/*     */     //   657: invokevirtual append : (Ljava/lang/String;)Ljava/lang/StringBuilder;
/*     */     //   660: sipush #5222
/*     */     //   663: invokestatic OH0 : (I)Ljava/lang/String;
/*     */     //   666: invokevirtual append : (Ljava/lang/String;)Ljava/lang/StringBuilder;
/*     */     //   669: pop
/*     */     //   670: goto -> 690
/*     */     //   673: aload #6
/*     */     //   675: ldc '\\n'
/*     */     //   677: invokevirtual append : (Ljava/lang/String;)Ljava/lang/StringBuilder;
/*     */     //   680: sipush #5225
/*     */     //   683: invokestatic OH0 : (I)Ljava/lang/String;
/*     */     //   686: invokevirtual append : (Ljava/lang/String;)Ljava/lang/StringBuilder;
/*     */     //   689: pop
/*     */     //   690: aload_1
/*     */     //   691: ifnull -> 985
/*     */     //   694: aload #4
/*     */     //   696: invokevirtual isEmpty : ()Z
/*     */     //   699: ifne -> 723
/*     */     //   702: aload #6
/*     */     //   704: dup
/*     */     //   705: ldc '\\n'
/*     */     //   707: invokevirtual append : (Ljava/lang/String;)Ljava/lang/StringBuilder;
/*     */     //   710: pop
/*     */     //   711: sipush #5057
/*     */     //   714: aload #4
/*     */     //   716: invokestatic Go : (ILjava/lang/String;)Ljava/lang/String;
/*     */     //   719: invokevirtual append : (Ljava/lang/String;)Ljava/lang/StringBuilder;
/*     */     //   722: pop
/*     */     //   723: aload #5
/*     */     //   725: invokevirtual isEmpty : ()Z
/*     */     //   728: ifne -> 746
/*     */     //   731: aload #6
/*     */     //   733: dup
/*     */     //   734: ldc '\\n'
/*     */     //   736: invokevirtual append : (Ljava/lang/String;)Ljava/lang/StringBuilder;
/*     */     //   739: pop
/*     */     //   740: aload #5
/*     */     //   742: invokevirtual append : (Ljava/lang/String;)Ljava/lang/StringBuilder;
/*     */     //   745: pop
/*     */     //   746: aload_1
/*     */     //   747: getfield K0 : Lf/jd0;
/*     */     //   750: invokevirtual AL : ()Z
/*     */     //   753: ifeq -> 759
/*     */     //   756: goto -> 788
/*     */     //   759: iconst_0
/*     */     //   760: istore_2
/*     */     //   761: iload_2
/*     */     //   762: aload_1
/*     */     //   763: getfield wt : [B
/*     */     //   766: dup
/*     */     //   767: astore_3
/*     */     //   768: arraylength
/*     */     //   769: if_icmpge -> 788
/*     */     //   772: aload_3
/*     */     //   773: iload_2
/*     */     //   774: baload
/*     */     //   775: ifeq -> 782
/*     */     //   778: iconst_1
/*     */     //   779: goto -> 789
/*     */     //   782: iinc #2, 1
/*     */     //   785: goto -> 761
/*     */     //   788: iconst_0
/*     */     //   789: ifeq -> 897
/*     */     //   792: aload #6
/*     */     //   794: bipush #10
/*     */     //   796: invokevirtual append : (C)Ljava/lang/StringBuilder;
/*     */     //   799: pop
/*     */     //   800: getstatic f/hR.h40 : [Lf/hR;
/*     */     //   803: dup
/*     */     //   804: astore_2
/*     */     //   805: arraylength
/*     */     //   806: istore_3
/*     */     //   807: iconst_0
/*     */     //   808: istore #4
/*     */     //   810: iload #4
/*     */     //   812: iload_3
/*     */     //   813: if_icmpge -> 897
/*     */     //   816: aload_1
/*     */     //   817: aload_2
/*     */     //   818: iload #4
/*     */     //   820: aaload
/*     */     //   821: astore #5
/*     */     //   823: getfield wt : [B
/*     */     //   826: aload #5
/*     */     //   828: getfield dL : B
/*     */     //   831: baload
/*     */     //   832: dup
/*     */     //   833: istore #8
/*     */     //   835: ifne -> 841
/*     */     //   838: goto -> 891
/*     */     //   841: iload #8
/*     */     //   843: aload #6
/*     */     //   845: bipush #10
/*     */     //   847: invokevirtual append : (C)Ljava/lang/StringBuilder;
/*     */     //   850: aload #5
/*     */     //   852: invokevirtual append : (Ljava/lang/Object;)Ljava/lang/StringBuilder;
/*     */     //   855: ldc_w ': '
/*     */     //   858: invokevirtual append : (Ljava/lang/String;)Ljava/lang/StringBuilder;
/*     */     //   861: astore #5
/*     */     //   863: ifle -> 874
/*     */     //   866: ldc_w '+'
/*     */     //   869: astore #9
/*     */     //   871: goto -> 878
/*     */     //   874: ldc ''
/*     */     //   876: astore #9
/*     */     //   878: aload #5
/*     */     //   880: aload #9
/*     */     //   882: invokevirtual append : (Ljava/lang/String;)Ljava/lang/StringBuilder;
/*     */     //   885: iload #8
/*     */     //   887: invokevirtual append : (I)Ljava/lang/StringBuilder;
/*     */     //   890: pop
/*     */     //   891: iinc #4, 1
/*     */     //   894: goto -> 810
/*     */     //   897: aload_0
/*     */     //   898: aload_1
/*     */     //   899: getfield FT : B
/*     */     //   902: invokevirtual a0 : (B)Lf/PE;
/*     */     //   905: dup
/*     */     //   906: astore_1
/*     */     //   907: new java/lang/StringBuilder
/*     */     //   910: dup
/*     */     //   911: astore_2
/*     */     //   912: invokespecial <init> : ()V
/*     */     //   915: getfield h30 : B
/*     */     //   918: ifle -> 959
/*     */     //   921: aload_2
/*     */     //   922: iconst_2
/*     */     //   923: anewarray java/lang/String
/*     */     //   926: dup
/*     */     //   927: astore_3
/*     */     //   928: aload_1
/*     */     //   929: aload_3
/*     */     //   930: ldc_w 110366
/*     */     //   933: invokestatic OH0 : (I)Ljava/lang/String;
/*     */     //   936: iconst_0
/*     */     //   937: swap
/*     */     //   938: aastore
/*     */     //   939: getfield h30 : B
/*     */     //   942: invokestatic valueOf : (I)Ljava/lang/String;
/*     */     //   945: iconst_1
/*     */     //   946: swap
/*     */     //   947: aastore
/*     */     //   948: sipush #7008
/*     */     //   951: aload_3
/*     */     //   952: invokestatic sB : (I[Ljava/lang/String;)Ljava/lang/String;
/*     */     //   955: invokevirtual append : (Ljava/lang/String;)Ljava/lang/StringBuilder;
/*     */     //   958: pop
/*     */     //   959: aload_2
/*     */     //   960: invokevirtual toString : ()Ljava/lang/String;
/*     */     //   963: dup
/*     */     //   964: astore_1
/*     */     //   965: invokevirtual isEmpty : ()Z
/*     */     //   968: ifne -> 985
/*     */     //   971: aload #6
/*     */     //   973: dup
/*     */     //   974: ldc '\\n\\n'
/*     */     //   976: invokevirtual append : (Ljava/lang/String;)Ljava/lang/StringBuilder;
/*     */     //   979: pop
/*     */     //   980: aload_1
/*     */     //   981: invokevirtual append : (Ljava/lang/String;)Ljava/lang/StringBuilder;
/*     */     //   984: pop
/*     */     //   985: aload_0
/*     */     //   986: getfield q20 : Lf/R00;
/*     */     //   989: dup
/*     */     //   990: astore_0
/*     */     //   991: ifnull -> 1382
/*     */     //   994: aload #7
/*     */     //   996: getfield Zf : Ljava/util/EnumMap;
/*     */     //   999: invokevirtual size : ()I
/*     */     //   1002: ifle -> 1009
/*     */     //   1005: iconst_1
/*     */     //   1006: goto -> 1010
/*     */     //   1009: iconst_0
/*     */     //   1010: ifeq -> 1382
/*     */     //   1013: aload #7
/*     */     //   1015: getfield Zf : Ljava/util/EnumMap;
/*     */     //   1018: invokevirtual entrySet : ()Ljava/util/Set;
/*     */     //   1021: invokestatic unmodifiableSet : (Ljava/util/Set;)Ljava/util/Set;
/*     */     //   1024: invokeinterface iterator : ()Ljava/util/Iterator;
/*     */     //   1029: astore_1
/*     */     //   1030: aload_1
/*     */     //   1031: invokeinterface hasNext : ()Z
/*     */     //   1036: ifeq -> 1382
/*     */     //   1039: aload_0
/*     */     //   1040: aload #6
/*     */     //   1042: aload_1
/*     */     //   1043: invokeinterface next : ()Ljava/lang/Object;
/*     */     //   1048: checkcast java/util/Map$Entry
/*     */     //   1051: astore_2
/*     */     //   1052: bipush #10
/*     */     //   1054: invokevirtual append : (C)Ljava/lang/StringBuilder;
/*     */     //   1057: pop
/*     */     //   1058: aload_2
/*     */     //   1059: invokeinterface getValue : ()Ljava/lang/Object;
/*     */     //   1064: checkcast [S
/*     */     //   1067: astore_3
/*     */     //   1068: invokevirtual ordinal : ()I
/*     */     //   1071: dup
/*     */     //   1072: istore #4
/*     */     //   1074: ifeq -> 1262
/*     */     //   1077: iload #4
/*     */     //   1079: iconst_1
/*     */     //   1080: if_icmpeq -> 1212
/*     */     //   1083: iload #4
/*     */     //   1085: iconst_2
/*     */     //   1086: if_icmpeq -> 1092
/*     */     //   1089: goto -> 1030
/*     */     //   1092: aload_3
/*     */     //   1093: iconst_0
/*     */     //   1094: saload
/*     */     //   1095: aload_3
/*     */     //   1096: iconst_1
/*     */     //   1097: saload
/*     */     //   1098: if_icmpne -> 1151
/*     */     //   1101: aload #6
/*     */     //   1103: iconst_2
/*     */     //   1104: anewarray java/lang/String
/*     */     //   1107: dup
/*     */     //   1108: astore #4
/*     */     //   1110: aload_3
/*     */     //   1111: aload #4
/*     */     //   1113: aload_2
/*     */     //   1114: invokeinterface getKey : ()Ljava/lang/Object;
/*     */     //   1119: checkcast f/hR
/*     */     //   1122: invokevirtual toString : ()Ljava/lang/String;
/*     */     //   1125: iconst_0
/*     */     //   1126: swap
/*     */     //   1127: aastore
/*     */     //   1128: iconst_0
/*     */     //   1129: saload
/*     */     //   1130: invokestatic toString : (S)Ljava/lang/String;
/*     */     //   1133: iconst_1
/*     */     //   1134: swap
/*     */     //   1135: aastore
/*     */     //   1136: sipush #5242
/*     */     //   1139: aload #4
/*     */     //   1141: invokestatic sB : (I[Ljava/lang/String;)Ljava/lang/String;
/*     */     //   1144: invokevirtual append : (Ljava/lang/String;)Ljava/lang/StringBuilder;
/*     */     //   1147: pop
/*     */     //   1148: goto -> 1030
/*     */     //   1151: aload #6
/*     */     //   1153: iconst_3
/*     */     //   1154: anewarray java/lang/String
/*     */     //   1157: dup
/*     */     //   1158: astore #4
/*     */     //   1160: aload_3
/*     */     //   1161: aload #4
/*     */     //   1163: aload_3
/*     */     //   1164: aload #4
/*     */     //   1166: aload_2
/*     */     //   1167: invokeinterface getKey : ()Ljava/lang/Object;
/*     */     //   1172: checkcast f/hR
/*     */     //   1175: invokevirtual toString : ()Ljava/lang/String;
/*     */     //   1178: iconst_0
/*     */     //   1179: swap
/*     */     //   1180: aastore
/*     */     //   1181: iconst_0
/*     */     //   1182: saload
/*     */     //   1183: invokestatic toString : (S)Ljava/lang/String;
/*     */     //   1186: iconst_1
/*     */     //   1187: swap
/*     */     //   1188: aastore
/*     */     //   1189: iconst_1
/*     */     //   1190: saload
/*     */     //   1191: invokestatic toString : (S)Ljava/lang/String;
/*     */     //   1194: iconst_2
/*     */     //   1195: swap
/*     */     //   1196: aastore
/*     */     //   1197: sipush #5243
/*     */     //   1200: aload #4
/*     */     //   1202: invokestatic sB : (I[Ljava/lang/String;)Ljava/lang/String;
/*     */     //   1205: invokevirtual append : (Ljava/lang/String;)Ljava/lang/StringBuilder;
/*     */     //   1208: pop
/*     */     //   1209: goto -> 1030
/*     */     //   1212: aload #6
/*     */     //   1214: iconst_2
/*     */     //   1215: anewarray java/lang/String
/*     */     //   1218: dup
/*     */     //   1219: astore #4
/*     */     //   1221: aload_3
/*     */     //   1222: aload #4
/*     */     //   1224: aload_2
/*     */     //   1225: invokeinterface getKey : ()Ljava/lang/Object;
/*     */     //   1230: checkcast f/hR
/*     */     //   1233: invokevirtual toString : ()Ljava/lang/String;
/*     */     //   1236: iconst_0
/*     */     //   1237: swap
/*     */     //   1238: aastore
/*     */     //   1239: iconst_0
/*     */     //   1240: saload
/*     */     //   1241: invokestatic toString : (S)Ljava/lang/String;
/*     */     //   1244: iconst_1
/*     */     //   1245: swap
/*     */     //   1246: aastore
/*     */     //   1247: sipush #5241
/*     */     //   1250: aload #4
/*     */     //   1252: invokestatic sB : (I[Ljava/lang/String;)Ljava/lang/String;
/*     */     //   1255: invokevirtual append : (Ljava/lang/String;)Ljava/lang/StringBuilder;
/*     */     //   1258: pop
/*     */     //   1259: goto -> 1030
/*     */     //   1262: aload_3
/*     */     //   1263: iconst_0
/*     */     //   1264: saload
/*     */     //   1265: aload_3
/*     */     //   1266: iconst_1
/*     */     //   1267: saload
/*     */     //   1268: if_icmpne -> 1321
/*     */     //   1271: aload #6
/*     */     //   1273: iconst_2
/*     */     //   1274: anewarray java/lang/String
/*     */     //   1277: dup
/*     */     //   1278: astore #4
/*     */     //   1280: aload_3
/*     */     //   1281: aload #4
/*     */     //   1283: aload_2
/*     */     //   1284: invokeinterface getKey : ()Ljava/lang/Object;
/*     */     //   1289: checkcast f/hR
/*     */     //   1292: invokevirtual toString : ()Ljava/lang/String;
/*     */     //   1295: iconst_0
/*     */     //   1296: swap
/*     */     //   1297: aastore
/*     */     //   1298: iconst_0
/*     */     //   1299: saload
/*     */     //   1300: invokestatic toString : (S)Ljava/lang/String;
/*     */     //   1303: iconst_1
/*     */     //   1304: swap
/*     */     //   1305: aastore
/*     */     //   1306: sipush #5240
/*     */     //   1309: aload #4
/*     */     //   1311: invokestatic sB : (I[Ljava/lang/String;)Ljava/lang/String;
/*     */     //   1314: invokevirtual append : (Ljava/lang/String;)Ljava/lang/StringBuilder;
/*     */     //   1317: pop
/*     */     //   1318: goto -> 1030
/*     */     //   1321: aload #6
/*     */     //   1323: iconst_3
/*     */     //   1324: anewarray java/lang/String
/*     */     //   1327: dup
/*     */     //   1328: astore #4
/*     */     //   1330: aload_3
/*     */     //   1331: aload #4
/*     */     //   1333: aload_3
/*     */     //   1334: aload #4
/*     */     //   1336: aload_2
/*     */     //   1337: invokeinterface getKey : ()Ljava/lang/Object;
/*     */     //   1342: checkcast f/hR
/*     */     //   1345: invokevirtual toString : ()Ljava/lang/String;
/*     */     //   1348: iconst_0
/*     */     //   1349: swap
/*     */     //   1350: aastore
/*     */     //   1351: iconst_0
/*     */     //   1352: saload
/*     */     //   1353: invokestatic toString : (S)Ljava/lang/String;
/*     */     //   1356: iconst_1
/*     */     //   1357: swap
/*     */     //   1358: aastore
/*     */     //   1359: iconst_1
/*     */     //   1360: saload
/*     */     //   1361: invokestatic toString : (S)Ljava/lang/String;
/*     */     //   1364: iconst_2
/*     */     //   1365: swap
/*     */     //   1366: aastore
/*     */     //   1367: sipush #5244
/*     */     //   1370: aload #4
/*     */     //   1372: invokestatic sB : (I[Ljava/lang/String;)Ljava/lang/String;
/*     */     //   1375: invokevirtual append : (Ljava/lang/String;)Ljava/lang/StringBuilder;
/*     */     //   1378: pop
/*     */     //   1379: goto -> 1030
/*     */     //   1382: aload #6
/*     */     //   1384: invokevirtual toString : ()Ljava/lang/String;
/*     */     //   1387: areturn
/*     */     //   1388: ldc ''
/*     */     //   1390: areturn
/*     */     // Line number table:
/*     */     //   Java source line number -> byte code offset
/*     */     //   #1	-> 15
/*     */     //   #2	-> 48
/*     */     //   #3	-> 67
/*     */     //   #4	-> 91
/*     */     //   #5	-> 103
/*     */     //   #6	-> 189
/*     */     //   #7	-> 192
/*     */     //   #8	-> 195
/*     */     //   #9	-> 204
/*     */     //   #10	-> 220
/*     */     //   #11	-> 232
/*     */     //   #12	-> 263
/*     */     //   #13	-> 342
/*     */     //   #14	-> 345
/*     */     //   #15	-> 354
/*     */     //   #16	-> 364
/*     */     //   #17	-> 367
/*     */     //   #18	-> 378
/*     */     //   #19	-> 420
/*     */     //   #20	-> 423
/*     */     //   #21	-> 428
/*     */     //   #22	-> 434
/*     */     //   #23	-> 492
/*     */     //   #24	-> 503
/*     */     //   #25	-> 530
/*     */     //   #26	-> 747
/*     */     //   #27	-> 763
/*     */     //   #28	-> 796
/*     */     //   #29	-> 823
/*     */     //   #30	-> 828
/*     */     //   #31	-> 831
/*     */     //   #32	-> 847
/*     */     //   #33	-> 899
/*     */     //   #34	-> 902
/*     */     //   #35	-> 907
/*     */     //   #36	-> 915
/*     */     //   #37	-> 923
/*     */     //   #38	-> 939
/*     */     //   #39	-> 942
/*     */     //   #40	-> 965
/*     */     //   #41	-> 986
/*     */     //   #42	-> 996
/*     */     //   #43	-> 1015
/*     */     //   #44	-> 1024
/*     */   }
/*     */   
/*     */   public static String ku0(MM paramMM) {
/*     */     this();
/*     */     String[] arrayOfString;
/*     */     StringBuilder stringBuilder;
/*     */     short s = paramMM.Wk0;
/*     */     byte b;
/*     */     if ((b = paramMM.og0) == 1) {
/*     */       b = paramMM.ZA;
/*     */       byte b1 = paramMM.ja0;
/*     */       String str = Ml0.OH0(5615);
/*     */       arrayOfString1[0] = str;
/*     */       String[] arrayOfString1;
/*     */       (arrayOfString1 = new String[2])[1] = Ml0.OH0(s + 150000);
/*     */       stringBuilder.append(Ml0.sB(5583, arrayOfString1));
/*     */       stringBuilder.append("\n");
/*     */       stringBuilder.append(Ml0.OH0(5584));
/*     */       if (paramMM.AC) {
/*     */         stringBuilder.append("\n • ");
/*     */         stringBuilder.append(Ml0.OH0(5585));
/*     */       } 
/*     */       if (paramMM.YB0) {
/*     */         stringBuilder.append("\n • ");
/*     */         stringBuilder.append(Ml0.OH0(8100));
/*     */       } 
/*     */       if (paramMM.com5 > 0) {
/*     */         stringBuilder.append("\n • ");
/*     */         stringBuilder.append(Ml0.Go(5686, Integer.toString(paramMM.com5)));
/*     */       } 
/*     */       if (b > 0) {
/*     */         stringBuilder.append("\n • ");
/*     */         stringBuilder.append(Ml0.Go(9110, Integer.toString(b)));
/*     */         if (b < 6) {
/*     */           stringBuilder.append(" + ");
/*     */           arrayOfString[0] = Integer.toString(6 - b);
/*     */           (arrayOfString = new String[2])[1] = Integer.toString(b1);
/*     */           stringBuilder.append(Ml0.sB(5587, arrayOfString));
/*     */         } 
/*     */       } else {
/*     */         stringBuilder.append("\n • ");
/*     */         arrayOfString[0] = "6";
/*     */         (arrayOfString = new String[2])[1] = Integer.toString(b1);
/*     */         stringBuilder.append(Ml0.sB(5587, arrayOfString));
/*     */       } 
/*     */     } else if (b == 2) {
/*     */       stringBuilder.append(NumberFormat.getInstance().format(((MM)arrayOfString).Ur));
/*     */       stringBuilder.append(" ");
/*     */       stringBuilder.append(Ml0.OH0(121));
/*     */     } 
/*     */     return stringBuilder.toString().trim();
/*     */   }
/*     */   
/*     */   public static String e0(A30 paramA30, short paramShort, int paramInt) {
/*     */     boolean bool1 = paramA30.x40;
/*     */     boolean bool2 = paramA30.ci0;
/*     */     boolean bool3 = paramA30.jJ0;
/*     */     boolean bool4 = paramA30.O00;
/*     */     byte b2 = paramA30.Yk0;
/*     */     byte b3 = paramA30.Rt;
/*     */     byte b4 = paramA30.CF;
/*     */     int i = paramA30.I;
/*     */     int j = paramA30.NF0;
/*     */     int k = paramA30.Bd0;
/*     */     short s2 = paramA30.CO;
/*     */     short s3 = paramA30.e2;
/*     */     byte b5 = paramA30.B6;
/*     */     short s1;
/*     */     if ((s1 = paramA30.fd) > 0) {
/*     */       this();
/*     */       String str = "";
/*     */       if (bool1 && bool2) {
/*     */         str = Ml0.OH0(5621);
/*     */       } else if (bool1) {
/*     */         str = Ml0.OH0(5614);
/*     */       } else if (bool2) {
/*     */         str = Ml0.OH0(5615);
/*     */       } 
/*     */       arrayOfString2[0] = str;
/*     */       (arrayOfString2 = new String[2])[1] = Ml0.OH0(s1 + 150000);
/*     */       stringBuilder1.append(Ml0.sB(5583, arrayOfString2));
/*     */       if (bool3 || b2 > 0 || b3 > 0) {
/*     */         stringBuilder1.append("\n");
/*     */         stringBuilder1.append(Ml0.OH0(5584));
/*     */         if (bool3) {
/*     */           stringBuilder1.append("\n • ");
/*     */           stringBuilder1.append(Ml0.OH0(5585));
/*     */         } 
/*     */         if (bool4) {
/*     */           stringBuilder1.append("\n • ");
/*     */           stringBuilder1.append(Ml0.OH0(8100));
/*     */         } 
/*     */         if (b2 > 0) {
/*     */           stringBuilder1.append("\n • ");
/*     */           stringBuilder1.append(Ml0.Go(5586, Integer.toString(b2)));
/*     */         } 
/*     */         if (b3 > 0) {
/*     */           stringBuilder1.append("\n • ");
/*     */           stringBuilder1.append(Ml0.Go(9110, Integer.toString(b3)));
/*     */           if (b3 < 6) {
/*     */             stringBuilder1.append(" + ");
/*     */             arrayOfString1[0] = Integer.toString(6 - b3);
/*     */             (arrayOfString1 = new String[2])[1] = Integer.toString(b4);
/*     */             stringBuilder1.append(Ml0.sB(5587, arrayOfString1));
/*     */           } 
/*     */         } else {
/*     */           stringBuilder1.append("\n • ");
/*     */           arrayOfString1[0] = "6";
/*     */           (arrayOfString1 = new String[2])[1] = Integer.toString(b4);
/*     */           stringBuilder1.append(Ml0.sB(5587, arrayOfString1));
/*     */         } 
/*     */       } 
/*     */       return stringBuilder1.toString().trim();
/*     */     } 
/*     */     this();
/*     */     StringBuilder stringBuilder1;
/*     */     boolean bool;
/*     */     String[] arrayOfString1, arrayOfString2;
/*     */     StringBuilder stringBuilder2;
/*     */     byte b1;
/*     */     bool1 = false;
/*     */     if (((A30)stringBuilder1).I > 0)
/*     */       b1 = (byte)1; 
/*     */     if (((A30)stringBuilder1).Bd0 > 0)
/*     */       b1 = (byte)(b1 + 1); 
/*     */     if (((A30)stringBuilder1).NF0 > 0)
/*     */       b1 = (byte)(b1 + 1); 
/*     */     if (((A30)stringBuilder1).CO > 0)
/*     */       b1 = (byte)(b1 + 1); 
/*     */     if (b1 > 1) {
/*     */       bool = true;
/*     */     } else {
/*     */       bool = false;
/*     */     } 
/*     */     if (bool) {
/*     */       stringBuilder2.append(Ml0.OH0(5584));
/*     */       stringBuilder2.append("\n");
/*     */     } 
/*     */     if (b5 > 0 && i < 1 && j < 1) {
/*     */       stringBuilder2.append(" • ");
/*     */       if (b5 == 1) {
/*     */         String[] arrayOfString;
/*     */         (arrayOfString = new String[2])[0] = NumberFormat.getInstance().format(arrayOfString2);
/*     */         (new String[2])[1] = NumberFormat.getInstance().format((arrayOfString2 * arrayOfString1));
/*     */         stringBuilder2.append(Ml0.sB(5590, arrayOfString));
/*     */       } else if (b5 == 2) {
/*     */         String[] arrayOfString;
/*     */         (arrayOfString = new String[2])[0] = NumberFormat.getInstance().format(arrayOfString2);
/*     */         (new String[2])[1] = NumberFormat.getInstance().format((arrayOfString2 * arrayOfString1));
/*     */         stringBuilder2.append(Ml0.sB(5591, arrayOfString));
/*     */       } 
/*     */     } 
/*     */     if (i > 0) {
/*     */       stringBuilder2.append(" • ");
/*     */       stringBuilder2.append("$");
/*     */       stringBuilder2.append(NumberFormat.getInstance().format(i));
/*     */     } 
/*     */     if (k > 0) {
/*     */       if (stringBuilder2.length() > 0)
/*     */         stringBuilder2.append("\n"); 
/*     */       stringBuilder2.append(" • ");
/*     */       stringBuilder2.append(NumberFormat.getInstance().format(k));
/*     */       stringBuilder2.append(" ");
/*     */       stringBuilder2.append(Ml0.OH0(3002));
/*     */     } 
/*     */     if (j > 0) {
/*     */       if (stringBuilder2.length() > 0)
/*     */         stringBuilder2.append("\n"); 
/*     */       stringBuilder2.append(" • ");
/*     */       stringBuilder2.append(NumberFormat.getInstance().format(j));
/*     */       stringBuilder2.append(" ");
/*     */       stringBuilder2.append(Ml0.OH0(121));
/*     */     } 
/*     */     if (s2 > 0) {
/*     */       if (stringBuilder2.length() > 0)
/*     */         stringBuilder2.append("\n"); 
/*     */       stringBuilder2.append(" • ");
/*     */       stringBuilder2.append(NumberFormat.getInstance().format(s3));
/*     */       stringBuilder2.append("x ");
/*     */       stringBuilder2.append(Ml0.OH0((Of.eH.On0(s2)).Iu));
/*     */     } 
/*     */     return stringBuilder2.toString();
/*     */   }
/*     */   
/*     */   public static String Ih(Pi paramPi) {
/*     */     this();
/*     */     StringBuilder stringBuilder;
/*     */     short s1 = paramPi.PQ;
/*     */     short s2 = paramPi.ed;
/*     */     short s3 = paramPi.protected;
/*     */     short s4 = paramPi.ew;
/*     */     CC0 cC0 = paramPi.ai;
/*     */     DO dO = paramPi.U9;
/*     */     String str = "";
/*     */     byte b;
/*     */     if ((b = paramPi.Gk0) != 0) {
/*     */       if (b != 1) {
/*     */         if (b == 2) {
/*     */           StringBuilder stringBuilder1;
/*     */           this();
/*     */           str = yh0.jJ0(5637, stringBuilder1, "\n\n");
/*     */         } 
/*     */       } else {
/*     */         StringBuilder stringBuilder1;
/*     */         this();
/*     */         str = yh0.jJ0(5632, stringBuilder1, "\n\n");
/*     */       } 
/*     */     } else {
/*     */       StringBuilder stringBuilder1;
/*     */       this();
/*     */       str = yh0.jJ0(5631, stringBuilder1, "\n\n");
/*     */     } 
/*     */     UD0 uD0;
/*     */     if (s1 > 0 && (uD0 = On.v30().lpT3(s1)) != null)
/*     */       stringBuilder.append(uD0.o60(false)); 
/*     */     WD wD;
/*     */     if (s2 > 0 && (wD = yk0.cw().mP(s2)) != null) {
/*     */       if (stringBuilder.length() > 0)
/*     */         stringBuilder.append(" + "); 
/*     */       stringBuilder.append(Ml0.OH0(wD.iz));
/*     */     } 
/*     */     if (s3 > 0) {
/*     */       int i = s3 + 210000;
/*     */       if (Ml0.nW.return(i)) {
/*     */         if (stringBuilder.length() > 0)
/*     */           stringBuilder.append(" + "); 
/*     */         stringBuilder.append(Ml0.OH0(i));
/*     */       } 
/*     */     } 
/*     */     if (s4 > 0) {
/*     */       LPT3 lPT3 = Of.eH.On0(s4);
/*     */       if (stringBuilder.length() > 0)
/*     */         stringBuilder.append(" + "); 
/*     */       stringBuilder.append(Ml0.OH0(lPT3.Iu));
/*     */     } 
/*     */     if (cC0 != null) {
/*     */       if (stringBuilder.length() > 0)
/*     */         stringBuilder.append(" + "); 
/*     */       stringBuilder.append(Ml0.OH0(cC0.a10));
/*     */     } 
/*     */     if (dO != null) {
/*     */       if (stringBuilder.length() > 0)
/*     */         stringBuilder.append(" + "); 
/*     */       stringBuilder.append(Ml0.OH0(dO.mt0));
/*     */     } 
/*     */     stringBuilder.insert(0, str);
/*     */     return stringBuilder.toString();
/*     */   }
/*     */   
/*     */   public static String wY(int paramInt1, int paramInt2, String paramString) {
/*     */     (new StringBuilder()).append(paramInt1 + " / " + paramInt2);
/*     */     (new StringBuilder()).append("\n");
/*     */     (new StringBuilder()).append("--");
/*     */     (new StringBuilder()).append("\n");
/*     */     (new StringBuilder()).append(paramString);
/*     */     return (new StringBuilder()).toString();
/*     */   }
/*     */   
/*     */   public static String Em0(nV paramnV) {
/*     */     if (paramnV == null)
/*     */       return ""; 
/*     */     if (paramnV.t3 == null)
/*     */       return Ml0.OH0(1806); 
/*     */     return B40.df("+10% ").append(paramnV.t3).append("\n-10% ").append(paramnV.Qc0).toString();
/*     */   }
/*     */   
/*     */   public static String sW(hR[] paramArrayOfhR) {
/*     */     return (paramArrayOfhR.length < 1) ? "" : ((paramArrayOfhR.length == 1) ? paramArrayOfhR[0].toString() : Ml0.sB(paramArrayOfhR.length - 2 + 200458, (String[])Stream.<hR>of(paramArrayOfhR).map(hR::toString).toArray(rG0::P40)));
/*     */   }
/*     */   
/*     */   public static String oB0(mA parammA) {
/*     */     int i = parammA.WF + 920000;
/*     */     if (Ml0.nW.return(i))
/*     */       return Ml0.OH0(i); 
/*     */     Ml0.nW.A3(i, str);
/*     */     String str;
/*     */     return str = Of.eH.cOm7.values().stream().filter(parammA::kg0).findFirst().map(rG0::MA0).orElse("");
/*     */   }
/*     */   
/*     */   public static String u(mA parammA, boolean paramBoolean) {
/*     */     this();
/*     */     StringBuilder stringBuilder;
/*     */     int i;
/*     */     mA mA1;
/*     */     if (parammA == (mA1 = mA.Wh0) && paramBoolean) {
/*     */       i = 11199;
/*     */     } else {
/*     */       i = parammA.WF + 11000;
/*     */     } 
/*     */     stringBuilder.append(Ml0.OH0(i));
/*     */     stringBuilder.append("\n\n");
/*     */     String str2;
/*     */     if (!(str2 = oB0(parammA)).isEmpty()) {
/*     */       stringBuilder.append(str2);
/*     */       stringBuilder.append("\n");
/*     */     } 
/*     */     String str1 = Ml0.OH0((parammA == mA1 && paramBoolean) ? 11399 : (parammA.WF + 11200));
/*     */     stringBuilder.append(str1);
/*     */     return stringBuilder.toString();
/*     */   }
/*     */   
/*     */   public static boolean kg0(mA parammA, LPT3 paramLPT3) {
/*     */     return (paramLPT3.KI == parammA);
/*     */   }
/*     */   
/*     */   static {
/*     */     (J2 = new DecimalFormat()).setMaximumFractionDigits(2);
/*     */   }
/*     */   
/*     */   public static String M5(j40 paramj40) {
/*     */     return Zs0(paramj40, false, false, false);
/*     */   }
/*     */   
/*     */   public static String Yc(LPT3 paramLPT3) {
/*     */     return Qb0(paramLPT3, false, false);
/*     */   } }


/* Location:              /Users/vnnsnnt/Documents/Codespace/JavaWorkspace/RedTrainer/src/main/java/org/trainer/client/PokeMMO.jar!/f/rG0.class
 * Java compiler version: 8 (52.0)
 * JD-Core Version:       1.1.3
 */