/*  1 */ package f;public abstract class ro { public static ik fE0 = C00.gd(ro.class); public static final short[][][] H70; public static byte l10 = 0; public static short eL = 95; public static final short[] Sa0 = new short[0]; public static final int[] try = new int[0]; public static final boolean[] dC = new boolean[0]; public int Cf0; public byte[] nJ; public P10 Bk0; public c4 e20; public Ku aM0; public qN sE; public fH0 Lz = null; public vh0 Qa = new vh0(); public Uc0[] Pi = new Uc0[aq0.SL0.length]; public Uc0 z2 = null; public zr0[] Fe = new zr0[yM.tZ.length]; public hP[] cl = new hP[CJ.Bc0.length]; public Dm0[] YS = new Dm0[Tl0.yY.length]; public qc0 OK = null; public Iq0 y80 = new Iq0(); public Uk hZ = null; public P4 Ld = null; public BF fF0 = new BF(); public Oc0 E50 = new Oc0(); public QK0 qH0 = new QK0(); public Z zl = new Z(); public mG Wn0 = null; public Yp0 Tr0 = null; public boolean ky = false; public boolean tN = false; public Ca hB0 = null; public boolean sU = false; public boolean Ax = false; public final EJ0 wG = new EJ0(); public short pp0 = 0; public short el = 0; public short M9 = 0; public boolean XQ = false; public cG uk = cG.yc; public boolean yu = false; public int Ta0 = 0; public boolean GG0 = false; public short default; public short a = 0; public short bn = 0; public final ak lR = new ak(); public final ak kw0 = new ak(); public yM jG0 = yM.r4; public byte[] XA0; public h30 Ie0 = new h30(); public final Dq0 R3 = new Dq0(); public final g2 Mg0 = new g2(); public boolean p10 = false; public long b = System.currentTimeMillis(); public short[] I6; public int[] uv0; public short[] GN; public boolean[] PM; public Xj0 cOm3; public Xj0 k20; public boolean cv; public boolean ni0; public byte cJ0; public byte[] vB; public U50[] W20; public int dy0; public AtomicBoolean d00; public qa0 II; public int KK; public byte[] Ge0; public ro(P10 paramP10, int paramInt, byte[] paramArrayOfbyte) { short[] arrayOfShort = Sa0; this.uv0 = try; this.GN = this; this.PM = dC; this.cOm3 = new Xj0(); this.k20 = new Xj0(); this.cv = false; this.ni0 = false; this.cJ0 = 0; this.vB = null; this.W20 = new U50[0]; this.dy0 = 0; this.d00 = new AtomicBoolean(false); this.II = null; this.Bk0 = paramP10; this.Cf0 = paramInt; this.nJ = paramArrayOfbyte; this.sE = new qN(paramInt); Ha0(null, true); Am(new EG0()); } private void Sl(byte paramByte, short paramShort) { lx0(paramByte, (byte)0); if (paramShort == 15) km.a3.Ct
/*  2 */         .pm
/*  3 */         .Kk(new nl[] { nl.COM7 });  } public static pM[] sc(short paramShort) { if (paramShort != 245) switch (paramShort) { default: return new pM[] { pM.x7 };case 144: case 145: case 146: break; }   return new pM[] { pM.x7, pM.V3 }; } public final void oy(Ku paramKu) { if (this.XQ || dm0() != 5) return;  if (paramKu != this.aM0) return;  this.aM0 = null; oD(Ml0.OH0(1517), ZY.XY); A1.L7.ac0(this::bH, 10000L); } public final void Ze0() { Ku ku; if ((ku = this.aM0) == null || ku.sO) { A1 a1 = A1.L7; this.nc.execute(this::bH); }  } public final int ff() { return this.Cf0; } public final qN UK() { return this.sE; } public final Uc0 s40(aq0 paramaq0) { P4 p4; if (paramaq0 == aq0.dy) return ((p4 = this.Ld) == null) ? null : ou();  return ((ro)super).Pi[paramaq0.Cl0]; } public final void Am(Uc0 paramUc0) { Jy0(paramUc0.Nul, paramUc0); } public final void Jy0(aq0 paramaq0, Uc0 paramUc0) { this.Pi[paramaq0.Cl0] = paramUc0; } public final void tb0() { aq0[] arrayOfAq0; byte b1; byte b2; for (arrayOfAq0 = aq0.Yz0, b1 = 3, b2 = 0; b2 < b1; ) { aq0 aq0 = arrayOfAq0[b2]; Uc0 uc0; if ((uc0 = this.Pi[aq0.Cl0]) != null) { this.z2 = uc0; return; }  b2++; }  } public final Uc0 dl0() { return this.z2; } public final zr0 Ak() { return gN(this.jG0); } public final void bH() { if (this.XQ || dm0() != 5) return;  short s; if (((s = this.a) & ZY.di0.iL) == 0 && (s & ZY.I6.iL) == 0 && (s & 
/*  4 */       ZY.qG
/*  5 */       .iL) == 0) return;  if (this
/*  6 */       .W20.length < 1) return;  Ku ku; if ((ku = this.aM0) != null && 
/*  7 */       !ku.sO)
/*  8 */       return;  if (!this.d00.compareAndSet(false, true)) return;  ZY zY; oD(Ml0.OH0(1514), zY = ZY.XY); if (!sh0.YO(this)) { int i; if ((i = this.dy0) == 0) { i = xi0.A90(5, 20); } else { i = (int)Math.pow(i, 2.0D) * 30; }  this.dy0++; oD(Ml0.la(1515, i + ""), zY);
/*    */       
/* 10 */       Runnable runnable = this::bH; long l = (i * 1000); A1.L7.ac0(runnable, l); }  this.d00.set(false); } public final zr0 gN(yM paramyM) { return this.Fe[paramyM.Xv0]; } public final hP Y40(CJ paramCJ) { hP hP1; if ((hP1 = this.cl[paramCJ.pb]) == null) { this(paramCJ, new Xm[0]); this.cl[paramCJ.pb] = hP1; }  return hP1; } public final qc0 DS() { return this.OK; } public final Uk BR() { return this.hZ; } public final BF vC() { return this.fF0; } public final Oc0 rC0() { return this.E50; } public final mG ik0() { return this.Wn0; } public final Yp0 Nh0() { return this.Tr0; } public final fH0 IQ() { return this.Lz; } public final byte Zm() { fH0 fH01; return ((fH01 = this.Lz) == null) ? 0 : this.Oa0; } public final void QL() { String str1; fH0 fH01; if ((fH01 = this.Lz) == null) return;  boolean bool = true; String str2 = fH01.tu; ed.CZ.VF(bool, str2); KI kI; if ((kI = this.Qa.Jr0()) == null) return;  byte b; if ((b = kI.E10) == 1) { String str; if (this.Lz.Xu0 == 0) { str1 = Ml0.OH0(260001); } else { str1 = Ml0.OH0(260000); }  ed.CZ.VF((byte)6, str1); if (this.Lz.Xu0 == 0)
/* 11 */       { str = Ml0.OH0(260003); }
/*    */       else
/* 13 */       { str = Ml0.OH0(260002); }  ed.CZ.VF((byte)2, this); } else { byte b1 = 6; str1 = Ml0.kd0(str1);
/* 14 */       ed.CZ.VF(b1, str1); }  } public abstract boolean Sg(Mv0 paramMv0); public final void oD(String paramString, ZY paramZY) { this(paramZY, 0, "", null, (byte)0, paramString); Mv0 mv0; Sg(this); } public final void lF(String paramString) { p9(ZY.l3, paramString, "", true); } public final int p9(ZY paramZY, String paramString1, String paramString2, boolean paramBoolean) { // Byte code:
/*    */     //   0: aload_2
/*    */     //   1: invokevirtual trim : ()Ljava/lang/String;
/*    */     //   4: dup
/*    */     //   5: astore_2
/*    */     //   6: invokevirtual length : ()I
/*    */     //   9: iconst_1
/*    */     //   10: if_icmpge -> 15
/*    */     //   13: iconst_0
/*    */     //   14: ireturn
/*    */     //   15: iload #4
/*    */     //   17: getstatic f/gm.By0 : Z
/*    */     //   20: pop
/*    */     //   21: ifeq -> 143
/*    */     //   24: getstatic f/Pg.nc : Lf/Pg;
/*    */     //   27: getfield GO : Ljava/util/ArrayList;
/*    */     //   30: invokevirtual iterator : ()Ljava/util/Iterator;
/*    */     //   33: astore #4
/*    */     //   35: aload #4
/*    */     //   37: invokeinterface hasNext : ()Z
/*    */     //   42: ifeq -> 137
/*    */     //   45: aload #4
/*    */     //   47: invokeinterface next : ()Ljava/lang/Object;
/*    */     //   52: checkcast f/x60
/*    */     //   55: dup
/*    */     //   56: astore #5
/*    */     //   58: getfield Fz : Z
/*    */     //   61: ifeq -> 76
/*    */     //   64: aload_2
/*    */     //   65: aload #5
/*    */     //   67: getfield v00 : Ljava/lang/String;
/*    */     //   70: invokestatic M60 : (Ljava/lang/String;Ljava/lang/String;)Z
/*    */     //   73: ifne -> 113
/*    */     //   76: aload #5
/*    */     //   78: getfield Fz : Z
/*    */     //   81: ifne -> 129
/*    */     //   84: aload_2
/*    */     //   85: aload #5
/*    */     //   87: getfield v00 : Ljava/lang/String;
/*    */     //   90: invokevirtual equalsIgnoreCase : (Ljava/lang/String;)Z
/*    */     //   93: ifeq -> 129
/*    */     //   96: getstatic f/km.a3 : Lf/vh0;
/*    */     //   99: getfield Ct : Lf/Jo;
/*    */     //   102: getfield CC : B
/*    */     //   105: aload #5
/*    */     //   107: invokevirtual Gs0 : ()I
/*    */     //   110: if_icmplt -> 129
/*    */     //   113: aload #5
/*    */     //   115: aload_2
/*    */     //   116: ldc_w ' '
/*    */     //   119: invokevirtual split : (Ljava/lang/String;)[Ljava/lang/String;
/*    */     //   122: invokevirtual Da0 : ([Ljava/lang/String;)V
/*    */     //   125: iconst_1
/*    */     //   126: goto -> 130
/*    */     //   129: iconst_0
/*    */     //   130: ifeq -> 35
/*    */     //   133: iconst_1
/*    */     //   134: goto -> 138
/*    */     //   137: iconst_0
/*    */     //   138: ifeq -> 143
/*    */     //   141: iconst_1
/*    */     //   142: ireturn
/*    */     //   143: aload_1
/*    */     //   144: getstatic f/ZY.lB : Lf/ZY;
/*    */     //   147: if_acmpne -> 179
/*    */     //   150: aload_0
/*    */     //   151: getfield Wn0 : Lf/mG;
/*    */     //   154: ifnonnull -> 179
/*    */     //   157: aload_2
/*    */     //   158: ldc_w '/'
/*    */     //   161: invokevirtual startsWith : (Ljava/lang/String;)Z
/*    */     //   164: ifne -> 179
/*    */     //   167: aload_0
/*    */     //   168: sipush #1531
/*    */     //   171: invokestatic OH0 : (I)Ljava/lang/String;
/*    */     //   174: invokevirtual Pq : (Ljava/lang/String;)V
/*    */     //   177: iconst_0
/*    */     //   178: ireturn
/*    */     //   179: aload_0
/*    */     //   180: getfield e20 : Lf/c4;
/*    */     //   183: new f/vC
/*    */     //   186: dup
/*    */     //   187: aload_1
/*    */     //   188: aload_2
/*    */     //   189: aload_3
/*    */     //   190: invokespecial <init> : (Lf/ZY;Ljava/lang/String;Ljava/lang/String;)V
/*    */     //   193: invokevirtual W3 : (Lf/Bi;)V
/*    */     //   196: iconst_2
/*    */     //   197: ireturn
/*    */     // Line number table:
/*    */     //   Java source line number -> byte code offset
/*    */     //   #1	-> 24
/*    */     //   #2	-> 27
/*    */     //   #3	-> 30
/*    */     //   #4	-> 58
/*    */     //   #5	-> 67
/*    */     //   #6	-> 99
/*    */     //   #7	-> 102
/*    */     //   #8	-> 107
/*    */     //   #9	-> 144
/*    */     //   #10	-> 151
/* 14 */     //   #11	-> 158 } public final void lx0(byte paramByte1, byte paramByte2) { this.zl.lpt7.T30(); this.e20.W3(new lpt7(paramByte1, paramByte2)); } public final void N7(byte paramByte, byte... paramVarArgs) { this.zl.lpt7.T30(); this.e20.W3(new Tn0(paramByte, paramVarArgs)); } public final void Ch0() { if (this.e20 != null) { R8 r8 = (R8)this; UB0.Kg0.fN(new Jf0(r8)); UB0.Kg0.fN(new ZV(this)); }  if (this.aM0 != null) UB0.Kg0.fN(new lB0(this));  } public final void TA0(boolean paramBoolean) { this.ky = paramBoolean; if (!paramBoolean) { for (Iterator<tc> iterator = this.Qa.KO.values().iterator(); iterator.hasNext();) { if ((tc = iterator.next()).zl() && ((Kr0)(tc = tc)).pr0 < System.currentTimeMillis() + 500L) ((Kr0)tc).pr0 = System.currentTimeMillis() + 500L;  }  this.tN = false; }  } public final boolean NR() { sH sH; if (this.ky || (sH = km.wI0.HV) != null || this != null) return true;  } public final void UW() { Gp0 gp0; if ((gp0 = km.MR) == null) return;  boolean bool1 = gp0.RM(), bool2 = km.MR.sQ(); ve ve = js.vu0.MH0.yq0; if (km.MR.yx0() && km.MR.sQ() && ve != null && ve.ab0.dP) { ve.LJ0(false, true); R8 r8 = km.u4; byte b = ve.La0; String str = ve.l5.F2.PH0.toString(); r8.e20
/* 15 */         .W3(new gj0(b, str)); }
/* 16 */      km.MR = null; qj0 qj0; if (bool1 && (qj0 = km.Ll0) != null) { qj0
/* 17 */         .Fj0 = true; km.Ll0 = null; }  if (bool2) { this
/* 18 */         .e20.W3(new Cp0()); } else { this.e20.W3(new M80()); }  km.iE0.Hf0(); Uc0 uc0; if ((uc0 = s40(aq0.LI)) != null) { Ix0(); j40[] arrayOfJ40; for (int i = (arrayOfJ40 = lPt3()).length; bool2 < i; )
/* 19 */       { (this[bool2]).Zs
/* 20 */           .m80 = -1; bool2++; }  }  } public final void tq0(short paramShort1, int paramInt1, int paramInt2, short paramShort2, byte paramByte) { boolean bool = false; ps0(paramShort1, paramInt1, paramInt2, paramShort2, paramByte, (byte)0, bool); } public abstract void ps0(short paramShort1, int paramInt1, int paramInt2, short paramShort2, byte paramByte1, byte paramByte2, boolean paramBoolean); public final void lO(Qv0 paramQv01, Qv0 paramQv02) { Qv0[] arrayOfQv01; (arrayOfQv01 = new Qv0[1])[0] = paramQv01; Qv0[] arrayOfQv02; (arrayOfQv02 = new Qv0[1])[0] = paramQv02; Zt(this, arrayOfQv02); } public final void Zt(Qv0[] paramArrayOfQv01, Qv0[] paramArrayOfQv02) { if (paramArrayOfQv01.length != paramArrayOfQv02.length) return;  if (paramArrayOfQv01.length == 0) return;  if (paramArrayOfQv01.length > 127) return;  for (byte b = 0; b < paramArrayOfQv01.length; b++) { if (paramArrayOfQv01[b].lK() == paramArrayOfQv02[b].lK() && paramArrayOfQv01[b].fH0() == paramArrayOfQv02[b].fH0()) return;  if (paramArrayOfQv01[b].fH0() < 0 || paramArrayOfQv02[b].fH0() < 0) return;  }  this.e20.W3(new dt0(paramArrayOfQv01, paramArrayOfQv02)); } public final void mS(int paramInt, byte paramByte1, Vg0 paramVg0, short paramShort, byte paramByte2) { this.e20.W3(new Nf0(paramInt, paramByte1, paramVg0, paramShort, paramByte2)); } public final void DK0() { Jo jo; if ((jo = this.Qa.Ct) == null) return;  fH0 fH01; if ((fH01.vv0 = (short)((fH01 = this.Lz).vv0 - 1)) < 0) fH01.vv0 = 0;  short s2 = fH01.fa0; short s1; if ((s1 = fH01.rH0) > 0 || s2 > 0) { String str1; Ku0 ku0; String str2; if (!jo.xi) { byte b = 1; if (s1 < 1 && s2 > 0 && (fH01.fa0 = (short)(s2 - b)) < 1) { fH01.YN = m9.Bt0; fH01.Cr = 0; fH01.fa0 = 0; }  if (s1 > 0) fH01.rH0 = (short)(s1 - b);  }  if (s1 - 1 == 1) { boolean bool; short s; if ((s = fH01.f6) > 0 && this.Fe[1].vH0((byte)-1, s, (short)1)) { bool = true; } else { bool = false; }  if (s < 1) { str2 = Ml0.OH0(245079); } else { str2 = Ml0.OH0(s + 240000); }  if (bool) { str1 = Ml0.Go(6012, str2); Aq aq = Aq.yr0; ku0 = (paramByte -> { if (paramByte == 1) UB0.Kg0.fN(());  }); km.kH0.CU(this, aq, ku0); return; }  } else if (s2 - 1 == 1 && str2 <= null) { boolean bool; short s; if ((s = ((fH0)ku0).Cr) > 0 && ((ro)super).Fe[1].vH0((byte)-1, s, (short)1)) { bool = true; } else { bool = false; }
/*    */ 
/*    */ 
/*    */ 
/*    */         
/* 25 */         str2 = Ml0.OH0(((s < 1) ? Of.eH.On0((short)1041) : Of.eH.On0(s)).Iu); if (bool)
/* 26 */         { str1 = Ml0.Go(6012, str2); Aq aq = Aq.yr0; Ku0 ku01 = paramByte -> { if (paramByte == 1) UB0.Kg0.fN(());  }; km.kH0.CU(this, aq, ku01); return; }  } else { return; }  super.Pq(Ml0.Go(6011, str2)); }
/*    */      }
/*    */ 
/*    */   
/*    */   public final void mO(int paramInt) {
/*    */     this.e20.W3(new ch0(paramInt));
/*    */   }
/*    */   
/*    */   public final void OI(byte paramByte, int paramInt, short paramShort, boolean paramBoolean) {
/*    */     this.e20.W3(new zd(paramByte, paramInt, paramShort, paramBoolean));
/*    */   }
/*    */   
/*    */   public final void FL(dL0 paramdL0, byte paramByte, short paramShort) {
/*    */     this.e20.W3(new yz0(paramdL0, paramByte, paramShort));
/*    */   }
/*    */   
/*    */   public final void Dn() {
/*    */     c4 c41;
/*    */     if ((c41 = this.e20) != null) {
/*    */       Dt dt;
/*    */       this();
/*    */       c41.W3(dt);
/*    */     } 
/*    */     Ku ku;
/*    */     if ((ku = this.aM0) == null) {
/*    */       A1 a1 = A1.L7;
/*    */       this.nc.execute(this::bH);
/*    */     } else if (ku.hO == 3) {
/*    */       jB jB;
/*    */       this();
/*    */       ku.Tr0(this);
/*    */     } 
/*    */   }
/*    */   
/*    */   public final void Ha0(uM paramuM, boolean paramBoolean) {
/*    */     if (paramBoolean) {
/*    */       ArrayList<?> arrayList;
/*    */       if ((arrayList = h1.wL0()).isEmpty())
/*    */         return; 
/*    */       uM1 = (uM)arrayList.get(0);
/*    */       for (uM uM2 : arrayList) {
/*    */         if (h1.LF0.equalsIgnoreCase(uM2.Fg)) {
/*    */           uM1 = uM2;
/*    */           break;
/*    */         } 
/*    */       } 
/*    */     } 
/*    */     this();
/*    */     uM uM1;
/*    */     HashSet<ZY> hashSet1, hashSet2;
/*    */     this();
/*    */     ZY[] arrayOfZY;
/*    */     int i;
/*    */     short s2;
/*    */     for (i = (arrayOfZY = ZY.R70).length, s2 = 0; s2 < i; ) {
/*    */       ZY zY = arrayOfZY[s2];
/*    */       if (!uM1.ul.contains(zY))
/*    */         hashSet1.add(zY); 
/*    */       s2++;
/*    */     } 
/*    */     short s1;
/*    */     for (s1 = 0, i = (arrayOfZY = ZY.R70).length, s2 = 0; s2 < i; ) {
/*    */       ZY zY;
/*    */       if ((zY = arrayOfZY[s2]).hd)
/*    */         hashSet1.add(zY); 
/*    */       s1 = (short)(s1 | zY.iL);
/*    */       s2++;
/*    */     } 
/*    */     for (Iterator<ZY> iterator = hashSet1.iterator(); iterator.hasNext();) {
/*    */       if ((zY = iterator.next()).oZ < 16 && ((i = this.a) & (s2 = zY.iL)) == 0) {
/*    */         this.a = (short)(i | s2);
/*    */         hashSet2.add(zY);
/*    */       } 
/*    */     } 
/*    */     this.bn = (short)((this.a ^ 0xFFFFFFFF) & s1);
/*    */     if (!paramBoolean) {
/*    */       for (Iterator<ZY> iterator1 = hashSet2.iterator(); iterator1.hasNext();)
/*    */         oD(Ml0.Go(1523, Ml0.OH0((zY = iterator1.next()).UR)), zY); 
/*    */       if (!hashSet2.isEmpty())
/*    */         Dn(); 
/*    */     } 
/*    */   }
/*    */   
/*    */   public final void M6(byte paramByte, ky paramky, DO paramDO) {
/*    */     EZ eZ;
/*    */     Map map;
/*    */     if ((map = (Map)(eZ = EZ.G3).FC0.get(Byte.valueOf(paramByte))) == null) {
/*    */       EnumMap<Enum, Object> enumMap;
/*    */       Byte byte_ = Byte.valueOf(paramByte);
/*    */       this((Class)ky.class);
/*    */       ky[] arrayOfKy;
/*    */       byte b1, b2;
/*    */       for (arrayOfKy = ky.jG, b1 = 4, b2 = 0; b2 < b1; ) {
/*    */         EnumMap<Enum, Object> enumMap1;
/*    */         ky ky1 = arrayOfKy[b2];
/*    */         this((Class)DO.class);
/*    */         enumMap.put(ky1, enumMap1);
/*    */         b2++;
/*    */       } 
/*    */       eZ.FC0.put(byte_, enumMap);
/*    */       map = enumMap;
/*    */     } 
/*    */     Gu0 gu0;
/*    */     if ((gu0 = (Gu0)((Map)map.get(paramky)).get(paramDO)) == null) {
/*    */       gu0 = null;
/*    */     } else if (System.currentTimeMillis() >= gu0.l8) {
/*    */       ((Map)map.get(paramky)).put(paramDO, null);
/*    */       gu0 = null;
/*    */     } 
/*    */     if (gu0 != null) {
/*    */       rG(paramByte, paramky, paramDO, gu0);
/*    */       return;
/*    */     } 
/*    */     byte b = paramky.Xm0;
/*    */     this.e20.W3(new ti(paramByte, b, paramDO.y1));
/*    */   }
/*    */   
/*    */   public final g2 Um() {
/*    */     return this.Mg0;
/*    */   }
/*    */   
/*    */   public final boolean x00() {
/*    */     boolean bool;
/*    */     if (bool = this.Ax) {
/*    */       this.Ax = false;
/*    */       return true;
/*    */     } 
/*    */     return bool;
/*    */   }
/*    */   
/*    */   public abstract void Pq(String paramString);
/*    */   
/*    */   public abstract void b00(String paramString);
/*    */   
/*    */   public abstract void ow();
/*    */   
/*    */   public abstract void Wp();
/*    */   
/*    */   public final yM Uo0() {
/*    */     return this.jG0;
/*    */   }
/*    */   
/*    */   public abstract void rG(byte paramByte, ky paramky, DO paramDO, Gu0 paramGu0);
/*    */   
/*    */   public abstract void jr(Xv0 paramXv0, ZY paramZY, boolean paramBoolean1, boolean paramBoolean2);
/*    */   
/*    */   public abstract void W0(j40 paramj40);
/*    */   
/*    */   public abstract void TD(qa0 paramqa0);
/*    */   
/*    */   public abstract void tS(Kl0 paramKl0);
/*    */   
/*    */   public final void D80() {
/*    */     Jo jo = this.Qa.Ct;
/*    */     if (this.Qa.Jr0() == null || jo == null)
/*    */       return; 
/*    */     if (this.tN)
/*    */       return; 
/*    */     jo.J.Jg0 = true;
/*    */     zk0 zk0;
/*    */     if ((zk0 = jo.Ae) != null)
/*    */       this.Y1.Jg0 = true; 
/*    */     xr0 xr0;
/*    */     if ((xr0 = jo.HW.CJ0()) == null)
/*    */       return; 
/*    */     if (this instanceof il)
/*    */       km.wI0.iJ0.we(this, false, true); 
/*    */     hz().bf0(this, jo, true);
/*    */   }
/*    */   
/*    */   public final void jt0(byte paramByte, short paramShort1, short paramShort2) {
/*    */     kV kV2;
/*    */     if ((kV2 = kV.de(paramShort1, paramShort2, false)) == null) {
/*    */       lx0(paramByte, (byte)0);
/*    */       return;
/*    */     } 
/*    */     kV2.KI = (() -> lx0(paramByte, (byte)0));
/*    */     Pw pw;
/*    */     kV kV1;
/*    */     if ((kV1 = (pw = km.wI0).Uc0) != null) {
/*    */       if (!kV1.Ar) {
/*    */         kV1.Ar = true;
/*    */         kV1.Jy();
/*    */       } 
/*    */       if (kV1.ot())
/*    */         pA.Dg0.wI0(true); 
/*    */       kV1.dispose();
/*    */       Runnable runnable;
/*    */       if ((runnable = kV1.KI) != null)
/*    */         runnable.run(); 
/*    */     } 
/*    */     this.Uc0 = kV2;
/*    */   }
/*    */   
/*    */   public final void pb0(byte paramByte) {
/*    */     this(this.Qa.eA);
/*    */     k3 k3;
/*    */     (k3 = new k3()).KI = (() -> lx0(paramByte, (byte)0));
/*    */     km.wI0.i2.addFirst(k3);
/*    */   }
/*    */   
/*    */   public abstract void PC(short paramShort);
/*    */   
/*    */   public final void aUX(byte paramByte, short paramShort1, short paramShort2, short paramShort3) {
/*    */     // Byte code:
/*    */     //   0: iload_2
/*    */     //   1: iconst_0
/*    */     //   2: istore #5
/*    */     //   4: iconst_3
/*    */     //   5: if_icmpne -> 48
/*    */     //   8: iload_3
/*    */     //   9: bipush #19
/*    */     //   11: if_icmpeq -> 45
/*    */     //   14: iload_3
/*    */     //   15: bipush #70
/*    */     //   17: if_icmpeq -> 45
/*    */     //   20: iload_3
/*    */     //   21: bipush #91
/*    */     //   23: if_icmpeq -> 45
/*    */     //   26: iload_3
/*    */     //   27: bipush #100
/*    */     //   29: if_icmpeq -> 45
/*    */     //   32: aload_0
/*    */     //   33: iload_3
/*    */     //   34: iload #4
/*    */     //   36: iconst_1
/*    */     //   37: invokevirtual nJ : (SSZ)Z
/*    */     //   40: istore #5
/*    */     //   42: goto -> 48
/*    */     //   45: iconst_0
/*    */     //   46: istore #5
/*    */     //   48: iload #5
/*    */     //   50: ifeq -> 152
/*    */     //   53: iload_3
/*    */     //   54: aload_0
/*    */     //   55: iload_1
/*    */     //   56: iconst_0
/*    */     //   57: invokevirtual lx0 : (BB)V
/*    */     //   60: bipush #15
/*    */     //   62: if_icmpne -> 185
/*    */     //   65: getstatic f/km.a3 : Lf/vh0;
/*    */     //   68: getfield Ct : Lf/Jo;
/*    */     //   71: getfield pm : Lf/d7;
/*    */     //   74: dup
/*    */     //   75: astore_0
/*    */     //   76: iconst_1
/*    */     //   77: dup
/*    */     //   78: istore_1
/*    */     //   79: anewarray f/nl
/*    */     //   82: dup
/*    */     //   83: astore_2
/*    */     //   84: getstatic f/nl.COM7 : Lf/nl;
/*    */     //   87: iconst_0
/*    */     //   88: swap
/*    */     //   89: aastore
/*    */     //   90: getfield ew0 : Ljava/util/LinkedList;
/*    */     //   93: dup
/*    */     //   94: astore_3
/*    */     //   95: monitorenter
/*    */     //   96: iconst_0
/*    */     //   97: istore #4
/*    */     //   99: iload #4
/*    */     //   101: iload_1
/*    */     //   102: if_icmpge -> 142
/*    */     //   105: aload_2
/*    */     //   106: iload #4
/*    */     //   108: aaload
/*    */     //   109: dup
/*    */     //   110: astore #5
/*    */     //   112: ifnonnull -> 118
/*    */     //   115: goto -> 136
/*    */     //   118: aload_0
/*    */     //   119: getfield ew0 : Ljava/util/LinkedList;
/*    */     //   122: new f/xB0
/*    */     //   125: dup
/*    */     //   126: aload #5
/*    */     //   128: iconst_0
/*    */     //   129: invokespecial <init> : (Lf/nl;I)V
/*    */     //   132: invokevirtual add : (Ljava/lang/Object;)Z
/*    */     //   135: pop
/*    */     //   136: iinc #4, 1
/*    */     //   139: goto -> 99
/*    */     //   142: aload_3
/*    */     //   143: monitorexit
/*    */     //   144: goto -> 185
/*    */     //   147: astore_0
/*    */     //   148: aload_0
/*    */     //   149: aload_3
/*    */     //   150: monitorexit
/*    */     //   151: athrow
/*    */     //   152: getstatic f/km.wI0 : Lf/Pw;
/*    */     //   155: new f/sA0
/*    */     //   158: dup
/*    */     //   159: dup
/*    */     //   160: astore #5
/*    */     //   162: aload_0
/*    */     //   163: iload_1
/*    */     //   164: aload #5
/*    */     //   166: iload_2
/*    */     //   167: iload_3
/*    */     //   168: iload #4
/*    */     //   170: invokespecial <init> : (ISS)V
/*    */     //   173: iload_3
/*    */     //   174: <illegal opcode> run : (Lf/ro;BS)Ljava/lang/Runnable;
/*    */     //   179: putfield LN : Ljava/lang/Runnable;
/*    */     //   182: invokevirtual PH0 : (Lf/sA0;)V
/*    */     //   185: return
/*    */     // Line number table:
/*    */     //   Java source line number -> byte code offset
/*    */     //   #1	-> 68
/*    */     //   #2	-> 71
/*    */     //   #3	-> 79
/*    */     //   #4	-> 90
/*    */     //   #5	-> 95
/*    */     //   #6	-> 152
/*    */     //   #7	-> 179
/*    */     //   #8	-> 182
/*    */     // Exception table:
/*    */     //   from	to	target	type
/*    */     //   105	109	147	finally
/*    */     //   118	135	147	finally
/*    */     //   142	147	147	finally
/*    */     //   148	151	147	finally
/*    */   }
/*    */   
/*    */   public final void D10(byte paramByte1, short paramShort, boolean paramBoolean, byte paramByte2) {
/*    */     this(paramShort, paramBoolean, paramByte2);
/*    */     sA0 sA0;
/*    */     (sA0 = new sA0()).LN = (() -> lx0(paramByte, (byte)0));
/*    */     km.wI0.PH0(new sA0());
/*    */   }
/*    */   
/*    */   public final boolean nJ(short paramShort1, short paramShort2, boolean paramBoolean) {
/*    */     boolean bool1;
/*    */     boolean bool2;
/*    */     if (paramShort2 < 0) {
/*    */       paramShort2 = (short)(paramShort2 & 0xFFF);
/*    */     } else {
/*    */       j40 j40;
/*    */       if ((j40 = km.u4.s40(aq0.LI).ky(paramShort2)) != null) {
/*    */         bool1 = j40.Zs.Cw0;
/*    */       } else {
/*    */         bool1 = false;
/*    */       } 
/*    */     } 
/*    */     if (bool1 && this.Ie0.Z90(paramShort1) == bool1) {
/*    */       bool2 = true;
/*    */     } else {
/*    */       bool2 = false;
/*    */     } 
/*    */     if (!bool2 && paramBoolean)
/*    */       this.Ie0.st(paramShort1, bool1); 
/*    */     return bool2;
/*    */   }
/*    */   
/*    */   public final void a80() {
/*    */     if (this.XA0 == null)
/*    */       return; 
/*    */     String str = B40.df("https://pokemmo.com/donate/?account_id=").append(km.u4.Cf0).append("&key=").append(LF.oa0(this.XA0)).append("&local=").append(h1.pB0).append("&os=").append(yG.x3.i50).toString();
/*    */     if (!UB0.LL0.Zq(this)) {
/*    */       pA pA;
/*    */       yH0 yH0;
/*    */       if ((yH0 = (pA = pA.Dg0).af0) != null) {
/*    */         yH0.ra0();
/*    */         pA.af0 = null;
/*    */       } 
/*    */       this(this);
/*    */       pA.af0 = new yH0();
/*    */       pA.J8(yH0);
/*    */       pA.af0.mM();
/*    */       pA.af0.ME(km.wI0.dG() / 2 - pA.af0.xY / 2, km.wI0.k1() / 2 - pA.af0.HC / 2);
/*    */     } 
/*    */   }
/*    */   
/*    */   public final void ng() {
/*    */     for (Iterator iterator = this.Qa.iterator(); hasNext(); ) {
/*    */       tc tc;
/*    */       (tc = (tc)next()).getClass();
/*    */       if ((tc)next() instanceof Jo)
/*    */         ((Jo)tc).Dx0(); 
/*    */     } 
/*    */     My my;
/*    */     (my = km.si0).getClass();
/*    */     UB0.Kg0.fN(new rt0(this));
/*    */   }
/*    */   
/*    */   public final long l5() {
/*    */     return this.b;
/*    */   }
/*    */   
/*    */   public final int s3(int paramInt) {
/*    */     if (!this.cv) {
/*    */       String[] arrayOfString;
/*    */       if (!EC.AUX.isEmpty() && (arrayOfString = EC.AUX.split(",")).length >= 2) {
/*    */         int i = 0;
/*    */         byte b = 0;
/*    */         while (true) {
/*    */           if (b < arrayOfString.length) {
/*    */             if (!arrayOfString[b].isEmpty())
/*    */               try {
/*    */                 int j = Integer.parseInt(arrayOfString[b]);
/*    */                 if (b % 2 == 0) {
/*    */                   i = j;
/*    */                 } else {
/*    */                   this.cOm3.B3(i, j);
/*    */                 } 
/*    */                 b++;
/*    */                 continue;
/*    */               } catch (NumberFormatException numberFormatException) {
/*    */                 EC.Qm(null);
/*    */                 this.cOm3.clear();
/*    */                 break;
/*    */               }  
/*    */           } else {
/*    */             break;
/*    */           } 
/*    */           b++;
/*    */         } 
/*    */       } 
/*    */       this.cv = true;
/*    */     } 
/*    */     return this.cOm3.xC(paramInt);
/*    */   }
/*    */   
/*    */   public final boolean VF0(int paramInt) {
/*    */     if (!this.ni0) {
/*    */       String[] arrayOfString;
/*    */       if ((arrayOfString = EC.x6.split(",")).length >= 2) {
/*    */         int i = 0;
/*    */         byte b = 0;
/*    */         while (true) {
/*    */           if (b < arrayOfString.length) {
/*    */             if (!arrayOfString[b].isEmpty())
/*    */               try {
/*    */                 int j = Integer.parseInt(arrayOfString[b]);
/*    */                 if (b % 2 == 0) {
/*    */                   i = j;
/*    */                 } else {
/*    */                   this.k20.B3(i, j);
/*    */                 } 
/*    */                 b++;
/*    */                 continue;
/*    */               } catch (NumberFormatException numberFormatException) {
/*    */                 EC.ny0(null);
/*    */                 this.k20.clear();
/*    */                 break;
/*    */               }  
/*    */           } else {
/*    */             break;
/*    */           } 
/*    */           b++;
/*    */         } 
/*    */       } 
/*    */       this.ni0 = true;
/*    */     } 
/*    */     return (this.k20.xC(paramInt) == 1);
/*    */   }
/*    */   
/*    */   public final byte W6() {
/*    */     return this.cJ0;
/*    */   }
/*    */   
/*    */   public final void Q4(byte[] paramArrayOfbyte, U50[] paramArrayOfU50) {
/*    */     this.vB = paramArrayOfbyte;
/*    */     this.W20 = paramArrayOfU50;
/*    */     Ku ku;
/*    */     if ((ku = this.aM0) == null || ku.sO) {
/*    */       if (h1.mD0 || km.XU())
/*    */         return; 
/*    */       A1 a1 = A1.L7;
/*    */       this.nc.execute(this::bH);
/*    */     } 
/*    */   }
/*    */   
/*    */   public final boolean q10() {
/*    */     return (this.I6.length > 0);
/*    */   }
/*    */   
/*    */   public final short[] YV() {
/*    */     return this.I6;
/*    */   }
/*    */   
/*    */   public final int[] mL0() {
/*    */     return this.uv0;
/*    */   }
/*    */   
/*    */   public final boolean Nz(short paramShort) {
/*    */     // Byte code:
/*    */     //   0: aload_0
/*    */     //   1: getfield GN : [S
/*    */     //   4: astore_2
/*    */     //   5: iconst_0
/*    */     //   6: istore_3
/*    */     //   7: iload_3
/*    */     //   8: aload_2
/*    */     //   9: arraylength
/*    */     //   10: if_icmpge -> 29
/*    */     //   13: iload_1
/*    */     //   14: aload_2
/*    */     //   15: iload_3
/*    */     //   16: saload
/*    */     //   17: if_icmpne -> 23
/*    */     //   20: goto -> 31
/*    */     //   23: iinc #3, 1
/*    */     //   26: goto -> 7
/*    */     //   29: iconst_m1
/*    */     //   30: istore_3
/*    */     //   31: iload_3
/*    */     //   32: ifge -> 37
/*    */     //   35: iconst_0
/*    */     //   36: ireturn
/*    */     //   37: aload_0
/*    */     //   38: getfield PM : [Z
/*    */     //   41: iload_3
/*    */     //   42: baload
/*    */     //   43: ireturn
/*    */     // Line number table:
/*    */     //   Java source line number -> byte code offset
/*    */     //   #1	-> 9
/*    */     //   #2	-> 38
/*    */   }
/*    */   
/*    */   public final void J80(byte paramByte, int paramInt, short paramShort) {
/*    */     mS(paramInt, paramByte, null, paramShort, (byte)0);
/*    */   }
/*    */   
/*    */   public final void Aw(byte paramByte1, byte paramByte2, int paramInt) {
/*    */     this.e20.W3(new KL0(paramByte1, paramByte2, paramInt));
/*    */   }
/*    */   
/*    */   public final void bA0(int paramInt, byte paramByte) {
/*    */     this.e20.W3(new Xx0(paramInt, paramByte));
/*    */   }
/*    */   
/*    */   public final void jF(byte paramByte, boolean paramBoolean1, boolean paramBoolean2) {
/*    */     // Byte code:
/*    */     //   0: aload_0
/*    */     //   1: getfield hB0 : Lf/Ca;
/*    */     //   4: dup
/*    */     //   5: astore #4
/*    */     //   7: ifnull -> 26
/*    */     //   10: aload #4
/*    */     //   12: invokeinterface Lz0 : ()Z
/*    */     //   17: ifeq -> 21
/*    */     //   20: return
/*    */     //   21: aload_0
/*    */     //   22: aconst_null
/*    */     //   23: putfield hB0 : Lf/Ca;
/*    */     //   26: aload_0
/*    */     //   27: getfield Qa : Lf/vh0;
/*    */     //   30: getfield Ct : Lf/Jo;
/*    */     //   33: dup
/*    */     //   34: astore #4
/*    */     //   36: getfield HW : Lf/G5;
/*    */     //   39: getfield g50 : B
/*    */     //   42: iload_1
/*    */     //   43: if_icmpeq -> 146
/*    */     //   46: iload_1
/*    */     //   47: iconst_m1
/*    */     //   48: if_icmpeq -> 146
/*    */     //   51: aload #4
/*    */     //   53: getfield pm : Lf/d7;
/*    */     //   56: dup
/*    */     //   57: astore #5
/*    */     //   59: invokevirtual gD0 : ()Z
/*    */     //   62: ifne -> 68
/*    */     //   65: goto -> 94
/*    */     //   68: getstatic f/zm0.u20 : J
/*    */     //   71: aload #5
/*    */     //   73: getfield HQ : J
/*    */     //   76: lsub
/*    */     //   77: aload #5
/*    */     //   79: getfield tD0 : I
/*    */     //   82: bipush #100
/*    */     //   84: iadd
/*    */     //   85: i2l
/*    */     //   86: lcmp
/*    */     //   87: ifle -> 94
/*    */     //   90: iconst_1
/*    */     //   91: goto -> 95
/*    */     //   94: iconst_0
/*    */     //   95: ifeq -> 146
/*    */     //   98: aload #4
/*    */     //   100: getfield pm : Lf/d7;
/*    */     //   103: getfield ew0 : Ljava/util/LinkedList;
/*    */     //   106: invokeinterface isEmpty : ()Z
/*    */     //   111: ifeq -> 146
/*    */     //   114: aload #4
/*    */     //   116: getfield pm : Lf/d7;
/*    */     //   119: iload_1
/*    */     //   120: invokevirtual qz0 : (B)Z
/*    */     //   123: ifeq -> 146
/*    */     //   126: iload_3
/*    */     //   127: aload_0
/*    */     //   128: getfield e20 : Lf/c4;
/*    */     //   131: new f/hA
/*    */     //   134: dup
/*    */     //   135: iload_1
/*    */     //   136: invokespecial <init> : (B)V
/*    */     //   139: invokevirtual W3 : (Lf/Bi;)V
/*    */     //   142: ifne -> 146
/*    */     //   145: return
/*    */     //   146: iload_1
/*    */     //   147: aload #4
/*    */     //   149: new f/G5
/*    */     //   152: dup
/*    */     //   153: astore #5
/*    */     //   155: aload #4
/*    */     //   157: getfield HW : Lf/G5;
/*    */     //   160: invokespecial <init> : (Lf/G5;)V
/*    */     //   163: getfield HW : Lf/G5;
/*    */     //   166: getfield g50 : B
/*    */     //   169: istore #6
/*    */     //   171: iconst_m1
/*    */     //   172: if_icmpeq -> 181
/*    */     //   175: aload #5
/*    */     //   177: iload_1
/*    */     //   178: putfield g50 : B
/*    */     //   181: aload #4
/*    */     //   183: getfield pm : Lf/d7;
/*    */     //   186: dup
/*    */     //   187: astore #7
/*    */     //   189: invokevirtual gD0 : ()Z
/*    */     //   192: ifne -> 198
/*    */     //   195: goto -> 1333
/*    */     //   198: aload #7
/*    */     //   200: invokestatic u10 : ()V
/*    */     //   203: getfield OF0 : Lf/tc;
/*    */     //   206: invokevirtual default : ()Lf/static;
/*    */     //   209: dup
/*    */     //   210: astore #8
/*    */     //   212: getfield G30 : B
/*    */     //   215: iconst_m1
/*    */     //   216: if_icmpeq -> 225
/*    */     //   219: aload #8
/*    */     //   221: iconst_m1
/*    */     //   222: putfield G30 : B
/*    */     //   225: aload #7
/*    */     //   227: dup
/*    */     //   228: dup
/*    */     //   229: iconst_0
/*    */     //   230: putfield J4 : Z
/*    */     //   233: iconst_0
/*    */     //   234: putfield eF : Z
/*    */     //   237: getfield OF0 : Lf/tc;
/*    */     //   240: getfield HW : Lf/G5;
/*    */     //   243: dup
/*    */     //   244: dup2
/*    */     //   245: getfield mm : S
/*    */     //   248: istore #8
/*    */     //   250: getfield Yu0 : S
/*    */     //   253: istore #9
/*    */     //   255: getfield Qf0 : B
/*    */     //   258: istore #10
/*    */     //   260: invokevirtual VI0 : ()F
/*    */     //   263: fstore #11
/*    */     //   265: getstatic f/km.a3 : Lf/vh0;
/*    */     //   268: aload #7
/*    */     //   270: getfield OF0 : Lf/tc;
/*    */     //   273: getfield HW : Lf/G5;
/*    */     //   276: dup
/*    */     //   277: dup
/*    */     //   278: getfield FB : B
/*    */     //   281: istore #12
/*    */     //   283: getfield kD0 : B
/*    */     //   286: istore #13
/*    */     //   288: getfield vu0 : B
/*    */     //   291: istore #14
/*    */     //   293: iload #12
/*    */     //   295: iload #13
/*    */     //   297: iload #14
/*    */     //   299: invokevirtual COm8 : (BBB)Lf/KI;
/*    */     //   302: dup
/*    */     //   303: astore #12
/*    */     //   305: ifnonnull -> 311
/*    */     //   308: goto -> 1333
/*    */     //   311: iload_1
/*    */     //   312: aload #7
/*    */     //   314: getfield OF0 : Lf/tc;
/*    */     //   317: getfield HW : Lf/G5;
/*    */     //   320: invokevirtual CJ0 : ()Lf/xr0;
/*    */     //   323: astore #13
/*    */     //   325: iconst_m1
/*    */     //   326: if_icmpeq -> 367
/*    */     //   329: aload #13
/*    */     //   331: ifnull -> 343
/*    */     //   334: aload #13
/*    */     //   336: invokevirtual hz : ()Lf/ZK0;
/*    */     //   339: invokevirtual getClass : ()Ljava/lang/Class;
/*    */     //   342: pop
/*    */     //   343: aload #7
/*    */     //   345: getfield OF0 : Lf/tc;
/*    */     //   348: getfield HW : Lf/G5;
/*    */     //   351: dup
/*    */     //   352: astore #14
/*    */     //   354: getfield g50 : B
/*    */     //   357: iload_1
/*    */     //   358: if_icmpeq -> 367
/*    */     //   361: aload #14
/*    */     //   363: iload_1
/*    */     //   364: putfield g50 : B
/*    */     //   367: iload_1
/*    */     //   368: tableswitch default -> 400, 0 -> 457, 1 -> 439, 2 -> 425, 3 -> 411
/*    */     //   400: iload #8
/*    */     //   402: iload #9
/*    */     //   404: istore #15
/*    */     //   406: istore #14
/*    */     //   408: goto -> 472
/*    */     //   411: iload #8
/*    */     //   413: iconst_1
/*    */     //   414: iadd
/*    */     //   415: i2s
/*    */     //   416: istore #14
/*    */     //   418: iload #9
/*    */     //   420: istore #15
/*    */     //   422: goto -> 472
/*    */     //   425: iload #8
/*    */     //   427: iconst_1
/*    */     //   428: isub
/*    */     //   429: i2s
/*    */     //   430: istore #14
/*    */     //   432: iload #9
/*    */     //   434: istore #15
/*    */     //   436: goto -> 472
/*    */     //   439: iload #9
/*    */     //   441: iconst_1
/*    */     //   442: isub
/*    */     //   443: i2s
/*    */     //   444: istore #14
/*    */     //   446: iload #8
/*    */     //   448: iload #14
/*    */     //   450: istore #15
/*    */     //   452: istore #14
/*    */     //   454: goto -> 472
/*    */     //   457: iload #9
/*    */     //   459: iconst_1
/*    */     //   460: iadd
/*    */     //   461: i2s
/*    */     //   462: istore #14
/*    */     //   464: iload #8
/*    */     //   466: iload #14
/*    */     //   468: istore #15
/*    */     //   470: istore #14
/*    */     //   472: aload #13
/*    */     //   474: ifnull -> 496
/*    */     //   477: aload #13
/*    */     //   479: invokevirtual Y00 : ()Z
/*    */     //   482: ifeq -> 496
/*    */     //   485: aload #13
/*    */     //   487: iload_1
/*    */     //   488: invokevirtual Cx : (B)Lf/xr0;
/*    */     //   491: astore #16
/*    */     //   493: goto -> 527
/*    */     //   496: aload #13
/*    */     //   498: ifnonnull -> 507
/*    */     //   501: fconst_0
/*    */     //   502: fstore #16
/*    */     //   504: goto -> 514
/*    */     //   507: aload #13
/*    */     //   509: invokevirtual i00 : ()F
/*    */     //   512: fstore #16
/*    */     //   514: aload #12
/*    */     //   516: iload #14
/*    */     //   518: iload #15
/*    */     //   520: fload #16
/*    */     //   522: invokevirtual U30 : (SSF)Lf/xr0;
/*    */     //   525: astore #16
/*    */     //   527: aload #13
/*    */     //   529: ifnull -> 565
/*    */     //   532: aload #13
/*    */     //   534: invokevirtual hz : ()Lf/ZK0;
/*    */     //   537: dup
/*    */     //   538: invokevirtual getClass : ()Ljava/lang/Class;
/*    */     //   541: pop
/*    */     //   542: instanceof f/mO
/*    */     //   545: ifeq -> 565
/*    */     //   548: aload #13
/*    */     //   550: invokevirtual hz : ()Lf/ZK0;
/*    */     //   553: aload #12
/*    */     //   555: aload #13
/*    */     //   557: aload #16
/*    */     //   559: iload_1
/*    */     //   560: invokevirtual Zg0 : (Lf/KI;Lf/xr0;Lf/xr0;B)Lf/xr0;
/*    */     //   563: astore #16
/*    */     //   565: iload_2
/*    */     //   566: ifeq -> 587
/*    */     //   569: aload #13
/*    */     //   571: ifnull -> 587
/*    */     //   574: aload #13
/*    */     //   576: invokevirtual hz : ()Lf/ZK0;
/*    */     //   579: invokevirtual DD : ()Z
/*    */     //   582: ifne -> 587
/*    */     //   585: iconst_0
/*    */     //   586: istore_2
/*    */     //   587: aload #7
/*    */     //   589: getfield OF0 : Lf/tc;
/*    */     //   592: iconst_4
/*    */     //   593: invokevirtual so0 : (B)Z
/*    */     //   596: ifeq -> 642
/*    */     //   599: iload_3
/*    */     //   600: ifeq -> 642
/*    */     //   603: aload #7
/*    */     //   605: getfield J4 : Z
/*    */     //   608: ifne -> 642
/*    */     //   611: iload_1
/*    */     //   612: iconst_m1
/*    */     //   613: if_icmpne -> 642
/*    */     //   616: aload #7
/*    */     //   618: dup
/*    */     //   619: dup2
/*    */     //   620: iconst_1
/*    */     //   621: putfield eF : Z
/*    */     //   624: lconst_0
/*    */     //   625: invokevirtual j10 : (J)V
/*    */     //   628: getfield OF0 : Lf/tc;
/*    */     //   631: iload_2
/*    */     //   632: putfield dh : Z
/*    */     //   635: invokevirtual Q80 : ()V
/*    */     //   638: iconst_1
/*    */     //   639: goto -> 2133
/*    */     //   642: iload_3
/*    */     //   643: ifeq -> 705
/*    */     //   646: aload #7
/*    */     //   648: getfield OF0 : Lf/tc;
/*    */     //   651: bipush #17
/*    */     //   653: invokevirtual so0 : (B)Z
/*    */     //   656: ifne -> 705
/*    */     //   659: aload #7
/*    */     //   661: getfield OF0 : Lf/tc;
/*    */     //   664: iconst_4
/*    */     //   665: invokevirtual so0 : (B)Z
/*    */     //   668: ifeq -> 705
/*    */     //   671: aload #7
/*    */     //   673: getfield J4 : Z
/*    */     //   676: ifne -> 705
/*    */     //   679: aload #16
/*    */     //   681: ifnull -> 705
/*    */     //   684: aload #16
/*    */     //   686: invokevirtual hz : ()Lf/ZK0;
/*    */     //   689: iload_1
/*    */     //   690: invokevirtual eP : (B)Z
/*    */     //   693: ifne -> 705
/*    */     //   696: aload #7
/*    */     //   698: iconst_1
/*    */     //   699: putfield eF : Z
/*    */     //   702: goto -> 707
/*    */     //   705: iconst_0
/*    */     //   706: istore_3
/*    */     //   707: aload #16
/*    */     //   709: ifnull -> 1243
/*    */     //   712: aload #7
/*    */     //   714: aload #13
/*    */     //   716: aload #7
/*    */     //   718: getfield J4 : Z
/*    */     //   721: istore #17
/*    */     //   723: aload #16
/*    */     //   725: iload_1
/*    */     //   726: iload_2
/*    */     //   727: iload_3
/*    */     //   728: iload #17
/*    */     //   730: invokevirtual Dx0 : (Lf/xr0;Lf/xr0;BZZZ)Z
/*    */     //   733: ifne -> 1243
/*    */     //   736: aload #16
/*    */     //   738: invokevirtual hz : ()Lf/ZK0;
/*    */     //   741: iload_1
/*    */     //   742: invokevirtual eP : (B)Z
/*    */     //   745: ifeq -> 863
/*    */     //   748: iload_1
/*    */     //   749: aload #7
/*    */     //   751: iconst_1
/*    */     //   752: putfield J4 : Z
/*    */     //   755: iconst_0
/*    */     //   756: istore_3
/*    */     //   757: tableswitch default -> 788, 0 -> 821, 1 -> 811, 2 -> 801, 3 -> 791
/*    */     //   788: goto -> 828
/*    */     //   791: iload #14
/*    */     //   793: iconst_1
/*    */     //   794: iadd
/*    */     //   795: i2s
/*    */     //   796: istore #14
/*    */     //   798: goto -> 828
/*    */     //   801: iload #14
/*    */     //   803: iconst_1
/*    */     //   804: isub
/*    */     //   805: i2s
/*    */     //   806: istore #14
/*    */     //   808: goto -> 828
/*    */     //   811: iload #15
/*    */     //   813: iconst_1
/*    */     //   814: isub
/*    */     //   815: i2s
/*    */     //   816: istore #15
/*    */     //   818: goto -> 828
/*    */     //   821: iload #15
/*    */     //   823: iconst_1
/*    */     //   824: iadd
/*    */     //   825: i2s
/*    */     //   826: istore #15
/*    */     //   828: aload #16
/*    */     //   830: invokevirtual Y00 : ()Z
/*    */     //   833: ifeq -> 847
/*    */     //   836: aload #16
/*    */     //   838: iload_1
/*    */     //   839: invokevirtual Cx : (B)Lf/xr0;
/*    */     //   842: astore #16
/*    */     //   844: goto -> 707
/*    */     //   847: aload #12
/*    */     //   849: iload #14
/*    */     //   851: iload #15
/*    */     //   853: iload #10
/*    */     //   855: invokevirtual v50 : (III)Lf/xr0;
/*    */     //   858: astore #16
/*    */     //   860: goto -> 707
/*    */     //   863: getstatic f/km.a3 : Lf/vh0;
/*    */     //   866: aload #7
/*    */     //   868: getfield OF0 : Lf/tc;
/*    */     //   871: getfield HW : Lf/G5;
/*    */     //   874: getfield Qf0 : B
/*    */     //   877: aload #16
/*    */     //   879: invokevirtual bk : (BLf/xr0;)Z
/*    */     //   882: ifne -> 951
/*    */     //   885: aload #13
/*    */     //   887: iload_2
/*    */     //   888: iload_3
/*    */     //   889: invokestatic ZB0 : (ZZ)B
/*    */     //   892: istore #8
/*    */     //   894: ifnull -> 920
/*    */     //   897: aload #13
/*    */     //   899: dup
/*    */     //   900: aload #7
/*    */     //   902: getfield OF0 : Lf/tc;
/*    */     //   905: iload_1
/*    */     //   906: iload #8
/*    */     //   908: invokevirtual Hc0 : (Lf/xr0;Lf/tc;BB)Z
/*    */     //   911: ifeq -> 920
/*    */     //   914: iconst_1
/*    */     //   915: istore #8
/*    */     //   917: goto -> 943
/*    */     //   920: aload #16
/*    */     //   922: dup
/*    */     //   923: aload #7
/*    */     //   925: getfield OF0 : Lf/tc;
/*    */     //   928: iload_1
/*    */     //   929: iload #8
/*    */     //   931: invokevirtual jd0 : (Lf/xr0;Lf/tc;BB)Z
/*    */     //   934: ifeq -> 940
/*    */     //   937: goto -> 914
/*    */     //   940: iconst_0
/*    */     //   941: istore #8
/*    */     //   943: iload #8
/*    */     //   945: ifeq -> 951
/*    */     //   948: goto -> 1333
/*    */     //   951: aload #7
/*    */     //   953: dup
/*    */     //   954: dup2
/*    */     //   955: getfield OF0 : Lf/tc;
/*    */     //   958: iload_2
/*    */     //   959: putfield dh : Z
/*    */     //   962: lconst_0
/*    */     //   963: invokevirtual j10 : (J)V
/*    */     //   966: invokevirtual Q80 : ()V
/*    */     //   969: getfield OF0 : Lf/tc;
/*    */     //   972: getfield HW : Lf/G5;
/*    */     //   975: dup
/*    */     //   976: astore #8
/*    */     //   978: iload_1
/*    */     //   979: putfield g50 : B
/*    */     //   982: getstatic f/km.a3 : Lf/vh0;
/*    */     //   985: aload #8
/*    */     //   987: getfield Qf0 : B
/*    */     //   990: aload #16
/*    */     //   992: invokevirtual bk : (BLf/xr0;)Z
/*    */     //   995: ifeq -> 1186
/*    */     //   998: getstatic f/km.a3 : Lf/vh0;
/*    */     //   1001: aload #7
/*    */     //   1003: getfield OF0 : Lf/tc;
/*    */     //   1006: getfield HW : Lf/G5;
/*    */     //   1009: getfield Qf0 : B
/*    */     //   1012: istore #8
/*    */     //   1014: getfield KO : Ljava/util/concurrent/ConcurrentHashMap;
/*    */     //   1017: invokevirtual values : ()Ljava/util/Collection;
/*    */     //   1020: invokeinterface iterator : ()Ljava/util/Iterator;
/*    */     //   1025: astore #9
/*    */     //   1027: aload #9
/*    */     //   1029: invokeinterface hasNext : ()Z
/*    */     //   1034: ifeq -> 1078
/*    */     //   1037: aload #9
/*    */     //   1039: invokeinterface next : ()Ljava/lang/Object;
/*    */     //   1044: checkcast f/tc
/*    */     //   1047: dup
/*    */     //   1048: astore #10
/*    */     //   1050: invokevirtual zl : ()Z
/*    */     //   1053: ifeq -> 1027
/*    */     //   1056: aload #10
/*    */     //   1058: iload #8
/*    */     //   1060: aload #16
/*    */     //   1062: invokevirtual jC : (BLf/xr0;)Z
/*    */     //   1065: ifeq -> 1027
/*    */     //   1068: aload #10
/*    */     //   1070: checkcast f/Kr0
/*    */     //   1073: astore #8
/*    */     //   1075: goto -> 1081
/*    */     //   1078: aconst_null
/*    */     //   1079: astore #8
/*    */     //   1081: aload #8
/*    */     //   1083: ifnull -> 1130
/*    */     //   1086: getstatic f/G00.Av0 : Lf/G00;
/*    */     //   1089: aload #8
/*    */     //   1091: dup
/*    */     //   1092: getfield hG0 : B
/*    */     //   1095: istore #8
/*    */     //   1097: getfield zH0 : S
/*    */     //   1100: iload #8
/*    */     //   1102: swap
/*    */     //   1103: iconst_0
/*    */     //   1104: invokevirtual Cx0 : (BIZ)Lf/LJ;
/*    */     //   1107: getfield YB0 : B
/*    */     //   1110: ifeq -> 1119
/*    */     //   1113: iconst_1
/*    */     //   1114: istore #8
/*    */     //   1116: goto -> 1122
/*    */     //   1119: iconst_0
/*    */     //   1120: istore #8
/*    */     //   1122: iload #8
/*    */     //   1124: ifeq -> 1130
/*    */     //   1127: goto -> 1239
/*    */     //   1130: aload #16
/*    */     //   1132: invokevirtual hz : ()Lf/ZK0;
/*    */     //   1135: aload #7
/*    */     //   1137: getfield OF0 : Lf/tc;
/*    */     //   1140: iload_1
/*    */     //   1141: invokevirtual uH0 : (Lf/tc;B)Z
/*    */     //   1144: ifeq -> 1333
/*    */     //   1147: getstatic f/zm0.u20 : J
/*    */     //   1150: aload #7
/*    */     //   1152: getfield YJ : J
/*    */     //   1155: lsub
/*    */     //   1156: ldc2_w 500
/*    */     //   1159: lcmp
/*    */     //   1160: ifle -> 1333
/*    */     //   1163: aload #7
/*    */     //   1165: getstatic f/km.pm0 : Lf/VD0;
/*    */     //   1168: iconst_1
/*    */     //   1169: iconst_2
/*    */     //   1170: sipush #1370
/*    */     //   1173: fconst_0
/*    */     //   1174: invokevirtual bA0 : (ZBSF)V
/*    */     //   1177: getstatic f/zm0.u20 : J
/*    */     //   1180: putfield YJ : J
/*    */     //   1183: goto -> 1333
/*    */     //   1186: aload #16
/*    */     //   1188: invokevirtual hz : ()Lf/ZK0;
/*    */     //   1191: aload #7
/*    */     //   1193: getfield OF0 : Lf/tc;
/*    */     //   1196: iload_1
/*    */     //   1197: invokevirtual uH0 : (Lf/tc;B)Z
/*    */     //   1200: ifeq -> 1239
/*    */     //   1203: getstatic f/zm0.u20 : J
/*    */     //   1206: aload #7
/*    */     //   1208: getfield YJ : J
/*    */     //   1211: lsub
/*    */     //   1212: ldc2_w 500
/*    */     //   1215: lcmp
/*    */     //   1216: ifle -> 1239
/*    */     //   1219: aload #7
/*    */     //   1221: getstatic f/km.pm0 : Lf/VD0;
/*    */     //   1224: iconst_1
/*    */     //   1225: iconst_2
/*    */     //   1226: sipush #1370
/*    */     //   1229: fconst_0
/*    */     //   1230: invokevirtual bA0 : (ZBSF)V
/*    */     //   1233: getstatic f/zm0.u20 : J
/*    */     //   1236: putfield YJ : J
/*    */     //   1239: iconst_1
/*    */     //   1240: goto -> 2133
/*    */     //   1243: iload_2
/*    */     //   1244: ifeq -> 1265
/*    */     //   1247: aload #16
/*    */     //   1249: ifnull -> 1265
/*    */     //   1252: aload #16
/*    */     //   1254: invokevirtual hz : ()Lf/ZK0;
/*    */     //   1257: invokevirtual DD : ()Z
/*    */     //   1260: ifne -> 1265
/*    */     //   1263: iconst_0
/*    */     //   1264: istore_2
/*    */     //   1265: aload #13
/*    */     //   1267: iload_2
/*    */     //   1268: iload_3
/*    */     //   1269: invokestatic ZB0 : (ZZ)B
/*    */     //   1272: istore #10
/*    */     //   1274: ifnull -> 1300
/*    */     //   1277: aload #13
/*    */     //   1279: dup
/*    */     //   1280: aload #7
/*    */     //   1282: getfield OF0 : Lf/tc;
/*    */     //   1285: iload_1
/*    */     //   1286: iload #10
/*    */     //   1288: invokevirtual Hc0 : (Lf/xr0;Lf/tc;BB)Z
/*    */     //   1291: ifeq -> 1300
/*    */     //   1294: iconst_1
/*    */     //   1295: istore #12
/*    */     //   1297: goto -> 1328
/*    */     //   1300: aload #16
/*    */     //   1302: ifnull -> 1325
/*    */     //   1305: aload #16
/*    */     //   1307: dup
/*    */     //   1308: aload #7
/*    */     //   1310: getfield OF0 : Lf/tc;
/*    */     //   1313: iload_1
/*    */     //   1314: iload #10
/*    */     //   1316: invokevirtual jd0 : (Lf/xr0;Lf/tc;BB)Z
/*    */     //   1319: ifeq -> 1325
/*    */     //   1322: goto -> 1294
/*    */     //   1325: iconst_0
/*    */     //   1326: istore #12
/*    */     //   1328: iload #12
/*    */     //   1330: ifeq -> 1337
/*    */     //   1333: iconst_0
/*    */     //   1334: goto -> 2133
/*    */     //   1337: aload #16
/*    */     //   1339: aload #7
/*    */     //   1341: dup
/*    */     //   1342: getfield OF0 : Lf/tc;
/*    */     //   1345: iload_2
/*    */     //   1346: putfield dh : Z
/*    */     //   1349: lconst_0
/*    */     //   1350: invokevirtual j10 : (J)V
/*    */     //   1353: ifnonnull -> 1401
/*    */     //   1356: getstatic f/zm0.u20 : J
/*    */     //   1359: aload #7
/*    */     //   1361: getfield YJ : J
/*    */     //   1364: lsub
/*    */     //   1365: ldc2_w 500
/*    */     //   1368: lcmp
/*    */     //   1369: ifle -> 1392
/*    */     //   1372: aload #7
/*    */     //   1374: getstatic f/km.pm0 : Lf/VD0;
/*    */     //   1377: iconst_1
/*    */     //   1378: iconst_2
/*    */     //   1379: sipush #1370
/*    */     //   1382: fconst_0
/*    */     //   1383: invokevirtual bA0 : (ZBSF)V
/*    */     //   1386: getstatic f/zm0.u20 : J
/*    */     //   1389: putfield YJ : J
/*    */     //   1392: aload #7
/*    */     //   1394: invokevirtual Q80 : ()V
/*    */     //   1397: iconst_0
/*    */     //   1398: goto -> 2133
/*    */     //   1401: aload #13
/*    */     //   1403: iload #9
/*    */     //   1405: aload #16
/*    */     //   1407: iload #8
/*    */     //   1409: aload #16
/*    */     //   1411: invokevirtual Ka : ()S
/*    */     //   1414: isub
/*    */     //   1415: invokestatic abs : (I)I
/*    */     //   1418: istore #12
/*    */     //   1420: invokevirtual hA0 : ()S
/*    */     //   1423: isub
/*    */     //   1424: invokestatic abs : (I)I
/*    */     //   1427: istore #17
/*    */     //   1429: ifnull -> 1479
/*    */     //   1432: aload #13
/*    */     //   1434: invokevirtual Y00 : ()Z
/*    */     //   1437: ifeq -> 1479
/*    */     //   1440: aload #7
/*    */     //   1442: dup
/*    */     //   1443: getfield aA0 : Lf/eo;
/*    */     //   1446: aload #13
/*    */     //   1448: invokevirtual j5 : ()Lf/eo;
/*    */     //   1451: invokevirtual JL : (Lf/eo;)Lf/eo;
/*    */     //   1454: pop
/*    */     //   1455: getfield aA0 : Lf/eo;
/*    */     //   1458: dup
/*    */     //   1459: dup2
/*    */     //   1460: getfield y : F
/*    */     //   1463: fstore #8
/*    */     //   1465: getfield z : F
/*    */     //   1468: putfield y : F
/*    */     //   1471: fload #8
/*    */     //   1473: putfield z : F
/*    */     //   1476: goto -> 1590
/*    */     //   1479: aload #13
/*    */     //   1481: instanceof f/il
/*    */     //   1484: ifeq -> 1515
/*    */     //   1487: aload #7
/*    */     //   1489: getfield aA0 : Lf/eo;
/*    */     //   1492: iload #8
/*    */     //   1494: i2f
/*    */     //   1495: ldc_w 0.5
/*    */     //   1498: fadd
/*    */     //   1499: iload #9
/*    */     //   1501: i2f
/*    */     //   1502: ldc_w 0.5
/*    */     //   1505: fadd
/*    */     //   1506: fload #11
/*    */     //   1508: invokevirtual TG0 : (FFF)Lf/eo;
/*    */     //   1511: pop
/*    */     //   1512: goto -> 1590
/*    */     //   1515: iload #12
/*    */     //   1517: iconst_2
/*    */     //   1518: if_icmpgt -> 1555
/*    */     //   1521: iload #17
/*    */     //   1523: iconst_2
/*    */     //   1524: if_icmple -> 1530
/*    */     //   1527: goto -> 1555
/*    */     //   1530: aload #7
/*    */     //   1532: getfield aA0 : Lf/eo;
/*    */     //   1535: iload #9
/*    */     //   1537: iload #8
/*    */     //   1539: i2f
/*    */     //   1540: fstore #8
/*    */     //   1542: i2f
/*    */     //   1543: fload #8
/*    */     //   1545: swap
/*    */     //   1546: fload #11
/*    */     //   1548: invokevirtual TG0 : (FFF)Lf/eo;
/*    */     //   1551: pop
/*    */     //   1552: goto -> 1590
/*    */     //   1555: aload #7
/*    */     //   1557: getfield aA0 : Lf/eo;
/*    */     //   1560: aload #16
/*    */     //   1562: invokevirtual Ka : ()S
/*    */     //   1565: iload #14
/*    */     //   1567: iload #8
/*    */     //   1569: isub
/*    */     //   1570: isub
/*    */     //   1571: i2f
/*    */     //   1572: aload #16
/*    */     //   1574: invokevirtual hA0 : ()S
/*    */     //   1577: iload #15
/*    */     //   1579: iload #9
/*    */     //   1581: isub
/*    */     //   1582: isub
/*    */     //   1583: i2f
/*    */     //   1584: fload #11
/*    */     //   1586: invokevirtual TG0 : (FFF)Lf/eo;
/*    */     //   1589: pop
/*    */     //   1590: aload #16
/*    */     //   1592: aload #7
/*    */     //   1594: dup
/*    */     //   1595: dup
/*    */     //   1596: iconst_1
/*    */     //   1597: putfield n3 : Z
/*    */     //   1600: getfield OF0 : Lf/tc;
/*    */     //   1603: aload #13
/*    */     //   1605: invokevirtual d1 : (Lf/tc;Lf/xr0;)V
/*    */     //   1608: invokevirtual Q4 : ()Lf/KI;
/*    */     //   1611: invokevirtual o50 : ()Z
/*    */     //   1614: ifeq -> 1737
/*    */     //   1617: aload #16
/*    */     //   1619: invokevirtual Q4 : ()Lf/KI;
/*    */     //   1622: getfield E10 : B
/*    */     //   1625: invokestatic sz0 : (B)Z
/*    */     //   1628: ifeq -> 1737
/*    */     //   1631: aload #7
/*    */     //   1633: getfield OF0 : Lf/tc;
/*    */     //   1636: invokevirtual Pf : ()Z
/*    */     //   1639: ifeq -> 1737
/*    */     //   1642: aload #16
/*    */     //   1644: invokevirtual Q4 : ()Lf/KI;
/*    */     //   1647: checkcast f/Cy
/*    */     //   1650: dup
/*    */     //   1651: astore #8
/*    */     //   1653: aload #16
/*    */     //   1655: dup
/*    */     //   1656: invokevirtual Ka : ()S
/*    */     //   1659: istore #9
/*    */     //   1661: invokevirtual hA0 : ()S
/*    */     //   1664: istore #11
/*    */     //   1666: getfield et0 : I
/*    */     //   1669: dup
/*    */     //   1670: istore #12
/*    */     //   1672: iconst_1
/*    */     //   1673: if_icmplt -> 1716
/*    */     //   1676: aload #8
/*    */     //   1678: getfield ey : I
/*    */     //   1681: dup
/*    */     //   1682: istore #14
/*    */     //   1684: iconst_1
/*    */     //   1685: if_icmpge -> 1691
/*    */     //   1688: goto -> 1716
/*    */     //   1691: aload #8
/*    */     //   1693: iload #11
/*    */     //   1695: iload #9
/*    */     //   1697: iload #12
/*    */     //   1699: idiv
/*    */     //   1700: istore #9
/*    */     //   1702: iload #14
/*    */     //   1704: idiv
/*    */     //   1705: iload #9
/*    */     //   1707: swap
/*    */     //   1708: invokevirtual XJ0 : (II)Lf/Ws0;
/*    */     //   1711: astore #9
/*    */     //   1713: goto -> 1725
/*    */     //   1716: aload #8
/*    */     //   1718: iconst_0
/*    */     //   1719: iconst_0
/*    */     //   1720: invokevirtual XJ0 : (II)Lf/Ws0;
/*    */     //   1723: astore #9
/*    */     //   1725: aload #9
/*    */     //   1727: ifnull -> 1737
/*    */     //   1730: aload #8
/*    */     //   1732: aload #9
/*    */     //   1734: invokevirtual wy0 : (Lf/Ws0;)V
/*    */     //   1737: aload #16
/*    */     //   1739: aload #7
/*    */     //   1741: getfield OF0 : Lf/tc;
/*    */     //   1744: getfield HW : Lf/G5;
/*    */     //   1747: dup
/*    */     //   1748: aload #16
/*    */     //   1750: invokevirtual Q4 : ()Lf/KI;
/*    */     //   1753: getfield cA : B
/*    */     //   1756: aload #16
/*    */     //   1758: invokevirtual Q4 : ()Lf/KI;
/*    */     //   1761: getfield VZ : B
/*    */     //   1764: istore #8
/*    */     //   1766: putfield kD0 : B
/*    */     //   1769: iload #8
/*    */     //   1771: putfield vu0 : B
/*    */     //   1774: instanceof f/il
/*    */     //   1777: ifeq -> 1827
/*    */     //   1780: aload #7
/*    */     //   1782: getfield OF0 : Lf/tc;
/*    */     //   1785: getfield HW : Lf/G5;
/*    */     //   1788: aload #16
/*    */     //   1790: dup
/*    */     //   1791: dup2
/*    */     //   1792: invokevirtual Y00 : ()Z
/*    */     //   1795: istore #8
/*    */     //   1797: invokevirtual Ka : ()S
/*    */     //   1800: istore #9
/*    */     //   1802: invokevirtual hA0 : ()S
/*    */     //   1805: istore #11
/*    */     //   1807: invokevirtual bl0 : ()B
/*    */     //   1810: istore #12
/*    */     //   1812: iload #8
/*    */     //   1814: iload #9
/*    */     //   1816: iload #11
/*    */     //   1818: iload #12
/*    */     //   1820: iload_1
/*    */     //   1821: invokevirtual Zh : (ZSSBB)V
/*    */     //   1824: goto -> 1899
/*    */     //   1827: aload #16
/*    */     //   1829: dup
/*    */     //   1830: dup2
/*    */     //   1831: aload #7
/*    */     //   1833: getfield OF0 : Lf/tc;
/*    */     //   1836: getfield HW : Lf/G5;
/*    */     //   1839: astore #8
/*    */     //   1841: invokevirtual Y00 : ()Z
/*    */     //   1844: istore #9
/*    */     //   1846: invokevirtual Ka : ()S
/*    */     //   1849: istore #11
/*    */     //   1851: invokevirtual hA0 : ()S
/*    */     //   1854: istore #12
/*    */     //   1856: invokevirtual bl0 : ()B
/*    */     //   1859: ifge -> 1878
/*    */     //   1862: aload #7
/*    */     //   1864: getfield OF0 : Lf/tc;
/*    */     //   1867: getfield HW : Lf/G5;
/*    */     //   1870: getfield Qf0 : B
/*    */     //   1873: istore #14
/*    */     //   1875: goto -> 1885
/*    */     //   1878: aload #16
/*    */     //   1880: invokevirtual bl0 : ()B
/*    */     //   1883: istore #14
/*    */     //   1885: aload #8
/*    */     //   1887: iload #9
/*    */     //   1889: iload #11
/*    */     //   1891: iload #12
/*    */     //   1893: iload #14
/*    */     //   1895: iload_1
/*    */     //   1896: invokevirtual Zh : (ZSSBB)V
/*    */     //   1899: aload #13
/*    */     //   1901: aload #7
/*    */     //   1903: dup
/*    */     //   1904: getstatic f/zm0.u20 : J
/*    */     //   1907: putfield xc : J
/*    */     //   1910: invokevirtual Q80 : ()V
/*    */     //   1913: ifnull -> 1972
/*    */     //   1916: aload #13
/*    */     //   1918: invokevirtual hz : ()Lf/ZK0;
/*    */     //   1921: aload #13
/*    */     //   1923: aload #7
/*    */     //   1925: getfield OF0 : Lf/tc;
/*    */     //   1928: getfield HW : Lf/G5;
/*    */     //   1931: getfield g50 : B
/*    */     //   1934: pop
/*    */     //   1935: aload #16
/*    */     //   1937: invokevirtual VP : (Lf/xr0;Lf/xr0;)I
/*    */     //   1940: ifle -> 1972
/*    */     //   1943: aload #7
/*    */     //   1945: aload #13
/*    */     //   1947: invokevirtual hz : ()Lf/ZK0;
/*    */     //   1950: aload #13
/*    */     //   1952: aload #7
/*    */     //   1954: getfield OF0 : Lf/tc;
/*    */     //   1957: getfield HW : Lf/G5;
/*    */     //   1960: getfield g50 : B
/*    */     //   1963: pop
/*    */     //   1964: aload #16
/*    */     //   1966: invokevirtual VP : (Lf/xr0;Lf/xr0;)I
/*    */     //   1969: putfield tD0 : I
/*    */     //   1972: aload #7
/*    */     //   1974: getfield OF0 : Lf/tc;
/*    */     //   1977: invokevirtual Pf : ()Z
/*    */     //   1980: ifeq -> 2063
/*    */     //   1983: aload #7
/*    */     //   1985: getstatic f/km.u4 : Lf/R8;
/*    */     //   1988: invokevirtual DK0 : ()V
/*    */     //   1991: getfield OF0 : Lf/tc;
/*    */     //   1994: getfield HW : Lf/G5;
/*    */     //   1997: astore #8
/*    */     //   1999: getstatic f/km.u4 : Lf/R8;
/*    */     //   2002: getfield Lz : Lf/fH0;
/*    */     //   2005: dup
/*    */     //   2006: dup
/*    */     //   2007: dup2
/*    */     //   2008: aload #8
/*    */     //   2010: dup
/*    */     //   2011: dup
/*    */     //   2012: dup2
/*    */     //   2013: getfield FB : B
/*    */     //   2016: istore #8
/*    */     //   2018: getfield kD0 : B
/*    */     //   2021: istore #9
/*    */     //   2023: getfield vu0 : B
/*    */     //   2026: istore #11
/*    */     //   2028: getfield mm : S
/*    */     //   2031: istore #12
/*    */     //   2033: getfield Yu0 : S
/*    */     //   2036: istore #14
/*    */     //   2038: iload #8
/*    */     //   2040: putfield bv : B
/*    */     //   2043: iload #9
/*    */     //   2045: putfield GL0 : B
/*    */     //   2048: iload #11
/*    */     //   2050: putfield oI : B
/*    */     //   2053: iload #12
/*    */     //   2055: putfield WM : S
/*    */     //   2058: iload #14
/*    */     //   2060: putfield bg0 : S
/*    */     //   2063: aload #13
/*    */     //   2065: aload #16
/*    */     //   2067: if_acmpeq -> 2117
/*    */     //   2070: aload #13
/*    */     //   2072: aload #16
/*    */     //   2074: invokevirtual hz : ()Lf/ZK0;
/*    */     //   2077: aload #16
/*    */     //   2079: aload #7
/*    */     //   2081: getfield OF0 : Lf/tc;
/*    */     //   2084: aload #13
/*    */     //   2086: swap
/*    */     //   2087: iload #10
/*    */     //   2089: invokevirtual com4 : (Lf/xr0;Lf/xr0;Lf/tc;B)Z
/*    */     //   2092: pop
/*    */     //   2093: ifnull -> 2117
/*    */     //   2096: aload #7
/*    */     //   2098: aload #13
/*    */     //   2100: dup
/*    */     //   2101: invokevirtual hz : ()Lf/ZK0;
/*    */     //   2104: aload #7
/*    */     //   2106: getfield OF0 : Lf/tc;
/*    */     //   2109: aload #13
/*    */     //   2111: invokevirtual Uk0 : (Lf/tc;Lf/xr0;)V
/*    */     //   2114: invokevirtual Bg : (Lf/xr0;)V
/*    */     //   2117: aload #7
/*    */     //   2119: getfield OF0 : Lf/tc;
/*    */     //   2122: getfield HW : Lf/G5;
/*    */     //   2125: dup
/*    */     //   2126: getfield g50 : B
/*    */     //   2129: putfield ZJ0 : B
/*    */     //   2132: iconst_1
/*    */     //   2133: ifeq -> 2162
/*    */     //   2136: iload_1
/*    */     //   2137: iconst_m1
/*    */     //   2138: if_icmpeq -> 2192
/*    */     //   2141: aload_0
/*    */     //   2142: getfield e20 : Lf/c4;
/*    */     //   2145: new f/t
/*    */     //   2148: dup
/*    */     //   2149: aload #5
/*    */     //   2151: iload_2
/*    */     //   2152: iload_3
/*    */     //   2153: invokespecial <init> : (Lf/G5;ZZ)V
/*    */     //   2156: invokevirtual W3 : (Lf/Bi;)V
/*    */     //   2159: goto -> 2192
/*    */     //   2162: iload #6
/*    */     //   2164: aload #4
/*    */     //   2166: getfield HW : Lf/G5;
/*    */     //   2169: getfield g50 : B
/*    */     //   2172: dup
/*    */     //   2173: istore_1
/*    */     //   2174: if_icmpeq -> 2192
/*    */     //   2177: aload_0
/*    */     //   2178: getfield e20 : Lf/c4;
/*    */     //   2181: new f/hA
/*    */     //   2184: dup
/*    */     //   2185: iload_1
/*    */     //   2186: invokespecial <init> : (B)V
/*    */     //   2189: invokevirtual W3 : (Lf/Bi;)V
/*    */     //   2192: return
/*    */     // Line number table:
/*    */     //   Java source line number -> byte code offset
/*    */     //   #1	-> 30
/*    */     //   #2	-> 36
/*    */     //   #3	-> 39
/*    */     //   #4	-> 53
/*    */     //   #5	-> 59
/*    */     //   #6	-> 68
/*    */     //   #7	-> 73
/*    */     //   #8	-> 100
/*    */     //   #9	-> 103
/*    */     //   #10	-> 106
/*    */     //   #11	-> 116
/*    */     //   #12	-> 120
/*    */     //   #13	-> 157
/*    */     //   #14	-> 160
/*    */     //   #15	-> 163
/*    */     //   #16	-> 166
/*    */     //   #17	-> 178
/*    */     //   #18	-> 183
/*    */     //   #19	-> 189
/*    */     //   #20	-> 200
/*    */     //   #21	-> 212
/*    */     //   #22	-> 222
/*    */     //   #23	-> 230
/*    */     //   #24	-> 240
/*    */     //   #25	-> 245
/*    */     //   #26	-> 250
/*    */     //   #27	-> 255
/*    */     //   #28	-> 260
/*    */     //   #29	-> 273
/*    */     //   #30	-> 278
/*    */     //   #31	-> 283
/*    */     //   #32	-> 288
/*    */     //   #33	-> 299
/*    */     //   #34	-> 317
/*    */     //   #35	-> 320
/*    */     //   #36	-> 348
/*    */     //   #37	-> 354
/*    */     //   #38	-> 364
/*    */     //   #39	-> 479
/*    */     //   #40	-> 542
/*    */     //   #41	-> 550
/*    */     //   #42	-> 625
/*    */     //   #43	-> 628
/*    */     //   #44	-> 632
/*    */     //   #45	-> 635
/*    */     //   #46	-> 871
/*    */     //   #47	-> 874
/*    */     //   #48	-> 879
/*    */     //   #49	-> 902
/*    */     //   #50	-> 955
/*    */     //   #51	-> 959
/*    */     //   #52	-> 963
/*    */     //   #53	-> 966
/*    */     //   #54	-> 972
/*    */     //   #55	-> 979
/*    */     //   #56	-> 982
/*    */     //   #57	-> 987
/*    */     //   #58	-> 992
/*    */     //   #59	-> 1006
/*    */     //   #60	-> 1009
/*    */     //   #61	-> 1014
/*    */     //   #62	-> 1017
/*    */     //   #63	-> 1086
/*    */     //   #64	-> 1092
/*    */     //   #65	-> 1104
/*    */     //   #66	-> 1107
/*    */     //   #67	-> 1132
/*    */     //   #68	-> 1147
/*    */     //   #69	-> 1152
/*    */     //   #70	-> 1174
/*    */     //   #71	-> 1177
/*    */     //   #72	-> 1180
/*    */     //   #73	-> 1203
/*    */     //   #74	-> 1208
/*    */     //   #75	-> 1230
/*    */     //   #76	-> 1233
/*    */     //   #77	-> 1236
/*    */     //   #78	-> 1282
/*    */     //   #79	-> 1342
/*    */     //   #80	-> 1346
/*    */     //   #81	-> 1350
/*    */     //   #82	-> 1356
/*    */     //   #83	-> 1361
/*    */     //   #84	-> 1383
/*    */     //   #85	-> 1386
/*    */     //   #86	-> 1389
/*    */     //   #87	-> 1622
/*    */     //   #88	-> 1625
/*    */     //   #89	-> 1666
/*    */     //   #90	-> 1678
/*    */     //   #91	-> 1734
/*    */     //   #92	-> 1744
/*    */     //   #93	-> 1750
/*    */     //   #94	-> 1753
/*    */     //   #95	-> 1758
/*    */     //   #96	-> 1761
/*    */     //   #97	-> 1766
/*    */     //   #98	-> 1771
/*    */     //   #99	-> 1774
/*    */     //   #100	-> 1785
/*    */     //   #101	-> 1792
/*    */     //   #102	-> 1836
/*    */     //   #103	-> 1841
/*    */     //   #104	-> 1867
/*    */     //   #105	-> 1870
/*    */     //   #106	-> 1880
/*    */     //   #107	-> 1904
/*    */     //   #108	-> 1907
/*    */     //   #109	-> 1928
/*    */     //   #110	-> 1931
/*    */     //   #111	-> 1937
/*    */     //   #112	-> 1957
/*    */     //   #113	-> 1960
/*    */     //   #114	-> 1966
/*    */     //   #115	-> 1994
/*    */     //   #116	-> 1999
/*    */     //   #117	-> 2002
/*    */     //   #118	-> 2013
/*    */     //   #119	-> 2018
/*    */     //   #120	-> 2023
/*    */     //   #121	-> 2028
/*    */     //   #122	-> 2033
/*    */     //   #123	-> 2040
/*    */     //   #124	-> 2045
/*    */     //   #125	-> 2074
/*    */     //   #126	-> 2122
/*    */     //   #127	-> 2126
/*    */     //   #128	-> 2129
/*    */     //   #129	-> 2142
/*    */     //   #130	-> 2166
/*    */     //   #131	-> 2169
/*    */     //   #132	-> 2178
/*    */   }
/*    */   
/*    */   public final int dm0() {
/*    */     c4 c41;
/*    */     return ((c41 = this.e20) == null) ? 6 : this.VL0;
/*    */   }
/*    */   
/*    */   static {
/*    */     short[] arrayOfShort1;
/*    */     (arrayOfShort1 = new short[1])[0] = 360;
/*    */     short[][] arrayOfShort;
/*    */     (arrayOfShort = new short[5][])[0] = arrayOfShort1;
/*    */     (arrayOfShort1 = new short[2])[0] = 259;
/*    */     (new short[2])[1] = 272;
/*    */     (new short[5][])[1] = arrayOfShort1;
/*    */     (arrayOfShort1 = new short[1])[0] = 5450;
/*    */     (new short[5][])[2] = arrayOfShort1;
/*    */     (arrayOfShort1 = new short[1])[0] = 8450;
/*    */     (new short[5][])[3] = arrayOfShort1;
/*    */     (arrayOfShort1 = new short[1])[0] = 9450;
/*    */     (new short[5][])[4] = arrayOfShort1;
/*    */     (new short[8][][])[0] = arrayOfShort;
/*    */     (arrayOfShort1 = new short[1])[0] = 361;
/*    */     (arrayOfShort = new short[5][])[0] = arrayOfShort1;
/*    */     (arrayOfShort1 = new short[1])[0] = 361;
/*    */     (new short[5][])[1] = arrayOfShort1;
/*    */     (arrayOfShort1 = new short[1])[0] = 5442;
/*    */     (new short[5][])[2] = arrayOfShort1;
/*    */     (arrayOfShort1 = new short[1])[0] = 8442;
/*    */     (new short[5][])[3] = arrayOfShort1;
/*    */     (arrayOfShort1 = new short[1])[0] = 9442;
/*    */     (new short[5][])[4] = arrayOfShort1;
/*    */     (new short[8][][])[1] = arrayOfShort;
/*    */     (arrayOfShort1 = new short[1])[0] = 264;
/*    */     (arrayOfShort = new short[5][])[0] = arrayOfShort1;
/*    */     (arrayOfShort1 = new short[1])[0] = 264;
/*    */     (new short[5][])[1] = arrayOfShort1;
/*    */     (arrayOfShort1 = new short[1])[0] = 5447;
/*    */     (new short[5][])[2] = arrayOfShort1;
/*    */     (arrayOfShort1 = new short[1])[0] = 8447;
/*    */     (new short[5][])[3] = arrayOfShort1;
/*    */     (arrayOfShort1 = new short[1])[0] = 9447;
/*    */     (new short[5][])[4] = arrayOfShort1;
/*    */     (new short[8][][])[2] = arrayOfShort;
/*    */     (arrayOfShort1 = new short[1])[0] = 263;
/*    */     (arrayOfShort = new short[5][])[0] = arrayOfShort1;
/*    */     (arrayOfShort1 = new short[1])[0] = 263;
/*    */     (new short[5][])[1] = arrayOfShort1;
/*    */     (new short[5][])[2] = new short[0];
/*    */     (arrayOfShort1 = new short[1])[0] = 8446;
/*    */     (new short[5][])[3] = arrayOfShort1;
/*    */     (arrayOfShort1 = new short[1])[0] = 9446;
/*    */     (new short[5][])[4] = arrayOfShort1;
/*    */     (new short[8][][])[3] = arrayOfShort;
/*    */     (arrayOfShort1 = new short[1])[0] = 262;
/*    */     (arrayOfShort = new short[5][])[0] = arrayOfShort1;
/*    */     (arrayOfShort1 = new short[1])[0] = 262;
/*    */     (new short[5][])[1] = arrayOfShort1;
/*    */     (new short[5][])[2] = new short[0];
/*    */     (arrayOfShort1 = new short[1])[0] = 8445;
/*    */     (new short[5][])[3] = arrayOfShort1;
/*    */     (arrayOfShort1 = new short[1])[0] = 9445;
/*    */     (new short[5][])[4] = arrayOfShort1;
/*    */     (new short[8][][])[4] = arrayOfShort;
/*    */     (arrayOfShort1 = new short[1])[0] = 268;
/*    */     (arrayOfShort = new short[5][])[0] = arrayOfShort1;
/*    */     (arrayOfShort1 = new short[1])[0] = 268;
/*    */     (new short[5][])[1] = arrayOfShort1;
/*    */     (arrayOfShort1 = new short[1])[0] = 5448;
/*    */     (new short[5][])[2] = arrayOfShort1;
/*    */     (arrayOfShort1 = new short[1])[0] = 8448;
/*    */     (new short[5][])[3] = arrayOfShort1;
/*    */     (arrayOfShort1 = new short[1])[0] = 9448;
/*    */     (new short[5][])[4] = arrayOfShort1;
/*    */     (new short[8][][])[5] = arrayOfShort;
/*    */     (arrayOfShort1 = new short[1])[0] = 261;
/*    */     (arrayOfShort = new short[5][])[0] = arrayOfShort1;
/*    */     (arrayOfShort1 = new short[1])[0] = 261;
/*    */     (new short[5][])[1] = arrayOfShort1;
/*    */     (arrayOfShort1 = new short[1])[0] = 5471;
/*    */     (new short[5][])[2] = arrayOfShort1;
/*    */     (arrayOfShort1 = new short[1])[0] = 5471;
/*    */     (new short[5][])[3] = arrayOfShort1;
/*    */     (arrayOfShort1 = new short[1])[0] = 9471;
/*    */     (new short[5][])[4] = arrayOfShort1;
/*    */     (new short[8][][])[6] = arrayOfShort;
/*    */     (arrayOfShort = new short[5][])[0] = new short[0];
/*    */     (arrayOfShort1 = new short[1])[0] = 1540;
/*    */     (new short[5][])[1] = arrayOfShort1;
/*    */     (new short[5][])[2] = new short[0];
/*    */     (new short[5][])[3] = new short[0];
/*    */     (new short[5][])[4] = new short[0];
/*    */     H70 = new short[][][] { null, null, null, null, null, null, null, arrayOfShort };
/*    */   } }


/* Location:              /Users/vnnsnnt/Documents/Codespace/JavaWorkspace/RedTrainer/src/main/java/org/trainer/client/PokeMMO.jar!/f/ro.class
 * Java compiler version: 8 (52.0)
 * JD-Core Version:       1.1.3
 */