package f;

public final class Rp implements con {
  public final void ng(Object paramObject, int paramInt, float[] paramArrayOffloat) {
    // Byte code:
    //   0: iload_2
    //   1: aload_1
    //   2: checkcast f/C30
    //   5: astore_0
    //   6: tableswitch default -> 72, 1 -> 270, 2 -> 259, 3 -> 236, 4 -> 214, 5 -> 192, 6 -> 171, 7 -> 161, 8 -> 72, 9 -> 72, 10 -> 139, 11 -> 117, 12 -> 96, 13 -> 81
    //   72: getstatic f/Rp.Q80 : Z
    //   75: ifeq -> 279
    //   78: goto -> 278
    //   81: aload_0
    //   82: dup
    //   83: aload_3
    //   84: iconst_0
    //   85: faload
    //   86: f2i
    //   87: putfield ik : I
    //   90: invokevirtual go0 : ()V
    //   93: goto -> 278
    //   96: aload_0
    //   97: dup
    //   98: aload_3
    //   99: dup
    //   100: iconst_0
    //   101: faload
    //   102: fstore_0
    //   103: iconst_1
    //   104: faload
    //   105: fstore_1
    //   106: fload_0
    //   107: putfield DC : F
    //   110: fload_1
    //   111: putfield Cz : F
    //   114: goto -> 278
    //   117: aload_0
    //   118: dup
    //   119: aload_3
    //   120: aload_0
    //   121: getfield DC : F
    //   124: fstore_0
    //   125: iconst_0
    //   126: faload
    //   127: fstore_1
    //   128: fload_0
    //   129: putfield DC : F
    //   132: fload_1
    //   133: putfield Cz : F
    //   136: goto -> 278
    //   139: aload_0
    //   140: dup
    //   141: dup
    //   142: aload_3
    //   143: iconst_0
    //   144: faload
    //   145: fstore_0
    //   146: getfield Cz : F
    //   149: fstore_1
    //   150: fload_0
    //   151: putfield DC : F
    //   154: fload_1
    //   155: putfield Cz : F
    //   158: goto -> 278
    //   161: aload_0
    //   162: aload_3
    //   163: iconst_0
    //   164: faload
    //   165: putfield Y2 : F
    //   168: goto -> 278
    //   171: aload_0
    //   172: dup
    //   173: aload_3
    //   174: dup
    //   175: iconst_0
    //   176: faload
    //   177: fstore_0
    //   178: iconst_1
    //   179: faload
    //   180: fstore_1
    //   181: fload_0
    //   182: putfield Xm0 : F
    //   185: fload_1
    //   186: putfield ad : F
    //   189: goto -> 278
    //   192: aload_0
    //   193: dup
    //   194: aload_3
    //   195: aload_0
    //   196: getfield Xm0 : F
    //   199: fstore_0
    //   200: iconst_0
    //   201: faload
    //   202: fstore_1
    //   203: fload_0
    //   204: putfield Xm0 : F
    //   207: fload_1
    //   208: putfield ad : F
    //   211: goto -> 278
    //   214: aload_0
    //   215: dup
    //   216: dup
    //   217: aload_3
    //   218: iconst_0
    //   219: faload
    //   220: fstore_0
    //   221: getfield ad : F
    //   224: fstore_1
    //   225: fload_0
    //   226: putfield Xm0 : F
    //   229: fload_1
    //   230: putfield ad : F
    //   233: goto -> 278
    //   236: aload_0
    //   237: dup
    //   238: aload_3
    //   239: dup
    //   240: iconst_0
    //   241: faload
    //   242: f2i
    //   243: istore_0
    //   244: iconst_1
    //   245: faload
    //   246: f2i
    //   247: istore_1
    //   248: iload_0
    //   249: putfield ec : I
    //   252: iload_1
    //   253: putfield hv : I
    //   256: goto -> 278
    //   259: aload_0
    //   260: aload_3
    //   261: iconst_0
    //   262: faload
    //   263: f2i
    //   264: putfield hv : I
    //   267: goto -> 278
    //   270: aload_0
    //   271: aload_3
    //   272: iconst_0
    //   273: faload
    //   274: f2i
    //   275: putfield ec : I
    //   278: return
    //   279: new java/lang/AssertionError
    //   282: dup
    //   283: invokespecial <init> : ()V
    //   286: athrow
    // Line number table:
    //   Java source line number -> byte code offset
    //   #1	-> 72
    //   #2	-> 87
    //   #3	-> 90
    //   #4	-> 101
    //   #5	-> 107
    //   #6	-> 111
    //   #7	-> 121
    //   #8	-> 126
    //   #9	-> 129
    //   #10	-> 144
    //   #11	-> 146
    //   #12	-> 151
    //   #13	-> 164
    //   #14	-> 165
    //   #15	-> 176
    //   #16	-> 182
    //   #17	-> 186
    //   #18	-> 196
    //   #19	-> 201
    //   #20	-> 204
    //   #21	-> 219
    //   #22	-> 221
    //   #23	-> 226
    //   #24	-> 241
    //   #25	-> 249
    //   #26	-> 253
    //   #27	-> 262
    //   #28	-> 264
    //   #29	-> 273
    //   #30	-> 275
    //   #31	-> 279
  }
  
  public final int Uu0(Object paramObject, int paramInt, float[] paramArrayOffloat) {
    // Byte code:
    //   0: iload_2
    //   1: aload_1
    //   2: checkcast f/C30
    //   5: astore_0
    //   6: tableswitch default -> 72, 1 -> 241, 2 -> 227, 3 -> 204, 4 -> 191, 5 -> 178, 6 -> 157, 7 -> 144, 8 -> 72, 9 -> 72, 10 -> 131, 11 -> 118, 12 -> 97, 13 -> 83
    //   72: getstatic f/Rp.Q80 : Z
    //   75: ifeq -> 254
    //   78: iconst_0
    //   79: istore_0
    //   80: goto -> 252
    //   83: aload_3
    //   84: aload_0
    //   85: getfield ik : I
    //   88: i2f
    //   89: iconst_0
    //   90: swap
    //   91: fastore
    //   92: iconst_1
    //   93: istore_0
    //   94: goto -> 252
    //   97: aload_3
    //   98: aload_0
    //   99: aload_3
    //   100: aload_0
    //   101: getfield DC : F
    //   104: iconst_0
    //   105: swap
    //   106: fastore
    //   107: getfield Cz : F
    //   110: iconst_1
    //   111: swap
    //   112: fastore
    //   113: iconst_2
    //   114: istore_0
    //   115: goto -> 252
    //   118: aload_3
    //   119: aload_0
    //   120: getfield Cz : F
    //   123: iconst_0
    //   124: swap
    //   125: fastore
    //   126: iconst_1
    //   127: istore_0
    //   128: goto -> 252
    //   131: aload_3
    //   132: aload_0
    //   133: getfield DC : F
    //   136: iconst_0
    //   137: swap
    //   138: fastore
    //   139: iconst_1
    //   140: istore_0
    //   141: goto -> 252
    //   144: aload_3
    //   145: aload_0
    //   146: getfield Y2 : F
    //   149: iconst_0
    //   150: swap
    //   151: fastore
    //   152: iconst_1
    //   153: istore_0
    //   154: goto -> 252
    //   157: aload_3
    //   158: aload_0
    //   159: aload_3
    //   160: aload_0
    //   161: getfield Xm0 : F
    //   164: iconst_0
    //   165: swap
    //   166: fastore
    //   167: getfield ad : F
    //   170: iconst_1
    //   171: swap
    //   172: fastore
    //   173: iconst_2
    //   174: istore_0
    //   175: goto -> 252
    //   178: aload_3
    //   179: aload_0
    //   180: getfield ad : F
    //   183: iconst_0
    //   184: swap
    //   185: fastore
    //   186: iconst_1
    //   187: istore_0
    //   188: goto -> 252
    //   191: aload_3
    //   192: aload_0
    //   193: getfield Xm0 : F
    //   196: iconst_0
    //   197: swap
    //   198: fastore
    //   199: iconst_1
    //   200: istore_0
    //   201: goto -> 252
    //   204: aload_3
    //   205: aload_0
    //   206: aload_3
    //   207: aload_0
    //   208: getfield ec : I
    //   211: i2f
    //   212: iconst_0
    //   213: swap
    //   214: fastore
    //   215: getfield hv : I
    //   218: i2f
    //   219: iconst_1
    //   220: swap
    //   221: fastore
    //   222: iconst_2
    //   223: istore_0
    //   224: goto -> 252
    //   227: aload_3
    //   228: aload_0
    //   229: getfield hv : I
    //   232: i2f
    //   233: iconst_0
    //   234: swap
    //   235: fastore
    //   236: iconst_1
    //   237: istore_0
    //   238: goto -> 252
    //   241: aload_3
    //   242: aload_0
    //   243: getfield ec : I
    //   246: i2f
    //   247: iconst_0
    //   248: swap
    //   249: fastore
    //   250: iconst_1
    //   251: istore_0
    //   252: iload_0
    //   253: ireturn
    //   254: new java/lang/AssertionError
    //   257: dup
    //   258: invokespecial <init> : ()V
    //   261: athrow
    // Line number table:
    //   Java source line number -> byte code offset
    //   #1	-> 72
    //   #2	-> 85
    //   #3	-> 91
    //   #4	-> 101
    //   #5	-> 106
    //   #6	-> 107
    //   #7	-> 112
    //   #8	-> 120
    //   #9	-> 125
    //   #10	-> 133
    //   #11	-> 138
    //   #12	-> 146
    //   #13	-> 151
    //   #14	-> 161
    //   #15	-> 166
    //   #16	-> 167
    //   #17	-> 172
    //   #18	-> 180
    //   #19	-> 185
    //   #20	-> 193
    //   #21	-> 198
    //   #22	-> 208
    //   #23	-> 214
    //   #24	-> 215
    //   #25	-> 221
    //   #26	-> 229
    //   #27	-> 235
    //   #28	-> 243
    //   #29	-> 249
  }
}


/* Location:              /Users/vnnsnnt/Documents/Codespace/JavaWorkspace/RedTrainer/src/main/java/org/trainer/client/PokeMMO.jar!/f/Rp.class
 * Java compiler version: 8 (52.0)
 * JD-Core Version:       1.1.3
 */