/* 1 */ package f;public final class s00 implements Comparable { public final void V1(Y paramY) { this.ig.add(paramY); this
/*   */       
/* 3 */       .fD0 = this.fD0 + paramY.Lh.Sf0; }
/*   */ 
/*   */   
/*   */   public final LPT3 c0;
/*   */   public Y ah;
/*   */   public int fD0;
/*   */   public ArrayList ig;
/*   */   
/*   */   public s00(LPT3 paramLPT3) {
/*   */     ArrayList arrayList;
/*   */     this();
/*   */     this.ig = this;
/*   */     this.c0 = paramLPT3;
/*   */   }
/*   */   
/*   */   public final void Tn() {
/*   */     Collections.sort(this.ig, Comparator.comparing(Y::oD0));
/*   */     this.ah = this.ig.get(0);
/*   */   }
/*   */   
/*   */   public final void Au0() {
/*   */     this.fD0 = this.ig.stream().mapToInt(Y::oD0).sum();
/*   */   }
/*   */   
/*   */   public final int Qr0() {
/*   */     return this.fD0;
/*   */   }
/*   */   
/*   */   public final int compareTo(Object paramObject) {
/*   */     // Byte code:
/*   */     //   0: aload_0
/*   */     //   1: aload_1
/*   */     //   2: checkcast f/s00
/*   */     //   5: astore_1
/*   */     //   6: getfield ah : Lf/Y;
/*   */     //   9: dup
/*   */     //   10: astore_2
/*   */     //   11: getfield Bp0 : Lf/LPT3;
/*   */     //   14: getfield Y8 : Lf/Hu0;
/*   */     //   17: getstatic f/Hu0.jf0 : Lf/Hu0;
/*   */     //   20: if_acmpne -> 176
/*   */     //   23: aload_2
/*   */     //   24: getfield Lh : Lf/nH0;
/*   */     //   27: getfield p1 : S
/*   */     //   30: invokestatic l90 : (S)S
/*   */     //   33: aload_1
/*   */     //   34: getfield ah : Lf/Y;
/*   */     //   37: getfield Lh : Lf/nH0;
/*   */     //   40: getfield p1 : S
/*   */     //   43: invokestatic l90 : (S)S
/*   */     //   46: istore_2
/*   */     //   47: sipush #5001
/*   */     //   50: if_icmpne -> 59
/*   */     //   53: ldc 2147483647
/*   */     //   55: istore_0
/*   */     //   56: goto -> 109
/*   */     //   59: aload_0
/*   */     //   60: getfield ah : Lf/Y;
/*   */     //   63: getfield Lh : Lf/nH0;
/*   */     //   66: getfield p1 : S
/*   */     //   69: invokestatic l90 : (S)S
/*   */     //   72: istore_0
/*   */     //   73: getstatic f/Jf.Et : [S
/*   */     //   76: astore_3
/*   */     //   77: iconst_0
/*   */     //   78: istore #4
/*   */     //   80: iload #4
/*   */     //   82: bipush #25
/*   */     //   84: if_icmpge -> 107
/*   */     //   87: iload_0
/*   */     //   88: aload_3
/*   */     //   89: iload #4
/*   */     //   91: saload
/*   */     //   92: if_icmpne -> 101
/*   */     //   95: iload #4
/*   */     //   97: istore_0
/*   */     //   98: goto -> 109
/*   */     //   101: iinc #4, 1
/*   */     //   104: goto -> 80
/*   */     //   107: iconst_m1
/*   */     //   108: istore_0
/*   */     //   109: iload_2
/*   */     //   110: sipush #5001
/*   */     //   113: if_icmpne -> 122
/*   */     //   116: ldc 2147483647
/*   */     //   118: istore_1
/*   */     //   119: goto -> 168
/*   */     //   122: aload_1
/*   */     //   123: getfield ah : Lf/Y;
/*   */     //   126: getfield Lh : Lf/nH0;
/*   */     //   129: getfield p1 : S
/*   */     //   132: invokestatic l90 : (S)S
/*   */     //   135: istore_1
/*   */     //   136: getstatic f/Jf.Et : [S
/*   */     //   139: astore_2
/*   */     //   140: iconst_0
/*   */     //   141: istore_3
/*   */     //   142: iload_3
/*   */     //   143: bipush #25
/*   */     //   145: if_icmpge -> 166
/*   */     //   148: iload_1
/*   */     //   149: aload_2
/*   */     //   150: iload_3
/*   */     //   151: saload
/*   */     //   152: if_icmpne -> 160
/*   */     //   155: iload_3
/*   */     //   156: istore_1
/*   */     //   157: goto -> 168
/*   */     //   160: iinc #3, 1
/*   */     //   163: goto -> 142
/*   */     //   166: iconst_m1
/*   */     //   167: istore_1
/*   */     //   168: iload_0
/*   */     //   169: iload_1
/*   */     //   170: invokestatic compare : (II)I
/*   */     //   173: goto -> 195
/*   */     //   176: getstatic java/lang/String.CASE_INSENSITIVE_ORDER : Ljava/util/Comparator;
/*   */     //   179: aload_2
/*   */     //   180: invokevirtual JG0 : ()Ljava/lang/String;
/*   */     //   183: aload_1
/*   */     //   184: getfield ah : Lf/Y;
/*   */     //   187: invokevirtual JG0 : ()Ljava/lang/String;
/*   */     //   190: invokeinterface compare : (Ljava/lang/Object;Ljava/lang/Object;)I
/*   */     //   195: ireturn
/*   */     // Line number table:
/*   */     //   Java source line number -> byte code offset
/*   */     //   #1	-> 6
/*   */     //   #2	-> 11
/*   */     //   #3	-> 14
/*   */     //   #4	-> 17
/*   */     //   #5	-> 24
/*   */     //   #6	-> 27
/*   */     //   #7	-> 30
/*   */     //   #8	-> 37
/*   */     //   #9	-> 40
/*   */     //   #10	-> 43
/*   */     //   #11	-> 63
/*   */     //   #12	-> 66
/*   */     //   #13	-> 69
/*   */     //   #14	-> 91
/*   */     //   #15	-> 123
/*   */     //   #16	-> 126
/*   */     //   #17	-> 129
/*   */     //   #18	-> 132
/*   */     //   #19	-> 151
/*   */     //   #20	-> 170
/*   */   } }


/* Location:              /Users/vnnsnnt/Documents/Codespace/JavaWorkspace/RedTrainer/src/main/java/org/trainer/client/PokeMMO.jar!/f/s00.class
 * Java compiler version: 8 (52.0)
 * JD-Core Version:       1.1.3
 */