/* 1 */ package f;public final class s40 { public static final ik Gt = C00.gd(s40.class); public final MappedByteBuffer Rl0; public final String coM7; public final byte H5; public s40(RD0 paramRD0) { this.mD = null; this.Kf0 = paramRD0; byte[] arrayOfByte1; paramRD0.m30(arrayOfByte1 = new byte[255], 255); ByteBuffer byteBuffer; (byteBuffer = ByteBuffer.wrap(arrayOfByte1).order(ByteOrder.LITTLE_ENDIAN)).position(172); byte[] arrayOfByte2; ByteBuffer.wrap(arrayOfByte1).order(ByteOrder.LITTLE_ENDIAN).get(arrayOfByte2 = new byte[4]); this(arrayOfByte2); this.coM7 = str; byteBuffer.position(172); byteBuffer.getInt(); byteBuffer.position(188); byte b = byteBuffer.get(); String str; if ((this.wJ = n50.Bj0(str = new String(), b, this)) == null) { if (n50.vv0(str)) throw new Xz0(ez0.Pa(str.getBytes()) + " v" + b + " is not currently a supported rom type.");  throw new Np(ez0.Pa(str.getBytes()) + " v" + b + " is not currently a supported rom type."); }  this.Yk0 = a3.Lj(b, str); this.Rl0 = paramRD0.fg0(FileChannel.MapMode.READ_ONLY); Gt
/* 2 */       .info(B40.df("Loaded GBA ROM ").append(str.trim()).append(" v1.").append(b).toString()); }
/* 3 */   public final uq wJ; public final a3 Yk0; public final RD0 Kf0; public String mD; public final ByteBuffer pr() { return this.Rl0.slice().order(ByteOrder.LITTLE_ENDIAN); } public final uq bV() { return this.wJ; } public final RD0 GP() { return this.Kf0; } public final byte in() { a3 a31; if ((a31 = this.Yk0) != null) return a31.Nj ^ true;  return this.wJ.F9; }
/*   */ 
/*   */   
/*   */   public final void Qf0() {
/*   */     // Byte code:
/*   */     //   0: aload_0
/*   */     //   1: dup
/*   */     //   2: getstatic f/D2.Wf0 : Lf/D2;
/*   */     //   5: dup
/*   */     //   6: astore_1
/*   */     //   7: invokevirtual getClass : ()Ljava/lang/Class;
/*   */     //   10: pop
/*   */     //   11: invokevirtual in : ()B
/*   */     //   14: istore_2
/*   */     //   15: invokevirtual pr : ()Ljava/nio/ByteBuffer;
/*   */     //   18: dup
/*   */     //   19: astore_3
/*   */     //   20: aload_0
/*   */     //   21: dup
/*   */     //   22: invokevirtual pr : ()Ljava/nio/ByteBuffer;
/*   */     //   25: astore #4
/*   */     //   27: getfield wJ : Lf/uq;
/*   */     //   30: getstatic f/uq.sI0 : I
/*   */     //   33: invokevirtual nz : (I)I
/*   */     //   36: invokevirtual position : (I)Ljava/nio/Buffer;
/*   */     //   39: pop
/*   */     //   40: iconst_0
/*   */     //   41: istore #5
/*   */     //   43: iload #5
/*   */     //   45: bipush #22
/*   */     //   47: if_icmpge -> 188
/*   */     //   50: iload #5
/*   */     //   52: aload_3
/*   */     //   53: dup
/*   */     //   54: dup
/*   */     //   55: invokevirtual getInt : ()I
/*   */     //   58: invokestatic tx0 : (I)I
/*   */     //   61: istore #6
/*   */     //   63: invokevirtual getShort : ()S
/*   */     //   66: istore #7
/*   */     //   68: invokevirtual getShort : ()S
/*   */     //   71: pop
/*   */     //   72: ifeq -> 178
/*   */     //   75: iload #5
/*   */     //   77: bipush #18
/*   */     //   79: if_icmpeq -> 178
/*   */     //   82: iload #5
/*   */     //   84: bipush #19
/*   */     //   86: if_icmpeq -> 178
/*   */     //   89: iload #5
/*   */     //   91: bipush #21
/*   */     //   93: if_icmpne -> 99
/*   */     //   96: goto -> 178
/*   */     //   99: aload #4
/*   */     //   101: iload #6
/*   */     //   103: invokevirtual position : (I)Ljava/nio/Buffer;
/*   */     //   106: pop
/*   */     //   107: iconst_0
/*   */     //   108: istore #6
/*   */     //   110: iload #6
/*   */     //   112: iload #7
/*   */     //   114: if_icmpge -> 178
/*   */     //   117: aload_1
/*   */     //   118: iload #5
/*   */     //   120: aload #4
/*   */     //   122: invokevirtual getInt : ()I
/*   */     //   125: invokestatic tx0 : (I)I
/*   */     //   128: aload #4
/*   */     //   130: dup
/*   */     //   131: dup
/*   */     //   132: invokevirtual getInt : ()I
/*   */     //   135: pop
/*   */     //   136: invokevirtual getInt : ()I
/*   */     //   139: pop
/*   */     //   140: invokestatic j00 : (ILjava/nio/ByteBuffer;)Ljava/lang/String;
/*   */     //   143: astore #8
/*   */     //   145: iconst_2
/*   */     //   146: imul
/*   */     //   147: sipush #256
/*   */     //   150: imul
/*   */     //   151: iload #6
/*   */     //   153: iadd
/*   */     //   154: i2s
/*   */     //   155: istore #9
/*   */     //   157: getfield Xz0 : [Lf/hq0;
/*   */     //   160: iload_2
/*   */     //   161: aaload
/*   */     //   162: iload #9
/*   */     //   164: aload #8
/*   */     //   166: invokeinterface Vh0 : (SLjava/lang/Object;)Ljava/lang/Object;
/*   */     //   171: pop
/*   */     //   172: iinc #6, 1
/*   */     //   175: goto -> 110
/*   */     //   178: iload #5
/*   */     //   180: iconst_1
/*   */     //   181: iadd
/*   */     //   182: i2b
/*   */     //   183: istore #5
/*   */     //   185: goto -> 43
/*   */     //   188: aload_0
/*   */     //   189: dup
/*   */     //   190: getstatic f/Ml0.EH0 : [Ljava/lang/String;
/*   */     //   193: pop
/*   */     //   194: invokevirtual pr : ()Ljava/nio/ByteBuffer;
/*   */     //   197: astore_1
/*   */     //   198: getfield wJ : Lf/uq;
/*   */     //   201: dup
/*   */     //   202: astore_2
/*   */     //   203: getfield F9 : B
/*   */     //   206: iconst_1
/*   */     //   207: if_icmpne -> 888
/*   */     //   210: aload_2
/*   */     //   211: getstatic f/uq.lk : I
/*   */     //   214: invokevirtual nz : (I)I
/*   */     //   217: dup
/*   */     //   218: istore_2
/*   */     //   219: aload_0
/*   */     //   220: invokevirtual in : ()B
/*   */     //   223: sipush #1000
/*   */     //   226: imul
/*   */     //   227: ldc 140000
/*   */     //   229: iadd
/*   */     //   230: istore_3
/*   */     //   231: iconst_1
/*   */     //   232: if_icmpge -> 238
/*   */     //   235: goto -> 314
/*   */     //   238: aload_0
/*   */     //   239: invokevirtual pr : ()Ljava/nio/ByteBuffer;
/*   */     //   242: dup
/*   */     //   243: astore #4
/*   */     //   245: iload_2
/*   */     //   246: invokevirtual position : (I)Ljava/nio/Buffer;
/*   */     //   249: pop
/*   */     //   250: iconst_0
/*   */     //   251: istore_2
/*   */     //   252: aload #4
/*   */     //   254: dup
/*   */     //   255: invokevirtual getInt : ()I
/*   */     //   258: pop
/*   */     //   259: invokevirtual getInt : ()I
/*   */     //   262: invokestatic tx0 : (I)I
/*   */     //   265: dup
/*   */     //   266: istore #5
/*   */     //   268: iconst_1
/*   */     //   269: if_icmplt -> 314
/*   */     //   272: iload #5
/*   */     //   274: aload #4
/*   */     //   276: invokevirtual limit : ()I
/*   */     //   279: if_icmple -> 285
/*   */     //   282: goto -> 314
/*   */     //   285: iload #5
/*   */     //   287: aload_0
/*   */     //   288: invokevirtual pr : ()Ljava/nio/ByteBuffer;
/*   */     //   291: invokestatic ik : (ILjava/nio/ByteBuffer;)Ljava/lang/String;
/*   */     //   294: astore #5
/*   */     //   296: getstatic f/Ml0.nW : Lf/Ut0;
/*   */     //   299: iload_2
/*   */     //   300: iload_3
/*   */     //   301: iadd
/*   */     //   302: aload #5
/*   */     //   304: invokevirtual A3 : (ILjava/lang/Object;)Ljava/lang/Object;
/*   */     //   307: pop
/*   */     //   308: iinc #2, 1
/*   */     //   311: goto -> 252
/*   */     //   314: aload_0
/*   */     //   315: getfield wJ : Lf/uq;
/*   */     //   318: getstatic f/uq.Ow : I
/*   */     //   321: invokevirtual nz : (I)I
/*   */     //   324: dup
/*   */     //   325: istore_2
/*   */     //   326: aload_0
/*   */     //   327: dup
/*   */     //   328: getfield wJ : Lf/uq;
/*   */     //   331: getstatic f/uq.O7 : I
/*   */     //   334: invokevirtual nz : (I)I
/*   */     //   337: istore_3
/*   */     //   338: invokevirtual in : ()B
/*   */     //   341: bipush #120
/*   */     //   343: imul
/*   */     //   344: ldc_w 190000
/*   */     //   347: iadd
/*   */     //   348: istore #4
/*   */     //   350: ldc_w 2147483647
/*   */     //   353: istore #5
/*   */     //   355: iconst_1
/*   */     //   356: if_icmpge -> 362
/*   */     //   359: goto -> 426
/*   */     //   362: iload_3
/*   */     //   363: aload_1
/*   */     //   364: iload_2
/*   */     //   365: invokevirtual position : (I)Ljava/nio/Buffer;
/*   */     //   368: pop
/*   */     //   369: newarray byte
/*   */     //   371: astore_2
/*   */     //   372: iconst_0
/*   */     //   373: istore_3
/*   */     //   374: iload_3
/*   */     //   375: iload #5
/*   */     //   377: if_icmpge -> 426
/*   */     //   380: aload_2
/*   */     //   381: aload_1
/*   */     //   382: aload_2
/*   */     //   383: invokevirtual get : ([B)Ljava/nio/ByteBuffer;
/*   */     //   386: pop
/*   */     //   387: iconst_0
/*   */     //   388: baload
/*   */     //   389: dup
/*   */     //   390: istore #6
/*   */     //   392: iconst_m1
/*   */     //   393: if_icmpeq -> 426
/*   */     //   396: iload #6
/*   */     //   398: ifne -> 404
/*   */     //   401: goto -> 426
/*   */     //   404: getstatic f/Ml0.nW : Lf/Ut0;
/*   */     //   407: iload #4
/*   */     //   409: aload_2
/*   */     //   410: iinc #4, 1
/*   */     //   413: invokestatic LJ0 : ([B)Ljava/lang/String;
/*   */     //   416: invokevirtual A3 : (ILjava/lang/Object;)Ljava/lang/Object;
/*   */     //   419: pop
/*   */     //   420: iinc #3, 1
/*   */     //   423: goto -> 374
/*   */     //   426: aload_0
/*   */     //   427: dup
/*   */     //   428: dup
/*   */     //   429: dup2
/*   */     //   430: dup2
/*   */     //   431: getfield wJ : Lf/uq;
/*   */     //   434: getstatic f/uq.TY : I
/*   */     //   437: invokevirtual nz : (I)I
/*   */     //   440: ldc_w 100100
/*   */     //   443: iconst_m1
/*   */     //   444: invokestatic oI : (Lf/s40;III)V
/*   */     //   447: getfield wJ : Lf/uq;
/*   */     //   450: getstatic f/uq.protected : I
/*   */     //   453: invokevirtual nz : (I)I
/*   */     //   456: ldc_w 270600
/*   */     //   459: bipush #14
/*   */     //   461: invokestatic oI : (Lf/s40;III)V
/*   */     //   464: getfield wJ : Lf/uq;
/*   */     //   467: getstatic f/uq.Q60 : I
/*   */     //   470: dup
/*   */     //   471: istore_2
/*   */     //   472: invokevirtual nz : (I)I
/*   */     //   475: ldc_w 270200
/*   */     //   478: bipush #8
/*   */     //   480: invokestatic oI : (Lf/s40;III)V
/*   */     //   483: getfield wJ : Lf/uq;
/*   */     //   486: iload_2
/*   */     //   487: invokevirtual nz : (I)I
/*   */     //   490: bipush #28
/*   */     //   492: iadd
/*   */     //   493: dup
/*   */     //   494: istore_3
/*   */     //   495: ldc_w 270250
/*   */     //   498: istore #4
/*   */     //   500: iconst_4
/*   */     //   501: istore #5
/*   */     //   503: iconst_1
/*   */     //   504: if_icmpge -> 510
/*   */     //   507: goto -> 596
/*   */     //   510: aload_0
/*   */     //   511: invokevirtual pr : ()Ljava/nio/ByteBuffer;
/*   */     //   514: dup
/*   */     //   515: astore #6
/*   */     //   517: iload_3
/*   */     //   518: invokevirtual position : (I)Ljava/nio/Buffer;
/*   */     //   521: pop
/*   */     //   522: iconst_0
/*   */     //   523: istore_3
/*   */     //   524: iload #5
/*   */     //   526: iload_3
/*   */     //   527: if_icmpgt -> 533
/*   */     //   530: goto -> 596
/*   */     //   533: aload #6
/*   */     //   535: dup
/*   */     //   536: invokevirtual getInt : ()I
/*   */     //   539: pop
/*   */     //   540: invokevirtual getInt : ()I
/*   */     //   543: invokestatic tx0 : (I)I
/*   */     //   546: dup
/*   */     //   547: istore #7
/*   */     //   549: iconst_1
/*   */     //   550: if_icmplt -> 596
/*   */     //   553: iload #7
/*   */     //   555: aload #6
/*   */     //   557: invokevirtual limit : ()I
/*   */     //   560: if_icmple -> 566
/*   */     //   563: goto -> 596
/*   */     //   566: iload #7
/*   */     //   568: aload_0
/*   */     //   569: invokevirtual pr : ()Ljava/nio/ByteBuffer;
/*   */     //   572: invokestatic ik : (ILjava/nio/ByteBuffer;)Ljava/lang/String;
/*   */     //   575: astore #7
/*   */     //   577: getstatic f/Ml0.nW : Lf/Ut0;
/*   */     //   580: iload_3
/*   */     //   581: iload #4
/*   */     //   583: iadd
/*   */     //   584: aload #7
/*   */     //   586: invokevirtual A3 : (ILjava/lang/Object;)Ljava/lang/Object;
/*   */     //   589: pop
/*   */     //   590: iinc #3, 1
/*   */     //   593: goto -> 524
/*   */     //   596: aload_0
/*   */     //   597: aload_1
/*   */     //   598: aload_0
/*   */     //   599: dup
/*   */     //   600: dup
/*   */     //   601: getfield wJ : Lf/uq;
/*   */     //   604: iload_2
/*   */     //   605: invokevirtual nz : (I)I
/*   */     //   608: bipush #32
/*   */     //   610: iadd
/*   */     //   611: bipush #32
/*   */     //   613: iadd
/*   */     //   614: ldc_w 270255
/*   */     //   617: iconst_4
/*   */     //   618: invokestatic oI : (Lf/s40;III)V
/*   */     //   621: getfield wJ : Lf/uq;
/*   */     //   624: getstatic f/uq.dW : I
/*   */     //   627: invokevirtual nz : (I)I
/*   */     //   630: bipush #16
/*   */     //   632: ldc_w 270300
/*   */     //   635: invokestatic ik : (Ljava/nio/ByteBuffer;III)V
/*   */     //   638: getfield wJ : Lf/uq;
/*   */     //   641: getstatic f/uq.CoN : I
/*   */     //   644: dup
/*   */     //   645: istore_2
/*   */     //   646: invokevirtual iy0 : (I)Z
/*   */     //   649: ifeq -> 751
/*   */     //   652: aload_0
/*   */     //   653: getfield wJ : Lf/uq;
/*   */     //   656: getstatic f/uq.J6 : I
/*   */     //   659: dup
/*   */     //   660: istore_3
/*   */     //   661: invokevirtual iy0 : (I)Z
/*   */     //   664: ifeq -> 723
/*   */     //   667: aload_1
/*   */     //   668: dup
/*   */     //   669: aload_0
/*   */     //   670: dup
/*   */     //   671: getfield wJ : Lf/uq;
/*   */     //   674: iload_3
/*   */     //   675: invokevirtual nz : (I)I
/*   */     //   678: newarray byte
/*   */     //   680: astore_1
/*   */     //   681: getfield wJ : Lf/uq;
/*   */     //   684: iload_2
/*   */     //   685: invokevirtual nz : (I)I
/*   */     //   688: invokevirtual position : (I)Ljava/nio/Buffer;
/*   */     //   691: pop
/*   */     //   692: aload_1
/*   */     //   693: invokevirtual get : ([B)Ljava/nio/ByteBuffer;
/*   */     //   696: pop
/*   */     //   697: getstatic f/Ml0.nW : Lf/Ut0;
/*   */     //   700: aload_1
/*   */     //   701: invokestatic LJ0 : ([B)Ljava/lang/String;
/*   */     //   704: ldc_w '\|[^\|]+\|'
/*   */     //   707: ldc_w ' '
/*   */     //   710: invokevirtual replaceAll : (Ljava/lang/String;Ljava/lang/String;)Ljava/lang/String;
/*   */     //   713: bipush #8
/*   */     //   715: swap
/*   */     //   716: invokevirtual A3 : (ILjava/lang/Object;)Ljava/lang/Object;
/*   */     //   719: pop
/*   */     //   720: goto -> 751
/*   */     //   723: getstatic f/Ml0.nW : Lf/Ut0;
/*   */     //   726: aload_0
/*   */     //   727: getfield wJ : Lf/uq;
/*   */     //   730: iload_2
/*   */     //   731: invokevirtual nz : (I)I
/*   */     //   734: aload_1
/*   */     //   735: invokestatic ik : (ILjava/nio/ByteBuffer;)Ljava/lang/String;
/*   */     //   738: ldc_w ' '
/*   */     //   741: invokestatic SZ : (Ljava/lang/String;Ljava/lang/String;)Ljava/lang/String;
/*   */     //   744: bipush #8
/*   */     //   746: swap
/*   */     //   747: invokevirtual A3 : (ILjava/lang/Object;)Ljava/lang/Object;
/*   */     //   750: pop
/*   */     //   751: aload_0
/*   */     //   752: dup
/*   */     //   753: dup
/*   */     //   754: dup2
/*   */     //   755: dup2
/*   */     //   756: dup2
/*   */     //   757: dup2
/*   */     //   758: getfield wJ : Lf/uq;
/*   */     //   761: getstatic f/uq.V : I
/*   */     //   764: invokevirtual nz : (I)I
/*   */     //   767: ldc_w 205000
/*   */     //   770: iconst_m1
/*   */     //   771: invokestatic oI : (Lf/s40;III)V
/*   */     //   774: getfield wJ : Lf/uq;
/*   */     //   777: getstatic f/uq.yI0 : I
/*   */     //   780: invokevirtual nz : (I)I
/*   */     //   783: ldc_w 206000
/*   */     //   786: iconst_m1
/*   */     //   787: invokestatic oI : (Lf/s40;III)V
/*   */     //   790: invokevirtual pr : ()Ljava/nio/ByteBuffer;
/*   */     //   793: aload_0
/*   */     //   794: getfield wJ : Lf/uq;
/*   */     //   797: getstatic f/uq.bs0 : I
/*   */     //   800: invokevirtual nz : (I)I
/*   */     //   803: bipush #7
/*   */     //   805: ldc_w 206100
/*   */     //   808: invokestatic ik : (Ljava/nio/ByteBuffer;III)V
/*   */     //   811: getfield wJ : Lf/uq;
/*   */     //   814: getstatic f/uq.WH : I
/*   */     //   817: invokevirtual nz : (I)I
/*   */     //   820: ldc_w 285000
/*   */     //   823: iconst_m1
/*   */     //   824: invokestatic oI : (Lf/s40;III)V
/*   */     //   827: getfield wJ : Lf/uq;
/*   */     //   830: getstatic f/uq.G4 : I
/*   */     //   833: invokevirtual nz : (I)I
/*   */     //   836: ldc_w 310000
/*   */     //   839: iconst_m1
/*   */     //   840: invokestatic oI : (Lf/s40;III)V
/*   */     //   843: invokevirtual pr : ()Ljava/nio/ByteBuffer;
/*   */     //   846: aload_0
/*   */     //   847: getfield wJ : Lf/uq;
/*   */     //   850: getstatic f/uq.Gh : I
/*   */     //   853: invokevirtual nz : (I)I
/*   */     //   856: sipush #223
/*   */     //   859: ldc_w 310200
/*   */     //   862: invokestatic ik : (Ljava/nio/ByteBuffer;III)V
/*   */     //   865: invokevirtual pr : ()Ljava/nio/ByteBuffer;
/*   */     //   868: aload_0
/*   */     //   869: getfield wJ : Lf/uq;
/*   */     //   872: getstatic f/uq.nj0 : I
/*   */     //   875: invokevirtual nz : (I)I
/*   */     //   878: iconst_4
/*   */     //   879: ldc_w 311000
/*   */     //   882: invokestatic ik : (Ljava/nio/ByteBuffer;III)V
/*   */     //   885: goto -> 1144
/*   */     //   888: aload_0
/*   */     //   889: dup
/*   */     //   890: aload_2
/*   */     //   891: getstatic f/uq.lk : I
/*   */     //   894: invokevirtual nz : (I)I
/*   */     //   897: aload_0
/*   */     //   898: getfield wJ : Lf/uq;
/*   */     //   901: getfield F9 : B
/*   */     //   904: sipush #1000
/*   */     //   907: imul
/*   */     //   908: ldc 140000
/*   */     //   910: iadd
/*   */     //   911: iconst_m1
/*   */     //   912: invokestatic oI : (Lf/s40;III)V
/*   */     //   915: getfield wJ : Lf/uq;
/*   */     //   918: getstatic f/uq.Ow : I
/*   */     //   921: invokevirtual nz : (I)I
/*   */     //   924: dup
/*   */     //   925: istore_2
/*   */     //   926: aload_0
/*   */     //   927: getfield wJ : Lf/uq;
/*   */     //   930: getstatic f/uq.O7 : I
/*   */     //   933: invokevirtual nz : (I)I
/*   */     //   936: istore_3
/*   */     //   937: ldc_w 190000
/*   */     //   940: istore #4
/*   */     //   942: ldc_w 2147483647
/*   */     //   945: istore #5
/*   */     //   947: iconst_1
/*   */     //   948: if_icmpge -> 954
/*   */     //   951: goto -> 1018
/*   */     //   954: iload_3
/*   */     //   955: aload_1
/*   */     //   956: iload_2
/*   */     //   957: invokevirtual position : (I)Ljava/nio/Buffer;
/*   */     //   960: pop
/*   */     //   961: newarray byte
/*   */     //   963: astore_2
/*   */     //   964: iconst_0
/*   */     //   965: istore_3
/*   */     //   966: iload_3
/*   */     //   967: iload #5
/*   */     //   969: if_icmpge -> 1018
/*   */     //   972: aload_2
/*   */     //   973: aload_1
/*   */     //   974: aload_2
/*   */     //   975: invokevirtual get : ([B)Ljava/nio/ByteBuffer;
/*   */     //   978: pop
/*   */     //   979: iconst_0
/*   */     //   980: baload
/*   */     //   981: dup
/*   */     //   982: istore #6
/*   */     //   984: iconst_m1
/*   */     //   985: if_icmpeq -> 1018
/*   */     //   988: iload #6
/*   */     //   990: ifne -> 996
/*   */     //   993: goto -> 1018
/*   */     //   996: getstatic f/Ml0.nW : Lf/Ut0;
/*   */     //   999: iload #4
/*   */     //   1001: aload_2
/*   */     //   1002: iinc #4, 1
/*   */     //   1005: invokestatic LJ0 : ([B)Ljava/lang/String;
/*   */     //   1008: invokevirtual A3 : (ILjava/lang/Object;)Ljava/lang/Object;
/*   */     //   1011: pop
/*   */     //   1012: iinc #3, 1
/*   */     //   1015: goto -> 966
/*   */     //   1018: aload_0
/*   */     //   1019: dup
/*   */     //   1020: dup2
/*   */     //   1021: dup2
/*   */     //   1022: getfield wJ : Lf/uq;
/*   */     //   1025: getstatic f/uq.V : I
/*   */     //   1028: invokevirtual nz : (I)I
/*   */     //   1031: ldc_w 200000
/*   */     //   1034: iconst_m1
/*   */     //   1035: invokestatic oI : (Lf/s40;III)V
/*   */     //   1038: getfield wJ : Lf/uq;
/*   */     //   1041: getstatic f/uq.yx : I
/*   */     //   1044: invokevirtual nz : (I)I
/*   */     //   1047: ldc_w 300000
/*   */     //   1050: iconst_m1
/*   */     //   1051: invokestatic oI : (Lf/s40;III)V
/*   */     //   1054: getfield wJ : Lf/uq;
/*   */     //   1057: getstatic f/uq.pq0 : I
/*   */     //   1060: invokevirtual nz : (I)I
/*   */     //   1063: ldc_w 300050
/*   */     //   1066: iconst_m1
/*   */     //   1067: invokestatic oI : (Lf/s40;III)V
/*   */     //   1070: getstatic f/Ml0.nW : Lf/Ut0;
/*   */     //   1073: getstatic f/D2.Wf0 : Lf/D2;
/*   */     //   1076: dup
/*   */     //   1077: astore_2
/*   */     //   1078: iconst_0
/*   */     //   1079: sipush #8720
/*   */     //   1082: invokevirtual R30 : (BS)Ljava/lang/String;
/*   */     //   1085: bipush #6
/*   */     //   1087: swap
/*   */     //   1088: invokevirtual A3 : (ILjava/lang/Object;)Ljava/lang/Object;
/*   */     //   1091: pop
/*   */     //   1092: getstatic f/Ml0.nW : Lf/Ut0;
/*   */     //   1095: aload_2
/*   */     //   1096: iconst_0
/*   */     //   1097: sipush #525
/*   */     //   1100: invokevirtual R30 : (BS)Ljava/lang/String;
/*   */     //   1103: bipush #7
/*   */     //   1105: swap
/*   */     //   1106: invokevirtual A3 : (ILjava/lang/Object;)Ljava/lang/Object;
/*   */     //   1109: pop
/*   */     //   1110: getstatic f/Ml0.nW : Lf/Ut0;
/*   */     //   1113: ldc_w 250100
/*   */     //   1116: aload_0
/*   */     //   1117: getfield wJ : Lf/uq;
/*   */     //   1120: getstatic f/uq.Pv0 : I
/*   */     //   1123: invokevirtual nz : (I)I
/*   */     //   1126: aload_1
/*   */     //   1127: invokestatic ik : (ILjava/nio/ByteBuffer;)Ljava/lang/String;
/*   */     //   1130: aconst_null
/*   */     //   1131: invokestatic SZ : (Ljava/lang/String;Ljava/lang/String;)Ljava/lang/String;
/*   */     //   1134: invokevirtual A3 : (ILjava/lang/Object;)Ljava/lang/Object;
/*   */     //   1137: pop
/*   */     //   1138: goto -> 1144
/*   */     //   1141: invokevirtual printStackTrace : ()V
/*   */     //   1144: aload_0
/*   */     //   1145: getstatic f/Of.eH : Lf/Of;
/*   */     //   1148: dup
/*   */     //   1149: astore_1
/*   */     //   1150: invokevirtual getClass : ()Ljava/lang/Class;
/*   */     //   1153: pop
/*   */     //   1154: invokevirtual pr : ()Ljava/nio/ByteBuffer;
/*   */     //   1157: dup
/*   */     //   1158: astore_2
/*   */     //   1159: aload_0
/*   */     //   1160: getfield wJ : Lf/uq;
/*   */     //   1163: getstatic f/uq.r00 : I
/*   */     //   1166: invokevirtual nz : (I)I
/*   */     //   1169: invokevirtual position : (I)Ljava/nio/Buffer;
/*   */     //   1172: pop
/*   */     //   1173: iconst_0
/*   */     //   1174: istore_3
/*   */     //   1175: iload_3
/*   */     //   1176: aload_0
/*   */     //   1177: getfield wJ : Lf/uq;
/*   */     //   1180: getstatic f/uq.Dk0 : I
/*   */     //   1183: invokevirtual nz : (I)I
/*   */     //   1186: if_icmpge -> 1787
/*   */     //   1189: aload_0
/*   */     //   1190: new f/LPT3
/*   */     //   1193: dup
/*   */     //   1194: astore #4
/*   */     //   1196: invokespecial <init> : ()V
/*   */     //   1199: invokevirtual in : ()B
/*   */     //   1202: dup
/*   */     //   1203: istore #5
/*   */     //   1205: aload_2
/*   */     //   1206: dup
/*   */     //   1207: dup2
/*   */     //   1208: aload #4
/*   */     //   1210: aload_2
/*   */     //   1211: aload #4
/*   */     //   1213: aload_2
/*   */     //   1214: aload #4
/*   */     //   1216: iload #5
/*   */     //   1218: putfield ux0 : B
/*   */     //   1221: bipush #14
/*   */     //   1223: newarray byte
/*   */     //   1225: dup
/*   */     //   1226: aload_2
/*   */     //   1227: swap
/*   */     //   1228: invokevirtual get : ([B)Ljava/nio/ByteBuffer;
/*   */     //   1231: pop
/*   */     //   1232: invokestatic LJ0 : ([B)Ljava/lang/String;
/*   */     //   1235: astore #6
/*   */     //   1237: invokevirtual getShort : ()S
/*   */     //   1240: putfield bj0 : S
/*   */     //   1243: invokevirtual getShort : ()S
/*   */     //   1246: putfield ph0 : I
/*   */     //   1249: invokevirtual get : ()B
/*   */     //   1252: pop
/*   */     //   1253: invokevirtual get : ()B
/*   */     //   1256: pop
/*   */     //   1257: invokevirtual getInt : ()I
/*   */     //   1260: invokestatic tx0 : (I)I
/*   */     //   1263: aload_2
/*   */     //   1264: invokestatic j00 : (ILjava/nio/ByteBuffer;)Ljava/lang/String;
/*   */     //   1267: astore #7
/*   */     //   1269: invokevirtual getShort : ()S
/*   */     //   1272: pop
/*   */     //   1273: ifne -> 1339
/*   */     //   1276: aload_2
/*   */     //   1277: invokevirtual get : ()B
/*   */     //   1280: istore #8
/*   */     //   1282: getstatic f/Hu0.It : [Lf/Hu0;
/*   */     //   1285: dup
/*   */     //   1286: astore #9
/*   */     //   1288: arraylength
/*   */     //   1289: istore #10
/*   */     //   1291: iconst_0
/*   */     //   1292: istore #11
/*   */     //   1294: iload #11
/*   */     //   1296: iload #10
/*   */     //   1298: if_icmpge -> 1326
/*   */     //   1301: aload #9
/*   */     //   1303: iload #11
/*   */     //   1305: aaload
/*   */     //   1306: dup
/*   */     //   1307: astore #12
/*   */     //   1309: getfield od : B
/*   */     //   1312: iload #8
/*   */     //   1314: if_icmpne -> 1320
/*   */     //   1317: goto -> 1329
/*   */     //   1320: iinc #11, 1
/*   */     //   1323: goto -> 1294
/*   */     //   1326: aconst_null
/*   */     //   1327: astore #12
/*   */     //   1329: aload #4
/*   */     //   1331: aload #12
/*   */     //   1333: putfield Y8 : Lf/Hu0;
/*   */     //   1336: goto -> 1399
/*   */     //   1339: aload_2
/*   */     //   1340: invokevirtual get : ()B
/*   */     //   1343: istore #8
/*   */     //   1345: getstatic f/Hu0.It : [Lf/Hu0;
/*   */     //   1348: dup
/*   */     //   1349: astore #9
/*   */     //   1351: arraylength
/*   */     //   1352: istore #10
/*   */     //   1354: iconst_0
/*   */     //   1355: istore #11
/*   */     //   1357: iload #11
/*   */     //   1359: iload #10
/*   */     //   1361: if_icmpge -> 1389
/*   */     //   1364: aload #9
/*   */     //   1366: iload #11
/*   */     //   1368: aaload
/*   */     //   1369: dup
/*   */     //   1370: astore #12
/*   */     //   1372: getfield SC : B
/*   */     //   1375: iload #8
/*   */     //   1377: if_icmpne -> 1383
/*   */     //   1380: goto -> 1392
/*   */     //   1383: iinc #11, 1
/*   */     //   1386: goto -> 1357
/*   */     //   1389: aconst_null
/*   */     //   1390: astore #12
/*   */     //   1392: aload #4
/*   */     //   1394: aload #12
/*   */     //   1396: putfield Y8 : Lf/Hu0;
/*   */     //   1399: aload #4
/*   */     //   1401: getfield Y8 : Lf/Hu0;
/*   */     //   1404: getstatic f/Hu0.jf0 : Lf/Hu0;
/*   */     //   1407: if_acmpne -> 1422
/*   */     //   1410: aload #4
/*   */     //   1412: aload_2
/*   */     //   1413: invokevirtual get : ()B
/*   */     //   1416: putfield KU : B
/*   */     //   1419: goto -> 1427
/*   */     //   1422: aload_2
/*   */     //   1423: invokevirtual get : ()B
/*   */     //   1426: pop
/*   */     //   1427: aload #4
/*   */     //   1429: aload_2
/*   */     //   1430: dup
/*   */     //   1431: dup2
/*   */     //   1432: invokevirtual getInt : ()I
/*   */     //   1435: pop
/*   */     //   1436: invokevirtual getInt : ()I
/*   */     //   1439: pop
/*   */     //   1440: invokevirtual getInt : ()I
/*   */     //   1443: pop
/*   */     //   1444: invokevirtual getInt : ()I
/*   */     //   1447: pop
/*   */     //   1448: getfield Y8 : Lf/Hu0;
/*   */     //   1451: getstatic f/Hu0.JV : Lf/Hu0;
/*   */     //   1454: if_acmpeq -> 1464
/*   */     //   1457: aload #6
/*   */     //   1459: invokestatic Gt0 : (Ljava/lang/String;)Ljava/lang/String;
/*   */     //   1462: astore #6
/*   */     //   1464: aload #4
/*   */     //   1466: dup
/*   */     //   1467: getfield bj0 : S
/*   */     //   1470: ldc_w 240000
/*   */     //   1473: iadd
/*   */     //   1474: dup
/*   */     //   1475: istore #8
/*   */     //   1477: iload #5
/*   */     //   1479: aload #4
/*   */     //   1481: iload #8
/*   */     //   1483: putfield Iu : I
/*   */     //   1486: sipush #500
/*   */     //   1489: imul
/*   */     //   1490: dup
/*   */     //   1491: istore #5
/*   */     //   1493: iadd
/*   */     //   1494: getstatic f/Ml0.nW : Lf/Ut0;
/*   */     //   1497: swap
/*   */     //   1498: aload #6
/*   */     //   1500: invokevirtual A3 : (ILjava/lang/Object;)Ljava/lang/Object;
/*   */     //   1503: pop
/*   */     //   1504: getfield Iu : I
/*   */     //   1507: getstatic f/Ml0.nW : Lf/Ut0;
/*   */     //   1510: swap
/*   */     //   1511: invokevirtual return : (I)Z
/*   */     //   1514: ifne -> 1532
/*   */     //   1517: aload #4
/*   */     //   1519: getfield Iu : I
/*   */     //   1522: getstatic f/Ml0.nW : Lf/Ut0;
/*   */     //   1525: swap
/*   */     //   1526: aload #6
/*   */     //   1528: invokevirtual A3 : (ILjava/lang/Object;)Ljava/lang/Object;
/*   */     //   1531: pop
/*   */     //   1532: aload #4
/*   */     //   1534: dup
/*   */     //   1535: getfield bj0 : S
/*   */     //   1538: ldc_w 130000
/*   */     //   1541: iadd
/*   */     //   1542: dup
/*   */     //   1543: istore #8
/*   */     //   1545: iload #5
/*   */     //   1547: aload #4
/*   */     //   1549: iload #8
/*   */     //   1551: putfield wC0 : I
/*   */     //   1554: iadd
/*   */     //   1555: getstatic f/Ml0.nW : Lf/Ut0;
/*   */     //   1558: swap
/*   */     //   1559: aload #7
/*   */     //   1561: invokevirtual A3 : (ILjava/lang/Object;)Ljava/lang/Object;
/*   */     //   1564: pop
/*   */     //   1565: getfield bj0 : S
/*   */     //   1568: dup
/*   */     //   1569: istore #5
/*   */     //   1571: sipush #153
/*   */     //   1574: if_icmplt -> 1602
/*   */     //   1577: iload #5
/*   */     //   1579: sipush #158
/*   */     //   1582: if_icmpgt -> 1602
/*   */     //   1585: aload #4
/*   */     //   1587: getfield wC0 : I
/*   */     //   1590: iconst_0
/*   */     //   1591: iadd
/*   */     //   1592: getstatic f/Ml0.nW : Lf/Ut0;
/*   */     //   1595: swap
/*   */     //   1596: aload #7
/*   */     //   1598: invokevirtual A3 : (ILjava/lang/Object;)Ljava/lang/Object;
/*   */     //   1601: pop
/*   */     //   1602: aload #4
/*   */     //   1604: getfield bj0 : S
/*   */     //   1607: dup
/*   */     //   1608: istore #5
/*   */     //   1610: tableswitch default -> 1648, 5289 -> 1662, 5290 -> 1662, 5291 -> 1662, 5292 -> 1662, 5293 -> 1662, 5294 -> 1651
/*   */     //   1648: goto -> 1679
/*   */     //   1651: aload #4
/*   */     //   1653: ldc_w 100016
/*   */     //   1656: putfield wC0 : I
/*   */     //   1659: goto -> 1679
/*   */     //   1662: aload #4
/*   */     //   1664: iload #5
/*   */     //   1666: sipush #5289
/*   */     //   1669: isub
/*   */     //   1670: iconst_2
/*   */     //   1671: imul
/*   */     //   1672: ldc_w 100018
/*   */     //   1675: iadd
/*   */     //   1676: putfield wC0 : I
/*   */     //   1679: aload #4
/*   */     //   1681: getfield wC0 : I
/*   */     //   1684: getstatic f/Ml0.nW : Lf/Ut0;
/*   */     //   1687: swap
/*   */     //   1688: invokevirtual return : (I)Z
/*   */     //   1691: ifne -> 1709
/*   */     //   1694: aload #4
/*   */     //   1696: getfield wC0 : I
/*   */     //   1699: getstatic f/Ml0.nW : Lf/Ut0;
/*   */     //   1702: swap
/*   */     //   1703: aload #6
/*   */     //   1705: invokevirtual A3 : (ILjava/lang/Object;)Ljava/lang/Object;
/*   */     //   1708: pop
/*   */     //   1709: aload_1
/*   */     //   1710: aload #4
/*   */     //   1712: dup
/*   */     //   1713: getfield Y8 : Lf/Hu0;
/*   */     //   1716: getfield tj : S
/*   */     //   1719: putfield O5 : S
/*   */     //   1722: getfield ix : Ljava/util/TreeMap;
/*   */     //   1725: aload #4
/*   */     //   1727: getfield bj0 : S
/*   */     //   1730: invokestatic valueOf : (S)Ljava/lang/Short;
/*   */     //   1733: invokevirtual get : (Ljava/lang/Object;)Ljava/lang/Object;
/*   */     //   1736: checkcast f/LPT3
/*   */     //   1739: ifnull -> 1745
/*   */     //   1742: goto -> 1781
/*   */     //   1745: aload_1
/*   */     //   1746: dup
/*   */     //   1747: getfield ix : Ljava/util/TreeMap;
/*   */     //   1750: aload #4
/*   */     //   1752: getfield bj0 : S
/*   */     //   1755: invokestatic valueOf : (S)Ljava/lang/Short;
/*   */     //   1758: aload #4
/*   */     //   1760: invokevirtual put : (Ljava/lang/Object;Ljava/lang/Object;)Ljava/lang/Object;
/*   */     //   1763: pop
/*   */     //   1764: getfield cOm7 : Ljava/util/TreeMap;
/*   */     //   1767: aload #4
/*   */     //   1769: getfield bj0 : S
/*   */     //   1772: invokestatic valueOf : (S)Ljava/lang/Short;
/*   */     //   1775: aload #4
/*   */     //   1777: invokevirtual put : (Ljava/lang/Object;Ljava/lang/Object;)Ljava/lang/Object;
/*   */     //   1780: pop
/*   */     //   1781: iinc #3, 1
/*   */     //   1784: goto -> 1175
/*   */     //   1787: aload_2
/*   */     //   1788: aload_0
/*   */     //   1789: getfield wJ : Lf/uq;
/*   */     //   1792: getstatic f/uq.pY : I
/*   */     //   1795: invokevirtual nz : (I)I
/*   */     //   1798: invokevirtual position : (I)Ljava/nio/Buffer;
/*   */     //   1801: pop
/*   */     //   1802: iconst_0
/*   */     //   1803: istore_3
/*   */     //   1804: iload_3
/*   */     //   1805: bipush #58
/*   */     //   1807: if_icmpge -> 1841
/*   */     //   1810: aload_1
/*   */     //   1811: aload_2
/*   */     //   1812: iload_3
/*   */     //   1813: sipush #289
/*   */     //   1816: iadd
/*   */     //   1817: i2s
/*   */     //   1818: istore #4
/*   */     //   1820: invokevirtual getShort : ()S
/*   */     //   1823: istore #5
/*   */     //   1825: iload #4
/*   */     //   1827: invokevirtual On0 : (S)Lf/LPT3;
/*   */     //   1830: iload #5
/*   */     //   1832: putfield kx0 : S
/*   */     //   1835: iinc #3, 1
/*   */     //   1838: goto -> 1804
/*   */     //   1841: aload_0
/*   */     //   1842: getstatic f/HQ.Z90 : Lf/HQ;
/*   */     //   1845: dup
/*   */     //   1846: astore_1
/*   */     //   1847: invokevirtual getClass : ()Ljava/lang/Class;
/*   */     //   1850: pop
/*   */     //   1851: getfield wJ : Lf/uq;
/*   */     //   1854: getstatic f/uq.IS : I
/*   */     //   1857: dup
/*   */     //   1858: istore_2
/*   */     //   1859: invokevirtual iy0 : (I)Z
/*   */     //   1862: ifne -> 1868
/*   */     //   1865: goto -> 1940
/*   */     //   1868: aload_0
/*   */     //   1869: invokevirtual pr : ()Ljava/nio/ByteBuffer;
/*   */     //   1872: dup
/*   */     //   1873: astore_3
/*   */     //   1874: aload_0
/*   */     //   1875: getfield wJ : Lf/uq;
/*   */     //   1878: iload_2
/*   */     //   1879: invokevirtual nz : (I)I
/*   */     //   1882: invokevirtual position : (I)Ljava/nio/Buffer;
/*   */     //   1885: pop
/*   */     //   1886: iconst_0
/*   */     //   1887: istore_2
/*   */     //   1888: iload_2
/*   */     //   1889: aload_0
/*   */     //   1890: getfield wJ : Lf/uq;
/*   */     //   1893: getstatic f/uq.Ll : I
/*   */     //   1896: invokevirtual nz : (I)I
/*   */     //   1899: if_icmpge -> 1940
/*   */     //   1902: aload_1
/*   */     //   1903: new f/lj0
/*   */     //   1906: dup
/*   */     //   1907: astore #4
/*   */     //   1909: aload_0
/*   */     //   1910: invokevirtual in : ()B
/*   */     //   1913: aload_3
/*   */     //   1914: invokespecial <init> : (BLjava/nio/ByteBuffer;)V
/*   */     //   1917: getfield gr : Ljava/util/TreeMap;
/*   */     //   1920: aload #4
/*   */     //   1922: getfield Pu0 : S
/*   */     //   1925: invokestatic valueOf : (S)Ljava/lang/Short;
/*   */     //   1928: aload #4
/*   */     //   1930: invokevirtual put : (Ljava/lang/Object;Ljava/lang/Object;)Ljava/lang/Object;
/*   */     //   1933: pop
/*   */     //   1934: iinc #2, 1
/*   */     //   1937: goto -> 1888
/*   */     //   1940: aload_0
/*   */     //   1941: getstatic f/T30.Qh : Lf/T30;
/*   */     //   1944: dup
/*   */     //   1945: astore_1
/*   */     //   1946: invokevirtual getClass : ()Ljava/lang/Class;
/*   */     //   1949: pop
/*   */     //   1950: invokevirtual pr : ()Ljava/nio/ByteBuffer;
/*   */     //   1953: dup
/*   */     //   1954: astore_2
/*   */     //   1955: aload_0
/*   */     //   1956: getfield wJ : Lf/uq;
/*   */     //   1959: getstatic f/uq.jf0 : I
/*   */     //   1962: invokevirtual nz : (I)I
/*   */     //   1965: invokevirtual position : (I)Ljava/nio/Buffer;
/*   */     //   1968: pop
/*   */     //   1969: iconst_0
/*   */     //   1970: istore_3
/*   */     //   1971: aload_2
/*   */     //   1972: invokevirtual get : ()B
/*   */     //   1975: dup
/*   */     //   1976: istore #4
/*   */     //   1978: iflt -> 2071
/*   */     //   1981: iload #4
/*   */     //   1983: iconst_3
/*   */     //   1984: if_icmple -> 1990
/*   */     //   1987: goto -> 2071
/*   */     //   1990: aload_1
/*   */     //   1991: aload_2
/*   */     //   1992: dup
/*   */     //   1993: invokevirtual position : ()I
/*   */     //   1996: iconst_1
/*   */     //   1997: isub
/*   */     //   1998: invokevirtual position : (I)Ljava/nio/Buffer;
/*   */     //   2001: pop
/*   */     //   2002: new f/OU
/*   */     //   2005: dup
/*   */     //   2006: astore #4
/*   */     //   2008: iload_3
/*   */     //   2009: aload_0
/*   */     //   2010: invokevirtual in : ()B
/*   */     //   2013: istore #5
/*   */     //   2015: iconst_1
/*   */     //   2016: iadd
/*   */     //   2017: i2s
/*   */     //   2018: istore #6
/*   */     //   2020: iload #5
/*   */     //   2022: aload_2
/*   */     //   2023: iload_3
/*   */     //   2024: invokespecial <init> : (BLjava/nio/ByteBuffer;S)V
/*   */     //   2027: getfield O80 : Lf/OU;
/*   */     //   2030: ifnonnull -> 2039
/*   */     //   2033: aload_1
/*   */     //   2034: aload #4
/*   */     //   2036: putfield O80 : Lf/OU;
/*   */     //   2039: aload #4
/*   */     //   2041: aload_1
/*   */     //   2042: getfield lD0 : [Lf/Ry0;
/*   */     //   2045: aload_0
/*   */     //   2046: invokevirtual in : ()B
/*   */     //   2049: aaload
/*   */     //   2050: astore_3
/*   */     //   2051: getfield tK : S
/*   */     //   2054: aload_3
/*   */     //   2055: getfield VL : Lf/qw0;
/*   */     //   2058: swap
/*   */     //   2059: aload #4
/*   */     //   2061: invokevirtual Vh0 : (SLjava/lang/Object;)Ljava/lang/Object;
/*   */     //   2064: pop
/*   */     //   2065: iload #6
/*   */     //   2067: istore_3
/*   */     //   2068: goto -> 1971
/*   */     //   2071: aload_0
/*   */     //   2072: getstatic f/fV.Ca : Lf/fV;
/*   */     //   2075: dup
/*   */     //   2076: astore_1
/*   */     //   2077: invokevirtual getClass : ()Ljava/lang/Class;
/*   */     //   2080: pop
/*   */     //   2081: invokevirtual pr : ()Ljava/nio/ByteBuffer;
/*   */     //   2084: astore_2
/*   */     //   2085: aload_1
/*   */     //   2086: aload_2
/*   */     //   2087: aload_0
/*   */     //   2088: dup
/*   */     //   2089: invokevirtual pr : ()Ljava/nio/ByteBuffer;
/*   */     //   2092: astore_3
/*   */     //   2093: getfield wJ : Lf/uq;
/*   */     //   2096: getstatic f/uq.Mc : I
/*   */     //   2099: invokevirtual nz : (I)I
/*   */     //   2102: invokevirtual position : (I)Ljava/nio/Buffer;
/*   */     //   2105: pop
/*   */     //   2106: iconst_1
/*   */     //   2107: istore #4
/*   */     //   2109: getfield sw : [Lf/Pz;
/*   */     //   2112: aload_0
/*   */     //   2113: invokevirtual in : ()B
/*   */     //   2116: aaload
/*   */     //   2117: astore #5
/*   */     //   2119: aload_2
/*   */     //   2120: invokevirtual getInt : ()I
/*   */     //   2123: dup
/*   */     //   2124: istore #6
/*   */     //   2126: ifne -> 2132
/*   */     //   2129: goto -> 5308
/*   */     //   2132: iload #6
/*   */     //   2134: invokestatic tx0 : (I)I
/*   */     //   2137: dup
/*   */     //   2138: istore #6
/*   */     //   2140: iconst_1
/*   */     //   2141: if_icmpge -> 5243
/*   */     //   2144: iload #4
/*   */     //   2146: bipush #100
/*   */     //   2148: if_icmplt -> 5232
/*   */     //   2151: aload_2
/*   */     //   2152: aload_0
/*   */     //   2153: getfield wJ : Lf/uq;
/*   */     //   2156: getstatic f/uq.xL : I
/*   */     //   2159: invokevirtual nz : (I)I
/*   */     //   2162: invokevirtual position : (I)Ljava/nio/Buffer;
/*   */     //   2165: pop
/*   */     //   2166: bipush #10
/*   */     //   2168: newarray int
/*   */     //   2170: astore_3
/*   */     //   2171: iconst_0
/*   */     //   2172: istore #4
/*   */     //   2174: aload_2
/*   */     //   2175: invokevirtual getInt : ()I
/*   */     //   2178: invokestatic tx0 : (I)I
/*   */     //   2181: dup
/*   */     //   2182: istore #5
/*   */     //   2184: iconst_1
/*   */     //   2185: if_icmpge -> 5182
/*   */     //   2188: iload #4
/*   */     //   2190: dup
/*   */     //   2191: iconst_0
/*   */     //   2192: istore #5
/*   */     //   2194: newarray int
/*   */     //   2196: astore #6
/*   */     //   2198: ifne -> 2204
/*   */     //   2201: goto -> 2220
/*   */     //   2204: iload #4
/*   */     //   2206: ifle -> 5172
/*   */     //   2209: aload_3
/*   */     //   2210: iload #5
/*   */     //   2212: aload #6
/*   */     //   2214: iconst_0
/*   */     //   2215: iload #4
/*   */     //   2217: invokestatic arraycopy : (Ljava/lang/Object;ILjava/lang/Object;II)V
/*   */     //   2220: iload #4
/*   */     //   2222: aload_0
/*   */     //   2223: invokevirtual in : ()B
/*   */     //   2226: bipush #50
/*   */     //   2228: imul
/*   */     //   2229: istore_3
/*   */     //   2230: anewarray [I
/*   */     //   2233: astore #5
/*   */     //   2235: iconst_0
/*   */     //   2236: istore #7
/*   */     //   2238: iload #7
/*   */     //   2240: iload #4
/*   */     //   2242: if_icmpge -> 2346
/*   */     //   2245: iload #7
/*   */     //   2247: iload #4
/*   */     //   2249: aload_2
/*   */     //   2250: aload #6
/*   */     //   2252: iload #7
/*   */     //   2254: iaload
/*   */     //   2255: invokevirtual position : (I)Ljava/nio/Buffer;
/*   */     //   2258: pop
/*   */     //   2259: iconst_1
/*   */     //   2260: isub
/*   */     //   2261: if_icmpne -> 2279
/*   */     //   2264: aload_0
/*   */     //   2265: getfield wJ : Lf/uq;
/*   */     //   2268: getstatic f/uq.xL : I
/*   */     //   2271: invokevirtual nz : (I)I
/*   */     //   2274: istore #8
/*   */     //   2276: goto -> 2288
/*   */     //   2279: aload #6
/*   */     //   2281: iload #7
/*   */     //   2283: iconst_1
/*   */     //   2284: iadd
/*   */     //   2285: iaload
/*   */     //   2286: istore #8
/*   */     //   2288: aload #5
/*   */     //   2290: iload #7
/*   */     //   2292: iload #8
/*   */     //   2294: aload #6
/*   */     //   2296: iload #7
/*   */     //   2298: iaload
/*   */     //   2299: isub
/*   */     //   2300: iconst_4
/*   */     //   2301: idiv
/*   */     //   2302: newarray int
/*   */     //   2304: aastore
/*   */     //   2305: iconst_0
/*   */     //   2306: istore #8
/*   */     //   2308: iload #8
/*   */     //   2310: aload #5
/*   */     //   2312: iload #7
/*   */     //   2314: aaload
/*   */     //   2315: dup
/*   */     //   2316: astore #9
/*   */     //   2318: arraylength
/*   */     //   2319: if_icmpge -> 2340
/*   */     //   2322: aload #9
/*   */     //   2324: iload #8
/*   */     //   2326: aload_2
/*   */     //   2327: invokevirtual getInt : ()I
/*   */     //   2330: invokestatic tx0 : (I)I
/*   */     //   2333: iastore
/*   */     //   2334: iinc #8, 1
/*   */     //   2337: goto -> 2308
/*   */     //   2340: iinc #7, 1
/*   */     //   2343: goto -> 2238
/*   */     //   2346: iconst_0
/*   */     //   2347: istore #6
/*   */     //   2349: iload #6
/*   */     //   2351: iload #4
/*   */     //   2353: if_icmpge -> 2444
/*   */     //   2356: aload_1
/*   */     //   2357: getfield i60 : [[Lf/MZ;
/*   */     //   2360: aload #5
/*   */     //   2362: iload #6
/*   */     //   2364: dup
/*   */     //   2365: iload_3
/*   */     //   2366: iadd
/*   */     //   2367: istore #7
/*   */     //   2369: aaload
/*   */     //   2370: arraylength
/*   */     //   2371: anewarray f/MZ
/*   */     //   2374: iload #7
/*   */     //   2376: swap
/*   */     //   2377: aastore
/*   */     //   2378: iconst_0
/*   */     //   2379: istore #8
/*   */     //   2381: iload #8
/*   */     //   2383: aload #5
/*   */     //   2385: iload #6
/*   */     //   2387: aaload
/*   */     //   2388: dup
/*   */     //   2389: astore #9
/*   */     //   2391: arraylength
/*   */     //   2392: if_icmpge -> 2438
/*   */     //   2395: aload_1
/*   */     //   2396: aload_2
/*   */     //   2397: aload #9
/*   */     //   2399: iload #8
/*   */     //   2401: iaload
/*   */     //   2402: invokevirtual position : (I)Ljava/nio/Buffer;
/*   */     //   2405: pop
/*   */     //   2406: getfield i60 : [[Lf/MZ;
/*   */     //   2409: iload #7
/*   */     //   2411: aaload
/*   */     //   2412: iload #8
/*   */     //   2414: new f/MZ
/*   */     //   2417: dup
/*   */     //   2418: astore #9
/*   */     //   2420: iload #6
/*   */     //   2422: iload #8
/*   */     //   2424: aload_2
/*   */     //   2425: aload_0
/*   */     //   2426: invokespecial <init> : (IILjava/nio/ByteBuffer;Lf/s40;)V
/*   */     //   2429: aload #9
/*   */     //   2431: aastore
/*   */     //   2432: iinc #8, 1
/*   */     //   2435: goto -> 2381
/*   */     //   2438: iinc #6, 1
/*   */     //   2441: goto -> 2349
/*   */     //   2444: aload_0
/*   */     //   2445: getstatic f/s10.hU : Lf/s10;
/*   */     //   2448: dup
/*   */     //   2449: astore_1
/*   */     //   2450: invokevirtual getClass : ()Ljava/lang/Class;
/*   */     //   2453: pop
/*   */     //   2454: getfield wJ : Lf/uq;
/*   */     //   2457: getstatic f/uq.t10 : I
/*   */     //   2460: dup
/*   */     //   2461: istore_2
/*   */     //   2462: invokevirtual iy0 : (I)Z
/*   */     //   2465: ifne -> 2471
/*   */     //   2468: goto -> 2786
/*   */     //   2471: aload_0
/*   */     //   2472: aload_1
/*   */     //   2473: getfield vw0 : [Lf/Vc0;
/*   */     //   2476: aload_0
/*   */     //   2477: invokevirtual in : ()B
/*   */     //   2480: aaload
/*   */     //   2481: astore_1
/*   */     //   2482: invokevirtual pr : ()Ljava/nio/ByteBuffer;
/*   */     //   2485: dup
/*   */     //   2486: astore_3
/*   */     //   2487: aload_0
/*   */     //   2488: dup
/*   */     //   2489: dup
/*   */     //   2490: invokevirtual pr : ()Ljava/nio/ByteBuffer;
/*   */     //   2493: astore #4
/*   */     //   2495: invokevirtual pr : ()Ljava/nio/ByteBuffer;
/*   */     //   2498: astore #6
/*   */     //   2500: getfield wJ : Lf/uq;
/*   */     //   2503: iload_2
/*   */     //   2504: invokevirtual nz : (I)I
/*   */     //   2507: invokevirtual position : (I)Ljava/nio/Buffer;
/*   */     //   2510: pop
/*   */     //   2511: iconst_0
/*   */     //   2512: istore_2
/*   */     //   2513: iconst_0
/*   */     //   2514: istore #5
/*   */     //   2516: aload_3
/*   */     //   2517: invokevirtual getInt : ()I
/*   */     //   2520: dup
/*   */     //   2521: istore #7
/*   */     //   2523: invokestatic pk0 : (I)Z
/*   */     //   2526: ifne -> 2532
/*   */     //   2529: goto -> 2598
/*   */     //   2532: aload_3
/*   */     //   2533: invokevirtual get : ()B
/*   */     //   2536: dup
/*   */     //   2537: istore #8
/*   */     //   2539: ifge -> 2545
/*   */     //   2542: goto -> 2598
/*   */     //   2545: aload #4
/*   */     //   2547: iload #7
/*   */     //   2549: iload #8
/*   */     //   2551: aload_3
/*   */     //   2552: dup
/*   */     //   2553: invokevirtual position : ()I
/*   */     //   2556: iconst_3
/*   */     //   2557: iadd
/*   */     //   2558: invokevirtual position : (I)Ljava/nio/Buffer;
/*   */     //   2561: pop
/*   */     //   2562: anewarray java/lang/String
/*   */     //   2565: astore #7
/*   */     //   2567: invokestatic tx0 : (I)I
/*   */     //   2570: invokevirtual position : (I)Ljava/nio/Buffer;
/*   */     //   2573: pop
/*   */     //   2574: iconst_0
/*   */     //   2575: istore #9
/*   */     //   2577: iload #9
/*   */     //   2579: iload #8
/*   */     //   2581: if_icmpge -> 5150
/*   */     //   2584: aload #4
/*   */     //   2586: invokevirtual getInt : ()I
/*   */     //   2589: dup
/*   */     //   2590: istore #10
/*   */     //   2592: invokestatic pk0 : (I)Z
/*   */     //   2595: ifne -> 5107
/*   */     //   2598: aload_0
/*   */     //   2599: getfield wJ : Lf/uq;
/*   */     //   2602: getstatic f/uq.hi0 : I
/*   */     //   2605: invokevirtual iy0 : (I)Z
/*   */     //   2608: ifne -> 2614
/*   */     //   2611: goto -> 2786
/*   */     //   2614: aload_0
/*   */     //   2615: getfield wJ : Lf/uq;
/*   */     //   2618: getstatic f/uq.Vh0 : I
/*   */     //   2621: invokevirtual nz : (I)I
/*   */     //   2624: istore_2
/*   */     //   2625: iconst_0
/*   */     //   2626: istore #4
/*   */     //   2628: iload #4
/*   */     //   2630: bipush #30
/*   */     //   2632: if_icmpge -> 2786
/*   */     //   2635: aload_3
/*   */     //   2636: iload #4
/*   */     //   2638: iload_2
/*   */     //   2639: aload_0
/*   */     //   2640: getfield wJ : Lf/uq;
/*   */     //   2643: getstatic f/uq.hi0 : I
/*   */     //   2646: invokevirtual nz : (I)I
/*   */     //   2649: istore #7
/*   */     //   2651: imul
/*   */     //   2652: iconst_4
/*   */     //   2653: imul
/*   */     //   2654: iload #7
/*   */     //   2656: iadd
/*   */     //   2657: invokevirtual position : (I)Ljava/nio/Buffer;
/*   */     //   2660: pop
/*   */     //   2661: new java/util/ArrayList
/*   */     //   2664: dup
/*   */     //   2665: astore #7
/*   */     //   2667: invokespecial <init> : ()V
/*   */     //   2670: iconst_0
/*   */     //   2671: istore #8
/*   */     //   2673: iload #8
/*   */     //   2675: iload_2
/*   */     //   2676: if_icmpge -> 2738
/*   */     //   2679: aload_3
/*   */     //   2680: invokevirtual getInt : ()I
/*   */     //   2683: dup
/*   */     //   2684: istore #9
/*   */     //   2686: invokestatic pk0 : (I)Z
/*   */     //   2689: ifne -> 2700
/*   */     //   2692: iload #8
/*   */     //   2694: ifne -> 2738
/*   */     //   2697: goto -> 2786
/*   */     //   2700: iload #9
/*   */     //   2702: iload #5
/*   */     //   2704: aload #7
/*   */     //   2706: aload #6
/*   */     //   2708: dup
/*   */     //   2709: iload #9
/*   */     //   2711: invokestatic tx0 : (I)I
/*   */     //   2714: invokevirtual position : (I)Ljava/nio/Buffer;
/*   */     //   2717: pop
/*   */     //   2718: invokestatic Vf0 : (Ljava/nio/ByteBuffer;)Ljava/lang/String;
/*   */     //   2721: invokevirtual add : (Ljava/lang/Object;)Z
/*   */     //   2724: pop
/*   */     //   2725: if_icmple -> 2732
/*   */     //   2728: iload #9
/*   */     //   2730: istore #5
/*   */     //   2732: iinc #8, 1
/*   */     //   2735: goto -> 2673
/*   */     //   2738: iload #4
/*   */     //   2740: aload_1
/*   */     //   2741: new f/ss
/*   */     //   2744: dup
/*   */     //   2745: astore #8
/*   */     //   2747: iload #4
/*   */     //   2749: aload #7
/*   */     //   2751: iconst_0
/*   */     //   2752: anewarray java/lang/String
/*   */     //   2755: invokevirtual toArray : ([Ljava/lang/Object;)[Ljava/lang/Object;
/*   */     //   2758: checkcast [Ljava/lang/String;
/*   */     //   2761: invokespecial <init> : (B[Ljava/lang/String;)V
/*   */     //   2764: getfield dg0 : Lf/ak;
/*   */     //   2767: aload #8
/*   */     //   2769: getfield v2 : B
/*   */     //   2772: aload #8
/*   */     //   2774: invokevirtual VF : (BLjava/lang/Object;)Ljava/lang/Object;
/*   */     //   2777: pop
/*   */     //   2778: iconst_1
/*   */     //   2779: iadd
/*   */     //   2780: i2b
/*   */     //   2781: istore #4
/*   */     //   2783: goto -> 2628
/*   */     //   2786: aload_0
/*   */     //   2787: getstatic f/oo0.u60 : Lf/oo0;
/*   */     //   2790: dup
/*   */     //   2791: astore_1
/*   */     //   2792: invokevirtual getClass : ()Ljava/lang/Class;
/*   */     //   2795: pop
/*   */     //   2796: invokevirtual in : ()B
/*   */     //   2799: iconst_1
/*   */     //   2800: if_icmpeq -> 2806
/*   */     //   2803: goto -> 3262
/*   */     //   2806: aload_0
/*   */     //   2807: invokevirtual pr : ()Ljava/nio/ByteBuffer;
/*   */     //   2810: dup
/*   */     //   2811: astore_2
/*   */     //   2812: aload_0
/*   */     //   2813: getfield wJ : Lf/uq;
/*   */     //   2816: getstatic f/uq.fo0 : I
/*   */     //   2819: invokevirtual nz : (I)I
/*   */     //   2822: invokevirtual position : (I)Ljava/nio/Buffer;
/*   */     //   2825: pop
/*   */     //   2826: iconst_0
/*   */     //   2827: istore_3
/*   */     //   2828: iload_3
/*   */     //   2829: bipush #21
/*   */     //   2831: if_icmpge -> 3028
/*   */     //   2834: aload_2
/*   */     //   2835: invokevirtual getInt : ()I
/*   */     //   2838: dup
/*   */     //   2839: istore #4
/*   */     //   2841: invokestatic pk0 : (I)Z
/*   */     //   2844: ifne -> 2850
/*   */     //   2847: goto -> 3028
/*   */     //   2850: iload_3
/*   */     //   2851: aload_1
/*   */     //   2852: iload #4
/*   */     //   2854: invokestatic tx0 : (I)I
/*   */     //   2857: istore #4
/*   */     //   2859: new f/wl
/*   */     //   2862: dup
/*   */     //   2863: astore #5
/*   */     //   2865: aload_0
/*   */     //   2866: iload_3
/*   */     //   2867: iload #4
/*   */     //   2869: invokespecial <init> : (Lf/s40;BI)V
/*   */     //   2872: getfield MF0 : Ljava/util/TreeMap;
/*   */     //   2875: iload_3
/*   */     //   2876: invokestatic valueOf : (B)Ljava/lang/Byte;
/*   */     //   2879: aload #5
/*   */     //   2881: invokevirtual put : (Ljava/lang/Object;Ljava/lang/Object;)Ljava/lang/Object;
/*   */     //   2884: pop
/*   */     //   2885: iconst_1
/*   */     //   2886: if_icmpne -> 2936
/*   */     //   2889: aload #5
/*   */     //   2891: invokevirtual Wu0 : ()Ljava/lang/String;
/*   */     //   2894: dup
/*   */     //   2895: astore #4
/*   */     //   2897: ldc_w ' '
/*   */     //   2900: invokevirtual contains : (Ljava/lang/CharSequence;)Z
/*   */     //   2903: ifeq -> 2924
/*   */     //   2906: aload #4
/*   */     //   2908: ldc_w ' '
/*   */     //   2911: invokevirtual split : (Ljava/lang/String;)[Ljava/lang/String;
/*   */     //   2914: dup
/*   */     //   2915: arraylength
/*   */     //   2916: iconst_1
/*   */     //   2917: isub
/*   */     //   2918: aaload
/*   */     //   2919: invokevirtual trim : ()Ljava/lang/String;
/*   */     //   2922: astore #4
/*   */     //   2924: getstatic f/Ml0.nW : Lf/Ut0;
/*   */     //   2927: ldc_w 250101
/*   */     //   2930: aload #4
/*   */     //   2932: invokevirtual A3 : (ILjava/lang/Object;)Ljava/lang/Object;
/*   */     //   2935: pop
/*   */     //   2936: iload_3
/*   */     //   2937: iconst_2
/*   */     //   2938: if_icmpne -> 2974
/*   */     //   2941: aload #5
/*   */     //   2943: dup
/*   */     //   2944: invokevirtual Wu0 : ()Ljava/lang/String;
/*   */     //   2947: astore #4
/*   */     //   2949: getstatic f/Ml0.nW : Lf/Ut0;
/*   */     //   2952: ldc_w 260000
/*   */     //   2955: aload #4
/*   */     //   2957: invokevirtual A3 : (ILjava/lang/Object;)Ljava/lang/Object;
/*   */     //   2960: pop
/*   */     //   2961: ldc_w 260002
/*   */     //   2964: istore #4
/*   */     //   2966: invokevirtual Wu0 : ()Ljava/lang/String;
/*   */     //   2969: astore #5
/*   */     //   2971: goto -> 3009
/*   */     //   2974: iload_3
/*   */     //   2975: iconst_3
/*   */     //   2976: if_icmpne -> 3020
/*   */     //   2979: aload #5
/*   */     //   2981: dup
/*   */     //   2982: invokevirtual Wu0 : ()Ljava/lang/String;
/*   */     //   2985: astore #4
/*   */     //   2987: getstatic f/Ml0.nW : Lf/Ut0;
/*   */     //   2990: ldc_w 260001
/*   */     //   2993: aload #4
/*   */     //   2995: invokevirtual A3 : (ILjava/lang/Object;)Ljava/lang/Object;
/*   */     //   2998: pop
/*   */     //   2999: ldc_w 260003
/*   */     //   3002: istore #4
/*   */     //   3004: invokevirtual Wu0 : ()Ljava/lang/String;
/*   */     //   3007: astore #5
/*   */     //   3009: getstatic f/Ml0.nW : Lf/Ut0;
/*   */     //   3012: iload #4
/*   */     //   3014: aload #5
/*   */     //   3016: invokevirtual A3 : (ILjava/lang/Object;)Ljava/lang/Object;
/*   */     //   3019: pop
/*   */     //   3020: iload_3
/*   */     //   3021: iconst_1
/*   */     //   3022: iadd
/*   */     //   3023: i2b
/*   */     //   3024: istore_3
/*   */     //   3025: goto -> 2828
/*   */     //   3028: aload_2
/*   */     //   3029: aload_0
/*   */     //   3030: getfield wJ : Lf/uq;
/*   */     //   3033: getstatic f/uq.fs0 : I
/*   */     //   3036: invokevirtual nz : (I)I
/*   */     //   3039: invokevirtual position : (I)Ljava/nio/Buffer;
/*   */     //   3042: pop
/*   */     //   3043: iconst_0
/*   */     //   3044: istore_3
/*   */     //   3045: iload_3
/*   */     //   3046: bipush #78
/*   */     //   3048: if_icmpge -> 3163
/*   */     //   3051: iconst_4
/*   */     //   3052: newarray int
/*   */     //   3054: astore #4
/*   */     //   3056: iconst_0
/*   */     //   3057: istore #5
/*   */     //   3059: iload #5
/*   */     //   3061: iconst_4
/*   */     //   3062: if_icmpge -> 3083
/*   */     //   3065: aload #4
/*   */     //   3067: iload #5
/*   */     //   3069: aload_2
/*   */     //   3070: invokevirtual getInt : ()I
/*   */     //   3073: invokestatic tx0 : (I)I
/*   */     //   3076: iastore
/*   */     //   3077: iinc #5, 1
/*   */     //   3080: goto -> 3059
/*   */     //   3083: aload_0
/*   */     //   3084: new f/f80
/*   */     //   3087: dup
/*   */     //   3088: astore #5
/*   */     //   3090: aload #4
/*   */     //   3092: invokespecial <init> : ([I)V
/*   */     //   3095: invokevirtual pr : ()Ljava/nio/ByteBuffer;
/*   */     //   3098: astore #4
/*   */     //   3100: iconst_0
/*   */     //   3101: istore #6
/*   */     //   3103: iload #6
/*   */     //   3105: aload #5
/*   */     //   3107: getfield o70 : [I
/*   */     //   3110: dup
/*   */     //   3111: astore #7
/*   */     //   3113: arraylength
/*   */     //   3114: if_icmpge -> 3141
/*   */     //   3117: aload #5
/*   */     //   3119: getfield UP : [Ljava/lang/String;
/*   */     //   3122: iload #6
/*   */     //   3124: aload #7
/*   */     //   3126: iload #6
/*   */     //   3128: iaload
/*   */     //   3129: aload #4
/*   */     //   3131: invokestatic ik : (ILjava/nio/ByteBuffer;)Ljava/lang/String;
/*   */     //   3134: aastore
/*   */     //   3135: iinc #6, 1
/*   */     //   3138: goto -> 3103
/*   */     //   3141: iload_3
/*   */     //   3142: aload_1
/*   */     //   3143: getfield R50 : Ljava/util/TreeMap;
/*   */     //   3146: iload_3
/*   */     //   3147: invokestatic valueOf : (B)Ljava/lang/Byte;
/*   */     //   3150: aload #5
/*   */     //   3152: invokevirtual put : (Ljava/lang/Object;Ljava/lang/Object;)Ljava/lang/Object;
/*   */     //   3155: pop
/*   */     //   3156: iconst_1
/*   */     //   3157: iadd
/*   */     //   3158: i2b
/*   */     //   3159: istore_3
/*   */     //   3160: goto -> 3045
/*   */     //   3163: aload_2
/*   */     //   3164: aload_0
/*   */     //   3165: getfield wJ : Lf/uq;
/*   */     //   3168: getstatic f/uq.r80 : I
/*   */     //   3171: invokevirtual nz : (I)I
/*   */     //   3174: invokevirtual position : (I)Ljava/nio/Buffer;
/*   */     //   3177: pop
/*   */     //   3178: iconst_0
/*   */     //   3179: istore_3
/*   */     //   3180: iload_3
/*   */     //   3181: sipush #205
/*   */     //   3184: if_icmpge -> 3262
/*   */     //   3187: aload_2
/*   */     //   3188: invokevirtual getInt : ()I
/*   */     //   3191: dup
/*   */     //   3192: istore #4
/*   */     //   3194: iflt -> 3262
/*   */     //   3197: iload #4
/*   */     //   3199: invokestatic pk0 : (I)Z
/*   */     //   3202: ifne -> 3208
/*   */     //   3205: goto -> 3262
/*   */     //   3208: aload_1
/*   */     //   3209: iload #4
/*   */     //   3211: aload_2
/*   */     //   3212: dup
/*   */     //   3213: dup2
/*   */     //   3214: invokevirtual get : ()B
/*   */     //   3217: pop
/*   */     //   3218: invokevirtual get : ()B
/*   */     //   3221: pop
/*   */     //   3222: invokevirtual get : ()B
/*   */     //   3225: pop
/*   */     //   3226: invokevirtual get : ()B
/*   */     //   3229: pop
/*   */     //   3230: invokestatic tx0 : (I)I
/*   */     //   3233: istore #4
/*   */     //   3235: getfield t50 : Ljava/util/TreeMap;
/*   */     //   3238: iload #4
/*   */     //   3240: iload_3
/*   */     //   3241: invokestatic valueOf : (I)Ljava/lang/Integer;
/*   */     //   3244: astore #4
/*   */     //   3246: invokestatic valueOf : (I)Ljava/lang/Integer;
/*   */     //   3249: aload #4
/*   */     //   3251: swap
/*   */     //   3252: invokevirtual put : (Ljava/lang/Object;Ljava/lang/Object;)Ljava/lang/Object;
/*   */     //   3255: pop
/*   */     //   3256: iinc #3, 1
/*   */     //   3259: goto -> 3180
/*   */     //   3262: aload_0
/*   */     //   3263: getstatic f/hh.qu0 : Lf/hh;
/*   */     //   3266: astore_1
/*   */     //   3267: invokevirtual in : ()B
/*   */     //   3270: iconst_1
/*   */     //   3271: if_icmpeq -> 3277
/*   */     //   3274: goto -> 3569
/*   */     //   3277: aload_0
/*   */     //   3278: dup
/*   */     //   3279: invokevirtual in : ()B
/*   */     //   3282: istore_2
/*   */     //   3283: invokevirtual pr : ()Ljava/nio/ByteBuffer;
/*   */     //   3286: dup
/*   */     //   3287: astore_3
/*   */     //   3288: aload_0
/*   */     //   3289: dup
/*   */     //   3290: invokevirtual pr : ()Ljava/nio/ByteBuffer;
/*   */     //   3293: astore #4
/*   */     //   3295: getfield wJ : Lf/uq;
/*   */     //   3298: getstatic f/uq.mt : I
/*   */     //   3301: invokevirtual nz : (I)I
/*   */     //   3304: invokevirtual position : (I)Ljava/nio/Buffer;
/*   */     //   3307: pop
/*   */     //   3308: iconst_0
/*   */     //   3309: istore #5
/*   */     //   3311: iload #5
/*   */     //   3313: bipush #64
/*   */     //   3315: if_icmpge -> 3335
/*   */     //   3318: aload_1
/*   */     //   3319: getfield OW : [S
/*   */     //   3322: iload #5
/*   */     //   3324: aload_3
/*   */     //   3325: invokevirtual getShort : ()S
/*   */     //   3328: sastore
/*   */     //   3329: iinc #5, 1
/*   */     //   3332: goto -> 3311
/*   */     //   3335: iconst_4
/*   */     //   3336: dup
/*   */     //   3337: istore #5
/*   */     //   3339: newarray int
/*   */     //   3341: dup
/*   */     //   3342: astore #6
/*   */     //   3344: aload_0
/*   */     //   3345: aload #6
/*   */     //   3347: aload_0
/*   */     //   3348: aload #6
/*   */     //   3350: aload_0
/*   */     //   3351: aload #6
/*   */     //   3353: aload_0
/*   */     //   3354: getfield wJ : Lf/uq;
/*   */     //   3357: getstatic f/uq.rT : I
/*   */     //   3360: invokevirtual nz : (I)I
/*   */     //   3363: iconst_0
/*   */     //   3364: swap
/*   */     //   3365: iastore
/*   */     //   3366: getfield wJ : Lf/uq;
/*   */     //   3369: getstatic f/uq.k6 : I
/*   */     //   3372: invokevirtual nz : (I)I
/*   */     //   3375: iconst_1
/*   */     //   3376: swap
/*   */     //   3377: iastore
/*   */     //   3378: getfield wJ : Lf/uq;
/*   */     //   3381: getstatic f/uq.GQ : I
/*   */     //   3384: invokevirtual nz : (I)I
/*   */     //   3387: iconst_2
/*   */     //   3388: swap
/*   */     //   3389: iastore
/*   */     //   3390: getfield wJ : Lf/uq;
/*   */     //   3393: getstatic f/uq.mp0 : I
/*   */     //   3396: invokevirtual nz : (I)I
/*   */     //   3399: iconst_3
/*   */     //   3400: swap
/*   */     //   3401: iastore
/*   */     //   3402: iconst_0
/*   */     //   3403: istore #7
/*   */     //   3405: iload #7
/*   */     //   3407: iload #5
/*   */     //   3409: if_icmpge -> 3569
/*   */     //   3412: aload_1
/*   */     //   3413: aload_3
/*   */     //   3414: aload #6
/*   */     //   3416: iload #7
/*   */     //   3418: iaload
/*   */     //   3419: invokevirtual position : (I)Ljava/nio/Buffer;
/*   */     //   3422: pop
/*   */     //   3423: getfield VA0 : [Lf/pt0;
/*   */     //   3426: iload #7
/*   */     //   3428: new f/pt0
/*   */     //   3431: dup
/*   */     //   3432: astore #8
/*   */     //   3434: invokespecial <init> : ()V
/*   */     //   3437: aload #8
/*   */     //   3439: aastore
/*   */     //   3440: iconst_0
/*   */     //   3441: istore #8
/*   */     //   3443: iload #8
/*   */     //   3445: getstatic f/hh.tL : [I
/*   */     //   3448: iload #7
/*   */     //   3450: iaload
/*   */     //   3451: if_icmpge -> 3502
/*   */     //   3454: iload #8
/*   */     //   3456: aload_1
/*   */     //   3457: new f/xq0
/*   */     //   3460: dup
/*   */     //   3461: astore #9
/*   */     //   3463: iload_2
/*   */     //   3464: iload #7
/*   */     //   3466: iload #8
/*   */     //   3468: aload_3
/*   */     //   3469: aload #4
/*   */     //   3471: invokespecial <init> : (BBSLjava/nio/ByteBuffer;Ljava/nio/ByteBuffer;)V
/*   */     //   3474: getfield VA0 : [Lf/pt0;
/*   */     //   3477: iload #7
/*   */     //   3479: aaload
/*   */     //   3480: getfield E7 : Ljava/util/TreeMap;
/*   */     //   3483: iload #8
/*   */     //   3485: invokestatic valueOf : (S)Ljava/lang/Short;
/*   */     //   3488: aload #9
/*   */     //   3490: invokevirtual put : (Ljava/lang/Object;Ljava/lang/Object;)Ljava/lang/Object;
/*   */     //   3493: pop
/*   */     //   3494: iconst_1
/*   */     //   3495: iadd
/*   */     //   3496: i2s
/*   */     //   3497: istore #8
/*   */     //   3499: goto -> 3443
/*   */     //   3502: iconst_0
/*   */     //   3503: istore #8
/*   */     //   3505: iload #8
/*   */     //   3507: getstatic f/hh.gj0 : [I
/*   */     //   3510: iload #7
/*   */     //   3512: iaload
/*   */     //   3513: if_icmpge -> 3559
/*   */     //   3516: iload #8
/*   */     //   3518: aload_1
/*   */     //   3519: new f/M20
/*   */     //   3522: dup
/*   */     //   3523: astore #9
/*   */     //   3525: iload #8
/*   */     //   3527: aload_3
/*   */     //   3528: invokespecial <init> : (SLjava/nio/ByteBuffer;)V
/*   */     //   3531: getfield VA0 : [Lf/pt0;
/*   */     //   3534: iload #7
/*   */     //   3536: aaload
/*   */     //   3537: getfield ye : Ljava/util/TreeMap;
/*   */     //   3540: iload #8
/*   */     //   3542: invokestatic valueOf : (S)Ljava/lang/Short;
/*   */     //   3545: aload #9
/*   */     //   3547: invokevirtual put : (Ljava/lang/Object;Ljava/lang/Object;)Ljava/lang/Object;
/*   */     //   3550: pop
/*   */     //   3551: iconst_1
/*   */     //   3552: iadd
/*   */     //   3553: i2s
/*   */     //   3554: istore #8
/*   */     //   3556: goto -> 3505
/*   */     //   3559: iload #7
/*   */     //   3561: iconst_1
/*   */     //   3562: iadd
/*   */     //   3563: i2b
/*   */     //   3564: istore #7
/*   */     //   3566: goto -> 3405
/*   */     //   3569: aload_0
/*   */     //   3570: getstatic f/Z4.T0 : Lf/Z4;
/*   */     //   3573: dup
/*   */     //   3574: astore_1
/*   */     //   3575: invokevirtual getClass : ()Ljava/lang/Class;
/*   */     //   3578: pop
/*   */     //   3579: invokevirtual in : ()B
/*   */     //   3582: iconst_1
/*   */     //   3583: if_icmpeq -> 3589
/*   */     //   3586: goto -> 3788
/*   */     //   3589: aload_0
/*   */     //   3590: invokevirtual pr : ()Ljava/nio/ByteBuffer;
/*   */     //   3593: dup
/*   */     //   3594: astore_2
/*   */     //   3595: aload_0
/*   */     //   3596: getfield wJ : Lf/uq;
/*   */     //   3599: getstatic f/uq.I00 : I
/*   */     //   3602: invokevirtual nz : (I)I
/*   */     //   3605: invokevirtual position : (I)Ljava/nio/Buffer;
/*   */     //   3608: pop
/*   */     //   3609: iconst_0
/*   */     //   3610: istore_3
/*   */     //   3611: iload_3
/*   */     //   3612: bipush #96
/*   */     //   3614: if_icmpge -> 3647
/*   */     //   3617: iload_3
/*   */     //   3618: aload_1
/*   */     //   3619: getfield Ab : Lf/ak;
/*   */     //   3622: iload_3
/*   */     //   3623: new f/Md0
/*   */     //   3626: dup
/*   */     //   3627: astore #4
/*   */     //   3629: iload_3
/*   */     //   3630: aload_2
/*   */     //   3631: invokespecial <init> : (BLjava/nio/ByteBuffer;)V
/*   */     //   3634: aload #4
/*   */     //   3636: invokevirtual VF : (BLjava/lang/Object;)Ljava/lang/Object;
/*   */     //   3639: pop
/*   */     //   3640: iconst_1
/*   */     //   3641: iadd
/*   */     //   3642: i2b
/*   */     //   3643: istore_3
/*   */     //   3644: goto -> 3611
/*   */     //   3647: aload_0
/*   */     //   3648: aload_2
/*   */     //   3649: aload_0
/*   */     //   3650: getfield wJ : Lf/uq;
/*   */     //   3653: getstatic f/uq.CD : I
/*   */     //   3656: invokevirtual nz : (I)I
/*   */     //   3659: invokevirtual position : (I)Ljava/nio/Buffer;
/*   */     //   3662: pop
/*   */     //   3663: getfield wJ : Lf/uq;
/*   */     //   3666: getstatic f/uq.Kd : I
/*   */     //   3669: invokevirtual nz : (I)I
/*   */     //   3672: istore_3
/*   */     //   3673: iconst_0
/*   */     //   3674: istore #4
/*   */     //   3676: iconst_0
/*   */     //   3677: istore #5
/*   */     //   3679: iload #5
/*   */     //   3681: iload_3
/*   */     //   3682: if_icmpge -> 3733
/*   */     //   3685: new f/gr0
/*   */     //   3688: dup
/*   */     //   3689: dup
/*   */     //   3690: astore #6
/*   */     //   3692: aload_2
/*   */     //   3693: invokespecial <init> : (Ljava/nio/ByteBuffer;)V
/*   */     //   3696: getfield vK0 : B
/*   */     //   3699: dup
/*   */     //   3700: istore #7
/*   */     //   3702: iload #4
/*   */     //   3704: if_icmple -> 3711
/*   */     //   3707: iload #7
/*   */     //   3709: istore #4
/*   */     //   3711: iload #5
/*   */     //   3713: aload_1
/*   */     //   3714: getfield TF : Lf/qw0;
/*   */     //   3717: iload #5
/*   */     //   3719: aload #6
/*   */     //   3721: invokevirtual Vh0 : (SLjava/lang/Object;)Ljava/lang/Object;
/*   */     //   3724: pop
/*   */     //   3725: iconst_1
/*   */     //   3726: iadd
/*   */     //   3727: i2s
/*   */     //   3728: istore #5
/*   */     //   3730: goto -> 3679
/*   */     //   3733: aload_2
/*   */     //   3734: aload_0
/*   */     //   3735: getfield wJ : Lf/uq;
/*   */     //   3738: getstatic f/uq.CoM3 : I
/*   */     //   3741: invokevirtual nz : (I)I
/*   */     //   3744: invokevirtual position : (I)Ljava/nio/Buffer;
/*   */     //   3747: pop
/*   */     //   3748: iconst_0
/*   */     //   3749: istore_3
/*   */     //   3750: iload_3
/*   */     //   3751: iload #4
/*   */     //   3753: iconst_1
/*   */     //   3754: iadd
/*   */     //   3755: if_icmpge -> 3788
/*   */     //   3758: iload_3
/*   */     //   3759: aload_1
/*   */     //   3760: getfield V1 : Lf/ak;
/*   */     //   3763: iload_3
/*   */     //   3764: new f/ln0
/*   */     //   3767: dup
/*   */     //   3768: astore #5
/*   */     //   3770: iload_3
/*   */     //   3771: aload_2
/*   */     //   3772: invokespecial <init> : (BLjava/nio/ByteBuffer;)V
/*   */     //   3775: aload #5
/*   */     //   3777: invokevirtual VF : (BLjava/lang/Object;)Ljava/lang/Object;
/*   */     //   3780: pop
/*   */     //   3781: iconst_1
/*   */     //   3782: iadd
/*   */     //   3783: i2b
/*   */     //   3784: istore_3
/*   */     //   3785: goto -> 3750
/*   */     //   3788: aload_0
/*   */     //   3789: dup
/*   */     //   3790: dup2
/*   */     //   3791: getstatic f/AD.case : Lf/AD;
/*   */     //   3794: dup
/*   */     //   3795: astore #11
/*   */     //   3797: invokevirtual getClass : ()Ljava/lang/Class;
/*   */     //   3800: pop
/*   */     //   3801: new f/c9
/*   */     //   3804: dup
/*   */     //   3805: astore #12
/*   */     //   3807: aload_0
/*   */     //   3808: invokevirtual in : ()B
/*   */     //   3811: pop
/*   */     //   3812: invokespecial <init> : ()V
/*   */     //   3815: getfield wJ : Lf/uq;
/*   */     //   3818: getstatic f/uq.sW : I
/*   */     //   3821: invokevirtual nz : (I)I
/*   */     //   3824: istore_1
/*   */     //   3825: getfield wJ : Lf/uq;
/*   */     //   3828: getstatic f/uq.ga : I
/*   */     //   3831: invokevirtual nz : (I)I
/*   */     //   3834: istore #13
/*   */     //   3836: getfield wJ : Lf/uq;
/*   */     //   3839: getstatic f/uq.do0 : I
/*   */     //   3842: invokevirtual nz : (I)I
/*   */     //   3845: istore #14
/*   */     //   3847: invokestatic currentTimeMillis : ()J
/*   */     //   3850: pop2
/*   */     //   3851: invokevirtual pr : ()Ljava/nio/ByteBuffer;
/*   */     //   3854: dup
/*   */     //   3855: astore #15
/*   */     //   3857: iload_1
/*   */     //   3858: new java/util/HashMap
/*   */     //   3861: dup
/*   */     //   3862: astore #16
/*   */     //   3864: invokespecial <init> : ()V
/*   */     //   3867: invokevirtual position : (I)Ljava/nio/Buffer;
/*   */     //   3870: pop
/*   */     //   3871: aload #15
/*   */     //   3873: invokevirtual getInt : ()I
/*   */     //   3876: invokestatic tx0 : (I)I
/*   */     //   3879: dup
/*   */     //   3880: istore_1
/*   */     //   3881: iconst_1
/*   */     //   3882: if_icmpge -> 3888
/*   */     //   3885: goto -> 3927
/*   */     //   3888: aload #16
/*   */     //   3890: aload #15
/*   */     //   3892: dup
/*   */     //   3893: invokevirtual getShort : ()S
/*   */     //   3896: istore_2
/*   */     //   3897: invokevirtual getShort : ()S
/*   */     //   3900: pop
/*   */     //   3901: iload_2
/*   */     //   3902: getstatic f/aM0.Ij0 : Lf/aM0;
/*   */     //   3905: aload_0
/*   */     //   3906: invokevirtual pr : ()Ljava/nio/ByteBuffer;
/*   */     //   3909: astore_3
/*   */     //   3910: iconst_1
/*   */     //   3911: iload_1
/*   */     //   3912: aload_3
/*   */     //   3913: iconst_0
/*   */     //   3914: invokevirtual LY : (IILjava/nio/ByteBuffer;B)Lf/f1;
/*   */     //   3917: astore_1
/*   */     //   3918: invokestatic valueOf : (S)Ljava/lang/Short;
/*   */     //   3921: invokevirtual containsKey : (Ljava/lang/Object;)Z
/*   */     //   3924: ifeq -> 5093
/*   */     //   3927: aload #15
/*   */     //   3929: iload #13
/*   */     //   3931: invokevirtual position : (I)Ljava/nio/Buffer;
/*   */     //   3934: pop
/*   */     //   3935: iconst_0
/*   */     //   3936: istore_1
/*   */     //   3937: iload_1
/*   */     //   3938: iload #14
/*   */     //   3940: if_icmpge -> 4023
/*   */     //   3943: aload #15
/*   */     //   3945: invokevirtual getInt : ()I
/*   */     //   3948: invokestatic tx0 : (I)I
/*   */     //   3951: dup
/*   */     //   3952: istore_2
/*   */     //   3953: iflt -> 4023
/*   */     //   3956: iload_2
/*   */     //   3957: aload #15
/*   */     //   3959: invokevirtual limit : ()I
/*   */     //   3962: if_icmple -> 3968
/*   */     //   3965: goto -> 4023
/*   */     //   3968: aload #12
/*   */     //   3970: aload #15
/*   */     //   3972: dup
/*   */     //   3973: invokevirtual getShort : ()S
/*   */     //   3976: pop
/*   */     //   3977: invokevirtual getShort : ()S
/*   */     //   3980: istore_3
/*   */     //   3981: new f/U70
/*   */     //   3984: dup
/*   */     //   3985: dup
/*   */     //   3986: astore #4
/*   */     //   3988: new f/qJ0
/*   */     //   3991: dup
/*   */     //   3992: iload_2
/*   */     //   3993: aload_0
/*   */     //   3994: aload #16
/*   */     //   3996: iload_3
/*   */     //   3997: invokespecial <init> : (ILf/s40;Ljava/util/HashMap;S)V
/*   */     //   4000: invokespecial <init> : (Lf/N50;)V
/*   */     //   4003: iconst_1
/*   */     //   4004: putfield Gd0 : Z
/*   */     //   4007: getfield Nn0 : Lf/Ut0;
/*   */     //   4010: iload_1
/*   */     //   4011: aload #4
/*   */     //   4013: invokevirtual A3 : (ILjava/lang/Object;)Ljava/lang/Object;
/*   */     //   4016: pop
/*   */     //   4017: iinc #1, 1
/*   */     //   4020: goto -> 3937
/*   */     //   4023: aload_0
/*   */     //   4024: aload #11
/*   */     //   4026: getfield Hm : Lf/ak;
/*   */     //   4029: aload_0
/*   */     //   4030: invokevirtual in : ()B
/*   */     //   4033: aload #12
/*   */     //   4035: invokevirtual VF : (BLjava/lang/Object;)Ljava/lang/Object;
/*   */     //   4038: pop
/*   */     //   4039: getstatic f/wm0.y0 : Lf/wm0;
/*   */     //   4042: dup
/*   */     //   4043: astore_1
/*   */     //   4044: invokevirtual getClass : ()Ljava/lang/Class;
/*   */     //   4047: pop
/*   */     //   4048: invokevirtual pr : ()Ljava/nio/ByteBuffer;
/*   */     //   4051: dup
/*   */     //   4052: astore_2
/*   */     //   4053: aload_0
/*   */     //   4054: getfield wJ : Lf/uq;
/*   */     //   4057: getstatic f/uq.dM : I
/*   */     //   4060: invokevirtual nz : (I)I
/*   */     //   4063: invokevirtual position : (I)Ljava/nio/Buffer;
/*   */     //   4066: pop
/*   */     //   4067: new f/fH
/*   */     //   4070: dup
/*   */     //   4071: astore_3
/*   */     //   4072: invokespecial <init> : ()V
/*   */     //   4075: new f/fH
/*   */     //   4078: dup
/*   */     //   4079: astore #4
/*   */     //   4081: invokespecial <init> : ()V
/*   */     //   4084: iconst_0
/*   */     //   4085: istore #5
/*   */     //   4087: iload #5
/*   */     //   4089: aload_0
/*   */     //   4090: getfield wJ : Lf/uq;
/*   */     //   4093: getstatic f/uq.Dk0 : I
/*   */     //   4096: invokevirtual nz : (I)I
/*   */     //   4099: if_icmpge -> 4349
/*   */     //   4102: aload_2
/*   */     //   4103: invokevirtual getInt : ()I
/*   */     //   4106: invokestatic tx0 : (I)I
/*   */     //   4109: dup
/*   */     //   4110: istore #6
/*   */     //   4112: iconst_1
/*   */     //   4113: if_icmpge -> 4119
/*   */     //   4116: goto -> 4349
/*   */     //   4119: aload_1
/*   */     //   4120: aload_2
/*   */     //   4121: invokevirtual getInt : ()I
/*   */     //   4124: invokestatic tx0 : (I)I
/*   */     //   4127: istore #7
/*   */     //   4129: getfield Rv0 : Lf/qw0;
/*   */     //   4132: iload #5
/*   */     //   4134: invokevirtual Fb : (S)Z
/*   */     //   4137: ifeq -> 4143
/*   */     //   4140: goto -> 4339
/*   */     //   4143: aload_3
/*   */     //   4144: iload #6
/*   */     //   4146: i2l
/*   */     //   4147: bipush #32
/*   */     //   4149: lshl
/*   */     //   4150: iload #7
/*   */     //   4152: i2l
/*   */     //   4153: ldc2_w 4294967295
/*   */     //   4156: land
/*   */     //   4157: lor
/*   */     //   4158: dup2
/*   */     //   4159: lstore #8
/*   */     //   4161: invokevirtual C6 : (J)Z
/*   */     //   4164: ifeq -> 4240
/*   */     //   4167: aload_3
/*   */     //   4168: lload #8
/*   */     //   4170: invokevirtual mm : (J)I
/*   */     //   4173: dup
/*   */     //   4174: istore #6
/*   */     //   4176: ifge -> 4185
/*   */     //   4179: aconst_null
/*   */     //   4180: astore #6
/*   */     //   4182: goto -> 4194
/*   */     //   4185: aload_3
/*   */     //   4186: getfield Mx0 : [Ljava/lang/Object;
/*   */     //   4189: iload #6
/*   */     //   4191: aaload
/*   */     //   4192: astore #6
/*   */     //   4194: aload #4
/*   */     //   4196: aload #6
/*   */     //   4198: checkcast f/U70
/*   */     //   4201: astore #6
/*   */     //   4203: lload #8
/*   */     //   4205: invokevirtual mm : (J)I
/*   */     //   4208: dup
/*   */     //   4209: istore #7
/*   */     //   4211: ifge -> 4220
/*   */     //   4214: aconst_null
/*   */     //   4215: astore #7
/*   */     //   4217: goto -> 4230
/*   */     //   4220: aload #4
/*   */     //   4222: getfield Mx0 : [Ljava/lang/Object;
/*   */     //   4225: iload #7
/*   */     //   4227: aaload
/*   */     //   4228: astore #7
/*   */     //   4230: aload #7
/*   */     //   4232: checkcast f/U70
/*   */     //   4235: astore #7
/*   */     //   4237: goto -> 4315
/*   */     //   4240: aload #4
/*   */     //   4242: aload_3
/*   */     //   4243: new f/U70
/*   */     //   4246: dup
/*   */     //   4247: astore #10
/*   */     //   4249: new f/aE0
/*   */     //   4252: dup
/*   */     //   4253: astore #11
/*   */     //   4255: aload_0
/*   */     //   4256: iload #6
/*   */     //   4258: iload #7
/*   */     //   4260: invokespecial <init> : (Lf/s40;II)V
/*   */     //   4263: aload #11
/*   */     //   4265: invokespecial <init> : (Lf/N50;)V
/*   */     //   4268: lload #8
/*   */     //   4270: aload #10
/*   */     //   4272: invokevirtual Gm : (JLjava/lang/Object;)V
/*   */     //   4275: new f/U70
/*   */     //   4278: dup
/*   */     //   4279: astore #11
/*   */     //   4281: new f/kH
/*   */     //   4284: dup
/*   */     //   4285: astore #12
/*   */     //   4287: aload_0
/*   */     //   4288: iload #6
/*   */     //   4290: iload #7
/*   */     //   4292: invokespecial <init> : (Lf/s40;II)V
/*   */     //   4295: aload #12
/*   */     //   4297: invokespecial <init> : (Lf/N50;)V
/*   */     //   4300: lload #8
/*   */     //   4302: aload #11
/*   */     //   4304: invokevirtual Gm : (JLjava/lang/Object;)V
/*   */     //   4307: aload #10
/*   */     //   4309: aload #11
/*   */     //   4311: astore #7
/*   */     //   4313: astore #6
/*   */     //   4315: aload_1
/*   */     //   4316: dup
/*   */     //   4317: getfield Rv0 : Lf/qw0;
/*   */     //   4320: iload #5
/*   */     //   4322: aload #6
/*   */     //   4324: invokevirtual Vh0 : (SLjava/lang/Object;)Ljava/lang/Object;
/*   */     //   4327: pop
/*   */     //   4328: getfield ii : Lf/qw0;
/*   */     //   4331: iload #5
/*   */     //   4333: aload #7
/*   */     //   4335: invokevirtual Vh0 : (SLjava/lang/Object;)Ljava/lang/Object;
/*   */     //   4338: pop
/*   */     //   4339: iload #5
/*   */     //   4341: iconst_1
/*   */     //   4342: iadd
/*   */     //   4343: i2s
/*   */     //   4344: istore #5
/*   */     //   4346: goto -> 4087
/*   */     //   4349: invokestatic ds0 : ()Lf/NL;
/*   */     //   4352: aload_0
/*   */     //   4353: invokevirtual oH : (Lf/s40;)V
/*   */     //   4356: invokestatic Kw0 : ()Lf/h90;
/*   */     //   4359: dup
/*   */     //   4360: astore_1
/*   */     //   4361: invokevirtual getClass : ()Ljava/lang/Class;
/*   */     //   4364: pop
/*   */     //   4365: new f/U70
/*   */     //   4368: dup
/*   */     //   4369: astore_2
/*   */     //   4370: new f/rj0
/*   */     //   4373: dup
/*   */     //   4374: aload_0
/*   */     //   4375: invokespecial <init> : (Lf/s40;)V
/*   */     //   4378: invokespecial <init> : (Lf/N50;)V
/*   */     //   4381: iconst_0
/*   */     //   4382: istore_3
/*   */     //   4383: iload_3
/*   */     //   4384: bipush #8
/*   */     //   4386: if_icmpge -> 4423
/*   */     //   4389: aload_1
/*   */     //   4390: getfield WY : [[Lf/zh0;
/*   */     //   4393: aload_0
/*   */     //   4394: invokevirtual in : ()B
/*   */     //   4397: aaload
/*   */     //   4398: iload_3
/*   */     //   4399: new f/zh0
/*   */     //   4402: dup
/*   */     //   4403: aload_2
/*   */     //   4404: iload_3
/*   */     //   4405: bipush #16
/*   */     //   4407: imul
/*   */     //   4408: iconst_0
/*   */     //   4409: bipush #16
/*   */     //   4411: bipush #16
/*   */     //   4413: invokespecial <init> : (Lf/U70;IIII)V
/*   */     //   4416: aastore
/*   */     //   4417: iinc #3, 1
/*   */     //   4420: goto -> 4383
/*   */     //   4423: aload_0
/*   */     //   4424: invokevirtual in : ()B
/*   */     //   4427: dup
/*   */     //   4428: istore_2
/*   */     //   4429: ifeq -> 4466
/*   */     //   4432: iload_2
/*   */     //   4433: iconst_1
/*   */     //   4434: if_icmpeq -> 4440
/*   */     //   4437: goto -> 4540
/*   */     //   4440: aload_1
/*   */     //   4441: new f/U70
/*   */     //   4444: dup
/*   */     //   4445: astore_1
/*   */     //   4446: new f/wH
/*   */     //   4449: dup
/*   */     //   4450: astore_2
/*   */     //   4451: aload_0
/*   */     //   4452: invokespecial <init> : (Lf/s40;)V
/*   */     //   4455: aload_2
/*   */     //   4456: invokespecial <init> : (Lf/N50;)V
/*   */     //   4459: aload_1
/*   */     //   4460: putfield yH : Lf/U70;
/*   */     //   4463: goto -> 4540
/*   */     //   4466: aload_1
/*   */     //   4467: new f/U70
/*   */     //   4470: dup
/*   */     //   4471: astore_2
/*   */     //   4472: new f/qM
/*   */     //   4475: dup
/*   */     //   4476: aload_0
/*   */     //   4477: invokespecial <init> : (Lf/s40;)V
/*   */     //   4480: invokespecial <init> : (Lf/N50;)V
/*   */     //   4483: bipush #16
/*   */     //   4485: anewarray f/zh0
/*   */     //   4488: putfield cA : [Lf/zh0;
/*   */     //   4491: iconst_0
/*   */     //   4492: istore_3
/*   */     //   4493: iload_3
/*   */     //   4494: aload_1
/*   */     //   4495: getfield cA : [Lf/zh0;
/*   */     //   4498: dup
/*   */     //   4499: astore #4
/*   */     //   4501: arraylength
/*   */     //   4502: if_icmpge -> 4540
/*   */     //   4505: aload #4
/*   */     //   4507: new f/zh0
/*   */     //   4510: dup
/*   */     //   4511: astore #4
/*   */     //   4513: iload_3
/*   */     //   4514: bipush #16
/*   */     //   4516: imul
/*   */     //   4517: istore #5
/*   */     //   4519: aload_2
/*   */     //   4520: iconst_0
/*   */     //   4521: iload #5
/*   */     //   4523: bipush #16
/*   */     //   4525: bipush #16
/*   */     //   4527: invokespecial <init> : (Lf/U70;IIII)V
/*   */     //   4530: iload_3
/*   */     //   4531: aload #4
/*   */     //   4533: aastore
/*   */     //   4534: iinc #3, 1
/*   */     //   4537: goto -> 4493
/*   */     //   4540: aload_0
/*   */     //   4541: dup
/*   */     //   4542: getstatic f/RP.fB0 : Lf/RP;
/*   */     //   4545: dup
/*   */     //   4546: astore_1
/*   */     //   4547: invokevirtual getClass : ()Ljava/lang/Class;
/*   */     //   4550: pop
/*   */     //   4551: invokevirtual pr : ()Ljava/nio/ByteBuffer;
/*   */     //   4554: astore_2
/*   */     //   4555: invokevirtual in : ()B
/*   */     //   4558: iconst_1
/*   */     //   4559: if_icmpne -> 4666
/*   */     //   4562: aload_1
/*   */     //   4563: new f/Wf
/*   */     //   4566: dup
/*   */     //   4567: astore_3
/*   */     //   4568: aload_0
/*   */     //   4569: getfield wJ : Lf/uq;
/*   */     //   4572: getstatic f/uq.EU : I
/*   */     //   4575: invokevirtual nz : (I)I
/*   */     //   4578: iconst_1
/*   */     //   4579: bipush #8
/*   */     //   4581: iconst_1
/*   */     //   4582: aload_2
/*   */     //   4583: invokespecial <init> : (IIIILjava/nio/ByteBuffer;)V
/*   */     //   4586: iconst_4
/*   */     //   4587: anewarray f/zh0
/*   */     //   4590: putfield Up0 : [Lf/zh0;
/*   */     //   4593: iconst_0
/*   */     //   4594: istore_2
/*   */     //   4595: iload_2
/*   */     //   4596: aload_1
/*   */     //   4597: getfield Up0 : [Lf/zh0;
/*   */     //   4600: dup
/*   */     //   4601: astore #4
/*   */     //   4603: arraylength
/*   */     //   4604: if_icmpge -> 4897
/*   */     //   4607: aload #4
/*   */     //   4609: iload_2
/*   */     //   4610: bipush #32
/*   */     //   4612: imul
/*   */     //   4613: istore #4
/*   */     //   4615: new f/zh0
/*   */     //   4618: dup
/*   */     //   4619: astore #5
/*   */     //   4621: new f/U70
/*   */     //   4624: dup
/*   */     //   4625: astore #6
/*   */     //   4627: new f/dN
/*   */     //   4630: dup
/*   */     //   4631: astore #7
/*   */     //   4633: aload_3
/*   */     //   4634: aload_0
/*   */     //   4635: iload #4
/*   */     //   4637: invokespecial <init> : (Lf/Wf;Lf/s40;I)V
/*   */     //   4640: aload #7
/*   */     //   4642: invokespecial <init> : (Lf/N50;)V
/*   */     //   4645: aload #6
/*   */     //   4647: iconst_0
/*   */     //   4648: iconst_0
/*   */     //   4649: bipush #16
/*   */     //   4651: bipush #16
/*   */     //   4653: invokespecial <init> : (Lf/U70;IIII)V
/*   */     //   4656: iload_2
/*   */     //   4657: aload #5
/*   */     //   4659: aastore
/*   */     //   4660: iinc #2, 1
/*   */     //   4663: goto -> 4595
/*   */     //   4666: iconst_0
/*   */     //   4667: istore_3
/*   */     //   4668: iload_3
/*   */     //   4669: bipush #20
/*   */     //   4671: if_icmpge -> 4897
/*   */     //   4674: aload_1
/*   */     //   4675: dup
/*   */     //   4676: dup
/*   */     //   4677: aload_2
/*   */     //   4678: dup
/*   */     //   4679: dup2
/*   */     //   4680: dup2
/*   */     //   4681: iload_3
/*   */     //   4682: aload_0
/*   */     //   4683: getfield wJ : Lf/uq;
/*   */     //   4686: getstatic f/uq.ut0 : I
/*   */     //   4689: invokevirtual nz : (I)I
/*   */     //   4692: istore #4
/*   */     //   4694: bipush #20
/*   */     //   4696: imul
/*   */     //   4697: iload #4
/*   */     //   4699: iadd
/*   */     //   4700: invokevirtual position : (I)Ljava/nio/Buffer;
/*   */     //   4703: pop
/*   */     //   4704: invokevirtual getInt : ()I
/*   */     //   4707: invokestatic tx0 : (I)I
/*   */     //   4710: istore #4
/*   */     //   4712: invokevirtual getInt : ()I
/*   */     //   4715: invokestatic tx0 : (I)I
/*   */     //   4718: istore #5
/*   */     //   4720: invokevirtual getInt : ()I
/*   */     //   4723: invokestatic tx0 : (I)I
/*   */     //   4726: istore #6
/*   */     //   4728: invokevirtual getInt : ()I
/*   */     //   4731: invokestatic tx0 : (I)I
/*   */     //   4734: istore #7
/*   */     //   4736: invokevirtual getInt : ()I
/*   */     //   4739: invokestatic tx0 : (I)I
/*   */     //   4742: istore #8
/*   */     //   4744: iconst_0
/*   */     //   4745: istore #9
/*   */     //   4747: iconst_0
/*   */     //   4748: istore #10
/*   */     //   4750: new f/U70
/*   */     //   4753: dup
/*   */     //   4754: astore #11
/*   */     //   4756: new f/ni0
/*   */     //   4759: dup
/*   */     //   4760: aload_0
/*   */     //   4761: iload #4
/*   */     //   4763: iload #5
/*   */     //   4765: iload #8
/*   */     //   4767: iload #9
/*   */     //   4769: iload #10
/*   */     //   4771: invokespecial <init> : (Lf/s40;IIIIZ)V
/*   */     //   4774: invokespecial <init> : (Lf/N50;)V
/*   */     //   4777: getfield lu0 : Ljava/util/HashMap;
/*   */     //   4780: iload_3
/*   */     //   4781: invokestatic valueOf : (I)Ljava/lang/Integer;
/*   */     //   4784: aload #11
/*   */     //   4786: invokevirtual put : (Ljava/lang/Object;Ljava/lang/Object;)Ljava/lang/Object;
/*   */     //   4789: pop
/*   */     //   4790: getfield bh0 : Ljava/util/HashMap;
/*   */     //   4793: iload_3
/*   */     //   4794: invokestatic valueOf : (I)Ljava/lang/Integer;
/*   */     //   4797: new f/zh0
/*   */     //   4800: dup
/*   */     //   4801: aload #11
/*   */     //   4803: sipush #240
/*   */     //   4806: iconst_0
/*   */     //   4807: sipush #272
/*   */     //   4810: bipush #112
/*   */     //   4812: invokespecial <init> : (Lf/U70;IIII)V
/*   */     //   4815: invokevirtual put : (Ljava/lang/Object;Ljava/lang/Object;)Ljava/lang/Object;
/*   */     //   4818: pop
/*   */     //   4819: getfield On0 : Ljava/util/HashMap;
/*   */     //   4822: iload_3
/*   */     //   4823: invokestatic valueOf : (I)Ljava/lang/Integer;
/*   */     //   4826: iconst_2
/*   */     //   4827: istore #4
/*   */     //   4829: iconst_1
/*   */     //   4830: istore #5
/*   */     //   4832: new f/U70
/*   */     //   4835: dup
/*   */     //   4836: new f/ni0
/*   */     //   4839: dup
/*   */     //   4840: aload_0
/*   */     //   4841: iload #6
/*   */     //   4843: iload #7
/*   */     //   4845: iload #8
/*   */     //   4847: iload #4
/*   */     //   4849: iload #5
/*   */     //   4851: invokespecial <init> : (Lf/s40;IIIIZ)V
/*   */     //   4854: invokespecial <init> : (Lf/N50;)V
/*   */     //   4857: invokevirtual put : (Ljava/lang/Object;Ljava/lang/Object;)Ljava/lang/Object;
/*   */     //   4860: pop
/*   */     //   4861: iconst_2
/*   */     //   4862: istore #4
/*   */     //   4864: iconst_1
/*   */     //   4865: istore #5
/*   */     //   4867: new f/U70
/*   */     //   4870: new f/ni0
/*   */     //   4873: dup
/*   */     //   4874: aload_0
/*   */     //   4875: iload #6
/*   */     //   4877: iload #7
/*   */     //   4879: iload #8
/*   */     //   4881: iload #4
/*   */     //   4883: iload #5
/*   */     //   4885: invokespecial <init> : (Lf/s40;IIIIZ)V
/*   */     //   4888: invokespecial <init> : (Lf/N50;)V
/*   */     //   4891: iinc #3, 1
/*   */     //   4894: goto -> 4668
/*   */     //   4897: aload_0
/*   */     //   4898: dup
/*   */     //   4899: getstatic f/G00.Av0 : Lf/G00;
/*   */     //   4902: aload_0
/*   */     //   4903: invokevirtual CoM9 : (Lf/s40;)V
/*   */     //   4906: getstatic f/Nk.mS : Lf/Nk;
/*   */     //   4909: aload_0
/*   */     //   4910: invokevirtual aB0 : (Lf/s40;)V
/*   */     //   4913: invokestatic mH : ()Lf/iU;
/*   */     //   4916: aload_0
/*   */     //   4917: invokevirtual aD0 : (Lf/s40;)V
/*   */     //   4920: invokestatic QJ0 : ()Lf/WB0;
/*   */     //   4923: aload_0
/*   */     //   4924: invokevirtual GN : (Lf/s40;)V
/*   */     //   4927: getstatic f/Ps0.Ov0 : Lf/Ps0;
/*   */     //   4930: dup
/*   */     //   4931: astore_1
/*   */     //   4932: invokevirtual getClass : ()Ljava/lang/Class;
/*   */     //   4935: pop
/*   */     //   4936: invokevirtual pr : ()Ljava/nio/ByteBuffer;
/*   */     //   4939: dup
/*   */     //   4940: astore_2
/*   */     //   4941: aload_0
/*   */     //   4942: getfield wJ : Lf/uq;
/*   */     //   4945: getstatic f/uq.bI0 : I
/*   */     //   4948: invokevirtual nz : (I)I
/*   */     //   4951: invokevirtual position : (I)Ljava/nio/Buffer;
/*   */     //   4954: pop
/*   */     //   4955: invokevirtual pr : ()Ljava/nio/ByteBuffer;
/*   */     //   4958: astore_3
/*   */     //   4959: aload_2
/*   */     //   4960: invokevirtual getShort : ()S
/*   */     //   4963: dup
/*   */     //   4964: istore #4
/*   */     //   4966: iconst_1
/*   */     //   4967: if_icmpge -> 4973
/*   */     //   4970: goto -> 5078
/*   */     //   4973: aload_2
/*   */     //   4974: dup
/*   */     //   4975: dup
/*   */     //   4976: invokevirtual getShort : ()S
/*   */     //   4979: istore #5
/*   */     //   4981: invokevirtual getInt : ()I
/*   */     //   4984: istore #6
/*   */     //   4986: invokevirtual getInt : ()I
/*   */     //   4989: istore #7
/*   */     //   4991: iload #6
/*   */     //   4993: invokestatic pk0 : (I)Z
/*   */     //   4996: ifeq -> 5078
/*   */     //   4999: iload #7
/*   */     //   5001: invokestatic pk0 : (I)Z
/*   */     //   5004: ifne -> 5010
/*   */     //   5007: goto -> 5078
/*   */     //   5010: aload_1
/*   */     //   5011: aload_3
/*   */     //   5012: dup
/*   */     //   5013: iload #7
/*   */     //   5015: iload #6
/*   */     //   5017: invokestatic tx0 : (I)I
/*   */     //   5020: istore #6
/*   */     //   5022: invokestatic tx0 : (I)I
/*   */     //   5025: bipush #8
/*   */     //   5027: newarray byte
/*   */     //   5029: astore #7
/*   */     //   5031: invokevirtual position : (I)Ljava/nio/Buffer;
/*   */     //   5034: pop
/*   */     //   5035: aload #7
/*   */     //   5037: invokevirtual get : ([B)Ljava/nio/ByteBuffer;
/*   */     //   5040: pop
/*   */     //   5041: getfield np : Ljava/util/HashMap;
/*   */     //   5044: aload_0
/*   */     //   5045: invokevirtual in : ()B
/*   */     //   5048: sipush #10000
/*   */     //   5051: imul
/*   */     //   5052: iload #4
/*   */     //   5054: iadd
/*   */     //   5055: invokestatic valueOf : (I)Ljava/lang/Integer;
/*   */     //   5058: new f/wt0
/*   */     //   5061: dup
/*   */     //   5062: iload #5
/*   */     //   5064: iload #6
/*   */     //   5066: aload #7
/*   */     //   5068: invokespecial <init> : (SI[B)V
/*   */     //   5071: invokevirtual put : (Ljava/lang/Object;Ljava/lang/Object;)Ljava/lang/Object;
/*   */     //   5074: pop
/*   */     //   5075: goto -> 4959
/*   */     //   5078: aload_0
/*   */     //   5079: getstatic f/a80.Oz0 : Lf/a80;
/*   */     //   5082: aload_0
/*   */     //   5083: invokevirtual Kc : (Lf/s40;)V
/*   */     //   5086: invokevirtual in : ()B
/*   */     //   5089: invokestatic dw : (B)V
/*   */     //   5092: return
/*   */     //   5093: aload #16
/*   */     //   5095: iload_2
/*   */     //   5096: invokestatic valueOf : (S)Ljava/lang/Short;
/*   */     //   5099: aload_1
/*   */     //   5100: invokevirtual put : (Ljava/lang/Object;Ljava/lang/Object;)Ljava/lang/Object;
/*   */     //   5103: pop
/*   */     //   5104: goto -> 3871
/*   */     //   5107: iload #10
/*   */     //   5109: iload #5
/*   */     //   5111: aload #7
/*   */     //   5113: iload #9
/*   */     //   5115: aload #6
/*   */     //   5117: dup
/*   */     //   5118: iload #10
/*   */     //   5120: aload #4
/*   */     //   5122: invokevirtual getInt : ()I
/*   */     //   5125: pop
/*   */     //   5126: invokestatic tx0 : (I)I
/*   */     //   5129: invokevirtual position : (I)Ljava/nio/Buffer;
/*   */     //   5132: pop
/*   */     //   5133: invokestatic Vf0 : (Ljava/nio/ByteBuffer;)Ljava/lang/String;
/*   */     //   5136: aastore
/*   */     //   5137: if_icmple -> 5144
/*   */     //   5140: iload #10
/*   */     //   5142: istore #5
/*   */     //   5144: iinc #9, 1
/*   */     //   5147: goto -> 2577
/*   */     //   5150: aload_1
/*   */     //   5151: new f/ss
/*   */     //   5154: dup
/*   */     //   5155: iload_2
/*   */     //   5156: dup
/*   */     //   5157: iconst_1
/*   */     //   5158: iadd
/*   */     //   5159: i2b
/*   */     //   5160: istore_2
/*   */     //   5161: aload #7
/*   */     //   5163: invokespecial <init> : (B[Ljava/lang/String;)V
/*   */     //   5166: invokestatic Ss : (Lf/Vc0;Lf/ss;)V
/*   */     //   5169: goto -> 2516
/*   */     //   5172: new java/lang/ArrayIndexOutOfBoundsException
/*   */     //   5175: dup
/*   */     //   5176: iload #5
/*   */     //   5178: invokespecial <init> : (I)V
/*   */     //   5181: athrow
/*   */     //   5182: iload #4
/*   */     //   5184: iconst_1
/*   */     //   5185: iadd
/*   */     //   5186: dup
/*   */     //   5187: istore #6
/*   */     //   5189: aload_3
/*   */     //   5190: arraylength
/*   */     //   5191: if_icmple -> 5219
/*   */     //   5194: aload_3
/*   */     //   5195: dup
/*   */     //   5196: dup
/*   */     //   5197: arraylength
/*   */     //   5198: iconst_1
/*   */     //   5199: ishl
/*   */     //   5200: iload #6
/*   */     //   5202: invokestatic max : (II)I
/*   */     //   5205: newarray int
/*   */     //   5207: astore_3
/*   */     //   5208: arraylength
/*   */     //   5209: istore #7
/*   */     //   5211: iconst_0
/*   */     //   5212: aload_3
/*   */     //   5213: iconst_0
/*   */     //   5214: iload #7
/*   */     //   5216: invokestatic arraycopy : (Ljava/lang/Object;ILjava/lang/Object;II)V
/*   */     //   5219: aload_3
/*   */     //   5220: iload #4
/*   */     //   5222: iload #5
/*   */     //   5224: iastore
/*   */     //   5225: iload #6
/*   */     //   5227: istore #4
/*   */     //   5229: goto -> 2174
/*   */     //   5232: new java/lang/RuntimeException
/*   */     //   5235: dup
/*   */     //   5236: ldc_w 'Invalid map footer data, possible rom corruption'
/*   */     //   5239: invokespecial <init> : (Ljava/lang/String;)V
/*   */     //   5242: athrow
/*   */     //   5243: aload_3
/*   */     //   5244: iload #6
/*   */     //   5246: invokevirtual position : (I)Ljava/nio/Buffer;
/*   */     //   5249: pop
/*   */     //   5250: new f/ot
/*   */     //   5253: dup
/*   */     //   5254: dup
/*   */     //   5255: astore #7
/*   */     //   5257: iload #4
/*   */     //   5259: aload_3
/*   */     //   5260: aload_0
/*   */     //   5261: invokespecial <init> : (SLjava/nio/ByteBuffer;Lf/s40;)V
/*   */     //   5264: getfield iv0 : Z
/*   */     //   5267: ifeq -> 5308
/*   */     //   5270: aload #5
/*   */     //   5272: dup
/*   */     //   5273: getfield ob : Lf/qw0;
/*   */     //   5276: iload #4
/*   */     //   5278: aload #7
/*   */     //   5280: invokevirtual Vh0 : (SLjava/lang/Object;)Ljava/lang/Object;
/*   */     //   5283: pop
/*   */     //   5284: getfield Ze0 : Lf/Ut0;
/*   */     //   5287: iload #6
/*   */     //   5289: invokevirtual return : (I)Z
/*   */     //   5292: ifne -> 5308
/*   */     //   5295: aload #5
/*   */     //   5297: getfield Ze0 : Lf/Ut0;
/*   */     //   5300: iload #6
/*   */     //   5302: aload #7
/*   */     //   5304: invokevirtual A3 : (ILjava/lang/Object;)Ljava/lang/Object;
/*   */     //   5307: pop
/*   */     //   5308: iload #4
/*   */     //   5310: iconst_1
/*   */     //   5311: iadd
/*   */     //   5312: i2s
/*   */     //   5313: istore #4
/*   */     //   5315: goto -> 2119
/*   */     // Line number table:
/*   */     //   Java source line number -> byte code offset
/*   */     //   #1	-> 2
/*   */     //   #2	-> 7
/*   */     //   #3	-> 11
/*   */     //   #4	-> 27
/*   */     //   #5	-> 30
/*   */     //   #6	-> 190
/*   */     //   #7	-> 194
/*   */     //   #8	-> 198
/*   */     //   #9	-> 203
/*   */     //   #10	-> 211
/*   */     //   #11	-> 239
/*   */     //   #12	-> 315
/*   */     //   #13	-> 318
/*   */     //   #14	-> 328
/*   */     //   #15	-> 331
/*   */     //   #16	-> 365
/*   */     //   #17	-> 431
/*   */     //   #18	-> 434
/*   */     //   #19	-> 444
/*   */     //   #20	-> 447
/*   */     //   #21	-> 450
/*   */     //   #22	-> 464
/*   */     //   #23	-> 467
/*   */     //   #24	-> 483
/*   */     //   #25	-> 487
/*   */     //   #26	-> 511
/*   */     //   #27	-> 601
/*   */     //   #28	-> 605
/*   */     //   #29	-> 621
/*   */     //   #30	-> 624
/*   */     //   #31	-> 638
/*   */     //   #32	-> 641
/*   */     //   #33	-> 653
/*   */     //   #34	-> 656
/*   */     //   #35	-> 671
/*   */     //   #36	-> 675
/*   */     //   #37	-> 681
/*   */     //   #38	-> 685
/*   */     //   #39	-> 727
/*   */     //   #40	-> 731
/*   */     //   #41	-> 758
/*   */     //   #42	-> 761
/*   */     //   #43	-> 771
/*   */     //   #44	-> 774
/*   */     //   #45	-> 777
/*   */     //   #46	-> 794
/*   */     //   #47	-> 797
/*   */     //   #48	-> 811
/*   */     //   #49	-> 814
/*   */     //   #50	-> 824
/*   */     //   #51	-> 827
/*   */     //   #52	-> 830
/*   */     //   #53	-> 840
/*   */     //   #54	-> 843
/*   */     //   #55	-> 847
/*   */     //   #56	-> 850
/*   */     //   #57	-> 869
/*   */     //   #58	-> 872
/*   */     //   #59	-> 898
/*   */     //   #60	-> 901
/*   */     //   #61	-> 912
/*   */     //   #62	-> 915
/*   */     //   #63	-> 918
/*   */     //   #64	-> 927
/*   */     //   #65	-> 930
/*   */     //   #66	-> 957
/*   */     //   #67	-> 1022
/*   */     //   #68	-> 1025
/*   */     //   #69	-> 1035
/*   */     //   #70	-> 1038
/*   */     //   #71	-> 1041
/*   */     //   #72	-> 1051
/*   */     //   #73	-> 1054
/*   */     //   #74	-> 1057
/*   */     //   #75	-> 1067
/*   */     //   #76	-> 1070
/*   */     //   #77	-> 1073
/*   */     //   #78	-> 1082
/*   */     //   #79	-> 1117
/*   */     //   #80	-> 1120
/*   */     //   #81	-> 1131
/*   */     //   #82	-> 1134
/*   */     //   #83	-> 1145
/*   */     //   #84	-> 1150
/*   */     //   #85	-> 1154
/*   */     //   #86	-> 1160
/*   */     //   #87	-> 1163
/*   */     //   #88	-> 1177
/*   */     //   #89	-> 1180
/*   */     //   #90	-> 1218
/*   */     //   #91	-> 1282
/*   */     //   #92	-> 1333
/*   */     //   #93	-> 1345
/*   */     //   #94	-> 1396
/*   */     //   #95	-> 1494
/*   */     //   #96	-> 1504
/*   */     //   #97	-> 1507
/*   */     //   #98	-> 1511
/*   */     //   #99	-> 1519
/*   */     //   #100	-> 1522
/*   */     //   #101	-> 1535
/*   */     //   #102	-> 1555
/*   */     //   #103	-> 1565
/*   */     //   #104	-> 1592
/*   */     //   #105	-> 1604
/*   */     //   #106	-> 1684
/*   */     //   #107	-> 1688
/*   */     //   #108	-> 1696
/*   */     //   #109	-> 1699
/*   */     //   #110	-> 1713
/*   */     //   #111	-> 1716
/*   */     //   #112	-> 1719
/*   */     //   #113	-> 1722
/*   */     //   #114	-> 1727
/*   */     //   #115	-> 1730
/*   */     //   #116	-> 1752
/*   */     //   #117	-> 1755
/*   */     //   #118	-> 1769
/*   */     //   #119	-> 1772
/*   */     //   #120	-> 1789
/*   */     //   #121	-> 1792
/*   */     //   #122	-> 1832
/*   */     //   #123	-> 1842
/*   */     //   #124	-> 1847
/*   */     //   #125	-> 1851
/*   */     //   #126	-> 1854
/*   */     //   #127	-> 1875
/*   */     //   #128	-> 1879
/*   */     //   #129	-> 1890
/*   */     //   #130	-> 1893
/*   */     //   #131	-> 1922
/*   */     //   #132	-> 1925
/*   */     //   #133	-> 1941
/*   */     //   #134	-> 1946
/*   */     //   #135	-> 1950
/*   */     //   #136	-> 1956
/*   */     //   #137	-> 1959
/*   */     //   #138	-> 2051
/*   */     //   #139	-> 2055
/*   */     //   #140	-> 2061
/*   */     //   #141	-> 2072
/*   */     //   #142	-> 2077
/*   */     //   #143	-> 2081
/*   */     //   #144	-> 2093
/*   */     //   #145	-> 2096
/*   */     //   #146	-> 2153
/*   */     //   #147	-> 2156
/*   */     //   #148	-> 2168
/*   */     //   #149	-> 2175
/*   */     //   #150	-> 2194
/*   */     //   #151	-> 2217
/*   */     //   #152	-> 2223
/*   */     //   #153	-> 2265
/*   */     //   #154	-> 2268
/*   */     //   #155	-> 2445
/*   */     //   #156	-> 2450
/*   */     //   #157	-> 2454
/*   */     //   #158	-> 2457
/*   */     //   #159	-> 2500
/*   */     //   #160	-> 2504
/*   */     //   #161	-> 2599
/*   */     //   #162	-> 2602
/*   */     //   #163	-> 2615
/*   */     //   #164	-> 2618
/*   */     //   #165	-> 2640
/*   */     //   #166	-> 2643
/*   */     //   #167	-> 2764
/*   */     //   #168	-> 2769
/*   */     //   #169	-> 2787
/*   */     //   #170	-> 2792
/*   */     //   #171	-> 2796
/*   */     //   #172	-> 2813
/*   */     //   #173	-> 2816
/*   */     //   #174	-> 2924
/*   */     //   #175	-> 2944
/*   */     //   #176	-> 2949
/*   */     //   #177	-> 2966
/*   */     //   #178	-> 2987
/*   */     //   #179	-> 3004
/*   */     //   #180	-> 3009
/*   */     //   #181	-> 3030
/*   */     //   #182	-> 3033
/*   */     //   #183	-> 3107
/*   */     //   #184	-> 3143
/*   */     //   #185	-> 3165
/*   */     //   #186	-> 3168
/*   */     //   #187	-> 3263
/*   */     //   #188	-> 3267
/*   */     //   #189	-> 3295
/*   */     //   #190	-> 3298
/*   */     //   #191	-> 3354
/*   */     //   #192	-> 3357
/*   */     //   #193	-> 3366
/*   */     //   #194	-> 3369
/*   */     //   #195	-> 3378
/*   */     //   #196	-> 3381
/*   */     //   #197	-> 3390
/*   */     //   #198	-> 3393
/*   */     //   #199	-> 3480
/*   */     //   #200	-> 3485
/*   */     //   #201	-> 3507
/*   */     //   #202	-> 3537
/*   */     //   #203	-> 3542
/*   */     //   #204	-> 3570
/*   */     //   #205	-> 3575
/*   */     //   #206	-> 3579
/*   */     //   #207	-> 3596
/*   */     //   #208	-> 3599
/*   */     //   #209	-> 3650
/*   */     //   #210	-> 3653
/*   */     //   #211	-> 3663
/*   */     //   #212	-> 3666
/*   */     //   #213	-> 3696
/*   */     //   #214	-> 3714
/*   */     //   #215	-> 3735
/*   */     //   #216	-> 3738
/*   */     //   #217	-> 3791
/*   */     //   #218	-> 3797
/*   */     //   #219	-> 3801
/*   */     //   #220	-> 3815
/*   */     //   #221	-> 3818
/*   */     //   #222	-> 3825
/*   */     //   #223	-> 3828
/*   */     //   #224	-> 3836
/*   */     //   #225	-> 3839
/*   */     //   #226	-> 3902
/*   */     //   #227	-> 3906
/*   */     //   #228	-> 3914
/*   */     //   #229	-> 3918
/*   */     //   #230	-> 4004
/*   */     //   #231	-> 4007
/*   */     //   #232	-> 4026
/*   */     //   #233	-> 4039
/*   */     //   #234	-> 4044
/*   */     //   #235	-> 4048
/*   */     //   #236	-> 4054
/*   */     //   #237	-> 4057
/*   */     //   #238	-> 4090
/*   */     //   #239	-> 4093
/*   */     //   #240	-> 4134
/*   */     //   #241	-> 4161
/*   */     //   #242	-> 4170
/*   */     //   #243	-> 4198
/*   */     //   #244	-> 4205
/*   */     //   #245	-> 4232
/*   */     //   #246	-> 4349
/*   */     //   #247	-> 4365
/*   */     //   #248	-> 4424
/*   */     //   #249	-> 4441
/*   */     //   #250	-> 4467
/*   */     //   #251	-> 4542
/*   */     //   #252	-> 4547
/*   */     //   #253	-> 4551
/*   */     //   #254	-> 4569
/*   */     //   #255	-> 4572
/*   */     //   #256	-> 4683
/*   */     //   #257	-> 4686
/*   */     //   #258	-> 4750
/*   */     //   #259	-> 4777
/*   */     //   #260	-> 4832
/*   */     //   #261	-> 4857
/*   */     //   #262	-> 4867
/*   */     //   #263	-> 4899
/*   */     //   #264	-> 4903
/*   */     //   #265	-> 4906
/*   */     //   #266	-> 4910
/*   */     //   #267	-> 4927
/*   */     //   #268	-> 4932
/*   */     //   #269	-> 4936
/*   */     //   #270	-> 4942
/*   */     //   #271	-> 4945
/*   */     //   #272	-> 5079
/*   */     //   #273	-> 5096
/*   */     //   #274	-> 5122
/*   */     //   #275	-> 5172
/*   */     //   #276	-> 5190
/*   */     //   #277	-> 5224
/*   */     //   #278	-> 5232
/*   */     //   #279	-> 5289
/*   */     //   #280	-> 5297
/*   */     // Exception table:
/*   */     //   from	to	target	type
/*   */     //   1110	1113	1141	java/lang/Exception
/*   */     //   1116	1137	1141	java/lang/Exception
/*   */   } }


/* Location:              /Users/vnnsnnt/Documents/Codespace/JavaWorkspace/RedTrainer/src/main/java/org/trainer/client/PokeMMO.jar!/f/s40.class
 * Java compiler version: 8 (52.0)
 * JD-Core Version:       1.1.3
 */