/*  1 */ package f;public final class SB { public final String xH0; public final bg0 ll0; public int oJ0; public SB(String paramString, bg0 parambg0) { this.xH0 = paramString; this.ll0 = parambg0; } public final int Id(boolean paramBoolean) { try { int i; if (IO() == -1) { if (paramBoolean) return 0;  uF(-1); throw null; }  byte b = 0; while (true) { b++; IF(); if ((i = IO()) == -1) return b;  if (i == 44 && paramBoolean) { this.oJ0++; continue; }  break; }  uF(i); throw null; } catch (ParseException parseException) { throw this; } catch (Exception exception) { throw (ParseException)(new ParseException("Unable to execute", super.oJ0)).initCause(exception); }  } public final void IF() { kw0(); while (true) { int i; while ((i = IO()) != 43) { if (i != 45) return;  this.oJ0++; kw0(); bg0 bg02; Number number3 = (bg02 = this.ll0).tp(); Number number4;
/*  2 */         if (bg0.X5(number4 = this.ll0.tp()) || bg0.X5(number3)) {  } else {  }  if (false) { number3 = Float.valueOf(number4.floatValue() - number3.floatValue()); }
/*  3 */         else { number3 = Integer.valueOf(number4.intValue() - number3.intValue()); }  bg02
/*  4 */           .rk.add(number3); }  this
/*  5 */         .oJ0++; kw0(); bg0 bg01;
/*  6 */       Number number1 = (bg01 = this.ll0).tp(); Number number2;
/*  7 */       if (bg0.X5(number2 = this.ll0.tp()) || bg0.X5(number1)) {  } else {  }  if (false) { float f = number2.floatValue(); number1 = Float.valueOf(number1.floatValue() + f); }
/*  8 */       else { int j = number2.intValue(); number1 = Integer.valueOf(number1.intValue() + j); }  bg01
/*  9 */         .rk.add(number1); }  } public final void kw0() { rE(); while (true) { int i; while ((i = IO()) != 42) { if (i != 47) return;  this.oJ0++; rE(); bg0 bg02; Number number3 = (bg02 = this.ll0).tp(); Number number4; if (bg0.X5(number4 = this.ll0.tp()) || bg0.X5(number3)) {  } else {  }  if (false) { if (Math.abs(number3.floatValue()) != 0.0F) { number3 = Float.valueOf(number4.floatValue() / number3.floatValue()); } else { throw new IllegalStateException("division by zero"); }  } else if (number3.intValue() != 0) { number3 = Integer.valueOf(number4.intValue() / number3.intValue()); } else { throw new IllegalStateException("division by zero"); }  bg02.rk.add(number3); }  this.oJ0++; rE(); bg0 bg01; Number number1 = (bg01 = this.ll0).tp(); Number number2; if (bg0.X5(number2 = this.ll0.tp()) || bg0.X5(number1)) {  } else {  }  if (false) { float f = number2.floatValue(); number1 = Float.valueOf(number1.floatValue() * f); } else { int j = number2.intValue(); number1 = Integer.valueOf(number1.intValue() * j); }  bg01
/* 10 */         .rk.add(number1); }
/*    */      }
/*    */ 
/*    */   
/*    */   public final void rE() {
/*    */     // Byte code:
/*    */     //   0: aload_0
/*    */     //   1: invokevirtual IO : ()I
/*    */     //   4: dup
/*    */     //   5: istore_1
/*    */     //   6: i2c
/*    */     //   7: dup
/*    */     //   8: istore_2
/*    */     //   9: invokestatic isJavaIdentifierStart : (C)Z
/*    */     //   12: ifeq -> 1140
/*    */     //   15: aload_0
/*    */     //   16: getfield oJ0 : I
/*    */     //   19: istore_1
/*    */     //   20: aload_0
/*    */     //   21: getfield oJ0 : I
/*    */     //   24: aload_0
/*    */     //   25: getfield xH0 : Ljava/lang/String;
/*    */     //   28: invokevirtual length : ()I
/*    */     //   31: if_icmpge -> 64
/*    */     //   34: aload_0
/*    */     //   35: getfield xH0 : Ljava/lang/String;
/*    */     //   38: aload_0
/*    */     //   39: getfield oJ0 : I
/*    */     //   42: invokevirtual charAt : (I)C
/*    */     //   45: invokestatic isJavaIdentifierPart : (C)Z
/*    */     //   48: ifeq -> 64
/*    */     //   51: aload_0
/*    */     //   52: dup
/*    */     //   53: getfield oJ0 : I
/*    */     //   56: iconst_1
/*    */     //   57: iadd
/*    */     //   58: putfield oJ0 : I
/*    */     //   61: goto -> 20
/*    */     //   64: aload_0
/*    */     //   65: dup
/*    */     //   66: getfield xH0 : Ljava/lang/String;
/*    */     //   69: iload_1
/*    */     //   70: aload_0
/*    */     //   71: getfield oJ0 : I
/*    */     //   74: invokevirtual substring : (II)Ljava/lang/String;
/*    */     //   77: astore_1
/*    */     //   78: invokevirtual IO : ()I
/*    */     //   81: dup
/*    */     //   82: istore_2
/*    */     //   83: bipush #40
/*    */     //   85: if_icmpne -> 375
/*    */     //   88: aload_0
/*    */     //   89: dup
/*    */     //   90: dup
/*    */     //   91: getfield oJ0 : I
/*    */     //   94: iconst_1
/*    */     //   95: iadd
/*    */     //   96: putfield oJ0 : I
/*    */     //   99: iconst_1
/*    */     //   100: istore_2
/*    */     //   101: invokevirtual IF : ()V
/*    */     //   104: aload_0
/*    */     //   105: invokevirtual IO : ()I
/*    */     //   108: dup
/*    */     //   109: istore_3
/*    */     //   110: bipush #41
/*    */     //   112: if_icmpne -> 342
/*    */     //   115: iload_2
/*    */     //   116: aload_0
/*    */     //   117: dup
/*    */     //   118: dup
/*    */     //   119: getfield oJ0 : I
/*    */     //   122: iconst_1
/*    */     //   123: iadd
/*    */     //   124: putfield oJ0 : I
/*    */     //   127: getfield ll0 : Lf/bg0;
/*    */     //   130: dup
/*    */     //   131: astore_0
/*    */     //   132: invokevirtual getClass : ()Ljava/lang/Class;
/*    */     //   135: pop
/*    */     //   136: anewarray java/lang/Object
/*    */     //   139: astore_3
/*    */     //   140: iload_2
/*    */     //   141: istore #4
/*    */     //   143: iload #4
/*    */     //   145: dup
/*    */     //   146: iconst_m1
/*    */     //   147: iadd
/*    */     //   148: istore #4
/*    */     //   150: ifle -> 194
/*    */     //   153: aload_0
/*    */     //   154: getfield rk : Ljava/util/ArrayList;
/*    */     //   157: invokevirtual size : ()I
/*    */     //   160: dup
/*    */     //   161: istore #5
/*    */     //   163: ifeq -> 184
/*    */     //   166: aload_3
/*    */     //   167: iload #4
/*    */     //   169: aload_0
/*    */     //   170: getfield rk : Ljava/util/ArrayList;
/*    */     //   173: iload #5
/*    */     //   175: iconst_1
/*    */     //   176: isub
/*    */     //   177: invokevirtual remove : (I)Ljava/lang/Object;
/*    */     //   180: aastore
/*    */     //   181: goto -> 143
/*    */     //   184: new java/lang/IllegalStateException
/*    */     //   187: dup
/*    */     //   188: ldc 'stack underflow'
/*    */     //   190: invokespecial <init> : (Ljava/lang/String;)V
/*    */     //   193: athrow
/*    */     //   194: aload_0
/*    */     //   195: getfield Ud0 : Ljava/util/HashMap;
/*    */     //   198: aload_1
/*    */     //   199: invokevirtual get : (Ljava/lang/Object;)Ljava/lang/Object;
/*    */     //   202: checkcast f/wk0
/*    */     //   205: dup
/*    */     //   206: astore_1
/*    */     //   207: ifnull -> 332
/*    */     //   210: iconst_0
/*    */     //   211: istore #4
/*    */     //   213: iload #4
/*    */     //   215: iload_2
/*    */     //   216: if_icmpge -> 280
/*    */     //   219: aload_3
/*    */     //   220: iload #4
/*    */     //   222: aaload
/*    */     //   223: instanceof java/lang/Integer
/*    */     //   226: ifne -> 274
/*    */     //   229: iload_2
/*    */     //   230: newarray float
/*    */     //   232: astore #4
/*    */     //   234: iconst_0
/*    */     //   235: istore #5
/*    */     //   237: iload #5
/*    */     //   239: iload_2
/*    */     //   240: if_icmpge -> 264
/*    */     //   243: aload #4
/*    */     //   245: iload #5
/*    */     //   247: aload_3
/*    */     //   248: iload #5
/*    */     //   250: aaload
/*    */     //   251: checkcast java/lang/Number
/*    */     //   254: invokevirtual floatValue : ()F
/*    */     //   257: fastore
/*    */     //   258: iinc #5, 1
/*    */     //   261: goto -> 237
/*    */     //   264: aload_1
/*    */     //   265: aload #4
/*    */     //   267: invokevirtual F5 : ([F)Ljava/lang/Float;
/*    */     //   270: astore_1
/*    */     //   271: goto -> 322
/*    */     //   274: iinc #4, 1
/*    */     //   277: goto -> 213
/*    */     //   280: iload_2
/*    */     //   281: newarray int
/*    */     //   283: astore #4
/*    */     //   285: iconst_0
/*    */     //   286: istore #5
/*    */     //   288: iload #5
/*    */     //   290: iload_2
/*    */     //   291: if_icmpge -> 315
/*    */     //   294: aload #4
/*    */     //   296: iload #5
/*    */     //   298: aload_3
/*    */     //   299: iload #5
/*    */     //   301: aaload
/*    */     //   302: checkcast java/lang/Number
/*    */     //   305: invokevirtual intValue : ()I
/*    */     //   308: iastore
/*    */     //   309: iinc #5, 1
/*    */     //   312: goto -> 288
/*    */     //   315: aload_1
/*    */     //   316: aload #4
/*    */     //   318: invokevirtual Sx : ([I)Ljava/lang/Integer;
/*    */     //   321: astore_1
/*    */     //   322: aload_0
/*    */     //   323: getfield rk : Ljava/util/ArrayList;
/*    */     //   326: aload_1
/*    */     //   327: invokevirtual add : (Ljava/lang/Object;)Z
/*    */     //   330: pop
/*    */     //   331: return
/*    */     //   332: new java/lang/IllegalArgumentException
/*    */     //   335: dup
/*    */     //   336: ldc 'Unknown function'
/*    */     //   338: invokespecial <init> : (Ljava/lang/String;)V
/*    */     //   341: athrow
/*    */     //   342: iload_3
/*    */     //   343: bipush #44
/*    */     //   345: if_icmpne -> 368
/*    */     //   348: aload_0
/*    */     //   349: dup
/*    */     //   350: dup
/*    */     //   351: getfield oJ0 : I
/*    */     //   354: iconst_1
/*    */     //   355: iadd
/*    */     //   356: putfield oJ0 : I
/*    */     //   359: iinc #2, 1
/*    */     //   362: invokevirtual IF : ()V
/*    */     //   365: goto -> 104
/*    */     //   368: aload_0
/*    */     //   369: iload_3
/*    */     //   370: invokevirtual uF : (I)V
/*    */     //   373: aconst_null
/*    */     //   374: athrow
/*    */     //   375: aload_0
/*    */     //   376: getfield ll0 : Lf/bg0;
/*    */     //   379: checkcast f/Em
/*    */     //   382: dup
/*    */     //   383: astore_3
/*    */     //   384: getfield D50 : Lf/L00;
/*    */     //   387: astore #4
/*    */     //   389: aload #4
/*    */     //   391: ifnull -> 448
/*    */     //   394: aload #4
/*    */     //   396: getfield Fy : Lf/XR;
/*    */     //   399: aload_1
/*    */     //   400: invokevirtual VV : (Ljava/lang/Object;)Ljava/lang/Object;
/*    */     //   403: dup
/*    */     //   404: astore #5
/*    */     //   406: ifnull -> 412
/*    */     //   409: goto -> 425
/*    */     //   412: aload #4
/*    */     //   414: aload_1
/*    */     //   415: iconst_0
/*    */     //   416: invokevirtual mn0 : (Ljava/lang/String;Z)Lf/nY;
/*    */     //   419: dup
/*    */     //   420: astore #5
/*    */     //   422: ifnull -> 438
/*    */     //   425: aload_3
/*    */     //   426: getfield rk : Ljava/util/ArrayList;
/*    */     //   429: aload #5
/*    */     //   431: invokevirtual add : (Ljava/lang/Object;)Z
/*    */     //   434: pop
/*    */     //   435: goto -> 501
/*    */     //   438: aload #4
/*    */     //   440: getfield Bf0 : Lf/L00;
/*    */     //   443: astore #4
/*    */     //   445: goto -> 389
/*    */     //   448: aload_3
/*    */     //   449: getfield kN : Lf/dS;
/*    */     //   452: getfield ld0 : Lf/q80;
/*    */     //   455: getfield Fy : Lf/XR;
/*    */     //   458: aload_1
/*    */     //   459: invokevirtual VV : (Ljava/lang/Object;)Ljava/lang/Object;
/*    */     //   462: dup
/*    */     //   463: astore #4
/*    */     //   465: ifnull -> 471
/*    */     //   468: goto -> 491
/*    */     //   471: aload_3
/*    */     //   472: getfield kN : Lf/dS;
/*    */     //   475: getfield cOm1 : Ljava/util/HashMap;
/*    */     //   478: aload_1
/*    */     //   479: invokevirtual get : (Ljava/lang/Object;)Ljava/lang/Object;
/*    */     //   482: checkcast f/pe
/*    */     //   485: dup
/*    */     //   486: astore #4
/*    */     //   488: ifnull -> 1125
/*    */     //   491: aload_3
/*    */     //   492: getfield rk : Ljava/util/ArrayList;
/*    */     //   495: aload #4
/*    */     //   497: invokevirtual add : (Ljava/lang/Object;)Z
/*    */     //   500: pop
/*    */     //   501: iload_2
/*    */     //   502: bipush #46
/*    */     //   504: if_icmpeq -> 513
/*    */     //   507: iload_2
/*    */     //   508: bipush #91
/*    */     //   510: if_icmpne -> 1684
/*    */     //   513: iload_2
/*    */     //   514: aload_0
/*    */     //   515: dup
/*    */     //   516: getfield oJ0 : I
/*    */     //   519: iconst_1
/*    */     //   520: iadd
/*    */     //   521: dup
/*    */     //   522: istore_1
/*    */     //   523: putfield oJ0 : I
/*    */     //   526: bipush #46
/*    */     //   528: if_icmpne -> 975
/*    */     //   531: aload_0
/*    */     //   532: getfield oJ0 : I
/*    */     //   535: aload_0
/*    */     //   536: getfield xH0 : Ljava/lang/String;
/*    */     //   539: invokevirtual length : ()I
/*    */     //   542: if_icmpge -> 575
/*    */     //   545: aload_0
/*    */     //   546: getfield xH0 : Ljava/lang/String;
/*    */     //   549: aload_0
/*    */     //   550: getfield oJ0 : I
/*    */     //   553: invokevirtual charAt : (I)C
/*    */     //   556: invokestatic isJavaIdentifierPart : (C)Z
/*    */     //   559: ifeq -> 575
/*    */     //   562: aload_0
/*    */     //   563: dup
/*    */     //   564: getfield oJ0 : I
/*    */     //   567: iconst_1
/*    */     //   568: iadd
/*    */     //   569: putfield oJ0 : I
/*    */     //   572: goto -> 531
/*    */     //   575: aload_0
/*    */     //   576: dup
/*    */     //   577: getfield xH0 : Ljava/lang/String;
/*    */     //   580: iload_1
/*    */     //   581: aload_0
/*    */     //   582: getfield oJ0 : I
/*    */     //   585: invokevirtual substring : (II)Ljava/lang/String;
/*    */     //   588: astore_1
/*    */     //   589: getfield ll0 : Lf/bg0;
/*    */     //   592: dup
/*    */     //   593: astore_2
/*    */     //   594: getfield rk : Ljava/util/ArrayList;
/*    */     //   597: invokevirtual size : ()I
/*    */     //   600: dup
/*    */     //   601: istore_3
/*    */     //   602: ifeq -> 965
/*    */     //   605: aload_2
/*    */     //   606: getfield rk : Ljava/util/ArrayList;
/*    */     //   609: iload_3
/*    */     //   610: iconst_1
/*    */     //   611: isub
/*    */     //   612: invokevirtual remove : (I)Ljava/lang/Object;
/*    */     //   615: dup
/*    */     //   616: astore_3
/*    */     //   617: ifnull -> 954
/*    */     //   620: aload_3
/*    */     //   621: instanceof f/L00
/*    */     //   624: ifeq -> 644
/*    */     //   627: aload_3
/*    */     //   628: checkcast f/L00
/*    */     //   631: aload_1
/*    */     //   632: invokevirtual XC0 : (Ljava/lang/String;)Lf/L00;
/*    */     //   635: dup
/*    */     //   636: astore #4
/*    */     //   638: ifnull -> 644
/*    */     //   641: goto -> 849
/*    */     //   644: aload_3
/*    */     //   645: instanceof f/q80
/*    */     //   648: ifeq -> 685
/*    */     //   651: aload_3
/*    */     //   652: checkcast f/q80
/*    */     //   655: getfield Fy : Lf/XR;
/*    */     //   658: aload_1
/*    */     //   659: invokevirtual VV : (Ljava/lang/Object;)Ljava/lang/Object;
/*    */     //   662: dup
/*    */     //   663: astore #4
/*    */     //   665: ifnull -> 671
/*    */     //   668: goto -> 849
/*    */     //   671: new java/lang/IllegalArgumentException
/*    */     //   674: dup
/*    */     //   675: ldc 'field not found: '
/*    */     //   677: aload_1
/*    */     //   678: invokestatic tF0 : (Ljava/lang/String;Ljava/lang/String;)Ljava/lang/String;
/*    */     //   681: invokespecial <init> : (Ljava/lang/String;)V
/*    */     //   684: athrow
/*    */     //   685: aload_3
/*    */     //   686: instanceof f/mX
/*    */     //   689: ifeq -> 738
/*    */     //   692: ldc 'border'
/*    */     //   694: aload_1
/*    */     //   695: invokevirtual equals : (Ljava/lang/Object;)Z
/*    */     //   698: ifeq -> 738
/*    */     //   701: aload_3
/*    */     //   702: aconst_null
/*    */     //   703: astore_1
/*    */     //   704: instanceof f/VK0
/*    */     //   707: ifeq -> 720
/*    */     //   710: aload_3
/*    */     //   711: checkcast f/VK0
/*    */     //   714: invokeinterface mJ0 : ()Lf/uE0;
/*    */     //   719: astore_1
/*    */     //   720: aload_1
/*    */     //   721: ifnull -> 730
/*    */     //   724: aload_1
/*    */     //   725: astore #4
/*    */     //   727: goto -> 849
/*    */     //   730: getstatic f/uE0.rs0 : Lf/uE0;
/*    */     //   733: astore #4
/*    */     //   735: goto -> 849
/*    */     //   738: aload_3
/*    */     //   739: invokevirtual getClass : ()Ljava/lang/Class;
/*    */     //   742: dup
/*    */     //   743: astore #4
/*    */     //   745: invokevirtual isArray : ()Z
/*    */     //   748: ifeq -> 772
/*    */     //   751: ldc_w 'length'
/*    */     //   754: aload_1
/*    */     //   755: invokevirtual equals : (Ljava/lang/Object;)Z
/*    */     //   758: ifeq -> 862
/*    */     //   761: aload_3
/*    */     //   762: invokestatic getLength : (Ljava/lang/Object;)I
/*    */     //   765: invokestatic valueOf : (I)Ljava/lang/Integer;
/*    */     //   768: astore_1
/*    */     //   769: goto -> 724
/*    */     //   772: aload #4
/*    */     //   774: aload_1
/*    */     //   775: invokestatic Ow : (Ljava/lang/Class;Ljava/lang/String;)Ljava/lang/reflect/Method;
/*    */     //   778: dup
/*    */     //   779: astore #5
/*    */     //   781: ifnonnull -> 829
/*    */     //   784: aload #4
/*    */     //   786: invokevirtual getInterfaces : ()[Ljava/lang/Class;
/*    */     //   789: dup
/*    */     //   790: astore #6
/*    */     //   792: arraylength
/*    */     //   793: istore #7
/*    */     //   795: iconst_0
/*    */     //   796: istore #8
/*    */     //   798: iload #8
/*    */     //   800: iload #7
/*    */     //   802: if_icmpge -> 829
/*    */     //   805: aload #6
/*    */     //   807: iload #8
/*    */     //   809: aaload
/*    */     //   810: aload_1
/*    */     //   811: invokestatic Ow : (Ljava/lang/Class;Ljava/lang/String;)Ljava/lang/reflect/Method;
/*    */     //   814: dup
/*    */     //   815: astore #5
/*    */     //   817: ifnull -> 823
/*    */     //   820: goto -> 829
/*    */     //   823: iinc #8, 1
/*    */     //   826: goto -> 798
/*    */     //   829: aload #5
/*    */     //   831: ifnull -> 862
/*    */     //   834: aload #5
/*    */     //   836: iconst_0
/*    */     //   837: anewarray java/lang/Object
/*    */     //   840: aload_3
/*    */     //   841: swap
/*    */     //   842: invokevirtual invoke : (Ljava/lang/Object;[Ljava/lang/Object;)Ljava/lang/Object;
/*    */     //   845: astore_1
/*    */     //   846: goto -> 724
/*    */     //   849: aload_2
/*    */     //   850: getfield rk : Ljava/util/ArrayList;
/*    */     //   853: aload #4
/*    */     //   855: invokevirtual add : (Ljava/lang/Object;)Z
/*    */     //   858: pop
/*    */     //   859: goto -> 1065
/*    */     //   862: new java/lang/IllegalStateException
/*    */     //   865: dup
/*    */     //   866: new java/lang/StringBuilder
/*    */     //   869: dup
/*    */     //   870: invokespecial <init> : ()V
/*    */     //   873: ldc_w 'unknown field ''
/*    */     //   876: invokevirtual append : (Ljava/lang/String;)Ljava/lang/StringBuilder;
/*    */     //   879: aload_1
/*    */     //   880: invokevirtual append : (Ljava/lang/String;)Ljava/lang/StringBuilder;
/*    */     //   883: ldc_w '' of class ''
/*    */     //   886: invokevirtual append : (Ljava/lang/String;)Ljava/lang/StringBuilder;
/*    */     //   889: aload #4
/*    */     //   891: invokevirtual append : (Ljava/lang/Object;)Ljava/lang/StringBuilder;
/*    */     //   894: ldc_w '''
/*    */     //   897: invokevirtual append : (Ljava/lang/String;)Ljava/lang/StringBuilder;
/*    */     //   900: invokevirtual toString : ()Ljava/lang/String;
/*    */     //   903: invokespecial <init> : (Ljava/lang/String;)V
/*    */     //   906: athrow
/*    */     //   907: astore_0
/*    */     //   908: new java/lang/IllegalStateException
/*    */     //   911: dup
/*    */     //   912: new java/lang/StringBuilder
/*    */     //   915: dup
/*    */     //   916: invokespecial <init> : ()V
/*    */     //   919: ldc_w 'error accessing field ''
/*    */     //   922: invokevirtual append : (Ljava/lang/String;)Ljava/lang/StringBuilder;
/*    */     //   925: aload_1
/*    */     //   926: invokevirtual append : (Ljava/lang/String;)Ljava/lang/StringBuilder;
/*    */     //   929: ldc_w '' of class ''
/*    */     //   932: invokevirtual append : (Ljava/lang/String;)Ljava/lang/StringBuilder;
/*    */     //   935: aload #4
/*    */     //   937: invokevirtual append : (Ljava/lang/Object;)Ljava/lang/StringBuilder;
/*    */     //   940: ldc_w '''
/*    */     //   943: invokevirtual append : (Ljava/lang/String;)Ljava/lang/StringBuilder;
/*    */     //   946: invokevirtual toString : ()Ljava/lang/String;
/*    */     //   949: aload_0
/*    */     //   950: invokespecial <init> : (Ljava/lang/String;Ljava/lang/Throwable;)V
/*    */     //   953: athrow
/*    */     //   954: new java/lang/IllegalStateException
/*    */     //   957: dup
/*    */     //   958: ldc_w 'null pointer'
/*    */     //   961: invokespecial <init> : (Ljava/lang/String;)V
/*    */     //   964: athrow
/*    */     //   965: new java/lang/IllegalStateException
/*    */     //   968: dup
/*    */     //   969: ldc 'stack underflow'
/*    */     //   971: invokespecial <init> : (Ljava/lang/String;)V
/*    */     //   974: athrow
/*    */     //   975: aload_0
/*    */     //   976: dup
/*    */     //   977: invokevirtual rE : ()V
/*    */     //   980: invokevirtual IO : ()I
/*    */     //   983: dup
/*    */     //   984: istore_1
/*    */     //   985: bipush #93
/*    */     //   987: if_icmpne -> 1118
/*    */     //   990: aload_0
/*    */     //   991: dup
/*    */     //   992: dup
/*    */     //   993: getfield oJ0 : I
/*    */     //   996: iconst_1
/*    */     //   997: iadd
/*    */     //   998: putfield oJ0 : I
/*    */     //   1001: getfield ll0 : Lf/bg0;
/*    */     //   1004: dup
/*    */     //   1005: dup
/*    */     //   1006: astore_1
/*    */     //   1007: invokevirtual tp : ()Ljava/lang/Number;
/*    */     //   1010: astore_2
/*    */     //   1011: getfield rk : Ljava/util/ArrayList;
/*    */     //   1014: invokevirtual size : ()I
/*    */     //   1017: dup
/*    */     //   1018: istore_3
/*    */     //   1019: ifeq -> 1108
/*    */     //   1022: aload_1
/*    */     //   1023: getfield rk : Ljava/util/ArrayList;
/*    */     //   1026: iload_3
/*    */     //   1027: iconst_1
/*    */     //   1028: isub
/*    */     //   1029: invokevirtual remove : (I)Ljava/lang/Object;
/*    */     //   1032: dup
/*    */     //   1033: astore_3
/*    */     //   1034: ifnull -> 1097
/*    */     //   1037: aload_3
/*    */     //   1038: invokevirtual getClass : ()Ljava/lang/Class;
/*    */     //   1041: invokevirtual isArray : ()Z
/*    */     //   1044: ifeq -> 1086
/*    */     //   1047: aload_1
/*    */     //   1048: aload_3
/*    */     //   1049: aload_2
/*    */     //   1050: invokevirtual intValue : ()I
/*    */     //   1053: invokestatic get : (Ljava/lang/Object;I)Ljava/lang/Object;
/*    */     //   1056: astore_1
/*    */     //   1057: getfield rk : Ljava/util/ArrayList;
/*    */     //   1060: aload_1
/*    */     //   1061: invokevirtual add : (Ljava/lang/Object;)Z
/*    */     //   1064: pop
/*    */     //   1065: aload_0
/*    */     //   1066: invokevirtual IO : ()I
/*    */     //   1069: istore_2
/*    */     //   1070: goto -> 501
/*    */     //   1073: astore_0
/*    */     //   1074: new java/lang/IllegalStateException
/*    */     //   1077: dup
/*    */     //   1078: ldc_w 'array index out of bounds'
/*    */     //   1081: aload_0
/*    */     //   1082: invokespecial <init> : (Ljava/lang/String;Ljava/lang/Throwable;)V
/*    */     //   1085: athrow
/*    */     //   1086: new java/lang/IllegalStateException
/*    */     //   1089: dup
/*    */     //   1090: ldc_w 'array expected'
/*    */     //   1093: invokespecial <init> : (Ljava/lang/String;)V
/*    */     //   1096: athrow
/*    */     //   1097: new java/lang/IllegalStateException
/*    */     //   1100: dup
/*    */     //   1101: ldc_w 'null pointer'
/*    */     //   1104: invokespecial <init> : (Ljava/lang/String;)V
/*    */     //   1107: athrow
/*    */     //   1108: new java/lang/IllegalStateException
/*    */     //   1111: dup
/*    */     //   1112: ldc 'stack underflow'
/*    */     //   1114: invokespecial <init> : (Ljava/lang/String;)V
/*    */     //   1117: athrow
/*    */     //   1118: aload_0
/*    */     //   1119: iload_1
/*    */     //   1120: invokevirtual uF : (I)V
/*    */     //   1123: aconst_null
/*    */     //   1124: athrow
/*    */     //   1125: new java/lang/IllegalArgumentException
/*    */     //   1128: dup
/*    */     //   1129: ldc_w 'variable not found: '
/*    */     //   1132: aload_1
/*    */     //   1133: invokestatic tF0 : (Ljava/lang/String;Ljava/lang/String;)Ljava/lang/String;
/*    */     //   1136: invokespecial <init> : (Ljava/lang/String;)V
/*    */     //   1139: athrow
/*    */     //   1140: iload_1
/*    */     //   1141: bipush #45
/*    */     //   1143: if_icmpne -> 1209
/*    */     //   1146: aload_0
/*    */     //   1147: dup
/*    */     //   1148: dup2
/*    */     //   1149: getfield oJ0 : I
/*    */     //   1152: iconst_1
/*    */     //   1153: iadd
/*    */     //   1154: putfield oJ0 : I
/*    */     //   1157: invokevirtual rE : ()V
/*    */     //   1160: getfield ll0 : Lf/bg0;
/*    */     //   1163: dup
/*    */     //   1164: astore_0
/*    */     //   1165: invokevirtual tp : ()Ljava/lang/Number;
/*    */     //   1168: dup
/*    */     //   1169: astore_1
/*    */     //   1170: invokestatic X5 : (Ljava/lang/Number;)Z
/*    */     //   1173: ifeq -> 1188
/*    */     //   1176: aload_1
/*    */     //   1177: invokevirtual floatValue : ()F
/*    */     //   1180: fneg
/*    */     //   1181: invokestatic valueOf : (F)Ljava/lang/Float;
/*    */     //   1184: astore_1
/*    */     //   1185: goto -> 1197
/*    */     //   1188: aload_1
/*    */     //   1189: invokevirtual intValue : ()I
/*    */     //   1192: ineg
/*    */     //   1193: invokestatic valueOf : (I)Ljava/lang/Integer;
/*    */     //   1196: astore_1
/*    */     //   1197: aload_0
/*    */     //   1198: getfield rk : Ljava/util/ArrayList;
/*    */     //   1201: aload_1
/*    */     //   1202: invokevirtual add : (Ljava/lang/Object;)Z
/*    */     //   1205: pop
/*    */     //   1206: goto -> 1684
/*    */     //   1209: iload_1
/*    */     //   1210: bipush #46
/*    */     //   1212: if_icmpeq -> 1281
/*    */     //   1215: iload_1
/*    */     //   1216: bipush #43
/*    */     //   1218: if_icmpeq -> 1281
/*    */     //   1221: iload_2
/*    */     //   1222: invokestatic isDigit : (C)Z
/*    */     //   1225: ifeq -> 1231
/*    */     //   1228: goto -> 1281
/*    */     //   1231: iload_1
/*    */     //   1232: bipush #40
/*    */     //   1234: if_icmpne -> 1684
/*    */     //   1237: aload_0
/*    */     //   1238: dup
/*    */     //   1239: dup2
/*    */     //   1240: getfield oJ0 : I
/*    */     //   1243: iconst_1
/*    */     //   1244: iadd
/*    */     //   1245: putfield oJ0 : I
/*    */     //   1248: invokevirtual IF : ()V
/*    */     //   1251: invokevirtual IO : ()I
/*    */     //   1254: dup
/*    */     //   1255: istore_1
/*    */     //   1256: bipush #41
/*    */     //   1258: if_icmpne -> 1274
/*    */     //   1261: aload_0
/*    */     //   1262: dup
/*    */     //   1263: getfield oJ0 : I
/*    */     //   1266: iconst_1
/*    */     //   1267: iadd
/*    */     //   1268: putfield oJ0 : I
/*    */     //   1271: goto -> 1684
/*    */     //   1274: aload_0
/*    */     //   1275: iload_1
/*    */     //   1276: invokevirtual uF : (I)V
/*    */     //   1279: aconst_null
/*    */     //   1280: athrow
/*    */     //   1281: aload_0
/*    */     //   1282: dup
/*    */     //   1283: dup
/*    */     //   1284: getfield xH0 : Ljava/lang/String;
/*    */     //   1287: invokevirtual length : ()I
/*    */     //   1290: istore_1
/*    */     //   1291: getfield oJ0 : I
/*    */     //   1294: istore_2
/*    */     //   1295: getfield xH0 : Ljava/lang/String;
/*    */     //   1298: iload_2
/*    */     //   1299: invokevirtual charAt : (I)C
/*    */     //   1302: dup
/*    */     //   1303: istore_3
/*    */     //   1304: bipush #43
/*    */     //   1306: if_icmpeq -> 1515
/*    */     //   1309: iload_3
/*    */     //   1310: bipush #48
/*    */     //   1312: if_icmpeq -> 1318
/*    */     //   1315: goto -> 1527
/*    */     //   1318: aload_0
/*    */     //   1319: getfield oJ0 : I
/*    */     //   1322: iconst_1
/*    */     //   1323: iadd
/*    */     //   1324: dup
/*    */     //   1325: istore_3
/*    */     //   1326: iload_1
/*    */     //   1327: if_icmpge -> 1527
/*    */     //   1330: aload_0
/*    */     //   1331: getfield xH0 : Ljava/lang/String;
/*    */     //   1334: iload_3
/*    */     //   1335: invokevirtual charAt : (I)C
/*    */     //   1338: bipush #120
/*    */     //   1340: if_icmpne -> 1527
/*    */     //   1343: aload_0
/*    */     //   1344: dup
/*    */     //   1345: dup2
/*    */     //   1346: getfield oJ0 : I
/*    */     //   1349: iconst_2
/*    */     //   1350: iadd
/*    */     //   1351: putfield oJ0 : I
/*    */     //   1354: getfield xH0 : Ljava/lang/String;
/*    */     //   1357: invokevirtual length : ()I
/*    */     //   1360: istore_1
/*    */     //   1361: getfield oJ0 : I
/*    */     //   1364: istore_2
/*    */     //   1365: aload_0
/*    */     //   1366: getfield oJ0 : I
/*    */     //   1369: dup
/*    */     //   1370: istore_3
/*    */     //   1371: iload_1
/*    */     //   1372: if_icmpge -> 1406
/*    */     //   1375: aload_0
/*    */     //   1376: getfield xH0 : Ljava/lang/String;
/*    */     //   1379: iload_3
/*    */     //   1380: invokevirtual charAt : (I)C
/*    */     //   1383: ldc_w '0123456789abcdefABCDEF'
/*    */     //   1386: swap
/*    */     //   1387: invokevirtual indexOf : (I)I
/*    */     //   1390: iflt -> 1406
/*    */     //   1393: aload_0
/*    */     //   1394: dup
/*    */     //   1395: getfield oJ0 : I
/*    */     //   1398: iconst_1
/*    */     //   1399: iadd
/*    */     //   1400: putfield oJ0 : I
/*    */     //   1403: goto -> 1365
/*    */     //   1406: aload_0
/*    */     //   1407: getfield oJ0 : I
/*    */     //   1410: dup
/*    */     //   1411: istore_3
/*    */     //   1412: iload_2
/*    */     //   1413: isub
/*    */     //   1414: bipush #8
/*    */     //   1416: if_icmpgt -> 1484
/*    */     //   1419: iload_3
/*    */     //   1420: iload_2
/*    */     //   1421: if_icmpne -> 1450
/*    */     //   1424: iload_3
/*    */     //   1425: iload_1
/*    */     //   1426: if_icmpge -> 1441
/*    */     //   1429: aload_0
/*    */     //   1430: getfield xH0 : Ljava/lang/String;
/*    */     //   1433: iload_3
/*    */     //   1434: invokevirtual charAt : (I)C
/*    */     //   1437: istore_1
/*    */     //   1438: goto -> 1443
/*    */     //   1441: iconst_m1
/*    */     //   1442: istore_1
/*    */     //   1443: aload_0
/*    */     //   1444: iload_1
/*    */     //   1445: invokevirtual uF : (I)V
/*    */     //   1448: aconst_null
/*    */     //   1449: athrow
/*    */     //   1450: aload_0
/*    */     //   1451: getfield ll0 : Lf/bg0;
/*    */     //   1454: aload_0
/*    */     //   1455: getfield xH0 : Ljava/lang/String;
/*    */     //   1458: iload_2
/*    */     //   1459: iload_3
/*    */     //   1460: invokevirtual substring : (II)Ljava/lang/String;
/*    */     //   1463: bipush #16
/*    */     //   1465: invokestatic parseLong : (Ljava/lang/String;I)J
/*    */     //   1468: l2i
/*    */     //   1469: invokestatic valueOf : (I)Ljava/lang/Integer;
/*    */     //   1472: astore_0
/*    */     //   1473: getfield rk : Ljava/util/ArrayList;
/*    */     //   1476: aload_0
/*    */     //   1477: invokevirtual add : (Ljava/lang/Object;)Z
/*    */     //   1480: pop
/*    */     //   1481: goto -> 1684
/*    */     //   1484: new java/text/ParseException
/*    */     //   1487: dup
/*    */     //   1488: aload_0
/*    */     //   1489: ldc_w 'Number to large at '
/*    */     //   1492: invokestatic df : (Ljava/lang/String;)Ljava/lang/StringBuilder;
/*    */     //   1495: aload_0
/*    */     //   1496: getfield oJ0 : I
/*    */     //   1499: invokevirtual append : (I)Ljava/lang/StringBuilder;
/*    */     //   1502: invokevirtual toString : ()Ljava/lang/String;
/*    */     //   1505: astore_0
/*    */     //   1506: getfield oJ0 : I
/*    */     //   1509: aload_0
/*    */     //   1510: swap
/*    */     //   1511: invokespecial <init> : (Ljava/lang/String;I)V
/*    */     //   1514: athrow
/*    */     //   1515: aload_0
/*    */     //   1516: dup
/*    */     //   1517: getfield oJ0 : I
/*    */     //   1520: iconst_1
/*    */     //   1521: iadd
/*    */     //   1522: dup
/*    */     //   1523: istore_2
/*    */     //   1524: putfield oJ0 : I
/*    */     //   1527: aload_0
/*    */     //   1528: getfield oJ0 : I
/*    */     //   1531: dup
/*    */     //   1532: istore_3
/*    */     //   1533: iload_1
/*    */     //   1534: if_icmpge -> 1564
/*    */     //   1537: aload_0
/*    */     //   1538: getfield xH0 : Ljava/lang/String;
/*    */     //   1541: iload_3
/*    */     //   1542: invokevirtual charAt : (I)C
/*    */     //   1545: invokestatic isDigit : (C)Z
/*    */     //   1548: ifeq -> 1564
/*    */     //   1551: aload_0
/*    */     //   1552: dup
/*    */     //   1553: getfield oJ0 : I
/*    */     //   1556: iconst_1
/*    */     //   1557: iadd
/*    */     //   1558: putfield oJ0 : I
/*    */     //   1561: goto -> 1527
/*    */     //   1564: aload_0
/*    */     //   1565: getfield oJ0 : I
/*    */     //   1568: dup
/*    */     //   1569: istore_3
/*    */     //   1570: iload_1
/*    */     //   1571: if_icmpge -> 1656
/*    */     //   1574: aload_0
/*    */     //   1575: getfield xH0 : Ljava/lang/String;
/*    */     //   1578: iload_3
/*    */     //   1579: invokevirtual charAt : (I)C
/*    */     //   1582: bipush #46
/*    */     //   1584: if_icmpne -> 1656
/*    */     //   1587: aload_0
/*    */     //   1588: getfield oJ0 : I
/*    */     //   1591: iconst_1
/*    */     //   1592: iadd
/*    */     //   1593: dup
/*    */     //   1594: istore_3
/*    */     //   1595: iload_1
/*    */     //   1596: aload_0
/*    */     //   1597: iload_3
/*    */     //   1598: putfield oJ0 : I
/*    */     //   1601: if_icmpge -> 1621
/*    */     //   1604: aload_0
/*    */     //   1605: getfield xH0 : Ljava/lang/String;
/*    */     //   1608: iload_3
/*    */     //   1609: invokevirtual charAt : (I)C
/*    */     //   1612: invokestatic isDigit : (C)Z
/*    */     //   1615: ifeq -> 1621
/*    */     //   1618: goto -> 1587
/*    */     //   1621: aload_0
/*    */     //   1622: getfield oJ0 : I
/*    */     //   1625: dup
/*    */     //   1626: istore_1
/*    */     //   1627: iload_2
/*    */     //   1628: isub
/*    */     //   1629: iconst_1
/*    */     //   1630: if_icmple -> 1649
/*    */     //   1633: aload_0
/*    */     //   1634: getfield xH0 : Ljava/lang/String;
/*    */     //   1637: iload_2
/*    */     //   1638: iload_1
/*    */     //   1639: invokevirtual substring : (II)Ljava/lang/String;
/*    */     //   1642: invokestatic valueOf : (Ljava/lang/String;)Ljava/lang/Float;
/*    */     //   1645: astore_1
/*    */     //   1646: goto -> 1672
/*    */     //   1649: aload_0
/*    */     //   1650: iconst_m1
/*    */     //   1651: invokevirtual uF : (I)V
/*    */     //   1654: aconst_null
/*    */     //   1655: athrow
/*    */     //   1656: aload_0
/*    */     //   1657: getfield xH0 : Ljava/lang/String;
/*    */     //   1660: iload_2
/*    */     //   1661: aload_0
/*    */     //   1662: getfield oJ0 : I
/*    */     //   1665: invokevirtual substring : (II)Ljava/lang/String;
/*    */     //   1668: invokestatic valueOf : (Ljava/lang/String;)Ljava/lang/Integer;
/*    */     //   1671: astore_1
/*    */     //   1672: aload_0
/*    */     //   1673: getfield ll0 : Lf/bg0;
/*    */     //   1676: getfield rk : Ljava/util/ArrayList;
/*    */     //   1679: aload_1
/*    */     //   1680: invokevirtual add : (Ljava/lang/Object;)Z
/*    */     //   1683: pop
/*    */     //   1684: return
/*    */     // Line number table:
/*    */     //   Java source line number -> byte code offset
/*    */     //   #1	-> 16
/*    */     //   #2	-> 78
/*    */     //   #3	-> 101
/*    */     //   #4	-> 136
/*    */     //   #5	-> 154
/*    */     //   #6	-> 180
/*    */     //   #7	-> 184
/*    */     //   #8	-> 195
/*    */     //   #9	-> 222
/*    */     //   #10	-> 323
/*    */     //   #11	-> 332
/*    */     //   #12	-> 351
/*    */     //   #13	-> 376
/*    */     //   #14	-> 384
/*    */     //   #15	-> 396
/*    */     //   #16	-> 416
/*    */     //   #17	-> 426
/*    */     //   #18	-> 440
/*    */     //   #19	-> 455
/*    */     //   #20	-> 459
/*    */     //   #21	-> 472
/*    */     //   #22	-> 475
/*    */     //   #23	-> 479
/*    */     //   #24	-> 492
/*    */     //   #25	-> 516
/*    */     //   #26	-> 532
/*    */     //   #27	-> 589
/*    */     //   #28	-> 594
/*    */     //   #29	-> 621
/*    */     //   #30	-> 655
/*    */     //   #31	-> 659
/*    */     //   #32	-> 671
/*    */     //   #33	-> 675
/*    */     //   #34	-> 681
/*    */     //   #35	-> 739
/*    */     //   #36	-> 850
/*    */     //   #37	-> 862
/*    */     //   #38	-> 954
/*    */     //   #39	-> 965
/*    */     //   #40	-> 977
/*    */     //   #41	-> 980
/*    */     //   #42	-> 1001
/*    */     //   #43	-> 1007
/*    */     //   #44	-> 1011
/*    */     //   #45	-> 1038
/*    */     //   #46	-> 1057
/*    */     //   #47	-> 1066
/*    */     //   #48	-> 1074
/*    */     //   #49	-> 1108
/*    */     //   #50	-> 1120
/*    */     //   #51	-> 1125
/*    */     //   #52	-> 1129
/*    */     //   #53	-> 1136
/*    */     //   #54	-> 1149
/*    */     //   #55	-> 1165
/*    */     //   #56	-> 1170
/*    */     //   #57	-> 1189
/*    */     //   #58	-> 1198
/*    */     //   #59	-> 1222
/*    */     //   #60	-> 1251
/*    */     //   #61	-> 1284
/*    */     //   #62	-> 1354
/*    */     //   #63	-> 1473
/*    */     //   #64	-> 1477
/*    */     //   #65	-> 1484
/*    */     //   #66	-> 1489
/*    */     //   #67	-> 1496
/*    */     //   #68	-> 1517
/*    */     //   #69	-> 1676
/*    */     //   #70	-> 1680
/*    */     // Exception table:
/*    */     //   from	to	target	type
/*    */     //   745	748	907	finally
/*    */     //   751	758	907	finally
/*    */     //   761	768	907	finally
/*    */     //   772	778	907	finally
/*    */     //   784	789	907	finally
/*    */     //   792	793	907	finally
/*    */     //   805	814	907	finally
/*    */     //   834	845	907	finally
/*    */     //   1047	1056	1073	java/lang/ArrayIndexOutOfBoundsException
/*    */     //   1057	1064	1073	java/lang/ArrayIndexOutOfBoundsException
/*    */   }
/*    */   
/*    */   public final int IO() {
/*    */     while (true) {
/*    */       boolean bool;
/*    */       if (this.oJ0 == this.xH0.length()) {
/*    */         bool = false;
/*    */       } else if (!Character.isWhitespace(this.xH0.charAt(this.oJ0))) {
/*    */         bool = true;
/*    */       } else {
/*    */         this.oJ0++;
/*    */         continue;
/*    */       } 
/*    */       if (bool)
/*    */         return this.xH0.charAt(this.oJ0); 
/*    */       return -1;
/*    */     } 
/*    */   }
/*    */   
/*    */   public final void uF(int paramInt) {
/*    */     if (paramInt < 0)
/*    */       throw new ParseException("Unexpected end of string", this.oJ0); 
/*    */     String str = B40.df("Unexpected character '").append((char)paramInt).append("' at ").append(this.oJ0).toString();
/*    */     throw new ParseException(this, this.oJ0);
/*    */   } }


/* Location:              /Users/vnnsnnt/Documents/Codespace/JavaWorkspace/RedTrainer/src/main/java/org/trainer/client/PokeMMO.jar!/f/SB.class
 * Java compiler version: 8 (52.0)
 * JD-Core Version:       1.1.3
 */