/* 1 */ package f;public final class sc extends Wr { public static final String[][] Jt = new String[0][]; public String ub; private void sd0() { this.fr0
/* 2 */       .jf0(this); }
/*   */   public JG0[] SO; public sc(String paramString, String[] paramArrayOfString, Xs0[] paramArrayOfXs0, String[][] paramArrayOfString1) { // Byte code:
/*   */     //   0: aload_0
/*   */     //   1: aload_3
/*   */     //   2: aload_0
/*   */     //   3: aload_1
/*   */     //   4: aload_0
/*   */     //   5: dup
/*   */     //   6: dup
/*   */     //   7: aload_1
/*   */     //   8: aload_0
/*   */     //   9: invokespecial <init> : ()V
/*   */     //   12: putfield ub : Ljava/lang/String;
/*   */     //   15: new f/Ip
/*   */     //   18: dup
/*   */     //   19: astore_1
/*   */     //   20: invokespecial <init> : ()V
/*   */     //   23: iconst_1
/*   */     //   24: invokevirtual EP : (I)V
/*   */     //   27: ldc 'admin-small-frame'
/*   */     //   29: invokevirtual Xu : (Ljava/lang/String;)V
/*   */     //   32: invokevirtual Lo : (Ljava/lang/String;)V
/*   */     //   35: arraylength
/*   */     //   36: anewarray f/JG0
/*   */     //   39: putfield SO : [Lf/JG0;
/*   */     //   42: iconst_0
/*   */     //   43: istore #5
/*   */     //   45: iload #5
/*   */     //   47: aload_0
/*   */     //   48: getfield SO : [Lf/JG0;
/*   */     //   51: arraylength
/*   */     //   52: if_icmpge -> 203
/*   */     //   55: aload_3
/*   */     //   56: iload #5
/*   */     //   58: aaload
/*   */     //   59: invokevirtual ordinal : ()I
/*   */     //   62: dup
/*   */     //   63: istore #6
/*   */     //   65: ifeq -> 179
/*   */     //   68: iload #6
/*   */     //   70: iconst_1
/*   */     //   71: if_icmpeq -> 158
/*   */     //   74: iload #6
/*   */     //   76: iconst_2
/*   */     //   77: if_icmpeq -> 179
/*   */     //   80: iload #6
/*   */     //   82: iconst_4
/*   */     //   83: if_icmpeq -> 107
/*   */     //   86: aload_0
/*   */     //   87: getfield SO : [Lf/JG0;
/*   */     //   90: iload #5
/*   */     //   92: new f/of
/*   */     //   95: dup
/*   */     //   96: astore #6
/*   */     //   98: invokespecial <init> : ()V
/*   */     //   101: aload #6
/*   */     //   103: aastore
/*   */     //   104: goto -> 197
/*   */     //   107: aload_0
/*   */     //   108: new java/util/ArrayList
/*   */     //   111: dup
/*   */     //   112: astore #6
/*   */     //   114: aload #4
/*   */     //   116: iload #5
/*   */     //   118: aaload
/*   */     //   119: invokestatic asList : ([Ljava/lang/Object;)Ljava/util/List;
/*   */     //   122: invokespecial <init> : (Ljava/util/Collection;)V
/*   */     //   125: new f/W1
/*   */     //   128: dup
/*   */     //   129: dup
/*   */     //   130: astore #7
/*   */     //   132: invokespecial <init> : ()V
/*   */     //   135: new f/OZ
/*   */     //   138: dup
/*   */     //   139: aload #6
/*   */     //   141: invokespecial <init> : (Ljava/util/Collection;)V
/*   */     //   144: invokevirtual rk0 : (Lf/cQ;)V
/*   */     //   147: getfield SO : [Lf/JG0;
/*   */     //   150: iload #5
/*   */     //   152: aload #7
/*   */     //   154: aastore
/*   */     //   155: goto -> 197
/*   */     //   158: aload_0
/*   */     //   159: getfield SO : [Lf/JG0;
/*   */     //   162: iload #5
/*   */     //   164: new f/S50
/*   */     //   167: dup
/*   */     //   168: astore #6
/*   */     //   170: invokespecial <init> : ()V
/*   */     //   173: aload #6
/*   */     //   175: aastore
/*   */     //   176: goto -> 197
/*   */     //   179: aload_0
/*   */     //   180: getfield SO : [Lf/JG0;
/*   */     //   183: iload #5
/*   */     //   185: new f/BL0
/*   */     //   188: dup
/*   */     //   189: astore #6
/*   */     //   191: invokespecial <init> : ()V
/*   */     //   194: aload #6
/*   */     //   196: aastore
/*   */     //   197: iinc #5, 1
/*   */     //   200: goto -> 45
/*   */     //   203: aload_1
/*   */     //   204: dup
/*   */     //   205: new f/Un
/*   */     //   208: dup
/*   */     //   209: astore_3
/*   */     //   210: aload_0
/*   */     //   211: aload_3
/*   */     //   212: ldc 'Send'
/*   */     //   214: invokespecial <init> : (Ljava/lang/String;)V
/*   */     //   217: <illegal opcode> run : (Lf/sc;)Ljava/lang/Runnable;
/*   */     //   222: invokevirtual tW : (Ljava/lang/Runnable;)V
/*   */     //   225: new f/Un
/*   */     //   228: dup
/*   */     //   229: astore #4
/*   */     //   231: aload_0
/*   */     //   232: aload #4
/*   */     //   234: ldc 'Cancel'
/*   */     //   236: invokespecial <init> : (Ljava/lang/String;)V
/*   */     //   239: <illegal opcode> run : (Lf/sc;)Ljava/lang/Runnable;
/*   */     //   244: invokevirtual tW : (Ljava/lang/Runnable;)V
/*   */     //   247: invokevirtual mE0 : ()Lf/g0;
/*   */     //   250: astore #5
/*   */     //   252: invokevirtual d7 : ()Lf/cr0;
/*   */     //   255: astore #6
/*   */     //   257: iconst_0
/*   */     //   258: istore #7
/*   */     //   260: iload #7
/*   */     //   262: aload_0
/*   */     //   263: getfield SO : [Lf/JG0;
/*   */     //   266: arraylength
/*   */     //   267: if_icmpge -> 379
/*   */     //   270: aload #6
/*   */     //   272: aload_1
/*   */     //   273: aload #5
/*   */     //   275: aload_1
/*   */     //   276: new f/dQ
/*   */     //   279: dup
/*   */     //   280: dup
/*   */     //   281: astore #8
/*   */     //   283: new java/lang/StringBuilder
/*   */     //   286: dup
/*   */     //   287: astore #9
/*   */     //   289: aload_2
/*   */     //   290: iload #7
/*   */     //   292: aload #9
/*   */     //   294: invokespecial <init> : ()V
/*   */     //   297: aaload
/*   */     //   298: ldc ':'
/*   */     //   300: invokestatic Vr0 : (Ljava/lang/StringBuilder;Ljava/lang/String;Ljava/lang/String;)Ljava/lang/String;
/*   */     //   303: invokespecial <init> : (Ljava/lang/String;)V
/*   */     //   306: ldc 'label-title'
/*   */     //   308: invokevirtual Xu : (Ljava/lang/String;)V
/*   */     //   311: invokevirtual d7 : ()Lf/cr0;
/*   */     //   314: iconst_2
/*   */     //   315: anewarray f/JG0
/*   */     //   318: dup
/*   */     //   319: dup
/*   */     //   320: aload_0
/*   */     //   321: swap
/*   */     //   322: iconst_0
/*   */     //   323: aload #8
/*   */     //   325: aastore
/*   */     //   326: getfield SO : [Lf/JG0;
/*   */     //   329: iload #7
/*   */     //   331: aaload
/*   */     //   332: iconst_1
/*   */     //   333: swap
/*   */     //   334: aastore
/*   */     //   335: invokevirtual Mg : ([Lf/JG0;)Lf/U90;
/*   */     //   338: invokevirtual ee0 : (Lf/U90;)Lf/U90;
/*   */     //   341: pop
/*   */     //   342: invokevirtual mE0 : ()Lf/g0;
/*   */     //   345: iconst_2
/*   */     //   346: anewarray f/JG0
/*   */     //   349: dup
/*   */     //   350: dup
/*   */     //   351: aload_0
/*   */     //   352: swap
/*   */     //   353: iconst_0
/*   */     //   354: aload #8
/*   */     //   356: aastore
/*   */     //   357: getfield SO : [Lf/JG0;
/*   */     //   360: iload #7
/*   */     //   362: aaload
/*   */     //   363: iconst_1
/*   */     //   364: swap
/*   */     //   365: aastore
/*   */     //   366: invokevirtual Mg : ([Lf/JG0;)Lf/U90;
/*   */     //   369: invokevirtual ee0 : (Lf/U90;)Lf/U90;
/*   */     //   372: pop
/*   */     //   373: iinc #7, 1
/*   */     //   376: goto -> 260
/*   */     //   379: aload_0
/*   */     //   380: aload_1
/*   */     //   381: dup
/*   */     //   382: aload #6
/*   */     //   384: aload_1
/*   */     //   385: aload #5
/*   */     //   387: aload #6
/*   */     //   389: aload_1
/*   */     //   390: aload #5
/*   */     //   392: aload_1
/*   */     //   393: invokevirtual d7 : ()Lf/cr0;
/*   */     //   396: aload_3
/*   */     //   397: invokevirtual Ya : (Lf/JG0;)Lf/U90;
/*   */     //   400: iconst_5
/*   */     //   401: invokevirtual Aq : (I)Lf/U90;
/*   */     //   404: aload #4
/*   */     //   406: invokevirtual Ya : (Lf/JG0;)Lf/U90;
/*   */     //   409: invokevirtual ee0 : (Lf/U90;)Lf/U90;
/*   */     //   412: pop
/*   */     //   413: invokevirtual mE0 : ()Lf/g0;
/*   */     //   416: iconst_2
/*   */     //   417: anewarray f/JG0
/*   */     //   420: dup
/*   */     //   421: dup
/*   */     //   422: iconst_0
/*   */     //   423: aload_3
/*   */     //   424: aastore
/*   */     //   425: iconst_1
/*   */     //   426: aload #4
/*   */     //   428: aastore
/*   */     //   429: invokevirtual Mg : ([Lf/JG0;)Lf/U90;
/*   */     //   432: invokevirtual ee0 : (Lf/U90;)Lf/U90;
/*   */     //   435: pop
/*   */     //   436: invokevirtual rK0 : (Lf/U90;)V
/*   */     //   439: invokevirtual WN : (Lf/U90;)V
/*   */     //   442: invokevirtual J8 : (Lf/JG0;)V
/*   */     //   445: return
/*   */     // Line number table:
/*   */     //   Java source line number -> byte code offset
/*   */     //   #1	-> 298
/*   */     //   #2	-> 303 } private void x00() { this(this.ub); StringBuilder stringBuilder; JG0[] arrayOfJG0; int i; byte b; for (i = (arrayOfJG0 = this.SO).length, b = 0; b < i; )
/*   */     { JG0 jG0 = arrayOfJG0[b]; stringBuilder.append(" "); if (jG0 instanceof of)
/* 5 */       { stringBuilder.append(((of)jG0).F2.PH0.toString().trim()); } else if (jG0 instanceof W1) { stringBuilder.append(((W1)jG0).WW().toString().trim()); } else { throw new UnsupportedOperationException(); }  b++; }  km.u4.lF(stringBuilder.toString());
/* 6 */     close(); }
/*   */ 
/*   */   
/*   */   public final sc d6(int paramInt, String paramString) {
/*   */     JG0 jG0;
/*   */     if (jG0 = this.SO[paramInt] instanceof of) {
/*   */       ((of)jG0).Zh(paramString);
/*   */     } else {
/*   */       if (jG0 instanceof W1) {
/*   */         ((W1)jG0).COm6(paramString);
/*   */         return this;
/*   */       } 
/*   */       throw new UnsupportedOperationException();
/*   */     } 
/*   */     return this;
/*   */   }
/*   */   
/*   */   public final sc lI0() {
/*   */     TG0(this::sd0);
/*   */     return this;
/*   */   }
/*   */   
/*   */   public final void close() {
/*   */     Un un;
/*   */     if ((un = this.Ki) != null && un.Wg0())
/*   */       hm.Fz0(this.Ki.TG0.oh0); 
/*   */   } }


/* Location:              /Users/vnnsnnt/Documents/Codespace/JavaWorkspace/RedTrainer/src/main/java/org/trainer/client/PokeMMO.jar!/f/sc.class
 * Java compiler version: 8 (52.0)
 * JD-Core Version:       1.1.3
 */