/*    */ package f;public final class sC0 extends Ij implements r60 { public final byte jN; public Io[] lpT2; public Ip xk0; public Un ue; public Un Zr; public Io Fy; public xo0 CC0; public sC0(byte paramByte) { // Byte code:
/*    */     //   0: aload_0
/*    */     //   1: dup
/*    */     //   2: dup
/*    */     //   3: dup2
/*    */     //   4: dup2
/*    */     //   5: dup2
/*    */     //   6: dup2
/*    */     //   7: iload_1
/*    */     //   8: aload_0
/*    */     //   9: invokespecial <init> : ()V
/*    */     //   12: putfield jN : B
/*    */     //   15: <illegal opcode> run : (Lf/sC0;)Ljava/lang/Runnable;
/*    */     //   20: invokevirtual TG0 : (Ljava/lang/Runnable;)V
/*    */     //   23: ldc 'seed-plant-dialog'
/*    */     //   25: invokevirtual Xu : (Ljava/lang/String;)V
/*    */     //   28: sipush #8559
/*    */     //   31: invokestatic OH0 : (I)Ljava/lang/String;
/*    */     //   34: invokevirtual Lo : (Ljava/lang/String;)V
/*    */     //   37: new f/Ip
/*    */     //   40: dup
/*    */     //   41: invokespecial <init> : ()V
/*    */     //   44: putfield xk0 : Lf/Ip;
/*    */     //   47: new f/Un
/*    */     //   50: dup
/*    */     //   51: sipush #8559
/*    */     //   54: invokestatic OH0 : (I)Ljava/lang/String;
/*    */     //   57: invokespecial <init> : (Ljava/lang/String;)V
/*    */     //   60: putfield ue : Lf/Un;
/*    */     //   63: new f/Un
/*    */     //   66: dup
/*    */     //   67: bipush #53
/*    */     //   69: invokestatic OH0 : (I)Ljava/lang/String;
/*    */     //   72: invokespecial <init> : (Ljava/lang/String;)V
/*    */     //   75: putfield Zr : Lf/Un;
/*    */     //   78: getfield ue : Lf/Un;
/*    */     //   81: aload_0
/*    */     //   82: <illegal opcode> run : (Lf/sC0;)Ljava/lang/Runnable;
/*    */     //   87: invokevirtual tW : (Ljava/lang/Runnable;)V
/*    */     //   90: getfield Zr : Lf/Un;
/*    */     //   93: aload_0
/*    */     //   94: <illegal opcode> run : (Lf/sC0;)Ljava/lang/Runnable;
/*    */     //   99: invokevirtual tW : (Ljava/lang/Runnable;)V
/*    */     //   102: iconst_3
/*    */     //   103: anewarray f/Io
/*    */     //   106: putfield lpT2 : [Lf/Io;
/*    */     //   109: getstatic f/km.u4 : Lf/R8;
/*    */     //   112: getstatic f/yM.r4 : Lf/yM;
/*    */     //   115: invokevirtual gN : (Lf/yM;)Lf/zr0;
/*    */     //   118: invokevirtual O20 : ()[S
/*    */     //   121: astore_1
/*    */     //   122: iconst_0
/*    */     //   123: istore_2
/*    */     //   124: iload_2
/*    */     //   125: aload_0
/*    */     //   126: getfield lpT2 : [Lf/Io;
/*    */     //   129: dup
/*    */     //   130: astore_3
/*    */     //   131: arraylength
/*    */     //   132: if_icmpge -> 172
/*    */     //   135: aload_0
/*    */     //   136: aload_3
/*    */     //   137: iload_2
/*    */     //   138: new f/Io
/*    */     //   141: dup
/*    */     //   142: astore_3
/*    */     //   143: aload_0
/*    */     //   144: invokespecial <init> : (Lf/sC0;)V
/*    */     //   147: aload_3
/*    */     //   148: aastore
/*    */     //   149: getfield lpT2 : [Lf/Io;
/*    */     //   152: iload_2
/*    */     //   153: aaload
/*    */     //   154: dup
/*    */     //   155: aload_0
/*    */     //   156: swap
/*    */     //   157: iload_2
/*    */     //   158: <illegal opcode> run : (Lf/sC0;Lf/Io;I)Ljava/lang/Runnable;
/*    */     //   163: invokevirtual bm0 : (Ljava/lang/Runnable;)V
/*    */     //   166: iinc #2, 1
/*    */     //   169: goto -> 124
/*    */     //   172: aload_0
/*    */     //   173: dup
/*    */     //   174: dup
/*    */     //   175: dup2
/*    */     //   176: new f/Io
/*    */     //   179: dup
/*    */     //   180: aload_0
/*    */     //   181: swap
/*    */     //   182: dup
/*    */     //   183: aload_0
/*    */     //   184: invokespecial <init> : (Lf/sC0;)V
/*    */     //   187: putfield Fy : Lf/Io;
/*    */     //   190: bipush #12
/*    */     //   192: bipush #10
/*    */     //   194: invokevirtual lE : (II)V
/*    */     //   197: new f/xo0
/*    */     //   200: dup
/*    */     //   201: ldc '\\n\\n'
/*    */     //   203: invokespecial <init> : (Ljava/lang/String;)V
/*    */     //   206: putfield CC0 : Lf/xo0;
/*    */     //   209: getfield Fy : Lf/Io;
/*    */     //   212: iconst_0
/*    */     //   213: invokevirtual wI0 : (Z)V
/*    */     //   216: getfield CC0 : Lf/xo0;
/*    */     //   219: iconst_0
/*    */     //   220: invokevirtual wI0 : (Z)V
/*    */     //   223: getfield xk0 : Lf/Ip;
/*    */     //   226: dup
/*    */     //   227: aload_0
/*    */     //   228: swap
/*    */     //   229: invokevirtual d7 : ()Lf/cr0;
/*    */     //   232: bipush #15
/*    */     //   234: invokevirtual Aq : (I)Lf/U90;
/*    */     //   237: aload_0
/*    */     //   238: getfield xk0 : Lf/Ip;
/*    */     //   241: invokevirtual mE0 : ()Lf/g0;
/*    */     //   244: aload_0
/*    */     //   245: getfield lpT2 : [Lf/Io;
/*    */     //   248: invokevirtual Mg : ([Lf/JG0;)Lf/U90;
/*    */     //   251: invokevirtual ee0 : (Lf/U90;)Lf/U90;
/*    */     //   254: bipush #15
/*    */     //   256: invokevirtual Aq : (I)Lf/U90;
/*    */     //   259: astore_2
/*    */     //   260: getfield xk0 : Lf/Ip;
/*    */     //   263: invokevirtual mE0 : ()Lf/g0;
/*    */     //   266: iconst_2
/*    */     //   267: anewarray f/JG0
/*    */     //   270: dup
/*    */     //   271: dup
/*    */     //   272: aload_0
/*    */     //   273: swap
/*    */     //   274: aload_0
/*    */     //   275: getfield Fy : Lf/Io;
/*    */     //   278: iconst_0
/*    */     //   279: swap
/*    */     //   280: aastore
/*    */     //   281: getfield CC0 : Lf/xo0;
/*    */     //   284: iconst_1
/*    */     //   285: swap
/*    */     //   286: aastore
/*    */     //   287: aload_2
/*    */     //   288: bipush #15
/*    */     //   290: invokestatic aj0 : (Lf/g0;[Lf/JG0;Lf/U90;I)Lf/U90;
/*    */     //   293: aload_0
/*    */     //   294: getfield xk0 : Lf/Ip;
/*    */     //   297: invokevirtual d7 : ()Lf/cr0;
/*    */     //   300: iconst_2
/*    */     //   301: anewarray f/JG0
/*    */     //   304: dup
/*    */     //   305: dup
/*    */     //   306: aload_0
/*    */     //   307: swap
/*    */     //   308: aload_0
/*    */     //   309: getfield ue : Lf/Un;
/*    */     //   312: iconst_0
/*    */     //   313: swap
/*    */     //   314: aastore
/*    */     //   315: getfield Zr : Lf/Un;
/*    */     //   318: iconst_1
/*    */     //   319: swap
/*    */     //   320: aastore
/*    */     //   321: invokevirtual Mg : ([Lf/JG0;)Lf/U90;
/*    */     //   324: invokevirtual ee0 : (Lf/U90;)Lf/U90;
/*    */     //   327: invokevirtual Em0 : ()Lf/U90;
/*    */     //   330: invokevirtual WN : (Lf/U90;)V
/*    */     //   333: getfield xk0 : Lf/Ip;
/*    */     //   336: dup
/*    */     //   337: invokevirtual mE0 : ()Lf/g0;
/*    */     //   340: aload_0
/*    */     //   341: getfield xk0 : Lf/Ip;
/*    */     //   344: invokevirtual d7 : ()Lf/cr0;
/*    */     //   347: invokevirtual Em0 : ()Lf/U90;
/*    */     //   350: aload_0
/*    */     //   351: getfield lpT2 : [Lf/Io;
/*    */     //   354: iconst_0
/*    */     //   355: aaload
/*    */     //   356: invokevirtual Ya : (Lf/JG0;)Lf/U90;
/*    */     //   359: invokevirtual Em0 : ()Lf/U90;
/*    */     //   362: aload_0
/*    */     //   363: getfield lpT2 : [Lf/Io;
/*    */     //   366: iconst_1
/*    */     //   367: aaload
/*    */     //   368: invokevirtual Ya : (Lf/JG0;)Lf/U90;
/*    */     //   371: invokevirtual Em0 : ()Lf/U90;
/*    */     //   374: aload_0
/*    */     //   375: getfield lpT2 : [Lf/Io;
/*    */     //   378: iconst_2
/*    */     //   379: aaload
/*    */     //   380: invokevirtual Ya : (Lf/JG0;)Lf/U90;
/*    */     //   383: invokevirtual Em0 : ()Lf/U90;
/*    */     //   386: invokevirtual ee0 : (Lf/U90;)Lf/U90;
/*    */     //   389: aload_0
/*    */     //   390: getfield xk0 : Lf/Ip;
/*    */     //   393: invokevirtual d7 : ()Lf/cr0;
/*    */     //   396: invokevirtual Em0 : ()Lf/U90;
/*    */     //   399: iconst_2
/*    */     //   400: anewarray f/JG0
/*    */     //   403: dup
/*    */     //   404: dup
/*    */     //   405: aload_0
/*    */     //   406: swap
/*    */     //   407: aload_0
/*    */     //   408: getfield Fy : Lf/Io;
/*    */     //   411: iconst_0
/*    */     //   412: swap
/*    */     //   413: aastore
/*    */     //   414: getfield CC0 : Lf/xo0;
/*    */     //   417: iconst_1
/*    */     //   418: swap
/*    */     //   419: aastore
/*    */     //   420: invokevirtual Mg : ([Lf/JG0;)Lf/U90;
/*    */     //   423: invokevirtual Em0 : ()Lf/U90;
/*    */     //   426: invokevirtual ee0 : (Lf/U90;)Lf/U90;
/*    */     //   429: aload_0
/*    */     //   430: getfield xk0 : Lf/Ip;
/*    */     //   433: invokevirtual mE0 : ()Lf/g0;
/*    */     //   436: aload_0
/*    */     //   437: getfield ue : Lf/Un;
/*    */     //   440: invokevirtual Ya : (Lf/JG0;)Lf/U90;
/*    */     //   443: aload_0
/*    */     //   444: getfield Zr : Lf/Un;
/*    */     //   447: invokevirtual Ya : (Lf/JG0;)Lf/U90;
/*    */     //   450: invokevirtual ee0 : (Lf/U90;)Lf/U90;
/*    */     //   453: invokevirtual rK0 : (Lf/U90;)V
/*    */     //   456: iconst_0
/*    */     //   457: istore_2
/*    */     //   458: iload_2
/*    */     //   459: aload_0
/*    */     //   460: getfield lpT2 : [Lf/Io;
/*    */     //   463: arraylength
/*    */     //   464: if_icmpge -> 504
/*    */     //   467: aload_1
/*    */     //   468: iload_2
/*    */     //   469: saload
/*    */     //   470: dup
/*    */     //   471: istore_3
/*    */     //   472: ifle -> 498
/*    */     //   475: aload_0
/*    */     //   476: iload_3
/*    */     //   477: invokevirtual h50 : (S)Z
/*    */     //   480: ifeq -> 498
/*    */     //   483: aload_0
/*    */     //   484: getfield lpT2 : [Lf/Io;
/*    */     //   487: iload_2
/*    */     //   488: aaload
/*    */     //   489: aload_1
/*    */     //   490: iload_2
/*    */     //   491: saload
/*    */     //   492: iconst_0
/*    */     //   493: swap
/*    */     //   494: iconst_1
/*    */     //   495: invokevirtual LPt2 : (BSS)V
/*    */     //   498: iinc #2, 1
/*    */     //   501: goto -> 458
/*    */     //   504: aload_0
/*    */     //   505: dup
/*    */     //   506: getfield xk0 : Lf/Ip;
/*    */     //   509: invokevirtual J8 : (Lf/JG0;)V
/*    */     //   512: return
/*    */     // Line number table:
/*    */     //   Java source line number -> byte code offset
/*    */     //   #1	-> 290
/*    */     //   #2	-> 294 } private void jF0(Io paramIo, int paramInt) { // Byte code:
/*    */     //   0: aload_1
/*    */     //   1: invokevirtual p3 : ()Z
/*    */     //   4: ifeq -> 380
/*    */     //   7: new f/B3
/*    */     //   10: dup
/*    */     //   11: astore_3
/*    */     //   12: invokespecial <init> : ()V
/*    */     //   15: getstatic f/km.u4 : Lf/R8;
/*    */     //   18: getstatic f/yM.r4 : Lf/yM;
/*    */     //   21: pop
/*    */     //   22: getfield Fe : [Lf/zr0;
/*    */     //   25: iconst_1
/*    */     //   26: aaload
/*    */     //   27: dup
/*    */     //   28: astore #4
/*    */     //   30: new java/util/ArrayList
/*    */     //   33: dup
/*    */     //   34: astore #5
/*    */     //   36: invokespecial <init> : ()V
/*    */     //   39: new f/Lw
/*    */     //   42: dup
/*    */     //   43: astore #6
/*    */     //   45: invokespecial <init> : ()V
/*    */     //   48: invokevirtual ro0 : ()[Lf/Y;
/*    */     //   51: dup
/*    */     //   52: astore #7
/*    */     //   54: arraylength
/*    */     //   55: istore #8
/*    */     //   57: iconst_0
/*    */     //   58: istore #9
/*    */     //   60: iload #9
/*    */     //   62: iload #8
/*    */     //   64: if_icmpge -> 186
/*    */     //   67: aload #6
/*    */     //   69: aload #7
/*    */     //   71: iload #9
/*    */     //   73: aaload
/*    */     //   74: dup
/*    */     //   75: astore #10
/*    */     //   77: getfield Lh : Lf/nH0;
/*    */     //   80: getfield p1 : S
/*    */     //   83: invokevirtual Fb : (S)Z
/*    */     //   86: ifne -> 180
/*    */     //   89: aload #10
/*    */     //   91: getfield Lh : Lf/nH0;
/*    */     //   94: getfield p1 : S
/*    */     //   97: dup
/*    */     //   98: istore #11
/*    */     //   100: sipush #7030
/*    */     //   103: if_icmplt -> 117
/*    */     //   106: iload #11
/*    */     //   108: sipush #7039
/*    */     //   111: if_icmpgt -> 117
/*    */     //   114: goto -> 144
/*    */     //   117: iload #11
/*    */     //   119: sipush #1030
/*    */     //   122: if_icmplt -> 136
/*    */     //   125: iload #11
/*    */     //   127: sipush #1039
/*    */     //   130: if_icmpgt -> 136
/*    */     //   133: goto -> 144
/*    */     //   136: iload #11
/*    */     //   138: sipush #1446
/*    */     //   141: if_icmpne -> 150
/*    */     //   144: iconst_1
/*    */     //   145: istore #11
/*    */     //   147: goto -> 153
/*    */     //   150: iconst_0
/*    */     //   151: istore #11
/*    */     //   153: iload #11
/*    */     //   155: ifeq -> 180
/*    */     //   158: aload #6
/*    */     //   160: aload #10
/*    */     //   162: aload #5
/*    */     //   164: aload #10
/*    */     //   166: invokevirtual add : (Ljava/lang/Object;)Z
/*    */     //   169: pop
/*    */     //   170: getfield Lh : Lf/nH0;
/*    */     //   173: getfield p1 : S
/*    */     //   176: invokevirtual Ye0 : (S)Z
/*    */     //   179: pop
/*    */     //   180: iinc #9, 1
/*    */     //   183: goto -> 60
/*    */     //   186: aload #5
/*    */     //   188: dup
/*    */     //   189: invokestatic sort : (Ljava/util/List;)V
/*    */     //   192: invokevirtual iterator : ()Ljava/util/Iterator;
/*    */     //   195: astore #5
/*    */     //   197: aload #5
/*    */     //   199: invokeinterface hasNext : ()Z
/*    */     //   204: ifeq -> 325
/*    */     //   207: aload_3
/*    */     //   208: aload #5
/*    */     //   210: invokeinterface next : ()Ljava/lang/Object;
/*    */     //   215: checkcast f/Y
/*    */     //   218: astore #6
/*    */     //   220: new f/vi
/*    */     //   223: dup
/*    */     //   224: astore #7
/*    */     //   226: aload_1
/*    */     //   227: aload #6
/*    */     //   229: new java/lang/StringBuilder
/*    */     //   232: dup
/*    */     //   233: astore #8
/*    */     //   235: aload #4
/*    */     //   237: aload #6
/*    */     //   239: aload #8
/*    */     //   241: invokespecial <init> : ()V
/*    */     //   244: getfield Lh : Lf/nH0;
/*    */     //   247: getfield p1 : S
/*    */     //   250: invokevirtual jW : (S)I
/*    */     //   253: invokevirtual append : (I)Ljava/lang/StringBuilder;
/*    */     //   256: ldc_w 'x '
/*    */     //   259: invokevirtual append : (Ljava/lang/String;)Ljava/lang/StringBuilder;
/*    */     //   262: aload #6
/*    */     //   264: invokevirtual JG0 : ()Ljava/lang/String;
/*    */     //   267: invokevirtual append : (Ljava/lang/String;)Ljava/lang/StringBuilder;
/*    */     //   270: invokevirtual toString : ()Ljava/lang/String;
/*    */     //   273: astore #8
/*    */     //   275: getstatic f/wm0.y0 : Lf/wm0;
/*    */     //   278: aload #6
/*    */     //   280: getfield Bp0 : Lf/LPT3;
/*    */     //   283: iconst_0
/*    */     //   284: invokevirtual HR : (Lf/LPT3;Z)Lf/U70;
/*    */     //   287: astore #6
/*    */     //   289: iload_2
/*    */     //   290: <illegal opcode> run : (Lf/Io;Lf/Y;I)Ljava/lang/Runnable;
/*    */     //   295: astore #9
/*    */     //   297: aload #8
/*    */     //   299: aload #6
/*    */     //   301: iconst_3
/*    */     //   302: iconst_3
/*    */     //   303: bipush #24
/*    */     //   305: bipush #24
/*    */     //   307: aload #9
/*    */     //   309: iconst_1
/*    */     //   310: invokespecial <init> : (Ljava/lang/String;Lf/U70;IIIILjava/lang/Runnable;Z)V
/*    */     //   313: getfield aV : Ljava/util/ArrayList;
/*    */     //   316: aload #7
/*    */     //   318: invokevirtual add : (Ljava/lang/Object;)Z
/*    */     //   321: pop
/*    */     //   322: goto -> 197
/*    */     //   325: iload_2
/*    */     //   326: iconst_2
/*    */     //   327: if_icmpge -> 342
/*    */     //   330: aload_0
/*    */     //   331: getfield lpT2 : [Lf/Io;
/*    */     //   334: iload_2
/*    */     //   335: iconst_1
/*    */     //   336: iadd
/*    */     //   337: aaload
/*    */     //   338: astore_1
/*    */     //   339: goto -> 347
/*    */     //   342: aload_0
/*    */     //   343: getfield ue : Lf/Un;
/*    */     //   346: astore_1
/*    */     //   347: aload_3
/*    */     //   348: getfield aV : Ljava/util/ArrayList;
/*    */     //   351: invokevirtual size : ()I
/*    */     //   354: iconst_1
/*    */     //   355: if_icmpge -> 369
/*    */     //   358: aload_3
/*    */     //   359: sipush #6007
/*    */     //   362: invokestatic OH0 : (I)Ljava/lang/String;
/*    */     //   365: aconst_null
/*    */     //   366: invokevirtual mD : (Ljava/lang/String;Ljava/lang/Runnable;)V
/*    */     //   369: aload_3
/*    */     //   370: aload_1
/*    */     //   371: aload_0
/*    */     //   372: getfield lpT2 : [Lf/Io;
/*    */     //   375: iload_2
/*    */     //   376: aaload
/*    */     //   377: invokestatic om : (Lf/B3;Lf/Un;Lf/O0;)V
/*    */     //   380: return
/*    */     // Line number table:
/*    */     //   Java source line number -> byte code offset
/*    */     //   #1	-> 22
/*    */     //   #2	-> 26
/*    */     //   #3	-> 30
/*    */     //   #4	-> 77
/*    */     //   #5	-> 80
/*    */     //   #6	-> 83
/*    */     //   #7	-> 91
/*    */     //   #8	-> 94
/*    */     //   #9	-> 166
/*    */     //   #10	-> 170
/*    */     //   #11	-> 173
/*    */     //   #12	-> 176
/*    */     //   #13	-> 244
/*    */     //   #14	-> 247
/*    */     //   #15	-> 250
/*    */     //   #16	-> 275
/*    */     //   #17	-> 280
/*    */     //   #18	-> 284
/*    */     //   #19	-> 290
/*    */     //   #20	-> 313
/*    */     //   #21	-> 331
/*    */     //   #22	-> 348
/*  1 */     //   #23	-> 362 } public static void ul(Io paramIo, Y paramY, int paramInt) { paramIo.Tm0(paramY);
/*    */ 
/*    */     
/*  4 */     short s = paramY.Lh.p1;
/*  5 */     (km.u4.Fe[1]).YH0[paramInt] = s; } private void ae() { zr0 zr0 = km.u4.Fe[1]; byte b = 0; short[] arrayOfShort; while (b < (arrayOfShort = zr0.YH0).length) { arrayOfShort[b] = 0; b = (byte)(b + 1); }  CL(); } public final void u9() { R8 r8 = km.u4; byte b = this.jN, arrayOfByte1[] = new byte[10]; int i = 0; Io[] arrayOfIo; int j; byte b1; for (j = (arrayOfIo = this.lpT2).length, b1 = 0; b1 < j; ) { short s; if ((s = (arrayOfIo[b1]).hC0) >= 1) { s = (byte)(s % 1000); int k; if ((k = i + 1) > arrayOfByte1.length) { arrayOfByte1 = new byte[Math.max(arrayOfByte1.length << 1, k)]; int m = arrayOfByte1.length; System.arraycopy(arrayOfByte1, 0, arrayOfByte1, 0, m); }  arrayOfByte1[i] = s;
/*  6 */         i = k; }  b1++; }  boolean bool = false;
/*  7 */     byte[] arrayOfByte2 = new byte[i]; if (i != 0) if (i > 0)
/*  8 */       { System.arraycopy(arrayOfByte1, bool, arrayOfByte2, 0, i); }
/*    */       else
/* 10 */       { throw new ArrayIndexOutOfBoundsException(bool); }   r8.N7(b, arrayOfByte2); ra0(); } public final boolean i2(oa0 paramoa0) { Runnable runnable; if (B8.Wm0(paramoa0.cz0) && paramoa0.oO()) { Io[] arrayOfIo; int i; byte b; for (i = (arrayOfIo = this.lpT2).length, b = 0; b < i; ) { Io io = arrayOfIo[b]; if (h1.J20(paramoa0.GG0, BM.bC) && io.p3()) { if ((runnable = io.Tw0) != null)
/*    */             run();  return true; }  b++; }
/* 12 */        BM bM; if (h1.J20(paramoa0.GG0, bM = BM.bC) && ((sC0)super).ue.p3()) { hm.Fz0(((sC0)super).ue.TG0.oh0); return true; }
/*    */       
/* 14 */       if (h1.J20(paramoa0.GG0, BM.lc) || (
/*    */         
/* 16 */         h1.J20(paramoa0.GG0, bM) && ((sC0)super).Zr.p3()))
/*    */       
/*    */       { 
/*    */ 
/*    */ 
/*    */ 
/*    */ 
/*    */ 
/*    */ 
/*    */ 
/*    */         
/* 27 */         hm.Fz0(((sC0)super).Zr.TG0.oh0); return true; }  if (h1.J20(paramoa0.GG0, BM.ni) || h1.J20(paramoa0.GG0, BM.Oq)) { q0(); if (((sC0)super).Fy.p3()) q0();  return true; }  if (h1.J20(paramoa0.GG0, BM.N70) || h1.J20(paramoa0.GG0, BM.M8)) { oZ(); if (((sC0)super).Fy.p3())
/* 28 */           oZ();  return true; }  }  return super.i2(paramoa0); }
/*    */ 
/*    */   
/*    */   public final void CL() {
/*    */     km.u4.lx0(this.jN, (byte)0);
/*    */     ra0();
/*    */   }
/*    */   
/*    */   public final void IG0() {
/*    */     if (this.Fy.hC0 > 0) {
/*    */       VA0.c90(this.ue);
/*    */     } else {
/*    */       Io[] arrayOfIo;
/*    */       int i;
/*    */       byte b;
/*    */       for (i = (arrayOfIo = this.lpT2).length, b = 0; b < i; ) {
/*    */         Io io;
/*    */         if ((io = this[b]).hC0 < 1) {
/*    */           VA0.c90(io);
/*    */           break;
/*    */         } 
/*    */         b++;
/*    */       } 
/*    */     } 
/*    */   }
/*    */   
/*    */   public final void d40() {
/*    */     super.d40();
/*    */     mM();
/*    */     qB0(et.Wi0);
/*    */   }
/*    */   
/*    */   public final boolean h50(short paramShort) {
/*    */     this();
/*    */     h30 h30;
/*    */     Io[] arrayOfIo;
/*    */     int i;
/*    */     byte b;
/*    */     for (i = (arrayOfIo = this.lpT2).length, b = 0; b < i; ) {
/*    */       short s1;
/*    */       if ((s1 = (arrayOfIo[b]).hC0) >= 1) {
/*    */         s1 = 1;
/*    */         boolean bool = true;
/*    */         int j = -j - 1;
/*    */         this.Qz0[j] = (short)(this.Qz0[j] + s1);
/*    */         this.Qz0[j] = bool;
/*    */         this.JO[j];
/*    */         if (!((j = sq(s1)) < 0))
/*    */           xt0(this.Mw); 
/*    */       } 
/*    */       b++;
/*    */     } 
/*    */     short s = (short)(Z90(paramShort) + 1);
/*    */     return km.u4.Fe[1].vH0((byte)-1, paramShort, s);
/*    */   } }


/* Location:              /Users/vnnsnnt/Documents/Codespace/JavaWorkspace/RedTrainer/src/main/java/org/trainer/client/PokeMMO.jar!/f/sC0.class
 * Java compiler version: 8 (52.0)
 * JD-Core Version:       1.1.3
 */