/*  1 */ package f;public abstract class SE0 extends O0 { public static boolean f80 = false; public xJ0 Mc; public final e2 HO = new e2(500); public final e2 TD = new e2(1000); public int fE0 = -1; public boolean COm8 = false; public boolean lW = false; public SE0(xJ0 paramxJ0, short paramShort1, int paramInt, short paramShort2) { super(paramShort1, paramInt, (short)1, paramShort2, true); Xu("item-slot"); this.Mc = paramxJ0; this.Oa0 = paramShort2; if (km.XU()) { CW().uE0(et.Wi0); E20(); lE(21, 6); } else { lE(10, 10); }  t4(); } public static void gI0(List paramList, ss paramss, hO paramhO, Y paramY, j40 paramj40, int paramInt, byte paramByte) { Vc0 vc02; f80 = false; int k; if ((k = paramByte - 1) >= paramList.size()) {
/*    */       
/*  3 */       vc02 = s10.hU.vw0[10]; vc02
/*  4 */         .ix
/*  5 */         .Lt(paramss.v2); return;
/*  6 */     }  E50 e50 = vc02.get(k); km.kH0
/*  7 */       .D1
/*  8 */       .Ct(paramhO, true); km.kH0.Kd0 = System.currentTimeMillis();
/*    */ 
/*    */     
/* 11 */     short s1 = paramY.Lh.p1;
/* 12 */     int i = paramY.Lh.Wy;
/* 13 */     int j = paramj40.Jg;
/* 14 */     short s2 = (short)e50.Zp0; byte b = (byte)paramInt;
/* 15 */     km.u4.ps0(s1, i, j, s2, b, (byte)1, false);
/*    */ 
/*    */     
/* 18 */     Vc0 vc01 = s10.hU.vw0[10]; vc01
/* 19 */       .ix
/* 20 */       .Lt(paramss.v2); } public boolean i2(oa0 paramoa0) { int i; if (paramoa0.Cz0()) { if (!this.Mc.ti) { if (this.os) { if (paramoa0.Ud()) { Ik0 ik0; xJ0 xJ01; SE0 sE0; if ((ik0 = this.Ex) != null && this.os && (sE0 = (xJ01 = ik0.tC0).fr) != null) { if (xJ01.VJ == null) sE0.Kh(0, (short)0, true);  xJ01.r4(paramoa0); SE0 sE01; if ((sE0 = xJ01.VJ) != null && sE0 != (sE01 = xJ01.fr)) { short s1 = sE0.hC0; int j = sE0.Fc; short s2 = sE01.hC0; sE0.Kh(sE01.Fc, s2, true); xJ01.fr.Kh(j, s1, true); }  xJ01.Ys(null); xJ01.fr = null; }  this.os = false; this.O.gf0(O0.kC0, false); } else { Ik0 ik0; if ((ik0 = this.Ex) != null) ik0.tC0.r4(paramoa0);  }  }
/* 21 */         else { this
/* 22 */             .os = true;
/* 23 */           this.O
/* 24 */             .gf0(O0.kC0, true); Ik0 ik0; if (paramoa0.Ua && (ik0 = this.Ex) != null)
/* 25 */           { ik0.tC0
/* 26 */               .fr = this;
/* 27 */             ik0.tC0.r4(paramoa0); }  }
/* 28 */          if (!paramoa0.Ua && paramoa0
/* 29 */           .vl == 1 && paramoa0
/* 30 */           .cz0 == 4)
/* 31 */           Kh(0, (short)0, true);  }  if (paramoa0
/* 32 */         .vl == 0 && paramoa0
/* 33 */         .cz0 == 4) { if (paramoa0
/* 34 */           .Ua && 
/* 35 */           !km.XU()) return true; 
/* 36 */         i = paramoa0.aK;
/*    */         
/* 38 */         if (mu0(i, paramoa0.gk0))
/* 39 */           return ld();  }  return true; }  return super.i2(i); }
/*    */ 
/*    */   
/*    */   public static int z40(LPT3 paramLPT3) {
/*    */     short s;
/*    */     if ((s = dx.l90(paramLPT3.bj0)) != 5154) {
/*    */       switch (s) {
/*    */         default:
/*    */           return Integer.MAX_VALUE;
/*    */         case 5041:
/*    */           return 4;
/*    */         case 5040:
/*    */           return 3;
/*    */         case 5039:
/*    */           return 2;
/*    */         case 5038:
/*    */           break;
/*    */       } 
/*    */       s = 1;
/*    */     } else {
/*    */       s = 0;
/*    */     } 
/*    */     return s;
/*    */   }
/*    */   
/*    */   public static boolean ev0(LPT3 paramLPT3) {
/*    */     return (paramLPT3.C90 > 0 && paramLPT3.default(false) == dv.Vx0);
/*    */   }
/*    */   
/*    */   public final void qb0() {
/*    */     if (this.hC0 == 0) {
/*    */       s6("");
/*    */       Ep0("");
/*    */       return;
/*    */     } 
/*    */     switch (this.Oa0) {
/*    */       case 8:
/*    */       
/*    */       case 7:
/*    */       
/*    */       case 6:
/*    */       
/*    */       case 5:
/*    */       
/*    */       case 4:
/*    */       
/*    */       case 3:
/*    */       
/*    */       case 2:
/*    */       
/*    */       case 1:
/*    */       
/*    */       case 0:
/*    */         s6(km.Lpt1.H9(h1.Qd0, null));
/*    */         break;
/*    */     } 
/*    */     String str;
/*    */     if ((str = this.GE0) == null || str.isEmpty())
/*    */       s6(" "); 
/*    */     this.fE0 = -1;
/*    */     if (this.hC0 != 0) {
/*    */       e2 e21;
/*    */       if ((e21 = this.TD) != null)
/*    */         e21.jn0 = 0L; 
/*    */       bg();
/*    */     } 
/*    */   }
/*    */   
/*    */   public final void t4() {
/*    */     super.t4();
/*    */   }
/*    */   
/*    */   public final void Kh(int paramInt, short paramShort, boolean paramBoolean) {
/*    */     if (this.COm8)
/*    */       return; 
/*    */     this.hC0 = paramShort;
/*    */     if (paramShort < 1)
/*    */       paramInt = 0; 
/*    */     this.Fc = paramInt;
/*    */     if (!this.lW && paramBoolean) {
/*    */       switch (this.Oa0) {
/*    */         case 8:
/*    */           EC.l4 = paramShort;
/*    */           EC.VA0 = paramInt;
/*    */           break;
/*    */         case 7:
/*    */           EC.PU = paramShort;
/*    */           EC.w1 = paramInt;
/*    */           break;
/*    */         case 6:
/*    */           EC.ef0 = paramShort;
/*    */           EC.NV = paramInt;
/*    */           break;
/*    */         case 5:
/*    */           EC.Y90 = paramShort;
/*    */           EC.FX = paramInt;
/*    */           break;
/*    */         case 4:
/*    */           EC.Hc0 = paramShort;
/*    */           EC.yc = paramInt;
/*    */           break;
/*    */         case 3:
/*    */           EC.Qj = paramShort;
/*    */           EC.Y60 = paramInt;
/*    */           break;
/*    */         case 2:
/*    */           EC.LS = paramShort;
/*    */           EC.Fj = paramInt;
/*    */           break;
/*    */         case 1:
/*    */           EC.fr = paramShort;
/*    */           EC.ie = paramInt;
/*    */           break;
/*    */         case 0:
/*    */           EC.nF = paramShort;
/*    */           EC.xM = paramInt;
/*    */           break;
/*    */       } 
/*    */       EC.WD0 = true;
/*    */     } 
/*    */     qb0();
/*    */     super.t4();
/*    */   }
/*    */   
/*    */   public final void Tm0(Y paramY) {
/*    */     if (this.COm8)
/*    */       return; 
/*    */     if (paramY == null) {
/*    */       Kh(0, (short)0, true);
/*    */     } else {
/*    */       if (paramY.Bp0.default(false) == dv.wS)
/*    */         return; 
/*    */       short s = paramY.Lh.p1;
/*    */       Kh(paramY.Lh.Wy, s, true);
/*    */     } 
/*    */   }
/*    */   
/*    */   public final boolean ld() {
/*    */     // Byte code:
/*    */     //   0: aload_0
/*    */     //   1: getfield hC0 : S
/*    */     //   4: dup
/*    */     //   5: istore_1
/*    */     //   6: ifle -> 481
/*    */     //   9: aload_0
/*    */     //   10: getfield HO : Lf/e2;
/*    */     //   13: invokevirtual Po0 : ()Z
/*    */     //   16: ifeq -> 481
/*    */     //   19: getstatic f/Of.eH : Lf/Of;
/*    */     //   22: iload_1
/*    */     //   23: invokevirtual On0 : (S)Lf/LPT3;
/*    */     //   26: dup
/*    */     //   27: astore_2
/*    */     //   28: getfield c3 : Lf/wc;
/*    */     //   31: ifnull -> 50
/*    */     //   34: getstatic f/km.u4 : Lf/R8;
/*    */     //   37: iload_1
/*    */     //   38: aload_0
/*    */     //   39: getfield Fc : I
/*    */     //   42: iconst_0
/*    */     //   43: iconst_1
/*    */     //   44: iconst_m1
/*    */     //   45: invokevirtual tq0 : (SIISB)V
/*    */     //   48: iconst_1
/*    */     //   49: ireturn
/*    */     //   50: getstatic f/km.MR : Lf/Gp0;
/*    */     //   53: ifnull -> 219
/*    */     //   56: aload_2
/*    */     //   57: iconst_1
/*    */     //   58: invokevirtual default : (Z)Lf/dv;
/*    */     //   61: invokevirtual ordinal : ()I
/*    */     //   64: dup
/*    */     //   65: istore_0
/*    */     //   66: iconst_2
/*    */     //   67: if_icmpeq -> 82
/*    */     //   70: iload_0
/*    */     //   71: iconst_3
/*    */     //   72: if_icmpeq -> 82
/*    */     //   75: iload_0
/*    */     //   76: iconst_4
/*    */     //   77: if_icmpeq -> 82
/*    */     //   80: iconst_0
/*    */     //   81: ireturn
/*    */     //   82: getstatic f/km.wI0 : Lf/Pw;
/*    */     //   85: getfield K7 : Lf/Wl;
/*    */     //   88: dup
/*    */     //   89: astore_0
/*    */     //   90: ifnull -> 217
/*    */     //   93: aload_0
/*    */     //   94: getfield LW : Lf/kf;
/*    */     //   97: dup
/*    */     //   98: astore_0
/*    */     //   99: ifnonnull -> 105
/*    */     //   102: goto -> 217
/*    */     //   105: aload_0
/*    */     //   106: getfield n00 : Lf/ia0;
/*    */     //   109: dup
/*    */     //   110: astore_1
/*    */     //   111: ifnonnull -> 116
/*    */     //   114: iconst_1
/*    */     //   115: ireturn
/*    */     //   116: aload_0
/*    */     //   117: invokevirtual kv : ()Z
/*    */     //   120: ifeq -> 215
/*    */     //   123: aload_1
/*    */     //   124: dup
/*    */     //   125: iconst_1
/*    */     //   126: invokevirtual wI0 : (Z)V
/*    */     //   129: getfield K90 : Lf/Dk;
/*    */     //   132: dup
/*    */     //   133: astore_0
/*    */     //   134: ifnull -> 148
/*    */     //   137: aload_1
/*    */     //   138: dup
/*    */     //   139: aload_0
/*    */     //   140: invokevirtual jf0 : (Lf/JG0;)Z
/*    */     //   143: pop
/*    */     //   144: aconst_null
/*    */     //   145: putfield K90 : Lf/Dk;
/*    */     //   148: aload_1
/*    */     //   149: dup
/*    */     //   150: dup2
/*    */     //   151: dup2
/*    */     //   152: invokevirtual gx : ()V
/*    */     //   155: new f/Dk
/*    */     //   158: dup
/*    */     //   159: dup
/*    */     //   160: astore_0
/*    */     //   161: aload_1
/*    */     //   162: aload_2
/*    */     //   163: iconst_0
/*    */     //   164: iconst_0
/*    */     //   165: invokespecial <init> : (Lf/Bf;Lf/LPT3;IZ)V
/*    */     //   168: putfield K90 : Lf/Dk;
/*    */     //   171: aload_0
/*    */     //   172: invokevirtual y : ()Lf/Un;
/*    */     //   175: invokestatic c90 : (Lf/JG0;)Z
/*    */     //   178: pop
/*    */     //   179: iconst_1
/*    */     //   180: anewarray f/JG0
/*    */     //   183: dup
/*    */     //   184: aload_1
/*    */     //   185: getfield K90 : Lf/Dk;
/*    */     //   188: iconst_0
/*    */     //   189: swap
/*    */     //   190: aastore
/*    */     //   191: invokevirtual vo0 : ([Lf/JG0;)Lf/U90;
/*    */     //   194: invokevirtual WN : (Lf/U90;)V
/*    */     //   197: iconst_1
/*    */     //   198: anewarray f/JG0
/*    */     //   201: dup
/*    */     //   202: aload_1
/*    */     //   203: getfield K90 : Lf/Dk;
/*    */     //   206: iconst_0
/*    */     //   207: swap
/*    */     //   208: aastore
/*    */     //   209: invokevirtual AUX : ([Lf/JG0;)Lf/U90;
/*    */     //   212: invokevirtual rK0 : (Lf/U90;)V
/*    */     //   215: iconst_1
/*    */     //   216: ireturn
/*    */     //   217: iconst_1
/*    */     //   218: ireturn
/*    */     //   219: getstatic f/km.u4 : Lf/R8;
/*    */     //   222: invokevirtual NR : ()Z
/*    */     //   225: ifne -> 479
/*    */     //   228: getstatic f/km.u4 : Lf/R8;
/*    */     //   231: getfield tN : Z
/*    */     //   234: ifeq -> 240
/*    */     //   237: goto -> 479
/*    */     //   240: aload_2
/*    */     //   241: iconst_0
/*    */     //   242: invokevirtual default : (Z)Lf/dv;
/*    */     //   245: invokevirtual ordinal : ()I
/*    */     //   248: tableswitch default -> 280, 1 -> 466, 2 -> 282, 3 -> 282, 4 -> 282
/*    */     //   280: iconst_0
/*    */     //   281: ireturn
/*    */     //   282: aconst_null
/*    */     //   283: astore_0
/*    */     //   284: getstatic f/km.u4 : Lf/R8;
/*    */     //   287: getstatic f/yM.r4 : Lf/yM;
/*    */     //   290: pop
/*    */     //   291: getfield Fe : [Lf/zr0;
/*    */     //   294: iconst_1
/*    */     //   295: aaload
/*    */     //   296: invokevirtual ro0 : ()[Lf/Y;
/*    */     //   299: dup
/*    */     //   300: astore_2
/*    */     //   301: arraylength
/*    */     //   302: istore_3
/*    */     //   303: iconst_0
/*    */     //   304: istore #4
/*    */     //   306: iload #4
/*    */     //   308: iload_3
/*    */     //   309: if_icmpge -> 338
/*    */     //   312: iload_1
/*    */     //   313: aload_2
/*    */     //   314: iload #4
/*    */     //   316: aaload
/*    */     //   317: dup
/*    */     //   318: astore #5
/*    */     //   320: getfield Lh : Lf/nH0;
/*    */     //   323: getfield p1 : S
/*    */     //   326: if_icmpne -> 332
/*    */     //   329: aload #5
/*    */     //   331: astore_0
/*    */     //   332: iinc #4, 1
/*    */     //   335: goto -> 306
/*    */     //   338: aload_0
/*    */     //   339: ifnonnull -> 344
/*    */     //   342: iconst_0
/*    */     //   343: ireturn
/*    */     //   344: getstatic f/pA.Dg0 : Lf/pA;
/*    */     //   347: dup
/*    */     //   348: astore_1
/*    */     //   349: getfield Mc : Lf/wg0;
/*    */     //   352: dup
/*    */     //   353: astore_2
/*    */     //   354: ifnull -> 367
/*    */     //   357: aload_1
/*    */     //   358: aload_2
/*    */     //   359: invokevirtual ra0 : ()Z
/*    */     //   362: pop
/*    */     //   363: aconst_null
/*    */     //   364: putfield Mc : Lf/wg0;
/*    */     //   367: aload_1
/*    */     //   368: dup
/*    */     //   369: dup
/*    */     //   370: dup2
/*    */     //   371: new f/wg0
/*    */     //   374: dup
/*    */     //   375: aload_1
/*    */     //   376: swap
/*    */     //   377: dup
/*    */     //   378: aload_1
/*    */     //   379: iconst_1
/*    */     //   380: invokespecial <init> : (Lf/pA;Z)V
/*    */     //   383: putfield Mc : Lf/wg0;
/*    */     //   386: sipush #350
/*    */     //   389: sipush #200
/*    */     //   392: invokevirtual uh0 : (II)V
/*    */     //   395: getfield Mc : Lf/wg0;
/*    */     //   398: sipush #350
/*    */     //   401: sipush #200
/*    */     //   404: invokevirtual Tm : (II)Z
/*    */     //   407: pop
/*    */     //   408: getfield Mc : Lf/wg0;
/*    */     //   411: getstatic f/km.wI0 : Lf/Pw;
/*    */     //   414: invokevirtual dG : ()I
/*    */     //   417: iconst_2
/*    */     //   418: idiv
/*    */     //   419: aload_1
/*    */     //   420: getfield Mc : Lf/wg0;
/*    */     //   423: getfield xY : I
/*    */     //   426: iconst_2
/*    */     //   427: idiv
/*    */     //   428: isub
/*    */     //   429: getstatic f/km.wI0 : Lf/Pw;
/*    */     //   432: invokevirtual k1 : ()I
/*    */     //   435: iconst_2
/*    */     //   436: idiv
/*    */     //   437: aload_1
/*    */     //   438: getfield Mc : Lf/wg0;
/*    */     //   441: getfield HC : I
/*    */     //   444: iconst_2
/*    */     //   445: idiv
/*    */     //   446: isub
/*    */     //   447: invokevirtual ME : (II)Z
/*    */     //   450: pop
/*    */     //   451: getfield Mc : Lf/wg0;
/*    */     //   454: invokevirtual J8 : (Lf/JG0;)V
/*    */     //   457: getfield Mc : Lf/wg0;
/*    */     //   460: aload_0
/*    */     //   461: invokevirtual SL0 : (Lf/Y;)V
/*    */     //   464: iconst_1
/*    */     //   465: ireturn
/*    */     //   466: getstatic f/km.u4 : Lf/R8;
/*    */     //   469: iload_1
/*    */     //   470: iconst_0
/*    */     //   471: iconst_0
/*    */     //   472: iconst_1
/*    */     //   473: iconst_m1
/*    */     //   474: invokevirtual tq0 : (SIISB)V
/*    */     //   477: iconst_1
/*    */     //   478: ireturn
/*    */     //   479: iconst_0
/*    */     //   480: ireturn
/*    */     //   481: iload_1
/*    */     //   482: ifge -> 1467
/*    */     //   485: aload_0
/*    */     //   486: getfield HO : Lf/e2;
/*    */     //   489: invokevirtual Po0 : ()Z
/*    */     //   492: ifeq -> 1467
/*    */     //   495: getstatic f/km.u4 : Lf/R8;
/*    */     //   498: dup
/*    */     //   499: astore_2
/*    */     //   500: ifnull -> 1467
/*    */     //   503: aload_2
/*    */     //   504: invokevirtual NR : ()Z
/*    */     //   507: ifeq -> 512
/*    */     //   510: iconst_0
/*    */     //   511: ireturn
/*    */     //   512: getstatic f/km.a3 : Lf/vh0;
/*    */     //   515: invokevirtual Jr0 : ()Lf/KI;
/*    */     //   518: dup
/*    */     //   519: astore_2
/*    */     //   520: ifnull -> 535
/*    */     //   523: aload_2
/*    */     //   524: invokevirtual XC : ()Z
/*    */     //   527: ifeq -> 535
/*    */     //   530: iconst_1
/*    */     //   531: istore_2
/*    */     //   532: goto -> 537
/*    */     //   535: iconst_0
/*    */     //   536: istore_2
/*    */     //   537: iload_1
/*    */     //   538: iconst_m1
/*    */     //   539: imul
/*    */     //   540: i2s
/*    */     //   541: dup
/*    */     //   542: istore_1
/*    */     //   543: iload_2
/*    */     //   544: invokestatic e6 : (SZ)Z
/*    */     //   547: ifne -> 552
/*    */     //   550: iconst_0
/*    */     //   551: ireturn
/*    */     //   552: iconst_0
/*    */     //   553: istore_3
/*    */     //   554: aconst_null
/*    */     //   555: astore #4
/*    */     //   557: getstatic f/km.u4 : Lf/R8;
/*    */     //   560: getfield z2 : Lf/Uc0;
/*    */     //   563: invokevirtual lPt3 : ()[Lf/j40;
/*    */     //   566: dup
/*    */     //   567: astore #5
/*    */     //   569: arraylength
/*    */     //   570: istore #6
/*    */     //   572: iconst_0
/*    */     //   573: istore #7
/*    */     //   575: iload #7
/*    */     //   577: iload #6
/*    */     //   579: if_icmpge -> 676
/*    */     //   582: aload #5
/*    */     //   584: iload #7
/*    */     //   586: aaload
/*    */     //   587: dup
/*    */     //   588: astore #8
/*    */     //   590: ifnull -> 670
/*    */     //   593: aload #8
/*    */     //   595: getfield Zs : Lf/Q90;
/*    */     //   598: invokevirtual YC : ()Z
/*    */     //   601: ifeq -> 607
/*    */     //   604: goto -> 670
/*    */     //   607: iconst_0
/*    */     //   608: istore #9
/*    */     //   610: iload #9
/*    */     //   612: iconst_4
/*    */     //   613: if_icmpge -> 670
/*    */     //   616: aload #8
/*    */     //   618: getfield Zs : Lf/Q90;
/*    */     //   621: dup
/*    */     //   622: astore #10
/*    */     //   624: getfield En0 : [S
/*    */     //   627: iload #9
/*    */     //   629: saload
/*    */     //   630: iload_1
/*    */     //   631: if_icmpne -> 660
/*    */     //   634: aload #10
/*    */     //   636: getfield rI0 : [B
/*    */     //   639: iload #9
/*    */     //   641: baload
/*    */     //   642: dup
/*    */     //   643: istore #10
/*    */     //   645: iload_3
/*    */     //   646: if_icmpgt -> 653
/*    */     //   649: iload_3
/*    */     //   650: ifne -> 660
/*    */     //   653: iload #10
/*    */     //   655: aload #8
/*    */     //   657: astore #4
/*    */     //   659: istore_3
/*    */     //   660: iload #9
/*    */     //   662: iconst_1
/*    */     //   663: iadd
/*    */     //   664: i2b
/*    */     //   665: istore #9
/*    */     //   667: goto -> 610
/*    */     //   670: iinc #7, 1
/*    */     //   673: goto -> 575
/*    */     //   676: aload #4
/*    */     //   678: ifnonnull -> 704
/*    */     //   681: getstatic f/km.u4 : Lf/R8;
/*    */     //   684: iload_1
/*    */     //   685: ldc_w 110000
/*    */     //   688: iadd
/*    */     //   689: invokestatic OH0 : (I)Ljava/lang/String;
/*    */     //   692: sipush #6081
/*    */     //   695: swap
/*    */     //   696: invokestatic Go : (ILjava/lang/String;)Ljava/lang/String;
/*    */     //   699: invokevirtual Pq : (Ljava/lang/String;)V
/*    */     //   702: iconst_0
/*    */     //   703: ireturn
/*    */     //   704: iload_1
/*    */     //   705: sipush #230
/*    */     //   708: if_icmpne -> 1357
/*    */     //   711: iload_3
/*    */     //   712: getstatic f/gm.lw : B
/*    */     //   715: if_icmpge -> 1357
/*    */     //   718: getstatic f/km.MR : Lf/Gp0;
/*    */     //   721: ifnonnull -> 1357
/*    */     //   724: getstatic f/SE0.f80 : Z
/*    */     //   727: ifeq -> 732
/*    */     //   730: iconst_0
/*    */     //   731: ireturn
/*    */     //   732: aload #4
/*    */     //   734: getfield Zs : Lf/Q90;
/*    */     //   737: getfield En0 : [S
/*    */     //   740: dup
/*    */     //   741: astore_0
/*    */     //   742: sipush #230
/*    */     //   745: istore_1
/*    */     //   746: iconst_0
/*    */     //   747: istore_2
/*    */     //   748: ifnull -> 782
/*    */     //   751: aload_0
/*    */     //   752: arraylength
/*    */     //   753: iconst_1
/*    */     //   754: if_icmpge -> 760
/*    */     //   757: goto -> 782
/*    */     //   760: iload_2
/*    */     //   761: aload_0
/*    */     //   762: arraylength
/*    */     //   763: if_icmpge -> 782
/*    */     //   766: iload_1
/*    */     //   767: aload_0
/*    */     //   768: iload_2
/*    */     //   769: saload
/*    */     //   770: if_icmpne -> 776
/*    */     //   773: goto -> 784
/*    */     //   776: iinc #2, 1
/*    */     //   779: goto -> 760
/*    */     //   782: iconst_m1
/*    */     //   783: istore_2
/*    */     //   784: iload_2
/*    */     //   785: iconst_m1
/*    */     //   786: if_icmpne -> 803
/*    */     //   789: getstatic f/km.u4 : Lf/R8;
/*    */     //   792: ldc_w 200244
/*    */     //   795: invokestatic OH0 : (I)Ljava/lang/String;
/*    */     //   798: invokevirtual Pq : (Ljava/lang/String;)V
/*    */     //   801: iconst_0
/*    */     //   802: ireturn
/*    */     //   803: getstatic f/km.u4 : Lf/R8;
/*    */     //   806: dup
/*    */     //   807: getfield jG0 : Lf/yM;
/*    */     //   810: invokevirtual gN : (Lf/yM;)Lf/zr0;
/*    */     //   813: invokevirtual ro0 : ()[Lf/Y;
/*    */     //   816: invokestatic stream : ([Ljava/lang/Object;)Ljava/util/stream/Stream;
/*    */     //   819: <illegal opcode> apply : ()Ljava/util/function/Function;
/*    */     //   824: invokeinterface map : (Ljava/util/function/Function;)Ljava/util/stream/Stream;
/*    */     //   829: <illegal opcode> test : ()Ljava/util/function/Predicate;
/*    */     //   834: invokeinterface filter : (Ljava/util/function/Predicate;)Ljava/util/stream/Stream;
/*    */     //   839: invokeinterface distinct : ()Ljava/util/stream/Stream;
/*    */     //   844: <illegal opcode> applyAsInt : ()Ljava/util/function/ToIntFunction;
/*    */     //   849: invokestatic comparingInt : (Ljava/util/function/ToIntFunction;)Ljava/util/Comparator;
/*    */     //   852: invokeinterface min : (Ljava/util/Comparator;)Ljava/util/Optional;
/*    */     //   857: aconst_null
/*    */     //   858: invokevirtual orElse : (Ljava/lang/Object;)Ljava/lang/Object;
/*    */     //   861: checkcast f/LPT3
/*    */     //   864: dup
/*    */     //   865: astore_0
/*    */     //   866: ifnonnull -> 883
/*    */     //   869: getstatic f/km.u4 : Lf/R8;
/*    */     //   872: ldc_w 200244
/*    */     //   875: invokestatic OH0 : (I)Ljava/lang/String;
/*    */     //   878: invokevirtual Pq : (Ljava/lang/String;)V
/*    */     //   881: iconst_0
/*    */     //   882: ireturn
/*    */     //   883: getstatic f/km.u4 : Lf/R8;
/*    */     //   886: dup
/*    */     //   887: getfield jG0 : Lf/yM;
/*    */     //   890: invokevirtual gN : (Lf/yM;)Lf/zr0;
/*    */     //   893: aload_0
/*    */     //   894: invokevirtual V7 : (Lf/LPT3;)Lf/Y;
/*    */     //   897: dup
/*    */     //   898: astore_1
/*    */     //   899: ifnonnull -> 916
/*    */     //   902: getstatic f/km.u4 : Lf/R8;
/*    */     //   905: ldc_w 200244
/*    */     //   908: invokestatic OH0 : (I)Ljava/lang/String;
/*    */     //   911: invokevirtual Pq : (Ljava/lang/String;)V
/*    */     //   914: iconst_0
/*    */     //   915: ireturn
/*    */     //   916: aload_1
/*    */     //   917: aload #4
/*    */     //   919: aload_1
/*    */     //   920: iconst_1
/*    */     //   921: putstatic f/SE0.f80 : Z
/*    */     //   924: getfield Lh : Lf/nH0;
/*    */     //   927: getfield Sf0 : S
/*    */     //   930: istore_3
/*    */     //   931: getfield Zs : Lf/Q90;
/*    */     //   934: iload_2
/*    */     //   935: invokestatic cw : ()Lf/yk0;
/*    */     //   938: sipush #230
/*    */     //   941: invokevirtual mP : (S)Lf/WD;
/*    */     //   944: getfield nul : B
/*    */     //   947: invokevirtual Vk0 : (IB)B
/*    */     //   950: aload #4
/*    */     //   952: getfield Zs : Lf/Q90;
/*    */     //   955: getfield rI0 : [B
/*    */     //   958: iload_2
/*    */     //   959: baload
/*    */     //   960: isub
/*    */     //   961: istore #5
/*    */     //   963: getfield Bp0 : Lf/LPT3;
/*    */     //   966: getfield EA : Z
/*    */     //   969: ifeq -> 987
/*    */     //   972: iload_3
/*    */     //   973: iload #5
/*    */     //   975: aload_0
/*    */     //   976: getfield C90 : B
/*    */     //   979: idiv
/*    */     //   980: invokestatic min : (II)I
/*    */     //   983: istore_3
/*    */     //   984: goto -> 989
/*    */     //   987: iconst_1
/*    */     //   988: istore_3
/*    */     //   989: new java/util/ArrayList
/*    */     //   992: dup
/*    */     //   993: astore #5
/*    */     //   995: invokespecial <init> : ()V
/*    */     //   998: iload_3
/*    */     //   999: ifle -> 1029
/*    */     //   1002: aload #5
/*    */     //   1004: new f/E50
/*    */     //   1007: dup
/*    */     //   1008: astore #6
/*    */     //   1010: iload_3
/*    */     //   1011: i2b
/*    */     //   1012: aload_0
/*    */     //   1013: swap
/*    */     //   1014: invokespecial <init> : (Lf/LPT3;B)V
/*    */     //   1017: aload #6
/*    */     //   1019: invokevirtual add : (Ljava/lang/Object;)Z
/*    */     //   1022: pop
/*    */     //   1023: iinc #3, -1
/*    */     //   1026: goto -> 998
/*    */     //   1029: aload #5
/*    */     //   1031: invokeinterface stream : ()Ljava/util/stream/Stream;
/*    */     //   1036: <illegal opcode> apply : ()Ljava/util/function/Function;
/*    */     //   1041: invokeinterface map : (Ljava/util/function/Function;)Ljava/util/stream/Stream;
/*    */     //   1046: invokestatic toList : ()Ljava/util/stream/Collector;
/*    */     //   1049: invokeinterface collect : (Ljava/util/stream/Collector;)Ljava/lang/Object;
/*    */     //   1054: checkcast java/util/List
/*    */     //   1057: dup
/*    */     //   1058: astore_0
/*    */     //   1059: bipush #53
/*    */     //   1061: invokestatic OH0 : (I)Ljava/lang/String;
/*    */     //   1064: invokeinterface add : (Ljava/lang/Object;)Z
/*    */     //   1069: pop
/*    */     //   1070: getstatic f/s10.hU : Lf/s10;
/*    */     //   1073: dup
/*    */     //   1074: astore_3
/*    */     //   1075: new f/ss
/*    */     //   1078: dup
/*    */     //   1079: astore #6
/*    */     //   1081: aload_0
/*    */     //   1082: iconst_0
/*    */     //   1083: anewarray java/lang/String
/*    */     //   1086: invokeinterface toArray : ([Ljava/lang/Object;)[Ljava/lang/Object;
/*    */     //   1091: checkcast [Ljava/lang/String;
/*    */     //   1094: iconst_0
/*    */     //   1095: swap
/*    */     //   1096: invokespecial <init> : (B[Ljava/lang/String;)V
/*    */     //   1099: getfield vw0 : [Lf/Vc0;
/*    */     //   1102: bipush #10
/*    */     //   1104: aaload
/*    */     //   1105: astore_0
/*    */     //   1106: bipush #-128
/*    */     //   1108: istore #7
/*    */     //   1110: iload #7
/*    */     //   1112: ifge -> 1346
/*    */     //   1115: aload_0
/*    */     //   1116: getfield ix : Lf/ak;
/*    */     //   1119: iload #7
/*    */     //   1121: invokevirtual Ha0 : (B)Ljava/lang/Object;
/*    */     //   1124: checkcast f/ss
/*    */     //   1127: ifnonnull -> 1336
/*    */     //   1130: aload_3
/*    */     //   1131: aload #6
/*    */     //   1133: iload #7
/*    */     //   1135: putfield v2 : B
/*    */     //   1138: getfield vw0 : [Lf/Vc0;
/*    */     //   1141: bipush #10
/*    */     //   1143: aaload
/*    */     //   1144: aload #6
/*    */     //   1146: invokestatic Ss : (Lf/Vc0;Lf/ss;)V
/*    */     //   1149: iconst_2
/*    */     //   1150: anewarray java/lang/String
/*    */     //   1153: dup
/*    */     //   1154: dup
/*    */     //   1155: astore_0
/*    */     //   1156: aload #4
/*    */     //   1158: invokevirtual m : ()Ljava/lang/String;
/*    */     //   1161: iconst_0
/*    */     //   1162: swap
/*    */     //   1163: aastore
/*    */     //   1164: ldc_w 110230
/*    */     //   1167: invokestatic OH0 : (I)Ljava/lang/String;
/*    */     //   1170: iconst_1
/*    */     //   1171: swap
/*    */     //   1172: aastore
/*    */     //   1173: sipush #8600
/*    */     //   1176: aload_0
/*    */     //   1177: invokestatic sB : (I[Ljava/lang/String;)Ljava/lang/String;
/*    */     //   1180: astore_0
/*    */     //   1181: new f/p2
/*    */     //   1184: dup
/*    */     //   1185: astore_3
/*    */     //   1186: aload #5
/*    */     //   1188: aload #6
/*    */     //   1190: aload_3
/*    */     //   1191: dup
/*    */     //   1192: aload #6
/*    */     //   1194: getstatic f/km.u4 : Lf/R8;
/*    */     //   1197: getfield Lz : Lf/fH0;
/*    */     //   1200: getfield OU : I
/*    */     //   1203: istore #5
/*    */     //   1205: getstatic f/Aq.id0 : Lf/Aq;
/*    */     //   1208: astore #6
/*    */     //   1210: getfield v2 : B
/*    */     //   1213: istore #7
/*    */     //   1215: iload #5
/*    */     //   1217: aload #6
/*    */     //   1219: iconst_1
/*    */     //   1220: anewarray java/lang/String
/*    */     //   1223: dup
/*    */     //   1224: astore #5
/*    */     //   1226: iconst_0
/*    */     //   1227: ldc ''
/*    */     //   1229: aastore
/*    */     //   1230: aload_0
/*    */     //   1231: iload #7
/*    */     //   1233: aload #5
/*    */     //   1235: invokespecial <init> : (ILf/Aq;Ljava/lang/String;B[Ljava/lang/String;)V
/*    */     //   1238: aload_1
/*    */     //   1239: aload #4
/*    */     //   1241: iload_2
/*    */     //   1242: <illegal opcode> S00 : (Ljava/util/List;Lf/ss;Lf/hO;Lf/Y;Lf/j40;I)Lf/Ku0;
/*    */     //   1247: putfield XK0 : Lf/Ku0;
/*    */     //   1250: getstatic f/km.kH0 : Lf/Qz0;
/*    */     //   1253: dup
/*    */     //   1254: astore_0
/*    */     //   1255: aload_3
/*    */     //   1256: aload_0
/*    */     //   1257: dup
/*    */     //   1258: dup
/*    */     //   1259: dup2
/*    */     //   1260: aload_3
/*    */     //   1261: aload_0
/*    */     //   1262: sipush #-32767
/*    */     //   1265: istore_1
/*    */     //   1266: invokevirtual Ub : ()I
/*    */     //   1269: invokevirtual si : (Lf/JG0;I)V
/*    */     //   1272: getfield A5 : Lf/Ut0;
/*    */     //   1275: iload_1
/*    */     //   1276: aload_3
/*    */     //   1277: invokevirtual A3 : (ILjava/lang/Object;)Ljava/lang/Object;
/*    */     //   1280: pop
/*    */     //   1281: getfield A5 : Lf/Ut0;
/*    */     //   1284: iload_1
/*    */     //   1285: invokevirtual Z6 : (I)Ljava/lang/Object;
/*    */     //   1288: checkcast f/hO
/*    */     //   1291: ldc_w -2147483648
/*    */     //   1294: ldc_w -2147483648
/*    */     //   1297: invokevirtual ME : (II)Z
/*    */     //   1300: pop
/*    */     //   1301: getfield A5 : Lf/Ut0;
/*    */     //   1304: iload_1
/*    */     //   1305: invokevirtual Z6 : (I)Ljava/lang/Object;
/*    */     //   1308: checkcast f/hO
/*    */     //   1311: invokevirtual mM : ()V
/*    */     //   1314: getfield Ot : Lf/js;
/*    */     //   1317: aload_0
/*    */     //   1318: invokevirtual Af : (Lf/JG0;)V
/*    */     //   1321: invokevirtual Af : (Lf/JG0;)V
/*    */     //   1324: getstatic f/km.kH0 : Lf/Qz0;
/*    */     //   1327: getfield D1 : Lf/fQ;
/*    */     //   1330: aload_3
/*    */     //   1331: invokevirtual Com3 : (Ljava/lang/Object;)V
/*    */     //   1334: iconst_1
/*    */     //   1335: ireturn
/*    */     //   1336: iload #7
/*    */     //   1338: iconst_1
/*    */     //   1339: iadd
/*    */     //   1340: i2b
/*    */     //   1341: istore #7
/*    */     //   1343: goto -> 1110
/*    */     //   1346: new java/lang/RuntimeException
/*    */     //   1349: dup
/*    */     //   1350: ldc_w 'Unable to allocate id'
/*    */     //   1353: invokespecial <init> : (Ljava/lang/String;)V
/*    */     //   1356: athrow
/*    */     //   1357: iload_1
/*    */     //   1358: iload_2
/*    */     //   1359: invokestatic CE0 : (SZ)Z
/*    */     //   1362: ifeq -> 1395
/*    */     //   1365: aload_0
/*    */     //   1366: aload #4
/*    */     //   1368: getstatic f/js.vu0 : Lf/js;
/*    */     //   1371: aload_0
/*    */     //   1372: dup
/*    */     //   1373: getfield Kd : I
/*    */     //   1376: istore_0
/*    */     //   1377: getfield er0 : I
/*    */     //   1380: istore_2
/*    */     //   1381: invokevirtual getClass : ()Ljava/lang/Class;
/*    */     //   1384: pop
/*    */     //   1385: iload_1
/*    */     //   1386: iload_0
/*    */     //   1387: iload_2
/*    */     //   1388: aconst_null
/*    */     //   1389: invokestatic yC0 : (Lf/JG0;Lf/j40;SIILjava/lang/Runnable;)V
/*    */     //   1392: goto -> 1465
/*    */     //   1395: iload_1
/*    */     //   1396: aload #4
/*    */     //   1398: getstatic f/km.u4 : Lf/R8;
/*    */     //   1401: astore_0
/*    */     //   1402: getfield Jg : I
/*    */     //   1405: istore_2
/*    */     //   1406: iconst_0
/*    */     //   1407: istore_3
/*    */     //   1408: iconst_0
/*    */     //   1409: istore #4
/*    */     //   1411: bipush #19
/*    */     //   1413: if_icmpne -> 1446
/*    */     //   1416: aload_0
/*    */     //   1417: dup
/*    */     //   1418: invokevirtual getClass : ()Ljava/lang/Class;
/*    */     //   1421: pop
/*    */     //   1422: iconst_1
/*    */     //   1423: istore_0
/*    */     //   1424: aconst_null
/*    */     //   1425: astore_1
/*    */     //   1426: getfield YG0 : Lf/js;
/*    */     //   1429: getfield MH0 : Lf/pA;
/*    */     //   1432: dup
/*    */     //   1433: astore_2
/*    */     //   1434: ifnull -> 1465
/*    */     //   1437: aload_2
/*    */     //   1438: iload_0
/*    */     //   1439: aload_1
/*    */     //   1440: invokevirtual U10 : (ZLf/R2;)V
/*    */     //   1443: goto -> 1465
/*    */     //   1446: aload_0
/*    */     //   1447: getfield e20 : Lf/c4;
/*    */     //   1450: new f/NH
/*    */     //   1453: dup
/*    */     //   1454: iload_2
/*    */     //   1455: iload_3
/*    */     //   1456: iload #4
/*    */     //   1458: iload_1
/*    */     //   1459: invokespecial <init> : (IIIS)V
/*    */     //   1462: invokevirtual W3 : (Lf/Bi;)V
/*    */     //   1465: iconst_1
/*    */     //   1466: ireturn
/*    */     //   1467: iconst_0
/*    */     //   1468: ireturn
/*    */     // Line number table:
/*    */     //   Java source line number -> byte code offset
/*    */     //   #1	-> 19
/*    */     //   #2	-> 23
/*    */     //   #3	-> 28
/*    */     //   #4	-> 34
/*    */     //   #5	-> 85
/*    */     //   #6	-> 94
/*    */     //   #7	-> 106
/*    */     //   #8	-> 117
/*    */     //   #9	-> 129
/*    */     //   #10	-> 172
/*    */     //   #11	-> 175
/*    */     //   #12	-> 180
/*    */     //   #13	-> 219
/*    */     //   #14	-> 231
/*    */     //   #15	-> 242
/*    */     //   #16	-> 291
/*    */     //   #17	-> 295
/*    */     //   #18	-> 296
/*    */     //   #19	-> 320
/*    */     //   #20	-> 323
/*    */     //   #21	-> 344
/*    */     //   #22	-> 349
/*    */     //   #23	-> 359
/*    */     //   #24	-> 423
/*    */     //   #25	-> 427
/*    */     //   #26	-> 441
/*    */     //   #27	-> 445
/*    */     //   #28	-> 447
/*    */     //   #29	-> 451
/*    */     //   #30	-> 466
/*    */     //   #31	-> 560
/*    */     //   #32	-> 563
/*    */     //   #33	-> 595
/*    */     //   #34	-> 618
/*    */     //   #35	-> 624
/*    */     //   #36	-> 629
/*    */     //   #37	-> 636
/*    */     //   #38	-> 641
/*    */     //   #39	-> 681
/*    */     //   #40	-> 734
/*    */     //   #41	-> 737
/*    */     //   #42	-> 752
/*    */     //   #43	-> 789
/*    */     //   #44	-> 807
/*    */     //   #45	-> 810
/*    */     //   #46	-> 813
/*    */     //   #47	-> 887
/*    */     //   #48	-> 890
/*    */     //   #49	-> 894
/*    */     //   #50	-> 924
/*    */     //   #51	-> 927
/*    */     //   #52	-> 931
/*    */     //   #53	-> 935
/*    */     //   #54	-> 944
/*    */     //   #55	-> 947
/*    */     //   #56	-> 952
/*    */     //   #57	-> 955
/*    */     //   #58	-> 959
/*    */     //   #59	-> 963
/*    */     //   #60	-> 966
/*    */     //   #61	-> 976
/*    */     //   #62	-> 979
/*    */     //   #63	-> 1070
/*    */     //   #64	-> 1075
/*    */     //   #65	-> 1099
/*    */     //   #66	-> 1104
/*    */     //   #67	-> 1116
/*    */     //   #68	-> 1121
/*    */     //   #69	-> 1135
/*    */     //   #70	-> 1150
/*    */     //   #71	-> 1197
/*    */     //   #72	-> 1200
/*    */     //   #73	-> 1205
/*    */     //   #74	-> 1247
/*    */     //   #75	-> 1250
/*    */     //   #76	-> 1266
/*    */     //   #77	-> 1269
/*    */     //   #78	-> 1272
/*    */     //   #79	-> 1297
/*    */     //   #80	-> 1301
/*    */     //   #81	-> 1324
/*    */     //   #82	-> 1327
/*    */     //   #83	-> 1331
/*    */     //   #84	-> 1346
/*    */     //   #85	-> 1359
/*    */     //   #86	-> 1368
/*    */     //   #87	-> 1373
/*    */     //   #88	-> 1377
/*    */     //   #89	-> 1381
/*    */     //   #90	-> 1402
/*    */     //   #91	-> 1418
/*    */     //   #92	-> 1426
/*    */     //   #93	-> 1429
/*    */     //   #94	-> 1440
/*    */     //   #95	-> 1447
/*    */     //   #96	-> 1450
/*    */   }
/*    */   
/*    */   public final void R60(throws paramthrows) {
/*    */     super.R60(paramthrows);
/*    */     if (this.TD.Po0())
/*    */       bg(); 
/*    */   }
/*    */   
/*    */   public final void Ve(throws paramthrows, int paramInt1, int paramInt2, int paramInt3) {
/*    */     if (!this.Mc.ti)
/*    */       this.hC0.sG0(paramInt1, paramInt2); 
/*    */   }
/*    */   
/*    */   public final void V90(throws paramthrows) {
/*    */     super.V90(paramthrows);
/*    */     if (km.wI0.K7 != null) {
/*    */       short s = -32767;
/*    */       Qz0 qz0;
/*    */       if ((qz0 = km.kH0).A5.return(s)) {
/*    */         hO hO = (hO)this.A5.remove(s);
/*    */       } else {
/*    */         qz0 = null;
/*    */       } 
/*    */       if (this != null) {
/*    */         km.kH0.D1.Ct(this, true);
/*    */         km.kH0.Kd0 = System.currentTimeMillis();
/*    */         EE0();
/*    */         f80 = false;
/*    */       } 
/*    */     } 
/*    */   }
/*    */   
/*    */   public final void bg() {
/*    */     Hu0 hu0;
/*    */     short s;
/*    */     if ((s = this.hC0) > 0) {
/*    */       hu0 = (Of.eH.On0(s)).Y8;
/*    */       int i;
/*    */       if ((i = km.u4.gN(km.u4.jG0).jW(s)) != this.fE0)
/*    */         if (hu0 != Hu0.Bm) {
/*    */           this.fE0 = i;
/*    */           Ep0(Integer.toString(i));
/*    */         } else {
/*    */           this.fE0 = -1;
/*    */           Ep0("");
/*    */         }  
/*    */     } else if (hu0 < null) {
/*    */       boolean bool;
/*    */       short s1 = -1;
/*    */       short s2 = (short)(hu0 * -1);
/*    */       KI kI;
/*    */       if ((kI = km.a3.Jr0()) != null && kI.XC()) {
/*    */         bool = true;
/*    */       } else {
/*    */         bool = false;
/*    */       } 
/*    */       if (s2 == 230 || (bool && LF.e6(s2, bool))) {
/*    */         s1 = 0;
/*    */         j40[] arrayOfJ40;
/*    */         int i;
/*    */         byte b;
/*    */         for (i = (arrayOfJ40 = km.u4.z2.lPt3()).length, b = 0; b < i; ) {
/*    */           j40 j40;
/*    */           if ((j40 = arrayOfJ40[b]) != null && !j40.Zs.YC())
/*    */             for (byte b1 = 0; b1 < 4; ) {
/*    */               Q90 q90;
/*    */               if ((q90 = j40.Zs).En0[b1] == s2)
/*    */                 s1 = (short)(s1 + q90.rI0[b1]); 
/*    */               b1++;
/*    */             }  
/*    */           b++;
/*    */         } 
/*    */       } 
/*    */       if (this.fE0 != s1) {
/*    */         this.fE0 = s1;
/*    */         Ep0(Integer.toString(s1));
/*    */       } 
/*    */     } 
/*    */   } }


/* Location:              /Users/vnnsnnt/Documents/Codespace/JavaWorkspace/RedTrainer/src/main/java/org/trainer/client/PokeMMO.jar!/f/SE0.class
 * Java compiler version: 8 (52.0)
 * JD-Core Version:       1.1.3
 */