/* 1 */ package f;public final class sk extends GS implements Np0 { public final byte XR; public final byte T; public sk(byte paramByte1, byte paramByte2, int paramInt) { if (paramByte1 != 33) { this.T = paramByte2; this.XR = paramByte1; this.cl = paramInt; this.ez0 = null; return; }  throw new IllegalArgumentException(XD0.SD0("Illegal constructor for info ", paramByte1)); }
/*   */   
/*   */   public final hR[] ez0; public final int cl;
/*   */   public final void Nl(hm0 paramhm01, hm0 paramhm02, boolean paramBoolean1, boolean paramBoolean2, short paramShort, boolean paramBoolean3, kf paramkf, b60 paramb60) {
/*   */     // Byte code:
/*   */     //   0: getstatic f/km.MR : Lf/Gp0;
/*   */     //   3: dup
/*   */     //   4: astore_1
/*   */     //   5: ifnonnull -> 9
/*   */     //   8: return
/*   */     //   9: aload_0
/*   */     //   10: aconst_null
/*   */     //   11: astore_3
/*   */     //   12: getfield XR : B
/*   */     //   15: dup
/*   */     //   16: istore #4
/*   */     //   18: iconst_5
/*   */     //   19: if_icmpeq -> 64
/*   */     //   22: iload #4
/*   */     //   24: tableswitch default -> 60, 49 -> 64, 50 -> 64, 51 -> 64, 52 -> 64, 53 -> 64
/*   */     //   60: iconst_1
/*   */     //   61: goto -> 65
/*   */     //   64: iconst_0
/*   */     //   65: ifeq -> 99
/*   */     //   68: aload_1
/*   */     //   69: aload_0
/*   */     //   70: getfield cl : I
/*   */     //   73: invokevirtual f70 : (I)Lf/cOm4;
/*   */     //   76: dup
/*   */     //   77: astore_1
/*   */     //   78: ifnonnull -> 82
/*   */     //   81: return
/*   */     //   82: aload_0
/*   */     //   83: aload_1
/*   */     //   84: getfield gc : Lf/jd0;
/*   */     //   87: astore_3
/*   */     //   88: getfield cl : I
/*   */     //   91: ifeq -> 99
/*   */     //   94: aload_3
/*   */     //   95: ifnonnull -> 99
/*   */     //   98: return
/*   */     //   99: aload_0
/*   */     //   100: getstatic f/km.MR : Lf/Gp0;
/*   */     //   103: aload_0
/*   */     //   104: getfield T : B
/*   */     //   107: invokevirtual a0 : (B)Lf/PE;
/*   */     //   110: astore_1
/*   */     //   111: getstatic f/km.wI0 : Lf/Pw;
/*   */     //   114: getfield K7 : Lf/Wl;
/*   */     //   117: astore #4
/*   */     //   119: getfield XR : B
/*   */     //   122: dup
/*   */     //   123: istore #5
/*   */     //   125: tableswitch default -> 164, 0 -> 416, 1 -> 431, 2 -> 320, 3 -> 291, 4 -> 273, 5 -> 257
/*   */     //   164: iload #5
/*   */     //   166: tableswitch default -> 192, 16 -> 537, 17 -> 521, 18 -> 505
/*   */     //   192: iload #5
/*   */     //   194: tableswitch default -> 220, 32 -> 595, 33 -> 595, 34 -> 553
/*   */     //   220: iload #5
/*   */     //   222: tableswitch default -> 256, 49 -> 984, 50 -> 972, 51 -> 893, 52 -> 822, 53 -> 685
/*   */     //   256: return
/*   */     //   257: aload #7
/*   */     //   259: aload_2
/*   */     //   260: invokevirtual coM1 : ()Ljava/lang/String;
/*   */     //   263: ldc 16807009
/*   */     //   265: swap
/*   */     //   266: invokestatic Go : (ILjava/lang/String;)Ljava/lang/String;
/*   */     //   269: invokevirtual Kq : (Ljava/lang/String;)V
/*   */     //   272: return
/*   */     //   273: aload #4
/*   */     //   275: aload_0
/*   */     //   276: aload_1
/*   */     //   277: iconst_0
/*   */     //   278: putfield ax0 : B
/*   */     //   281: getfield T : B
/*   */     //   284: sipush #-543
/*   */     //   287: invokevirtual yw0 : (BS)V
/*   */     //   290: return
/*   */     //   291: aload #4
/*   */     //   293: aload_0
/*   */     //   294: aload_1
/*   */     //   295: aload #7
/*   */     //   297: ldc 16807006
/*   */     //   299: invokestatic OH0 : (I)Ljava/lang/String;
/*   */     //   302: invokevirtual Kq : (Ljava/lang/String;)V
/*   */     //   305: bipush #127
/*   */     //   307: putfield ax0 : B
/*   */     //   310: getfield T : B
/*   */     //   313: sipush #-543
/*   */     //   316: invokevirtual yw0 : (BS)V
/*   */     //   319: return
/*   */     //   320: aload #7
/*   */     //   322: dup
/*   */     //   323: dup
/*   */     //   324: getfield AD : Lf/Gp0;
/*   */     //   327: aload_3
/*   */     //   328: getfield ta : Lf/Q90;
/*   */     //   331: getfield q10 : I
/*   */     //   334: invokevirtual fa : (I)Lf/hm0;
/*   */     //   337: dup
/*   */     //   338: astore_0
/*   */     //   339: invokevirtual fA : ()Ljava/lang/String;
/*   */     //   342: ldc 16807005
/*   */     //   344: swap
/*   */     //   345: invokestatic Go : (ILjava/lang/String;)Ljava/lang/String;
/*   */     //   348: invokevirtual cr : (Ljava/lang/String;)V
/*   */     //   351: getfield AD : Lf/Gp0;
/*   */     //   354: aload_0
/*   */     //   355: getfield FT : B
/*   */     //   358: invokestatic Sr0 : (B)B
/*   */     //   361: istore_1
/*   */     //   362: getfield cl : [[Lf/hm0;
/*   */     //   365: iload_1
/*   */     //   366: aaload
/*   */     //   367: invokestatic stream : ([Ljava/lang/Object;)Ljava/util/stream/Stream;
/*   */     //   370: <illegal opcode> test : ()Ljava/util/function/Predicate;
/*   */     //   375: invokeinterface filter : (Ljava/util/function/Predicate;)Ljava/util/stream/Stream;
/*   */     //   380: <illegal opcode> apply : ()Ljava/util/function/IntFunction;
/*   */     //   385: invokeinterface toArray : (Ljava/util/function/IntFunction;)[Ljava/lang/Object;
/*   */     //   390: checkcast [Lf/hm0;
/*   */     //   393: dup
/*   */     //   394: astore_1
/*   */     //   395: arraylength
/*   */     //   396: ifle -> 415
/*   */     //   399: aload #7
/*   */     //   401: new f/jr0
/*   */     //   404: dup
/*   */     //   405: astore_2
/*   */     //   406: aload_0
/*   */     //   407: aload_1
/*   */     //   408: invokespecial <init> : (Lf/hm0;[Lf/hm0;)V
/*   */     //   411: aload_2
/*   */     //   412: invokevirtual t80 : (Lf/wb;)V
/*   */     //   415: return
/*   */     //   416: aload #7
/*   */     //   418: aload_3
/*   */     //   419: invokevirtual Qe : ()Ljava/lang/String;
/*   */     //   422: ldc 16807004
/*   */     //   424: swap
/*   */     //   425: invokestatic Go : (ILjava/lang/String;)Ljava/lang/String;
/*   */     //   428: invokevirtual Kq : (Ljava/lang/String;)V
/*   */     //   431: aload_0
/*   */     //   432: aload #7
/*   */     //   434: getstatic f/F40.ef0 : Lf/F40;
/*   */     //   437: astore_2
/*   */     //   438: bipush #15
/*   */     //   440: istore_3
/*   */     //   441: getfield AD : Lf/Gp0;
/*   */     //   444: astore #5
/*   */     //   446: getfield XR : B
/*   */     //   449: ifne -> 460
/*   */     //   452: sipush #168
/*   */     //   455: istore #6
/*   */     //   457: goto -> 465
/*   */     //   460: sipush #170
/*   */     //   463: istore #6
/*   */     //   465: aload #4
/*   */     //   467: aload_0
/*   */     //   468: aload_1
/*   */     //   469: aload #7
/*   */     //   471: aload_2
/*   */     //   472: iload_3
/*   */     //   473: aload #5
/*   */     //   475: iload #6
/*   */     //   477: aload_0
/*   */     //   478: getfield T : B
/*   */     //   481: invokevirtual iD : (IB)I
/*   */     //   484: invokestatic Qf0 : (Lf/F40;II)Ljava/lang/String;
/*   */     //   487: invokevirtual Kq : (Ljava/lang/String;)V
/*   */     //   490: bipush #127
/*   */     //   492: putfield Fy0 : B
/*   */     //   495: getfield T : B
/*   */     //   498: sipush #519
/*   */     //   501: invokevirtual yw0 : (BS)V
/*   */     //   504: return
/*   */     //   505: aload #7
/*   */     //   507: aload_3
/*   */     //   508: invokevirtual Qe : ()Ljava/lang/String;
/*   */     //   511: ldc 16807001
/*   */     //   513: swap
/*   */     //   514: invokestatic Go : (ILjava/lang/String;)Ljava/lang/String;
/*   */     //   517: invokevirtual Kq : (Ljava/lang/String;)V
/*   */     //   520: return
/*   */     //   521: aload #7
/*   */     //   523: aload_3
/*   */     //   524: invokevirtual Qe : ()Ljava/lang/String;
/*   */     //   527: ldc 16807003
/*   */     //   529: swap
/*   */     //   530: invokestatic Go : (ILjava/lang/String;)Ljava/lang/String;
/*   */     //   533: invokevirtual Kq : (Ljava/lang/String;)V
/*   */     //   536: return
/*   */     //   537: aload #7
/*   */     //   539: aload_3
/*   */     //   540: invokevirtual Qe : ()Ljava/lang/String;
/*   */     //   543: ldc 16807002
/*   */     //   545: swap
/*   */     //   546: invokestatic Go : (ILjava/lang/String;)Ljava/lang/String;
/*   */     //   549: invokevirtual Kq : (Ljava/lang/String;)V
/*   */     //   552: return
/*   */     //   553: aload #7
/*   */     //   555: dup
/*   */     //   556: aload_3
/*   */     //   557: invokevirtual Qe : ()Ljava/lang/String;
/*   */     //   560: ldc 16807010
/*   */     //   562: swap
/*   */     //   563: invokestatic Go : (ILjava/lang/String;)Ljava/lang/String;
/*   */     //   566: invokevirtual Kq : (Ljava/lang/String;)V
/*   */     //   569: getfield YP : Ljava/util/LinkedList;
/*   */     //   572: new f/LV
/*   */     //   575: dup
/*   */     //   576: new f/MY
/*   */     //   579: dup
/*   */     //   580: aconst_null
/*   */     //   581: ldc 1.5
/*   */     //   583: aconst_null
/*   */     //   584: invokespecial <init> : (Lf/hm0;FLjava/lang/Runnable;)V
/*   */     //   587: invokespecial <init> : (Lf/wb;)V
/*   */     //   590: invokevirtual add : (Ljava/lang/Object;)Z
/*   */     //   593: pop
/*   */     //   594: return
/*   */     //   595: aload_0
/*   */     //   596: getfield ez0 : [Lf/hR;
/*   */     //   599: dup
/*   */     //   600: astore_0
/*   */     //   601: arraylength
/*   */     //   602: iconst_1
/*   */     //   603: if_icmple -> 648
/*   */     //   606: aload_0
/*   */     //   607: arraylength
/*   */     //   608: ldc_w 200458
/*   */     //   611: iadd
/*   */     //   612: iconst_2
/*   */     //   613: isub
/*   */     //   614: aload_0
/*   */     //   615: invokestatic stream : ([Ljava/lang/Object;)Ljava/util/stream/Stream;
/*   */     //   618: <illegal opcode> apply : ()Ljava/util/function/Function;
/*   */     //   623: invokeinterface map : (Ljava/util/function/Function;)Ljava/util/stream/Stream;
/*   */     //   628: <illegal opcode> apply : ()Ljava/util/function/IntFunction;
/*   */     //   633: invokeinterface toArray : (Ljava/util/function/IntFunction;)[Ljava/lang/Object;
/*   */     //   638: checkcast [Ljava/lang/String;
/*   */     //   641: invokestatic sB : (I[Ljava/lang/String;)Ljava/lang/String;
/*   */     //   644: astore_0
/*   */     //   645: goto -> 655
/*   */     //   648: aload_0
/*   */     //   649: iconst_0
/*   */     //   650: aaload
/*   */     //   651: invokevirtual toString : ()Ljava/lang/String;
/*   */     //   654: astore_0
/*   */     //   655: aload #7
/*   */     //   657: iconst_2
/*   */     //   658: anewarray java/lang/String
/*   */     //   661: dup
/*   */     //   662: dup
/*   */     //   663: astore_1
/*   */     //   664: aload_3
/*   */     //   665: invokevirtual Qe : ()Ljava/lang/String;
/*   */     //   668: iconst_0
/*   */     //   669: swap
/*   */     //   670: aastore
/*   */     //   671: iconst_1
/*   */     //   672: aload_0
/*   */     //   673: aastore
/*   */     //   674: ldc_w 16807007
/*   */     //   677: aload_1
/*   */     //   678: invokestatic sB : (I[Ljava/lang/String;)Ljava/lang/String;
/*   */     //   681: invokevirtual Kq : (Ljava/lang/String;)V
/*   */     //   684: return
/*   */     //   685: aload #7
/*   */     //   687: ldc_w 200497
/*   */     //   690: invokestatic OH0 : (I)Ljava/lang/String;
/*   */     //   693: invokevirtual cr : (Ljava/lang/String;)V
/*   */     //   696: getstatic f/km.MR : Lf/Gp0;
/*   */     //   699: aload_0
/*   */     //   700: getfield T : B
/*   */     //   703: iconst_1
/*   */     //   704: invokevirtual N0 : (BB)Lf/hm0;
/*   */     //   707: dup
/*   */     //   708: astore_0
/*   */     //   709: ifnull -> 821
/*   */     //   712: getstatic f/km.wI0 : Lf/Pw;
/*   */     //   715: getfield K7 : Lf/Wl;
/*   */     //   718: getfield LW : Lf/kf;
/*   */     //   721: new f/LV
/*   */     //   724: dup
/*   */     //   725: astore_1
/*   */     //   726: getstatic f/O5.AU : Lf/O5;
/*   */     //   729: aload_0
/*   */     //   730: bipush #113
/*   */     //   732: invokevirtual xa : (Lf/hm0;S)Lf/wb;
/*   */     //   735: iconst_0
/*   */     //   736: swap
/*   */     //   737: invokespecial <init> : (BLf/wb;)V
/*   */     //   740: getfield YP : Ljava/util/LinkedList;
/*   */     //   743: aload_1
/*   */     //   744: invokevirtual add : (Ljava/lang/Object;)Z
/*   */     //   747: pop
/*   */     //   748: getstatic f/km.wI0 : Lf/Pw;
/*   */     //   751: getfield K7 : Lf/Wl;
/*   */     //   754: getfield LW : Lf/kf;
/*   */     //   757: new f/LV
/*   */     //   760: dup
/*   */     //   761: astore_1
/*   */     //   762: getstatic f/O5.AU : Lf/O5;
/*   */     //   765: aload_0
/*   */     //   766: bipush #115
/*   */     //   768: invokevirtual xa : (Lf/hm0;S)Lf/wb;
/*   */     //   771: iconst_0
/*   */     //   772: swap
/*   */     //   773: invokespecial <init> : (BLf/wb;)V
/*   */     //   776: getfield YP : Ljava/util/LinkedList;
/*   */     //   779: aload_1
/*   */     //   780: invokevirtual add : (Ljava/lang/Object;)Z
/*   */     //   783: pop
/*   */     //   784: getstatic f/km.wI0 : Lf/Pw;
/*   */     //   787: getfield K7 : Lf/Wl;
/*   */     //   790: getfield LW : Lf/kf;
/*   */     //   793: new f/LV
/*   */     //   796: dup
/*   */     //   797: astore_1
/*   */     //   798: getstatic f/O5.AU : Lf/O5;
/*   */     //   801: aload_0
/*   */     //   802: sipush #219
/*   */     //   805: invokevirtual xa : (Lf/hm0;S)Lf/wb;
/*   */     //   808: iconst_0
/*   */     //   809: swap
/*   */     //   810: invokespecial <init> : (BLf/wb;)V
/*   */     //   813: getfield YP : Ljava/util/LinkedList;
/*   */     //   816: aload_1
/*   */     //   817: invokevirtual add : (Ljava/lang/Object;)Z
/*   */     //   820: pop
/*   */     //   821: return
/*   */     //   822: aload #7
/*   */     //   824: ldc_w 200496
/*   */     //   827: invokestatic OH0 : (I)Ljava/lang/String;
/*   */     //   830: invokevirtual cr : (Ljava/lang/String;)V
/*   */     //   833: getstatic f/km.wI0 : Lf/Pw;
/*   */     //   836: getfield K7 : Lf/Wl;
/*   */     //   839: getfield LW : Lf/kf;
/*   */     //   842: new f/OJ
/*   */     //   845: dup
/*   */     //   846: aload_0
/*   */     //   847: getstatic f/km.MR : Lf/Gp0;
/*   */     //   850: astore_0
/*   */     //   851: getfield T : B
/*   */     //   854: aload_0
/*   */     //   855: getfield cl : [[Lf/hm0;
/*   */     //   858: swap
/*   */     //   859: aaload
/*   */     //   860: invokestatic stream : ([Ljava/lang/Object;)Ljava/util/stream/Stream;
/*   */     //   863: <illegal opcode> test : ()Ljava/util/function/Predicate;
/*   */     //   868: invokeinterface filter : (Ljava/util/function/Predicate;)Ljava/util/stream/Stream;
/*   */     //   873: <illegal opcode> apply : ()Ljava/util/function/IntFunction;
/*   */     //   878: invokeinterface toArray : (Ljava/util/function/IntFunction;)[Ljava/lang/Object;
/*   */     //   883: checkcast [Lf/hm0;
/*   */     //   886: invokespecial <init> : ([Lf/hm0;)V
/*   */     //   889: invokevirtual t80 : (Lf/wb;)V
/*   */     //   892: return
/*   */     //   893: aload_0
/*   */     //   894: aload #7
/*   */     //   896: ldc_w 200495
/*   */     //   899: invokestatic OH0 : (I)Ljava/lang/String;
/*   */     //   902: invokevirtual Kq : (Ljava/lang/String;)V
/*   */     //   905: getstatic f/km.MR : Lf/Gp0;
/*   */     //   908: astore_0
/*   */     //   909: getfield T : B
/*   */     //   912: aload_0
/*   */     //   913: getfield cl : [[Lf/hm0;
/*   */     //   916: swap
/*   */     //   917: aaload
/*   */     //   918: dup
/*   */     //   919: astore_0
/*   */     //   920: arraylength
/*   */     //   921: istore_1
/*   */     //   922: iconst_0
/*   */     //   923: istore_2
/*   */     //   924: iload_2
/*   */     //   925: iload_1
/*   */     //   926: if_icmpge -> 971
/*   */     //   929: aload_0
/*   */     //   930: iload_2
/*   */     //   931: aaload
/*   */     //   932: dup
/*   */     //   933: astore_3
/*   */     //   934: ifnull -> 965
/*   */     //   937: aload_3
/*   */     //   938: getfield K0 : Lf/jd0;
/*   */     //   941: invokevirtual AL : ()Z
/*   */     //   944: ifne -> 965
/*   */     //   947: aload_3
/*   */     //   948: dup
/*   */     //   949: dup2
/*   */     //   950: iconst_1
/*   */     //   951: putfield A0 : Z
/*   */     //   954: getfield eq0 : Lf/uT;
/*   */     //   957: pop
/*   */     //   958: invokevirtual yL0 : ()V
/*   */     //   961: invokevirtual Af : ()Lf/uT;
/*   */     //   964: pop
/*   */     //   965: iinc #2, 1
/*   */     //   968: goto -> 924
/*   */     //   971: return
/*   */     //   972: aload #7
/*   */     //   974: ldc_w 200494
/*   */     //   977: invokestatic OH0 : (I)Ljava/lang/String;
/*   */     //   980: invokevirtual Kq : (Ljava/lang/String;)V
/*   */     //   983: return
/*   */     //   984: aload #7
/*   */     //   986: dup
/*   */     //   987: dup2
/*   */     //   988: ldc_w 200492
/*   */     //   991: invokestatic OH0 : (I)Ljava/lang/String;
/*   */     //   994: invokevirtual Kq : (Ljava/lang/String;)V
/*   */     //   997: getfield YP : Ljava/util/LinkedList;
/*   */     //   1000: new f/LV
/*   */     //   1003: dup
/*   */     //   1004: new f/MY
/*   */     //   1007: dup
/*   */     //   1008: aconst_null
/*   */     //   1009: ldc 1.5
/*   */     //   1011: aconst_null
/*   */     //   1012: invokespecial <init> : (Lf/hm0;FLjava/lang/Runnable;)V
/*   */     //   1015: invokespecial <init> : (Lf/wb;)V
/*   */     //   1018: invokevirtual add : (Ljava/lang/Object;)Z
/*   */     //   1021: pop
/*   */     //   1022: ldc_w 200493
/*   */     //   1025: invokestatic OH0 : (I)Ljava/lang/String;
/*   */     //   1028: invokevirtual Kq : (Ljava/lang/String;)V
/*   */     //   1031: getfield YP : Ljava/util/LinkedList;
/*   */     //   1034: new f/LV
/*   */     //   1037: dup
/*   */     //   1038: new f/MY
/*   */     //   1041: dup
/*   */     //   1042: aconst_null
/*   */     //   1043: ldc 1.5
/*   */     //   1045: aconst_null
/*   */     //   1046: invokespecial <init> : (Lf/hm0;FLjava/lang/Runnable;)V
/*   */     //   1049: invokespecial <init> : (Lf/wb;)V
/*   */     //   1052: invokevirtual add : (Ljava/lang/Object;)Z
/*   */     //   1055: pop
/*   */     //   1056: return
/*   */     // Line number table:
/*   */     //   Java source line number -> byte code offset
/*   */     //   #1	-> 12
/*   */     //   #2	-> 70
/*   */     //   #3	-> 84
/*   */     //   #4	-> 88
/*   */     //   #5	-> 114
/*   */     //   #6	-> 119
/*   */     //   #7	-> 278
/*   */     //   #8	-> 281
/*   */     //   #9	-> 307
/*   */     //   #10	-> 310
/*   */     //   #11	-> 324
/*   */     //   #12	-> 328
/*   */     //   #13	-> 331
/*   */     //   #14	-> 334
/*   */     //   #15	-> 351
/*   */     //   #16	-> 355
/*   */     //   #17	-> 358
/*   */     //   #18	-> 362
/*   */     //   #19	-> 366
/*   */     //   #20	-> 367
/*   */     //   #21	-> 441
/*   */     //   #22	-> 446
/*   */     //   #23	-> 492
/*   */     //   #24	-> 495
/*   */     //   #25	-> 569
/*   */     //   #26	-> 596
/*   */     //   #27	-> 715
/*   */     //   #28	-> 718
/*   */     //   #29	-> 721
/*   */     //   #30	-> 726
/*   */     //   #31	-> 732
/*   */     //   #32	-> 740
/*   */     //   #33	-> 744
/*   */     //   #34	-> 748
/*   */     //   #35	-> 751
/*   */     //   #36	-> 754
/*   */     //   #37	-> 757
/*   */     //   #38	-> 762
/*   */     //   #39	-> 768
/*   */     //   #40	-> 776
/*   */     //   #41	-> 780
/*   */     //   #42	-> 784
/*   */     //   #43	-> 787
/*   */     //   #44	-> 790
/*   */     //   #45	-> 793
/*   */     //   #46	-> 798
/*   */     //   #47	-> 805
/*   */     //   #48	-> 813
/*   */     //   #49	-> 817
/*   */     //   #50	-> 827
/*   */     //   #51	-> 836
/*   */     //   #52	-> 839
/*   */     //   #53	-> 842
/*   */     //   #54	-> 855
/*   */     //   #55	-> 859
/*   */     //   #56	-> 860
/*   */     //   #57	-> 913
/*   */     //   #58	-> 917
/*   */     //   #59	-> 920
/*   */     //   #60	-> 938
/*   */     //   #61	-> 951
/*   */     //   #62	-> 958
/*   */     //   #63	-> 997
/*   */     //   #64	-> 1025
/*   */     //   #65	-> 1031
/*   */   }
/*   */   public sk(byte paramByte1, byte paramByte2, int paramInt, hR[] paramArrayOfhR) {
/* 8 */     if (paramByte1 == 33) { this.T = paramByte2; this.XR = paramByte1; this.cl = paramInt; this.ez0 = paramArrayOfhR; return; }  throw new IllegalArgumentException(XD0.SD0("Illegal constructor for info ", paramByte1));
/*   */   }
/*   */   
/*   */   public final byte YG0() {
/*   */     return -17;
/*   */   }
/*   */   
/*   */   public final boolean Lt() {
/*   */     return !(this.XR != 5);
/*   */   } }


/* Location:              /Users/vnnsnnt/Documents/Codespace/JavaWorkspace/RedTrainer/src/main/java/org/trainer/client/PokeMMO.jar!/f/sk.class
 * Java compiler version: 8 (52.0)
 * JD-Core Version:       1.1.3
 */