/* 1 */ package f;public abstract class so0 extends JG0 { public Ip ms0; public final Un ge; public final Un Zc; public final ge0 Lj0; public final dQ HK; private void zf0(UX paramUX) { this.UF
/* 2 */       .PQ(paramUX.Ii); } public final W1 DW; public final Ip Yp0; public final Un[] qf; public Dn0 UF; public Un vq; public so0(Vp0 paramVp0, short paramShort) { // Byte code:
/*   */     //   0: aload_0
/*   */     //   1: dup
/*   */     //   2: dup2
/*   */     //   3: invokespecial <init> : ()V
/*   */     //   6: new f/Dn0
/*   */     //   9: dup
/*   */     //   10: aload_0
/*   */     //   11: getstatic f/km.a3 : Lf/vh0;
/*   */     //   14: invokevirtual wQ : ()Lf/Jo;
/*   */     //   17: aload_1
/*   */     //   18: iload_2
/*   */     //   19: invokespecial <init> : (Lf/so0;Lf/Jo;Lf/Vp0;S)V
/*   */     //   22: putfield UF : Lf/Dn0;
/*   */     //   25: new f/Un
/*   */     //   28: dup
/*   */     //   29: dup
/*   */     //   30: astore_3
/*   */     //   31: bipush #56
/*   */     //   33: invokestatic OH0 : (I)Ljava/lang/String;
/*   */     //   36: invokespecial <init> : (Ljava/lang/String;)V
/*   */     //   39: putfield ge : Lf/Un;
/*   */     //   42: new f/Un
/*   */     //   45: dup
/*   */     //   46: dup
/*   */     //   47: astore #4
/*   */     //   49: bipush #53
/*   */     //   51: invokestatic OH0 : (I)Ljava/lang/String;
/*   */     //   54: invokespecial <init> : (Ljava/lang/String;)V
/*   */     //   57: putfield Zc : Lf/Un;
/*   */     //   60: invokestatic XU : ()Z
/*   */     //   63: ifeq -> 94
/*   */     //   66: aload_0
/*   */     //   67: getfield UF : Lf/Dn0;
/*   */     //   70: astore #5
/*   */     //   72: invokestatic XU : ()Z
/*   */     //   75: ifeq -> 84
/*   */     //   78: iconst_4
/*   */     //   79: istore #6
/*   */     //   81: goto -> 87
/*   */     //   84: iconst_3
/*   */     //   85: istore #6
/*   */     //   87: aload #5
/*   */     //   89: iload #6
/*   */     //   91: invokevirtual gT : (I)V
/*   */     //   94: aload_1
/*   */     //   95: new f/ge0
/*   */     //   98: dup
/*   */     //   99: astore #5
/*   */     //   101: aload_0
/*   */     //   102: dup
/*   */     //   103: aload #5
/*   */     //   105: dup
/*   */     //   106: invokespecial <init> : ()V
/*   */     //   109: putfield Lj0 : Lf/ge0;
/*   */     //   112: <illegal opcode> run : (Lf/so0;)Ljava/lang/Runnable;
/*   */     //   117: invokevirtual tW : (Ljava/lang/Runnable;)V
/*   */     //   120: getstatic f/Vp0.MP : Lf/Vp0;
/*   */     //   123: if_acmpne -> 132
/*   */     //   126: iconst_1
/*   */     //   127: istore #6
/*   */     //   129: goto -> 135
/*   */     //   132: iconst_0
/*   */     //   133: istore #6
/*   */     //   135: aload_1
/*   */     //   136: aload #5
/*   */     //   138: iload #6
/*   */     //   140: invokevirtual zs : (Z)V
/*   */     //   143: getstatic f/Vp0.bG : Lf/Vp0;
/*   */     //   146: dup
/*   */     //   147: astore #6
/*   */     //   149: if_acmpeq -> 158
/*   */     //   152: iconst_1
/*   */     //   153: istore #7
/*   */     //   155: goto -> 161
/*   */     //   158: iconst_0
/*   */     //   159: istore #7
/*   */     //   161: aload_1
/*   */     //   162: aload #6
/*   */     //   164: aload_0
/*   */     //   165: dup
/*   */     //   166: aload #5
/*   */     //   168: iload #7
/*   */     //   170: invokevirtual wI0 : (Z)V
/*   */     //   173: getfield UF : Lf/Dn0;
/*   */     //   176: aload #5
/*   */     //   178: invokevirtual EE : ()Z
/*   */     //   181: invokevirtual Ul : (Z)V
/*   */     //   184: new f/dQ
/*   */     //   187: dup
/*   */     //   188: dup
/*   */     //   189: astore #6
/*   */     //   191: sipush #3007
/*   */     //   194: invokestatic OH0 : (I)Ljava/lang/String;
/*   */     //   197: invokespecial <init> : (Ljava/lang/String;)V
/*   */     //   200: putfield HK : Lf/dQ;
/*   */     //   203: if_acmpeq -> 212
/*   */     //   206: iconst_1
/*   */     //   207: istore #7
/*   */     //   209: goto -> 215
/*   */     //   212: iconst_0
/*   */     //   213: istore #7
/*   */     //   215: aload_1
/*   */     //   216: aload #5
/*   */     //   218: dup
/*   */     //   219: aload_3
/*   */     //   220: dup
/*   */     //   221: aload #4
/*   */     //   223: dup
/*   */     //   224: aload #6
/*   */     //   226: iload #7
/*   */     //   228: invokevirtual wI0 : (Z)V
/*   */     //   231: bipush #120
/*   */     //   233: bipush #30
/*   */     //   235: invokevirtual uh0 : (II)V
/*   */     //   238: bipush #120
/*   */     //   240: bipush #30
/*   */     //   242: invokevirtual Tm : (II)Z
/*   */     //   245: pop
/*   */     //   246: bipush #120
/*   */     //   248: bipush #30
/*   */     //   250: invokevirtual uh0 : (II)V
/*   */     //   253: bipush #120
/*   */     //   255: bipush #30
/*   */     //   257: invokevirtual Tm : (II)Z
/*   */     //   260: pop
/*   */     //   261: bipush #30
/*   */     //   263: bipush #30
/*   */     //   265: invokevirtual uh0 : (II)V
/*   */     //   268: bipush #30
/*   */     //   270: bipush #30
/*   */     //   272: invokevirtual Tm : (II)Z
/*   */     //   275: pop
/*   */     //   276: getstatic f/Vp0.c6 : Lf/Vp0;
/*   */     //   279: if_acmpeq -> 392
/*   */     //   282: new f/OZ
/*   */     //   285: dup
/*   */     //   286: astore_3
/*   */     //   287: bipush #7
/*   */     //   289: anewarray java/lang/String
/*   */     //   292: dup
/*   */     //   293: dup2
/*   */     //   294: dup2
/*   */     //   295: dup2
/*   */     //   296: sipush #2987
/*   */     //   299: invokestatic OH0 : (I)Ljava/lang/String;
/*   */     //   302: iconst_0
/*   */     //   303: swap
/*   */     //   304: aastore
/*   */     //   305: sipush #2986
/*   */     //   308: invokestatic OH0 : (I)Ljava/lang/String;
/*   */     //   311: iconst_1
/*   */     //   312: swap
/*   */     //   313: aastore
/*   */     //   314: sipush #2985
/*   */     //   317: invokestatic OH0 : (I)Ljava/lang/String;
/*   */     //   320: iconst_2
/*   */     //   321: swap
/*   */     //   322: aastore
/*   */     //   323: sipush #2984
/*   */     //   326: invokestatic OH0 : (I)Ljava/lang/String;
/*   */     //   329: iconst_3
/*   */     //   330: swap
/*   */     //   331: aastore
/*   */     //   332: sipush #2983
/*   */     //   335: invokestatic OH0 : (I)Ljava/lang/String;
/*   */     //   338: iconst_4
/*   */     //   339: swap
/*   */     //   340: aastore
/*   */     //   341: sipush #2998
/*   */     //   344: invokestatic OH0 : (I)Ljava/lang/String;
/*   */     //   347: iconst_5
/*   */     //   348: swap
/*   */     //   349: aastore
/*   */     //   350: sipush #2988
/*   */     //   353: invokestatic OH0 : (I)Ljava/lang/String;
/*   */     //   356: bipush #6
/*   */     //   358: swap
/*   */     //   359: aastore
/*   */     //   360: invokespecial <init> : ([Ljava/lang/Object;)V
/*   */     //   363: new f/W1
/*   */     //   366: dup
/*   */     //   367: astore #4
/*   */     //   369: aload_0
/*   */     //   370: dup
/*   */     //   371: aload #4
/*   */     //   373: dup
/*   */     //   374: aload_3
/*   */     //   375: invokespecial <init> : (Lf/cQ;)V
/*   */     //   378: putfield DW : Lf/W1;
/*   */     //   381: <illegal opcode> run : (Lf/so0;)Ljava/lang/Runnable;
/*   */     //   386: invokevirtual D30 : (Ljava/lang/Runnable;)V
/*   */     //   389: goto -> 439
/*   */     //   392: aload_0
/*   */     //   393: new f/OZ
/*   */     //   396: dup
/*   */     //   397: astore_3
/*   */     //   398: iconst_1
/*   */     //   399: anewarray java/lang/String
/*   */     //   402: dup
/*   */     //   403: sipush #2985
/*   */     //   406: invokestatic OH0 : (I)Ljava/lang/String;
/*   */     //   409: iconst_0
/*   */     //   410: swap
/*   */     //   411: aastore
/*   */     //   412: invokespecial <init> : ([Ljava/lang/Object;)V
/*   */     //   415: new f/W1
/*   */     //   418: dup
/*   */     //   419: aload_0
/*   */     //   420: swap
/*   */     //   421: dup
/*   */     //   422: aload_3
/*   */     //   423: invokespecial <init> : (Lf/cQ;)V
/*   */     //   426: putfield DW : Lf/W1;
/*   */     //   429: iconst_0
/*   */     //   430: invokevirtual wI0 : (Z)V
/*   */     //   433: getfield UF : Lf/Dn0;
/*   */     //   436: invokevirtual NF : ()V
/*   */     //   439: aload_1
/*   */     //   440: aload_0
/*   */     //   441: getfield DW : Lf/W1;
/*   */     //   444: iconst_0
/*   */     //   445: invokevirtual Z30 : (I)V
/*   */     //   448: ifnonnull -> 456
/*   */     //   451: aconst_null
/*   */     //   452: astore_3
/*   */     //   453: goto -> 462
/*   */     //   456: aload_1
/*   */     //   457: iload_2
/*   */     //   458: invokevirtual fM0 : (S)Lf/wc;
/*   */     //   461: astore_3
/*   */     //   462: aload_3
/*   */     //   463: ifnull -> 507
/*   */     //   466: aload_3
/*   */     //   467: sipush #16384
/*   */     //   470: invokevirtual l9 : (I)Z
/*   */     //   473: ifeq -> 507
/*   */     //   476: new f/Un
/*   */     //   479: dup
/*   */     //   480: astore_3
/*   */     //   481: aload_0
/*   */     //   482: aload_1
/*   */     //   483: aload_0
/*   */     //   484: aload_3
/*   */     //   485: dup
/*   */     //   486: sipush #2989
/*   */     //   489: invokestatic OH0 : (I)Ljava/lang/String;
/*   */     //   492: invokespecial <init> : (Ljava/lang/String;)V
/*   */     //   495: putfield vq : Lf/Un;
/*   */     //   498: iload_2
/*   */     //   499: <illegal opcode> run : (Lf/so0;Lf/Vp0;S)Ljava/lang/Runnable;
/*   */     //   504: invokevirtual tW : (Ljava/lang/Runnable;)V
/*   */     //   507: new f/Ip
/*   */     //   510: dup
/*   */     //   511: dup2
/*   */     //   512: dup2
/*   */     //   513: dup2
/*   */     //   514: aload_0
/*   */     //   515: swap
/*   */     //   516: dup
/*   */     //   517: invokespecial <init> : ()V
/*   */     //   520: putfield Yp0 : Lf/Ip;
/*   */     //   523: ldc 'preview-color-dialog'
/*   */     //   525: invokevirtual Xu : (Ljava/lang/String;)V
/*   */     //   528: invokevirtual d7 : ()Lf/cr0;
/*   */     //   531: invokevirtual rK0 : (Lf/U90;)V
/*   */     //   534: invokevirtual mE0 : ()Lf/g0;
/*   */     //   537: invokevirtual WN : (Lf/U90;)V
/*   */     //   540: invokevirtual mE0 : ()Lf/g0;
/*   */     //   543: astore_3
/*   */     //   544: invokevirtual d7 : ()Lf/cr0;
/*   */     //   547: astore #4
/*   */     //   549: getstatic f/UX.jj : [Lf/UX;
/*   */     //   552: dup
/*   */     //   553: astore #5
/*   */     //   555: aload_0
/*   */     //   556: aload #5
/*   */     //   558: arraylength
/*   */     //   559: anewarray f/Un
/*   */     //   562: putfield qf : [Lf/Un;
/*   */     //   565: iconst_0
/*   */     //   566: istore #6
/*   */     //   568: arraylength
/*   */     //   569: istore #7
/*   */     //   571: iconst_0
/*   */     //   572: istore #8
/*   */     //   574: iload #8
/*   */     //   576: iload #7
/*   */     //   578: if_icmpge -> 760
/*   */     //   581: aload #4
/*   */     //   583: aload_0
/*   */     //   584: aload_3
/*   */     //   585: aload_0
/*   */     //   586: dup
/*   */     //   587: dup
/*   */     //   588: dup2
/*   */     //   589: aload #5
/*   */     //   591: iload #8
/*   */     //   593: aaload
/*   */     //   594: astore #9
/*   */     //   596: getfield qf : [Lf/Un;
/*   */     //   599: iload #6
/*   */     //   601: new f/Fy0
/*   */     //   604: dup
/*   */     //   605: astore #10
/*   */     //   607: invokespecial <init> : ()V
/*   */     //   610: aload #10
/*   */     //   612: aastore
/*   */     //   613: getfield qf : [Lf/Un;
/*   */     //   616: iload #6
/*   */     //   618: aaload
/*   */     //   619: ldc 'color-button'
/*   */     //   621: invokevirtual Xu : (Ljava/lang/String;)V
/*   */     //   624: getfield qf : [Lf/Un;
/*   */     //   627: iload #6
/*   */     //   629: aaload
/*   */     //   630: dup
/*   */     //   631: astore #10
/*   */     //   633: new f/I
/*   */     //   636: dup
/*   */     //   637: aload #10
/*   */     //   639: new f/pRn
/*   */     //   642: dup
/*   */     //   643: astore #10
/*   */     //   645: aload #9
/*   */     //   647: invokevirtual Lv : ()Lf/ao;
/*   */     //   650: invokevirtual Jt : ()I
/*   */     //   653: invokespecial <init> : (I)V
/*   */     //   656: aload #10
/*   */     //   658: invokespecial <init> : (Lf/JG0;Lf/pRn;)V
/*   */     //   661: invokevirtual Vo0 : (Lf/I;)V
/*   */     //   664: getfield qf : [Lf/Un;
/*   */     //   667: iload #6
/*   */     //   669: aaload
/*   */     //   670: aload_0
/*   */     //   671: aload #9
/*   */     //   673: <illegal opcode> run : (Lf/so0;Lf/UX;)Ljava/lang/Runnable;
/*   */     //   678: invokevirtual tW : (Ljava/lang/Runnable;)V
/*   */     //   681: getfield qf : [Lf/Un;
/*   */     //   684: iload #6
/*   */     //   686: aaload
/*   */     //   687: invokevirtual Ya : (Lf/JG0;)Lf/U90;
/*   */     //   690: pop
/*   */     //   691: getfield qf : [Lf/Un;
/*   */     //   694: iload #6
/*   */     //   696: aaload
/*   */     //   697: invokevirtual Ya : (Lf/JG0;)Lf/U90;
/*   */     //   700: pop
/*   */     //   701: iload #6
/*   */     //   703: iconst_1
/*   */     //   704: iadd
/*   */     //   705: dup
/*   */     //   706: istore #6
/*   */     //   708: iconst_3
/*   */     //   709: irem
/*   */     //   710: ifne -> 754
/*   */     //   713: aload_0
/*   */     //   714: dup
/*   */     //   715: dup2
/*   */     //   716: getfield Yp0 : Lf/Ip;
/*   */     //   719: invokevirtual iJ0 : ()Lf/U90;
/*   */     //   722: aload_3
/*   */     //   723: invokevirtual ee0 : (Lf/U90;)Lf/U90;
/*   */     //   726: pop
/*   */     //   727: getfield Yp0 : Lf/Ip;
/*   */     //   730: invokevirtual xh : ()Lf/U90;
/*   */     //   733: aload #4
/*   */     //   735: invokevirtual ee0 : (Lf/U90;)Lf/U90;
/*   */     //   738: pop
/*   */     //   739: getfield Yp0 : Lf/Ip;
/*   */     //   742: invokevirtual mE0 : ()Lf/g0;
/*   */     //   745: astore_3
/*   */     //   746: getfield Yp0 : Lf/Ip;
/*   */     //   749: invokevirtual d7 : ()Lf/cr0;
/*   */     //   752: astore #4
/*   */     //   754: iinc #8, 1
/*   */     //   757: goto -> 574
/*   */     //   760: aload_1
/*   */     //   761: aload_0
/*   */     //   762: dup
/*   */     //   763: dup
/*   */     //   764: getfield Yp0 : Lf/Ip;
/*   */     //   767: invokevirtual iJ0 : ()Lf/U90;
/*   */     //   770: aload_3
/*   */     //   771: invokevirtual ee0 : (Lf/U90;)Lf/U90;
/*   */     //   774: pop
/*   */     //   775: getfield Yp0 : Lf/Ip;
/*   */     //   778: invokevirtual xh : ()Lf/U90;
/*   */     //   781: aload #4
/*   */     //   783: invokevirtual ee0 : (Lf/U90;)Lf/U90;
/*   */     //   786: pop
/*   */     //   787: getfield UF : Lf/Dn0;
/*   */     //   790: getstatic f/pRn.TRANSPARENT_WHITE : Lf/pRn;
/*   */     //   793: pop
/*   */     //   794: invokevirtual getClass : ()Ljava/lang/Class;
/*   */     //   797: pop
/*   */     //   798: ifnull -> 827
/*   */     //   801: aload_1
/*   */     //   802: iload_2
/*   */     //   803: invokevirtual Ko : (S)Z
/*   */     //   806: ifne -> 812
/*   */     //   809: goto -> 827
/*   */     //   812: aload_0
/*   */     //   813: getfield qf : [Lf/Un;
/*   */     //   816: iconst_0
/*   */     //   817: aaload
/*   */     //   818: invokevirtual Xe0 : ()Lf/protected;
/*   */     //   821: invokevirtual s1 : ()V
/*   */     //   824: goto -> 835
/*   */     //   827: aload_0
/*   */     //   828: getfield Yp0 : Lf/Ip;
/*   */     //   831: iconst_0
/*   */     //   832: invokevirtual wI0 : (Z)V
/* 2 */     //   835: return } private void Ee(Vp0 paramVp0, short paramShort) { this.UF.Mk0[paramVp0.gw0]
/*   */       
/* 4 */       .f3(paramShort, 1.0F); }
/*   */ 
/*   */   
/*   */   private void YJ0() {
/*   */     // Byte code:
/*   */     //   0: aload_0
/*   */     //   1: getfield DW : Lf/W1;
/*   */     //   4: getfield Wa0 : Lf/A60;
/*   */     //   7: getfield go : I
/*   */     //   10: tableswitch default -> 52, 0 -> 203, 1 -> 177, 2 -> 151, 3 -> 125, 4 -> 99, 5 -> 73, 6 -> 55
/*   */     //   52: goto -> 238
/*   */     //   55: aload_0
/*   */     //   56: getfield UF : Lf/Dn0;
/*   */     //   59: dup
/*   */     //   60: getstatic f/lPT9.fh0 : Lf/lPT9;
/*   */     //   63: putfield Ng0 : Lf/lPT9;
/*   */     //   66: iconst_2
/*   */     //   67: putfield Dd : I
/*   */     //   70: goto -> 238
/*   */     //   73: aload_0
/*   */     //   74: getfield UF : Lf/Dn0;
/*   */     //   77: dup
/*   */     //   78: astore_1
/*   */     //   79: getstatic f/lPT9.jR : Lf/lPT9;
/*   */     //   82: putfield Ng0 : Lf/lPT9;
/*   */     //   85: invokestatic XU : ()Z
/*   */     //   88: ifeq -> 94
/*   */     //   91: goto -> 231
/*   */     //   94: iconst_2
/*   */     //   95: istore_2
/*   */     //   96: goto -> 233
/*   */     //   99: aload_0
/*   */     //   100: getfield UF : Lf/Dn0;
/*   */     //   103: dup
/*   */     //   104: dup
/*   */     //   105: astore_1
/*   */     //   106: iconst_4
/*   */     //   107: putfield ah : I
/*   */     //   110: getstatic f/lPT9.U4 : Lf/lPT9;
/*   */     //   113: putfield Ng0 : Lf/lPT9;
/*   */     //   116: invokestatic XU : ()Z
/*   */     //   119: ifeq -> 231
/*   */     //   122: goto -> 226
/*   */     //   125: aload_0
/*   */     //   126: getfield UF : Lf/Dn0;
/*   */     //   129: dup
/*   */     //   130: dup
/*   */     //   131: astore_1
/*   */     //   132: iconst_3
/*   */     //   133: putfield ah : I
/*   */     //   136: getstatic f/lPT9.U4 : Lf/lPT9;
/*   */     //   139: putfield Ng0 : Lf/lPT9;
/*   */     //   142: invokestatic XU : ()Z
/*   */     //   145: ifeq -> 231
/*   */     //   148: goto -> 226
/*   */     //   151: aload_0
/*   */     //   152: getfield UF : Lf/Dn0;
/*   */     //   155: dup
/*   */     //   156: dup
/*   */     //   157: astore_1
/*   */     //   158: iconst_2
/*   */     //   159: putfield ah : I
/*   */     //   162: getstatic f/lPT9.U4 : Lf/lPT9;
/*   */     //   165: putfield Ng0 : Lf/lPT9;
/*   */     //   168: invokestatic XU : ()Z
/*   */     //   171: ifeq -> 231
/*   */     //   174: goto -> 226
/*   */     //   177: aload_0
/*   */     //   178: getfield UF : Lf/Dn0;
/*   */     //   181: dup
/*   */     //   182: dup
/*   */     //   183: astore_1
/*   */     //   184: iconst_1
/*   */     //   185: putfield ah : I
/*   */     //   188: getstatic f/lPT9.U4 : Lf/lPT9;
/*   */     //   191: putfield Ng0 : Lf/lPT9;
/*   */     //   194: invokestatic XU : ()Z
/*   */     //   197: ifeq -> 231
/*   */     //   200: goto -> 226
/*   */     //   203: aload_0
/*   */     //   204: getfield UF : Lf/Dn0;
/*   */     //   207: dup
/*   */     //   208: dup
/*   */     //   209: astore_1
/*   */     //   210: iconst_0
/*   */     //   211: putfield ah : I
/*   */     //   214: getstatic f/lPT9.U4 : Lf/lPT9;
/*   */     //   217: putfield Ng0 : Lf/lPT9;
/*   */     //   220: invokestatic XU : ()Z
/*   */     //   223: ifeq -> 231
/*   */     //   226: iconst_4
/*   */     //   227: istore_2
/*   */     //   228: goto -> 233
/*   */     //   231: iconst_3
/*   */     //   232: istore_2
/*   */     //   233: aload_1
/*   */     //   234: iload_2
/*   */     //   235: putfield Dd : I
/*   */     //   238: aload_0
/*   */     //   239: getfield vq : Lf/Un;
/*   */     //   242: dup
/*   */     //   243: astore_1
/*   */     //   244: ifnull -> 272
/*   */     //   247: aload_0
/*   */     //   248: getfield DW : Lf/W1;
/*   */     //   251: getfield Wa0 : Lf/A60;
/*   */     //   254: getfield go : I
/*   */     //   257: ifne -> 265
/*   */     //   260: iconst_1
/*   */     //   261: istore_0
/*   */     //   262: goto -> 267
/*   */     //   265: iconst_0
/*   */     //   266: istore_0
/*   */     //   267: aload_1
/*   */     //   268: iload_0
/*   */     //   269: invokevirtual wI0 : (Z)V
/*   */     //   272: return
/*   */     // Line number table:
/*   */     //   Java source line number -> byte code offset
/*   */     //   #1	-> 4
/*   */     //   #2	-> 7
/*   */     //   #3	-> 56
/*   */     //   #4	-> 63
/*   */     //   #5	-> 67
/*   */     //   #6	-> 74
/*   */     //   #7	-> 82
/*   */     //   #8	-> 85
/*   */     //   #9	-> 107
/*   */     //   #10	-> 110
/*   */     //   #11	-> 113
/*   */     //   #12	-> 116
/*   */     //   #13	-> 133
/*   */     //   #14	-> 136
/*   */     //   #15	-> 139
/*   */     //   #16	-> 142
/*   */     //   #17	-> 159
/*   */     //   #18	-> 162
/*   */     //   #19	-> 165
/*   */     //   #20	-> 168
/*   */     //   #21	-> 185
/*   */     //   #22	-> 188
/*   */     //   #23	-> 191
/*   */     //   #24	-> 194
/*   */     //   #25	-> 211
/*   */     //   #26	-> 214
/*   */     //   #27	-> 217
/*   */     //   #28	-> 220
/*   */     //   #29	-> 235
/*   */     //   #30	-> 239
/*   */     //   #31	-> 251
/*   */     //   #32	-> 254
/*   */     //   #33	-> 269
/*   */   }
/*   */   
/*   */   private void mX() {
/*   */     this.UF.LI0 = this.UF.LI0 ^ true;
/*   */   }
/*   */   
/*   */   public void R60(throws paramthrows) {
/*   */     // Byte code:
/*   */     //   0: invokestatic XU : ()Z
/*   */     //   3: ifeq -> 46
/*   */     //   6: aload_0
/*   */     //   7: getfield UF : Lf/Dn0;
/*   */     //   10: dup
/*   */     //   11: astore_2
/*   */     //   12: getfield Ng0 : Lf/lPT9;
/*   */     //   15: getstatic f/lPT9.U4 : Lf/lPT9;
/*   */     //   18: if_acmpne -> 27
/*   */     //   21: bipush #-40
/*   */     //   23: istore_3
/*   */     //   24: goto -> 30
/*   */     //   27: bipush #40
/*   */     //   29: istore_3
/*   */     //   30: aload_0
/*   */     //   31: getfield Yp0 : Lf/Ip;
/*   */     //   34: dup
/*   */     //   35: astore #4
/*   */     //   37: getfield dP : Z
/*   */     //   40: ifeq -> 90
/*   */     //   43: goto -> 82
/*   */     //   46: aload_0
/*   */     //   47: getfield UF : Lf/Dn0;
/*   */     //   50: dup
/*   */     //   51: astore_2
/*   */     //   52: getfield Ng0 : Lf/lPT9;
/*   */     //   55: getstatic f/lPT9.U4 : Lf/lPT9;
/*   */     //   58: if_acmpne -> 66
/*   */     //   61: iconst_0
/*   */     //   62: istore_3
/*   */     //   63: goto -> 69
/*   */     //   66: bipush #80
/*   */     //   68: istore_3
/*   */     //   69: aload_0
/*   */     //   70: getfield Yp0 : Lf/Ip;
/*   */     //   73: dup
/*   */     //   74: astore #4
/*   */     //   76: getfield dP : Z
/*   */     //   79: ifeq -> 90
/*   */     //   82: aload #4
/*   */     //   84: getfield HC : I
/*   */     //   87: goto -> 91
/*   */     //   90: iconst_0
/*   */     //   91: bipush #10
/*   */     //   93: iadd
/*   */     //   94: istore #4
/*   */     //   96: aload_0
/*   */     //   97: aload_2
/*   */     //   98: iload #4
/*   */     //   100: aload_2
/*   */     //   101: iload_3
/*   */     //   102: putfield Uq : I
/*   */     //   105: putfield Z1 : I
/*   */     //   108: getfield UF : Lf/Dn0;
/*   */     //   111: dup
/*   */     //   112: astore_2
/*   */     //   113: getfield Ng0 : Lf/lPT9;
/*   */     //   116: getstatic f/lPT9.jR : Lf/lPT9;
/*   */     //   119: if_acmpeq -> 129
/*   */     //   122: aload_2
/*   */     //   123: invokevirtual nUl : ()V
/*   */     //   126: goto -> 158
/*   */     //   129: aload_2
/*   */     //   130: dup
/*   */     //   131: dup
/*   */     //   132: getstatic f/km.a3 : Lf/vh0;
/*   */     //   135: getfield Ct : Lf/Jo;
/*   */     //   138: getfield Eh0 : B
/*   */     //   141: istore_2
/*   */     //   142: getfield Uq : I
/*   */     //   145: istore_3
/*   */     //   146: getfield Z1 : I
/*   */     //   149: istore #4
/*   */     //   151: iload_2
/*   */     //   152: iload_3
/*   */     //   153: iload #4
/*   */     //   155: invokevirtual FD0 : (BII)V
/*   */     //   158: aload_0
/*   */     //   159: aload_1
/*   */     //   160: invokespecial R60 : (Lf/throws;)V
/*   */     //   163: return
/*   */     // Line number table:
/*   */     //   Java source line number -> byte code offset
/*   */     //   #1	-> 12
/*   */     //   #2	-> 15
/*   */     //   #3	-> 37
/*   */     //   #4	-> 47
/*   */     //   #5	-> 52
/*   */     //   #6	-> 55
/*   */     //   #7	-> 76
/*   */     //   #8	-> 84
/*   */     //   #9	-> 102
/*   */     //   #10	-> 105
/*   */     //   #11	-> 108
/*   */     //   #12	-> 113
/*   */     //   #13	-> 116
/*   */     //   #14	-> 135
/*   */     //   #15	-> 138
/*   */     //   #16	-> 142
/*   */     //   #17	-> 155
/*   */     //   #18	-> 160
/*   */   } }


/* Location:              /Users/vnnsnnt/Documents/Codespace/JavaWorkspace/RedTrainer/src/main/java/org/trainer/client/PokeMMO.jar!/f/so0.class
 * Java compiler version: 8 (52.0)
 * JD-Core Version:       1.1.3
 */