/*    */ package f;public abstract class T80 { public static lg0 N2(fQ paramfQ, boolean paramBoolean, Runnable paramRunnable1, Runnable paramRunnable2) { // Byte code:
/*    */     //   0: new f/lg0
/*    */     //   3: dup
/*    */     //   4: dup
/*    */     //   5: astore #4
/*    */     //   7: invokespecial <init> : ()V
/*    */     //   10: ldc 'advanced-search-dialog'
/*    */     //   12: invokevirtual Xu : (Ljava/lang/String;)V
/*    */     //   15: new f/Un
/*    */     //   18: dup
/*    */     //   19: astore #5
/*    */     //   21: sipush #8008
/*    */     //   24: invokestatic OH0 : (I)Ljava/lang/String;
/*    */     //   27: invokespecial <init> : (Ljava/lang/String;)V
/*    */     //   30: new f/Un
/*    */     //   33: dup
/*    */     //   34: astore #6
/*    */     //   36: sipush #8112
/*    */     //   39: invokestatic OH0 : (I)Ljava/lang/String;
/*    */     //   42: invokespecial <init> : (Ljava/lang/String;)V
/*    */     //   45: new f/dQ
/*    */     //   48: dup
/*    */     //   49: dup2
/*    */     //   50: astore #7
/*    */     //   52: sipush #8113
/*    */     //   55: invokestatic OH0 : (I)Ljava/lang/String;
/*    */     //   58: astore #8
/*    */     //   60: invokespecial <init> : ()V
/*    */     //   63: aload #8
/*    */     //   65: invokevirtual E1 : (Ljava/lang/String;)V
/*    */     //   68: ldc 'label-title-medium2'
/*    */     //   70: invokevirtual Xu : (Ljava/lang/String;)V
/*    */     //   73: new f/zT
/*    */     //   76: dup
/*    */     //   77: astore #8
/*    */     //   79: bipush #9
/*    */     //   81: iconst_0
/*    */     //   82: iconst_0
/*    */     //   83: aload_0
/*    */     //   84: invokestatic Cz : (IIILf/fQ;)I
/*    */     //   87: istore #9
/*    */     //   89: iconst_0
/*    */     //   90: ldc 2147483647
/*    */     //   92: iload #9
/*    */     //   94: invokespecial <init> : (III)V
/*    */     //   97: new f/Rm
/*    */     //   100: dup
/*    */     //   101: dup
/*    */     //   102: dup2
/*    */     //   103: astore #9
/*    */     //   105: aload #8
/*    */     //   107: invokespecial <init> : (Lf/zT;)V
/*    */     //   110: ldc '$'
/*    */     //   112: putfield W70 : Ljava/lang/String;
/*    */     //   115: invokevirtual t90 : ()V
/*    */     //   118: invokevirtual Jc : ()V
/*    */     //   121: new f/dQ
/*    */     //   124: dup
/*    */     //   125: dup2
/*    */     //   126: astore #8
/*    */     //   128: sipush #8114
/*    */     //   131: invokestatic OH0 : (I)Ljava/lang/String;
/*    */     //   134: astore #10
/*    */     //   136: invokespecial <init> : ()V
/*    */     //   139: aload #10
/*    */     //   141: invokevirtual E1 : (Ljava/lang/String;)V
/*    */     //   144: ldc 'label-title-medium2'
/*    */     //   146: invokevirtual Xu : (Ljava/lang/String;)V
/*    */     //   149: new f/zT
/*    */     //   152: dup
/*    */     //   153: astore #10
/*    */     //   155: bipush #10
/*    */     //   157: iconst_0
/*    */     //   158: iconst_0
/*    */     //   159: aload_0
/*    */     //   160: invokestatic Cz : (IIILf/fQ;)I
/*    */     //   163: istore #11
/*    */     //   165: iconst_0
/*    */     //   166: ldc 2147483647
/*    */     //   168: iload #11
/*    */     //   170: invokespecial <init> : (III)V
/*    */     //   173: new f/Rm
/*    */     //   176: dup
/*    */     //   177: dup
/*    */     //   178: dup2
/*    */     //   179: astore #11
/*    */     //   181: aload #10
/*    */     //   183: invokespecial <init> : (Lf/zT;)V
/*    */     //   186: ldc '$'
/*    */     //   188: putfield W70 : Ljava/lang/String;
/*    */     //   191: invokevirtual t90 : ()V
/*    */     //   194: invokevirtual Jc : ()V
/*    */     //   197: new f/dQ
/*    */     //   200: dup
/*    */     //   201: dup2
/*    */     //   202: astore #10
/*    */     //   204: sipush #8100
/*    */     //   207: invokestatic OH0 : (I)Ljava/lang/String;
/*    */     //   210: astore #12
/*    */     //   212: invokespecial <init> : ()V
/*    */     //   215: aload #12
/*    */     //   217: invokevirtual E1 : (Ljava/lang/String;)V
/*    */     //   220: ldc 'label-title-medium2'
/*    */     //   222: invokevirtual Xu : (Ljava/lang/String;)V
/*    */     //   225: iconst_3
/*    */     //   226: anewarray java/lang/String
/*    */     //   229: dup
/*    */     //   230: dup2
/*    */     //   231: astore #12
/*    */     //   233: iconst_0
/*    */     //   234: ldc '--'
/*    */     //   236: aastore
/*    */     //   237: sipush #8101
/*    */     //   240: invokestatic OH0 : (I)Ljava/lang/String;
/*    */     //   243: iconst_1
/*    */     //   244: swap
/*    */     //   245: aastore
/*    */     //   246: sipush #8102
/*    */     //   249: invokestatic OH0 : (I)Ljava/lang/String;
/*    */     //   252: iconst_2
/*    */     //   253: swap
/*    */     //   254: aastore
/*    */     //   255: new f/OZ
/*    */     //   258: dup
/*    */     //   259: astore #13
/*    */     //   261: aload #12
/*    */     //   263: invokespecial <init> : ([Ljava/lang/Object;)V
/*    */     //   266: new f/W1
/*    */     //   269: dup
/*    */     //   270: dup
/*    */     //   271: astore #12
/*    */     //   273: aload #13
/*    */     //   275: aload #12
/*    */     //   277: invokespecial <init> : ()V
/*    */     //   280: invokevirtual rk0 : (Lf/cQ;)V
/*    */     //   283: iconst_1
/*    */     //   284: iconst_1
/*    */     //   285: iconst_0
/*    */     //   286: aload_0
/*    */     //   287: invokestatic Cz : (IIILf/fQ;)I
/*    */     //   290: invokevirtual Z30 : (I)V
/*    */     //   293: new f/dQ
/*    */     //   296: dup
/*    */     //   297: dup2
/*    */     //   298: astore #13
/*    */     //   300: sipush #8103
/*    */     //   303: invokestatic OH0 : (I)Ljava/lang/String;
/*    */     //   306: astore #14
/*    */     //   308: invokespecial <init> : ()V
/*    */     //   311: aload #14
/*    */     //   313: invokevirtual E1 : (Ljava/lang/String;)V
/*    */     //   316: ldc 'label-title-medium2'
/*    */     //   318: invokevirtual Xu : (Ljava/lang/String;)V
/*    */     //   321: iconst_5
/*    */     //   322: anewarray java/lang/String
/*    */     //   325: dup
/*    */     //   326: dup2
/*    */     //   327: dup2
/*    */     //   328: astore #14
/*    */     //   330: iconst_0
/*    */     //   331: ldc '--'
/*    */     //   333: aastore
/*    */     //   334: bipush #49
/*    */     //   336: invokestatic OH0 : (I)Ljava/lang/String;
/*    */     //   339: iconst_1
/*    */     //   340: swap
/*    */     //   341: aastore
/*    */     //   342: sipush #10996
/*    */     //   345: invokestatic OH0 : (I)Ljava/lang/String;
/*    */     //   348: iconst_2
/*    */     //   349: swap
/*    */     //   350: aastore
/*    */     //   351: sipush #5614
/*    */     //   354: invokestatic OH0 : (I)Ljava/lang/String;
/*    */     //   357: iconst_3
/*    */     //   358: swap
/*    */     //   359: aastore
/*    */     //   360: bipush #61
/*    */     //   362: invokestatic OH0 : (I)Ljava/lang/String;
/*    */     //   365: iconst_4
/*    */     //   366: swap
/*    */     //   367: aastore
/*    */     //   368: new f/OZ
/*    */     //   371: dup
/*    */     //   372: astore #15
/*    */     //   374: aload #14
/*    */     //   376: invokespecial <init> : ([Ljava/lang/Object;)V
/*    */     //   379: new f/W1
/*    */     //   382: dup
/*    */     //   383: dup
/*    */     //   384: astore #14
/*    */     //   386: aload #15
/*    */     //   388: aload #14
/*    */     //   390: invokespecial <init> : ()V
/*    */     //   393: invokevirtual rk0 : (Lf/cQ;)V
/*    */     //   396: bipush #8
/*    */     //   398: iconst_0
/*    */     //   399: iconst_0
/*    */     //   400: aload_0
/*    */     //   401: invokestatic Cz : (IIILf/fQ;)I
/*    */     //   404: invokevirtual Z30 : (I)V
/*    */     //   407: new f/dQ
/*    */     //   410: dup
/*    */     //   411: dup2
/*    */     //   412: astore #15
/*    */     //   414: sipush #8106
/*    */     //   417: invokestatic OH0 : (I)Ljava/lang/String;
/*    */     //   420: astore #16
/*    */     //   422: invokespecial <init> : ()V
/*    */     //   425: aload #16
/*    */     //   427: invokevirtual E1 : (Ljava/lang/String;)V
/*    */     //   430: ldc 'label-title-medium2'
/*    */     //   432: invokevirtual Xu : (Ljava/lang/String;)V
/*    */     //   435: getstatic f/nV.ko0 : [Lf/nV;
/*    */     //   438: dup
/*    */     //   439: dup
/*    */     //   440: astore #16
/*    */     //   442: arraylength
/*    */     //   443: iconst_1
/*    */     //   444: iadd
/*    */     //   445: anewarray java/lang/String
/*    */     //   448: dup
/*    */     //   449: astore #17
/*    */     //   451: iconst_0
/*    */     //   452: ldc '--'
/*    */     //   454: aastore
/*    */     //   455: arraylength
/*    */     //   456: istore #18
/*    */     //   458: iconst_0
/*    */     //   459: istore #19
/*    */     //   461: iload #19
/*    */     //   463: iload #18
/*    */     //   465: if_icmpge -> 496
/*    */     //   468: aload #17
/*    */     //   470: aload #16
/*    */     //   472: iload #19
/*    */     //   474: aaload
/*    */     //   475: dup
/*    */     //   476: getfield nh : B
/*    */     //   479: iconst_1
/*    */     //   480: iadd
/*    */     //   481: istore #20
/*    */     //   483: invokevirtual cK0 : ()Ljava/lang/String;
/*    */     //   486: iload #20
/*    */     //   488: swap
/*    */     //   489: aastore
/*    */     //   490: iinc #19, 1
/*    */     //   493: goto -> 461
/*    */     //   496: new f/OZ
/*    */     //   499: dup
/*    */     //   500: astore #16
/*    */     //   502: aload #17
/*    */     //   504: invokespecial <init> : ([Ljava/lang/Object;)V
/*    */     //   507: new f/W1
/*    */     //   510: dup
/*    */     //   511: dup
/*    */     //   512: astore #17
/*    */     //   514: aload #16
/*    */     //   516: aload #17
/*    */     //   518: invokespecial <init> : ()V
/*    */     //   521: invokevirtual rk0 : (Lf/cQ;)V
/*    */     //   524: iconst_2
/*    */     //   525: iconst_1
/*    */     //   526: iconst_0
/*    */     //   527: aload_0
/*    */     //   528: invokestatic Cz : (IIILf/fQ;)I
/*    */     //   531: invokevirtual Z30 : (I)V
/*    */     //   534: new f/dQ
/*    */     //   537: dup
/*    */     //   538: dup2
/*    */     //   539: astore #16
/*    */     //   541: sipush #8107
/*    */     //   544: invokestatic OH0 : (I)Ljava/lang/String;
/*    */     //   547: astore #18
/*    */     //   549: invokespecial <init> : ()V
/*    */     //   552: aload #18
/*    */     //   554: invokevirtual E1 : (Ljava/lang/String;)V
/*    */     //   557: ldc 'label-title-medium2'
/*    */     //   559: invokevirtual Xu : (Ljava/lang/String;)V
/*    */     //   562: getstatic f/Ls0.Il0 : [Lf/Ls0;
/*    */     //   565: dup
/*    */     //   566: dup
/*    */     //   567: astore #18
/*    */     //   569: arraylength
/*    */     //   570: iconst_1
/*    */     //   571: iadd
/*    */     //   572: anewarray java/lang/String
/*    */     //   575: dup
/*    */     //   576: astore #19
/*    */     //   578: iconst_0
/*    */     //   579: ldc '--'
/*    */     //   581: aastore
/*    */     //   582: arraylength
/*    */     //   583: istore #20
/*    */     //   585: iconst_0
/*    */     //   586: istore #21
/*    */     //   588: iload #21
/*    */     //   590: iload #20
/*    */     //   592: if_icmpge -> 619
/*    */     //   595: aload #19
/*    */     //   597: aload #18
/*    */     //   599: iload #21
/*    */     //   601: aaload
/*    */     //   602: getfield Hr0 : B
/*    */     //   605: dup
/*    */     //   606: ldc 181000
/*    */     //   608: iadd
/*    */     //   609: invokestatic OH0 : (I)Ljava/lang/String;
/*    */     //   612: aastore
/*    */     //   613: iinc #21, 1
/*    */     //   616: goto -> 588
/*    */     //   619: new f/OZ
/*    */     //   622: dup
/*    */     //   623: astore #18
/*    */     //   625: aload #19
/*    */     //   627: invokespecial <init> : ([Ljava/lang/Object;)V
/*    */     //   630: new f/W1
/*    */     //   633: dup
/*    */     //   634: dup
/*    */     //   635: astore #19
/*    */     //   637: aload #18
/*    */     //   639: aload #19
/*    */     //   641: invokespecial <init> : ()V
/*    */     //   644: invokevirtual rk0 : (Lf/cQ;)V
/*    */     //   647: bipush #7
/*    */     //   649: iconst_0
/*    */     //   650: iconst_0
/*    */     //   651: aload_0
/*    */     //   652: invokestatic Cz : (IIILf/fQ;)I
/*    */     //   655: invokevirtual Z30 : (I)V
/*    */     //   658: new f/dQ
/*    */     //   661: dup
/*    */     //   662: dup2
/*    */     //   663: astore #18
/*    */     //   665: sipush #8097
/*    */     //   668: invokestatic OH0 : (I)Ljava/lang/String;
/*    */     //   671: astore #20
/*    */     //   673: invokespecial <init> : ()V
/*    */     //   676: aload #20
/*    */     //   678: invokevirtual E1 : (Ljava/lang/String;)V
/*    */     //   681: ldc 'label-title-medium2'
/*    */     //   683: invokevirtual Xu : (Ljava/lang/String;)V
/*    */     //   686: new f/zT
/*    */     //   689: dup
/*    */     //   690: astore #20
/*    */     //   692: invokestatic now : ()Ljava/time/Year;
/*    */     //   695: invokevirtual getValue : ()I
/*    */     //   698: bipush #15
/*    */     //   700: iconst_0
/*    */     //   701: iconst_0
/*    */     //   702: aload_0
/*    */     //   703: invokestatic Cz : (IIILf/fQ;)I
/*    */     //   706: istore #21
/*    */     //   708: sipush #2012
/*    */     //   711: swap
/*    */     //   712: iload #21
/*    */     //   714: invokespecial <init> : (III)V
/*    */     //   717: new f/Io0
/*    */     //   720: dup
/*    */     //   721: dup
/*    */     //   722: astore #21
/*    */     //   724: aload #20
/*    */     //   726: dup
/*    */     //   727: invokespecial <init> : (Lf/zT;Lf/zT;)V
/*    */     //   730: invokevirtual Jc : ()V
/*    */     //   733: new f/dQ
/*    */     //   736: dup
/*    */     //   737: dup2
/*    */     //   738: astore #20
/*    */     //   740: sipush #8096
/*    */     //   743: invokestatic OH0 : (I)Ljava/lang/String;
/*    */     //   746: astore #22
/*    */     //   748: invokespecial <init> : ()V
/*    */     //   751: aload #22
/*    */     //   753: invokevirtual E1 : (Ljava/lang/String;)V
/*    */     //   756: ldc 'label-title-medium2'
/*    */     //   758: invokevirtual Xu : (Ljava/lang/String;)V
/*    */     //   761: new f/of
/*    */     //   764: dup
/*    */     //   765: dup2
/*    */     //   766: astore #22
/*    */     //   768: aconst_null
/*    */     //   769: invokespecial <init> : (Lf/Sa0;)V
/*    */     //   772: iconst_1
/*    */     //   773: putfield n00 : Z
/*    */     //   776: <illegal opcode> Nj0 : ()Lf/CF0;
/*    */     //   781: invokevirtual Aw0 : (Lf/CF0;)V
/*    */     //   784: new f/dQ
/*    */     //   787: dup
/*    */     //   788: dup2
/*    */     //   789: astore #23
/*    */     //   791: sipush #8099
/*    */     //   794: invokestatic OH0 : (I)Ljava/lang/String;
/*    */     //   797: astore #24
/*    */     //   799: invokespecial <init> : ()V
/*    */     //   802: aload #24
/*    */     //   804: invokevirtual E1 : (Ljava/lang/String;)V
/*    */     //   807: ldc 'label-title-medium2'
/*    */     //   809: invokevirtual Xu : (Ljava/lang/String;)V
/*    */     //   812: iconst_3
/*    */     //   813: anewarray java/lang/String
/*    */     //   816: dup
/*    */     //   817: dup2
/*    */     //   818: astore #24
/*    */     //   820: iconst_0
/*    */     //   821: ldc '--'
/*    */     //   823: aastore
/*    */     //   824: sipush #8104
/*    */     //   827: invokestatic OH0 : (I)Ljava/lang/String;
/*    */     //   830: iconst_1
/*    */     //   831: swap
/*    */     //   832: aastore
/*    */     //   833: sipush #8105
/*    */     //   836: invokestatic OH0 : (I)Ljava/lang/String;
/*    */     //   839: iconst_2
/*    */     //   840: swap
/*    */     //   841: aastore
/*    */     //   842: new f/OZ
/*    */     //   845: dup
/*    */     //   846: astore #25
/*    */     //   848: aload #24
/*    */     //   850: invokespecial <init> : ([Ljava/lang/Object;)V
/*    */     //   853: new f/W1
/*    */     //   856: dup
/*    */     //   857: dup
/*    */     //   858: astore #24
/*    */     //   860: aload #25
/*    */     //   862: aload #24
/*    */     //   864: invokespecial <init> : ()V
/*    */     //   867: invokevirtual rk0 : (Lf/cQ;)V
/*    */     //   870: bipush #13
/*    */     //   872: iconst_1
/*    */     //   873: iconst_0
/*    */     //   874: aload_0
/*    */     //   875: invokestatic Cz : (IIILf/fQ;)I
/*    */     //   878: invokevirtual Z30 : (I)V
/*    */     //   881: new f/dQ
/*    */     //   884: dup
/*    */     //   885: dup2
/*    */     //   886: astore #25
/*    */     //   888: sipush #8119
/*    */     //   891: invokestatic OH0 : (I)Ljava/lang/String;
/*    */     //   894: astore #26
/*    */     //   896: invokespecial <init> : ()V
/*    */     //   899: aload #26
/*    */     //   901: invokevirtual E1 : (Ljava/lang/String;)V
/*    */     //   904: ldc 'label-title-medium2'
/*    */     //   906: invokevirtual Xu : (Ljava/lang/String;)V
/*    */     //   909: iconst_4
/*    */     //   910: anewarray java/lang/String
/*    */     //   913: dup
/*    */     //   914: dup
/*    */     //   915: dup2
/*    */     //   916: astore #26
/*    */     //   918: iconst_0
/*    */     //   919: ldc '--'
/*    */     //   921: aastore
/*    */     //   922: sipush #8104
/*    */     //   925: invokestatic OH0 : (I)Ljava/lang/String;
/*    */     //   928: iconst_1
/*    */     //   929: swap
/*    */     //   930: aastore
/*    */     //   931: sipush #8105
/*    */     //   934: invokestatic OH0 : (I)Ljava/lang/String;
/*    */     //   937: iconst_2
/*    */     //   938: swap
/*    */     //   939: aastore
/*    */     //   940: sipush #8098
/*    */     //   943: invokestatic OH0 : (I)Ljava/lang/String;
/*    */     //   946: iconst_3
/*    */     //   947: swap
/*    */     //   948: aastore
/*    */     //   949: new f/OZ
/*    */     //   952: dup
/*    */     //   953: astore #27
/*    */     //   955: aload #26
/*    */     //   957: invokespecial <init> : ([Ljava/lang/Object;)V
/*    */     //   960: new f/W1
/*    */     //   963: dup
/*    */     //   964: dup
/*    */     //   965: astore #26
/*    */     //   967: aload #27
/*    */     //   969: aload #26
/*    */     //   971: invokespecial <init> : ()V
/*    */     //   974: invokevirtual rk0 : (Lf/cQ;)V
/*    */     //   977: bipush #14
/*    */     //   979: iconst_1
/*    */     //   980: iconst_0
/*    */     //   981: aload_0
/*    */     //   982: invokestatic Cz : (IIILf/fQ;)I
/*    */     //   985: invokevirtual Z30 : (I)V
/*    */     //   988: new f/dQ
/*    */     //   991: dup
/*    */     //   992: dup2
/*    */     //   993: astore #27
/*    */     //   995: sipush #8115
/*    */     //   998: invokestatic OH0 : (I)Ljava/lang/String;
/*    */     //   1001: astore #28
/*    */     //   1003: invokespecial <init> : ()V
/*    */     //   1006: aload #28
/*    */     //   1008: invokevirtual E1 : (Ljava/lang/String;)V
/*    */     //   1011: ldc 'label-title-medium2'
/*    */     //   1013: invokevirtual Xu : (Ljava/lang/String;)V
/*    */     //   1016: getstatic f/DO.HB0 : [Lf/DO;
/*    */     //   1019: arraylength
/*    */     //   1020: iconst_1
/*    */     //   1021: iadd
/*    */     //   1022: anewarray java/lang/String
/*    */     //   1025: dup
/*    */     //   1026: astore #28
/*    */     //   1028: iconst_0
/*    */     //   1029: ldc '--'
/*    */     //   1031: aastore
/*    */     //   1032: iconst_0
/*    */     //   1033: istore #29
/*    */     //   1035: iload #29
/*    */     //   1037: getstatic f/DO.HB0 : [Lf/DO;
/*    */     //   1040: dup
/*    */     //   1041: astore #30
/*    */     //   1043: arraylength
/*    */     //   1044: if_icmpge -> 1072
/*    */     //   1047: aload #28
/*    */     //   1049: aload #30
/*    */     //   1051: iload #29
/*    */     //   1053: dup
/*    */     //   1054: iconst_1
/*    */     //   1055: iadd
/*    */     //   1056: istore #29
/*    */     //   1058: aaload
/*    */     //   1059: getfield mt0 : I
/*    */     //   1062: invokestatic OH0 : (I)Ljava/lang/String;
/*    */     //   1065: iload #29
/*    */     //   1067: swap
/*    */     //   1068: aastore
/*    */     //   1069: goto -> 1035
/*    */     //   1072: new f/OZ
/*    */     //   1075: dup
/*    */     //   1076: astore #29
/*    */     //   1078: aload #28
/*    */     //   1080: invokespecial <init> : ([Ljava/lang/Object;)V
/*    */     //   1083: new f/W1
/*    */     //   1086: dup
/*    */     //   1087: dup
/*    */     //   1088: astore #28
/*    */     //   1090: aload #29
/*    */     //   1092: aload #28
/*    */     //   1094: invokespecial <init> : ()V
/*    */     //   1097: invokevirtual rk0 : (Lf/cQ;)V
/*    */     //   1100: bipush #11
/*    */     //   1102: iconst_0
/*    */     //   1103: iconst_0
/*    */     //   1104: aload_0
/*    */     //   1105: invokestatic Cz : (IIILf/fQ;)I
/*    */     //   1108: invokevirtual Z30 : (I)V
/*    */     //   1111: new f/dQ
/*    */     //   1114: dup
/*    */     //   1115: dup2
/*    */     //   1116: astore #29
/*    */     //   1118: sipush #8116
/*    */     //   1121: invokestatic OH0 : (I)Ljava/lang/String;
/*    */     //   1124: astore #30
/*    */     //   1126: invokespecial <init> : ()V
/*    */     //   1129: aload #30
/*    */     //   1131: invokevirtual E1 : (Ljava/lang/String;)V
/*    */     //   1134: ldc 'label-title-medium2'
/*    */     //   1136: invokevirtual Xu : (Ljava/lang/String;)V
/*    */     //   1139: getstatic f/mA.ak0 : [Lf/mA;
/*    */     //   1142: invokestatic of : ([Ljava/lang/Object;)Ljava/util/stream/Stream;
/*    */     //   1145: <illegal opcode> test : ()Ljava/util/function/Predicate;
/*    */     //   1150: invokeinterface filter : (Ljava/util/function/Predicate;)Ljava/util/stream/Stream;
/*    */     //   1155: invokestatic toList : ()Ljava/util/stream/Collector;
/*    */     //   1158: invokeinterface collect : (Ljava/util/stream/Collector;)Ljava/lang/Object;
/*    */     //   1163: checkcast java/util/List
/*    */     //   1166: dup
/*    */     //   1167: astore #30
/*    */     //   1169: iconst_0
/*    */     //   1170: aconst_null
/*    */     //   1171: invokeinterface add : (ILjava/lang/Object;)V
/*    */     //   1176: new f/OZ
/*    */     //   1179: dup
/*    */     //   1180: astore #31
/*    */     //   1182: aload #30
/*    */     //   1184: invokespecial <init> : (Ljava/util/Collection;)V
/*    */     //   1187: new f/W1
/*    */     //   1190: dup
/*    */     //   1191: dup
/*    */     //   1192: dup2
/*    */     //   1193: dup2
/*    */     //   1194: astore #30
/*    */     //   1196: aload #31
/*    */     //   1198: aload #30
/*    */     //   1200: invokespecial <init> : ()V
/*    */     //   1203: invokevirtual rk0 : (Lf/cQ;)V
/*    */     //   1206: ldc '--'
/*    */     //   1208: putfield zx : Ljava/lang/String;
/*    */     //   1211: invokevirtual s3 : ()V
/*    */     //   1214: bipush #12
/*    */     //   1216: iconst_0
/*    */     //   1217: iconst_m1
/*    */     //   1218: aload_0
/*    */     //   1219: invokestatic Cz : (IIILf/fQ;)I
/*    */     //   1222: invokevirtual Z30 : (I)V
/*    */     //   1225: <illegal opcode> run : (Lf/W1;)Ljava/lang/Runnable;
/*    */     //   1230: invokevirtual D30 : (Ljava/lang/Runnable;)V
/*    */     //   1233: iconst_2
/*    */     //   1234: anewarray f/dQ
/*    */     //   1237: astore #31
/*    */     //   1239: iconst_2
/*    */     //   1240: anewarray f/Rm
/*    */     //   1243: astore #32
/*    */     //   1245: iconst_0
/*    */     //   1246: istore #33
/*    */     //   1248: iload #33
/*    */     //   1250: iconst_2
/*    */     //   1251: if_icmpge -> 1339
/*    */     //   1254: aload #32
/*    */     //   1256: iload #33
/*    */     //   1258: new f/dQ
/*    */     //   1261: dup
/*    */     //   1262: astore #34
/*    */     //   1264: aload #31
/*    */     //   1266: iload #33
/*    */     //   1268: aload #34
/*    */     //   1270: dup
/*    */     //   1271: iload #33
/*    */     //   1273: sipush #8108
/*    */     //   1276: iadd
/*    */     //   1277: invokestatic OH0 : (I)Ljava/lang/String;
/*    */     //   1280: astore #35
/*    */     //   1282: invokespecial <init> : ()V
/*    */     //   1285: aload #35
/*    */     //   1287: invokevirtual E1 : (Ljava/lang/String;)V
/*    */     //   1290: aload #34
/*    */     //   1292: aastore
/*    */     //   1293: ldc 'label-title-medium2'
/*    */     //   1295: invokevirtual Xu : (Ljava/lang/String;)V
/*    */     //   1298: new f/zT
/*    */     //   1301: dup
/*    */     //   1302: astore #34
/*    */     //   1304: iload #33
/*    */     //   1306: bipush #100
/*    */     //   1308: imul
/*    */     //   1309: istore #35
/*    */     //   1311: iconst_1
/*    */     //   1312: bipush #100
/*    */     //   1314: iload #35
/*    */     //   1316: invokespecial <init> : (III)V
/*    */     //   1319: new f/Rm
/*    */     //   1322: dup
/*    */     //   1323: astore #35
/*    */     //   1325: aload #34
/*    */     //   1327: invokespecial <init> : (Lf/zT;)V
/*    */     //   1330: aload #35
/*    */     //   1332: aastore
/*    */     //   1333: iinc #33, 1
/*    */     //   1336: goto -> 1248
/*    */     //   1339: getstatic f/hR.Tm0 : [Lf/hR;
/*    */     //   1342: dup
/*    */     //   1343: dup2
/*    */     //   1344: dup2
/*    */     //   1345: astore #33
/*    */     //   1347: arraylength
/*    */     //   1348: iconst_2
/*    */     //   1349: multianewarray[[Lf/rh; 2
/*    */     //   1353: astore #34
/*    */     //   1355: arraylength
/*    */     //   1356: iconst_2
/*    */     //   1357: multianewarray[[Lf/dQ; 2
/*    */     //   1361: astore #35
/*    */     //   1363: arraylength
/*    */     //   1364: iconst_2
/*    */     //   1365: multianewarray[[Lf/rh; 2
/*    */     //   1369: astore #36
/*    */     //   1371: arraylength
/*    */     //   1372: iconst_2
/*    */     //   1373: multianewarray[[Lf/dQ; 2
/*    */     //   1377: astore #37
/*    */     //   1379: arraylength
/*    */     //   1380: istore #38
/*    */     //   1382: iconst_0
/*    */     //   1383: istore #39
/*    */     //   1385: iload #39
/*    */     //   1387: iload #38
/*    */     //   1389: if_icmpge -> 1821
/*    */     //   1392: aload #33
/*    */     //   1394: iload #39
/*    */     //   1396: aaload
/*    */     //   1397: dup
/*    */     //   1398: astore #40
/*    */     //   1400: getfield NT : Z
/*    */     //   1403: ifeq -> 1409
/*    */     //   1406: goto -> 1815
/*    */     //   1409: iconst_0
/*    */     //   1410: istore #41
/*    */     //   1412: iload #41
/*    */     //   1414: iconst_2
/*    */     //   1415: if_icmpge -> 1815
/*    */     //   1418: iload #41
/*    */     //   1420: aload #34
/*    */     //   1422: aload #40
/*    */     //   1424: aload #34
/*    */     //   1426: aload #40
/*    */     //   1428: aload #35
/*    */     //   1430: aload #40
/*    */     //   1432: aload #35
/*    */     //   1434: aload #40
/*    */     //   1436: getfield dL : B
/*    */     //   1439: aaload
/*    */     //   1440: iload #41
/*    */     //   1442: new f/dQ
/*    */     //   1445: dup
/*    */     //   1446: dup
/*    */     //   1447: astore #42
/*    */     //   1449: iload #41
/*    */     //   1451: sipush #8110
/*    */     //   1454: iadd
/*    */     //   1455: aload #40
/*    */     //   1457: invokevirtual toString : ()Ljava/lang/String;
/*    */     //   1460: invokestatic Go : (ILjava/lang/String;)Ljava/lang/String;
/*    */     //   1463: astore #43
/*    */     //   1465: invokespecial <init> : ()V
/*    */     //   1468: aload #43
/*    */     //   1470: invokevirtual E1 : (Ljava/lang/String;)V
/*    */     //   1473: aload #42
/*    */     //   1475: aastore
/*    */     //   1476: getfield dL : B
/*    */     //   1479: aaload
/*    */     //   1480: iload #41
/*    */     //   1482: aaload
/*    */     //   1483: ldc 'label-title-medium2'
/*    */     //   1485: invokevirtual Xu : (Ljava/lang/String;)V
/*    */     //   1488: getfield dL : B
/*    */     //   1491: aaload
/*    */     //   1492: iload #41
/*    */     //   1494: new f/rh
/*    */     //   1497: dup
/*    */     //   1498: astore #42
/*    */     //   1500: new f/zT
/*    */     //   1503: dup
/*    */     //   1504: iconst_0
/*    */     //   1505: bipush #31
/*    */     //   1507: iconst_0
/*    */     //   1508: invokespecial <init> : (III)V
/*    */     //   1511: invokespecial <init> : (Lf/er;)V
/*    */     //   1514: aload #42
/*    */     //   1516: aastore
/*    */     //   1517: getfield dL : B
/*    */     //   1520: aaload
/*    */     //   1521: iload #41
/*    */     //   1523: aaload
/*    */     //   1524: astore #42
/*    */     //   1526: ifne -> 1535
/*    */     //   1529: iconst_5
/*    */     //   1530: istore #43
/*    */     //   1532: goto -> 1539
/*    */     //   1535: bipush #6
/*    */     //   1537: istore #43
/*    */     //   1539: aload_0
/*    */     //   1540: iload #41
/*    */     //   1542: bipush #31
/*    */     //   1544: imul
/*    */     //   1545: istore #44
/*    */     //   1547: invokevirtual r30 : ()Lf/Hc0;
/*    */     //   1550: astore #45
/*    */     //   1552: aload #45
/*    */     //   1554: invokevirtual hasNext : ()Z
/*    */     //   1557: ifeq -> 1605
/*    */     //   1560: aload #45
/*    */     //   1562: invokevirtual next : ()Ljava/lang/Object;
/*    */     //   1565: checkcast f/sK
/*    */     //   1568: dup
/*    */     //   1569: astore #46
/*    */     //   1571: getfield ak : B
/*    */     //   1574: iload #43
/*    */     //   1576: if_icmpne -> 1552
/*    */     //   1579: aload #46
/*    */     //   1581: checkcast f/S80
/*    */     //   1584: getfield IL : Lf/hR;
/*    */     //   1587: getfield dL : B
/*    */     //   1590: aload #40
/*    */     //   1592: getfield dL : B
/*    */     //   1595: if_icmpne -> 1552
/*    */     //   1598: aload #46
/*    */     //   1600: invokevirtual a7 : ()I
/*    */     //   1603: istore #44
/*    */     //   1605: iload #41
/*    */     //   1607: aload #36
/*    */     //   1609: aload #40
/*    */     //   1611: aload #36
/*    */     //   1613: aload #40
/*    */     //   1615: aload #37
/*    */     //   1617: aload #40
/*    */     //   1619: aload #37
/*    */     //   1621: aload #40
/*    */     //   1623: aload #42
/*    */     //   1625: iload #44
/*    */     //   1627: invokevirtual l4 : (I)V
/*    */     //   1630: getfield dL : B
/*    */     //   1633: aaload
/*    */     //   1634: iload #41
/*    */     //   1636: new f/dQ
/*    */     //   1639: dup
/*    */     //   1640: dup
/*    */     //   1641: astore #42
/*    */     //   1643: iload #41
/*    */     //   1645: sipush #8093
/*    */     //   1648: iadd
/*    */     //   1649: aload #40
/*    */     //   1651: invokevirtual toString : ()Ljava/lang/String;
/*    */     //   1654: invokestatic Go : (ILjava/lang/String;)Ljava/lang/String;
/*    */     //   1657: astore #43
/*    */     //   1659: invokespecial <init> : ()V
/*    */     //   1662: aload #43
/*    */     //   1664: invokevirtual E1 : (Ljava/lang/String;)V
/*    */     //   1667: aload #42
/*    */     //   1669: aastore
/*    */     //   1670: getfield dL : B
/*    */     //   1673: aaload
/*    */     //   1674: iload #41
/*    */     //   1676: aaload
/*    */     //   1677: ldc 'label-title-medium2'
/*    */     //   1679: invokevirtual Xu : (Ljava/lang/String;)V
/*    */     //   1682: getfield dL : B
/*    */     //   1685: aaload
/*    */     //   1686: iload #41
/*    */     //   1688: new f/rh
/*    */     //   1691: dup
/*    */     //   1692: astore #42
/*    */     //   1694: new f/zT
/*    */     //   1697: dup
/*    */     //   1698: iconst_0
/*    */     //   1699: sipush #252
/*    */     //   1702: iconst_0
/*    */     //   1703: invokespecial <init> : (III)V
/*    */     //   1706: invokespecial <init> : (Lf/er;)V
/*    */     //   1709: aload #42
/*    */     //   1711: aastore
/*    */     //   1712: getfield dL : B
/*    */     //   1715: aaload
/*    */     //   1716: iload #41
/*    */     //   1718: aaload
/*    */     //   1719: astore #42
/*    */     //   1721: ifne -> 1731
/*    */     //   1724: bipush #17
/*    */     //   1726: istore #43
/*    */     //   1728: goto -> 1735
/*    */     //   1731: bipush #18
/*    */     //   1733: istore #43
/*    */     //   1735: aload_0
/*    */     //   1736: iload #41
/*    */     //   1738: sipush #252
/*    */     //   1741: imul
/*    */     //   1742: istore #44
/*    */     //   1744: invokevirtual r30 : ()Lf/Hc0;
/*    */     //   1747: astore #45
/*    */     //   1749: aload #45
/*    */     //   1751: invokevirtual hasNext : ()Z
/*    */     //   1754: ifeq -> 1802
/*    */     //   1757: aload #45
/*    */     //   1759: invokevirtual next : ()Ljava/lang/Object;
/*    */     //   1762: checkcast f/sK
/*    */     //   1765: dup
/*    */     //   1766: astore #46
/*    */     //   1768: getfield ak : B
/*    */     //   1771: iload #43
/*    */     //   1773: if_icmpne -> 1749
/*    */     //   1776: aload #46
/*    */     //   1778: checkcast f/S80
/*    */     //   1781: getfield IL : Lf/hR;
/*    */     //   1784: getfield dL : B
/*    */     //   1787: aload #40
/*    */     //   1789: getfield dL : B
/*    */     //   1792: if_icmpne -> 1749
/*    */     //   1795: aload #46
/*    */     //   1797: invokevirtual a7 : ()I
/*    */     //   1800: istore #44
/*    */     //   1802: aload #42
/*    */     //   1804: iload #44
/*    */     //   1806: invokevirtual l4 : (I)V
/*    */     //   1809: iinc #41, 1
/*    */     //   1812: goto -> 1412
/*    */     //   1815: iinc #39, 1
/*    */     //   1818: goto -> 1385
/*    */     //   1821: aload #4
/*    */     //   1823: dup
/*    */     //   1824: new f/dQ
/*    */     //   1827: dup
/*    */     //   1828: dup2
/*    */     //   1829: astore #33
/*    */     //   1831: sipush #8092
/*    */     //   1834: invokestatic OH0 : (I)Ljava/lang/String;
/*    */     //   1837: astore #38
/*    */     //   1839: invokespecial <init> : ()V
/*    */     //   1842: aload #38
/*    */     //   1844: invokevirtual E1 : (Ljava/lang/String;)V
/*    */     //   1847: ldc 'label-title-medium2'
/*    */     //   1849: invokevirtual Xu : (Ljava/lang/String;)V
/*    */     //   1852: new f/rh
/*    */     //   1855: dup
/*    */     //   1856: dup
/*    */     //   1857: astore #38
/*    */     //   1859: new f/zT
/*    */     //   1862: dup
/*    */     //   1863: iconst_0
/*    */     //   1864: bipush #6
/*    */     //   1866: iconst_0
/*    */     //   1867: invokespecial <init> : (III)V
/*    */     //   1870: invokespecial <init> : (Lf/er;)V
/*    */     //   1873: invokevirtual Jc : ()V
/*    */     //   1876: new f/dQ
/*    */     //   1879: dup
/*    */     //   1880: dup2
/*    */     //   1881: astore #39
/*    */     //   1883: sipush #8091
/*    */     //   1886: invokestatic OH0 : (I)Ljava/lang/String;
/*    */     //   1889: astore #40
/*    */     //   1891: invokespecial <init> : ()V
/*    */     //   1894: aload #40
/*    */     //   1896: invokevirtual E1 : (Ljava/lang/String;)V
/*    */     //   1899: ldc 'label-title-medium2'
/*    */     //   1901: invokevirtual Xu : (Ljava/lang/String;)V
/*    */     //   1904: new f/ge0
/*    */     //   1907: dup
/*    */     //   1908: dup
/*    */     //   1909: astore #40
/*    */     //   1911: invokespecial <init> : ()V
/*    */     //   1914: getfield TG0 : Lf/protected;
/*    */     //   1917: iconst_0
/*    */     //   1918: invokevirtual Fx0 : (Z)V
/*    */     //   1921: new f/dQ
/*    */     //   1924: dup
/*    */     //   1925: dup2
/*    */     //   1926: astore #41
/*    */     //   1928: sipush #8086
/*    */     //   1931: invokestatic OH0 : (I)Ljava/lang/String;
/*    */     //   1934: astore #42
/*    */     //   1936: invokespecial <init> : ()V
/*    */     //   1939: aload #42
/*    */     //   1941: invokevirtual E1 : (Ljava/lang/String;)V
/*    */     //   1944: ldc 'label-title-medium2'
/*    */     //   1946: invokevirtual Xu : (Ljava/lang/String;)V
/*    */     //   1949: new f/ge0
/*    */     //   1952: dup
/*    */     //   1953: dup
/*    */     //   1954: astore #42
/*    */     //   1956: invokespecial <init> : ()V
/*    */     //   1959: getfield TG0 : Lf/protected;
/*    */     //   1962: iconst_0
/*    */     //   1963: invokevirtual Fx0 : (Z)V
/*    */     //   1966: new f/dQ
/*    */     //   1969: dup
/*    */     //   1970: dup2
/*    */     //   1971: astore #43
/*    */     //   1973: sipush #8085
/*    */     //   1976: invokestatic OH0 : (I)Ljava/lang/String;
/*    */     //   1979: astore #44
/*    */     //   1981: invokespecial <init> : ()V
/*    */     //   1984: aload #44
/*    */     //   1986: invokevirtual E1 : (Ljava/lang/String;)V
/*    */     //   1989: ldc 'label-title-medium2'
/*    */     //   1991: invokevirtual Xu : (Ljava/lang/String;)V
/*    */     //   1994: new f/ge0
/*    */     //   1997: dup
/*    */     //   1998: dup
/*    */     //   1999: astore #44
/*    */     //   2001: invokespecial <init> : ()V
/*    */     //   2004: getfield TG0 : Lf/protected;
/*    */     //   2007: iconst_0
/*    */     //   2008: invokevirtual Fx0 : (Z)V
/*    */     //   2011: invokestatic builder : ()Ljava/util/stream/Stream$Builder;
/*    */     //   2014: dup
/*    */     //   2015: astore #45
/*    */     //   2017: invokestatic v30 : ()Lf/On;
/*    */     //   2020: getfield iI0 : Ljava/util/HashMap;
/*    */     //   2023: invokevirtual values : ()Ljava/util/Collection;
/*    */     //   2026: invokeinterface stream : ()Ljava/util/stream/Stream;
/*    */     //   2031: <illegal opcode> test : ()Ljava/util/function/Predicate;
/*    */     //   2036: invokeinterface filter : (Ljava/util/function/Predicate;)Ljava/util/stream/Stream;
/*    */     //   2041: aload #45
/*    */     //   2043: dup
/*    */     //   2044: invokevirtual getClass : ()Ljava/lang/Class;
/*    */     //   2047: pop
/*    */     //   2048: <illegal opcode> accept : (Ljava/util/stream/Stream$Builder;)Ljava/util/function/Consumer;
/*    */     //   2053: invokeinterface forEach : (Ljava/util/function/Consumer;)V
/*    */     //   2058: getstatic f/gm.EI0 : [S
/*    */     //   2061: arraylength
/*    */     //   2062: iconst_0
/*    */     //   2063: swap
/*    */     //   2064: invokestatic range : (II)Ljava/util/stream/IntStream;
/*    */     //   2067: <illegal opcode> apply : ()Ljava/util/function/IntFunction;
/*    */     //   2072: invokeinterface mapToObj : (Ljava/util/function/IntFunction;)Ljava/util/stream/Stream;
/*    */     //   2077: aload #45
/*    */     //   2079: <illegal opcode> accept : (Ljava/util/stream/Stream$Builder;)Ljava/util/function/Consumer;
/*    */     //   2084: invokeinterface forEach : (Ljava/util/function/Consumer;)V
/*    */     //   2089: getstatic f/gm.QN : [S
/*    */     //   2092: arraylength
/*    */     //   2093: iconst_0
/*    */     //   2094: swap
/*    */     //   2095: invokestatic range : (II)Ljava/util/stream/IntStream;
/*    */     //   2098: <illegal opcode> apply : ()Ljava/util/function/IntFunction;
/*    */     //   2103: invokeinterface mapToObj : (Ljava/util/function/IntFunction;)Ljava/util/stream/Stream;
/*    */     //   2108: aload #45
/*    */     //   2110: <illegal opcode> accept : (Ljava/util/stream/Stream$Builder;)Ljava/util/function/Consumer;
/*    */     //   2115: invokeinterface forEach : (Ljava/util/function/Consumer;)V
/*    */     //   2120: invokeinterface build : ()Ljava/util/stream/Stream;
/*    */     //   2125: <illegal opcode> apply : ()Ljava/util/function/Function;
/*    */     //   2130: invokeinterface map : (Ljava/util/function/Function;)Ljava/util/stream/Stream;
/*    */     //   2135: <illegal opcode> apply : ()Ljava/util/function/Function;
/*    */     //   2140: invokeinterface flatMap : (Ljava/util/function/Function;)Ljava/util/stream/Stream;
/*    */     //   2145: invokeinterface distinct : ()Ljava/util/stream/Stream;
/*    */     //   2150: <illegal opcode> applyAsInt : ()Ljava/util/function/ToIntFunction;
/*    */     //   2155: invokeinterface mapToInt : (Ljava/util/function/ToIntFunction;)Ljava/util/stream/IntStream;
/*    */     //   2160: invokeinterface toArray : ()[I
/*    */     //   2165: dup
/*    */     //   2166: astore #45
/*    */     //   2168: invokestatic stream : ([I)Ljava/util/stream/IntStream;
/*    */     //   2171: <illegal opcode> apply : ()Ljava/util/function/IntFunction;
/*    */     //   2176: invokeinterface mapToObj : (Ljava/util/function/IntFunction;)Ljava/util/stream/Stream;
/*    */     //   2181: invokestatic toList : ()Ljava/util/stream/Collector;
/*    */     //   2184: invokeinterface collect : (Ljava/util/stream/Collector;)Ljava/lang/Object;
/*    */     //   2189: checkcast java/util/List
/*    */     //   2192: astore #46
/*    */     //   2194: new f/dQ
/*    */     //   2197: dup
/*    */     //   2198: dup2
/*    */     //   2199: astore #47
/*    */     //   2201: sipush #8088
/*    */     //   2204: invokestatic OH0 : (I)Ljava/lang/String;
/*    */     //   2207: astore #48
/*    */     //   2209: invokespecial <init> : ()V
/*    */     //   2212: aload #48
/*    */     //   2214: invokevirtual E1 : (Ljava/lang/String;)V
/*    */     //   2217: ldc 'label-title-medium2'
/*    */     //   2219: invokevirtual Xu : (Ljava/lang/String;)V
/*    */     //   2222: new f/of
/*    */     //   2225: dup
/*    */     //   2226: astore #48
/*    */     //   2228: aload #46
/*    */     //   2230: aload #48
/*    */     //   2232: dup
/*    */     //   2233: aconst_null
/*    */     //   2234: invokespecial <init> : (Lf/Sa0;)V
/*    */     //   2237: iconst_1
/*    */     //   2238: putfield n00 : Z
/*    */     //   2241: <illegal opcode> Nj0 : (Ljava/util/List;)Lf/CF0;
/*    */     //   2246: invokevirtual Aw0 : (Lf/CF0;)V
/*    */     //   2249: new f/Un
/*    */     //   2252: dup
/*    */     //   2253: astore #49
/*    */     //   2255: ldc_w '< '
/*    */     //   2258: invokestatic df : (Ljava/lang/String;)Ljava/lang/StringBuilder;
/*    */     //   2261: sipush #8089
/*    */     //   2264: invokestatic OH0 : (I)Ljava/lang/String;
/*    */     //   2267: invokevirtual append : (Ljava/lang/String;)Ljava/lang/StringBuilder;
/*    */     //   2270: invokevirtual toString : ()Ljava/lang/String;
/*    */     //   2273: invokespecial <init> : (Ljava/lang/String;)V
/*    */     //   2276: new f/Un
/*    */     //   2279: dup
/*    */     //   2280: dup
/*    */     //   2281: astore #50
/*    */     //   2283: new java/lang/StringBuilder
/*    */     //   2286: dup
/*    */     //   2287: astore #51
/*    */     //   2289: invokespecial <init> : ()V
/*    */     //   2292: sipush #8090
/*    */     //   2295: aload #51
/*    */     //   2297: ldc_w ' >'
/*    */     //   2300: invokestatic jJ0 : (ILjava/lang/StringBuilder;Ljava/lang/String;)Ljava/lang/String;
/*    */     //   2303: invokespecial <init> : (Ljava/lang/String;)V
/*    */     //   2306: aload #5
/*    */     //   2308: iload_1
/*    */     //   2309: aload #7
/*    */     //   2311: aload #9
/*    */     //   2313: aload #8
/*    */     //   2315: aload #11
/*    */     //   2317: aload #10
/*    */     //   2319: aload #12
/*    */     //   2321: aload #13
/*    */     //   2323: aload #14
/*    */     //   2325: aload #15
/*    */     //   2327: aload #17
/*    */     //   2329: aload #16
/*    */     //   2331: aload #19
/*    */     //   2333: aload #29
/*    */     //   2335: aload #30
/*    */     //   2337: aload #20
/*    */     //   2339: aload #22
/*    */     //   2341: aload #23
/*    */     //   2343: aload #24
/*    */     //   2345: aload #25
/*    */     //   2347: aload #26
/*    */     //   2349: aload #31
/*    */     //   2351: aload #32
/*    */     //   2353: aload #35
/*    */     //   2355: aload #34
/*    */     //   2357: aload #33
/*    */     //   2359: aload #38
/*    */     //   2361: aload #41
/*    */     //   2363: aload #42
/*    */     //   2365: aload #6
/*    */     //   2367: <illegal opcode> run : (Lf/Ip;Lf/Un;Lf/Un;ZLf/dQ;Lf/Rm;Lf/dQ;Lf/Rm;Lf/dQ;Lf/W1;Lf/dQ;Lf/W1;Lf/dQ;Lf/W1;Lf/dQ;Lf/W1;Lf/dQ;Lf/W1;Lf/dQ;Lf/of;Lf/dQ;Lf/W1;Lf/dQ;Lf/W1;[Lf/dQ;[Lf/Rm;[[Lf/dQ;[[Lf/rh;Lf/dQ;Lf/rh;Lf/dQ;Lf/ge0;Lf/Un;)Ljava/lang/Runnable;
/*    */     //   2372: dup
/*    */     //   2373: astore #7
/*    */     //   2375: aload #6
/*    */     //   2377: aload_0
/*    */     //   2378: aload #14
/*    */     //   2380: aload #6
/*    */     //   2382: aload #5
/*    */     //   2384: aload_0
/*    */     //   2385: aload_2
/*    */     //   2386: aload #5
/*    */     //   2388: aload #50
/*    */     //   2390: dup
/*    */     //   2391: aload #49
/*    */     //   2393: aload #7
/*    */     //   2395: aload #49
/*    */     //   2397: aload #4
/*    */     //   2399: aload #49
/*    */     //   2401: aload #5
/*    */     //   2403: iload_1
/*    */     //   2404: aload #29
/*    */     //   2406: aload #30
/*    */     //   2408: aload #20
/*    */     //   2410: aload #22
/*    */     //   2412: aload #27
/*    */     //   2414: aload #28
/*    */     //   2416: aload #18
/*    */     //   2418: aload #21
/*    */     //   2420: aload #37
/*    */     //   2422: aload #36
/*    */     //   2424: aload #47
/*    */     //   2426: aload #48
/*    */     //   2428: aload #43
/*    */     //   2430: aload #44
/*    */     //   2432: aload #39
/*    */     //   2434: aload #40
/*    */     //   2436: aload #6
/*    */     //   2438: <illegal opcode> run : (Lf/Ip;Lf/Un;Lf/Un;ZLf/dQ;Lf/W1;Lf/dQ;Lf/of;Lf/dQ;Lf/W1;Lf/dQ;Lf/rh;[[Lf/dQ;[[Lf/rh;Lf/dQ;Lf/of;Lf/dQ;Lf/ge0;Lf/dQ;Lf/ge0;Lf/Un;)Ljava/lang/Runnable;
/*    */     //   2443: astore_0
/*    */     //   2444: ldc_w 'label-button-small2-centered'
/*    */     //   2447: invokevirtual Xu : (Ljava/lang/String;)V
/*    */     //   2450: invokevirtual tW : (Ljava/lang/Runnable;)V
/*    */     //   2453: ldc_w 'label-button-small2-centered'
/*    */     //   2456: invokevirtual Xu : (Ljava/lang/String;)V
/*    */     //   2459: aload_0
/*    */     //   2460: invokevirtual tW : (Ljava/lang/Runnable;)V
/*    */     //   2463: ldc_w 'label-button-small2-centered'
/*    */     //   2466: invokevirtual Xu : (Ljava/lang/String;)V
/*    */     //   2469: <illegal opcode> run : (Lf/fQ;Ljava/lang/Runnable;)Ljava/lang/Runnable;
/*    */     //   2474: invokevirtual tW : (Ljava/lang/Runnable;)V
/*    */     //   2477: ldc_w 'label-button-small2-centered'
/*    */     //   2480: invokevirtual Xu : (Ljava/lang/String;)V
/*    */     //   2483: iload_1
/*    */     //   2484: aload #9
/*    */     //   2486: aload #11
/*    */     //   2488: aload #40
/*    */     //   2490: aload #12
/*    */     //   2492: aload #17
/*    */     //   2494: aload #24
/*    */     //   2496: aload #26
/*    */     //   2498: aload #21
/*    */     //   2500: aload #22
/*    */     //   2502: aload #28
/*    */     //   2504: aload #30
/*    */     //   2506: aload #32
/*    */     //   2508: aload #19
/*    */     //   2510: aload #38
/*    */     //   2512: aload #34
/*    */     //   2514: aload #36
/*    */     //   2516: aload #48
/*    */     //   2518: aload #46
/*    */     //   2520: aload #45
/*    */     //   2522: aload #42
/*    */     //   2524: aload #44
/*    */     //   2526: aload_3
/*    */     //   2527: <illegal opcode> run : (Lf/fQ;Lf/W1;ZLf/Rm;Lf/Rm;Lf/ge0;Lf/W1;Lf/W1;Lf/W1;Lf/W1;Lf/rh;Lf/of;Lf/W1;Lf/W1;[Lf/Rm;Lf/W1;Lf/rh;[[Lf/rh;[[Lf/rh;Lf/of;Ljava/util/List;[ILf/ge0;Lf/ge0;Ljava/lang/Runnable;)Ljava/lang/Runnable;
/*    */     //   2532: invokevirtual tW : (Ljava/lang/Runnable;)V
/*    */     //   2535: invokeinterface run : ()V
/*    */     //   2540: areturn
/*    */     // Line number table:
/*    */     //   Java source line number -> byte code offset
/*    */     //   #1	-> 0
/*    */     //   #2	-> 10
/*    */     //   #3	-> 60
/*    */     //   #4	-> 68
/*    */     //   #5	-> 110
/*    */     //   #6	-> 118
/*    */     //   #7	-> 136
/*    */     //   #8	-> 144
/*    */     //   #9	-> 186
/*    */     //   #10	-> 194
/*    */     //   #11	-> 212
/*    */     //   #12	-> 220
/*    */     //   #13	-> 277
/*    */     //   #14	-> 287
/*    */     //   #15	-> 308
/*    */     //   #16	-> 316
/*    */     //   #17	-> 390
/*    */     //   #18	-> 401
/*    */     //   #19	-> 422
/*    */     //   #20	-> 430
/*    */     //   #21	-> 476
/*    */     //   #22	-> 483
/*    */     //   #23	-> 518
/*    */     //   #24	-> 528
/*    */     //   #25	-> 549
/*    */     //   #26	-> 557
/*    */     //   #27	-> 602
/*    */     //   #28	-> 609
/*    */     //   #29	-> 612
/*    */     //   #30	-> 641
/*    */     //   #31	-> 652
/*    */     //   #32	-> 673
/*    */     //   #33	-> 681
/*    */     //   #34	-> 748
/*    */     //   #35	-> 756
/*    */     //   #36	-> 769
/*    */     //   #37	-> 773
/*    */     //   #38	-> 776
/*    */     //   #39	-> 799
/*    */     //   #40	-> 807
/*    */     //   #41	-> 864
/*    */     //   #42	-> 875
/*    */     //   #43	-> 896
/*    */     //   #44	-> 904
/*    */     //   #45	-> 971
/*    */     //   #46	-> 982
/*    */     //   #47	-> 1003
/*    */     //   #48	-> 1011
/*    */     //   #49	-> 1059
/*    */     //   #50	-> 1062
/*    */     //   #51	-> 1068
/*    */     //   #52	-> 1094
/*    */     //   #53	-> 1105
/*    */     //   #54	-> 1126
/*    */     //   #55	-> 1134
/*    */     //   #56	-> 1200
/*    */     //   #57	-> 1206
/*    */     //   #58	-> 1219
/*    */     //   #59	-> 1282
/*    */     //   #60	-> 1292
/*    */     //   #61	-> 1400
/*    */     //   #62	-> 1436
/*    */     //   #63	-> 1439
/*    */     //   #64	-> 1465
/*    */     //   #65	-> 1475
/*    */     //   #66	-> 1476
/*    */     //   #67	-> 1479
/*    */     //   #68	-> 1488
/*    */     //   #69	-> 1491
/*    */     //   #70	-> 1517
/*    */     //   #71	-> 1520
/*    */     //   #72	-> 1547
/*    */     //   #73	-> 1571
/*    */     //   #74	-> 1581
/*    */     //   #75	-> 1584
/*    */     //   #76	-> 1587
/*    */     //   #77	-> 1600
/*    */     //   #78	-> 1627
/*    */     //   #79	-> 1630
/*    */     //   #80	-> 1633
/*    */     //   #81	-> 1659
/*    */     //   #82	-> 1669
/*    */     //   #83	-> 1670
/*    */     //   #84	-> 1673
/*    */     //   #85	-> 1682
/*    */     //   #86	-> 1685
/*    */     //   #87	-> 1712
/*    */     //   #88	-> 1715
/*    */     //   #89	-> 1744
/*    */     //   #90	-> 1768
/*    */     //   #91	-> 1778
/*    */     //   #92	-> 1781
/*    */     //   #93	-> 1784
/*    */     //   #94	-> 1797
/*    */     //   #95	-> 1806
/*    */     //   #96	-> 1839
/*    */     //   #97	-> 1847
/*    */     //   #98	-> 1891
/*    */     //   #99	-> 1899
/*    */     //   #100	-> 1914
/*    */     //   #101	-> 1918
/*    */     //   #102	-> 1921
/*    */     //   #103	-> 1936
/*    */     //   #104	-> 1944
/*    */     //   #105	-> 1959
/*    */     //   #106	-> 1963
/*    */     //   #107	-> 1966
/*    */     //   #108	-> 1981
/*    */     //   #109	-> 1989
/*    */     //   #110	-> 2004
/*    */     //   #111	-> 2008
/*    */     //   #112	-> 2011
/*    */     //   #113	-> 2020
/*    */     //   #114	-> 2023
/*    */     //   #115	-> 2026
/*    */     //   #116	-> 2209
/*    */     //   #117	-> 2217
/*    */     //   #118	-> 2234
/*    */     //   #119	-> 2238
/*    */     //   #120	-> 2241
/*    */     //   #121	-> 2255
/*    */     //   #122	-> 2264
/*    */     //   #123	-> 2297
/*    */     //   #124	-> 2303 } public static lg0 dp0(fQ paramfQ, Runnable paramRunnable1, Runnable paramRunnable2) { // Byte code:
/*    */     //   0: new f/lg0
/*    */     //   3: dup
/*    */     //   4: dup
/*    */     //   5: dup2
/*    */     //   6: astore_3
/*    */     //   7: invokespecial <init> : ()V
/*    */     //   10: ldc 'advanced-search-dialog'
/*    */     //   12: invokevirtual Xu : (Ljava/lang/String;)V
/*    */     //   15: new f/g0
/*    */     //   18: dup
/*    */     //   19: aload_3
/*    */     //   20: invokespecial <init> : (Lf/Ip;)V
/*    */     //   23: invokevirtual rK0 : (Lf/U90;)V
/*    */     //   26: new f/cr0
/*    */     //   29: dup
/*    */     //   30: aload_3
/*    */     //   31: invokespecial <init> : (Lf/Ip;)V
/*    */     //   34: invokevirtual WN : (Lf/U90;)V
/*    */     //   37: new f/Un
/*    */     //   40: dup
/*    */     //   41: dup
/*    */     //   42: astore #4
/*    */     //   44: sipush #8112
/*    */     //   47: invokestatic OH0 : (I)Ljava/lang/String;
/*    */     //   50: invokespecial <init> : (Ljava/lang/String;)V
/*    */     //   53: ldc_w 'label-button-small2-centered'
/*    */     //   56: invokevirtual Xu : (Ljava/lang/String;)V
/*    */     //   59: new f/Un
/*    */     //   62: dup
/*    */     //   63: dup
/*    */     //   64: astore #5
/*    */     //   66: sipush #8008
/*    */     //   69: invokestatic OH0 : (I)Ljava/lang/String;
/*    */     //   72: invokespecial <init> : (Ljava/lang/String;)V
/*    */     //   75: ldc_w 'label-button-small2-centered'
/*    */     //   78: invokevirtual Xu : (Ljava/lang/String;)V
/*    */     //   81: new f/dQ
/*    */     //   84: dup
/*    */     //   85: dup2
/*    */     //   86: astore #6
/*    */     //   88: sipush #8113
/*    */     //   91: invokestatic OH0 : (I)Ljava/lang/String;
/*    */     //   94: astore #7
/*    */     //   96: invokespecial <init> : ()V
/*    */     //   99: aload #7
/*    */     //   101: invokevirtual E1 : (Ljava/lang/String;)V
/*    */     //   104: ldc 'label-title-medium2'
/*    */     //   106: invokevirtual Xu : (Ljava/lang/String;)V
/*    */     //   109: new f/zT
/*    */     //   112: dup
/*    */     //   113: astore #7
/*    */     //   115: bipush #9
/*    */     //   117: iconst_0
/*    */     //   118: iconst_0
/*    */     //   119: aload_0
/*    */     //   120: invokestatic Cz : (IIILf/fQ;)I
/*    */     //   123: istore #8
/*    */     //   125: iconst_0
/*    */     //   126: ldc 2147483647
/*    */     //   128: iload #8
/*    */     //   130: invokespecial <init> : (III)V
/*    */     //   133: new f/Rm
/*    */     //   136: dup
/*    */     //   137: dup
/*    */     //   138: dup2
/*    */     //   139: astore #8
/*    */     //   141: aload #7
/*    */     //   143: invokespecial <init> : (Lf/zT;)V
/*    */     //   146: ldc '$'
/*    */     //   148: putfield W70 : Ljava/lang/String;
/*    */     //   151: invokevirtual t90 : ()V
/*    */     //   154: invokevirtual Jc : ()V
/*    */     //   157: new f/dQ
/*    */     //   160: dup
/*    */     //   161: dup2
/*    */     //   162: astore #7
/*    */     //   164: sipush #8114
/*    */     //   167: invokestatic OH0 : (I)Ljava/lang/String;
/*    */     //   170: astore #9
/*    */     //   172: invokespecial <init> : ()V
/*    */     //   175: aload #9
/*    */     //   177: invokevirtual E1 : (Ljava/lang/String;)V
/*    */     //   180: ldc 'label-title-medium2'
/*    */     //   182: invokevirtual Xu : (Ljava/lang/String;)V
/*    */     //   185: new f/zT
/*    */     //   188: dup
/*    */     //   189: astore #9
/*    */     //   191: bipush #10
/*    */     //   193: iconst_0
/*    */     //   194: iconst_0
/*    */     //   195: aload_0
/*    */     //   196: invokestatic Cz : (IIILf/fQ;)I
/*    */     //   199: istore #10
/*    */     //   201: iconst_0
/*    */     //   202: ldc 2147483647
/*    */     //   204: iload #10
/*    */     //   206: invokespecial <init> : (III)V
/*    */     //   209: new f/Rm
/*    */     //   212: dup
/*    */     //   213: dup
/*    */     //   214: dup2
/*    */     //   215: astore #10
/*    */     //   217: aload #9
/*    */     //   219: invokespecial <init> : (Lf/zT;)V
/*    */     //   222: ldc '$'
/*    */     //   224: putfield W70 : Ljava/lang/String;
/*    */     //   227: invokevirtual t90 : ()V
/*    */     //   230: invokevirtual Jc : ()V
/*    */     //   233: new f/dQ
/*    */     //   236: dup
/*    */     //   237: dup2
/*    */     //   238: astore #9
/*    */     //   240: sipush #8120
/*    */     //   243: invokestatic OH0 : (I)Ljava/lang/String;
/*    */     //   246: astore #11
/*    */     //   248: invokespecial <init> : ()V
/*    */     //   251: aload #11
/*    */     //   253: invokevirtual E1 : (Ljava/lang/String;)V
/*    */     //   256: ldc 'label-title-medium2'
/*    */     //   258: invokevirtual Xu : (Ljava/lang/String;)V
/*    */     //   261: getstatic f/Hu0.It : [Lf/Hu0;
/*    */     //   264: dup
/*    */     //   265: dup
/*    */     //   266: astore #11
/*    */     //   268: arraylength
/*    */     //   269: iconst_1
/*    */     //   270: iadd
/*    */     //   271: anewarray java/lang/String
/*    */     //   274: dup
/*    */     //   275: astore #12
/*    */     //   277: iconst_0
/*    */     //   278: ldc '--'
/*    */     //   280: aastore
/*    */     //   281: arraylength
/*    */     //   282: istore #13
/*    */     //   284: iconst_0
/*    */     //   285: istore #14
/*    */     //   287: iload #14
/*    */     //   289: iload #13
/*    */     //   291: if_icmpge -> 325
/*    */     //   294: aload #12
/*    */     //   296: aload #11
/*    */     //   298: iload #14
/*    */     //   300: aaload
/*    */     //   301: dup
/*    */     //   302: astore #15
/*    */     //   304: getfield od : B
/*    */     //   307: aload #15
/*    */     //   309: getfield jC0 : I
/*    */     //   312: invokestatic OH0 : (I)Ljava/lang/String;
/*    */     //   315: invokevirtual toUpperCase : ()Ljava/lang/String;
/*    */     //   318: aastore
/*    */     //   319: iinc #14, 1
/*    */     //   322: goto -> 287
/*    */     //   325: new f/OZ
/*    */     //   328: dup
/*    */     //   329: astore #11
/*    */     //   331: aload #12
/*    */     //   333: invokespecial <init> : ([Ljava/lang/Object;)V
/*    */     //   336: new f/W1
/*    */     //   339: dup
/*    */     //   340: dup
/*    */     //   341: astore #12
/*    */     //   343: aload #11
/*    */     //   345: aload #12
/*    */     //   347: invokespecial <init> : ()V
/*    */     //   350: invokevirtual rk0 : (Lf/cQ;)V
/*    */     //   353: bipush #32
/*    */     //   355: iconst_0
/*    */     //   356: iconst_0
/*    */     //   357: aload_0
/*    */     //   358: invokestatic Cz : (IIILf/fQ;)I
/*    */     //   361: invokevirtual Z30 : (I)V
/*    */     //   364: new f/dQ
/*    */     //   367: dup
/*    */     //   368: dup2
/*    */     //   369: astore #11
/*    */     //   371: sipush #8121
/*    */     //   374: invokestatic OH0 : (I)Ljava/lang/String;
/*    */     //   377: astore #13
/*    */     //   379: invokespecial <init> : ()V
/*    */     //   382: aload #13
/*    */     //   384: invokevirtual E1 : (Ljava/lang/String;)V
/*    */     //   387: ldc 'label-title-medium2'
/*    */     //   389: invokevirtual Xu : (Ljava/lang/String;)V
/*    */     //   392: getstatic f/Vp0.Jo : [Lf/Vp0;
/*    */     //   395: dup
/*    */     //   396: dup
/*    */     //   397: astore #13
/*    */     //   399: arraylength
/*    */     //   400: iconst_1
/*    */     //   401: isub
/*    */     //   402: anewarray java/lang/String
/*    */     //   405: dup
/*    */     //   406: astore #14
/*    */     //   408: iconst_0
/*    */     //   409: ldc '--'
/*    */     //   411: aastore
/*    */     //   412: arraylength
/*    */     //   413: istore #15
/*    */     //   415: iconst_0
/*    */     //   416: istore #16
/*    */     //   418: iload #16
/*    */     //   420: iload #15
/*    */     //   422: if_icmpge -> 477
/*    */     //   425: aload #13
/*    */     //   427: iload #16
/*    */     //   429: aaload
/*    */     //   430: dup
/*    */     //   431: astore #17
/*    */     //   433: getstatic f/Vp0.Rj : Lf/Vp0;
/*    */     //   436: if_acmpeq -> 471
/*    */     //   439: aload #17
/*    */     //   441: getstatic f/Vp0.c6 : Lf/Vp0;
/*    */     //   444: if_acmpne -> 450
/*    */     //   447: goto -> 471
/*    */     //   450: aload #14
/*    */     //   452: aload #17
/*    */     //   454: getfield gw0 : B
/*    */     //   457: iconst_1
/*    */     //   458: iadd
/*    */     //   459: aload #17
/*    */     //   461: invokevirtual V00 : ()I
/*    */     //   464: invokestatic OH0 : (I)Ljava/lang/String;
/*    */     //   467: invokevirtual toUpperCase : ()Ljava/lang/String;
/*    */     //   470: aastore
/*    */     //   471: iinc #16, 1
/*    */     //   474: goto -> 418
/*    */     //   477: aload_3
/*    */     //   478: aload #4
/*    */     //   480: aload_0
/*    */     //   481: aload #8
/*    */     //   483: aload #5
/*    */     //   485: aload_0
/*    */     //   486: aload_1
/*    */     //   487: new f/OZ
/*    */     //   490: dup
/*    */     //   491: astore_1
/*    */     //   492: aload #14
/*    */     //   494: invokespecial <init> : ([Ljava/lang/Object;)V
/*    */     //   497: new f/W1
/*    */     //   500: dup
/*    */     //   501: dup
/*    */     //   502: astore #13
/*    */     //   504: aload_1
/*    */     //   505: aload #13
/*    */     //   507: invokespecial <init> : ()V
/*    */     //   510: invokevirtual rk0 : (Lf/cQ;)V
/*    */     //   513: bipush #33
/*    */     //   515: iconst_0
/*    */     //   516: iconst_0
/*    */     //   517: aload_0
/*    */     //   518: invokestatic Cz : (IIILf/fQ;)I
/*    */     //   521: invokevirtual Z30 : (I)V
/*    */     //   524: new f/dQ
/*    */     //   527: dup
/*    */     //   528: dup2
/*    */     //   529: astore_0
/*    */     //   530: sipush #8091
/*    */     //   533: invokestatic OH0 : (I)Ljava/lang/String;
/*    */     //   536: astore_1
/*    */     //   537: invokespecial <init> : ()V
/*    */     //   540: aload_1
/*    */     //   541: invokevirtual E1 : (Ljava/lang/String;)V
/*    */     //   544: ldc 'label-title-medium2'
/*    */     //   546: invokevirtual Xu : (Ljava/lang/String;)V
/*    */     //   549: new f/ge0
/*    */     //   552: dup
/*    */     //   553: dup
/*    */     //   554: astore_1
/*    */     //   555: invokespecial <init> : ()V
/*    */     //   558: getfield TG0 : Lf/protected;
/*    */     //   561: iconst_0
/*    */     //   562: invokevirtual Fx0 : (Z)V
/*    */     //   565: <illegal opcode> run : (Lf/fQ;Ljava/lang/Runnable;)Ljava/lang/Runnable;
/*    */     //   570: invokevirtual tW : (Ljava/lang/Runnable;)V
/*    */     //   573: aload #10
/*    */     //   575: aload_1
/*    */     //   576: aload #12
/*    */     //   578: aload #13
/*    */     //   580: aload_2
/*    */     //   581: <illegal opcode> run : (Lf/fQ;Lf/Rm;Lf/Rm;Lf/ge0;Lf/W1;Lf/W1;Ljava/lang/Runnable;)Ljava/lang/Runnable;
/*    */     //   586: invokevirtual tW : (Ljava/lang/Runnable;)V
/*    */     //   589: getfield Xz0 : Lf/U90;
/*    */     //   592: astore_2
/*    */     //   593: new f/cr0
/*    */     //   596: dup
/*    */     //   597: astore #14
/*    */     //   599: aload_3
/*    */     //   600: invokespecial <init> : (Lf/Ip;)V
/*    */     //   603: invokestatic XU : ()Z
/*    */     //   606: ifne -> 612
/*    */     //   609: goto -> 635
/*    */     //   612: aload #14
/*    */     //   614: new f/rb
/*    */     //   617: dup
/*    */     //   618: astore #15
/*    */     //   620: aload_3
/*    */     //   621: iconst_0
/*    */     //   622: iconst_0
/*    */     //   623: sipush #32767
/*    */     //   626: iconst_0
/*    */     //   627: invokespecial <init> : (Lf/Ip;IIIZ)V
/*    */     //   630: aload #15
/*    */     //   632: invokevirtual G90 : (Lf/eD0;)V
/*    */     //   635: aload_3
/*    */     //   636: dup
/*    */     //   637: dup2
/*    */     //   638: dup2
/*    */     //   639: dup2
/*    */     //   640: aload_2
/*    */     //   641: aload #14
/*    */     //   643: aload #4
/*    */     //   645: invokevirtual Ya : (Lf/JG0;)Lf/U90;
/*    */     //   648: invokevirtual Em0 : ()Lf/U90;
/*    */     //   651: aload #5
/*    */     //   653: invokevirtual Ya : (Lf/JG0;)Lf/U90;
/*    */     //   656: invokevirtual ee0 : (Lf/U90;)Lf/U90;
/*    */     //   659: pop
/*    */     //   660: getfield o30 : Lf/U90;
/*    */     //   663: aload_3
/*    */     //   664: iconst_2
/*    */     //   665: anewarray f/JG0
/*    */     //   668: dup
/*    */     //   669: dup
/*    */     //   670: iconst_0
/*    */     //   671: aload #4
/*    */     //   673: aastore
/*    */     //   674: iconst_1
/*    */     //   675: aload #5
/*    */     //   677: aastore
/*    */     //   678: invokevirtual AUX : ([Lf/JG0;)Lf/U90;
/*    */     //   681: invokevirtual ee0 : (Lf/U90;)Lf/U90;
/*    */     //   684: pop
/*    */     //   685: getfield Xz0 : Lf/U90;
/*    */     //   688: aload_3
/*    */     //   689: iconst_4
/*    */     //   690: anewarray f/JG0
/*    */     //   693: dup
/*    */     //   694: dup
/*    */     //   695: dup2
/*    */     //   696: iconst_0
/*    */     //   697: aload #6
/*    */     //   699: aastore
/*    */     //   700: iconst_1
/*    */     //   701: aload #8
/*    */     //   703: aastore
/*    */     //   704: iconst_2
/*    */     //   705: aload #7
/*    */     //   707: aastore
/*    */     //   708: iconst_3
/*    */     //   709: aload #10
/*    */     //   711: aastore
/*    */     //   712: invokevirtual vo0 : ([Lf/JG0;)Lf/U90;
/*    */     //   715: invokevirtual ee0 : (Lf/U90;)Lf/U90;
/*    */     //   718: pop
/*    */     //   719: getfield o30 : Lf/U90;
/*    */     //   722: aload_3
/*    */     //   723: iconst_4
/*    */     //   724: anewarray f/JG0
/*    */     //   727: dup
/*    */     //   728: dup
/*    */     //   729: dup2
/*    */     //   730: iconst_0
/*    */     //   731: aload #6
/*    */     //   733: aastore
/*    */     //   734: iconst_1
/*    */     //   735: aload #8
/*    */     //   737: aastore
/*    */     //   738: iconst_2
/*    */     //   739: aload #7
/*    */     //   741: aastore
/*    */     //   742: iconst_3
/*    */     //   743: aload #10
/*    */     //   745: aastore
/*    */     //   746: invokevirtual AUX : ([Lf/JG0;)Lf/U90;
/*    */     //   749: invokevirtual ee0 : (Lf/U90;)Lf/U90;
/*    */     //   752: pop
/*    */     //   753: getfield Xz0 : Lf/U90;
/*    */     //   756: aload_3
/*    */     //   757: iconst_4
/*    */     //   758: anewarray f/JG0
/*    */     //   761: dup
/*    */     //   762: dup
/*    */     //   763: dup2
/*    */     //   764: iconst_0
/*    */     //   765: aload #9
/*    */     //   767: aastore
/*    */     //   768: iconst_1
/*    */     //   769: aload #12
/*    */     //   771: aastore
/*    */     //   772: iconst_2
/*    */     //   773: aload #11
/*    */     //   775: aastore
/*    */     //   776: iconst_3
/*    */     //   777: aload #13
/*    */     //   779: aastore
/*    */     //   780: invokevirtual vo0 : ([Lf/JG0;)Lf/U90;
/*    */     //   783: invokevirtual ee0 : (Lf/U90;)Lf/U90;
/*    */     //   786: pop
/*    */     //   787: getfield o30 : Lf/U90;
/*    */     //   790: aload_3
/*    */     //   791: iconst_4
/*    */     //   792: anewarray f/JG0
/*    */     //   795: dup
/*    */     //   796: dup
/*    */     //   797: dup2
/*    */     //   798: iconst_0
/*    */     //   799: aload #9
/*    */     //   801: aastore
/*    */     //   802: iconst_1
/*    */     //   803: aload #12
/*    */     //   805: aastore
/*    */     //   806: iconst_2
/*    */     //   807: aload #11
/*    */     //   809: aastore
/*    */     //   810: iconst_3
/*    */     //   811: aload #13
/*    */     //   813: aastore
/*    */     //   814: invokevirtual AUX : ([Lf/JG0;)Lf/U90;
/*    */     //   817: invokevirtual ee0 : (Lf/U90;)Lf/U90;
/*    */     //   820: pop
/*    */     //   821: getfield Xz0 : Lf/U90;
/*    */     //   824: aload_3
/*    */     //   825: iconst_2
/*    */     //   826: anewarray f/JG0
/*    */     //   829: dup
/*    */     //   830: dup
/*    */     //   831: iconst_0
/*    */     //   832: aload_0
/*    */     //   833: aastore
/*    */     //   834: iconst_1
/*    */     //   835: aload_1
/*    */     //   836: aastore
/*    */     //   837: invokevirtual vo0 : ([Lf/JG0;)Lf/U90;
/*    */     //   840: invokevirtual Em0 : ()Lf/U90;
/*    */     //   843: invokevirtual ee0 : (Lf/U90;)Lf/U90;
/*    */     //   846: pop
/*    */     //   847: getfield o30 : Lf/U90;
/*    */     //   850: aload_3
/*    */     //   851: iconst_2
/*    */     //   852: anewarray f/JG0
/*    */     //   855: dup
/*    */     //   856: dup
/*    */     //   857: iconst_0
/*    */     //   858: aload_0
/*    */     //   859: aastore
/*    */     //   860: iconst_1
/*    */     //   861: aload_1
/*    */     //   862: aastore
/*    */     //   863: invokevirtual AUX : ([Lf/JG0;)Lf/U90;
/*    */     //   866: invokevirtual ee0 : (Lf/U90;)Lf/U90;
/*    */     //   869: pop
/*    */     //   870: areturn
/*    */     // Line number table:
/*    */     //   Java source line number -> byte code offset
/*    */     //   #1	-> 0
/*    */     //   #2	-> 10
/*    */     //   #3	-> 15
/*    */     //   #4	-> 23
/*    */     //   #5	-> 26
/*    */     //   #6	-> 34
/*    */     //   #7	-> 96
/*    */     //   #8	-> 104
/*    */     //   #9	-> 146
/*    */     //   #10	-> 154
/*    */     //   #11	-> 172
/*    */     //   #12	-> 180
/*    */     //   #13	-> 222
/*    */     //   #14	-> 230
/*    */     //   #15	-> 248
/*    */     //   #16	-> 256
/*    */     //   #17	-> 304
/*    */     //   #18	-> 309
/*    */     //   #19	-> 312
/*    */     //   #20	-> 347
/*    */     //   #21	-> 358
/*    */     //   #22	-> 379
/*    */     //   #23	-> 387
/*    */     //   #24	-> 454
/*    */     //   #25	-> 461
/*    */     //   #26	-> 507
/*    */     //   #27	-> 518
/*    */     //   #28	-> 537
/*    */     //   #29	-> 544
/*    */     //   #30	-> 558
/*    */     //   #31	-> 562
/*    */     //   #32	-> 565
/*    */     //   #33	-> 589
/*    */     //   #34	-> 593
/*    */     //   #35	-> 603
/*    */     //   #36	-> 614
/*    */     //   #37	-> 645
/*    */     //   #38	-> 660
/*    */     //   #39	-> 665
/*    */     //   #40	-> 685
/*    */     //   #41	-> 690
/*    */     //   #42	-> 719
/*    */     //   #43	-> 724
/*    */     //   #44	-> 753
/*    */     //   #45	-> 758
/*    */     //   #46	-> 787
/*    */     //   #47	-> 792
/*    */     //   #48	-> 821
/*    */     //   #49	-> 826
/*    */     //   #50	-> 847
/*  1 */     //   #51	-> 852 } public static int Cz(int paramInt1, int paramInt2, int paramInt3, fQ paramfQ) { for (Hc0 hc0 = paramfQ.r30(); hc0.hasNext();) { if ((sK = (sK)hc0.next()).ak == paramInt1)
/*  2 */         return sK.a7() + paramInt2;  }  return paramInt3; } public static void O6(fQ paramfQ, Rm paramRm1, Rm paramRm2, ge0 paramge0, W1 paramW11, W1 paramW12, Runnable paramRunnable) { paramfQ.clear(); int i; if ((i = paramRm1.T8) > 0) { ua ua; this(i, (byte)9); paramfQ.Com3(ua); }  if (paramRm2
/*  3 */       .T8 > 0 || paramge0
/*  4 */       .TG0
/*  5 */       .nm0()) {
/*  6 */       ua ua; if ((i = paramRm2.T8) <= 0)
/*    */       
/*    */       { 
/*  9 */         i = km.u4.Lz.Ii; } else if (paramge0
/* 10 */         .TG0
/* 11 */         .nm0())
/*    */       
/*    */       { 
/*    */         
/* 15 */         i = Math.min(i, km.u4.Lz.Ii); }  this(i, (byte)10); paramfQ.Com3(ua);
/*    */     } 
/* 17 */     if ((i = paramW11.Wa0.go) > 0) paramfQ
/* 18 */         .Com3(new n20((byte)i));
/*    */     
/* 20 */     if ((i = paramW12.Wa0.go) > 0) paramfQ
/* 21 */         .Com3(new Lg((byte)(i - 1)));  paramRunnable.run(); }
/*    */   public static void Dr(fQ paramfQ, W1 paramW11, boolean paramBoolean, Rm paramRm1, Rm paramRm2, ge0 paramge01, W1 paramW12, W1 paramW13, W1 paramW14, W1 paramW15, rh paramrh1, of paramof1, W1 paramW16, W1 paramW17, Rm[] paramArrayOfRm, W1 paramW18, rh paramrh2, rh[][] paramArrayOfrh1, rh[][] paramArrayOfrh2, of paramof2, List paramList, int[] paramArrayOfint, ge0 paramge02, ge0 paramge03, Runnable paramRunnable) { // Byte code:
/*    */     //   0: aload_1
/*    */     //   1: aload_0
/*    */     //   2: invokevirtual clear : ()V
/*    */     //   5: getfield Wa0 : Lf/A60;
/*    */     //   8: getfield go : I
/*    */     //   11: dup
/*    */     //   12: istore_1
/*    */     //   13: ifle -> 29
/*    */     //   16: aload_0
/*    */     //   17: new f/N8
/*    */     //   20: dup
/*    */     //   21: iload_1
/*    */     //   22: i2b
/*    */     //   23: invokespecial <init> : (B)V
/*    */     //   26: invokevirtual Com3 : (Ljava/lang/Object;)V
/*    */     //   29: iload_2
/*    */     //   30: ifeq -> 58
/*    */     //   33: aload_3
/*    */     //   34: getfield T8 : I
/*    */     //   37: dup
/*    */     //   38: istore_1
/*    */     //   39: ifle -> 58
/*    */     //   42: aload_0
/*    */     //   43: new f/ua
/*    */     //   46: dup
/*    */     //   47: astore_3
/*    */     //   48: iload_1
/*    */     //   49: bipush #9
/*    */     //   51: invokespecial <init> : (IB)V
/*    */     //   54: aload_3
/*    */     //   55: invokevirtual Com3 : (Ljava/lang/Object;)V
/*    */     //   58: iload_2
/*    */     //   59: ifeq -> 145
/*    */     //   62: aload #4
/*    */     //   64: getfield T8 : I
/*    */     //   67: ifgt -> 81
/*    */     //   70: aload #5
/*    */     //   72: getfield TG0 : Lf/protected;
/*    */     //   75: invokevirtual nm0 : ()Z
/*    */     //   78: ifeq -> 145
/*    */     //   81: aload #4
/*    */     //   83: getfield T8 : I
/*    */     //   86: dup
/*    */     //   87: istore_1
/*    */     //   88: ifgt -> 104
/*    */     //   91: getstatic f/km.u4 : Lf/R8;
/*    */     //   94: getfield Lz : Lf/fH0;
/*    */     //   97: getfield Ii : I
/*    */     //   100: istore_1
/*    */     //   101: goto -> 129
/*    */     //   104: aload #5
/*    */     //   106: getfield TG0 : Lf/protected;
/*    */     //   109: invokevirtual nm0 : ()Z
/*    */     //   112: ifeq -> 129
/*    */     //   115: iload_1
/*    */     //   116: getstatic f/km.u4 : Lf/R8;
/*    */     //   119: getfield Lz : Lf/fH0;
/*    */     //   122: getfield Ii : I
/*    */     //   125: invokestatic min : (II)I
/*    */     //   128: istore_1
/*    */     //   129: aload_0
/*    */     //   130: new f/ua
/*    */     //   133: dup
/*    */     //   134: astore_2
/*    */     //   135: iload_1
/*    */     //   136: bipush #10
/*    */     //   138: invokespecial <init> : (IB)V
/*    */     //   141: aload_2
/*    */     //   142: invokevirtual Com3 : (Ljava/lang/Object;)V
/*    */     //   145: aload #6
/*    */     //   147: getfield Wa0 : Lf/A60;
/*    */     //   150: getfield go : I
/*    */     //   153: dup
/*    */     //   154: istore_1
/*    */     //   155: ifle -> 173
/*    */     //   158: aload_0
/*    */     //   159: new f/u6
/*    */     //   162: dup
/*    */     //   163: iload_1
/*    */     //   164: iconst_1
/*    */     //   165: isub
/*    */     //   166: i2b
/*    */     //   167: invokespecial <init> : (B)V
/*    */     //   170: invokevirtual Com3 : (Ljava/lang/Object;)V
/*    */     //   173: aload #7
/*    */     //   175: getfield Wa0 : Lf/A60;
/*    */     //   178: getfield go : I
/*    */     //   181: dup
/*    */     //   182: istore_1
/*    */     //   183: ifle -> 201
/*    */     //   186: aload_0
/*    */     //   187: new f/E2
/*    */     //   190: dup
/*    */     //   191: iload_1
/*    */     //   192: iconst_1
/*    */     //   193: isub
/*    */     //   194: i2b
/*    */     //   195: invokespecial <init> : (B)V
/*    */     //   198: invokevirtual Com3 : (Ljava/lang/Object;)V
/*    */     //   201: aload #8
/*    */     //   203: getfield Wa0 : Lf/A60;
/*    */     //   206: getfield go : I
/*    */     //   209: dup
/*    */     //   210: istore_1
/*    */     //   211: ifle -> 229
/*    */     //   214: aload_0
/*    */     //   215: new f/Bd
/*    */     //   218: dup
/*    */     //   219: iload_1
/*    */     //   220: iconst_1
/*    */     //   221: isub
/*    */     //   222: i2b
/*    */     //   223: invokespecial <init> : (B)V
/*    */     //   226: invokevirtual Com3 : (Ljava/lang/Object;)V
/*    */     //   229: aload #9
/*    */     //   231: getfield Wa0 : Lf/A60;
/*    */     //   234: getfield go : I
/*    */     //   237: dup
/*    */     //   238: istore_1
/*    */     //   239: ifle -> 257
/*    */     //   242: aload_0
/*    */     //   243: new f/o00
/*    */     //   246: dup
/*    */     //   247: iload_1
/*    */     //   248: iconst_1
/*    */     //   249: isub
/*    */     //   250: i2b
/*    */     //   251: invokespecial <init> : (B)V
/*    */     //   254: invokevirtual Com3 : (Ljava/lang/Object;)V
/*    */     //   257: aload #10
/*    */     //   259: getfield T8 : I
/*    */     //   262: dup
/*    */     //   263: istore_1
/*    */     //   264: ifle -> 281
/*    */     //   267: aload_0
/*    */     //   268: new f/Dz
/*    */     //   271: dup
/*    */     //   272: astore_2
/*    */     //   273: iload_1
/*    */     //   274: invokespecial <init> : (I)V
/*    */     //   277: aload_2
/*    */     //   278: invokevirtual Com3 : (Ljava/lang/Object;)V
/*    */     //   281: aload #11
/*    */     //   283: getfield F2 : Lf/ak0;
/*    */     //   286: getfield PH0 : Ljava/lang/StringBuilder;
/*    */     //   289: invokevirtual toString : ()Ljava/lang/String;
/*    */     //   292: invokevirtual isEmpty : ()Z
/*    */     //   295: ifne -> 454
/*    */     //   298: invokestatic cw : ()Lf/yk0;
/*    */     //   301: dup
/*    */     //   302: aload #11
/*    */     //   304: getfield F2 : Lf/ak0;
/*    */     //   307: getfield PH0 : Ljava/lang/StringBuilder;
/*    */     //   310: invokevirtual toString : ()Ljava/lang/String;
/*    */     //   313: astore_1
/*    */     //   314: invokevirtual getClass : ()Ljava/lang/Class;
/*    */     //   317: pop
/*    */     //   318: aload_1
/*    */     //   319: invokevirtual toLowerCase : ()Ljava/lang/String;
/*    */     //   322: ldc_w '[-_\s]'
/*    */     //   325: ldc_w ''
/*    */     //   328: invokevirtual replaceAll : (Ljava/lang/String;Ljava/lang/String;)Ljava/lang/String;
/*    */     //   331: astore_1
/*    */     //   332: getfield iu : Lf/qw0;
/*    */     //   335: dup
/*    */     //   336: astore_2
/*    */     //   337: invokevirtual getClass : ()Ljava/lang/Class;
/*    */     //   340: pop
/*    */     //   341: new f/iL
/*    */     //   344: dup
/*    */     //   345: aload_2
/*    */     //   346: invokespecial <init> : (Lf/qw0;)V
/*    */     //   349: invokevirtual iterator : ()Ljava/util/Iterator;
/*    */     //   352: astore_2
/*    */     //   353: aload_2
/*    */     //   354: checkcast f/DA0
/*    */     //   357: invokevirtual hasNext : ()Z
/*    */     //   360: ifeq -> 403
/*    */     //   363: aload_2
/*    */     //   364: checkcast f/Ke
/*    */     //   367: invokevirtual q00 : ()Ljava/lang/Object;
/*    */     //   370: checkcast f/WD
/*    */     //   373: dup
/*    */     //   374: astore_3
/*    */     //   375: getfield iz : I
/*    */     //   378: invokestatic OH0 : (I)Ljava/lang/String;
/*    */     //   381: invokevirtual toLowerCase : ()Ljava/lang/String;
/*    */     //   384: ldc_w '[-_\s]'
/*    */     //   387: ldc_w ''
/*    */     //   390: invokevirtual replaceAll : (Ljava/lang/String;Ljava/lang/String;)Ljava/lang/String;
/*    */     //   393: aload_1
/*    */     //   394: invokevirtual equals : (Ljava/lang/Object;)Z
/*    */     //   397: ifeq -> 353
/*    */     //   400: goto -> 405
/*    */     //   403: aconst_null
/*    */     //   404: astore_3
/*    */     //   405: aload_3
/*    */     //   406: ifnonnull -> 439
/*    */     //   409: aload_0
/*    */     //   410: invokevirtual clear : ()V
/*    */     //   413: getstatic f/js.vu0 : Lf/js;
/*    */     //   416: sipush #8095
/*    */     //   419: aload #11
/*    */     //   421: getfield F2 : Lf/ak0;
/*    */     //   424: getfield PH0 : Ljava/lang/StringBuilder;
/*    */     //   427: invokevirtual toString : ()Ljava/lang/String;
/*    */     //   430: invokestatic Go : (ILjava/lang/String;)Ljava/lang/String;
/*    */     //   433: iconst_m1
/*    */     //   434: swap
/*    */     //   435: invokevirtual Pu : (ILjava/lang/String;)V
/*    */     //   438: return
/*    */     //   439: aload_0
/*    */     //   440: new f/JK0
/*    */     //   443: dup
/*    */     //   444: aload_3
/*    */     //   445: getfield HA : S
/*    */     //   448: invokespecial <init> : (S)V
/*    */     //   451: invokevirtual Com3 : (Ljava/lang/Object;)V
/*    */     //   454: aload #12
/*    */     //   456: getfield Wa0 : Lf/A60;
/*    */     //   459: getfield go : I
/*    */     //   462: dup
/*    */     //   463: istore_1
/*    */     //   464: ifle -> 490
/*    */     //   467: aload_0
/*    */     //   468: getstatic f/DO.HB0 : [Lf/DO;
/*    */     //   471: iload_1
/*    */     //   472: iconst_1
/*    */     //   473: isub
/*    */     //   474: aaload
/*    */     //   475: astore_1
/*    */     //   476: new f/Tj0
/*    */     //   479: dup
/*    */     //   480: aload_1
/*    */     //   481: getfield y1 : B
/*    */     //   484: invokespecial <init> : (B)V
/*    */     //   487: invokevirtual Com3 : (Ljava/lang/Object;)V
/*    */     //   490: aload #13
/*    */     //   492: invokevirtual WW : ()Ljava/lang/Object;
/*    */     //   495: checkcast f/mA
/*    */     //   498: dup
/*    */     //   499: astore_1
/*    */     //   500: ifnull -> 517
/*    */     //   503: aload_0
/*    */     //   504: new f/COM1
/*    */     //   507: dup
/*    */     //   508: astore_2
/*    */     //   509: aload_1
/*    */     //   510: invokespecial <init> : (Lf/mA;)V
/*    */     //   513: aload_2
/*    */     //   514: invokevirtual Com3 : (Ljava/lang/Object;)V
/*    */     //   517: aload #14
/*    */     //   519: iconst_0
/*    */     //   520: aaload
/*    */     //   521: getfield T8 : I
/*    */     //   524: dup
/*    */     //   525: istore_1
/*    */     //   526: iconst_1
/*    */     //   527: if_icmple -> 543
/*    */     //   530: aload_0
/*    */     //   531: new f/extends
/*    */     //   534: dup
/*    */     //   535: iload_1
/*    */     //   536: i2b
/*    */     //   537: invokespecial <init> : (B)V
/*    */     //   540: invokevirtual Com3 : (Ljava/lang/Object;)V
/*    */     //   543: aload #14
/*    */     //   545: iconst_1
/*    */     //   546: aaload
/*    */     //   547: getfield T8 : I
/*    */     //   550: dup
/*    */     //   551: istore_1
/*    */     //   552: bipush #100
/*    */     //   554: if_icmpge -> 570
/*    */     //   557: aload_0
/*    */     //   558: new f/Yt0
/*    */     //   561: dup
/*    */     //   562: iload_1
/*    */     //   563: i2b
/*    */     //   564: invokespecial <init> : (B)V
/*    */     //   567: invokevirtual Com3 : (Ljava/lang/Object;)V
/*    */     //   570: aload #15
/*    */     //   572: getfield Wa0 : Lf/A60;
/*    */     //   575: getfield go : I
/*    */     //   578: dup
/*    */     //   579: istore_1
/*    */     //   580: ifle -> 596
/*    */     //   583: aload_0
/*    */     //   584: new f/eH
/*    */     //   587: dup
/*    */     //   588: iload_1
/*    */     //   589: i2b
/*    */     //   590: invokespecial <init> : (B)V
/*    */     //   593: invokevirtual Com3 : (Ljava/lang/Object;)V
/*    */     //   596: getstatic f/hR.Tm0 : [Lf/hR;
/*    */     //   599: dup
/*    */     //   600: astore_1
/*    */     //   601: arraylength
/*    */     //   602: istore_2
/*    */     //   603: iconst_0
/*    */     //   604: istore_3
/*    */     //   605: iload_3
/*    */     //   606: iload_2
/*    */     //   607: if_icmpge -> 878
/*    */     //   610: aload_1
/*    */     //   611: iload_3
/*    */     //   612: aaload
/*    */     //   613: dup
/*    */     //   614: astore #4
/*    */     //   616: getfield NT : Z
/*    */     //   619: ifeq -> 625
/*    */     //   622: goto -> 872
/*    */     //   625: iconst_0
/*    */     //   626: istore #5
/*    */     //   628: iload #5
/*    */     //   630: iconst_2
/*    */     //   631: if_icmpge -> 872
/*    */     //   634: aload #16
/*    */     //   636: getfield T8 : I
/*    */     //   639: ifne -> 753
/*    */     //   642: iload #5
/*    */     //   644: aload #17
/*    */     //   646: aload #4
/*    */     //   648: getfield dL : B
/*    */     //   651: aaload
/*    */     //   652: iload #5
/*    */     //   654: aaload
/*    */     //   655: getfield T8 : I
/*    */     //   658: istore #6
/*    */     //   660: ifne -> 669
/*    */     //   663: iconst_0
/*    */     //   664: istore #7
/*    */     //   666: goto -> 673
/*    */     //   669: bipush #31
/*    */     //   671: istore #7
/*    */     //   673: iload #5
/*    */     //   675: iload #6
/*    */     //   677: iload #7
/*    */     //   679: invokestatic compare : (II)I
/*    */     //   682: istore #6
/*    */     //   684: ifne -> 693
/*    */     //   687: iconst_1
/*    */     //   688: istore #7
/*    */     //   690: goto -> 696
/*    */     //   693: iconst_m1
/*    */     //   694: istore #7
/*    */     //   696: iload #6
/*    */     //   698: iload #7
/*    */     //   700: if_icmpne -> 753
/*    */     //   703: iload #5
/*    */     //   705: new f/S80
/*    */     //   708: astore #6
/*    */     //   710: ifne -> 719
/*    */     //   713: iconst_5
/*    */     //   714: istore #7
/*    */     //   716: goto -> 723
/*    */     //   719: bipush #6
/*    */     //   721: istore #7
/*    */     //   723: aload_0
/*    */     //   724: aload #6
/*    */     //   726: dup
/*    */     //   727: iload #7
/*    */     //   729: aload #17
/*    */     //   731: aload #4
/*    */     //   733: getfield dL : B
/*    */     //   736: aaload
/*    */     //   737: iload #5
/*    */     //   739: aaload
/*    */     //   740: getfield T8 : I
/*    */     //   743: i2s
/*    */     //   744: aload #4
/*    */     //   746: swap
/*    */     //   747: invokespecial <init> : (BLf/hR;S)V
/*    */     //   750: invokevirtual Com3 : (Ljava/lang/Object;)V
/*    */     //   753: iload #5
/*    */     //   755: aload #18
/*    */     //   757: aload #4
/*    */     //   759: getfield dL : B
/*    */     //   762: aaload
/*    */     //   763: iload #5
/*    */     //   765: aaload
/*    */     //   766: getfield T8 : I
/*    */     //   769: istore #6
/*    */     //   771: ifne -> 780
/*    */     //   774: iconst_0
/*    */     //   775: istore #7
/*    */     //   777: goto -> 785
/*    */     //   780: sipush #252
/*    */     //   783: istore #7
/*    */     //   785: iload #5
/*    */     //   787: iload #6
/*    */     //   789: iload #7
/*    */     //   791: invokestatic compare : (II)I
/*    */     //   794: istore #6
/*    */     //   796: ifne -> 805
/*    */     //   799: iconst_1
/*    */     //   800: istore #7
/*    */     //   802: goto -> 808
/*    */     //   805: iconst_m1
/*    */     //   806: istore #7
/*    */     //   808: iload #6
/*    */     //   810: iload #7
/*    */     //   812: if_icmpne -> 866
/*    */     //   815: iload #5
/*    */     //   817: new f/S80
/*    */     //   820: astore #6
/*    */     //   822: ifne -> 832
/*    */     //   825: bipush #17
/*    */     //   827: istore #7
/*    */     //   829: goto -> 836
/*    */     //   832: bipush #18
/*    */     //   834: istore #7
/*    */     //   836: aload_0
/*    */     //   837: aload #6
/*    */     //   839: dup
/*    */     //   840: iload #7
/*    */     //   842: aload #18
/*    */     //   844: aload #4
/*    */     //   846: getfield dL : B
/*    */     //   849: aaload
/*    */     //   850: iload #5
/*    */     //   852: aaload
/*    */     //   853: getfield T8 : I
/*    */     //   856: i2s
/*    */     //   857: aload #4
/*    */     //   859: swap
/*    */     //   860: invokespecial <init> : (BLf/hR;S)V
/*    */     //   863: invokevirtual Com3 : (Ljava/lang/Object;)V
/*    */     //   866: iinc #5, 1
/*    */     //   869: goto -> 628
/*    */     //   872: iinc #3, 1
/*    */     //   875: goto -> 605
/*    */     //   878: aload #16
/*    */     //   880: getfield T8 : I
/*    */     //   883: ifle -> 1050
/*    */     //   886: new java/util/ArrayList
/*    */     //   889: dup
/*    */     //   890: astore_1
/*    */     //   891: invokespecial <init> : ()V
/*    */     //   894: getstatic f/hR.Tm0 : [Lf/hR;
/*    */     //   897: dup
/*    */     //   898: astore_2
/*    */     //   899: arraylength
/*    */     //   900: istore_3
/*    */     //   901: iconst_0
/*    */     //   902: istore #4
/*    */     //   904: iload #4
/*    */     //   906: iload_3
/*    */     //   907: if_icmpge -> 1022
/*    */     //   910: aload_2
/*    */     //   911: iload #4
/*    */     //   913: aaload
/*    */     //   914: dup
/*    */     //   915: astore #5
/*    */     //   917: getfield NT : Z
/*    */     //   920: ifeq -> 926
/*    */     //   923: goto -> 1016
/*    */     //   926: aload #17
/*    */     //   928: aload #5
/*    */     //   930: getfield dL : B
/*    */     //   933: aaload
/*    */     //   934: dup
/*    */     //   935: astore #6
/*    */     //   937: iconst_0
/*    */     //   938: aaload
/*    */     //   939: getfield T8 : I
/*    */     //   942: dup
/*    */     //   943: istore #7
/*    */     //   945: ifgt -> 960
/*    */     //   948: aload #6
/*    */     //   950: iconst_1
/*    */     //   951: aaload
/*    */     //   952: getfield T8 : I
/*    */     //   955: bipush #31
/*    */     //   957: if_icmpge -> 1016
/*    */     //   960: aload_1
/*    */     //   961: dup
/*    */     //   962: new f/S80
/*    */     //   965: dup
/*    */     //   966: iload #7
/*    */     //   968: i2s
/*    */     //   969: istore #6
/*    */     //   971: iconst_5
/*    */     //   972: aload #5
/*    */     //   974: iload #6
/*    */     //   976: invokespecial <init> : (BLf/hR;S)V
/*    */     //   979: invokevirtual add : (Ljava/lang/Object;)Z
/*    */     //   982: pop
/*    */     //   983: new f/S80
/*    */     //   986: dup
/*    */     //   987: aload #17
/*    */     //   989: aload #5
/*    */     //   991: getfield dL : B
/*    */     //   994: aaload
/*    */     //   995: iconst_1
/*    */     //   996: aaload
/*    */     //   997: getfield T8 : I
/*    */     //   1000: i2s
/*    */     //   1001: istore #6
/*    */     //   1003: bipush #6
/*    */     //   1005: aload #5
/*    */     //   1007: iload #6
/*    */     //   1009: invokespecial <init> : (BLf/hR;S)V
/*    */     //   1012: invokevirtual add : (Ljava/lang/Object;)Z
/*    */     //   1015: pop
/*    */     //   1016: iinc #4, 1
/*    */     //   1019: goto -> 904
/*    */     //   1022: aload_0
/*    */     //   1023: new f/XH
/*    */     //   1026: dup
/*    */     //   1027: aload_1
/*    */     //   1028: iconst_0
/*    */     //   1029: anewarray f/S80
/*    */     //   1032: invokevirtual toArray : ([Ljava/lang/Object;)[Ljava/lang/Object;
/*    */     //   1035: checkcast [Lf/S80;
/*    */     //   1038: aload #16
/*    */     //   1040: getfield T8 : I
/*    */     //   1043: i2b
/*    */     //   1044: invokespecial <init> : ([Lf/S80;B)V
/*    */     //   1047: invokevirtual Com3 : (Ljava/lang/Object;)V
/*    */     //   1050: aload #19
/*    */     //   1052: getfield F2 : Lf/ak0;
/*    */     //   1055: getfield PH0 : Ljava/lang/StringBuilder;
/*    */     //   1058: invokevirtual toString : ()Ljava/lang/String;
/*    */     //   1061: invokevirtual isEmpty : ()Z
/*    */     //   1064: ifne -> 1176
/*    */     //   1067: aload #19
/*    */     //   1069: iconst_m1
/*    */     //   1070: istore_1
/*    */     //   1071: getfield F2 : Lf/ak0;
/*    */     //   1074: getfield PH0 : Ljava/lang/StringBuilder;
/*    */     //   1077: invokevirtual toString : ()Ljava/lang/String;
/*    */     //   1080: invokevirtual trim : ()Ljava/lang/String;
/*    */     //   1083: astore_2
/*    */     //   1084: iconst_0
/*    */     //   1085: istore_3
/*    */     //   1086: iload_3
/*    */     //   1087: aload #20
/*    */     //   1089: invokeinterface size : ()I
/*    */     //   1094: if_icmpge -> 1127
/*    */     //   1097: aload #20
/*    */     //   1099: iload_3
/*    */     //   1100: invokeinterface get : (I)Ljava/lang/Object;
/*    */     //   1105: checkcast java/lang/String
/*    */     //   1108: aload_2
/*    */     //   1109: invokevirtual equalsIgnoreCase : (Ljava/lang/String;)Z
/*    */     //   1112: ifeq -> 1121
/*    */     //   1115: aload #21
/*    */     //   1117: iload_3
/*    */     //   1118: iaload
/*    */     //   1119: i2s
/*    */     //   1120: istore_1
/*    */     //   1121: iinc #3, 1
/*    */     //   1124: goto -> 1086
/*    */     //   1127: iload_1
/*    */     //   1128: iconst_m1
/*    */     //   1129: if_icmpne -> 1162
/*    */     //   1132: aload_0
/*    */     //   1133: invokevirtual clear : ()V
/*    */     //   1136: getstatic f/js.vu0 : Lf/js;
/*    */     //   1139: sipush #8087
/*    */     //   1142: aload #19
/*    */     //   1144: getfield F2 : Lf/ak0;
/*    */     //   1147: getfield PH0 : Ljava/lang/StringBuilder;
/*    */     //   1150: invokevirtual toString : ()Ljava/lang/String;
/*    */     //   1153: invokestatic Go : (ILjava/lang/String;)Ljava/lang/String;
/*    */     //   1156: iconst_m1
/*    */     //   1157: swap
/*    */     //   1158: invokevirtual Pu : (ILjava/lang/String;)V
/*    */     //   1161: return
/*    */     //   1162: aload_0
/*    */     //   1163: new f/ug0
/*    */     //   1166: dup
/*    */     //   1167: astore_2
/*    */     //   1168: iload_1
/*    */     //   1169: invokespecial <init> : (S)V
/*    */     //   1172: aload_2
/*    */     //   1173: invokevirtual Com3 : (Ljava/lang/Object;)V
/*    */     //   1176: aload #22
/*    */     //   1178: getfield TG0 : Lf/protected;
/*    */     //   1181: invokevirtual nm0 : ()Z
/*    */     //   1184: ifeq -> 1200
/*    */     //   1187: aload_0
/*    */     //   1188: new f/uS
/*    */     //   1191: dup
/*    */     //   1192: astore_1
/*    */     //   1193: invokespecial <init> : ()V
/*    */     //   1196: aload_1
/*    */     //   1197: invokevirtual Com3 : (Ljava/lang/Object;)V
/*    */     //   1200: aload #23
/*    */     //   1202: getfield TG0 : Lf/protected;
/*    */     //   1205: invokevirtual nm0 : ()Z
/*    */     //   1208: ifeq -> 1224
/*    */     //   1211: aload_0
/*    */     //   1212: new f/oK
/*    */     //   1215: dup
/*    */     //   1216: astore_0
/*    */     //   1217: invokespecial <init> : ()V
/*    */     //   1220: aload_0
/*    */     //   1221: invokevirtual Com3 : (Ljava/lang/Object;)V
/*    */     //   1224: aload #24
/*    */     //   1226: invokeinterface run : ()V
/*    */     //   1231: return
/*    */     // Line number table:
/*    */     //   Java source line number -> byte code offset
/*    */     //   #1	-> 5
/*    */     //   #2	-> 8
/*    */     //   #3	-> 17
/*    */     //   #4	-> 34
/*    */     //   #5	-> 43
/*    */     //   #6	-> 64
/*    */     //   #7	-> 72
/*    */     //   #8	-> 75
/*    */     //   #9	-> 83
/*    */     //   #10	-> 91
/*    */     //   #11	-> 94
/*    */     //   #12	-> 97
/*    */     //   #13	-> 106
/*    */     //   #14	-> 109
/*    */     //   #15	-> 116
/*    */     //   #16	-> 119
/*    */     //   #17	-> 122
/*    */     //   #18	-> 125
/*    */     //   #19	-> 147
/*    */     //   #20	-> 150
/*    */     //   #21	-> 159
/*    */     //   #22	-> 175
/*    */     //   #23	-> 178
/*    */     //   #24	-> 187
/*    */     //   #25	-> 203
/*    */     //   #26	-> 206
/*    */     //   #27	-> 215
/*    */     //   #28	-> 231
/*    */     //   #29	-> 234
/*    */     //   #30	-> 243
/*    */     //   #31	-> 259
/*    */     //   #32	-> 268
/*    */     //   #33	-> 283
/*    */     //   #34	-> 286
/*    */     //   #35	-> 289
/*    */     //   #36	-> 292
/*    */     //   #37	-> 304
/*    */     //   #38	-> 307
/*    */     //   #39	-> 310
/*    */     //   #40	-> 314
/*    */     //   #41	-> 319
/*    */     //   #42	-> 341
/*    */     //   #43	-> 349
/*    */     //   #44	-> 375
/*    */     //   #45	-> 378
/*    */     //   #46	-> 381
/*    */     //   #47	-> 410
/*    */     //   #48	-> 413
/*    */     //   #49	-> 421
/*    */     //   #50	-> 424
/*    */     //   #51	-> 427
/*    */     //   #52	-> 430
/*    */     //   #53	-> 435
/*    */     //   #54	-> 440
/*    */     //   #55	-> 445
/*    */     //   #56	-> 448
/*    */     //   #57	-> 456
/*    */     //   #58	-> 459
/*    */     //   #59	-> 468
/*    */     //   #60	-> 481
/*    */     //   #61	-> 484
/*    */     //   #62	-> 521
/*    */     //   #63	-> 531
/*    */     //   #64	-> 547
/*    */     //   #65	-> 558
/*    */     //   #66	-> 572
/*    */     //   #67	-> 575
/*    */     //   #68	-> 584
/*    */     //   #69	-> 616
/*    */     //   #70	-> 636
/*    */     //   #71	-> 648
/*    */     //   #72	-> 651
/*    */     //   #73	-> 655
/*    */     //   #74	-> 679
/*    */     //   #75	-> 733
/*    */     //   #76	-> 736
/*    */     //   #77	-> 740
/*    */     //   #78	-> 747
/*    */     //   #79	-> 759
/*    */     //   #80	-> 762
/*    */     //   #81	-> 766
/*    */     //   #82	-> 791
/*    */     //   #83	-> 846
/*    */     //   #84	-> 849
/*    */     //   #85	-> 853
/*    */     //   #86	-> 860
/*    */     //   #87	-> 880
/*    */     //   #88	-> 886
/*    */     //   #89	-> 917
/*    */     //   #90	-> 930
/*    */     //   #91	-> 933
/*    */     //   #92	-> 939
/*    */     //   #93	-> 951
/*    */     //   #94	-> 952
/*    */     //   #95	-> 962
/*    */     //   #96	-> 991
/*    */     //   #97	-> 994
/*    */     //   #98	-> 997
/*    */     //   #99	-> 1009
/*    */     //   #100	-> 1040
/*    */     //   #101	-> 1044
/*    */     //   #102	-> 1052
/*    */     //   #103	-> 1055
/*    */     //   #104	-> 1058
/*    */     //   #105	-> 1061
/*    */     //   #106	-> 1071
/*    */     //   #107	-> 1074
/*    */     //   #108	-> 1077
/*    */     //   #109	-> 1080
/*    */     //   #110	-> 1136
/*    */     //   #111	-> 1144
/*    */     //   #112	-> 1147
/*    */     //   #113	-> 1150
/*    */     //   #114	-> 1153
/*    */     //   #115	-> 1158
/*    */     //   #116	-> 1163
/*    */     //   #117	-> 1178
/*    */     //   #118	-> 1181
/*    */     //   #119	-> 1188
/*    */     //   #120	-> 1202
/*    */     //   #121	-> 1205
/* 22 */     //   #122	-> 1212 } public static void Or0(Ip paramIp, Un paramUn1, Un paramUn2, boolean paramBoolean, dQ paramdQ1, W1 paramW11, dQ paramdQ2, of paramof1, dQ paramdQ3, W1 paramW12, dQ paramdQ4, rh paramrh, dQ[][] paramArrayOfdQ, rh[][] paramArrayOfrh, dQ paramdQ5, of paramof2, dQ paramdQ6, ge0 paramge01, dQ paramdQ7, ge0 paramge02, Un paramUn3) { paramIp.gx(); paramIp.rK0(new g0(paramIp)); paramIp.WN(new cr0(paramIp)); U90 u90 = paramIp.Xz0; this(paramIp); cr0 cr0; if (km.XU()) { rb rb; this(paramIp, 0, 0, 32767, false); cr0.G90(rb); }  u90.ee0(cr0.Ya(paramUn1).Em0().Ya(paramUn2)); paramIp.o30.ee0(paramIp.AUX(new JG0[] { paramUn1, paramUn2 })); if (!paramBoolean) { paramIp.Xz0.ee0(paramIp.vo0(new JG0[] { paramdQ1, paramW11, paramdQ2, paramof1 })); paramIp.o30.ee0(paramIp.AUX(new JG0[] { paramdQ1, paramW11, paramdQ2, paramof1 })); }  paramIp.Xz0.ee0(paramIp.vo0(new JG0[] { paramdQ3, paramW12, paramdQ4, paramrh })); paramIp.o30.ee0(paramIp.AUX(new JG0[] { paramdQ3, paramW12, paramdQ4, paramrh })); hR[] arrayOfHR; int i; byte b; for (i = (arrayOfHR = hR.Tm0).length, b = 0; b < i; ) { hR hR; if (!(hR = arrayOfHR[b]).NT) { byte b2; arrayOfJG02[
/*    */             
/* 24 */             0] = paramArrayOfdQ[b2 = hR.dL][0]; arrayOfJG02[1] = paramArrayOfrh[b2][0]; arrayOfJG02[2] = paramArrayOfdQ[b2][1]; JG0[] arrayOfJG02; (arrayOfJG02 = new JG0[4])[3] = paramArrayOfrh[b2][1]; paramIp.Xz0.ee0(paramIp.vo0(new JG0[4]));
/*    */         byte b1;
/* 26 */         arrayOfJG01[
/*    */             
/* 28 */             0] = paramArrayOfdQ[b1 = hR.dL][0]; arrayOfJG01[1] = paramArrayOfrh[b1][0]; arrayOfJG01[2] = paramArrayOfdQ[b1][1]; JG0[] arrayOfJG01; (arrayOfJG01 = new JG0[4])[3] = paramArrayOfrh[b1][1]; paramIp.o30.ee0(paramIp.AUX(new JG0[4])); }  b++; }  paramIp
/* 29 */       .Xz0
/* 30 */       .ee0(paramIp.vo0(new JG0[] { paramdQ5, paramof2, paramdQ6, paramge01 }));
/* 31 */     paramIp.o30
/* 32 */       .ee0(paramIp.AUX(new JG0[] { paramdQ5, paramof2, paramdQ6, paramge01 })); if (paramBoolean) { paramIp
/* 33 */         .Xz0
/* 34 */         .ee0(paramIp.vo0(new JG0[] { paramdQ7, paramge02 }).Em0());
/* 35 */       paramIp.o30
/* 36 */         .ee0(paramIp.AUX(new JG0[] { paramdQ7, paramge02 })); }  paramIp
/* 37 */       .Xz0
/*    */       
/* 39 */       .ee0((new cr0(paramIp)).Em0().Ya(paramUn3));
/* 40 */     paramIp.o30
/* 41 */       .Em0().ee0(paramIp.AUX(new JG0[] { paramUn3 })); } public static void I9(Ip paramIp, Un paramUn1, Un paramUn2, boolean paramBoolean, dQ paramdQ1, Rm paramRm1, dQ paramdQ2, Rm paramRm2, dQ paramdQ3, W1 paramW11, dQ paramdQ4, W1 paramW12, dQ paramdQ5, W1 paramW13, dQ paramdQ6, W1 paramW14, dQ paramdQ7, W1 paramW15, dQ paramdQ8, of paramof, dQ paramdQ9, W1 paramW16, dQ paramdQ10, W1 paramW17, dQ[] paramArrayOfdQ, Rm[] paramArrayOfRm, dQ[][] paramArrayOfdQ1, rh[][] paramArrayOfrh, dQ paramdQ11, rh paramrh, dQ paramdQ12, ge0 paramge0, Un paramUn3) { paramIp.gx(); paramIp.rK0(new g0(paramIp)); paramIp.WN(new cr0(paramIp)); U90 u90 = paramIp.Xz0; this(paramIp); cr0 cr0; if (km.XU()) { rb rb; this(paramIp, 0, 0, 32767, false); cr0.G90(rb); }  u90.ee0(cr0.Ya(paramUn1).Em0().Ya(paramUn2)); paramIp.o30.ee0(paramIp.AUX(new JG0[] { paramUn1, paramUn2 })); if (paramBoolean) { paramIp.Xz0.ee0(paramIp.vo0(new JG0[] { paramdQ1, paramRm1, paramdQ2, paramRm2 })); paramIp.o30.ee0(paramIp.AUX(new JG0[] { paramdQ1, paramRm1, paramdQ2, paramRm2 })); }  paramIp.Xz0.ee0(paramIp.vo0(new JG0[] { paramdQ3, paramW11, paramdQ4, paramW12 })); paramIp.o30.ee0(paramIp.AUX(new JG0[] { paramdQ3, paramW11, paramdQ4, paramW12 })); paramIp.Xz0.ee0(paramIp.vo0(new JG0[] { paramdQ5, paramW13, paramdQ6, paramW14 })); paramIp.o30.ee0(paramIp.AUX(new JG0[] { paramdQ5, paramW13, paramdQ6, paramW14 })); if (paramBoolean) { paramIp.Xz0.ee0(paramIp.vo0(new JG0[] { paramdQ7, paramW15, paramdQ8, paramof })); paramIp.o30.ee0(paramIp.AUX(new JG0[] { paramdQ7, paramW15, paramdQ8, paramof })); }
/* 42 */      paramIp.Xz0.ee0(paramIp.vo0(new JG0[] { paramdQ9, paramW16, paramdQ10, paramW17 })); paramIp.o30.ee0(paramIp.AUX(new JG0[] { paramdQ9, paramW16, paramdQ10, paramW17 })); arrayOfJG0[0] = paramArrayOfdQ[0]; arrayOfJG0[1] = paramArrayOfRm[0]; arrayOfJG0[2] = paramArrayOfdQ[1]; JG0[] arrayOfJG0; (arrayOfJG0 = new JG0[4])[3] = paramArrayOfRm[1]; paramIp.Xz0.ee0(paramIp.vo0(new JG0[4])); arrayOfJG0[0] = paramArrayOfdQ[0]; arrayOfJG0[1] = paramArrayOfRm[0]; arrayOfJG0[2] = paramArrayOfdQ[1]; (arrayOfJG0 = new JG0[4])[3] = paramArrayOfRm[1]; paramIp.o30.ee0(paramIp.AUX(new JG0[4])); hR[] arrayOfHR; for (int i = (arrayOfHR = hR.Tm0).length; paramBoolean < i; ) { hR hR; if (!(hR = arrayOfHR[paramBoolean]).NT) { byte b2; arrayOfJG02[0] = paramArrayOfdQ1[b2 = hR.dL][0]; arrayOfJG02[1] = paramArrayOfrh[b2][0]; arrayOfJG02[2] = paramArrayOfdQ1[b2][1]; JG0[] arrayOfJG02; (arrayOfJG02 = new JG0[4])[3] = paramArrayOfrh[b2][1]; paramIp.Xz0.ee0(paramIp.vo0(new JG0[4])); byte b1; arrayOfJG01[
/*    */             
/* 44 */             0] = paramArrayOfdQ1[b1 = hR.dL][0]; arrayOfJG01[1] = paramArrayOfrh[b1][0]; arrayOfJG01[2] = paramArrayOfdQ1[b1][1]; JG0[] arrayOfJG01; (arrayOfJG01 = new JG0[4])[3] = paramArrayOfrh[b1][1]; paramIp.o30.ee0(paramIp.AUX(new JG0[4])); }  paramBoolean++; }  paramIp
/* 45 */       .Xz0
/* 46 */       .ee0(paramIp.vo0(new JG0[] { paramdQ11, paramrh, paramdQ12, paramge0 }));
/* 47 */     paramIp.o30
/* 48 */       .ee0(paramIp.AUX(new JG0[] { paramdQ11, paramrh, paramdQ12, paramge0 }));
/* 49 */     paramIp.Xz0
/*    */       
/* 51 */       .ee0((new cr0(paramIp)).Em0().Ya(paramUn3));
/* 52 */     paramIp.o30
/* 53 */       .Em0().ee0(paramIp.AUX(new JG0[] { paramUn3 })); }
/*    */ 
/*    */   
/*    */   public static boolean rq(UD0 paramUD0) {
/*    */     return paramUD0.lS ^ true;
/*    */   }
/*    */   
/*    */   public static void k7(W1 paramW1) {
/*    */     if (paramW1.Wa0.go < 1)
/*    */       paramW1.Z30(-1); 
/*    */   }
/*    */   
/*    */   public static boolean FG(mA parammA) {
/*    */     boolean bool;
/*    */     byte[] arrayOfByte;
/*    */     int i = (arrayOfByte = gm.mr).length;
/*    */     byte b = 0;
/*    */     while (true) {
/*    */       if (b < i) {
/*    */         byte b1 = arrayOfByte[b];
/*    */         if (parammA.WF == b1) {
/*    */           boolean bool1 = true;
/*    */           break;
/*    */         } 
/*    */         b++;
/*    */         continue;
/*    */       } 
/*    */       bool = false;
/*    */       break;
/*    */     } 
/*    */     return (!bool && parammA.zL0());
/*    */   } }


/* Location:              /Users/vnnsnnt/Documents/Codespace/JavaWorkspace/RedTrainer/src/main/java/org/trainer/client/PokeMMO.jar!/f/T80.class
 * Java compiler version: 8 (52.0)
 * JD-Core Version:       1.1.3
 */