/*   */ package f;public final class Th0 extends so0 { private void Pl0(LPT3 paramLPT3, fv0 paramfv0) {
/* 2 */     arrayOfString[0] = "1"; String[] arrayOfString; (arrayOfString = new String[3])[
/*   */         
/* 4 */         1] = Ml0.OH0(paramLPT3.Iu);
/*   */ 
/*   */ 
/*   */ 
/*   */     
/* 9 */     (new String[3])[2] = B40.df("$").append(NumberFormat.getInstance().format((paramfv0.B90 * 1))).toString(); js.vu0.uh(new h70(Ml0.sB(8039, arrayOfString), new gM(this, paramfv0), null));
/*   */   }
/*   */   
/*   */   public final vF0[] Vt;
/*   */   public final dQ[] fV;
/*   */   
/*   */   public Th0(fv0 paramfv0, LPT3 paramLPT3, byte paramByte) {
/*   */     // Byte code:
/*   */     //   0: aload_0
/*   */     //   1: aload_2
/*   */     //   2: aload_0
/*   */     //   3: aload_2
/*   */     //   4: aload_0
/*   */     //   5: dup
/*   */     //   6: dup
/*   */     //   7: dup2
/*   */     //   8: invokestatic b20 : ()Lf/Of;
/*   */     //   11: aload_2
/*   */     //   12: invokevirtual u1 : ()S
/*   */     //   15: invokevirtual On0 : (S)Lf/LPT3;
/*   */     //   18: invokevirtual Pd0 : ()Lf/wc;
/*   */     //   21: invokevirtual bk0 : ()Lf/Vp0;
/*   */     //   24: invokestatic b20 : ()Lf/Of;
/*   */     //   27: aload_2
/*   */     //   28: invokevirtual u1 : ()S
/*   */     //   31: invokevirtual On0 : (S)Lf/LPT3;
/*   */     //   34: invokevirtual Pd0 : ()Lf/wc;
/*   */     //   37: invokevirtual Zj : ()S
/*   */     //   40: invokespecial <init> : (Lf/Vp0;S)V
/*   */     //   43: ldc 'previewwidget'
/*   */     //   45: invokevirtual Xu : (Ljava/lang/String;)V
/*   */     //   48: new f/Ip
/*   */     //   51: dup
/*   */     //   52: invokespecial <init> : ()V
/*   */     //   55: putfield ms0 : Lf/Ip;
/*   */     //   58: getfield Yp0 : Lf/Ip;
/*   */     //   61: iconst_0
/*   */     //   62: invokevirtual wI0 : (Z)V
/*   */     //   65: getfield UF : Lf/Dn0;
/*   */     //   68: iload_3
/*   */     //   69: invokevirtual PQ : (B)V
/*   */     //   72: new f/Zz0
/*   */     //   75: dup
/*   */     //   76: astore_3
/*   */     //   77: invokespecial <init> : ()V
/*   */     //   80: invokestatic Tn : (Lf/LPT3;)[Lf/vF0;
/*   */     //   83: putfield Vt : [Lf/vF0;
/*   */     //   86: invokestatic ee0 : (Lf/LPT3;)[Lf/dQ;
/*   */     //   89: putfield fV : [Lf/dQ;
/*   */     //   92: iconst_0
/*   */     //   93: istore #4
/*   */     //   95: iload #4
/*   */     //   97: aload_0
/*   */     //   98: getfield Vt : [Lf/vF0;
/*   */     //   101: dup
/*   */     //   102: astore #5
/*   */     //   104: arraylength
/*   */     //   105: if_icmpge -> 143
/*   */     //   108: aload_3
/*   */     //   109: iconst_2
/*   */     //   110: anewarray f/JG0
/*   */     //   113: dup
/*   */     //   114: dup
/*   */     //   115: aload_0
/*   */     //   116: swap
/*   */     //   117: aload #5
/*   */     //   119: iload #4
/*   */     //   121: aaload
/*   */     //   122: iconst_0
/*   */     //   123: swap
/*   */     //   124: aastore
/*   */     //   125: getfield fV : [Lf/dQ;
/*   */     //   128: iload #4
/*   */     //   130: aaload
/*   */     //   131: iconst_1
/*   */     //   132: swap
/*   */     //   133: aastore
/*   */     //   134: invokevirtual of0 : ([Lf/JG0;)V
/*   */     //   137: iinc #4, 1
/*   */     //   140: goto -> 95
/*   */     //   143: aload_2
/*   */     //   144: invokestatic iw : (Lf/LPT3;)Ljava/lang/StringBuilder;
/*   */     //   147: dup
/*   */     //   148: astore #4
/*   */     //   150: invokevirtual length : ()I
/*   */     //   153: ifle -> 225
/*   */     //   156: aload #4
/*   */     //   158: invokevirtual toString : ()Ljava/lang/String;
/*   */     //   161: invokevirtual trim : ()Ljava/lang/String;
/*   */     //   164: ldc '\n'
/*   */     //   166: invokevirtual split : (Ljava/lang/String;)[Ljava/lang/String;
/*   */     //   169: dup
/*   */     //   170: astore #4
/*   */     //   172: arraylength
/*   */     //   173: istore #5
/*   */     //   175: iconst_0
/*   */     //   176: istore #6
/*   */     //   178: iload #6
/*   */     //   180: iload #5
/*   */     //   182: if_icmpge -> 225
/*   */     //   185: aload_3
/*   */     //   186: aload #4
/*   */     //   188: iload #6
/*   */     //   190: aaload
/*   */     //   191: astore #7
/*   */     //   193: iconst_1
/*   */     //   194: anewarray f/JG0
/*   */     //   197: dup
/*   */     //   198: new f/dQ
/*   */     //   201: dup
/*   */     //   202: astore #8
/*   */     //   204: aload #7
/*   */     //   206: invokevirtual trim : ()Ljava/lang/String;
/*   */     //   209: invokespecial <init> : (Ljava/lang/String;)V
/*   */     //   212: iconst_0
/*   */     //   213: aload #8
/*   */     //   215: aastore
/*   */     //   216: invokevirtual of0 : ([Lf/JG0;)V
/*   */     //   219: iinc #6, 1
/*   */     //   222: goto -> 178
/*   */     //   225: aload_0
/*   */     //   226: dup
/*   */     //   227: dup
/*   */     //   228: dup2
/*   */     //   229: dup2
/*   */     //   230: getfield ge : Lf/Un;
/*   */     //   233: aload_0
/*   */     //   234: aload_2
/*   */     //   235: aload_1
/*   */     //   236: <illegal opcode> run : (Lf/Th0;Lf/LPT3;Lf/fv0;)Ljava/lang/Runnable;
/*   */     //   241: invokevirtual tW : (Ljava/lang/Runnable;)V
/*   */     //   244: getfield Zc : Lf/Un;
/*   */     //   247: bipush #65
/*   */     //   249: invokestatic OH0 : (I)Ljava/lang/String;
/*   */     //   252: invokevirtual s6 : (Ljava/lang/String;)V
/*   */     //   255: getfield Zc : Lf/Un;
/*   */     //   258: aload_0
/*   */     //   259: <illegal opcode> run : (Lf/Th0;)Ljava/lang/Runnable;
/*   */     //   264: invokevirtual tW : (Ljava/lang/Runnable;)V
/*   */     //   267: getfield ms0 : Lf/Ip;
/*   */     //   270: invokevirtual J8 : (Lf/JG0;)V
/*   */     //   273: getfield ms0 : Lf/Ip;
/*   */     //   276: dup
/*   */     //   277: invokevirtual d7 : ()Lf/cr0;
/*   */     //   280: bipush #6
/*   */     //   282: anewarray f/U90
/*   */     //   285: dup
/*   */     //   286: dup
/*   */     //   287: astore_1
/*   */     //   288: aload_0
/*   */     //   289: aload_1
/*   */     //   290: aload_0
/*   */     //   291: aload_1
/*   */     //   292: aload_0
/*   */     //   293: aload_1
/*   */     //   294: aload_0
/*   */     //   295: aload_1
/*   */     //   296: aload_0
/*   */     //   297: aload_1
/*   */     //   298: aload_0
/*   */     //   299: getfield ms0 : Lf/Ip;
/*   */     //   302: iconst_1
/*   */     //   303: anewarray f/JG0
/*   */     //   306: dup
/*   */     //   307: iconst_0
/*   */     //   308: aload_3
/*   */     //   309: aastore
/*   */     //   310: invokevirtual AUX : ([Lf/JG0;)Lf/U90;
/*   */     //   313: iconst_0
/*   */     //   314: swap
/*   */     //   315: aastore
/*   */     //   316: getfield ms0 : Lf/Ip;
/*   */     //   319: invokevirtual mE0 : ()Lf/g0;
/*   */     //   322: bipush #50
/*   */     //   324: invokevirtual Aq : (I)Lf/U90;
/*   */     //   327: iconst_1
/*   */     //   328: swap
/*   */     //   329: aastore
/*   */     //   330: getfield ms0 : Lf/Ip;
/*   */     //   333: iconst_2
/*   */     //   334: anewarray f/JG0
/*   */     //   337: dup
/*   */     //   338: dup
/*   */     //   339: aload_0
/*   */     //   340: swap
/*   */     //   341: aload_0
/*   */     //   342: getfield HK : Lf/dQ;
/*   */     //   345: iconst_0
/*   */     //   346: swap
/*   */     //   347: aastore
/*   */     //   348: getfield Lj0 : Lf/ge0;
/*   */     //   351: iconst_1
/*   */     //   352: swap
/*   */     //   353: aastore
/*   */     //   354: invokevirtual AUX : ([Lf/JG0;)Lf/U90;
/*   */     //   357: iconst_2
/*   */     //   358: swap
/*   */     //   359: aastore
/*   */     //   360: getfield ms0 : Lf/Ip;
/*   */     //   363: iconst_1
/*   */     //   364: anewarray f/JG0
/*   */     //   367: dup
/*   */     //   368: aload_0
/*   */     //   369: getfield vq : Lf/Un;
/*   */     //   372: iconst_0
/*   */     //   373: swap
/*   */     //   374: aastore
/*   */     //   375: invokevirtual AUX : ([Lf/JG0;)Lf/U90;
/*   */     //   378: iconst_3
/*   */     //   379: swap
/*   */     //   380: aastore
/*   */     //   381: getfield ms0 : Lf/Ip;
/*   */     //   384: iconst_1
/*   */     //   385: anewarray f/JG0
/*   */     //   388: dup
/*   */     //   389: aload_0
/*   */     //   390: getfield DW : Lf/W1;
/*   */     //   393: iconst_0
/*   */     //   394: swap
/*   */     //   395: aastore
/*   */     //   396: invokevirtual AUX : ([Lf/JG0;)Lf/U90;
/*   */     //   399: iconst_4
/*   */     //   400: swap
/*   */     //   401: aastore
/*   */     //   402: getfield ms0 : Lf/Ip;
/*   */     //   405: iconst_2
/*   */     //   406: anewarray f/JG0
/*   */     //   409: dup
/*   */     //   410: dup
/*   */     //   411: aload_0
/*   */     //   412: swap
/*   */     //   413: aload_0
/*   */     //   414: getfield ge : Lf/Un;
/*   */     //   417: iconst_0
/*   */     //   418: swap
/*   */     //   419: aastore
/*   */     //   420: getfield Zc : Lf/Un;
/*   */     //   423: iconst_1
/*   */     //   424: swap
/*   */     //   425: aastore
/*   */     //   426: invokevirtual vo0 : ([Lf/JG0;)Lf/U90;
/*   */     //   429: iconst_5
/*   */     //   430: swap
/*   */     //   431: aastore
/*   */     //   432: invokevirtual cOM8 : ([Lf/U90;)Lf/U90;
/*   */     //   435: invokevirtual WN : (Lf/U90;)V
/*   */     //   438: getfield ms0 : Lf/Ip;
/*   */     //   441: dup
/*   */     //   442: invokevirtual mE0 : ()Lf/g0;
/*   */     //   445: iconst_1
/*   */     //   446: anewarray f/U90
/*   */     //   449: dup
/*   */     //   450: aload_0
/*   */     //   451: getfield ms0 : Lf/Ip;
/*   */     //   454: invokevirtual d7 : ()Lf/cr0;
/*   */     //   457: sipush #300
/*   */     //   460: invokevirtual Aq : (I)Lf/U90;
/*   */     //   463: aload_0
/*   */     //   464: getfield ms0 : Lf/Ip;
/*   */     //   467: invokevirtual mE0 : ()Lf/g0;
/*   */     //   470: bipush #6
/*   */     //   472: anewarray f/U90
/*   */     //   475: dup
/*   */     //   476: dup
/*   */     //   477: astore_1
/*   */     //   478: aload_0
/*   */     //   479: aload_1
/*   */     //   480: aload_0
/*   */     //   481: aload_1
/*   */     //   482: aload_0
/*   */     //   483: aload_1
/*   */     //   484: aload_0
/*   */     //   485: aload_1
/*   */     //   486: aload_0
/*   */     //   487: aload_1
/*   */     //   488: aload_0
/*   */     //   489: getfield ms0 : Lf/Ip;
/*   */     //   492: iconst_1
/*   */     //   493: anewarray f/JG0
/*   */     //   496: dup
/*   */     //   497: iconst_0
/*   */     //   498: aload_3
/*   */     //   499: aastore
/*   */     //   500: invokevirtual vo0 : ([Lf/JG0;)Lf/U90;
/*   */     //   503: iconst_0
/*   */     //   504: swap
/*   */     //   505: aastore
/*   */     //   506: getfield ms0 : Lf/Ip;
/*   */     //   509: invokevirtual d7 : ()Lf/cr0;
/*   */     //   512: iconst_1
/*   */     //   513: swap
/*   */     //   514: aastore
/*   */     //   515: getfield ms0 : Lf/Ip;
/*   */     //   518: iconst_1
/*   */     //   519: anewarray f/JG0
/*   */     //   522: dup
/*   */     //   523: aload_0
/*   */     //   524: getfield HK : Lf/dQ;
/*   */     //   527: iconst_0
/*   */     //   528: swap
/*   */     //   529: aastore
/*   */     //   530: invokevirtual vo0 : ([Lf/JG0;)Lf/U90;
/*   */     //   533: invokevirtual Em0 : ()Lf/U90;
/*   */     //   536: aload_0
/*   */     //   537: getfield Lj0 : Lf/ge0;
/*   */     //   540: invokevirtual Ya : (Lf/JG0;)Lf/U90;
/*   */     //   543: iconst_2
/*   */     //   544: swap
/*   */     //   545: aastore
/*   */     //   546: getfield ms0 : Lf/Ip;
/*   */     //   549: iconst_1
/*   */     //   550: anewarray f/JG0
/*   */     //   553: dup
/*   */     //   554: aload_0
/*   */     //   555: getfield vq : Lf/Un;
/*   */     //   558: iconst_0
/*   */     //   559: swap
/*   */     //   560: aastore
/*   */     //   561: invokevirtual vo0 : ([Lf/JG0;)Lf/U90;
/*   */     //   564: iconst_3
/*   */     //   565: swap
/*   */     //   566: aastore
/*   */     //   567: getfield ms0 : Lf/Ip;
/*   */     //   570: iconst_1
/*   */     //   571: anewarray f/JG0
/*   */     //   574: dup
/*   */     //   575: aload_0
/*   */     //   576: getfield DW : Lf/W1;
/*   */     //   579: iconst_0
/*   */     //   580: swap
/*   */     //   581: aastore
/*   */     //   582: invokevirtual vo0 : ([Lf/JG0;)Lf/U90;
/*   */     //   585: iconst_4
/*   */     //   586: swap
/*   */     //   587: aastore
/*   */     //   588: getfield ms0 : Lf/Ip;
/*   */     //   591: iconst_2
/*   */     //   592: anewarray f/JG0
/*   */     //   595: dup
/*   */     //   596: dup
/*   */     //   597: aload_0
/*   */     //   598: swap
/*   */     //   599: aload_0
/*   */     //   600: getfield ge : Lf/Un;
/*   */     //   603: iconst_0
/*   */     //   604: swap
/*   */     //   605: aastore
/*   */     //   606: getfield Zc : Lf/Un;
/*   */     //   609: iconst_1
/*   */     //   610: swap
/*   */     //   611: aastore
/*   */     //   612: invokevirtual AUX : ([Lf/JG0;)Lf/U90;
/*   */     //   615: iconst_5
/*   */     //   616: swap
/*   */     //   617: aastore
/*   */     //   618: invokevirtual cOM8 : ([Lf/U90;)Lf/U90;
/*   */     //   621: invokevirtual ee0 : (Lf/U90;)Lf/U90;
/*   */     //   624: iconst_0
/*   */     //   625: swap
/*   */     //   626: aastore
/*   */     //   627: invokevirtual cOM8 : ([Lf/U90;)Lf/U90;
/*   */     //   630: invokevirtual rK0 : (Lf/U90;)V
/*   */     //   633: invokestatic XU : ()Z
/*   */     //   636: ifeq -> 670
/*   */     //   639: aload_0
/*   */     //   640: getfield Vt : [Lf/vF0;
/*   */     //   643: dup
/*   */     //   644: astore_0
/*   */     //   645: arraylength
/*   */     //   646: istore_1
/*   */     //   647: iconst_0
/*   */     //   648: istore_2
/*   */     //   649: iload_2
/*   */     //   650: iload_1
/*   */     //   651: if_icmpge -> 670
/*   */     //   654: aload_0
/*   */     //   655: iload_2
/*   */     //   656: aaload
/*   */     //   657: invokevirtual ZH0 : ()Lf/rH;
/*   */     //   660: fconst_2
/*   */     //   661: invokevirtual Ii0 : (F)V
/*   */     //   664: iinc #2, 1
/*   */     //   667: goto -> 649
/*   */     //   670: return
/*   */   }
/*   */   
/*   */   public final boolean i2(oa0 paramoa0) {
/*   */     return false;
/*   */   }
/*   */   
/*   */   public final void d40() {
/*   */     this.ms0.mM();
/*   */     mM();
/*   */     ec(et.Wi0, 0);
/*   */   } }


/* Location:              /Users/vnnsnnt/Documents/Codespace/JavaWorkspace/RedTrainer/src/main/java/org/trainer/client/PokeMMO.jar!/f/Th0.class
 * Java compiler version: 8 (52.0)
 * JD-Core Version:       1.1.3
 */