package f;

public final class TI implements Runnable {
  public TI(XK0 paramXK0) {}
  
  public final void run() {
    // Byte code:
    //   0: aload_0
    //   1: dup
    //   2: getfield py : Lf/XK0;
    //   5: getfield g30 : Lf/Vq0;
    //   8: invokevirtual nv0 : ()I
    //   11: istore_1
    //   12: getfield py : Lf/XK0;
    //   15: getfield Vu0 : Lf/Vq0;
    //   18: dup
    //   19: astore_2
    //   20: ifnonnull -> 28
    //   23: iconst_0
    //   24: istore_2
    //   25: goto -> 33
    //   28: aload_2
    //   29: invokevirtual nv0 : ()I
    //   32: istore_2
    //   33: aload_0
    //   34: getfield py : Lf/XK0;
    //   37: dup
    //   38: astore_3
    //   39: getfield Lm : [[Lf/sM;
    //   42: ifnonnull -> 84
    //   45: aload_3
    //   46: getfield g30 : Lf/Vq0;
    //   49: bipush #55
    //   51: invokestatic OH0 : (I)Ljava/lang/String;
    //   54: astore_0
    //   55: new f/JG0
    //   58: dup
    //   59: invokespecial <init> : ()V
    //   62: aload_0
    //   63: invokevirtual WS : (Lf/JG0;Ljava/lang/String;)Lf/Li0;
    //   66: pop
    //   67: getstatic f/km.u4 : Lf/R8;
    //   70: getfield e20 : Lf/c4;
    //   73: new f/ri
    //   76: dup
    //   77: invokespecial <init> : ()V
    //   80: invokevirtual W3 : (Lf/Bi;)V
    //   83: return
    //   84: aload_0
    //   85: aload_3
    //   86: invokevirtual i2 : ()V
    //   89: getfield py : Lf/XK0;
    //   92: getfield g30 : Lf/Vq0;
    //   95: dup
    //   96: dup2
    //   97: getfield d00 : Lf/Fp;
    //   100: invokevirtual gx : ()V
    //   103: getfield PRN : Lf/Q20;
    //   106: invokevirtual gx : ()V
    //   109: getfield Us0 : Ljava/util/ArrayList;
    //   112: invokevirtual clear : ()V
    //   115: aconst_null
    //   116: putfield zO : Lf/Li0;
    //   119: iconst_0
    //   120: istore_3
    //   121: getstatic f/Tx0.jb : [Lf/Tx0;
    //   124: dup
    //   125: astore #4
    //   127: arraylength
    //   128: istore #5
    //   130: iconst_0
    //   131: istore #6
    //   133: iload #6
    //   135: iload #5
    //   137: if_icmpge -> 1807
    //   140: aload_0
    //   141: aload #4
    //   143: iload #6
    //   145: aaload
    //   146: astore #7
    //   148: getfield py : Lf/XK0;
    //   151: getfield Lm : [[Lf/sM;
    //   154: aload #7
    //   156: getfield Ri0 : B
    //   159: aaload
    //   160: arraylength
    //   161: iconst_1
    //   162: if_icmpge -> 168
    //   165: goto -> 1801
    //   168: aload #7
    //   170: getstatic f/Tx0.f50 : Lf/Tx0;
    //   173: if_acmpne -> 189
    //   176: getstatic f/km.mI0 : Lf/P1;
    //   179: iconst_1
    //   180: invokevirtual s2 : (B)Z
    //   183: ifne -> 189
    //   186: goto -> 1801
    //   189: aload_0
    //   190: new java/util/ArrayList
    //   193: dup
    //   194: astore_3
    //   195: invokespecial <init> : ()V
    //   198: getfield py : Lf/XK0;
    //   201: getfield Lm : [[Lf/sM;
    //   204: aload #7
    //   206: getfield Ri0 : B
    //   209: aaload
    //   210: dup
    //   211: astore #8
    //   213: arraylength
    //   214: istore #9
    //   216: iconst_0
    //   217: istore #10
    //   219: iload #10
    //   221: iload #9
    //   223: if_icmpge -> 242
    //   226: aload_3
    //   227: aload #8
    //   229: iload #10
    //   231: aaload
    //   232: invokevirtual add : (Ljava/lang/Object;)Z
    //   235: pop
    //   236: iinc #10, 1
    //   239: goto -> 219
    //   242: aload_0
    //   243: getfield py : Lf/XK0;
    //   246: getfield jK0 : Lf/W1;
    //   249: getfield Wa0 : Lf/A60;
    //   252: getfield go : I
    //   255: dup
    //   256: istore #8
    //   258: ifne -> 299
    //   261: aload #7
    //   263: new f/sZ
    //   266: astore #8
    //   268: getstatic f/Tx0.sp : Lf/Tx0;
    //   271: if_acmpne -> 280
    //   274: iconst_1
    //   275: istore #9
    //   277: goto -> 283
    //   280: iconst_0
    //   281: istore #9
    //   283: aload_3
    //   284: aload #8
    //   286: iload #9
    //   288: invokespecial <init> : (Z)V
    //   291: aload #8
    //   293: invokestatic sort : (Ljava/util/List;Ljava/util/Comparator;)V
    //   296: goto -> 392
    //   299: iload #8
    //   301: iconst_1
    //   302: if_icmpne -> 323
    //   305: aload_3
    //   306: new f/OA0
    //   309: dup
    //   310: astore #8
    //   312: invokespecial <init> : ()V
    //   315: aload #8
    //   317: invokestatic sort : (Ljava/util/List;Ljava/util/Comparator;)V
    //   320: goto -> 392
    //   323: iload #8
    //   325: iconst_2
    //   326: if_icmpne -> 347
    //   329: aload_3
    //   330: new f/rk0
    //   333: dup
    //   334: astore #8
    //   336: invokespecial <init> : ()V
    //   339: aload #8
    //   341: invokestatic sort : (Ljava/util/List;Ljava/util/Comparator;)V
    //   344: goto -> 392
    //   347: iload #8
    //   349: iconst_3
    //   350: if_icmpne -> 371
    //   353: aload_3
    //   354: new f/Cv
    //   357: dup
    //   358: astore #8
    //   360: invokespecial <init> : ()V
    //   363: aload #8
    //   365: invokestatic sort : (Ljava/util/List;Ljava/util/Comparator;)V
    //   368: goto -> 392
    //   371: iload #8
    //   373: iconst_4
    //   374: if_icmpne -> 392
    //   377: aload_3
    //   378: new f/hp
    //   381: dup
    //   382: astore #8
    //   384: invokespecial <init> : ()V
    //   387: aload #8
    //   389: invokestatic sort : (Ljava/util/List;Ljava/util/Comparator;)V
    //   392: aload #7
    //   394: iconst_1
    //   395: istore #8
    //   397: new f/Ip
    //   400: dup
    //   401: astore #9
    //   403: invokespecial <init> : ()V
    //   406: new f/Ip
    //   409: dup
    //   410: astore #10
    //   412: invokespecial <init> : ()V
    //   415: new f/cr0
    //   418: dup
    //   419: astore #11
    //   421: aload #10
    //   423: invokespecial <init> : (Lf/Ip;)V
    //   426: new f/g0
    //   429: dup
    //   430: astore #12
    //   432: aload #10
    //   434: invokespecial <init> : (Lf/Ip;)V
    //   437: iconst_2
    //   438: istore #13
    //   440: getstatic f/Tx0.sE0 : Lf/Tx0;
    //   443: if_acmpne -> 1431
    //   446: aload_0
    //   447: getfield py : Lf/XK0;
    //   450: new f/Vq0
    //   453: dup
    //   454: invokespecial <init> : ()V
    //   457: putfield Vu0 : Lf/Vq0;
    //   460: getstatic f/Vp0.Jo : [Lf/Vp0;
    //   463: dup
    //   464: astore #14
    //   466: arraylength
    //   467: istore #15
    //   469: iconst_0
    //   470: istore #16
    //   472: iload #16
    //   474: iload #15
    //   476: if_icmpge -> 896
    //   479: iload #13
    //   481: aload #14
    //   483: iload #16
    //   485: aaload
    //   486: astore #17
    //   488: new f/Ip
    //   491: dup
    //   492: astore #18
    //   494: invokespecial <init> : ()V
    //   497: new f/cr0
    //   500: dup
    //   501: astore #19
    //   503: aload #18
    //   505: invokespecial <init> : (Lf/Ip;)V
    //   508: new f/g0
    //   511: dup
    //   512: astore #20
    //   514: aload #18
    //   516: invokespecial <init> : (Lf/Ip;)V
    //   519: anewarray f/LPt1
    //   522: astore #21
    //   524: iconst_0
    //   525: istore #22
    //   527: iconst_0
    //   528: istore #23
    //   530: iconst_0
    //   531: istore #24
    //   533: iload #24
    //   535: aload_0
    //   536: getfield py : Lf/XK0;
    //   539: getfield Lm : [[Lf/sM;
    //   542: aload #7
    //   544: getfield Ri0 : B
    //   547: aaload
    //   548: arraylength
    //   549: if_icmpge -> 710
    //   552: aload_3
    //   553: iload #24
    //   555: invokevirtual get : (I)Ljava/lang/Object;
    //   558: checkcast f/sM
    //   561: dup
    //   562: astore #25
    //   564: invokevirtual Ga0 : ()Lf/wc;
    //   567: ifnull -> 704
    //   570: aload #25
    //   572: invokevirtual Ga0 : ()Lf/wc;
    //   575: getfield Hl0 : Lf/Vp0;
    //   578: aload #17
    //   580: if_acmpne -> 704
    //   583: aload #7
    //   585: iload #22
    //   587: iconst_1
    //   588: iadd
    //   589: istore #26
    //   591: new f/LPt1
    //   594: astore #27
    //   596: getstatic f/Tx0.sp : Lf/Tx0;
    //   599: if_acmpne -> 608
    //   602: iconst_1
    //   603: istore #28
    //   605: goto -> 611
    //   608: iconst_0
    //   609: istore #28
    //   611: iload #26
    //   613: iload #13
    //   615: aload #21
    //   617: iload #22
    //   619: aload #27
    //   621: aload #25
    //   623: iload #28
    //   625: invokespecial <init> : (Lf/sM;Z)V
    //   628: aload #27
    //   630: aastore
    //   631: iload #23
    //   633: iconst_1
    //   634: iadd
    //   635: istore #22
    //   637: irem
    //   638: ifne -> 696
    //   641: iload #13
    //   643: aload #20
    //   645: aload #18
    //   647: aload #21
    //   649: aload #19
    //   651: aload #18
    //   653: aload #21
    //   655: iconst_0
    //   656: istore #21
    //   658: invokevirtual AUX : ([Lf/JG0;)Lf/U90;
    //   661: iconst_5
    //   662: invokevirtual Aq : (I)Lf/U90;
    //   665: invokevirtual ee0 : (Lf/U90;)Lf/U90;
    //   668: pop
    //   669: invokevirtual vo0 : ([Lf/JG0;)Lf/U90;
    //   672: invokevirtual ee0 : (Lf/U90;)Lf/U90;
    //   675: pop
    //   676: anewarray f/LPt1
    //   679: astore #23
    //   681: iload #21
    //   683: iload #22
    //   685: aload #23
    //   687: astore #21
    //   689: istore #23
    //   691: istore #22
    //   693: goto -> 704
    //   696: iload #26
    //   698: iload #22
    //   700: istore #23
    //   702: istore #22
    //   704: iinc #24, 1
    //   707: goto -> 533
    //   710: iload #22
    //   712: new f/g0
    //   715: dup
    //   716: astore #22
    //   718: aload #18
    //   720: invokespecial <init> : (Lf/Ip;)V
    //   723: new f/cr0
    //   726: dup
    //   727: astore #24
    //   729: aload #18
    //   731: invokespecial <init> : (Lf/Ip;)V
    //   734: iconst_0
    //   735: istore #25
    //   737: ifle -> 792
    //   740: iconst_0
    //   741: istore #26
    //   743: iload #26
    //   745: iload #13
    //   747: if_icmpge -> 792
    //   750: aload #21
    //   752: iload #26
    //   754: aaload
    //   755: dup
    //   756: astore #27
    //   758: ifnonnull -> 764
    //   761: goto -> 786
    //   764: aload #24
    //   766: aload #21
    //   768: iload #26
    //   770: aload #22
    //   772: aload #27
    //   774: iinc #25, 1
    //   777: invokevirtual Ya : (Lf/JG0;)Lf/U90;
    //   780: pop
    //   781: aaload
    //   782: invokevirtual Ya : (Lf/JG0;)Lf/U90;
    //   785: pop
    //   786: iinc #26, 1
    //   789: goto -> 743
    //   792: iload #25
    //   794: iconst_2
    //   795: if_icmpge -> 804
    //   798: aload #24
    //   800: invokevirtual Em0 : ()Lf/U90;
    //   803: pop
    //   804: iload #23
    //   806: aload #18
    //   808: dup
    //   809: aload #20
    //   811: aload #19
    //   813: aload #22
    //   815: invokevirtual ee0 : (Lf/U90;)Lf/U90;
    //   818: pop
    //   819: aload #24
    //   821: invokevirtual ee0 : (Lf/U90;)Lf/U90;
    //   824: pop
    //   825: aload #19
    //   827: invokevirtual WN : (Lf/U90;)V
    //   830: aload #20
    //   832: invokevirtual rK0 : (Lf/U90;)V
    //   835: new f/rS
    //   838: dup
    //   839: dup2
    //   840: astore #19
    //   842: aload #18
    //   844: invokespecial <init> : (Lf/JG0;)V
    //   847: iconst_2
    //   848: invokevirtual zG0 : (I)V
    //   851: ldc_w 'sp'
    //   854: invokevirtual Xu : (Ljava/lang/String;)V
    //   857: ifle -> 890
    //   860: aload_0
    //   861: getfield py : Lf/XK0;
    //   864: getfield Vu0 : Lf/Vq0;
    //   867: aload #19
    //   869: aload #17
    //   871: invokevirtual V00 : ()I
    //   874: invokestatic OH0 : (I)Ljava/lang/String;
    //   877: ldc_w '\n'
    //   880: ldc_w ' '
    //   883: invokevirtual replaceAll : (Ljava/lang/String;Ljava/lang/String;)Ljava/lang/String;
    //   886: invokevirtual WS : (Lf/JG0;Ljava/lang/String;)Lf/Li0;
    //   889: pop
    //   890: iinc #16, 1
    //   893: goto -> 472
    //   896: iload #13
    //   898: new f/Ip
    //   901: dup
    //   902: dup2
    //   903: astore #14
    //   905: invokespecial <init> : ()V
    //   908: new f/cr0
    //   911: dup
    //   912: astore #15
    //   914: aload #14
    //   916: invokespecial <init> : (Lf/Ip;)V
    //   919: new f/g0
    //   922: dup
    //   923: astore #16
    //   925: aload #15
    //   927: dup
    //   928: aload #16
    //   930: aload #14
    //   932: invokespecial <init> : (Lf/Ip;)V
    //   935: invokevirtual Em0 : ()Lf/U90;
    //   938: pop
    //   939: new f/g0
    //   942: dup
    //   943: astore #17
    //   945: aload #14
    //   947: invokespecial <init> : (Lf/Ip;)V
    //   950: new f/cr0
    //   953: dup
    //   954: astore #18
    //   956: aload #14
    //   958: invokespecial <init> : (Lf/Ip;)V
    //   961: aload #17
    //   963: invokevirtual ee0 : (Lf/U90;)Lf/U90;
    //   966: pop
    //   967: aload #18
    //   969: invokevirtual ee0 : (Lf/U90;)Lf/U90;
    //   972: pop
    //   973: aload #15
    //   975: invokevirtual WN : (Lf/U90;)V
    //   978: aload #16
    //   980: invokevirtual rK0 : (Lf/U90;)V
    //   983: new f/rS
    //   986: dup
    //   987: dup
    //   988: aload #14
    //   990: invokespecial <init> : (Lf/JG0;)V
    //   993: iconst_2
    //   994: invokevirtual zG0 : (I)V
    //   997: ldc_w 'sp'
    //   1000: invokevirtual Xu : (Ljava/lang/String;)V
    //   1003: new f/Ip
    //   1006: dup
    //   1007: astore #14
    //   1009: invokespecial <init> : ()V
    //   1012: new f/cr0
    //   1015: dup
    //   1016: astore #15
    //   1018: aload #14
    //   1020: invokespecial <init> : (Lf/Ip;)V
    //   1023: new f/g0
    //   1026: dup
    //   1027: astore #16
    //   1029: aload #14
    //   1031: invokespecial <init> : (Lf/Ip;)V
    //   1034: anewarray f/kK
    //   1037: astore #17
    //   1039: iconst_0
    //   1040: istore #18
    //   1042: iconst_0
    //   1043: istore #19
    //   1045: iconst_0
    //   1046: istore #20
    //   1048: iload #20
    //   1050: aload_0
    //   1051: getfield py : Lf/XK0;
    //   1054: getfield Lm : [[Lf/sM;
    //   1057: aload #7
    //   1059: getfield Ri0 : B
    //   1062: aaload
    //   1063: arraylength
    //   1064: if_icmpge -> 1193
    //   1067: aload_3
    //   1068: iload #20
    //   1070: invokevirtual get : (I)Ljava/lang/Object;
    //   1073: checkcast f/sM
    //   1076: dup
    //   1077: astore #21
    //   1079: getfield pE0 : B
    //   1082: iconst_5
    //   1083: if_icmpne -> 1187
    //   1086: iload #18
    //   1088: iconst_1
    //   1089: iadd
    //   1090: dup
    //   1091: istore #22
    //   1093: iload #13
    //   1095: aload #17
    //   1097: iload #18
    //   1099: new f/kK
    //   1102: dup
    //   1103: astore #18
    //   1105: aload #21
    //   1107: iconst_0
    //   1108: invokespecial <init> : (Lf/sM;Z)V
    //   1111: aload #18
    //   1113: aastore
    //   1114: iload #19
    //   1116: iconst_1
    //   1117: iadd
    //   1118: istore #18
    //   1120: irem
    //   1121: ifne -> 1179
    //   1124: iload #13
    //   1126: aload #16
    //   1128: aload #14
    //   1130: aload #17
    //   1132: aload #15
    //   1134: aload #14
    //   1136: aload #17
    //   1138: iconst_0
    //   1139: istore #17
    //   1141: invokevirtual AUX : ([Lf/JG0;)Lf/U90;
    //   1144: iconst_5
    //   1145: invokevirtual Aq : (I)Lf/U90;
    //   1148: invokevirtual ee0 : (Lf/U90;)Lf/U90;
    //   1151: pop
    //   1152: invokevirtual vo0 : ([Lf/JG0;)Lf/U90;
    //   1155: invokevirtual ee0 : (Lf/U90;)Lf/U90;
    //   1158: pop
    //   1159: anewarray f/kK
    //   1162: astore #19
    //   1164: iload #17
    //   1166: aload #19
    //   1168: iload #18
    //   1170: istore #19
    //   1172: astore #17
    //   1174: istore #18
    //   1176: goto -> 1187
    //   1179: iload #22
    //   1181: iload #18
    //   1183: istore #19
    //   1185: istore #18
    //   1187: iinc #20, 1
    //   1190: goto -> 1048
    //   1193: iload #18
    //   1195: new f/g0
    //   1198: dup
    //   1199: astore_3
    //   1200: aload #14
    //   1202: invokespecial <init> : (Lf/Ip;)V
    //   1205: new f/cr0
    //   1208: dup
    //   1209: astore #18
    //   1211: aload #14
    //   1213: invokespecial <init> : (Lf/Ip;)V
    //   1216: ifle -> 1282
    //   1219: iconst_0
    //   1220: istore #20
    //   1222: iload #20
    //   1224: iload #13
    //   1226: if_icmpge -> 1282
    //   1229: aload #17
    //   1231: iload #20
    //   1233: aaload
    //   1234: ifnonnull -> 1255
    //   1237: aload #17
    //   1239: new f/kK
    //   1242: dup
    //   1243: astore #21
    //   1245: aconst_null
    //   1246: iconst_0
    //   1247: invokespecial <init> : (Lf/sM;Z)V
    //   1250: iload #20
    //   1252: aload #21
    //   1254: aastore
    //   1255: aload #18
    //   1257: aload #17
    //   1259: iload #20
    //   1261: aload_3
    //   1262: aload #17
    //   1264: iload #20
    //   1266: aaload
    //   1267: invokevirtual Ya : (Lf/JG0;)Lf/U90;
    //   1270: pop
    //   1271: aaload
    //   1272: invokevirtual Ya : (Lf/JG0;)Lf/U90;
    //   1275: pop
    //   1276: iinc #20, 1
    //   1279: goto -> 1222
    //   1282: iload #19
    //   1284: aload #14
    //   1286: dup
    //   1287: aload #16
    //   1289: aload #15
    //   1291: aload_3
    //   1292: invokevirtual ee0 : (Lf/U90;)Lf/U90;
    //   1295: pop
    //   1296: aload #18
    //   1298: invokevirtual ee0 : (Lf/U90;)Lf/U90;
    //   1301: pop
    //   1302: aload #15
    //   1304: invokevirtual WN : (Lf/U90;)V
    //   1307: aload #16
    //   1309: invokevirtual rK0 : (Lf/U90;)V
    //   1312: new f/rS
    //   1315: dup
    //   1316: dup2
    //   1317: astore_3
    //   1318: aload #14
    //   1320: invokespecial <init> : (Lf/JG0;)V
    //   1323: iconst_2
    //   1324: invokevirtual zG0 : (I)V
    //   1327: ldc_w 'sp'
    //   1330: invokevirtual Xu : (Ljava/lang/String;)V
    //   1333: ifle -> 1354
    //   1336: aload_0
    //   1337: getfield py : Lf/XK0;
    //   1340: getfield Vu0 : Lf/Vq0;
    //   1343: aload_3
    //   1344: sipush #3030
    //   1347: invokestatic OH0 : (I)Ljava/lang/String;
    //   1350: invokevirtual WS : (Lf/JG0;Ljava/lang/String;)Lf/Li0;
    //   1353: pop
    //   1354: aload #9
    //   1356: dup
    //   1357: dup2
    //   1358: aload #10
    //   1360: aload #12
    //   1362: aload #10
    //   1364: aload #11
    //   1366: aload #12
    //   1368: aload_0
    //   1369: aload #11
    //   1371: aload_0
    //   1372: getfield py : Lf/XK0;
    //   1375: getfield Vu0 : Lf/Vq0;
    //   1378: invokevirtual Ya : (Lf/JG0;)Lf/U90;
    //   1381: pop
    //   1382: getfield py : Lf/XK0;
    //   1385: getfield Vu0 : Lf/Vq0;
    //   1388: invokevirtual Ya : (Lf/JG0;)Lf/U90;
    //   1391: pop
    //   1392: invokevirtual WN : (Lf/U90;)V
    //   1395: invokevirtual rK0 : (Lf/U90;)V
    //   1398: iconst_1
    //   1399: anewarray f/JG0
    //   1402: dup
    //   1403: iconst_0
    //   1404: aload #10
    //   1406: aastore
    //   1407: invokevirtual AUX : ([Lf/JG0;)Lf/U90;
    //   1410: invokevirtual rK0 : (Lf/U90;)V
    //   1413: iconst_1
    //   1414: anewarray f/JG0
    //   1417: dup
    //   1418: iconst_0
    //   1419: aload #10
    //   1421: aastore
    //   1422: invokevirtual vo0 : ([Lf/JG0;)Lf/U90;
    //   1425: invokevirtual WN : (Lf/U90;)V
    //   1428: goto -> 1777
    //   1431: iconst_2
    //   1432: dup
    //   1433: istore #13
    //   1435: anewarray f/JG0
    //   1438: astore #14
    //   1440: iconst_0
    //   1441: istore #15
    //   1443: iconst_0
    //   1444: istore #16
    //   1446: iload #16
    //   1448: aload_0
    //   1449: getfield py : Lf/XK0;
    //   1452: getfield Lm : [[Lf/sM;
    //   1455: aload #7
    //   1457: getfield Ri0 : B
    //   1460: aaload
    //   1461: arraylength
    //   1462: if_icmpge -> 1607
    //   1465: aload_3
    //   1466: iload #16
    //   1468: invokevirtual get : (I)Ljava/lang/Object;
    //   1471: checkcast f/sM
    //   1474: dup
    //   1475: astore #17
    //   1477: iload #15
    //   1479: iconst_1
    //   1480: iadd
    //   1481: istore #18
    //   1483: invokevirtual Ga0 : ()Lf/wc;
    //   1486: ifnonnull -> 1504
    //   1489: new f/kK
    //   1492: dup
    //   1493: astore #19
    //   1495: aload #17
    //   1497: iconst_0
    //   1498: invokespecial <init> : (Lf/sM;Z)V
    //   1501: goto -> 1535
    //   1504: aload #7
    //   1506: new f/LPt1
    //   1509: astore #19
    //   1511: getstatic f/Tx0.sp : Lf/Tx0;
    //   1514: if_acmpne -> 1523
    //   1517: iconst_1
    //   1518: istore #20
    //   1520: goto -> 1526
    //   1523: iconst_0
    //   1524: istore #20
    //   1526: aload #19
    //   1528: aload #17
    //   1530: iload #20
    //   1532: invokespecial <init> : (Lf/sM;Z)V
    //   1535: iload #18
    //   1537: iload #13
    //   1539: aload #14
    //   1541: iload #15
    //   1543: aload #19
    //   1545: aastore
    //   1546: irem
    //   1547: ifne -> 1597
    //   1550: iload #13
    //   1552: aload #12
    //   1554: aload #10
    //   1556: aload #14
    //   1558: aload #11
    //   1560: aload #10
    //   1562: aload #14
    //   1564: iconst_0
    //   1565: istore #14
    //   1567: invokevirtual AUX : ([Lf/JG0;)Lf/U90;
    //   1570: invokevirtual ee0 : (Lf/U90;)Lf/U90;
    //   1573: pop
    //   1574: invokevirtual vo0 : ([Lf/JG0;)Lf/U90;
    //   1577: invokevirtual ee0 : (Lf/U90;)Lf/U90;
    //   1580: pop
    //   1581: anewarray f/JG0
    //   1584: astore #15
    //   1586: aload #15
    //   1588: iload #14
    //   1590: istore #15
    //   1592: astore #14
    //   1594: goto -> 1601
    //   1597: iload #18
    //   1599: istore #15
    //   1601: iinc #16, 1
    //   1604: goto -> 1446
    //   1607: iload #15
    //   1609: new f/g0
    //   1612: dup
    //   1613: astore_3
    //   1614: aload #10
    //   1616: invokespecial <init> : (Lf/Ip;)V
    //   1619: new f/cr0
    //   1622: dup
    //   1623: astore #15
    //   1625: aload #10
    //   1627: invokespecial <init> : (Lf/Ip;)V
    //   1630: ifle -> 1696
    //   1633: iconst_0
    //   1634: istore #16
    //   1636: iload #16
    //   1638: iload #13
    //   1640: if_icmpge -> 1696
    //   1643: aload #14
    //   1645: iload #16
    //   1647: aaload
    //   1648: ifnonnull -> 1669
    //   1651: aload #14
    //   1653: new f/kK
    //   1656: dup
    //   1657: astore #17
    //   1659: aconst_null
    //   1660: iconst_0
    //   1661: invokespecial <init> : (Lf/sM;Z)V
    //   1664: iload #16
    //   1666: aload #17
    //   1668: aastore
    //   1669: aload #15
    //   1671: aload #14
    //   1673: iload #16
    //   1675: aload_3
    //   1676: aload #14
    //   1678: iload #16
    //   1680: aaload
    //   1681: invokevirtual Ya : (Lf/JG0;)Lf/U90;
    //   1684: pop
    //   1685: aaload
    //   1686: invokevirtual Ya : (Lf/JG0;)Lf/U90;
    //   1689: pop
    //   1690: iinc #16, 1
    //   1693: goto -> 1636
    //   1696: aload #9
    //   1698: dup
    //   1699: dup2
    //   1700: aload #10
    //   1702: aload #12
    //   1704: aload #10
    //   1706: aload #11
    //   1708: aload #12
    //   1710: aload #15
    //   1712: aload #11
    //   1714: aload_3
    //   1715: invokevirtual ee0 : (Lf/U90;)Lf/U90;
    //   1718: pop
    //   1719: invokevirtual ee0 : (Lf/U90;)Lf/U90;
    //   1722: pop
    //   1723: invokevirtual WN : (Lf/U90;)V
    //   1726: invokevirtual rK0 : (Lf/U90;)V
    //   1729: new f/rS
    //   1732: dup
    //   1733: astore_3
    //   1734: aload #10
    //   1736: aload_3
    //   1737: dup
    //   1738: aconst_null
    //   1739: invokespecial <init> : (Lf/JG0;)V
    //   1742: iconst_2
    //   1743: invokevirtual zG0 : (I)V
    //   1746: invokevirtual Gz0 : (Lf/JG0;)V
    //   1749: iconst_1
    //   1750: anewarray f/JG0
    //   1753: dup
    //   1754: iconst_0
    //   1755: aload_3
    //   1756: aastore
    //   1757: invokevirtual AUX : ([Lf/JG0;)Lf/U90;
    //   1760: invokevirtual rK0 : (Lf/U90;)V
    //   1763: iconst_1
    //   1764: anewarray f/JG0
    //   1767: dup
    //   1768: iconst_0
    //   1769: aload_3
    //   1770: aastore
    //   1771: invokevirtual vo0 : ([Lf/JG0;)Lf/U90;
    //   1774: invokevirtual WN : (Lf/U90;)V
    //   1777: aload_0
    //   1778: getfield py : Lf/XK0;
    //   1781: getfield g30 : Lf/Vq0;
    //   1784: aload #9
    //   1786: aload #7
    //   1788: getfield Ps0 : I
    //   1791: invokestatic OH0 : (I)Ljava/lang/String;
    //   1794: invokevirtual WS : (Lf/JG0;Ljava/lang/String;)Lf/Li0;
    //   1797: pop
    //   1798: iload #8
    //   1800: istore_3
    //   1801: iinc #6, 1
    //   1804: goto -> 133
    //   1807: iload_3
    //   1808: ifne -> 1837
    //   1811: aload_0
    //   1812: getfield py : Lf/XK0;
    //   1815: getfield g30 : Lf/Vq0;
    //   1818: sipush #3004
    //   1821: invokestatic OH0 : (I)Ljava/lang/String;
    //   1824: astore_3
    //   1825: new f/Ip
    //   1828: dup
    //   1829: invokespecial <init> : ()V
    //   1832: aload_3
    //   1833: invokevirtual WS : (Lf/JG0;Ljava/lang/String;)Lf/Li0;
    //   1836: pop
    //   1837: aload_0
    //   1838: dup
    //   1839: getfield py : Lf/XK0;
    //   1842: getfield g30 : Lf/Vq0;
    //   1845: dup
    //   1846: iload_1
    //   1847: invokevirtual Hf : (I)Lf/Li0;
    //   1850: invokevirtual dA0 : (Lf/Li0;)V
    //   1853: getfield py : Lf/XK0;
    //   1856: getfield Vu0 : Lf/Vq0;
    //   1859: dup
    //   1860: astore_0
    //   1861: ifnull -> 1873
    //   1864: aload_0
    //   1865: dup
    //   1866: iload_2
    //   1867: invokevirtual Hf : (I)Lf/Li0;
    //   1870: invokevirtual dA0 : (Lf/Li0;)V
    //   1873: return
    // Line number table:
    //   Java source line number -> byte code offset
    //   #1	-> 70
    //   #2	-> 73
    //   #3	-> 86
    //   #4	-> 97
    //   #5	-> 100
    //   #6	-> 121
    //   #7	-> 156
    //   #8	-> 159
    //   #9	-> 206
    //   #10	-> 209
    //   #11	-> 249
    //   #12	-> 252
    //   #13	-> 263
    //   #14	-> 415
    //   #15	-> 426
    //   #16	-> 440
    //   #17	-> 497
    //   #18	-> 508
    //   #19	-> 519
    //   #20	-> 544
    //   #21	-> 547
    //   #22	-> 575
    //   #23	-> 591
    //   #24	-> 712
    //   #25	-> 723
    //   #26	-> 754
    //   #27	-> 908
    //   #28	-> 919
    //   #29	-> 935
    //   #30	-> 939
    //   #31	-> 950
    //   #32	-> 963
    //   #33	-> 1012
    //   #34	-> 1023
    //   #35	-> 1034
    //   #36	-> 1059
    //   #37	-> 1062
    //   #38	-> 1079
    //   #39	-> 1099
    //   #40	-> 1195
    //   #41	-> 1205
    //   #42	-> 1233
    //   #43	-> 1247
    //   #44	-> 1254
    //   #45	-> 1457
    //   #46	-> 1460
    //   #47	-> 1609
    //   #48	-> 1619
    //   #49	-> 1647
    //   #50	-> 1661
    //   #51	-> 1668
    //   #52	-> 1739
    //   #53	-> 1743
    //   #54	-> 1788
    //   #55	-> 1791
  }
}


/* Location:              /Users/vnnsnnt/Documents/Codespace/JavaWorkspace/RedTrainer/src/main/java/org/trainer/client/PokeMMO.jar!/f/TI.class
 * Java compiler version: 8 (52.0)
 * JD-Core Version:       1.1.3
 */