/*  1 */ package f;public final class tR extends Wr { public final byte Mn0; public final byte rb; public final byte yv; public final rS X2; public final Un EX; public final Un o6; public of Z80; public final Ip JI; public final void ZC0(byte paramByte) { j40[] arrayOfJ401; if (paramByte < 0 || paramByte >= (arrayOfJ401 = this.y40).length) return;  j40 j401 = arrayOfJ401[paramByte]; if (Arrays.<j40>asList(this.WR).contains(j401)) return;  j40[] arrayOfJ402; for (byte b = 0; b < (arrayOfJ402 = this.WR).length; ) { if (arrayOfJ402[b] == null) { String str; arrayOfJ402[b] = j401; this.B80[b] = paramByte; cr cr1 = this.mM[b]; short s;
/*  2 */         if ((s = j401.Zs.Cw0) > 0) { cr1
/*  3 */             .As
/*    */             
/*  5 */             .sm(um0.Kt0.lb(s, false, (byte)0));
/*    */           
/*  7 */           cr1.z4 = On.v30().lpT3(s).o60(false); cr1.zn(); } else { cr1
/*  8 */             .As
/*  9 */             .H();
/* 10 */           cr1.z4 = null; cr1.zn(); }
/* 11 */          cr1.As
/* 12 */           .vU = true;
/* 13 */         if (this.yv == 2) { cr1 = this.mM[b]; str = j401.m(); } else { cr1 = this.mM[b];
/* 14 */           str = rG0.Zs0((j40)str, false, false, false); }  cr1
/* 15 */           .z4 = str;
/* 16 */         cr1.zn();
/* 17 */         (this.mM[b])
/* 18 */           .As
/* 19 */           .tL(36, 36); Ye0(); return; }  b = (byte)(b + 1); }  } public j40[] y40; public j40[] WR; public byte[] B80; public cr[] mM; public Lw z20; public Lw M9; public Wp[] ly; public tR(pA parampA, byte paramByte1, byte paramByte2, byte paramByte3, byte paramByte4, j40[] paramArrayOfj40) { pRn pRn; rS rS1; this.y40 = null; this.z20 = new Lw(); this.M9 = new Lw(); this.ly = new Wp[0]; this.Mn0 = paramByte3; this.rb = paramByte4; this.yv = paramByte1; if (paramByte1 == 0 || paramByte1 == 2) { this.y40 = paramArrayOfj40; } else if (paramByte1 == 1) { this.y40 = km.u4.s40(aq0.LI).zc0(); }  this((byte)-1, (byte)-1, (byte)-1, (byte)-1); Vo0(new I(this, pRn)); Xu("mm-rental-window"); Lo(Ml0.OH0(5511)); EP(1); this(); this.X2 = new rS(); if (this.y40.length > 7) { rS1.zG0(2); } else { rS1.zG0(3); }  this.JI = new Ip(); (this.EX = new Un(Ml0.OH0(5512))).tW(new Ly(this, paramByte2, parampA)); (this.o6 = new Un(Ml0.OH0(53))).tW(new b6(paramByte2, parampA)); this.WR = new j40[paramByte3]; this.B80 = new byte[paramByte3]; this.mM = new cr[paramByte3]; for (byte b1 = 0; b1 < paramByte3; b1 = (byte)(b1 + 1)) { cr cr1; this(this, b1); this.mM[b1] = cr1; this.B80[b1] = -1; }  (this.Z80 = new of()).LE(); this.Z80.JD0(new aK0(this)); cr01.Ya(this.X2); g0 g0; (g0 = this.JI.mE0()).Ya(this.X2); cr0 cr01; (cr01 = this.JI.d7()).ee0(this.JI.mE0().Mg((JG0[])this.mM)); cr0 cr02 = this.JI.d7(); byte b2; for (b2 = 0; b2 < paramByte3; b2 = (byte)(b2 + 1)) { if (b2 > 0) cr02.Em0();  cr02.Ya(this.mM[b2]); }  g0.ee0(cr02); if ((paramByte4 & 0x1) != 0) { cr01.ee0(this.JI.vo0(new JG0[] { this.EX, this.o6 })).Em0(); g0.ee0(this.JI.AUX(new JG0[] { this.EX, this.o6 })); } else { cr01.ee0(this.JI.AUX(new JG0[] { this.EX })).Em0(); g0.ee0(this.JI.vo0(new JG0[] { this.EX })); }  this.JI.WN(cr01); this.JI.rK0(g0); J8(this.JI); if ((paramByte4 & 0x8) != 0) for (byte b = 0; b < paramByte3; b = (byte)(b + 1)) ZC0(b);   Og(); Ye0(); } public final void Og() { this(); Ip ip; cr0 cr0; g0 g0; this(ip); this(ip); byte b; j40[] arrayOfJ40; int i; byte b1; for (this.ly = new Wp[7], b = 0, i = (arrayOfJ40 = this.y40).length, b1 = 0; b1 < i; ) { UD0 uD0 = On.v30().lpT3(j401.Zs.Cw0); j40 j401; if ((j401 = arrayOfJ40[b1]) != null && (this.Z80.F2.length() <= 0 || LF.M60(uD0.o60(false), this.Z80.F2.toString().toLowerCase()))) { boolean bool; Wp arrayOfWp[] = this.ly, wp = new Wp(); if (this.yv != 2) { bool = true; } else { bool = false; }  this(this, j401, b, bool); arrayOfWp[b] = wp; if ((b = (byte)(b + 1)) % 7 == 0) { b = 0; cr0.ee0((new g0(ip)).Mg((JG0[])this.ly)); g0.ee0((new cr0(ip)).Mg((JG0[])this.ly)); }  }  b1++; }  if (b > 0) { Wp[] arrayOfWp; for (arrayOfWp = new Wp[b], i = 0; i < b; ) { arrayOfWp[i] = this.ly[i]; i++; }  cr0.ee0((new g0(ip)).Mg((JG0[])arrayOfWp));
/*    */       
/* 21 */       g0.ee0((new cr0(ip)).Mg((JG0[])arrayOfWp)); }  ip.WN(cr0); ip.rK0(g0); this.X2.Gz0(ip); Ye0(); super
/* 22 */       .d40(); }
/*    */ 
/*    */   
/*    */   public final void EX(nY paramnY) {}
/*    */   
/*    */   public final void d40() {
/*    */     super.d40();
/*    */   }
/*    */   
/*    */   public final void Ye0() {
/*    */     // Byte code:
/*    */     //   0: aload_0
/*    */     //   1: dup
/*    */     //   2: getfield z20 : Lf/Lw;
/*    */     //   5: invokevirtual clear : ()V
/*    */     //   8: getfield M9 : Lf/Lw;
/*    */     //   11: invokevirtual clear : ()V
/*    */     //   14: iconst_0
/*    */     //   15: istore_1
/*    */     //   16: iload_1
/*    */     //   17: aload_0
/*    */     //   18: getfield WR : [Lf/j40;
/*    */     //   21: dup
/*    */     //   22: astore_2
/*    */     //   23: arraylength
/*    */     //   24: if_icmpge -> 81
/*    */     //   27: aload_2
/*    */     //   28: iload_1
/*    */     //   29: aaload
/*    */     //   30: dup
/*    */     //   31: astore_2
/*    */     //   32: ifnonnull -> 38
/*    */     //   35: goto -> 73
/*    */     //   38: aload_0
/*    */     //   39: dup
/*    */     //   40: getfield z20 : Lf/Lw;
/*    */     //   43: aload_2
/*    */     //   44: getfield Zs : Lf/Q90;
/*    */     //   47: getfield Cw0 : S
/*    */     //   50: invokevirtual Ye0 : (S)Z
/*    */     //   53: pop
/*    */     //   54: getfield M9 : Lf/Lw;
/*    */     //   57: aload_0
/*    */     //   58: getfield WR : [Lf/j40;
/*    */     //   61: iload_1
/*    */     //   62: aaload
/*    */     //   63: getfield Zs : Lf/Q90;
/*    */     //   66: invokevirtual p10 : ()S
/*    */     //   69: invokevirtual Ye0 : (S)Z
/*    */     //   72: pop
/*    */     //   73: iload_1
/*    */     //   74: iconst_1
/*    */     //   75: iadd
/*    */     //   76: i2b
/*    */     //   77: istore_1
/*    */     //   78: goto -> 16
/*    */     //   81: iconst_0
/*    */     //   82: istore_1
/*    */     //   83: iconst_0
/*    */     //   84: istore_2
/*    */     //   85: iload_2
/*    */     //   86: aload_0
/*    */     //   87: getfield WR : [Lf/j40;
/*    */     //   90: dup
/*    */     //   91: astore_3
/*    */     //   92: arraylength
/*    */     //   93: if_icmpge -> 112
/*    */     //   96: aload_3
/*    */     //   97: iload_2
/*    */     //   98: aaload
/*    */     //   99: ifnonnull -> 104
/*    */     //   102: iconst_1
/*    */     //   103: istore_1
/*    */     //   104: iload_2
/*    */     //   105: iconst_1
/*    */     //   106: iadd
/*    */     //   107: i2b
/*    */     //   108: istore_2
/*    */     //   109: goto -> 85
/*    */     //   112: aload_0
/*    */     //   113: getfield ly : [Lf/Wp;
/*    */     //   116: dup
/*    */     //   117: astore_2
/*    */     //   118: arraylength
/*    */     //   119: istore_3
/*    */     //   120: iconst_0
/*    */     //   121: istore #4
/*    */     //   123: iload #4
/*    */     //   125: iload_3
/*    */     //   126: if_icmpge -> 752
/*    */     //   129: aload_2
/*    */     //   130: iload #4
/*    */     //   132: aaload
/*    */     //   133: dup
/*    */     //   134: astore #5
/*    */     //   136: ifnonnull -> 142
/*    */     //   139: goto -> 746
/*    */     //   142: aload #5
/*    */     //   144: dup
/*    */     //   145: dup
/*    */     //   146: aconst_null
/*    */     //   147: putfield z4 : Ljava/lang/Object;
/*    */     //   150: invokevirtual zn : ()V
/*    */     //   153: getfield db0 : Lf/I;
/*    */     //   156: ifnonnull -> 192
/*    */     //   159: aload #5
/*    */     //   161: new f/I
/*    */     //   164: dup
/*    */     //   165: astore #6
/*    */     //   167: new f/Ja0
/*    */     //   170: dup
/*    */     //   171: astore #7
/*    */     //   173: aload #5
/*    */     //   175: invokespecial <init> : (Lf/JG0;)V
/*    */     //   178: getstatic f/pRn.WHITE : Lf/pRn;
/*    */     //   181: aload #7
/*    */     //   183: swap
/*    */     //   184: invokespecial <init> : (Lf/I7;Lf/pRn;)V
/*    */     //   187: aload #6
/*    */     //   189: putfield db0 : Lf/I;
/*    */     //   192: aload #5
/*    */     //   194: getfield jC : Lf/j40;
/*    */     //   197: getfield Zs : Lf/Q90;
/*    */     //   200: invokevirtual YC : ()Z
/*    */     //   203: ifne -> 718
/*    */     //   206: aload #5
/*    */     //   208: getfield jC : Lf/j40;
/*    */     //   211: getfield Zs : Lf/Q90;
/*    */     //   214: getfield Cw0 : S
/*    */     //   217: lookupswitch default -> 268, 150 -> 272, 249 -> 272, 384 -> 272, 493 -> 272, 647 -> 272
/*    */     //   268: iconst_0
/*    */     //   269: goto -> 273
/*    */     //   272: iconst_1
/*    */     //   273: ifeq -> 279
/*    */     //   276: goto -> 718
/*    */     //   279: aload_0
/*    */     //   280: getfield WR : [Lf/j40;
/*    */     //   283: invokestatic asList : ([Ljava/lang/Object;)Ljava/util/List;
/*    */     //   286: aload #5
/*    */     //   288: getfield jC : Lf/j40;
/*    */     //   291: invokeinterface contains : (Ljava/lang/Object;)Z
/*    */     //   296: ifeq -> 397
/*    */     //   299: aload_0
/*    */     //   300: getfield yv : B
/*    */     //   303: iconst_2
/*    */     //   304: if_icmpne -> 347
/*    */     //   307: aload #5
/*    */     //   309: getfield jC : Lf/j40;
/*    */     //   312: dup
/*    */     //   313: astore #6
/*    */     //   315: ifnonnull -> 326
/*    */     //   318: ldc_w ''
/*    */     //   321: astore #6
/*    */     //   323: goto -> 333
/*    */     //   326: aload #6
/*    */     //   328: invokevirtual m : ()Ljava/lang/String;
/*    */     //   331: astore #6
/*    */     //   333: aload #5
/*    */     //   335: dup
/*    */     //   336: aload #6
/*    */     //   338: putfield z4 : Ljava/lang/Object;
/*    */     //   341: invokevirtual zn : ()V
/*    */     //   344: goto -> 366
/*    */     //   347: aload #5
/*    */     //   349: dup
/*    */     //   350: dup
/*    */     //   351: getfield jC : Lf/j40;
/*    */     //   354: iconst_0
/*    */     //   355: iconst_0
/*    */     //   356: iconst_0
/*    */     //   357: invokestatic Zs0 : (Lf/j40;ZZZ)Ljava/lang/String;
/*    */     //   360: putfield z4 : Ljava/lang/Object;
/*    */     //   363: invokevirtual zn : ()V
/*    */     //   366: aload #5
/*    */     //   368: dup
/*    */     //   369: iconst_0
/*    */     //   370: invokevirtual sk0 : (Z)V
/*    */     //   373: getfield db0 : Lf/I;
/*    */     //   376: new f/pRn
/*    */     //   379: dup
/*    */     //   380: iconst_0
/*    */     //   381: iconst_0
/*    */     //   382: iconst_0
/*    */     //   383: bipush #55
/*    */     //   385: invokespecial <init> : (BBBB)V
/*    */     //   388: sipush #250
/*    */     //   391: invokevirtual sz : (Lf/pRn;I)V
/*    */     //   394: goto -> 746
/*    */     //   397: aload_0
/*    */     //   398: getfield rb : B
/*    */     //   401: iconst_4
/*    */     //   402: iand
/*    */     //   403: ifeq -> 471
/*    */     //   406: aload_0
/*    */     //   407: getfield z20 : Lf/Lw;
/*    */     //   410: aload #5
/*    */     //   412: getfield jC : Lf/j40;
/*    */     //   415: getfield Zs : Lf/Q90;
/*    */     //   418: getfield Cw0 : S
/*    */     //   421: invokevirtual Fb : (S)Z
/*    */     //   424: ifeq -> 471
/*    */     //   427: aload #5
/*    */     //   429: dup
/*    */     //   430: dup2
/*    */     //   431: sipush #5714
/*    */     //   434: invokestatic OH0 : (I)Ljava/lang/String;
/*    */     //   437: putfield z4 : Ljava/lang/Object;
/*    */     //   440: invokevirtual zn : ()V
/*    */     //   443: iconst_0
/*    */     //   444: invokevirtual sk0 : (Z)V
/*    */     //   447: getfield db0 : Lf/I;
/*    */     //   450: new f/pRn
/*    */     //   453: dup
/*    */     //   454: iconst_0
/*    */     //   455: iconst_0
/*    */     //   456: iconst_0
/*    */     //   457: bipush #55
/*    */     //   459: invokespecial <init> : (BBBB)V
/*    */     //   462: sipush #250
/*    */     //   465: invokevirtual sz : (Lf/pRn;I)V
/*    */     //   468: goto -> 746
/*    */     //   471: aload_0
/*    */     //   472: getfield rb : B
/*    */     //   475: iconst_2
/*    */     //   476: iand
/*    */     //   477: ifeq -> 559
/*    */     //   480: aload #5
/*    */     //   482: getfield jC : Lf/j40;
/*    */     //   485: getfield Zs : Lf/Q90;
/*    */     //   488: invokevirtual p10 : ()S
/*    */     //   491: ifle -> 559
/*    */     //   494: aload_0
/*    */     //   495: getfield M9 : Lf/Lw;
/*    */     //   498: aload #5
/*    */     //   500: getfield jC : Lf/j40;
/*    */     //   503: getfield Zs : Lf/Q90;
/*    */     //   506: invokevirtual p10 : ()S
/*    */     //   509: invokevirtual Fb : (S)Z
/*    */     //   512: ifeq -> 559
/*    */     //   515: aload #5
/*    */     //   517: dup
/*    */     //   518: dup2
/*    */     //   519: sipush #5716
/*    */     //   522: invokestatic OH0 : (I)Ljava/lang/String;
/*    */     //   525: putfield z4 : Ljava/lang/Object;
/*    */     //   528: invokevirtual zn : ()V
/*    */     //   531: iconst_0
/*    */     //   532: invokevirtual sk0 : (Z)V
/*    */     //   535: getfield db0 : Lf/I;
/*    */     //   538: new f/pRn
/*    */     //   541: dup
/*    */     //   542: iconst_0
/*    */     //   543: iconst_0
/*    */     //   544: iconst_0
/*    */     //   545: bipush #55
/*    */     //   547: invokespecial <init> : (BBBB)V
/*    */     //   550: sipush #250
/*    */     //   553: invokevirtual sz : (Lf/pRn;I)V
/*    */     //   556: goto -> 746
/*    */     //   559: aload_0
/*    */     //   560: getfield rb : B
/*    */     //   563: bipush #16
/*    */     //   565: iand
/*    */     //   566: ifeq -> 629
/*    */     //   569: aload #5
/*    */     //   571: getfield jC : Lf/j40;
/*    */     //   574: getfield Zs : Lf/Q90;
/*    */     //   577: getfield od : B
/*    */     //   580: bipush #50
/*    */     //   582: if_icmple -> 629
/*    */     //   585: aload #5
/*    */     //   587: dup
/*    */     //   588: dup2
/*    */     //   589: sipush #5730
/*    */     //   592: invokestatic OH0 : (I)Ljava/lang/String;
/*    */     //   595: putfield z4 : Ljava/lang/Object;
/*    */     //   598: invokevirtual zn : ()V
/*    */     //   601: iconst_0
/*    */     //   602: invokevirtual sk0 : (Z)V
/*    */     //   605: getfield db0 : Lf/I;
/*    */     //   608: new f/pRn
/*    */     //   611: dup
/*    */     //   612: iconst_0
/*    */     //   613: iconst_0
/*    */     //   614: iconst_0
/*    */     //   615: bipush #55
/*    */     //   617: invokespecial <init> : (BBBB)V
/*    */     //   620: sipush #250
/*    */     //   623: invokevirtual sz : (Lf/pRn;I)V
/*    */     //   626: goto -> 746
/*    */     //   629: aload_0
/*    */     //   630: getfield yv : B
/*    */     //   633: iconst_2
/*    */     //   634: if_icmpne -> 677
/*    */     //   637: aload #5
/*    */     //   639: getfield jC : Lf/j40;
/*    */     //   642: dup
/*    */     //   643: astore #6
/*    */     //   645: ifnonnull -> 656
/*    */     //   648: ldc_w ''
/*    */     //   651: astore #6
/*    */     //   653: goto -> 663
/*    */     //   656: aload #6
/*    */     //   658: invokevirtual m : ()Ljava/lang/String;
/*    */     //   661: astore #6
/*    */     //   663: aload #5
/*    */     //   665: dup
/*    */     //   666: aload #6
/*    */     //   668: putfield z4 : Ljava/lang/Object;
/*    */     //   671: invokevirtual zn : ()V
/*    */     //   674: goto -> 696
/*    */     //   677: aload #5
/*    */     //   679: dup
/*    */     //   680: dup
/*    */     //   681: getfield jC : Lf/j40;
/*    */     //   684: iconst_0
/*    */     //   685: iconst_0
/*    */     //   686: iconst_0
/*    */     //   687: invokestatic Zs0 : (Lf/j40;ZZZ)Ljava/lang/String;
/*    */     //   690: putfield z4 : Ljava/lang/Object;
/*    */     //   693: invokevirtual zn : ()V
/*    */     //   696: aload #5
/*    */     //   698: dup
/*    */     //   699: iconst_1
/*    */     //   700: invokevirtual sk0 : (Z)V
/*    */     //   703: getfield db0 : Lf/I;
/*    */     //   706: getstatic f/pRn.WHITE : Lf/pRn;
/*    */     //   709: sipush #250
/*    */     //   712: invokevirtual sz : (Lf/pRn;I)V
/*    */     //   715: goto -> 746
/*    */     //   718: aload #5
/*    */     //   720: dup
/*    */     //   721: iconst_0
/*    */     //   722: invokevirtual sk0 : (Z)V
/*    */     //   725: getfield db0 : Lf/I;
/*    */     //   728: new f/pRn
/*    */     //   731: dup
/*    */     //   732: iconst_0
/*    */     //   733: iconst_0
/*    */     //   734: iconst_0
/*    */     //   735: bipush #55
/*    */     //   737: invokespecial <init> : (BBBB)V
/*    */     //   740: sipush #250
/*    */     //   743: invokevirtual sz : (Lf/pRn;I)V
/*    */     //   746: iinc #4, 1
/*    */     //   749: goto -> 123
/*    */     //   752: aload_0
/*    */     //   753: getfield EX : Lf/Un;
/*    */     //   756: iload_1
/*    */     //   757: iconst_1
/*    */     //   758: ixor
/*    */     //   759: invokevirtual sk0 : (Z)V
/*    */     //   762: return
/*    */     // Line number table:
/*    */     //   Java source line number -> byte code offset
/*    */     //   #1	-> 44
/*    */     //   #2	-> 47
/*    */     //   #3	-> 50
/*    */     //   #4	-> 63
/*    */     //   #5	-> 66
/*    */     //   #6	-> 147
/*    */     //   #7	-> 153
/*    */     //   #8	-> 161
/*    */     //   #9	-> 167
/*    */     //   #10	-> 178
/*    */     //   #11	-> 189
/*    */     //   #12	-> 194
/*    */     //   #13	-> 197
/*    */     //   #14	-> 200
/*    */     //   #15	-> 208
/*    */     //   #16	-> 211
/*    */     //   #17	-> 214
/*    */     //   #18	-> 280
/*    */     //   #19	-> 288
/*    */     //   #20	-> 291
/*    */     //   #21	-> 309
/*    */     //   #22	-> 318
/*    */     //   #23	-> 338
/*    */     //   #24	-> 351
/*    */     //   #25	-> 357
/*    */     //   #26	-> 360
/*    */     //   #27	-> 370
/*    */     //   #28	-> 373
/*    */     //   #29	-> 376
/*    */     //   #30	-> 412
/*    */     //   #31	-> 415
/*    */     //   #32	-> 418
/*    */     //   #33	-> 421
/*    */     //   #34	-> 437
/*    */     //   #35	-> 444
/*    */     //   #36	-> 447
/*    */     //   #37	-> 450
/*    */     //   #38	-> 482
/*    */     //   #39	-> 485
/*    */     //   #40	-> 488
/*    */     //   #41	-> 500
/*    */     //   #42	-> 503
/*    */     //   #43	-> 506
/*    */     //   #44	-> 525
/*    */     //   #45	-> 532
/*    */     //   #46	-> 535
/*    */     //   #47	-> 538
/*    */     //   #48	-> 571
/*    */     //   #49	-> 574
/*    */     //   #50	-> 577
/*    */     //   #51	-> 592
/*    */     //   #52	-> 595
/*    */     //   #53	-> 602
/*    */     //   #54	-> 605
/*    */     //   #55	-> 608
/*    */     //   #56	-> 639
/*    */     //   #57	-> 648
/*    */     //   #58	-> 668
/*    */     //   #59	-> 681
/*    */     //   #60	-> 687
/*    */     //   #61	-> 690
/*    */     //   #62	-> 700
/*    */     //   #63	-> 703
/*    */     //   #64	-> 706
/*    */     //   #65	-> 725
/*    */     //   #66	-> 728
/*    */   } }


/* Location:              /Users/vnnsnnt/Documents/Codespace/JavaWorkspace/RedTrainer/src/main/java/org/trainer/client/PokeMMO.jar!/f/tR.class
 * Java compiler version: 8 (52.0)
 * JD-Core Version:       1.1.3
 */