/* 1 */ package f;public final class tU extends JG0 { private void p50(j40 paramj40) { ra0(); R8 r8 = km.u4; int i = paramj40.Jg;
/*   */ 
/*   */ 
/*   */     
/* 5 */     String str = this.WE.F2.PH0.toString();
/* 6 */     r8.e20
/* 7 */       .W3(new En0(i, this)); }
/*   */ 
/*   */   
/*   */   public final Ip bv;
/*   */   public final of WE;
/*   */   
/*   */   public tU(j40 paramj40) {
/*   */     // Byte code:
/*   */     //   0: aload_1
/*   */     //   1: aload_0
/*   */     //   2: dup
/*   */     //   3: invokespecial <init> : ()V
/*   */     //   6: ldc 'confirm-widget'
/*   */     //   8: invokevirtual Xu : (Ljava/lang/String;)V
/*   */     //   11: new f/Ip
/*   */     //   14: dup
/*   */     //   15: astore_2
/*   */     //   16: aload_0
/*   */     //   17: aload_2
/*   */     //   18: dup
/*   */     //   19: invokespecial <init> : ()V
/*   */     //   22: putfield bv : Lf/Ip;
/*   */     //   25: ldc 'confirm-panel'
/*   */     //   27: invokevirtual Xu : (Ljava/lang/String;)V
/*   */     //   30: new f/dQ
/*   */     //   33: dup
/*   */     //   34: astore_3
/*   */     //   35: aload_1
/*   */     //   36: invokevirtual Hn : ()Ljava/lang/String;
/*   */     //   39: sipush #1845
/*   */     //   42: swap
/*   */     //   43: invokestatic Go : (ILjava/lang/String;)Ljava/lang/String;
/*   */     //   46: invokespecial <init> : (Ljava/lang/String;)V
/*   */     //   49: new f/of
/*   */     //   52: dup
/*   */     //   53: dup
/*   */     //   54: astore #4
/*   */     //   56: aload_3
/*   */     //   57: aload #4
/*   */     //   59: aload_0
/*   */     //   60: aload #4
/*   */     //   62: dup
/*   */     //   63: invokespecial <init> : ()V
/*   */     //   66: putfield WE : Lf/of;
/*   */     //   69: invokevirtual LE : ()V
/*   */     //   72: invokevirtual Xy : ()Ljava/lang/String;
/*   */     //   75: pop
/*   */     //   76: bipush #16
/*   */     //   78: invokevirtual co : (I)V
/*   */     //   81: ldc '[a-zA-Z0-9 ,.!?"'\-~ÀÁÂÃÄÅÆÇÈÉÊËÌÍÎÏÐÑÒÓÔÕÖØÙÚÛÜÝÞßàáâãäåæçèéêëìíîïðñòóôõöøùúûüýþÿ]'
/*   */     //   83: invokevirtual Lpt5 : (Ljava/lang/String;)V
/*   */     //   86: invokevirtual eC : ()Lf/Q90;
/*   */     //   89: invokevirtual xt : ()Z
/*   */     //   92: ifeq -> 107
/*   */     //   95: aload #4
/*   */     //   97: aload_1
/*   */     //   98: invokevirtual eC : ()Lf/Q90;
/*   */     //   101: invokevirtual AA0 : ()Ljava/lang/String;
/*   */     //   104: invokevirtual Zh : (Ljava/lang/String;)V
/*   */     //   107: aload_0
/*   */     //   108: aload_2
/*   */     //   109: dup
/*   */     //   110: dup
/*   */     //   111: dup2
/*   */     //   112: new f/Un
/*   */     //   115: dup
/*   */     //   116: astore #5
/*   */     //   118: aload_0
/*   */     //   119: aload_1
/*   */     //   120: aload #5
/*   */     //   122: bipush #60
/*   */     //   124: invokestatic OH0 : (I)Ljava/lang/String;
/*   */     //   127: invokespecial <init> : (Ljava/lang/String;)V
/*   */     //   130: <illegal opcode> run : (Lf/tU;Lf/j40;)Ljava/lang/Runnable;
/*   */     //   135: invokevirtual tW : (Ljava/lang/Runnable;)V
/*   */     //   138: new f/Un
/*   */     //   141: dup
/*   */     //   142: astore_1
/*   */     //   143: aload_0
/*   */     //   144: aload_1
/*   */     //   145: bipush #53
/*   */     //   147: invokestatic OH0 : (I)Ljava/lang/String;
/*   */     //   150: invokespecial <init> : (Ljava/lang/String;)V
/*   */     //   153: <illegal opcode> run : (Lf/tU;)Ljava/lang/Runnable;
/*   */     //   158: invokevirtual tW : (Ljava/lang/Runnable;)V
/*   */     //   161: invokevirtual d7 : ()Lf/cr0;
/*   */     //   164: aload_3
/*   */     //   165: invokevirtual Ya : (Lf/JG0;)Lf/U90;
/*   */     //   168: aload #4
/*   */     //   170: invokevirtual Ya : (Lf/JG0;)Lf/U90;
/*   */     //   173: aload_2
/*   */     //   174: invokevirtual d7 : ()Lf/cr0;
/*   */     //   177: iconst_2
/*   */     //   178: anewarray f/JG0
/*   */     //   181: dup
/*   */     //   182: dup
/*   */     //   183: iconst_0
/*   */     //   184: aload #5
/*   */     //   186: aastore
/*   */     //   187: iconst_1
/*   */     //   188: aload_1
/*   */     //   189: aastore
/*   */     //   190: invokevirtual Mg : ([Lf/JG0;)Lf/U90;
/*   */     //   193: invokevirtual ee0 : (Lf/U90;)Lf/U90;
/*   */     //   196: invokevirtual Em0 : ()Lf/U90;
/*   */     //   199: invokevirtual WN : (Lf/U90;)V
/*   */     //   202: invokevirtual mE0 : ()Lf/g0;
/*   */     //   205: aload_3
/*   */     //   206: invokevirtual Ya : (Lf/JG0;)Lf/U90;
/*   */     //   209: aload #4
/*   */     //   211: invokevirtual Ya : (Lf/JG0;)Lf/U90;
/*   */     //   214: aload_2
/*   */     //   215: invokevirtual mE0 : ()Lf/g0;
/*   */     //   218: aload #5
/*   */     //   220: invokevirtual Ya : (Lf/JG0;)Lf/U90;
/*   */     //   223: aload_1
/*   */     //   224: invokevirtual Ya : (Lf/JG0;)Lf/U90;
/*   */     //   227: invokevirtual ee0 : (Lf/U90;)Lf/U90;
/*   */     //   230: invokevirtual rK0 : (Lf/U90;)V
/*   */     //   233: invokevirtual J8 : (Lf/JG0;)V
/*   */     //   236: return
/*   */   }
/*   */   
/*   */   public final void LM(throws paramthrows) {
/*   */     VA0.c90(this.WE);
/*   */   }
/*   */   
/*   */   public final void d40() {
/*   */     this.bv.mM();
/*   */     mM();
/*   */     ec(et.Wi0, 0);
/*   */   } }


/* Location:              /Users/vnnsnnt/Documents/Codespace/JavaWorkspace/RedTrainer/src/main/java/org/trainer/client/PokeMMO.jar!/f/tU.class
 * Java compiler version: 8 (52.0)
 * JD-Core Version:       1.1.3
 */