package f;

public final class U80 implements Runnable {
  public U80(XF paramXF, nv0 paramnv0, int paramInt) {}
  
  public final void run() {
    // Byte code:
    //   0: aload_0
    //   1: dup
    //   2: dup
    //   3: getfield Ev : Lf/XF;
    //   6: astore_0
    //   7: getfield R90 : Lf/nv0;
    //   10: astore_1
    //   11: getfield tQ : I
    //   14: dup
    //   15: istore_2
    //   16: iflt -> 732
    //   19: iload_2
    //   20: aload_0
    //   21: getfield uG0 : [Lf/nv0;
    //   24: dup
    //   25: astore_3
    //   26: arraylength
    //   27: if_icmple -> 33
    //   30: goto -> 737
    //   33: aload_0
    //   34: iload_2
    //   35: aload_0
    //   36: aload_3
    //   37: iload_2
    //   38: aaload
    //   39: dup
    //   40: astore_2
    //   41: getfield rd0 : Lf/WD;
    //   44: astore_3
    //   45: getfield x1 : Lf/Un;
    //   48: aload_2
    //   49: getfield v10 : Z
    //   52: invokevirtual sk0 : (Z)V
    //   55: putfield gM : I
    //   58: aload_3
    //   59: aload_0
    //   60: dup
    //   61: dup
    //   62: getfield AE : Lf/dQ;
    //   65: aload_3
    //   66: getfield iz : I
    //   69: invokestatic OH0 : (I)Ljava/lang/String;
    //   72: invokevirtual E1 : (Ljava/lang/String;)V
    //   75: getfield Ml : Lf/vF0;
    //   78: getfield TS : Lf/rH;
    //   81: iconst_1
    //   82: anewarray f/pe0
    //   85: dup
    //   86: invokestatic ZZ : ()Lf/interface;
    //   89: aload_3
    //   90: aconst_null
    //   91: aconst_null
    //   92: invokevirtual Wt : (Lf/Q90;Lf/Mx;)Lf/Ht0;
    //   95: getfield zm0 : B
    //   98: invokevirtual xk0 : (I)Lf/pe0;
    //   101: iconst_0
    //   102: swap
    //   103: aastore
    //   104: invokevirtual Pn : ([Lf/pe0;)Lf/JG0;
    //   107: pop
    //   108: getfield bh0 : Lf/Ro0;
    //   111: aload_3
    //   112: getfield hR : I
    //   115: invokestatic OH0 : (I)Ljava/lang/String;
    //   118: ldc '\|br\|'
    //   120: ldc '\\n'
    //   122: invokevirtual replaceAll : (Ljava/lang/String;Ljava/lang/String;)Ljava/lang/String;
    //   125: invokevirtual E1 : (Ljava/lang/String;)V
    //   128: getfield Di0 : S
    //   131: ifne -> 146
    //   134: aload_0
    //   135: getfield XC : Lf/dQ;
    //   138: ldc '--'
    //   140: invokevirtual E1 : (Ljava/lang/String;)V
    //   143: goto -> 176
    //   146: aload_0
    //   147: getfield XC : Lf/dQ;
    //   150: new java/lang/StringBuilder
    //   153: dup
    //   154: aload_3
    //   155: swap
    //   156: invokespecial <init> : ()V
    //   159: getfield Di0 : S
    //   162: invokevirtual append : (I)Ljava/lang/StringBuilder;
    //   165: ldc ''
    //   167: invokevirtual append : (Ljava/lang/String;)Ljava/lang/StringBuilder;
    //   170: invokevirtual toString : ()Ljava/lang/String;
    //   173: invokevirtual E1 : (Ljava/lang/String;)V
    //   176: aload_3
    //   177: getfield Jp0 : B
    //   180: dup
    //   181: istore_2
    //   182: ifeq -> 227
    //   185: iload_2
    //   186: bipush #101
    //   188: if_icmpne -> 194
    //   191: goto -> 227
    //   194: aload_0
    //   195: getfield C1 : Lf/dQ;
    //   198: new java/lang/StringBuilder
    //   201: dup
    //   202: aload_3
    //   203: swap
    //   204: invokespecial <init> : ()V
    //   207: getfield Jp0 : B
    //   210: invokevirtual append : (I)Ljava/lang/StringBuilder;
    //   213: ldc ''
    //   215: invokevirtual append : (Ljava/lang/String;)Ljava/lang/StringBuilder;
    //   218: invokevirtual toString : ()Ljava/lang/String;
    //   221: invokevirtual E1 : (Ljava/lang/String;)V
    //   224: goto -> 236
    //   227: aload_0
    //   228: getfield C1 : Lf/dQ;
    //   231: ldc '100'
    //   233: invokevirtual E1 : (Ljava/lang/String;)V
    //   236: aload_0
    //   237: dup
    //   238: getfield fq0 : Lf/dQ;
    //   241: new java/lang/StringBuilder
    //   244: dup
    //   245: aload_3
    //   246: swap
    //   247: invokespecial <init> : ()V
    //   250: getfield nul : B
    //   253: invokevirtual append : (I)Ljava/lang/StringBuilder;
    //   256: ldc ''
    //   258: invokevirtual append : (Ljava/lang/String;)Ljava/lang/StringBuilder;
    //   261: invokevirtual toString : ()Ljava/lang/String;
    //   264: invokevirtual E1 : (Ljava/lang/String;)V
    //   267: getfield aUx : Lf/Px0;
    //   270: getstatic f/Px0.Ty : Lf/Px0;
    //   273: if_acmpeq -> 684
    //   276: aload_3
    //   277: getstatic f/bl0.DO : Lf/bl0;
    //   280: astore_2
    //   281: getfield HA : S
    //   284: aload_2
    //   285: getfield Nw0 : Lf/qw0;
    //   288: swap
    //   289: invokevirtual Z90 : (S)Ljava/lang/Object;
    //   292: checkcast f/Ni
    //   295: dup
    //   296: astore_2
    //   297: ifnonnull -> 312
    //   300: aload_0
    //   301: getfield YV : Lf/dQ;
    //   304: ldc '???'
    //   306: invokevirtual E1 : (Ljava/lang/String;)V
    //   309: goto -> 737
    //   312: aload_0
    //   313: getfield aUx : Lf/Px0;
    //   316: dup
    //   317: astore_3
    //   318: getstatic f/Px0.fJ0 : Lf/Px0;
    //   321: if_acmpne -> 398
    //   324: aload_2
    //   325: getfield Ut : S
    //   328: ifle -> 372
    //   331: aload_0
    //   332: getfield YV : Lf/dQ;
    //   335: new java/lang/StringBuilder
    //   338: dup
    //   339: aload_2
    //   340: swap
    //   341: invokespecial <init> : ()V
    //   344: getfield Ut : S
    //   347: invokevirtual append : (I)Ljava/lang/StringBuilder;
    //   350: ldc ' '
    //   352: invokevirtual append : (Ljava/lang/String;)Ljava/lang/StringBuilder;
    //   355: bipush #121
    //   357: invokestatic OH0 : (I)Ljava/lang/String;
    //   360: invokevirtual append : (Ljava/lang/String;)Ljava/lang/StringBuilder;
    //   363: invokevirtual toString : ()Ljava/lang/String;
    //   366: invokevirtual E1 : (Ljava/lang/String;)V
    //   369: goto -> 684
    //   372: aload_0
    //   373: getfield YV : Lf/dQ;
    //   376: ldc '??? '
    //   378: invokestatic df : (Ljava/lang/String;)Ljava/lang/StringBuilder;
    //   381: bipush #121
    //   383: invokestatic OH0 : (I)Ljava/lang/String;
    //   386: invokevirtual append : (Ljava/lang/String;)Ljava/lang/StringBuilder;
    //   389: invokevirtual toString : ()Ljava/lang/String;
    //   392: invokevirtual E1 : (Ljava/lang/String;)V
    //   395: goto -> 684
    //   398: aload_3
    //   399: getstatic f/Px0.py : Lf/Px0;
    //   402: if_acmpne -> 498
    //   405: aload_0
    //   406: aload_2
    //   407: getstatic f/Of.eH : Lf/Of;
    //   410: dup
    //   411: sipush #5086
    //   414: invokevirtual On0 : (S)Lf/LPT3;
    //   417: astore_2
    //   418: sipush #5087
    //   421: invokevirtual On0 : (S)Lf/LPT3;
    //   424: astore_3
    //   425: getfield Q70 : S
    //   428: istore #4
    //   430: getfield YV : Lf/dQ;
    //   433: iconst_4
    //   434: anewarray java/lang/String
    //   437: dup
    //   438: astore #5
    //   440: aload_3
    //   441: aload #5
    //   443: iload #4
    //   445: aload #5
    //   447: aload_2
    //   448: aload #5
    //   450: iload #4
    //   452: iconst_2
    //   453: imul
    //   454: invokestatic toString : (I)Ljava/lang/String;
    //   457: iconst_0
    //   458: swap
    //   459: aastore
    //   460: getfield Iu : I
    //   463: invokestatic OH0 : (I)Ljava/lang/String;
    //   466: iconst_1
    //   467: swap
    //   468: aastore
    //   469: invokestatic toString : (I)Ljava/lang/String;
    //   472: iconst_2
    //   473: swap
    //   474: aastore
    //   475: getfield Iu : I
    //   478: invokestatic OH0 : (I)Ljava/lang/String;
    //   481: iconst_3
    //   482: swap
    //   483: aastore
    //   484: sipush #1934
    //   487: aload #5
    //   489: invokestatic sB : (I[Ljava/lang/String;)Ljava/lang/String;
    //   492: invokevirtual E1 : (Ljava/lang/String;)V
    //   495: goto -> 684
    //   498: aload_3
    //   499: getstatic f/Px0.Rc0 : Lf/Px0;
    //   502: if_acmpne -> 561
    //   505: aload_0
    //   506: aload_2
    //   507: getstatic f/Of.eH : Lf/Of;
    //   510: sipush #5093
    //   513: invokevirtual On0 : (S)Lf/LPT3;
    //   516: astore_2
    //   517: getfield Q70 : S
    //   520: istore_3
    //   521: getfield YV : Lf/dQ;
    //   524: new java/lang/StringBuilder
    //   527: dup
    //   528: iload_3
    //   529: swap
    //   530: invokespecial <init> : ()V
    //   533: invokevirtual append : (I)Ljava/lang/StringBuilder;
    //   536: ldc_w 'x '
    //   539: invokevirtual append : (Ljava/lang/String;)Ljava/lang/StringBuilder;
    //   542: aload_2
    //   543: getfield Iu : I
    //   546: invokestatic OH0 : (I)Ljava/lang/String;
    //   549: invokevirtual append : (Ljava/lang/String;)Ljava/lang/StringBuilder;
    //   552: invokevirtual toString : ()Ljava/lang/String;
    //   555: invokevirtual E1 : (Ljava/lang/String;)V
    //   558: goto -> 684
    //   561: aload_2
    //   562: getfield aX : [Lf/kc;
    //   565: dup
    //   566: astore_2
    //   567: arraylength
    //   568: ifle -> 684
    //   571: aload_2
    //   572: new java/lang/StringBuilder
    //   575: dup
    //   576: astore_3
    //   577: invokespecial <init> : ()V
    //   580: arraylength
    //   581: istore #4
    //   583: iconst_0
    //   584: istore #5
    //   586: iload #5
    //   588: iload #4
    //   590: if_icmpge -> 673
    //   593: aload_3
    //   594: aload_2
    //   595: iload #5
    //   597: aaload
    //   598: astore #6
    //   600: getstatic f/Of.eH : Lf/Of;
    //   603: aload #6
    //   605: getfield Hu0 : S
    //   608: invokevirtual On0 : (S)Lf/LPT3;
    //   611: astore #7
    //   613: invokevirtual length : ()I
    //   616: ifle -> 626
    //   619: aload_3
    //   620: ldc '\\n'
    //   622: invokevirtual append : (Ljava/lang/String;)Ljava/lang/StringBuilder;
    //   625: pop
    //   626: aload_3
    //   627: new java/lang/StringBuilder
    //   630: dup
    //   631: aload #6
    //   633: swap
    //   634: invokespecial <init> : ()V
    //   637: getfield Oy : S
    //   640: invokevirtual append : (I)Ljava/lang/StringBuilder;
    //   643: ldc_w 'x '
    //   646: invokevirtual append : (Ljava/lang/String;)Ljava/lang/StringBuilder;
    //   649: aload #7
    //   651: getfield Iu : I
    //   654: invokestatic OH0 : (I)Ljava/lang/String;
    //   657: invokevirtual append : (Ljava/lang/String;)Ljava/lang/StringBuilder;
    //   660: invokevirtual toString : ()Ljava/lang/String;
    //   663: invokevirtual append : (Ljava/lang/String;)Ljava/lang/StringBuilder;
    //   666: pop
    //   667: iinc #5, 1
    //   670: goto -> 586
    //   673: aload_0
    //   674: getfield YV : Lf/dQ;
    //   677: aload_3
    //   678: invokevirtual toString : ()Ljava/lang/String;
    //   681: invokevirtual E1 : (Ljava/lang/String;)V
    //   684: aload_0
    //   685: getfield oK0 : [Lf/mc;
    //   688: aload_0
    //   689: getfield gM : I
    //   692: aaload
    //   693: invokevirtual p3 : ()Z
    //   696: ifne -> 737
    //   699: aload_1
    //   700: ifnull -> 719
    //   703: aload_0
    //   704: getfield oK0 : [Lf/mc;
    //   707: aload_1
    //   708: getfield ik0 : I
    //   711: aaload
    //   712: invokestatic c90 : (Lf/JG0;)Z
    //   715: pop
    //   716: goto -> 737
    //   719: aload_0
    //   720: getfield oK0 : [Lf/mc;
    //   723: iconst_0
    //   724: aaload
    //   725: invokestatic c90 : (Lf/JG0;)Z
    //   728: pop
    //   729: goto -> 737
    //   732: aload_0
    //   733: invokevirtual getClass : ()Ljava/lang/Class;
    //   736: pop
    //   737: return
    // Line number table:
    //   Java source line number -> byte code offset
    //   #1	-> 21
    //   #2	-> 26
    //   #3	-> 66
    //   #4	-> 69
    //   #5	-> 72
    //   #6	-> 78
    //   #7	-> 82
    //   #8	-> 92
    //   #9	-> 95
    //   #10	-> 98
    //   #11	-> 112
    //   #12	-> 118
    //   #13	-> 128
    //   #14	-> 135
    //   #15	-> 159
    //   #16	-> 162
    //   #17	-> 177
    //   #18	-> 195
    //   #19	-> 207
    //   #20	-> 210
    //   #21	-> 250
    //   #22	-> 253
    //   #23	-> 277
    //   #24	-> 281
    //   #25	-> 285
    //   #26	-> 289
    //   #27	-> 301
    //   #28	-> 325
    //   #29	-> 332
    //   #30	-> 344
    //   #31	-> 347
    //   #32	-> 376
    //   #33	-> 383
    //   #34	-> 407
    //   #35	-> 414
    //   #36	-> 425
    //   #37	-> 430
    //   #38	-> 460
    //   #39	-> 468
    //   #40	-> 475
    //   #41	-> 483
    //   #42	-> 507
    //   #43	-> 513
    //   #44	-> 517
    //   #45	-> 521
    //   #46	-> 543
    //   #47	-> 549
    //   #48	-> 562
    //   #49	-> 567
    //   #50	-> 600
    //   #51	-> 605
    //   #52	-> 608
    //   #53	-> 637
    //   #54	-> 640
    //   #55	-> 651
    //   #56	-> 657
    //   #57	-> 733
  }
}


/* Location:              /Users/vnnsnnt/Documents/Codespace/JavaWorkspace/RedTrainer/src/main/java/org/trainer/client/PokeMMO.jar!/f/U80.class
 * Java compiler version: 8 (52.0)
 * JD-Core Version:       1.1.3
 */