/*    */ package f;
/*  2 */ public final class Uh extends Ip implements r60 { public final wg0 jv; public Ip k40; public p30 Wu0; public static void aR(wg0 paramwg0, Y paramY, j40 paramj40, byte paramByte) { short s = paramY.Lh.p1;
/*  3 */     int i = paramY.Lh.Wy;
/*  4 */     int j = paramj40.Jg;
/*  5 */     paramwg0.ZN(s, i, j, (short)1, paramByte); }
/*    */   public mc[] rB;
/*    */   public int Mo0;
/*    */   public int Mu; public Uh(wg0 paramwg0, Y paramY, j40 paramj40) { // Byte code:
/*    */     //   0: aload_0
/*    */     //   1: dup
/*    */     //   2: dup
/*    */     //   3: aload_1
/*    */     //   4: aload_0
/*    */     //   5: dup
/*    */     //   6: dup
/*    */     //   7: invokespecial <init> : ()V
/*    */     //   10: iconst_0
/*    */     //   11: putfield Mo0 : I
/*    */     //   14: iconst_2
/*    */     //   15: putfield Mu : I
/*    */     //   18: putfield jv : Lf/wg0;
/*    */     //   21: ldc 'tm-learn-inner-panel'
/*    */     //   23: invokevirtual Xu : (Ljava/lang/String;)V
/*    */     //   26: iconst_5
/*    */     //   27: anewarray f/mc
/*    */     //   30: putfield rB : [Lf/mc;
/*    */     //   33: iconst_0
/*    */     //   34: istore #4
/*    */     //   36: iload #4
/*    */     //   38: aload_0
/*    */     //   39: getfield rB : [Lf/mc;
/*    */     //   42: dup
/*    */     //   43: astore #5
/*    */     //   45: arraylength
/*    */     //   46: if_icmpge -> 104
/*    */     //   49: iload #4
/*    */     //   51: aload_0
/*    */     //   52: dup
/*    */     //   53: aload #5
/*    */     //   55: iload #4
/*    */     //   57: new f/mc
/*    */     //   60: dup
/*    */     //   61: astore #5
/*    */     //   63: ldc ''
/*    */     //   65: ldc ''
/*    */     //   67: invokespecial <init> : (Ljava/lang/String;Ljava/lang/String;)V
/*    */     //   70: aload #5
/*    */     //   72: aastore
/*    */     //   73: getfield rB : [Lf/mc;
/*    */     //   76: iload #4
/*    */     //   78: aaload
/*    */     //   79: ldc 'item-move-dialog-button'
/*    */     //   81: invokevirtual Xu : (Ljava/lang/String;)V
/*    */     //   84: getfield rB : [Lf/mc;
/*    */     //   87: iload #4
/*    */     //   89: aaload
/*    */     //   90: getstatic f/et.COM2 : Lf/et;
/*    */     //   93: invokevirtual C70 : (Lf/et;)V
/*    */     //   96: iconst_1
/*    */     //   97: iadd
/*    */     //   98: i2b
/*    */     //   99: istore #4
/*    */     //   101: goto -> 36
/*    */     //   104: iconst_0
/*    */     //   105: istore #4
/*    */     //   107: iload #4
/*    */     //   109: aload_0
/*    */     //   110: getfield rB : [Lf/mc;
/*    */     //   113: dup
/*    */     //   114: astore #5
/*    */     //   116: arraylength
/*    */     //   117: if_icmpge -> 369
/*    */     //   120: iload #4
/*    */     //   122: iconst_4
/*    */     //   123: if_icmpne -> 138
/*    */     //   126: aload_2
/*    */     //   127: invokevirtual Ng : ()Lf/LPT3;
/*    */     //   130: invokevirtual a90 : ()S
/*    */     //   133: istore #5
/*    */     //   135: goto -> 149
/*    */     //   138: aload_3
/*    */     //   139: invokevirtual eC : ()Lf/Q90;
/*    */     //   142: iload #4
/*    */     //   144: invokevirtual Fp0 : (I)S
/*    */     //   147: istore #5
/*    */     //   149: iload #5
/*    */     //   151: ifne -> 215
/*    */     //   154: aload_0
/*    */     //   155: dup
/*    */     //   156: dup
/*    */     //   157: dup2
/*    */     //   158: getfield rB : [Lf/mc;
/*    */     //   161: iload #4
/*    */     //   163: aaload
/*    */     //   164: ldc '-'
/*    */     //   166: invokevirtual s6 : (Ljava/lang/String;)V
/*    */     //   169: getfield rB : [Lf/mc;
/*    */     //   172: iload #4
/*    */     //   174: aaload
/*    */     //   175: ldc ''
/*    */     //   177: invokevirtual Ep0 : (Ljava/lang/String;)V
/*    */     //   180: getfield rB : [Lf/mc;
/*    */     //   183: iload #4
/*    */     //   185: aaload
/*    */     //   186: iconst_0
/*    */     //   187: invokevirtual sk0 : (Z)V
/*    */     //   190: getfield rB : [Lf/mc;
/*    */     //   193: iload #4
/*    */     //   195: aaload
/*    */     //   196: invokevirtual CW : ()Lf/rH;
/*    */     //   199: invokevirtual H : ()V
/*    */     //   202: getfield rB : [Lf/mc;
/*    */     //   205: iload #4
/*    */     //   207: aaload
/*    */     //   208: aconst_null
/*    */     //   209: invokevirtual Gq0 : (Ljava/lang/Object;)V
/*    */     //   212: goto -> 359
/*    */     //   215: aload_0
/*    */     //   216: dup
/*    */     //   217: dup
/*    */     //   218: dup2
/*    */     //   219: dup2
/*    */     //   220: getfield rB : [Lf/mc;
/*    */     //   223: iload #4
/*    */     //   225: aaload
/*    */     //   226: iconst_1
/*    */     //   227: invokevirtual sk0 : (Z)V
/*    */     //   230: invokestatic cw : ()Lf/yk0;
/*    */     //   233: iload #5
/*    */     //   235: invokevirtual mP : (S)Lf/WD;
/*    */     //   238: astore #5
/*    */     //   240: getfield rB : [Lf/mc;
/*    */     //   243: iload #4
/*    */     //   245: aaload
/*    */     //   246: aload #5
/*    */     //   248: aload_3
/*    */     //   249: invokestatic Ii0 : (Lf/WD;Lf/j40;)Lf/Ip;
/*    */     //   252: invokevirtual Gq0 : (Ljava/lang/Object;)V
/*    */     //   255: getfield rB : [Lf/mc;
/*    */     //   258: iload #4
/*    */     //   260: aaload
/*    */     //   261: aload #5
/*    */     //   263: invokestatic oV : (Lf/WD;)Ljava/lang/String;
/*    */     //   266: invokevirtual Ep0 : (Ljava/lang/String;)V
/*    */     //   269: getfield rB : [Lf/mc;
/*    */     //   272: iload #4
/*    */     //   274: aaload
/*    */     //   275: aload #5
/*    */     //   277: invokevirtual cW : ()Ljava/lang/String;
/*    */     //   280: invokevirtual s6 : (Ljava/lang/String;)V
/*    */     //   283: getfield rB : [Lf/mc;
/*    */     //   286: iload #4
/*    */     //   288: aaload
/*    */     //   289: aload_1
/*    */     //   290: aload_2
/*    */     //   291: aload_3
/*    */     //   292: iload #4
/*    */     //   294: <illegal opcode> run : (Lf/wg0;Lf/Y;Lf/j40;B)Ljava/lang/Runnable;
/*    */     //   299: invokevirtual tW : (Ljava/lang/Runnable;)V
/*    */     //   302: getfield rB : [Lf/mc;
/*    */     //   305: iload #4
/*    */     //   307: aaload
/*    */     //   308: invokevirtual CW : ()Lf/rH;
/*    */     //   311: iconst_1
/*    */     //   312: anewarray f/pe0
/*    */     //   315: dup
/*    */     //   316: invokestatic ZZ : ()Lf/interface;
/*    */     //   319: aload #5
/*    */     //   321: aload_3
/*    */     //   322: invokevirtual eC : ()Lf/Q90;
/*    */     //   325: invokevirtual Fn : (Lf/Q90;)Lf/Ht0;
/*    */     //   328: invokevirtual oI : ()B
/*    */     //   331: invokevirtual Pk0 : (I)Lf/pe0;
/*    */     //   334: iconst_0
/*    */     //   335: swap
/*    */     //   336: aastore
/*    */     //   337: invokevirtual Pn : ([Lf/pe0;)Lf/JG0;
/*    */     //   340: pop
/*    */     //   341: getfield rB : [Lf/mc;
/*    */     //   344: iload #4
/*    */     //   346: aaload
/*    */     //   347: invokevirtual CW : ()Lf/rH;
/*    */     //   350: sipush #153
/*    */     //   353: bipush #10
/*    */     //   355: invokevirtual zT : (II)Lf/JG0;
/*    */     //   358: pop
/*    */     //   359: iload #4
/*    */     //   361: iconst_1
/*    */     //   362: iadd
/*    */     //   363: i2b
/*    */     //   364: istore #4
/*    */     //   366: goto -> 107
/*    */     //   369: aload_0
/*    */     //   370: dup
/*    */     //   371: dup2
/*    */     //   372: dup2
/*    */     //   373: aload #5
/*    */     //   375: iconst_4
/*    */     //   376: aaload
/*    */     //   377: iconst_0
/*    */     //   378: invokevirtual sk0 : (Z)V
/*    */     //   381: new f/p30
/*    */     //   384: dup
/*    */     //   385: aload_0
/*    */     //   386: swap
/*    */     //   387: dup
/*    */     //   388: bipush #53
/*    */     //   390: invokestatic OH0 : (I)Ljava/lang/String;
/*    */     //   393: bipush #96
/*    */     //   395: bipush #30
/*    */     //   397: invokespecial <init> : (Ljava/lang/String;II)V
/*    */     //   400: putfield Wu0 : Lf/p30;
/*    */     //   403: ldc 'battle-button-return'
/*    */     //   405: invokevirtual Xu : (Ljava/lang/String;)V
/*    */     //   408: getfield Wu0 : Lf/p30;
/*    */     //   411: new f/ji0
/*    */     //   414: dup
/*    */     //   415: aload_1
/*    */     //   416: invokespecial <init> : (Lf/wg0;)V
/*    */     //   419: invokevirtual tW : (Ljava/lang/Runnable;)V
/*    */     //   422: new f/Ip
/*    */     //   425: dup
/*    */     //   426: dup
/*    */     //   427: aload_0
/*    */     //   428: swap
/*    */     //   429: dup
/*    */     //   430: invokespecial <init> : ()V
/*    */     //   433: putfield k40 : Lf/Ip;
/*    */     //   436: invokevirtual d7 : ()Lf/cr0;
/*    */     //   439: bipush #18
/*    */     //   441: invokevirtual Aq : (I)Lf/U90;
/*    */     //   444: iconst_3
/*    */     //   445: anewarray f/U90
/*    */     //   448: dup
/*    */     //   449: dup
/*    */     //   450: astore_1
/*    */     //   451: aload_0
/*    */     //   452: aload_1
/*    */     //   453: aload_0
/*    */     //   454: aload_1
/*    */     //   455: aload_0
/*    */     //   456: getfield k40 : Lf/Ip;
/*    */     //   459: invokevirtual mE0 : ()Lf/g0;
/*    */     //   462: iconst_2
/*    */     //   463: anewarray f/JG0
/*    */     //   466: dup
/*    */     //   467: dup
/*    */     //   468: astore_1
/*    */     //   469: aload_0
/*    */     //   470: getfield rB : [Lf/mc;
/*    */     //   473: dup
/*    */     //   474: aload_1
/*    */     //   475: swap
/*    */     //   476: iconst_0
/*    */     //   477: aaload
/*    */     //   478: iconst_0
/*    */     //   479: swap
/*    */     //   480: aastore
/*    */     //   481: iconst_1
/*    */     //   482: aaload
/*    */     //   483: iconst_1
/*    */     //   484: swap
/*    */     //   485: aastore
/*    */     //   486: invokevirtual Mg : ([Lf/JG0;)Lf/U90;
/*    */     //   489: iconst_0
/*    */     //   490: swap
/*    */     //   491: aastore
/*    */     //   492: getfield k40 : Lf/Ip;
/*    */     //   495: invokevirtual mE0 : ()Lf/g0;
/*    */     //   498: iconst_2
/*    */     //   499: anewarray f/JG0
/*    */     //   502: dup
/*    */     //   503: dup
/*    */     //   504: astore_1
/*    */     //   505: aload_0
/*    */     //   506: getfield rB : [Lf/mc;
/*    */     //   509: dup
/*    */     //   510: aload_1
/*    */     //   511: swap
/*    */     //   512: iconst_2
/*    */     //   513: aaload
/*    */     //   514: iconst_0
/*    */     //   515: swap
/*    */     //   516: aastore
/*    */     //   517: iconst_3
/*    */     //   518: aaload
/*    */     //   519: iconst_1
/*    */     //   520: swap
/*    */     //   521: aastore
/*    */     //   522: invokevirtual Mg : ([Lf/JG0;)Lf/U90;
/*    */     //   525: iconst_1
/*    */     //   526: swap
/*    */     //   527: aastore
/*    */     //   528: getfield k40 : Lf/Ip;
/*    */     //   531: invokevirtual mE0 : ()Lf/g0;
/*    */     //   534: iconst_1
/*    */     //   535: anewarray f/JG0
/*    */     //   538: dup
/*    */     //   539: aload_0
/*    */     //   540: getfield rB : [Lf/mc;
/*    */     //   543: iconst_4
/*    */     //   544: aaload
/*    */     //   545: iconst_0
/*    */     //   546: swap
/*    */     //   547: aastore
/*    */     //   548: invokevirtual Mg : ([Lf/JG0;)Lf/U90;
/*    */     //   551: iconst_2
/*    */     //   552: swap
/*    */     //   553: aastore
/*    */     //   554: invokevirtual cOM8 : ([Lf/U90;)Lf/U90;
/*    */     //   557: invokevirtual WN : (Lf/U90;)V
/*    */     //   560: getfield k40 : Lf/Ip;
/*    */     //   563: dup
/*    */     //   564: invokevirtual d7 : ()Lf/cr0;
/*    */     //   567: iconst_2
/*    */     //   568: anewarray f/U90
/*    */     //   571: dup
/*    */     //   572: dup
/*    */     //   573: aload_0
/*    */     //   574: swap
/*    */     //   575: aload_0
/*    */     //   576: getfield k40 : Lf/Ip;
/*    */     //   579: invokevirtual mE0 : ()Lf/g0;
/*    */     //   582: iconst_3
/*    */     //   583: anewarray f/JG0
/*    */     //   586: dup
/*    */     //   587: dup
/*    */     //   588: astore_1
/*    */     //   589: aload_0
/*    */     //   590: getfield rB : [Lf/mc;
/*    */     //   593: dup
/*    */     //   594: astore_2
/*    */     //   595: aload_1
/*    */     //   596: aload_2
/*    */     //   597: aload_1
/*    */     //   598: aload_2
/*    */     //   599: iconst_0
/*    */     //   600: aaload
/*    */     //   601: iconst_0
/*    */     //   602: swap
/*    */     //   603: aastore
/*    */     //   604: iconst_2
/*    */     //   605: aaload
/*    */     //   606: iconst_1
/*    */     //   607: swap
/*    */     //   608: aastore
/*    */     //   609: iconst_4
/*    */     //   610: aaload
/*    */     //   611: iconst_2
/*    */     //   612: swap
/*    */     //   613: aastore
/*    */     //   614: invokevirtual Mg : ([Lf/JG0;)Lf/U90;
/*    */     //   617: iconst_0
/*    */     //   618: swap
/*    */     //   619: aastore
/*    */     //   620: getfield k40 : Lf/Ip;
/*    */     //   623: invokevirtual mE0 : ()Lf/g0;
/*    */     //   626: iconst_2
/*    */     //   627: anewarray f/JG0
/*    */     //   630: dup
/*    */     //   631: dup
/*    */     //   632: astore_1
/*    */     //   633: aload_0
/*    */     //   634: getfield rB : [Lf/mc;
/*    */     //   637: dup
/*    */     //   638: aload_1
/*    */     //   639: swap
/*    */     //   640: iconst_1
/*    */     //   641: aaload
/*    */     //   642: iconst_0
/*    */     //   643: swap
/*    */     //   644: aastore
/*    */     //   645: iconst_3
/*    */     //   646: aaload
/*    */     //   647: iconst_1
/*    */     //   648: swap
/*    */     //   649: aastore
/*    */     //   650: invokevirtual Mg : ([Lf/JG0;)Lf/U90;
/*    */     //   653: iconst_1
/*    */     //   654: swap
/*    */     //   655: aastore
/*    */     //   656: invokevirtual cOM8 : ([Lf/U90;)Lf/U90;
/*    */     //   659: invokevirtual rK0 : (Lf/U90;)V
/*    */     //   662: getfield k40 : Lf/Ip;
/*    */     //   665: invokevirtual J8 : (Lf/JG0;)V
/*    */     //   668: getfield Wu0 : Lf/p30;
/*    */     //   671: invokevirtual J8 : (Lf/JG0;)V
/*    */     //   674: return } public final void LM(throws paramthrows) { this.k1 = false; mc[] arrayOfMc; int i; if ((i = this.Mo0) >= 0 && i < (arrayOfMc = this.rB).length)
/*    */       VA0.c90(this[i]);  } public final boolean i2(oa0 paramoa0) { // Byte code:
/*    */     //   0: aload_1
/*    */     //   1: getfield cz0 : I
/*    */     //   4: invokestatic Wm0 : (I)Z
/*    */     //   7: ifeq -> 260
/*    */     //   10: aload_1
/*    */     //   11: invokevirtual oO : ()Z
/*    */     //   14: ifeq -> 260
/*    */     //   17: aload_1
/*    */     //   18: getfield GG0 : I
/*    */     //   21: getstatic f/BM.bC : Lf/BM;
/*    */     //   24: invokestatic J20 : (ILf/BM;)Z
/*    */     //   27: ifeq -> 60
/*    */     //   30: aload_0
/*    */     //   31: getfield rB : [Lf/mc;
/*    */     //   34: aload_0
/*    */     //   35: getfield Mo0 : I
/*    */     //   38: aaload
/*    */     //   39: dup
/*    */     //   40: astore_0
/*    */     //   41: getfield kN : Z
/*    */     //   44: ifeq -> 258
/*    */     //   47: aload_0
/*    */     //   48: getfield TG0 : Lf/protected;
/*    */     //   51: getfield oh0 : [Ljava/lang/Runnable;
/*    */     //   54: invokestatic Fz0 : ([Ljava/lang/Runnable;)V
/*    */     //   57: goto -> 258
/*    */     //   60: aload_1
/*    */     //   61: getfield GG0 : I
/*    */     //   64: getstatic f/BM.lc : Lf/BM;
/*    */     //   67: invokestatic J20 : (ILf/BM;)Z
/*    */     //   70: ifeq -> 86
/*    */     //   73: aload_0
/*    */     //   74: getfield Wu0 : Lf/p30;
/*    */     //   77: getfield TG0 : Lf/protected;
/*    */     //   80: getfield oh0 : [Ljava/lang/Runnable;
/*    */     //   83: invokestatic Fz0 : ([Ljava/lang/Runnable;)V
/*    */     //   86: aload_1
/*    */     //   87: getfield GG0 : I
/*    */     //   90: getstatic f/BM.M8 : Lf/BM;
/*    */     //   93: invokestatic J20 : (ILf/BM;)Z
/*    */     //   96: ifeq -> 118
/*    */     //   99: aload_0
/*    */     //   100: getfield Mo0 : I
/*    */     //   103: iconst_1
/*    */     //   104: iadd
/*    */     //   105: dup
/*    */     //   106: istore_1
/*    */     //   107: aload_0
/*    */     //   108: getfield Mu : I
/*    */     //   111: irem
/*    */     //   112: ifne -> 226
/*    */     //   115: goto -> 231
/*    */     //   118: aload_1
/*    */     //   119: getfield GG0 : I
/*    */     //   122: getstatic f/BM.Oq : Lf/BM;
/*    */     //   125: invokestatic J20 : (ILf/BM;)Z
/*    */     //   128: ifeq -> 161
/*    */     //   131: aload_0
/*    */     //   132: getfield Mo0 : I
/*    */     //   135: dup
/*    */     //   136: istore_1
/*    */     //   137: iconst_1
/*    */     //   138: iadd
/*    */     //   139: aload_0
/*    */     //   140: getfield Mu : I
/*    */     //   143: irem
/*    */     //   144: iconst_1
/*    */     //   145: if_icmpne -> 151
/*    */     //   148: goto -> 231
/*    */     //   151: aload_0
/*    */     //   152: iload_1
/*    */     //   153: iconst_1
/*    */     //   154: isub
/*    */     //   155: putfield Mo0 : I
/*    */     //   158: goto -> 231
/*    */     //   161: aload_1
/*    */     //   162: getfield GG0 : I
/*    */     //   165: getstatic f/BM.ni : Lf/BM;
/*    */     //   168: invokestatic J20 : (ILf/BM;)Z
/*    */     //   171: ifeq -> 191
/*    */     //   174: aload_0
/*    */     //   175: getfield Mo0 : I
/*    */     //   178: aload_0
/*    */     //   179: getfield Mu : I
/*    */     //   182: isub
/*    */     //   183: dup
/*    */     //   184: istore_1
/*    */     //   185: ifge -> 226
/*    */     //   188: goto -> 231
/*    */     //   191: aload_1
/*    */     //   192: getfield GG0 : I
/*    */     //   195: getstatic f/BM.N70 : Lf/BM;
/*    */     //   198: invokestatic J20 : (ILf/BM;)Z
/*    */     //   201: ifeq -> 231
/*    */     //   204: aload_0
/*    */     //   205: getfield Mo0 : I
/*    */     //   208: aload_0
/*    */     //   209: getfield Mu : I
/*    */     //   212: iadd
/*    */     //   213: dup
/*    */     //   214: istore_1
/*    */     //   215: aload_0
/*    */     //   216: getfield rB : [Lf/mc;
/*    */     //   219: arraylength
/*    */     //   220: if_icmplt -> 226
/*    */     //   223: goto -> 231
/*    */     //   226: aload_0
/*    */     //   227: iload_1
/*    */     //   228: putfield Mo0 : I
/*    */     //   231: aload_0
/*    */     //   232: getfield Mo0 : I
/*    */     //   235: dup
/*    */     //   236: istore_1
/*    */     //   237: iflt -> 258
/*    */     //   240: iload_1
/*    */     //   241: aload_0
/*    */     //   242: getfield rB : [Lf/mc;
/*    */     //   245: dup
/*    */     //   246: astore_0
/*    */     //   247: arraylength
/*    */     //   248: if_icmpge -> 258
/*    */     //   251: aload_0
/*    */     //   252: iload_1
/*    */     //   253: aaload
/*    */     //   254: invokestatic c90 : (Lf/JG0;)Z
/*    */     //   257: pop
/*    */     //   258: iconst_1
/*    */     //   259: ireturn
/*    */     //   260: aload_0
/*    */     //   261: aload_1
/*    */     //   262: invokespecial i2 : (Lf/oa0;)Z
/*    */     //   265: ireturn
/*    */     // Line number table:
/*    */     //   Java source line number -> byte code offset
/*    */     //   #1	-> 1
/*    */     //   #2	-> 4
/*    */     //   #3	-> 11
/*    */     //   #4	-> 18
/*    */     //   #5	-> 21
/*    */     //   #6	-> 41
/*    */     //   #7	-> 48
/*    */     //   #8	-> 51
/*    */     //   #9	-> 54
/*    */     //   #10	-> 61
/*    */     //   #11	-> 64
/*    */     //   #12	-> 77
/*    */     //   #13	-> 80
/*    */     //   #14	-> 83
/*    */     //   #15	-> 87
/*    */     //   #16	-> 90
/*    */     //   #17	-> 119
/*    */     //   #18	-> 122
/*    */     //   #19	-> 162
/*    */     //   #20	-> 165
/*    */     //   #21	-> 192
/*    */     //   #22	-> 195
/*    */     //   #23	-> 262 } public final void d40() { this.k40.Tm(this.jv.qF(), this.jv.Hy()); this.k40.ME(this.jv.RS(), this.jv.e3() + 50); this.k40.kN(5, 8, 5, 8);
/*    */     this.Wu0.mM();
/* 11 */     this.Wu0.ME(this.fr0.m40() - this.Wu0.xY - 5, this.fr0.mD() - this.Wu0.HC - 6); }
/*    */    }


/* Location:              /Users/vnnsnnt/Documents/Codespace/JavaWorkspace/RedTrainer/src/main/java/org/trainer/client/PokeMMO.jar!/f/Uh.class
 * Java compiler version: 8 (52.0)
 * JD-Core Version:       1.1.3
 */