/*  1 */ package f;public final class v10 extends Qa0 implements r60 { public static final ik Ss0 = C00.gd(v10.class); public final js IF; public final Ip oB; public Un Ki; public final W1 jh0; public final W1 i5; public final FL Zg0; public final OZ Yk0; public final W1 Ca0; public final FL I80; public final zT sl0; public final zT UC; public final FL so0; public final FL l80; public final W1 Rp; public final FL R; public final zT eW; public final FL FB; public final FL u30; public final FL He; public final FL K30; public final FL U3; public final FL Zx; public boolean TI; public Mt0 A3; public byte rT; public final zT tC0; public final zT Zz0; public final zT FN; public final FL rQ; public final FL og0; public final zT super; public final OZ Wp0; public final W1 n00; public final OZ E10; public final rI0 Mb; public final zT HL; public final FL cz; public final FL pD; public final FL J6; public final OZ t0; public final E1 hi; public final OZ MR; public final Q3 LQ; public final OZ GQ; public final xl0 P10; public final W1 Id0; public final FL zi0; public final FL lS; private void Ho(ScheduledFuture paramScheduledFuture) { if (paramScheduledFuture.cancel(false)) { Mt0 mt0; if (!km.ER()) {
/*    */ 
/*    */         
/*  4 */         h1.c20 = (byte)this.i5.Wa0.go; km.iE0.GY(); h1.Gh0 = true;
/*    */       } 
/*    */       int i;
/*  7 */       if ((i = this.Ca0.Wa0.go) >= 0)
/*    */       
/*    */       { 
/*    */         
/* 11 */         mt0 = this.Yk0.Fj.get(i); } else { this(h1.tR, h1.wd0); }  this.A3 = mt0; this
/*    */ 
/*    */         
/* 14 */         .rT = h1.c20 = (byte)this.i5.Wa0.go; }  } public final FL Wr; public final FL JE; public final FL a0; public final W1 Ly; public final W1 pX; public final FL DC0; public final FL Kj; public final FL ii0; public final FL Z50; public final FL Rs0; public final FL V1; public final FL wB; public final FL pw; public final FL Eh; public final W1 BG0; public final FL ab0; public final FL Le0; public final W1 JT; public final zT qx; public final zT TA; public final W1 HD; public final String[] WE; public final W1 B3; public final OZ ej0; public final W1 RL0; public final W1 eh0; public final ge0[] II; public final W1 g50; public final zT D60; public final FL Y60; public Gr[] Ny; public final aM lJ; public final aM Ij; public final aM NY; public final aM UH; public final aM aY; public final aM To; public final FL UI; public final FL Vx0; public final Lx0 ux; public final Lx0 F70; public final Lx0 H7; public final Lx0 pRN; public final Lx0 Xt; public final Ip T30; public final Lx0 Kz0; public boolean qU; public e2 bm0; public v10(js paramjs, boolean paramBoolean) { // Byte code:
/*    */     //   0: aload_0
/*    */     //   1: dup
/*    */     //   2: dup
/*    */     //   3: aload_1
/*    */     //   4: aload_0
/*    */     //   5: dup
/*    */     //   6: dup2
/*    */     //   7: invokestatic XU : ()Z
/*    */     //   10: invokespecial <init> : (Z)V
/*    */     //   13: iconst_0
/*    */     //   14: putfield TI : Z
/*    */     //   17: getstatic f/h1.c20 : B
/*    */     //   20: putfield rT : B
/*    */     //   23: new f/e2
/*    */     //   26: dup
/*    */     //   27: sipush #250
/*    */     //   30: invokespecial <init> : (I)V
/*    */     //   33: putfield bm0 : Lf/e2;
/*    */     //   36: putfield IF : Lf/js;
/*    */     //   39: new f/P40
/*    */     //   42: dup
/*    */     //   43: aload_0
/*    */     //   44: invokespecial <init> : (Lf/v10;)V
/*    */     //   47: invokevirtual TG0 : (Ljava/lang/Runnable;)V
/*    */     //   50: new f/Ip
/*    */     //   53: dup
/*    */     //   54: invokespecial <init> : ()V
/*    */     //   57: putfield oB : Lf/Ip;
/*    */     //   60: getstatic f/km.u4 : Lf/R8;
/*    */     //   63: dup
/*    */     //   64: astore_3
/*    */     //   65: ifnonnull -> 73
/*    */     //   68: aconst_null
/*    */     //   69: astore_3
/*    */     //   70: goto -> 78
/*    */     //   73: aload_3
/*    */     //   74: invokevirtual IQ : ()Lf/fH0;
/*    */     //   77: astore_3
/*    */     //   78: aload_3
/*    */     //   79: ifnull -> 88
/*    */     //   82: iconst_1
/*    */     //   83: istore #4
/*    */     //   85: goto -> 91
/*    */     //   88: iconst_0
/*    */     //   89: istore #4
/*    */     //   91: aload_0
/*    */     //   92: dup
/*    */     //   93: dup
/*    */     //   94: iload #4
/*    */     //   96: putfield qU : Z
/*    */     //   99: ldc 'settings-panel'
/*    */     //   101: invokevirtual Xu : (Ljava/lang/String;)V
/*    */     //   104: sipush #1200
/*    */     //   107: invokestatic OH0 : (I)Ljava/lang/String;
/*    */     //   110: invokevirtual Lo : (Ljava/lang/String;)V
/*    */     //   113: new f/OZ
/*    */     //   116: dup
/*    */     //   117: dup
/*    */     //   118: astore #4
/*    */     //   120: invokestatic KP : ()[Lf/Kz;
/*    */     //   123: invokespecial <init> : ([Ljava/lang/Object;)V
/*    */     //   126: new f/W1
/*    */     //   129: dup
/*    */     //   130: astore #5
/*    */     //   132: aload_0
/*    */     //   133: aload #5
/*    */     //   135: aload_0
/*    */     //   136: aload #5
/*    */     //   138: dup
/*    */     //   139: aload #4
/*    */     //   141: invokespecial <init> : (Lf/cQ;)V
/*    */     //   144: putfield jh0 : Lf/W1;
/*    */     //   147: invokestatic a50 : ()Lf/Kz;
/*    */     //   150: invokevirtual COm6 : (Ljava/lang/Object;)V
/*    */     //   153: <illegal opcode> run : (Lf/v10;)Ljava/lang/Runnable;
/*    */     //   158: invokevirtual D30 : (Ljava/lang/Runnable;)V
/*    */     //   161: invokevirtual pu : ()I
/*    */     //   164: iconst_2
/*    */     //   165: if_icmpge -> 174
/*    */     //   168: aload #5
/*    */     //   170: iconst_0
/*    */     //   171: invokevirtual sk0 : (Z)V
/*    */     //   174: new f/dQ
/*    */     //   177: dup
/*    */     //   178: dup
/*    */     //   179: astore #4
/*    */     //   181: aload #5
/*    */     //   183: aload #4
/*    */     //   185: dup
/*    */     //   186: sipush #1217
/*    */     //   189: invokestatic OH0 : (I)Ljava/lang/String;
/*    */     //   192: invokespecial <init> : (Ljava/lang/String;)V
/*    */     //   195: sipush #1218
/*    */     //   198: invokestatic OH0 : (I)Ljava/lang/String;
/*    */     //   201: invokevirtual Gq0 : (Ljava/lang/Object;)V
/*    */     //   204: invokevirtual VH : (Lf/JG0;)V
/*    */     //   207: ldc_w 'label-settings-title'
/*    */     //   210: invokevirtual Xu : (Ljava/lang/String;)V
/*    */     //   213: new f/at
/*    */     //   216: dup
/*    */     //   217: astore #6
/*    */     //   219: iconst_1
/*    */     //   220: anewarray f/JG0
/*    */     //   223: dup
/*    */     //   224: iconst_0
/*    */     //   225: aload #5
/*    */     //   227: aastore
/*    */     //   228: invokespecial <init> : ([Lf/JG0;)V
/*    */     //   231: iconst_3
/*    */     //   232: anewarray java/lang/String
/*    */     //   235: astore #5
/*    */     //   237: iconst_0
/*    */     //   238: istore #7
/*    */     //   240: iload #7
/*    */     //   242: iconst_3
/*    */     //   243: if_icmpge -> 265
/*    */     //   246: aload #5
/*    */     //   248: iload #7
/*    */     //   250: dup
/*    */     //   251: sipush #1271
/*    */     //   254: iadd
/*    */     //   255: invokestatic OH0 : (I)Ljava/lang/String;
/*    */     //   258: aastore
/*    */     //   259: iinc #7, 1
/*    */     //   262: goto -> 240
/*    */     //   265: aload_0
/*    */     //   266: new f/OZ
/*    */     //   269: dup
/*    */     //   270: astore #7
/*    */     //   272: aload #5
/*    */     //   274: invokespecial <init> : ([Ljava/lang/Object;)V
/*    */     //   277: new f/W1
/*    */     //   280: dup
/*    */     //   281: dup
/*    */     //   282: astore #5
/*    */     //   284: aload #7
/*    */     //   286: invokespecial <init> : (Lf/cQ;)V
/*    */     //   289: putfield i5 : Lf/W1;
/*    */     //   292: invokestatic lK : ()Lf/yG;
/*    */     //   295: getstatic f/yG.A1 : Lf/yG;
/*    */     //   298: if_acmpne -> 315
/*    */     //   301: aload #5
/*    */     //   303: dup
/*    */     //   304: iconst_0
/*    */     //   305: invokevirtual Z30 : (I)V
/*    */     //   308: iconst_0
/*    */     //   309: invokevirtual sk0 : (Z)V
/*    */     //   312: goto -> 348
/*    */     //   315: getstatic f/h1.c20 : B
/*    */     //   318: dup
/*    */     //   319: istore #7
/*    */     //   321: iflt -> 337
/*    */     //   324: iload #7
/*    */     //   326: iconst_3
/*    */     //   327: if_icmpge -> 337
/*    */     //   330: aload #5
/*    */     //   332: iload #7
/*    */     //   334: invokevirtual Z30 : (I)V
/*    */     //   337: aload #5
/*    */     //   339: aload_0
/*    */     //   340: <illegal opcode> run : (Lf/v10;)Ljava/lang/Runnable;
/*    */     //   345: invokevirtual D30 : (Ljava/lang/Runnable;)V
/*    */     //   348: new java/util/HashSet
/*    */     //   351: dup
/*    */     //   352: astore #5
/*    */     //   354: invokespecial <init> : ()V
/*    */     //   357: getstatic f/UB0.M60 : Lf/w70;
/*    */     //   360: invokevirtual LpT5 : ()[Lf/Zv;
/*    */     //   363: astore #7
/*    */     //   365: invokestatic XU : ()Z
/*    */     //   368: ifeq -> 394
/*    */     //   371: aload #5
/*    */     //   373: new f/Mt0
/*    */     //   376: dup
/*    */     //   377: astore #8
/*    */     //   379: sipush #1280
/*    */     //   382: sipush #720
/*    */     //   385: invokespecial <init> : (II)V
/*    */     //   388: aload #8
/*    */     //   390: invokevirtual add : (Ljava/lang/Object;)Z
/*    */     //   393: pop
/*    */     //   394: aload #7
/*    */     //   396: arraylength
/*    */     //   397: istore #8
/*    */     //   399: iconst_0
/*    */     //   400: istore #9
/*    */     //   402: iload #9
/*    */     //   404: iload #8
/*    */     //   406: if_icmpge -> 492
/*    */     //   409: aload #7
/*    */     //   411: iload #9
/*    */     //   413: aaload
/*    */     //   414: dup
/*    */     //   415: astore #10
/*    */     //   417: ifnonnull -> 423
/*    */     //   420: goto -> 471
/*    */     //   423: aload #10
/*    */     //   425: getfield FP : I
/*    */     //   428: dup
/*    */     //   429: istore #11
/*    */     //   431: sipush #768
/*    */     //   434: if_icmpge -> 451
/*    */     //   437: aload #10
/*    */     //   439: getfield wp : I
/*    */     //   442: sipush #1024
/*    */     //   445: if_icmpge -> 451
/*    */     //   448: goto -> 471
/*    */     //   451: aload #5
/*    */     //   453: new f/Mt0
/*    */     //   456: dup
/*    */     //   457: aload #10
/*    */     //   459: getfield wp : I
/*    */     //   462: iload #11
/*    */     //   464: invokespecial <init> : (II)V
/*    */     //   467: invokevirtual add : (Ljava/lang/Object;)Z
/*    */     //   470: pop
/*    */     //   471: iinc #9, 1
/*    */     //   474: goto -> 402
/*    */     //   477: astore #7
/*    */     //   479: getstatic f/v10.Ss0 : Lf/ik;
/*    */     //   482: ldc_w 'Could not load display modes'
/*    */     //   485: aload #7
/*    */     //   487: invokeinterface error : (Ljava/lang/String;Ljava/lang/Throwable;)V
/*    */     //   492: aload_0
/*    */     //   493: dup
/*    */     //   494: aload #5
/*    */     //   496: aload_0
/*    */     //   497: new f/Mt0
/*    */     //   500: dup
/*    */     //   501: astore #7
/*    */     //   503: getstatic f/h1.tR : I
/*    */     //   506: getstatic f/h1.wd0 : I
/*    */     //   509: swap
/*    */     //   510: swap
/*    */     //   511: invokespecial <init> : (II)V
/*    */     //   514: aload #7
/*    */     //   516: putfield A3 : Lf/Mt0;
/*    */     //   519: aload #7
/*    */     //   521: invokevirtual add : (Ljava/lang/Object;)Z
/*    */     //   524: pop
/*    */     //   525: new java/util/ArrayList
/*    */     //   528: dup
/*    */     //   529: dup
/*    */     //   530: astore #7
/*    */     //   532: aload #5
/*    */     //   534: invokespecial <init> : (Ljava/util/Collection;)V
/*    */     //   537: invokestatic sort : (Ljava/util/List;)V
/*    */     //   540: new f/OZ
/*    */     //   543: dup
/*    */     //   544: astore #5
/*    */     //   546: aload #7
/*    */     //   548: invokespecial <init> : (Ljava/util/Collection;)V
/*    */     //   551: aload #5
/*    */     //   553: putfield Yk0 : Lf/OZ;
/*    */     //   556: new f/W1
/*    */     //   559: dup
/*    */     //   560: astore #7
/*    */     //   562: aload #5
/*    */     //   564: invokespecial <init> : (Lf/cQ;)V
/*    */     //   567: aload #7
/*    */     //   569: putfield Ca0 : Lf/W1;
/*    */     //   572: iconst_0
/*    */     //   573: istore #5
/*    */     //   575: iload #5
/*    */     //   577: aload_0
/*    */     //   578: getfield Yk0 : Lf/OZ;
/*    */     //   581: invokevirtual pu : ()I
/*    */     //   584: if_icmpge -> 644
/*    */     //   587: getstatic f/h1.wd0 : I
/*    */     //   590: aload_0
/*    */     //   591: getfield Yk0 : Lf/OZ;
/*    */     //   594: iload #5
/*    */     //   596: invokevirtual c90 : (I)Ljava/lang/Object;
/*    */     //   599: checkcast f/Mt0
/*    */     //   602: getfield oi : I
/*    */     //   605: if_icmpne -> 638
/*    */     //   608: getstatic f/h1.tR : I
/*    */     //   611: aload_0
/*    */     //   612: getfield Yk0 : Lf/OZ;
/*    */     //   615: iload #5
/*    */     //   617: invokevirtual c90 : (I)Ljava/lang/Object;
/*    */     //   620: checkcast f/Mt0
/*    */     //   623: getfield XZ : I
/*    */     //   626: if_icmpne -> 638
/*    */     //   629: aload_0
/*    */     //   630: getfield Ca0 : Lf/W1;
/*    */     //   633: iload #5
/*    */     //   635: invokevirtual Z30 : (I)V
/*    */     //   638: iinc #5, 1
/*    */     //   641: goto -> 575
/*    */     //   644: aload_0
/*    */     //   645: getfield Ca0 : Lf/W1;
/*    */     //   648: aload_0
/*    */     //   649: <illegal opcode> run : (Lf/v10;)Ljava/lang/Runnable;
/*    */     //   654: invokevirtual D30 : (Ljava/lang/Runnable;)V
/*    */     //   657: new f/dQ
/*    */     //   660: dup
/*    */     //   661: dup
/*    */     //   662: astore #5
/*    */     //   664: aload_0
/*    */     //   665: aload #5
/*    */     //   667: sipush #1270
/*    */     //   670: invokestatic OH0 : (I)Ljava/lang/String;
/*    */     //   673: invokespecial <init> : (Ljava/lang/String;)V
/*    */     //   676: getfield i5 : Lf/W1;
/*    */     //   679: invokevirtual VH : (Lf/JG0;)V
/*    */     //   682: ldc_w 'label-settings-title'
/*    */     //   685: invokevirtual Xu : (Ljava/lang/String;)V
/*    */     //   688: new f/dQ
/*    */     //   691: dup
/*    */     //   692: dup
/*    */     //   693: astore #7
/*    */     //   695: aload_0
/*    */     //   696: aload #7
/*    */     //   698: sipush #1250
/*    */     //   701: invokestatic OH0 : (I)Ljava/lang/String;
/*    */     //   704: invokespecial <init> : (Ljava/lang/String;)V
/*    */     //   707: getfield Ca0 : Lf/W1;
/*    */     //   710: invokevirtual VH : (Lf/JG0;)V
/*    */     //   713: ldc_w 'label-settings-title'
/*    */     //   716: invokevirtual Xu : (Ljava/lang/String;)V
/*    */     //   719: new f/at
/*    */     //   722: dup
/*    */     //   723: astore #8
/*    */     //   725: iconst_1
/*    */     //   726: anewarray f/JG0
/*    */     //   729: dup
/*    */     //   730: aload_0
/*    */     //   731: getfield i5 : Lf/W1;
/*    */     //   734: iconst_0
/*    */     //   735: swap
/*    */     //   736: aastore
/*    */     //   737: invokespecial <init> : ([Lf/JG0;)V
/*    */     //   740: new f/at
/*    */     //   743: dup
/*    */     //   744: astore #9
/*    */     //   746: iconst_1
/*    */     //   747: anewarray f/JG0
/*    */     //   750: dup
/*    */     //   751: aload_0
/*    */     //   752: getfield Ca0 : Lf/W1;
/*    */     //   755: iconst_0
/*    */     //   756: swap
/*    */     //   757: aastore
/*    */     //   758: invokespecial <init> : ([Lf/JG0;)V
/*    */     //   761: new f/FL
/*    */     //   764: dup
/*    */     //   765: aload_0
/*    */     //   766: swap
/*    */     //   767: dup
/*    */     //   768: ldc_w 'V-Sync'
/*    */     //   771: invokespecial <init> : (Ljava/lang/String;)V
/*    */     //   774: putfield Zg0 : Lf/FL;
/*    */     //   777: getstatic f/h1.ru0 : Z
/*    */     //   780: invokevirtual QS : (Z)V
/*    */     //   783: invokestatic zp : ()Z
/*    */     //   786: ifeq -> 822
/*    */     //   789: getstatic f/km.G60 : I
/*    */     //   792: bipush #28
/*    */     //   794: if_icmplt -> 822
/*    */     //   797: new f/FL
/*    */     //   800: dup
/*    */     //   801: aload_0
/*    */     //   802: swap
/*    */     //   803: dup
/*    */     //   804: sipush #600
/*    */     //   807: invokespecial <init> : (I)V
/*    */     //   810: putfield I80 : Lf/FL;
/*    */     //   813: getstatic f/h1.fD : Z
/*    */     //   816: invokevirtual QS : (Z)V
/*    */     //   819: goto -> 827
/*    */     //   822: aload_0
/*    */     //   823: aconst_null
/*    */     //   824: putfield I80 : Lf/FL;
/*    */     //   827: invokestatic lK : ()Lf/yG;
/*    */     //   830: getstatic f/yG.A1 : Lf/yG;
/*    */     //   833: if_acmpne -> 880
/*    */     //   836: getstatic f/q00.No : Z
/*    */     //   839: ifne -> 880
/*    */     //   842: new f/FL
/*    */     //   845: dup
/*    */     //   846: dup
/*    */     //   847: aload_0
/*    */     //   848: swap
/*    */     //   849: dup
/*    */     //   850: sipush #1223
/*    */     //   853: invokestatic OH0 : (I)Ljava/lang/String;
/*    */     //   856: invokespecial <init> : (Ljava/lang/String;)V
/*    */     //   859: putfield Zx : Lf/FL;
/*    */     //   862: getstatic f/h1.qL : Z
/*    */     //   865: invokevirtual QS : (Z)V
/*    */     //   868: sipush #1224
/*    */     //   871: invokestatic OH0 : (I)Ljava/lang/String;
/*    */     //   874: invokevirtual yp0 : (Ljava/lang/String;)V
/*    */     //   877: goto -> 885
/*    */     //   880: aload_0
/*    */     //   881: aconst_null
/*    */     //   882: putfield Zx : Lf/FL;
/*    */     //   885: new f/FL
/*    */     //   888: dup
/*    */     //   889: aload_0
/*    */     //   890: swap
/*    */     //   891: dup
/*    */     //   892: sipush #1261
/*    */     //   895: invokespecial <init> : (I)V
/*    */     //   898: putfield Wr : Lf/FL;
/*    */     //   901: getstatic f/h1.Eg0 : Z
/*    */     //   904: invokevirtual QS : (Z)V
/*    */     //   907: new f/FL
/*    */     //   910: dup
/*    */     //   911: dup
/*    */     //   912: aload_0
/*    */     //   913: swap
/*    */     //   914: dup
/*    */     //   915: sipush #1252
/*    */     //   918: invokespecial <init> : (I)V
/*    */     //   921: putfield so0 : Lf/FL;
/*    */     //   924: getstatic f/h1.gt0 : Z
/*    */     //   927: invokevirtual QS : (Z)V
/*    */     //   930: sipush #1267
/*    */     //   933: invokestatic OH0 : (I)Ljava/lang/String;
/*    */     //   936: invokevirtual yp0 : (Ljava/lang/String;)V
/*    */     //   939: new f/FL
/*    */     //   942: dup
/*    */     //   943: dup
/*    */     //   944: aload_0
/*    */     //   945: swap
/*    */     //   946: dup
/*    */     //   947: sipush #1257
/*    */     //   950: invokespecial <init> : (I)V
/*    */     //   953: putfield l80 : Lf/FL;
/*    */     //   956: getstatic f/h1.zR : Z
/*    */     //   959: invokevirtual QS : (Z)V
/*    */     //   962: sipush #1268
/*    */     //   965: invokestatic OH0 : (I)Ljava/lang/String;
/*    */     //   968: invokevirtual yp0 : (Ljava/lang/String;)V
/*    */     //   971: new f/OZ
/*    */     //   974: dup
/*    */     //   975: astore #10
/*    */     //   977: iconst_2
/*    */     //   978: anewarray java/lang/String
/*    */     //   981: dup
/*    */     //   982: dup
/*    */     //   983: sipush #1287
/*    */     //   986: invokestatic OH0 : (I)Ljava/lang/String;
/*    */     //   989: iconst_0
/*    */     //   990: swap
/*    */     //   991: aastore
/*    */     //   992: sipush #1289
/*    */     //   995: invokestatic OH0 : (I)Ljava/lang/String;
/*    */     //   998: iconst_1
/*    */     //   999: swap
/*    */     //   1000: aastore
/*    */     //   1001: invokespecial <init> : ([Ljava/lang/Object;)V
/*    */     //   1004: new f/W1
/*    */     //   1007: dup
/*    */     //   1008: astore #11
/*    */     //   1010: aload_0
/*    */     //   1011: aload #11
/*    */     //   1013: dup
/*    */     //   1014: aload #10
/*    */     //   1016: invokespecial <init> : (Lf/cQ;)V
/*    */     //   1019: putfield Rp : Lf/W1;
/*    */     //   1022: getstatic f/h1.YJ : I
/*    */     //   1025: invokevirtual Z30 : (I)V
/*    */     //   1028: new f/dQ
/*    */     //   1031: dup
/*    */     //   1032: dup
/*    */     //   1033: astore #10
/*    */     //   1035: aload #11
/*    */     //   1037: aload #10
/*    */     //   1039: sipush #1253
/*    */     //   1042: invokestatic OH0 : (I)Ljava/lang/String;
/*    */     //   1045: invokespecial <init> : (Ljava/lang/String;)V
/*    */     //   1048: invokevirtual VH : (Lf/JG0;)V
/*    */     //   1051: ldc_w 'label-settings-title'
/*    */     //   1054: invokevirtual Xu : (Ljava/lang/String;)V
/*    */     //   1057: new f/FL
/*    */     //   1060: dup
/*    */     //   1061: dup
/*    */     //   1062: aload_0
/*    */     //   1063: swap
/*    */     //   1064: dup
/*    */     //   1065: sipush #1255
/*    */     //   1068: invokespecial <init> : (I)V
/*    */     //   1071: putfield pw : Lf/FL;
/*    */     //   1074: getstatic f/h1.bp0 : Z
/*    */     //   1077: invokevirtual QS : (Z)V
/*    */     //   1080: sipush #1269
/*    */     //   1083: invokestatic OH0 : (I)Ljava/lang/String;
/*    */     //   1086: invokevirtual yp0 : (Ljava/lang/String;)V
/*    */     //   1089: new f/FL
/*    */     //   1092: dup
/*    */     //   1093: aload_0
/*    */     //   1094: swap
/*    */     //   1095: dup
/*    */     //   1096: sipush #1317
/*    */     //   1099: invokespecial <init> : (I)V
/*    */     //   1102: putfield Eh : Lf/FL;
/*    */     //   1105: getstatic f/h1.X2 : Z
/*    */     //   1108: invokevirtual QS : (Z)V
/*    */     //   1111: new f/OZ
/*    */     //   1114: dup
/*    */     //   1115: astore #11
/*    */     //   1117: iconst_3
/*    */     //   1118: anewarray java/lang/String
/*    */     //   1121: dup
/*    */     //   1122: dup2
/*    */     //   1123: sipush #6153
/*    */     //   1126: invokestatic OH0 : (I)Ljava/lang/String;
/*    */     //   1129: iconst_0
/*    */     //   1130: swap
/*    */     //   1131: aastore
/*    */     //   1132: sipush #6154
/*    */     //   1135: invokestatic OH0 : (I)Ljava/lang/String;
/*    */     //   1138: iconst_1
/*    */     //   1139: swap
/*    */     //   1140: aastore
/*    */     //   1141: sipush #6155
/*    */     //   1144: invokestatic OH0 : (I)Ljava/lang/String;
/*    */     //   1147: iconst_2
/*    */     //   1148: swap
/*    */     //   1149: aastore
/*    */     //   1150: invokespecial <init> : ([Ljava/lang/Object;)V
/*    */     //   1153: new f/W1
/*    */     //   1156: dup
/*    */     //   1157: astore #12
/*    */     //   1159: aload_0
/*    */     //   1160: aload #12
/*    */     //   1162: dup
/*    */     //   1163: aload #11
/*    */     //   1165: invokespecial <init> : (Lf/cQ;)V
/*    */     //   1168: putfield BG0 : Lf/W1;
/*    */     //   1171: getstatic f/h1.ei : I
/*    */     //   1174: invokevirtual Z30 : (I)V
/*    */     //   1177: new f/dQ
/*    */     //   1180: dup
/*    */     //   1181: dup
/*    */     //   1182: astore #11
/*    */     //   1184: aload #12
/*    */     //   1186: aload #11
/*    */     //   1188: sipush #6156
/*    */     //   1191: invokestatic OH0 : (I)Ljava/lang/String;
/*    */     //   1194: invokespecial <init> : (Ljava/lang/String;)V
/*    */     //   1197: invokevirtual VH : (Lf/JG0;)V
/*    */     //   1200: ldc_w 'label-settings-title'
/*    */     //   1203: invokevirtual Xu : (Ljava/lang/String;)V
/*    */     //   1206: new f/FL
/*    */     //   1209: dup
/*    */     //   1210: dup
/*    */     //   1211: aload_0
/*    */     //   1212: swap
/*    */     //   1213: dup
/*    */     //   1214: sipush #1248
/*    */     //   1217: invokespecial <init> : (I)V
/*    */     //   1220: putfield ab0 : Lf/FL;
/*    */     //   1223: getstatic f/h1.qu0 : Z
/*    */     //   1226: invokevirtual QS : (Z)V
/*    */     //   1229: sipush #1249
/*    */     //   1232: invokestatic OH0 : (I)Ljava/lang/String;
/*    */     //   1235: invokevirtual yp0 : (Ljava/lang/String;)V
/*    */     //   1238: new f/FL
/*    */     //   1241: dup
/*    */     //   1242: aload_0
/*    */     //   1243: swap
/*    */     //   1244: dup
/*    */     //   1245: sipush #1258
/*    */     //   1248: invokespecial <init> : (I)V
/*    */     //   1251: putfield a0 : Lf/FL;
/*    */     //   1254: getstatic f/h1.Lf0 : Z
/*    */     //   1257: invokevirtual QS : (Z)V
/*    */     //   1260: new f/dQ
/*    */     //   1263: dup
/*    */     //   1264: astore #12
/*    */     //   1266: sipush #1319
/*    */     //   1269: invokestatic OH0 : (I)Ljava/lang/String;
/*    */     //   1272: invokespecial <init> : (Ljava/lang/String;)V
/*    */     //   1275: iconst_3
/*    */     //   1276: anewarray java/lang/String
/*    */     //   1279: astore #13
/*    */     //   1281: iconst_0
/*    */     //   1282: istore #14
/*    */     //   1284: iload #14
/*    */     //   1286: iconst_3
/*    */     //   1287: if_icmpge -> 1309
/*    */     //   1290: aload #13
/*    */     //   1292: iload #14
/*    */     //   1294: dup
/*    */     //   1295: sipush #1320
/*    */     //   1298: iadd
/*    */     //   1299: invokestatic OH0 : (I)Ljava/lang/String;
/*    */     //   1302: aastore
/*    */     //   1303: iinc #14, 1
/*    */     //   1306: goto -> 1284
/*    */     //   1309: aload_0
/*    */     //   1310: new f/OZ
/*    */     //   1313: dup
/*    */     //   1314: astore #14
/*    */     //   1316: aload #13
/*    */     //   1318: invokespecial <init> : ([Ljava/lang/Object;)V
/*    */     //   1321: new f/W1
/*    */     //   1324: dup
/*    */     //   1325: astore #15
/*    */     //   1327: aload #14
/*    */     //   1329: invokespecial <init> : (Lf/cQ;)V
/*    */     //   1332: aload #15
/*    */     //   1334: putfield Ly : Lf/W1;
/*    */     //   1337: getstatic f/h1.nv : I
/*    */     //   1340: dup
/*    */     //   1341: istore #14
/*    */     //   1343: iflt -> 1362
/*    */     //   1346: iload #14
/*    */     //   1348: iconst_3
/*    */     //   1349: if_icmpge -> 1362
/*    */     //   1352: aload #15
/*    */     //   1354: iload #14
/*    */     //   1356: invokevirtual Z30 : (I)V
/*    */     //   1359: goto -> 1368
/*    */     //   1362: aload #15
/*    */     //   1364: iconst_1
/*    */     //   1365: invokevirtual Z30 : (I)V
/*    */     //   1368: aload_0
/*    */     //   1369: aload #12
/*    */     //   1371: new f/at
/*    */     //   1374: dup
/*    */     //   1375: astore #14
/*    */     //   1377: iconst_1
/*    */     //   1378: anewarray f/JG0
/*    */     //   1381: dup
/*    */     //   1382: iconst_0
/*    */     //   1383: aload #15
/*    */     //   1385: aastore
/*    */     //   1386: invokespecial <init> : ([Lf/JG0;)V
/*    */     //   1389: ldc_w 'label-settings-title'
/*    */     //   1392: invokevirtual Xu : (Ljava/lang/String;)V
/*    */     //   1395: new f/dQ
/*    */     //   1398: dup
/*    */     //   1399: astore #15
/*    */     //   1401: sipush #1318
/*    */     //   1404: invokestatic OH0 : (I)Ljava/lang/String;
/*    */     //   1407: invokespecial <init> : (Ljava/lang/String;)V
/*    */     //   1410: new f/OZ
/*    */     //   1413: dup
/*    */     //   1414: astore #16
/*    */     //   1416: aload #13
/*    */     //   1418: invokespecial <init> : ([Ljava/lang/Object;)V
/*    */     //   1421: new f/W1
/*    */     //   1424: dup
/*    */     //   1425: dup
/*    */     //   1426: astore #13
/*    */     //   1428: aload #16
/*    */     //   1430: invokespecial <init> : (Lf/cQ;)V
/*    */     //   1433: putfield pX : Lf/W1;
/*    */     //   1436: getstatic f/h1.ak0 : I
/*    */     //   1439: dup
/*    */     //   1440: istore #16
/*    */     //   1442: iflt -> 1461
/*    */     //   1445: iload #16
/*    */     //   1447: iconst_3
/*    */     //   1448: if_icmpge -> 1461
/*    */     //   1451: aload #13
/*    */     //   1453: iload #16
/*    */     //   1455: invokevirtual Z30 : (I)V
/*    */     //   1458: goto -> 1467
/*    */     //   1461: aload #13
/*    */     //   1463: iconst_1
/*    */     //   1464: invokevirtual Z30 : (I)V
/*    */     //   1467: aload_0
/*    */     //   1468: aload #15
/*    */     //   1470: new f/at
/*    */     //   1473: dup
/*    */     //   1474: astore #16
/*    */     //   1476: iconst_1
/*    */     //   1477: anewarray f/JG0
/*    */     //   1480: dup
/*    */     //   1481: iconst_0
/*    */     //   1482: aload #13
/*    */     //   1484: aastore
/*    */     //   1485: invokespecial <init> : ([Lf/JG0;)V
/*    */     //   1488: ldc_w 'label-settings-title'
/*    */     //   1491: invokevirtual Xu : (Ljava/lang/String;)V
/*    */     //   1494: new f/dQ
/*    */     //   1497: dup
/*    */     //   1498: dup
/*    */     //   1499: astore #13
/*    */     //   1501: sipush #1254
/*    */     //   1504: invokestatic OH0 : (I)Ljava/lang/String;
/*    */     //   1507: invokespecial <init> : (Ljava/lang/String;)V
/*    */     //   1510: ldc_w 'label-settings-title'
/*    */     //   1513: invokevirtual Xu : (Ljava/lang/String;)V
/*    */     //   1516: new f/zT
/*    */     //   1519: dup
/*    */     //   1520: dup
/*    */     //   1521: astore #17
/*    */     //   1523: getstatic f/h1.dB0 : I
/*    */     //   1526: istore #18
/*    */     //   1528: bipush #10
/*    */     //   1530: sipush #1000
/*    */     //   1533: iload #18
/*    */     //   1535: invokespecial <init> : (III)V
/*    */     //   1538: putfield sl0 : Lf/zT;
/*    */     //   1541: new f/rh
/*    */     //   1544: dup
/*    */     //   1545: dup
/*    */     //   1546: astore #18
/*    */     //   1548: aload #17
/*    */     //   1550: invokespecial <init> : (Lf/er;)V
/*    */     //   1553: ldc_w 'label-settings-vai'
/*    */     //   1556: invokevirtual Xu : (Ljava/lang/String;)V
/*    */     //   1559: new f/dQ
/*    */     //   1562: dup
/*    */     //   1563: dup
/*    */     //   1564: astore #17
/*    */     //   1566: sipush #1274
/*    */     //   1569: invokestatic OH0 : (I)Ljava/lang/String;
/*    */     //   1572: invokespecial <init> : (Ljava/lang/String;)V
/*    */     //   1575: ldc_w 'label-settings-title'
/*    */     //   1578: invokevirtual Xu : (Ljava/lang/String;)V
/*    */     //   1581: new f/zT
/*    */     //   1584: dup
/*    */     //   1585: astore #19
/*    */     //   1587: getstatic f/h1.Ju0 : I
/*    */     //   1590: istore #20
/*    */     //   1592: iconst_0
/*    */     //   1593: bipush #100
/*    */     //   1595: iload #20
/*    */     //   1597: invokespecial <init> : (III)V
/*    */     //   1600: new f/BJ0
/*    */     //   1603: dup
/*    */     //   1604: dup
/*    */     //   1605: astore #20
/*    */     //   1607: aload #19
/*    */     //   1609: invokespecial <init> : (Lf/zT;)V
/*    */     //   1612: ldc_w 'label-settings-vai'
/*    */     //   1615: invokevirtual Xu : (Ljava/lang/String;)V
/*    */     //   1618: new f/dQ
/*    */     //   1621: dup
/*    */     //   1622: dup
/*    */     //   1623: astore #19
/*    */     //   1625: sipush #1264
/*    */     //   1628: invokestatic OH0 : (I)Ljava/lang/String;
/*    */     //   1631: invokespecial <init> : (Ljava/lang/String;)V
/*    */     //   1634: ldc_w 'label-settings-title'
/*    */     //   1637: invokevirtual Xu : (Ljava/lang/String;)V
/*    */     //   1640: getstatic f/I20.oq : I
/*    */     //   1643: bipush #16
/*    */     //   1645: if_icmple -> 1653
/*    */     //   1648: bipush #16
/*    */     //   1650: putstatic f/I20.oq : I
/*    */     //   1653: aload_0
/*    */     //   1654: new f/zT
/*    */     //   1657: dup
/*    */     //   1658: dup
/*    */     //   1659: astore #21
/*    */     //   1661: getstatic f/I20.oq : I
/*    */     //   1664: i2d
/*    */     //   1665: invokestatic sqrt : (D)D
/*    */     //   1668: invokestatic round : (D)J
/*    */     //   1671: l2i
/*    */     //   1672: getstatic f/h1.Vu0 : I
/*    */     //   1675: i2d
/*    */     //   1676: invokestatic sqrt : (D)D
/*    */     //   1679: invokestatic round : (D)J
/*    */     //   1682: l2i
/*    */     //   1683: istore #22
/*    */     //   1685: iconst_0
/*    */     //   1686: swap
/*    */     //   1687: iload #22
/*    */     //   1689: invokespecial <init> : (III)V
/*    */     //   1692: putfield UC : Lf/zT;
/*    */     //   1695: new f/J60
/*    */     //   1698: dup
/*    */     //   1699: dup
/*    */     //   1700: astore #22
/*    */     //   1702: aload #21
/*    */     //   1704: invokespecial <init> : (Lf/zT;)V
/*    */     //   1707: ldc_w 'label-settings-vai'
/*    */     //   1710: invokevirtual Xu : (Ljava/lang/String;)V
/*    */     //   1713: getstatic f/I20.oq : I
/*    */     //   1716: iconst_2
/*    */     //   1717: if_icmpge -> 1726
/*    */     //   1720: aload #22
/*    */     //   1722: iconst_0
/*    */     //   1723: invokevirtual sk0 : (Z)V
/*    */     //   1726: aload_0
/*    */     //   1727: new f/dQ
/*    */     //   1730: dup
/*    */     //   1731: dup2
/*    */     //   1732: astore #21
/*    */     //   1734: sipush #1241
/*    */     //   1737: invokestatic OH0 : (I)Ljava/lang/String;
/*    */     //   1740: invokespecial <init> : (Ljava/lang/String;)V
/*    */     //   1743: sipush #1242
/*    */     //   1746: invokestatic OH0 : (I)Ljava/lang/String;
/*    */     //   1749: invokevirtual Gq0 : (Ljava/lang/Object;)V
/*    */     //   1752: ldc_w 'label-settings-title'
/*    */     //   1755: invokevirtual Xu : (Ljava/lang/String;)V
/*    */     //   1758: new f/zT
/*    */     //   1761: dup
/*    */     //   1762: dup
/*    */     //   1763: astore #23
/*    */     //   1765: invokestatic Ek : ()I
/*    */     //   1768: istore #24
/*    */     //   1770: iconst_0
/*    */     //   1771: bipush #100
/*    */     //   1773: iload #24
/*    */     //   1775: invokespecial <init> : (III)V
/*    */     //   1778: putfield HL : Lf/zT;
/*    */     //   1781: new f/ka
/*    */     //   1784: dup
/*    */     //   1785: dup
/*    */     //   1786: astore #24
/*    */     //   1788: aload #23
/*    */     //   1790: invokespecial <init> : (Lf/zT;)V
/*    */     //   1793: ldc_w 'label-settings-vai'
/*    */     //   1796: invokevirtual Xu : (Ljava/lang/String;)V
/*    */     //   1799: new f/FL
/*    */     //   1802: dup
/*    */     //   1803: dup
/*    */     //   1804: aload_0
/*    */     //   1805: swap
/*    */     //   1806: dup
/*    */     //   1807: sipush #1243
/*    */     //   1810: invokespecial <init> : (I)V
/*    */     //   1813: putfield R : Lf/FL;
/*    */     //   1816: sipush #1244
/*    */     //   1819: invokestatic OH0 : (I)Ljava/lang/String;
/*    */     //   1822: invokevirtual yp0 : (Ljava/lang/String;)V
/*    */     //   1825: getstatic f/h1.WX : Z
/*    */     //   1828: invokevirtual QS : (Z)V
/*    */     //   1831: new f/dQ
/*    */     //   1834: dup
/*    */     //   1835: dup2
/*    */     //   1836: astore #23
/*    */     //   1838: sipush #1221
/*    */     //   1841: invokestatic OH0 : (I)Ljava/lang/String;
/*    */     //   1844: invokespecial <init> : (Ljava/lang/String;)V
/*    */     //   1847: sipush #1222
/*    */     //   1850: invokestatic OH0 : (I)Ljava/lang/String;
/*    */     //   1853: invokevirtual Gq0 : (Ljava/lang/Object;)V
/*    */     //   1856: ldc_w 'label-settings-title'
/*    */     //   1859: invokevirtual Xu : (Ljava/lang/String;)V
/*    */     //   1862: invokestatic XU : ()Z
/*    */     //   1865: ifeq -> 1874
/*    */     //   1868: iconst_2
/*    */     //   1869: istore #25
/*    */     //   1871: goto -> 1877
/*    */     //   1874: iconst_3
/*    */     //   1875: istore #25
/*    */     //   1877: aload_0
/*    */     //   1878: dup
/*    */     //   1879: dup
/*    */     //   1880: new f/zT
/*    */     //   1883: dup
/*    */     //   1884: dup
/*    */     //   1885: astore #26
/*    */     //   1887: iload #25
/*    */     //   1889: dup
/*    */     //   1890: getstatic f/h1.b40 : I
/*    */     //   1893: invokestatic max : (II)I
/*    */     //   1896: bipush #8
/*    */     //   1898: swap
/*    */     //   1899: invokespecial <init> : (III)V
/*    */     //   1902: putfield eW : Lf/zT;
/*    */     //   1905: new f/eq
/*    */     //   1908: dup
/*    */     //   1909: dup
/*    */     //   1910: astore #25
/*    */     //   1912: aload #26
/*    */     //   1914: invokespecial <init> : (Lf/zT;)V
/*    */     //   1917: ldc_w 'label-settings-vai'
/*    */     //   1920: invokevirtual Xu : (Ljava/lang/String;)V
/*    */     //   1923: new f/FL
/*    */     //   1926: dup
/*    */     //   1927: dup
/*    */     //   1928: aload_0
/*    */     //   1929: swap
/*    */     //   1930: dup
/*    */     //   1931: sipush #1297
/*    */     //   1934: invokespecial <init> : (I)V
/*    */     //   1937: putfield FB : Lf/FL;
/*    */     //   1940: sipush #1298
/*    */     //   1943: invokestatic OH0 : (I)Ljava/lang/String;
/*    */     //   1946: invokevirtual yp0 : (Ljava/lang/String;)V
/*    */     //   1949: getstatic f/h1.hR : Z
/*    */     //   1952: invokevirtual QS : (Z)V
/*    */     //   1955: new f/FL
/*    */     //   1958: dup
/*    */     //   1959: dup
/*    */     //   1960: aload_0
/*    */     //   1961: swap
/*    */     //   1962: dup
/*    */     //   1963: sipush #1284
/*    */     //   1966: invokespecial <init> : (I)V
/*    */     //   1969: putfield u30 : Lf/FL;
/*    */     //   1972: sipush #1285
/*    */     //   1975: invokestatic OH0 : (I)Ljava/lang/String;
/*    */     //   1978: invokevirtual yp0 : (Ljava/lang/String;)V
/*    */     //   1981: getstatic f/h1.Vy : Z
/*    */     //   1984: invokevirtual QS : (Z)V
/*    */     //   1987: new f/FL
/*    */     //   1990: dup
/*    */     //   1991: dup
/*    */     //   1992: aload_0
/*    */     //   1993: swap
/*    */     //   1994: dup
/*    */     //   1995: sipush #1213
/*    */     //   1998: invokespecial <init> : (I)V
/*    */     //   2001: putfield He : Lf/FL;
/*    */     //   2004: sipush #1214
/*    */     //   2007: invokestatic OH0 : (I)Ljava/lang/String;
/*    */     //   2010: invokevirtual yp0 : (Ljava/lang/String;)V
/*    */     //   2013: getstatic f/h1.SZ : Z
/*    */     //   2016: invokevirtual QS : (Z)V
/*    */     //   2019: new f/FL
/*    */     //   2022: dup
/*    */     //   2023: dup
/*    */     //   2024: aload_0
/*    */     //   2025: swap
/*    */     //   2026: dup
/*    */     //   2027: sipush #1234
/*    */     //   2030: invokespecial <init> : (I)V
/*    */     //   2033: putfield K30 : Lf/FL;
/*    */     //   2036: sipush #1235
/*    */     //   2039: invokestatic OH0 : (I)Ljava/lang/String;
/*    */     //   2042: invokevirtual yp0 : (Ljava/lang/String;)V
/*    */     //   2045: getstatic f/h1.rn : Z
/*    */     //   2048: invokevirtual QS : (Z)V
/*    */     //   2051: new f/FL
/*    */     //   2054: dup
/*    */     //   2055: aload_0
/*    */     //   2056: swap
/*    */     //   2057: dup
/*    */     //   2058: sipush #1233
/*    */     //   2061: invokespecial <init> : (I)V
/*    */     //   2064: putfield U3 : Lf/FL;
/*    */     //   2067: getstatic f/h1.Pm : Z
/*    */     //   2070: invokevirtual QS : (Z)V
/*    */     //   2073: new f/dQ
/*    */     //   2076: dup
/*    */     //   2077: dup
/*    */     //   2078: astore #26
/*    */     //   2080: sipush #1237
/*    */     //   2083: invokestatic OH0 : (I)Ljava/lang/String;
/*    */     //   2086: invokespecial <init> : (Ljava/lang/String;)V
/*    */     //   2089: ldc_w 'label-settings-title'
/*    */     //   2092: invokevirtual Xu : (Ljava/lang/String;)V
/*    */     //   2095: new f/zT
/*    */     //   2098: dup
/*    */     //   2099: dup
/*    */     //   2100: astore #27
/*    */     //   2102: getstatic f/h1.UD0 : I
/*    */     //   2105: istore #28
/*    */     //   2107: iconst_1
/*    */     //   2108: iconst_4
/*    */     //   2109: iload #28
/*    */     //   2111: invokespecial <init> : (III)V
/*    */     //   2114: putfield qx : Lf/zT;
/*    */     //   2117: new f/Tz
/*    */     //   2120: dup
/*    */     //   2121: dup
/*    */     //   2122: astore #28
/*    */     //   2124: aload #27
/*    */     //   2126: invokespecial <init> : (Lf/zT;)V
/*    */     //   2129: ldc_w 'label-settings-vai'
/*    */     //   2132: invokevirtual Xu : (Ljava/lang/String;)V
/*    */     //   2135: new f/dQ
/*    */     //   2138: dup
/*    */     //   2139: dup
/*    */     //   2140: astore #27
/*    */     //   2142: sipush #1238
/*    */     //   2145: invokestatic OH0 : (I)Ljava/lang/String;
/*    */     //   2148: invokespecial <init> : (Ljava/lang/String;)V
/*    */     //   2151: ldc_w 'label-settings-title'
/*    */     //   2154: invokevirtual Xu : (Ljava/lang/String;)V
/*    */     //   2157: new f/zT
/*    */     //   2160: dup
/*    */     //   2161: dup
/*    */     //   2162: astore #29
/*    */     //   2164: getstatic f/h1.Wx0 : I
/*    */     //   2167: istore #30
/*    */     //   2169: iconst_1
/*    */     //   2170: iconst_4
/*    */     //   2171: iload #30
/*    */     //   2173: invokespecial <init> : (III)V
/*    */     //   2176: putfield TA : Lf/zT;
/*    */     //   2179: new f/CU
/*    */     //   2182: dup
/*    */     //   2183: dup
/*    */     //   2184: astore #30
/*    */     //   2186: aload #29
/*    */     //   2188: invokespecial <init> : (Lf/zT;)V
/*    */     //   2191: ldc_w 'label-settings-vai'
/*    */     //   2194: invokevirtual Xu : (Ljava/lang/String;)V
/*    */     //   2197: new f/Un
/*    */     //   2200: dup
/*    */     //   2201: dup
/*    */     //   2202: astore #29
/*    */     //   2204: bipush #53
/*    */     //   2206: invokestatic OH0 : (I)Ljava/lang/String;
/*    */     //   2209: invokespecial <init> : (Ljava/lang/String;)V
/*    */     //   2212: new f/ml0
/*    */     //   2215: dup
/*    */     //   2216: aload_0
/*    */     //   2217: invokespecial <init> : (Lf/v10;)V
/*    */     //   2220: invokevirtual tW : (Ljava/lang/Runnable;)V
/*    */     //   2223: new f/Un
/*    */     //   2226: dup
/*    */     //   2227: astore #31
/*    */     //   2229: aload_0
/*    */     //   2230: dup
/*    */     //   2231: aload #31
/*    */     //   2233: dup
/*    */     //   2234: bipush #54
/*    */     //   2236: invokestatic OH0 : (I)Ljava/lang/String;
/*    */     //   2239: invokespecial <init> : (Ljava/lang/String;)V
/*    */     //   2242: putfield Ki : Lf/Un;
/*    */     //   2245: <illegal opcode> run : (Lf/v10;)Ljava/lang/Runnable;
/*    */     //   2250: invokevirtual tW : (Ljava/lang/Runnable;)V
/*    */     //   2253: new f/dQ
/*    */     //   2256: dup
/*    */     //   2257: astore #31
/*    */     //   2259: sipush #1276
/*    */     //   2262: invokestatic OH0 : (I)Ljava/lang/String;
/*    */     //   2265: invokespecial <init> : (Ljava/lang/String;)V
/*    */     //   2268: new f/zT
/*    */     //   2271: dup
/*    */     //   2272: astore #32
/*    */     //   2274: aload_0
/*    */     //   2275: dup
/*    */     //   2276: aload #32
/*    */     //   2278: dup
/*    */     //   2279: getstatic f/h1.Hh0 : I
/*    */     //   2282: istore #33
/*    */     //   2284: iconst_0
/*    */     //   2285: bipush #100
/*    */     //   2287: iload #33
/*    */     //   2289: invokespecial <init> : (III)V
/*    */     //   2292: putfield tC0 : Lf/zT;
/*    */     //   2295: <illegal opcode> run : (Lf/v10;)Ljava/lang/Runnable;
/*    */     //   2300: invokevirtual Ac0 : (Ljava/lang/Runnable;)V
/*    */     //   2303: new f/dQ
/*    */     //   2306: dup
/*    */     //   2307: astore #33
/*    */     //   2309: sipush #1277
/*    */     //   2312: invokestatic OH0 : (I)Ljava/lang/String;
/*    */     //   2315: invokespecial <init> : (Ljava/lang/String;)V
/*    */     //   2318: new f/dQ
/*    */     //   2321: dup
/*    */     //   2322: astore #34
/*    */     //   2324: sipush #1279
/*    */     //   2327: invokestatic OH0 : (I)Ljava/lang/String;
/*    */     //   2330: invokespecial <init> : (Ljava/lang/String;)V
/*    */     //   2333: new f/zT
/*    */     //   2336: dup
/*    */     //   2337: astore #35
/*    */     //   2339: aload_0
/*    */     //   2340: dup
/*    */     //   2341: aload #35
/*    */     //   2343: dup
/*    */     //   2344: getstatic f/h1.HF : I
/*    */     //   2347: istore #36
/*    */     //   2349: iconst_0
/*    */     //   2350: bipush #100
/*    */     //   2352: iload #36
/*    */     //   2354: invokespecial <init> : (III)V
/*    */     //   2357: putfield Zz0 : Lf/zT;
/*    */     //   2360: <illegal opcode> run : (Lf/v10;)Ljava/lang/Runnable;
/*    */     //   2365: invokevirtual Ac0 : (Ljava/lang/Runnable;)V
/*    */     //   2368: new f/zT
/*    */     //   2371: dup
/*    */     //   2372: astore #36
/*    */     //   2374: aload_0
/*    */     //   2375: dup
/*    */     //   2376: aload #36
/*    */     //   2378: dup
/*    */     //   2379: getstatic f/h1.xP : I
/*    */     //   2382: istore #37
/*    */     //   2384: iconst_0
/*    */     //   2385: bipush #100
/*    */     //   2387: iload #37
/*    */     //   2389: invokespecial <init> : (III)V
/*    */     //   2392: putfield FN : Lf/zT;
/*    */     //   2395: <illegal opcode> run : (Lf/v10;)Ljava/lang/Runnable;
/*    */     //   2400: invokevirtual Ac0 : (Ljava/lang/Runnable;)V
/*    */     //   2403: new f/dQ
/*    */     //   2406: dup
/*    */     //   2407: astore #37
/*    */     //   2409: sipush #1365
/*    */     //   2412: invokestatic OH0 : (I)Ljava/lang/String;
/*    */     //   2415: invokespecial <init> : (Ljava/lang/String;)V
/*    */     //   2418: new f/OZ
/*    */     //   2421: dup
/*    */     //   2422: dup
/*    */     //   2423: astore #38
/*    */     //   2425: getstatic f/UB0.L90 : Lf/OL;
/*    */     //   2428: invokeinterface Mv : ()[Ljava/lang/String;
/*    */     //   2433: invokespecial <init> : ([Ljava/lang/Object;)V
/*    */     //   2436: sipush #1366
/*    */     //   2439: invokestatic OH0 : (I)Ljava/lang/String;
/*    */     //   2442: astore #39
/*    */     //   2444: iconst_0
/*    */     //   2445: aload #39
/*    */     //   2447: invokevirtual CR : (ILjava/lang/Object;)V
/*    */     //   2450: new f/W1
/*    */     //   2453: dup
/*    */     //   2454: astore #40
/*    */     //   2456: aload_0
/*    */     //   2457: aload #40
/*    */     //   2459: dup
/*    */     //   2460: aload #38
/*    */     //   2462: invokespecial <init> : (Lf/cQ;)V
/*    */     //   2465: putfield eh0 : Lf/W1;
/*    */     //   2468: iconst_0
/*    */     //   2469: invokevirtual Z30 : (I)V
/*    */     //   2472: getstatic f/h1.PB : Ljava/lang/String;
/*    */     //   2475: invokevirtual isEmpty : ()Z
/*    */     //   2478: ifne -> 2489
/*    */     //   2481: aload #40
/*    */     //   2483: getstatic f/h1.PB : Ljava/lang/String;
/*    */     //   2486: invokevirtual COm6 : (Ljava/lang/Object;)V
/*    */     //   2489: aload_0
/*    */     //   2490: dup
/*    */     //   2491: aload #40
/*    */     //   2493: aload_0
/*    */     //   2494: aload #39
/*    */     //   2496: <illegal opcode> run : (Lf/v10;Ljava/lang/String;)Ljava/lang/Runnable;
/*    */     //   2501: invokevirtual D30 : (Ljava/lang/Runnable;)V
/*    */     //   2504: new f/at
/*    */     //   2507: dup
/*    */     //   2508: astore #38
/*    */     //   2510: iconst_1
/*    */     //   2511: anewarray f/JG0
/*    */     //   2514: dup
/*    */     //   2515: iconst_0
/*    */     //   2516: aload #40
/*    */     //   2518: aastore
/*    */     //   2519: invokespecial <init> : ([Lf/JG0;)V
/*    */     //   2522: new f/rh
/*    */     //   2525: dup
/*    */     //   2526: astore #39
/*    */     //   2528: aload #32
/*    */     //   2530: invokespecial <init> : (Lf/er;)V
/*    */     //   2533: new f/rh
/*    */     //   2536: dup
/*    */     //   2537: astore #32
/*    */     //   2539: aload #35
/*    */     //   2541: invokespecial <init> : (Lf/er;)V
/*    */     //   2544: new f/rh
/*    */     //   2547: dup
/*    */     //   2548: astore #35
/*    */     //   2550: aload #36
/*    */     //   2552: invokespecial <init> : (Lf/er;)V
/*    */     //   2555: new f/FL
/*    */     //   2558: dup
/*    */     //   2559: aload_0
/*    */     //   2560: swap
/*    */     //   2561: dup
/*    */     //   2562: sipush #1282
/*    */     //   2565: invokespecial <init> : (I)V
/*    */     //   2568: putfield rQ : Lf/FL;
/*    */     //   2571: getstatic f/h1.VJ0 : Z
/*    */     //   2574: invokevirtual QS : (Z)V
/*    */     //   2577: new f/dQ
/*    */     //   2580: dup
/*    */     //   2581: astore #36
/*    */     //   2583: sipush #1283
/*    */     //   2586: invokestatic OH0 : (I)Ljava/lang/String;
/*    */     //   2589: invokespecial <init> : (Ljava/lang/String;)V
/*    */     //   2592: new f/zT
/*    */     //   2595: dup
/*    */     //   2596: dup
/*    */     //   2597: astore #40
/*    */     //   2599: getstatic f/h1.In0 : F
/*    */     //   2602: ldc_w 100.0
/*    */     //   2605: fmul
/*    */     //   2606: invokestatic round : (F)I
/*    */     //   2609: istore #41
/*    */     //   2611: iconst_0
/*    */     //   2612: bipush #100
/*    */     //   2614: iload #41
/*    */     //   2616: invokespecial <init> : (III)V
/*    */     //   2619: putfield super : Lf/zT;
/*    */     //   2622: new f/GF
/*    */     //   2625: dup
/*    */     //   2626: astore #41
/*    */     //   2628: aload #35
/*    */     //   2630: aload #32
/*    */     //   2632: aload #39
/*    */     //   2634: aload #36
/*    */     //   2636: aload #34
/*    */     //   2638: aload #37
/*    */     //   2640: aload #33
/*    */     //   2642: aload #31
/*    */     //   2644: aload #41
/*    */     //   2646: aload #40
/*    */     //   2648: invokespecial <init> : (Lf/zT;)V
/*    */     //   2651: ldc_w 'label-settings-title'
/*    */     //   2654: invokevirtual Xu : (Ljava/lang/String;)V
/*    */     //   2657: ldc_w 'label-settings-title'
/*    */     //   2660: invokevirtual Xu : (Ljava/lang/String;)V
/*    */     //   2663: ldc_w 'label-settings-title'
/*    */     //   2666: invokevirtual Xu : (Ljava/lang/String;)V
/*    */     //   2669: ldc_w 'label-settings-title'
/*    */     //   2672: invokevirtual Xu : (Ljava/lang/String;)V
/*    */     //   2675: ldc_w 'label-settings-title'
/*    */     //   2678: invokevirtual Xu : (Ljava/lang/String;)V
/*    */     //   2681: ldc_w 'label-settings-vai'
/*    */     //   2684: invokevirtual Xu : (Ljava/lang/String;)V
/*    */     //   2687: ldc_w 'label-settings-vai'
/*    */     //   2690: invokevirtual Xu : (Ljava/lang/String;)V
/*    */     //   2693: ldc_w 'label-settings-vai'
/*    */     //   2696: invokevirtual Xu : (Ljava/lang/String;)V
/*    */     //   2699: ldc_w 'label-settings-vai'
/*    */     //   2702: invokevirtual Xu : (Ljava/lang/String;)V
/*    */     //   2705: new f/FL
/*    */     //   2708: dup
/*    */     //   2709: dup
/*    */     //   2710: astore #40
/*    */     //   2712: sipush #1349
/*    */     //   2715: invokespecial <init> : (I)V
/*    */     //   2718: putfield Y60 : Lf/FL;
/*    */     //   2721: getstatic f/km.iE0 : Lf/r9;
/*    */     //   2724: getstatic f/PX.Oc : Lf/PX;
/*    */     //   2727: dup
/*    */     //   2728: astore #42
/*    */     //   2730: invokevirtual wG0 : (Lf/PX;)Z
/*    */     //   2733: ifeq -> 2747
/*    */     //   2736: aload #40
/*    */     //   2738: getstatic f/h1.D30 : Z
/*    */     //   2741: invokevirtual QS : (Z)V
/*    */     //   2744: goto -> 2773
/*    */     //   2747: aload #40
/*    */     //   2749: dup
/*    */     //   2750: dup
/*    */     //   2751: iconst_0
/*    */     //   2752: invokevirtual QS : (Z)V
/*    */     //   2755: invokevirtual SB0 : ()V
/*    */     //   2758: getstatic f/km.iE0 : Lf/r9;
/*    */     //   2761: aload #42
/*    */     //   2763: invokevirtual MK : (Lf/PX;)Ljava/lang/String;
/*    */     //   2766: invokevirtual yp0 : (Ljava/lang/String;)V
/*    */     //   2769: iconst_0
/*    */     //   2770: putstatic f/h1.D30 : Z
/*    */     //   2773: new f/fQ
/*    */     //   2776: dup
/*    */     //   2777: astore #40
/*    */     //   2779: invokespecial <init> : ()V
/*    */     //   2782: getstatic f/BM.ba0 : [Lf/BM;
/*    */     //   2785: dup
/*    */     //   2786: astore #42
/*    */     //   2788: arraylength
/*    */     //   2789: istore #43
/*    */     //   2791: iconst_0
/*    */     //   2792: istore #44
/*    */     //   2794: iload #44
/*    */     //   2796: iload #43
/*    */     //   2798: if_icmpge -> 2842
/*    */     //   2801: aload #42
/*    */     //   2803: iload #44
/*    */     //   2805: aaload
/*    */     //   2806: dup
/*    */     //   2807: astore #45
/*    */     //   2809: invokevirtual Ff : ()Z
/*    */     //   2812: ifne -> 2818
/*    */     //   2815: goto -> 2836
/*    */     //   2818: aload #40
/*    */     //   2820: new f/Gr
/*    */     //   2823: dup
/*    */     //   2824: astore #46
/*    */     //   2826: aload #45
/*    */     //   2828: invokespecial <init> : (Lf/BM;)V
/*    */     //   2831: aload #46
/*    */     //   2833: invokevirtual Com3 : (Ljava/lang/Object;)V
/*    */     //   2836: iinc #44, 1
/*    */     //   2839: goto -> 2794
/*    */     //   2842: aload #40
/*    */     //   2844: ldc_w f/Gr
/*    */     //   2847: invokevirtual Ib : (Ljava/lang/Class;)[Ljava/lang/Object;
/*    */     //   2850: checkcast [Lf/Gr;
/*    */     //   2853: dup
/*    */     //   2854: astore #40
/*    */     //   2856: aload_0
/*    */     //   2857: aload #40
/*    */     //   2859: putfield Ny : [Lf/Gr;
/*    */     //   2862: arraylength
/*    */     //   2863: istore #42
/*    */     //   2865: iconst_0
/*    */     //   2866: istore #43
/*    */     //   2868: iload #43
/*    */     //   2870: iload #42
/*    */     //   2872: if_icmpge -> 2893
/*    */     //   2875: aload #40
/*    */     //   2877: iload #43
/*    */     //   2879: aaload
/*    */     //   2880: aload_0
/*    */     //   2881: getfield Ny : [Lf/Gr;
/*    */     //   2884: invokevirtual kK0 : ([Lf/Gr;)V
/*    */     //   2887: iinc #43, 1
/*    */     //   2890: goto -> 2868
/*    */     //   2893: new f/Un
/*    */     //   2896: dup
/*    */     //   2897: astore #40
/*    */     //   2899: aload_0
/*    */     //   2900: aload #40
/*    */     //   2902: sipush #1388
/*    */     //   2905: invokestatic OH0 : (I)Ljava/lang/String;
/*    */     //   2908: invokespecial <init> : (Ljava/lang/String;)V
/*    */     //   2911: <illegal opcode> run : (Lf/v10;)Ljava/lang/Runnable;
/*    */     //   2916: invokevirtual tW : (Ljava/lang/Runnable;)V
/*    */     //   2919: invokestatic JR : ()Lf/fQ;
/*    */     //   2922: ldc_w f/ah0
/*    */     //   2925: invokevirtual Ib : (Ljava/lang/Class;)[Ljava/lang/Object;
/*    */     //   2928: checkcast [Lf/ah0;
/*    */     //   2931: dup
/*    */     //   2932: dup
/*    */     //   2933: astore #42
/*    */     //   2935: arraylength
/*    */     //   2936: anewarray f/dQ
/*    */     //   2939: astore #43
/*    */     //   2941: arraylength
/*    */     //   2942: bipush #26
/*    */     //   2944: multianewarray[[Lf/zv; 2
/*    */     //   2948: astore #44
/*    */     //   2950: getstatic f/h1.D30 : Z
/*    */     //   2953: ifeq -> 4024
/*    */     //   2956: iconst_0
/*    */     //   2957: istore #45
/*    */     //   2959: iload #45
/*    */     //   2961: aload #42
/*    */     //   2963: arraylength
/*    */     //   2964: if_icmpge -> 4024
/*    */     //   2967: aload #44
/*    */     //   2969: iload #45
/*    */     //   2971: aload #44
/*    */     //   2973: iload #45
/*    */     //   2975: aload #44
/*    */     //   2977: iload #45
/*    */     //   2979: aload #44
/*    */     //   2981: iload #45
/*    */     //   2983: aload #44
/*    */     //   2985: iload #45
/*    */     //   2987: aload #44
/*    */     //   2989: iload #45
/*    */     //   2991: aload #44
/*    */     //   2993: iload #45
/*    */     //   2995: aload #44
/*    */     //   2997: iload #45
/*    */     //   2999: aload #44
/*    */     //   3001: iload #45
/*    */     //   3003: aload #44
/*    */     //   3005: iload #45
/*    */     //   3007: aload #44
/*    */     //   3009: iload #45
/*    */     //   3011: aload #44
/*    */     //   3013: iload #45
/*    */     //   3015: aload #44
/*    */     //   3017: iload #45
/*    */     //   3019: aload #44
/*    */     //   3021: iload #45
/*    */     //   3023: aload #44
/*    */     //   3025: iload #45
/*    */     //   3027: aload #44
/*    */     //   3029: iload #45
/*    */     //   3031: aload #44
/*    */     //   3033: iload #45
/*    */     //   3035: aload #44
/*    */     //   3037: iload #45
/*    */     //   3039: aload #44
/*    */     //   3041: iload #45
/*    */     //   3043: aload #44
/*    */     //   3045: iload #45
/*    */     //   3047: aload #44
/*    */     //   3049: iload #45
/*    */     //   3051: aload #44
/*    */     //   3053: iload #45
/*    */     //   3055: aload #44
/*    */     //   3057: iload #45
/*    */     //   3059: aload #44
/*    */     //   3061: iload #45
/*    */     //   3063: aload #44
/*    */     //   3065: iload #45
/*    */     //   3067: aload #44
/*    */     //   3069: iload #45
/*    */     //   3071: aload #44
/*    */     //   3073: iload #45
/*    */     //   3075: aload #42
/*    */     //   3077: iload #45
/*    */     //   3079: aaload
/*    */     //   3080: invokestatic eE : (Lf/ah0;)Lf/rx0;
/*    */     //   3083: astore #46
/*    */     //   3085: new f/dQ
/*    */     //   3088: dup
/*    */     //   3089: astore #47
/*    */     //   3091: aload #43
/*    */     //   3093: iload #45
/*    */     //   3095: aload #47
/*    */     //   3097: dup
/*    */     //   3098: aload #46
/*    */     //   3100: invokevirtual LPt1 : ()Ljava/lang/String;
/*    */     //   3103: invokespecial <init> : (Ljava/lang/String;)V
/*    */     //   3106: aastore
/*    */     //   3107: ldc_w 'label-settings-title'
/*    */     //   3110: invokevirtual Xu : (Ljava/lang/String;)V
/*    */     //   3113: aaload
/*    */     //   3114: new f/zv
/*    */     //   3117: dup
/*    */     //   3118: astore #47
/*    */     //   3120: getstatic f/BM.bC : Lf/BM;
/*    */     //   3123: astore #48
/*    */     //   3125: sipush #1300
/*    */     //   3128: aload #46
/*    */     //   3130: aload #48
/*    */     //   3132: invokespecial <init> : (ILf/rx0;Lf/BM;)V
/*    */     //   3135: iconst_0
/*    */     //   3136: aload #47
/*    */     //   3138: aastore
/*    */     //   3139: aaload
/*    */     //   3140: new f/zv
/*    */     //   3143: dup
/*    */     //   3144: astore #47
/*    */     //   3146: getstatic f/BM.lc : Lf/BM;
/*    */     //   3149: astore #48
/*    */     //   3151: sipush #1301
/*    */     //   3154: aload #46
/*    */     //   3156: aload #48
/*    */     //   3158: invokespecial <init> : (ILf/rx0;Lf/BM;)V
/*    */     //   3161: iconst_1
/*    */     //   3162: aload #47
/*    */     //   3164: aastore
/*    */     //   3165: aaload
/*    */     //   3166: new f/zv
/*    */     //   3169: dup
/*    */     //   3170: astore #47
/*    */     //   3172: getstatic f/BM.ni : Lf/BM;
/*    */     //   3175: astore #48
/*    */     //   3177: sipush #1302
/*    */     //   3180: aload #46
/*    */     //   3182: aload #48
/*    */     //   3184: invokespecial <init> : (ILf/rx0;Lf/BM;)V
/*    */     //   3187: iconst_2
/*    */     //   3188: aload #47
/*    */     //   3190: aastore
/*    */     //   3191: aaload
/*    */     //   3192: new f/zv
/*    */     //   3195: dup
/*    */     //   3196: astore #47
/*    */     //   3198: getstatic f/BM.N70 : Lf/BM;
/*    */     //   3201: astore #48
/*    */     //   3203: sipush #1303
/*    */     //   3206: aload #46
/*    */     //   3208: aload #48
/*    */     //   3210: invokespecial <init> : (ILf/rx0;Lf/BM;)V
/*    */     //   3213: iconst_3
/*    */     //   3214: aload #47
/*    */     //   3216: aastore
/*    */     //   3217: aaload
/*    */     //   3218: new f/zv
/*    */     //   3221: dup
/*    */     //   3222: astore #47
/*    */     //   3224: getstatic f/BM.Oq : Lf/BM;
/*    */     //   3227: astore #48
/*    */     //   3229: sipush #1304
/*    */     //   3232: aload #46
/*    */     //   3234: aload #48
/*    */     //   3236: invokespecial <init> : (ILf/rx0;Lf/BM;)V
/*    */     //   3239: iconst_4
/*    */     //   3240: aload #47
/*    */     //   3242: aastore
/*    */     //   3243: aaload
/*    */     //   3244: new f/zv
/*    */     //   3247: dup
/*    */     //   3248: astore #47
/*    */     //   3250: getstatic f/BM.M8 : Lf/BM;
/*    */     //   3253: astore #48
/*    */     //   3255: sipush #1305
/*    */     //   3258: aload #46
/*    */     //   3260: aload #48
/*    */     //   3262: invokespecial <init> : (ILf/rx0;Lf/BM;)V
/*    */     //   3265: iconst_5
/*    */     //   3266: aload #47
/*    */     //   3268: aastore
/*    */     //   3269: aaload
/*    */     //   3270: new f/zv
/*    */     //   3273: dup
/*    */     //   3274: astore #47
/*    */     //   3276: getstatic f/BM.PW : Lf/BM;
/*    */     //   3279: astore #48
/*    */     //   3281: sipush #1363
/*    */     //   3284: aload #46
/*    */     //   3286: aload #48
/*    */     //   3288: invokespecial <init> : (ILf/rx0;Lf/BM;)V
/*    */     //   3291: bipush #6
/*    */     //   3293: aload #47
/*    */     //   3295: aastore
/*    */     //   3296: aaload
/*    */     //   3297: new f/zv
/*    */     //   3300: dup
/*    */     //   3301: astore #47
/*    */     //   3303: getstatic f/BM.fN : Lf/BM;
/*    */     //   3306: astore #48
/*    */     //   3308: sipush #1364
/*    */     //   3311: aload #46
/*    */     //   3313: aload #48
/*    */     //   3315: invokespecial <init> : (ILf/rx0;Lf/BM;)V
/*    */     //   3318: bipush #7
/*    */     //   3320: aload #47
/*    */     //   3322: aastore
/*    */     //   3323: aaload
/*    */     //   3324: new f/zv
/*    */     //   3327: dup
/*    */     //   3328: astore #47
/*    */     //   3330: new java/lang/StringBuilder
/*    */     //   3333: dup
/*    */     //   3334: astore #48
/*    */     //   3336: invokespecial <init> : ()V
/*    */     //   3339: sipush #1306
/*    */     //   3342: aload #48
/*    */     //   3344: ldc_w ' 1:'
/*    */     //   3347: invokestatic jJ0 : (ILjava/lang/StringBuilder;Ljava/lang/String;)Ljava/lang/String;
/*    */     //   3350: aload #46
/*    */     //   3352: getstatic f/BM.Ul : Lf/BM;
/*    */     //   3355: invokespecial <init> : (Ljava/lang/String;Lf/rx0;Lf/BM;)V
/*    */     //   3358: bipush #8
/*    */     //   3360: aload #47
/*    */     //   3362: aastore
/*    */     //   3363: aaload
/*    */     //   3364: new f/zv
/*    */     //   3367: dup
/*    */     //   3368: astore #47
/*    */     //   3370: new java/lang/StringBuilder
/*    */     //   3373: dup
/*    */     //   3374: astore #48
/*    */     //   3376: invokespecial <init> : ()V
/*    */     //   3379: sipush #1306
/*    */     //   3382: aload #48
/*    */     //   3384: ldc_w ' 2:'
/*    */     //   3387: invokestatic jJ0 : (ILjava/lang/StringBuilder;Ljava/lang/String;)Ljava/lang/String;
/*    */     //   3390: aload #46
/*    */     //   3392: getstatic f/BM.Vv0 : Lf/BM;
/*    */     //   3395: invokespecial <init> : (Ljava/lang/String;Lf/rx0;Lf/BM;)V
/*    */     //   3398: bipush #9
/*    */     //   3400: aload #47
/*    */     //   3402: aastore
/*    */     //   3403: aaload
/*    */     //   3404: new f/zv
/*    */     //   3407: dup
/*    */     //   3408: astore #47
/*    */     //   3410: new java/lang/StringBuilder
/*    */     //   3413: dup
/*    */     //   3414: astore #48
/*    */     //   3416: invokespecial <init> : ()V
/*    */     //   3419: sipush #1306
/*    */     //   3422: aload #48
/*    */     //   3424: ldc_w ' 3:'
/*    */     //   3427: invokestatic jJ0 : (ILjava/lang/StringBuilder;Ljava/lang/String;)Ljava/lang/String;
/*    */     //   3430: aload #46
/*    */     //   3432: getstatic f/BM.lpT3 : Lf/BM;
/*    */     //   3435: invokespecial <init> : (Ljava/lang/String;Lf/rx0;Lf/BM;)V
/*    */     //   3438: bipush #10
/*    */     //   3440: aload #47
/*    */     //   3442: aastore
/*    */     //   3443: aaload
/*    */     //   3444: new f/zv
/*    */     //   3447: dup
/*    */     //   3448: astore #47
/*    */     //   3450: new java/lang/StringBuilder
/*    */     //   3453: dup
/*    */     //   3454: astore #48
/*    */     //   3456: invokespecial <init> : ()V
/*    */     //   3459: sipush #1306
/*    */     //   3462: aload #48
/*    */     //   3464: ldc_w ' 4:'
/*    */     //   3467: invokestatic jJ0 : (ILjava/lang/StringBuilder;Ljava/lang/String;)Ljava/lang/String;
/*    */     //   3470: aload #46
/*    */     //   3472: getstatic f/BM.WN : Lf/BM;
/*    */     //   3475: invokespecial <init> : (Ljava/lang/String;Lf/rx0;Lf/BM;)V
/*    */     //   3478: bipush #11
/*    */     //   3480: aload #47
/*    */     //   3482: aastore
/*    */     //   3483: aaload
/*    */     //   3484: new f/zv
/*    */     //   3487: dup
/*    */     //   3488: astore #47
/*    */     //   3490: new java/lang/StringBuilder
/*    */     //   3493: dup
/*    */     //   3494: astore #48
/*    */     //   3496: invokespecial <init> : ()V
/*    */     //   3499: sipush #1306
/*    */     //   3502: aload #48
/*    */     //   3504: ldc_w ' 5:'
/*    */     //   3507: invokestatic jJ0 : (ILjava/lang/StringBuilder;Ljava/lang/String;)Ljava/lang/String;
/*    */     //   3510: aload #46
/*    */     //   3512: getstatic f/BM.Vs : Lf/BM;
/*    */     //   3515: invokespecial <init> : (Ljava/lang/String;Lf/rx0;Lf/BM;)V
/*    */     //   3518: bipush #12
/*    */     //   3520: aload #47
/*    */     //   3522: aastore
/*    */     //   3523: aaload
/*    */     //   3524: new f/zv
/*    */     //   3527: dup
/*    */     //   3528: astore #47
/*    */     //   3530: new java/lang/StringBuilder
/*    */     //   3533: dup
/*    */     //   3534: astore #48
/*    */     //   3536: invokespecial <init> : ()V
/*    */     //   3539: sipush #1306
/*    */     //   3542: aload #48
/*    */     //   3544: ldc_w ' 6:'
/*    */     //   3547: invokestatic jJ0 : (ILjava/lang/StringBuilder;Ljava/lang/String;)Ljava/lang/String;
/*    */     //   3550: aload #46
/*    */     //   3552: getstatic f/BM.jA : Lf/BM;
/*    */     //   3555: invokespecial <init> : (Ljava/lang/String;Lf/rx0;Lf/BM;)V
/*    */     //   3558: bipush #13
/*    */     //   3560: aload #47
/*    */     //   3562: aastore
/*    */     //   3563: aaload
/*    */     //   3564: new f/zv
/*    */     //   3567: dup
/*    */     //   3568: astore #47
/*    */     //   3570: new java/lang/StringBuilder
/*    */     //   3573: dup
/*    */     //   3574: astore #48
/*    */     //   3576: invokespecial <init> : ()V
/*    */     //   3579: sipush #1306
/*    */     //   3582: aload #48
/*    */     //   3584: ldc_w ' 7:'
/*    */     //   3587: invokestatic jJ0 : (ILjava/lang/StringBuilder;Ljava/lang/String;)Ljava/lang/String;
/*    */     //   3590: aload #46
/*    */     //   3592: getstatic f/BM.Um0 : Lf/BM;
/*    */     //   3595: invokespecial <init> : (Ljava/lang/String;Lf/rx0;Lf/BM;)V
/*    */     //   3598: bipush #14
/*    */     //   3600: aload #47
/*    */     //   3602: aastore
/*    */     //   3603: aaload
/*    */     //   3604: new f/zv
/*    */     //   3607: dup
/*    */     //   3608: astore #47
/*    */     //   3610: new java/lang/StringBuilder
/*    */     //   3613: dup
/*    */     //   3614: astore #48
/*    */     //   3616: invokespecial <init> : ()V
/*    */     //   3619: sipush #1306
/*    */     //   3622: aload #48
/*    */     //   3624: ldc_w ' 8:'
/*    */     //   3627: invokestatic jJ0 : (ILjava/lang/StringBuilder;Ljava/lang/String;)Ljava/lang/String;
/*    */     //   3630: aload #46
/*    */     //   3632: getstatic f/BM.Km : Lf/BM;
/*    */     //   3635: invokespecial <init> : (Ljava/lang/String;Lf/rx0;Lf/BM;)V
/*    */     //   3638: bipush #15
/*    */     //   3640: aload #47
/*    */     //   3642: aastore
/*    */     //   3643: aaload
/*    */     //   3644: new f/zv
/*    */     //   3647: dup
/*    */     //   3648: astore #47
/*    */     //   3650: new java/lang/StringBuilder
/*    */     //   3653: dup
/*    */     //   3654: astore #48
/*    */     //   3656: invokespecial <init> : ()V
/*    */     //   3659: sipush #1306
/*    */     //   3662: aload #48
/*    */     //   3664: ldc_w ' 9:'
/*    */     //   3667: invokestatic jJ0 : (ILjava/lang/StringBuilder;Ljava/lang/String;)Ljava/lang/String;
/*    */     //   3670: aload #46
/*    */     //   3672: getstatic f/BM.Hg : Lf/BM;
/*    */     //   3675: invokespecial <init> : (Ljava/lang/String;Lf/rx0;Lf/BM;)V
/*    */     //   3678: bipush #16
/*    */     //   3680: aload #47
/*    */     //   3682: aastore
/*    */     //   3683: aaload
/*    */     //   3684: new f/zv
/*    */     //   3687: dup
/*    */     //   3688: astore #47
/*    */     //   3690: getstatic f/BM.cf : Lf/BM;
/*    */     //   3693: astore #48
/*    */     //   3695: sipush #1308
/*    */     //   3698: aload #46
/*    */     //   3700: aload #48
/*    */     //   3702: invokespecial <init> : (ILf/rx0;Lf/BM;)V
/*    */     //   3705: bipush #17
/*    */     //   3707: aload #47
/*    */     //   3709: aastore
/*    */     //   3710: aaload
/*    */     //   3711: new f/zv
/*    */     //   3714: dup
/*    */     //   3715: astore #47
/*    */     //   3717: getstatic f/BM.Rd : Lf/BM;
/*    */     //   3720: astore #48
/*    */     //   3722: sipush #1309
/*    */     //   3725: aload #46
/*    */     //   3727: aload #48
/*    */     //   3729: invokespecial <init> : (ILf/rx0;Lf/BM;)V
/*    */     //   3732: bipush #18
/*    */     //   3734: aload #47
/*    */     //   3736: aastore
/*    */     //   3737: aaload
/*    */     //   3738: new f/zv
/*    */     //   3741: dup
/*    */     //   3742: astore #47
/*    */     //   3744: getstatic f/BM.I0 : Lf/BM;
/*    */     //   3747: astore #48
/*    */     //   3749: sipush #1307
/*    */     //   3752: aload #46
/*    */     //   3754: aload #48
/*    */     //   3756: invokespecial <init> : (ILf/rx0;Lf/BM;)V
/*    */     //   3759: bipush #19
/*    */     //   3761: aload #47
/*    */     //   3763: aastore
/*    */     //   3764: aaload
/*    */     //   3765: new f/zv
/*    */     //   3768: dup
/*    */     //   3769: astore #47
/*    */     //   3771: getstatic f/BM.TC : Lf/BM;
/*    */     //   3774: astore #48
/*    */     //   3776: iconst_1
/*    */     //   3777: aload #46
/*    */     //   3779: aload #48
/*    */     //   3781: invokespecial <init> : (ILf/rx0;Lf/BM;)V
/*    */     //   3784: bipush #20
/*    */     //   3786: aload #47
/*    */     //   3788: aastore
/*    */     //   3789: aaload
/*    */     //   3790: new f/zv
/*    */     //   3793: dup
/*    */     //   3794: astore #47
/*    */     //   3796: getstatic f/BM.l30 : Lf/BM;
/*    */     //   3799: astore #48
/*    */     //   3801: sipush #1310
/*    */     //   3804: aload #46
/*    */     //   3806: aload #48
/*    */     //   3808: invokespecial <init> : (ILf/rx0;Lf/BM;)V
/*    */     //   3811: bipush #21
/*    */     //   3813: aload #47
/*    */     //   3815: aastore
/*    */     //   3816: aaload
/*    */     //   3817: new f/zv
/*    */     //   3820: dup
/*    */     //   3821: astore #47
/*    */     //   3823: getstatic f/BM.eH0 : Lf/BM;
/*    */     //   3826: astore #48
/*    */     //   3828: sipush #1311
/*    */     //   3831: aload #46
/*    */     //   3833: aload #48
/*    */     //   3835: invokespecial <init> : (ILf/rx0;Lf/BM;)V
/*    */     //   3838: bipush #22
/*    */     //   3840: aload #47
/*    */     //   3842: aastore
/*    */     //   3843: aaload
/*    */     //   3844: new f/zv
/*    */     //   3847: dup
/*    */     //   3848: astore #47
/*    */     //   3850: getstatic f/BM.Ij0 : Lf/BM;
/*    */     //   3853: astore #48
/*    */     //   3855: sipush #1313
/*    */     //   3858: aload #46
/*    */     //   3860: aload #48
/*    */     //   3862: invokespecial <init> : (ILf/rx0;Lf/BM;)V
/*    */     //   3865: bipush #23
/*    */     //   3867: aload #47
/*    */     //   3869: aastore
/*    */     //   3870: aaload
/*    */     //   3871: new f/zv
/*    */     //   3874: dup
/*    */     //   3875: astore #47
/*    */     //   3877: getstatic f/BM.i40 : Lf/BM;
/*    */     //   3880: astore #48
/*    */     //   3882: sipush #1314
/*    */     //   3885: aload #46
/*    */     //   3887: aload #48
/*    */     //   3889: invokespecial <init> : (ILf/rx0;Lf/BM;)V
/*    */     //   3892: bipush #24
/*    */     //   3894: aload #47
/*    */     //   3896: aastore
/*    */     //   3897: aaload
/*    */     //   3898: new f/zv
/*    */     //   3901: dup
/*    */     //   3902: astore #47
/*    */     //   3904: getstatic f/BM.W1 : Lf/BM;
/*    */     //   3907: astore #48
/*    */     //   3909: sipush #1312
/*    */     //   3912: aload #46
/*    */     //   3914: aload #48
/*    */     //   3916: invokespecial <init> : (ILf/rx0;Lf/BM;)V
/*    */     //   3919: bipush #25
/*    */     //   3921: aload #47
/*    */     //   3923: aastore
/*    */     //   3924: new java/util/ArrayList
/*    */     //   3927: dup
/*    */     //   3928: astore #46
/*    */     //   3930: invokespecial <init> : ()V
/*    */     //   3933: aaload
/*    */     //   3934: dup
/*    */     //   3935: astore #47
/*    */     //   3937: arraylength
/*    */     //   3938: istore #48
/*    */     //   3940: iconst_0
/*    */     //   3941: istore #49
/*    */     //   3943: iload #49
/*    */     //   3945: iload #48
/*    */     //   3947: if_icmpge -> 3970
/*    */     //   3950: aload #46
/*    */     //   3952: aload #47
/*    */     //   3954: iload #49
/*    */     //   3956: aaload
/*    */     //   3957: invokevirtual YG : ()Lf/wo0;
/*    */     //   3960: invokevirtual add : (Ljava/lang/Object;)Z
/*    */     //   3963: pop
/*    */     //   3964: iinc #49, 1
/*    */     //   3967: goto -> 3943
/*    */     //   3970: aload #46
/*    */     //   3972: dup
/*    */     //   3973: iconst_0
/*    */     //   3974: anewarray f/wo0
/*    */     //   3977: invokevirtual toArray : ([Ljava/lang/Object;)[Ljava/lang/Object;
/*    */     //   3980: checkcast [Lf/wo0;
/*    */     //   3983: astore #46
/*    */     //   3985: invokevirtual iterator : ()Ljava/util/Iterator;
/*    */     //   3988: astore #47
/*    */     //   3990: aload #47
/*    */     //   3992: invokeinterface hasNext : ()Z
/*    */     //   3997: ifeq -> 4018
/*    */     //   4000: aload #47
/*    */     //   4002: invokeinterface next : ()Ljava/lang/Object;
/*    */     //   4007: checkcast f/wo0
/*    */     //   4010: aload #46
/*    */     //   4012: invokevirtual ym0 : ([Lf/wo0;)V
/*    */     //   4015: goto -> 3990
/*    */     //   4018: iinc #45, 1
/*    */     //   4021: goto -> 2959
/*    */     //   4024: aload_0
/*    */     //   4025: dup
/*    */     //   4026: new f/dQ
/*    */     //   4029: dup
/*    */     //   4030: astore #45
/*    */     //   4032: sipush #1325
/*    */     //   4035: invokestatic OH0 : (I)Ljava/lang/String;
/*    */     //   4038: invokespecial <init> : (Ljava/lang/String;)V
/*    */     //   4041: new f/zT
/*    */     //   4044: dup
/*    */     //   4045: dup
/*    */     //   4046: astore #46
/*    */     //   4048: getstatic f/h1.sK0 : I
/*    */     //   4051: istore #47
/*    */     //   4053: iconst_1
/*    */     //   4054: iconst_4
/*    */     //   4055: iload #47
/*    */     //   4057: invokespecial <init> : (III)V
/*    */     //   4060: putfield D60 : Lf/zT;
/*    */     //   4063: new f/rh
/*    */     //   4066: dup
/*    */     //   4067: astore #47
/*    */     //   4069: aload #46
/*    */     //   4071: invokespecial <init> : (Lf/er;)V
/*    */     //   4074: new f/dQ
/*    */     //   4077: dup
/*    */     //   4078: astore #46
/*    */     //   4080: sipush #1315
/*    */     //   4083: invokestatic OH0 : (I)Ljava/lang/String;
/*    */     //   4086: invokespecial <init> : (Ljava/lang/String;)V
/*    */     //   4089: iconst_3
/*    */     //   4090: anewarray java/lang/String
/*    */     //   4093: dup
/*    */     //   4094: dup2
/*    */     //   4095: astore #48
/*    */     //   4097: bipush #50
/*    */     //   4099: invokestatic OH0 : (I)Ljava/lang/String;
/*    */     //   4102: iconst_0
/*    */     //   4103: swap
/*    */     //   4104: aastore
/*    */     //   4105: sipush #1316
/*    */     //   4108: invokestatic OH0 : (I)Ljava/lang/String;
/*    */     //   4111: iconst_1
/*    */     //   4112: swap
/*    */     //   4113: aastore
/*    */     //   4114: bipush #51
/*    */     //   4116: invokestatic OH0 : (I)Ljava/lang/String;
/*    */     //   4119: iconst_2
/*    */     //   4120: swap
/*    */     //   4121: aastore
/*    */     //   4122: new f/OZ
/*    */     //   4125: dup
/*    */     //   4126: astore #49
/*    */     //   4128: aload #48
/*    */     //   4130: invokespecial <init> : ([Ljava/lang/Object;)V
/*    */     //   4133: new f/W1
/*    */     //   4136: dup
/*    */     //   4137: dup
/*    */     //   4138: astore #48
/*    */     //   4140: aload #49
/*    */     //   4142: invokespecial <init> : (Lf/cQ;)V
/*    */     //   4145: putfield JT : Lf/W1;
/*    */     //   4148: getstatic f/h1.rl0 : I
/*    */     //   4151: dup
/*    */     //   4152: istore #49
/*    */     //   4154: iconst_m1
/*    */     //   4155: if_icmple -> 4165
/*    */     //   4158: aload #48
/*    */     //   4160: iload #49
/*    */     //   4162: invokevirtual Z30 : (I)V
/*    */     //   4165: new f/dQ
/*    */     //   4168: dup
/*    */     //   4169: astore #48
/*    */     //   4171: sipush #1332
/*    */     //   4174: invokestatic OH0 : (I)Ljava/lang/String;
/*    */     //   4177: invokespecial <init> : (Ljava/lang/String;)V
/*    */     //   4180: invokestatic i20 : ()Lf/cE;
/*    */     //   4183: invokevirtual dp0 : ()[Ljava/lang/String;
/*    */     //   4186: dup
/*    */     //   4187: aload_0
/*    */     //   4188: swap
/*    */     //   4189: putfield WE : [Ljava/lang/String;
/*    */     //   4192: arraylength
/*    */     //   4193: dup
/*    */     //   4194: istore #49
/*    */     //   4196: anewarray java/lang/String
/*    */     //   4199: astore #50
/*    */     //   4201: iconst_m1
/*    */     //   4202: istore #51
/*    */     //   4204: iconst_0
/*    */     //   4205: istore #52
/*    */     //   4207: iload #52
/*    */     //   4209: iload #49
/*    */     //   4211: if_icmpge -> 4290
/*    */     //   4214: invokestatic i20 : ()Lf/cE;
/*    */     //   4217: aload_0
/*    */     //   4218: getfield WE : [Ljava/lang/String;
/*    */     //   4221: iload #52
/*    */     //   4223: aaload
/*    */     //   4224: invokevirtual nB : (Ljava/lang/String;)Ljava/lang/String;
/*    */     //   4227: dup
/*    */     //   4228: astore #53
/*    */     //   4230: aload #50
/*    */     //   4232: iload #52
/*    */     //   4234: aload #53
/*    */     //   4236: aastore
/*    */     //   4237: ldc_w ' ('
/*    */     //   4240: invokevirtual contains : (Ljava/lang/CharSequence;)Z
/*    */     //   4243: ifeq -> 4264
/*    */     //   4246: aload #50
/*    */     //   4248: iload #52
/*    */     //   4250: aload #50
/*    */     //   4252: iload #52
/*    */     //   4254: aaload
/*    */     //   4255: ldc_w ' \('
/*    */     //   4258: invokevirtual split : (Ljava/lang/String;)[Ljava/lang/String;
/*    */     //   4261: iconst_0
/*    */     //   4262: aaload
/*    */     //   4263: aastore
/*    */     //   4264: getstatic f/h1.pB0 : Ljava/lang/String;
/*    */     //   4267: aload_0
/*    */     //   4268: getfield WE : [Ljava/lang/String;
/*    */     //   4271: iload #52
/*    */     //   4273: aaload
/*    */     //   4274: invokevirtual equalsIgnoreCase : (Ljava/lang/String;)Z
/*    */     //   4277: ifeq -> 4284
/*    */     //   4280: iload #52
/*    */     //   4282: istore #51
/*    */     //   4284: iinc #52, 1
/*    */     //   4287: goto -> 4207
/*    */     //   4290: iload #51
/*    */     //   4292: aload_0
/*    */     //   4293: new f/OZ
/*    */     //   4296: dup
/*    */     //   4297: astore #49
/*    */     //   4299: aload #50
/*    */     //   4301: invokespecial <init> : ([Ljava/lang/Object;)V
/*    */     //   4304: new f/W1
/*    */     //   4307: dup
/*    */     //   4308: astore #50
/*    */     //   4310: aload #49
/*    */     //   4312: invokespecial <init> : (Lf/cQ;)V
/*    */     //   4315: aload #50
/*    */     //   4317: putfield HD : Lf/W1;
/*    */     //   4320: iconst_m1
/*    */     //   4321: if_icmple -> 4331
/*    */     //   4324: aload #50
/*    */     //   4326: iload #51
/*    */     //   4328: invokevirtual Z30 : (I)V
/*    */     //   4331: aload_0
/*    */     //   4332: new f/dQ
/*    */     //   4335: dup
/*    */     //   4336: astore #49
/*    */     //   4338: getstatic f/F40.ef0 : Lf/F40;
/*    */     //   4341: dup
/*    */     //   4342: astore #50
/*    */     //   4344: bipush #30
/*    */     //   4346: iconst_5
/*    */     //   4347: invokestatic Qf0 : (Lf/F40;II)Ljava/lang/String;
/*    */     //   4350: invokespecial <init> : (Ljava/lang/String;)V
/*    */     //   4353: new f/OZ
/*    */     //   4356: dup
/*    */     //   4357: astore #51
/*    */     //   4359: iconst_2
/*    */     //   4360: anewarray java/lang/String
/*    */     //   4363: dup
/*    */     //   4364: dup
/*    */     //   4365: aload #50
/*    */     //   4367: swap
/*    */     //   4368: aload #50
/*    */     //   4370: bipush #30
/*    */     //   4372: bipush #19
/*    */     //   4374: invokestatic Qf0 : (Lf/F40;II)Ljava/lang/String;
/*    */     //   4377: iconst_0
/*    */     //   4378: swap
/*    */     //   4379: aastore
/*    */     //   4380: bipush #30
/*    */     //   4382: bipush #20
/*    */     //   4384: invokestatic Qf0 : (Lf/F40;II)Ljava/lang/String;
/*    */     //   4387: iconst_1
/*    */     //   4388: swap
/*    */     //   4389: aastore
/*    */     //   4390: invokespecial <init> : ([Ljava/lang/Object;)V
/*    */     //   4393: new f/W1
/*    */     //   4396: dup
/*    */     //   4397: aload #51
/*    */     //   4399: invokespecial <init> : (Lf/cQ;)V
/*    */     //   4402: putfield B3 : Lf/W1;
/*    */     //   4405: iconst_0
/*    */     //   4406: istore #50
/*    */     //   4408: iload #50
/*    */     //   4410: aload #51
/*    */     //   4412: invokevirtual pu : ()I
/*    */     //   4415: if_icmpge -> 4441
/*    */     //   4418: getstatic f/h1.zr0 : I
/*    */     //   4421: iload #50
/*    */     //   4423: if_icmpne -> 4435
/*    */     //   4426: aload_0
/*    */     //   4427: getfield B3 : Lf/W1;
/*    */     //   4430: iload #50
/*    */     //   4432: invokevirtual Z30 : (I)V
/*    */     //   4435: iinc #50, 1
/*    */     //   4438: goto -> 4408
/*    */     //   4441: aload_0
/*    */     //   4442: dup
/*    */     //   4443: new f/dQ
/*    */     //   4446: dup
/*    */     //   4447: astore #50
/*    */     //   4449: sipush #1337
/*    */     //   4452: invokestatic OH0 : (I)Ljava/lang/String;
/*    */     //   4455: invokespecial <init> : (Ljava/lang/String;)V
/*    */     //   4458: new f/OZ
/*    */     //   4461: dup
/*    */     //   4462: dup
/*    */     //   4463: astore #51
/*    */     //   4465: invokestatic k20 : ()[Ljava/lang/String;
/*    */     //   4468: invokespecial <init> : ([Ljava/lang/Object;)V
/*    */     //   4471: putfield ej0 : Lf/OZ;
/*    */     //   4474: new f/W1
/*    */     //   4477: dup
/*    */     //   4478: aload #51
/*    */     //   4480: invokespecial <init> : (Lf/cQ;)V
/*    */     //   4483: putfield RL0 : Lf/W1;
/*    */     //   4486: iconst_0
/*    */     //   4487: istore #51
/*    */     //   4489: iload #51
/*    */     //   4491: aload_0
/*    */     //   4492: getfield ej0 : Lf/OZ;
/*    */     //   4495: invokevirtual pu : ()I
/*    */     //   4498: if_icmpge -> 4543
/*    */     //   4501: getstatic f/h1.qc : Ljava/lang/String;
/*    */     //   4504: invokestatic nS : (Ljava/lang/String;)Lf/Xv0;
/*    */     //   4507: invokevirtual D70 : ()Ljava/lang/String;
/*    */     //   4510: aload_0
/*    */     //   4511: getfield ej0 : Lf/OZ;
/*    */     //   4514: iload #51
/*    */     //   4516: invokevirtual c90 : (I)Ljava/lang/Object;
/*    */     //   4519: checkcast java/lang/String
/*    */     //   4522: invokevirtual equalsIgnoreCase : (Ljava/lang/String;)Z
/*    */     //   4525: ifeq -> 4537
/*    */     //   4528: aload_0
/*    */     //   4529: getfield RL0 : Lf/W1;
/*    */     //   4532: iload #51
/*    */     //   4534: invokevirtual Z30 : (I)V
/*    */     //   4537: iinc #51, 1
/*    */     //   4540: goto -> 4489
/*    */     //   4543: new f/dQ
/*    */     //   4546: dup
/*    */     //   4547: astore #51
/*    */     //   4549: sipush #1339
/*    */     //   4552: invokestatic OH0 : (I)Ljava/lang/String;
/*    */     //   4555: invokespecial <init> : (Ljava/lang/String;)V
/*    */     //   4558: getstatic f/Xv0.Kf0 : [Lf/Xv0;
/*    */     //   4561: dup
/*    */     //   4562: astore #52
/*    */     //   4564: aload_0
/*    */     //   4565: aload #52
/*    */     //   4567: dup
/*    */     //   4568: arraylength
/*    */     //   4569: anewarray f/dQ
/*    */     //   4572: astore #53
/*    */     //   4574: arraylength
/*    */     //   4575: anewarray f/ge0
/*    */     //   4578: putfield II : [Lf/ge0;
/*    */     //   4581: arraylength
/*    */     //   4582: istore #54
/*    */     //   4584: iconst_0
/*    */     //   4585: istore #55
/*    */     //   4587: iload #55
/*    */     //   4589: iload #54
/*    */     //   4591: if_icmpge -> 4716
/*    */     //   4594: aload_0
/*    */     //   4595: dup
/*    */     //   4596: dup
/*    */     //   4597: aload #53
/*    */     //   4599: aload #52
/*    */     //   4601: iload #55
/*    */     //   4603: aaload
/*    */     //   4604: dup
/*    */     //   4605: astore #56
/*    */     //   4607: invokevirtual RI0 : ()B
/*    */     //   4610: new f/dQ
/*    */     //   4613: dup
/*    */     //   4614: new java/lang/StringBuilder
/*    */     //   4617: dup
/*    */     //   4618: aload #56
/*    */     //   4620: swap
/*    */     //   4621: invokespecial <init> : ()V
/*    */     //   4624: invokevirtual D70 : ()Ljava/lang/String;
/*    */     //   4627: invokevirtual append : (Ljava/lang/String;)Ljava/lang/StringBuilder;
/*    */     //   4630: ldc_w ' ['
/*    */     //   4633: invokevirtual append : (Ljava/lang/String;)Ljava/lang/StringBuilder;
/*    */     //   4636: aload #56
/*    */     //   4638: invokevirtual gV : ()Ljava/lang/String;
/*    */     //   4641: invokevirtual append : (Ljava/lang/String;)Ljava/lang/StringBuilder;
/*    */     //   4644: ldc_w ']'
/*    */     //   4647: invokevirtual append : (Ljava/lang/String;)Ljava/lang/StringBuilder;
/*    */     //   4650: invokevirtual toString : ()Ljava/lang/String;
/*    */     //   4653: invokespecial <init> : (Ljava/lang/String;)V
/*    */     //   4656: aastore
/*    */     //   4657: getfield II : [Lf/ge0;
/*    */     //   4660: aload #56
/*    */     //   4662: invokevirtual RI0 : ()B
/*    */     //   4665: new f/ge0
/*    */     //   4668: dup
/*    */     //   4669: invokespecial <init> : ()V
/*    */     //   4672: aastore
/*    */     //   4673: getfield II : [Lf/ge0;
/*    */     //   4676: aload #56
/*    */     //   4678: invokevirtual RI0 : ()B
/*    */     //   4681: aaload
/*    */     //   4682: ldc_w 'togglebutton-small'
/*    */     //   4685: invokevirtual Xu : (Ljava/lang/String;)V
/*    */     //   4688: getfield II : [Lf/ge0;
/*    */     //   4691: aload #56
/*    */     //   4693: invokevirtual RI0 : ()B
/*    */     //   4696: aaload
/*    */     //   4697: invokestatic Jx0 : ()Ljava/util/HashSet;
/*    */     //   4700: aload #56
/*    */     //   4702: invokevirtual contains : (Ljava/lang/Object;)Z
/*    */     //   4705: iconst_1
/*    */     //   4706: ixor
/*    */     //   4707: invokevirtual zs : (Z)V
/*    */     //   4710: iinc #55, 1
/*    */     //   4713: goto -> 4587
/*    */     //   4716: aload_0
/*    */     //   4717: dup
/*    */     //   4718: aload #46
/*    */     //   4720: aload #11
/*    */     //   4722: new f/Un
/*    */     //   4725: dup
/*    */     //   4726: dup2
/*    */     //   4727: astore #52
/*    */     //   4729: sipush #1324
/*    */     //   4732: invokestatic OH0 : (I)Ljava/lang/String;
/*    */     //   4735: invokespecial <init> : (Ljava/lang/String;)V
/*    */     //   4738: ldc_w 'translate-link'
/*    */     //   4741: invokevirtual Xu : (Ljava/lang/String;)V
/*    */     //   4744: new f/DE0
/*    */     //   4747: dup
/*    */     //   4748: invokespecial <init> : ()V
/*    */     //   4751: invokevirtual tW : (Ljava/lang/Runnable;)V
/*    */     //   4754: new f/dQ
/*    */     //   4757: dup
/*    */     //   4758: astore #54
/*    */     //   4760: aload #51
/*    */     //   4762: aload #50
/*    */     //   4764: aload #49
/*    */     //   4766: aload #48
/*    */     //   4768: aload #45
/*    */     //   4770: aload #54
/*    */     //   4772: sipush #1342
/*    */     //   4775: invokestatic OH0 : (I)Ljava/lang/String;
/*    */     //   4778: invokespecial <init> : (Ljava/lang/String;)V
/*    */     //   4781: new f/OZ
/*    */     //   4784: dup
/*    */     //   4785: astore #55
/*    */     //   4787: iconst_4
/*    */     //   4788: anewarray java/lang/String
/*    */     //   4791: dup
/*    */     //   4792: dup
/*    */     //   4793: dup2
/*    */     //   4794: bipush #71
/*    */     //   4796: invokestatic OH0 : (I)Ljava/lang/String;
/*    */     //   4799: iconst_0
/*    */     //   4800: swap
/*    */     //   4801: aastore
/*    */     //   4802: bipush #72
/*    */     //   4804: invokestatic OH0 : (I)Ljava/lang/String;
/*    */     //   4807: iconst_1
/*    */     //   4808: swap
/*    */     //   4809: aastore
/*    */     //   4810: bipush #73
/*    */     //   4812: invokestatic OH0 : (I)Ljava/lang/String;
/*    */     //   4815: iconst_2
/*    */     //   4816: swap
/*    */     //   4817: aastore
/*    */     //   4818: bipush #48
/*    */     //   4820: invokestatic OH0 : (I)Ljava/lang/String;
/*    */     //   4823: iconst_3
/*    */     //   4824: swap
/*    */     //   4825: aastore
/*    */     //   4826: invokespecial <init> : ([Ljava/lang/Object;)V
/*    */     //   4829: new f/W1
/*    */     //   4832: dup
/*    */     //   4833: astore #56
/*    */     //   4835: aload_0
/*    */     //   4836: aload #56
/*    */     //   4838: dup
/*    */     //   4839: aload #55
/*    */     //   4841: invokespecial <init> : (Lf/cQ;)V
/*    */     //   4844: putfield g50 : Lf/W1;
/*    */     //   4847: getstatic f/h1.f0 : I
/*    */     //   4850: invokevirtual Z30 : (I)V
/*    */     //   4853: new f/FL
/*    */     //   4856: dup
/*    */     //   4857: aload_0
/*    */     //   4858: swap
/*    */     //   4859: dup
/*    */     //   4860: sipush #1326
/*    */     //   4863: invokespecial <init> : (I)V
/*    */     //   4866: putfield DC0 : Lf/FL;
/*    */     //   4869: getstatic f/h1.yA0 : Z
/*    */     //   4872: invokevirtual QS : (Z)V
/*    */     //   4875: new f/FL
/*    */     //   4878: dup
/*    */     //   4879: aload_0
/*    */     //   4880: swap
/*    */     //   4881: dup
/*    */     //   4882: sipush #1345
/*    */     //   4885: invokespecial <init> : (I)V
/*    */     //   4888: putfield Kj : Lf/FL;
/*    */     //   4891: getstatic f/h1.sP : Z
/*    */     //   4894: invokevirtual QS : (Z)V
/*    */     //   4897: new f/FL
/*    */     //   4900: dup
/*    */     //   4901: aload_0
/*    */     //   4902: swap
/*    */     //   4903: dup
/*    */     //   4904: sipush #1343
/*    */     //   4907: invokespecial <init> : (I)V
/*    */     //   4910: putfield og0 : Lf/FL;
/*    */     //   4913: getstatic f/h1.me0 : Z
/*    */     //   4916: invokevirtual QS : (Z)V
/*    */     //   4919: new f/FL
/*    */     //   4922: dup
/*    */     //   4923: aload_0
/*    */     //   4924: swap
/*    */     //   4925: dup
/*    */     //   4926: sipush #1330
/*    */     //   4929: invokespecial <init> : (I)V
/*    */     //   4932: putfield ii0 : Lf/FL;
/*    */     //   4935: getstatic f/h1.bf : Z
/*    */     //   4938: invokevirtual QS : (Z)V
/*    */     //   4941: new f/FL
/*    */     //   4944: dup
/*    */     //   4945: aload_0
/*    */     //   4946: swap
/*    */     //   4947: dup
/*    */     //   4948: sipush #1347
/*    */     //   4951: invokespecial <init> : (I)V
/*    */     //   4954: putfield Le0 : Lf/FL;
/*    */     //   4957: getstatic f/h1.QP : Z
/*    */     //   4960: invokevirtual QS : (Z)V
/*    */     //   4963: new f/FL
/*    */     //   4966: dup
/*    */     //   4967: aload_0
/*    */     //   4968: swap
/*    */     //   4969: dup
/*    */     //   4970: sipush #1335
/*    */     //   4973: invokespecial <init> : (I)V
/*    */     //   4976: putfield Z50 : Lf/FL;
/*    */     //   4979: getstatic f/h1.M20 : Z
/*    */     //   4982: invokevirtual QS : (Z)V
/*    */     //   4985: new f/FL
/*    */     //   4988: dup
/*    */     //   4989: aload_0
/*    */     //   4990: swap
/*    */     //   4991: dup
/*    */     //   4992: sipush #1336
/*    */     //   4995: invokespecial <init> : (I)V
/*    */     //   4998: putfield Rs0 : Lf/FL;
/*    */     //   5001: getstatic f/h1.Po0 : Z
/*    */     //   5004: invokevirtual QS : (Z)V
/*    */     //   5007: new f/FL
/*    */     //   5010: dup
/*    */     //   5011: aload_0
/*    */     //   5012: swap
/*    */     //   5013: dup
/*    */     //   5014: sipush #1338
/*    */     //   5017: invokespecial <init> : (I)V
/*    */     //   5020: putfield V1 : Lf/FL;
/*    */     //   5023: getstatic f/h1.c7 : Z
/*    */     //   5026: invokevirtual QS : (Z)V
/*    */     //   5029: new f/FL
/*    */     //   5032: dup
/*    */     //   5033: aload_0
/*    */     //   5034: swap
/*    */     //   5035: dup
/*    */     //   5036: sipush #1346
/*    */     //   5039: invokespecial <init> : (I)V
/*    */     //   5042: putfield wB : Lf/FL;
/*    */     //   5045: getstatic f/h1.Iu0 : Z
/*    */     //   5048: invokevirtual QS : (Z)V
/*    */     //   5051: ldc_w 'label-settings-title'
/*    */     //   5054: invokevirtual Xu : (Ljava/lang/String;)V
/*    */     //   5057: ldc_w 'label-settings-title'
/*    */     //   5060: invokevirtual Xu : (Ljava/lang/String;)V
/*    */     //   5063: ldc_w 'label-settings-title'
/*    */     //   5066: invokevirtual Xu : (Ljava/lang/String;)V
/*    */     //   5069: ldc_w 'label-settings-title'
/*    */     //   5072: invokevirtual Xu : (Ljava/lang/String;)V
/*    */     //   5075: ldc_w 'label-settings-title'
/*    */     //   5078: invokevirtual Xu : (Ljava/lang/String;)V
/*    */     //   5081: ldc_w 'label-settings-title'
/*    */     //   5084: invokevirtual Xu : (Ljava/lang/String;)V
/*    */     //   5087: ldc_w 'label-settings-title'
/*    */     //   5090: invokevirtual Xu : (Ljava/lang/String;)V
/*    */     //   5093: ldc_w 'label-settings-title'
/*    */     //   5096: invokevirtual Xu : (Ljava/lang/String;)V
/*    */     //   5099: new f/at
/*    */     //   5102: dup
/*    */     //   5103: astore #55
/*    */     //   5105: iconst_1
/*    */     //   5106: anewarray f/JG0
/*    */     //   5109: dup
/*    */     //   5110: aload_0
/*    */     //   5111: getfield HD : Lf/W1;
/*    */     //   5114: iconst_0
/*    */     //   5115: swap
/*    */     //   5116: aastore
/*    */     //   5117: invokespecial <init> : ([Lf/JG0;)V
/*    */     //   5120: new f/at
/*    */     //   5123: dup
/*    */     //   5124: astore #57
/*    */     //   5126: iconst_1
/*    */     //   5127: anewarray f/JG0
/*    */     //   5130: dup
/*    */     //   5131: aload_0
/*    */     //   5132: getfield B3 : Lf/W1;
/*    */     //   5135: iconst_0
/*    */     //   5136: swap
/*    */     //   5137: aastore
/*    */     //   5138: invokespecial <init> : ([Lf/JG0;)V
/*    */     //   5141: new f/at
/*    */     //   5144: dup
/*    */     //   5145: astore #58
/*    */     //   5147: iconst_1
/*    */     //   5148: anewarray f/JG0
/*    */     //   5151: dup
/*    */     //   5152: aload_0
/*    */     //   5153: getfield RL0 : Lf/W1;
/*    */     //   5156: iconst_0
/*    */     //   5157: swap
/*    */     //   5158: aastore
/*    */     //   5159: invokespecial <init> : ([Lf/JG0;)V
/*    */     //   5162: new f/at
/*    */     //   5165: dup
/*    */     //   5166: astore #59
/*    */     //   5168: iconst_1
/*    */     //   5169: anewarray f/JG0
/*    */     //   5172: dup
/*    */     //   5173: iconst_0
/*    */     //   5174: aload #56
/*    */     //   5176: aastore
/*    */     //   5177: invokespecial <init> : ([Lf/JG0;)V
/*    */     //   5180: new f/at
/*    */     //   5183: dup
/*    */     //   5184: astore #56
/*    */     //   5186: iconst_1
/*    */     //   5187: anewarray f/JG0
/*    */     //   5190: dup
/*    */     //   5191: aload_0
/*    */     //   5192: getfield BG0 : Lf/W1;
/*    */     //   5195: iconst_0
/*    */     //   5196: swap
/*    */     //   5197: aastore
/*    */     //   5198: invokespecial <init> : ([Lf/JG0;)V
/*    */     //   5201: new f/at
/*    */     //   5204: dup
/*    */     //   5205: astore #60
/*    */     //   5207: iconst_1
/*    */     //   5208: anewarray f/JG0
/*    */     //   5211: dup
/*    */     //   5212: aload_0
/*    */     //   5213: getfield JT : Lf/W1;
/*    */     //   5216: iconst_0
/*    */     //   5217: swap
/*    */     //   5218: aastore
/*    */     //   5219: invokespecial <init> : ([Lf/JG0;)V
/*    */     //   5222: new f/dQ
/*    */     //   5225: dup
/*    */     //   5226: astore #61
/*    */     //   5228: sipush #1260
/*    */     //   5231: invokestatic OH0 : (I)Ljava/lang/String;
/*    */     //   5234: invokespecial <init> : (Ljava/lang/String;)V
/*    */     //   5237: new f/OZ
/*    */     //   5240: dup
/*    */     //   5241: dup
/*    */     //   5242: astore #62
/*    */     //   5244: getstatic f/km.iE0 : Lf/r9;
/*    */     //   5247: invokevirtual DX : ()[Ljava/lang/String;
/*    */     //   5250: invokespecial <init> : ([Ljava/lang/Object;)V
/*    */     //   5253: putfield Wp0 : Lf/OZ;
/*    */     //   5256: new f/W1
/*    */     //   5259: dup
/*    */     //   5260: aload #62
/*    */     //   5262: invokespecial <init> : (Lf/cQ;)V
/*    */     //   5265: putfield n00 : Lf/W1;
/*    */     //   5268: iconst_0
/*    */     //   5269: istore #62
/*    */     //   5271: iconst_m1
/*    */     //   5272: istore #63
/*    */     //   5274: getstatic f/km.iE0 : Lf/r9;
/*    */     //   5277: invokevirtual DX : ()[Ljava/lang/String;
/*    */     //   5280: dup
/*    */     //   5281: astore #64
/*    */     //   5283: arraylength
/*    */     //   5284: istore #65
/*    */     //   5286: iconst_0
/*    */     //   5287: istore #66
/*    */     //   5289: iload #66
/*    */     //   5291: iload #65
/*    */     //   5293: if_icmpge -> 5324
/*    */     //   5296: aload #64
/*    */     //   5298: iload #66
/*    */     //   5300: aaload
/*    */     //   5301: getstatic f/h1.MW : Ljava/lang/String;
/*    */     //   5304: swap
/*    */     //   5305: invokevirtual equalsIgnoreCase : (Ljava/lang/String;)Z
/*    */     //   5308: ifeq -> 5315
/*    */     //   5311: iload #62
/*    */     //   5313: istore #63
/*    */     //   5315: iinc #62, 1
/*    */     //   5318: iinc #66, 1
/*    */     //   5321: goto -> 5289
/*    */     //   5324: aload_0
/*    */     //   5325: aload #61
/*    */     //   5327: aload_0
/*    */     //   5328: getfield n00 : Lf/W1;
/*    */     //   5331: iload #63
/*    */     //   5333: invokevirtual Z30 : (I)V
/*    */     //   5336: new f/at
/*    */     //   5339: dup
/*    */     //   5340: astore #62
/*    */     //   5342: iconst_1
/*    */     //   5343: anewarray f/JG0
/*    */     //   5346: dup
/*    */     //   5347: aload_0
/*    */     //   5348: getfield n00 : Lf/W1;
/*    */     //   5351: iconst_0
/*    */     //   5352: swap
/*    */     //   5353: aastore
/*    */     //   5354: invokespecial <init> : ([Lf/JG0;)V
/*    */     //   5357: ldc_w 'label-settings-title'
/*    */     //   5360: invokevirtual Xu : (Ljava/lang/String;)V
/*    */     //   5363: new f/dQ
/*    */     //   5366: dup
/*    */     //   5367: astore #63
/*    */     //   5369: sipush #1247
/*    */     //   5372: invokestatic OH0 : (I)Ljava/lang/String;
/*    */     //   5375: invokespecial <init> : (Ljava/lang/String;)V
/*    */     //   5378: new f/OZ
/*    */     //   5381: dup
/*    */     //   5382: dup
/*    */     //   5383: astore #64
/*    */     //   5385: getstatic f/UB0.M60 : Lf/w70;
/*    */     //   5388: invokevirtual fG0 : ()I
/*    */     //   5391: getstatic f/UB0.M60 : Lf/w70;
/*    */     //   5394: invokevirtual dL : ()I
/*    */     //   5397: invokestatic ng : (II)Ljava/util/ArrayList;
/*    */     //   5400: invokespecial <init> : (Ljava/util/Collection;)V
/*    */     //   5403: putfield E10 : Lf/OZ;
/*    */     //   5406: new f/rI0
/*    */     //   5409: dup
/*    */     //   5410: aload_0
/*    */     //   5411: swap
/*    */     //   5412: dup
/*    */     //   5413: aload #64
/*    */     //   5415: invokespecial <init> : (Lf/OZ;)V
/*    */     //   5418: putfield Mb : Lf/rI0;
/*    */     //   5421: ldc_w 'combobox'
/*    */     //   5424: invokevirtual Xu : (Ljava/lang/String;)V
/*    */     //   5427: iconst_0
/*    */     //   5428: istore #64
/*    */     //   5430: iload #64
/*    */     //   5432: aload_0
/*    */     //   5433: getfield E10 : Lf/OZ;
/*    */     //   5436: invokevirtual pu : ()I
/*    */     //   5439: if_icmpge -> 5489
/*    */     //   5442: iload #64
/*    */     //   5444: ifeq -> 5474
/*    */     //   5447: getstatic f/h1.zA0 : F
/*    */     //   5450: aload_0
/*    */     //   5451: getfield E10 : Lf/OZ;
/*    */     //   5454: iload #64
/*    */     //   5456: invokevirtual c90 : (I)Ljava/lang/Object;
/*    */     //   5459: checkcast java/lang/Float
/*    */     //   5462: invokevirtual floatValue : ()F
/*    */     //   5465: fconst_1
/*    */     //   5466: swap
/*    */     //   5467: fdiv
/*    */     //   5468: invokestatic JC0 : (FF)Z
/*    */     //   5471: ifeq -> 5483
/*    */     //   5474: aload_0
/*    */     //   5475: getfield Mb : Lf/rI0;
/*    */     //   5478: iload #64
/*    */     //   5480: invokevirtual Z30 : (I)V
/*    */     //   5483: iinc #64, 1
/*    */     //   5486: goto -> 5430
/*    */     //   5489: aload_0
/*    */     //   5490: new f/FL
/*    */     //   5493: dup
/*    */     //   5494: aload_0
/*    */     //   5495: swap
/*    */     //   5496: dup
/*    */     //   5497: sipush #1299
/*    */     //   5500: invokespecial <init> : (I)V
/*    */     //   5503: putfield J6 : Lf/FL;
/*    */     //   5506: getstatic f/h1.je : Z
/*    */     //   5509: invokevirtual QS : (Z)V
/*    */     //   5512: new f/dQ
/*    */     //   5515: dup
/*    */     //   5516: astore #64
/*    */     //   5518: sipush #1290
/*    */     //   5521: invokestatic OH0 : (I)Ljava/lang/String;
/*    */     //   5524: invokespecial <init> : (Ljava/lang/String;)V
/*    */     //   5527: new f/OZ
/*    */     //   5530: dup
/*    */     //   5531: dup
/*    */     //   5532: astore #65
/*    */     //   5534: bipush #9
/*    */     //   5536: anewarray java/lang/Float
/*    */     //   5539: dup
/*    */     //   5540: dup2
/*    */     //   5541: dup2
/*    */     //   5542: dup2
/*    */     //   5543: dup2
/*    */     //   5544: ldc_w 0.7
/*    */     //   5547: invokestatic valueOf : (F)Ljava/lang/Float;
/*    */     //   5550: iconst_0
/*    */     //   5551: swap
/*    */     //   5552: aastore
/*    */     //   5553: ldc_w 0.8
/*    */     //   5556: invokestatic valueOf : (F)Ljava/lang/Float;
/*    */     //   5559: iconst_1
/*    */     //   5560: swap
/*    */     //   5561: aastore
/*    */     //   5562: ldc_w 0.9
/*    */     //   5565: invokestatic valueOf : (F)Ljava/lang/Float;
/*    */     //   5568: iconst_2
/*    */     //   5569: swap
/*    */     //   5570: aastore
/*    */     //   5571: fconst_1
/*    */     //   5572: invokestatic valueOf : (F)Ljava/lang/Float;
/*    */     //   5575: iconst_3
/*    */     //   5576: swap
/*    */     //   5577: aastore
/*    */     //   5578: ldc_w 1.1
/*    */     //   5581: invokestatic valueOf : (F)Ljava/lang/Float;
/*    */     //   5584: iconst_4
/*    */     //   5585: swap
/*    */     //   5586: aastore
/*    */     //   5587: ldc_w 1.2
/*    */     //   5590: invokestatic valueOf : (F)Ljava/lang/Float;
/*    */     //   5593: iconst_5
/*    */     //   5594: swap
/*    */     //   5595: aastore
/*    */     //   5596: ldc_w 1.3
/*    */     //   5599: invokestatic valueOf : (F)Ljava/lang/Float;
/*    */     //   5602: bipush #6
/*    */     //   5604: swap
/*    */     //   5605: aastore
/*    */     //   5606: ldc_w 1.4
/*    */     //   5609: invokestatic valueOf : (F)Ljava/lang/Float;
/*    */     //   5612: bipush #7
/*    */     //   5614: swap
/*    */     //   5615: aastore
/*    */     //   5616: ldc_w 1.5
/*    */     //   5619: invokestatic valueOf : (F)Ljava/lang/Float;
/*    */     //   5622: bipush #8
/*    */     //   5624: swap
/*    */     //   5625: aastore
/*    */     //   5626: invokespecial <init> : ([Ljava/lang/Object;)V
/*    */     //   5629: putfield t0 : Lf/OZ;
/*    */     //   5632: new f/E1
/*    */     //   5635: dup
/*    */     //   5636: aload_0
/*    */     //   5637: swap
/*    */     //   5638: dup
/*    */     //   5639: aload #65
/*    */     //   5641: invokespecial <init> : (Lf/OZ;)V
/*    */     //   5644: putfield hi : Lf/E1;
/*    */     //   5647: ldc_w 'combobox'
/*    */     //   5650: invokevirtual Xu : (Ljava/lang/String;)V
/*    */     //   5653: iconst_0
/*    */     //   5654: istore #65
/*    */     //   5656: iload #65
/*    */     //   5658: aload_0
/*    */     //   5659: getfield t0 : Lf/OZ;
/*    */     //   5662: invokevirtual pu : ()I
/*    */     //   5665: if_icmpge -> 5707
/*    */     //   5668: getstatic f/h1.b90 : F
/*    */     //   5671: aload_0
/*    */     //   5672: getfield t0 : Lf/OZ;
/*    */     //   5675: iload #65
/*    */     //   5677: invokevirtual c90 : (I)Ljava/lang/Object;
/*    */     //   5680: checkcast java/lang/Float
/*    */     //   5683: invokevirtual floatValue : ()F
/*    */     //   5686: invokestatic JC0 : (FF)Z
/*    */     //   5689: ifeq -> 5701
/*    */     //   5692: aload_0
/*    */     //   5693: getfield hi : Lf/E1;
/*    */     //   5696: iload #65
/*    */     //   5698: invokevirtual Z30 : (I)V
/*    */     //   5701: iinc #65, 1
/*    */     //   5704: goto -> 5656
/*    */     //   5707: aload_0
/*    */     //   5708: aload #64
/*    */     //   5710: new f/at
/*    */     //   5713: dup
/*    */     //   5714: astore #65
/*    */     //   5716: iconst_1
/*    */     //   5717: anewarray f/JG0
/*    */     //   5720: dup
/*    */     //   5721: aload_0
/*    */     //   5722: getfield hi : Lf/E1;
/*    */     //   5725: iconst_0
/*    */     //   5726: swap
/*    */     //   5727: aastore
/*    */     //   5728: invokespecial <init> : ([Lf/JG0;)V
/*    */     //   5731: ldc_w 'label-settings-title'
/*    */     //   5734: invokevirtual Xu : (Ljava/lang/String;)V
/*    */     //   5737: new f/dQ
/*    */     //   5740: dup
/*    */     //   5741: astore #66
/*    */     //   5743: sipush #1291
/*    */     //   5746: invokestatic OH0 : (I)Ljava/lang/String;
/*    */     //   5749: invokespecial <init> : (Ljava/lang/String;)V
/*    */     //   5752: new f/OZ
/*    */     //   5755: dup
/*    */     //   5756: dup
/*    */     //   5757: astore #67
/*    */     //   5759: bipush #9
/*    */     //   5761: anewarray java/lang/Float
/*    */     //   5764: dup
/*    */     //   5765: dup2
/*    */     //   5766: dup2
/*    */     //   5767: dup2
/*    */     //   5768: dup2
/*    */     //   5769: ldc_w 0.7
/*    */     //   5772: invokestatic valueOf : (F)Ljava/lang/Float;
/*    */     //   5775: iconst_0
/*    */     //   5776: swap
/*    */     //   5777: aastore
/*    */     //   5778: ldc_w 0.8
/*    */     //   5781: invokestatic valueOf : (F)Ljava/lang/Float;
/*    */     //   5784: iconst_1
/*    */     //   5785: swap
/*    */     //   5786: aastore
/*    */     //   5787: ldc_w 0.9
/*    */     //   5790: invokestatic valueOf : (F)Ljava/lang/Float;
/*    */     //   5793: iconst_2
/*    */     //   5794: swap
/*    */     //   5795: aastore
/*    */     //   5796: fconst_1
/*    */     //   5797: invokestatic valueOf : (F)Ljava/lang/Float;
/*    */     //   5800: iconst_3
/*    */     //   5801: swap
/*    */     //   5802: aastore
/*    */     //   5803: ldc_w 1.1
/*    */     //   5806: invokestatic valueOf : (F)Ljava/lang/Float;
/*    */     //   5809: iconst_4
/*    */     //   5810: swap
/*    */     //   5811: aastore
/*    */     //   5812: ldc_w 1.2
/*    */     //   5815: invokestatic valueOf : (F)Ljava/lang/Float;
/*    */     //   5818: iconst_5
/*    */     //   5819: swap
/*    */     //   5820: aastore
/*    */     //   5821: ldc_w 1.3
/*    */     //   5824: invokestatic valueOf : (F)Ljava/lang/Float;
/*    */     //   5827: bipush #6
/*    */     //   5829: swap
/*    */     //   5830: aastore
/*    */     //   5831: ldc_w 1.4
/*    */     //   5834: invokestatic valueOf : (F)Ljava/lang/Float;
/*    */     //   5837: bipush #7
/*    */     //   5839: swap
/*    */     //   5840: aastore
/*    */     //   5841: ldc_w 1.5
/*    */     //   5844: invokestatic valueOf : (F)Ljava/lang/Float;
/*    */     //   5847: bipush #8
/*    */     //   5849: swap
/*    */     //   5850: aastore
/*    */     //   5851: invokespecial <init> : ([Ljava/lang/Object;)V
/*    */     //   5854: putfield MR : Lf/OZ;
/*    */     //   5857: new f/Q3
/*    */     //   5860: dup
/*    */     //   5861: aload_0
/*    */     //   5862: swap
/*    */     //   5863: dup
/*    */     //   5864: aload #67
/*    */     //   5866: invokespecial <init> : (Lf/OZ;)V
/*    */     //   5869: putfield LQ : Lf/Q3;
/*    */     //   5872: ldc_w 'combobox'
/*    */     //   5875: invokevirtual Xu : (Ljava/lang/String;)V
/*    */     //   5878: iconst_0
/*    */     //   5879: istore #67
/*    */     //   5881: iload #67
/*    */     //   5883: aload_0
/*    */     //   5884: getfield MR : Lf/OZ;
/*    */     //   5887: invokevirtual pu : ()I
/*    */     //   5890: if_icmpge -> 5932
/*    */     //   5893: getstatic f/h1.Fg : F
/*    */     //   5896: aload_0
/*    */     //   5897: getfield MR : Lf/OZ;
/*    */     //   5900: iload #67
/*    */     //   5902: invokevirtual c90 : (I)Ljava/lang/Object;
/*    */     //   5905: checkcast java/lang/Float
/*    */     //   5908: invokevirtual floatValue : ()F
/*    */     //   5911: invokestatic JC0 : (FF)Z
/*    */     //   5914: ifeq -> 5926
/*    */     //   5917: aload_0
/*    */     //   5918: getfield LQ : Lf/Q3;
/*    */     //   5921: iload #67
/*    */     //   5923: invokevirtual Z30 : (I)V
/*    */     //   5926: iinc #67, 1
/*    */     //   5929: goto -> 5881
/*    */     //   5932: aload #66
/*    */     //   5934: new f/at
/*    */     //   5937: dup
/*    */     //   5938: astore #67
/*    */     //   5940: iconst_1
/*    */     //   5941: anewarray f/JG0
/*    */     //   5944: dup
/*    */     //   5945: aload_0
/*    */     //   5946: getfield LQ : Lf/Q3;
/*    */     //   5949: iconst_0
/*    */     //   5950: swap
/*    */     //   5951: aastore
/*    */     //   5952: invokespecial <init> : ([Lf/JG0;)V
/*    */     //   5955: ldc_w 'label-settings-title'
/*    */     //   5958: invokevirtual Xu : (Ljava/lang/String;)V
/*    */     //   5961: new f/dQ
/*    */     //   5964: dup
/*    */     //   5965: dup
/*    */     //   5966: astore #68
/*    */     //   5968: aload_0
/*    */     //   5969: aload #68
/*    */     //   5971: sipush #1293
/*    */     //   5974: invokestatic OH0 : (I)Ljava/lang/String;
/*    */     //   5977: invokespecial <init> : (Ljava/lang/String;)V
/*    */     //   5980: new f/OZ
/*    */     //   5983: dup
/*    */     //   5984: dup
/*    */     //   5985: astore #69
/*    */     //   5987: bipush #6
/*    */     //   5989: anewarray java/lang/Float
/*    */     //   5992: dup
/*    */     //   5993: dup
/*    */     //   5994: dup2
/*    */     //   5995: dup2
/*    */     //   5996: ldc_w 0.1
/*    */     //   5999: invokestatic valueOf : (F)Ljava/lang/Float;
/*    */     //   6002: iconst_0
/*    */     //   6003: swap
/*    */     //   6004: aastore
/*    */     //   6005: ldc_w 0.2
/*    */     //   6008: invokestatic valueOf : (F)Ljava/lang/Float;
/*    */     //   6011: iconst_1
/*    */     //   6012: swap
/*    */     //   6013: aastore
/*    */     //   6014: ldc_w 0.3
/*    */     //   6017: invokestatic valueOf : (F)Ljava/lang/Float;
/*    */     //   6020: iconst_2
/*    */     //   6021: swap
/*    */     //   6022: aastore
/*    */     //   6023: ldc_w 0.4
/*    */     //   6026: invokestatic valueOf : (F)Ljava/lang/Float;
/*    */     //   6029: iconst_3
/*    */     //   6030: swap
/*    */     //   6031: aastore
/*    */     //   6032: ldc_w 0.5
/*    */     //   6035: invokestatic valueOf : (F)Ljava/lang/Float;
/*    */     //   6038: iconst_4
/*    */     //   6039: swap
/*    */     //   6040: aastore
/*    */     //   6041: ldc_w 0.6
/*    */     //   6044: invokestatic valueOf : (F)Ljava/lang/Float;
/*    */     //   6047: iconst_5
/*    */     //   6048: swap
/*    */     //   6049: aastore
/*    */     //   6050: invokespecial <init> : ([Ljava/lang/Object;)V
/*    */     //   6053: putfield GQ : Lf/OZ;
/*    */     //   6056: new f/xl0
/*    */     //   6059: dup
/*    */     //   6060: aload_0
/*    */     //   6061: swap
/*    */     //   6062: dup
/*    */     //   6063: aload #69
/*    */     //   6065: invokespecial <init> : (Lf/OZ;)V
/*    */     //   6068: putfield P10 : Lf/xl0;
/*    */     //   6071: ldc_w 'combobox'
/*    */     //   6074: invokevirtual Xu : (Ljava/lang/String;)V
/*    */     //   6077: sipush #1294
/*    */     //   6080: invokestatic OH0 : (I)Ljava/lang/String;
/*    */     //   6083: invokevirtual Gq0 : (Ljava/lang/Object;)V
/*    */     //   6086: bipush #100
/*    */     //   6088: invokevirtual Pb0 : (I)V
/*    */     //   6091: iconst_0
/*    */     //   6092: istore #69
/*    */     //   6094: iload #69
/*    */     //   6096: aload_0
/*    */     //   6097: getfield GQ : Lf/OZ;
/*    */     //   6100: invokevirtual pu : ()I
/*    */     //   6103: if_icmpge -> 6145
/*    */     //   6106: getstatic f/h1.nR : F
/*    */     //   6109: aload_0
/*    */     //   6110: getfield GQ : Lf/OZ;
/*    */     //   6113: iload #69
/*    */     //   6115: invokevirtual c90 : (I)Ljava/lang/Object;
/*    */     //   6118: checkcast java/lang/Float
/*    */     //   6121: invokevirtual floatValue : ()F
/*    */     //   6124: invokestatic JC0 : (FF)Z
/*    */     //   6127: ifeq -> 6139
/*    */     //   6130: aload_0
/*    */     //   6131: getfield P10 : Lf/xl0;
/*    */     //   6134: iload #69
/*    */     //   6136: invokevirtual Z30 : (I)V
/*    */     //   6139: iinc #69, 1
/*    */     //   6142: goto -> 6094
/*    */     //   6145: aload #68
/*    */     //   6147: new f/at
/*    */     //   6150: dup
/*    */     //   6151: astore #69
/*    */     //   6153: iconst_1
/*    */     //   6154: anewarray f/JG0
/*    */     //   6157: dup
/*    */     //   6158: aload_0
/*    */     //   6159: getfield P10 : Lf/xl0;
/*    */     //   6162: iconst_0
/*    */     //   6163: swap
/*    */     //   6164: aastore
/*    */     //   6165: invokespecial <init> : ([Lf/JG0;)V
/*    */     //   6168: ldc_w 'label-settings-title'
/*    */     //   6171: invokevirtual Xu : (Ljava/lang/String;)V
/*    */     //   6174: new f/dQ
/*    */     //   6177: dup
/*    */     //   6178: astore #70
/*    */     //   6180: sipush #1295
/*    */     //   6183: invokestatic OH0 : (I)Ljava/lang/String;
/*    */     //   6186: invokespecial <init> : (Ljava/lang/String;)V
/*    */     //   6189: iconst_4
/*    */     //   6190: anewarray java/lang/String
/*    */     //   6193: astore #71
/*    */     //   6195: iconst_0
/*    */     //   6196: istore #72
/*    */     //   6198: iload #72
/*    */     //   6200: iconst_4
/*    */     //   6201: if_icmpge -> 6223
/*    */     //   6204: aload #71
/*    */     //   6206: iload #72
/*    */     //   6208: dup
/*    */     //   6209: sipush #1286
/*    */     //   6212: iadd
/*    */     //   6213: invokestatic OH0 : (I)Ljava/lang/String;
/*    */     //   6216: aastore
/*    */     //   6217: iinc #72, 1
/*    */     //   6220: goto -> 6198
/*    */     //   6223: new f/OZ
/*    */     //   6226: dup
/*    */     //   6227: astore #72
/*    */     //   6229: aload #71
/*    */     //   6231: invokespecial <init> : ([Ljava/lang/Object;)V
/*    */     //   6234: new f/W1
/*    */     //   6237: dup
/*    */     //   6238: astore #71
/*    */     //   6240: aload_0
/*    */     //   6241: aload #71
/*    */     //   6243: aload #72
/*    */     //   6245: invokespecial <init> : (Lf/cQ;)V
/*    */     //   6248: aload #71
/*    */     //   6250: putfield Id0 : Lf/W1;
/*    */     //   6253: ldc_w 'combobox'
/*    */     //   6256: invokevirtual Xu : (Ljava/lang/String;)V
/*    */     //   6259: getstatic f/h1.QJ : I
/*    */     //   6262: dup
/*    */     //   6263: istore #72
/*    */     //   6265: iconst_1
/*    */     //   6266: if_icmpge -> 6278
/*    */     //   6269: aload #71
/*    */     //   6271: iconst_0
/*    */     //   6272: invokevirtual Z30 : (I)V
/*    */     //   6275: goto -> 6322
/*    */     //   6278: iload #72
/*    */     //   6280: iconst_3
/*    */     //   6281: if_icmpgt -> 6293
/*    */     //   6284: aload #71
/*    */     //   6286: iconst_1
/*    */     //   6287: invokevirtual Z30 : (I)V
/*    */     //   6290: goto -> 6322
/*    */     //   6293: iload #72
/*    */     //   6295: bipush #7
/*    */     //   6297: if_icmpgt -> 6309
/*    */     //   6300: aload #71
/*    */     //   6302: iconst_2
/*    */     //   6303: invokevirtual Z30 : (I)V
/*    */     //   6306: goto -> 6322
/*    */     //   6309: iload #72
/*    */     //   6311: bipush #12
/*    */     //   6313: if_icmpgt -> 6322
/*    */     //   6316: aload #71
/*    */     //   6318: iconst_3
/*    */     //   6319: invokevirtual Z30 : (I)V
/*    */     //   6322: aload_0
/*    */     //   6323: dup
/*    */     //   6324: dup
/*    */     //   6325: dup2
/*    */     //   6326: dup2
/*    */     //   6327: aload #47
/*    */     //   6329: aload #63
/*    */     //   6331: aload #70
/*    */     //   6333: dup
/*    */     //   6334: dup
/*    */     //   6335: sipush #1296
/*    */     //   6338: invokestatic OH0 : (I)Ljava/lang/String;
/*    */     //   6341: invokevirtual Gq0 : (Ljava/lang/Object;)V
/*    */     //   6344: bipush #100
/*    */     //   6346: invokevirtual Pb0 : (I)V
/*    */     //   6349: ldc_w 'label-settings-title'
/*    */     //   6352: invokevirtual Xu : (Ljava/lang/String;)V
/*    */     //   6355: new f/at
/*    */     //   6358: dup
/*    */     //   6359: astore #72
/*    */     //   6361: iconst_1
/*    */     //   6362: anewarray f/JG0
/*    */     //   6365: dup
/*    */     //   6366: iconst_0
/*    */     //   6367: aload #71
/*    */     //   6369: aastore
/*    */     //   6370: invokespecial <init> : ([Lf/JG0;)V
/*    */     //   6373: new f/FL
/*    */     //   6376: dup
/*    */     //   6377: astore #71
/*    */     //   6379: aload_0
/*    */     //   6380: aload #71
/*    */     //   6382: dup
/*    */     //   6383: sipush #1292
/*    */     //   6386: invokespecial <init> : (I)V
/*    */     //   6389: putfield zi0 : Lf/FL;
/*    */     //   6392: getstatic f/h1.c00 : Z
/*    */     //   6395: invokevirtual QS : (Z)V
/*    */     //   6398: new f/FL
/*    */     //   6401: dup
/*    */     //   6402: astore #73
/*    */     //   6404: aload_0
/*    */     //   6405: aload #73
/*    */     //   6407: dup
/*    */     //   6408: sipush #1331
/*    */     //   6411: invokespecial <init> : (I)V
/*    */     //   6414: putfield lS : Lf/FL;
/*    */     //   6417: getstatic f/h1.Wo : Z
/*    */     //   6420: invokevirtual QS : (Z)V
/*    */     //   6423: new f/FL
/*    */     //   6426: dup
/*    */     //   6427: astore #74
/*    */     //   6429: aload_0
/*    */     //   6430: aload #74
/*    */     //   6432: dup
/*    */     //   6433: sipush #1266
/*    */     //   6436: invokespecial <init> : (I)V
/*    */     //   6439: putfield JE : Lf/FL;
/*    */     //   6442: getstatic f/h1.IC0 : Z
/*    */     //   6445: invokevirtual QS : (Z)V
/*    */     //   6448: new f/FL
/*    */     //   6451: dup
/*    */     //   6452: dup
/*    */     //   6453: astore #75
/*    */     //   6455: aload_0
/*    */     //   6456: aload #75
/*    */     //   6458: dup
/*    */     //   6459: sipush #1245
/*    */     //   6462: invokespecial <init> : (I)V
/*    */     //   6465: putfield cz : Lf/FL;
/*    */     //   6468: getstatic f/h1.ho : Z
/*    */     //   6471: invokevirtual QS : (Z)V
/*    */     //   6474: sipush #1246
/*    */     //   6477: invokestatic OH0 : (I)Ljava/lang/String;
/*    */     //   6480: invokevirtual yp0 : (Ljava/lang/String;)V
/*    */     //   6483: new f/FL
/*    */     //   6486: dup
/*    */     //   6487: astore #76
/*    */     //   6489: aload_0
/*    */     //   6490: aload #76
/*    */     //   6492: dup
/*    */     //   6493: sipush #1236
/*    */     //   6496: invokespecial <init> : (I)V
/*    */     //   6499: putfield pD : Lf/FL;
/*    */     //   6502: getstatic f/h1.VV : Z
/*    */     //   6505: invokevirtual QS : (Z)V
/*    */     //   6508: new f/at
/*    */     //   6511: dup
/*    */     //   6512: astore #77
/*    */     //   6514: iconst_1
/*    */     //   6515: anewarray f/JG0
/*    */     //   6518: dup
/*    */     //   6519: aload_0
/*    */     //   6520: getfield Mb : Lf/rI0;
/*    */     //   6523: iconst_0
/*    */     //   6524: swap
/*    */     //   6525: aastore
/*    */     //   6526: invokespecial <init> : ([Lf/JG0;)V
/*    */     //   6529: ldc_w 'label-settings-title'
/*    */     //   6532: invokevirtual Xu : (Ljava/lang/String;)V
/*    */     //   6535: ldc_w 'label-settings-vai'
/*    */     //   6538: invokevirtual Xu : (Ljava/lang/String;)V
/*    */     //   6541: new f/dQ
/*    */     //   6544: dup
/*    */     //   6545: dup2
/*    */     //   6546: astore #78
/*    */     //   6548: invokespecial <init> : ()V
/*    */     //   6551: ldc_w 'label-settings-title'
/*    */     //   6554: invokevirtual Xu : (Ljava/lang/String;)V
/*    */     //   6557: iconst_0
/*    */     //   6558: invokevirtual wI0 : (Z)V
/*    */     //   6561: new f/dQ
/*    */     //   6564: dup
/*    */     //   6565: dup
/*    */     //   6566: astore #79
/*    */     //   6568: sipush #1360
/*    */     //   6571: invokestatic OH0 : (I)Ljava/lang/String;
/*    */     //   6574: invokespecial <init> : (Ljava/lang/String;)V
/*    */     //   6577: ldc_w 'label-settings-title-small'
/*    */     //   6580: invokevirtual Xu : (Ljava/lang/String;)V
/*    */     //   6583: new f/dQ
/*    */     //   6586: dup
/*    */     //   6587: dup
/*    */     //   6588: astore #80
/*    */     //   6590: sipush #1361
/*    */     //   6593: invokestatic OH0 : (I)Ljava/lang/String;
/*    */     //   6596: invokespecial <init> : (Ljava/lang/String;)V
/*    */     //   6599: ldc_w 'label-settings-title-small'
/*    */     //   6602: invokevirtual Xu : (Ljava/lang/String;)V
/*    */     //   6605: new f/dQ
/*    */     //   6608: dup
/*    */     //   6609: dup
/*    */     //   6610: astore #81
/*    */     //   6612: sipush #1362
/*    */     //   6615: invokestatic OH0 : (I)Ljava/lang/String;
/*    */     //   6618: invokespecial <init> : (Ljava/lang/String;)V
/*    */     //   6621: ldc_w 'label-settings-title-small'
/*    */     //   6624: invokevirtual Xu : (Ljava/lang/String;)V
/*    */     //   6627: new f/aM
/*    */     //   6630: dup
/*    */     //   6631: iconst_0
/*    */     //   6632: aload_3
/*    */     //   6633: invokespecial <init> : (BLf/fH0;)V
/*    */     //   6636: putfield lJ : Lf/aM;
/*    */     //   6639: new f/aM
/*    */     //   6642: dup
/*    */     //   6643: iconst_1
/*    */     //   6644: aload_3
/*    */     //   6645: invokespecial <init> : (BLf/fH0;)V
/*    */     //   6648: putfield Ij : Lf/aM;
/*    */     //   6651: new f/aM
/*    */     //   6654: dup
/*    */     //   6655: iconst_2
/*    */     //   6656: aload_3
/*    */     //   6657: invokespecial <init> : (BLf/fH0;)V
/*    */     //   6660: putfield NY : Lf/aM;
/*    */     //   6663: new f/aM
/*    */     //   6666: dup
/*    */     //   6667: iconst_3
/*    */     //   6668: aload_3
/*    */     //   6669: invokespecial <init> : (BLf/fH0;)V
/*    */     //   6672: putfield UH : Lf/aM;
/*    */     //   6675: new f/aM
/*    */     //   6678: dup
/*    */     //   6679: iconst_4
/*    */     //   6680: aload_3
/*    */     //   6681: invokespecial <init> : (BLf/fH0;)V
/*    */     //   6684: putfield aY : Lf/aM;
/*    */     //   6687: new f/aM
/*    */     //   6690: dup
/*    */     //   6691: iconst_5
/*    */     //   6692: aload_3
/*    */     //   6693: invokespecial <init> : (BLf/fH0;)V
/*    */     //   6696: putfield To : Lf/aM;
/*    */     //   6699: new f/cs0
/*    */     //   6702: dup
/*    */     //   6703: astore #82
/*    */     //   6705: sipush #1376
/*    */     //   6708: invokestatic OH0 : (I)Ljava/lang/String;
/*    */     //   6711: sipush #1377
/*    */     //   6714: invokestatic OH0 : (I)Ljava/lang/String;
/*    */     //   6717: new f/I00
/*    */     //   6720: dup
/*    */     //   6721: aload_1
/*    */     //   6722: invokespecial <init> : (Lf/js;)V
/*    */     //   6725: invokespecial <init> : (Ljava/lang/String;Ljava/lang/String;Ljava/lang/Runnable;)V
/*    */     //   6728: new f/cs0
/*    */     //   6731: dup
/*    */     //   6732: astore #83
/*    */     //   6734: sipush #1380
/*    */     //   6737: invokestatic OH0 : (I)Ljava/lang/String;
/*    */     //   6740: sipush #1377
/*    */     //   6743: invokestatic OH0 : (I)Ljava/lang/String;
/*    */     //   6746: new f/ZX
/*    */     //   6749: dup
/*    */     //   6750: invokespecial <init> : ()V
/*    */     //   6753: invokespecial <init> : (Ljava/lang/String;Ljava/lang/String;Ljava/lang/Runnable;)V
/*    */     //   6756: new f/cs0
/*    */     //   6759: dup
/*    */     //   6760: astore #84
/*    */     //   6762: sipush #1382
/*    */     //   6765: invokestatic OH0 : (I)Ljava/lang/String;
/*    */     //   6768: sipush #1377
/*    */     //   6771: invokestatic OH0 : (I)Ljava/lang/String;
/*    */     //   6774: new f/t5
/*    */     //   6777: dup
/*    */     //   6778: aload_1
/*    */     //   6779: invokespecial <init> : (Lf/js;)V
/*    */     //   6782: invokespecial <init> : (Ljava/lang/String;Ljava/lang/String;Ljava/lang/Runnable;)V
/*    */     //   6785: new f/cs0
/*    */     //   6788: dup
/*    */     //   6789: astore_1
/*    */     //   6790: sipush #1374
/*    */     //   6793: invokestatic OH0 : (I)Ljava/lang/String;
/*    */     //   6796: sipush #1377
/*    */     //   6799: invokestatic OH0 : (I)Ljava/lang/String;
/*    */     //   6802: <illegal opcode> run : ()Ljava/lang/Runnable;
/*    */     //   6807: invokespecial <init> : (Ljava/lang/String;Ljava/lang/String;Ljava/lang/Runnable;)V
/*    */     //   6810: new f/FL
/*    */     //   6813: dup
/*    */     //   6814: aload_0
/*    */     //   6815: swap
/*    */     //   6816: dup
/*    */     //   6817: sipush #1219
/*    */     //   6820: invokestatic OH0 : (I)Ljava/lang/String;
/*    */     //   6823: invokespecial <init> : (Ljava/lang/String;)V
/*    */     //   6826: putfield UI : Lf/FL;
/*    */     //   6829: getstatic f/h1.FJ : Z
/*    */     //   6832: invokevirtual QS : (Z)V
/*    */     //   6835: new f/Lx0
/*    */     //   6838: dup
/*    */     //   6839: dup
/*    */     //   6840: astore #85
/*    */     //   6842: invokespecial <init> : ()V
/*    */     //   6845: putfield ux : Lf/Lx0;
/*    */     //   6848: invokestatic ER : ()Z
/*    */     //   6851: ifne -> 6940
/*    */     //   6854: invokestatic lK : ()Lf/yG;
/*    */     //   6857: getstatic f/yG.A1 : Lf/yG;
/*    */     //   6860: if_acmpeq -> 6886
/*    */     //   6863: aload #85
/*    */     //   6865: iconst_2
/*    */     //   6866: anewarray f/JG0
/*    */     //   6869: dup
/*    */     //   6870: dup
/*    */     //   6871: astore #86
/*    */     //   6873: iconst_0
/*    */     //   6874: aload #5
/*    */     //   6876: aastore
/*    */     //   6877: iconst_1
/*    */     //   6878: aload #8
/*    */     //   6880: aastore
/*    */     //   6881: aload #86
/*    */     //   6883: invokevirtual hf0 : ([Lf/JG0;)V
/*    */     //   6886: aload_0
/*    */     //   6887: aload #85
/*    */     //   6889: aload_0
/*    */     //   6890: aload #85
/*    */     //   6892: iconst_2
/*    */     //   6893: anewarray f/JG0
/*    */     //   6896: dup
/*    */     //   6897: dup
/*    */     //   6898: iconst_0
/*    */     //   6899: aload #7
/*    */     //   6901: aastore
/*    */     //   6902: iconst_1
/*    */     //   6903: aload #9
/*    */     //   6905: aastore
/*    */     //   6906: invokevirtual hf0 : ([Lf/JG0;)V
/*    */     //   6909: getfield Zg0 : Lf/FL;
/*    */     //   6912: invokevirtual wY : ()[Lf/JG0;
/*    */     //   6915: invokevirtual hf0 : ([Lf/JG0;)V
/*    */     //   6918: getfield Zx : Lf/FL;
/*    */     //   6921: dup
/*    */     //   6922: astore #5
/*    */     //   6924: ifnull -> 6978
/*    */     //   6927: aload #85
/*    */     //   6929: aload #5
/*    */     //   6931: invokevirtual wY : ()[Lf/JG0;
/*    */     //   6934: invokevirtual hf0 : ([Lf/JG0;)V
/*    */     //   6937: goto -> 6978
/*    */     //   6940: invokestatic zp : ()Z
/*    */     //   6943: ifeq -> 6966
/*    */     //   6946: aload_0
/*    */     //   6947: getfield I80 : Lf/FL;
/*    */     //   6950: dup
/*    */     //   6951: astore #5
/*    */     //   6953: ifnull -> 6966
/*    */     //   6956: aload #85
/*    */     //   6958: aload #5
/*    */     //   6960: invokevirtual wY : ()[Lf/JG0;
/*    */     //   6963: invokevirtual hf0 : ([Lf/JG0;)V
/*    */     //   6966: aload #85
/*    */     //   6968: aload_0
/*    */     //   6969: getfield R : Lf/FL;
/*    */     //   6972: invokevirtual wY : ()[Lf/JG0;
/*    */     //   6975: invokevirtual hf0 : ([Lf/JG0;)V
/*    */     //   6978: getstatic f/km.iE0 : Lf/r9;
/*    */     //   6981: invokevirtual Nb0 : ()Z
/*    */     //   6984: ifeq -> 7010
/*    */     //   6987: aload #85
/*    */     //   6989: iconst_2
/*    */     //   6990: anewarray f/JG0
/*    */     //   6993: dup
/*    */     //   6994: dup
/*    */     //   6995: astore #5
/*    */     //   6997: iconst_0
/*    */     //   6998: aload #4
/*    */     //   7000: aastore
/*    */     //   7001: iconst_1
/*    */     //   7002: aload #6
/*    */     //   7004: aastore
/*    */     //   7005: aload #5
/*    */     //   7007: invokevirtual hf0 : ([Lf/JG0;)V
/*    */     //   7010: aload #85
/*    */     //   7012: dup
/*    */     //   7013: dup
/*    */     //   7014: aload_0
/*    */     //   7015: aload #85
/*    */     //   7017: dup
/*    */     //   7018: iconst_2
/*    */     //   7019: anewarray f/JG0
/*    */     //   7022: dup
/*    */     //   7023: dup
/*    */     //   7024: iconst_0
/*    */     //   7025: aload #13
/*    */     //   7027: aastore
/*    */     //   7028: iconst_1
/*    */     //   7029: aload #18
/*    */     //   7031: aastore
/*    */     //   7032: invokevirtual hf0 : ([Lf/JG0;)V
/*    */     //   7035: iconst_2
/*    */     //   7036: anewarray f/JG0
/*    */     //   7039: dup
/*    */     //   7040: dup
/*    */     //   7041: iconst_0
/*    */     //   7042: aload #23
/*    */     //   7044: aastore
/*    */     //   7045: iconst_1
/*    */     //   7046: aload #25
/*    */     //   7048: aastore
/*    */     //   7049: invokevirtual hf0 : ([Lf/JG0;)V
/*    */     //   7052: getfield FB : Lf/FL;
/*    */     //   7055: invokevirtual wY : ()[Lf/JG0;
/*    */     //   7058: invokevirtual hf0 : ([Lf/JG0;)V
/*    */     //   7061: iconst_2
/*    */     //   7062: anewarray f/JG0
/*    */     //   7065: dup
/*    */     //   7066: dup
/*    */     //   7067: iconst_0
/*    */     //   7068: aload #19
/*    */     //   7070: aastore
/*    */     //   7071: iconst_1
/*    */     //   7072: aload #22
/*    */     //   7074: aastore
/*    */     //   7075: invokevirtual hf0 : ([Lf/JG0;)V
/*    */     //   7078: iconst_2
/*    */     //   7079: anewarray f/JG0
/*    */     //   7082: dup
/*    */     //   7083: dup
/*    */     //   7084: iconst_0
/*    */     //   7085: aload #21
/*    */     //   7087: aastore
/*    */     //   7088: iconst_1
/*    */     //   7089: aload #24
/*    */     //   7091: aastore
/*    */     //   7092: invokevirtual hf0 : ([Lf/JG0;)V
/*    */     //   7095: invokestatic XU : ()Z
/*    */     //   7098: ifne -> 7125
/*    */     //   7101: aload #85
/*    */     //   7103: aload_0
/*    */     //   7104: aload #85
/*    */     //   7106: aload_0
/*    */     //   7107: getfield l80 : Lf/FL;
/*    */     //   7110: invokevirtual wY : ()[Lf/JG0;
/*    */     //   7113: invokevirtual hf0 : ([Lf/JG0;)V
/*    */     //   7116: getfield pw : Lf/FL;
/*    */     //   7119: invokevirtual wY : ()[Lf/JG0;
/*    */     //   7122: invokevirtual hf0 : ([Lf/JG0;)V
/*    */     //   7125: aload #85
/*    */     //   7127: aload_0
/*    */     //   7128: aload #85
/*    */     //   7130: dup
/*    */     //   7131: dup
/*    */     //   7132: aload_0
/*    */     //   7133: aload #85
/*    */     //   7135: iconst_2
/*    */     //   7136: anewarray f/JG0
/*    */     //   7139: dup
/*    */     //   7140: dup
/*    */     //   7141: iconst_0
/*    */     //   7142: aload #10
/*    */     //   7144: aastore
/*    */     //   7145: new f/at
/*    */     //   7148: dup
/*    */     //   7149: astore #4
/*    */     //   7151: iconst_1
/*    */     //   7152: anewarray f/JG0
/*    */     //   7155: dup
/*    */     //   7156: aload_0
/*    */     //   7157: getfield Rp : Lf/W1;
/*    */     //   7160: iconst_0
/*    */     //   7161: swap
/*    */     //   7162: aastore
/*    */     //   7163: invokespecial <init> : ([Lf/JG0;)V
/*    */     //   7166: iconst_1
/*    */     //   7167: aload #4
/*    */     //   7169: aastore
/*    */     //   7170: invokevirtual hf0 : ([Lf/JG0;)V
/*    */     //   7173: getfield so0 : Lf/FL;
/*    */     //   7176: invokevirtual wY : ()[Lf/JG0;
/*    */     //   7179: invokevirtual hf0 : ([Lf/JG0;)V
/*    */     //   7182: iconst_2
/*    */     //   7183: anewarray f/JG0
/*    */     //   7186: dup
/*    */     //   7187: dup
/*    */     //   7188: iconst_0
/*    */     //   7189: aload #26
/*    */     //   7191: aastore
/*    */     //   7192: iconst_1
/*    */     //   7193: aload #28
/*    */     //   7195: aastore
/*    */     //   7196: invokevirtual hf0 : ([Lf/JG0;)V
/*    */     //   7199: iconst_2
/*    */     //   7200: anewarray f/JG0
/*    */     //   7203: dup
/*    */     //   7204: dup
/*    */     //   7205: iconst_0
/*    */     //   7206: aload #27
/*    */     //   7208: aastore
/*    */     //   7209: iconst_1
/*    */     //   7210: aload #30
/*    */     //   7212: aastore
/*    */     //   7213: invokevirtual hf0 : ([Lf/JG0;)V
/*    */     //   7216: getfield U3 : Lf/FL;
/*    */     //   7219: invokevirtual wY : ()[Lf/JG0;
/*    */     //   7222: invokevirtual hf0 : ([Lf/JG0;)V
/*    */     //   7225: new f/Lx0
/*    */     //   7228: dup
/*    */     //   7229: dup2
/*    */     //   7230: astore #4
/*    */     //   7232: aload_0
/*    */     //   7233: aload #4
/*    */     //   7235: dup
/*    */     //   7236: invokespecial <init> : ()V
/*    */     //   7239: putfield H7 : Lf/Lx0;
/*    */     //   7242: iconst_2
/*    */     //   7243: anewarray f/JG0
/*    */     //   7246: dup
/*    */     //   7247: dup
/*    */     //   7248: iconst_0
/*    */     //   7249: aload #31
/*    */     //   7251: aastore
/*    */     //   7252: iconst_1
/*    */     //   7253: aload #39
/*    */     //   7255: aastore
/*    */     //   7256: invokevirtual hf0 : ([Lf/JG0;)V
/*    */     //   7259: iconst_2
/*    */     //   7260: anewarray f/JG0
/*    */     //   7263: dup
/*    */     //   7264: dup
/*    */     //   7265: iconst_0
/*    */     //   7266: aload #33
/*    */     //   7268: aastore
/*    */     //   7269: iconst_1
/*    */     //   7270: aload #32
/*    */     //   7272: aastore
/*    */     //   7273: invokevirtual hf0 : ([Lf/JG0;)V
/*    */     //   7276: iconst_2
/*    */     //   7277: anewarray f/JG0
/*    */     //   7280: dup
/*    */     //   7281: dup
/*    */     //   7282: iconst_0
/*    */     //   7283: aload #34
/*    */     //   7285: aastore
/*    */     //   7286: iconst_1
/*    */     //   7287: aload #35
/*    */     //   7289: aastore
/*    */     //   7290: invokevirtual hf0 : ([Lf/JG0;)V
/*    */     //   7293: invokestatic XU : ()Z
/*    */     //   7296: ifne -> 7322
/*    */     //   7299: aload #4
/*    */     //   7301: iconst_2
/*    */     //   7302: anewarray f/JG0
/*    */     //   7305: dup
/*    */     //   7306: dup
/*    */     //   7307: astore #5
/*    */     //   7309: iconst_0
/*    */     //   7310: aload #37
/*    */     //   7312: aastore
/*    */     //   7313: iconst_1
/*    */     //   7314: aload #38
/*    */     //   7316: aastore
/*    */     //   7317: aload #5
/*    */     //   7319: invokevirtual hf0 : ([Lf/JG0;)V
/*    */     //   7322: aload_0
/*    */     //   7323: aload #4
/*    */     //   7325: aload_0
/*    */     //   7326: aload #4
/*    */     //   7328: dup
/*    */     //   7329: aload_0
/*    */     //   7330: getfield rQ : Lf/FL;
/*    */     //   7333: invokevirtual wY : ()[Lf/JG0;
/*    */     //   7336: invokevirtual hf0 : ([Lf/JG0;)V
/*    */     //   7339: iconst_2
/*    */     //   7340: anewarray f/JG0
/*    */     //   7343: dup
/*    */     //   7344: dup
/*    */     //   7345: iconst_0
/*    */     //   7346: aload #36
/*    */     //   7348: aastore
/*    */     //   7349: iconst_1
/*    */     //   7350: aload #41
/*    */     //   7352: aastore
/*    */     //   7353: invokevirtual hf0 : ([Lf/JG0;)V
/*    */     //   7356: getfield og0 : Lf/FL;
/*    */     //   7359: invokevirtual wY : ()[Lf/JG0;
/*    */     //   7362: invokevirtual hf0 : ([Lf/JG0;)V
/*    */     //   7365: new f/Lx0
/*    */     //   7368: dup
/*    */     //   7369: dup
/*    */     //   7370: astore #4
/*    */     //   7372: invokespecial <init> : ()V
/*    */     //   7375: putfield F70 : Lf/Lx0;
/*    */     //   7378: invokestatic zp : ()Z
/*    */     //   7381: ifne -> 7449
/*    */     //   7384: aload #4
/*    */     //   7386: aload #74
/*    */     //   7388: aload #4
/*    */     //   7390: dup
/*    */     //   7391: dup
/*    */     //   7392: iconst_2
/*    */     //   7393: anewarray f/JG0
/*    */     //   7396: dup
/*    */     //   7397: dup
/*    */     //   7398: iconst_0
/*    */     //   7399: aload #61
/*    */     //   7401: aastore
/*    */     //   7402: iconst_1
/*    */     //   7403: aload #62
/*    */     //   7405: aastore
/*    */     //   7406: invokevirtual hf0 : ([Lf/JG0;)V
/*    */     //   7409: iconst_2
/*    */     //   7410: anewarray f/JG0
/*    */     //   7413: dup
/*    */     //   7414: dup
/*    */     //   7415: iconst_0
/*    */     //   7416: aload #63
/*    */     //   7418: aastore
/*    */     //   7419: iconst_1
/*    */     //   7420: aload #77
/*    */     //   7422: aastore
/*    */     //   7423: invokevirtual hf0 : ([Lf/JG0;)V
/*    */     //   7426: iconst_2
/*    */     //   7427: anewarray f/JG0
/*    */     //   7430: dup
/*    */     //   7431: dup
/*    */     //   7432: iconst_0
/*    */     //   7433: aload #17
/*    */     //   7435: aastore
/*    */     //   7436: iconst_1
/*    */     //   7437: aload #20
/*    */     //   7439: aastore
/*    */     //   7440: invokevirtual hf0 : ([Lf/JG0;)V
/*    */     //   7443: invokevirtual wY : ()[Lf/JG0;
/*    */     //   7446: invokevirtual hf0 : ([Lf/JG0;)V
/*    */     //   7449: aload #4
/*    */     //   7451: aload #75
/*    */     //   7453: invokevirtual wY : ()[Lf/JG0;
/*    */     //   7456: invokevirtual hf0 : ([Lf/JG0;)V
/*    */     //   7459: getstatic f/t90.md0 : Ljava/lang/String;
/*    */     //   7462: ifnull -> 7475
/*    */     //   7465: aload #4
/*    */     //   7467: aload #76
/*    */     //   7469: invokevirtual wY : ()[Lf/JG0;
/*    */     //   7472: invokevirtual hf0 : ([Lf/JG0;)V
/*    */     //   7475: invokestatic XU : ()Z
/*    */     //   7478: ifne -> 7493
/*    */     //   7481: aload #4
/*    */     //   7483: aload_0
/*    */     //   7484: getfield Wr : Lf/FL;
/*    */     //   7487: invokevirtual wY : ()[Lf/JG0;
/*    */     //   7490: invokevirtual hf0 : ([Lf/JG0;)V
/*    */     //   7493: aload #4
/*    */     //   7495: aload_0
/*    */     //   7496: aload #4
/*    */     //   7498: aload_0
/*    */     //   7499: getfield a0 : Lf/FL;
/*    */     //   7502: invokevirtual wY : ()[Lf/JG0;
/*    */     //   7505: invokevirtual hf0 : ([Lf/JG0;)V
/*    */     //   7508: getfield ab0 : Lf/FL;
/*    */     //   7511: invokevirtual wY : ()[Lf/JG0;
/*    */     //   7514: invokevirtual hf0 : ([Lf/JG0;)V
/*    */     //   7517: invokestatic XU : ()Z
/*    */     //   7520: ifeq -> 7626
/*    */     //   7523: aload #4
/*    */     //   7525: aload #73
/*    */     //   7527: aload #4
/*    */     //   7529: aload #71
/*    */     //   7531: aload #4
/*    */     //   7533: dup
/*    */     //   7534: dup
/*    */     //   7535: dup2
/*    */     //   7536: aload_0
/*    */     //   7537: getfield J6 : Lf/FL;
/*    */     //   7540: invokevirtual wY : ()[Lf/JG0;
/*    */     //   7543: invokevirtual hf0 : ([Lf/JG0;)V
/*    */     //   7546: iconst_2
/*    */     //   7547: anewarray f/JG0
/*    */     //   7550: dup
/*    */     //   7551: dup
/*    */     //   7552: iconst_0
/*    */     //   7553: aload #64
/*    */     //   7555: aastore
/*    */     //   7556: iconst_1
/*    */     //   7557: aload #65
/*    */     //   7559: aastore
/*    */     //   7560: invokevirtual hf0 : ([Lf/JG0;)V
/*    */     //   7563: iconst_2
/*    */     //   7564: anewarray f/JG0
/*    */     //   7567: dup
/*    */     //   7568: dup
/*    */     //   7569: iconst_0
/*    */     //   7570: aload #68
/*    */     //   7572: aastore
/*    */     //   7573: iconst_1
/*    */     //   7574: aload #69
/*    */     //   7576: aastore
/*    */     //   7577: invokevirtual hf0 : ([Lf/JG0;)V
/*    */     //   7580: iconst_2
/*    */     //   7581: anewarray f/JG0
/*    */     //   7584: dup
/*    */     //   7585: dup
/*    */     //   7586: iconst_0
/*    */     //   7587: aload #70
/*    */     //   7589: aastore
/*    */     //   7590: iconst_1
/*    */     //   7591: aload #72
/*    */     //   7593: aastore
/*    */     //   7594: invokevirtual hf0 : ([Lf/JG0;)V
/*    */     //   7597: iconst_2
/*    */     //   7598: anewarray f/JG0
/*    */     //   7601: dup
/*    */     //   7602: dup
/*    */     //   7603: iconst_0
/*    */     //   7604: aload #66
/*    */     //   7606: aastore
/*    */     //   7607: iconst_1
/*    */     //   7608: aload #67
/*    */     //   7610: aastore
/*    */     //   7611: invokevirtual hf0 : ([Lf/JG0;)V
/*    */     //   7614: invokevirtual wY : ()[Lf/JG0;
/*    */     //   7617: invokevirtual hf0 : ([Lf/JG0;)V
/*    */     //   7620: invokevirtual wY : ()[Lf/JG0;
/*    */     //   7623: invokevirtual hf0 : ([Lf/JG0;)V
/*    */     //   7626: aload #4
/*    */     //   7628: dup
/*    */     //   7629: iconst_2
/*    */     //   7630: anewarray f/JG0
/*    */     //   7633: dup
/*    */     //   7634: dup
/*    */     //   7635: iconst_0
/*    */     //   7636: aload #12
/*    */     //   7638: aastore
/*    */     //   7639: iconst_1
/*    */     //   7640: aload #14
/*    */     //   7642: aastore
/*    */     //   7643: invokevirtual hf0 : ([Lf/JG0;)V
/*    */     //   7646: iconst_2
/*    */     //   7647: anewarray f/JG0
/*    */     //   7650: dup
/*    */     //   7651: dup
/*    */     //   7652: iconst_0
/*    */     //   7653: aload #15
/*    */     //   7655: aastore
/*    */     //   7656: iconst_1
/*    */     //   7657: aload #16
/*    */     //   7659: aastore
/*    */     //   7660: invokevirtual hf0 : ([Lf/JG0;)V
/*    */     //   7663: new f/Lx0
/*    */     //   7666: dup
/*    */     //   7667: dup2
/*    */     //   7668: astore #4
/*    */     //   7670: aload_0
/*    */     //   7671: aload #4
/*    */     //   7673: aload_0
/*    */     //   7674: aload #4
/*    */     //   7676: aload_0
/*    */     //   7677: aload #4
/*    */     //   7679: aload_0
/*    */     //   7680: aload #4
/*    */     //   7682: aload_0
/*    */     //   7683: aload #4
/*    */     //   7685: aload_0
/*    */     //   7686: aload #4
/*    */     //   7688: aload_0
/*    */     //   7689: aload #4
/*    */     //   7691: dup
/*    */     //   7692: aload_0
/*    */     //   7693: aload #4
/*    */     //   7695: dup
/*    */     //   7696: invokespecial <init> : ()V
/*    */     //   7699: putfield Xt : Lf/Lx0;
/*    */     //   7702: ldc_w 'settings-label-area'
/*    */     //   7705: invokevirtual Xu : (Ljava/lang/String;)V
/*    */     //   7708: iconst_2
/*    */     //   7709: anewarray f/JG0
/*    */     //   7712: dup
/*    */     //   7713: dup
/*    */     //   7714: iconst_0
/*    */     //   7715: aload #45
/*    */     //   7717: aastore
/*    */     //   7718: iconst_1
/*    */     //   7719: aload #47
/*    */     //   7721: aastore
/*    */     //   7722: invokevirtual hf0 : ([Lf/JG0;)V
/*    */     //   7725: getfield ii0 : Lf/FL;
/*    */     //   7728: invokevirtual wY : ()[Lf/JG0;
/*    */     //   7731: invokevirtual hf0 : ([Lf/JG0;)V
/*    */     //   7734: getfield Kj : Lf/FL;
/*    */     //   7737: invokevirtual wY : ()[Lf/JG0;
/*    */     //   7740: invokevirtual hf0 : ([Lf/JG0;)V
/*    */     //   7743: getfield Le0 : Lf/FL;
/*    */     //   7746: invokevirtual wY : ()[Lf/JG0;
/*    */     //   7749: invokevirtual hf0 : ([Lf/JG0;)V
/*    */     //   7752: getfield u30 : Lf/FL;
/*    */     //   7755: invokevirtual wY : ()[Lf/JG0;
/*    */     //   7758: invokevirtual hf0 : ([Lf/JG0;)V
/*    */     //   7761: getfield He : Lf/FL;
/*    */     //   7764: invokevirtual wY : ()[Lf/JG0;
/*    */     //   7767: invokevirtual hf0 : ([Lf/JG0;)V
/*    */     //   7770: getfield K30 : Lf/FL;
/*    */     //   7773: invokevirtual wY : ()[Lf/JG0;
/*    */     //   7776: invokevirtual hf0 : ([Lf/JG0;)V
/*    */     //   7779: getfield Eh : Lf/FL;
/*    */     //   7782: invokevirtual wY : ()[Lf/JG0;
/*    */     //   7785: invokevirtual hf0 : ([Lf/JG0;)V
/*    */     //   7788: iconst_2
/*    */     //   7789: anewarray f/JG0
/*    */     //   7792: dup
/*    */     //   7793: dup
/*    */     //   7794: iconst_0
/*    */     //   7795: aload #11
/*    */     //   7797: aastore
/*    */     //   7798: iconst_1
/*    */     //   7799: aload #56
/*    */     //   7801: aastore
/*    */     //   7802: invokevirtual hf0 : ([Lf/JG0;)V
/*    */     //   7805: iconst_2
/*    */     //   7806: anewarray f/JG0
/*    */     //   7809: dup
/*    */     //   7810: dup
/*    */     //   7811: iconst_0
/*    */     //   7812: aload #46
/*    */     //   7814: aastore
/*    */     //   7815: iconst_1
/*    */     //   7816: aload #60
/*    */     //   7818: aastore
/*    */     //   7819: invokevirtual hf0 : ([Lf/JG0;)V
/*    */     //   7822: new f/Lx0
/*    */     //   7825: dup
/*    */     //   7826: dup
/*    */     //   7827: astore #4
/*    */     //   7829: aload_0
/*    */     //   7830: dup
/*    */     //   7831: aload #4
/*    */     //   7833: dup
/*    */     //   7834: invokespecial <init> : ()V
/*    */     //   7837: putfield pRN : Lf/Lx0;
/*    */     //   7840: getfield Y60 : Lf/FL;
/*    */     //   7843: invokevirtual wY : ()[Lf/JG0;
/*    */     //   7846: invokevirtual hf0 : ([Lf/JG0;)V
/*    */     //   7849: iconst_1
/*    */     //   7850: anewarray f/JG0
/*    */     //   7853: dup
/*    */     //   7854: iconst_0
/*    */     //   7855: aload #40
/*    */     //   7857: aastore
/*    */     //   7858: invokevirtual hf0 : ([Lf/JG0;)V
/*    */     //   7861: iconst_0
/*    */     //   7862: istore #4
/*    */     //   7864: iload #4
/*    */     //   7866: aload_0
/*    */     //   7867: getfield Ny : [Lf/Gr;
/*    */     //   7870: dup
/*    */     //   7871: astore #5
/*    */     //   7873: arraylength
/*    */     //   7874: if_icmpge -> 7898
/*    */     //   7877: aload_0
/*    */     //   7878: getfield pRN : Lf/Lx0;
/*    */     //   7881: aload #5
/*    */     //   7883: iload #4
/*    */     //   7885: aaload
/*    */     //   7886: invokevirtual lpT6 : ()[Lf/JG0;
/*    */     //   7889: invokevirtual hf0 : ([Lf/JG0;)V
/*    */     //   7892: iinc #4, 1
/*    */     //   7895: goto -> 7864
/*    */     //   7898: new f/Lx0
/*    */     //   7901: dup
/*    */     //   7902: astore #4
/*    */     //   7904: aload_0
/*    */     //   7905: aload #4
/*    */     //   7907: aload_0
/*    */     //   7908: aload #4
/*    */     //   7910: aload_0
/*    */     //   7911: aload #4
/*    */     //   7913: aload_0
/*    */     //   7914: aload #4
/*    */     //   7916: dup
/*    */     //   7917: aload_0
/*    */     //   7918: dup
/*    */     //   7919: aload #4
/*    */     //   7921: dup
/*    */     //   7922: invokespecial <init> : ()V
/*    */     //   7925: putfield Kz0 : Lf/Lx0;
/*    */     //   7928: getfield DC0 : Lf/FL;
/*    */     //   7931: invokevirtual wY : ()[Lf/JG0;
/*    */     //   7934: invokevirtual hf0 : ([Lf/JG0;)V
/*    */     //   7937: iconst_2
/*    */     //   7938: anewarray f/JG0
/*    */     //   7941: dup
/*    */     //   7942: dup
/*    */     //   7943: iconst_0
/*    */     //   7944: aload #54
/*    */     //   7946: aastore
/*    */     //   7947: iconst_1
/*    */     //   7948: aload #59
/*    */     //   7950: aastore
/*    */     //   7951: invokevirtual hf0 : ([Lf/JG0;)V
/*    */     //   7954: getfield Z50 : Lf/FL;
/*    */     //   7957: invokevirtual wY : ()[Lf/JG0;
/*    */     //   7960: invokevirtual hf0 : ([Lf/JG0;)V
/*    */     //   7963: getfield Rs0 : Lf/FL;
/*    */     //   7966: invokevirtual wY : ()[Lf/JG0;
/*    */     //   7969: invokevirtual hf0 : ([Lf/JG0;)V
/*    */     //   7972: getfield V1 : Lf/FL;
/*    */     //   7975: invokevirtual wY : ()[Lf/JG0;
/*    */     //   7978: invokevirtual hf0 : ([Lf/JG0;)V
/*    */     //   7981: getfield wB : Lf/FL;
/*    */     //   7984: invokevirtual wY : ()[Lf/JG0;
/*    */     //   7987: invokevirtual hf0 : ([Lf/JG0;)V
/*    */     //   7990: new f/Ip
/*    */     //   7993: dup
/*    */     //   7994: dup
/*    */     //   7995: astore #4
/*    */     //   7997: aload_0
/*    */     //   7998: aload #4
/*    */     //   8000: dup
/*    */     //   8001: invokespecial <init> : ()V
/*    */     //   8004: putfield T30 : Lf/Ip;
/*    */     //   8007: ldc_w 'settings-label-area'
/*    */     //   8010: invokevirtual Xu : (Ljava/lang/String;)V
/*    */     //   8013: invokevirtual d7 : ()Lf/cr0;
/*    */     //   8016: aload #4
/*    */     //   8018: iconst_2
/*    */     //   8019: anewarray f/JG0
/*    */     //   8022: dup
/*    */     //   8023: dup
/*    */     //   8024: iconst_0
/*    */     //   8025: aload #48
/*    */     //   8027: aastore
/*    */     //   8028: iconst_1
/*    */     //   8029: aload #55
/*    */     //   8031: aastore
/*    */     //   8032: invokevirtual AUX : ([Lf/JG0;)Lf/U90;
/*    */     //   8035: invokevirtual ee0 : (Lf/U90;)Lf/U90;
/*    */     //   8038: astore #5
/*    */     //   8040: getstatic f/km.mI0 : Lf/P1;
/*    */     //   8043: getfield AN : Lf/Wo;
/*    */     //   8046: dup
/*    */     //   8047: astore #6
/*    */     //   8049: ifnull -> 8085
/*    */     //   8052: aload #6
/*    */     //   8054: invokevirtual gw : ()Z
/*    */     //   8057: ifeq -> 8085
/*    */     //   8060: aload #5
/*    */     //   8062: aload #4
/*    */     //   8064: iconst_2
/*    */     //   8065: anewarray f/JG0
/*    */     //   8068: dup
/*    */     //   8069: dup
/*    */     //   8070: iconst_0
/*    */     //   8071: aload #49
/*    */     //   8073: aastore
/*    */     //   8074: iconst_1
/*    */     //   8075: aload #57
/*    */     //   8077: aastore
/*    */     //   8078: invokevirtual AUX : ([Lf/JG0;)Lf/U90;
/*    */     //   8081: invokevirtual ee0 : (Lf/U90;)Lf/U90;
/*    */     //   8084: pop
/*    */     //   8085: aload #4
/*    */     //   8087: aload #5
/*    */     //   8089: aload #4
/*    */     //   8091: iconst_1
/*    */     //   8092: anewarray f/JG0
/*    */     //   8095: dup
/*    */     //   8096: iconst_0
/*    */     //   8097: aload #52
/*    */     //   8099: aastore
/*    */     //   8100: invokevirtual AUX : ([Lf/JG0;)Lf/U90;
/*    */     //   8103: invokevirtual ee0 : (Lf/U90;)Lf/U90;
/*    */     //   8106: aload #4
/*    */     //   8108: iconst_2
/*    */     //   8109: anewarray f/JG0
/*    */     //   8112: dup
/*    */     //   8113: dup
/*    */     //   8114: iconst_0
/*    */     //   8115: aload #50
/*    */     //   8117: aastore
/*    */     //   8118: iconst_1
/*    */     //   8119: aload #58
/*    */     //   8121: aastore
/*    */     //   8122: invokevirtual AUX : ([Lf/JG0;)Lf/U90;
/*    */     //   8125: invokevirtual ee0 : (Lf/U90;)Lf/U90;
/*    */     //   8128: pop
/*    */     //   8129: invokevirtual mE0 : ()Lf/g0;
/*    */     //   8132: aload #4
/*    */     //   8134: iconst_2
/*    */     //   8135: anewarray f/JG0
/*    */     //   8138: dup
/*    */     //   8139: dup
/*    */     //   8140: iconst_0
/*    */     //   8141: aload #48
/*    */     //   8143: aastore
/*    */     //   8144: iconst_1
/*    */     //   8145: aload #55
/*    */     //   8147: aastore
/*    */     //   8148: invokevirtual vo0 : ([Lf/JG0;)Lf/U90;
/*    */     //   8151: invokevirtual ee0 : (Lf/U90;)Lf/U90;
/*    */     //   8154: astore #6
/*    */     //   8156: getstatic f/km.mI0 : Lf/P1;
/*    */     //   8159: getfield AN : Lf/Wo;
/*    */     //   8162: dup
/*    */     //   8163: astore #7
/*    */     //   8165: ifnull -> 8201
/*    */     //   8168: aload #7
/*    */     //   8170: invokevirtual gw : ()Z
/*    */     //   8173: ifeq -> 8201
/*    */     //   8176: aload #6
/*    */     //   8178: aload #4
/*    */     //   8180: iconst_2
/*    */     //   8181: anewarray f/JG0
/*    */     //   8184: dup
/*    */     //   8185: dup
/*    */     //   8186: iconst_0
/*    */     //   8187: aload #49
/*    */     //   8189: aastore
/*    */     //   8190: iconst_1
/*    */     //   8191: aload #57
/*    */     //   8193: aastore
/*    */     //   8194: invokevirtual vo0 : ([Lf/JG0;)Lf/U90;
/*    */     //   8197: invokevirtual ee0 : (Lf/U90;)Lf/U90;
/*    */     //   8200: pop
/*    */     //   8201: aload #6
/*    */     //   8203: aload #4
/*    */     //   8205: invokevirtual d7 : ()Lf/cr0;
/*    */     //   8208: aload #52
/*    */     //   8210: invokevirtual Ya : (Lf/JG0;)Lf/U90;
/*    */     //   8213: invokevirtual ee0 : (Lf/U90;)Lf/U90;
/*    */     //   8216: aload #4
/*    */     //   8218: iconst_2
/*    */     //   8219: anewarray f/JG0
/*    */     //   8222: dup
/*    */     //   8223: dup
/*    */     //   8224: iconst_0
/*    */     //   8225: aload #50
/*    */     //   8227: aastore
/*    */     //   8228: iconst_1
/*    */     //   8229: aload #58
/*    */     //   8231: aastore
/*    */     //   8232: invokevirtual vo0 : ([Lf/JG0;)Lf/U90;
/*    */     //   8235: invokevirtual ee0 : (Lf/U90;)Lf/U90;
/*    */     //   8238: pop
/*    */     //   8239: new f/Ip
/*    */     //   8242: dup
/*    */     //   8243: dup
/*    */     //   8244: dup2
/*    */     //   8245: astore #4
/*    */     //   8247: invokespecial <init> : ()V
/*    */     //   8250: ldc_w 'label-settings-value'
/*    */     //   8253: invokevirtual Xu : (Ljava/lang/String;)V
/*    */     //   8256: invokevirtual d7 : ()Lf/cr0;
/*    */     //   8259: astore #7
/*    */     //   8261: invokevirtual mE0 : ()Lf/g0;
/*    */     //   8264: astore #8
/*    */     //   8266: iconst_0
/*    */     //   8267: istore #9
/*    */     //   8269: iload #9
/*    */     //   8271: aload_0
/*    */     //   8272: getfield II : [Lf/ge0;
/*    */     //   8275: dup
/*    */     //   8276: astore #10
/*    */     //   8278: arraylength
/*    */     //   8279: if_icmpge -> 8364
/*    */     //   8282: aload #8
/*    */     //   8284: aload #4
/*    */     //   8286: aload #7
/*    */     //   8288: aload #4
/*    */     //   8290: iconst_2
/*    */     //   8291: anewarray f/JG0
/*    */     //   8294: dup
/*    */     //   8295: dup
/*    */     //   8296: astore #11
/*    */     //   8298: aload #53
/*    */     //   8300: iload #9
/*    */     //   8302: aload #11
/*    */     //   8304: aload #10
/*    */     //   8306: iload #9
/*    */     //   8308: aaload
/*    */     //   8309: iconst_0
/*    */     //   8310: swap
/*    */     //   8311: aastore
/*    */     //   8312: aaload
/*    */     //   8313: iconst_1
/*    */     //   8314: swap
/*    */     //   8315: aastore
/*    */     //   8316: invokevirtual AUX : ([Lf/JG0;)Lf/U90;
/*    */     //   8319: invokevirtual ee0 : (Lf/U90;)Lf/U90;
/*    */     //   8322: pop
/*    */     //   8323: iconst_2
/*    */     //   8324: anewarray f/JG0
/*    */     //   8327: dup
/*    */     //   8328: dup
/*    */     //   8329: astore #10
/*    */     //   8331: aload #53
/*    */     //   8333: iload #9
/*    */     //   8335: aload #10
/*    */     //   8337: aload_0
/*    */     //   8338: getfield II : [Lf/ge0;
/*    */     //   8341: iload #9
/*    */     //   8343: aaload
/*    */     //   8344: iconst_0
/*    */     //   8345: swap
/*    */     //   8346: aastore
/*    */     //   8347: aaload
/*    */     //   8348: iconst_1
/*    */     //   8349: swap
/*    */     //   8350: aastore
/*    */     //   8351: invokevirtual vo0 : ([Lf/JG0;)Lf/U90;
/*    */     //   8354: invokevirtual ee0 : (Lf/U90;)Lf/U90;
/*    */     //   8357: pop
/*    */     //   8358: iinc #9, 1
/*    */     //   8361: goto -> 8269
/*    */     //   8364: aload_0
/*    */     //   8365: dup
/*    */     //   8366: aload #6
/*    */     //   8368: aload_0
/*    */     //   8369: aload #5
/*    */     //   8371: aload_0
/*    */     //   8372: aload #4
/*    */     //   8374: aload #8
/*    */     //   8376: aload #4
/*    */     //   8378: aload #7
/*    */     //   8380: invokevirtual WN : (Lf/U90;)V
/*    */     //   8383: invokevirtual rK0 : (Lf/U90;)V
/*    */     //   8386: getfield T30 : Lf/Ip;
/*    */     //   8389: iconst_2
/*    */     //   8390: anewarray f/JG0
/*    */     //   8393: dup
/*    */     //   8394: dup
/*    */     //   8395: iconst_0
/*    */     //   8396: aload #51
/*    */     //   8398: aastore
/*    */     //   8399: iconst_1
/*    */     //   8400: aload #4
/*    */     //   8402: aastore
/*    */     //   8403: invokevirtual AUX : ([Lf/JG0;)Lf/U90;
/*    */     //   8406: invokevirtual ee0 : (Lf/U90;)Lf/U90;
/*    */     //   8409: pop
/*    */     //   8410: getfield T30 : Lf/Ip;
/*    */     //   8413: iconst_2
/*    */     //   8414: anewarray f/JG0
/*    */     //   8417: dup
/*    */     //   8418: dup
/*    */     //   8419: iconst_0
/*    */     //   8420: aload #51
/*    */     //   8422: aastore
/*    */     //   8423: iconst_1
/*    */     //   8424: aload #4
/*    */     //   8426: aastore
/*    */     //   8427: invokevirtual vo0 : ([Lf/JG0;)Lf/U90;
/*    */     //   8430: invokevirtual ee0 : (Lf/U90;)Lf/U90;
/*    */     //   8433: pop
/*    */     //   8434: getfield T30 : Lf/Ip;
/*    */     //   8437: aload #5
/*    */     //   8439: invokevirtual WN : (Lf/U90;)V
/*    */     //   8442: getfield T30 : Lf/Ip;
/*    */     //   8445: aload #6
/*    */     //   8447: invokevirtual rK0 : (Lf/U90;)V
/*    */     //   8450: new f/Lx0
/*    */     //   8453: dup
/*    */     //   8454: astore #4
/*    */     //   8456: aload_0
/*    */     //   8457: aload #4
/*    */     //   8459: aload_0
/*    */     //   8460: aload #4
/*    */     //   8462: aload_0
/*    */     //   8463: aload #4
/*    */     //   8465: aload_0
/*    */     //   8466: aload #4
/*    */     //   8468: aload_0
/*    */     //   8469: aload #4
/*    */     //   8471: aload_0
/*    */     //   8472: aload #4
/*    */     //   8474: dup
/*    */     //   8475: invokespecial <init> : ()V
/*    */     //   8478: iconst_4
/*    */     //   8479: anewarray f/JG0
/*    */     //   8482: dup
/*    */     //   8483: dup
/*    */     //   8484: dup2
/*    */     //   8485: iconst_0
/*    */     //   8486: aload #78
/*    */     //   8488: aastore
/*    */     //   8489: iconst_1
/*    */     //   8490: aload #79
/*    */     //   8492: aastore
/*    */     //   8493: iconst_2
/*    */     //   8494: aload #80
/*    */     //   8496: aastore
/*    */     //   8497: iconst_3
/*    */     //   8498: aload #81
/*    */     //   8500: aastore
/*    */     //   8501: invokevirtual hf0 : ([Lf/JG0;)V
/*    */     //   8504: getfield lJ : Lf/aM;
/*    */     //   8507: invokevirtual sK0 : ()[Lf/JG0;
/*    */     //   8510: invokevirtual hf0 : ([Lf/JG0;)V
/*    */     //   8513: getfield Ij : Lf/aM;
/*    */     //   8516: invokevirtual sK0 : ()[Lf/JG0;
/*    */     //   8519: invokevirtual hf0 : ([Lf/JG0;)V
/*    */     //   8522: getfield NY : Lf/aM;
/*    */     //   8525: invokevirtual sK0 : ()[Lf/JG0;
/*    */     //   8528: invokevirtual hf0 : ([Lf/JG0;)V
/*    */     //   8531: getfield UH : Lf/aM;
/*    */     //   8534: invokevirtual sK0 : ()[Lf/JG0;
/*    */     //   8537: invokevirtual hf0 : ([Lf/JG0;)V
/*    */     //   8540: getfield aY : Lf/aM;
/*    */     //   8543: invokevirtual sK0 : ()[Lf/JG0;
/*    */     //   8546: invokevirtual hf0 : ([Lf/JG0;)V
/*    */     //   8549: getfield To : Lf/aM;
/*    */     //   8552: invokevirtual sK0 : ()[Lf/JG0;
/*    */     //   8555: invokevirtual hf0 : ([Lf/JG0;)V
/*    */     //   8558: new f/Lx0
/*    */     //   8561: dup
/*    */     //   8562: astore #5
/*    */     //   8564: invokespecial <init> : ()V
/*    */     //   8567: invokestatic zp : ()Z
/*    */     //   8570: ifne -> 8603
/*    */     //   8573: aload #5
/*    */     //   8575: aload #83
/*    */     //   8577: aload #5
/*    */     //   8579: aload #84
/*    */     //   8581: aload #5
/*    */     //   8583: aload #82
/*    */     //   8585: invokevirtual k30 : ()[Lf/JG0;
/*    */     //   8588: invokevirtual hf0 : ([Lf/JG0;)V
/*    */     //   8591: invokevirtual k30 : ()[Lf/JG0;
/*    */     //   8594: invokevirtual hf0 : ([Lf/JG0;)V
/*    */     //   8597: invokevirtual k30 : ()[Lf/JG0;
/*    */     //   8600: invokevirtual hf0 : ([Lf/JG0;)V
/*    */     //   8603: getstatic f/km.a3 : Lf/vh0;
/*    */     //   8606: dup
/*    */     //   8607: astore #6
/*    */     //   8609: ifnull -> 8629
/*    */     //   8612: aload #6
/*    */     //   8614: invokevirtual wQ : ()Lf/Jo;
/*    */     //   8617: ifnull -> 8629
/*    */     //   8620: aload #5
/*    */     //   8622: aload_1
/*    */     //   8623: invokevirtual k30 : ()[Lf/JG0;
/*    */     //   8626: invokevirtual hf0 : ([Lf/JG0;)V
/*    */     //   8629: aload #5
/*    */     //   8631: aload_0
/*    */     //   8632: getfield UI : Lf/FL;
/*    */     //   8635: invokevirtual wY : ()[Lf/JG0;
/*    */     //   8638: invokevirtual hf0 : ([Lf/JG0;)V
/*    */     //   8641: new f/FL
/*    */     //   8644: dup
/*    */     //   8645: astore_1
/*    */     //   8646: aload_0
/*    */     //   8647: aload_1
/*    */     //   8648: dup
/*    */     //   8649: sipush #1387
/*    */     //   8652: invokespecial <init> : (I)V
/*    */     //   8655: putfield Vx0 : Lf/FL;
/*    */     //   8658: getstatic f/h1.PF0 : Z
/*    */     //   8661: invokevirtual QS : (Z)V
/*    */     //   8664: new f/Lx0
/*    */     //   8667: dup
/*    */     //   8668: astore #6
/*    */     //   8670: aload_1
/*    */     //   8671: aload #6
/*    */     //   8673: invokespecial <init> : ()V
/*    */     //   8676: invokevirtual wY : ()[Lf/JG0;
/*    */     //   8679: invokevirtual hf0 : ([Lf/JG0;)V
/*    */     //   8682: new f/Vq0
/*    */     //   8685: dup
/*    */     //   8686: dup
/*    */     //   8687: dup2
/*    */     //   8688: dup2
/*    */     //   8689: astore_1
/*    */     //   8690: invokespecial <init> : ()V
/*    */     //   8693: new f/rS
/*    */     //   8696: dup
/*    */     //   8697: dup
/*    */     //   8698: aload_0
/*    */     //   8699: getfield ux : Lf/Lx0;
/*    */     //   8702: invokespecial <init> : (Lf/JG0;)V
/*    */     //   8705: ldc_w 'settings-scrollpane'
/*    */     //   8708: invokevirtual Xu : (Ljava/lang/String;)V
/*    */     //   8711: new f/rS
/*    */     //   8714: dup
/*    */     //   8715: dup
/*    */     //   8716: astore #7
/*    */     //   8718: aload_0
/*    */     //   8719: getfield H7 : Lf/Lx0;
/*    */     //   8722: invokespecial <init> : (Lf/JG0;)V
/*    */     //   8725: ldc_w 'settings-scrollpane'
/*    */     //   8728: invokevirtual Xu : (Ljava/lang/String;)V
/*    */     //   8731: new f/rS
/*    */     //   8734: dup
/*    */     //   8735: dup
/*    */     //   8736: astore #8
/*    */     //   8738: aload_0
/*    */     //   8739: getfield Xt : Lf/Lx0;
/*    */     //   8742: invokespecial <init> : (Lf/JG0;)V
/*    */     //   8745: ldc_w 'settings-scrollpane'
/*    */     //   8748: invokevirtual Xu : (Ljava/lang/String;)V
/*    */     //   8751: new f/rS
/*    */     //   8754: dup
/*    */     //   8755: dup
/*    */     //   8756: astore #9
/*    */     //   8758: aload_0
/*    */     //   8759: getfield F70 : Lf/Lx0;
/*    */     //   8762: invokespecial <init> : (Lf/JG0;)V
/*    */     //   8765: ldc_w 'settings-scrollpane'
/*    */     //   8768: invokevirtual Xu : (Ljava/lang/String;)V
/*    */     //   8771: new f/rS
/*    */     //   8774: dup
/*    */     //   8775: dup
/*    */     //   8776: astore #10
/*    */     //   8778: aload_0
/*    */     //   8779: getfield pRN : Lf/Lx0;
/*    */     //   8782: invokespecial <init> : (Lf/JG0;)V
/*    */     //   8785: ldc_w 'settings-scrollpane'
/*    */     //   8788: invokevirtual Xu : (Ljava/lang/String;)V
/*    */     //   8791: new f/rS
/*    */     //   8794: dup
/*    */     //   8795: dup
/*    */     //   8796: astore #11
/*    */     //   8798: aload_0
/*    */     //   8799: getfield T30 : Lf/Ip;
/*    */     //   8802: invokespecial <init> : (Lf/JG0;)V
/*    */     //   8805: ldc_w 'settings-scrollpane'
/*    */     //   8808: invokevirtual Xu : (Ljava/lang/String;)V
/*    */     //   8811: new f/rS
/*    */     //   8814: dup
/*    */     //   8815: dup
/*    */     //   8816: astore #12
/*    */     //   8818: aload_0
/*    */     //   8819: getfield Kz0 : Lf/Lx0;
/*    */     //   8822: invokespecial <init> : (Lf/JG0;)V
/*    */     //   8825: ldc_w 'settings-scrollpane'
/*    */     //   8828: invokevirtual Xu : (Ljava/lang/String;)V
/*    */     //   8831: new f/rS
/*    */     //   8834: dup
/*    */     //   8835: dup
/*    */     //   8836: astore #13
/*    */     //   8838: aload #4
/*    */     //   8840: invokespecial <init> : (Lf/JG0;)V
/*    */     //   8843: ldc_w 'settings-scrollpane'
/*    */     //   8846: invokevirtual Xu : (Ljava/lang/String;)V
/*    */     //   8849: new f/rS
/*    */     //   8852: dup
/*    */     //   8853: dup
/*    */     //   8854: astore #4
/*    */     //   8856: aload #5
/*    */     //   8858: invokespecial <init> : (Lf/JG0;)V
/*    */     //   8861: ldc_w 'settings-scrollpane'
/*    */     //   8864: invokevirtual Xu : (Ljava/lang/String;)V
/*    */     //   8867: new f/rS
/*    */     //   8870: dup
/*    */     //   8871: dup
/*    */     //   8872: astore #5
/*    */     //   8874: aload #6
/*    */     //   8876: invokespecial <init> : (Lf/JG0;)V
/*    */     //   8879: ldc_w 'settings-scrollpane'
/*    */     //   8882: invokevirtual Xu : (Ljava/lang/String;)V
/*    */     //   8885: sipush #1201
/*    */     //   8888: invokestatic OH0 : (I)Ljava/lang/String;
/*    */     //   8891: invokevirtual WS : (Lf/JG0;Ljava/lang/String;)Lf/Li0;
/*    */     //   8894: pop
/*    */     //   8895: aload #7
/*    */     //   8897: sipush #1202
/*    */     //   8900: invokestatic OH0 : (I)Ljava/lang/String;
/*    */     //   8903: invokevirtual WS : (Lf/JG0;Ljava/lang/String;)Lf/Li0;
/*    */     //   8906: pop
/*    */     //   8907: aload #9
/*    */     //   8909: sipush #1210
/*    */     //   8912: invokestatic OH0 : (I)Ljava/lang/String;
/*    */     //   8915: invokevirtual WS : (Lf/JG0;Ljava/lang/String;)Lf/Li0;
/*    */     //   8918: pop
/*    */     //   8919: aload #8
/*    */     //   8921: sipush #1204
/*    */     //   8924: invokestatic OH0 : (I)Ljava/lang/String;
/*    */     //   8927: invokevirtual WS : (Lf/JG0;Ljava/lang/String;)Lf/Li0;
/*    */     //   8930: pop
/*    */     //   8931: aload #10
/*    */     //   8933: sipush #1203
/*    */     //   8936: invokestatic OH0 : (I)Ljava/lang/String;
/*    */     //   8939: invokevirtual WS : (Lf/JG0;Ljava/lang/String;)Lf/Li0;
/*    */     //   8942: pop
/*    */     //   8943: getstatic f/h1.D30 : Z
/*    */     //   8946: ifeq -> 9259
/*    */     //   8949: aload #42
/*    */     //   8951: arraylength
/*    */     //   8952: anewarray f/Ip
/*    */     //   8955: astore #6
/*    */     //   8957: iconst_0
/*    */     //   8958: istore #7
/*    */     //   8960: iload #7
/*    */     //   8962: aload #42
/*    */     //   8964: arraylength
/*    */     //   8965: if_icmpge -> 9259
/*    */     //   8968: aload #42
/*    */     //   8970: iload #7
/*    */     //   8972: aload #6
/*    */     //   8974: iload #7
/*    */     //   8976: aload #6
/*    */     //   8978: iload #7
/*    */     //   8980: new f/Ip
/*    */     //   8983: dup
/*    */     //   8984: astore #8
/*    */     //   8986: aload #6
/*    */     //   8988: iload #7
/*    */     //   8990: aload #8
/*    */     //   8992: invokespecial <init> : ()V
/*    */     //   8995: aload #8
/*    */     //   8997: aastore
/*    */     //   8998: ldc_w 'settings-label-area'
/*    */     //   9001: invokevirtual Xu : (Ljava/lang/String;)V
/*    */     //   9004: aaload
/*    */     //   9005: invokevirtual d7 : ()Lf/cr0;
/*    */     //   9008: astore #8
/*    */     //   9010: aaload
/*    */     //   9011: invokevirtual mE0 : ()Lf/g0;
/*    */     //   9014: astore #9
/*    */     //   9016: aaload
/*    */     //   9017: invokestatic eE : (Lf/ah0;)Lf/rx0;
/*    */     //   9020: dup
/*    */     //   9021: astore #10
/*    */     //   9023: ifnonnull -> 9029
/*    */     //   9026: goto -> 9253
/*    */     //   9029: aload #9
/*    */     //   9031: aload #8
/*    */     //   9033: aload #9
/*    */     //   9035: aload #6
/*    */     //   9037: iload #7
/*    */     //   9039: aload #8
/*    */     //   9041: aload #6
/*    */     //   9043: iload #7
/*    */     //   9045: aaload
/*    */     //   9046: iconst_1
/*    */     //   9047: anewarray f/JG0
/*    */     //   9050: dup
/*    */     //   9051: aload #43
/*    */     //   9053: iload #7
/*    */     //   9055: aaload
/*    */     //   9056: iconst_0
/*    */     //   9057: swap
/*    */     //   9058: aastore
/*    */     //   9059: invokevirtual AUX : ([Lf/JG0;)Lf/U90;
/*    */     //   9062: invokevirtual ee0 : (Lf/U90;)Lf/U90;
/*    */     //   9065: pop
/*    */     //   9066: aaload
/*    */     //   9067: iconst_1
/*    */     //   9068: anewarray f/JG0
/*    */     //   9071: dup
/*    */     //   9072: aload #43
/*    */     //   9074: iload #7
/*    */     //   9076: aaload
/*    */     //   9077: iconst_0
/*    */     //   9078: swap
/*    */     //   9079: aastore
/*    */     //   9080: invokevirtual vo0 : ([Lf/JG0;)Lf/U90;
/*    */     //   9083: invokevirtual ee0 : (Lf/U90;)Lf/U90;
/*    */     //   9086: pop
/*    */     //   9087: new f/Un
/*    */     //   9090: dup
/*    */     //   9091: dup
/*    */     //   9092: astore #14
/*    */     //   9094: aload #10
/*    */     //   9096: aload #44
/*    */     //   9098: aload #14
/*    */     //   9100: sipush #1388
/*    */     //   9103: invokestatic OH0 : (I)Ljava/lang/String;
/*    */     //   9106: invokespecial <init> : (Ljava/lang/String;)V
/*    */     //   9109: iload #7
/*    */     //   9111: <illegal opcode> run : (Lf/rx0;[[Lf/zv;I)Ljava/lang/Runnable;
/*    */     //   9116: invokevirtual tW : (Ljava/lang/Runnable;)V
/*    */     //   9119: invokevirtual Ya : (Lf/JG0;)Lf/U90;
/*    */     //   9122: pop
/*    */     //   9123: aload #14
/*    */     //   9125: invokevirtual Ya : (Lf/JG0;)Lf/U90;
/*    */     //   9128: pop
/*    */     //   9129: iconst_0
/*    */     //   9130: istore #14
/*    */     //   9132: iload #14
/*    */     //   9134: aload #44
/*    */     //   9136: iload #7
/*    */     //   9138: aaload
/*    */     //   9139: dup
/*    */     //   9140: astore #15
/*    */     //   9142: arraylength
/*    */     //   9143: if_icmpge -> 9199
/*    */     //   9146: aload #9
/*    */     //   9148: aload #6
/*    */     //   9150: iload #7
/*    */     //   9152: aload #8
/*    */     //   9154: aload #6
/*    */     //   9156: iload #7
/*    */     //   9158: aaload
/*    */     //   9159: aload #15
/*    */     //   9161: iload #14
/*    */     //   9163: aaload
/*    */     //   9164: invokevirtual LX : ()[Lf/JG0;
/*    */     //   9167: invokevirtual AUX : ([Lf/JG0;)Lf/U90;
/*    */     //   9170: invokevirtual ee0 : (Lf/U90;)Lf/U90;
/*    */     //   9173: pop
/*    */     //   9174: aaload
/*    */     //   9175: aload #44
/*    */     //   9177: iload #7
/*    */     //   9179: aaload
/*    */     //   9180: iload #14
/*    */     //   9182: aaload
/*    */     //   9183: invokevirtual LX : ()[Lf/JG0;
/*    */     //   9186: invokevirtual vo0 : ([Lf/JG0;)Lf/U90;
/*    */     //   9189: invokevirtual ee0 : (Lf/U90;)Lf/U90;
/*    */     //   9192: pop
/*    */     //   9193: iinc #14, 1
/*    */     //   9196: goto -> 9132
/*    */     //   9199: aload_1
/*    */     //   9200: aload #10
/*    */     //   9202: aload #6
/*    */     //   9204: iload #7
/*    */     //   9206: aload #6
/*    */     //   9208: iload #7
/*    */     //   9210: aaload
/*    */     //   9211: aload #8
/*    */     //   9213: invokevirtual WN : (Lf/U90;)V
/*    */     //   9216: aaload
/*    */     //   9217: aload #9
/*    */     //   9219: invokevirtual rK0 : (Lf/U90;)V
/*    */     //   9222: new f/rS
/*    */     //   9225: dup
/*    */     //   9226: dup
/*    */     //   9227: astore #8
/*    */     //   9229: aload #6
/*    */     //   9231: iload #7
/*    */     //   9233: aaload
/*    */     //   9234: invokespecial <init> : (Lf/JG0;)V
/*    */     //   9237: ldc_w 'settings-scrollpane'
/*    */     //   9240: invokevirtual Xu : (Ljava/lang/String;)V
/*    */     //   9243: invokevirtual Ih0 : ()Ljava/lang/String;
/*    */     //   9246: aload #8
/*    */     //   9248: swap
/*    */     //   9249: invokevirtual WS : (Lf/JG0;Ljava/lang/String;)Lf/Li0;
/*    */     //   9252: pop
/*    */     //   9253: iinc #7, 1
/*    */     //   9256: goto -> 8960
/*    */     //   9259: aload_3
/*    */     //   9260: aload_1
/*    */     //   9261: dup
/*    */     //   9262: sipush #1206
/*    */     //   9265: invokestatic OH0 : (I)Ljava/lang/String;
/*    */     //   9268: aload #11
/*    */     //   9270: swap
/*    */     //   9271: invokevirtual WS : (Lf/JG0;Ljava/lang/String;)Lf/Li0;
/*    */     //   9274: astore_3
/*    */     //   9275: sipush #1208
/*    */     //   9278: invokestatic OH0 : (I)Ljava/lang/String;
/*    */     //   9281: aload #12
/*    */     //   9283: swap
/*    */     //   9284: invokevirtual WS : (Lf/JG0;Ljava/lang/String;)Lf/Li0;
/*    */     //   9287: pop
/*    */     //   9288: ifnull -> 9305
/*    */     //   9291: aload_1
/*    */     //   9292: sipush #1205
/*    */     //   9295: invokestatic OH0 : (I)Ljava/lang/String;
/*    */     //   9298: aload #13
/*    */     //   9300: swap
/*    */     //   9301: invokevirtual WS : (Lf/JG0;Ljava/lang/String;)Lf/Li0;
/*    */     //   9304: pop
/*    */     //   9305: aload_1
/*    */     //   9306: aload #4
/*    */     //   9308: sipush #1209
/*    */     //   9311: invokestatic OH0 : (I)Ljava/lang/String;
/*    */     //   9314: invokevirtual WS : (Lf/JG0;Ljava/lang/String;)Lf/Li0;
/*    */     //   9317: pop
/*    */     //   9318: getstatic f/q00.PG : Z
/*    */     //   9321: ifeq -> 9338
/*    */     //   9324: aload_1
/*    */     //   9325: sipush #1211
/*    */     //   9328: invokestatic OH0 : (I)Ljava/lang/String;
/*    */     //   9331: aload #5
/*    */     //   9333: swap
/*    */     //   9334: invokevirtual WS : (Lf/JG0;Ljava/lang/String;)Lf/Li0;
/*    */     //   9337: pop
/*    */     //   9338: iload_2
/*    */     //   9339: ifeq -> 9347
/*    */     //   9342: aload_1
/*    */     //   9343: aload_3
/*    */     //   9344: invokevirtual dA0 : (Lf/Li0;)V
/*    */     //   9347: invokestatic XU : ()Z
/*    */     //   9350: ifne -> 9478
/*    */     //   9353: aload_0
/*    */     //   9354: dup
/*    */     //   9355: getfield oB : Lf/Ip;
/*    */     //   9358: invokevirtual d7 : ()Lf/cr0;
/*    */     //   9361: astore_2
/*    */     //   9362: getfield oB : Lf/Ip;
/*    */     //   9365: invokevirtual mE0 : ()Lf/g0;
/*    */     //   9368: dup
/*    */     //   9369: astore_3
/*    */     //   9370: aload_1
/*    */     //   9371: aload_2
/*    */     //   9372: invokevirtual Em0 : ()Lf/U90;
/*    */     //   9375: aload_1
/*    */     //   9376: invokevirtual Ya : (Lf/JG0;)Lf/U90;
/*    */     //   9379: invokevirtual Em0 : ()Lf/U90;
/*    */     //   9382: pop
/*    */     //   9383: invokevirtual Ya : (Lf/JG0;)Lf/U90;
/*    */     //   9386: pop
/*    */     //   9387: invokestatic XU : ()Z
/*    */     //   9390: ifne -> 9459
/*    */     //   9393: aload_3
/*    */     //   9394: aload_0
/*    */     //   9395: aload_2
/*    */     //   9396: aload_0
/*    */     //   9397: getfield oB : Lf/Ip;
/*    */     //   9400: iconst_2
/*    */     //   9401: anewarray f/JG0
/*    */     //   9404: dup
/*    */     //   9405: dup
/*    */     //   9406: aload_0
/*    */     //   9407: swap
/*    */     //   9408: iconst_0
/*    */     //   9409: aload #29
/*    */     //   9411: aastore
/*    */     //   9412: getfield Ki : Lf/Un;
/*    */     //   9415: iconst_1
/*    */     //   9416: swap
/*    */     //   9417: aastore
/*    */     //   9418: invokevirtual AUX : ([Lf/JG0;)Lf/U90;
/*    */     //   9421: invokevirtual ee0 : (Lf/U90;)Lf/U90;
/*    */     //   9424: pop
/*    */     //   9425: getfield oB : Lf/Ip;
/*    */     //   9428: invokevirtual d7 : ()Lf/cr0;
/*    */     //   9431: invokevirtual Em0 : ()Lf/U90;
/*    */     //   9434: iconst_2
/*    */     //   9435: anewarray f/JG0
/*    */     //   9438: dup
/*    */     //   9439: dup
/*    */     //   9440: aload_0
/*    */     //   9441: swap
/*    */     //   9442: iconst_0
/*    */     //   9443: aload #29
/*    */     //   9445: aastore
/*    */     //   9446: getfield Ki : Lf/Un;
/*    */     //   9449: iconst_1
/*    */     //   9450: swap
/*    */     //   9451: aastore
/*    */     //   9452: invokevirtual Mg : ([Lf/JG0;)Lf/U90;
/*    */     //   9455: invokevirtual ee0 : (Lf/U90;)Lf/U90;
/*    */     //   9458: pop
/*    */     //   9459: aload_0
/*    */     //   9460: dup
/*    */     //   9461: getfield oB : Lf/Ip;
/*    */     //   9464: aload_2
/*    */     //   9465: invokevirtual WN : (Lf/U90;)V
/*    */     //   9468: getfield oB : Lf/Ip;
/*    */     //   9471: aload_3
/*    */     //   9472: invokevirtual rK0 : (Lf/U90;)V
/*    */     //   9475: goto -> 9552
/*    */     //   9478: aload_0
/*    */     //   9479: dup
/*    */     //   9480: dup2
/*    */     //   9481: dup2
/*    */     //   9482: dup2
/*    */     //   9483: getfield oB : Lf/Ip;
/*    */     //   9486: invokevirtual d7 : ()Lf/cr0;
/*    */     //   9489: aload_1
/*    */     //   9490: invokevirtual Ya : (Lf/JG0;)Lf/U90;
/*    */     //   9493: invokevirtual Em0 : ()Lf/U90;
/*    */     //   9496: astore_2
/*    */     //   9497: getfield oB : Lf/Ip;
/*    */     //   9500: invokevirtual d7 : ()Lf/cr0;
/*    */     //   9503: invokevirtual Em0 : ()Lf/U90;
/*    */     //   9506: aload_1
/*    */     //   9507: invokevirtual Ya : (Lf/JG0;)Lf/U90;
/*    */     //   9510: invokevirtual Em0 : ()Lf/U90;
/*    */     //   9513: astore_1
/*    */     //   9514: getfield oB : Lf/Ip;
/*    */     //   9517: aload_2
/*    */     //   9518: invokevirtual WN : (Lf/U90;)V
/*    */     //   9521: getfield oB : Lf/Ip;
/*    */     //   9524: aload_1
/*    */     //   9525: invokevirtual rK0 : (Lf/U90;)V
/*    */     //   9528: getfield Ki : Lf/Un;
/*    */     //   9531: ldc_w 'mobile-save-icon'
/*    */     //   9534: invokevirtual Xu : (Ljava/lang/String;)V
/*    */     //   9537: getfield Ki : Lf/Un;
/*    */     //   9540: ldc_w ''
/*    */     //   9543: invokevirtual s6 : (Ljava/lang/String;)V
/*    */     //   9546: getfield Ki : Lf/Un;
/*    */     //   9549: invokevirtual J8 : (Lf/JG0;)V
/*    */     //   9552: aload_0
/*    */     //   9553: dup
/*    */     //   9554: getfield oB : Lf/Ip;
/*    */     //   9557: invokevirtual J8 : (Lf/JG0;)V
/*    */     //   9560: return
/*    */     // Line number table:
/*    */     //   Java source line number -> byte code offset
/*    */     //   #1	-> 3344
/*    */     //   #2	-> 3352
/*    */     //   #3	-> 3384
/*    */     //   #4	-> 3392
/*    */     //   #5	-> 3424
/*    */     //   #6	-> 3432
/*    */     //   #7	-> 3464
/*    */     //   #8	-> 3472
/*    */     //   #9	-> 3504
/*    */     //   #10	-> 3512
/*    */     //   #11	-> 3544
/*    */     //   #12	-> 3552
/*    */     //   #13	-> 3584
/*    */     //   #14	-> 3592
/*    */     //   #15	-> 3624
/*    */     //   #16	-> 3632
/*    */     //   #17	-> 3664
/*    */     //   #18	-> 3672
/*    */     // Exception table:
/*    */     //   from	to	target	type
/*    */     //   357	363	477	java/lang/Exception
/*    */     //   365	368	477	java/lang/Exception
/*    */     //   371	376	477	java/lang/Exception
/*    */     //   379	393	477	java/lang/Exception
/*    */     //   394	397	477	java/lang/Exception
/*    */     //   409	414	477	java/lang/Exception
/*    */     //   423	428	477	java/lang/Exception
/*    */     //   437	442	477	java/lang/Exception
/* 14 */     //   451	470	477	java/lang/Exception } public static Zv Ss(int paramInt1, int paramInt2, Zv[] paramArrayOfZv) { Zv zv = null; int i = paramArrayOfZv.length; for (byte b = 0; b < i; b++) { Zv zv1; int j; int k; if ((j = (zv1 = paramArrayOfZv[b]).wp) == paramInt1 && (k = zv1.FP) == paramInt2 && (zv == null || ((j *= k) >= (k = zv.wp * zv.FP) && (j > k || ((j = zv1.sa0) >= (k = zv.sa0) && (j > k || zv1.BB > zv.BB)))))) zv = zv1;  }  return zv; } private void bd() { this.i5.Z30(h1.c20); Od0(this.rT, this.A3); js.vu0.DJ(Ml0.OH0(1399), null); if (!km.ER()) { h1.c20 = (byte)this.i5.Wa0.go; km.iE0.GY(); h1.Gh0 = true; }  } public static void Xb(Tq paramTq, Gr paramGr) { paramTq.VF0 = true; js js1 = js.vu0; char c = '՗'; String str; if ((str = paramGr.PT.wL.toString()).contains(":")) str = str.substring(0, str.lastIndexOf(':'));  js1.Pu(-1, Ml0.Go(c, str)); } public static void qr0(rx0 paramrx0, zv[][] paramArrayOfzv, int paramInt) { paramrx0.rc.clear(); paramrx0.Ie(); zv[] arrayOfZv; for (byte b = 0; b < (arrayOfZv = paramArrayOfzv[paramInt]).length; ) { (arrayOfZv[b]).DM.M90(); b++; }  js.vu0.Pu(-1, Ml0.Go(1389, paramrx0.BT)); } private void UI() { Gr[] arrayOfGr; int i; byte b; for (i = (arrayOfGr = this.Ny).length, b = 0; b < i; ) { Gr gr; int j = gr.qg.L00; (gr = this[b]).P2.s6(km.Lpt1.am(j)); b++; }  } private void Zy0(String paramString) { String str; if ((str = (String)this.eh0.WW()).equals(paramString)) { UB0.L90.gW(null); h1.PB = ""; h1.Gh0 = true; return; }  UB0.L90.gW(this); h1.PB = this; h1.Gh0 = true; } public static void Od0(byte paramByte, Mt0 paramMt0) { Zv zv; int i; if (paramByte == 1) { int j = paramMt0.XZ; i = paramMt0.oi; Zv[] arrayOfZv = new Zv[0]; try { arrayOfZv = fa.SE0(UB0.M60.wf()); } catch (Exception exception) {} if ((zv = Ss(j, i, arrayOfZv)) == null) { UB0.M60.zn(fa.je0(UB0.M60.wf())); } else { UB0.M60.zn(zv); }  } else { Mt0 mt0; boolean bool; km.iE0.getClass(); if (zv == 2) { int[][] arrayOfInt = new int[4][1]; try { int m, i1, arrayOfInt1[] = arrayOfInt[0], arrayOfInt2[] = arrayOfInt[1], arrayOfInt3[] = arrayOfInt[2], arrayOfInt4[] = arrayOfInt[3]; GLFW.glfwGetMonitorWorkarea(((ba)UB0.M60.wf()).Jr, arrayOfInt1, arrayOfInt2, arrayOfInt3, arrayOfInt4); bool = false; try { if (GLFW.glfwGetWindowAttrib(UB0.M60.AW.ne0, 131080) == 1) { bool = true; } else { bool = false; }  } finally {} bool = i.XZ; int n = i.oi; if (bool != 0) { m = arrayOfInt[2][0]; i1 = arrayOfInt[3][0]; } else { if (bool <= (i1 = m[2][0])) i1 = bool;  if (n > (m = m[3][0])) { m = i1 = m; } else { m = i1 = n; }  }  if (m < 640) m = 640;  } finally { Exception exception = null; r9.pk0.info("Failed to retrieve monitor information", exception); }  }
/* 15 */        w70 w70 = UB0.M60; if (zv == 2) { bool = true; } else { bool = false; }
/*    */       
/* 17 */       int k = bool ^ true;
/*    */ 
/*    */       
/* 20 */       GLFW.glfwSetWindowAttrib(w70.AW.ne0, 131077, k); if (zv == 2 || mt0
/* 21 */         .XZ < UB0.M60.fG0() || mt0.oi < UB0.M60.dL()) km.iE0.Q7(false);  int j = mt0.XZ; UB0.M60.O10(j, mt0.oi); km.iE0.LY(zv); }
/*    */      }
/*    */ 
/*    */   
/*    */   private void Yb0() {
/*    */     vR.Le.uh = this.FN.hk / 100.0F;
/*    */     if (this.bm0.Po0())
/*    */       km.pm0.fy((short)1583); 
/*    */   }
/*    */   
/*    */   private void ja() {
/*    */     vR.aG0.uh = this.Zz0.hk / 100.0F;
/*    */     if (this.bm0.Po0())
/*    */       km.pm0.bA0(true, (byte)2, (short)1583, 0.0F); 
/*    */   }
/*    */   
/*    */   private void Ye() {
/*    */     vR vR;
/*    */     (vR = vR.XZ).uh = this.tC0.hk / 100.0F;
/*    */     VD0 vD0;
/*    */     lr lr;
/*    */     if ((lr = (vD0 = km.pm0).kR) != null)
/*    */       if (lr instanceof eU) {
/*    */         U00((byte)0, (short)0, false, true);
/*    */       } else {
/*    */         lr.vf0(vR.Sq());
/*    */       }  
/*    */   }
/*    */   
/*    */   private void EP() {
/*    */     this.TI = true;
/*    */     int i = this.Ca0.Wa0.go;
/*    */     this.A3 = this.Yk0.Fj.get(i);
/*    */   }
/*    */   
/*    */   private void Ma0() {
/*    */     if (this.jh0.WW() == Kz.rL0) {
/*    */       km.iE0.getClass();
/*    */       if (!ANGLELoader.isInstalled()) {
/*    */         (new h70(Ml0.OH0(1215), v10::ok, this)).sD0 = true;
/*    */         js.vu0.uh((new h70(Ml0.OH0(1215), v10::ok, this)).Id(this::P2));
/*    */       } 
/*    */     } 
/*    */   }
/*    */   
/*    */   private void P2() {
/*    */     this.jh0.COm6(Kz.valueOf(h1.ev));
/*    */   }
/*    */   
/*    */   public final boolean zr0() {
/*    */     this();
/*    */     Stream.<Gr>of(this.Ny).filter(Gr::ko0).filter(Gr::Kg0).forEach(tq::Xb);
/*    */     Tq tq;
/*    */     return (tq = new Tq()).VF0 ^ true;
/*    */   }
/*    */   
/*    */   public final void close() {
/*    */     this.IF.jf0(this);
/*    */     vR[] arrayOfVR;
/*    */     int i;
/*    */     byte b;
/*    */     for (i = (arrayOfVR = vR.x30).length, b = 0; b < i; ) {
/*    */       (this[b]).uh = Float.NaN;
/*    */       b++;
/*    */     } 
/*    */     VD0 vD0;
/*    */     lr lr;
/*    */     if ((lr = (vD0 = km.pm0).kR) != null)
/*    */       if (lr instanceof eU) {
/*    */         U00((byte)0, (short)0, false, true);
/*    */       } else {
/*    */         lr.vf0(vR.XZ.Sq());
/*    */       }  
/*    */   }
/*    */   
/*    */   public final void O10() {
/*    */     // Byte code:
/*    */     //   0: iconst_0
/*    */     //   1: istore_1
/*    */     //   2: ldc_w ''
/*    */     //   5: astore_2
/*    */     //   6: invokestatic ER : ()Z
/*    */     //   9: ifne -> 327
/*    */     //   12: getstatic f/h1.c20 : B
/*    */     //   15: iconst_2
/*    */     //   16: if_icmpeq -> 41
/*    */     //   19: aload_0
/*    */     //   20: getfield i5 : Lf/W1;
/*    */     //   23: getfield Wa0 : Lf/A60;
/*    */     //   26: getfield go : I
/*    */     //   29: iconst_2
/*    */     //   30: if_icmpne -> 36
/*    */     //   33: goto -> 41
/*    */     //   36: iconst_0
/*    */     //   37: istore_3
/*    */     //   38: goto -> 43
/*    */     //   41: iconst_1
/*    */     //   42: istore_3
/*    */     //   43: iload_1
/*    */     //   44: iload_3
/*    */     //   45: ior
/*    */     //   46: istore_1
/*    */     //   47: getstatic f/h1.Eg0 : Z
/*    */     //   50: aload_0
/*    */     //   51: getfield Wr : Lf/FL;
/*    */     //   54: invokevirtual Fk0 : ()Z
/*    */     //   57: if_icmpeq -> 115
/*    */     //   60: aload_0
/*    */     //   61: getfield Wr : Lf/FL;
/*    */     //   64: invokevirtual Fk0 : ()Z
/*    */     //   67: putstatic f/h1.Eg0 : Z
/*    */     //   70: getstatic f/pA.Dg0 : Lf/pA;
/*    */     //   73: dup
/*    */     //   74: astore_3
/*    */     //   75: ifnull -> 115
/*    */     //   78: aload_3
/*    */     //   79: getfield Qp0 : Lf/finally;
/*    */     //   82: dup
/*    */     //   83: astore #4
/*    */     //   85: getfield fr0 : Lf/JG0;
/*    */     //   88: ifnull -> 115
/*    */     //   91: aload_3
/*    */     //   92: dup
/*    */     //   93: aload #4
/*    */     //   95: invokevirtual ra0 : ()Z
/*    */     //   98: pop
/*    */     //   99: new f/finally
/*    */     //   102: dup
/*    */     //   103: astore_3
/*    */     //   104: invokespecial <init> : ()V
/*    */     //   107: aload_3
/*    */     //   108: putfield Qp0 : Lf/finally;
/*    */     //   111: aload_3
/*    */     //   112: invokevirtual J8 : (Lf/JG0;)V
/*    */     //   115: getstatic f/h1.IC0 : Z
/*    */     //   118: aload_0
/*    */     //   119: getfield JE : Lf/FL;
/*    */     //   122: invokevirtual Fk0 : ()Z
/*    */     //   125: if_icmpeq -> 189
/*    */     //   128: aload_0
/*    */     //   129: getfield JE : Lf/FL;
/*    */     //   132: invokevirtual Fk0 : ()Z
/*    */     //   135: putstatic f/h1.IC0 : Z
/*    */     //   138: getstatic f/js.vu0 : Lf/js;
/*    */     //   141: astore_3
/*    */     //   142: ldc_w 'maingui'
/*    */     //   145: invokestatic df : (Ljava/lang/String;)Ljava/lang/StringBuilder;
/*    */     //   148: astore #4
/*    */     //   150: getstatic f/h1.IC0 : Z
/*    */     //   153: ifeq -> 164
/*    */     //   156: ldc_w '-cursor'
/*    */     //   159: astore #5
/*    */     //   161: goto -> 169
/*    */     //   164: ldc_w ''
/*    */     //   167: astore #5
/*    */     //   169: aload_3
/*    */     //   170: aload #4
/*    */     //   172: aload #5
/*    */     //   174: invokevirtual append : (Ljava/lang/String;)Ljava/lang/StringBuilder;
/*    */     //   177: invokevirtual toString : ()Ljava/lang/String;
/*    */     //   180: invokevirtual Xu : (Ljava/lang/String;)V
/*    */     //   183: getstatic f/js.vu0 : Lf/js;
/*    */     //   186: invokevirtual cZ : ()V
/*    */     //   189: aload_0
/*    */     //   190: dup
/*    */     //   191: getfield so0 : Lf/FL;
/*    */     //   194: invokevirtual Fk0 : ()Z
/*    */     //   197: putstatic f/h1.gt0 : Z
/*    */     //   200: getfield TI : Z
/*    */     //   203: ifeq -> 256
/*    */     //   206: aload_0
/*    */     //   207: getfield Ca0 : Lf/W1;
/*    */     //   210: getfield Wa0 : Lf/A60;
/*    */     //   213: getfield go : I
/*    */     //   216: dup
/*    */     //   217: istore_3
/*    */     //   218: iconst_m1
/*    */     //   219: if_icmple -> 256
/*    */     //   222: aload_0
/*    */     //   223: getfield Yk0 : Lf/OZ;
/*    */     //   226: getfield Fj : Ljava/util/ArrayList;
/*    */     //   229: iload_3
/*    */     //   230: invokevirtual get : (I)Ljava/lang/Object;
/*    */     //   233: checkcast f/Mt0
/*    */     //   236: dup
/*    */     //   237: astore_3
/*    */     //   238: ifnull -> 256
/*    */     //   241: aload_0
/*    */     //   242: getfield i5 : Lf/W1;
/*    */     //   245: getfield Wa0 : Lf/A60;
/*    */     //   248: getfield go : I
/*    */     //   251: i2b
/*    */     //   252: aload_3
/*    */     //   253: invokestatic Od0 : (BLf/Mt0;)V
/*    */     //   256: aload_0
/*    */     //   257: getfield rT : B
/*    */     //   260: aload_0
/*    */     //   261: getfield i5 : Lf/W1;
/*    */     //   264: getfield Wa0 : Lf/A60;
/*    */     //   267: getfield go : I
/*    */     //   270: if_icmpeq -> 311
/*    */     //   273: getstatic f/A1.L7 : Lf/A1;
/*    */     //   276: aload_0
/*    */     //   277: <illegal opcode> run : (Lf/v10;)Ljava/lang/Runnable;
/*    */     //   282: ldc2_w 8000
/*    */     //   285: invokevirtual ac0 : (Ljava/lang/Runnable;J)Ljava/util/concurrent/ScheduledFuture;
/*    */     //   288: astore_3
/*    */     //   289: getstatic f/js.vu0 : Lf/js;
/*    */     //   292: aload_0
/*    */     //   293: aload_3
/*    */     //   294: sipush #1398
/*    */     //   297: invokestatic OH0 : (I)Ljava/lang/String;
/*    */     //   300: astore_3
/*    */     //   301: <illegal opcode> run : (Lf/v10;Ljava/util/concurrent/ScheduledFuture;)Ljava/lang/Runnable;
/*    */     //   306: aload_3
/*    */     //   307: swap
/*    */     //   308: invokevirtual DJ : (Ljava/lang/String;Ljava/lang/Runnable;)V
/*    */     //   311: aload_0
/*    */     //   312: getfield Zx : Lf/FL;
/*    */     //   315: dup
/*    */     //   316: astore_3
/*    */     //   317: ifnull -> 327
/*    */     //   320: aload_3
/*    */     //   321: invokevirtual Fk0 : ()Z
/*    */     //   324: putstatic f/h1.qL : Z
/*    */     //   327: aload_0
/*    */     //   328: getfield R : Lf/FL;
/*    */     //   331: invokevirtual Fk0 : ()Z
/*    */     //   334: getstatic f/h1.WX : Z
/*    */     //   337: if_icmpeq -> 352
/*    */     //   340: aload_0
/*    */     //   341: iconst_1
/*    */     //   342: istore_1
/*    */     //   343: getfield R : Lf/FL;
/*    */     //   346: invokevirtual Fk0 : ()Z
/*    */     //   349: putstatic f/h1.WX : Z
/*    */     //   352: aload_0
/*    */     //   353: getfield I80 : Lf/FL;
/*    */     //   356: dup
/*    */     //   357: astore_3
/*    */     //   358: ifnull -> 383
/*    */     //   361: aload_3
/*    */     //   362: invokevirtual Fk0 : ()Z
/*    */     //   365: getstatic f/h1.fD : Z
/*    */     //   368: if_icmpeq -> 383
/*    */     //   371: aload_0
/*    */     //   372: iconst_1
/*    */     //   373: istore_1
/*    */     //   374: getfield I80 : Lf/FL;
/*    */     //   377: invokevirtual Fk0 : ()Z
/*    */     //   380: putstatic f/h1.fD : Z
/*    */     //   383: aload_0
/*    */     //   384: getstatic f/h1.b40 : I
/*    */     //   387: istore_3
/*    */     //   388: getfield eW : Lf/zT;
/*    */     //   391: dup
/*    */     //   392: astore #4
/*    */     //   394: getfield hk : I
/*    */     //   397: dup
/*    */     //   398: istore #5
/*    */     //   400: aload #4
/*    */     //   402: getfield Lpt3 : I
/*    */     //   405: if_icmpgt -> 411
/*    */     //   408: iconst_m1
/*    */     //   409: istore #5
/*    */     //   411: iload_3
/*    */     //   412: iload #5
/*    */     //   414: dup
/*    */     //   415: putstatic f/h1.b40 : I
/*    */     //   418: if_icmpeq -> 426
/*    */     //   421: iconst_1
/*    */     //   422: istore_3
/*    */     //   423: goto -> 428
/*    */     //   426: iconst_0
/*    */     //   427: istore_3
/*    */     //   428: getstatic f/h1.hR : Z
/*    */     //   431: aload_0
/*    */     //   432: getfield FB : Lf/FL;
/*    */     //   435: invokevirtual Fk0 : ()Z
/*    */     //   438: if_icmpeq -> 447
/*    */     //   441: iconst_1
/*    */     //   442: istore #4
/*    */     //   444: goto -> 450
/*    */     //   447: iconst_0
/*    */     //   448: istore #4
/*    */     //   450: aload_0
/*    */     //   451: dup
/*    */     //   452: dup2
/*    */     //   453: getfield FB : Lf/FL;
/*    */     //   456: invokevirtual Fk0 : ()Z
/*    */     //   459: putstatic f/h1.hR : Z
/*    */     //   462: getfield u30 : Lf/FL;
/*    */     //   465: invokevirtual Fk0 : ()Z
/*    */     //   468: putstatic f/h1.Vy : Z
/*    */     //   471: getfield He : Lf/FL;
/*    */     //   474: invokevirtual Fk0 : ()Z
/*    */     //   477: putstatic f/h1.SZ : Z
/*    */     //   480: getfield K30 : Lf/FL;
/*    */     //   483: invokevirtual Fk0 : ()Z
/*    */     //   486: putstatic f/h1.rn : Z
/*    */     //   489: getstatic f/h1.Pm : Z
/*    */     //   492: aload_0
/*    */     //   493: getfield U3 : Lf/FL;
/*    */     //   496: invokevirtual Fk0 : ()Z
/*    */     //   499: if_icmpeq -> 514
/*    */     //   502: aload_0
/*    */     //   503: getfield U3 : Lf/FL;
/*    */     //   506: invokevirtual Fk0 : ()Z
/*    */     //   509: putstatic f/h1.Pm : Z
/*    */     //   512: iconst_1
/*    */     //   513: istore_1
/*    */     //   514: aload_0
/*    */     //   515: getfield sl0 : Lf/zT;
/*    */     //   518: getfield hk : I
/*    */     //   521: putstatic f/h1.dB0 : I
/*    */     //   524: getstatic f/h1.Lf0 : Z
/*    */     //   527: aload_0
/*    */     //   528: getfield a0 : Lf/FL;
/*    */     //   531: invokevirtual Fk0 : ()Z
/*    */     //   534: if_icmpeq -> 567
/*    */     //   537: aload_0
/*    */     //   538: getfield a0 : Lf/FL;
/*    */     //   541: invokevirtual Fk0 : ()Z
/*    */     //   544: putstatic f/h1.Lf0 : Z
/*    */     //   547: getstatic f/js.vu0 : Lf/js;
/*    */     //   550: aload_0
/*    */     //   551: getfield a0 : Lf/FL;
/*    */     //   554: invokevirtual Fk0 : ()Z
/*    */     //   557: istore #5
/*    */     //   559: getfield es : Lf/xs;
/*    */     //   562: iload #5
/*    */     //   564: invokevirtual wI0 : (Z)V
/*    */     //   567: aload_0
/*    */     //   568: dup
/*    */     //   569: dup
/*    */     //   570: dup2
/*    */     //   571: getfield Ly : Lf/W1;
/*    */     //   574: getfield Wa0 : Lf/A60;
/*    */     //   577: getfield go : I
/*    */     //   580: putstatic f/h1.nv : I
/*    */     //   583: getfield pX : Lf/W1;
/*    */     //   586: getfield Wa0 : Lf/A60;
/*    */     //   589: getfield go : I
/*    */     //   592: putstatic f/h1.ak0 : I
/*    */     //   595: getfield Eh : Lf/FL;
/*    */     //   598: invokevirtual Fk0 : ()Z
/*    */     //   601: putstatic f/h1.X2 : Z
/*    */     //   604: getfield J6 : Lf/FL;
/*    */     //   607: invokevirtual Fk0 : ()Z
/*    */     //   610: putstatic f/h1.je : Z
/*    */     //   613: getfield hi : Lf/E1;
/*    */     //   616: getfield Wa0 : Lf/A60;
/*    */     //   619: getfield go : I
/*    */     //   622: dup
/*    */     //   623: istore #5
/*    */     //   625: iconst_m1
/*    */     //   626: if_icmple -> 650
/*    */     //   629: aload_0
/*    */     //   630: getfield t0 : Lf/OZ;
/*    */     //   633: getfield Fj : Ljava/util/ArrayList;
/*    */     //   636: iload #5
/*    */     //   638: invokevirtual get : (I)Ljava/lang/Object;
/*    */     //   641: checkcast java/lang/Float
/*    */     //   644: invokevirtual floatValue : ()F
/*    */     //   647: putstatic f/h1.b90 : F
/*    */     //   650: aload_0
/*    */     //   651: getfield LQ : Lf/Q3;
/*    */     //   654: getfield Wa0 : Lf/A60;
/*    */     //   657: getfield go : I
/*    */     //   660: dup
/*    */     //   661: istore #5
/*    */     //   663: iconst_m1
/*    */     //   664: if_icmple -> 688
/*    */     //   667: aload_0
/*    */     //   668: getfield MR : Lf/OZ;
/*    */     //   671: getfield Fj : Ljava/util/ArrayList;
/*    */     //   674: iload #5
/*    */     //   676: invokevirtual get : (I)Ljava/lang/Object;
/*    */     //   679: checkcast java/lang/Float
/*    */     //   682: invokevirtual floatValue : ()F
/*    */     //   685: putstatic f/h1.Fg : F
/*    */     //   688: aload_0
/*    */     //   689: getfield zi0 : Lf/FL;
/*    */     //   692: invokevirtual Fk0 : ()Z
/*    */     //   695: putstatic f/h1.c00 : Z
/*    */     //   698: getstatic f/h1.Wo : Z
/*    */     //   701: aload_0
/*    */     //   702: getfield lS : Lf/FL;
/*    */     //   705: invokevirtual Fk0 : ()Z
/*    */     //   708: if_icmpeq -> 735
/*    */     //   711: aload_0
/*    */     //   712: getfield lS : Lf/FL;
/*    */     //   715: invokevirtual Fk0 : ()Z
/*    */     //   718: putstatic f/h1.Wo : Z
/*    */     //   721: getstatic f/pA.Dg0 : Lf/pA;
/*    */     //   724: dup
/*    */     //   725: astore #5
/*    */     //   727: ifnull -> 735
/*    */     //   730: aload #5
/*    */     //   732: invokevirtual dp0 : ()V
/*    */     //   735: aload_0
/*    */     //   736: getfield P10 : Lf/xl0;
/*    */     //   739: getfield Wa0 : Lf/A60;
/*    */     //   742: getfield go : I
/*    */     //   745: dup
/*    */     //   746: istore #5
/*    */     //   748: iconst_m1
/*    */     //   749: if_icmple -> 812
/*    */     //   752: aload_0
/*    */     //   753: getfield GQ : Lf/OZ;
/*    */     //   756: getfield Fj : Ljava/util/ArrayList;
/*    */     //   759: iload #5
/*    */     //   761: invokevirtual get : (I)Ljava/lang/Object;
/*    */     //   764: checkcast java/lang/Float
/*    */     //   767: invokevirtual floatValue : ()F
/*    */     //   770: getstatic f/h1.nR : F
/*    */     //   773: fcmpl
/*    */     //   774: ifeq -> 779
/*    */     //   777: iconst_1
/*    */     //   778: istore_1
/*    */     //   779: aload_0
/*    */     //   780: getfield GQ : Lf/OZ;
/*    */     //   783: aload_0
/*    */     //   784: getfield P10 : Lf/xl0;
/*    */     //   787: getfield Wa0 : Lf/A60;
/*    */     //   790: getfield go : I
/*    */     //   793: istore #5
/*    */     //   795: getfield Fj : Ljava/util/ArrayList;
/*    */     //   798: iload #5
/*    */     //   800: invokevirtual get : (I)Ljava/lang/Object;
/*    */     //   803: checkcast java/lang/Float
/*    */     //   806: invokevirtual floatValue : ()F
/*    */     //   809: putstatic f/h1.nR : F
/*    */     //   812: aload_0
/*    */     //   813: getfield Id0 : Lf/W1;
/*    */     //   816: getfield Wa0 : Lf/A60;
/*    */     //   819: getfield go : I
/*    */     //   822: dup
/*    */     //   823: istore #5
/*    */     //   825: iconst_m1
/*    */     //   826: if_icmple -> 874
/*    */     //   829: iload #5
/*    */     //   831: iconst_1
/*    */     //   832: if_icmpeq -> 870
/*    */     //   835: iload #5
/*    */     //   837: iconst_2
/*    */     //   838: if_icmpeq -> 862
/*    */     //   841: iload #5
/*    */     //   843: iconst_3
/*    */     //   844: if_icmpeq -> 854
/*    */     //   847: iconst_0
/*    */     //   848: putstatic f/h1.QJ : I
/*    */     //   851: goto -> 874
/*    */     //   854: bipush #12
/*    */     //   856: putstatic f/h1.QJ : I
/*    */     //   859: goto -> 874
/*    */     //   862: bipush #7
/*    */     //   864: putstatic f/h1.QJ : I
/*    */     //   867: goto -> 874
/*    */     //   870: iconst_3
/*    */     //   871: putstatic f/h1.QJ : I
/*    */     //   874: aload_0
/*    */     //   875: getstatic f/h1.Vu0 : I
/*    */     //   878: istore #5
/*    */     //   880: getfield UC : Lf/zT;
/*    */     //   883: getfield hk : I
/*    */     //   886: dup
/*    */     //   887: istore #6
/*    */     //   889: iconst_1
/*    */     //   890: if_icmpge -> 897
/*    */     //   893: iconst_0
/*    */     //   894: goto -> 911
/*    */     //   897: iload #6
/*    */     //   899: i2d
/*    */     //   900: dstore #6
/*    */     //   902: ldc2_w 2.0
/*    */     //   905: dload #6
/*    */     //   907: invokestatic pow : (DD)D
/*    */     //   910: d2i
/*    */     //   911: dup
/*    */     //   912: putstatic f/h1.Vu0 : I
/*    */     //   915: getstatic f/I20.oq : I
/*    */     //   918: dup
/*    */     //   919: istore #6
/*    */     //   921: if_icmple -> 929
/*    */     //   924: iload #6
/*    */     //   926: putstatic f/h1.Vu0 : I
/*    */     //   929: aload_0
/*    */     //   930: getfield HL : Lf/zT;
/*    */     //   933: dup
/*    */     //   934: astore #6
/*    */     //   936: getfield hk : I
/*    */     //   939: dup
/*    */     //   940: istore #7
/*    */     //   942: iconst_1
/*    */     //   943: if_icmplt -> 999
/*    */     //   946: iload #7
/*    */     //   948: aload #6
/*    */     //   950: getfield lK : I
/*    */     //   953: if_icmplt -> 959
/*    */     //   956: goto -> 999
/*    */     //   959: invokestatic ER : ()Z
/*    */     //   962: ifeq -> 972
/*    */     //   965: bipush #20
/*    */     //   967: istore #6
/*    */     //   969: goto -> 975
/*    */     //   972: iconst_0
/*    */     //   973: istore #6
/*    */     //   975: iload #7
/*    */     //   977: iload #6
/*    */     //   979: if_icmpne -> 986
/*    */     //   982: iconst_m1
/*    */     //   983: goto -> 993
/*    */     //   986: aload_0
/*    */     //   987: getfield HL : Lf/zT;
/*    */     //   990: getfield hk : I
/*    */     //   993: putstatic f/h1.y00 : I
/*    */     //   996: goto -> 1003
/*    */     //   999: iconst_0
/*    */     //   1000: putstatic f/h1.y00 : I
/*    */     //   1003: getstatic f/h1.Vu0 : I
/*    */     //   1006: iload #5
/*    */     //   1008: if_icmpeq -> 1013
/*    */     //   1011: iconst_1
/*    */     //   1012: istore_1
/*    */     //   1013: aload_0
/*    */     //   1014: getstatic f/km.iE0 : Lf/r9;
/*    */     //   1017: getstatic f/h1.dB0 : I
/*    */     //   1020: istore #5
/*    */     //   1022: getstatic f/h1.A4 : Lf/ik;
/*    */     //   1025: pop
/*    */     //   1026: getstatic f/h1.A4 : Lf/ik;
/*    */     //   1029: pop
/*    */     //   1030: invokevirtual getClass : ()Ljava/lang/Class;
/*    */     //   1033: pop
/*    */     //   1034: getstatic f/UB0.M60 : Lf/w70;
/*    */     //   1037: getfield AW : Lf/MJ0;
/*    */     //   1040: getfield oA0 : Lf/fa;
/*    */     //   1043: iload #5
/*    */     //   1045: putfield cC : I
/*    */     //   1048: getfield jh0 : Lf/W1;
/*    */     //   1051: invokevirtual WW : ()Ljava/lang/Object;
/*    */     //   1054: checkcast f/Kz
/*    */     //   1057: astore #5
/*    */     //   1059: getstatic f/h1.ev : Ljava/lang/String;
/*    */     //   1062: invokestatic valueOf : (Ljava/lang/String;)Lf/Kz;
/*    */     //   1065: aload #5
/*    */     //   1067: if_acmpeq -> 1104
/*    */     //   1070: aload #5
/*    */     //   1072: dup
/*    */     //   1073: invokevirtual name : ()Ljava/lang/String;
/*    */     //   1076: putstatic f/h1.ev : Ljava/lang/String;
/*    */     //   1079: getstatic f/Kz.rL0 : Lf/Kz;
/*    */     //   1082: if_acmpne -> 1102
/*    */     //   1085: getstatic f/km.iE0 : Lf/r9;
/*    */     //   1088: invokevirtual getClass : ()Ljava/lang/Class;
/*    */     //   1091: pop
/*    */     //   1092: invokestatic isInstalled : ()Z
/*    */     //   1095: ifne -> 1102
/*    */     //   1098: ldc_w 'angle'
/*    */     //   1101: astore_2
/*    */     //   1102: iconst_1
/*    */     //   1103: istore_1
/*    */     //   1104: getstatic f/h1.D30 : Z
/*    */     //   1107: aload_0
/*    */     //   1108: getfield Y60 : Lf/FL;
/*    */     //   1111: invokevirtual Fk0 : ()Z
/*    */     //   1114: if_icmpeq -> 1129
/*    */     //   1117: aload_0
/*    */     //   1118: getfield Y60 : Lf/FL;
/*    */     //   1121: invokevirtual Fk0 : ()Z
/*    */     //   1124: putstatic f/h1.D30 : Z
/*    */     //   1127: iconst_1
/*    */     //   1128: istore_1
/*    */     //   1129: aload_0
/*    */     //   1130: getfield Ny : [Lf/Gr;
/*    */     //   1133: dup
/*    */     //   1134: astore #5
/*    */     //   1136: arraylength
/*    */     //   1137: istore #6
/*    */     //   1139: iconst_0
/*    */     //   1140: istore #7
/*    */     //   1142: iload #7
/*    */     //   1144: iload #6
/*    */     //   1146: if_icmpge -> 1194
/*    */     //   1149: aload #5
/*    */     //   1151: iload #7
/*    */     //   1153: aaload
/*    */     //   1154: dup
/*    */     //   1155: astore #8
/*    */     //   1157: getfield qg : Lf/BM;
/*    */     //   1160: aload #8
/*    */     //   1162: getfield P2 : Lf/zh;
/*    */     //   1165: getfield dt0 : I
/*    */     //   1168: istore #8
/*    */     //   1170: getfield gT : Lf/HJ;
/*    */     //   1173: dup
/*    */     //   1174: astore #9
/*    */     //   1176: ifnull -> 1188
/*    */     //   1179: aload #9
/*    */     //   1181: iload #8
/*    */     //   1183: invokeinterface z0 : (I)V
/*    */     //   1188: iinc #7, 1
/*    */     //   1191: goto -> 1142
/*    */     //   1194: aload_0
/*    */     //   1195: dup
/*    */     //   1196: dup2
/*    */     //   1197: dup2
/*    */     //   1198: dup2
/*    */     //   1199: dup2
/*    */     //   1200: getfield tC0 : Lf/zT;
/*    */     //   1203: getfield hk : I
/*    */     //   1206: putstatic f/h1.Hh0 : I
/*    */     //   1209: getfield Zz0 : Lf/zT;
/*    */     //   1212: getfield hk : I
/*    */     //   1215: putstatic f/h1.HF : I
/*    */     //   1218: getfield FN : Lf/zT;
/*    */     //   1221: getfield hk : I
/*    */     //   1224: putstatic f/h1.xP : I
/*    */     //   1227: getfield rQ : Lf/FL;
/*    */     //   1230: invokevirtual Fk0 : ()Z
/*    */     //   1233: putstatic f/h1.VJ0 : Z
/*    */     //   1236: getfield super : Lf/zT;
/*    */     //   1239: getfield hk : I
/*    */     //   1242: i2f
/*    */     //   1243: ldc_w 100.0
/*    */     //   1246: fdiv
/*    */     //   1247: putstatic f/h1.In0 : F
/*    */     //   1250: getfield DC0 : Lf/FL;
/*    */     //   1253: invokevirtual Fk0 : ()Z
/*    */     //   1256: putstatic f/h1.yA0 : Z
/*    */     //   1259: getfield D60 : Lf/zT;
/*    */     //   1262: getfield hk : I
/*    */     //   1265: putstatic f/h1.sK0 : I
/*    */     //   1268: getfield og0 : Lf/FL;
/*    */     //   1271: invokevirtual Fk0 : ()Z
/*    */     //   1274: putstatic f/h1.me0 : Z
/*    */     //   1277: getfield Kj : Lf/FL;
/*    */     //   1280: invokevirtual Fk0 : ()Z
/*    */     //   1283: putstatic f/h1.sP : Z
/*    */     //   1286: getfield JT : Lf/W1;
/*    */     //   1289: getfield Wa0 : Lf/A60;
/*    */     //   1292: getfield go : I
/*    */     //   1295: putstatic f/h1.rl0 : I
/*    */     //   1298: getstatic f/h1.sP : Z
/*    */     //   1301: ifne -> 1311
/*    */     //   1304: getstatic f/km.n20 : Lf/q7;
/*    */     //   1307: iconst_0
/*    */     //   1308: putfield qO : Z
/*    */     //   1311: aload_0
/*    */     //   1312: dup
/*    */     //   1313: dup
/*    */     //   1314: dup2
/*    */     //   1315: dup2
/*    */     //   1316: dup2
/*    */     //   1317: dup2
/*    */     //   1318: dup2
/*    */     //   1319: dup2
/*    */     //   1320: getfield Le0 : Lf/FL;
/*    */     //   1323: invokevirtual Fk0 : ()Z
/*    */     //   1326: putstatic f/h1.QP : Z
/*    */     //   1329: getfield l80 : Lf/FL;
/*    */     //   1332: invokevirtual Fk0 : ()Z
/*    */     //   1335: putstatic f/h1.zR : Z
/*    */     //   1338: getfield ii0 : Lf/FL;
/*    */     //   1341: invokevirtual Fk0 : ()Z
/*    */     //   1344: putstatic f/h1.bf : Z
/*    */     //   1347: getfield pw : Lf/FL;
/*    */     //   1350: invokevirtual Fk0 : ()Z
/*    */     //   1353: putstatic f/h1.bp0 : Z
/*    */     //   1356: getfield ab0 : Lf/FL;
/*    */     //   1359: invokevirtual Fk0 : ()Z
/*    */     //   1362: putstatic f/h1.qu0 : Z
/*    */     //   1365: getfield BG0 : Lf/W1;
/*    */     //   1368: getfield Wa0 : Lf/A60;
/*    */     //   1371: getfield go : I
/*    */     //   1374: putstatic f/h1.ei : I
/*    */     //   1377: getfield Rp : Lf/W1;
/*    */     //   1380: getfield Wa0 : Lf/A60;
/*    */     //   1383: getfield go : I
/*    */     //   1386: putstatic f/h1.YJ : I
/*    */     //   1389: getfield qx : Lf/zT;
/*    */     //   1392: getfield hk : I
/*    */     //   1395: putstatic f/h1.UD0 : I
/*    */     //   1398: getfield TA : Lf/zT;
/*    */     //   1401: getfield hk : I
/*    */     //   1404: putstatic f/h1.Wx0 : I
/*    */     //   1407: getfield Z50 : Lf/FL;
/*    */     //   1410: invokevirtual Fk0 : ()Z
/*    */     //   1413: putstatic f/h1.M20 : Z
/*    */     //   1416: getfield Rs0 : Lf/FL;
/*    */     //   1419: invokevirtual Fk0 : ()Z
/*    */     //   1422: putstatic f/h1.Po0 : Z
/*    */     //   1425: getfield V1 : Lf/FL;
/*    */     //   1428: invokevirtual Fk0 : ()Z
/*    */     //   1431: putstatic f/h1.c7 : Z
/*    */     //   1434: getfield wB : Lf/FL;
/*    */     //   1437: invokevirtual Fk0 : ()Z
/*    */     //   1440: putstatic f/h1.Iu0 : Z
/*    */     //   1443: getfield UI : Lf/FL;
/*    */     //   1446: invokevirtual Fk0 : ()Z
/*    */     //   1449: putstatic f/h1.FJ : Z
/*    */     //   1452: getstatic f/t90.md0 : Ljava/lang/String;
/*    */     //   1455: astore #5
/*    */     //   1457: iconst_0
/*    */     //   1458: istore #6
/*    */     //   1460: getfield HD : Lf/W1;
/*    */     //   1463: getfield Wa0 : Lf/A60;
/*    */     //   1466: getfield go : I
/*    */     //   1469: dup
/*    */     //   1470: istore #7
/*    */     //   1472: iconst_m1
/*    */     //   1473: if_icmple -> 1557
/*    */     //   1476: aload_0
/*    */     //   1477: getfield WE : [Ljava/lang/String;
/*    */     //   1480: iload #7
/*    */     //   1482: aaload
/*    */     //   1483: dup
/*    */     //   1484: astore #7
/*    */     //   1486: ifnull -> 1557
/*    */     //   1489: getstatic f/h1.pB0 : Ljava/lang/String;
/*    */     //   1492: aload #7
/*    */     //   1494: invokevirtual equalsIgnoreCase : (Ljava/lang/String;)Z
/*    */     //   1497: ifne -> 1557
/*    */     //   1500: getstatic f/cE.eo0 : Lf/cE;
/*    */     //   1503: aload #7
/*    */     //   1505: invokevirtual sG : (Ljava/lang/String;)Z
/*    */     //   1508: ifeq -> 1557
/*    */     //   1511: aload #5
/*    */     //   1513: aload #7
/*    */     //   1515: putstatic f/h1.pB0 : Ljava/lang/String;
/*    */     //   1518: iconst_1
/*    */     //   1519: putstatic f/h1.p0 : Z
/*    */     //   1522: iconst_1
/*    */     //   1523: istore_1
/*    */     //   1524: ifnonnull -> 1536
/*    */     //   1527: getstatic f/t90.md0 : Ljava/lang/String;
/*    */     //   1530: ifnull -> 1551
/*    */     //   1533: goto -> 1547
/*    */     //   1536: aload #5
/*    */     //   1538: getstatic f/t90.md0 : Ljava/lang/String;
/*    */     //   1541: invokevirtual equals : (Ljava/lang/Object;)Z
/*    */     //   1544: ifne -> 1551
/*    */     //   1547: iconst_1
/*    */     //   1548: goto -> 1552
/*    */     //   1551: iconst_0
/*    */     //   1552: iload #6
/*    */     //   1554: ior
/*    */     //   1555: istore #6
/*    */     //   1557: aload_0
/*    */     //   1558: getfield B3 : Lf/W1;
/*    */     //   1561: getfield Wa0 : Lf/A60;
/*    */     //   1564: getfield go : I
/*    */     //   1567: dup
/*    */     //   1568: istore #5
/*    */     //   1570: iconst_m1
/*    */     //   1571: if_icmple -> 1593
/*    */     //   1574: getstatic f/h1.zr0 : I
/*    */     //   1577: iload #5
/*    */     //   1579: if_icmpeq -> 1593
/*    */     //   1582: iload #5
/*    */     //   1584: dup
/*    */     //   1585: putstatic f/h1.zr0 : I
/*    */     //   1588: putstatic f/YK0.L10 : I
/*    */     //   1591: iconst_1
/*    */     //   1592: istore_1
/*    */     //   1593: aload_0
/*    */     //   1594: getfield Zg0 : Lf/FL;
/*    */     //   1597: invokevirtual Fk0 : ()Z
/*    */     //   1600: getstatic f/h1.ru0 : Z
/*    */     //   1603: if_icmpeq -> 1637
/*    */     //   1606: aload_0
/*    */     //   1607: getfield Zg0 : Lf/FL;
/*    */     //   1610: invokevirtual Fk0 : ()Z
/*    */     //   1613: dup
/*    */     //   1614: dup
/*    */     //   1615: istore #5
/*    */     //   1617: putstatic f/h1.ru0 : Z
/*    */     //   1620: getstatic f/UB0.M60 : Lf/w70;
/*    */     //   1623: getfield AW : Lf/MJ0;
/*    */     //   1626: getfield oA0 : Lf/fa;
/*    */     //   1629: iload #5
/*    */     //   1631: putfield fn0 : Z
/*    */     //   1634: invokestatic glfwSwapInterval : (I)V
/*    */     //   1637: aload_0
/*    */     //   1638: getfield RL0 : Lf/W1;
/*    */     //   1641: getfield Wa0 : Lf/A60;
/*    */     //   1644: getfield go : I
/*    */     //   1647: dup
/*    */     //   1648: istore #5
/*    */     //   1650: iconst_m1
/*    */     //   1651: if_icmple -> 1768
/*    */     //   1654: aload_0
/*    */     //   1655: getfield ej0 : Lf/OZ;
/*    */     //   1658: getfield Fj : Ljava/util/ArrayList;
/*    */     //   1661: iload #5
/*    */     //   1663: invokevirtual get : (I)Ljava/lang/Object;
/*    */     //   1666: checkcast java/lang/String
/*    */     //   1669: astore #5
/*    */     //   1671: getstatic f/Xv0.Kf0 : [Lf/Xv0;
/*    */     //   1674: dup
/*    */     //   1675: astore #7
/*    */     //   1677: arraylength
/*    */     //   1678: istore #8
/*    */     //   1680: iconst_0
/*    */     //   1681: istore #9
/*    */     //   1683: iload #9
/*    */     //   1685: iload #8
/*    */     //   1687: if_icmpge -> 1718
/*    */     //   1690: aload #7
/*    */     //   1692: iload #9
/*    */     //   1694: aaload
/*    */     //   1695: dup
/*    */     //   1696: astore #10
/*    */     //   1698: getfield w : Ljava/lang/String;
/*    */     //   1701: aload #5
/*    */     //   1703: invokevirtual equalsIgnoreCase : (Ljava/lang/String;)Z
/*    */     //   1706: ifeq -> 1712
/*    */     //   1709: goto -> 1723
/*    */     //   1712: iinc #9, 1
/*    */     //   1715: goto -> 1683
/*    */     //   1718: getstatic f/Xv0.eC0 : Lf/Xv0;
/*    */     //   1721: astore #10
/*    */     //   1723: aload #10
/*    */     //   1725: ifnull -> 1768
/*    */     //   1728: aload #10
/*    */     //   1730: getfield uz0 : Ljava/lang/String;
/*    */     //   1733: getstatic f/h1.qc : Ljava/lang/String;
/*    */     //   1736: invokevirtual equalsIgnoreCase : (Ljava/lang/String;)Z
/*    */     //   1739: ifne -> 1768
/*    */     //   1742: aload #10
/*    */     //   1744: getfield uz0 : Ljava/lang/String;
/*    */     //   1747: putstatic f/h1.qc : Ljava/lang/String;
/*    */     //   1750: iconst_1
/*    */     //   1751: putstatic f/h1.Bb : Z
/*    */     //   1754: getstatic f/km.u4 : Lf/R8;
/*    */     //   1757: dup
/*    */     //   1758: astore #5
/*    */     //   1760: ifnull -> 1768
/*    */     //   1763: aload #5
/*    */     //   1765: invokevirtual Dn : ()V
/*    */     //   1768: new java/util/HashSet
/*    */     //   1771: dup
/*    */     //   1772: astore #5
/*    */     //   1774: invokespecial <init> : ()V
/*    */     //   1777: iconst_0
/*    */     //   1778: istore #7
/*    */     //   1780: iload #7
/*    */     //   1782: aload_0
/*    */     //   1783: getfield II : [Lf/ge0;
/*    */     //   1786: dup
/*    */     //   1787: astore #8
/*    */     //   1789: arraylength
/*    */     //   1790: if_icmpge -> 1826
/*    */     //   1793: aload #8
/*    */     //   1795: iload #7
/*    */     //   1797: aaload
/*    */     //   1798: getfield TG0 : Lf/protected;
/*    */     //   1801: invokevirtual nm0 : ()Z
/*    */     //   1804: ifne -> 1820
/*    */     //   1807: aload #5
/*    */     //   1809: iload #7
/*    */     //   1811: i2b
/*    */     //   1812: iconst_1
/*    */     //   1813: invokestatic tE : (BZ)Lf/Xv0;
/*    */     //   1816: invokevirtual add : (Ljava/lang/Object;)Z
/*    */     //   1819: pop
/*    */     //   1820: iinc #7, 1
/*    */     //   1823: goto -> 1780
/*    */     //   1826: aload #5
/*    */     //   1828: invokestatic tz : (Ljava/util/HashSet;)Z
/*    */     //   1831: ifeq -> 1848
/*    */     //   1834: getstatic f/km.u4 : Lf/R8;
/*    */     //   1837: dup
/*    */     //   1838: astore #5
/*    */     //   1840: ifnull -> 1848
/*    */     //   1843: aload #5
/*    */     //   1845: invokevirtual Dn : ()V
/*    */     //   1848: aload_0
/*    */     //   1849: getfield g50 : Lf/W1;
/*    */     //   1852: getfield Wa0 : Lf/A60;
/*    */     //   1855: getfield go : I
/*    */     //   1858: dup
/*    */     //   1859: istore #5
/*    */     //   1861: iconst_m1
/*    */     //   1862: if_icmple -> 1870
/*    */     //   1865: iload #5
/*    */     //   1867: putstatic f/h1.f0 : I
/*    */     //   1870: aload_0
/*    */     //   1871: getfield qU : Z
/*    */     //   1874: ifeq -> 1997
/*    */     //   1877: getstatic f/km.u4 : Lf/R8;
/*    */     //   1880: ifnull -> 1997
/*    */     //   1883: aload_0
/*    */     //   1884: getfield lJ : Lf/aM;
/*    */     //   1887: invokevirtual OH0 : ()I
/*    */     //   1890: iconst_0
/*    */     //   1891: ior
/*    */     //   1892: aload_0
/*    */     //   1893: getfield Ij : Lf/aM;
/*    */     //   1896: invokevirtual OH0 : ()I
/*    */     //   1899: ior
/*    */     //   1900: aload_0
/*    */     //   1901: getfield NY : Lf/aM;
/*    */     //   1904: invokevirtual OH0 : ()I
/*    */     //   1907: ior
/*    */     //   1908: aload_0
/*    */     //   1909: getfield UH : Lf/aM;
/*    */     //   1912: invokevirtual OH0 : ()I
/*    */     //   1915: ior
/*    */     //   1916: aload_0
/*    */     //   1917: getfield aY : Lf/aM;
/*    */     //   1920: invokevirtual OH0 : ()I
/*    */     //   1923: ior
/*    */     //   1924: aload_0
/*    */     //   1925: getfield To : Lf/aM;
/*    */     //   1928: invokevirtual OH0 : ()I
/*    */     //   1931: ior
/*    */     //   1932: istore #5
/*    */     //   1934: getstatic f/km.u4 : Lf/R8;
/*    */     //   1937: dup
/*    */     //   1938: astore #7
/*    */     //   1940: getfield Lz : Lf/fH0;
/*    */     //   1943: dup
/*    */     //   1944: astore #8
/*    */     //   1946: ifnonnull -> 1952
/*    */     //   1949: goto -> 1997
/*    */     //   1952: aload #8
/*    */     //   1954: iconst_0
/*    */     //   1955: istore #9
/*    */     //   1957: getfield fz : I
/*    */     //   1960: iload #5
/*    */     //   1962: if_icmpeq -> 1975
/*    */     //   1965: aload #8
/*    */     //   1967: iload #5
/*    */     //   1969: putfield fz : I
/*    */     //   1972: iconst_1
/*    */     //   1973: istore #9
/*    */     //   1975: iload #9
/*    */     //   1977: ifeq -> 1997
/*    */     //   1980: aload #7
/*    */     //   1982: getfield e20 : Lf/c4;
/*    */     //   1985: new f/s50
/*    */     //   1988: dup
/*    */     //   1989: iload #5
/*    */     //   1991: invokespecial <init> : (I)V
/*    */     //   1994: invokevirtual W3 : (Lf/Bi;)V
/*    */     //   1997: getstatic f/js.vu0 : Lf/js;
/*    */     //   2000: getfield MH0 : Lf/pA;
/*    */     //   2003: dup
/*    */     //   2004: astore #5
/*    */     //   2006: ifnull -> 2032
/*    */     //   2009: aload #5
/*    */     //   2011: getfield TF : Lf/wu;
/*    */     //   2014: dup
/*    */     //   2015: astore #5
/*    */     //   2017: ifnull -> 2032
/*    */     //   2020: aload #5
/*    */     //   2022: dup
/*    */     //   2023: getstatic f/h1.JF : Z
/*    */     //   2026: invokevirtual Ui0 : (Z)V
/*    */     //   2029: invokevirtual jw : ()V
/*    */     //   2032: aload_0
/*    */     //   2033: getstatic f/h1.MW : Ljava/lang/String;
/*    */     //   2036: astore #5
/*    */     //   2038: getfield n00 : Lf/W1;
/*    */     //   2041: getfield Wa0 : Lf/A60;
/*    */     //   2044: getfield go : I
/*    */     //   2047: dup
/*    */     //   2048: istore #7
/*    */     //   2050: iconst_m1
/*    */     //   2051: if_icmple -> 2110
/*    */     //   2054: aload #5
/*    */     //   2056: aload_0
/*    */     //   2057: getfield Wp0 : Lf/OZ;
/*    */     //   2060: getfield Fj : Ljava/util/ArrayList;
/*    */     //   2063: iload #7
/*    */     //   2065: invokevirtual get : (I)Ljava/lang/Object;
/*    */     //   2068: checkcast java/lang/String
/*    */     //   2071: invokevirtual equalsIgnoreCase : (Ljava/lang/String;)Z
/*    */     //   2074: ifne -> 2110
/*    */     //   2077: aload_0
/*    */     //   2078: getfield Wp0 : Lf/OZ;
/*    */     //   2081: aload_0
/*    */     //   2082: getfield n00 : Lf/W1;
/*    */     //   2085: getfield Wa0 : Lf/A60;
/*    */     //   2088: getfield go : I
/*    */     //   2091: istore_1
/*    */     //   2092: getfield Fj : Ljava/util/ArrayList;
/*    */     //   2095: iload_1
/*    */     //   2096: invokevirtual get : (I)Ljava/lang/Object;
/*    */     //   2099: checkcast java/lang/String
/*    */     //   2102: putstatic f/h1.MW : Ljava/lang/String;
/*    */     //   2105: iconst_1
/*    */     //   2106: istore #6
/*    */     //   2108: iconst_1
/*    */     //   2109: istore_1
/*    */     //   2110: aload_0
/*    */     //   2111: getfield Mb : Lf/rI0;
/*    */     //   2114: getfield Wa0 : Lf/A60;
/*    */     //   2117: getfield go : I
/*    */     //   2120: dup
/*    */     //   2121: istore #7
/*    */     //   2123: iconst_m1
/*    */     //   2124: if_icmple -> 2157
/*    */     //   2127: getstatic f/h1.zA0 : F
/*    */     //   2130: aload_0
/*    */     //   2131: getfield E10 : Lf/OZ;
/*    */     //   2134: getfield Fj : Ljava/util/ArrayList;
/*    */     //   2137: iload #7
/*    */     //   2139: invokevirtual get : (I)Ljava/lang/Object;
/*    */     //   2142: checkcast java/lang/Float
/*    */     //   2145: invokevirtual floatValue : ()F
/*    */     //   2148: fconst_1
/*    */     //   2149: swap
/*    */     //   2150: fdiv
/*    */     //   2151: invokestatic JC0 : (FF)Z
/*    */     //   2154: ifeq -> 2170
/*    */     //   2157: getstatic f/h1.ho : Z
/*    */     //   2160: aload_0
/*    */     //   2161: getfield cz : Lf/FL;
/*    */     //   2164: invokevirtual Fk0 : ()Z
/*    */     //   2167: if_icmpeq -> 2237
/*    */     //   2170: aload_0
/*    */     //   2171: dup
/*    */     //   2172: getfield E10 : Lf/OZ;
/*    */     //   2175: aload_0
/*    */     //   2176: getfield Mb : Lf/rI0;
/*    */     //   2179: getfield Wa0 : Lf/A60;
/*    */     //   2182: getfield go : I
/*    */     //   2185: istore #6
/*    */     //   2187: getfield Fj : Ljava/util/ArrayList;
/*    */     //   2190: iload #6
/*    */     //   2192: invokevirtual get : (I)Ljava/lang/Object;
/*    */     //   2195: checkcast java/lang/Float
/*    */     //   2198: invokevirtual floatValue : ()F
/*    */     //   2201: fconst_1
/*    */     //   2202: swap
/*    */     //   2203: fdiv
/*    */     //   2204: putstatic f/h1.zA0 : F
/*    */     //   2207: getfield cz : Lf/FL;
/*    */     //   2210: invokevirtual Fk0 : ()Z
/*    */     //   2213: putstatic f/h1.ho : Z
/*    */     //   2216: iconst_1
/*    */     //   2217: istore #6
/*    */     //   2219: getstatic f/km.wI0 : Lf/Pw;
/*    */     //   2222: getstatic f/UB0.M60 : Lf/w70;
/*    */     //   2225: invokevirtual fG0 : ()I
/*    */     //   2228: getstatic f/UB0.M60 : Lf/w70;
/*    */     //   2231: invokevirtual dL : ()I
/*    */     //   2234: invokevirtual c0 : (II)V
/*    */     //   2237: iload #4
/*    */     //   2239: ifne -> 2246
/*    */     //   2242: iload_3
/*    */     //   2243: ifeq -> 2264
/*    */     //   2246: getstatic f/km.wI0 : Lf/Pw;
/*    */     //   2249: getstatic f/UB0.M60 : Lf/w70;
/*    */     //   2252: invokevirtual fG0 : ()I
/*    */     //   2255: getstatic f/UB0.M60 : Lf/w70;
/*    */     //   2258: invokevirtual dL : ()I
/*    */     //   2261: invokevirtual c0 : (II)V
/*    */     //   2264: aload_0
/*    */     //   2265: getfield pD : Lf/FL;
/*    */     //   2268: invokevirtual Fk0 : ()Z
/*    */     //   2271: getstatic f/h1.VV : Z
/*    */     //   2274: if_icmpeq -> 2300
/*    */     //   2277: aload_0
/*    */     //   2278: dup
/*    */     //   2279: getfield pD : Lf/FL;
/*    */     //   2282: invokevirtual Fk0 : ()Z
/*    */     //   2285: putstatic f/h1.VV : Z
/*    */     //   2288: getfield pD : Lf/FL;
/*    */     //   2291: invokevirtual Fk0 : ()Z
/*    */     //   2294: putstatic f/t90.w40 : Z
/*    */     //   2297: iconst_1
/*    */     //   2298: istore #6
/*    */     //   2300: aload #5
/*    */     //   2302: aload_0
/*    */     //   2303: getfield Vx0 : Lf/FL;
/*    */     //   2306: invokevirtual Fk0 : ()Z
/*    */     //   2309: putstatic f/h1.PF0 : Z
/*    */     //   2312: ldc_w 'android'
/*    */     //   2315: invokevirtual equals : (Ljava/lang/Object;)Z
/*    */     //   2318: getstatic f/h1.MW : Ljava/lang/String;
/*    */     //   2321: ldc_w 'android'
/*    */     //   2324: invokevirtual equals : (Ljava/lang/Object;)Z
/*    */     //   2327: if_icmpeq -> 2400
/*    */     //   2330: iconst_0
/*    */     //   2331: putstatic f/h1.mD0 : Z
/*    */     //   2334: iconst_0
/*    */     //   2335: putstatic f/h1.JF : Z
/*    */     //   2338: iconst_0
/*    */     //   2339: putstatic f/h1.S9 : I
/*    */     //   2342: iconst_0
/*    */     //   2343: putstatic f/h1.Ba0 : I
/*    */     //   2346: sipush #400
/*    */     //   2349: putstatic f/h1.Ke0 : I
/*    */     //   2352: sipush #200
/*    */     //   2355: putstatic f/h1.CR : I
/*    */     //   2358: sipush #250
/*    */     //   2361: putstatic f/h1.mG : I
/*    */     //   2364: iconst_0
/*    */     //   2365: putstatic f/h1.yc : I
/*    */     //   2368: invokestatic Td : ()Z
/*    */     //   2371: pop
/*    */     //   2372: getstatic f/km.f70 : Lf/k7;
/*    */     //   2375: sipush #1200
/*    */     //   2378: invokestatic OH0 : (I)Ljava/lang/String;
/*    */     //   2381: sipush #1179
/*    */     //   2384: invokestatic OH0 : (I)Ljava/lang/String;
/*    */     //   2387: getstatic f/LP.fw : Lf/LP;
/*    */     //   2390: <illegal opcode> run : ()Ljava/lang/Runnable;
/*    */     //   2395: iconst_0
/*    */     //   2396: invokevirtual iJ0 : (Ljava/lang/String;Ljava/lang/String;Lf/LP;Ljava/lang/Runnable;Z)V
/*    */     //   2399: return
/*    */     //   2400: iload #6
/*    */     //   2402: ifeq -> 2409
/*    */     //   2405: invokestatic Zy : ()Ljava/lang/Exception;
/*    */     //   2408: pop
/*    */     //   2409: iload_1
/*    */     //   2410: ifeq -> 2427
/*    */     //   2413: getstatic f/js.vu0 : Lf/js;
/*    */     //   2416: sipush #1375
/*    */     //   2419: invokestatic OH0 : (I)Ljava/lang/String;
/*    */     //   2422: iconst_m1
/*    */     //   2423: swap
/*    */     //   2424: invokevirtual Pu : (ILjava/lang/String;)V
/*    */     //   2427: getstatic f/UB0.Kg0 : Lf/Q50;
/*    */     //   2430: getstatic f/km.iE0 : Lf/r9;
/*    */     //   2433: dup
/*    */     //   2434: invokevirtual getClass : ()Ljava/lang/Class;
/*    */     //   2437: pop
/*    */     //   2438: <illegal opcode> run : (Lf/P2;)Ljava/lang/Runnable;
/*    */     //   2443: invokevirtual fN : (Ljava/lang/Runnable;)V
/*    */     //   2446: getstatic f/km.iE0 : Lf/r9;
/*    */     //   2449: invokevirtual Hf0 : ()V
/*    */     //   2452: invokestatic Td : ()Z
/*    */     //   2455: ifne -> 2477
/*    */     //   2458: getstatic f/js.vu0 : Lf/js;
/*    */     //   2461: dup
/*    */     //   2462: astore_0
/*    */     //   2463: ifnull -> 2477
/*    */     //   2466: aload_0
/*    */     //   2467: bipush #87
/*    */     //   2469: invokestatic OH0 : (I)Ljava/lang/String;
/*    */     //   2472: iconst_m1
/*    */     //   2473: swap
/*    */     //   2474: invokevirtual Pu : (ILjava/lang/String;)V
/*    */     //   2477: aload_2
/*    */     //   2478: invokevirtual isEmpty : ()Z
/*    */     //   2481: ifne -> 2501
/*    */     //   2484: getstatic f/km.Gj : Lf/af;
/*    */     //   2487: iconst_1
/*    */     //   2488: anewarray java/lang/String
/*    */     //   2491: dup
/*    */     //   2492: astore_0
/*    */     //   2493: iconst_0
/*    */     //   2494: aload_2
/*    */     //   2495: aastore
/*    */     //   2496: iconst_1
/*    */     //   2497: aload_0
/*    */     //   2498: invokevirtual lPt2 : (Z[Ljava/lang/String;)V
/*    */     //   2501: return
/*    */     // Line number table:
/*    */     //   Java source line number -> byte code offset
/*    */     //   #1	-> 23
/*    */     //   #2	-> 26
/*    */     //   #3	-> 47
/*    */     //   #4	-> 70
/*    */     //   #5	-> 79
/*    */     //   #6	-> 85
/*    */     //   #7	-> 95
/*    */     //   #8	-> 115
/*    */     //   #9	-> 138
/*    */     //   #10	-> 142
/*    */     //   #11	-> 150
/*    */     //   #12	-> 183
/*    */     //   #13	-> 186
/*    */     //   #14	-> 210
/*    */     //   #15	-> 213
/*    */     //   #16	-> 223
/*    */     //   #17	-> 226
/*    */     //   #18	-> 230
/*    */     //   #19	-> 233
/*    */     //   #20	-> 245
/*    */     //   #21	-> 248
/*    */     //   #22	-> 253
/*    */     //   #23	-> 264
/*    */     //   #24	-> 267
/*    */     //   #25	-> 273
/*    */     //   #26	-> 277
/*    */     //   #27	-> 289
/*    */     //   #28	-> 297
/*    */     //   #29	-> 394
/*    */     //   #30	-> 402
/*    */     //   #31	-> 415
/*    */     //   #32	-> 518
/*    */     //   #33	-> 521
/*    */     //   #34	-> 547
/*    */     //   #35	-> 551
/*    */     //   #36	-> 559
/*    */     //   #37	-> 564
/*    */     //   #38	-> 571
/*    */     //   #39	-> 574
/*    */     //   #40	-> 577
/*    */     //   #41	-> 580
/*    */     //   #42	-> 586
/*    */     //   #43	-> 589
/*    */     //   #44	-> 592
/*    */     //   #45	-> 616
/*    */     //   #46	-> 619
/*    */     //   #47	-> 630
/*    */     //   #48	-> 633
/*    */     //   #49	-> 638
/*    */     //   #50	-> 641
/*    */     //   #51	-> 654
/*    */     //   #52	-> 657
/*    */     //   #53	-> 668
/*    */     //   #54	-> 671
/*    */     //   #55	-> 676
/*    */     //   #56	-> 679
/*    */     //   #57	-> 721
/*    */     //   #58	-> 732
/*    */     //   #59	-> 739
/*    */     //   #60	-> 742
/*    */     //   #61	-> 753
/*    */     //   #62	-> 756
/*    */     //   #63	-> 761
/*    */     //   #64	-> 764
/*    */     //   #65	-> 787
/*    */     //   #66	-> 790
/*    */     //   #67	-> 795
/*    */     //   #68	-> 800
/*    */     //   #69	-> 803
/*    */     //   #70	-> 816
/*    */     //   #71	-> 819
/*    */     //   #72	-> 848
/*    */     //   #73	-> 883
/*    */     //   #74	-> 907
/*    */     //   #75	-> 936
/*    */     //   #76	-> 950
/*    */     //   #77	-> 959
/*    */     //   #78	-> 987
/*    */     //   #79	-> 990
/*    */     //   #80	-> 993
/*    */     //   #81	-> 1034
/*    */     //   #82	-> 1037
/*    */     //   #83	-> 1040
/*    */     //   #84	-> 1045
/*    */     //   #85	-> 1048
/*    */     //   #86	-> 1059
/*    */     //   #87	-> 1073
/*    */     //   #88	-> 1079
/*    */     //   #89	-> 1092
/*    */     //   #90	-> 1098
/*    */     //   #91	-> 1157
/*    */     //   #92	-> 1162
/*    */     //   #93	-> 1165
/*    */     //   #94	-> 1170
/*    */     //   #95	-> 1183
/*    */     //   #96	-> 1200
/*    */     //   #97	-> 1203
/*    */     //   #98	-> 1206
/*    */     //   #99	-> 1212
/*    */     //   #100	-> 1215
/*    */     //   #101	-> 1221
/*    */     //   #102	-> 1224
/*    */     //   #103	-> 1239
/*    */     //   #104	-> 1247
/*    */     //   #105	-> 1262
/*    */     //   #106	-> 1265
/*    */     //   #107	-> 1289
/*    */     //   #108	-> 1292
/*    */     //   #109	-> 1295
/*    */     //   #110	-> 1368
/*    */     //   #111	-> 1371
/*    */     //   #112	-> 1374
/*    */     //   #113	-> 1380
/*    */     //   #114	-> 1383
/*    */     //   #115	-> 1386
/*    */     //   #116	-> 1392
/*    */     //   #117	-> 1395
/*    */     //   #118	-> 1401
/*    */     //   #119	-> 1404
/*    */     //   #120	-> 1463
/*    */     //   #121	-> 1466
/*    */     //   #122	-> 1477
/*    */     //   #123	-> 1500
/*    */     //   #124	-> 1505
/*    */     //   #125	-> 1561
/*    */     //   #126	-> 1564
/*    */     //   #127	-> 1574
/*    */     //   #128	-> 1623
/*    */     //   #129	-> 1626
/*    */     //   #130	-> 1631
/*    */     //   #131	-> 1638
/*    */     //   #132	-> 1641
/*    */     //   #133	-> 1644
/*    */     //   #134	-> 1655
/*    */     //   #135	-> 1658
/*    */     //   #136	-> 1663
/*    */     //   #137	-> 1666
/*    */     //   #138	-> 1671
/*    */     //   #139	-> 1730
/*    */     //   #140	-> 1733
/*    */     //   #141	-> 1744
/*    */     //   #142	-> 1747
/*    */     //   #143	-> 1798
/*    */     //   #144	-> 1801
/*    */     //   #145	-> 1813
/*    */     //   #146	-> 1852
/*    */     //   #147	-> 1855
/*    */     //   #148	-> 1867
/*    */     //   #149	-> 1940
/*    */     //   #150	-> 1957
/*    */     //   #151	-> 1969
/*    */     //   #152	-> 1982
/*    */     //   #153	-> 1997
/*    */     //   #154	-> 2000
/*    */     //   #155	-> 2011
/*    */     //   #156	-> 2023
/*    */     //   #157	-> 2041
/*    */     //   #158	-> 2044
/*    */     //   #159	-> 2057
/*    */     //   #160	-> 2060
/*    */     //   #161	-> 2065
/*    */     //   #162	-> 2068
/*    */     //   #163	-> 2085
/*    */     //   #164	-> 2088
/*    */     //   #165	-> 2092
/*    */     //   #166	-> 2096
/*    */     //   #167	-> 2099
/*    */     //   #168	-> 2114
/*    */     //   #169	-> 2117
/*    */     //   #170	-> 2127
/*    */     //   #171	-> 2134
/*    */     //   #172	-> 2139
/*    */     //   #173	-> 2142
/*    */     //   #174	-> 2179
/*    */     //   #175	-> 2182
/*    */     //   #176	-> 2187
/*    */     //   #177	-> 2192
/*    */     //   #178	-> 2195
/*    */     //   #179	-> 2331
/*    */     //   #180	-> 2368
/*    */     //   #181	-> 2396
/*    */     //   #182	-> 2405
/*    */     //   #183	-> 2413
/*    */     //   #184	-> 2419
/*    */     //   #185	-> 2424
/*    */     //   #186	-> 2427
/*    */     //   #187	-> 2458
/*    */     //   #188	-> 2469
/*    */     //   #189	-> 2474
/*    */     //   #190	-> 2478
/*    */   }
/*    */   
/*    */   public final void d40() {
/*    */     if (this.fr0 == null)
/*    */       return; 
/*    */     if (km.XU()) {
/*    */       Tm(km.wI0.dG(), km.wI0.k1());
/*    */       super.d40();
/*    */       this.Ki.mM();
/*    */       this.Ki.QJ0(et.t9, -68, 0);
/*    */       return;
/*    */     } 
/*    */     mM();
/*    */     this.oB.mM();
/*    */     this.ux.mM();
/*    */     this.F70.mM();
/*    */     this.H7.mM();
/*    */     this.pRN.mM();
/*    */     this.Xt.mM();
/*    */     super.d40();
/*    */   }
/*    */   
/*    */   public final void IG0() {
/*    */     VA0.c90(this);
/*    */   }
/*    */   
/*    */   public final boolean i2(oa0 paramoa0) {
/*    */     if (B8.Wm0(paramoa0.cz0) && paramoa0.oO()) {
/*    */       if (js.com3(this))
/*    */         return super.i2(paramoa0); 
/*    */       if (h1.J20(paramoa0.GG0, BM.lc)) {
/*    */         close();
/*    */         return true;
/*    */       } 
/*    */     } 
/*    */     return super.i2(paramoa0);
/*    */   } }


/* Location:              /Users/vnnsnnt/Documents/Codespace/JavaWorkspace/RedTrainer/src/main/java/org/trainer/client/PokeMMO.jar!/f/v10.class
 * Java compiler version: 17 (61.0)
 * JD-Core Version:       1.1.3
 */