/* 1 */ package f;public final class Vb extends GS implements Np0 { private void uR(hm0 paramhm0, kf paramkf) { paramhm0.tx(this.fX); this(paramhm0, paramkf.oD(paramhm0)); Ke0 ke0; paramkf.YP.add(this); }
/*   */ 
/*   */   
/*   */   public final short ee0;
/*   */   public final short fX;
/*   */   
/*   */   public Vb(short paramShort1, short paramShort2) {
/*   */     this.fX = paramShort1;
/*   */     this.ee0 = paramShort2;
/*   */   }
/*   */   
/*   */   public final byte YG0() {
/*   */     return 83;
/*   */   }
/*   */   
/*   */   public final void Nl(hm0 paramhm01, hm0 paramhm02, boolean paramBoolean1, boolean paramBoolean2, short paramShort, boolean paramBoolean3, kf paramkf, b60 paramb60) {
/*   */     // Byte code:
/*   */     //   0: aload #7
/*   */     //   2: aload_0
/*   */     //   3: aload_1
/*   */     //   4: aload #7
/*   */     //   6: dup
/*   */     //   7: getstatic f/Of.eH : Lf/Of;
/*   */     //   10: aload_0
/*   */     //   11: getfield ee0 : S
/*   */     //   14: invokevirtual On0 : (S)Lf/LPT3;
/*   */     //   17: astore_0
/*   */     //   18: getstatic f/F40.ef0 : Lf/F40;
/*   */     //   21: astore_2
/*   */     //   22: bipush #14
/*   */     //   24: istore_3
/*   */     //   25: getfield AD : Lf/Gp0;
/*   */     //   28: sipush #914
/*   */     //   31: aload_1
/*   */     //   32: invokevirtual ex : (ILf/hm0;)I
/*   */     //   35: istore #4
/*   */     //   37: iconst_2
/*   */     //   38: anewarray java/lang/String
/*   */     //   41: dup
/*   */     //   42: dup
/*   */     //   43: astore #5
/*   */     //   45: aload_1
/*   */     //   46: invokevirtual fA : ()Ljava/lang/String;
/*   */     //   49: iconst_0
/*   */     //   50: swap
/*   */     //   51: aastore
/*   */     //   52: iconst_1
/*   */     //   53: aload_0
/*   */     //   54: getfield Iu : I
/*   */     //   57: invokestatic OH0 : (I)Ljava/lang/String;
/*   */     //   60: aastore
/*   */     //   61: iconst_2
/*   */     //   62: aload_2
/*   */     //   63: iload_3
/*   */     //   64: iload #4
/*   */     //   66: aload #5
/*   */     //   68: invokestatic lz : (BLf/F40;II[Ljava/lang/String;)Ljava/lang/String;
/*   */     //   71: astore_0
/*   */     //   72: <illegal opcode> run : (Lf/Vb;Lf/hm0;Lf/kf;)Ljava/lang/Runnable;
/*   */     //   77: astore_1
/*   */     //   78: aload_0
/*   */     //   79: ldc ''
/*   */     //   81: aload_1
/*   */     //   82: invokevirtual r00 : (Ljava/lang/String;Ljava/lang/String;Ljava/lang/Runnable;)V
/*   */     //   85: return
/*   */     // Line number table:
/*   */     //   Java source line number -> byte code offset
/*   */     //   #1	-> 7
/*   */     //   #2	-> 11
/*   */     //   #3	-> 25
/*   */     //   #4	-> 32
/*   */     //   #5	-> 54
/*   */     //   #6	-> 60
/*   */     //   #7	-> 68
/*   */     //   #8	-> 72
/*   */   } }


/* Location:              /Users/vnnsnnt/Documents/Codespace/JavaWorkspace/RedTrainer/src/main/java/org/trainer/client/PokeMMO.jar!/f/Vb.class
 * Java compiler version: 8 (52.0)
 * JD-Core Version:       1.1.3
 */