/*  1 */ package f;public final class ve extends kD0 implements r60 { public static final DecimalFormat IR = new DecimalFormat("#0.00"); public static final SimpleDateFormat fC0 = new SimpleDateFormat("dd/MM/yyyy hh:mm a z"); public final pA jf; public Vq0 zH0; public rS Oo; public Df[] Xg; public ArrayList IC; public of l5; public byte La0; public Un DY; public Un Bm; public dQ Zj0; public rS bF; public Un[] A90; public Uy0 g0; public Vq0 p10; public Ip Ic0; public rS EP; public dQ SF0; public W1 e20; private void AK() { Df[] arrayOfDf; int i; byte b; for (i = (arrayOfDf = this.Xg).length, b = 0; b < i; ) { (arrayOfDf[b]).cOM7
/*  2 */         .E1(""); (arrayOfDf[b]).lPt8 = false; arrayOfDf[b].ZA();
/*  3 */       (arrayOfDf[b]).XC0.TS
/*  4 */         .VL0 = false;
/*  5 */       (arrayOfDf[b]).ap.E1(""); (arrayOfDf[b]).K8.s6(Ml0.OH0(5515)); b++; }
/*  6 */      km.u4
/*  7 */       .e20
/*  8 */       .W3(new Sc());
/*  9 */     this.gp = false; this.aF = true; this.Bm.s6(Ml0.OH0(65)); this.Bm.sk0(false); } public DK Bg; public W1 Lj0; public iB[] tj; public boolean gp; public boolean aF; public DK[] BB; public int WL; public final CC0[] dp; public final yX[] Vf0; public DO[] OI0; public boolean Oh0; public qa0[] TC; public int MQ; public int EC; public Un[][] iE; public final int Pk0; public Comparator jZ; public oo nl0; public final ArrayList El; public e2 Di; public ve(pA parampA, boolean paramBoolean, qa0[] paramArrayOfqa0, yX[] paramArrayOfyX, Ad[] paramArrayOfAd, int paramInt) { // Byte code:
/*    */     //   0: iload_2
/*    */     //   1: aload_0
/*    */     //   2: dup
/*    */     //   3: iload #6
/*    */     //   5: aload_0
/*    */     //   6: aload #4
/*    */     //   8: aload_0
/*    */     //   9: aload_3
/*    */     //   10: aload_0
/*    */     //   11: iload_2
/*    */     //   12: aload_0
/*    */     //   13: dup
/*    */     //   14: dup
/*    */     //   15: aload_1
/*    */     //   16: aload_0
/*    */     //   17: dup
/*    */     //   18: dup
/*    */     //   19: dup2
/*    */     //   20: dup2
/*    */     //   21: dup2
/*    */     //   22: dup2
/*    */     //   23: dup2
/*    */     //   24: dup2
/*    */     //   25: dup2
/*    */     //   26: invokestatic XU : ()Z
/*    */     //   29: ldc 'matchmakingframe'
/*    */     //   31: swap
/*    */     //   32: invokespecial <init> : (Ljava/lang/String;Z)V
/*    */     //   35: new java/util/ArrayList
/*    */     //   38: dup
/*    */     //   39: invokespecial <init> : ()V
/*    */     //   42: putfield IC : Ljava/util/ArrayList;
/*    */     //   45: new f/of
/*    */     //   48: dup
/*    */     //   49: invokespecial <init> : ()V
/*    */     //   52: putfield l5 : Lf/of;
/*    */     //   55: iconst_0
/*    */     //   56: putfield La0 : B
/*    */     //   59: aconst_null
/*    */     //   60: putfield Bg : Lf/DK;
/*    */     //   63: bipush #6
/*    */     //   65: anewarray f/iB
/*    */     //   68: putfield tj : [Lf/iB;
/*    */     //   71: iconst_0
/*    */     //   72: putfield gp : Z
/*    */     //   75: iconst_0
/*    */     //   76: putfield aF : Z
/*    */     //   79: aconst_null
/*    */     //   80: putfield BB : [Lf/DK;
/*    */     //   83: iconst_m1
/*    */     //   84: putfield WL : I
/*    */     //   87: getstatic f/CC0.Se0 : [Lf/CC0;
/*    */     //   90: putfield dp : [Lf/CC0;
/*    */     //   93: getstatic f/DO.LM : [Lf/DO;
/*    */     //   96: putfield OI0 : [Lf/DO;
/*    */     //   99: iconst_0
/*    */     //   100: putfield MQ : I
/*    */     //   103: iconst_0
/*    */     //   104: putfield EC : I
/*    */     //   107: getstatic f/HS.hp : Ljava/util/Comparator;
/*    */     //   110: putfield jZ : Ljava/util/Comparator;
/*    */     //   113: aconst_null
/*    */     //   114: putfield nl0 : Lf/oo;
/*    */     //   117: new f/e2
/*    */     //   120: dup
/*    */     //   121: sipush #250
/*    */     //   124: invokespecial <init> : (I)V
/*    */     //   127: putfield Di : Lf/e2;
/*    */     //   130: putfield jf : Lf/pA;
/*    */     //   133: <illegal opcode> run : (Lf/ve;)Ljava/lang/Runnable;
/*    */     //   138: invokevirtual TG0 : (Ljava/lang/Runnable;)V
/*    */     //   141: putfield Oh0 : Z
/*    */     //   144: putfield TC : [Lf/qa0;
/*    */     //   147: putfield Vf0 : [Lf/yX;
/*    */     //   150: putfield Pk0 : I
/*    */     //   153: ldc 'UTC'
/*    */     //   155: invokestatic of : (Ljava/lang/String;)Ljava/time/ZoneId;
/*    */     //   158: invokestatic now : (Ljava/time/ZoneId;)Ljava/time/YearMonth;
/*    */     //   161: pop
/*    */     //   162: ldc 'matchmakingframe'
/*    */     //   164: invokevirtual Xu : (Ljava/lang/String;)V
/*    */     //   167: ifeq -> 183
/*    */     //   170: aload_0
/*    */     //   171: sipush #9150
/*    */     //   174: invokestatic OH0 : (I)Ljava/lang/String;
/*    */     //   177: invokevirtual Lo : (Ljava/lang/String;)V
/*    */     //   180: goto -> 193
/*    */     //   183: aload_0
/*    */     //   184: sipush #5500
/*    */     //   187: invokestatic OH0 : (I)Ljava/lang/String;
/*    */     //   190: invokevirtual Lo : (Ljava/lang/String;)V
/*    */     //   193: aload_0
/*    */     //   194: dup
/*    */     //   195: iconst_1
/*    */     //   196: invokevirtual EP : (I)V
/*    */     //   199: new f/Vq0
/*    */     //   202: dup
/*    */     //   203: invokespecial <init> : ()V
/*    */     //   206: putfield zH0 : Lf/Vq0;
/*    */     //   209: new f/Ip
/*    */     //   212: dup
/*    */     //   213: dup
/*    */     //   214: astore_1
/*    */     //   215: aload_0
/*    */     //   216: aload_1
/*    */     //   217: invokespecial <init> : ()V
/*    */     //   220: new f/rS
/*    */     //   223: dup
/*    */     //   224: invokespecial <init> : ()V
/*    */     //   227: putfield Oo : Lf/rS;
/*    */     //   230: invokevirtual mE0 : ()Lf/g0;
/*    */     //   233: astore_3
/*    */     //   234: invokevirtual d7 : ()Lf/cr0;
/*    */     //   237: dup
/*    */     //   238: astore #6
/*    */     //   240: aload_0
/*    */     //   241: aload_3
/*    */     //   242: aload_0
/*    */     //   243: dup
/*    */     //   244: new f/Un
/*    */     //   247: dup
/*    */     //   248: astore #7
/*    */     //   250: aload_0
/*    */     //   251: dup
/*    */     //   252: aload #7
/*    */     //   254: dup
/*    */     //   255: sipush #5507
/*    */     //   258: invokestatic OH0 : (I)Ljava/lang/String;
/*    */     //   261: invokespecial <init> : (Ljava/lang/String;)V
/*    */     //   264: putfield DY : Lf/Un;
/*    */     //   267: <illegal opcode> run : (Lf/ve;)Ljava/lang/Runnable;
/*    */     //   272: invokevirtual tW : (Ljava/lang/Runnable;)V
/*    */     //   275: getfield DY : Lf/Un;
/*    */     //   278: ldc 'signup-button'
/*    */     //   280: invokevirtual Xu : (Ljava/lang/String;)V
/*    */     //   283: new f/dQ
/*    */     //   286: dup
/*    */     //   287: aload_0
/*    */     //   288: swap
/*    */     //   289: dup
/*    */     //   290: ldc_w ''
/*    */     //   293: invokespecial <init> : (Ljava/lang/String;)V
/*    */     //   296: putfield Zj0 : Lf/dQ;
/*    */     //   299: ldc_w 'label-time'
/*    */     //   302: invokevirtual Xu : (Ljava/lang/String;)V
/*    */     //   305: getfield Oo : Lf/rS;
/*    */     //   308: invokevirtual Ya : (Lf/JG0;)Lf/U90;
/*    */     //   311: pop
/*    */     //   312: getfield Oo : Lf/rS;
/*    */     //   315: invokevirtual Ya : (Lf/JG0;)Lf/U90;
/*    */     //   318: pop
/*    */     //   319: new java/util/ArrayList
/*    */     //   322: dup
/*    */     //   323: aload_0
/*    */     //   324: swap
/*    */     //   325: dup
/*    */     //   326: invokespecial <init> : ()V
/*    */     //   329: putfield El : Ljava/util/ArrayList;
/*    */     //   332: new f/Uh0
/*    */     //   335: dup
/*    */     //   336: aconst_null
/*    */     //   337: invokespecial <init> : (Lf/super;)V
/*    */     //   340: invokevirtual add : (Ljava/lang/Object;)Z
/*    */     //   343: pop
/*    */     //   344: getstatic f/km.u4 : Lf/R8;
/*    */     //   347: invokevirtual Um : ()Lf/g2;
/*    */     //   350: astore #7
/*    */     //   352: iconst_0
/*    */     //   353: istore #8
/*    */     //   355: iload #8
/*    */     //   357: getstatic f/km.u4 : Lf/R8;
/*    */     //   360: invokevirtual IQ : ()Lf/fH0;
/*    */     //   363: invokevirtual Sy0 : ()B
/*    */     //   366: invokestatic Gc : (B)B
/*    */     //   369: if_icmpge -> 415
/*    */     //   372: aload #7
/*    */     //   374: iload #8
/*    */     //   376: invokevirtual LPT5 : (B)Lf/super;
/*    */     //   379: dup
/*    */     //   380: astore #9
/*    */     //   382: invokevirtual com6 : ()Z
/*    */     //   385: ifeq -> 405
/*    */     //   388: aload_0
/*    */     //   389: getfield El : Ljava/util/ArrayList;
/*    */     //   392: new f/Uh0
/*    */     //   395: dup
/*    */     //   396: aload #9
/*    */     //   398: invokespecial <init> : (Lf/super;)V
/*    */     //   401: invokevirtual add : (Ljava/lang/Object;)Z
/*    */     //   404: pop
/*    */     //   405: iload #8
/*    */     //   407: iconst_1
/*    */     //   408: iadd
/*    */     //   409: i2b
/*    */     //   410: istore #8
/*    */     //   412: goto -> 355
/*    */     //   415: iload_2
/*    */     //   416: ifne -> 484
/*    */     //   419: aload_3
/*    */     //   420: aload_1
/*    */     //   421: aload #6
/*    */     //   423: aload_1
/*    */     //   424: iconst_2
/*    */     //   425: anewarray f/JG0
/*    */     //   428: dup
/*    */     //   429: dup
/*    */     //   430: aload_0
/*    */     //   431: swap
/*    */     //   432: aload_0
/*    */     //   433: getfield DY : Lf/Un;
/*    */     //   436: iconst_0
/*    */     //   437: swap
/*    */     //   438: aastore
/*    */     //   439: getfield Zj0 : Lf/dQ;
/*    */     //   442: iconst_1
/*    */     //   443: swap
/*    */     //   444: aastore
/*    */     //   445: invokevirtual AUX : ([Lf/JG0;)Lf/U90;
/*    */     //   448: invokevirtual ee0 : (Lf/U90;)Lf/U90;
/*    */     //   451: pop
/*    */     //   452: iconst_1
/*    */     //   453: anewarray f/JG0
/*    */     //   456: dup
/*    */     //   457: aload_0
/*    */     //   458: getfield Zj0 : Lf/dQ;
/*    */     //   461: iconst_0
/*    */     //   462: swap
/*    */     //   463: aastore
/*    */     //   464: invokevirtual vo0 : ([Lf/JG0;)Lf/U90;
/*    */     //   467: invokevirtual Em0 : ()Lf/U90;
/*    */     //   470: aload_0
/*    */     //   471: getfield DY : Lf/Un;
/*    */     //   474: invokevirtual Ya : (Lf/JG0;)Lf/U90;
/*    */     //   477: invokevirtual ee0 : (Lf/U90;)Lf/U90;
/*    */     //   480: pop
/*    */     //   481: goto -> 689
/*    */     //   484: aload_0
/*    */     //   485: new f/OZ
/*    */     //   488: dup
/*    */     //   489: astore #7
/*    */     //   491: aload_0
/*    */     //   492: getfield El : Ljava/util/ArrayList;
/*    */     //   495: invokespecial <init> : (Ljava/util/Collection;)V
/*    */     //   498: new f/W1
/*    */     //   501: dup
/*    */     //   502: aload_0
/*    */     //   503: swap
/*    */     //   504: dup
/*    */     //   505: aload #7
/*    */     //   507: invokespecial <init> : (Lf/cQ;)V
/*    */     //   510: putfield Lj0 : Lf/W1;
/*    */     //   513: ldc_w 'signup-combobox'
/*    */     //   516: invokevirtual Xu : (Ljava/lang/String;)V
/*    */     //   519: getfield El : Ljava/util/ArrayList;
/*    */     //   522: invokevirtual size : ()I
/*    */     //   525: iconst_1
/*    */     //   526: if_icmpgt -> 537
/*    */     //   529: aload_0
/*    */     //   530: getfield Lj0 : Lf/W1;
/*    */     //   533: iconst_0
/*    */     //   534: invokevirtual sk0 : (Z)V
/*    */     //   537: aload_0
/*    */     //   538: dup
/*    */     //   539: getfield Lj0 : Lf/W1;
/*    */     //   542: iconst_0
/*    */     //   543: invokevirtual Z30 : (I)V
/*    */     //   546: getfield Lj0 : Lf/W1;
/*    */     //   549: aload_0
/*    */     //   550: <illegal opcode> run : (Lf/ve;)Ljava/lang/Runnable;
/*    */     //   555: invokevirtual D30 : (Ljava/lang/Runnable;)V
/*    */     //   558: iconst_0
/*    */     //   559: istore #7
/*    */     //   561: iload #7
/*    */     //   563: aload_0
/*    */     //   564: getfield tj : [Lf/iB;
/*    */     //   567: dup
/*    */     //   568: astore #8
/*    */     //   570: arraylength
/*    */     //   571: if_icmpge -> 600
/*    */     //   574: iload #7
/*    */     //   576: aload #8
/*    */     //   578: iload #7
/*    */     //   580: new f/iB
/*    */     //   583: dup
/*    */     //   584: astore #7
/*    */     //   586: invokespecial <init> : ()V
/*    */     //   589: aload #7
/*    */     //   591: aastore
/*    */     //   592: iconst_1
/*    */     //   593: iadd
/*    */     //   594: i2b
/*    */     //   595: istore #7
/*    */     //   597: goto -> 561
/*    */     //   600: aload_3
/*    */     //   601: aload_1
/*    */     //   602: aload #6
/*    */     //   604: aload_1
/*    */     //   605: aload #6
/*    */     //   607: aload_0
/*    */     //   608: invokevirtual XJ0 : ()V
/*    */     //   611: iconst_1
/*    */     //   612: anewarray f/JG0
/*    */     //   615: dup
/*    */     //   616: aload_0
/*    */     //   617: getfield Lj0 : Lf/W1;
/*    */     //   620: iconst_0
/*    */     //   621: swap
/*    */     //   622: aastore
/*    */     //   623: invokevirtual Mg : ([Lf/JG0;)Lf/U90;
/*    */     //   626: pop
/*    */     //   627: invokevirtual mE0 : ()Lf/g0;
/*    */     //   630: aload_0
/*    */     //   631: getfield tj : [Lf/iB;
/*    */     //   634: invokevirtual Mg : ([Lf/JG0;)Lf/U90;
/*    */     //   637: invokevirtual ee0 : (Lf/U90;)Lf/U90;
/*    */     //   640: pop
/*    */     //   641: invokevirtual d7 : ()Lf/cr0;
/*    */     //   644: invokevirtual Em0 : ()Lf/U90;
/*    */     //   647: iconst_1
/*    */     //   648: anewarray f/JG0
/*    */     //   651: dup
/*    */     //   652: aload_0
/*    */     //   653: getfield Lj0 : Lf/W1;
/*    */     //   656: iconst_0
/*    */     //   657: swap
/*    */     //   658: aastore
/*    */     //   659: invokevirtual Mg : ([Lf/JG0;)Lf/U90;
/*    */     //   662: invokevirtual Em0 : ()Lf/U90;
/*    */     //   665: invokevirtual ee0 : (Lf/U90;)Lf/U90;
/*    */     //   668: aload_1
/*    */     //   669: invokevirtual d7 : ()Lf/cr0;
/*    */     //   672: invokevirtual Em0 : ()Lf/U90;
/*    */     //   675: aload_0
/*    */     //   676: getfield tj : [Lf/iB;
/*    */     //   679: invokevirtual Mg : ([Lf/JG0;)Lf/U90;
/*    */     //   682: invokevirtual Em0 : ()Lf/U90;
/*    */     //   685: invokevirtual ee0 : (Lf/U90;)Lf/U90;
/*    */     //   688: pop
/*    */     //   689: iload_2
/*    */     //   690: aload_0
/*    */     //   691: aload_1
/*    */     //   692: aload #6
/*    */     //   694: aload_1
/*    */     //   695: aload_3
/*    */     //   696: invokevirtual rK0 : (Lf/U90;)V
/*    */     //   699: invokevirtual WN : (Lf/U90;)V
/*    */     //   702: getfield zH0 : Lf/Vq0;
/*    */     //   705: aload_1
/*    */     //   706: sipush #5525
/*    */     //   709: invokestatic OH0 : (I)Ljava/lang/String;
/*    */     //   712: invokevirtual WS : (Lf/JG0;Ljava/lang/String;)Lf/Li0;
/*    */     //   715: pop
/*    */     //   716: new f/Ip
/*    */     //   719: dup
/*    */     //   720: astore_1
/*    */     //   721: invokespecial <init> : ()V
/*    */     //   724: new f/Ip
/*    */     //   727: dup
/*    */     //   728: astore_3
/*    */     //   729: invokespecial <init> : ()V
/*    */     //   732: new f/Ip
/*    */     //   735: dup
/*    */     //   736: astore #6
/*    */     //   738: invokespecial <init> : ()V
/*    */     //   741: ifne -> 1297
/*    */     //   744: aload_0
/*    */     //   745: dup
/*    */     //   746: getfield zH0 : Lf/Vq0;
/*    */     //   749: sipush #5651
/*    */     //   752: invokestatic OH0 : (I)Ljava/lang/String;
/*    */     //   755: astore #7
/*    */     //   757: new f/my
/*    */     //   760: dup
/*    */     //   761: aload #7
/*    */     //   763: swap
/*    */     //   764: aload #5
/*    */     //   766: aload_0
/*    */     //   767: getfield Pk0 : I
/*    */     //   770: invokespecial <init> : ([Lf/Ad;I)V
/*    */     //   773: invokevirtual WS : (Lf/JG0;Ljava/lang/String;)Lf/Li0;
/*    */     //   776: pop
/*    */     //   777: new f/Vq0
/*    */     //   780: dup
/*    */     //   781: aload_0
/*    */     //   782: swap
/*    */     //   783: dup
/*    */     //   784: invokespecial <init> : ()V
/*    */     //   787: putfield p10 : Lf/Vq0;
/*    */     //   790: ldc_w 'tier-tabbed-pane'
/*    */     //   793: invokevirtual Xu : (Ljava/lang/String;)V
/*    */     //   796: sipush #1127
/*    */     //   799: invokestatic OH0 : (I)Ljava/lang/String;
/*    */     //   802: astore #5
/*    */     //   804: getfield zH0 : Lf/Vq0;
/*    */     //   807: aload_0
/*    */     //   808: getfield p10 : Lf/Vq0;
/*    */     //   811: aload #5
/*    */     //   813: invokevirtual WS : (Lf/JG0;Ljava/lang/String;)Lf/Li0;
/*    */     //   816: pop
/*    */     //   817: new java/util/TreeMap
/*    */     //   820: dup
/*    */     //   821: astore #5
/*    */     //   823: invokespecial <init> : ()V
/*    */     //   826: new java/util/HashSet
/*    */     //   829: dup
/*    */     //   830: astore #7
/*    */     //   832: invokespecial <init> : ()V
/*    */     //   835: getstatic f/DK.gw : [Lf/DK;
/*    */     //   838: dup
/*    */     //   839: astore #8
/*    */     //   841: arraylength
/*    */     //   842: istore #9
/*    */     //   844: iconst_0
/*    */     //   845: istore #10
/*    */     //   847: iload #10
/*    */     //   849: iload #9
/*    */     //   851: if_icmpge -> 928
/*    */     //   854: aload #8
/*    */     //   856: iload #10
/*    */     //   858: aaload
/*    */     //   859: dup
/*    */     //   860: astore #11
/*    */     //   862: invokevirtual GH0 : ()Z
/*    */     //   865: ifeq -> 922
/*    */     //   868: aload #11
/*    */     //   870: invokevirtual uy : ()Z
/*    */     //   873: ifeq -> 922
/*    */     //   876: aload #7
/*    */     //   878: aload #11
/*    */     //   880: invokevirtual nr : ()I
/*    */     //   883: invokestatic valueOf : (I)Ljava/lang/Integer;
/*    */     //   886: invokevirtual contains : (Ljava/lang/Object;)Z
/*    */     //   889: ifne -> 922
/*    */     //   892: aload #7
/*    */     //   894: aload #11
/*    */     //   896: aload #5
/*    */     //   898: aload #11
/*    */     //   900: invokevirtual nr : ()I
/*    */     //   903: invokestatic valueOf : (I)Ljava/lang/Integer;
/*    */     //   906: aload #11
/*    */     //   908: invokevirtual put : (Ljava/lang/Object;Ljava/lang/Object;)Ljava/lang/Object;
/*    */     //   911: pop
/*    */     //   912: invokevirtual nr : ()I
/*    */     //   915: invokestatic valueOf : (I)Ljava/lang/Integer;
/*    */     //   918: invokevirtual add : (Ljava/lang/Object;)Z
/*    */     //   921: pop
/*    */     //   922: iinc #10, 1
/*    */     //   925: goto -> 847
/*    */     //   928: aload #5
/*    */     //   930: aconst_null
/*    */     //   931: astore #5
/*    */     //   933: invokevirtual values : ()Ljava/util/Collection;
/*    */     //   936: invokeinterface iterator : ()Ljava/util/Iterator;
/*    */     //   941: astore #7
/*    */     //   943: aload #7
/*    */     //   945: invokeinterface hasNext : ()Z
/*    */     //   950: ifeq -> 1026
/*    */     //   953: aload #7
/*    */     //   955: invokeinterface next : ()Ljava/lang/Object;
/*    */     //   960: checkcast f/DK
/*    */     //   963: dup
/*    */     //   964: astore #8
/*    */     //   966: invokevirtual GH0 : ()Z
/*    */     //   969: ifeq -> 943
/*    */     //   972: aload #8
/*    */     //   974: invokevirtual uy : ()Z
/*    */     //   977: ifeq -> 943
/*    */     //   980: aload #5
/*    */     //   982: aload_0
/*    */     //   983: getfield p10 : Lf/Vq0;
/*    */     //   986: aload #8
/*    */     //   988: invokestatic db : (Lf/DK;)Ljava/lang/String;
/*    */     //   991: new f/Ip
/*    */     //   994: dup
/*    */     //   995: invokespecial <init> : ()V
/*    */     //   998: invokevirtual MB : ()Lf/Ip;
/*    */     //   1001: swap
/*    */     //   1002: invokevirtual WS : (Lf/JG0;Ljava/lang/String;)Lf/Li0;
/*    */     //   1005: aload_0
/*    */     //   1006: aload #8
/*    */     //   1008: <illegal opcode> run : (Lf/ve;Lf/DK;)Ljava/lang/Runnable;
/*    */     //   1013: invokevirtual Ac0 : (Ljava/lang/Runnable;)V
/*    */     //   1016: ifnonnull -> 943
/*    */     //   1019: aload #8
/*    */     //   1021: astore #5
/*    */     //   1023: goto -> 943
/*    */     //   1026: aload_0
/*    */     //   1027: dup
/*    */     //   1028: dup
/*    */     //   1029: dup2
/*    */     //   1030: aload #5
/*    */     //   1032: invokevirtual AG : (Lf/DK;)V
/*    */     //   1035: new f/Ip
/*    */     //   1038: dup
/*    */     //   1039: astore #5
/*    */     //   1041: invokespecial <init> : ()V
/*    */     //   1044: new f/rS
/*    */     //   1047: dup
/*    */     //   1048: aload_0
/*    */     //   1049: swap
/*    */     //   1050: dup
/*    */     //   1051: invokespecial <init> : ()V
/*    */     //   1054: putfield bF : Lf/rS;
/*    */     //   1057: ldc_w 'stats'
/*    */     //   1060: invokevirtual Xu : (Ljava/lang/String;)V
/*    */     //   1063: getfield bF : Lf/rS;
/*    */     //   1066: new f/dQ
/*    */     //   1069: dup
/*    */     //   1070: bipush #74
/*    */     //   1072: invokestatic OH0 : (I)Ljava/lang/String;
/*    */     //   1075: invokespecial <init> : (Ljava/lang/String;)V
/*    */     //   1078: invokevirtual Gz0 : (Lf/JG0;)V
/*    */     //   1081: new f/dQ
/*    */     //   1084: dup
/*    */     //   1085: astore #7
/*    */     //   1087: new java/lang/StringBuilder
/*    */     //   1090: dup
/*    */     //   1091: astore #8
/*    */     //   1093: invokespecial <init> : ()V
/*    */     //   1096: sipush #8112
/*    */     //   1099: aload #8
/*    */     //   1101: ldc_w ':'
/*    */     //   1104: invokestatic jJ0 : (ILjava/lang/StringBuilder;Ljava/lang/String;)Ljava/lang/String;
/*    */     //   1107: invokespecial <init> : (Ljava/lang/String;)V
/*    */     //   1110: new f/Uy0
/*    */     //   1113: dup
/*    */     //   1114: aload_0
/*    */     //   1115: invokespecial <init> : (Lf/ve;)V
/*    */     //   1118: putfield g0 : Lf/Uy0;
/*    */     //   1121: getfield l5 : Lf/of;
/*    */     //   1124: invokevirtual LE : ()V
/*    */     //   1127: getfield l5 : Lf/of;
/*    */     //   1130: aload_0
/*    */     //   1131: <illegal opcode> SX : (Lf/ve;)Lf/a70;
/*    */     //   1136: invokevirtual JD0 : (Lf/a70;)V
/*    */     //   1139: invokestatic XU : ()Z
/*    */     //   1142: ifeq -> 1155
/*    */     //   1145: aload_0
/*    */     //   1146: getfield g0 : Lf/Uy0;
/*    */     //   1149: ldc_w 'mobile-pager'
/*    */     //   1152: invokevirtual Xu : (Ljava/lang/String;)V
/*    */     //   1155: aload_0
/*    */     //   1156: aload #5
/*    */     //   1158: dup
/*    */     //   1159: dup2
/*    */     //   1160: iconst_1
/*    */     //   1161: anewarray f/JG0
/*    */     //   1164: dup
/*    */     //   1165: aload_0
/*    */     //   1166: getfield bF : Lf/rS;
/*    */     //   1169: iconst_0
/*    */     //   1170: swap
/*    */     //   1171: aastore
/*    */     //   1172: invokevirtual AUX : ([Lf/JG0;)Lf/U90;
/*    */     //   1175: aload #5
/*    */     //   1177: invokevirtual d7 : ()Lf/cr0;
/*    */     //   1180: invokevirtual Em0 : ()Lf/U90;
/*    */     //   1183: aload_0
/*    */     //   1184: getfield g0 : Lf/Uy0;
/*    */     //   1187: invokevirtual Ya : (Lf/JG0;)Lf/U90;
/*    */     //   1190: invokevirtual Em0 : ()Lf/U90;
/*    */     //   1193: iconst_2
/*    */     //   1194: anewarray f/JG0
/*    */     //   1197: dup
/*    */     //   1198: dup
/*    */     //   1199: aload_0
/*    */     //   1200: swap
/*    */     //   1201: iconst_0
/*    */     //   1202: aload #7
/*    */     //   1204: aastore
/*    */     //   1205: getfield l5 : Lf/of;
/*    */     //   1208: iconst_1
/*    */     //   1209: swap
/*    */     //   1210: aastore
/*    */     //   1211: invokevirtual Mg : ([Lf/JG0;)Lf/U90;
/*    */     //   1214: invokevirtual ee0 : (Lf/U90;)Lf/U90;
/*    */     //   1217: invokevirtual rK0 : (Lf/U90;)V
/*    */     //   1220: iconst_1
/*    */     //   1221: anewarray f/JG0
/*    */     //   1224: dup
/*    */     //   1225: aload_0
/*    */     //   1226: getfield bF : Lf/rS;
/*    */     //   1229: iconst_0
/*    */     //   1230: swap
/*    */     //   1231: aastore
/*    */     //   1232: invokevirtual vo0 : ([Lf/JG0;)Lf/U90;
/*    */     //   1235: aload #5
/*    */     //   1237: iconst_3
/*    */     //   1238: anewarray f/JG0
/*    */     //   1241: dup
/*    */     //   1242: dup
/*    */     //   1243: aload_0
/*    */     //   1244: swap
/*    */     //   1245: dup
/*    */     //   1246: aload_0
/*    */     //   1247: getfield g0 : Lf/Uy0;
/*    */     //   1250: iconst_0
/*    */     //   1251: swap
/*    */     //   1252: aastore
/*    */     //   1253: iconst_1
/*    */     //   1254: aload #7
/*    */     //   1256: aastore
/*    */     //   1257: getfield l5 : Lf/of;
/*    */     //   1260: iconst_2
/*    */     //   1261: swap
/*    */     //   1262: aastore
/*    */     //   1263: invokevirtual AUX : ([Lf/JG0;)Lf/U90;
/*    */     //   1266: invokevirtual ee0 : (Lf/U90;)Lf/U90;
/*    */     //   1269: invokevirtual WN : (Lf/U90;)V
/*    */     //   1272: getfield zH0 : Lf/Vq0;
/*    */     //   1275: aload #5
/*    */     //   1277: sipush #5667
/*    */     //   1280: invokestatic OH0 : (I)Ljava/lang/String;
/*    */     //   1283: invokevirtual WS : (Lf/JG0;Ljava/lang/String;)Lf/Li0;
/*    */     //   1286: dup
/*    */     //   1287: aload_0
/*    */     //   1288: swap
/*    */     //   1289: <illegal opcode> run : (Lf/ve;Lf/Li0;)Ljava/lang/Runnable;
/*    */     //   1294: invokevirtual Ac0 : (Ljava/lang/Runnable;)V
/*    */     //   1297: aload_0
/*    */     //   1298: aload_1
/*    */     //   1299: dup
/*    */     //   1300: dup
/*    */     //   1301: ldc_w 'info-layout'
/*    */     //   1304: invokevirtual Xu : (Ljava/lang/String;)V
/*    */     //   1307: new f/dQ
/*    */     //   1310: dup
/*    */     //   1311: astore #5
/*    */     //   1313: sipush #5526
/*    */     //   1316: invokestatic OH0 : (I)Ljava/lang/String;
/*    */     //   1319: invokespecial <init> : (Ljava/lang/String;)V
/*    */     //   1322: iconst_1
/*    */     //   1323: anewarray f/JG0
/*    */     //   1326: dup
/*    */     //   1327: iconst_0
/*    */     //   1328: aload #5
/*    */     //   1330: aastore
/*    */     //   1331: invokevirtual AUX : ([Lf/JG0;)Lf/U90;
/*    */     //   1334: astore #7
/*    */     //   1336: iconst_1
/*    */     //   1337: anewarray f/JG0
/*    */     //   1340: dup
/*    */     //   1341: iconst_0
/*    */     //   1342: aload #5
/*    */     //   1344: aastore
/*    */     //   1345: invokevirtual vo0 : ([Lf/JG0;)Lf/U90;
/*    */     //   1348: astore #5
/*    */     //   1350: getfield dp : [Lf/CC0;
/*    */     //   1353: dup
/*    */     //   1354: astore #8
/*    */     //   1356: arraylength
/*    */     //   1357: istore #9
/*    */     //   1359: iconst_0
/*    */     //   1360: istore #10
/*    */     //   1362: iload #10
/*    */     //   1364: iload #9
/*    */     //   1366: if_icmpge -> 1486
/*    */     //   1369: aload #5
/*    */     //   1371: aload_1
/*    */     //   1372: aload #7
/*    */     //   1374: aload_1
/*    */     //   1375: aload #8
/*    */     //   1377: iload #10
/*    */     //   1379: aaload
/*    */     //   1380: astore #11
/*    */     //   1382: new f/dQ
/*    */     //   1385: dup
/*    */     //   1386: dup
/*    */     //   1387: astore #12
/*    */     //   1389: aload #11
/*    */     //   1391: invokevirtual k6 : ()B
/*    */     //   1394: sipush #5700
/*    */     //   1397: iadd
/*    */     //   1398: invokestatic OH0 : (I)Ljava/lang/String;
/*    */     //   1401: invokespecial <init> : (Ljava/lang/String;)V
/*    */     //   1404: ldc_w 'label-type'
/*    */     //   1407: invokevirtual Xu : (Ljava/lang/String;)V
/*    */     //   1410: new f/dQ
/*    */     //   1413: dup
/*    */     //   1414: dup
/*    */     //   1415: astore #13
/*    */     //   1417: aload #11
/*    */     //   1419: invokevirtual k6 : ()B
/*    */     //   1422: sipush #5710
/*    */     //   1425: iadd
/*    */     //   1426: invokestatic OH0 : (I)Ljava/lang/String;
/*    */     //   1429: invokespecial <init> : (Ljava/lang/String;)V
/*    */     //   1432: ldc_w 'label-desc'
/*    */     //   1435: invokevirtual Xu : (Ljava/lang/String;)V
/*    */     //   1438: iconst_2
/*    */     //   1439: anewarray f/JG0
/*    */     //   1442: dup
/*    */     //   1443: dup
/*    */     //   1444: iconst_0
/*    */     //   1445: aload #12
/*    */     //   1447: aastore
/*    */     //   1448: iconst_1
/*    */     //   1449: aload #13
/*    */     //   1451: aastore
/*    */     //   1452: invokevirtual vo0 : ([Lf/JG0;)Lf/U90;
/*    */     //   1455: invokevirtual ee0 : (Lf/U90;)Lf/U90;
/*    */     //   1458: pop
/*    */     //   1459: iconst_2
/*    */     //   1460: anewarray f/JG0
/*    */     //   1463: dup
/*    */     //   1464: dup
/*    */     //   1465: iconst_0
/*    */     //   1466: aload #12
/*    */     //   1468: aastore
/*    */     //   1469: iconst_1
/*    */     //   1470: aload #13
/*    */     //   1472: aastore
/*    */     //   1473: invokevirtual AUX : ([Lf/JG0;)Lf/U90;
/*    */     //   1476: invokevirtual ee0 : (Lf/U90;)Lf/U90;
/*    */     //   1479: pop
/*    */     //   1480: iinc #10, 1
/*    */     //   1483: goto -> 1362
/*    */     //   1486: aload #4
/*    */     //   1488: aload_3
/*    */     //   1489: dup
/*    */     //   1490: dup
/*    */     //   1491: aload_0
/*    */     //   1492: aload_1
/*    */     //   1493: aload #5
/*    */     //   1495: aload_1
/*    */     //   1496: dup
/*    */     //   1497: aload #7
/*    */     //   1499: aload_1
/*    */     //   1500: invokevirtual d7 : ()Lf/cr0;
/*    */     //   1503: invokevirtual ee0 : (Lf/U90;)Lf/U90;
/*    */     //   1506: invokevirtual rK0 : (Lf/U90;)V
/*    */     //   1509: invokevirtual mE0 : ()Lf/g0;
/*    */     //   1512: invokevirtual ee0 : (Lf/U90;)Lf/U90;
/*    */     //   1515: invokevirtual WN : (Lf/U90;)V
/*    */     //   1518: getfield zH0 : Lf/Vq0;
/*    */     //   1521: aload_1
/*    */     //   1522: sipush #5527
/*    */     //   1525: invokestatic OH0 : (I)Ljava/lang/String;
/*    */     //   1528: invokevirtual WS : (Lf/JG0;Ljava/lang/String;)Lf/Li0;
/*    */     //   1531: pop
/*    */     //   1532: ldc_w 'info-layout'
/*    */     //   1535: invokevirtual Xu : (Ljava/lang/String;)V
/*    */     //   1538: invokevirtual mE0 : ()Lf/g0;
/*    */     //   1541: astore_1
/*    */     //   1542: invokevirtual d7 : ()Lf/cr0;
/*    */     //   1545: dup
/*    */     //   1546: astore #5
/*    */     //   1548: aload_3
/*    */     //   1549: aload_1
/*    */     //   1550: aload_3
/*    */     //   1551: new f/dQ
/*    */     //   1554: dup
/*    */     //   1555: astore #7
/*    */     //   1557: invokespecial <init> : ()V
/*    */     //   1560: iconst_1
/*    */     //   1561: anewarray f/JG0
/*    */     //   1564: dup
/*    */     //   1565: iconst_0
/*    */     //   1566: aload #7
/*    */     //   1568: aastore
/*    */     //   1569: invokevirtual vo0 : ([Lf/JG0;)Lf/U90;
/*    */     //   1572: invokevirtual ee0 : (Lf/U90;)Lf/U90;
/*    */     //   1575: pop
/*    */     //   1576: iconst_1
/*    */     //   1577: anewarray f/JG0
/*    */     //   1580: dup
/*    */     //   1581: iconst_0
/*    */     //   1582: aload #7
/*    */     //   1584: aastore
/*    */     //   1585: invokevirtual AUX : ([Lf/JG0;)Lf/U90;
/*    */     //   1588: invokevirtual ee0 : (Lf/U90;)Lf/U90;
/*    */     //   1591: pop
/*    */     //   1592: arraylength
/*    */     //   1593: iconst_1
/*    */     //   1594: if_icmpge -> 1661
/*    */     //   1597: aload_1
/*    */     //   1598: aload_3
/*    */     //   1599: aload #5
/*    */     //   1601: aload_3
/*    */     //   1602: new f/dQ
/*    */     //   1605: dup
/*    */     //   1606: dup
/*    */     //   1607: astore #4
/*    */     //   1609: sipush #5634
/*    */     //   1612: invokestatic OH0 : (I)Ljava/lang/String;
/*    */     //   1615: invokespecial <init> : (Ljava/lang/String;)V
/*    */     //   1618: ldc_w 'label-game-mode'
/*    */     //   1621: invokevirtual Xu : (Ljava/lang/String;)V
/*    */     //   1624: iconst_1
/*    */     //   1625: anewarray f/JG0
/*    */     //   1628: dup
/*    */     //   1629: iconst_0
/*    */     //   1630: aload #4
/*    */     //   1632: aastore
/*    */     //   1633: invokevirtual AUX : ([Lf/JG0;)Lf/U90;
/*    */     //   1636: invokevirtual ee0 : (Lf/U90;)Lf/U90;
/*    */     //   1639: pop
/*    */     //   1640: invokevirtual d7 : ()Lf/cr0;
/*    */     //   1643: invokevirtual Em0 : ()Lf/U90;
/*    */     //   1646: aload #4
/*    */     //   1648: invokevirtual Ya : (Lf/JG0;)Lf/U90;
/*    */     //   1651: invokevirtual Em0 : ()Lf/U90;
/*    */     //   1654: invokevirtual ee0 : (Lf/U90;)Lf/U90;
/*    */     //   1657: pop
/*    */     //   1658: goto -> 2396
/*    */     //   1661: aload #4
/*    */     //   1663: arraylength
/*    */     //   1664: istore #7
/*    */     //   1666: iconst_0
/*    */     //   1667: istore #8
/*    */     //   1669: iload #8
/*    */     //   1671: iload #7
/*    */     //   1673: if_icmpge -> 2396
/*    */     //   1676: aload #4
/*    */     //   1678: iload #8
/*    */     //   1680: aaload
/*    */     //   1681: dup
/*    */     //   1682: astore #9
/*    */     //   1684: new f/dQ
/*    */     //   1687: astore #10
/*    */     //   1689: invokevirtual WT : ()Lf/DO;
/*    */     //   1692: ifnonnull -> 1706
/*    */     //   1695: sipush #5749
/*    */     //   1698: invokestatic OH0 : (I)Ljava/lang/String;
/*    */     //   1701: astore #11
/*    */     //   1703: goto -> 1716
/*    */     //   1706: aload #9
/*    */     //   1708: invokevirtual WT : ()Lf/DO;
/*    */     //   1711: invokevirtual jt : ()Ljava/lang/String;
/*    */     //   1714: astore #11
/*    */     //   1716: aload #9
/*    */     //   1718: aload #5
/*    */     //   1720: aload_3
/*    */     //   1721: aload_1
/*    */     //   1722: aload_3
/*    */     //   1723: aload #10
/*    */     //   1725: dup
/*    */     //   1726: aload #11
/*    */     //   1728: invokespecial <init> : (Ljava/lang/String;)V
/*    */     //   1731: ldc_w 'label-banned-title'
/*    */     //   1734: invokevirtual Xu : (Ljava/lang/String;)V
/*    */     //   1737: iconst_1
/*    */     //   1738: anewarray f/JG0
/*    */     //   1741: dup
/*    */     //   1742: iconst_0
/*    */     //   1743: aload #10
/*    */     //   1745: aastore
/*    */     //   1746: invokevirtual vo0 : ([Lf/JG0;)Lf/U90;
/*    */     //   1749: invokevirtual ee0 : (Lf/U90;)Lf/U90;
/*    */     //   1752: pop
/*    */     //   1753: iconst_1
/*    */     //   1754: anewarray f/JG0
/*    */     //   1757: dup
/*    */     //   1758: iconst_0
/*    */     //   1759: aload #10
/*    */     //   1761: aastore
/*    */     //   1762: invokevirtual AUX : ([Lf/JG0;)Lf/U90;
/*    */     //   1765: invokevirtual ee0 : (Lf/U90;)Lf/U90;
/*    */     //   1768: pop
/*    */     //   1769: invokevirtual d6 : ()Ljava/util/ArrayList;
/*    */     //   1772: dup
/*    */     //   1773: dup
/*    */     //   1774: astore #9
/*    */     //   1776: invokevirtual size : ()I
/*    */     //   1779: bipush #8
/*    */     //   1781: invokestatic min : (II)I
/*    */     //   1784: anewarray f/vF0
/*    */     //   1787: astore #10
/*    */     //   1789: iconst_0
/*    */     //   1790: istore #11
/*    */     //   1792: iconst_0
/*    */     //   1793: istore #12
/*    */     //   1795: invokeinterface iterator : ()Ljava/util/Iterator;
/*    */     //   1800: astore #13
/*    */     //   1802: aload #13
/*    */     //   1804: invokeinterface hasNext : ()Z
/*    */     //   1809: ifeq -> 2353
/*    */     //   1812: aload #13
/*    */     //   1814: invokeinterface next : ()Ljava/lang/Object;
/*    */     //   1819: checkcast f/Pi
/*    */     //   1822: astore #14
/*    */     //   1824: invokestatic XU : ()Z
/*    */     //   1827: ifeq -> 1846
/*    */     //   1830: new f/vF0
/*    */     //   1833: dup
/*    */     //   1834: astore #15
/*    */     //   1836: bipush #72
/*    */     //   1838: bipush #72
/*    */     //   1840: invokespecial <init> : (II)V
/*    */     //   1843: goto -> 1859
/*    */     //   1846: new f/vF0
/*    */     //   1849: dup
/*    */     //   1850: astore #15
/*    */     //   1852: bipush #48
/*    */     //   1854: bipush #48
/*    */     //   1856: invokespecial <init> : (II)V
/*    */     //   1859: aload #14
/*    */     //   1861: aload_3
/*    */     //   1862: aload #15
/*    */     //   1864: invokevirtual J8 : (Lf/JG0;)V
/*    */     //   1867: invokevirtual Rv0 : ()B
/*    */     //   1870: ifeq -> 1905
/*    */     //   1873: aload #14
/*    */     //   1875: invokevirtual Rv0 : ()B
/*    */     //   1878: iconst_2
/*    */     //   1879: if_icmpne -> 1885
/*    */     //   1882: goto -> 1905
/*    */     //   1885: aload #14
/*    */     //   1887: invokevirtual Rv0 : ()B
/*    */     //   1890: iconst_1
/*    */     //   1891: if_icmpne -> 1913
/*    */     //   1894: aload #15
/*    */     //   1896: ldc_w 'label-suspect-testing-monster'
/*    */     //   1899: invokevirtual Xu : (Ljava/lang/String;)V
/*    */     //   1902: goto -> 1913
/*    */     //   1905: aload #15
/*    */     //   1907: ldc_w 'label-banned-monster'
/*    */     //   1910: invokevirtual Xu : (Ljava/lang/String;)V
/*    */     //   1913: aload #14
/*    */     //   1915: iconst_0
/*    */     //   1916: istore #16
/*    */     //   1918: invokevirtual G20 : ()S
/*    */     //   1921: ifle -> 1958
/*    */     //   1924: aload #15
/*    */     //   1926: invokevirtual ZH0 : ()Lf/rH;
/*    */     //   1929: iconst_1
/*    */     //   1930: anewarray f/zh0
/*    */     //   1933: dup
/*    */     //   1934: invokestatic TK0 : ()Lf/um0;
/*    */     //   1937: aload #14
/*    */     //   1939: invokevirtual G20 : ()S
/*    */     //   1942: iconst_0
/*    */     //   1943: iconst_0
/*    */     //   1944: invokevirtual lb : (SZB)[Lf/zh0;
/*    */     //   1947: iconst_0
/*    */     //   1948: aaload
/*    */     //   1949: iconst_0
/*    */     //   1950: swap
/*    */     //   1951: aastore
/*    */     //   1952: invokevirtual sm : ([Lf/zh0;)V
/*    */     //   1955: goto -> 2130
/*    */     //   1958: aload #14
/*    */     //   1960: invokevirtual vW : ()S
/*    */     //   1963: ifle -> 2000
/*    */     //   1966: aload #15
/*    */     //   1968: invokevirtual ZH0 : ()Lf/rH;
/*    */     //   1971: iconst_1
/*    */     //   1972: anewarray f/U70
/*    */     //   1975: dup
/*    */     //   1976: invokestatic y8 : ()Lf/wm0;
/*    */     //   1979: aload #14
/*    */     //   1981: invokevirtual vW : ()S
/*    */     //   1984: invokevirtual eM0 : (S)Lf/U70;
/*    */     //   1987: iconst_0
/*    */     //   1988: swap
/*    */     //   1989: aastore
/*    */     //   1990: invokevirtual qt : ([Lf/U70;)Lf/JG0;
/*    */     //   1993: pop
/*    */     //   1994: iconst_1
/*    */     //   1995: istore #16
/*    */     //   1997: goto -> 2130
/*    */     //   2000: aload #14
/*    */     //   2002: invokevirtual FO : ()S
/*    */     //   2005: ifle -> 2063
/*    */     //   2008: invokestatic cw : ()Lf/yk0;
/*    */     //   2011: aload #14
/*    */     //   2013: invokevirtual FO : ()S
/*    */     //   2016: invokevirtual mP : (S)Lf/WD;
/*    */     //   2019: dup
/*    */     //   2020: astore #17
/*    */     //   2022: ifnull -> 2130
/*    */     //   2025: aload #15
/*    */     //   2027: invokevirtual ZH0 : ()Lf/rH;
/*    */     //   2030: iconst_1
/*    */     //   2031: anewarray f/U70
/*    */     //   2034: dup
/*    */     //   2035: invokestatic y8 : ()Lf/wm0;
/*    */     //   2038: aload #17
/*    */     //   2040: aconst_null
/*    */     //   2041: invokevirtual Fn : (Lf/Q90;)Lf/Ht0;
/*    */     //   2044: invokevirtual hA : ()S
/*    */     //   2047: invokevirtual eM0 : (S)Lf/U70;
/*    */     //   2050: iconst_0
/*    */     //   2051: swap
/*    */     //   2052: aastore
/*    */     //   2053: invokevirtual qt : ([Lf/U70;)Lf/JG0;
/*    */     //   2056: pop
/*    */     //   2057: iconst_1
/*    */     //   2058: istore #16
/*    */     //   2060: goto -> 2130
/*    */     //   2063: aload #14
/*    */     //   2065: invokevirtual Nu : ()S
/*    */     //   2068: ifle -> 2103
/*    */     //   2071: aload #15
/*    */     //   2073: invokevirtual ZH0 : ()Lf/rH;
/*    */     //   2076: iconst_1
/*    */     //   2077: anewarray f/U70
/*    */     //   2080: dup
/*    */     //   2081: invokestatic y8 : ()Lf/wm0;
/*    */     //   2084: sipush #1018
/*    */     //   2087: invokevirtual eM0 : (S)Lf/U70;
/*    */     //   2090: iconst_0
/*    */     //   2091: swap
/*    */     //   2092: aastore
/*    */     //   2093: invokevirtual qt : ([Lf/U70;)Lf/JG0;
/*    */     //   2096: pop
/*    */     //   2097: iconst_1
/*    */     //   2098: istore #16
/*    */     //   2100: goto -> 2130
/*    */     //   2103: aload #15
/*    */     //   2105: invokevirtual ZH0 : ()Lf/rH;
/*    */     //   2108: iconst_1
/*    */     //   2109: anewarray f/U70
/*    */     //   2112: dup
/*    */     //   2113: invokestatic y8 : ()Lf/wm0;
/*    */     //   2116: iconst_0
/*    */     //   2117: invokevirtual eM0 : (S)Lf/U70;
/*    */     //   2120: iconst_0
/*    */     //   2121: swap
/*    */     //   2122: aastore
/*    */     //   2123: invokevirtual qt : ([Lf/U70;)Lf/JG0;
/*    */     //   2126: pop
/*    */     //   2127: iconst_1
/*    */     //   2128: istore #16
/*    */     //   2130: iload #16
/*    */     //   2132: ifeq -> 2216
/*    */     //   2135: invokestatic XU : ()Z
/*    */     //   2138: ifeq -> 2165
/*    */     //   2141: aload #15
/*    */     //   2143: dup
/*    */     //   2144: invokevirtual ZH0 : ()Lf/rH;
/*    */     //   2147: ldc_w 1.5
/*    */     //   2150: invokevirtual Ii0 : (F)V
/*    */     //   2153: invokevirtual ZH0 : ()Lf/rH;
/*    */     //   2156: iconst_0
/*    */     //   2157: iconst_0
/*    */     //   2158: invokevirtual zT : (II)Lf/JG0;
/*    */     //   2161: pop
/*    */     //   2162: goto -> 2189
/*    */     //   2165: aload #15
/*    */     //   2167: dup
/*    */     //   2168: invokevirtual ZH0 : ()Lf/rH;
/*    */     //   2171: bipush #6
/*    */     //   2173: bipush #6
/*    */     //   2175: invokevirtual zT : (II)Lf/JG0;
/*    */     //   2178: pop
/*    */     //   2179: invokevirtual ZH0 : ()Lf/rH;
/*    */     //   2182: bipush #36
/*    */     //   2184: bipush #36
/*    */     //   2186: invokevirtual tL : (II)V
/*    */     //   2189: aload #15
/*    */     //   2191: dup
/*    */     //   2192: invokevirtual ZH0 : ()Lf/rH;
/*    */     //   2195: bipush #6
/*    */     //   2197: bipush #6
/*    */     //   2199: invokevirtual zT : (II)Lf/JG0;
/*    */     //   2202: pop
/*    */     //   2203: invokevirtual ZH0 : ()Lf/rH;
/*    */     //   2206: bipush #36
/*    */     //   2208: bipush #36
/*    */     //   2210: invokevirtual tL : (II)V
/*    */     //   2213: goto -> 2257
/*    */     //   2216: invokestatic XU : ()Z
/*    */     //   2219: ifeq -> 2245
/*    */     //   2222: aload #15
/*    */     //   2224: dup
/*    */     //   2225: invokevirtual ZH0 : ()Lf/rH;
/*    */     //   2228: fconst_2
/*    */     //   2229: invokevirtual Ii0 : (F)V
/*    */     //   2232: invokevirtual ZH0 : ()Lf/rH;
/*    */     //   2235: iconst_0
/*    */     //   2236: bipush #-4
/*    */     //   2238: invokevirtual zT : (II)Lf/JG0;
/*    */     //   2241: pop
/*    */     //   2242: goto -> 2257
/*    */     //   2245: aload #15
/*    */     //   2247: invokevirtual ZH0 : ()Lf/rH;
/*    */     //   2250: bipush #48
/*    */     //   2252: bipush #48
/*    */     //   2254: invokevirtual tL : (II)V
/*    */     //   2257: aload #10
/*    */     //   2259: iload #12
/*    */     //   2261: aload #15
/*    */     //   2263: dup
/*    */     //   2264: aload #14
/*    */     //   2266: invokestatic Ih : (Lf/Pi;)Ljava/lang/String;
/*    */     //   2269: invokevirtual Gq0 : (Ljava/lang/Object;)V
/*    */     //   2272: iconst_0
/*    */     //   2273: invokevirtual Pb0 : (I)V
/*    */     //   2276: iinc #12, 1
/*    */     //   2279: aload #15
/*    */     //   2281: aastore
/*    */     //   2282: iload #11
/*    */     //   2284: iconst_1
/*    */     //   2285: iadd
/*    */     //   2286: dup
/*    */     //   2287: istore #11
/*    */     //   2289: bipush #8
/*    */     //   2291: irem
/*    */     //   2292: ifne -> 1802
/*    */     //   2295: aload #9
/*    */     //   2297: aload #5
/*    */     //   2299: aload_3
/*    */     //   2300: aload #10
/*    */     //   2302: aload_1
/*    */     //   2303: aload_3
/*    */     //   2304: invokevirtual d7 : ()Lf/cr0;
/*    */     //   2307: invokevirtual Em0 : ()Lf/U90;
/*    */     //   2310: aload #10
/*    */     //   2312: invokevirtual Mg : ([Lf/JG0;)Lf/U90;
/*    */     //   2315: invokevirtual Em0 : ()Lf/U90;
/*    */     //   2318: invokevirtual ee0 : (Lf/U90;)Lf/U90;
/*    */     //   2321: pop
/*    */     //   2322: invokevirtual AUX : ([Lf/JG0;)Lf/U90;
/*    */     //   2325: invokevirtual ee0 : (Lf/U90;)Lf/U90;
/*    */     //   2328: pop
/*    */     //   2329: iconst_0
/*    */     //   2330: istore #12
/*    */     //   2332: invokeinterface size : ()I
/*    */     //   2337: iload #11
/*    */     //   2339: isub
/*    */     //   2340: bipush #8
/*    */     //   2342: invokestatic min : (II)I
/*    */     //   2345: anewarray f/vF0
/*    */     //   2348: astore #10
/*    */     //   2350: goto -> 1802
/*    */     //   2353: iload #12
/*    */     //   2355: ifle -> 2390
/*    */     //   2358: aload #5
/*    */     //   2360: aload_3
/*    */     //   2361: aload #10
/*    */     //   2363: aload_1
/*    */     //   2364: aload_3
/*    */     //   2365: invokevirtual d7 : ()Lf/cr0;
/*    */     //   2368: invokevirtual Em0 : ()Lf/U90;
/*    */     //   2371: aload #10
/*    */     //   2373: invokevirtual Mg : ([Lf/JG0;)Lf/U90;
/*    */     //   2376: invokevirtual Em0 : ()Lf/U90;
/*    */     //   2379: invokevirtual ee0 : (Lf/U90;)Lf/U90;
/*    */     //   2382: pop
/*    */     //   2383: invokevirtual AUX : ([Lf/JG0;)Lf/U90;
/*    */     //   2386: invokevirtual ee0 : (Lf/U90;)Lf/U90;
/*    */     //   2389: pop
/*    */     //   2390: iinc #8, 1
/*    */     //   2393: goto -> 1669
/*    */     //   2396: iload_2
/*    */     //   2397: aload #6
/*    */     //   2399: dup
/*    */     //   2400: dup
/*    */     //   2401: aload_0
/*    */     //   2402: aload_3
/*    */     //   2403: aload #5
/*    */     //   2405: aload_3
/*    */     //   2406: aload_1
/*    */     //   2407: aload_3
/*    */     //   2408: invokevirtual d7 : ()Lf/cr0;
/*    */     //   2411: invokevirtual ee0 : (Lf/U90;)Lf/U90;
/*    */     //   2414: invokevirtual rK0 : (Lf/U90;)V
/*    */     //   2417: invokevirtual Em0 : ()Lf/U90;
/*    */     //   2420: aload_3
/*    */     //   2421: invokevirtual mE0 : ()Lf/g0;
/*    */     //   2424: invokevirtual ee0 : (Lf/U90;)Lf/U90;
/*    */     //   2427: invokevirtual WN : (Lf/U90;)V
/*    */     //   2430: getfield zH0 : Lf/Vq0;
/*    */     //   2433: aload_3
/*    */     //   2434: sipush #5530
/*    */     //   2437: invokestatic OH0 : (I)Ljava/lang/String;
/*    */     //   2440: invokevirtual WS : (Lf/JG0;Ljava/lang/String;)Lf/Li0;
/*    */     //   2443: aload_0
/*    */     //   2444: <illegal opcode> run : (Lf/ve;)Ljava/lang/Runnable;
/*    */     //   2449: invokevirtual Ac0 : (Ljava/lang/Runnable;)V
/*    */     //   2452: ldc_w 'info-layout'
/*    */     //   2455: invokevirtual Xu : (Ljava/lang/String;)V
/*    */     //   2458: invokevirtual mE0 : ()Lf/g0;
/*    */     //   2461: astore_1
/*    */     //   2462: invokevirtual d7 : ()Lf/cr0;
/*    */     //   2465: astore_2
/*    */     //   2466: ifeq -> 2616
/*    */     //   2469: new f/dQ
/*    */     //   2472: dup
/*    */     //   2473: dup
/*    */     //   2474: astore_3
/*    */     //   2475: sipush #7102
/*    */     //   2478: invokestatic OH0 : (I)Ljava/lang/String;
/*    */     //   2481: invokespecial <init> : (Ljava/lang/String;)V
/*    */     //   2484: ldc_w 'label-type'
/*    */     //   2487: invokevirtual Xu : (Ljava/lang/String;)V
/*    */     //   2490: new java/lang/StringBuilder
/*    */     //   2493: dup
/*    */     //   2494: astore #4
/*    */     //   2496: invokespecial <init> : ()V
/*    */     //   2499: sipush #7140
/*    */     //   2502: istore #5
/*    */     //   2504: iload #5
/*    */     //   2506: sipush #7146
/*    */     //   2509: if_icmpgt -> 2546
/*    */     //   2512: aload #4
/*    */     //   2514: invokevirtual length : ()I
/*    */     //   2517: ifle -> 2529
/*    */     //   2520: aload #4
/*    */     //   2522: ldc_w '\\n'
/*    */     //   2525: invokevirtual append : (Ljava/lang/String;)Ljava/lang/StringBuilder;
/*    */     //   2528: pop
/*    */     //   2529: aload #4
/*    */     //   2531: iload #5
/*    */     //   2533: invokestatic OH0 : (I)Ljava/lang/String;
/*    */     //   2536: invokevirtual append : (Ljava/lang/String;)Ljava/lang/StringBuilder;
/*    */     //   2539: pop
/*    */     //   2540: iinc #5, 1
/*    */     //   2543: goto -> 2504
/*    */     //   2546: aload_2
/*    */     //   2547: aload #6
/*    */     //   2549: aload_1
/*    */     //   2550: aload #6
/*    */     //   2552: new f/dQ
/*    */     //   2555: dup
/*    */     //   2556: dup
/*    */     //   2557: astore #5
/*    */     //   2559: aload #4
/*    */     //   2561: invokevirtual toString : ()Ljava/lang/String;
/*    */     //   2564: invokespecial <init> : (Ljava/lang/String;)V
/*    */     //   2567: ldc_w 'label-desc'
/*    */     //   2570: invokevirtual Xu : (Ljava/lang/String;)V
/*    */     //   2573: iconst_2
/*    */     //   2574: anewarray f/JG0
/*    */     //   2577: dup
/*    */     //   2578: dup
/*    */     //   2579: iconst_0
/*    */     //   2580: aload_3
/*    */     //   2581: aastore
/*    */     //   2582: iconst_1
/*    */     //   2583: aload #5
/*    */     //   2585: aastore
/*    */     //   2586: invokevirtual vo0 : ([Lf/JG0;)Lf/U90;
/*    */     //   2589: invokevirtual ee0 : (Lf/U90;)Lf/U90;
/*    */     //   2592: pop
/*    */     //   2593: iconst_2
/*    */     //   2594: anewarray f/JG0
/*    */     //   2597: dup
/*    */     //   2598: dup
/*    */     //   2599: iconst_0
/*    */     //   2600: aload_3
/*    */     //   2601: aastore
/*    */     //   2602: iconst_1
/*    */     //   2603: aload #5
/*    */     //   2605: aastore
/*    */     //   2606: invokevirtual AUX : ([Lf/JG0;)Lf/U90;
/*    */     //   2609: invokevirtual ee0 : (Lf/U90;)Lf/U90;
/*    */     //   2612: pop
/*    */     //   2613: goto -> 2852
/*    */     //   2616: iconst_0
/*    */     //   2617: istore_3
/*    */     //   2618: iload_3
/*    */     //   2619: iconst_4
/*    */     //   2620: if_icmpge -> 2852
/*    */     //   2623: iload_3
/*    */     //   2624: ifeq -> 2691
/*    */     //   2627: iload_3
/*    */     //   2628: iconst_1
/*    */     //   2629: if_icmpeq -> 2673
/*    */     //   2632: iload_3
/*    */     //   2633: iconst_2
/*    */     //   2634: if_icmpeq -> 2655
/*    */     //   2637: sipush #7104
/*    */     //   2640: istore #4
/*    */     //   2642: sipush #7160
/*    */     //   2645: istore #5
/*    */     //   2647: sipush #7163
/*    */     //   2650: istore #7
/*    */     //   2652: goto -> 2706
/*    */     //   2655: sipush #7103
/*    */     //   2658: istore #4
/*    */     //   2660: sipush #7150
/*    */     //   2663: istore #5
/*    */     //   2665: sipush #7153
/*    */     //   2668: istore #7
/*    */     //   2670: goto -> 2706
/*    */     //   2673: sipush #7101
/*    */     //   2676: istore #4
/*    */     //   2678: sipush #7130
/*    */     //   2681: istore #5
/*    */     //   2683: sipush #7135
/*    */     //   2686: istore #7
/*    */     //   2688: goto -> 2706
/*    */     //   2691: sipush #7100
/*    */     //   2694: istore #4
/*    */     //   2696: sipush #7120
/*    */     //   2699: istore #5
/*    */     //   2701: sipush #7121
/*    */     //   2704: istore #7
/*    */     //   2706: new f/dQ
/*    */     //   2709: dup
/*    */     //   2710: dup
/*    */     //   2711: astore #8
/*    */     //   2713: iload #4
/*    */     //   2715: invokestatic OH0 : (I)Ljava/lang/String;
/*    */     //   2718: invokespecial <init> : (Ljava/lang/String;)V
/*    */     //   2721: ldc_w 'label-type'
/*    */     //   2724: invokevirtual Xu : (Ljava/lang/String;)V
/*    */     //   2727: new java/lang/StringBuilder
/*    */     //   2730: dup
/*    */     //   2731: astore #4
/*    */     //   2733: invokespecial <init> : ()V
/*    */     //   2736: iload #5
/*    */     //   2738: iload #7
/*    */     //   2740: if_icmpgt -> 2777
/*    */     //   2743: aload #4
/*    */     //   2745: invokevirtual length : ()I
/*    */     //   2748: ifle -> 2760
/*    */     //   2751: aload #4
/*    */     //   2753: ldc_w '\\n'
/*    */     //   2756: invokevirtual append : (Ljava/lang/String;)Ljava/lang/StringBuilder;
/*    */     //   2759: pop
/*    */     //   2760: aload #4
/*    */     //   2762: iload #5
/*    */     //   2764: invokestatic OH0 : (I)Ljava/lang/String;
/*    */     //   2767: invokevirtual append : (Ljava/lang/String;)Ljava/lang/StringBuilder;
/*    */     //   2770: pop
/*    */     //   2771: iinc #5, 1
/*    */     //   2774: goto -> 2736
/*    */     //   2777: aload_2
/*    */     //   2778: aload #6
/*    */     //   2780: aload_1
/*    */     //   2781: aload #6
/*    */     //   2783: new f/dQ
/*    */     //   2786: dup
/*    */     //   2787: dup
/*    */     //   2788: astore #5
/*    */     //   2790: aload #4
/*    */     //   2792: invokevirtual toString : ()Ljava/lang/String;
/*    */     //   2795: invokespecial <init> : (Ljava/lang/String;)V
/*    */     //   2798: ldc_w 'label-desc'
/*    */     //   2801: invokevirtual Xu : (Ljava/lang/String;)V
/*    */     //   2804: iconst_2
/*    */     //   2805: anewarray f/JG0
/*    */     //   2808: dup
/*    */     //   2809: dup
/*    */     //   2810: iconst_0
/*    */     //   2811: aload #8
/*    */     //   2813: aastore
/*    */     //   2814: iconst_1
/*    */     //   2815: aload #5
/*    */     //   2817: aastore
/*    */     //   2818: invokevirtual vo0 : ([Lf/JG0;)Lf/U90;
/*    */     //   2821: invokevirtual ee0 : (Lf/U90;)Lf/U90;
/*    */     //   2824: pop
/*    */     //   2825: iconst_2
/*    */     //   2826: anewarray f/JG0
/*    */     //   2829: dup
/*    */     //   2830: dup
/*    */     //   2831: iconst_0
/*    */     //   2832: aload #8
/*    */     //   2834: aastore
/*    */     //   2835: iconst_1
/*    */     //   2836: aload #5
/*    */     //   2838: aastore
/*    */     //   2839: invokevirtual AUX : ([Lf/JG0;)Lf/U90;
/*    */     //   2842: invokevirtual ee0 : (Lf/U90;)Lf/U90;
/*    */     //   2845: pop
/*    */     //   2846: iinc #3, 1
/*    */     //   2849: goto -> 2618
/*    */     //   2852: aload_0
/*    */     //   2853: dup
/*    */     //   2854: dup
/*    */     //   2855: dup2
/*    */     //   2856: dup2
/*    */     //   2857: dup2
/*    */     //   2858: dup2
/*    */     //   2859: aload #6
/*    */     //   2861: aload_2
/*    */     //   2862: aload #6
/*    */     //   2864: aload_1
/*    */     //   2865: aload #6
/*    */     //   2867: invokevirtual d7 : ()Lf/cr0;
/*    */     //   2870: invokevirtual ee0 : (Lf/U90;)Lf/U90;
/*    */     //   2873: invokevirtual rK0 : (Lf/U90;)V
/*    */     //   2876: invokevirtual Em0 : ()Lf/U90;
/*    */     //   2879: aload #6
/*    */     //   2881: invokevirtual mE0 : ()Lf/g0;
/*    */     //   2884: invokevirtual ee0 : (Lf/U90;)Lf/U90;
/*    */     //   2887: invokevirtual WN : (Lf/U90;)V
/*    */     //   2890: getfield zH0 : Lf/Vq0;
/*    */     //   2893: aload #6
/*    */     //   2895: sipush #5531
/*    */     //   2898: invokestatic OH0 : (I)Ljava/lang/String;
/*    */     //   2901: invokevirtual WS : (Lf/JG0;Ljava/lang/String;)Lf/Li0;
/*    */     //   2904: pop
/*    */     //   2905: getfield zH0 : Lf/Vq0;
/*    */     //   2908: invokevirtual J8 : (Lf/JG0;)V
/*    */     //   2911: getfield zH0 : Lf/Vq0;
/*    */     //   2914: putfield Bm0 : Lf/JG0;
/*    */     //   2917: new f/Un
/*    */     //   2920: dup
/*    */     //   2921: aload_0
/*    */     //   2922: swap
/*    */     //   2923: dup
/*    */     //   2924: invokespecial <init> : ()V
/*    */     //   2927: putfield ki0 : Lf/Un;
/*    */     //   2930: ldc_w 'minimizeButton'
/*    */     //   2933: invokevirtual Xu : (Ljava/lang/String;)V
/*    */     //   2936: getfield ki0 : Lf/Un;
/*    */     //   2939: iconst_0
/*    */     //   2940: invokevirtual Zf0 : (Z)V
/*    */     //   2943: getfield ki0 : Lf/Un;
/*    */     //   2946: iconst_0
/*    */     //   2947: invokevirtual wI0 : (Z)V
/*    */     //   2950: getfield ki0 : Lf/Un;
/*    */     //   2953: aload_0
/*    */     //   2954: <illegal opcode> run : (Lf/ve;)Ljava/lang/Runnable;
/*    */     //   2959: invokevirtual tW : (Ljava/lang/Runnable;)V
/*    */     //   2962: getfield ki0 : Lf/Un;
/*    */     //   2965: invokevirtual J8 : (Lf/JG0;)V
/*    */     //   2968: invokevirtual rH0 : ()V
/*    */     //   2971: invokestatic XU : ()Z
/*    */     //   2974: ifeq -> 3025
/*    */     //   2977: aload_0
/*    */     //   2978: dup
/*    */     //   2979: new f/Fy0
/*    */     //   2982: dup
/*    */     //   2983: dup
/*    */     //   2984: astore_1
/*    */     //   2985: ldc_w ''
/*    */     //   2988: sipush #280
/*    */     //   2991: bipush #60
/*    */     //   2993: invokespecial <init> : (Ljava/lang/String;II)V
/*    */     //   2996: putfield vi : Lf/Fy0;
/*    */     //   2999: aload_1
/*    */     //   3000: invokevirtual zY : ()Lf/rH;
/*    */     //   3003: iconst_4
/*    */     //   3004: iconst_5
/*    */     //   3005: invokevirtual zT : (II)Lf/JG0;
/*    */     //   3008: pop
/*    */     //   3009: getfield vi : Lf/Fy0;
/*    */     //   3012: invokevirtual zY : ()Lf/rH;
/*    */     //   3015: bipush #48
/*    */     //   3017: bipush #48
/*    */     //   3019: invokevirtual tL : (II)V
/*    */     //   3022: goto -> 3070
/*    */     //   3025: aload_0
/*    */     //   3026: dup
/*    */     //   3027: new f/Fy0
/*    */     //   3030: dup
/*    */     //   3031: dup
/*    */     //   3032: astore_1
/*    */     //   3033: ldc_w ''
/*    */     //   3036: sipush #200
/*    */     //   3039: bipush #30
/*    */     //   3041: invokespecial <init> : (Ljava/lang/String;II)V
/*    */     //   3044: putfield vi : Lf/Fy0;
/*    */     //   3047: aload_1
/*    */     //   3048: invokevirtual zY : ()Lf/rH;
/*    */     //   3051: iconst_4
/*    */     //   3052: iconst_3
/*    */     //   3053: invokevirtual zT : (II)Lf/JG0;
/*    */     //   3056: pop
/*    */     //   3057: getfield vi : Lf/Fy0;
/*    */     //   3060: invokevirtual zY : ()Lf/rH;
/*    */     //   3063: bipush #24
/*    */     //   3065: bipush #24
/*    */     //   3067: invokevirtual tL : (II)V
/*    */     //   3070: aload_0
/*    */     //   3071: dup
/*    */     //   3072: dup
/*    */     //   3073: dup2
/*    */     //   3074: dup2
/*    */     //   3075: dup2
/*    */     //   3076: getfield vi : Lf/Fy0;
/*    */     //   3079: invokevirtual zY : ()Lf/rH;
/*    */     //   3082: iconst_1
/*    */     //   3083: anewarray f/U70
/*    */     //   3086: dup
/*    */     //   3087: getstatic f/cC0.xK : Lf/cC0;
/*    */     //   3090: invokevirtual xr0 : ()Lf/U70;
/*    */     //   3093: iconst_0
/*    */     //   3094: swap
/*    */     //   3095: aastore
/*    */     //   3096: invokevirtual qt : ([Lf/U70;)Lf/JG0;
/*    */     //   3099: pop
/*    */     //   3100: getfield vi : Lf/Fy0;
/*    */     //   3103: invokevirtual zY : ()Lf/rH;
/*    */     //   3106: bipush #25
/*    */     //   3108: invokevirtual EV : (I)V
/*    */     //   3111: getfield vi : Lf/Fy0;
/*    */     //   3114: invokevirtual zY : ()Lf/rH;
/*    */     //   3117: invokevirtual HY : ()V
/*    */     //   3120: getfield vi : Lf/Fy0;
/*    */     //   3123: aload_0
/*    */     //   3124: <illegal opcode> run : (Lf/ve;)Ljava/lang/Runnable;
/*    */     //   3129: invokevirtual tW : (Ljava/lang/Runnable;)V
/*    */     //   3132: getfield ab0 : Lf/uB0;
/*    */     //   3135: aload_0
/*    */     //   3136: getfield vi : Lf/Fy0;
/*    */     //   3139: invokevirtual J8 : (Lf/JG0;)V
/*    */     //   3142: getfield ab0 : Lf/uB0;
/*    */     //   3145: invokevirtual J8 : (Lf/JG0;)V
/*    */     //   3148: getfield ab0 : Lf/uB0;
/*    */     //   3151: iconst_0
/*    */     //   3152: invokevirtual wI0 : (Z)V
/*    */     //   3155: invokevirtual j8 : ()V
/*    */     //   3158: return
/*    */     // Line number table:
/*    */     //   Java source line number -> byte code offset
/*    */     //   #1	-> 1101
/*    */     //   #2	-> 1107 } private void Hy0(wA0[] paramArrayOfwA0, int paramInt) { // Byte code:
/*    */     //   0: aload_1
/*    */     //   1: new f/dQ
/*    */     //   4: dup
/*    */     //   5: dup
/*    */     //   6: astore_3
/*    */     //   7: sipush #5663
/*    */     //   10: invokestatic OH0 : (I)Ljava/lang/String;
/*    */     //   13: astore #4
/*    */     //   15: invokespecial <init> : ()V
/*    */     //   18: aload #4
/*    */     //   20: invokevirtual E1 : (Ljava/lang/String;)V
/*    */     //   23: new f/dQ
/*    */     //   26: dup
/*    */     //   27: dup
/*    */     //   28: astore #4
/*    */     //   30: ldc_w ''
/*    */     //   33: astore #5
/*    */     //   35: invokespecial <init> : ()V
/*    */     //   38: aload #5
/*    */     //   40: invokevirtual E1 : (Ljava/lang/String;)V
/*    */     //   43: new f/dQ
/*    */     //   46: dup
/*    */     //   47: dup
/*    */     //   48: astore #5
/*    */     //   50: sipush #9155
/*    */     //   53: invokestatic OH0 : (I)Ljava/lang/String;
/*    */     //   56: astore #6
/*    */     //   58: invokespecial <init> : ()V
/*    */     //   61: aload #6
/*    */     //   63: invokevirtual E1 : (Ljava/lang/String;)V
/*    */     //   66: new f/dQ
/*    */     //   69: dup
/*    */     //   70: dup
/*    */     //   71: dup2
/*    */     //   72: astore #6
/*    */     //   74: sipush #5664
/*    */     //   77: invokestatic OH0 : (I)Ljava/lang/String;
/*    */     //   80: astore #7
/*    */     //   82: invokespecial <init> : ()V
/*    */     //   85: aload #7
/*    */     //   87: invokevirtual E1 : (Ljava/lang/String;)V
/*    */     //   90: sipush #5665
/*    */     //   93: invokestatic OH0 : (I)Ljava/lang/String;
/*    */     //   96: putfield z4 : Ljava/lang/Object;
/*    */     //   99: invokevirtual zn : ()V
/*    */     //   102: new f/dQ
/*    */     //   105: dup
/*    */     //   106: dup
/*    */     //   107: astore #7
/*    */     //   109: sipush #5666
/*    */     //   112: invokestatic OH0 : (I)Ljava/lang/String;
/*    */     //   115: astore #8
/*    */     //   117: invokespecial <init> : ()V
/*    */     //   120: aload #8
/*    */     //   122: invokevirtual E1 : (Ljava/lang/String;)V
/*    */     //   125: new f/dQ
/*    */     //   128: dup
/*    */     //   129: astore #8
/*    */     //   131: aload #7
/*    */     //   133: aload #6
/*    */     //   135: aload #5
/*    */     //   137: aload #4
/*    */     //   139: aload_3
/*    */     //   140: aload #8
/*    */     //   142: dup
/*    */     //   143: sipush #5668
/*    */     //   146: invokestatic OH0 : (I)Ljava/lang/String;
/*    */     //   149: astore #4
/*    */     //   151: invokespecial <init> : ()V
/*    */     //   154: aload #4
/*    */     //   156: invokevirtual E1 : (Ljava/lang/String;)V
/*    */     //   159: ldc_w 'label-rank'
/*    */     //   162: invokevirtual Xu : (Ljava/lang/String;)V
/*    */     //   165: ldc_w 'label-title-icon'
/*    */     //   168: invokevirtual Xu : (Ljava/lang/String;)V
/*    */     //   171: ldc_w 'label-name'
/*    */     //   174: invokevirtual Xu : (Ljava/lang/String;)V
/*    */     //   177: ldc_w 'label-winloss'
/*    */     //   180: invokevirtual Xu : (Ljava/lang/String;)V
/*    */     //   183: ldc_w 'label-winpercent'
/*    */     //   186: invokevirtual Xu : (Ljava/lang/String;)V
/*    */     //   189: ldc_w 'label-rating'
/*    */     //   192: invokevirtual Xu : (Ljava/lang/String;)V
/*    */     //   195: new f/Ip
/*    */     //   198: dup
/*    */     //   199: dup2
/*    */     //   200: dup2
/*    */     //   201: astore #4
/*    */     //   203: invokespecial <init> : ()V
/*    */     //   206: new f/g0
/*    */     //   209: dup
/*    */     //   210: aload #4
/*    */     //   212: invokespecial <init> : (Lf/Ip;)V
/*    */     //   215: invokevirtual rK0 : (Lf/U90;)V
/*    */     //   218: new f/cr0
/*    */     //   221: dup
/*    */     //   222: aload #4
/*    */     //   224: invokespecial <init> : (Lf/Ip;)V
/*    */     //   227: invokevirtual WN : (Lf/U90;)V
/*    */     //   230: getfield Xz0 : Lf/U90;
/*    */     //   233: new f/cr0
/*    */     //   236: dup
/*    */     //   237: aload #4
/*    */     //   239: invokespecial <init> : (Lf/Ip;)V
/*    */     //   242: iconst_5
/*    */     //   243: anewarray f/JG0
/*    */     //   246: dup
/*    */     //   247: dup2
/*    */     //   248: dup2
/*    */     //   249: iconst_0
/*    */     //   250: aload_3
/*    */     //   251: aastore
/*    */     //   252: iconst_1
/*    */     //   253: aload #5
/*    */     //   255: aastore
/*    */     //   256: iconst_2
/*    */     //   257: aload #6
/*    */     //   259: aastore
/*    */     //   260: iconst_3
/*    */     //   261: aload #7
/*    */     //   263: aastore
/*    */     //   264: iconst_4
/*    */     //   265: aload #8
/*    */     //   267: aastore
/*    */     //   268: invokevirtual Mg : ([Lf/JG0;)Lf/U90;
/*    */     //   271: invokevirtual ee0 : (Lf/U90;)Lf/U90;
/*    */     //   274: pop
/*    */     //   275: getfield o30 : Lf/U90;
/*    */     //   278: new f/g0
/*    */     //   281: dup
/*    */     //   282: aload #4
/*    */     //   284: invokespecial <init> : (Lf/Ip;)V
/*    */     //   287: iconst_5
/*    */     //   288: anewarray f/JG0
/*    */     //   291: dup
/*    */     //   292: dup2
/*    */     //   293: dup2
/*    */     //   294: iconst_0
/*    */     //   295: aload_3
/*    */     //   296: aastore
/*    */     //   297: iconst_1
/*    */     //   298: aload #5
/*    */     //   300: aastore
/*    */     //   301: iconst_2
/*    */     //   302: aload #6
/*    */     //   304: aastore
/*    */     //   305: iconst_3
/*    */     //   306: aload #7
/*    */     //   308: aastore
/*    */     //   309: iconst_4
/*    */     //   310: aload #8
/*    */     //   312: aastore
/*    */     //   313: invokevirtual Mg : ([Lf/JG0;)Lf/U90;
/*    */     //   316: invokevirtual ee0 : (Lf/U90;)Lf/U90;
/*    */     //   319: pop
/*    */     //   320: new java/util/ArrayList
/*    */     //   323: dup
/*    */     //   324: astore_3
/*    */     //   325: invokespecial <init> : ()V
/*    */     //   328: ifnonnull -> 399
/*    */     //   331: aload #4
/*    */     //   333: dup
/*    */     //   334: new f/dQ
/*    */     //   337: dup
/*    */     //   338: dup
/*    */     //   339: astore_1
/*    */     //   340: sipush #5582
/*    */     //   343: invokestatic OH0 : (I)Ljava/lang/String;
/*    */     //   346: astore #5
/*    */     //   348: invokespecial <init> : ()V
/*    */     //   351: aload #5
/*    */     //   353: invokevirtual E1 : (Ljava/lang/String;)V
/*    */     //   356: getfield Xz0 : Lf/U90;
/*    */     //   359: aload #4
/*    */     //   361: iconst_1
/*    */     //   362: anewarray f/JG0
/*    */     //   365: dup
/*    */     //   366: iconst_0
/*    */     //   367: aload_1
/*    */     //   368: aastore
/*    */     //   369: invokevirtual vo0 : ([Lf/JG0;)Lf/U90;
/*    */     //   372: invokevirtual ee0 : (Lf/U90;)Lf/U90;
/*    */     //   375: pop
/*    */     //   376: getfield o30 : Lf/U90;
/*    */     //   379: aload #4
/*    */     //   381: iconst_1
/*    */     //   382: anewarray f/JG0
/*    */     //   385: dup
/*    */     //   386: iconst_0
/*    */     //   387: aload_1
/*    */     //   388: aastore
/*    */     //   389: invokevirtual AUX : ([Lf/JG0;)Lf/U90;
/*    */     //   392: invokevirtual ee0 : (Lf/U90;)Lf/U90;
/*    */     //   395: pop
/*    */     //   396: goto -> 405
/*    */     //   399: aload_3
/*    */     //   400: aload_1
/*    */     //   401: invokestatic addAll : (Ljava/util/Collection;[Ljava/lang/Object;)Z
/*    */     //   404: pop
/*    */     //   405: aload_3
/*    */     //   406: invokevirtual iterator : ()Ljava/util/Iterator;
/*    */     //   409: astore_1
/*    */     //   410: aload_1
/*    */     //   411: invokeinterface hasNext : ()Z
/*    */     //   416: ifeq -> 903
/*    */     //   419: aload_1
/*    */     //   420: invokeinterface next : ()Ljava/lang/Object;
/*    */     //   425: checkcast f/wA0
/*    */     //   428: astore_3
/*    */     //   429: new f/dQ
/*    */     //   432: dup
/*    */     //   433: dup
/*    */     //   434: astore #5
/*    */     //   436: sipush #5663
/*    */     //   439: invokestatic OH0 : (I)Ljava/lang/String;
/*    */     //   442: astore #6
/*    */     //   444: invokespecial <init> : ()V
/*    */     //   447: aload #6
/*    */     //   449: invokevirtual E1 : (Ljava/lang/String;)V
/*    */     //   452: invokestatic XU : ()Z
/*    */     //   455: ifeq -> 509
/*    */     //   458: new f/VP
/*    */     //   461: dup
/*    */     //   462: dup2
/*    */     //   463: astore #6
/*    */     //   465: aload_3
/*    */     //   466: bipush #48
/*    */     //   468: istore #7
/*    */     //   470: bipush #48
/*    */     //   472: istore #8
/*    */     //   474: getfield ZP : Lf/FV;
/*    */     //   477: astore #9
/*    */     //   479: iload #7
/*    */     //   481: iload #8
/*    */     //   483: aload #9
/*    */     //   485: invokespecial <init> : (IILf/FV;)V
/*    */     //   488: iconst_2
/*    */     //   489: istore #7
/*    */     //   491: getfield X70 : Lf/Dn0;
/*    */     //   494: iload #7
/*    */     //   496: putfield Dd : I
/*    */     //   499: bipush #-34
/*    */     //   501: bipush #-31
/*    */     //   503: invokevirtual nx : (II)V
/*    */     //   506: goto -> 538
/*    */     //   509: new f/VP
/*    */     //   512: dup
/*    */     //   513: astore #6
/*    */     //   515: aload_3
/*    */     //   516: bipush #24
/*    */     //   518: istore #7
/*    */     //   520: bipush #24
/*    */     //   522: istore #8
/*    */     //   524: getfield ZP : Lf/FV;
/*    */     //   527: astore #9
/*    */     //   529: iload #7
/*    */     //   531: iload #8
/*    */     //   533: aload #9
/*    */     //   535: invokespecial <init> : (IILf/FV;)V
/*    */     //   538: aload #4
/*    */     //   540: dup
/*    */     //   541: aload_3
/*    */     //   542: dup
/*    */     //   543: new f/dQ
/*    */     //   546: dup
/*    */     //   547: dup
/*    */     //   548: astore #7
/*    */     //   550: sipush #9155
/*    */     //   553: invokestatic OH0 : (I)Ljava/lang/String;
/*    */     //   556: astore #8
/*    */     //   558: invokespecial <init> : ()V
/*    */     //   561: aload #8
/*    */     //   563: invokevirtual E1 : (Ljava/lang/String;)V
/*    */     //   566: getfield Xr0 : I
/*    */     //   569: istore #8
/*    */     //   571: getfield Gm : I
/*    */     //   574: istore #9
/*    */     //   576: new f/dQ
/*    */     //   579: dup
/*    */     //   580: dup
/*    */     //   581: astore #10
/*    */     //   583: new java/lang/StringBuilder
/*    */     //   586: dup
/*    */     //   587: iload #8
/*    */     //   589: swap
/*    */     //   590: invokespecial <init> : ()V
/*    */     //   593: invokevirtual append : (I)Ljava/lang/StringBuilder;
/*    */     //   596: ldc_w ' / '
/*    */     //   599: invokevirtual append : (Ljava/lang/String;)Ljava/lang/StringBuilder;
/*    */     //   602: iload #9
/*    */     //   604: invokevirtual append : (I)Ljava/lang/StringBuilder;
/*    */     //   607: invokevirtual toString : ()Ljava/lang/String;
/*    */     //   610: astore #11
/*    */     //   612: invokespecial <init> : ()V
/*    */     //   615: aload #11
/*    */     //   617: invokevirtual E1 : (Ljava/lang/String;)V
/*    */     //   620: new f/dQ
/*    */     //   623: dup
/*    */     //   624: dup
/*    */     //   625: astore #11
/*    */     //   627: sipush #5666
/*    */     //   630: invokestatic OH0 : (I)Ljava/lang/String;
/*    */     //   633: astore #12
/*    */     //   635: invokespecial <init> : ()V
/*    */     //   638: aload #12
/*    */     //   640: invokevirtual E1 : (Ljava/lang/String;)V
/*    */     //   643: new f/dQ
/*    */     //   646: dup
/*    */     //   647: astore #12
/*    */     //   649: aload #7
/*    */     //   651: aload_3
/*    */     //   652: aload #5
/*    */     //   654: aload_3
/*    */     //   655: aload #12
/*    */     //   657: aload #11
/*    */     //   659: aload #10
/*    */     //   661: aload #7
/*    */     //   663: aload #5
/*    */     //   665: aload #12
/*    */     //   667: dup
/*    */     //   668: sipush #5668
/*    */     //   671: invokestatic OH0 : (I)Ljava/lang/String;
/*    */     //   674: astore #13
/*    */     //   676: invokespecial <init> : ()V
/*    */     //   679: aload #13
/*    */     //   681: invokevirtual E1 : (Ljava/lang/String;)V
/*    */     //   684: ldc_w 'label-rank-value'
/*    */     //   687: invokevirtual Xu : (Ljava/lang/String;)V
/*    */     //   690: ldc_w 'label-name-value'
/*    */     //   693: invokevirtual Xu : (Ljava/lang/String;)V
/*    */     //   696: ldc_w 'label-winloss-value'
/*    */     //   699: invokevirtual Xu : (Ljava/lang/String;)V
/*    */     //   702: ldc_w 'label-winpercent-value'
/*    */     //   705: invokevirtual Xu : (Ljava/lang/String;)V
/*    */     //   708: ldc_w 'label-rating-value'
/*    */     //   711: invokevirtual Xu : (Ljava/lang/String;)V
/*    */     //   714: getfield G20 : S
/*    */     //   717: invokestatic toString : (I)Ljava/lang/String;
/*    */     //   720: invokevirtual E1 : (Ljava/lang/String;)V
/*    */     //   723: getfield ZP : Lf/FV;
/*    */     //   726: getfield Pb : Ljava/lang/String;
/*    */     //   729: invokevirtual E1 : (Ljava/lang/String;)V
/*    */     //   732: new java/lang/StringBuilder
/*    */     //   735: dup
/*    */     //   736: astore #13
/*    */     //   738: invokespecial <init> : ()V
/*    */     //   741: getstatic f/ve.IR : Ljava/text/DecimalFormat;
/*    */     //   744: dup
/*    */     //   745: astore #14
/*    */     //   747: aload_3
/*    */     //   748: aload #11
/*    */     //   750: aload #13
/*    */     //   752: aload #14
/*    */     //   754: iload #8
/*    */     //   756: i2d
/*    */     //   757: iload #8
/*    */     //   759: iload #9
/*    */     //   761: iadd
/*    */     //   762: i2d
/*    */     //   763: ddiv
/*    */     //   764: ldc2_w 100.0
/*    */     //   767: dmul
/*    */     //   768: invokevirtual format : (D)Ljava/lang/String;
/*    */     //   771: invokevirtual append : (Ljava/lang/String;)Ljava/lang/StringBuilder;
/*    */     //   774: ldc_w '%'
/*    */     //   777: invokevirtual append : (Ljava/lang/String;)Ljava/lang/StringBuilder;
/*    */     //   780: invokevirtual toString : ()Ljava/lang/String;
/*    */     //   783: invokevirtual E1 : (Ljava/lang/String;)V
/*    */     //   786: getfield A30 : F
/*    */     //   789: f2d
/*    */     //   790: invokevirtual format : (D)Ljava/lang/String;
/*    */     //   793: invokevirtual E1 : (Ljava/lang/String;)V
/*    */     //   796: getfield Xz0 : Lf/U90;
/*    */     //   799: new f/cr0
/*    */     //   802: dup
/*    */     //   803: aload #4
/*    */     //   805: invokespecial <init> : (Lf/Ip;)V
/*    */     //   808: bipush #6
/*    */     //   810: anewarray f/JG0
/*    */     //   813: dup
/*    */     //   814: dup
/*    */     //   815: dup2
/*    */     //   816: dup2
/*    */     //   817: iconst_0
/*    */     //   818: aload #5
/*    */     //   820: aastore
/*    */     //   821: iconst_1
/*    */     //   822: aload #6
/*    */     //   824: aastore
/*    */     //   825: iconst_2
/*    */     //   826: aload #7
/*    */     //   828: aastore
/*    */     //   829: iconst_3
/*    */     //   830: aload #10
/*    */     //   832: aastore
/*    */     //   833: iconst_4
/*    */     //   834: aload #11
/*    */     //   836: aastore
/*    */     //   837: iconst_5
/*    */     //   838: aload #12
/*    */     //   840: aastore
/*    */     //   841: invokevirtual Mg : ([Lf/JG0;)Lf/U90;
/*    */     //   844: invokevirtual ee0 : (Lf/U90;)Lf/U90;
/*    */     //   847: pop
/*    */     //   848: getfield o30 : Lf/U90;
/*    */     //   851: new f/g0
/*    */     //   854: dup
/*    */     //   855: aload #4
/*    */     //   857: invokespecial <init> : (Lf/Ip;)V
/*    */     //   860: bipush #6
/*    */     //   862: anewarray f/JG0
/*    */     //   865: dup
/*    */     //   866: dup
/*    */     //   867: dup2
/*    */     //   868: dup2
/*    */     //   869: iconst_0
/*    */     //   870: aload #5
/*    */     //   872: aastore
/*    */     //   873: iconst_1
/*    */     //   874: aload #6
/*    */     //   876: aastore
/*    */     //   877: iconst_2
/*    */     //   878: aload #7
/*    */     //   880: aastore
/*    */     //   881: iconst_3
/*    */     //   882: aload #10
/*    */     //   884: aastore
/*    */     //   885: iconst_4
/*    */     //   886: aload #11
/*    */     //   888: aastore
/*    */     //   889: iconst_5
/*    */     //   890: aload #12
/*    */     //   892: aastore
/*    */     //   893: invokevirtual Mg : ([Lf/JG0;)Lf/U90;
/*    */     //   896: invokevirtual ee0 : (Lf/U90;)Lf/U90;
/*    */     //   899: pop
/*    */     //   900: goto -> 410
/*    */     //   903: aload_0
/*    */     //   904: dup
/*    */     //   905: getfield SF0 : Lf/dQ;
/*    */     //   908: getstatic f/ve.fC0 : Ljava/text/SimpleDateFormat;
/*    */     //   911: iload_2
/*    */     //   912: i2l
/*    */     //   913: ldc2_w 1000
/*    */     //   916: lmul
/*    */     //   917: invokestatic valueOf : (J)Ljava/lang/Long;
/*    */     //   920: invokevirtual format : (Ljava/lang/Object;)Ljava/lang/String;
/*    */     //   923: sipush #5650
/*    */     //   926: swap
/*    */     //   927: invokestatic Go : (ILjava/lang/String;)Ljava/lang/String;
/*    */     //   930: invokevirtual E1 : (Ljava/lang/String;)V
/*    */     //   933: getfield EP : Lf/rS;
/*    */     //   936: aload #4
/*    */     //   938: invokevirtual Gz0 : (Lf/JG0;)V
/*    */     //   941: return
/*    */     // Line number table:
/*    */     //   Java source line number -> byte code offset
/*    */     //   #1	-> 15
/*    */     //   #2	-> 23
/*    */     //   #3	-> 35
/*    */     //   #4	-> 43
/*    */     //   #5	-> 58
/*    */     //   #6	-> 66
/*    */     //   #7	-> 82
/*    */     //   #8	-> 93
/*    */     //   #9	-> 96
/*    */     //   #10	-> 102
/*    */     //   #11	-> 117
/*    */     //   #12	-> 125
/*    */     //   #13	-> 151
/*    */     //   #14	-> 159
/*    */     //   #15	-> 206
/*    */     //   #16	-> 215
/*    */     //   #17	-> 218
/*    */     //   #18	-> 227
/*    */     //   #19	-> 230
/*    */     //   #20	-> 233
/*    */     //   #21	-> 243
/*    */     //   #22	-> 275
/*    */     //   #23	-> 278
/*    */     //   #24	-> 288
/*    */     //   #25	-> 348
/*    */     //   #26	-> 356
/*    */     //   #27	-> 362
/*    */     //   #28	-> 376
/*    */     //   #29	-> 382
/*    */     //   #30	-> 444
/*    */     //   #31	-> 452
/*    */     //   #32	-> 474
/*    */     //   #33	-> 485
/*    */     //   #34	-> 491
/*    */     //   #35	-> 496
/*    */     //   #36	-> 503
/*    */     //   #37	-> 524
/*    */     //   #38	-> 535
/*    */     //   #39	-> 558
/*    */     //   #40	-> 566
/*    */     //   #41	-> 571
/*    */     //   #42	-> 576
/*    */     //   #43	-> 612
/*    */     //   #44	-> 620
/*    */     //   #45	-> 635
/*    */     //   #46	-> 643
/*    */     //   #47	-> 676
/*    */     //   #48	-> 684
/*    */     //   #49	-> 714
/*    */     //   #50	-> 717
/*    */     //   #51	-> 723
/*    */     //   #52	-> 726
/*    */     //   #53	-> 729
/*    */     //   #54	-> 786
/*    */     //   #55	-> 790
/*    */     //   #56	-> 796
/*    */     //   #57	-> 799
/*    */     //   #58	-> 810
/*    */     //   #59	-> 848
/*    */     //   #60	-> 851
/*  9 */     //   #61	-> 862 } private void X6(short paramShort, byte paramByte, HS[] paramArrayOfHS) { String str = Ml0.OH0(5659); this(); Ip ip; dQ dQ1; Un un1, un2, un3; (new dQ()).E1(str); this(Ml0.OH0(5669)); this(Ml0.OH0(5661)); this(Ml0.OH0(5668)); this(); dQ2.E1(""); dQ1.Xu("label-battle"); un1.Xu("label-tier"); un1.tW(() -> { Comparator comparator; if (this.jZ == (comparator = HS.d10)) { this.jZ = comparator.reversed(); } else { this.jZ = comparator; }  kO(paramShort, paramByte, paramArrayOfHS); }); un3.Xu("label-rating"); un3.tW(() -> { Comparator comparator; if (this.jZ == (comparator = HS.hp)) { this.jZ = comparator.reversed(); } else { this.jZ = comparator; }  kO(paramShort, paramByte, paramArrayOfHS); }); un2.Xu("label-duration"); un2.tW(() -> { Comparator comparator; if (this.jZ == (comparator = HS.yr0)) { this.jZ = comparator.reversed(); } else { this.jZ = comparator; }  kO(paramShort, paramByte, paramArrayOfHS); }); dQ dQ2; (dQ2 = new dQ()).Xu("label-vs"); this(); (new Ip()).rK0(new g0(ip)); (new Ip()).WN(new cr0(ip)); (new Ip()).Xz0
/*    */       
/* 11 */       .ee0((new cr0(ip)).Mg(new JG0[] { dQ1, un1, un3, un2, dQ2 }));
/* 12 */     (new Ip()).o30
/*    */       
/* 14 */       .ee0((new g0(ip)).Mg(new JG0[] { dQ1, un1, un3, un2, dQ2 })); for (this.A90 = new Un[paramArrayOfHS.length], paramByte = 0; paramByte < paramArrayOfHS.length; )
/*    */     { dQ dQ3; VP vP; dQ dQ6; Un un; HS hS;
/*    */       FV[] arrayOfFV;
/* 17 */       String str1 = ((arrayOfFV = (hS = paramArrayOfHS[paramByte]).pi)[0]).Pb;
/*    */       
/* 19 */       String str2 = ((hS = paramArrayOfHS[paramByte]).pi[1]).Pb;
/* 20 */       if (!km.XU()) { if (str1.length() >= 10) str1 = str1.substring(0, 8) + "...";  if (str2.length() >= 10) str2 = str2.substring(0, 8) + "...";  }  if (km.XU()) { FV fV1 = arrayOfFV[0]; super(50, 36, fV1); FV fV2 = arrayOfFV[1]; this(50, 36, fV2);
/* 21 */         ((VP)dQ2).X70
/* 22 */           .Dd = 2;
/* 23 */         dQ2.nx(-32, -36);
/* 24 */         (vP = new VP()).X70
/* 25 */           .Dd = 2;
/* 26 */         (new VP()).nx(-32, -36); } else { FV fV1 = arrayOfFV[0]; super(21, 24, fV1); FV fV2 = arrayOfFV[1]; this(21, 24, fV2); dQ2.nx(-17, -12); (vP = new VP()).nx(-17, -12); }
/* 27 */        dQ dQ4 = P6.A(str1);
/*    */       
/* 29 */       String str3 = Ml0.OH0(5024);
/* 30 */       this(); (new dQ()).E1(str3);
/*    */ 
/*    */       
/* 33 */       dQ4.z4 = (arrayOfFV[0]).Pb; dQ4.zn();
/*    */       
/*    */       dQ dQ5;
/* 36 */       (dQ5 = P6.A(str2)).z4 = (arrayOfFV[1]).Pb; P6.A(str2).zn(); int i;
/* 37 */       if ((i = hS.gY) < 1)
/* 38 */       { dQ6 = P6.A("--"); }
/* 39 */       else { dQ dQ9; String str6 = dQ6 + "+";
/* 40 */         this(); (new dQ()).E1(str6); dQ6 = dQ9; }
/* 41 */        dQ dQ7 = new dQ(); DK dK;
/* 42 */       if ((dK = hS.bA) == DK.L || dK == DK.d70) {  }
/*    */       else
/*    */       {  }
/* 45 */        String str4 = Ml0.OH0(dK.G70.st);
/* 46 */       this(); dQ7.E1(str4);
/*    */ 
/*    */       
/* 49 */       String str5 = LF.Ya((int)(System.currentTimeMillis() / 1000L) - hS.prn, 1);
/* 50 */       this(); dQ8.E1(str5);
/* 51 */       this("➤"); this.A90[paramByte] = un; this.A90[paramByte].Xu("button-symbol"); this.A90[paramByte].tW(hS::oF0); dQ4.Xu("label-name-spectate-value-button"); dQ5.Xu("label-name-spectate-value-button"); dQ3.Xu("label-vs-value"); dQ7.Xu("label-tier-value"); dQ6.Xu("label-rating-value"); dQ dQ8; (dQ8 = new dQ()).Xu("label-duration-value");
/* 52 */       ip.Xz0
/*    */         
/* 54 */         .ee0((new cr0(ip)).Mg(new JG0[] { dQ2, dQ4, dQ3, vP, dQ5, dQ7, dQ6, dQ8, this.A90[paramByte] }));
/* 55 */       ip.o30
/*    */         
/* 57 */         .ee0((new g0(ip)).Mg(new JG0[] { dQ2, dQ4, dQ3, vP, dQ5, dQ7, dQ6, dQ8, this.A90[paramByte] })); paramByte++; }  if (paramArrayOfHS.length < 1) { dQ dQ3; String str1 = Ml0.OH0(5662);
/* 58 */       this(); (new dQ()).E1(str1);
/* 59 */       (new dQ()).Xu("label-name");
/* 60 */       ip.Xz0
/*    */         
/* 62 */         .ee0((new cr0(ip)).Mg(new JG0[] { dQ3 }));
/* 63 */       ip.o30
/*    */         
/* 65 */         .ee0((new g0(ip)).Mg(new JG0[] { dQ3 })); }  this.bF.Gz0(ip); }
/*    */ 
/*    */   
/*    */   public static void oF0(HS paramHS) {
/*    */     R8 r8 = km.u4;
/*    */     int i = paramHS.S90;
/*    */     r8.e20.W3(new PG0(i));
/*    */   }
/*    */   
/*    */   private void wv0() {
/*    */     LJ0(false, true);
/*    */   }
/*    */   
/*    */   private void P1() {
/*    */     if (this.BB != null || this.WL > 0)
/*    */       LJ0(true, true); 
/*    */   }
/*    */   
/*    */   private void nJ(Li0 paramLi0) {
/*    */     if (paramLi0 == this.zH0.zO) {
/*    */       this.La0 = 0;
/*    */       boolean bool = false;
/*    */       String str = "";
/*    */       km.u4.e20.W3(new gj0(bool, str));
/*    */     } 
/*    */   }
/*    */   
/*    */   private void cI0(int paramInt) {
/*    */     // Byte code:
/*    */     //   0: aload_0
/*    */     //   1: ldc2_w 250
/*    */     //   4: lstore_2
/*    */     //   5: getfield nl0 : Lf/oo;
/*    */     //   8: dup
/*    */     //   9: astore_1
/*    */     //   10: ifnull -> 69
/*    */     //   13: aload_1
/*    */     //   14: dup
/*    */     //   15: monitorenter
/*    */     //   16: getfield lu0 : J
/*    */     //   19: aload_1
/*    */     //   20: monitorexit
/*    */     //   21: lconst_0
/*    */     //   22: lcmp
/*    */     //   23: ifle -> 69
/*    */     //   26: aload_0
/*    */     //   27: dup
/*    */     //   28: dup
/*    */     //   29: getfield nl0 : Lf/oo;
/*    */     //   32: dup
/*    */     //   33: dup
/*    */     //   34: astore_1
/*    */     //   35: monitorenter
/*    */     //   36: getfield lu0 : J
/*    */     //   39: aload_1
/*    */     //   40: monitorexit
/*    */     //   41: invokestatic nanoTime : ()J
/*    */     //   44: ldc2_w 1000000
/*    */     //   47: ldiv
/*    */     //   48: lsub
/*    */     //   49: lstore_2
/*    */     //   50: getfield nl0 : Lf/oo;
/*    */     //   53: invokevirtual uw0 : ()V
/*    */     //   56: aconst_null
/*    */     //   57: putfield nl0 : Lf/oo;
/*    */     //   60: goto -> 69
/*    */     //   63: aload_1
/*    */     //   64: monitorexit
/*    */     //   65: athrow
/*    */     //   66: aload_1
/*    */     //   67: monitorexit
/*    */     //   68: athrow
/*    */     //   69: aload_0
/*    */     //   70: lload_2
/*    */     //   71: new f/Qh
/*    */     //   74: dup
/*    */     //   75: astore_1
/*    */     //   76: aload_0
/*    */     //   77: invokespecial <init> : (Lf/ve;)V
/*    */     //   80: l2f
/*    */     //   81: ldc_w 1000.0
/*    */     //   84: fdiv
/*    */     //   85: fstore_0
/*    */     //   86: invokestatic k6 : ()Lf/HC;
/*    */     //   89: aload_1
/*    */     //   90: fload_0
/*    */     //   91: invokevirtual S : (Lf/oo;F)Lf/oo;
/*    */     //   94: putfield nl0 : Lf/oo;
/*    */     //   97: return
/*    */     // Line number table:
/*    */     //   Java source line number -> byte code offset
/*    */     //   #1	-> 5
/*    */     //   #2	-> 16
/*    */     //   #3	-> 29
/*    */     //   #4	-> 36
/*    */     //   #5	-> 41
/*    */     //   #6	-> 86
/*    */     //   #7	-> 94
/*    */     // Exception table:
/*    */     //   from	to	target	type
/*    */     //   16	19	66	finally
/*    */     //   36	39	63	finally
/*    */   }
/*    */   
/*    */   private void gx0(DK paramDK) {
/*    */     this.Bg = paramDK;
/*    */     tn0();
/*    */   }
/*    */   
/*    */   public static String db(DK paramDK) {
/*    */     DK[] arrayOfDK;
/*    */     int i;
/*    */     byte b;
/*    */     for (i = (arrayOfDK = DK.gw).length, b = 0; b < i; ) {
/*    */       DK dK;
/*    */       if (!(dK = arrayOfDK[b]).Iq && dK.Qu == paramDK.Qu)
/*    */         return dK.toString(); 
/*    */       b++;
/*    */     } 
/*    */     return "";
/*    */   }
/*    */   
/*    */   public final void tn0() {
/*    */     this.Ic0 = new Ip();
/*    */     (this.EP = new rS(null)).Xu("stats");
/*    */     String str = Ml0.OH0(74);
/*    */     (new dQ()).E1(str);
/*    */     this.EP.Gz0(new dQ());
/*    */     str = Ml0.Go(5650, "-");
/*    */     (new dQ()).E1(str);
/*    */     (this.SF0 = new dQ()).Xu("label-leaderboard-updated-time");
/*    */     byte b = km.u4.cJ0;
/*    */     this();
/*    */     OZ oZ;
/*    */     ArrayList<String> arrayList;
/*    */     for (byte b1 = 0; b1 <= b; ) {
/*    */       String str1;
/*    */       if (b1 == 0) {
/*    */         str1 = Ml0.OH0(5495);
/*    */       } else {
/*    */         str1 = Ml0.Go(5496, Integer.toString(b1));
/*    */       } 
/*    */       arrayList.add(str1);
/*    */       b1 = (byte)(b1 + 1);
/*    */     } 
/*    */     this(arrayList);
/*    */     this();
/*    */     w1.rk0(oZ);
/*    */     this.e20 = w1;
/*    */     W1 w1;
/*    */     (w1 = new W1()).Z30(arrayList.size() - 1);
/*    */     this.e20.D30(this::nB);
/*    */     this.Ic0.rK0(this.Ic0.AUX(new JG0[] { this.EP }).ee0(this.Ic0.vo0(new JG0[] { this.e20 }).Em0().Ya(this.SF0)));
/*    */     this.Ic0.WN(this.Ic0.vo0(new JG0[] { this.EP }).ee0(this.Ic0.AUX(new JG0[] { this.e20, this.SF0 })));
/*    */     this.p10.zO.qs0(this.Ic0);
/*    */     nB();
/*    */   }
/*    */   
/*    */   public final void j8() {
/*    */     // Byte code:
/*    */     //   0: aload_0
/*    */     //   1: new java/util/ArrayList
/*    */     //   4: dup
/*    */     //   5: astore_1
/*    */     //   6: invokespecial <init> : ()V
/*    */     //   9: new f/Un
/*    */     //   12: dup
/*    */     //   13: astore_2
/*    */     //   14: aload_0
/*    */     //   15: dup
/*    */     //   16: aload_2
/*    */     //   17: dup
/*    */     //   18: bipush #65
/*    */     //   20: invokestatic OH0 : (I)Ljava/lang/String;
/*    */     //   23: invokespecial <init> : (Ljava/lang/String;)V
/*    */     //   26: putfield Bm : Lf/Un;
/*    */     //   29: <illegal opcode> run : (Lf/ve;)Ljava/lang/Runnable;
/*    */     //   34: invokevirtual tW : (Ljava/lang/Runnable;)V
/*    */     //   37: new f/Ip
/*    */     //   40: dup
/*    */     //   41: dup2
/*    */     //   42: astore_2
/*    */     //   43: invokespecial <init> : ()V
/*    */     //   46: new f/cr0
/*    */     //   49: dup
/*    */     //   50: aload_2
/*    */     //   51: invokespecial <init> : (Lf/Ip;)V
/*    */     //   54: invokevirtual WN : (Lf/U90;)V
/*    */     //   57: new f/g0
/*    */     //   60: dup
/*    */     //   61: aload_2
/*    */     //   62: invokespecial <init> : (Lf/Ip;)V
/*    */     //   65: invokevirtual rK0 : (Lf/U90;)V
/*    */     //   68: new f/g0
/*    */     //   71: dup
/*    */     //   72: astore_3
/*    */     //   73: aload_2
/*    */     //   74: invokespecial <init> : (Lf/Ip;)V
/*    */     //   77: new f/cr0
/*    */     //   80: dup
/*    */     //   81: astore #4
/*    */     //   83: aload_2
/*    */     //   84: invokespecial <init> : (Lf/Ip;)V
/*    */     //   87: getfield Oh0 : Z
/*    */     //   90: ifeq -> 275
/*    */     //   93: aload_0
/*    */     //   94: dup
/*    */     //   95: aload_2
/*    */     //   96: ldc_w 'tournament-signup'
/*    */     //   99: invokevirtual Xu : (Ljava/lang/String;)V
/*    */     //   102: getfield TC : [Lf/qa0;
/*    */     //   105: arraylength
/*    */     //   106: anewarray f/Df
/*    */     //   109: putfield Xg : [Lf/Df;
/*    */     //   112: iconst_0
/*    */     //   113: istore #5
/*    */     //   115: iload #5
/*    */     //   117: aload_0
/*    */     //   118: getfield TC : [Lf/qa0;
/*    */     //   121: dup
/*    */     //   122: astore #6
/*    */     //   124: arraylength
/*    */     //   125: if_icmpge -> 268
/*    */     //   128: iload #5
/*    */     //   130: aload_3
/*    */     //   131: aload #4
/*    */     //   133: dup
/*    */     //   134: aload_0
/*    */     //   135: dup
/*    */     //   136: getfield Xg : [Lf/Df;
/*    */     //   139: iload #5
/*    */     //   141: new f/Df
/*    */     //   144: dup
/*    */     //   145: aload_0
/*    */     //   146: aload #6
/*    */     //   148: iload #5
/*    */     //   150: aaload
/*    */     //   151: invokespecial <init> : (Lf/ve;Lf/qa0;)V
/*    */     //   154: aastore
/*    */     //   155: getfield Xg : [Lf/Df;
/*    */     //   158: iload #5
/*    */     //   160: aaload
/*    */     //   161: getfield mK : Lf/Ip;
/*    */     //   164: astore #6
/*    */     //   166: invokevirtual Em0 : ()Lf/U90;
/*    */     //   169: pop
/*    */     //   170: aload #6
/*    */     //   172: invokevirtual Ya : (Lf/JG0;)Lf/U90;
/*    */     //   175: pop
/*    */     //   176: aload #6
/*    */     //   178: invokevirtual Ya : (Lf/JG0;)Lf/U90;
/*    */     //   181: pop
/*    */     //   182: ifle -> 241
/*    */     //   185: iload #5
/*    */     //   187: iconst_1
/*    */     //   188: iadd
/*    */     //   189: iconst_2
/*    */     //   190: irem
/*    */     //   191: ifne -> 241
/*    */     //   194: aload_2
/*    */     //   195: dup
/*    */     //   196: aload #4
/*    */     //   198: invokevirtual Em0 : ()Lf/U90;
/*    */     //   201: pop
/*    */     //   202: getfield o30 : Lf/U90;
/*    */     //   205: aload_3
/*    */     //   206: invokevirtual ee0 : (Lf/U90;)Lf/U90;
/*    */     //   209: pop
/*    */     //   210: getfield Xz0 : Lf/U90;
/*    */     //   213: aload #4
/*    */     //   215: invokevirtual ee0 : (Lf/U90;)Lf/U90;
/*    */     //   218: pop
/*    */     //   219: new f/g0
/*    */     //   222: dup
/*    */     //   223: astore_3
/*    */     //   224: aload_2
/*    */     //   225: invokespecial <init> : (Lf/Ip;)V
/*    */     //   228: new f/cr0
/*    */     //   231: dup
/*    */     //   232: astore #4
/*    */     //   234: aload_2
/*    */     //   235: invokespecial <init> : (Lf/Ip;)V
/*    */     //   238: goto -> 247
/*    */     //   241: aload #4
/*    */     //   243: invokevirtual Em0 : ()Lf/U90;
/*    */     //   246: pop
/*    */     //   247: aload_1
/*    */     //   248: aload_0
/*    */     //   249: getfield Xg : [Lf/Df;
/*    */     //   252: iload #5
/*    */     //   254: aaload
/*    */     //   255: getfield K8 : Lf/Un;
/*    */     //   258: invokevirtual add : (Ljava/lang/Object;)Z
/*    */     //   261: pop
/*    */     //   262: iinc #5, 1
/*    */     //   265: goto -> 115
/*    */     //   268: aload_0
/*    */     //   269: invokevirtual update : ()V
/*    */     //   272: goto -> 1059
/*    */     //   275: aload_0
/*    */     //   276: dup
/*    */     //   277: iconst_0
/*    */     //   278: anewarray f/Df
/*    */     //   281: putfield Xg : [Lf/Df;
/*    */     //   284: getfield IC : Ljava/util/ArrayList;
/*    */     //   287: invokevirtual clear : ()V
/*    */     //   290: new f/Ip
/*    */     //   293: dup
/*    */     //   294: dup2
/*    */     //   295: dup2
/*    */     //   296: astore #5
/*    */     //   298: invokespecial <init> : ()V
/*    */     //   301: ldc_w 'game-mode'
/*    */     //   304: invokevirtual Xu : (Ljava/lang/String;)V
/*    */     //   307: new f/cr0
/*    */     //   310: dup
/*    */     //   311: astore #6
/*    */     //   313: aload #5
/*    */     //   315: invokespecial <init> : (Lf/Ip;)V
/*    */     //   318: new f/g0
/*    */     //   321: dup
/*    */     //   322: astore #7
/*    */     //   324: aload #5
/*    */     //   326: invokespecial <init> : (Lf/Ip;)V
/*    */     //   329: invokevirtual GH0 : ()V
/*    */     //   332: aload #6
/*    */     //   334: invokevirtual WN : (Lf/U90;)V
/*    */     //   337: aload #7
/*    */     //   339: invokevirtual rK0 : (Lf/U90;)V
/*    */     //   342: iconst_0
/*    */     //   343: istore #8
/*    */     //   345: iload #8
/*    */     //   347: getstatic f/DK.aB : I
/*    */     //   350: if_icmpgt -> 1035
/*    */     //   353: getstatic f/DK.gw : [Lf/DK;
/*    */     //   356: dup
/*    */     //   357: astore #9
/*    */     //   359: arraylength
/*    */     //   360: istore #10
/*    */     //   362: iconst_0
/*    */     //   363: istore #11
/*    */     //   365: iload #11
/*    */     //   367: iload #10
/*    */     //   369: if_icmpge -> 405
/*    */     //   372: aload #9
/*    */     //   374: iload #11
/*    */     //   376: aaload
/*    */     //   377: dup
/*    */     //   378: astore #12
/*    */     //   380: getfield Qu : I
/*    */     //   383: iload #8
/*    */     //   385: if_icmpne -> 399
/*    */     //   388: aload #12
/*    */     //   390: getfield Iq : Z
/*    */     //   393: ifne -> 399
/*    */     //   396: goto -> 408
/*    */     //   399: iinc #11, 1
/*    */     //   402: goto -> 365
/*    */     //   405: aconst_null
/*    */     //   406: astore #12
/*    */     //   408: iconst_1
/*    */     //   409: istore #9
/*    */     //   411: getstatic f/DK.gw : [Lf/DK;
/*    */     //   414: dup
/*    */     //   415: astore #10
/*    */     //   417: arraylength
/*    */     //   418: istore #11
/*    */     //   420: iconst_0
/*    */     //   421: istore #13
/*    */     //   423: iload #13
/*    */     //   425: iload #11
/*    */     //   427: if_icmpge -> 465
/*    */     //   430: aload #10
/*    */     //   432: iload #13
/*    */     //   434: aaload
/*    */     //   435: dup
/*    */     //   436: astore #14
/*    */     //   438: getfield Qu : I
/*    */     //   441: iload #8
/*    */     //   443: if_icmpne -> 459
/*    */     //   446: aload #14
/*    */     //   448: getfield Iq : Z
/*    */     //   451: iload #9
/*    */     //   453: if_icmpne -> 459
/*    */     //   456: goto -> 468
/*    */     //   459: iinc #13, 1
/*    */     //   462: goto -> 423
/*    */     //   465: aconst_null
/*    */     //   466: astore #14
/*    */     //   468: aload #12
/*    */     //   470: ifnull -> 1029
/*    */     //   473: aload #14
/*    */     //   475: ifnonnull -> 481
/*    */     //   478: goto -> 1029
/*    */     //   481: aload #12
/*    */     //   483: getfield yg0 : Z
/*    */     //   486: ifne -> 500
/*    */     //   489: aload #14
/*    */     //   491: getfield yg0 : Z
/*    */     //   494: ifne -> 500
/*    */     //   497: goto -> 1029
/*    */     //   500: aload_0
/*    */     //   501: new f/pC
/*    */     //   504: dup
/*    */     //   505: astore #9
/*    */     //   507: aload_0
/*    */     //   508: dup
/*    */     //   509: dup
/*    */     //   510: getfield dp : [Lf/CC0;
/*    */     //   513: astore #10
/*    */     //   515: getfield El : Ljava/util/ArrayList;
/*    */     //   518: astore #11
/*    */     //   520: aload #12
/*    */     //   522: aload #14
/*    */     //   524: aload #10
/*    */     //   526: aload #11
/*    */     //   528: invokespecial <init> : (Lf/ve;Lf/DK;Lf/DK;[Lf/CC0;Ljava/util/List;)V
/*    */     //   531: getfield IC : Ljava/util/ArrayList;
/*    */     //   534: aload #9
/*    */     //   536: invokevirtual add : (Ljava/lang/Object;)Z
/*    */     //   539: pop
/*    */     //   540: new f/dQ
/*    */     //   543: dup
/*    */     //   544: dup2
/*    */     //   545: astore #10
/*    */     //   547: aload #12
/*    */     //   549: new java/lang/StringBuilder
/*    */     //   552: dup
/*    */     //   553: astore #11
/*    */     //   555: invokespecial <init> : ()V
/*    */     //   558: getfield Hc : I
/*    */     //   561: aload #11
/*    */     //   563: ldc_w ':'
/*    */     //   566: invokestatic jJ0 : (ILjava/lang/StringBuilder;Ljava/lang/String;)Ljava/lang/String;
/*    */     //   569: astore #11
/*    */     //   571: invokespecial <init> : ()V
/*    */     //   574: aload #11
/*    */     //   576: invokevirtual E1 : (Ljava/lang/String;)V
/*    */     //   579: ldc_w 'label-game-mode'
/*    */     //   582: invokevirtual Xu : (Ljava/lang/String;)V
/*    */     //   585: iconst_1
/*    */     //   586: anewarray f/U90
/*    */     //   589: astore #11
/*    */     //   591: iconst_0
/*    */     //   592: istore #12
/*    */     //   594: new f/cr0
/*    */     //   597: dup
/*    */     //   598: aload #5
/*    */     //   600: swap
/*    */     //   601: aload #5
/*    */     //   603: invokespecial <init> : (Lf/Ip;)V
/*    */     //   606: iconst_1
/*    */     //   607: anewarray f/JG0
/*    */     //   610: dup
/*    */     //   611: iconst_0
/*    */     //   612: aload #10
/*    */     //   614: aastore
/*    */     //   615: invokevirtual AUX : ([Lf/JG0;)Lf/U90;
/*    */     //   618: invokevirtual ee0 : (Lf/U90;)Lf/U90;
/*    */     //   621: astore #13
/*    */     //   623: invokestatic XU : ()Z
/*    */     //   626: ifeq -> 636
/*    */     //   629: bipush #28
/*    */     //   631: istore #14
/*    */     //   633: goto -> 639
/*    */     //   636: iconst_4
/*    */     //   637: istore #14
/*    */     //   639: aload #13
/*    */     //   641: iload #14
/*    */     //   643: invokevirtual Aq : (I)Lf/U90;
/*    */     //   646: iconst_2
/*    */     //   647: anewarray f/U90
/*    */     //   650: dup
/*    */     //   651: dup
/*    */     //   652: aload #5
/*    */     //   654: swap
/*    */     //   655: aload #5
/*    */     //   657: iconst_1
/*    */     //   658: anewarray f/JG0
/*    */     //   661: dup
/*    */     //   662: aload #9
/*    */     //   664: getfield Wf : Lf/ge0;
/*    */     //   667: iconst_0
/*    */     //   668: swap
/*    */     //   669: aastore
/*    */     //   670: invokevirtual AUX : ([Lf/JG0;)Lf/U90;
/*    */     //   673: iconst_0
/*    */     //   674: swap
/*    */     //   675: aastore
/*    */     //   676: iconst_1
/*    */     //   677: anewarray f/JG0
/*    */     //   680: dup
/*    */     //   681: aload #9
/*    */     //   683: getfield ZT : Lf/dQ;
/*    */     //   686: iconst_0
/*    */     //   687: swap
/*    */     //   688: aastore
/*    */     //   689: invokevirtual AUX : ([Lf/JG0;)Lf/U90;
/*    */     //   692: iconst_1
/*    */     //   693: swap
/*    */     //   694: aastore
/*    */     //   695: invokevirtual cOM8 : ([Lf/U90;)Lf/U90;
/*    */     //   698: astore #13
/*    */     //   700: invokestatic XU : ()Z
/*    */     //   703: ifeq -> 713
/*    */     //   706: bipush #92
/*    */     //   708: istore #14
/*    */     //   710: goto -> 717
/*    */     //   713: bipush #29
/*    */     //   715: istore #14
/*    */     //   717: aload_1
/*    */     //   718: aload #9
/*    */     //   720: aload_1
/*    */     //   721: aload #9
/*    */     //   723: aload #6
/*    */     //   725: aload #7
/*    */     //   727: aload #6
/*    */     //   729: aload #7
/*    */     //   731: aload #11
/*    */     //   733: dup
/*    */     //   734: iload #12
/*    */     //   736: aload #13
/*    */     //   738: iload #14
/*    */     //   740: invokevirtual Aq : (I)Lf/U90;
/*    */     //   743: iconst_2
/*    */     //   744: anewarray f/U90
/*    */     //   747: dup
/*    */     //   748: dup
/*    */     //   749: aload #5
/*    */     //   751: swap
/*    */     //   752: aload #5
/*    */     //   754: iconst_1
/*    */     //   755: anewarray f/JG0
/*    */     //   758: dup
/*    */     //   759: aload #9
/*    */     //   761: getfield ar : Lf/ge0;
/*    */     //   764: iconst_0
/*    */     //   765: swap
/*    */     //   766: aastore
/*    */     //   767: invokevirtual AUX : ([Lf/JG0;)Lf/U90;
/*    */     //   770: iconst_0
/*    */     //   771: swap
/*    */     //   772: aastore
/*    */     //   773: iconst_1
/*    */     //   774: anewarray f/JG0
/*    */     //   777: dup
/*    */     //   778: aload #9
/*    */     //   780: getfield WJ : Lf/dQ;
/*    */     //   783: iconst_0
/*    */     //   784: swap
/*    */     //   785: aastore
/*    */     //   786: invokevirtual AUX : ([Lf/JG0;)Lf/U90;
/*    */     //   789: iconst_1
/*    */     //   790: swap
/*    */     //   791: aastore
/*    */     //   792: invokevirtual cOM8 : ([Lf/U90;)Lf/U90;
/*    */     //   795: aastore
/*    */     //   796: invokevirtual cOM8 : ([Lf/U90;)Lf/U90;
/*    */     //   799: pop
/*    */     //   800: new f/g0
/*    */     //   803: dup
/*    */     //   804: aload #5
/*    */     //   806: invokespecial <init> : (Lf/Ip;)V
/*    */     //   809: iconst_5
/*    */     //   810: anewarray f/U90
/*    */     //   813: dup
/*    */     //   814: dup
/*    */     //   815: astore #11
/*    */     //   817: aload #5
/*    */     //   819: aload #11
/*    */     //   821: aload #5
/*    */     //   823: aload #11
/*    */     //   825: aload #5
/*    */     //   827: aload #11
/*    */     //   829: aload #5
/*    */     //   831: aload #11
/*    */     //   833: aload #5
/*    */     //   835: iconst_1
/*    */     //   836: anewarray f/JG0
/*    */     //   839: dup
/*    */     //   840: iconst_0
/*    */     //   841: aload #10
/*    */     //   843: aastore
/*    */     //   844: invokevirtual vo0 : ([Lf/JG0;)Lf/U90;
/*    */     //   847: iconst_0
/*    */     //   848: swap
/*    */     //   849: aastore
/*    */     //   850: iconst_1
/*    */     //   851: anewarray f/JG0
/*    */     //   854: dup
/*    */     //   855: aload #9
/*    */     //   857: getfield Wf : Lf/ge0;
/*    */     //   860: iconst_0
/*    */     //   861: swap
/*    */     //   862: aastore
/*    */     //   863: invokevirtual vo0 : ([Lf/JG0;)Lf/U90;
/*    */     //   866: iconst_1
/*    */     //   867: swap
/*    */     //   868: aastore
/*    */     //   869: iconst_1
/*    */     //   870: anewarray f/JG0
/*    */     //   873: dup
/*    */     //   874: aload #9
/*    */     //   876: getfield ZT : Lf/dQ;
/*    */     //   879: iconst_0
/*    */     //   880: swap
/*    */     //   881: aastore
/*    */     //   882: invokevirtual vo0 : ([Lf/JG0;)Lf/U90;
/*    */     //   885: iconst_2
/*    */     //   886: swap
/*    */     //   887: aastore
/*    */     //   888: iconst_1
/*    */     //   889: anewarray f/JG0
/*    */     //   892: dup
/*    */     //   893: aload #9
/*    */     //   895: getfield ar : Lf/ge0;
/*    */     //   898: iconst_0
/*    */     //   899: swap
/*    */     //   900: aastore
/*    */     //   901: invokevirtual vo0 : ([Lf/JG0;)Lf/U90;
/*    */     //   904: iconst_3
/*    */     //   905: swap
/*    */     //   906: aastore
/*    */     //   907: iconst_1
/*    */     //   908: anewarray f/JG0
/*    */     //   911: dup
/*    */     //   912: aload #9
/*    */     //   914: getfield WJ : Lf/dQ;
/*    */     //   917: iconst_0
/*    */     //   918: swap
/*    */     //   919: aastore
/*    */     //   920: invokevirtual vo0 : ([Lf/JG0;)Lf/U90;
/*    */     //   923: iconst_4
/*    */     //   924: swap
/*    */     //   925: aastore
/*    */     //   926: invokevirtual cOM8 : ([Lf/U90;)Lf/U90;
/*    */     //   929: invokevirtual ee0 : (Lf/U90;)Lf/U90;
/*    */     //   932: pop
/*    */     //   933: new f/cr0
/*    */     //   936: dup
/*    */     //   937: aload #5
/*    */     //   939: invokespecial <init> : (Lf/Ip;)V
/*    */     //   942: iconst_1
/*    */     //   943: invokevirtual Aq : (I)Lf/U90;
/*    */     //   946: aload #9
/*    */     //   948: getfield BD0 : Lf/W1;
/*    */     //   951: invokevirtual Ya : (Lf/JG0;)Lf/U90;
/*    */     //   954: iconst_5
/*    */     //   955: invokevirtual Aq : (I)Lf/U90;
/*    */     //   958: aload #9
/*    */     //   960: getfield ht0 : [Lf/iB;
/*    */     //   963: invokevirtual Mg : ([Lf/JG0;)Lf/U90;
/*    */     //   966: invokevirtual Em0 : ()Lf/U90;
/*    */     //   969: invokevirtual ee0 : (Lf/U90;)Lf/U90;
/*    */     //   972: pop
/*    */     //   973: new f/cr0
/*    */     //   976: dup
/*    */     //   977: aload #5
/*    */     //   979: invokespecial <init> : (Lf/Ip;)V
/*    */     //   982: iconst_1
/*    */     //   983: anewarray f/U90
/*    */     //   986: dup
/*    */     //   987: aload #5
/*    */     //   989: aload #9
/*    */     //   991: getfield ht0 : [Lf/iB;
/*    */     //   994: invokevirtual AUX : ([Lf/JG0;)Lf/U90;
/*    */     //   997: aload #9
/*    */     //   999: getfield BD0 : Lf/W1;
/*    */     //   1002: invokevirtual Ya : (Lf/JG0;)Lf/U90;
/*    */     //   1005: iconst_0
/*    */     //   1006: swap
/*    */     //   1007: aastore
/*    */     //   1008: invokevirtual cOM8 : ([Lf/U90;)Lf/U90;
/*    */     //   1011: invokevirtual ee0 : (Lf/U90;)Lf/U90;
/*    */     //   1014: pop
/*    */     //   1015: getfield Wf : Lf/ge0;
/*    */     //   1018: invokevirtual add : (Ljava/lang/Object;)Z
/*    */     //   1021: pop
/*    */     //   1022: getfield ar : Lf/ge0;
/*    */     //   1025: invokevirtual add : (Ljava/lang/Object;)Z
/*    */     //   1028: pop
/*    */     //   1029: iinc #8, 1
/*    */     //   1032: goto -> 345
/*    */     //   1035: aload_1
/*    */     //   1036: aload_0
/*    */     //   1037: aload_3
/*    */     //   1038: aload #5
/*    */     //   1040: aload #4
/*    */     //   1042: aload #5
/*    */     //   1044: invokevirtual Ya : (Lf/JG0;)Lf/U90;
/*    */     //   1047: pop
/*    */     //   1048: invokevirtual Ya : (Lf/JG0;)Lf/U90;
/*    */     //   1051: pop
/*    */     //   1052: getfield DY : Lf/Un;
/*    */     //   1055: invokevirtual add : (Ljava/lang/Object;)Z
/*    */     //   1058: pop
/*    */     //   1059: aload_0
/*    */     //   1060: dup
/*    */     //   1061: aload_2
/*    */     //   1062: dup
/*    */     //   1063: dup2
/*    */     //   1064: getfield o30 : Lf/U90;
/*    */     //   1067: aload_3
/*    */     //   1068: invokevirtual ee0 : (Lf/U90;)Lf/U90;
/*    */     //   1071: pop
/*    */     //   1072: getfield Xz0 : Lf/U90;
/*    */     //   1075: aload #4
/*    */     //   1077: invokevirtual ee0 : (Lf/U90;)Lf/U90;
/*    */     //   1080: pop
/*    */     //   1081: getfield o30 : Lf/U90;
/*    */     //   1084: iconst_5
/*    */     //   1085: invokevirtual Aq : (I)Lf/U90;
/*    */     //   1088: pop
/*    */     //   1089: getfield Xz0 : Lf/U90;
/*    */     //   1092: iconst_5
/*    */     //   1093: invokevirtual Aq : (I)Lf/U90;
/*    */     //   1096: pop
/*    */     //   1097: iconst_1
/*    */     //   1098: anewarray [Lf/Un;
/*    */     //   1101: dup
/*    */     //   1102: aload_1
/*    */     //   1103: iconst_0
/*    */     //   1104: anewarray f/Un
/*    */     //   1107: invokevirtual toArray : ([Ljava/lang/Object;)[Ljava/lang/Object;
/*    */     //   1110: checkcast [Lf/Un;
/*    */     //   1113: iconst_0
/*    */     //   1114: swap
/*    */     //   1115: aastore
/*    */     //   1116: putfield iE : [[Lf/Un;
/*    */     //   1119: getfield Xg : [Lf/Df;
/*    */     //   1122: arraylength
/*    */     //   1123: iconst_1
/*    */     //   1124: if_icmpne -> 1145
/*    */     //   1127: aload_2
/*    */     //   1128: dup
/*    */     //   1129: getfield o30 : Lf/U90;
/*    */     //   1132: iconst_5
/*    */     //   1133: invokevirtual Aq : (I)Lf/U90;
/*    */     //   1136: pop
/*    */     //   1137: getfield Xz0 : Lf/U90;
/*    */     //   1140: iconst_5
/*    */     //   1141: invokevirtual Aq : (I)Lf/U90;
/*    */     //   1144: pop
/*    */     //   1145: aload_0
/*    */     //   1146: getfield Oh0 : Z
/*    */     //   1149: ifeq -> 1228
/*    */     //   1152: aload_0
/*    */     //   1153: getfield Xg : [Lf/Df;
/*    */     //   1156: arraylength
/*    */     //   1157: iconst_1
/*    */     //   1158: if_icmpge -> 1228
/*    */     //   1161: aload #4
/*    */     //   1163: aload_3
/*    */     //   1164: aload_2
/*    */     //   1165: new f/dQ
/*    */     //   1168: dup
/*    */     //   1169: dup2
/*    */     //   1170: astore_1
/*    */     //   1171: sipush #9151
/*    */     //   1174: invokestatic OH0 : (I)Ljava/lang/String;
/*    */     //   1177: astore_3
/*    */     //   1178: invokespecial <init> : ()V
/*    */     //   1181: aload_3
/*    */     //   1182: invokevirtual E1 : (Ljava/lang/String;)V
/*    */     //   1185: ldc_w 'label-game-mode'
/*    */     //   1188: invokevirtual Xu : (Ljava/lang/String;)V
/*    */     //   1191: iconst_1
/*    */     //   1192: anewarray f/JG0
/*    */     //   1195: dup
/*    */     //   1196: iconst_0
/*    */     //   1197: aload_1
/*    */     //   1198: aastore
/*    */     //   1199: invokevirtual AUX : ([Lf/JG0;)Lf/U90;
/*    */     //   1202: invokevirtual ee0 : (Lf/U90;)Lf/U90;
/*    */     //   1205: pop
/*    */     //   1206: new f/cr0
/*    */     //   1209: dup
/*    */     //   1210: aload_2
/*    */     //   1211: invokespecial <init> : (Lf/Ip;)V
/*    */     //   1214: invokevirtual Em0 : ()Lf/U90;
/*    */     //   1217: aload_1
/*    */     //   1218: invokevirtual Ya : (Lf/JG0;)Lf/U90;
/*    */     //   1221: invokevirtual Em0 : ()Lf/U90;
/*    */     //   1224: invokevirtual ee0 : (Lf/U90;)Lf/U90;
/*    */     //   1227: pop
/*    */     //   1228: aload_0
/*    */     //   1229: dup
/*    */     //   1230: aload_2
/*    */     //   1231: dup
/*    */     //   1232: dup
/*    */     //   1233: new f/cr0
/*    */     //   1236: dup
/*    */     //   1237: astore_0
/*    */     //   1238: aload_2
/*    */     //   1239: invokespecial <init> : (Lf/Ip;)V
/*    */     //   1242: new f/g0
/*    */     //   1245: dup
/*    */     //   1246: astore_1
/*    */     //   1247: aload_2
/*    */     //   1248: invokespecial <init> : (Lf/Ip;)V
/*    */     //   1251: getfield o30 : Lf/U90;
/*    */     //   1254: aload_0
/*    */     //   1255: invokevirtual ee0 : (Lf/U90;)Lf/U90;
/*    */     //   1258: pop
/*    */     //   1259: getfield Xz0 : Lf/U90;
/*    */     //   1262: aload_1
/*    */     //   1263: invokevirtual ee0 : (Lf/U90;)Lf/U90;
/*    */     //   1266: pop
/*    */     //   1267: getfield o30 : Lf/U90;
/*    */     //   1270: iconst_5
/*    */     //   1271: invokevirtual Aq : (I)Lf/U90;
/*    */     //   1274: pop
/*    */     //   1275: getfield Oo : Lf/rS;
/*    */     //   1278: aload_2
/*    */     //   1279: invokevirtual Gz0 : (Lf/JG0;)V
/*    */     //   1282: getfield iE : [[Lf/Un;
/*    */     //   1285: dup
/*    */     //   1286: astore_0
/*    */     //   1287: arraylength
/*    */     //   1288: ifle -> 1307
/*    */     //   1291: aload_0
/*    */     //   1292: iconst_0
/*    */     //   1293: aaload
/*    */     //   1294: dup
/*    */     //   1295: astore_0
/*    */     //   1296: arraylength
/*    */     //   1297: ifle -> 1307
/*    */     //   1300: aload_0
/*    */     //   1301: iconst_0
/*    */     //   1302: aaload
/*    */     //   1303: invokestatic c90 : (Lf/JG0;)Z
/*    */     //   1306: pop
/*    */     //   1307: return
/*    */     // Line number table:
/*    */     //   Java source line number -> byte code offset
/*    */     //   #1	-> 46
/*    */     //   #2	-> 54
/*    */     //   #3	-> 57
/*    */     //   #4	-> 65
/*    */     //   #5	-> 68
/*    */     //   #6	-> 77
/*    */     //   #7	-> 87
/*    */     //   #8	-> 161
/*    */     //   #9	-> 166
/*    */     //   #10	-> 202
/*    */     //   #11	-> 206
/*    */     //   #12	-> 210
/*    */     //   #13	-> 215
/*    */     //   #14	-> 219
/*    */     //   #15	-> 228
/*    */     //   #16	-> 243
/*    */     //   #17	-> 255
/*    */     //   #18	-> 258
/*    */     //   #19	-> 307
/*    */     //   #20	-> 318
/*    */     //   #21	-> 329
/*    */     //   #22	-> 353
/*    */     //   #23	-> 483
/*    */     //   #24	-> 501
/*    */     //   #25	-> 558
/*    */     //   #26	-> 563
/*    */     //   #27	-> 571
/*    */     //   #28	-> 579
/*    */     //   #29	-> 594
/*    */     //   #30	-> 607
/*    */     //   #31	-> 800
/*    */     //   #32	-> 810
/*    */     //   #33	-> 933
/*    */     //   #34	-> 943
/*    */     //   #35	-> 973
/*    */     //   #36	-> 983
/*    */     //   #37	-> 1064
/*    */     //   #38	-> 1068
/*    */     //   #39	-> 1072
/*    */     //   #40	-> 1077
/*    */     //   #41	-> 1081
/*    */     //   #42	-> 1085
/*    */     //   #43	-> 1089
/*    */     //   #44	-> 1093
/*    */     //   #45	-> 1129
/*    */     //   #46	-> 1133
/*    */     //   #47	-> 1137
/*    */     //   #48	-> 1141
/*    */     //   #49	-> 1178
/*    */     //   #50	-> 1185
/*    */     //   #51	-> 1206
/*    */     //   #52	-> 1214
/*    */     //   #53	-> 1233
/*    */     //   #54	-> 1242
/*    */     //   #55	-> 1251
/*    */     //   #56	-> 1255
/*    */     //   #57	-> 1259
/*    */     //   #58	-> 1263
/*    */     //   #59	-> 1267
/*    */     //   #60	-> 1271
/*    */   }
/*    */   
/*    */   public final void update() {
/*    */     long l = DK.In.Eg0 - System.currentTimeMillis();
/*    */     for (l = L70.gq.wU * 1000L + l; l < 0L;)
/*    */       l += 120000L; 
/*    */     if ((l /= 1000L) > 0L) {
/*    */       char c = 'ᕾ';
/*    */       c = 'ᖉ';
/*    */       if (l > 120L && (l /= 60L) > 60L) {
/*    */         l /= 60L;
/*    */         c = 'ᖊ';
/*    */       } 
/*    */       String str = Long.toString(l);
/*    */       if (!this.Oh0)
/*    */         this.Zj0.E1(Ml0.Go(c, str)); 
/*    */       this.vi.s6(Ml0.Go(5508, str));
/*    */     } 
/*    */     if (this.ab0.dP)
/*    */       return; 
/*    */     Df[] arrayOfDf;
/*    */     if ((arrayOfDf = this.Xg) != null) {
/*    */       int i;
/*    */       byte b;
/*    */       for (i = arrayOfDf.length, b = 0; b < i; ) {
/*    */         qa0 qa02;
/*    */         long l2 = ((qa02 = df.po0).Mr0 * 60 * 1000);
/*    */         Df df;
/*    */         L70 l70;
/*    */         qa0 qa01;
/*    */         long l1, l3;
/*    */         if ((l3 = (l1 = (qa01 = (df = arrayOfDf[b]).po0).Gr - (qa01.Mr0 * 60 * 1000) - System.currentTimeMillis() + ((l70 = L70.gq).wU * 1000)) / 1000L) > 0L) {
/*    */           df.Go0.Nu((float)(l2 - l1) / (float)l2);
/*    */           df.R.E1(Ml0.Go(5400, LF.W70(l3)));
/*    */         } else {
/*    */           long l5 = (df.po0.Mr0 * 60 * 1000);
/*    */           long l4;
/*    */           if ((l2 = (l4 = qa02.Gr - System.currentTimeMillis() + (l70.wU * 1000)) / 1000L) > 0L) {
/*    */             df.Go0.Nu((float)(l5 - l4) / (float)l5);
/*    */             df.R.E1(Ml0.Go(5401, LF.W70(l2)));
/*    */           } else {
/*    */             for (l5 = 60000L; l4 < 0L; l4 += 60000L);
/*    */             df.Go0.Nu((float)(l5 - l4) / (float)l5);
/*    */             df.R.E1(Ml0.Go(5502, NumberFormat.getInstance().format(l4 / 1000L)));
/*    */           } 
/*    */         } 
/*    */         df.ZA();
/*    */         b++;
/*    */       } 
/*    */     } 
/*    */     if (!this.Oh0)
/*    */       this.Zj0.bA = false; 
/*    */   }
/*    */   
/*    */   public final void ox() {
/*    */     Df[] arrayOfDf;
/*    */     int i;
/*    */     byte b;
/*    */     for (this.BB = null, this.WL = -1, i = (arrayOfDf = this.Xg).length, b = 0; b < i; ) {
/*    */       (arrayOfDf[b]).cOM7.E1("");
/*    */       (arrayOfDf[b]).lPt8 = true;
/*    */       arrayOfDf[b].ZA();
/*    */       (arrayOfDf[b]).K8.z4 = null;
/*    */       (arrayOfDf[b]).K8.zn();
/*    */       (arrayOfDf[b]).XC0.TS.VL0 = false;
/*    */       (arrayOfDf[b]).ap.E1("");
/*    */       (arrayOfDf[b]).K8.s6(Ml0.OH0(5515));
/*    */       b++;
/*    */     } 
/*    */     for (Iterator<pC> iterator = this.IC.iterator(); iterator.hasNext(); ) {
/*    */       (iterator.next()).pz0 = false;
/*    */       ((pC)iterator.next()).DG();
/*    */     } 
/*    */     this.Bm.s6(Ml0.OH0(65));
/*    */     this.Bm.sk0(true);
/*    */     this.ki0.sk0(false);
/*    */     this.ki0.wI0(false);
/*    */     this.DY.s6(Ml0.OH0(5507));
/*    */     this.DY.sk0(true);
/*    */   }
/*    */   
/*    */   public final void rH0() {
/*    */     if (!this.ab0.dP)
/*    */       if (km.XU()) {
/*    */         this.ki0.mM();
/*    */         this.ki0.uh0(60, 60);
/*    */         this.ki0.QJ0(et.t9, -60, 0);
/*    */       } else {
/*    */         this.ki0.mM();
/*    */         this.ki0.uh0(16, 16);
/*    */         this.ki0.RI(16, 16);
/*    */         this.ki0.Tm(16, 16);
/*    */         this.ki0.ME(Xq() - 38, this.er0 + 10);
/*    */       }  
/*    */   }
/*    */   
/*    */   public final Un fL0() {
/*    */     int i;
/*    */     Un[] arrayOfUn;
/*    */     int j;
/*    */     Un[][] arrayOfUn1;
/*    */     return ((j = this.EC) >= (arrayOfUn1 = this.iE).length || (i = this.MQ) >= (arrayOfUn = arrayOfUn1[j]).length) ? null : arrayOfUn[i];
/*    */   }
/*    */   
/*    */   public final void Vk0() {
/*    */     if (this.BB != null || this.WL != -1) {
/*    */       c4();
/*    */       return;
/*    */     } 
/*    */     this();
/*    */     ArrayList<DK> arrayList;
/*    */     byte[] arrayOfByte1 = new byte[10];
/*    */     int i = 0;
/*    */     for (Iterator<pC> iterator = this.IC.iterator(); iterator.hasNext(); ) {
/*    */       pC pC;
/*    */       ge0 ge0;
/*    */       if ((ge0 = (pC = iterator.next()).ar).kN && ge0.TG0.nm0()) {
/*    */         arrayList.add(pC.a8);
/*    */         byte b = ((Uh0)pC.BD0.WW()).aj0;
/*    */         int j;
/*    */         if ((j = i + 1) > arrayOfByte1.length) {
/*    */           arrayOfByte1 = new byte[Math.max(arrayOfByte1.length << 1, j)];
/*    */           j = arrayOfByte1.length;
/*    */           System.arraycopy(arrayOfByte1, 0, arrayOfByte1, 0, j);
/*    */         } 
/*    */         j = i + 1;
/*    */         arrayOfByte1[i] = b;
/*    */         i = j;
/*    */       } 
/*    */       if ((ge0 = pC.Wf).kN && ge0.TG0.nm0()) {
/*    */         arrayList.add(pC.ct);
/*    */         byte b = ((Uh0)pC.BD0.WW()).aj0;
/*    */         int j;
/*    */         if ((j = i + 1) > arrayOfByte1.length) {
/*    */           arrayOfByte1 = new byte[Math.max(arrayOfByte1.length << 1, j)];
/*    */           j = arrayOfByte1.length;
/*    */           System.arraycopy(arrayOfByte1, 0, arrayOfByte1, 0, j);
/*    */         } 
/*    */         j = i + 1;
/*    */         arrayOfByte1[i] = b;
/*    */         i = j;
/*    */       } 
/*    */     } 
/*    */     if (arrayList.isEmpty()) {
/*    */       km.pm0.bL((byte)2, (short)1367);
/*    */       return;
/*    */     } 
/*    */     zJ0 zJ0 = new zJ0();
/*    */     DK[] arrayOfDK = arrayList.<DK>toArray(new DK[0]);
/*    */     boolean bool = false;
/*    */     byte[] arrayOfByte2 = new byte[i];
/*    */     if (i != 0)
/*    */       if (i > 0) {
/*    */         System.arraycopy(arrayOfByte1, bool, arrayOfByte2, 0, i);
/*    */       } else {
/*    */         throw new ArrayIndexOutOfBoundsException(bool);
/*    */       }  
/*    */     this(arrayOfDK, arrayOfByte2);
/*    */     th0(zJ0);
/*    */   }
/*    */   
/*    */   public final void th0(zJ0 paramzJ0) {
/*    */     if (this.BB != null || this.WL != -1) {
/*    */       c4();
/*    */       return;
/*    */     } 
/*    */     if ((paramzJ0.As != null)) {
/*    */       vr0(paramzJ0);
/*    */       return;
/*    */     } 
/*    */     qa0 qa01;
/*    */     if ((qa01 = paramzJ0.B) != null) {
/*    */       String str;
/*    */       if (qa01.yw == 2) {
/*    */         byte b;
/*    */         if ((b = qa01.b20) != 2 && b != 3) {
/*    */           vr0(paramzJ0);
/*    */         } else {
/*    */           str = Ml0.Go(9120, qa01.MU());
/*    */           js.vu0.uh(new h70(str, () -> vr0(paramzJ0), this));
/*    */         } 
/*    */         return;
/*    */       } 
/*    */       vr0((zJ0)str);
/*    */     } 
/*    */   }
/*    */   
/*    */   public final void nB() {
/*    */     DK dK;
/*    */     if ((dK = this.Bg) == null) {
/*    */       Zs(0, (byte)0, null, null);
/*    */       return;
/*    */     } 
/*    */     byte b = (byte)this.e20.Wa0.go;
/*    */     km.u4.e20.W3(new Lt(b, dK));
/*    */   }
/*    */   
/*    */   public final void AG(DK paramDK) {
/*    */     this.Bg = paramDK;
/*    */     tn0();
/*    */   }
/*    */   
/*    */   public final void kO(short paramShort, byte paramByte, HS[] paramArrayOfHS) {
/*    */     // Byte code:
/*    */     //   0: aload_0
/*    */     //   1: getfield La0 : B
/*    */     //   4: iload_2
/*    */     //   5: if_icmpeq -> 9
/*    */     //   8: return
/*    */     //   9: aload_0
/*    */     //   10: aload_3
/*    */     //   11: aload_0
/*    */     //   12: getfield jZ : Ljava/util/Comparator;
/*    */     //   15: invokestatic sort : ([Ljava/lang/Object;Ljava/util/Comparator;)V
/*    */     //   18: getfield g0 : Lf/Uy0;
/*    */     //   21: aload_0
/*    */     //   22: getfield La0 : B
/*    */     //   25: iload_1
/*    */     //   26: invokevirtual r1 : (II)V
/*    */     //   29: getstatic f/UB0.Kg0 : Lf/Q50;
/*    */     //   32: aload_0
/*    */     //   33: iload_1
/*    */     //   34: iload_2
/*    */     //   35: aload_3
/*    */     //   36: <illegal opcode> run : (Lf/ve;SB[Lf/HS;)Ljava/lang/Runnable;
/*    */     //   41: invokevirtual fN : (Ljava/lang/Runnable;)V
/*    */     //   44: return
/*    */   }
/*    */   
/*    */   public final void Zs(int paramInt, byte paramByte, DK paramDK, wA0[] paramArrayOfwA0) {
/*    */     // Byte code:
/*    */     //   0: aload_3
/*    */     //   1: aload_0
/*    */     //   2: getfield Bg : Lf/DK;
/*    */     //   5: if_acmpeq -> 9
/*    */     //   8: return
/*    */     //   9: aload_3
/*    */     //   10: ifnull -> 28
/*    */     //   13: iload_2
/*    */     //   14: aload_0
/*    */     //   15: getfield e20 : Lf/W1;
/*    */     //   18: getfield Wa0 : Lf/A60;
/*    */     //   21: getfield go : I
/*    */     //   24: if_icmpeq -> 28
/*    */     //   27: return
/*    */     //   28: getstatic f/UB0.Kg0 : Lf/Q50;
/*    */     //   31: aload_0
/*    */     //   32: aload #4
/*    */     //   34: iload_1
/*    */     //   35: <illegal opcode> run : (Lf/ve;[Lf/wA0;I)Ljava/lang/Runnable;
/*    */     //   40: invokevirtual fN : (Ljava/lang/Runnable;)V
/*    */     //   43: return
/*    */     // Line number table:
/*    */     //   Java source line number -> byte code offset
/*    */     //   #1	-> 18
/*    */     //   #2	-> 21
/*    */     //   #3	-> 28
/*    */   }
/*    */   
/*    */   public final void XJ0() {
/*    */     Uh0 uh0;
/*    */     W1 w1;
/*    */     if ((w1 = this.Lj0) == null) {
/*    */       w1 = null;
/*    */     } else {
/*    */       uh0 = (Uh0)w1.WW();
/*    */     } 
/*    */     iB[] arrayOfIB = this.tj;
/*    */     CC0[] arrayOfCC0 = this.dp;
/*    */     DO[] arrayOfDO = this.OI0;
/*    */     XT(uh0, (Qv0[])this, arrayOfCC0, arrayOfDO);
/*    */   }
/*    */   
/*    */   public final void vr0(zJ0 paramzJ0) {
/*    */     if (this.BB != null || this.WL > 0)
/*    */       return; 
/*    */     qa0 qa01;
/*    */     if ((qa01 = paramzJ0.B) != null) {
/*    */       this.OI0 = qa01.Lm;
/*    */     } else {
/*    */       this.OI0 = DO.LM;
/*    */     } 
/*    */     this.gp = true;
/*    */     this.aF = false;
/*    */     km.u4.e20.W3(new az(paramzJ0));
/*    */     Df[] arrayOfDf;
/*    */     int i;
/*    */     byte b;
/*    */     for (i = (arrayOfDf = this.Xg).length, b = 0; b < i; ) {
/*    */       Df df;
/*    */       (df = arrayOfDf[b]).cOM7.E1("");
/*    */       (arrayOfDf[b]).lPt8 = false;
/*    */       arrayOfDf[b].ZA();
/*    */       qa0 qa02;
/*    */       if ((qa02 = paramzJ0.B) != null && qa02.Mg0 == (qa02 = df.po0).Mg0)
/*    */         df.cOM7.E1(Ml0.Go(5505, qa02.P8())); 
/*    */       b++;
/*    */     } 
/*    */     for (Iterator<pC> iterator = this.IC.iterator(); iterator.hasNext(); ) {
/*    */       (iterator.next()).pz0 = true;
/*    */       ((pC)iterator.next()).DG();
/*    */     } 
/*    */     this.Bm.s6(Ml0.OH0(5504));
/*    */     this.ki0.sk0(true);
/*    */     this.ki0.wI0(true);
/*    */     update();
/*    */   }
/*    */   
/*    */   public final void c4() {
/*    */     if (!this.Bm.kN)
/*    */       return; 
/*    */     if (this.BB != null || this.WL > 0 || this.gp) {
/*    */       String str = Ml0.OH0(5524);
/*    */       (new h70(str, this::AK, this)).sD0 = true;
/*    */       js.vu0.uh(new h70(str, this::AK, this));
/*    */       return;
/*    */     } 
/*    */     pA pA1;
/*    */     ve ve1;
/*    */     if ((ve1 = (pA1 = this.jf).yq0) != null) {
/*    */       ve1.ra0();
/*    */       this.yq0 = null;
/*    */     } 
/*    */     km.u4.e20.W3(new O9());
/*    */   }
/*    */   
/*    */   public final void V90(throws paramthrows) {
/*    */     if (this.Di.Po0())
/*    */       update(); 
/*    */     super.V90(paramthrows);
/*    */   }
/*    */   
/*    */   public final void mM() {
/*    */     if (km.XU() && !this.ab0.dP) {
/*    */       SM();
/*    */       Tm(this.Bo0.xY, this.Bo0.HC);
/*    */     } else {
/*    */       super.mM();
/*    */     } 
/*    */   }
/*    */   
/*    */   public final void d40() {
/*    */     super.d40();
/*    */     rH0();
/*    */   }
/*    */   
/*    */   public final void LM(throws paramthrows) {
/*    */     if (fL0() == null) {
/*    */       VA0.c90(this);
/*    */     } else {
/*    */       VA0.c90(fL0());
/*    */     } 
/*    */   }
/*    */   
/*    */   public final void N50(int paramInt1, int paramInt2) {
/*    */     Un un;
/*    */     if (paramInt1 < 0)
/*    */       paramInt1 = 0; 
/*    */     Un[][] arrayOfUn1;
/*    */     if (paramInt1 >= (arrayOfUn1 = this.iE).length)
/*    */       paramInt1 = arrayOfUn1.length - 1; 
/*    */     if (paramInt2 < 0)
/*    */       paramInt2 = 0; 
/*    */     Un[] arrayOfUn;
/*    */     if (paramInt2 >= (arrayOfUn = arrayOfUn1[paramInt1]).length)
/*    */       paramInt2 = arrayOfUn.length - 1; 
/*    */     if (paramInt2 < 0 || paramInt2 >= arrayOfUn.length || !(arrayOfUn[paramInt2]).dP) {
/*    */       un = null;
/*    */     } else {
/*    */       this.MQ = paramInt2;
/*    */       this.EC = un;
/*    */       un = fL0();
/*    */     } 
/*    */     if (un == null)
/*    */       return; 
/*    */     if (fL0() == null)
/*    */       return; 
/*    */     VA0.c90(fL0());
/*    */   }
/*    */   
/*    */   public final boolean i2(oa0 paramoa0) {
/*    */     if (B8.Wm0(paramoa0.cz0) && paramoa0.oO()) {
/*    */       if (js.com3(this))
/*    */         return super.i2(paramoa0); 
/*    */       int i = paramoa0.GG0;
/*    */       if (this.zH0.nv0() == 0) {
/*    */         if (h1.J20(i, BM.Oq)) {
/*    */           N50(this.EC, this.MQ - 1);
/*    */           return true;
/*    */         } 
/*    */         if (h1.J20(i, BM.M8)) {
/*    */           N50(this.EC, this.MQ + 1);
/*    */           return true;
/*    */         } 
/*    */         if (h1.J20(i, BM.N70) && this.zH0.nv0() + 1 < this.zH0.Us0.size()) {
/*    */           this.zH0.dA0(this.zH0.Hf(this.zH0.nv0() + 1));
/*    */           return true;
/*    */         } 
/*    */         if (h1.J20(i, BM.bC)) {
/*    */           if (fL0() != null)
/*    */             hm.Fz0((fL0()).TG0.oh0); 
/*    */           return true;
/*    */         } 
/*    */         if (h1.J20(i, BM.lc)) {
/*    */           c4();
/*    */           return true;
/*    */         } 
/*    */       } else {
/*    */         if (h1.J20(i, BM.ni) && this.zH0.nv0() > 0) {
/*    */           this.zH0.dA0(this.zH0.Hf(this.zH0.nv0() - 1));
/*    */           return true;
/*    */         } 
/*    */         if (h1.J20(i, BM.N70) && this.zH0.nv0() + 1 < this.zH0.Us0.size()) {
/*    */           this.zH0.dA0(this.zH0.Hf(this.zH0.nv0() + 1));
/*    */           return true;
/*    */         } 
/*    */         if (h1.J20(i, BM.lc)) {
/*    */           c4();
/*    */           return true;
/*    */         } 
/*    */       } 
/*    */     } 
/*    */     return super.i2(paramoa0);
/*    */   }
/*    */   
/*    */   public final void XT(Uh0 paramUh0, Qv0[] paramArrayOfQv0, CC0[] paramArrayOfCC0, DO[] paramArrayOfDO) {
/*    */     // Byte code:
/*    */     //   0: aload #4
/*    */     //   2: aload_3
/*    */     //   3: new f/Lw
/*    */     //   6: dup
/*    */     //   7: astore_3
/*    */     //   8: invokespecial <init> : ()V
/*    */     //   11: new f/Lw
/*    */     //   14: dup
/*    */     //   15: astore #4
/*    */     //   17: invokespecial <init> : ()V
/*    */     //   20: invokestatic asList : ([Ljava/lang/Object;)Ljava/util/List;
/*    */     //   23: astore #5
/*    */     //   25: invokestatic asList : ([Ljava/lang/Object;)Ljava/util/List;
/*    */     //   28: dup
/*    */     //   29: astore #6
/*    */     //   31: aconst_null
/*    */     //   32: astore #7
/*    */     //   34: invokeinterface iterator : ()Ljava/util/Iterator;
/*    */     //   39: astore #8
/*    */     //   41: aload #8
/*    */     //   43: invokeinterface hasNext : ()Z
/*    */     //   48: ifeq -> 77
/*    */     //   51: aload #8
/*    */     //   53: invokeinterface next : ()Ljava/lang/Object;
/*    */     //   58: checkcast f/DO
/*    */     //   61: dup
/*    */     //   62: astore #9
/*    */     //   64: getfield Jm0 : Z
/*    */     //   67: ifeq -> 41
/*    */     //   70: aload #9
/*    */     //   72: astore #7
/*    */     //   74: goto -> 41
/*    */     //   77: aload_1
/*    */     //   78: ifnull -> 89
/*    */     //   81: aload_1
/*    */     //   82: getfield m10 : Lf/super;
/*    */     //   85: astore_1
/*    */     //   86: goto -> 91
/*    */     //   89: aconst_null
/*    */     //   90: astore_1
/*    */     //   91: iconst_0
/*    */     //   92: istore #8
/*    */     //   94: iload #8
/*    */     //   96: aload_2
/*    */     //   97: arraylength
/*    */     //   98: if_icmpge -> 1236
/*    */     //   101: aload_1
/*    */     //   102: ifnonnull -> 125
/*    */     //   105: getstatic f/km.u4 : Lf/R8;
/*    */     //   108: getstatic f/aq0.LI : Lf/aq0;
/*    */     //   111: invokevirtual s40 : (Lf/aq0;)Lf/Uc0;
/*    */     //   114: iload #8
/*    */     //   116: i2s
/*    */     //   117: invokevirtual ky : (S)Lf/j40;
/*    */     //   120: astore #9
/*    */     //   122: goto -> 177
/*    */     //   125: aload_1
/*    */     //   126: getfield Ss : [I
/*    */     //   129: iload #8
/*    */     //   131: iaload
/*    */     //   132: istore #9
/*    */     //   134: getstatic f/km.u4 : Lf/R8;
/*    */     //   137: getstatic f/aq0.LI : Lf/aq0;
/*    */     //   140: invokevirtual s40 : (Lf/aq0;)Lf/Uc0;
/*    */     //   143: iload #9
/*    */     //   145: invokevirtual de0 : (I)Lf/j40;
/*    */     //   148: dup
/*    */     //   149: astore #10
/*    */     //   151: ifnonnull -> 173
/*    */     //   154: getstatic f/km.u4 : Lf/R8;
/*    */     //   157: getstatic f/aq0.XJ0 : Lf/aq0;
/*    */     //   160: invokevirtual s40 : (Lf/aq0;)Lf/Uc0;
/*    */     //   163: iload #9
/*    */     //   165: invokevirtual de0 : (I)Lf/j40;
/*    */     //   168: astore #9
/*    */     //   170: goto -> 177
/*    */     //   173: aload #10
/*    */     //   175: astore #9
/*    */     //   177: aload_2
/*    */     //   178: iload #8
/*    */     //   180: aaload
/*    */     //   181: dup
/*    */     //   182: astore #10
/*    */     //   184: ifnonnull -> 190
/*    */     //   187: goto -> 1226
/*    */     //   190: aload #9
/*    */     //   192: aload #10
/*    */     //   194: aload #9
/*    */     //   196: invokevirtual zf : (Lf/j40;)V
/*    */     //   199: iconst_0
/*    */     //   200: istore #11
/*    */     //   202: new java/lang/StringBuilder
/*    */     //   205: dup
/*    */     //   206: astore #12
/*    */     //   208: invokespecial <init> : ()V
/*    */     //   211: ifnull -> 1043
/*    */     //   214: aload #9
/*    */     //   216: getfield Zs : Lf/Q90;
/*    */     //   219: invokevirtual YC : ()Z
/*    */     //   222: ifeq -> 228
/*    */     //   225: goto -> 1043
/*    */     //   228: aload #7
/*    */     //   230: ifnull -> 286
/*    */     //   233: aload #9
/*    */     //   235: getfield LPT4 : Lf/UD0;
/*    */     //   238: getfield G2 : Ljava/util/HashSet;
/*    */     //   241: aload #7
/*    */     //   243: invokevirtual contains : (Ljava/lang/Object;)Z
/*    */     //   246: ifne -> 359
/*    */     //   249: aload #12
/*    */     //   251: aload #7
/*    */     //   253: getfield mt0 : I
/*    */     //   256: invokestatic OH0 : (I)Ljava/lang/String;
/*    */     //   259: sipush #5625
/*    */     //   262: swap
/*    */     //   263: invokestatic Go : (ILjava/lang/String;)Ljava/lang/String;
/*    */     //   266: astore #11
/*    */     //   268: invokevirtual length : ()I
/*    */     //   271: ifle -> 348
/*    */     //   274: aload #12
/*    */     //   276: ldc_w '\\n'
/*    */     //   279: invokevirtual append : (Ljava/lang/String;)Ljava/lang/StringBuilder;
/*    */     //   282: pop
/*    */     //   283: goto -> 348
/*    */     //   286: aload #6
/*    */     //   288: invokeinterface isEmpty : ()Z
/*    */     //   293: ifne -> 359
/*    */     //   296: aload #6
/*    */     //   298: aload #9
/*    */     //   300: getfield LPT4 : Lf/UD0;
/*    */     //   303: getfield ee : Lf/DO;
/*    */     //   306: invokeinterface contains : (Ljava/lang/Object;)Z
/*    */     //   311: ifne -> 359
/*    */     //   314: aload #12
/*    */     //   316: aload #9
/*    */     //   318: getfield LPT4 : Lf/UD0;
/*    */     //   321: getfield ee : Lf/DO;
/*    */     //   324: getfield mt0 : I
/*    */     //   327: invokestatic OH0 : (I)Ljava/lang/String;
/*    */     //   330: sipush #5629
/*    */     //   333: swap
/*    */     //   334: invokestatic Go : (ILjava/lang/String;)Ljava/lang/String;
/*    */     //   337: astore #11
/*    */     //   339: invokevirtual length : ()I
/*    */     //   342: ifle -> 348
/*    */     //   345: goto -> 274
/*    */     //   348: aload #12
/*    */     //   350: aload #11
/*    */     //   352: invokevirtual append : (Ljava/lang/String;)Ljava/lang/StringBuilder;
/*    */     //   355: pop
/*    */     //   356: iconst_1
/*    */     //   357: istore #11
/*    */     //   359: aload #5
/*    */     //   361: getstatic f/CC0.T2 : Lf/CC0;
/*    */     //   364: dup
/*    */     //   365: astore #13
/*    */     //   367: invokeinterface contains : (Ljava/lang/Object;)Z
/*    */     //   372: ifeq -> 428
/*    */     //   375: aload_3
/*    */     //   376: aload #9
/*    */     //   378: getfield Zs : Lf/Q90;
/*    */     //   381: getfield Cw0 : S
/*    */     //   384: invokevirtual Fb : (S)Z
/*    */     //   387: ifeq -> 428
/*    */     //   390: aload #12
/*    */     //   392: aload #13
/*    */     //   394: getfield a10 : I
/*    */     //   397: invokestatic OH0 : (I)Ljava/lang/String;
/*    */     //   400: astore #11
/*    */     //   402: invokevirtual length : ()I
/*    */     //   405: ifle -> 417
/*    */     //   408: aload #12
/*    */     //   410: ldc_w '\\n'
/*    */     //   413: invokevirtual append : (Ljava/lang/String;)Ljava/lang/StringBuilder;
/*    */     //   416: pop
/*    */     //   417: aload #12
/*    */     //   419: aload #11
/*    */     //   421: invokevirtual append : (Ljava/lang/String;)Ljava/lang/StringBuilder;
/*    */     //   424: pop
/*    */     //   425: iconst_1
/*    */     //   426: istore #11
/*    */     //   428: aload #5
/*    */     //   430: getstatic f/CC0.pq : Lf/CC0;
/*    */     //   433: dup
/*    */     //   434: astore #13
/*    */     //   436: invokeinterface contains : (Ljava/lang/Object;)Z
/*    */     //   441: ifeq -> 509
/*    */     //   444: aload #9
/*    */     //   446: getfield Zs : Lf/Q90;
/*    */     //   449: invokevirtual p10 : ()S
/*    */     //   452: ifle -> 509
/*    */     //   455: aload #4
/*    */     //   457: aload #9
/*    */     //   459: getfield Zs : Lf/Q90;
/*    */     //   462: invokevirtual p10 : ()S
/*    */     //   465: invokevirtual Fb : (S)Z
/*    */     //   468: ifeq -> 509
/*    */     //   471: aload #12
/*    */     //   473: aload #13
/*    */     //   475: getfield a10 : I
/*    */     //   478: invokestatic OH0 : (I)Ljava/lang/String;
/*    */     //   481: astore #11
/*    */     //   483: invokevirtual length : ()I
/*    */     //   486: ifle -> 498
/*    */     //   489: aload #12
/*    */     //   491: ldc_w '\\n'
/*    */     //   494: invokevirtual append : (Ljava/lang/String;)Ljava/lang/StringBuilder;
/*    */     //   497: pop
/*    */     //   498: aload #12
/*    */     //   500: aload #11
/*    */     //   502: invokevirtual append : (Ljava/lang/String;)Ljava/lang/StringBuilder;
/*    */     //   505: pop
/*    */     //   506: iconst_1
/*    */     //   507: istore #11
/*    */     //   509: aload #7
/*    */     //   511: ifnull -> 523
/*    */     //   514: aload #7
/*    */     //   516: getfield Ua0 : B
/*    */     //   519: iconst_1
/*    */     //   520: if_icmpge -> 572
/*    */     //   523: aload #9
/*    */     //   525: getfield Zs : Lf/Q90;
/*    */     //   528: getfield od : B
/*    */     //   531: bipush #50
/*    */     //   533: if_icmpge -> 572
/*    */     //   536: aload #12
/*    */     //   538: sipush #5627
/*    */     //   541: invokestatic OH0 : (I)Ljava/lang/String;
/*    */     //   544: astore #11
/*    */     //   546: invokevirtual length : ()I
/*    */     //   549: ifle -> 561
/*    */     //   552: aload #12
/*    */     //   554: ldc_w '\\n'
/*    */     //   557: invokevirtual append : (Ljava/lang/String;)Ljava/lang/StringBuilder;
/*    */     //   560: pop
/*    */     //   561: aload #12
/*    */     //   563: aload #11
/*    */     //   565: invokevirtual append : (Ljava/lang/String;)Ljava/lang/StringBuilder;
/*    */     //   568: pop
/*    */     //   569: iconst_1
/*    */     //   570: istore #11
/*    */     //   572: aload #5
/*    */     //   574: getstatic f/CC0.fn0 : Lf/CC0;
/*    */     //   577: invokeinterface contains : (Ljava/lang/Object;)Z
/*    */     //   582: ifeq -> 675
/*    */     //   585: getstatic f/CC0.LF0 : [S
/*    */     //   588: dup
/*    */     //   589: astore #13
/*    */     //   591: arraylength
/*    */     //   592: istore #14
/*    */     //   594: iconst_0
/*    */     //   595: istore #15
/*    */     //   597: iload #15
/*    */     //   599: iload #14
/*    */     //   601: if_icmpge -> 675
/*    */     //   604: aload #9
/*    */     //   606: aload #13
/*    */     //   608: iload #15
/*    */     //   610: saload
/*    */     //   611: istore #16
/*    */     //   613: getfield Zs : Lf/Q90;
/*    */     //   616: invokevirtual p10 : ()S
/*    */     //   619: invokestatic l90 : (S)S
/*    */     //   622: iload #16
/*    */     //   624: if_icmpne -> 669
/*    */     //   627: aload #12
/*    */     //   629: getstatic f/CC0.fn0 : Lf/CC0;
/*    */     //   632: getfield a10 : I
/*    */     //   635: invokestatic OH0 : (I)Ljava/lang/String;
/*    */     //   638: astore #11
/*    */     //   640: invokevirtual length : ()I
/*    */     //   643: ifle -> 655
/*    */     //   646: aload #12
/*    */     //   648: ldc_w '\\n'
/*    */     //   651: invokevirtual append : (Ljava/lang/String;)Ljava/lang/StringBuilder;
/*    */     //   654: pop
/*    */     //   655: aload #12
/*    */     //   657: aload #11
/*    */     //   659: invokevirtual append : (Ljava/lang/String;)Ljava/lang/StringBuilder;
/*    */     //   662: pop
/*    */     //   663: iconst_1
/*    */     //   664: istore #11
/*    */     //   666: goto -> 675
/*    */     //   669: iinc #15, 1
/*    */     //   672: goto -> 597
/*    */     //   675: aload #5
/*    */     //   677: getstatic f/CC0.X2 : Lf/CC0;
/*    */     //   680: invokeinterface contains : (Ljava/lang/Object;)Z
/*    */     //   685: ifeq -> 778
/*    */     //   688: getstatic f/CC0.vf0 : [S
/*    */     //   691: dup
/*    */     //   692: astore #13
/*    */     //   694: arraylength
/*    */     //   695: istore #14
/*    */     //   697: iconst_0
/*    */     //   698: istore #15
/*    */     //   700: iload #15
/*    */     //   702: iload #14
/*    */     //   704: if_icmpge -> 778
/*    */     //   707: aload #9
/*    */     //   709: aload #13
/*    */     //   711: iload #15
/*    */     //   713: saload
/*    */     //   714: istore #16
/*    */     //   716: getfield Zs : Lf/Q90;
/*    */     //   719: invokevirtual p10 : ()S
/*    */     //   722: invokestatic l90 : (S)S
/*    */     //   725: iload #16
/*    */     //   727: if_icmpne -> 772
/*    */     //   730: aload #12
/*    */     //   732: getstatic f/CC0.X2 : Lf/CC0;
/*    */     //   735: getfield a10 : I
/*    */     //   738: invokestatic OH0 : (I)Ljava/lang/String;
/*    */     //   741: astore #11
/*    */     //   743: invokevirtual length : ()I
/*    */     //   746: ifle -> 758
/*    */     //   749: aload #12
/*    */     //   751: ldc_w '\\n'
/*    */     //   754: invokevirtual append : (Ljava/lang/String;)Ljava/lang/StringBuilder;
/*    */     //   757: pop
/*    */     //   758: aload #12
/*    */     //   760: aload #11
/*    */     //   762: invokevirtual append : (Ljava/lang/String;)Ljava/lang/StringBuilder;
/*    */     //   765: pop
/*    */     //   766: iconst_1
/*    */     //   767: istore #11
/*    */     //   769: goto -> 778
/*    */     //   772: iinc #15, 1
/*    */     //   775: goto -> 700
/*    */     //   778: aload_0
/*    */     //   779: getfield Vf0 : [Lf/yX;
/*    */     //   782: dup
/*    */     //   783: astore #13
/*    */     //   785: arraylength
/*    */     //   786: istore #14
/*    */     //   788: iconst_0
/*    */     //   789: istore #15
/*    */     //   791: iload #15
/*    */     //   793: iload #14
/*    */     //   795: if_icmpge -> 1013
/*    */     //   798: aload #13
/*    */     //   800: iload #15
/*    */     //   802: aaload
/*    */     //   803: getfield U30 : Ljava/util/ArrayList;
/*    */     //   806: invokevirtual iterator : ()Ljava/util/Iterator;
/*    */     //   809: astore #16
/*    */     //   811: aload #16
/*    */     //   813: invokeinterface hasNext : ()Z
/*    */     //   818: ifeq -> 1007
/*    */     //   821: aload #16
/*    */     //   823: invokeinterface next : ()Ljava/lang/Object;
/*    */     //   828: checkcast f/Pi
/*    */     //   831: dup
/*    */     //   832: astore #17
/*    */     //   834: aload #9
/*    */     //   836: dup
/*    */     //   837: getfield Zs : Lf/Q90;
/*    */     //   840: astore #18
/*    */     //   842: invokevirtual rX : ()S
/*    */     //   845: istore #19
/*    */     //   847: getfield Gk0 : B
/*    */     //   850: dup
/*    */     //   851: istore #20
/*    */     //   853: ifeq -> 866
/*    */     //   856: iload #20
/*    */     //   858: iconst_2
/*    */     //   859: if_icmpeq -> 866
/*    */     //   862: iconst_0
/*    */     //   863: goto -> 879
/*    */     //   866: aload #17
/*    */     //   868: aload #18
/*    */     //   870: iload #19
/*    */     //   872: aload #5
/*    */     //   874: aload #6
/*    */     //   876: invokevirtual Ic0 : (Lf/Q90;SLjava/util/List;Ljava/util/List;)Z
/*    */     //   879: ifeq -> 921
/*    */     //   882: aload #12
/*    */     //   884: sipush #5628
/*    */     //   887: invokestatic OH0 : (I)Ljava/lang/String;
/*    */     //   890: astore #11
/*    */     //   892: invokevirtual length : ()I
/*    */     //   895: ifle -> 907
/*    */     //   898: aload #12
/*    */     //   900: ldc_w '\\n'
/*    */     //   903: invokevirtual append : (Ljava/lang/String;)Ljava/lang/StringBuilder;
/*    */     //   906: pop
/*    */     //   907: aload #12
/*    */     //   909: aload #11
/*    */     //   911: invokevirtual append : (Ljava/lang/String;)Ljava/lang/StringBuilder;
/*    */     //   914: pop
/*    */     //   915: iconst_1
/*    */     //   916: istore #11
/*    */     //   918: goto -> 811
/*    */     //   921: aload #17
/*    */     //   923: aload #9
/*    */     //   925: dup
/*    */     //   926: getfield Zs : Lf/Q90;
/*    */     //   929: astore #18
/*    */     //   931: invokevirtual rX : ()S
/*    */     //   934: istore #19
/*    */     //   936: getfield Gk0 : B
/*    */     //   939: iconst_1
/*    */     //   940: if_icmpeq -> 947
/*    */     //   943: iconst_0
/*    */     //   944: goto -> 960
/*    */     //   947: aload #17
/*    */     //   949: aload #18
/*    */     //   951: iload #19
/*    */     //   953: aload #5
/*    */     //   955: aload #6
/*    */     //   957: invokevirtual Ic0 : (Lf/Q90;SLjava/util/List;Ljava/util/List;)Z
/*    */     //   960: ifeq -> 811
/*    */     //   963: aload #12
/*    */     //   965: sipush #5630
/*    */     //   968: invokestatic OH0 : (I)Ljava/lang/String;
/*    */     //   971: astore #17
/*    */     //   973: invokevirtual length : ()I
/*    */     //   976: ifle -> 988
/*    */     //   979: aload #12
/*    */     //   981: ldc_w '\\n'
/*    */     //   984: invokevirtual append : (Ljava/lang/String;)Ljava/lang/StringBuilder;
/*    */     //   987: pop
/*    */     //   988: iload #11
/*    */     //   990: aload #12
/*    */     //   992: aload #17
/*    */     //   994: invokevirtual append : (Ljava/lang/String;)Ljava/lang/StringBuilder;
/*    */     //   997: pop
/*    */     //   998: ifne -> 811
/*    */     //   1001: iconst_2
/*    */     //   1002: istore #11
/*    */     //   1004: goto -> 811
/*    */     //   1007: iinc #15, 1
/*    */     //   1010: goto -> 791
/*    */     //   1013: aload #4
/*    */     //   1015: aload #9
/*    */     //   1017: aload_3
/*    */     //   1018: aload #9
/*    */     //   1020: getfield Zs : Lf/Q90;
/*    */     //   1023: getfield Cw0 : S
/*    */     //   1026: invokevirtual Ye0 : (S)Z
/*    */     //   1029: pop
/*    */     //   1030: getfield Zs : Lf/Q90;
/*    */     //   1033: invokevirtual p10 : ()S
/*    */     //   1036: invokevirtual Ye0 : (S)Z
/*    */     //   1039: pop
/*    */     //   1040: goto -> 1079
/*    */     //   1043: aload #12
/*    */     //   1045: sipush #5626
/*    */     //   1048: invokestatic OH0 : (I)Ljava/lang/String;
/*    */     //   1051: astore #9
/*    */     //   1053: invokevirtual length : ()I
/*    */     //   1056: ifle -> 1068
/*    */     //   1059: aload #12
/*    */     //   1061: ldc_w '\\n'
/*    */     //   1064: invokevirtual append : (Ljava/lang/String;)Ljava/lang/StringBuilder;
/*    */     //   1067: pop
/*    */     //   1068: aload #12
/*    */     //   1070: aload #9
/*    */     //   1072: invokevirtual append : (Ljava/lang/String;)Ljava/lang/StringBuilder;
/*    */     //   1075: pop
/*    */     //   1076: iconst_m1
/*    */     //   1077: istore #11
/*    */     //   1079: iload #11
/*    */     //   1081: aload #10
/*    */     //   1083: dup
/*    */     //   1084: dup
/*    */     //   1085: aload #12
/*    */     //   1087: invokevirtual toString : ()Ljava/lang/String;
/*    */     //   1090: putfield z4 : Ljava/lang/Object;
/*    */     //   1093: invokevirtual zn : ()V
/*    */     //   1096: iconst_0
/*    */     //   1097: putfield jl : I
/*    */     //   1100: tableswitch default -> 1132, -1 -> 1195, 0 -> 1175, 1 -> 1155, 2 -> 1135
/*    */     //   1132: goto -> 1226
/*    */     //   1135: ldc_w 'label-suspect-testing-monster'
/*    */     //   1138: dup
/*    */     //   1139: astore #9
/*    */     //   1141: aload #10
/*    */     //   1143: getfield cl : Ljava/lang/String;
/*    */     //   1146: invokevirtual equals : (Ljava/lang/Object;)Z
/*    */     //   1149: ifeq -> 1215
/*    */     //   1152: goto -> 1226
/*    */     //   1155: ldc_w 'label-banned-monster'
/*    */     //   1158: dup
/*    */     //   1159: astore #9
/*    */     //   1161: aload #10
/*    */     //   1163: getfield cl : Ljava/lang/String;
/*    */     //   1166: invokevirtual equals : (Ljava/lang/Object;)Z
/*    */     //   1169: ifeq -> 1215
/*    */     //   1172: goto -> 1226
/*    */     //   1175: ldc_w 'label-unbanned-monster'
/*    */     //   1178: dup
/*    */     //   1179: astore #9
/*    */     //   1181: aload #10
/*    */     //   1183: getfield cl : Ljava/lang/String;
/*    */     //   1186: invokevirtual equals : (Ljava/lang/Object;)Z
/*    */     //   1189: ifeq -> 1215
/*    */     //   1192: goto -> 1226
/*    */     //   1195: ldc_w 'label-monster-slot'
/*    */     //   1198: dup
/*    */     //   1199: astore #9
/*    */     //   1201: aload #10
/*    */     //   1203: getfield cl : Ljava/lang/String;
/*    */     //   1206: invokevirtual equals : (Ljava/lang/Object;)Z
/*    */     //   1209: ifeq -> 1215
/*    */     //   1212: goto -> 1226
/*    */     //   1215: aload #10
/*    */     //   1217: dup
/*    */     //   1218: aload #9
/*    */     //   1220: invokevirtual Xu : (Ljava/lang/String;)V
/*    */     //   1223: invokevirtual cZ : ()V
/*    */     //   1226: iload #8
/*    */     //   1228: iconst_1
/*    */     //   1229: iadd
/*    */     //   1230: i2b
/*    */     //   1231: istore #8
/*    */     //   1233: goto -> 94
/*    */     //   1236: return
/*    */     // Line number table:
/*    */     //   Java source line number -> byte code offset
/*    */     //   #1	-> 64
/*    */     //   #2	-> 82
/*    */     //   #3	-> 97
/*    */     //   #4	-> 126
/*    */     //   #5	-> 134
/*    */     //   #6	-> 216
/*    */     //   #7	-> 235
/*    */     //   #8	-> 238
/*    */     //   #9	-> 243
/*    */     //   #10	-> 253
/*    */     //   #11	-> 256
/*    */     //   #12	-> 268
/*    */     //   #13	-> 288
/*    */     //   #14	-> 300
/*    */     //   #15	-> 303
/*    */     //   #16	-> 306
/*    */     //   #17	-> 318
/*    */     //   #18	-> 321
/*    */     //   #19	-> 324
/*    */     //   #20	-> 327
/*    */     //   #21	-> 339
/*    */     //   #22	-> 361
/*    */     //   #23	-> 378
/*    */     //   #24	-> 381
/*    */     //   #25	-> 384
/*    */     //   #26	-> 394
/*    */     //   #27	-> 397
/*    */     //   #28	-> 402
/*    */     //   #29	-> 430
/*    */     //   #30	-> 446
/*    */     //   #31	-> 449
/*    */     //   #32	-> 459
/*    */     //   #33	-> 462
/*    */     //   #34	-> 475
/*    */     //   #35	-> 478
/*    */     //   #36	-> 483
/*    */     //   #37	-> 516
/*    */     //   #38	-> 525
/*    */     //   #39	-> 528
/*    */     //   #40	-> 541
/*    */     //   #41	-> 546
/*    */     //   #42	-> 574
/*    */     //   #43	-> 613
/*    */     //   #44	-> 616
/*    */     //   #45	-> 632
/*    */     //   #46	-> 635
/*    */     //   #47	-> 640
/*    */     //   #48	-> 677
/*    */     //   #49	-> 716
/*    */     //   #50	-> 719
/*    */     //   #51	-> 735
/*    */     //   #52	-> 738
/*    */     //   #53	-> 743
/*    */     //   #54	-> 779
/*    */     //   #55	-> 803
/*    */     //   #56	-> 806
/*    */     //   #57	-> 837
/*    */     //   #58	-> 842
/*    */     //   #59	-> 847
/*    */     //   #60	-> 876
/*    */     //   #61	-> 887
/*    */     //   #62	-> 892
/*    */     //   #63	-> 926
/*    */     //   #64	-> 931
/*    */     //   #65	-> 936
/*    */     //   #66	-> 968
/*    */     //   #67	-> 973
/*    */     //   #68	-> 1020
/*    */     //   #69	-> 1023
/*    */     //   #70	-> 1026
/*    */     //   #71	-> 1030
/*    */     //   #72	-> 1033
/*    */     //   #73	-> 1053
/*    */     //   #74	-> 1087
/*    */     //   #75	-> 1090
/*    */     //   #76	-> 1097
/*    */     //   #77	-> 1135
/*    */     //   #78	-> 1143
/*    */     //   #79	-> 1155
/*    */     //   #80	-> 1163
/*    */     //   #81	-> 1175
/*    */     //   #82	-> 1183
/*    */     //   #83	-> 1195
/*    */     //   #84	-> 1203
/*    */   } }


/* Location:              /Users/vnnsnnt/Documents/Codespace/JavaWorkspace/RedTrainer/src/main/java/org/trainer/client/PokeMMO.jar!/f/ve.class
 * Java compiler version: 8 (52.0)
 * JD-Core Version:       1.1.3
 */