/* 1 */ package f;public class VH extends Qa0 implements r60 { public final Ip uC0; public final Un fo; private void BU(Tx paramTx) { ra0(); paramTx
/*   */       
/* 3 */       .Bn(this.Hl.F2.toString()); } public final of Hl; public VH(String paramString, int paramInt, Tx paramTx) { // Byte code:
/*   */     //   0: aload_0
/*   */     //   1: dup
/*   */     //   2: dup
/*   */     //   3: invokestatic XU : ()Z
/*   */     //   6: iconst_1
/*   */     //   7: invokespecial <init> : (ZZ)V
/*   */     //   10: ldc 'confirm-widget'
/*   */     //   12: invokevirtual Xu : (Ljava/lang/String;)V
/*   */     //   15: new f/Ip
/*   */     //   18: dup
/*   */     //   19: dup
/*   */     //   20: dup2
/*   */     //   21: dup2
/*   */     //   22: astore #4
/*   */     //   24: aload_0
/*   */     //   25: aload #4
/*   */     //   27: dup
/*   */     //   28: invokespecial <init> : ()V
/*   */     //   31: putfield uC0 : Lf/Ip;
/*   */     //   34: ldc 'confirm-panel'
/*   */     //   36: invokevirtual Xu : (Ljava/lang/String;)V
/*   */     //   39: new f/dQ
/*   */     //   42: dup
/*   */     //   43: astore #5
/*   */     //   45: aload_1
/*   */     //   46: invokespecial <init> : (Ljava/lang/String;)V
/*   */     //   49: new f/of
/*   */     //   52: dup
/*   */     //   53: astore_1
/*   */     //   54: iload_2
/*   */     //   55: aload #5
/*   */     //   57: aload_0
/*   */     //   58: aload_1
/*   */     //   59: dup
/*   */     //   60: invokespecial <init> : ()V
/*   */     //   63: putfield Hl : Lf/of;
/*   */     //   66: invokevirtual Xy : ()Ljava/lang/String;
/*   */     //   69: pop
/*   */     //   70: invokevirtual co : (I)V
/*   */     //   73: new f/Un
/*   */     //   76: dup
/*   */     //   77: astore_2
/*   */     //   78: aload_0
/*   */     //   79: aload_3
/*   */     //   80: aload_0
/*   */     //   81: aload_2
/*   */     //   82: dup
/*   */     //   83: bipush #52
/*   */     //   85: invokestatic OH0 : (I)Ljava/lang/String;
/*   */     //   88: invokespecial <init> : (Ljava/lang/String;)V
/*   */     //   91: putfield fo : Lf/Un;
/*   */     //   94: <illegal opcode> run : (Lf/VH;Lf/Tx;)Ljava/lang/Runnable;
/*   */     //   99: invokevirtual tW : (Ljava/lang/Runnable;)V
/*   */     //   102: new f/Un
/*   */     //   105: dup
/*   */     //   106: astore_3
/*   */     //   107: aload_0
/*   */     //   108: aload_3
/*   */     //   109: bipush #53
/*   */     //   111: invokestatic OH0 : (I)Ljava/lang/String;
/*   */     //   114: invokespecial <init> : (Ljava/lang/String;)V
/*   */     //   117: <illegal opcode> run : (Lf/VH;)Ljava/lang/Runnable;
/*   */     //   122: invokevirtual tW : (Ljava/lang/Runnable;)V
/*   */     //   125: invokevirtual d7 : ()Lf/cr0;
/*   */     //   128: aload #5
/*   */     //   130: invokevirtual Ya : (Lf/JG0;)Lf/U90;
/*   */     //   133: aload #4
/*   */     //   135: invokevirtual mE0 : ()Lf/g0;
/*   */     //   138: iconst_1
/*   */     //   139: anewarray f/JG0
/*   */     //   142: dup
/*   */     //   143: iconst_0
/*   */     //   144: aload_1
/*   */     //   145: aastore
/*   */     //   146: invokevirtual Mg : ([Lf/JG0;)Lf/U90;
/*   */     //   149: invokevirtual ee0 : (Lf/U90;)Lf/U90;
/*   */     //   152: aload #4
/*   */     //   154: invokevirtual d7 : ()Lf/cr0;
/*   */     //   157: iconst_2
/*   */     //   158: anewarray f/JG0
/*   */     //   161: dup
/*   */     //   162: dup
/*   */     //   163: iconst_0
/*   */     //   164: aload_2
/*   */     //   165: aastore
/*   */     //   166: iconst_1
/*   */     //   167: aload_3
/*   */     //   168: aastore
/*   */     //   169: invokevirtual Mg : ([Lf/JG0;)Lf/U90;
/*   */     //   172: invokevirtual ee0 : (Lf/U90;)Lf/U90;
/*   */     //   175: invokevirtual Em0 : ()Lf/U90;
/*   */     //   178: invokevirtual WN : (Lf/U90;)V
/*   */     //   181: invokevirtual mE0 : ()Lf/g0;
/*   */     //   184: aload #5
/*   */     //   186: invokevirtual Ya : (Lf/JG0;)Lf/U90;
/*   */     //   189: aload #4
/*   */     //   191: invokevirtual d7 : ()Lf/cr0;
/*   */     //   194: iconst_1
/*   */     //   195: anewarray f/JG0
/*   */     //   198: dup
/*   */     //   199: iconst_0
/*   */     //   200: aload_1
/*   */     //   201: aastore
/*   */     //   202: invokevirtual Mg : ([Lf/JG0;)Lf/U90;
/*   */     //   205: invokevirtual ee0 : (Lf/U90;)Lf/U90;
/*   */     //   208: aload #4
/*   */     //   210: invokevirtual mE0 : ()Lf/g0;
/*   */     //   213: aload_2
/*   */     //   214: invokevirtual Ya : (Lf/JG0;)Lf/U90;
/*   */     //   217: aload_3
/*   */     //   218: invokevirtual Ya : (Lf/JG0;)Lf/U90;
/*   */     //   221: invokevirtual ee0 : (Lf/U90;)Lf/U90;
/*   */     //   224: invokevirtual rK0 : (Lf/U90;)V
/*   */     //   227: invokevirtual J8 : (Lf/JG0;)V
/* 3 */     //   230: return } public final void hy0() { VA0.c90(this.Hl); } public final boolean i2(oa0 paramoa0) { if (B8.Wm0(paramoa0.cz0) && this.Hl.p3()) { this.Hl.i2(paramoa0); return true; }  return super.i2(paramoa0); }
/*   */ 
/*   */   
/*   */   public final void LM(throws paramthrows) {
/*   */     super.LM(paramthrows);
/*   */     VA0.c90(this.Hl);
/*   */   }
/*   */   
/*   */   public final void d40() {
/*   */     super.d40();
/*   */     this.uC0.mM();
/*   */     QI();
/*   */     this.uC0.js0(et.Wi0);
/*   */   } }


/* Location:              /Users/vnnsnnt/Documents/Codespace/JavaWorkspace/RedTrainer/src/main/java/org/trainer/client/PokeMMO.jar!/f/VH.class
 * Java compiler version: 8 (52.0)
 * JD-Core Version:       1.1.3
 */