package f;

public final class vz extends OQ {
  public float iG0;
  
  public vz(int paramInt) {
    super(paramInt);
  }
  
  public final void rH(AH0 paramAH0, Ym0 paramYm0, ls0 paramls0) {
    super.rH(paramAH0, paramYm0, paramls0);
  }
  
  public final void ai0(AH0 paramAH0, Ym0 paramYm0) {
    if (this.rd0 != 0) {
      this.qL = arrayOfFloat[paramAH0.Ze0(6)];
      float[] arrayOfFloat;
      this.iG0 = (arrayOfFloat = K30.dr0)[paramAH0.Ze0(6)];
    } 
  }
  
  public final boolean Pg0(AH0 paramAH0) {
    return super.Pg0(paramAH0);
  }
  
  public final boolean cOM7(int paramInt, Va paramVa1, Va paramVa2) {
    // Byte code:
    //   0: aload_0
    //   1: getfield rd0 : I
    //   4: ifeq -> 118
    //   7: iload_1
    //   8: aload_0
    //   9: dup
    //   10: getfield ua : F
    //   13: aload_0
    //   14: getfield bv0 : F
    //   17: fmul
    //   18: aload_0
    //   19: getfield Iz : F
    //   22: fadd
    //   23: dup
    //   24: fstore #4
    //   26: putfield ua : F
    //   29: ifne -> 70
    //   32: aload_3
    //   33: aload_2
    //   34: aload_0
    //   35: fload #4
    //   37: aload_0
    //   38: fload #4
    //   40: aload_0
    //   41: getfield qL : F
    //   44: fmul
    //   45: fstore_0
    //   46: getfield iG0 : F
    //   49: fmul
    //   50: fstore_1
    //   51: getfield E7 : I
    //   54: istore_2
    //   55: getfield z0 : [F
    //   58: iload_2
    //   59: fload_0
    //   60: fastore
    //   61: getfield z0 : [F
    //   64: iload_2
    //   65: fload_1
    //   66: fastore
    //   67: goto -> 118
    //   70: iload_1
    //   71: iconst_1
    //   72: if_icmpne -> 98
    //   75: aload_2
    //   76: aload_0
    //   77: fload #4
    //   79: aload_0
    //   80: getfield qL : F
    //   83: fmul
    //   84: fstore_0
    //   85: getfield E7 : I
    //   88: istore_1
    //   89: getfield z0 : [F
    //   92: iload_1
    //   93: fload_0
    //   94: fastore
    //   95: goto -> 118
    //   98: aload_2
    //   99: aload_0
    //   100: fload #4
    //   102: aload_0
    //   103: getfield iG0 : F
    //   106: fmul
    //   107: fstore_0
    //   108: getfield E7 : I
    //   111: istore_1
    //   112: getfield z0 : [F
    //   115: iload_1
    //   116: fload_0
    //   117: fastore
    //   118: iconst_1
    //   119: ireturn
    // Line number table:
    //   Java source line number -> byte code offset
    //   #1	-> 55
    //   #2	-> 60
    //   #3	-> 61
    //   #4	-> 66
    //   #5	-> 80
    //   #6	-> 89
    //   #7	-> 94
    //   #8	-> 103
    //   #9	-> 112
    //   #10	-> 117
  }
}


/* Location:              /Users/vnnsnnt/Documents/Codespace/JavaWorkspace/RedTrainer/src/main/java/org/trainer/client/PokeMMO.jar!/f/vz.class
 * Java compiler version: 6 (50.0)
 * JD-Core Version:       1.1.3
 */