/*  1 */ package f;public final class W30 extends QZ { public final String DP() { String str; if (this.Z9 > 1) { StringBuilder stringBuilder; this(); String[] arrayOfString1; (arrayOfString1 = new String[1])[0] = this.gy; (new StringBuilder())
/*    */ 
/*    */         
/*  4 */         .append(Ml0.lz((byte)2, F40.ef0, 15, 8, arrayOfString1)); (new StringBuilder()).append("\n\n"); char c = '᚞'; String[] arrayOfString2; (arrayOfString2 = new String[2])[
/*  5 */           0] = this.gy;
/*  6 */       boolean bool = true; byte b; if ((b = this.Z9) >= 100)
/*  7 */       { str = N.Gl0(new StringBuilder(), this.Z9, "+"); }
/*  8 */       else { str = Integer.toString(b); }  arrayOfString2[bool] = this; stringBuilder.append(Ml0.sB(c, arrayOfString2)); return stringBuilder.toString(); }  String[] arrayOfString; (arrayOfString = new String[1])[
/*  9 */         0] = ((W30)super).gy;
/*    */     
/* 11 */     return Ml0.lz((byte)2, F40.ef0, 15, 8, arrayOfString); }
/*    */ 
/*    */   
/*    */   public C30[] Sa = null;
/*    */   public dK0 On0;
/*    */   public mi bH;
/*    */   public final String gy;
/*    */   public final OE0 iL0;
/*    */   public final rs0 Ne0;
/*    */   public final short CY;
/*    */   public final byte Z9;
/*    */   public ArrayList fm0 = null;
/*    */   
/*    */   public W30(byte paramByte1, String paramString, OE0 paramOE0, rs0 paramrs0, short paramShort, byte paramByte2, rK paramrK) {
/*    */     super(paramByte1);
/*    */     this.gy = paramString;
/*    */     this.iL0 = paramOE0;
/*    */     this.Ne0 = paramrs0;
/*    */     this.CY = paramShort;
/*    */     this.Z9 = paramByte2;
/*    */     if (paramrK == rK.bh)
/*    */       dg0(); 
/*    */   }
/*    */   
/*    */   public final ET PN() {
/*    */     return ET.eh;
/*    */   }
/*    */   
/*    */   public final void kO(int paramInt1, int paramInt2) {
/*    */     mi mi1 = new mi();
/*    */     this(c30);
/*    */     this.bH = mi1;
/*    */     C30 c30;
/*    */     (c30 = (this.Sa = km.q00.zZ(this.iL0))[0]).ec = paramInt1 + 45;
/*    */     ((this.Sa = km.q00.zZ(this.iL0))[0]).hv = 159;
/*    */   }
/*    */   
/*    */   public final void s6(float paramFloat1, float paramFloat2) {
/*    */     // Byte code:
/*    */     //   0: aload_0
/*    */     //   1: new java/util/ArrayList
/*    */     //   4: dup
/*    */     //   5: invokespecial <init> : ()V
/*    */     //   8: putfield fm0 : Ljava/util/ArrayList;
/*    */     //   11: getstatic f/km.q00 : Lf/Hk;
/*    */     //   14: dup
/*    */     //   15: astore_1
/*    */     //   16: aload_0
/*    */     //   17: getfield iL0 : Lf/OE0;
/*    */     //   20: astore_3
/*    */     //   21: invokevirtual getClass : ()Ljava/lang/Class;
/*    */     //   24: pop
/*    */     //   25: new java/util/ArrayList
/*    */     //   28: dup
/*    */     //   29: astore #4
/*    */     //   31: invokespecial <init> : ()V
/*    */     //   34: getstatic f/Vp0.CR : Lf/Vp0;
/*    */     //   37: dup
/*    */     //   38: aload_3
/*    */     //   39: swap
/*    */     //   40: invokevirtual JM : (Lf/Vp0;)S
/*    */     //   43: invokevirtual O5 : (S)Z
/*    */     //   46: istore #5
/*    */     //   48: iconst_0
/*    */     //   49: istore #6
/*    */     //   51: iload #6
/*    */     //   53: iconst_2
/*    */     //   54: if_icmpge -> 797
/*    */     //   57: iload #6
/*    */     //   59: ifne -> 68
/*    */     //   62: iconst_1
/*    */     //   63: istore #7
/*    */     //   65: goto -> 71
/*    */     //   68: iconst_0
/*    */     //   69: istore #7
/*    */     //   71: iload #6
/*    */     //   73: iconst_1
/*    */     //   74: if_icmpne -> 147
/*    */     //   77: aload_1
/*    */     //   78: aload_3
/*    */     //   79: dup
/*    */     //   80: getstatic f/lPT9.jR : Lf/lPT9;
/*    */     //   83: astore #8
/*    */     //   85: getfield Xu : Lf/H10;
/*    */     //   88: getfield goto : B
/*    */     //   91: istore #9
/*    */     //   93: getfield QM : B
/*    */     //   96: istore #10
/*    */     //   98: aload #8
/*    */     //   100: iload #9
/*    */     //   102: iload #10
/*    */     //   104: invokevirtual zK0 : (Lf/lPT9;II)Lf/pe0;
/*    */     //   107: dup
/*    */     //   108: astore #8
/*    */     //   110: ifnull -> 147
/*    */     //   113: aload #4
/*    */     //   115: new f/uT
/*    */     //   118: dup
/*    */     //   119: astore #9
/*    */     //   121: aload #8
/*    */     //   123: dup
/*    */     //   124: getfield H0 : I
/*    */     //   127: istore #10
/*    */     //   129: getfield Vn0 : I
/*    */     //   132: iload #10
/*    */     //   134: swap
/*    */     //   135: aload #8
/*    */     //   137: iconst_1
/*    */     //   138: invokespecial <init> : (IILf/pe0;Z)V
/*    */     //   141: aload #9
/*    */     //   143: invokevirtual add : (Ljava/lang/Object;)Z
/*    */     //   146: pop
/*    */     //   147: getstatic f/Vp0.Sz0 : Lf/Vp0;
/*    */     //   150: dup
/*    */     //   151: astore #8
/*    */     //   153: aload_3
/*    */     //   154: aload #8
/*    */     //   156: invokevirtual JM : (Lf/Vp0;)S
/*    */     //   159: invokevirtual G6 : (S)Z
/*    */     //   162: ifeq -> 180
/*    */     //   165: getstatic f/lPT9.U4 : Lf/lPT9;
/*    */     //   168: pop
/*    */     //   169: getstatic f/Vp0.sg0 : Lf/Vp0;
/*    */     //   172: aload_3
/*    */     //   173: aload #4
/*    */     //   175: iload #7
/*    */     //   177: invokestatic Yr : (Lf/Vp0;Lf/OE0;Ljava/util/ArrayList;Z)V
/*    */     //   180: aload #8
/*    */     //   182: aload_3
/*    */     //   183: aload #8
/*    */     //   185: invokevirtual JM : (Lf/Vp0;)S
/*    */     //   188: invokevirtual Jz0 : (S)Z
/*    */     //   191: ifeq -> 209
/*    */     //   194: getstatic f/lPT9.U4 : Lf/lPT9;
/*    */     //   197: pop
/*    */     //   198: getstatic f/Vp0.M9 : Lf/Vp0;
/*    */     //   201: aload_3
/*    */     //   202: aload #4
/*    */     //   204: iload #7
/*    */     //   206: invokestatic Yr : (Lf/Vp0;Lf/OE0;Ljava/util/ArrayList;Z)V
/*    */     //   209: aload_3
/*    */     //   210: getstatic f/Vp0.rK : Lf/Vp0;
/*    */     //   213: dup
/*    */     //   214: astore #9
/*    */     //   216: invokevirtual JM : (Lf/Vp0;)S
/*    */     //   219: iconst_1
/*    */     //   220: if_icmpeq -> 229
/*    */     //   223: iconst_1
/*    */     //   224: istore #10
/*    */     //   226: goto -> 232
/*    */     //   229: iconst_0
/*    */     //   230: istore #10
/*    */     //   232: iload #10
/*    */     //   234: ifne -> 251
/*    */     //   237: aload #9
/*    */     //   239: getstatic f/lPT9.U4 : Lf/lPT9;
/*    */     //   242: pop
/*    */     //   243: aload_3
/*    */     //   244: aload #4
/*    */     //   246: iload #7
/*    */     //   248: invokestatic Yr : (Lf/Vp0;Lf/OE0;Ljava/util/ArrayList;Z)V
/*    */     //   251: iload #5
/*    */     //   253: aload #8
/*    */     //   255: getstatic f/lPT9.jR : Lf/lPT9;
/*    */     //   258: astore #8
/*    */     //   260: aload_3
/*    */     //   261: aload #4
/*    */     //   263: iload #7
/*    */     //   265: invokestatic Yr : (Lf/Vp0;Lf/OE0;Ljava/util/ArrayList;Z)V
/*    */     //   268: ifne -> 282
/*    */     //   271: getstatic f/Vp0.CR : Lf/Vp0;
/*    */     //   274: aload_3
/*    */     //   275: aload #4
/*    */     //   277: iload #7
/*    */     //   279: invokestatic Yr : (Lf/Vp0;Lf/OE0;Ljava/util/ArrayList;Z)V
/*    */     //   282: aload_3
/*    */     //   283: dup
/*    */     //   284: getstatic f/Vp0.Pa0 : Lf/Vp0;
/*    */     //   287: aload_3
/*    */     //   288: aload #4
/*    */     //   290: iload #7
/*    */     //   292: invokestatic Yr : (Lf/Vp0;Lf/OE0;Ljava/util/ArrayList;Z)V
/*    */     //   295: getstatic f/Vp0.K7 : Lf/Vp0;
/*    */     //   298: aload_3
/*    */     //   299: aload #4
/*    */     //   301: iload #7
/*    */     //   303: invokestatic Yr : (Lf/Vp0;Lf/OE0;Ljava/util/ArrayList;Z)V
/*    */     //   306: getfield QM : B
/*    */     //   309: istore #9
/*    */     //   311: getstatic f/Vp0.bG : Lf/Vp0;
/*    */     //   314: dup
/*    */     //   315: astore #11
/*    */     //   317: invokevirtual JM : (Lf/Vp0;)S
/*    */     //   320: iconst_m1
/*    */     //   321: if_icmpeq -> 554
/*    */     //   324: aload_3
/*    */     //   325: aload #11
/*    */     //   327: aload_3
/*    */     //   328: getstatic f/Vp0.MP : Lf/Vp0;
/*    */     //   331: invokevirtual JM : (Lf/Vp0;)S
/*    */     //   334: istore #11
/*    */     //   336: invokevirtual JM : (Lf/Vp0;)S
/*    */     //   339: istore #12
/*    */     //   341: iconst_0
/*    */     //   342: istore #13
/*    */     //   344: iload #13
/*    */     //   346: iconst_2
/*    */     //   347: if_icmpge -> 751
/*    */     //   350: iload #13
/*    */     //   352: ifne -> 363
/*    */     //   355: getstatic f/Vp0.MP : Lf/Vp0;
/*    */     //   358: astore #14
/*    */     //   360: goto -> 368
/*    */     //   363: getstatic f/Vp0.bG : Lf/Vp0;
/*    */     //   366: astore #14
/*    */     //   368: iconst_0
/*    */     //   369: istore #15
/*    */     //   371: iload #15
/*    */     //   373: iconst_3
/*    */     //   374: if_icmpge -> 544
/*    */     //   377: iload #15
/*    */     //   379: iconst_1
/*    */     //   380: if_icmpne -> 386
/*    */     //   383: goto -> 534
/*    */     //   386: aload_1
/*    */     //   387: aload #8
/*    */     //   389: iload #7
/*    */     //   391: iconst_1
/*    */     //   392: ixor
/*    */     //   393: iload #15
/*    */     //   395: invokestatic Pj0 : (IB)B
/*    */     //   398: istore #16
/*    */     //   400: iload #11
/*    */     //   402: iload #12
/*    */     //   404: iload #9
/*    */     //   406: iload #16
/*    */     //   408: iconst_1
/*    */     //   409: aconst_null
/*    */     //   410: invokevirtual WJ : (Lf/lPT9;SSBBZLf/vd;)[Lf/pe0;
/*    */     //   413: dup
/*    */     //   414: astore #16
/*    */     //   416: ifnull -> 534
/*    */     //   419: aload #16
/*    */     //   421: iload #13
/*    */     //   423: aaload
/*    */     //   424: dup
/*    */     //   425: astore #16
/*    */     //   427: ifnull -> 534
/*    */     //   430: iload #15
/*    */     //   432: new f/uT
/*    */     //   435: dup
/*    */     //   436: astore #17
/*    */     //   438: aload #16
/*    */     //   440: dup
/*    */     //   441: getfield H0 : I
/*    */     //   444: istore #18
/*    */     //   446: getfield Vn0 : I
/*    */     //   449: iload #18
/*    */     //   451: swap
/*    */     //   452: aload #16
/*    */     //   454: iconst_1
/*    */     //   455: invokespecial <init> : (IILf/pe0;Z)V
/*    */     //   458: ifne -> 518
/*    */     //   461: aload_3
/*    */     //   462: aload #14
/*    */     //   464: invokevirtual F00 : (Lf/Vp0;)Lf/UX;
/*    */     //   467: dup
/*    */     //   468: astore #16
/*    */     //   470: ifnull -> 518
/*    */     //   473: aload #14
/*    */     //   475: getstatic f/Vp0.MP : Lf/Vp0;
/*    */     //   478: if_acmpne -> 488
/*    */     //   481: iload #11
/*    */     //   483: istore #18
/*    */     //   485: goto -> 492
/*    */     //   488: iload #12
/*    */     //   490: istore #18
/*    */     //   492: aload #14
/*    */     //   494: iload #18
/*    */     //   496: invokevirtual Ko : (S)Z
/*    */     //   499: ifne -> 505
/*    */     //   502: goto -> 518
/*    */     //   505: aload #17
/*    */     //   507: aload #16
/*    */     //   509: getfield xK0 : Lcom/badlogic/gdx/graphics/Color;
/*    */     //   512: invokevirtual DD : (Lcom/badlogic/gdx/graphics/Color;)V
/*    */     //   515: goto -> 526
/*    */     //   518: aload #17
/*    */     //   520: getstatic com/badlogic/gdx/graphics/Color.WHITE : Lcom/badlogic/gdx/graphics/Color;
/*    */     //   523: invokevirtual DD : (Lcom/badlogic/gdx/graphics/Color;)V
/*    */     //   526: aload #4
/*    */     //   528: aload #17
/*    */     //   530: invokevirtual add : (Ljava/lang/Object;)Z
/*    */     //   533: pop
/*    */     //   534: iload #15
/*    */     //   536: iconst_1
/*    */     //   537: iadd
/*    */     //   538: i2b
/*    */     //   539: istore #15
/*    */     //   541: goto -> 371
/*    */     //   544: iload #13
/*    */     //   546: iconst_1
/*    */     //   547: iadd
/*    */     //   548: i2b
/*    */     //   549: istore #13
/*    */     //   551: goto -> 344
/*    */     //   554: aload_3
/*    */     //   555: getstatic f/Vp0.MP : Lf/Vp0;
/*    */     //   558: dup
/*    */     //   559: astore #11
/*    */     //   561: invokevirtual JM : (Lf/Vp0;)S
/*    */     //   564: dup
/*    */     //   565: istore #12
/*    */     //   567: iconst_m1
/*    */     //   568: if_icmpne -> 574
/*    */     //   571: goto -> 751
/*    */     //   574: aload #11
/*    */     //   576: iload #12
/*    */     //   578: invokevirtual fM0 : (S)Lf/wc;
/*    */     //   581: dup
/*    */     //   582: astore #11
/*    */     //   584: ifnonnull -> 590
/*    */     //   587: goto -> 751
/*    */     //   590: aload #11
/*    */     //   592: aload #8
/*    */     //   594: invokevirtual ml : (Lf/lPT9;)Lf/X9;
/*    */     //   597: dup
/*    */     //   598: astore #8
/*    */     //   600: ifnonnull -> 606
/*    */     //   603: goto -> 751
/*    */     //   606: aload #8
/*    */     //   608: invokevirtual st0 : ()V
/*    */     //   611: iconst_0
/*    */     //   612: istore #12
/*    */     //   614: iload #12
/*    */     //   616: iconst_3
/*    */     //   617: if_icmpge -> 751
/*    */     //   620: iload #7
/*    */     //   622: ifeq -> 635
/*    */     //   625: iload #12
/*    */     //   627: iconst_3
/*    */     //   628: iadd
/*    */     //   629: i2b
/*    */     //   630: istore #13
/*    */     //   632: goto -> 639
/*    */     //   635: iload #12
/*    */     //   637: istore #13
/*    */     //   639: aload #8
/*    */     //   641: iload #13
/*    */     //   643: iload #9
/*    */     //   645: invokevirtual QB0 : (BB)Lf/pe0;
/*    */     //   648: dup
/*    */     //   649: astore #13
/*    */     //   651: ifnonnull -> 657
/*    */     //   654: goto -> 741
/*    */     //   657: iload #12
/*    */     //   659: new f/uT
/*    */     //   662: dup
/*    */     //   663: astore #14
/*    */     //   665: aload #13
/*    */     //   667: dup
/*    */     //   668: getfield H0 : I
/*    */     //   671: istore #15
/*    */     //   673: getfield Vn0 : I
/*    */     //   676: iload #15
/*    */     //   678: swap
/*    */     //   679: aload #13
/*    */     //   681: iconst_1
/*    */     //   682: invokespecial <init> : (IILf/pe0;Z)V
/*    */     //   685: ifne -> 725
/*    */     //   688: aload_3
/*    */     //   689: getstatic f/Vp0.MP : Lf/Vp0;
/*    */     //   692: invokevirtual F00 : (Lf/Vp0;)Lf/UX;
/*    */     //   695: dup
/*    */     //   696: astore #13
/*    */     //   698: ifnull -> 725
/*    */     //   701: aload #11
/*    */     //   703: invokevirtual XF0 : ()Z
/*    */     //   706: ifne -> 712
/*    */     //   709: goto -> 725
/*    */     //   712: aload #14
/*    */     //   714: aload #13
/*    */     //   716: getfield xK0 : Lcom/badlogic/gdx/graphics/Color;
/*    */     //   719: invokevirtual DD : (Lcom/badlogic/gdx/graphics/Color;)V
/*    */     //   722: goto -> 733
/*    */     //   725: aload #14
/*    */     //   727: getstatic com/badlogic/gdx/graphics/Color.WHITE : Lcom/badlogic/gdx/graphics/Color;
/*    */     //   730: invokevirtual DD : (Lcom/badlogic/gdx/graphics/Color;)V
/*    */     //   733: aload #4
/*    */     //   735: aload #14
/*    */     //   737: invokevirtual add : (Ljava/lang/Object;)Z
/*    */     //   740: pop
/*    */     //   741: iload #12
/*    */     //   743: iconst_1
/*    */     //   744: iadd
/*    */     //   745: i2b
/*    */     //   746: istore #12
/*    */     //   748: goto -> 614
/*    */     //   751: iload #10
/*    */     //   753: ifeq -> 771
/*    */     //   756: getstatic f/lPT9.U4 : Lf/lPT9;
/*    */     //   759: pop
/*    */     //   760: getstatic f/Vp0.rK : Lf/Vp0;
/*    */     //   763: aload_3
/*    */     //   764: aload #4
/*    */     //   766: iload #7
/*    */     //   768: invokestatic Yr : (Lf/Vp0;Lf/OE0;Ljava/util/ArrayList;Z)V
/*    */     //   771: iload #5
/*    */     //   773: ifeq -> 791
/*    */     //   776: getstatic f/lPT9.U4 : Lf/lPT9;
/*    */     //   779: pop
/*    */     //   780: getstatic f/Vp0.CR : Lf/Vp0;
/*    */     //   783: aload_3
/*    */     //   784: aload #4
/*    */     //   786: iload #7
/*    */     //   788: invokestatic Yr : (Lf/Vp0;Lf/OE0;Ljava/util/ArrayList;Z)V
/*    */     //   791: iinc #6, 1
/*    */     //   794: goto -> 51
/*    */     //   797: aload #4
/*    */     //   799: invokevirtual iterator : ()Ljava/util/Iterator;
/*    */     //   802: astore_1
/*    */     //   803: aload_1
/*    */     //   804: invokeinterface hasNext : ()Z
/*    */     //   809: ifeq -> 858
/*    */     //   812: aload_0
/*    */     //   813: aload_1
/*    */     //   814: invokeinterface next : ()Ljava/lang/Object;
/*    */     //   819: checkcast f/uT
/*    */     //   822: dup
/*    */     //   823: dup
/*    */     //   824: astore_3
/*    */     //   825: getstatic f/vH.xC : Lf/eo;
/*    */     //   828: invokevirtual WI0 : (Lf/eo;)V
/*    */     //   831: getfield He0 : Lf/eo;
/*    */     //   834: fload_2
/*    */     //   835: ldc_w 0.25
/*    */     //   838: fadd
/*    */     //   839: ldc_w -0.025
/*    */     //   842: fconst_0
/*    */     //   843: invokevirtual Tz : (FFF)Lf/eo;
/*    */     //   846: pop
/*    */     //   847: getfield fm0 : Ljava/util/ArrayList;
/*    */     //   850: aload_3
/*    */     //   851: invokevirtual add : (Ljava/lang/Object;)Z
/*    */     //   854: pop
/*    */     //   855: goto -> 803
/*    */     //   858: return
/*    */     // Line number table:
/*    */     //   Java source line number -> byte code offset
/*    */     //   #1	-> 25
/*    */     //   #2	-> 85
/*    */     //   #3	-> 88
/*    */     //   #4	-> 93
/*    */     //   #5	-> 104
/*    */     //   #6	-> 115
/*    */     //   #7	-> 124
/*    */     //   #8	-> 129
/*    */     //   #9	-> 138
/*    */     //   #10	-> 143
/*    */     //   #11	-> 306
/*    */     //   #12	-> 311
/*    */     //   #13	-> 432
/*    */     //   #14	-> 441
/*    */     //   #15	-> 446
/*    */     //   #16	-> 455
/*    */     //   #17	-> 464
/*    */     //   #18	-> 509
/*    */     //   #19	-> 512
/*    */     //   #20	-> 645
/*    */     //   #21	-> 659
/*    */     //   #22	-> 668
/*    */     //   #23	-> 673
/*    */     //   #24	-> 682
/*    */     //   #25	-> 689
/*    */     //   #26	-> 716
/*    */     //   #27	-> 719
/*    */     //   #28	-> 756
/*    */     //   #29	-> 799
/*    */     //   #30	-> 831
/*    */     //   #31	-> 843
/*    */   }
/*    */   
/*    */   public final List lK() {
/*    */     return this.fm0;
/*    */   }
/*    */   
/*    */   public final void Ll0(tH paramtH) {
/*    */     if (this.bH != null)
/*    */       this.Sa[0].Ht(paramtH); 
/*    */     dK0 dK01;
/*    */     if ((dK01 = this.On0) != null)
/*    */       Yo0(paramtH); 
/*    */   }
/*    */   
/*    */   public final void ub(int paramInt1, int paramInt2, boolean paramBoolean) {
/*    */     if (paramBoolean)
/*    */       this.On0 = (dK0)(new dK0(this.Sa, paramInt1)).ff0(); 
/*    */     this.bH = null;
/*    */   }
/*    */   
/*    */   public final void Oi() {
/*    */     boolean bool = false;
/*    */     (this.Sa[0]).ec = 45;
/*    */     (this.Sa[0]).hv = bool;
/*    */   }
/*    */   
/*    */   public final mi pW() {
/*    */     return this.bH;
/*    */   }
/*    */   
/*    */   public final boolean mL() {
/*    */     boolean bool;
/*    */     Gp0 gp0;
/*    */     if ((gp0 = km.MR) == null)
/*    */       return false; 
/*    */     if (this.T20 >= this.kx) {
/*    */       bool = true;
/*    */     } else {
/*    */       bool = false;
/*    */     } 
/*    */     return !!bool;
/*    */   }
/*    */   
/*    */   public final String Lc() {
/*    */     return Ml0.Go(5038, Integer.toString(km.MR.kx));
/*    */   }
/*    */   
/*    */   public final String dy() {
/*    */     return this.gy;
/*    */   }
/*    */   
/*    */   public final String s7(byte paramByte) {
/*    */     byte b;
/*    */     Gp0 gp0;
/*    */     if ((gp0 = km.MR) != null && !gp0.sQ() && km.MR.hG0() == (b = this.Fu) && km.MR.wB(b) == this)
/*    */       return ""; 
/*    */     return this.gy;
/*    */   }
/*    */   
/*    */   public final boolean jj(byte paramByte) {
/*    */     byte b;
/*    */     Gp0 gp0;
/*    */     if ((gp0 = km.MR) != null && !gp0.sQ() && km.MR.hG0() == (b = this.Fu) && km.MR.wB(b) == this)
/*    */       return false; 
/*    */     return true;
/*    */   }
/*    */   
/*    */   public final boolean GT(kf paramkf, boolean paramBoolean, String paramString, byte paramByte, hj[] paramArrayOfhj, int paramInt) {
/*    */     paramBoolean = super.GT(paramkf, paramBoolean, paramString, paramByte, paramArrayOfhj, paramInt);
/*    */     if (!paramBoolean && !paramString.isEmpty()) {
/*    */       char c;
/*    */       paramBoolean = true;
/*    */       if (paramByte > 1) {
/*    */         c = '᎚';
/*    */       } else {
/*    */         c = '᎙';
/*    */       } 
/*    */       (new String[2])[0] = paramString;
/*    */       boolean bool = true;
/*    */       (new String[2])[bool] = this.gy;
/*    */       paramkf.Kq(Ml0.sB(c, new String[2]));
/*    */     } 
/*    */     return paramBoolean;
/*    */   }
/*    */   
/*    */   public final rs0 kf() {
/*    */     return this.Ne0;
/*    */   }
/*    */   
/*    */   public final short Bp0() {
/*    */     return this.CY;
/*    */   } }


/* Location:              /Users/vnnsnnt/Documents/Codespace/JavaWorkspace/RedTrainer/src/main/java/org/trainer/client/PokeMMO.jar!/f/W30.class
 * Java compiler version: 8 (52.0)
 * JD-Core Version:       1.1.3
 */