/*    */ package f;public final class wg0 extends Qa0 implements Bf, r60 { public static final HashMap X80 = new HashMap<>(); public final pA Dr0; public final boolean c8; public final boolean aw0; public final Hu0[] Se0; public final Ip ID0; public final kI0 QP; public Hu0 UI; public final nJ[] f0; public final NuL[] Br; public dQ yr0; public final of fJ; public Dk TA0; public ex y60; public nn0 Vs; public Uh Da0; public ck COm7; public int SV; public int Zp0; public final yM A00; public wg0(pA parampA, boolean paramBoolean) { // Byte code:
/*    */     //   0: aload_0
/*    */     //   1: dup
/*    */     //   2: dup
/*    */     //   3: iload_2
/*    */     //   4: aload_0
/*    */     //   5: aload_1
/*    */     //   6: aload_0
/*    */     //   7: dup
/*    */     //   8: dup2
/*    */     //   9: invokestatic XU : ()Z
/*    */     //   12: invokespecial <init> : (Z)V
/*    */     //   15: getstatic f/Hu0.M8 : Lf/Hu0;
/*    */     //   18: dup
/*    */     //   19: astore_1
/*    */     //   20: putfield UI : Lf/Hu0;
/*    */     //   23: iconst_m1
/*    */     //   24: putfield SV : I
/*    */     //   27: iconst_0
/*    */     //   28: putfield Zp0 : I
/*    */     //   31: putfield Dr0 : Lf/pA;
/*    */     //   34: putfield c8 : Z
/*    */     //   37: <illegal opcode> run : (Lf/wg0;)Ljava/lang/Runnable;
/*    */     //   42: invokevirtual TG0 : (Ljava/lang/Runnable;)V
/*    */     //   45: invokestatic XU : ()Z
/*    */     //   48: ifeq -> 60
/*    */     //   51: aload_0
/*    */     //   52: ldc 'mobile-inventory-tabbedframe'
/*    */     //   54: invokevirtual Xu : (Ljava/lang/String;)V
/*    */     //   57: goto -> 66
/*    */     //   60: aload_0
/*    */     //   61: ldc 'inventory-tabbedframe'
/*    */     //   63: invokevirtual Xu : (Ljava/lang/String;)V
/*    */     //   66: aload_0
/*    */     //   67: iconst_1
/*    */     //   68: invokevirtual EP : (I)V
/*    */     //   71: getstatic f/km.u4 : Lf/R8;
/*    */     //   74: invokevirtual Uo0 : ()Lf/yM;
/*    */     //   77: dup
/*    */     //   78: astore_3
/*    */     //   79: aload_0
/*    */     //   80: aload_3
/*    */     //   81: putfield A00 : Lf/yM;
/*    */     //   84: getstatic f/yM.LU : Lf/yM;
/*    */     //   87: dup
/*    */     //   88: astore #4
/*    */     //   90: if_acmpeq -> 109
/*    */     //   93: aload_3
/*    */     //   94: getstatic f/yM.SN : Lf/yM;
/*    */     //   97: if_acmpne -> 103
/*    */     //   100: goto -> 109
/*    */     //   103: iconst_0
/*    */     //   104: istore #5
/*    */     //   106: goto -> 112
/*    */     //   109: iconst_1
/*    */     //   110: istore #5
/*    */     //   112: iload #5
/*    */     //   114: aload_0
/*    */     //   115: iload #5
/*    */     //   117: putfield aw0 : Z
/*    */     //   120: ifeq -> 173
/*    */     //   123: aload_0
/*    */     //   124: dup
/*    */     //   125: dup
/*    */     //   126: iload_2
/*    */     //   127: aload_0
/*    */     //   128: sipush #1460
/*    */     //   131: invokestatic OH0 : (I)Ljava/lang/String;
/*    */     //   134: invokevirtual toUpperCase : ()Ljava/lang/String;
/*    */     //   137: invokevirtual Lo : (Ljava/lang/String;)V
/*    */     //   140: iconst_1
/*    */     //   141: ixor
/*    */     //   142: dup
/*    */     //   143: istore #5
/*    */     //   145: anewarray f/nJ
/*    */     //   148: putfield f0 : [Lf/nJ;
/*    */     //   151: iload #5
/*    */     //   153: anewarray f/NuL
/*    */     //   156: putfield Br : [Lf/NuL;
/*    */     //   159: iconst_1
/*    */     //   160: anewarray f/Hu0
/*    */     //   163: dup
/*    */     //   164: iconst_0
/*    */     //   165: aload_1
/*    */     //   166: aastore
/*    */     //   167: putfield Se0 : [Lf/Hu0;
/*    */     //   170: goto -> 265
/*    */     //   173: iload_2
/*    */     //   174: aload_0
/*    */     //   175: new java/lang/StringBuilder
/*    */     //   178: dup
/*    */     //   179: astore #5
/*    */     //   181: invokespecial <init> : ()V
/*    */     //   184: sipush #1400
/*    */     //   187: aload #5
/*    */     //   189: ldc ' - '
/*    */     //   191: invokestatic X9 : (ILjava/lang/StringBuilder;Ljava/lang/String;)Ljava/lang/StringBuilder;
/*    */     //   194: aload_1
/*    */     //   195: invokevirtual oo : ()I
/*    */     //   198: invokestatic OH0 : (I)Ljava/lang/String;
/*    */     //   201: invokevirtual toUpperCase : ()Ljava/lang/String;
/*    */     //   204: invokevirtual append : (Ljava/lang/String;)Ljava/lang/StringBuilder;
/*    */     //   207: invokevirtual toString : ()Ljava/lang/String;
/*    */     //   210: invokevirtual Lo : (Ljava/lang/String;)V
/*    */     //   213: ifeq -> 220
/*    */     //   216: iconst_0
/*    */     //   217: goto -> 224
/*    */     //   220: getstatic f/Hu0.It : [Lf/Hu0;
/*    */     //   223: arraylength
/*    */     //   224: anewarray f/nJ
/*    */     //   227: astore #5
/*    */     //   229: iload_2
/*    */     //   230: aload_0
/*    */     //   231: aload #5
/*    */     //   233: putfield f0 : [Lf/nJ;
/*    */     //   236: ifeq -> 243
/*    */     //   239: iconst_0
/*    */     //   240: goto -> 247
/*    */     //   243: getstatic f/Hu0.It : [Lf/Hu0;
/*    */     //   246: arraylength
/*    */     //   247: anewarray f/NuL
/*    */     //   250: astore #5
/*    */     //   252: aload_0
/*    */     //   253: dup
/*    */     //   254: aload #5
/*    */     //   256: putfield Br : [Lf/NuL;
/*    */     //   259: getstatic f/Hu0.pJ : [Lf/Hu0;
/*    */     //   262: putfield Se0 : [Lf/Hu0;
/*    */     //   265: aload_0
/*    */     //   266: dup
/*    */     //   267: new f/of
/*    */     //   270: dup
/*    */     //   271: astore #5
/*    */     //   273: aload_0
/*    */     //   274: aload #5
/*    */     //   276: aload_0
/*    */     //   277: aload #5
/*    */     //   279: dup
/*    */     //   280: invokespecial <init> : ()V
/*    */     //   283: putfield fJ : Lf/of;
/*    */     //   286: invokevirtual LE : ()V
/*    */     //   289: <illegal opcode> SX : (Lf/wg0;)Lf/a70;
/*    */     //   294: invokevirtual JD0 : (Lf/a70;)V
/*    */     //   297: new f/kI0
/*    */     //   300: dup
/*    */     //   301: dup
/*    */     //   302: astore #6
/*    */     //   304: aload_0
/*    */     //   305: aload #6
/*    */     //   307: dup
/*    */     //   308: invokespecial <init> : ()V
/*    */     //   311: putfield QP : Lf/kI0;
/*    */     //   314: iconst_0
/*    */     //   315: invokevirtual Xh : (Z)V
/*    */     //   318: ldc 'tabbedpane'
/*    */     //   320: invokevirtual Xu : (Ljava/lang/String;)V
/*    */     //   323: new f/Ip
/*    */     //   326: dup
/*    */     //   327: dup2
/*    */     //   328: dup2
/*    */     //   329: aload_0
/*    */     //   330: swap
/*    */     //   331: dup
/*    */     //   332: invokespecial <init> : ()V
/*    */     //   335: putfield ID0 : Lf/Ip;
/*    */     //   338: invokevirtual d7 : ()Lf/cr0;
/*    */     //   341: bipush #10
/*    */     //   343: invokevirtual Aq : (I)Lf/U90;
/*    */     //   346: iconst_1
/*    */     //   347: anewarray f/JG0
/*    */     //   350: dup
/*    */     //   351: iconst_0
/*    */     //   352: aload #6
/*    */     //   354: aastore
/*    */     //   355: invokevirtual Mg : ([Lf/JG0;)Lf/U90;
/*    */     //   358: invokevirtual rK0 : (Lf/U90;)V
/*    */     //   361: iconst_1
/*    */     //   362: anewarray f/JG0
/*    */     //   365: dup
/*    */     //   366: iconst_0
/*    */     //   367: aload #6
/*    */     //   369: aastore
/*    */     //   370: invokevirtual vo0 : ([Lf/JG0;)Lf/U90;
/*    */     //   373: invokevirtual WN : (Lf/U90;)V
/*    */     //   376: invokevirtual J8 : (Lf/JG0;)V
/*    */     //   379: aload #5
/*    */     //   381: invokevirtual J8 : (Lf/JG0;)V
/*    */     //   384: invokestatic XU : ()Z
/*    */     //   387: ifeq -> 433
/*    */     //   390: aload_0
/*    */     //   391: dup
/*    */     //   392: new f/dQ
/*    */     //   395: dup
/*    */     //   396: dup
/*    */     //   397: astore #5
/*    */     //   399: invokestatic getInstance : ()Ljava/text/NumberFormat;
/*    */     //   402: getstatic f/km.u4 : Lf/R8;
/*    */     //   405: invokevirtual IQ : ()Lf/fH0;
/*    */     //   408: invokevirtual rK0 : ()I
/*    */     //   411: i2l
/*    */     //   412: invokevirtual format : (J)Ljava/lang/String;
/*    */     //   415: sipush #1928
/*    */     //   418: swap
/*    */     //   419: invokestatic Go : (ILjava/lang/String;)Ljava/lang/String;
/*    */     //   422: invokespecial <init> : (Ljava/lang/String;)V
/*    */     //   425: putfield yr0 : Lf/dQ;
/*    */     //   428: aload #5
/*    */     //   430: invokevirtual J8 : (Lf/JG0;)V
/*    */     //   433: invokestatic XU : ()Z
/*    */     //   436: ifeq -> 461
/*    */     //   439: aload_0
/*    */     //   440: dup
/*    */     //   441: new f/ck
/*    */     //   444: dup
/*    */     //   445: astore #5
/*    */     //   447: aload_0
/*    */     //   448: invokespecial <init> : (Lf/wg0;)V
/*    */     //   451: aload #5
/*    */     //   453: putfield COm7 : Lf/ck;
/*    */     //   456: aload #5
/*    */     //   458: invokevirtual J8 : (Lf/JG0;)V
/*    */     //   461: iload_2
/*    */     //   462: getstatic f/km.a3 : Lf/vh0;
/*    */     //   465: invokevirtual ui0 : ()B
/*    */     //   468: istore #5
/*    */     //   470: getstatic f/km.u4 : Lf/R8;
/*    */     //   473: aload_3
/*    */     //   474: invokevirtual gN : (Lf/yM;)Lf/zr0;
/*    */     //   477: invokevirtual ro0 : ()[Lf/Y;
/*    */     //   480: astore #6
/*    */     //   482: ifne -> 536
/*    */     //   485: aload_3
/*    */     //   486: aload #4
/*    */     //   488: if_acmpeq -> 498
/*    */     //   491: aload_3
/*    */     //   492: getstatic f/yM.SN : Lf/yM;
/*    */     //   495: if_acmpne -> 536
/*    */     //   498: aload_0
/*    */     //   499: aload_1
/*    */     //   500: aload #6
/*    */     //   502: invokestatic of : ([Ljava/lang/Object;)Ljava/util/stream/Stream;
/*    */     //   505: iload #5
/*    */     //   507: <illegal opcode> test : (B)Ljava/util/function/Predicate;
/*    */     //   512: invokeinterface filter : (Ljava/util/function/Predicate;)Ljava/util/stream/Stream;
/*    */     //   517: <illegal opcode> apply : ()Ljava/util/function/IntFunction;
/*    */     //   522: invokeinterface toArray : (Ljava/util/function/IntFunction;)[Ljava/lang/Object;
/*    */     //   527: checkcast [Lf/Y;
/*    */     //   530: invokevirtual kc0 : (Lf/Hu0;[Lf/Y;)V
/*    */     //   533: goto -> 609
/*    */     //   536: getstatic f/Hu0.pJ : [Lf/Hu0;
/*    */     //   539: dup
/*    */     //   540: astore_1
/*    */     //   541: arraylength
/*    */     //   542: istore_3
/*    */     //   543: iconst_0
/*    */     //   544: istore #4
/*    */     //   546: iload #4
/*    */     //   548: iload_3
/*    */     //   549: if_icmpge -> 609
/*    */     //   552: iload_2
/*    */     //   553: aload_1
/*    */     //   554: iload #4
/*    */     //   556: aaload
/*    */     //   557: astore #7
/*    */     //   559: ifeq -> 565
/*    */     //   562: goto -> 603
/*    */     //   565: aload_0
/*    */     //   566: aload #7
/*    */     //   568: aload #6
/*    */     //   570: invokestatic of : ([Ljava/lang/Object;)Ljava/util/stream/Stream;
/*    */     //   573: aload #7
/*    */     //   575: iload #5
/*    */     //   577: <illegal opcode> test : (Lf/Hu0;B)Ljava/util/function/Predicate;
/*    */     //   582: invokeinterface filter : (Ljava/util/function/Predicate;)Ljava/util/stream/Stream;
/*    */     //   587: <illegal opcode> apply : ()Ljava/util/function/IntFunction;
/*    */     //   592: invokeinterface toArray : (Ljava/util/function/IntFunction;)[Ljava/lang/Object;
/*    */     //   597: checkcast [Lf/Y;
/*    */     //   600: invokevirtual kc0 : (Lf/Hu0;[Lf/Y;)V
/*    */     //   603: iinc #4, 1
/*    */     //   606: goto -> 546
/*    */     //   609: aload_0
/*    */     //   610: sipush #550
/*    */     //   613: sipush #140
/*    */     //   616: invokevirtual uh0 : (II)V
/*    */     //   619: return
/*    */     // Line number table:
/*    */     //   Java source line number -> byte code offset
/*    */     //   #1	-> 189
/*    */     //   #2	-> 195 }
/*  2 */   private void wT(Y paramY) { short s; if ((s = paramY.Lh.Sf0) > 1)
/*    */     { WG0 wG0; AD0 aD02, aD01;
/*  4 */       if ((aD01 = (AD0)vC0.Bv0(js.vu0, AD0.class)) != null) { VA0.c90(aD01);
/*    */         
/*    */         return; }
/*    */       
/*  8 */       String str = Ml0.Go(1432, Ml0.OH0(paramY.Bp0.Iu)); this(this, paramY); this(str, s, wG0, this);
/*  9 */       js.vu0
/*    */         
/* 11 */         .si(aD02, js.vu0.Ub()); }
/* 12 */     else { sd0(paramY, (short)1); }  } private void l60(Y paramY) { boolean bool = false; ZN((short)372, bool, paramY.Lh.Wy, (short)0, (byte)-1); } private void d70(Y paramY1, Y paramY2) { if (paramY1 == null) { km.u4.Pq(Ml0.OH0(8580)); return; }  short s = paramY1.Lh.p1; int i = paramY1.Lh.Wy; ZN(s, i, paramY2.Lh.Wy, (short)1, (byte)-1); } public static void Md0(Y paramY, int paramInt) { if (pA.Dg0.WH != null) { SE0[] arrayOfSE0; String[] arrayOfString; (arrayOfString = new String[2])[0] = paramY.JG0(); (new String[2])[1] = (paramInt + 1) + ""; js.vu0.Pu(-1, Ml0.sB(1415, arrayOfString)); xJ0 xJ0 = pA.Dg0.WH; short s = paramY.Lh.p1; int i = paramY.Lh.Wy; if (paramInt >= 0) { if (paramInt < (arrayOfSE0 = xJ0.sN).length) arrayOfSE0[paramInt]
/* 13 */             .Kh(i, s, true);  } else { arrayOfSE0
/* 14 */           .getClass(); }  }  }
/*    */   public static void no0(Y paramY) { Gp0 gp0; if ((gp0 = Lj.UK0(paramY.Bp0.KI)) == null) return;  this(); e50 e50; gp0.W.add(e50); km.MR = gp0; }
/*    */   private void vX(Y paramY, short paramShort) { int i = paramY.Lh.Wy; km.u4.e20.W3(new Bf0(i, paramShort)); if (km.XU() && paramShort >= paramY.Lh.Sf0) this.COm7.VJ(null);  }
/*    */   public static void BF0() { pA pA1; wg0 wg01; if ((wg01 = (pA1 = pA.Dg0).iA0) != null) { pA1.uP = wg01.Kd; pA1.dM = wg01.er0; wg01.ra0(); pA1.iA0 = null; js.vu0.KE(); }  } public static void Jr() { pA pA1; wg0 wg01; if ((wg01 = (pA1 = pA.Dg0).Mc) != null) { wg01.ra0(); pA1.Mc = null; js.vu0.KE(); }  } private void xe(Hu0 paramHu0, int[] paramArrayOfint) { int i; (this.Br[i = paramHu0.wt0]).H40.rt(paramArrayOfint[i]); } private boolean FL0(Hu0 paramHu0, byte paramByte, Y paramY) { byte b; if ((paramY.Bp0.Y8 == paramHu0 || this.aw0) && ((b = paramY.Lh.Pw0) == paramByte || b == -1)) return true;  } private void eT(Hu0 paramHu0) { this.UI = paramHu0; if (this.aw0) { Lo(Ml0.OH0(1460).toUpperCase()); } else { StringBuilder stringBuilder; this(); Lo(pv.X9(1400, stringBuilder, " - ").append(Ml0.OH0(this.UI.jC0).toUpperCase()).toString()); }  } public static boolean JH(Hu0 paramHu0, byte paramByte, Y paramY) { byte b; return (paramY.Bp0.Y8 == paramHu0 && ((b = paramY.Lh.Pw0) == paramByte || b == -1)); } public static boolean xn0(byte paramByte, Y paramY) { byte b; if ((b = paramY.Lh.Pw0) == paramByte || b == -1) return true;  } public final void kc0(Hu0 paramHu0, Y[] paramArrayOfY) { // Byte code:
/*    */     //   0: aload_0
/*    */     //   1: dup
/*    */     //   2: dup
/*    */     //   3: new f/NuL
/*    */     //   6: dup
/*    */     //   7: astore_3
/*    */     //   8: aload_0
/*    */     //   9: dup
/*    */     //   10: getfield COm7 : Lf/ck;
/*    */     //   13: aload_1
/*    */     //   14: aload_2
/*    */     //   15: invokespecial <init> : (Lf/wg0;Lf/ck;Lf/Hu0;[Lf/Y;)V
/*    */     //   18: getfield Br : [Lf/NuL;
/*    */     //   21: aload_1
/*    */     //   22: getfield wt0 : I
/*    */     //   25: dup
/*    */     //   26: istore_2
/*    */     //   27: aload_3
/*    */     //   28: aastore
/*    */     //   29: getfield f0 : [Lf/nJ;
/*    */     //   32: astore #4
/*    */     //   34: getfield QP : Lf/kI0;
/*    */     //   37: astore #5
/*    */     //   39: invokestatic XU : ()Z
/*    */     //   42: ifeq -> 57
/*    */     //   45: aload_1
/*    */     //   46: getfield jC0 : I
/*    */     //   49: invokestatic OH0 : (I)Ljava/lang/String;
/*    */     //   52: astore #6
/*    */     //   54: goto -> 62
/*    */     //   57: ldc_w ''
/*    */     //   60: astore #6
/*    */     //   62: aload #5
/*    */     //   64: invokevirtual getClass : ()Ljava/lang/Class;
/*    */     //   67: pop
/*    */     //   68: new f/nJ
/*    */     //   71: dup
/*    */     //   72: dup2
/*    */     //   73: astore #7
/*    */     //   75: aload #5
/*    */     //   77: invokespecial <init> : (Lf/kI0;)V
/*    */     //   80: getfield r00 : Lf/Dj;
/*    */     //   83: aload #6
/*    */     //   85: invokevirtual s6 : (Ljava/lang/String;)V
/*    */     //   88: getfield em : Lf/JG0;
/*    */     //   91: dup
/*    */     //   92: astore #6
/*    */     //   94: aload_3
/*    */     //   95: if_acmpeq -> 142
/*    */     //   98: aload #6
/*    */     //   100: ifnull -> 114
/*    */     //   103: aload #5
/*    */     //   105: getfield ut : Lf/Fp;
/*    */     //   108: aload #6
/*    */     //   110: invokevirtual jf0 : (Lf/JG0;)Z
/*    */     //   113: pop
/*    */     //   114: aload #5
/*    */     //   116: aload_3
/*    */     //   117: aload #7
/*    */     //   119: dup
/*    */     //   120: aload_3
/*    */     //   121: putfield em : Lf/JG0;
/*    */     //   124: invokevirtual getValue : ()Z
/*    */     //   127: invokevirtual wI0 : (Z)V
/*    */     //   130: getfield ut : Lf/Fp;
/*    */     //   133: dup
/*    */     //   134: aload_3
/*    */     //   135: swap
/*    */     //   136: invokevirtual Ub : ()I
/*    */     //   139: invokevirtual si : (Lf/JG0;I)V
/*    */     //   142: aload #5
/*    */     //   144: dup
/*    */     //   145: dup
/*    */     //   146: getfield aR : Lf/Q20;
/*    */     //   149: dup
/*    */     //   150: aload #7
/*    */     //   152: getfield r00 : Lf/Dj;
/*    */     //   155: astore_3
/*    */     //   156: invokevirtual Ub : ()I
/*    */     //   159: aload_3
/*    */     //   160: swap
/*    */     //   161: invokevirtual si : (Lf/JG0;I)V
/*    */     //   164: getfield qL : Ljava/util/ArrayList;
/*    */     //   167: aload #7
/*    */     //   169: invokevirtual add : (Ljava/lang/Object;)Z
/*    */     //   172: pop
/*    */     //   173: getfield qL : Ljava/util/ArrayList;
/*    */     //   176: invokevirtual size : ()I
/*    */     //   179: iconst_1
/*    */     //   180: if_icmpne -> 190
/*    */     //   183: aload #5
/*    */     //   185: aload #7
/*    */     //   187: invokevirtual Ax0 : (Lf/nJ;)V
/*    */     //   190: aload #5
/*    */     //   192: iconst_0
/*    */     //   193: istore_3
/*    */     //   194: getfield qL : Ljava/util/ArrayList;
/*    */     //   197: invokevirtual size : ()I
/*    */     //   200: istore #6
/*    */     //   202: iload_3
/*    */     //   203: iload #6
/*    */     //   205: if_icmpge -> 292
/*    */     //   208: iload_3
/*    */     //   209: aload #5
/*    */     //   211: getfield qL : Ljava/util/ArrayList;
/*    */     //   214: iload_3
/*    */     //   215: invokevirtual get : (I)Ljava/lang/Object;
/*    */     //   218: checkcast f/nJ
/*    */     //   221: getfield r00 : Lf/Dj;
/*    */     //   224: getfield O : Lf/Sa0;
/*    */     //   227: astore #8
/*    */     //   229: getstatic f/kI0.K6 : Lf/Ll;
/*    */     //   232: astore #9
/*    */     //   234: ifne -> 243
/*    */     //   237: iconst_1
/*    */     //   238: istore #10
/*    */     //   240: goto -> 246
/*    */     //   243: iconst_0
/*    */     //   244: istore #10
/*    */     //   246: iload_3
/*    */     //   247: iload #6
/*    */     //   249: aload #8
/*    */     //   251: aload #9
/*    */     //   253: iload #10
/*    */     //   255: invokevirtual gf0 : (Lf/Ll;Z)V
/*    */     //   258: getstatic f/kI0.lf : Lf/Ll;
/*    */     //   261: astore #9
/*    */     //   263: iconst_1
/*    */     //   264: isub
/*    */     //   265: if_icmpne -> 274
/*    */     //   268: iconst_1
/*    */     //   269: istore #10
/*    */     //   271: goto -> 277
/*    */     //   274: iconst_0
/*    */     //   275: istore #10
/*    */     //   277: aload #8
/*    */     //   279: aload #9
/*    */     //   281: iload #10
/*    */     //   283: invokevirtual gf0 : (Lf/Ll;Z)V
/*    */     //   286: iinc #3, 1
/*    */     //   289: goto -> 202
/*    */     //   292: aload_1
/*    */     //   293: aload_0
/*    */     //   294: dup
/*    */     //   295: aload #4
/*    */     //   297: iload_2
/*    */     //   298: aload #7
/*    */     //   300: aastore
/*    */     //   301: getfield f0 : [Lf/nJ;
/*    */     //   304: aload_1
/*    */     //   305: getfield wt0 : I
/*    */     //   308: aaload
/*    */     //   309: getfield r00 : Lf/Dj;
/*    */     //   312: dup
/*    */     //   313: dup
/*    */     //   314: invokevirtual getClass : ()Ljava/lang/Class;
/*    */     //   317: pop
/*    */     //   318: ldc_w 'inventory-tab-empty'
/*    */     //   321: invokevirtual Xu : (Ljava/lang/String;)V
/*    */     //   324: invokevirtual cZ : ()V
/*    */     //   327: getfield f0 : [Lf/nJ;
/*    */     //   330: aload_1
/*    */     //   331: getfield wt0 : I
/*    */     //   334: aaload
/*    */     //   335: aload_0
/*    */     //   336: aload_1
/*    */     //   337: <illegal opcode> run : (Lf/wg0;Lf/Hu0;)Ljava/lang/Runnable;
/*    */     //   342: invokevirtual Ac0 : (Ljava/lang/Runnable;)V
/*    */     //   345: invokevirtual ordinal : ()I
/*    */     //   348: tableswitch default -> 396, 0 -> 445, 1 -> 438, 2 -> 431, 3 -> 424, 4 -> 417, 5 -> 396, 6 -> 410, 7 -> 403
/*    */     //   396: sipush #5459
/*    */     //   399: istore_2
/*    */     //   400: goto -> 449
/*    */     //   403: sipush #5057
/*    */     //   406: istore_2
/*    */     //   407: goto -> 449
/*    */     //   410: sipush #5017
/*    */     //   413: istore_2
/*    */     //   414: goto -> 449
/*    */     //   417: sipush #5155
/*    */     //   420: istore_2
/*    */     //   421: goto -> 449
/*    */     //   424: sipush #5252
/*    */     //   427: istore_2
/*    */     //   428: goto -> 449
/*    */     //   431: sipush #5004
/*    */     //   434: istore_2
/*    */     //   435: goto -> 449
/*    */     //   438: sipush #5476
/*    */     //   441: istore_2
/*    */     //   442: goto -> 449
/*    */     //   445: sipush #5436
/*    */     //   448: istore_2
/*    */     //   449: aload_0
/*    */     //   450: getfield aw0 : Z
/*    */     //   453: ifeq -> 460
/*    */     //   456: sipush #1421
/*    */     //   459: istore_2
/*    */     //   460: getstatic f/wg0.X80 : Ljava/util/HashMap;
/*    */     //   463: dup
/*    */     //   464: astore_3
/*    */     //   465: iload_2
/*    */     //   466: invokestatic valueOf : (S)Ljava/lang/Short;
/*    */     //   469: invokevirtual get : (Ljava/lang/Object;)Ljava/lang/Object;
/*    */     //   472: checkcast [Lf/U70;
/*    */     //   475: dup
/*    */     //   476: astore #4
/*    */     //   478: ifnonnull -> 523
/*    */     //   481: aload_3
/*    */     //   482: iload_2
/*    */     //   483: iconst_2
/*    */     //   484: anewarray f/U70
/*    */     //   487: dup
/*    */     //   488: astore #4
/*    */     //   490: getstatic f/wm0.y0 : Lf/wm0;
/*    */     //   493: dup
/*    */     //   494: astore_3
/*    */     //   495: iload_2
/*    */     //   496: aload #4
/*    */     //   498: aload_3
/*    */     //   499: iload_2
/*    */     //   500: iconst_1
/*    */     //   501: invokevirtual SJ0 : (SZ)Lf/U70;
/*    */     //   504: iconst_0
/*    */     //   505: swap
/*    */     //   506: aastore
/*    */     //   507: iconst_0
/*    */     //   508: invokevirtual SJ0 : (SZ)Lf/U70;
/*    */     //   511: iconst_1
/*    */     //   512: swap
/*    */     //   513: aastore
/*    */     //   514: invokestatic valueOf : (S)Ljava/lang/Short;
/*    */     //   517: aload #4
/*    */     //   519: invokevirtual put : (Ljava/lang/Object;Ljava/lang/Object;)Ljava/lang/Object;
/*    */     //   522: pop
/*    */     //   523: aload_0
/*    */     //   524: getfield f0 : [Lf/nJ;
/*    */     //   527: aload_1
/*    */     //   528: getfield wt0 : I
/*    */     //   531: aaload
/*    */     //   532: getfield r00 : Lf/Dj;
/*    */     //   535: getfield N20 : Lf/rH;
/*    */     //   538: dup
/*    */     //   539: astore_0
/*    */     //   540: aload #4
/*    */     //   542: invokevirtual qt : ([Lf/U70;)Lf/JG0;
/*    */     //   545: pop
/*    */     //   546: invokestatic XU : ()Z
/*    */     //   549: ifeq -> 569
/*    */     //   552: aload_0
/*    */     //   553: dup
/*    */     //   554: bipush #48
/*    */     //   556: bipush #48
/*    */     //   558: invokevirtual tL : (II)V
/*    */     //   561: bipush #6
/*    */     //   563: bipush #6
/*    */     //   565: invokevirtual zT : (II)Lf/JG0;
/*    */     //   568: pop
/*    */     //   569: return
/*    */     // Line number table:
/*    */     //   Java source line number -> byte code offset
/*    */     //   #1	-> 22
/*    */     //   #2	-> 28
/*    */     //   #3	-> 46
/*    */     //   #4	-> 49
/*    */     //   #5	-> 68
/*    */     //   #6	-> 80
/*    */     //   #7	-> 88
/*    */     //   #8	-> 136
/*    */     //   #9	-> 139
/*    */     //   #10	-> 146
/*    */     //   #11	-> 156
/*    */     //   #12	-> 161
/*    */     //   #13	-> 164
/*    */     //   #14	-> 194
/*    */     //   #15	-> 224
/*    */     //   #16	-> 229
/*    */     //   #17	-> 300
/*    */     //   #18	-> 305
/*    */     //   #19	-> 308
/*    */     //   #20	-> 309
/*    */     //   #21	-> 314
/*    */     //   #22	-> 318
/*    */     //   #23	-> 327
/*    */     //   #24	-> 331
/*    */     //   #25	-> 334
/*    */     //   #26	-> 490
/*    */     //   #27	-> 501
/*    */     //   #28	-> 508
/*    */     //   #29	-> 513
/*    */     //   #30	-> 528
/*    */     //   #31	-> 531
/*    */     //   #32	-> 532
/*    */     //   #33	-> 535
/* 17 */     //   #34	-> 542 } public final boolean sU() { return false; } private void t70(int paramInt) { NuL[] arrayOfNuL; if (paramInt == 66 || paramInt == 111) { aj(); return; }  if (LF.Ll0(this.fJ.F2.toString(), true).isEmpty()) { byte b; for (paramInt = (arrayOfNuL = this.Br).length, b = 0; b < paramInt; ) { this[b].FK(); b++; }  } else { ((wg0)super).SV = -1; JG0 jG0; Hu0 hu0, arrayOfHu0[]; int i; byte b; for (jG0 = ((wg0)super).Br[((wg0)super).UI.wt0].FK(), hu0 = ((wg0)super).UI, i = (arrayOfHu0 = ((wg0)super).Se0).length, b = 0; b < i; ) { JG0 jG01 = ((wg0)super).Br[hu01.wt0].FK(); Hu0 hu01; if ((hu01 = arrayOfHu0[b]) != ((wg0)super).UI && jG0 == null) { hu0 = hu01; jG0 = jG01; }  b++; }  if (jG0 != null) { ((wg0)super).QP.Ax0(((wg0)super).QP.qL.get(hu0.wt0)); if (((wg0)super).fJ.p3()) VA0.c90(((wg0)super).fJ);  (((wg0)super).Br[hu0.wt0]).H40.ai(jG0); }  }  }
/*    */   public final void close() { pA pA1; if (this.c8) { wg0 wg01; if ((wg01 = (pA1 = this.Dr0).Mc) != null) { wg01.ra0(); this.Mc = null; js.vu0.KE(); }  } else { wg0 wg01; if ((wg01 = (pA1 = ((wg0)super).Dr0).iA0) != null) { this.uP = wg01.Kd; this.dM = wg01.er0; wg01.ra0(); this.iA0 = null; js.vu0.KE(); }  }  }
/*    */   public final void update() { // Byte code:
/*    */     //   0: aload_0
/*    */     //   1: getfield c8 : Z
/*    */     //   4: ifeq -> 8
/*    */     //   7: return
/*    */     //   8: aload_0
/*    */     //   9: getfield Se0 : [Lf/Hu0;
/*    */     //   12: dup
/*    */     //   13: dup
/*    */     //   14: astore_1
/*    */     //   15: arraylength
/*    */     //   16: newarray int
/*    */     //   18: astore_2
/*    */     //   19: arraylength
/*    */     //   20: istore_3
/*    */     //   21: iconst_0
/*    */     //   22: istore #4
/*    */     //   24: iload #4
/*    */     //   26: iload_3
/*    */     //   27: if_icmpge -> 61
/*    */     //   30: aload_2
/*    */     //   31: aload_1
/*    */     //   32: iload #4
/*    */     //   34: aaload
/*    */     //   35: getfield wt0 : I
/*    */     //   38: dup
/*    */     //   39: aload_0
/*    */     //   40: getfield Br : [Lf/NuL;
/*    */     //   43: swap
/*    */     //   44: aaload
/*    */     //   45: getfield H40 : Lf/rS;
/*    */     //   48: getfield PB : Lf/Ja;
/*    */     //   51: getfield Ny0 : I
/*    */     //   54: iastore
/*    */     //   55: iinc #4, 1
/*    */     //   58: goto -> 24
/*    */     //   61: aload_0
/*    */     //   62: getstatic f/km.a3 : Lf/vh0;
/*    */     //   65: getfield eA : B
/*    */     //   68: istore_1
/*    */     //   69: getstatic f/km.u4 : Lf/R8;
/*    */     //   72: aload_0
/*    */     //   73: getfield A00 : Lf/yM;
/*    */     //   76: invokevirtual gN : (Lf/yM;)Lf/zr0;
/*    */     //   79: invokevirtual ro0 : ()[Lf/Y;
/*    */     //   82: astore_3
/*    */     //   83: getfield Se0 : [Lf/Hu0;
/*    */     //   86: dup
/*    */     //   87: astore #4
/*    */     //   89: arraylength
/*    */     //   90: istore #5
/*    */     //   92: iconst_0
/*    */     //   93: istore #6
/*    */     //   95: iload #6
/*    */     //   97: iload #5
/*    */     //   99: if_icmpge -> 179
/*    */     //   102: aload_0
/*    */     //   103: aload #4
/*    */     //   105: iload #6
/*    */     //   107: aaload
/*    */     //   108: astore #7
/*    */     //   110: getfield Br : [Lf/NuL;
/*    */     //   113: aload #7
/*    */     //   115: getfield wt0 : I
/*    */     //   118: aaload
/*    */     //   119: dup
/*    */     //   120: aload_3
/*    */     //   121: invokestatic of : ([Ljava/lang/Object;)Ljava/util/stream/Stream;
/*    */     //   124: aload_0
/*    */     //   125: aload #7
/*    */     //   127: iload_1
/*    */     //   128: <illegal opcode> test : (Lf/wg0;Lf/Hu0;B)Ljava/util/function/Predicate;
/*    */     //   133: invokeinterface filter : (Ljava/util/function/Predicate;)Ljava/util/stream/Stream;
/*    */     //   138: <illegal opcode> apply : ()Ljava/util/function/IntFunction;
/*    */     //   143: invokeinterface toArray : (Ljava/util/function/IntFunction;)[Ljava/lang/Object;
/*    */     //   148: checkcast [Lf/Y;
/*    */     //   151: putfield Hu : [Lf/Y;
/*    */     //   154: invokevirtual FK : ()Lf/JG0;
/*    */     //   157: pop
/*    */     //   158: getstatic f/UB0.Kg0 : Lf/Q50;
/*    */     //   161: aload_0
/*    */     //   162: aload #7
/*    */     //   164: aload_2
/*    */     //   165: <illegal opcode> run : (Lf/wg0;Lf/Hu0;[I)Ljava/lang/Runnable;
/*    */     //   170: invokevirtual fN : (Ljava/lang/Runnable;)V
/*    */     //   173: iinc #6, 1
/*    */     //   176: goto -> 95
/*    */     //   179: return
/*    */     // Line number table:
/*    */     //   Java source line number -> byte code offset
/*    */     //   #1	-> 35
/*    */     //   #2	-> 40
/*    */     //   #3	-> 45
/*    */     //   #4	-> 48
/*    */     //   #5	-> 51
/*    */     //   #6	-> 54
/*    */     //   #7	-> 65
/*    */     //   #8	-> 69
/*    */     //   #9	-> 115
/*    */     //   #10	-> 118
/*    */     //   #11	-> 151
/*    */     //   #12	-> 154
/* 19 */     //   #13	-> 158 } public final void d40() { int i = 530, j = 378; if (km.XU()) { i = km.wI0.dG(); j = km.wI0.k1(); kN(0, 0, 0, 0); uh0(i, j); NuL[] arrayOfNuL; int k; byte b; for (k = (arrayOfNuL = this.Br).length, b = 0; b < k; ) { this.QP.kN(0, 0, 0, 0); arrayOfNuL[b].kN(0, 0, 0, 0); b++; }  } else { uh0(i, 386); }  this.ID0.Tm(i - 15, j); this.ID0.wI0(true); this.fJ.wI0(true); if (!km.XU()) { NuL[] arrayOfNuL; int k; byte b; for (k = (arrayOfNuL = this.Br).length, b = 0; b < k; ) { arrayOfNuL[b].uh0(i - 37, j + 20); arrayOfNuL[b].kN(10, 10, 10, 10); b++; }  }  ck ck1; if ((ck1 = this.COm7) != null) ck1.ME(300, 0);  Dk dk; if ((dk = this.TA0) != null) { dk.Tm(i, j + 28); this.TA0.ME(0, 0); this.ID0.wI0(false); this.fJ.wI0(false); }  ex ex1; if ((ex1 = this.y60) != null) { ex1.Tm(i, j + 28); this.y60.ME(0, 0); this.ID0.wI0(false); this.fJ.wI0(false); }  nn0 nn01; if ((nn01 = this.Vs) != null) { nn01.Tm(i, j + 28); this.Vs.ME(0, 0); this.ID0.wI0(false); this.fJ.wI0(false); }  Uh uh; if ((uh = this.Da0) != null) { uh.Tm(i, j + 28); this.Da0.ME(0, 0); this.ID0.wI0(false); this.fJ.wI0(false); }  super.d40(); if (km.Nr()) { this.fJ.Tm(180, 28); this.fJ.ME(this.Kd + 330, this.er0 + 40); } else { this
/* 20 */         .QP
/* 21 */         .ME(0, 61);
/* 22 */       this.fJ.mM(); this.fJ.js0(et.kL0); this.yr0.mM(); this.yr0
/* 23 */         .ME(this.fJ.Xq() + 15, 10); }  } public final void SL0(Y paramY) { // Byte code:
/*    */     //   0: getstatic f/km.MR : Lf/Gp0;
/*    */     //   3: ifnonnull -> 256
/*    */     //   6: getstatic f/km.u4 : Lf/R8;
/*    */     //   9: invokevirtual NR : ()Z
/*    */     //   12: ifeq -> 18
/*    */     //   15: goto -> 256
/*    */     //   18: aload_1
/*    */     //   19: ifnull -> 54
/*    */     //   22: aload_1
/*    */     //   23: getfield Bp0 : Lf/LPT3;
/*    */     //   26: getfield c3 : Lf/wc;
/*    */     //   29: ifnull -> 54
/*    */     //   32: aload_0
/*    */     //   33: aload_1
/*    */     //   34: getfield Lh : Lf/nH0;
/*    */     //   37: dup
/*    */     //   38: getfield p1 : S
/*    */     //   41: istore_0
/*    */     //   42: getfield Wy : I
/*    */     //   45: iload_0
/*    */     //   46: swap
/*    */     //   47: iconst_0
/*    */     //   48: iconst_1
/*    */     //   49: iconst_m1
/*    */     //   50: invokevirtual ZN : (SIISB)V
/*    */     //   53: return
/*    */     //   54: aload_1
/*    */     //   55: ifnonnull -> 59
/*    */     //   58: return
/*    */     //   59: aload_1
/*    */     //   60: getfield Bp0 : Lf/LPT3;
/*    */     //   63: iconst_0
/*    */     //   64: invokevirtual default : (Z)Lf/dv;
/*    */     //   67: invokevirtual ordinal : ()I
/*    */     //   70: tableswitch default -> 100, 1 -> 184, 2 -> 175, 3 -> 166, 4 -> 103
/*    */     //   100: goto -> 255
/*    */     //   103: aload_0
/*    */     //   104: getfield Vs : Lf/nn0;
/*    */     //   107: dup
/*    */     //   108: astore_2
/*    */     //   109: ifnull -> 123
/*    */     //   112: aload_0
/*    */     //   113: dup
/*    */     //   114: aload_2
/*    */     //   115: invokevirtual jf0 : (Lf/JG0;)Z
/*    */     //   118: pop
/*    */     //   119: aconst_null
/*    */     //   120: putfield Vs : Lf/nn0;
/*    */     //   123: aload_0
/*    */     //   124: dup
/*    */     //   125: dup
/*    */     //   126: dup2
/*    */     //   127: new f/nn0
/*    */     //   130: dup
/*    */     //   131: dup
/*    */     //   132: astore_2
/*    */     //   133: aload_0
/*    */     //   134: aload_1
/*    */     //   135: invokespecial <init> : (Lf/wg0;Lf/Y;)V
/*    */     //   138: putfield Vs : Lf/nn0;
/*    */     //   141: aload_2
/*    */     //   142: getfield aH0 : Lf/Y;
/*    */     //   145: invokevirtual JG0 : ()Ljava/lang/String;
/*    */     //   148: invokevirtual Lo : (Ljava/lang/String;)V
/*    */     //   151: getfield Vs : Lf/nn0;
/*    */     //   154: astore_0
/*    */     //   155: invokevirtual Ub : ()I
/*    */     //   158: aload_0
/*    */     //   159: swap
/*    */     //   160: invokevirtual si : (Lf/JG0;I)V
/*    */     //   163: goto -> 255
/*    */     //   166: aload_0
/*    */     //   167: aload_1
/*    */     //   168: iconst_0
/*    */     //   169: invokevirtual ty : (Lf/Y;Z)V
/*    */     //   172: goto -> 255
/*    */     //   175: aload_0
/*    */     //   176: aload_1
/*    */     //   177: iconst_0
/*    */     //   178: invokevirtual ty : (Lf/Y;Z)V
/*    */     //   181: goto -> 255
/*    */     //   184: aload_1
/*    */     //   185: aload_0
/*    */     //   186: aload_1
/*    */     //   187: getfield Lh : Lf/nH0;
/*    */     //   190: dup
/*    */     //   191: getfield p1 : S
/*    */     //   194: istore_2
/*    */     //   195: getfield Wy : I
/*    */     //   198: istore_3
/*    */     //   199: iload_2
/*    */     //   200: aload_1
/*    */     //   201: getfield Bp0 : Lf/LPT3;
/*    */     //   204: getfield EA : Z
/*    */     //   207: iconst_1
/*    */     //   208: ixor
/*    */     //   209: istore_2
/*    */     //   210: iload_3
/*    */     //   211: iconst_0
/*    */     //   212: iload_2
/*    */     //   213: iconst_m1
/*    */     //   214: invokevirtual ZN : (SIISB)V
/*    */     //   217: getfield Bp0 : Lf/LPT3;
/*    */     //   220: getfield Y8 : Lf/Hu0;
/*    */     //   223: getstatic f/Hu0.Bm : Lf/Hu0;
/*    */     //   226: if_acmpeq -> 251
/*    */     //   229: aload_1
/*    */     //   230: getfield Lh : Lf/nH0;
/*    */     //   233: getfield p1 : S
/*    */     //   236: dup
/*    */     //   237: istore_1
/*    */     //   238: sipush #1227
/*    */     //   241: if_icmplt -> 255
/*    */     //   244: iload_1
/*    */     //   245: sipush #1230
/*    */     //   248: if_icmpgt -> 255
/*    */     //   251: aload_0
/*    */     //   252: invokevirtual close : ()V
/*    */     //   255: return
/*    */     //   256: getstatic f/js.vu0 : Lf/js;
/*    */     //   259: sipush #6002
/*    */     //   262: invokestatic OH0 : (I)Ljava/lang/String;
/*    */     //   265: iconst_m1
/*    */     //   266: swap
/*    */     //   267: invokevirtual Pu : (ILjava/lang/String;)V
/*    */     //   270: return
/*    */     // Line number table:
/*    */     //   Java source line number -> byte code offset
/*    */     //   #1	-> 23
/*    */     //   #2	-> 26
/*    */     //   #3	-> 34
/*    */     //   #4	-> 38
/*    */     //   #5	-> 42
/*    */     //   #6	-> 50
/*    */     //   #7	-> 60
/*    */     //   #8	-> 64
/*    */     //   #9	-> 104
/*    */     //   #10	-> 142
/*    */     //   #11	-> 145
/*    */     //   #12	-> 148
/*    */     //   #13	-> 155
/*    */     //   #14	-> 169
/*    */     //   #15	-> 178
/*    */     //   #16	-> 187
/*    */     //   #17	-> 191
/*    */     //   #18	-> 195
/*    */     //   #19	-> 201
/*    */     //   #20	-> 204
/*    */     //   #21	-> 214
/*    */     //   #22	-> 217
/*    */     //   #23	-> 220
/*    */     //   #24	-> 223
/*    */     //   #25	-> 230
/*    */     //   #26	-> 233
/*    */     //   #27	-> 252
/*    */     //   #28	-> 256
/*    */     //   #29	-> 262
/*    */     //   #30	-> 267 }
/*    */   public final void ZN(short paramShort1, int paramInt1, int paramInt2, short paramShort2, byte paramByte) { kJ(); km.u4.tq0(paramShort1, paramInt1, paramInt2, paramShort2, paramByte); }
/*    */   public final boolean i2(oa0 paramoa0) { pA pA1; wg0 wg01; if (B8.Pg(paramoa0.cz0)) js.vu0.KE();  if (B8.Wm0(paramoa0.cz0) && paramoa0.oO()) { Y[] arrayOfY; int i = paramoa0.GG0; ex ex1; if ((ex1 = this.y60) != null) { ex1.i2(paramoa0); return true; }  Dk dk; if ((dk = this.TA0) != null) { dk.i2(paramoa0); return true; }  Uh uh; if ((uh = this.Da0) != null) { uh.i2(paramoa0); return true; }  nn0 nn01; if ((nn01 = this.Vs) != null) { nn01.i2(paramoa0); return true; }  if (this.fJ.p3()) { this.fJ.i2(paramoa0); return true; }  BM bM1 = BM.ni, bM2 = BM.N70, bM3 = BM.Oq, bM4 = BM.M8; if (i == 34 && paramoa0.com8 == 4) { this.fJ.BA(); return true; }  if (km.XU() && this.SV < 0) { bM4 = bM2; bM2 = bM1; bM1 = bM3 = bM4; } else { bM3 = bM2 = bM3; }  if (h1.J20(i, bM1)) { if (km.XU() && this.SV < 1) return true;  int j; if ((j = this.SV) < 0) return true;  if ((this.SV = j - 1) < 0) { int k; kI0 kI01; if ((kI01 = this.QP).qL.isEmpty()) { k = -1; } else { k = k.qL.indexOf(k.yI0); }  this.Zp0 = k; }  aj(); return true; }  if (h1.J20(i, bM3)) { int j = this.SV + 1; if ((this.Br[this.UI.wt0]).ke0.return(j) && ++this.SV == 0) this.Zp0 = 0;  aj(); return true; }  if (h1.J20(i, bM2) && !this.fJ.p3()) { if (km.XU() && this.SV >= 0) { int k; this.SV = -1; kI0 kI01; if ((kI01 = this.QP).qL.isEmpty()) { k = -1; } else { k = k.qL.indexOf(k.yI0); }  this.Zp0 = k + 1; }  if (this.SV < 0) { if (--this.Zp0 < 0) this.Zp0 = 0;  this.QP.Ax0(this.f0[this.Zp0]); aj(); return true; }  int j; if ((j = this.Zp0) > 0)
/*    */           this.Zp0 = j - 1;  aj(); return true; }  if (h1.J20(i, bM4) && !this.fJ.p3()) { NuL[] arrayOfNuL; int j; if ((j = this.SV) < 0) { this.Zp0 = j; if ((j = this.Zp0 + 1) >= (arrayOfNuL = this.Br).length)
/* 27 */             this.Zp0 = arrayOfNuL.length - 1;  this.QP.Ax0(this.f0[this.Zp0]); aj(); return true; }  i = this.Zp0; Un[] arrayOfUn; if (((arrayOfUn = (Un[])(this.Br[this.UI.wt0]).ke0.Z6(arrayOfNuL)) != null && arrayOfUn.length > i)) this
/* 28 */             .Zp0++;  aj(); return true; }  if (h1.J20(i, BM.bC) && !this.fJ.p3()) { if (this.SV < 0) return true;  Un un = fG0();
/*    */ 
/*    */ 
/*    */ 
/*    */         
/* 33 */         if (this.Zp0 < 0) this.Zp0 = 0;  if (this.Zp0 >= arrayOfY.length) this.Zp0 = arrayOfY.length - 1;  if ((((i = this.SV) < 0 || (arrayOfY = (Y[])(this.Br[this.UI.wt0]).CS.Z6(i)) == null) ? null : arrayOfY[this.Zp0]) != null && un != null)
/*    */         {
/*    */           
/* 36 */           hm.Fz0(un.TG0.oh0); }  return true; }
/* 37 */        if (h1.J20(arrayOfY, BM.lc) && !this.fJ.p3()) { if (this.c8)
/*    */         
/* 39 */         { if ((wg01 = (pA1 = pA.Dg0).Mc) != null) { wg01
/* 40 */               .ra0(); this.Mc = null;
/* 41 */             js.vu0
/* 42 */               .KE(); }
/*    */            }
/* 44 */         else if ((wg01 = (pA1 = pA.Dg0).iA0) != null) { this
/*    */             
/* 46 */             .uP = wg01.Kd;
/*    */           
/* 48 */           this.dM = wg01.er0; wg01.ra0(); this.iA0 = null;
/* 49 */           js.vu0
/* 50 */             .KE(); }  return true; }  }
/* 51 */      return super.i2((oa0)wg01); }
/*    */ 
/*    */   
/*    */   public final void yL0(LPT3 paramLPT3, int paramInt, j40 paramj40) {
/*    */     ex ex2;
/*    */     if ((ex2 = this.y60) != null) {
/*    */       jf0(ex2);
/*    */       this.y60 = null;
/*    */     } 
/*    */     this(this, paramLPT3, paramInt, paramj40);
/*    */     this.y60 = new ex();
/*    */     Lo(ex2.k7.wL.toString());
/*    */     ex ex1 = this.y60;
/*    */     si(this, Ub());
/*    */   }
/*    */   
/*    */   public final void kJ() {
/*    */     if (this.aw0) {
/*    */       Lo(Ml0.OH0(1460).toUpperCase());
/*    */     } else {
/*    */       StringBuilder stringBuilder;
/*    */       this();
/*    */       Lo(pv.X9(1400, stringBuilder, " - ").append(Ml0.OH0(this.UI.jC0).toUpperCase()).toString());
/*    */     } 
/*    */     Uh uh;
/*    */     if ((uh = this.Da0) != null) {
/*    */       jf0(uh);
/*    */       this.Da0 = null;
/*    */     } 
/*    */     nn0 nn01;
/*    */     if ((nn01 = this.Vs) != null) {
/*    */       jf0(nn01);
/*    */       this.Vs = null;
/*    */     } 
/*    */     Dk dk;
/*    */     if ((dk = this.TA0) != null) {
/*    */       jf0(dk);
/*    */       this.TA0 = null;
/*    */     } 
/*    */     ex ex1;
/*    */     if ((ex1 = this.y60) != null) {
/*    */       jf0(ex1);
/*    */       this.y60 = null;
/*    */     } 
/*    */     aj();
/*    */   }
/*    */   
/*    */   public final void V90(throws paramthrows) {
/*    */     super.V90(paramthrows);
/*    */     if (this.c8 && this.Da0 == null && this.Vs == null && this.TA0 == null && this.y60 == null)
/*    */       UB0.Kg0.fN(wg0::Jr); 
/*    */     if (this.Da0 != null || this.Vs != null || this.TA0 != null || this.y60 != null)
/*    */       js.vu0.KE(); 
/*    */     Gp0 gp0;
/*    */     if ((gp0 = km.MR) != null && !sQ() && km.u4 != null)
/*    */       UB0.Kg0.fN(wg0::BF0); 
/*    */   }
/*    */   
/*    */   public final void ty(Y paramY, boolean paramBoolean) {
/*    */     Dk dk2;
/*    */     if ((dk2 = this.TA0) != null) {
/*    */       jf0(dk2);
/*    */       this.TA0 = null;
/*    */     } 
/*    */     LPT3 lPT3 = paramY.Bp0;
/*    */     this(this, this, paramY.Lh.Wy, paramBoolean);
/*    */     this.TA0 = new Dk();
/*    */     Lo(dk2.Dm.wL.toString());
/*    */     Dk dk1 = this.TA0;
/*    */     si(this, Ub());
/*    */   }
/*    */   
/*    */   public final void sd0(Y paramY, short paramShort) {
/*    */     // Byte code:
/*    */     //   0: getstatic f/js.vu0 : Lf/js;
/*    */     //   3: new f/h70
/*    */     //   6: dup
/*    */     //   7: dup
/*    */     //   8: aload_0
/*    */     //   9: aload_1
/*    */     //   10: iconst_2
/*    */     //   11: anewarray java/lang/String
/*    */     //   14: dup
/*    */     //   15: astore_0
/*    */     //   16: aload_1
/*    */     //   17: aload_0
/*    */     //   18: iload_2
/*    */     //   19: invokestatic toString : (I)Ljava/lang/String;
/*    */     //   22: iconst_0
/*    */     //   23: swap
/*    */     //   24: aastore
/*    */     //   25: invokevirtual tH0 : ()Ljava/lang/String;
/*    */     //   28: iconst_1
/*    */     //   29: swap
/*    */     //   30: aastore
/*    */     //   31: sipush #1431
/*    */     //   34: aload_0
/*    */     //   35: invokestatic sB : (I[Ljava/lang/String;)Ljava/lang/String;
/*    */     //   38: astore_0
/*    */     //   39: iload_2
/*    */     //   40: <illegal opcode> run : (Lf/wg0;Lf/Y;S)Ljava/lang/Runnable;
/*    */     //   45: aload_0
/*    */     //   46: swap
/*    */     //   47: aconst_null
/*    */     //   48: invokespecial <init> : (Ljava/lang/String;Ljava/lang/Runnable;Lf/JG0;)V
/*    */     //   51: iconst_1
/*    */     //   52: putfield sD0 : Z
/*    */     //   55: invokevirtual uh : (Lf/h70;)V
/*    */     //   58: return
/*    */     // Line number table:
/*    */     //   Java source line number -> byte code offset
/*    */     //   #1	-> 0
/*    */     //   #2	-> 3
/*    */     //   #3	-> 52
/*    */     //   #4	-> 55
/*    */   }
/*    */   
/*    */   public final void IG0() {
/*    */     VA0.c90(fG0());
/*    */   }
/*    */   
/*    */   public final void ED0(throws paramthrows) {
/*    */     super.ED0(paramthrows);
/*    */     js.vu0.KE();
/*    */   }
/*    */   
/*    */   public final Un fG0() {
/*    */     nJ nJ1;
/*    */     Dk dk;
/*    */     if ((dk = this.TA0) != null)
/*    */       return dk.y(); 
/*    */     ex ex1;
/*    */     if ((ex1 = this.y60) != null)
/*    */       return ex1.Tn[ex1.aJ]; 
/*    */     Uh uh;
/*    */     if ((uh = this.Da0) != null)
/*    */       return uh.rB[uh.Mo0]; 
/*    */     nn0 nn01;
/*    */     if ((nn01 = this.Vs) != null)
/*    */       return nn01.cw0[nn01.Ts]; 
/*    */     int i;
/*    */     if ((i = this.SV) < 0) {
/*    */       kI0 kI01;
/*    */       if ((kI01 = this.QP) == null || (nJ1 = this.yI0) == null)
/*    */         return null; 
/*    */       return this.r00;
/*    */     } 
/*    */     Un[] arrayOfUn;
/*    */     if ((arrayOfUn = (Un[])(((wg0)super).Br[((wg0)super).UI.wt0]).ke0.Z6(i)) == null)
/*    */       return null; 
/*    */     if (((wg0)super).Zp0 < 0)
/*    */       ((wg0)super).Zp0 = 0; 
/*    */     if (((wg0)super).Zp0 >= arrayOfUn.length)
/*    */       ((wg0)super).Zp0 = arrayOfUn.length - 1; 
/*    */     return arrayOfUn[((wg0)super).Zp0];
/*    */   }
/*    */   
/*    */   public final void aj() {
/*    */     Un un;
/*    */     if ((un = fG0()) != null) {
/*    */       VA0.c90(un);
/*    */       Object object;
/*    */       if ((object = un.z4) != null) {
/*    */         js.vu0.j90(this.Br[this.UI.wt0], object, et.F30);
/*    */       } else {
/*    */         js.vu0.KE();
/*    */       } 
/*    */       (this.Br[this.UI.wt0]).H40.ai(un);
/*    */       if (km.XU())
/*    */         hm.Fz0(un.TG0.oh0); 
/*    */     } else {
/*    */       js.vu0.KE();
/*    */     } 
/*    */   }
/*    */   
/*    */   public final void uV(short paramShort, Q90 paramQ90) {
/*    */     kJ();
/*    */     R8 r8 = km.u4;
/*    */     int i = paramQ90.q10;
/*    */     aq0 aq0 = paramQ90.COm1;
/*    */     this.e20.W3(new zD(i, paramShort, aq0));
/*    */   }
/*    */   
/*    */   public final B3 dc0(Y paramY) {
/*    */     // Byte code:
/*    */     //   0: new f/B3
/*    */     //   3: dup
/*    */     //   4: astore_2
/*    */     //   5: invokespecial <init> : ()V
/*    */     //   8: invokestatic XU : ()Z
/*    */     //   11: ifeq -> 22
/*    */     //   14: aload_0
/*    */     //   15: getfield COm7 : Lf/ck;
/*    */     //   18: aload_1
/*    */     //   19: invokevirtual VJ : (Lf/Y;)V
/*    */     //   22: aload_1
/*    */     //   23: getfield Bp0 : Lf/LPT3;
/*    */     //   26: iconst_0
/*    */     //   27: invokevirtual default : (Z)Lf/dv;
/*    */     //   30: getstatic f/dv.wS : Lf/dv;
/*    */     //   33: if_acmpeq -> 251
/*    */     //   36: getstatic f/km.MR : Lf/Gp0;
/*    */     //   39: ifnonnull -> 251
/*    */     //   42: getstatic f/km.u4 : Lf/R8;
/*    */     //   45: invokevirtual NR : ()Z
/*    */     //   48: ifne -> 251
/*    */     //   51: aload_1
/*    */     //   52: aload_2
/*    */     //   53: new f/Hk0
/*    */     //   56: dup
/*    */     //   57: astore_3
/*    */     //   58: aload_0
/*    */     //   59: aload_1
/*    */     //   60: aload_3
/*    */     //   61: sipush #1410
/*    */     //   64: invokestatic OH0 : (I)Ljava/lang/String;
/*    */     //   67: invokespecial <init> : (Ljava/lang/String;)V
/*    */     //   70: <illegal opcode> run : (Lf/wg0;Lf/Y;)Ljava/lang/Runnable;
/*    */     //   75: putfield rv : Ljava/lang/Runnable;
/*    */     //   78: getfield aV : Ljava/util/ArrayList;
/*    */     //   81: aload_3
/*    */     //   82: invokevirtual add : (Ljava/lang/Object;)Z
/*    */     //   85: pop
/*    */     //   86: getfield Bp0 : Lf/LPT3;
/*    */     //   89: getfield KI : Lf/mA;
/*    */     //   92: getstatic f/mA.uZ : Lf/mA;
/*    */     //   95: if_acmpeq -> 131
/*    */     //   98: aload_2
/*    */     //   99: new f/Hk0
/*    */     //   102: dup
/*    */     //   103: astore_3
/*    */     //   104: aload_1
/*    */     //   105: aload_3
/*    */     //   106: sipush #3006
/*    */     //   109: invokestatic OH0 : (I)Ljava/lang/String;
/*    */     //   112: invokespecial <init> : (Ljava/lang/String;)V
/*    */     //   115: <illegal opcode> run : (Lf/Y;)Ljava/lang/Runnable;
/*    */     //   120: putfield rv : Ljava/lang/Runnable;
/*    */     //   123: getfield aV : Ljava/util/ArrayList;
/*    */     //   126: aload_3
/*    */     //   127: invokevirtual add : (Ljava/lang/Object;)Z
/*    */     //   130: pop
/*    */     //   131: aload_1
/*    */     //   132: getfield Lh : Lf/nH0;
/*    */     //   135: getfield b8 : Lf/yM;
/*    */     //   138: getfield Gq : Z
/*    */     //   141: getstatic f/km.u4 : Lf/R8;
/*    */     //   144: invokevirtual q10 : ()Z
/*    */     //   147: if_icmpeq -> 251
/*    */     //   150: new f/B3
/*    */     //   153: dup
/*    */     //   154: astore_3
/*    */     //   155: sipush #1412
/*    */     //   158: invokestatic OH0 : (I)Ljava/lang/String;
/*    */     //   161: invokespecial <init> : (Ljava/lang/String;)V
/*    */     //   164: iconst_0
/*    */     //   165: istore #4
/*    */     //   167: iload #4
/*    */     //   169: bipush #9
/*    */     //   171: if_icmpge -> 242
/*    */     //   174: aload_3
/*    */     //   175: new f/Hk0
/*    */     //   178: dup
/*    */     //   179: astore #5
/*    */     //   181: aload_1
/*    */     //   182: iload #4
/*    */     //   184: aload #5
/*    */     //   186: new java/lang/StringBuilder
/*    */     //   189: dup
/*    */     //   190: invokespecial <init> : ()V
/*    */     //   193: iload #4
/*    */     //   195: iconst_1
/*    */     //   196: iadd
/*    */     //   197: dup
/*    */     //   198: istore #4
/*    */     //   200: invokevirtual append : (I)Ljava/lang/StringBuilder;
/*    */     //   203: ldc_w ''
/*    */     //   206: invokevirtual append : (Ljava/lang/String;)Ljava/lang/StringBuilder;
/*    */     //   209: invokevirtual toString : ()Ljava/lang/String;
/*    */     //   212: sipush #1413
/*    */     //   215: swap
/*    */     //   216: invokestatic Go : (ILjava/lang/String;)Ljava/lang/String;
/*    */     //   219: invokespecial <init> : (Ljava/lang/String;)V
/*    */     //   222: <illegal opcode> run : (Lf/Y;I)Ljava/lang/Runnable;
/*    */     //   227: putfield rv : Ljava/lang/Runnable;
/*    */     //   230: getfield aV : Ljava/util/ArrayList;
/*    */     //   233: aload #5
/*    */     //   235: invokevirtual add : (Ljava/lang/Object;)Z
/*    */     //   238: pop
/*    */     //   239: goto -> 167
/*    */     //   242: aload_2
/*    */     //   243: getfield aV : Ljava/util/ArrayList;
/*    */     //   246: aload_3
/*    */     //   247: invokevirtual add : (Ljava/lang/Object;)Z
/*    */     //   250: pop
/*    */     //   251: aload_1
/*    */     //   252: getfield Lh : Lf/nH0;
/*    */     //   255: getfield b8 : Lf/yM;
/*    */     //   258: getfield Gq : Z
/*    */     //   261: ifeq -> 376
/*    */     //   264: aload_1
/*    */     //   265: getfield Bp0 : Lf/LPT3;
/*    */     //   268: invokevirtual lF0 : ()Z
/*    */     //   271: ifeq -> 376
/*    */     //   274: aload_1
/*    */     //   275: getfield Bp0 : Lf/LPT3;
/*    */     //   278: getfield bj0 : S
/*    */     //   281: sipush #1446
/*    */     //   284: if_icmpeq -> 376
/*    */     //   287: aload_2
/*    */     //   288: dup
/*    */     //   289: getstatic f/km.u4 : Lf/R8;
/*    */     //   292: aload_0
/*    */     //   293: getfield A00 : Lf/yM;
/*    */     //   296: invokevirtual gN : (Lf/yM;)Lf/zr0;
/*    */     //   299: sipush #1028
/*    */     //   302: invokevirtual C8 : (S)Lf/Y;
/*    */     //   305: astore_3
/*    */     //   306: new f/Hk0
/*    */     //   309: dup
/*    */     //   310: astore #4
/*    */     //   312: aload_0
/*    */     //   313: aload_3
/*    */     //   314: aload #4
/*    */     //   316: sipush #8551
/*    */     //   319: invokestatic OH0 : (I)Ljava/lang/String;
/*    */     //   322: invokespecial <init> : (Ljava/lang/String;)V
/*    */     //   325: aload_1
/*    */     //   326: <illegal opcode> run : (Lf/wg0;Lf/Y;Lf/Y;)Ljava/lang/Runnable;
/*    */     //   331: putfield rv : Ljava/lang/Runnable;
/*    */     //   334: getfield aV : Ljava/util/ArrayList;
/*    */     //   337: aload #4
/*    */     //   339: invokevirtual add : (Ljava/lang/Object;)Z
/*    */     //   342: pop
/*    */     //   343: new f/Hk0
/*    */     //   346: dup
/*    */     //   347: astore_3
/*    */     //   348: aload_0
/*    */     //   349: aload_1
/*    */     //   350: aload_3
/*    */     //   351: sipush #8571
/*    */     //   354: invokestatic OH0 : (I)Ljava/lang/String;
/*    */     //   357: invokespecial <init> : (Ljava/lang/String;)V
/*    */     //   360: <illegal opcode> run : (Lf/wg0;Lf/Y;)Ljava/lang/Runnable;
/*    */     //   365: putfield rv : Ljava/lang/Runnable;
/*    */     //   368: getfield aV : Ljava/util/ArrayList;
/*    */     //   371: aload_3
/*    */     //   372: invokevirtual add : (Ljava/lang/Object;)Z
/*    */     //   375: pop
/*    */     //   376: aload_1
/*    */     //   377: getfield Bp0 : Lf/LPT3;
/*    */     //   380: dup
/*    */     //   381: astore_3
/*    */     //   382: getfield Y8 : Lf/Hu0;
/*    */     //   385: dup
/*    */     //   386: astore #4
/*    */     //   388: getstatic f/Hu0.Bm : Lf/Hu0;
/*    */     //   391: if_acmpeq -> 443
/*    */     //   394: aload #4
/*    */     //   396: getstatic f/Hu0.w2 : Lf/Hu0;
/*    */     //   399: if_acmpeq -> 443
/*    */     //   402: aload_3
/*    */     //   403: getfield kd : Z
/*    */     //   406: ifeq -> 443
/*    */     //   409: aload_2
/*    */     //   410: new f/Hk0
/*    */     //   413: dup
/*    */     //   414: astore_3
/*    */     //   415: aload_0
/*    */     //   416: aload_1
/*    */     //   417: aload_3
/*    */     //   418: sipush #1411
/*    */     //   421: invokestatic OH0 : (I)Ljava/lang/String;
/*    */     //   424: invokespecial <init> : (Ljava/lang/String;)V
/*    */     //   427: <illegal opcode> run : (Lf/wg0;Lf/Y;)Ljava/lang/Runnable;
/*    */     //   432: putfield rv : Ljava/lang/Runnable;
/*    */     //   435: getfield aV : Ljava/util/ArrayList;
/*    */     //   438: aload_3
/*    */     //   439: invokevirtual add : (Ljava/lang/Object;)Z
/*    */     //   442: pop
/*    */     //   443: aload_1
/*    */     //   444: getfield Lh : Lf/nH0;
/*    */     //   447: getfield b8 : Lf/yM;
/*    */     //   450: getfield Gq : Z
/*    */     //   453: ifeq -> 501
/*    */     //   456: aload_1
/*    */     //   457: getfield Bp0 : Lf/LPT3;
/*    */     //   460: iconst_1
/*    */     //   461: invokevirtual rg0 : (Z)Z
/*    */     //   464: ifeq -> 501
/*    */     //   467: aload_2
/*    */     //   468: new f/Hk0
/*    */     //   471: dup
/*    */     //   472: astore_3
/*    */     //   473: aload_0
/*    */     //   474: aload_1
/*    */     //   475: aload_3
/*    */     //   476: sipush #1424
/*    */     //   479: invokestatic OH0 : (I)Ljava/lang/String;
/*    */     //   482: invokespecial <init> : (Ljava/lang/String;)V
/*    */     //   485: <illegal opcode> run : (Lf/wg0;Lf/Y;)Ljava/lang/Runnable;
/*    */     //   490: putfield rv : Ljava/lang/Runnable;
/*    */     //   493: getfield aV : Ljava/util/ArrayList;
/*    */     //   496: aload_3
/*    */     //   497: invokevirtual add : (Ljava/lang/Object;)Z
/*    */     //   500: pop
/*    */     //   501: aload_2
/*    */     //   502: dup
/*    */     //   503: new f/Hk0
/*    */     //   506: dup
/*    */     //   507: dup
/*    */     //   508: astore_0
/*    */     //   509: sipush #1423
/*    */     //   512: invokestatic OH0 : (I)Ljava/lang/String;
/*    */     //   515: invokespecial <init> : (Ljava/lang/String;)V
/*    */     //   518: aconst_null
/*    */     //   519: putfield rv : Ljava/lang/Runnable;
/*    */     //   522: getfield aV : Ljava/util/ArrayList;
/*    */     //   525: aload_0
/*    */     //   526: invokevirtual add : (Ljava/lang/Object;)Z
/*    */     //   529: pop
/*    */     //   530: areturn
/*    */     // Line number table:
/*    */     //   Java source line number -> byte code offset
/*    */     //   #1	-> 23
/*    */     //   #2	-> 27
/*    */     //   #3	-> 75
/*    */     //   #4	-> 78
/*    */     //   #5	-> 86
/*    */     //   #6	-> 89
/*    */     //   #7	-> 92
/*    */     //   #8	-> 120
/*    */     //   #9	-> 123
/*    */     //   #10	-> 132
/*    */     //   #11	-> 135
/*    */     //   #12	-> 138
/*    */     //   #13	-> 141
/*    */     //   #14	-> 227
/*    */     //   #15	-> 230
/*    */     //   #16	-> 252
/*    */     //   #17	-> 255
/*    */     //   #18	-> 258
/*    */     //   #19	-> 265
/*    */     //   #20	-> 268
/*    */     //   #21	-> 275
/*    */     //   #22	-> 278
/*    */     //   #23	-> 289
/*    */     //   #24	-> 331
/*    */     //   #25	-> 334
/*    */     //   #26	-> 343
/*    */     //   #27	-> 365
/*    */     //   #28	-> 368
/*    */     //   #29	-> 377
/*    */     //   #30	-> 382
/*    */     //   #31	-> 388
/*    */     //   #32	-> 403
/*    */     //   #33	-> 410
/*    */     //   #34	-> 432
/*    */     //   #35	-> 435
/*    */     //   #36	-> 444
/*    */     //   #37	-> 447
/*    */     //   #38	-> 450
/*    */     //   #39	-> 457
/*    */     //   #40	-> 461
/*    */     //   #41	-> 468
/*    */     //   #42	-> 490
/*    */     //   #43	-> 493
/*    */     //   #44	-> 503
/*    */     //   #45	-> 519
/*    */     //   #46	-> 522
/*    */   } }


/* Location:              /Users/vnnsnnt/Documents/Codespace/JavaWorkspace/RedTrainer/src/main/java/org/trainer/client/PokeMMO.jar!/f/wg0.class
 * Java compiler version: 8 (52.0)
 * JD-Core Version:       1.1.3
 */