package f;

public final class Wg0 extends of {
  public Wg0(Ge0 paramGe0, short paramShort) {}
  
  public final void Zh(String paramString) {
    // Byte code:
    //   0: aload_1
    //   1: aload_0
    //   2: aload_1
    //   3: iconst_0
    //   4: invokevirtual Be0 : (Ljava/lang/String;Z)V
    //   7: iconst_1
    //   8: invokestatic Ll0 : (Ljava/lang/String;Z)Ljava/lang/String;
    //   11: dup
    //   12: astore_1
    //   13: invokevirtual isEmpty : ()Z
    //   16: ifeq -> 20
    //   19: return
    //   20: invokestatic cw : ()Lf/yk0;
    //   23: dup
    //   24: aload_1
    //   25: swap
    //   26: invokevirtual getClass : ()Ljava/lang/Class;
    //   29: pop
    //   30: invokevirtual toLowerCase : ()Ljava/lang/String;
    //   33: astore_2
    //   34: getfield iu : Lf/qw0;
    //   37: dup
    //   38: astore_3
    //   39: invokevirtual getClass : ()Ljava/lang/Class;
    //   42: pop
    //   43: new f/iL
    //   46: dup
    //   47: aload_3
    //   48: invokespecial <init> : (Lf/qw0;)V
    //   51: invokevirtual iterator : ()Ljava/util/Iterator;
    //   54: astore_3
    //   55: aload_3
    //   56: checkcast f/DA0
    //   59: invokevirtual hasNext : ()Z
    //   62: ifeq -> 97
    //   65: aload_3
    //   66: checkcast f/Ke
    //   69: invokevirtual q00 : ()Ljava/lang/Object;
    //   72: checkcast f/WD
    //   75: dup
    //   76: astore #4
    //   78: getfield iz : I
    //   81: invokestatic OH0 : (I)Ljava/lang/String;
    //   84: invokevirtual toLowerCase : ()Ljava/lang/String;
    //   87: aload_2
    //   88: invokevirtual equals : (Ljava/lang/Object;)Z
    //   91: ifeq -> 55
    //   94: goto -> 100
    //   97: aconst_null
    //   98: astore #4
    //   100: aload #4
    //   102: ifnull -> 155
    //   105: getstatic f/km.u4 : Lf/R8;
    //   108: ldc '//setskill '
    //   110: invokestatic df : (Ljava/lang/String;)Ljava/lang/StringBuilder;
    //   113: aload_0
    //   114: getfield Po0 : S
    //   117: invokevirtual append : (I)Ljava/lang/StringBuilder;
    //   120: ldc ' '
    //   122: invokevirtual append : (Ljava/lang/String;)Ljava/lang/StringBuilder;
    //   125: aload_0
    //   126: getfield N3 : Lf/Ge0;
    //   129: getfield ht0 : I
    //   132: invokevirtual append : (I)Ljava/lang/StringBuilder;
    //   135: ldc ' '
    //   137: invokevirtual append : (Ljava/lang/String;)Ljava/lang/StringBuilder;
    //   140: aload #4
    //   142: getfield HA : S
    //   145: invokevirtual append : (I)Ljava/lang/StringBuilder;
    //   148: invokevirtual toString : ()Ljava/lang/String;
    //   151: invokevirtual lF : (Ljava/lang/String;)V
    //   154: return
    //   155: invokestatic cw : ()Lf/yk0;
    //   158: invokevirtual jQ : ()Lf/iL;
    //   161: invokevirtual iterator : ()Ljava/util/Iterator;
    //   164: astore_2
    //   165: aload_2
    //   166: checkcast f/DA0
    //   169: invokevirtual hasNext : ()Z
    //   172: ifeq -> 249
    //   175: aload_2
    //   176: checkcast f/Ke
    //   179: invokevirtual q00 : ()Ljava/lang/Object;
    //   182: checkcast f/WD
    //   185: dup
    //   186: astore_3
    //   187: getfield iz : I
    //   190: invokestatic OH0 : (I)Ljava/lang/String;
    //   193: aload_1
    //   194: invokestatic qS : (Ljava/lang/String;Ljava/lang/String;)Z
    //   197: ifeq -> 165
    //   200: getstatic f/km.u4 : Lf/R8;
    //   203: ldc '//setskill '
    //   205: invokestatic df : (Ljava/lang/String;)Ljava/lang/StringBuilder;
    //   208: aload_0
    //   209: getfield Po0 : S
    //   212: invokevirtual append : (I)Ljava/lang/StringBuilder;
    //   215: ldc ' '
    //   217: invokevirtual append : (Ljava/lang/String;)Ljava/lang/StringBuilder;
    //   220: aload_0
    //   221: getfield N3 : Lf/Ge0;
    //   224: getfield ht0 : I
    //   227: invokevirtual append : (I)Ljava/lang/StringBuilder;
    //   230: ldc ' '
    //   232: invokevirtual append : (Ljava/lang/String;)Ljava/lang/StringBuilder;
    //   235: aload_3
    //   236: getfield HA : S
    //   239: invokevirtual append : (I)Ljava/lang/StringBuilder;
    //   242: invokevirtual toString : ()Ljava/lang/String;
    //   245: invokevirtual lF : (Ljava/lang/String;)V
    //   248: return
    //   249: return
    // Line number table:
    //   Java source line number -> byte code offset
    //   #1	-> 4
    //   #2	-> 8
    //   #3	-> 13
    //   #4	-> 30
    //   #5	-> 43
    //   #6	-> 51
    //   #7	-> 78
    //   #8	-> 81
    //   #9	-> 84
    //   #10	-> 105
    //   #11	-> 108
    //   #12	-> 114
    //   #13	-> 142
    //   #14	-> 145
    //   #15	-> 187
    //   #16	-> 190
    //   #17	-> 194
    //   #18	-> 203
    //   #19	-> 209
    //   #20	-> 236
    //   #21	-> 239
  }
}


/* Location:              /Users/vnnsnnt/Documents/Codespace/JavaWorkspace/RedTrainer/src/main/java/org/trainer/client/PokeMMO.jar!/f/Wg0.class
 * Java compiler version: 8 (52.0)
 * JD-Core Version:       1.1.3
 */