/*  1 */ package f;public final class wL extends Qa0 { public static final ik AJ0 = C00.gd(wL.class); public Ip jH0; public boolean cO = false; public O90 WI; public float lw; public boolean tI0; public final void Ol0(RD0 paramRD0, byte paramByte, Consumer paramConsumer) { hZ hZ; (hZ = UB0.vj0.N0("roms")).iz0(); RD0 rD02; (rD02 = UB0.vj0.N0("roms").f0("importing.tmp")).La0(); if (Mk0.sz0(paramByte)) { str = ".nds"; } else { str = ".gba"; }  RD0 rD01 = hZ.f0(paramByte + "_" + System.currentTimeMillis() + str + "_import");
/*  2 */     this(Ml0.OH0(1091)); O90 o90; String str; this.WI = new O90();
/*  3 */     js.vu0
/*    */       
/*  5 */       .si(o90, js.vu0.Ub());
/*  6 */     this.tI0 = true;
/*  7 */     A1 a1 = A1.L7;
/*  8 */     a1
/*  9 */       .nc
/* 10 */       .execute(() -> { // Byte code:
/*    */           //   0: aload_1
/*    */           //   1: invokevirtual bo : ()Ljava/io/File;
/*    */           //   4: invokevirtual getAbsolutePath : ()Ljava/lang/String;
/*    */           //   7: astore #7
/*    */           //   9: invokestatic zp : ()Z
/*    */           //   12: ifeq -> 46
/*    */           //   15: aload_2
/*    */           //   16: invokevirtual getClass : ()Ljava/lang/Class;
/*    */           //   19: ldc_w f/RD0
/*    */           //   22: invokevirtual equals : (Ljava/lang/Object;)Z
/*    */           //   25: ifne -> 46
/*    */           //   28: getstatic f/km.iE0 : Lf/r9;
/*    */           //   31: invokevirtual getClass : ()Ljava/lang/Class;
/*    */           //   34: pop
/*    */           //   35: aconst_null
/*    */           //   36: aload #7
/*    */           //   38: aload_3
/*    */           //   39: invokestatic extract : (Ljava/io/FileDescriptor;Ljava/lang/String;Ljava/lang/String;)I
/*    */           //   42: istore_3
/*    */           //   43: goto -> 62
/*    */           //   46: aload_2
/*    */           //   47: invokevirtual bo : ()Ljava/io/File;
/*    */           //   50: invokevirtual getAbsolutePath : ()Ljava/lang/String;
/*    */           //   53: aload #7
/*    */           //   55: aload_3
/*    */           //   56: invokestatic extract : (Ljava/lang/String;Ljava/lang/String;Ljava/lang/String;)I
/*    */           //   59: goto -> 42
/*    */           //   62: aload_0
/*    */           //   63: dup
/*    */           //   64: getstatic f/wL.AJ0 : Lf/ik;
/*    */           //   67: dup
/*    */           //   68: new java/lang/StringBuilder
/*    */           //   71: dup
/*    */           //   72: invokespecial <init> : ()V
/*    */           //   75: ldc_w 'LibArchive extract code: '
/*    */           //   78: invokevirtual append : (Ljava/lang/String;)Ljava/lang/StringBuilder;
/*    */           //   81: iload_3
/*    */           //   82: invokevirtual append : (I)Ljava/lang/StringBuilder;
/*    */           //   85: invokevirtual toString : ()Ljava/lang/String;
/*    */           //   88: invokeinterface info : (Ljava/lang/String;)V
/*    */           //   93: new java/lang/StringBuilder
/*    */           //   96: dup
/*    */           //   97: invokespecial <init> : ()V
/*    */           //   100: ldc_w 'Libarchive error string: '
/*    */           //   103: invokevirtual append : (Ljava/lang/String;)Ljava/lang/StringBuilder;
/*    */           //   106: invokestatic getErrorString : ()Ljava/lang/String;
/*    */           //   109: invokevirtual append : (Ljava/lang/String;)Ljava/lang/StringBuilder;
/*    */           //   112: invokevirtual toString : ()Ljava/lang/String;
/*    */           //   115: invokeinterface info : (Ljava/lang/String;)V
/*    */           //   120: getstatic f/UB0.Kg0 : Lf/Q50;
/*    */           //   123: aload_0
/*    */           //   124: iload_3
/*    */           //   125: aload_2
/*    */           //   126: aload_1
/*    */           //   127: aload #4
/*    */           //   129: aload #5
/*    */           //   131: iload #6
/*    */           //   133: <illegal opcode> run : (Lf/wL;ILf/RD0;Lf/RD0;Lf/RD0;Ljava/util/function/Consumer;B)Ljava/lang/Runnable;
/*    */           //   138: invokevirtual fN : (Ljava/lang/Runnable;)V
/*    */           //   141: iconst_0
/*    */           //   142: putfield tI0 : Z
/*    */           //   145: fconst_1
/*    */           //   146: putfield lw : F
/*    */           //   149: getstatic f/UB0.Kg0 : Lf/Q50;
/*    */           //   152: aload_0
/*    */           //   153: <illegal opcode> run : (Lf/wL;)Ljava/lang/Runnable;
/*    */           //   158: invokevirtual fN : (Ljava/lang/Runnable;)V
/*    */           //   161: return
/*    */           //   162: aload_0
/*    */           //   163: dup
/*    */           //   164: iconst_0
/*    */           //   165: putfield tI0 : Z
/*    */           //   168: fconst_1
/*    */           //   169: putfield lw : F
/*    */           //   172: getstatic f/UB0.Kg0 : Lf/Q50;
/*    */           //   175: aload_0
/*    */           //   176: <illegal opcode> run : (Lf/wL;)Ljava/lang/Runnable;
/*    */           //   181: invokevirtual fN : (Ljava/lang/Runnable;)V
/*    */           //   184: athrow
/*    */           // Exception table:
/*    */           //   from	to	target	type
/*    */           //   9	12	162	finally
/*    */           //   15	25	162	finally
/*    */           //   28	34	162	finally
/*    */           //   36	42	162	finally
/*    */           //   46	141	162	finally }); } public e2 CoN = new e2(100); public Un wa; public byte[] dL0 = new byte[] { 2, 0, 1, 3, 4 }; public Un[] Ph0 = new Un[5]; public final void r90() { // Byte code:
/*    */     //   0: aload_0
/*    */     //   1: getfield jH0 : Lf/Ip;
/*    */     //   4: dup
/*    */     //   5: astore_1
/*    */     //   6: ifnull -> 24
/*    */     //   9: aload_0
/*    */     //   10: dup
/*    */     //   11: dup
/*    */     //   12: aload_1
/*    */     //   13: invokevirtual jf0 : (Lf/JG0;)Z
/*    */     //   16: pop
/*    */     //   17: getfield wa : Lf/Un;
/*    */     //   20: invokevirtual jf0 : (Lf/JG0;)Z
/*    */     //   23: pop
/*    */     //   24: aload_0
/*    */     //   25: dup
/*    */     //   26: sipush #1175
/*    */     //   29: invokestatic OH0 : (I)Ljava/lang/String;
/*    */     //   32: invokevirtual Lo : (Ljava/lang/String;)V
/*    */     //   35: new f/Ip
/*    */     //   38: dup
/*    */     //   39: invokespecial <init> : ()V
/*    */     //   42: putfield jH0 : Lf/Ip;
/*    */     //   45: new f/Un
/*    */     //   48: dup
/*    */     //   49: astore_1
/*    */     //   50: aload_0
/*    */     //   51: aload_1
/*    */     //   52: bipush #65
/*    */     //   54: invokestatic OH0 : (I)Ljava/lang/String;
/*    */     //   57: invokespecial <init> : (Ljava/lang/String;)V
/*    */     //   60: <illegal opcode> run : (Lf/wL;)Ljava/lang/Runnable;
/*    */     //   65: invokevirtual tW : (Ljava/lang/Runnable;)V
/*    */     //   68: new f/Un
/*    */     //   71: dup
/*    */     //   72: aload_0
/*    */     //   73: swap
/*    */     //   74: dup
/*    */     //   75: bipush #65
/*    */     //   77: invokestatic OH0 : (I)Ljava/lang/String;
/*    */     //   80: invokespecial <init> : (Ljava/lang/String;)V
/*    */     //   83: putfield wa : Lf/Un;
/*    */     //   86: <illegal opcode> run : ()Ljava/lang/Runnable;
/*    */     //   91: invokevirtual tW : (Ljava/lang/Runnable;)V
/*    */     //   94: new f/Un
/*    */     //   97: dup
/*    */     //   98: dup2
/*    */     //   99: dup2
/*    */     //   100: astore_2
/*    */     //   101: sipush #1174
/*    */     //   104: invokestatic OH0 : (I)Ljava/lang/String;
/*    */     //   107: invokespecial <init> : (Ljava/lang/String;)V
/*    */     //   110: sipush #1173
/*    */     //   113: invokestatic OH0 : (I)Ljava/lang/String;
/*    */     //   116: putfield z4 : Ljava/lang/Object;
/*    */     //   119: invokevirtual zn : ()V
/*    */     //   122: sipush #150
/*    */     //   125: putfield jl : I
/*    */     //   128: <illegal opcode> run : ()Ljava/lang/Runnable;
/*    */     //   133: invokevirtual tW : (Ljava/lang/Runnable;)V
/*    */     //   136: new f/Ip
/*    */     //   139: dup
/*    */     //   140: dup
/*    */     //   141: astore_3
/*    */     //   142: invokespecial <init> : ()V
/*    */     //   145: ldc 'dialoglayout'
/*    */     //   147: invokevirtual Xu : (Ljava/lang/String;)V
/*    */     //   150: new f/cr0
/*    */     //   153: dup
/*    */     //   154: astore #4
/*    */     //   156: aload_3
/*    */     //   157: invokespecial <init> : (Lf/Ip;)V
/*    */     //   160: new f/g0
/*    */     //   163: dup
/*    */     //   164: astore #5
/*    */     //   166: aload_3
/*    */     //   167: invokespecial <init> : (Lf/Ip;)V
/*    */     //   170: new f/dQ
/*    */     //   173: dup
/*    */     //   174: dup2
/*    */     //   175: astore #6
/*    */     //   177: sipush #1332
/*    */     //   180: invokestatic OH0 : (I)Ljava/lang/String;
/*    */     //   183: astore #7
/*    */     //   185: invokespecial <init> : ()V
/*    */     //   188: aload #7
/*    */     //   190: invokevirtual E1 : (Ljava/lang/String;)V
/*    */     //   193: ldc 'label-settings-title'
/*    */     //   195: invokevirtual Xu : (Ljava/lang/String;)V
/*    */     //   198: getstatic f/cE.eo0 : Lf/cE;
/*    */     //   201: invokevirtual dp0 : ()[Ljava/lang/String;
/*    */     //   204: dup
/*    */     //   205: astore #7
/*    */     //   207: arraylength
/*    */     //   208: dup
/*    */     //   209: istore #8
/*    */     //   211: anewarray java/lang/String
/*    */     //   214: astore #9
/*    */     //   216: iconst_m1
/*    */     //   217: istore #10
/*    */     //   219: iconst_0
/*    */     //   220: istore #11
/*    */     //   222: iload #11
/*    */     //   224: iload #8
/*    */     //   226: if_icmpge -> 269
/*    */     //   229: aload #9
/*    */     //   231: iload #11
/*    */     //   233: getstatic f/cE.eo0 : Lf/cE;
/*    */     //   236: aload #7
/*    */     //   238: iload #11
/*    */     //   240: aaload
/*    */     //   241: invokevirtual nB : (Ljava/lang/String;)Ljava/lang/String;
/*    */     //   244: aastore
/*    */     //   245: getstatic f/h1.pB0 : Ljava/lang/String;
/*    */     //   248: aload #7
/*    */     //   250: iload #11
/*    */     //   252: aaload
/*    */     //   253: invokevirtual equalsIgnoreCase : (Ljava/lang/String;)Z
/*    */     //   256: ifeq -> 263
/*    */     //   259: iload #11
/*    */     //   261: istore #10
/*    */     //   263: iinc #11, 1
/*    */     //   266: goto -> 222
/*    */     //   269: iload #10
/*    */     //   271: new f/OZ
/*    */     //   274: dup
/*    */     //   275: astore #8
/*    */     //   277: aload #9
/*    */     //   279: invokespecial <init> : ([Ljava/lang/Object;)V
/*    */     //   282: new f/W1
/*    */     //   285: dup
/*    */     //   286: dup
/*    */     //   287: astore #9
/*    */     //   289: invokespecial <init> : ()V
/*    */     //   292: aload #8
/*    */     //   294: invokevirtual rk0 : (Lf/cQ;)V
/*    */     //   297: iconst_m1
/*    */     //   298: if_icmple -> 308
/*    */     //   301: aload #9
/*    */     //   303: iload #10
/*    */     //   305: invokevirtual Z30 : (I)V
/*    */     //   308: aload #5
/*    */     //   310: aload_3
/*    */     //   311: aload #4
/*    */     //   313: aload_3
/*    */     //   314: aload #9
/*    */     //   316: aload_0
/*    */     //   317: aload #7
/*    */     //   319: aload #9
/*    */     //   321: <illegal opcode> run : (Lf/wL;[Ljava/lang/String;Lf/W1;)Ljava/lang/Runnable;
/*    */     //   326: invokevirtual D30 : (Ljava/lang/Runnable;)V
/*    */     //   329: iconst_2
/*    */     //   330: anewarray f/JG0
/*    */     //   333: dup
/*    */     //   334: dup
/*    */     //   335: iconst_0
/*    */     //   336: aload #6
/*    */     //   338: aastore
/*    */     //   339: iconst_1
/*    */     //   340: aload #9
/*    */     //   342: aastore
/*    */     //   343: invokevirtual AUX : ([Lf/JG0;)Lf/U90;
/*    */     //   346: invokevirtual ee0 : (Lf/U90;)Lf/U90;
/*    */     //   349: pop
/*    */     //   350: iconst_2
/*    */     //   351: anewarray f/JG0
/*    */     //   354: dup
/*    */     //   355: dup
/*    */     //   356: iconst_0
/*    */     //   357: aload #6
/*    */     //   359: aastore
/*    */     //   360: iconst_1
/*    */     //   361: aload #9
/*    */     //   363: aastore
/*    */     //   364: invokevirtual vo0 : ([Lf/JG0;)Lf/U90;
/*    */     //   367: iconst_5
/*    */     //   368: invokevirtual Aq : (I)Lf/U90;
/*    */     //   371: invokevirtual ee0 : (Lf/U90;)Lf/U90;
/*    */     //   374: pop
/*    */     //   375: iconst_0
/*    */     //   376: istore #6
/*    */     //   378: iload #6
/*    */     //   380: aload_0
/*    */     //   381: getfield dL0 : [B
/*    */     //   384: dup
/*    */     //   385: astore #7
/*    */     //   387: arraylength
/*    */     //   388: if_icmpge -> 585
/*    */     //   391: iload #6
/*    */     //   393: aload #5
/*    */     //   395: aload_3
/*    */     //   396: aload #4
/*    */     //   398: aload_3
/*    */     //   399: aload_0
/*    */     //   400: dup
/*    */     //   401: aload #7
/*    */     //   403: iload #6
/*    */     //   405: baload
/*    */     //   406: dup
/*    */     //   407: istore #7
/*    */     //   409: invokestatic cC0 : (B)Ljava/lang/String;
/*    */     //   412: astore #8
/*    */     //   414: new f/dQ
/*    */     //   417: dup
/*    */     //   418: dup2
/*    */     //   419: astore #9
/*    */     //   421: aload #8
/*    */     //   423: ldc ':'
/*    */     //   425: invokestatic tF0 : (Ljava/lang/String;Ljava/lang/String;)Ljava/lang/String;
/*    */     //   428: astore #10
/*    */     //   430: invokespecial <init> : ()V
/*    */     //   433: aload #10
/*    */     //   435: invokevirtual E1 : (Ljava/lang/String;)V
/*    */     //   438: ldc 'label-settings-title'
/*    */     //   440: invokevirtual Xu : (Ljava/lang/String;)V
/*    */     //   443: new f/Un
/*    */     //   446: dup
/*    */     //   447: astore #10
/*    */     //   449: aload_0
/*    */     //   450: iload #7
/*    */     //   452: aload #10
/*    */     //   454: sipush #1176
/*    */     //   457: invokestatic OH0 : (I)Ljava/lang/String;
/*    */     //   460: invokespecial <init> : (Ljava/lang/String;)V
/*    */     //   463: <illegal opcode> run : (Lf/wL;B)Ljava/lang/Runnable;
/*    */     //   468: invokevirtual tW : (Ljava/lang/Runnable;)V
/*    */     //   471: getfield Ph0 : [Lf/Un;
/*    */     //   474: iload #6
/*    */     //   476: new f/Un
/*    */     //   479: dup
/*    */     //   480: astore #11
/*    */     //   482: invokespecial <init> : ()V
/*    */     //   485: aload #11
/*    */     //   487: aastore
/*    */     //   488: getfield Ph0 : [Lf/Un;
/*    */     //   491: iload #6
/*    */     //   493: aaload
/*    */     //   494: aload_0
/*    */     //   495: iload #7
/*    */     //   497: aload #8
/*    */     //   499: <illegal opcode> run : (Lf/wL;BLjava/lang/String;)Ljava/lang/Runnable;
/*    */     //   504: invokevirtual tW : (Ljava/lang/Runnable;)V
/*    */     //   507: iconst_3
/*    */     //   508: anewarray f/JG0
/*    */     //   511: dup
/*    */     //   512: dup
/*    */     //   513: aload_0
/*    */     //   514: swap
/*    */     //   515: dup
/*    */     //   516: iconst_0
/*    */     //   517: aload #9
/*    */     //   519: aastore
/*    */     //   520: iconst_1
/*    */     //   521: aload #10
/*    */     //   523: aastore
/*    */     //   524: getfield Ph0 : [Lf/Un;
/*    */     //   527: iload #6
/*    */     //   529: aaload
/*    */     //   530: iconst_2
/*    */     //   531: swap
/*    */     //   532: aastore
/*    */     //   533: invokevirtual AUX : ([Lf/JG0;)Lf/U90;
/*    */     //   536: invokevirtual ee0 : (Lf/U90;)Lf/U90;
/*    */     //   539: pop
/*    */     //   540: iconst_3
/*    */     //   541: anewarray f/JG0
/*    */     //   544: dup
/*    */     //   545: dup
/*    */     //   546: aload_0
/*    */     //   547: swap
/*    */     //   548: dup
/*    */     //   549: iconst_0
/*    */     //   550: aload #9
/*    */     //   552: aastore
/*    */     //   553: iconst_1
/*    */     //   554: aload #10
/*    */     //   556: aastore
/*    */     //   557: getfield Ph0 : [Lf/Un;
/*    */     //   560: iload #6
/*    */     //   562: aaload
/*    */     //   563: iconst_2
/*    */     //   564: swap
/*    */     //   565: aastore
/*    */     //   566: invokevirtual vo0 : ([Lf/JG0;)Lf/U90;
/*    */     //   569: iconst_5
/*    */     //   570: invokevirtual Aq : (I)Lf/U90;
/*    */     //   573: invokevirtual ee0 : (Lf/U90;)Lf/U90;
/*    */     //   576: pop
/*    */     //   577: iconst_1
/*    */     //   578: iadd
/*    */     //   579: i2b
/*    */     //   580: istore #6
/*    */     //   582: goto -> 378
/*    */     //   585: aload_0
/*    */     //   586: invokevirtual Yg : ()V
/*    */     //   589: invokestatic XU : ()Z
/*    */     //   592: ifne -> 668
/*    */     //   595: aload #5
/*    */     //   597: aload_3
/*    */     //   598: aload #4
/*    */     //   600: iconst_5
/*    */     //   601: invokevirtual Aq : (I)Lf/U90;
/*    */     //   604: new f/g0
/*    */     //   607: dup
/*    */     //   608: aload_3
/*    */     //   609: invokespecial <init> : (Lf/Ip;)V
/*    */     //   612: iconst_2
/*    */     //   613: anewarray f/JG0
/*    */     //   616: dup
/*    */     //   617: dup
/*    */     //   618: iconst_0
/*    */     //   619: aload_2
/*    */     //   620: aastore
/*    */     //   621: iconst_1
/*    */     //   622: aload_1
/*    */     //   623: aastore
/*    */     //   624: invokevirtual Mg : ([Lf/JG0;)Lf/U90;
/*    */     //   627: invokevirtual ee0 : (Lf/U90;)Lf/U90;
/*    */     //   630: iconst_5
/*    */     //   631: invokevirtual Aq : (I)Lf/U90;
/*    */     //   634: pop
/*    */     //   635: iconst_1
/*    */     //   636: anewarray f/JG0
/*    */     //   639: dup
/*    */     //   640: iconst_0
/*    */     //   641: aload_2
/*    */     //   642: aastore
/*    */     //   643: invokevirtual vo0 : ([Lf/JG0;)Lf/U90;
/*    */     //   646: invokevirtual Em0 : ()Lf/U90;
/*    */     //   649: iconst_1
/*    */     //   650: anewarray f/JG0
/*    */     //   653: dup
/*    */     //   654: iconst_0
/*    */     //   655: aload_1
/*    */     //   656: aastore
/*    */     //   657: invokevirtual Mg : ([Lf/JG0;)Lf/U90;
/*    */     //   660: iconst_5
/*    */     //   661: invokevirtual Aq : (I)Lf/U90;
/*    */     //   664: invokevirtual ee0 : (Lf/U90;)Lf/U90;
/*    */     //   667: pop
/*    */     //   668: invokestatic ER : ()Z
/*    */     //   671: ifeq -> 795
/*    */     //   674: aload #5
/*    */     //   676: aload #4
/*    */     //   678: new f/Un
/*    */     //   681: dup
/*    */     //   682: astore_1
/*    */     //   683: aload_0
/*    */     //   684: aload_1
/*    */     //   685: sipush #1162
/*    */     //   688: invokestatic OH0 : (I)Ljava/lang/String;
/*    */     //   691: invokespecial <init> : (Ljava/lang/String;)V
/*    */     //   694: <illegal opcode> run : (Lf/wL;)Ljava/lang/Runnable;
/*    */     //   699: invokevirtual tW : (Ljava/lang/Runnable;)V
/*    */     //   702: new f/Un
/*    */     //   705: dup
/*    */     //   706: astore_2
/*    */     //   707: aload_0
/*    */     //   708: aload_2
/*    */     //   709: sipush #1163
/*    */     //   712: invokestatic OH0 : (I)Ljava/lang/String;
/*    */     //   715: invokespecial <init> : (Ljava/lang/String;)V
/*    */     //   718: <illegal opcode> run : (Lf/wL;)Ljava/lang/Runnable;
/*    */     //   723: invokevirtual tW : (Ljava/lang/Runnable;)V
/*    */     //   726: iconst_5
/*    */     //   727: invokevirtual Aq : (I)Lf/U90;
/*    */     //   730: new f/g0
/*    */     //   733: dup
/*    */     //   734: aload_3
/*    */     //   735: invokespecial <init> : (Lf/Ip;)V
/*    */     //   738: iconst_2
/*    */     //   739: anewarray f/JG0
/*    */     //   742: dup
/*    */     //   743: dup
/*    */     //   744: iconst_0
/*    */     //   745: aload_1
/*    */     //   746: aastore
/*    */     //   747: iconst_1
/*    */     //   748: aload_2
/*    */     //   749: aastore
/*    */     //   750: invokevirtual Mg : ([Lf/JG0;)Lf/U90;
/*    */     //   753: invokevirtual ee0 : (Lf/U90;)Lf/U90;
/*    */     //   756: iconst_5
/*    */     //   757: invokevirtual Aq : (I)Lf/U90;
/*    */     //   760: pop
/*    */     //   761: new f/cr0
/*    */     //   764: dup
/*    */     //   765: aload_3
/*    */     //   766: invokespecial <init> : (Lf/Ip;)V
/*    */     //   769: invokevirtual Em0 : ()Lf/U90;
/*    */     //   772: iconst_2
/*    */     //   773: anewarray f/JG0
/*    */     //   776: dup
/*    */     //   777: dup
/*    */     //   778: iconst_0
/*    */     //   779: aload_1
/*    */     //   780: aastore
/*    */     //   781: iconst_1
/*    */     //   782: aload_2
/*    */     //   783: aastore
/*    */     //   784: invokevirtual Mg : ([Lf/JG0;)Lf/U90;
/*    */     //   787: iconst_5
/*    */     //   788: invokevirtual Aq : (I)Lf/U90;
/*    */     //   791: invokevirtual ee0 : (Lf/U90;)Lf/U90;
/*    */     //   794: pop
/*    */     //   795: aload_0
/*    */     //   796: dup
/*    */     //   797: dup
/*    */     //   798: dup2
/*    */     //   799: aload_3
/*    */     //   800: aload #5
/*    */     //   802: aload_3
/*    */     //   803: aload #4
/*    */     //   805: invokevirtual WN : (Lf/U90;)V
/*    */     //   808: invokevirtual rK0 : (Lf/U90;)V
/*    */     //   811: getfield jH0 : Lf/Ip;
/*    */     //   814: dup
/*    */     //   815: dup
/*    */     //   816: astore_1
/*    */     //   817: invokevirtual getClass : ()Ljava/lang/Class;
/*    */     //   820: pop
/*    */     //   821: new f/cr0
/*    */     //   824: dup
/*    */     //   825: aload_1
/*    */     //   826: invokespecial <init> : (Lf/Ip;)V
/*    */     //   829: invokevirtual Em0 : ()Lf/U90;
/*    */     //   832: aload_3
/*    */     //   833: invokevirtual Ya : (Lf/JG0;)Lf/U90;
/*    */     //   836: invokevirtual Em0 : ()Lf/U90;
/*    */     //   839: invokevirtual WN : (Lf/U90;)V
/*    */     //   842: getfield jH0 : Lf/Ip;
/*    */     //   845: dup
/*    */     //   846: dup
/*    */     //   847: astore_1
/*    */     //   848: invokevirtual getClass : ()Ljava/lang/Class;
/*    */     //   851: pop
/*    */     //   852: new f/cr0
/*    */     //   855: dup
/*    */     //   856: aload_1
/*    */     //   857: invokespecial <init> : (Lf/Ip;)V
/*    */     //   860: invokevirtual Em0 : ()Lf/U90;
/*    */     //   863: aload_3
/*    */     //   864: invokevirtual Ya : (Lf/JG0;)Lf/U90;
/*    */     //   867: invokevirtual Em0 : ()Lf/U90;
/*    */     //   870: invokevirtual rK0 : (Lf/U90;)V
/*    */     //   873: getfield jH0 : Lf/Ip;
/*    */     //   876: astore_1
/*    */     //   877: invokevirtual Ub : ()I
/*    */     //   880: aload_1
/*    */     //   881: swap
/*    */     //   882: invokevirtual si : (Lf/JG0;I)V
/*    */     //   885: getstatic f/UB0.Kg0 : Lf/Q50;
/*    */     //   888: invokevirtual getClass : ()Ljava/lang/Class;
/*    */     //   891: pop
/*    */     //   892: getstatic f/Dp0.Ro0 : Lf/Dp0;
/*    */     //   895: getstatic f/Dp0.QG : Lf/Dp0;
/*    */     //   898: if_acmpne -> 905
/*    */     //   901: iconst_1
/*    */     //   902: goto -> 906
/*    */     //   905: iconst_0
/*    */     //   906: ifne -> 915
/*    */     //   909: invokestatic zp : ()Z
/*    */     //   912: ifeq -> 955
/*    */     //   915: invokestatic XU : ()Z
/*    */     //   918: ifeq -> 955
/*    */     //   921: aload_0
/*    */     //   922: dup
/*    */     //   923: dup
/*    */     //   924: dup2
/*    */     //   925: getfield wa : Lf/Un;
/*    */     //   928: ldc_w 'mobile-gear-icon'
/*    */     //   931: invokevirtual Xu : (Ljava/lang/String;)V
/*    */     //   934: getfield wa : Lf/Un;
/*    */     //   937: ldc_w ''
/*    */     //   940: invokevirtual s6 : (Ljava/lang/String;)V
/*    */     //   943: getfield wa : Lf/Un;
/*    */     //   946: astore_0
/*    */     //   947: invokevirtual Ub : ()I
/*    */     //   950: aload_0
/*    */     //   951: swap
/*    */     //   952: invokevirtual si : (Lf/JG0;I)V
/*    */     //   955: return
/*    */     // Line number table:
/*    */     //   Java source line number -> byte code offset
/*    */     //   #1	-> 116
/*    */     //   #2	-> 125
/*    */     //   #3	-> 128
/*    */     //   #4	-> 150
/*    */     //   #5	-> 160
/*    */     //   #6	-> 170
/*    */     //   #7	-> 185
/*    */     //   #8	-> 193
/*    */     //   #9	-> 198
/*    */     //   #10	-> 201
/*    */     //   #11	-> 233
/*    */     //   #12	-> 240
/*    */     //   #13	-> 289
/*    */     //   #14	-> 305
/*    */     //   #15	-> 423
/*    */     //   #16	-> 430
/*    */     //   #17	-> 438
/*    */     //   #18	-> 604
/*    */     //   #19	-> 613
/*    */     //   #20	-> 730
/*    */     //   #21	-> 739
/*    */     //   #22	-> 761
/*    */     //   #23	-> 769
/*    */     //   #24	-> 821
/*    */     //   #25	-> 829
/*    */     //   #26	-> 852
/*    */     //   #27	-> 860
/*    */     //   #28	-> 877
/*    */     //   #29	-> 885
/*    */     //   #30	-> 892
/*    */     //   #31	-> 895
/*    */     //   #32	-> 909
/* 10 */     //   #33	-> 947 } public final void Yg() { byte[] arrayOfByte; for (byte b = 0; b < (arrayOfByte = this.dL0).length; b = (byte)(b + 1)) { byte b1 = arrayOfByte[b]; if (km.mI0.s2(b1) || (b1 == 4 && km.mI0.yE != null)) { this.Ph0[b].s6(Ml0.OH0(1177)); } else if (b1 == 2) { this.Ph0[b].s6(Ml0.OH0(1168)); } else { this.Ph0[b].s6(Ml0.OH0(1169)); }  }  } public final void close() { r9 r9; if (km.mI0.AN == null) { js.vu0.DJ(Ml0.Go(1178, Ml0.cC0((byte)2)), null); return; }  if (this.cO) { (r9 = km.iE0).getClass(); js js; if ((js = js.vu0) == null) { bn(); } else { lPt6 lPt6; String str = Ml0.OH0(1179); this(this); js.DJ(str, lPt6); }  return; }  ra0(); } private void by0(int paramInt, RD0 paramRD01, RD0 paramRD02, RD0 paramRD03, Consumer<hZ> paramConsumer, byte paramByte) { if (paramInt != 0) { if (paramInt == 2) { js.vu0.DJ(Ml0.Go(1093, paramRD01.bo().getAbsolutePath()), null); return; }  this[0] = String.valueOf(paramInt); String[] arrayOfString; (arrayOfString = new String[2])[1] = paramRD01.bo().getAbsolutePath(); js.vu0.DJ(Ml0.sB(1090, this), null); return; }  if (!paramRD02.L0()) { js.vu0.DJ(Ml0.Go(1092, paramRD01.bo().getAbsolutePath()), null); return; }
/* 11 */      if (!km.iE0.Qz(paramRD02.bo())) {
/* 12 */       js.vu0
/*    */         
/* 14 */         .DJ(Ml0.Go(1094, paramRD02.bo().getAbsolutePath()), null); return;
/* 15 */     }  (new RD0(paramRD02.bo())).mp(paramRD03); paramConsumer.accept(UB0.vj0.lPT1(paramRD03.bo().getAbsolutePath())); String str = paramRD03.bo().getAbsolutePath().replace("_import", ""); switch (paramByte) { case 4:
/* 16 */         h1.h0 = this; break;case 3: h1.Re0 = this; break;case 2: h1.yD0 = this; break;case 1: h1.Vh = this; break;case 0: h1.Pq = this; break; }  h1.Td(); }
/*    */ 
/*    */   
/*    */   public final void V90(throws paramthrows) {
/*    */     super.V90(paramthrows);
/*    */     if (this.WI != null && this.CoN.Po0())
/*    */       if (this.tI0) {
/*    */         this.WI.uc0(Libarchive.getAlreadyExtracted() / Libarchive.getSizeToExtract());
/*    */       } else {
/*    */         this.WI.uc0(this.lw);
/*    */       }  
/*    */   }
/*    */   
/*    */   public final boolean tr(RD0 paramRD0, byte paramByte, boolean paramBoolean) {
/*    */     // Byte code:
/*    */     //   0: iload_2
/*    */     //   1: getstatic f/wL.AJ0 : Lf/ik;
/*    */     //   4: ldc_w 'Possible rom '
/*    */     //   7: invokestatic df : (Ljava/lang/String;)Ljava/lang/StringBuilder;
/*    */     //   10: aload_1
/*    */     //   11: getfield ml : Ljava/io/File;
/*    */     //   14: invokevirtual getName : ()Ljava/lang/String;
/*    */     //   17: invokevirtual append : (Ljava/lang/String;)Ljava/lang/StringBuilder;
/*    */     //   20: ldc_w ' (size: '
/*    */     //   23: invokevirtual append : (Ljava/lang/String;)Ljava/lang/StringBuilder;
/*    */     //   26: aload_1
/*    */     //   27: invokevirtual tN : ()J
/*    */     //   30: ldc2_w 1048576
/*    */     //   33: ldiv
/*    */     //   34: invokevirtual append : (J)Ljava/lang/StringBuilder;
/*    */     //   37: ldc_w ' MB)'
/*    */     //   40: invokevirtual append : (Ljava/lang/String;)Ljava/lang/StringBuilder;
/*    */     //   43: invokevirtual toString : ()Ljava/lang/String;
/*    */     //   46: invokeinterface info : (Ljava/lang/String;)V
/*    */     //   51: invokestatic n80 : (B)Z
/*    */     //   54: ifeq -> 310
/*    */     //   57: iload_2
/*    */     //   58: invokestatic cC0 : (B)Ljava/lang/String;
/*    */     //   61: astore #4
/*    */     //   63: new f/s40
/*    */     //   66: dup
/*    */     //   67: dup
/*    */     //   68: astore #5
/*    */     //   70: aload_1
/*    */     //   71: invokespecial <init> : (Lf/RD0;)V
/*    */     //   74: getfield wJ : Lf/uq;
/*    */     //   77: ifnonnull -> 83
/*    */     //   80: goto -> 247
/*    */     //   83: aload #5
/*    */     //   85: invokevirtual in : ()B
/*    */     //   88: iload_2
/*    */     //   89: if_icmpeq -> 127
/*    */     //   92: getstatic f/js.vu0 : Lf/js;
/*    */     //   95: sipush #1183
/*    */     //   98: iconst_2
/*    */     //   99: anewarray java/lang/String
/*    */     //   102: dup
/*    */     //   103: dup
/*    */     //   104: aload_1
/*    */     //   105: iconst_0
/*    */     //   106: istore_0
/*    */     //   107: invokevirtual rw : ()Ljava/lang/String;
/*    */     //   110: iload_0
/*    */     //   111: swap
/*    */     //   112: aastore
/*    */     //   113: iconst_1
/*    */     //   114: aload #4
/*    */     //   116: aastore
/*    */     //   117: invokestatic sB : (I[Ljava/lang/String;)Ljava/lang/String;
/*    */     //   120: aconst_null
/*    */     //   121: invokevirtual DJ : (Ljava/lang/String;Ljava/lang/Runnable;)V
/*    */     //   124: goto -> 247
/*    */     //   127: iload_2
/*    */     //   128: ifeq -> 166
/*    */     //   131: iload_2
/*    */     //   132: iconst_1
/*    */     //   133: if_icmpeq -> 139
/*    */     //   136: goto -> 190
/*    */     //   139: aload_1
/*    */     //   140: aload_0
/*    */     //   141: iconst_1
/*    */     //   142: putfield cO : Z
/*    */     //   145: invokevirtual rw : ()Ljava/lang/String;
/*    */     //   148: putstatic f/h1.Vh : Ljava/lang/String;
/*    */     //   151: invokestatic Td : ()Z
/*    */     //   154: pop
/*    */     //   155: getstatic f/km.mI0 : Lf/P1;
/*    */     //   158: aload #5
/*    */     //   160: putfield UI0 : Lf/s40;
/*    */     //   163: goto -> 190
/*    */     //   166: aload_1
/*    */     //   167: aload_0
/*    */     //   168: iconst_1
/*    */     //   169: putfield cO : Z
/*    */     //   172: invokevirtual rw : ()Ljava/lang/String;
/*    */     //   175: putstatic f/h1.Pq : Ljava/lang/String;
/*    */     //   178: invokestatic Td : ()Z
/*    */     //   181: pop
/*    */     //   182: getstatic f/km.mI0 : Lf/P1;
/*    */     //   185: aload #5
/*    */     //   187: putfield UG0 : Lf/s40;
/*    */     //   190: aload_0
/*    */     //   191: aload_1
/*    */     //   192: iload_2
/*    */     //   193: iload_3
/*    */     //   194: invokevirtual ng0 : (Lf/RD0;BZ)V
/*    */     //   197: iconst_1
/*    */     //   198: goto -> 309
/*    */     //   201: astore_0
/*    */     //   202: aload_0
/*    */     //   203: dup
/*    */     //   204: invokevirtual printStackTrace : ()V
/*    */     //   207: getstatic f/km.mI0 : Lf/P1;
/*    */     //   210: invokevirtual getClass : ()Ljava/lang/Class;
/*    */     //   213: pop
/*    */     //   214: invokestatic Nn0 : (Ljava/lang/Exception;)Z
/*    */     //   217: ifeq -> 251
/*    */     //   220: getstatic f/wL.AJ0 : Lf/ik;
/*    */     //   223: ldc_w 'OutOfMemoryError loading rom'
/*    */     //   226: aload_0
/*    */     //   227: invokeinterface error : (Ljava/lang/String;Ljava/lang/Throwable;)V
/*    */     //   232: getstatic f/js.vu0 : Lf/js;
/*    */     //   235: bipush #81
/*    */     //   237: ldc_w 'Fatal OutOfMemoryError.\\n\\nPlease restart the application and try again.\\nIf this persists please raise the memory allocation.\\nPlease visit https://pokemmo.com/oom for more information.'
/*    */     //   240: invokestatic la : (ILjava/lang/String;)Ljava/lang/String;
/*    */     //   243: aconst_null
/*    */     //   244: invokevirtual DJ : (Ljava/lang/String;Ljava/lang/Runnable;)V
/*    */     //   247: iconst_0
/*    */     //   248: goto -> 309
/*    */     //   251: getstatic f/js.vu0 : Lf/js;
/*    */     //   254: iconst_2
/*    */     //   255: anewarray java/lang/String
/*    */     //   258: dup
/*    */     //   259: dup
/*    */     //   260: astore_0
/*    */     //   261: aload_1
/*    */     //   262: getfield ml : Ljava/io/File;
/*    */     //   265: invokevirtual getName : ()Ljava/lang/String;
/*    */     //   268: iconst_0
/*    */     //   269: swap
/*    */     //   270: aastore
/*    */     //   271: iconst_1
/*    */     //   272: aload #4
/*    */     //   274: aastore
/*    */     //   275: sipush #1182
/*    */     //   278: aload_0
/*    */     //   279: invokestatic sB : (I[Ljava/lang/String;)Ljava/lang/String;
/*    */     //   282: aconst_null
/*    */     //   283: invokevirtual DJ : (Ljava/lang/String;Ljava/lang/Runnable;)V
/*    */     //   286: iconst_0
/*    */     //   287: goto -> 309
/*    */     //   290: invokevirtual printStackTrace : ()V
/*    */     //   293: getstatic f/js.vu0 : Lf/js;
/*    */     //   296: sipush #1147
/*    */     //   299: aload #4
/*    */     //   301: invokestatic Go : (ILjava/lang/String;)Ljava/lang/String;
/*    */     //   304: aconst_null
/*    */     //   305: invokevirtual DJ : (Ljava/lang/String;Ljava/lang/Runnable;)V
/*    */     //   308: iconst_0
/*    */     //   309: ireturn
/*    */     //   310: iload_2
/*    */     //   311: dup
/*    */     //   312: invokestatic cC0 : (B)Ljava/lang/String;
/*    */     //   315: astore #4
/*    */     //   317: new f/ml
/*    */     //   320: dup
/*    */     //   321: astore #5
/*    */     //   323: aload_1
/*    */     //   324: invokespecial <init> : (Lf/RD0;)V
/*    */     //   327: iconst_2
/*    */     //   328: if_icmpne -> 415
/*    */     //   331: getstatic f/Wo.Bc : [Ljava/lang/String;
/*    */     //   334: invokestatic asList : ([Ljava/lang/Object;)Ljava/util/List;
/*    */     //   337: aload #5
/*    */     //   339: getfield UI : Ljava/lang/String;
/*    */     //   342: invokeinterface contains : (Ljava/lang/Object;)Z
/*    */     //   347: ifeq -> 415
/*    */     //   350: aload_1
/*    */     //   351: aload_0
/*    */     //   352: new f/Wo
/*    */     //   355: dup
/*    */     //   356: dup
/*    */     //   357: astore_2
/*    */     //   358: aload_1
/*    */     //   359: invokespecial <init> : (Lf/RD0;)V
/*    */     //   362: invokevirtual BL : ()V
/*    */     //   365: getstatic f/km.mI0 : Lf/P1;
/*    */     //   368: aload_2
/*    */     //   369: putfield AN : Lf/Wo;
/*    */     //   372: iconst_1
/*    */     //   373: putfield cO : Z
/*    */     //   376: invokevirtual rw : ()Ljava/lang/String;
/*    */     //   379: putstatic f/h1.yD0 : Ljava/lang/String;
/*    */     //   382: iconst_1
/*    */     //   383: putstatic f/h1.A0 : Z
/*    */     //   386: invokestatic Td : ()Z
/*    */     //   389: pop
/*    */     //   390: iconst_2
/*    */     //   391: istore_2
/*    */     //   392: goto -> 562
/*    */     //   395: astore_0
/*    */     //   396: getstatic f/wL.AJ0 : Lf/ik;
/*    */     //   399: ldc_w 'Error loading rom'
/*    */     //   402: aload_0
/*    */     //   403: invokeinterface error : (Ljava/lang/String;Ljava/lang/Throwable;)V
/*    */     //   408: getstatic f/js.vu0 : Lf/js;
/*    */     //   411: astore_0
/*    */     //   412: goto -> 589
/*    */     //   415: iload_2
/*    */     //   416: iconst_4
/*    */     //   417: if_icmpne -> 496
/*    */     //   420: getstatic f/BE.Vt : [Ljava/lang/String;
/*    */     //   423: invokestatic asList : ([Ljava/lang/Object;)Ljava/util/List;
/*    */     //   426: aload #5
/*    */     //   428: getfield UI : Ljava/lang/String;
/*    */     //   431: invokeinterface contains : (Ljava/lang/Object;)Z
/*    */     //   436: ifeq -> 496
/*    */     //   439: aload_1
/*    */     //   440: aload_0
/*    */     //   441: new f/BE
/*    */     //   444: dup
/*    */     //   445: dup
/*    */     //   446: astore_2
/*    */     //   447: aload_1
/*    */     //   448: invokespecial <init> : (Lf/RD0;)V
/*    */     //   451: invokevirtual BL : ()V
/*    */     //   454: getstatic f/km.mI0 : Lf/P1;
/*    */     //   457: aload_2
/*    */     //   458: putfield yE : Lf/BE;
/*    */     //   461: iconst_1
/*    */     //   462: putfield cO : Z
/*    */     //   465: invokevirtual rw : ()Ljava/lang/String;
/*    */     //   468: putstatic f/h1.h0 : Ljava/lang/String;
/*    */     //   471: invokestatic Td : ()Z
/*    */     //   474: pop
/*    */     //   475: iconst_4
/*    */     //   476: istore_2
/*    */     //   477: goto -> 562
/*    */     //   480: astore_0
/*    */     //   481: getstatic f/wL.AJ0 : Lf/ik;
/*    */     //   484: ldc_w 'Error loading rom'
/*    */     //   487: aload_0
/*    */     //   488: invokeinterface error : (Ljava/lang/String;Ljava/lang/Throwable;)V
/*    */     //   493: goto -> 408
/*    */     //   496: iload_2
/*    */     //   497: iconst_3
/*    */     //   498: if_icmpne -> 652
/*    */     //   501: getstatic f/gD.o9 : [Ljava/lang/String;
/*    */     //   504: invokestatic asList : ([Ljava/lang/Object;)Ljava/util/List;
/*    */     //   507: aload #5
/*    */     //   509: getfield UI : Ljava/lang/String;
/*    */     //   512: invokeinterface contains : (Ljava/lang/Object;)Z
/*    */     //   517: ifeq -> 652
/*    */     //   520: aload_1
/*    */     //   521: aload_0
/*    */     //   522: new f/gD
/*    */     //   525: dup
/*    */     //   526: dup
/*    */     //   527: astore_2
/*    */     //   528: aload_1
/*    */     //   529: invokespecial <init> : (Lf/RD0;)V
/*    */     //   532: invokevirtual BL : ()V
/*    */     //   535: getstatic f/km.mI0 : Lf/P1;
/*    */     //   538: aload_2
/*    */     //   539: putfield MT : Lf/gD;
/*    */     //   542: iconst_1
/*    */     //   543: putfield cO : Z
/*    */     //   546: invokevirtual rw : ()Ljava/lang/String;
/*    */     //   549: putstatic f/h1.Re0 : Ljava/lang/String;
/*    */     //   552: iconst_1
/*    */     //   553: putstatic f/h1.A0 : Z
/*    */     //   556: invokestatic Td : ()Z
/*    */     //   559: pop
/*    */     //   560: iconst_3
/*    */     //   561: istore_2
/*    */     //   562: aload_0
/*    */     //   563: aload_1
/*    */     //   564: iload_2
/*    */     //   565: iload_3
/*    */     //   566: invokevirtual ng0 : (Lf/RD0;BZ)V
/*    */     //   569: iconst_1
/*    */     //   570: goto -> 688
/*    */     //   573: astore_0
/*    */     //   574: getstatic f/wL.AJ0 : Lf/ik;
/*    */     //   577: ldc_w 'Error loading rom'
/*    */     //   580: aload_0
/*    */     //   581: invokeinterface error : (Ljava/lang/String;Ljava/lang/Throwable;)V
/*    */     //   586: goto -> 408
/*    */     //   589: aload_0
/*    */     //   590: sipush #1144
/*    */     //   593: aload #4
/*    */     //   595: invokestatic Go : (ILjava/lang/String;)Ljava/lang/String;
/*    */     //   598: aconst_null
/*    */     //   599: invokevirtual DJ : (Ljava/lang/String;Ljava/lang/Runnable;)V
/*    */     //   602: goto -> 647
/*    */     //   605: astore_0
/*    */     //   606: aload_0
/*    */     //   607: getstatic f/wL.AJ0 : Lf/ik;
/*    */     //   610: ldc_w 'Error loading rom'
/*    */     //   613: aload_0
/*    */     //   614: invokeinterface error : (Ljava/lang/String;Ljava/lang/Throwable;)V
/*    */     //   619: getstatic f/km.mI0 : Lf/P1;
/*    */     //   622: invokevirtual getClass : ()Ljava/lang/Class;
/*    */     //   625: pop
/*    */     //   626: invokestatic Nn0 : (Ljava/lang/Exception;)Z
/*    */     //   629: ifeq -> 652
/*    */     //   632: getstatic f/js.vu0 : Lf/js;
/*    */     //   635: bipush #81
/*    */     //   637: ldc_w 'Fatal OutOfMemoryError.\\n\\nPlease restart the application and try again.\\nIf this persists please raise the memory allocation.\\nPlease visit https://pokemmo.com/oom for more information.'
/*    */     //   640: invokestatic la : (ILjava/lang/String;)Ljava/lang/String;
/*    */     //   643: aconst_null
/*    */     //   644: invokevirtual DJ : (Ljava/lang/String;Ljava/lang/Runnable;)V
/*    */     //   647: iconst_0
/*    */     //   648: goto -> 688
/*    */     //   651: pop
/*    */     //   652: getstatic f/js.vu0 : Lf/js;
/*    */     //   655: iconst_2
/*    */     //   656: anewarray java/lang/String
/*    */     //   659: dup
/*    */     //   660: dup
/*    */     //   661: astore_0
/*    */     //   662: aload_1
/*    */     //   663: getfield ml : Ljava/io/File;
/*    */     //   666: invokevirtual getName : ()Ljava/lang/String;
/*    */     //   669: iconst_0
/*    */     //   670: swap
/*    */     //   671: aastore
/*    */     //   672: iconst_1
/*    */     //   673: aload #4
/*    */     //   675: aastore
/*    */     //   676: sipush #1183
/*    */     //   679: aload_0
/*    */     //   680: invokestatic sB : (I[Ljava/lang/String;)Ljava/lang/String;
/*    */     //   683: aconst_null
/*    */     //   684: invokevirtual DJ : (Ljava/lang/String;Ljava/lang/Runnable;)V
/*    */     //   687: iconst_0
/*    */     //   688: ireturn
/*    */     // Line number table:
/*    */     //   Java source line number -> byte code offset
/*    */     //   #1	-> 4
/*    */     //   #2	-> 11
/*    */     //   #3	-> 14
/*    */     //   #4	-> 17
/*    */     //   #5	-> 58
/*    */     //   #6	-> 74
/*    */     //   #7	-> 85
/*    */     //   #8	-> 92
/*    */     //   #9	-> 99
/*    */     //   #10	-> 107
/*    */     //   #11	-> 112
/*    */     //   #12	-> 121
/*    */     //   #13	-> 142
/*    */     //   #14	-> 145
/*    */     //   #15	-> 148
/*    */     //   #16	-> 172
/*    */     //   #17	-> 175
/*    */     //   #18	-> 232
/*    */     //   #19	-> 237
/*    */     //   #20	-> 244
/*    */     //   #21	-> 251
/*    */     //   #22	-> 255
/*    */     //   #23	-> 262
/*    */     //   #24	-> 265
/*    */     //   #25	-> 270
/*    */     //   #26	-> 283
/*    */     //   #27	-> 290
/*    */     //   #28	-> 293
/*    */     //   #29	-> 301
/*    */     //   #30	-> 305
/*    */     //   #31	-> 312
/*    */     //   #32	-> 359
/*    */     //   #33	-> 362
/*    */     //   #34	-> 376
/*    */     //   #35	-> 379
/*    */     //   #36	-> 408
/*    */     //   #37	-> 420
/*    */     //   #38	-> 448
/*    */     //   #39	-> 451
/*    */     //   #40	-> 465
/*    */     //   #41	-> 468
/*    */     //   #42	-> 529
/*    */     //   #43	-> 532
/*    */     //   #44	-> 546
/*    */     //   #45	-> 549
/*    */     //   #46	-> 599
/*    */     //   #47	-> 607
/*    */     //   #48	-> 632
/*    */     //   #49	-> 637
/*    */     //   #50	-> 644
/*    */     //   #51	-> 652
/*    */     //   #52	-> 656
/*    */     //   #53	-> 663
/*    */     //   #54	-> 666
/*    */     //   #55	-> 671
/*    */     //   #56	-> 684
/*    */     // Exception table:
/*    */     //   from	to	target	type
/*    */     //   63	66	290	f/Xz0
/*    */     //   63	66	201	java/lang/Exception
/*    */     //   70	77	290	f/Xz0
/*    */     //   70	77	201	java/lang/Exception
/*    */     //   83	88	290	f/Xz0
/*    */     //   83	88	201	java/lang/Exception
/*    */     //   92	95	290	f/Xz0
/*    */     //   92	95	201	java/lang/Exception
/*    */     //   98	102	290	f/Xz0
/*    */     //   98	102	201	java/lang/Exception
/*    */     //   107	127	290	f/Xz0
/*    */     //   107	127	201	java/lang/Exception
/*    */     //   139	154	290	f/Xz0
/*    */     //   139	154	201	java/lang/Exception
/*    */     //   155	181	290	f/Xz0
/*    */     //   155	181	201	java/lang/Exception
/*    */     //   182	197	290	f/Xz0
/*    */     //   182	197	201	java/lang/Exception
/*    */     //   317	320	651	f/Np
/*    */     //   317	320	605	java/lang/Exception
/*    */     //   323	327	651	f/Np
/*    */     //   323	327	605	java/lang/Exception
/*    */     //   331	347	651	f/Np
/*    */     //   331	347	605	java/lang/Exception
/*    */     //   350	355	651	f/Np
/*    */     //   350	355	605	java/lang/Exception
/*    */     //   358	362	651	f/Np
/*    */     //   358	362	605	java/lang/Exception
/*    */     //   362	365	395	java/lang/Exception
/*    */     //   365	389	651	f/Np
/*    */     //   365	389	605	java/lang/Exception
/*    */     //   396	411	651	f/Np
/*    */     //   396	411	605	java/lang/Exception
/*    */     //   420	436	651	f/Np
/*    */     //   420	436	605	java/lang/Exception
/*    */     //   439	444	651	f/Np
/*    */     //   439	444	605	java/lang/Exception
/*    */     //   447	451	651	f/Np
/*    */     //   447	451	605	java/lang/Exception
/*    */     //   451	454	480	java/lang/Exception
/*    */     //   454	474	651	f/Np
/*    */     //   454	474	605	java/lang/Exception
/*    */     //   481	496	651	f/Np
/*    */     //   481	496	605	java/lang/Exception
/*    */     //   501	517	651	f/Np
/*    */     //   501	517	605	java/lang/Exception
/*    */     //   520	525	651	f/Np
/*    */     //   520	525	605	java/lang/Exception
/*    */     //   528	532	651	f/Np
/*    */     //   528	532	605	java/lang/Exception
/*    */     //   532	535	573	java/lang/Exception
/*    */     //   535	559	651	f/Np
/*    */     //   535	559	605	java/lang/Exception
/*    */     //   562	569	651	f/Np
/*    */     //   562	569	605	java/lang/Exception
/*    */     //   574	605	651	f/Np
/*    */     //   574	605	605	java/lang/Exception
/*    */   }
/*    */   
/*    */   public final void ng0(RD0 paramRD0, byte paramByte, boolean paramBoolean) {
/*    */     // Byte code:
/*    */     //   0: aload_0
/*    */     //   1: getstatic f/js.vu0 : Lf/js;
/*    */     //   4: iload_2
/*    */     //   5: invokestatic cC0 : (B)Ljava/lang/String;
/*    */     //   8: sipush #1184
/*    */     //   11: swap
/*    */     //   12: invokestatic Go : (ILjava/lang/String;)Ljava/lang/String;
/*    */     //   15: iconst_m1
/*    */     //   16: swap
/*    */     //   17: invokevirtual Pu : (ILjava/lang/String;)V
/*    */     //   20: invokevirtual Yg : ()V
/*    */     //   23: invokestatic ER : ()Z
/*    */     //   26: ifne -> 30
/*    */     //   29: return
/*    */     //   30: iload_3
/*    */     //   31: ifeq -> 35
/*    */     //   34: return
/*    */     //   35: iload_2
/*    */     //   36: new f/Zz0
/*    */     //   39: dup
/*    */     //   40: dup
/*    */     //   41: dup2
/*    */     //   42: astore_3
/*    */     //   43: invokespecial <init> : ()V
/*    */     //   46: new f/dQ
/*    */     //   49: dup
/*    */     //   50: dup
/*    */     //   51: astore #4
/*    */     //   53: sipush #1140
/*    */     //   56: invokestatic OH0 : (I)Ljava/lang/String;
/*    */     //   59: astore #5
/*    */     //   61: invokespecial <init> : ()V
/*    */     //   64: aload #5
/*    */     //   66: invokevirtual E1 : (Ljava/lang/String;)V
/*    */     //   69: iconst_1
/*    */     //   70: anewarray f/JG0
/*    */     //   73: dup
/*    */     //   74: iconst_0
/*    */     //   75: aload #4
/*    */     //   77: aastore
/*    */     //   78: invokevirtual of0 : ([Lf/JG0;)V
/*    */     //   81: new f/ge0
/*    */     //   84: dup
/*    */     //   85: astore #4
/*    */     //   87: invokespecial <init> : ()V
/*    */     //   90: new f/dQ
/*    */     //   93: dup
/*    */     //   94: dup
/*    */     //   95: astore #5
/*    */     //   97: sipush #1141
/*    */     //   100: invokestatic OH0 : (I)Ljava/lang/String;
/*    */     //   103: astore #6
/*    */     //   105: invokespecial <init> : ()V
/*    */     //   108: aload #6
/*    */     //   110: invokevirtual E1 : (Ljava/lang/String;)V
/*    */     //   113: getfield o30 : Lf/U90;
/*    */     //   116: aload_3
/*    */     //   117: iconst_2
/*    */     //   118: anewarray f/JG0
/*    */     //   121: dup
/*    */     //   122: dup
/*    */     //   123: iconst_0
/*    */     //   124: aload #4
/*    */     //   126: aastore
/*    */     //   127: iconst_1
/*    */     //   128: aload #5
/*    */     //   130: aastore
/*    */     //   131: invokevirtual AUX : ([Lf/JG0;)Lf/U90;
/*    */     //   134: invokevirtual ee0 : (Lf/U90;)Lf/U90;
/*    */     //   137: pop
/*    */     //   138: getfield Xz0 : Lf/U90;
/*    */     //   141: new f/cr0
/*    */     //   144: dup
/*    */     //   145: aload_3
/*    */     //   146: invokespecial <init> : (Lf/Ip;)V
/*    */     //   149: invokevirtual Em0 : ()Lf/U90;
/*    */     //   152: aload #4
/*    */     //   154: invokevirtual Ya : (Lf/JG0;)Lf/U90;
/*    */     //   157: bipush #10
/*    */     //   159: invokevirtual Aq : (I)Lf/U90;
/*    */     //   162: iconst_1
/*    */     //   163: anewarray f/JG0
/*    */     //   166: dup
/*    */     //   167: iconst_0
/*    */     //   168: aload #5
/*    */     //   170: aastore
/*    */     //   171: invokevirtual Mg : ([Lf/JG0;)Lf/U90;
/*    */     //   174: invokevirtual Em0 : ()Lf/U90;
/*    */     //   177: invokevirtual ee0 : (Lf/U90;)Lf/U90;
/*    */     //   180: pop
/*    */     //   181: getstatic f/UB0.vj0 : Lf/XG;
/*    */     //   184: ldc_w 'roms'
/*    */     //   187: invokevirtual N0 : (Ljava/lang/String;)Lf/hZ;
/*    */     //   190: dup
/*    */     //   191: dup
/*    */     //   192: astore #5
/*    */     //   194: invokevirtual iz0 : ()V
/*    */     //   197: ldc_w 'importing.tmp'
/*    */     //   200: invokevirtual f0 : (Ljava/lang/String;)Lf/RD0;
/*    */     //   203: dup
/*    */     //   204: astore #6
/*    */     //   206: invokevirtual La0 : ()Z
/*    */     //   209: pop
/*    */     //   210: new java/lang/StringBuilder
/*    */     //   213: dup
/*    */     //   214: iload_2
/*    */     //   215: swap
/*    */     //   216: invokespecial <init> : ()V
/*    */     //   219: invokevirtual append : (I)Ljava/lang/StringBuilder;
/*    */     //   222: astore #7
/*    */     //   224: invokestatic sz0 : (B)Z
/*    */     //   227: ifeq -> 238
/*    */     //   230: ldc_w '.nds'
/*    */     //   233: astore #8
/*    */     //   235: goto -> 243
/*    */     //   238: ldc_w '.gba'
/*    */     //   241: astore #8
/*    */     //   243: aload #5
/*    */     //   245: aload #7
/*    */     //   247: aload #8
/*    */     //   249: invokevirtual append : (Ljava/lang/String;)Ljava/lang/StringBuilder;
/*    */     //   252: ldc_w '_import'
/*    */     //   255: invokevirtual append : (Ljava/lang/String;)Ljava/lang/StringBuilder;
/*    */     //   258: invokevirtual toString : ()Ljava/lang/String;
/*    */     //   261: invokevirtual f0 : (Ljava/lang/String;)Lf/RD0;
/*    */     //   264: dup
/*    */     //   265: astore #5
/*    */     //   267: invokevirtual La0 : ()Z
/*    */     //   270: pop
/*    */     //   271: getstatic f/js.vu0 : Lf/js;
/*    */     //   274: new f/h70
/*    */     //   277: dup
/*    */     //   278: dup
/*    */     //   279: aload_3
/*    */     //   280: aload_0
/*    */     //   281: aload_1
/*    */     //   282: aload #6
/*    */     //   284: aload #5
/*    */     //   286: iload_2
/*    */     //   287: aload #4
/*    */     //   289: <illegal opcode> run : (Lf/wL;Lf/RD0;Lf/RD0;Lf/RD0;BLf/ge0;)Ljava/lang/Runnable;
/*    */     //   294: invokespecial <init> : (Lf/JG0;Ljava/lang/Runnable;)V
/*    */     //   297: iconst_1
/*    */     //   298: putfield sD0 : Z
/*    */     //   301: invokevirtual uh : (Lf/h70;)V
/*    */     //   304: return
/*    */     // Line number table:
/*    */     //   Java source line number -> byte code offset
/*    */     //   #1	-> 1
/*    */     //   #2	-> 5
/*    */     //   #3	-> 17
/*    */     //   #4	-> 20
/*    */     //   #5	-> 61
/*    */     //   #6	-> 70
/*    */     //   #7	-> 105
/*    */     //   #8	-> 113
/*    */     //   #9	-> 118
/*    */     //   #10	-> 138
/*    */     //   #11	-> 141
/*    */     //   #12	-> 149
/*    */     //   #13	-> 271
/*    */     //   #14	-> 274
/*    */     //   #15	-> 294
/*    */     //   #16	-> 298
/*    */     //   #17	-> 301
/*    */   }
/*    */   
/*    */   public final void d40() {
/*    */     if (km.XU())
/*    */       QI(); 
/*    */     super.d40();
/*    */     if (km.ER() && km.XU()) {
/*    */       this.wa.mM();
/*    */       this.wa.QJ0(et.t9, -68, 0);
/*    */     } 
/*    */   }
/*    */   
/*    */   public wL() {
/*    */     super(km.XU(), false);
/*    */     TG0(this::close);
/*    */     EP(1);
/*    */     jJ0(false);
/*    */     Xu("rom-panel");
/*    */     PX pX;
/*    */     if (!km.iE0.wG0(pX = PX.vr))
/*    */       js.N2().Pu(10000, km.iE0.MK(pX)); 
/*    */     r90();
/*    */   }
/*    */   
/*    */   private void UL0(RD0 paramRD01, RD0 paramRD02, RD0 paramRD03, byte paramByte, ge0 paramge0) {
/*    */     // Byte code:
/*    */     //   0: aload_0
/*    */     //   1: aload_1
/*    */     //   2: aload_2
/*    */     //   3: aload_0
/*    */     //   4: new f/O90
/*    */     //   7: dup
/*    */     //   8: dup
/*    */     //   9: astore_0
/*    */     //   10: getstatic f/js.iK : Lf/ik;
/*    */     //   13: pop
/*    */     //   14: sipush #1142
/*    */     //   17: invokestatic OH0 : (I)Ljava/lang/String;
/*    */     //   20: invokespecial <init> : (Ljava/lang/String;)V
/*    */     //   23: putfield WI : Lf/O90;
/*    */     //   26: getstatic f/js.vu0 : Lf/js;
/*    */     //   29: dup
/*    */     //   30: aload_0
/*    */     //   31: swap
/*    */     //   32: invokevirtual Ub : ()I
/*    */     //   35: invokevirtual si : (Lf/JG0;I)V
/*    */     //   38: getstatic f/A1.L7 : Lf/A1;
/*    */     //   41: astore_0
/*    */     //   42: aload_3
/*    */     //   43: iload #4
/*    */     //   45: aload #5
/*    */     //   47: <illegal opcode> run : (Lf/wL;Lf/RD0;Lf/RD0;Lf/RD0;BLf/ge0;)Ljava/lang/Runnable;
/*    */     //   52: aload_0
/*    */     //   53: getfield nc : Lf/cK0;
/*    */     //   56: swap
/*    */     //   57: invokevirtual execute : (Ljava/lang/Runnable;)V
/*    */     //   60: return
/*    */     // Line number table:
/*    */     //   Java source line number -> byte code offset
/*    */     //   #1	-> 10
/*    */     //   #2	-> 17
/*    */     //   #3	-> 26
/*    */     //   #4	-> 32
/*    */     //   #5	-> 35
/*    */     //   #6	-> 38
/*    */     //   #7	-> 47
/*    */     //   #8	-> 53
/*    */     //   #9	-> 57
/*    */   }
/*    */   
/*    */   private void mA(RD0 paramRD01, RD0 paramRD02, RD0 paramRD03, byte paramByte, ge0 paramge0) {
/*    */     O90 o90;
/*    */     JG0 jG0;
/*    */     InputStream inputStream = null;
/*    */     OutputStream outputStream = null;
/*    */     try {
/*    */       long l1;
/*    */       byte[] arrayOfByte;
/*    */       long l2;
/*    */       int i;
/*    */       for (inputStream = paramRD01.Yc(), outputStream = paramRD02.hh(), l1 = paramRD01.tN(), arrayOfByte = new byte[1024], l2 = 0L; (i = inputStream.read(arrayOfByte)) != -1; ) {
/*    */         this.lw = (float)(l2 += i) / (float)l1;
/*    */         outputStream.write(arrayOfByte, 0, i);
/*    */       } 
/*    */       inputStream.close();
/*    */       outputStream.close();
/*    */       if (!km.iE0.Qz(paramRD02.bo())) {
/*    */         UB0.Kg0.fN(paramRD02::ni);
/*    */         Ui.JC0(inputStream);
/*    */         Ui.JC0(outputStream);
/*    */         return;
/*    */       } 
/*    */       (new RD0(paramRD02.bo())).mp(paramRD03);
/*    */       Ui.JC0(inputStream);
/*    */       Ui.JC0(outputStream);
/*    */       if ((jG0 = (o90 = this.WI).fr0) != null)
/*    */         jG0.jf0(o90); 
/*    */       this.WI = null;
/*    */       String str = paramRD03.bo().getAbsolutePath().replace("_import", "");
/*    */       switch (paramByte) {
/*    */         case 4:
/*    */           h1.h0 = this;
/*    */           break;
/*    */         case 3:
/*    */           h1.Re0 = this;
/*    */           break;
/*    */         case 2:
/*    */           h1.yD0 = this;
/*    */           break;
/*    */         case 1:
/*    */           h1.Vh = this;
/*    */           break;
/*    */         case 0:
/*    */           h1.Pq = this;
/*    */           break;
/*    */       } 
/*    */       h1.Td();
/*    */       if (paramge0.TG0.nm0())
/*    */         paramRD01.La0(); 
/*    */       return;
/*    */     } catch (Exception exception) {
/*    */       AJ0.error("", this);
/*    */       o90.La0();
/*    */       paramRD03.La0();
/*    */       UB0.Kg0.fN(wL::en0);
/*    */       Ui.JC0((Closeable)jG0);
/*    */       Ui.JC0(outputStream);
/*    */       return;
/*    */     } finally {}
/*    */     Ui.JC0((Closeable)jG0);
/*    */     Ui.JC0(outputStream);
/*    */     throw this;
/*    */   }
/*    */   
/*    */   public static void en0() {
/*    */     js.vu0.Pu(-1, Ml0.OH0(1143));
/*    */   }
/*    */   
/*    */   public static void ni(RD0 paramRD0) {
/*    */     js.vu0.DJ(Ml0.Go(1094, paramRD0.bo().getAbsolutePath()), null);
/*    */   }
/*    */   
/*    */   private void sX() {
/*    */     O90 o90;
/*    */     JG0 jG0;
/*    */     if ((jG0 = (o90 = this.WI).fr0) != null)
/*    */       jG0.jf0(o90); 
/*    */     this.WI = null;
/*    */   }
/*    */   
/*    */   private void Zz() {
/*    */     this.cO = true;
/*    */     cE.eo0.getClass();
/*    */     if (km.ER()) {
/*    */       RD0[] arrayOfRD0;
/*    */       int i;
/*    */       byte b;
/*    */       for (i = (arrayOfRD0 = UB0.vj0.N0("data/strings").XX(".xml")).length, b = 0; b < i; ) {
/*    */         this[b].La0();
/*    */         b++;
/*    */       } 
/*    */     } 
/*    */     js.vu0.DJ(Ml0.OH0(1165), null);
/*    */   }
/*    */   
/*    */   private boolean IP(RD0 paramRD0) {
/*    */     // Byte code:
/*    */     //   0: getstatic f/cE.eo0 : Lf/cE;
/*    */     //   3: invokevirtual getClass : ()Ljava/lang/Class;
/*    */     //   6: pop
/*    */     //   7: new f/cn0
/*    */     //   10: dup
/*    */     //   11: dup
/*    */     //   12: astore_2
/*    */     //   13: aload_1
/*    */     //   14: invokespecial <init> : (Lf/RD0;)V
/*    */     //   17: getfield dG0 : Z
/*    */     //   20: ifeq -> 29
/*    */     //   23: goto -> 31
/*    */     //   26: invokevirtual printStackTrace : ()V
/*    */     //   29: aconst_null
/*    */     //   30: astore_2
/*    */     //   31: aload_2
/*    */     //   32: dup
/*    */     //   33: aconst_null
/*    */     //   34: invokevirtual zJ0 : (Lf/YK0;)V
/*    */     //   37: getfield dG0 : Z
/*    */     //   40: ifne -> 46
/*    */     //   43: goto -> 84
/*    */     //   46: aload_1
/*    */     //   47: getstatic f/UB0.vj0 : Lf/XG;
/*    */     //   50: new java/lang/StringBuilder
/*    */     //   53: dup
/*    */     //   54: invokespecial <init> : ()V
/*    */     //   57: ldc_w 'data/strings/'
/*    */     //   60: invokevirtual append : (Ljava/lang/String;)Ljava/lang/StringBuilder;
/*    */     //   63: aload_2
/*    */     //   64: invokevirtual cF : ()Ljava/lang/String;
/*    */     //   67: invokevirtual append : (Ljava/lang/String;)Ljava/lang/StringBuilder;
/*    */     //   70: invokevirtual toString : ()Ljava/lang/String;
/*    */     //   73: invokevirtual N0 : (Ljava/lang/String;)Lf/hZ;
/*    */     //   76: invokevirtual S2 : (Lf/RD0;)V
/*    */     //   79: iconst_1
/*    */     //   80: goto -> 85
/*    */     //   83: pop
/*    */     //   84: iconst_0
/*    */     //   85: ifeq -> 109
/*    */     //   88: aload_0
/*    */     //   89: getstatic f/js.vu0 : Lf/js;
/*    */     //   92: sipush #1164
/*    */     //   95: invokestatic OH0 : (I)Ljava/lang/String;
/*    */     //   98: aconst_null
/*    */     //   99: invokevirtual DJ : (Ljava/lang/String;Ljava/lang/Runnable;)V
/*    */     //   102: iconst_1
/*    */     //   103: putfield cO : Z
/*    */     //   106: goto -> 122
/*    */     //   109: getstatic f/js.vu0 : Lf/js;
/*    */     //   112: sipush #1166
/*    */     //   115: invokestatic OH0 : (I)Ljava/lang/String;
/*    */     //   118: aconst_null
/*    */     //   119: invokevirtual DJ : (Ljava/lang/String;Ljava/lang/Runnable;)V
/*    */     //   122: iconst_0
/*    */     //   123: ireturn
/*    */     // Line number table:
/*    */     //   Java source line number -> byte code offset
/*    */     //   #1	-> 0
/*    */     //   #2	-> 3
/*    */     //   #3	-> 7
/*    */     //   #4	-> 17
/*    */     //   #5	-> 26
/*    */     //   #6	-> 34
/*    */     //   #7	-> 37
/*    */     //   #8	-> 47
/*    */     //   #9	-> 89
/*    */     //   #10	-> 95
/*    */     //   #11	-> 99
/*    */     //   #12	-> 103
/*    */     //   #13	-> 109
/*    */     //   #14	-> 115
/*    */     //   #15	-> 119
/*    */     // Exception table:
/*    */     //   from	to	target	type
/*    */     //   7	10	26	java/lang/Exception
/*    */     //   13	20	26	java/lang/Exception
/*    */     //   26	29	83	java/lang/Exception
/*    */     //   31	40	83	java/lang/Exception
/*    */     //   46	79	83	java/lang/Exception
/*    */   }
/*    */   
/*    */   private void yh(byte paramByte, String paramString) {
/*    */     if (paramByte == 0 || paramByte == 1) {
/*    */       s40 s40;
/*    */       if ((s40 = km.mI0.Sa(paramByte)) == null) {
/*    */         js.vu0.DJ(Ml0.Go(1186, paramString), null);
/*    */         return;
/*    */       } 
/*    */       String str = this.wJ.class;
/*    */       Ex0(this.Kf0, this);
/*    */     } 
/*    */     if (paramByte == 2) {
/*    */       Wo wo;
/*    */       if ((wo = km.mI0.AN) == null) {
/*    */         js.vu0.DJ(Ml0.Go(1186, paramString), null);
/*    */         return;
/*    */       } 
/*    */       Ex0(this.Zo, paramString);
/*    */     } 
/*    */     if (paramByte == 3) {
/*    */       gD gD;
/*    */       if ((gD = km.mI0.MT) == null) {
/*    */         js.vu0.DJ(Ml0.Go(1186, paramString), null);
/*    */         return;
/*    */       } 
/*    */       Ex0(this.Zo, paramString);
/*    */     } 
/*    */     if (paramByte == 4) {
/*    */       BE bE;
/*    */       if ((bE = km.mI0.yE) == null) {
/*    */         js.vu0.DJ(Ml0.Go(1186, paramString), null);
/*    */         return;
/*    */       } 
/*    */       Ex0(this.Zo, paramString);
/*    */     } 
/*    */   }
/*    */   
/*    */   private boolean r20(byte paramByte, RD0 paramRD0) {
/*    */     // Byte code:
/*    */     //   0: aload_2
/*    */     //   1: sipush #255
/*    */     //   4: dup
/*    */     //   5: istore_3
/*    */     //   6: newarray byte
/*    */     //   8: dup
/*    */     //   9: astore #4
/*    */     //   11: iload_3
/*    */     //   12: invokevirtual m30 : ([BI)V
/*    */     //   15: getstatic f/D5.rk : Ljava/util/ArrayList;
/*    */     //   18: invokevirtual iterator : ()Ljava/util/Iterator;
/*    */     //   21: astore #5
/*    */     //   23: aload #5
/*    */     //   25: invokeinterface hasNext : ()Z
/*    */     //   30: ifeq -> 109
/*    */     //   33: iload_3
/*    */     //   34: aload #5
/*    */     //   36: invokeinterface next : ()Ljava/lang/Object;
/*    */     //   41: checkcast f/WY
/*    */     //   44: dup
/*    */     //   45: dup
/*    */     //   46: astore #6
/*    */     //   48: invokevirtual getClass : ()Ljava/lang/Class;
/*    */     //   51: pop
/*    */     //   52: getfield br0 : [B
/*    */     //   55: arraylength
/*    */     //   56: if_icmpge -> 62
/*    */     //   59: goto -> 92
/*    */     //   62: iconst_0
/*    */     //   63: istore #7
/*    */     //   65: iload #7
/*    */     //   67: aload #6
/*    */     //   69: getfield br0 : [B
/*    */     //   72: dup
/*    */     //   73: astore #8
/*    */     //   75: arraylength
/*    */     //   76: if_icmpge -> 102
/*    */     //   79: aload #8
/*    */     //   81: iload #7
/*    */     //   83: baload
/*    */     //   84: aload #4
/*    */     //   86: iload #7
/*    */     //   88: baload
/*    */     //   89: if_icmpeq -> 96
/*    */     //   92: iconst_0
/*    */     //   93: goto -> 103
/*    */     //   96: iinc #7, 1
/*    */     //   99: goto -> 65
/*    */     //   102: iconst_1
/*    */     //   103: ifeq -> 23
/*    */     //   106: goto -> 112
/*    */     //   109: aconst_null
/*    */     //   110: astore #6
/*    */     //   112: aload #6
/*    */     //   114: ifnull -> 163
/*    */     //   117: aload #6
/*    */     //   119: getfield sB : Z
/*    */     //   122: ifne -> 146
/*    */     //   125: getstatic f/js.vu0 : Lf/js;
/*    */     //   128: aload #6
/*    */     //   130: getfield QG0 : Ljava/lang/String;
/*    */     //   133: sipush #1089
/*    */     //   136: swap
/*    */     //   137: invokestatic Go : (ILjava/lang/String;)Ljava/lang/String;
/*    */     //   140: aconst_null
/*    */     //   141: invokevirtual DJ : (Ljava/lang/String;Ljava/lang/Runnable;)V
/*    */     //   144: iconst_0
/*    */     //   145: ireturn
/*    */     //   146: aload_0
/*    */     //   147: dup
/*    */     //   148: iload_1
/*    */     //   149: <illegal opcode> accept : (Lf/wL;B)Ljava/util/function/Consumer;
/*    */     //   154: astore_0
/*    */     //   155: aload_2
/*    */     //   156: iload_1
/*    */     //   157: aload_0
/*    */     //   158: invokevirtual Ol0 : (Lf/RD0;BLjava/util/function/Consumer;)V
/*    */     //   161: iconst_0
/*    */     //   162: ireturn
/*    */     //   163: aload_0
/*    */     //   164: aload_2
/*    */     //   165: iload_1
/*    */     //   166: iconst_0
/*    */     //   167: invokevirtual tr : (Lf/RD0;BZ)Z
/*    */     //   170: ireturn
/*    */     // Line number table:
/*    */     //   Java source line number -> byte code offset
/*    */     //   #1	-> 6
/*    */     //   #2	-> 15
/*    */     //   #3	-> 52
/*    */     //   #4	-> 119
/*    */     //   #5	-> 125
/*    */     //   #6	-> 130
/*    */     //   #7	-> 137
/*    */     //   #8	-> 141
/*    */     //   #9	-> 149
/*    */   }
/*    */   
/*    */   private void dO(String[] paramArrayOfString, W1 paramW1) {
/*    */     h1.pB0 = str;
/*    */     h1.p0 = true;
/*    */     h1.Td();
/*    */     this.cO = true;
/*    */     r90();
/*    */     Wx wx;
/*    */     js js;
/*    */     String str;
/*    */     if ((str = paramArrayOfString[paramW1.Wa0.go]) != null && !h1.pB0.equalsIgnoreCase(str) && cE.eo0.sG(str) && (js = js.vu0) != null && (wx = this.Dj0) != null)
/*    */       Og0(); 
/*    */   }
/*    */   
/*    */   public static void A00() {
/*    */     if (km.w5) {
/*    */       km.w5 = false;
/*    */     } else {
/*    */       km.w5 = true;
/*    */     } 
/*    */     js.vu0.Pu(-1, Ml0.OH0(1087));
/*    */   }
/*    */   
/*    */   public static void Ex0(RD0 paramRD0, String paramString) {
/*    */     String arrayOfString1[], str;
/*    */     if ((str = paramRD0.toString()) == null || str.isEmpty()) {
/*    */       (arrayOfString1 = new String[2])[0] = paramString;
/*    */       (new String[2])[1] = "UNKNOWN";
/*    */       js.vu0.DJ(Ml0.sB(1185, arrayOfString1), null);
/*    */       return;
/*    */     } 
/*    */     String[] arrayOfString2;
/*    */     (arrayOfString2 = new String[3])[0] = paramString;
/*    */     (new String[3])[1] = (String)arrayOfString1;
/*    */     (new String[3])[2] = "--";
/*    */     js.vu0.DJ(Ml0.sB(1185, arrayOfString2), null);
/*    */   } }


/* Location:              /Users/vnnsnnt/Documents/Codespace/JavaWorkspace/RedTrainer/src/main/java/org/trainer/client/PokeMMO.jar!/f/wL.class
 * Java compiler version: 8 (52.0)
 * JD-Core Version:       1.1.3
 */