package f;

public final class wp extends ZK0 {
  public static final byte[][] X90;
  
  static {
    byte[] arrayOfByte;
    (arrayOfByte = new byte[6])[0] = 1;
    (new byte[6])[1] = 2;
    (new byte[6])[2] = 15;
    (new byte[6])[3] = 2;
    (new byte[6])[4] = -2;
    (new byte[6])[5] = 2;
    (new byte[69][])[0] = arrayOfByte;
    (arrayOfByte = new byte[6])[0] = 2;
    (new byte[6])[1] = 2;
    (new byte[6])[2] = 15;
    (new byte[6])[3] = 3;
    (new byte[6])[4] = -2;
    (new byte[6])[5] = 2;
    (new byte[69][])[1] = arrayOfByte;
    (arrayOfByte = new byte[6])[0] = 4;
    (new byte[6])[1] = 2;
    (new byte[6])[2] = 15;
    (new byte[6])[3] = 5;
    (new byte[6])[4] = -2;
    (new byte[6])[5] = 2;
    (new byte[69][])[2] = arrayOfByte;
    (arrayOfByte = new byte[6])[0] = 5;
    (new byte[6])[1] = 2;
    (new byte[6])[2] = 15;
    (new byte[6])[3] = 6;
    (new byte[6])[4] = -2;
    (new byte[6])[5] = 2;
    (new byte[69][])[3] = arrayOfByte;
    (arrayOfByte = new byte[6])[0] = 7;
    (new byte[6])[1] = 2;
    (new byte[6])[2] = 15;
    (new byte[6])[3] = 8;
    (new byte[6])[4] = -2;
    (new byte[6])[5] = 2;
    (new byte[69][])[4] = arrayOfByte;
    (arrayOfByte = new byte[6])[0] = 8;
    (new byte[6])[1] = 2;
    (new byte[6])[2] = 15;
    (new byte[6])[3] = 9;
    (new byte[6])[4] = -2;
    (new byte[6])[5] = 2;
    (new byte[69][])[5] = arrayOfByte;
    (arrayOfByte = new byte[6])[0] = 0;
    (new byte[6])[1] = 2;
    (new byte[6])[2] = 16;
    (new byte[6])[3] = 10;
    (new byte[6])[4] = -2;
    (new byte[6])[5] = 2;
    (new byte[69][])[6] = arrayOfByte;
    (arrayOfByte = new byte[6])[0] = 1;
    (new byte[6])[1] = 2;
    (new byte[6])[2] = 16;
    (new byte[6])[3] = 1;
    (new byte[6])[4] = -2;
    (new byte[6])[5] = 3;
    (new byte[69][])[7] = arrayOfByte;
    (arrayOfByte = new byte[6])[0] = 0;
    (new byte[6])[1] = 2;
    (new byte[6])[2] = 17;
    (new byte[6])[3] = 1;
    (new byte[6])[4] = -2;
    (new byte[6])[5] = 4;
    (new byte[69][])[8] = arrayOfByte;
    (arrayOfByte = new byte[6])[0] = 1;
    (new byte[6])[1] = 2;
    (new byte[6])[2] = 17;
    (new byte[6])[3] = 2;
    (new byte[6])[4] = -2;
    (new byte[6])[5] = 4;
    (new byte[69][])[9] = arrayOfByte;
    (arrayOfByte = new byte[6])[0] = 2;
    (new byte[6])[1] = 2;
    (new byte[6])[2] = 17;
    (new byte[6])[3] = 3;
    (new byte[6])[4] = -2;
    (new byte[6])[5] = 4;
    (new byte[69][])[10] = arrayOfByte;
    (arrayOfByte = new byte[6])[0] = 1;
    (new byte[6])[1] = 2;
    (new byte[6])[2] = 19;
    (new byte[6])[3] = 2;
    (new byte[6])[4] = -2;
    (new byte[6])[5] = 6;
    (new byte[69][])[11] = arrayOfByte;
    (arrayOfByte = new byte[6])[0] = 2;
    (new byte[6])[1] = 2;
    (new byte[6])[2] = 19;
    (new byte[6])[3] = 3;
    (new byte[6])[4] = -2;
    (new byte[6])[5] = 6;
    (new byte[69][])[12] = arrayOfByte;
    (arrayOfByte = new byte[6])[0] = 3;
    (new byte[6])[1] = 2;
    (new byte[6])[2] = 19;
    (new byte[6])[3] = 4;
    (new byte[6])[4] = -2;
    (new byte[6])[5] = 6;
    (new byte[69][])[13] = arrayOfByte;
    (arrayOfByte = new byte[6])[0] = 4;
    (new byte[6])[1] = 2;
    (new byte[6])[2] = 19;
    (new byte[6])[3] = 5;
    (new byte[6])[4] = -2;
    (new byte[6])[5] = 6;
    (new byte[69][])[14] = arrayOfByte;
    (arrayOfByte = new byte[6])[0] = 5;
    (new byte[6])[1] = 2;
    (new byte[6])[2] = 19;
    (new byte[6])[3] = 6;
    (new byte[6])[4] = -2;
    (new byte[6])[5] = 6;
    (new byte[69][])[15] = arrayOfByte;
    (arrayOfByte = new byte[6])[0] = 6;
    (new byte[6])[1] = 2;
    (new byte[6])[2] = 19;
    (new byte[6])[3] = 7;
    (new byte[6])[4] = -2;
    (new byte[6])[5] = 6;
    (new byte[69][])[16] = arrayOfByte;
    (arrayOfByte = new byte[6])[0] = 7;
    (new byte[6])[1] = 2;
    (new byte[6])[2] = 19;
    (new byte[6])[3] = 8;
    (new byte[6])[4] = -2;
    (new byte[6])[5] = 6;
    (new byte[69][])[17] = arrayOfByte;
    (arrayOfByte = new byte[6])[0] = 8;
    (new byte[6])[1] = 2;
    (new byte[6])[2] = 19;
    (new byte[6])[3] = 9;
    (new byte[6])[4] = -2;
    (new byte[6])[5] = 6;
    (new byte[69][])[18] = arrayOfByte;
    (arrayOfByte = new byte[6])[0] = 9;
    (new byte[6])[1] = 2;
    (new byte[6])[2] = 19;
    (new byte[6])[3] = 10;
    (new byte[6])[4] = -2;
    (new byte[6])[5] = 6;
    (new byte[69][])[19] = arrayOfByte;
    (arrayOfByte = new byte[6])[0] = 1;
    (new byte[6])[1] = 2;
    (new byte[6])[2] = 20;
    (new byte[6])[3] = 2;
    (new byte[6])[4] = -2;
    (new byte[6])[5] = 12;
    (new byte[69][])[20] = arrayOfByte;
    (arrayOfByte = new byte[6])[0] = 2;
    (new byte[6])[1] = 2;
    (new byte[6])[2] = 20;
    (new byte[6])[3] = 3;
    (new byte[6])[4] = -2;
    (new byte[6])[5] = 12;
    (new byte[69][])[21] = arrayOfByte;
    (arrayOfByte = new byte[6])[0] = 3;
    (new byte[6])[1] = 2;
    (new byte[6])[2] = 20;
    (new byte[6])[3] = 4;
    (new byte[6])[4] = -2;
    (new byte[6])[5] = 12;
    (new byte[69][])[22] = arrayOfByte;
    (arrayOfByte = new byte[6])[0] = 4;
    (new byte[6])[1] = 2;
    (new byte[6])[2] = 20;
    (new byte[6])[3] = 5;
    (new byte[6])[4] = -2;
    (new byte[6])[5] = 12;
    (new byte[69][])[23] = arrayOfByte;
    (arrayOfByte = new byte[6])[0] = 5;
    (new byte[6])[1] = 2;
    (new byte[6])[2] = 20;
    (new byte[6])[3] = 6;
    (new byte[6])[4] = -2;
    (new byte[6])[5] = 12;
    (new byte[69][])[24] = arrayOfByte;
    (arrayOfByte = new byte[6])[0] = 6;
    (new byte[6])[1] = 2;
    (new byte[6])[2] = 20;
    (new byte[6])[3] = 7;
    (new byte[6])[4] = -2;
    (new byte[6])[5] = 12;
    (new byte[69][])[25] = arrayOfByte;
    (arrayOfByte = new byte[6])[0] = 7;
    (new byte[6])[1] = 2;
    (new byte[6])[2] = 20;
    (new byte[6])[3] = 8;
    (new byte[6])[4] = -2;
    (new byte[6])[5] = 12;
    (new byte[69][])[26] = arrayOfByte;
    (arrayOfByte = new byte[6])[0] = 9;
    (new byte[6])[1] = 2;
    (new byte[6])[2] = 20;
    (new byte[6])[3] = 1;
    (new byte[6])[4] = -2;
    (new byte[6])[5] = 11;
    (new byte[69][])[27] = arrayOfByte;
    (arrayOfByte = new byte[6])[0] = 10;
    (new byte[6])[1] = 2;
    (new byte[6])[2] = 20;
    (new byte[6])[3] = 2;
    (new byte[6])[4] = -2;
    (new byte[6])[5] = 11;
    (new byte[69][])[28] = arrayOfByte;
    (arrayOfByte = new byte[6])[0] = 5;
    (new byte[6])[1] = 2;
    (new byte[6])[2] = 21;
    (new byte[6])[3] = 6;
    (new byte[6])[4] = -1;
    (new byte[6])[5] = 13;
    (new byte[69][])[29] = arrayOfByte;
    (arrayOfByte = new byte[6])[0] = 6;
    (new byte[6])[1] = 2;
    (new byte[6])[2] = 21;
    (new byte[6])[3] = 7;
    (new byte[6])[4] = -1;
    (new byte[6])[5] = 13;
    (new byte[69][])[30] = arrayOfByte;
    (arrayOfByte = new byte[6])[0] = 0;
    (new byte[6])[1] = 2;
    (new byte[6])[2] = 22;
    (new byte[6])[3] = 8;
    (new byte[6])[4] = -1;
    (new byte[6])[5] = 13;
    (new byte[69][])[31] = arrayOfByte;
    (arrayOfByte = new byte[6])[0] = 5;
    (new byte[6])[1] = 2;
    (new byte[6])[2] = 27;
    (new byte[6])[3] = 7;
    (new byte[6])[4] = -1;
    (new byte[6])[5] = 19;
    (new byte[69][])[32] = arrayOfByte;
    (arrayOfByte = new byte[6])[0] = 6;
    (new byte[6])[1] = 2;
    (new byte[6])[2] = 27;
    (new byte[6])[3] = 8;
    (new byte[6])[4] = -1;
    (new byte[6])[5] = 19;
    (new byte[69][])[33] = arrayOfByte;
    (arrayOfByte = new byte[6])[0] = 0;
    (new byte[6])[1] = 3;
    (new byte[6])[2] = 38;
    (new byte[6])[3] = 8;
    (new byte[6])[4] = -1;
    (new byte[6])[5] = 20;
    (new byte[69][])[34] = arrayOfByte;
    (arrayOfByte = new byte[6])[0] = 0;
    (new byte[6])[1] = 3;
    (new byte[6])[2] = 39;
    (new byte[6])[3] = 2;
    (new byte[6])[4] = -1;
    (new byte[6])[5] = 20;
    (new byte[69][])[35] = arrayOfByte;
    (arrayOfByte = new byte[6])[0] = 1;
    (new byte[6])[1] = 3;
    (new byte[6])[2] = 39;
    (new byte[6])[3] = 3;
    (new byte[6])[4] = -1;
    (new byte[6])[5] = 20;
    (new byte[69][])[36] = arrayOfByte;
    (arrayOfByte = new byte[6])[0] = 2;
    (new byte[6])[1] = 3;
    (new byte[6])[2] = 39;
    (new byte[6])[3] = 4;
    (new byte[6])[4] = -1;
    (new byte[6])[5] = 20;
    (new byte[69][])[37] = arrayOfByte;
    (arrayOfByte = new byte[6])[0] = 3;
    (new byte[6])[1] = 3;
    (new byte[6])[2] = 39;
    (new byte[6])[3] = 5;
    (new byte[6])[4] = -1;
    (new byte[6])[5] = 20;
    (new byte[69][])[38] = arrayOfByte;
    (arrayOfByte = new byte[6])[0] = 4;
    (new byte[6])[1] = 3;
    (new byte[6])[2] = 39;
    (new byte[6])[3] = 6;
    (new byte[6])[4] = -1;
    (new byte[6])[5] = 20;
    (new byte[69][])[39] = arrayOfByte;
    (arrayOfByte = new byte[6])[0] = 5;
    (new byte[6])[1] = 3;
    (new byte[6])[2] = 39;
    (new byte[6])[3] = 7;
    (new byte[6])[4] = -1;
    (new byte[6])[5] = 20;
    (new byte[69][])[40] = arrayOfByte;
    (arrayOfByte = new byte[6])[0] = 0;
    (new byte[6])[1] = 2;
    (new byte[6])[2] = 42;
    (new byte[6])[3] = 4;
    (new byte[6])[4] = 0;
    (new byte[6])[5] = 31;
    (new byte[69][])[41] = arrayOfByte;
    (arrayOfByte = new byte[6])[0] = 1;
    (new byte[6])[1] = 2;
    (new byte[6])[2] = 42;
    (new byte[6])[3] = 0;
    (new byte[6])[4] = 0;
    (new byte[6])[5] = 32;
    (new byte[69][])[42] = arrayOfByte;
    (arrayOfByte = new byte[6])[0] = 0;
    (new byte[6])[1] = 2;
    (new byte[6])[2] = 44;
    (new byte[6])[3] = 4;
    (new byte[6])[4] = 0;
    (new byte[6])[5] = 35;
    (new byte[69][])[43] = arrayOfByte;
    (arrayOfByte = new byte[6])[0] = 1;
    (new byte[6])[1] = 2;
    (new byte[6])[2] = 44;
    (new byte[6])[3] = 0;
    (new byte[6])[4] = 0;
    (new byte[6])[5] = 34;
    (new byte[69][])[44] = arrayOfByte;
    (arrayOfByte = new byte[6])[0] = 2;
    (new byte[6])[1] = 2;
    (new byte[6])[2] = 44;
    (new byte[6])[3] = 2;
    (new byte[6])[4] = 0;
    (new byte[6])[5] = 34;
    (new byte[69][])[45] = arrayOfByte;
    (arrayOfByte = new byte[6])[0] = 3;
    (new byte[6])[1] = 2;
    (new byte[6])[2] = 44;
    (new byte[6])[3] = 0;
    (new byte[6])[4] = 0;
    (new byte[6])[5] = 31;
    (new byte[69][])[46] = arrayOfByte;
    (arrayOfByte = new byte[6])[0] = 0;
    (new byte[6])[1] = 2;
    (new byte[6])[2] = 48;
    (new byte[6])[3] = 5;
    (new byte[6])[4] = 0;
    (new byte[6])[5] = 39;
    (new byte[69][])[47] = arrayOfByte;
    (arrayOfByte = new byte[6])[0] = 1;
    (new byte[6])[1] = 2;
    (new byte[6])[2] = 48;
    (new byte[6])[3] = 0;
    (new byte[6])[4] = 0;
    (new byte[6])[5] = 38;
    (new byte[69][])[48] = arrayOfByte;
    (arrayOfByte = new byte[6])[0] = 0;
    (new byte[6])[1] = 2;
    (new byte[6])[2] = 49;
    (new byte[6])[3] = 1;
    (new byte[6])[4] = 0;
    (new byte[6])[5] = 39;
    (new byte[69][])[49] = arrayOfByte;
    (arrayOfByte = new byte[6])[0] = 1;
    (new byte[6])[1] = 2;
    (new byte[6])[2] = 49;
    (new byte[6])[3] = 2;
    (new byte[6])[4] = 0;
    (new byte[6])[5] = 39;
    (new byte[69][])[50] = arrayOfByte;
    (arrayOfByte = new byte[6])[0] = 2;
    (new byte[6])[1] = 2;
    (new byte[6])[2] = 49;
    (new byte[6])[3] = 3;
    (new byte[6])[4] = 0;
    (new byte[6])[5] = 39;
    (new byte[69][])[51] = arrayOfByte;
    (arrayOfByte = new byte[6])[0] = 3;
    (new byte[6])[1] = 2;
    (new byte[6])[2] = 49;
    (new byte[6])[3] = 4;
    (new byte[6])[4] = 0;
    (new byte[6])[5] = 39;
    (new byte[69][])[52] = arrayOfByte;
    (arrayOfByte = new byte[6])[0] = 0;
    (new byte[6])[1] = 2;
    (new byte[6])[2] = 54;
    (new byte[6])[3] = 1;
    (new byte[6])[4] = -1;
    (new byte[6])[5] = 43;
    (new byte[69][])[53] = arrayOfByte;
    (arrayOfByte = new byte[6])[0] = 0;
    (new byte[6])[1] = 2;
    (new byte[6])[2] = 55;
    (new byte[6])[3] = 2;
    (new byte[6])[4] = -1;
    (new byte[6])[5] = 43;
    (new byte[69][])[54] = arrayOfByte;
    (arrayOfByte = new byte[6])[0] = 1;
    (new byte[6])[1] = 2;
    (new byte[6])[2] = 55;
    (new byte[6])[3] = 3;
    (new byte[6])[4] = -1;
    (new byte[6])[5] = 43;
    (new byte[69][])[55] = arrayOfByte;
    (arrayOfByte = new byte[6])[0] = 3;
    (new byte[6])[1] = 2;
    (new byte[6])[2] = 55;
    (new byte[6])[3] = 1;
    (new byte[6])[4] = -1;
    (new byte[6])[5] = 63;
    (new byte[69][])[56] = arrayOfByte;
    (arrayOfByte = new byte[6])[0] = 0;
    (new byte[6])[1] = 2;
    (new byte[6])[2] = 56;
    (new byte[6])[3] = 2;
    (new byte[6])[4] = -1;
    (new byte[6])[5] = 63;
    (new byte[69][])[57] = arrayOfByte;
    (arrayOfByte = new byte[6])[0] = 0;
    (new byte[6])[1] = 2;
    (new byte[6])[2] = 57;
    (new byte[6])[3] = 3;
    (new byte[6])[4] = -1;
    (new byte[6])[5] = 63;
    (new byte[69][])[58] = arrayOfByte;
    (arrayOfByte = new byte[6])[0] = 0;
    (new byte[6])[1] = 2;
    (new byte[6])[2] = 59;
    (new byte[6])[3] = 1;
    (new byte[6])[4] = -1;
    (new byte[6])[5] = 49;
    (new byte[69][])[59] = arrayOfByte;
    (arrayOfByte = new byte[6])[0] = 1;
    (new byte[6])[1] = 2;
    (new byte[6])[2] = 59;
    (new byte[6])[3] = 2;
    (new byte[6])[4] = -1;
    (new byte[6])[5] = 49;
    (new byte[69][])[60] = arrayOfByte;
    (arrayOfByte = new byte[6])[0] = 2;
    (new byte[6])[1] = 2;
    (new byte[6])[2] = 59;
    (new byte[6])[3] = 3;
    (new byte[6])[4] = -1;
    (new byte[6])[5] = 49;
    (new byte[69][])[61] = arrayOfByte;
    (arrayOfByte = new byte[6])[0] = 2;
    (new byte[6])[1] = 2;
    (new byte[6])[2] = 61;
    (new byte[6])[3] = 1;
    (new byte[6])[4] = -1;
    (new byte[6])[5] = 57;
    (new byte[69][])[62] = arrayOfByte;
    (arrayOfByte = new byte[6])[0] = 3;
    (new byte[6])[1] = 2;
    (new byte[6])[2] = 61;
    (new byte[6])[3] = 2;
    (new byte[6])[4] = -1;
    (new byte[6])[5] = 57;
    (new byte[69][])[63] = arrayOfByte;
    (arrayOfByte = new byte[6])[0] = 1;
    (new byte[6])[1] = 2;
    (new byte[6])[2] = 62;
    (new byte[6])[3] = 2;
    (new byte[6])[4] = -1;
    (new byte[6])[5] = 59;
    (new byte[69][])[64] = arrayOfByte;
    (arrayOfByte = new byte[6])[0] = 2;
    (new byte[6])[1] = 2;
    (new byte[6])[2] = 62;
    (new byte[6])[3] = 3;
    (new byte[6])[4] = -1;
    (new byte[6])[5] = 59;
    (new byte[69][])[65] = arrayOfByte;
    (arrayOfByte = new byte[6])[0] = 3;
    (new byte[6])[1] = 2;
    (new byte[6])[2] = 62;
    (new byte[6])[3] = 2;
    (new byte[6])[4] = -5;
    (new byte[6])[5] = 30;
    (new byte[69][])[66] = arrayOfByte;
    (arrayOfByte = new byte[6])[0] = 4;
    (new byte[6])[1] = 2;
    (new byte[6])[2] = 62;
    (new byte[6])[3] = 3;
    (new byte[6])[4] = -5;
    (new byte[6])[5] = 30;
    (new byte[69][])[67] = arrayOfByte;
    (arrayOfByte = new byte[6])[0] = 5;
    (new byte[6])[1] = 2;
    (new byte[6])[2] = 62;
    (new byte[6])[3] = 4;
    (new byte[6])[4] = -5;
    (new byte[6])[5] = 30;
    X90 = new byte[][] { 
        null, null, null, null, null, null, null, null, null, null, 
        null, null, null, null, null, null, null, null, null, null, 
        null, null, null, null, null, null, null, null, null, null, 
        null, null, null, null, null, null, null, null, null, null, 
        null, null, null, null, null, null, null, null, null, null, 
        null, null, null, null, null, null, null, null, null, null, 
        null, null, null, null, null, null, null, null, arrayOfByte };
  }
  
  public final boolean wJ(byte paramByte) {
    return (paramByte == 0);
  }
  
  public final xr0 w10(byte paramByte, xr0 paramxr0) {
    // Byte code:
    //   0: iload_1
    //   1: ifeq -> 6
    //   4: aconst_null
    //   5: areturn
    //   6: aload_2
    //   7: invokevirtual Q4 : ()Lf/KI;
    //   10: dup
    //   11: astore_0
    //   12: invokevirtual Xg0 : ()S
    //   15: sipush #214
    //   18: if_icmpeq -> 24
    //   21: goto -> 104
    //   24: iconst_0
    //   25: istore_1
    //   26: iload_1
    //   27: getstatic f/wp.X90 : [[B
    //   30: astore_3
    //   31: bipush #69
    //   33: if_icmpge -> 104
    //   36: aload_2
    //   37: invokevirtual Ka : ()S
    //   40: aload_3
    //   41: iload_1
    //   42: aaload
    //   43: iconst_0
    //   44: baload
    //   45: if_icmpne -> 98
    //   48: aload_2
    //   49: invokevirtual hA0 : ()S
    //   52: aload_3
    //   53: iload_1
    //   54: aaload
    //   55: iconst_1
    //   56: baload
    //   57: if_icmpne -> 98
    //   60: aload_2
    //   61: invokevirtual bl0 : ()B
    //   64: aload_3
    //   65: iload_1
    //   66: aaload
    //   67: dup
    //   68: astore_3
    //   69: iconst_2
    //   70: baload
    //   71: if_icmpne -> 98
    //   74: aload_0
    //   75: aload_3
    //   76: dup
    //   77: dup
    //   78: iconst_5
    //   79: baload
    //   80: istore_0
    //   81: iconst_3
    //   82: baload
    //   83: i2s
    //   84: istore_1
    //   85: iconst_4
    //   86: baload
    //   87: i2s
    //   88: istore_2
    //   89: iload_0
    //   90: iload_1
    //   91: iload_2
    //   92: invokevirtual v4 : (BSS)Lf/xr0;
    //   95: goto -> 105
    //   98: iinc #1, 1
    //   101: goto -> 26
    //   104: aconst_null
    //   105: areturn
    // Line number table:
    //   Java source line number -> byte code offset
    //   #1	-> 7
  }
  
  public final boolean nk(byte paramByte) {
    return (paramByte == 0);
  }
  
  public final int VP(xr0 paramxr01, xr0 paramxr02) {
    return (int)((paramxr01.i00() - paramxr02.i00()) * 100.0F);
  }
}


/* Location:              /Users/vnnsnnt/Documents/Codespace/JavaWorkspace/RedTrainer/src/main/java/org/trainer/client/PokeMMO.jar!/f/wp.class
 * Java compiler version: 8 (52.0)
 * JD-Core Version:       1.1.3
 */