/* 1 */ package f;public final class wT extends zX { private void qE0(Ij0 paramIj0) { Ll ll; paramIj0.O
/* 2 */       .gf0(this, paramIj0.O.z60(ll = this.bh0) ^ true); }
/*   */ 
/*   */   
/*   */   public qs Qq;
/*   */   public final Ll bh0 = Ll.F10("picked");
/*   */   
/*   */   public wT(String paramString, zz paramzz) {
/*   */     super(paramString);
/*   */     this.Qq = paramzz;
/*   */   }
/*   */   
/*   */   public final JG0 X9(io paramio, int paramInt) {
/*   */     // Byte code:
/*   */     //   0: aload_0
/*   */     //   1: new f/Kh0
/*   */     //   4: dup
/*   */     //   5: dup
/*   */     //   6: astore_1
/*   */     //   7: aload_0
/*   */     //   8: invokespecial <init> : (Lf/wT;)V
/*   */     //   11: new f/xo
/*   */     //   14: dup
/*   */     //   15: aload_0
/*   */     //   16: getfield Qq : Lf/qs;
/*   */     //   19: iconst_0
/*   */     //   20: invokespecial <init> : (Lf/qs;I)V
/*   */     //   23: invokevirtual ow : (Lf/protected;)V
/*   */     //   26: ldc 'checkbox'
/*   */     //   28: astore_2
/*   */     //   29: getfield kn0 : Ljava/lang/String;
/*   */     //   32: dup
/*   */     //   33: astore_3
/*   */     //   34: ifnull -> 45
/*   */     //   37: aload_1
/*   */     //   38: aload_3
/*   */     //   39: invokevirtual Xu : (Ljava/lang/String;)V
/*   */     //   42: goto -> 50
/*   */     //   45: aload_1
/*   */     //   46: aload_2
/*   */     //   47: invokevirtual Xu : (Ljava/lang/String;)V
/*   */     //   50: aload_1
/*   */     //   51: dup
/*   */     //   52: aload_0
/*   */     //   53: aload_1
/*   */     //   54: <illegal opcode> run : (Lf/wT;Lf/Ij0;)Ljava/lang/Runnable;
/*   */     //   59: invokevirtual tW : (Ljava/lang/Runnable;)V
/*   */     //   62: areturn
/*   */     // Line number table:
/*   */     //   Java source line number -> byte code offset
/*   */     //   #1	-> 16
/*   */     //   #2	-> 20
/*   */     //   #3	-> 23
/*   */     //   #4	-> 29
/*   */     //   #5	-> 54
/*   */   } }


/* Location:              /Users/vnnsnnt/Documents/Codespace/JavaWorkspace/RedTrainer/src/main/java/org/trainer/client/PokeMMO.jar!/f/wT.class
 * Java compiler version: 8 (52.0)
 * JD-Core Version:       1.1.3
 */