/*  1 */ package f;public final class wv extends Qa0 implements r60 { public static boolean Ou0 = false; public Vq0 JK; public rS Fv0; public Ip NT; public Ip yD0; public Ip zm; public rS ky0; public Ip Se; public M2 DX; public mG V1; public final of Nm0; public ge0[][] R0; private void AH0(Jo paramJo) { this.yD0.gx(); g0 g0 = Mr.X60(this.yD0, this.yD0);
/*    */     
/*  3 */     cr0 cr0 = V2.Ur(this.yD0, this.yD0);
/*  4 */     if (km.XU()) if (this.V1
/*    */         
/*  6 */         .Ru(paramJo.Jg, (short)1)) { g0.ee0(this.yD0.vo0(new JG0[] { this.qv, this.j0 }).Aq(80)); cr0.ee0(this.yD0.AUX(new JG0[] { this.qv, this.j0 })); } else { cr0.Aq(60); }   this("yyyy-MM-dd"); SimpleDateFormat simpleDateFormat; dQ dQ1; this(); Date date; (date = new Date())
/*    */ 
/*    */       
/*  9 */       .setTime(this.V1.FH0.ho0 * 1000L); String str = Ml0.Go(2723, simpleDateFormat.format(date));
/* 10 */     this(); (new dQ()).E1(str); Ip ip;
/* 11 */     (ip = this.yD0).getClass();
/*    */     
/* 13 */     g0.ee0((new cr0(ip)).Em0().lW(et.t9, dQ1)); cr0.ee0(this.yD0.AUX(new JG0[] { dQ1 })); g0.ee0(this.yD0.vo0(new JG0[] { this.PI0 })); cr0.ee0(this.yD0.AUX(new JG0[] { this.PI0 })); if (!km.XU() && this.V1
/*    */       
/* 15 */       .Ru(paramJo.Jg, (short)1)) { g0.ee0(this.yD0.vo0(new JG0[] { this.qv, this.j0 })); cr0.ee0(this.yD0.AUX(new JG0[] { this.qv, this.j0 })); }  if (this.V1
/*    */       
/* 17 */       .Ru(paramJo.Jg, (short)4)) { g0.ee0(this.yD0.vo0(new JG0[] { this.ip0, this.dw }).Em0().Ya(this.mx)); arrayOfJG0[0] = this.ip0; arrayOfJG0[1] = this.dw; JG0[] arrayOfJG0; (arrayOfJG0 = new JG0[3])[2] = this.mx; cr0.ee0(this.yD0.AUX(new JG0[3])); } else { g0.ee0(this.yD0.vo0(new JG0[] { this.dw }).Em0().Ya(this.mx)); cr0.ee0(this.yD0.AUX(new JG0[] { this.dw, this.mx })); }  this.yD0.rK0(g0); this.yD0.WN(cr0); this.OE
/*    */       
/* 19 */       .wI0(this.V1.Ru(paramJo.Jg, (short)255)); } public final Fy0 OE; public final Fy0 ip0; public final JG0[] wi; public final of qv; public final Un j0; public rS PI0; public Un dw; public dQ mx; public JF0 HK; public of d4; public final boolean Ke; public wv(pA parampA) { // Byte code:
/*    */     //   0: aload_0
/*    */     //   1: dup
/*    */     //   2: dup
/*    */     //   3: dup2
/*    */     //   4: dup2
/*    */     //   5: dup2
/*    */     //   6: dup2
/*    */     //   7: dup2
/*    */     //   8: dup2
/*    */     //   9: invokestatic XU : ()Z
/*    */     //   12: invokespecial <init> : (Z)V
/*    */     //   15: getstatic f/jv.bv : [Lf/jv;
/*    */     //   18: dup
/*    */     //   19: astore_2
/*    */     //   20: arraylength
/*    */     //   21: iconst_3
/*    */     //   22: multianewarray[[Lf/ge0; 2
/*    */     //   26: putfield R0 : [[Lf/ge0;
/*    */     //   29: aload_2
/*    */     //   30: arraylength
/*    */     //   31: anewarray f/JG0
/*    */     //   34: putfield wi : [Lf/JG0;
/*    */     //   37: getstatic f/km.u4 : Lf/R8;
/*    */     //   40: invokevirtual ik0 : ()Lf/mG;
/*    */     //   43: dup
/*    */     //   44: aload_0
/*    */     //   45: swap
/*    */     //   46: putfield V1 : Lf/mG;
/*    */     //   49: getstatic f/km.a3 : Lf/vh0;
/*    */     //   52: invokevirtual wQ : ()Lf/Jo;
/*    */     //   55: invokevirtual VC : ()I
/*    */     //   58: sipush #255
/*    */     //   61: invokevirtual Ru : (IS)Z
/*    */     //   64: putfield Ke : Z
/*    */     //   67: ldc 'guildwindow'
/*    */     //   69: invokevirtual Xu : (Ljava/lang/String;)V
/*    */     //   72: getfield V1 : Lf/mG;
/*    */     //   75: invokevirtual IW : ()Ljava/lang/String;
/*    */     //   78: invokevirtual Lo : (Ljava/lang/String;)V
/*    */     //   81: iconst_1
/*    */     //   82: invokevirtual EP : (I)V
/*    */     //   85: new f/of
/*    */     //   88: dup
/*    */     //   89: invokespecial <init> : ()V
/*    */     //   92: putfield Nm0 : Lf/of;
/*    */     //   95: new f/mj0
/*    */     //   98: dup
/*    */     //   99: aload_1
/*    */     //   100: invokespecial <init> : (Lf/pA;)V
/*    */     //   103: invokevirtual TG0 : (Ljava/lang/Runnable;)V
/*    */     //   106: new f/Vq0
/*    */     //   109: dup
/*    */     //   110: aload_0
/*    */     //   111: swap
/*    */     //   112: dup
/*    */     //   113: invokespecial <init> : ()V
/*    */     //   116: putfield JK : Lf/Vq0;
/*    */     //   119: iconst_0
/*    */     //   120: invokevirtual T1 : (Z)V
/*    */     //   123: new f/Ip
/*    */     //   126: dup
/*    */     //   127: dup
/*    */     //   128: aload_0
/*    */     //   129: swap
/*    */     //   130: dup
/*    */     //   131: invokespecial <init> : ()V
/*    */     //   134: putfield NT : Lf/Ip;
/*    */     //   137: invokevirtual mE0 : ()Lf/g0;
/*    */     //   140: iconst_1
/*    */     //   141: anewarray f/U90
/*    */     //   144: dup
/*    */     //   145: aload_0
/*    */     //   146: getfield NT : Lf/Ip;
/*    */     //   149: invokevirtual d7 : ()Lf/cr0;
/*    */     //   152: iconst_1
/*    */     //   153: anewarray f/JG0
/*    */     //   156: dup
/*    */     //   157: aload_0
/*    */     //   158: getfield JK : Lf/Vq0;
/*    */     //   161: iconst_0
/*    */     //   162: swap
/*    */     //   163: aastore
/*    */     //   164: invokevirtual Mg : ([Lf/JG0;)Lf/U90;
/*    */     //   167: iconst_0
/*    */     //   168: swap
/*    */     //   169: aastore
/*    */     //   170: invokevirtual cOM8 : ([Lf/U90;)Lf/U90;
/*    */     //   173: invokevirtual rK0 : (Lf/U90;)V
/*    */     //   176: getfield NT : Lf/Ip;
/*    */     //   179: dup
/*    */     //   180: invokevirtual d7 : ()Lf/cr0;
/*    */     //   183: iconst_1
/*    */     //   184: anewarray f/U90
/*    */     //   187: dup
/*    */     //   188: aload_0
/*    */     //   189: getfield NT : Lf/Ip;
/*    */     //   192: invokevirtual mE0 : ()Lf/g0;
/*    */     //   195: iconst_1
/*    */     //   196: anewarray f/JG0
/*    */     //   199: dup
/*    */     //   200: aload_0
/*    */     //   201: getfield JK : Lf/Vq0;
/*    */     //   204: iconst_0
/*    */     //   205: swap
/*    */     //   206: aastore
/*    */     //   207: invokevirtual Mg : ([Lf/JG0;)Lf/U90;
/*    */     //   210: iconst_0
/*    */     //   211: swap
/*    */     //   212: aastore
/*    */     //   213: invokevirtual cOM8 : ([Lf/U90;)Lf/U90;
/*    */     //   216: invokevirtual WN : (Lf/U90;)V
/*    */     //   219: new f/Ip
/*    */     //   222: dup
/*    */     //   223: invokespecial <init> : ()V
/*    */     //   226: putfield yD0 : Lf/Ip;
/*    */     //   229: new f/M2
/*    */     //   232: dup
/*    */     //   233: invokespecial <init> : ()V
/*    */     //   236: putfield DX : Lf/M2;
/*    */     //   239: new f/da
/*    */     //   242: dup
/*    */     //   243: astore_2
/*    */     //   244: aload_0
/*    */     //   245: getfield DX : Lf/M2;
/*    */     //   248: invokespecial <init> : (Lf/Zq0;)V
/*    */     //   251: getfield DX : Lf/M2;
/*    */     //   254: aload_0
/*    */     //   255: getfield V1 : Lf/mG;
/*    */     //   258: invokevirtual hd0 : ()Lf/yy;
/*    */     //   261: invokevirtual Tr0 : ()Ljava/lang/String;
/*    */     //   264: invokevirtual cX : (Ljava/lang/String;)V
/*    */     //   267: new f/Fy0
/*    */     //   270: dup
/*    */     //   271: astore_3
/*    */     //   272: aload_0
/*    */     //   273: aload_3
/*    */     //   274: dup
/*    */     //   275: aload_0
/*    */     //   276: aload_3
/*    */     //   277: dup
/*    */     //   278: bipush #66
/*    */     //   280: invokestatic OH0 : (I)Ljava/lang/String;
/*    */     //   283: invokespecial <init> : (Ljava/lang/String;)V
/*    */     //   286: putfield ip0 : Lf/Fy0;
/*    */     //   289: invokevirtual zY : ()Lf/rH;
/*    */     //   292: iconst_1
/*    */     //   293: anewarray f/pe0
/*    */     //   296: dup
/*    */     //   297: invokestatic ZZ : ()Lf/interface;
/*    */     //   300: invokevirtual Lf : ()Lf/pe0;
/*    */     //   303: iconst_0
/*    */     //   304: swap
/*    */     //   305: aastore
/*    */     //   306: invokevirtual Pn : ([Lf/pe0;)Lf/JG0;
/*    */     //   309: pop
/*    */     //   310: invokevirtual zY : ()Lf/rH;
/*    */     //   313: iconst_5
/*    */     //   314: bipush #7
/*    */     //   316: invokevirtual zT : (II)Lf/JG0;
/*    */     //   319: pop
/*    */     //   320: <illegal opcode> run : (Lf/wv;)Ljava/lang/Runnable;
/*    */     //   325: invokevirtual tW : (Ljava/lang/Runnable;)V
/*    */     //   328: getfield V1 : Lf/mG;
/*    */     //   331: getstatic f/km.a3 : Lf/vh0;
/*    */     //   334: invokevirtual wQ : ()Lf/Jo;
/*    */     //   337: invokevirtual VC : ()I
/*    */     //   340: invokevirtual Ic0 : (I)Lf/jv;
/*    */     //   343: getstatic f/jv.Qq0 : Lf/jv;
/*    */     //   346: if_acmpne -> 406
/*    */     //   349: aload_0
/*    */     //   350: new f/Un
/*    */     //   353: astore_1
/*    */     //   354: getfield V1 : Lf/mG;
/*    */     //   357: invokevirtual hd0 : ()Lf/yy;
/*    */     //   360: invokevirtual H8 : ()Z
/*    */     //   363: ifeq -> 372
/*    */     //   366: sipush #2716
/*    */     //   369: goto -> 375
/*    */     //   372: sipush #2713
/*    */     //   375: invokestatic OH0 : (I)Ljava/lang/String;
/*    */     //   378: astore_3
/*    */     //   379: aload_1
/*    */     //   380: aload_0
/*    */     //   381: aload_1
/*    */     //   382: aload_3
/*    */     //   383: invokespecial <init> : (Ljava/lang/String;)V
/*    */     //   386: aload_1
/*    */     //   387: putfield dw : Lf/Un;
/*    */     //   390: new f/vs
/*    */     //   393: dup
/*    */     //   394: astore_1
/*    */     //   395: aload_0
/*    */     //   396: invokespecial <init> : (Lf/wv;)V
/*    */     //   399: aload_1
/*    */     //   400: invokevirtual tW : (Ljava/lang/Runnable;)V
/*    */     //   403: goto -> 437
/*    */     //   406: new f/Un
/*    */     //   409: dup
/*    */     //   410: aload_0
/*    */     //   411: swap
/*    */     //   412: dup
/*    */     //   413: sipush #2709
/*    */     //   416: invokestatic OH0 : (I)Ljava/lang/String;
/*    */     //   419: invokespecial <init> : (Ljava/lang/String;)V
/*    */     //   422: putfield dw : Lf/Un;
/*    */     //   425: new f/Sm
/*    */     //   428: dup
/*    */     //   429: aload_0
/*    */     //   430: aload_1
/*    */     //   431: invokespecial <init> : (Lf/wv;Lf/pA;)V
/*    */     //   434: invokevirtual tW : (Ljava/lang/Runnable;)V
/*    */     //   437: aload_0
/*    */     //   438: dup
/*    */     //   439: dup2
/*    */     //   440: dup2
/*    */     //   441: new f/dQ
/*    */     //   444: dup
/*    */     //   445: ldc_w ''
/*    */     //   448: invokespecial <init> : (Ljava/lang/String;)V
/*    */     //   451: putfield mx : Lf/dQ;
/*    */     //   454: new f/rS
/*    */     //   457: dup
/*    */     //   458: aload_0
/*    */     //   459: swap
/*    */     //   460: dup
/*    */     //   461: aload_2
/*    */     //   462: invokespecial <init> : (Lf/JG0;)V
/*    */     //   465: putfield PI0 : Lf/rS;
/*    */     //   468: ldc_w 'motdscroll'
/*    */     //   471: invokevirtual Xu : (Ljava/lang/String;)V
/*    */     //   474: new f/of
/*    */     //   477: dup
/*    */     //   478: aload_0
/*    */     //   479: swap
/*    */     //   480: dup
/*    */     //   481: invokespecial <init> : ()V
/*    */     //   484: putfield qv : Lf/of;
/*    */     //   487: invokevirtual LE : ()V
/*    */     //   490: new f/Un
/*    */     //   493: dup
/*    */     //   494: aload_0
/*    */     //   495: swap
/*    */     //   496: dup
/*    */     //   497: sipush #2711
/*    */     //   500: invokestatic OH0 : (I)Ljava/lang/String;
/*    */     //   503: invokespecial <init> : (Ljava/lang/String;)V
/*    */     //   506: putfield j0 : Lf/Un;
/*    */     //   509: new f/R1
/*    */     //   512: dup
/*    */     //   513: aload_0
/*    */     //   514: invokespecial <init> : (Lf/wv;)V
/*    */     //   517: invokevirtual tW : (Ljava/lang/Runnable;)V
/*    */     //   520: new f/Ip
/*    */     //   523: dup
/*    */     //   524: invokespecial <init> : ()V
/*    */     //   527: putfield zm : Lf/Ip;
/*    */     //   530: new f/JF0
/*    */     //   533: dup
/*    */     //   534: aload_0
/*    */     //   535: swap
/*    */     //   536: dup
/*    */     //   537: aload_0
/*    */     //   538: getfield V1 : Lf/mG;
/*    */     //   541: aload_0
/*    */     //   542: invokespecial <init> : (Lf/mG;Lf/wv;)V
/*    */     //   545: putfield HK : Lf/JF0;
/*    */     //   548: getstatic f/wv.Ou0 : Z
/*    */     //   551: ldc_w ''
/*    */     //   554: swap
/*    */     //   555: invokevirtual t8 : (Ljava/lang/String;Z)V
/*    */     //   558: getfield HK : Lf/JF0;
/*    */     //   561: new f/lL0
/*    */     //   564: dup
/*    */     //   565: aload_0
/*    */     //   566: invokespecial <init> : (Lf/wv;)V
/*    */     //   569: invokevirtual uB : (Lf/qe;)V
/*    */     //   572: new f/rS
/*    */     //   575: dup
/*    */     //   576: aload_0
/*    */     //   577: swap
/*    */     //   578: dup
/*    */     //   579: aload_0
/*    */     //   580: getfield HK : Lf/JF0;
/*    */     //   583: invokespecial <init> : (Lf/JG0;)V
/*    */     //   586: putfield Fv0 : Lf/rS;
/*    */     //   589: iconst_2
/*    */     //   590: invokevirtual zG0 : (I)V
/*    */     //   593: new f/of
/*    */     //   596: dup
/*    */     //   597: aload_0
/*    */     //   598: swap
/*    */     //   599: dup
/*    */     //   600: invokespecial <init> : ()V
/*    */     //   603: putfield d4 : Lf/of;
/*    */     //   606: invokevirtual LE : ()V
/*    */     //   609: getfield d4 : Lf/of;
/*    */     //   612: ldc_w 'editfield-search'
/*    */     //   615: invokevirtual Xu : (Ljava/lang/String;)V
/*    */     //   618: new f/ge0
/*    */     //   621: dup
/*    */     //   622: dup
/*    */     //   623: astore_1
/*    */     //   624: aload_0
/*    */     //   625: aload_1
/*    */     //   626: aload_0
/*    */     //   627: aload_1
/*    */     //   628: invokespecial <init> : ()V
/*    */     //   631: getfield d4 : Lf/of;
/*    */     //   634: aload_0
/*    */     //   635: aload_1
/*    */     //   636: <illegal opcode> SX : (Lf/wv;Lf/ge0;)Lf/a70;
/*    */     //   641: invokevirtual JD0 : (Lf/a70;)V
/*    */     //   644: <illegal opcode> run : (Lf/wv;Lf/ge0;)Ljava/lang/Runnable;
/*    */     //   649: invokevirtual tW : (Ljava/lang/Runnable;)V
/*    */     //   652: getstatic f/wv.Ou0 : Z
/*    */     //   655: invokevirtual zs : (Z)V
/*    */     //   658: new f/dQ
/*    */     //   661: dup
/*    */     //   662: astore_2
/*    */     //   663: aload_1
/*    */     //   664: aload_2
/*    */     //   665: sipush #1682
/*    */     //   668: invokestatic OH0 : (I)Ljava/lang/String;
/*    */     //   671: invokespecial <init> : (Ljava/lang/String;)V
/*    */     //   674: invokevirtual VH : (Lf/JG0;)V
/*    */     //   677: getfield zm : Lf/Ip;
/*    */     //   680: dup
/*    */     //   681: astore_3
/*    */     //   682: invokevirtual mE0 : ()Lf/g0;
/*    */     //   685: astore #4
/*    */     //   687: iconst_2
/*    */     //   688: anewarray f/U90
/*    */     //   691: astore #5
/*    */     //   693: iconst_0
/*    */     //   694: istore #6
/*    */     //   696: getfield zm : Lf/Ip;
/*    */     //   699: iconst_3
/*    */     //   700: anewarray f/JG0
/*    */     //   703: dup
/*    */     //   704: dup2
/*    */     //   705: aload_0
/*    */     //   706: getfield d4 : Lf/of;
/*    */     //   709: iconst_0
/*    */     //   710: swap
/*    */     //   711: aastore
/*    */     //   712: iconst_1
/*    */     //   713: aload_1
/*    */     //   714: aastore
/*    */     //   715: iconst_2
/*    */     //   716: aload_2
/*    */     //   717: aastore
/*    */     //   718: invokevirtual vo0 : ([Lf/JG0;)Lf/U90;
/*    */     //   721: astore #7
/*    */     //   723: invokestatic XU : ()Z
/*    */     //   726: ifeq -> 736
/*    */     //   729: bipush #80
/*    */     //   731: istore #8
/*    */     //   733: goto -> 739
/*    */     //   736: iconst_0
/*    */     //   737: istore #8
/*    */     //   739: aload_0
/*    */     //   740: dup
/*    */     //   741: dup
/*    */     //   742: aload_3
/*    */     //   743: aload #4
/*    */     //   745: aload #5
/*    */     //   747: dup
/*    */     //   748: aload_0
/*    */     //   749: aload #5
/*    */     //   751: iload #6
/*    */     //   753: aload #7
/*    */     //   755: iload #8
/*    */     //   757: invokevirtual Aq : (I)Lf/U90;
/*    */     //   760: aastore
/*    */     //   761: getfield zm : Lf/Ip;
/*    */     //   764: iconst_1
/*    */     //   765: anewarray f/JG0
/*    */     //   768: dup
/*    */     //   769: aload_0
/*    */     //   770: getfield Fv0 : Lf/rS;
/*    */     //   773: iconst_0
/*    */     //   774: swap
/*    */     //   775: aastore
/*    */     //   776: invokevirtual vo0 : ([Lf/JG0;)Lf/U90;
/*    */     //   779: iconst_1
/*    */     //   780: swap
/*    */     //   781: aastore
/*    */     //   782: invokevirtual cOM8 : ([Lf/U90;)Lf/U90;
/*    */     //   785: invokevirtual rK0 : (Lf/U90;)V
/*    */     //   788: getfield zm : Lf/Ip;
/*    */     //   791: dup
/*    */     //   792: invokevirtual d7 : ()Lf/cr0;
/*    */     //   795: iconst_2
/*    */     //   796: anewarray f/U90
/*    */     //   799: dup
/*    */     //   800: dup
/*    */     //   801: aload_0
/*    */     //   802: swap
/*    */     //   803: aload_0
/*    */     //   804: getfield zm : Lf/Ip;
/*    */     //   807: iconst_3
/*    */     //   808: anewarray f/JG0
/*    */     //   811: dup
/*    */     //   812: dup2
/*    */     //   813: aload_0
/*    */     //   814: getfield d4 : Lf/of;
/*    */     //   817: iconst_0
/*    */     //   818: swap
/*    */     //   819: aastore
/*    */     //   820: iconst_1
/*    */     //   821: aload_1
/*    */     //   822: aastore
/*    */     //   823: iconst_2
/*    */     //   824: aload_2
/*    */     //   825: aastore
/*    */     //   826: invokevirtual AUX : ([Lf/JG0;)Lf/U90;
/*    */     //   829: iconst_0
/*    */     //   830: swap
/*    */     //   831: aastore
/*    */     //   832: getfield zm : Lf/Ip;
/*    */     //   835: iconst_1
/*    */     //   836: anewarray f/JG0
/*    */     //   839: dup
/*    */     //   840: aload_0
/*    */     //   841: getfield Fv0 : Lf/rS;
/*    */     //   844: iconst_0
/*    */     //   845: swap
/*    */     //   846: aastore
/*    */     //   847: invokevirtual AUX : ([Lf/JG0;)Lf/U90;
/*    */     //   850: iconst_1
/*    */     //   851: swap
/*    */     //   852: aastore
/*    */     //   853: invokevirtual cOM8 : ([Lf/U90;)Lf/U90;
/*    */     //   856: invokevirtual WN : (Lf/U90;)V
/*    */     //   859: new f/Ip
/*    */     //   862: dup
/*    */     //   863: invokespecial <init> : ()V
/*    */     //   866: putfield Se : Lf/Ip;
/*    */     //   869: new f/rS
/*    */     //   872: dup
/*    */     //   873: aload_0
/*    */     //   874: swap
/*    */     //   875: dup
/*    */     //   876: invokespecial <init> : ()V
/*    */     //   879: putfield ky0 : Lf/rS;
/*    */     //   882: invokevirtual xZ : ()V
/*    */     //   885: getfield ky0 : Lf/rS;
/*    */     //   888: iconst_3
/*    */     //   889: invokevirtual zG0 : (I)V
/*    */     //   892: new f/dQ
/*    */     //   895: dup
/*    */     //   896: dup
/*    */     //   897: astore_1
/*    */     //   898: sipush #2749
/*    */     //   901: invokestatic OH0 : (I)Ljava/lang/String;
/*    */     //   904: invokespecial <init> : (Ljava/lang/String;)V
/*    */     //   907: ldc_w 'label-title-perm'
/*    */     //   910: invokevirtual Xu : (Ljava/lang/String;)V
/*    */     //   913: iconst_3
/*    */     //   914: anewarray f/dQ
/*    */     //   917: astore_2
/*    */     //   918: iconst_0
/*    */     //   919: istore_3
/*    */     //   920: iload_3
/*    */     //   921: iconst_3
/*    */     //   922: if_icmpge -> 961
/*    */     //   925: new f/dQ
/*    */     //   928: dup
/*    */     //   929: astore #4
/*    */     //   931: aload_2
/*    */     //   932: iload_3
/*    */     //   933: aload #4
/*    */     //   935: iload_3
/*    */     //   936: sipush #2750
/*    */     //   939: iadd
/*    */     //   940: invokestatic OH0 : (I)Ljava/lang/String;
/*    */     //   943: invokespecial <init> : (Ljava/lang/String;)V
/*    */     //   946: aload #4
/*    */     //   948: aastore
/*    */     //   949: ldc_w 'label-title-perm-val'
/*    */     //   952: invokevirtual Xu : (Ljava/lang/String;)V
/*    */     //   955: iinc #3, 1
/*    */     //   958: goto -> 920
/*    */     //   961: new f/Zz0
/*    */     //   964: dup
/*    */     //   965: dup
/*    */     //   966: astore_3
/*    */     //   967: invokespecial <init> : ()V
/*    */     //   970: aload_1
/*    */     //   971: aload_2
/*    */     //   972: invokevirtual t60 : (Lf/JG0;[Lf/JG0;)V
/*    */     //   975: iconst_0
/*    */     //   976: istore_1
/*    */     //   977: iload_1
/*    */     //   978: getstatic f/jv.bv : [Lf/jv;
/*    */     //   981: arraylength
/*    */     //   982: if_icmpge -> 1207
/*    */     //   985: aload_0
/*    */     //   986: iload_1
/*    */     //   987: invokestatic LD : (B)Lf/jv;
/*    */     //   990: astore_2
/*    */     //   991: getfield Ke : Z
/*    */     //   994: ifeq -> 1062
/*    */     //   997: aload_0
/*    */     //   998: dup
/*    */     //   999: dup2
/*    */     //   1000: getfield wi : [Lf/JG0;
/*    */     //   1003: iload_1
/*    */     //   1004: new f/of
/*    */     //   1007: dup
/*    */     //   1008: astore #4
/*    */     //   1010: invokespecial <init> : ()V
/*    */     //   1013: aload #4
/*    */     //   1015: aastore
/*    */     //   1016: getfield wi : [Lf/JG0;
/*    */     //   1019: iload_1
/*    */     //   1020: aaload
/*    */     //   1021: checkcast f/of
/*    */     //   1024: invokevirtual LE : ()V
/*    */     //   1027: getfield wi : [Lf/JG0;
/*    */     //   1030: iload_1
/*    */     //   1031: aaload
/*    */     //   1032: checkcast f/of
/*    */     //   1035: aload_0
/*    */     //   1036: getfield V1 : Lf/mG;
/*    */     //   1039: aload_2
/*    */     //   1040: invokevirtual Oh0 : (Lf/jv;)Ljava/lang/String;
/*    */     //   1043: invokevirtual Zh : (Ljava/lang/String;)V
/*    */     //   1046: getfield wi : [Lf/JG0;
/*    */     //   1049: iload_1
/*    */     //   1050: aaload
/*    */     //   1051: checkcast f/of
/*    */     //   1054: bipush #16
/*    */     //   1056: invokevirtual co : (I)V
/*    */     //   1059: goto -> 1099
/*    */     //   1062: aload_0
/*    */     //   1063: dup
/*    */     //   1064: getfield wi : [Lf/JG0;
/*    */     //   1067: iload_1
/*    */     //   1068: new f/dQ
/*    */     //   1071: dup
/*    */     //   1072: astore #4
/*    */     //   1074: aload_0
/*    */     //   1075: getfield V1 : Lf/mG;
/*    */     //   1078: aload_2
/*    */     //   1079: invokevirtual Oh0 : (Lf/jv;)Ljava/lang/String;
/*    */     //   1082: invokespecial <init> : (Ljava/lang/String;)V
/*    */     //   1085: aload #4
/*    */     //   1087: aastore
/*    */     //   1088: getfield wi : [Lf/JG0;
/*    */     //   1091: iload_1
/*    */     //   1092: aaload
/*    */     //   1093: ldc_w 'label-title-perm'
/*    */     //   1096: invokevirtual Xu : (Ljava/lang/String;)V
/*    */     //   1099: iconst_0
/*    */     //   1100: istore #4
/*    */     //   1102: iload #4
/*    */     //   1104: iconst_3
/*    */     //   1105: if_icmpge -> 1183
/*    */     //   1108: aload_2
/*    */     //   1109: aload_0
/*    */     //   1110: getfield R0 : [[Lf/ge0;
/*    */     //   1113: iload_1
/*    */     //   1114: aaload
/*    */     //   1115: iload #4
/*    */     //   1117: new f/ge0
/*    */     //   1120: dup
/*    */     //   1121: astore #5
/*    */     //   1123: invokespecial <init> : ()V
/*    */     //   1126: aload #5
/*    */     //   1128: aastore
/*    */     //   1129: getstatic f/jv.Qq0 : Lf/jv;
/*    */     //   1132: if_acmpne -> 1161
/*    */     //   1135: aload_0
/*    */     //   1136: dup
/*    */     //   1137: getfield R0 : [[Lf/ge0;
/*    */     //   1140: iload_1
/*    */     //   1141: aaload
/*    */     //   1142: iload #4
/*    */     //   1144: aaload
/*    */     //   1145: iconst_0
/*    */     //   1146: invokevirtual sk0 : (Z)V
/*    */     //   1149: getfield R0 : [[Lf/ge0;
/*    */     //   1152: iload_1
/*    */     //   1153: aaload
/*    */     //   1154: iload #4
/*    */     //   1156: aaload
/*    */     //   1157: iconst_1
/*    */     //   1158: invokevirtual zs : (Z)V
/*    */     //   1161: aload_0
/*    */     //   1162: getfield R0 : [[Lf/ge0;
/*    */     //   1165: iload_1
/*    */     //   1166: aaload
/*    */     //   1167: iload #4
/*    */     //   1169: aaload
/*    */     //   1170: aload_0
/*    */     //   1171: getfield Ke : Z
/*    */     //   1174: invokevirtual sk0 : (Z)V
/*    */     //   1177: iinc #4, 1
/*    */     //   1180: goto -> 1102
/*    */     //   1183: iload_1
/*    */     //   1184: aload_3
/*    */     //   1185: aload_0
/*    */     //   1186: getfield wi : [Lf/JG0;
/*    */     //   1189: iload_1
/*    */     //   1190: aaload
/*    */     //   1191: aload_0
/*    */     //   1192: getfield R0 : [[Lf/ge0;
/*    */     //   1195: iload_1
/*    */     //   1196: aaload
/*    */     //   1197: invokevirtual t60 : (Lf/JG0;[Lf/JG0;)V
/*    */     //   1200: iconst_1
/*    */     //   1201: iadd
/*    */     //   1202: i2b
/*    */     //   1203: istore_1
/*    */     //   1204: goto -> 977
/*    */     //   1207: aload_0
/*    */     //   1208: dup
/*    */     //   1209: dup
/*    */     //   1210: getfield ky0 : Lf/rS;
/*    */     //   1213: aload_3
/*    */     //   1214: invokevirtual Gz0 : (Lf/JG0;)V
/*    */     //   1217: new f/Fy0
/*    */     //   1220: dup
/*    */     //   1221: astore_1
/*    */     //   1222: aload_0
/*    */     //   1223: aload_1
/*    */     //   1224: aload_0
/*    */     //   1225: aload_1
/*    */     //   1226: dup
/*    */     //   1227: aload_0
/*    */     //   1228: aload_1
/*    */     //   1229: dup
/*    */     //   1230: bipush #54
/*    */     //   1232: invokestatic OH0 : (I)Ljava/lang/String;
/*    */     //   1235: invokespecial <init> : (Ljava/lang/String;)V
/*    */     //   1238: putfield OE : Lf/Fy0;
/*    */     //   1241: invokevirtual zY : ()Lf/rH;
/*    */     //   1244: iconst_1
/*    */     //   1245: anewarray f/pe0
/*    */     //   1248: dup
/*    */     //   1249: invokestatic ZZ : ()Lf/interface;
/*    */     //   1252: invokevirtual Wz : ()Lf/pe0;
/*    */     //   1255: iconst_0
/*    */     //   1256: swap
/*    */     //   1257: aastore
/*    */     //   1258: invokevirtual Pn : ([Lf/pe0;)Lf/JG0;
/*    */     //   1261: pop
/*    */     //   1262: invokevirtual zY : ()Lf/rH;
/*    */     //   1265: iconst_5
/*    */     //   1266: bipush #7
/*    */     //   1268: invokevirtual zT : (II)Lf/JG0;
/*    */     //   1271: pop
/*    */     //   1272: <illegal opcode> run : (Lf/wv;)Ljava/lang/Runnable;
/*    */     //   1277: invokevirtual tW : (Ljava/lang/Runnable;)V
/*    */     //   1280: getfield Ke : Z
/*    */     //   1283: invokevirtual sk0 : (Z)V
/*    */     //   1286: getfield Se : Lf/Ip;
/*    */     //   1289: dup
/*    */     //   1290: invokevirtual mE0 : ()Lf/g0;
/*    */     //   1293: iconst_2
/*    */     //   1294: anewarray f/U90
/*    */     //   1297: dup
/*    */     //   1298: dup
/*    */     //   1299: aload_0
/*    */     //   1300: swap
/*    */     //   1301: aload_0
/*    */     //   1302: getfield Se : Lf/Ip;
/*    */     //   1305: iconst_1
/*    */     //   1306: anewarray f/JG0
/*    */     //   1309: dup
/*    */     //   1310: aload_0
/*    */     //   1311: getfield ky0 : Lf/rS;
/*    */     //   1314: iconst_0
/*    */     //   1315: swap
/*    */     //   1316: aastore
/*    */     //   1317: invokevirtual vo0 : ([Lf/JG0;)Lf/U90;
/*    */     //   1320: iconst_0
/*    */     //   1321: swap
/*    */     //   1322: aastore
/*    */     //   1323: getfield Se : Lf/Ip;
/*    */     //   1326: invokevirtual d7 : ()Lf/cr0;
/*    */     //   1329: invokevirtual Em0 : ()Lf/U90;
/*    */     //   1332: aload_1
/*    */     //   1333: invokevirtual Ya : (Lf/JG0;)Lf/U90;
/*    */     //   1336: iconst_1
/*    */     //   1337: swap
/*    */     //   1338: aastore
/*    */     //   1339: invokevirtual cOM8 : ([Lf/U90;)Lf/U90;
/*    */     //   1342: invokevirtual rK0 : (Lf/U90;)V
/*    */     //   1345: getfield Se : Lf/Ip;
/*    */     //   1348: dup
/*    */     //   1349: astore_2
/*    */     //   1350: invokevirtual d7 : ()Lf/cr0;
/*    */     //   1353: astore_3
/*    */     //   1354: invokestatic XU : ()Z
/*    */     //   1357: ifeq -> 1367
/*    */     //   1360: bipush #60
/*    */     //   1362: istore #4
/*    */     //   1364: goto -> 1370
/*    */     //   1367: iconst_0
/*    */     //   1368: istore #4
/*    */     //   1370: aload_0
/*    */     //   1371: dup
/*    */     //   1372: dup
/*    */     //   1373: dup2
/*    */     //   1374: dup2
/*    */     //   1375: dup2
/*    */     //   1376: aload_2
/*    */     //   1377: aload_3
/*    */     //   1378: iload #4
/*    */     //   1380: invokevirtual Aq : (I)Lf/U90;
/*    */     //   1383: iconst_2
/*    */     //   1384: anewarray f/U90
/*    */     //   1387: dup
/*    */     //   1388: dup
/*    */     //   1389: aload_0
/*    */     //   1390: swap
/*    */     //   1391: aload_0
/*    */     //   1392: getfield Se : Lf/Ip;
/*    */     //   1395: iconst_1
/*    */     //   1396: anewarray f/JG0
/*    */     //   1399: dup
/*    */     //   1400: aload_0
/*    */     //   1401: getfield ky0 : Lf/rS;
/*    */     //   1404: iconst_0
/*    */     //   1405: swap
/*    */     //   1406: aastore
/*    */     //   1407: invokevirtual AUX : ([Lf/JG0;)Lf/U90;
/*    */     //   1410: iconst_0
/*    */     //   1411: swap
/*    */     //   1412: aastore
/*    */     //   1413: getfield Se : Lf/Ip;
/*    */     //   1416: iconst_1
/*    */     //   1417: anewarray f/JG0
/*    */     //   1420: dup
/*    */     //   1421: iconst_0
/*    */     //   1422: aload_1
/*    */     //   1423: aastore
/*    */     //   1424: invokevirtual AUX : ([Lf/JG0;)Lf/U90;
/*    */     //   1427: iconst_1
/*    */     //   1428: swap
/*    */     //   1429: aastore
/*    */     //   1430: invokevirtual cOM8 : ([Lf/U90;)Lf/U90;
/*    */     //   1433: invokevirtual WN : (Lf/U90;)V
/*    */     //   1436: invokevirtual nR : ()V
/*    */     //   1439: invokevirtual P4 : ()V
/*    */     //   1442: invokevirtual AI : ()V
/*    */     //   1445: getfield JK : Lf/Vq0;
/*    */     //   1448: aload_0
/*    */     //   1449: sipush #2700
/*    */     //   1452: invokestatic OH0 : (I)Ljava/lang/String;
/*    */     //   1455: astore_1
/*    */     //   1456: getfield yD0 : Lf/Ip;
/*    */     //   1459: aload_1
/*    */     //   1460: invokevirtual WS : (Lf/JG0;Ljava/lang/String;)Lf/Li0;
/*    */     //   1463: pop
/*    */     //   1464: getfield JK : Lf/Vq0;
/*    */     //   1467: aload_0
/*    */     //   1468: sipush #2701
/*    */     //   1471: invokestatic OH0 : (I)Ljava/lang/String;
/*    */     //   1474: astore_1
/*    */     //   1475: getfield zm : Lf/Ip;
/*    */     //   1478: aload_1
/*    */     //   1479: invokevirtual WS : (Lf/JG0;Ljava/lang/String;)Lf/Li0;
/*    */     //   1482: pop
/*    */     //   1483: getfield JK : Lf/Vq0;
/*    */     //   1486: aload_0
/*    */     //   1487: sipush #2710
/*    */     //   1490: invokestatic OH0 : (I)Ljava/lang/String;
/*    */     //   1493: astore_0
/*    */     //   1494: getfield Se : Lf/Ip;
/*    */     //   1497: aload_0
/*    */     //   1498: invokevirtual WS : (Lf/JG0;Ljava/lang/String;)Lf/Li0;
/*    */     //   1501: pop
/*    */     //   1502: getfield NT : Lf/Ip;
/*    */     //   1505: invokevirtual J8 : (Lf/JG0;)V
/*    */     //   1508: getfield V1 : Lf/mG;
/*    */     //   1511: invokevirtual o20 : ()Z
/*    */     //   1514: pop
/* 19 */     //   1515: return } public final void IZ(ON paramON, Un paramUn, int paramInt1, int paramInt2) { wv wv1; if (paramUn == null) { wv1 = this; } else { paramInt1 = wv1.Kd; paramInt2 = wv1.er0; }  B3 b3 = js.vu0.Ot(paramInt1, paramInt2, paramON.cy0.Pb); jv jv; if ((paramON.implements != (jv = jv.Qq0) && this.V1.Ru(km.a3.Ct.Jg, (short)2)) || (paramON.implements != jv && this.V1.Ru(km.a3.Ct.Jg, (short)255))) { Pu0 pu0; this(); b3.aV.add(pu0); }  if (paramON.implements != jv && this
/* 20 */       .V1
/*    */ 
/*    */       
/* 23 */       .Ru(km.a3.Ct.Jg, (short)2)) { Hk0 hk0; this(Ml0.OH0(2706)); (new Hk0())
/* 24 */         .rv = new w4(this, paramON);
/* 25 */       String str = (new Hk0()).kn0; (new Hk0()).kn0 = "popup-button"; (new Hk0()).l8("theme", str, "popup-button");
/* 26 */       b3.aV.add(hk0); }  if (paramON
/* 27 */       .implements != jv && this
/* 28 */       .V1
/*    */ 
/*    */       
/* 31 */       .Ru(km.a3.Ct.Jg, (short)255)) { B3 b31; this(Ml0.OH0(2707)); jv[] arrayOfJv; int i; byte b; for (i = (arrayOfJv = jv.bv).length, b = 0; b < i; ) { jv jv1 = arrayOfJv[b];
/* 32 */         if (paramON.implements
/* 33 */           .cJ != jv1.cJ)
/* 34 */         { Hk0 hk0; this(this.V1.Oh0(jv1)); (new Hk0())
/* 35 */             .rv = new ip0(this, jv1, paramON);
/* 36 */           b31.aV.add(hk0); }  b++; }  b3.aV.add(b31); }
/* 37 */      F7.T1(b3, wv1, paramInt1, paramInt2); }
/*    */ 
/*    */   
/*    */   private void Fz0() {
/*    */     if (this.Ke) {
/*    */       short s1 = Di(jv.yF0), s2 = Di(jv.uJ), s3 = Di(jv.L00), s4 = Di(jv.yg), s5 = Di(jv.ef);
/*    */       km.u4.e20.W3(new hs0(s1, s2, s3, s4, s5));
/*    */       s1 = 0;
/*    */       while (s1 < jv.bv.length) {
/*    */         jv jv = jv.LD(s1);
/*    */         String str;
/*    */         if (!(str = ((of)this.wi[s1]).F2.PH0.toString()).equals(this.V1.Oh0(jv))) {
/*    */           String str1;
/*    */           if (str.equals(str1 = Ml0.OH0(jv.MQ))) {
/*    */             str = "";
/*    */           } else if (str.isEmpty()) {
/*    */             ((of)this.wi[s1]).Zh(str1);
/*    */           } 
/*    */           km.u4.e20.W3(new B00(jv, str));
/*    */         } 
/*    */         s1 = (byte)(s1 + 1);
/*    */       } 
/*    */     } 
/*    */   }
/*    */   
/*    */   private void dX(ge0 paramge0) {
/*    */     boolean bool = paramge0.TG0.nm0();
/*    */     this.HK.t8(this.d4.F2.toString(), bool);
/*    */     Ou0 = paramge0.TG0.nm0();
/*    */   }
/*    */   
/*    */   private void nS(ge0 paramge0, int paramInt) {
/*    */     boolean bool = paramge0.TG0.nm0();
/*    */     this.HK.t8(this.d4.F2.toString(), bool);
/*    */   }
/*    */   
/*    */   private void Ks() {
/*    */     UB0.Kg0.fN(new Tr0(this));
/*    */   }
/*    */   
/*    */   public final void V90(throws paramthrows) {
/*    */     if (this.V1.FH0.H8()) {
/*    */       String str;
/*    */       dQ dQ1 = this.mx;
/*    */       int i;
/*    */       if ((i = this.V1.FH0.s80 - (int)(System.currentTimeMillis() / 1000L)) < 301) {
/*    */         str = Ml0.OH0(2715);
/*    */       } else {
/*    */         str = LF.za(str);
/*    */       } 
/*    */       dQ1.E1(Ml0.Go(2714, str));
/*    */     } 
/*    */     if (this.V1.o20()) {
/*    */       nR();
/*    */       this.DX.cX(this.V1.FH0.Ku0);
/*    */       P4();
/*    */     } 
/*    */     super.V90(paramthrows);
/*    */   }
/*    */   
/*    */   public final void d40() {
/*    */     if (km.XU())
/*    */       QI(); 
/*    */     super.d40();
/*    */   }
/*    */   
/*    */   public final void IG0() {
/*    */     VA0.c90(this);
/*    */   }
/*    */   
/*    */   public final boolean i2(oa0 paramoa0) {
/*    */     if (B8.Wm0(paramoa0.cz0) && paramoa0.oO()) {
/*    */       if (js.com3(this))
/*    */         return super.i2(paramoa0); 
/*    */       if (this.JK.nv0() == 1 && paramoa0.GG0 == 34 && paramoa0.com8 == 4) {
/*    */         this.d4.BA();
/*    */         return true;
/*    */       } 
/*    */       if (h1.J20(paramoa0.GG0, BM.lc)) {
/*    */         pA.Dg0.ni(false);
/*    */         return true;
/*    */       } 
/*    */     } 
/*    */     return super.i2(paramoa0);
/*    */   }
/*    */   
/*    */   public final void AI() {
/*    */     // Byte code:
/*    */     //   0: getstatic f/km.a3 : Lf/vh0;
/*    */     //   3: getfield Ct : Lf/Jo;
/*    */     //   6: dup
/*    */     //   7: astore_1
/*    */     //   8: ifnonnull -> 12
/*    */     //   11: return
/*    */     //   12: getstatic f/UB0.Kg0 : Lf/Q50;
/*    */     //   15: aload_0
/*    */     //   16: aload_1
/*    */     //   17: <illegal opcode> run : (Lf/wv;Lf/Jo;)Ljava/lang/Runnable;
/*    */     //   22: invokevirtual fN : (Ljava/lang/Runnable;)V
/*    */     //   25: return
/*    */     // Line number table:
/*    */     //   Java source line number -> byte code offset
/*    */     //   #1	-> 3
/*    */     //   #2	-> 12
/*    */   }
/*    */   
/*    */   public final void nR() {
/*    */     // Byte code:
/*    */     //   0: aload_0
/*    */     //   1: getfield V1 : Lf/mG;
/*    */     //   4: getfield FH0 : Lf/yy;
/*    */     //   7: invokevirtual H8 : ()Z
/*    */     //   10: ifeq -> 87
/*    */     //   13: aload_0
/*    */     //   14: getfield V1 : Lf/mG;
/*    */     //   17: getfield FH0 : Lf/yy;
/*    */     //   20: invokevirtual H8 : ()Z
/*    */     //   23: ifeq -> 150
/*    */     //   26: aload_0
/*    */     //   27: dup
/*    */     //   28: getfield mx : Lf/dQ;
/*    */     //   31: astore_1
/*    */     //   32: getfield V1 : Lf/mG;
/*    */     //   35: getfield FH0 : Lf/yy;
/*    */     //   38: getfield s80 : I
/*    */     //   41: invokestatic currentTimeMillis : ()J
/*    */     //   44: ldc2_w 1000
/*    */     //   47: ldiv
/*    */     //   48: l2i
/*    */     //   49: isub
/*    */     //   50: dup
/*    */     //   51: istore_2
/*    */     //   52: sipush #301
/*    */     //   55: if_icmpge -> 68
/*    */     //   58: sipush #2715
/*    */     //   61: invokestatic OH0 : (I)Ljava/lang/String;
/*    */     //   64: astore_2
/*    */     //   65: goto -> 73
/*    */     //   68: iload_2
/*    */     //   69: invokestatic za : (I)Ljava/lang/String;
/*    */     //   72: astore_2
/*    */     //   73: aload_1
/*    */     //   74: sipush #2714
/*    */     //   77: aload_2
/*    */     //   78: invokestatic Go : (ILjava/lang/String;)Ljava/lang/String;
/*    */     //   81: invokevirtual E1 : (Ljava/lang/String;)V
/*    */     //   84: goto -> 150
/*    */     //   87: aload_0
/*    */     //   88: getfield mx : Lf/dQ;
/*    */     //   91: sipush #2712
/*    */     //   94: iconst_2
/*    */     //   95: anewarray java/lang/String
/*    */     //   98: dup
/*    */     //   99: dup
/*    */     //   100: iconst_0
/*    */     //   101: new java/lang/StringBuilder
/*    */     //   104: dup
/*    */     //   105: aload_0
/*    */     //   106: swap
/*    */     //   107: invokespecial <init> : ()V
/*    */     //   110: getfield V1 : Lf/mG;
/*    */     //   113: dup
/*    */     //   114: astore_1
/*    */     //   115: getfield Aux : Lf/Ut0;
/*    */     //   118: dup
/*    */     //   119: astore_2
/*    */     //   120: aload_1
/*    */     //   121: aload_2
/*    */     //   122: monitorenter
/*    */     //   123: getfield Aux : Lf/Ut0;
/*    */     //   126: getfield ir0 : I
/*    */     //   129: istore_1
/*    */     //   130: monitorexit
/*    */     //   131: iload_1
/*    */     //   132: ldc_w ''
/*    */     //   135: invokestatic Gl0 : (Ljava/lang/StringBuilder;ILjava/lang/String;)Ljava/lang/String;
/*    */     //   138: aastore
/*    */     //   139: iconst_1
/*    */     //   140: ldc_w '150'
/*    */     //   143: aastore
/*    */     //   144: invokestatic sB : (I[Ljava/lang/String;)Ljava/lang/String;
/*    */     //   147: invokevirtual E1 : (Ljava/lang/String;)V
/*    */     //   150: aload_0
/*    */     //   151: getfield Ke : Z
/*    */     //   154: ifeq -> 192
/*    */     //   157: aload_0
/*    */     //   158: dup
/*    */     //   159: getfield dw : Lf/Un;
/*    */     //   162: astore_1
/*    */     //   163: getfield V1 : Lf/mG;
/*    */     //   166: getfield FH0 : Lf/yy;
/*    */     //   169: invokevirtual H8 : ()Z
/*    */     //   172: ifeq -> 181
/*    */     //   175: sipush #2716
/*    */     //   178: goto -> 184
/*    */     //   181: sipush #2713
/*    */     //   184: invokestatic OH0 : (I)Ljava/lang/String;
/*    */     //   187: aload_1
/*    */     //   188: swap
/*    */     //   189: invokevirtual s6 : (Ljava/lang/String;)V
/*    */     //   192: aload_0
/*    */     //   193: dup
/*    */     //   194: getfield HK : Lf/JF0;
/*    */     //   197: invokevirtual h2 : ()V
/*    */     //   200: invokevirtual AI : ()V
/*    */     //   203: return
/*    */     //   204: astore_0
/*    */     //   205: aload_0
/*    */     //   206: aload_2
/*    */     //   207: monitorexit
/*    */     //   208: athrow
/*    */     // Line number table:
/*    */     //   Java source line number -> byte code offset
/*    */     //   #1	-> 4
/*    */     //   #2	-> 7
/*    */     //   #3	-> 14
/*    */     //   #4	-> 17
/*    */     //   #5	-> 20
/*    */     //   #6	-> 35
/*    */     //   #7	-> 38
/*    */     //   #8	-> 41
/*    */     //   #9	-> 81
/*    */     //   #10	-> 88
/*    */     //   #11	-> 115
/*    */     //   #12	-> 122
/*    */     //   #13	-> 126
/*    */     //   #14	-> 130
/*    */     //   #15	-> 132
/*    */     //   #16	-> 138
/*    */     //   #17	-> 166
/*    */     //   #18	-> 169
/*    */     //   #19	-> 207
/*    */     // Exception table:
/*    */     //   from	to	target	type
/*    */     //   123	129	204	finally
/*    */     //   130	131	204	finally
/*    */     //   205	208	204	finally
/*    */   }
/*    */   
/*    */   public final void P4() {
/*    */     if (this.V1 == null)
/*    */       return; 
/*    */     jv[] arrayOfJv;
/*    */     int i;
/*    */     byte b;
/*    */     for (i = (arrayOfJv = jv.bv).length, b = 0; b < i; ) {
/*    */       jv jv = arrayOfJv[b];
/*    */       boolean bool2 = this.V1.FH0.HP(jv, (short)1);
/*    */       (this.R0[jv.cJ][0]).TG0.Fx0(bool2);
/*    */       bool2 = this.V1.FH0.HP(jv, (short)2);
/*    */       (this.R0[jv.cJ][1]).TG0.Fx0(bool2);
/*    */       boolean bool1 = this.V1.FH0.HP(jv, (short)4);
/*    */       (this.R0[jv.cJ][2]).TG0.Fx0(bool1);
/*    */       b++;
/*    */     } 
/*    */     AI();
/*    */   }
/*    */   
/*    */   public final short Di(jv paramjv) {
/*    */     short s = 0;
/*    */     if ((this.R0[paramjv.cJ][0]).TG0.nm0())
/*    */       s = (short)1; 
/*    */     if ((this.R0[paramjv.cJ][1]).TG0.nm0())
/*    */       s = (short)(s | 0x2); 
/*    */     if ((this.R0[paramjv.cJ][2]).TG0.nm0())
/*    */       s = (short)(s | 0x4); 
/*    */     return s;
/*    */   } }


/* Location:              /Users/vnnsnnt/Documents/Codespace/JavaWorkspace/RedTrainer/src/main/java/org/trainer/client/PokeMMO.jar!/f/wv.class
 * Java compiler version: 8 (52.0)
 * JD-Core Version:       1.1.3
 */