/*    */ package f;public final class Wx extends JG0 { public static final ik EB = C00.gd(Wx.class); public static iQ ub0 = new iQ((byte)10, (byte)30, (byte)11, (byte)12); public static iQ KY = new iQ((byte)12, (byte)20, (byte)1, (byte)14); public static iQ O40 = new iQ((byte)1, (byte)23, (byte)2, (byte)6); public final Ip rI; public final Wr bd0; public final Wr Q70; public final Ip Sd0; public final vl c; public final Ip hh; public MS bc; public final JG0 xp0; public final of sB0; public final of nI0; public final Un HB; public W1 kw0; public ge0 ru0; public Un Tn; public Un[] vV; public final js Ja; public final dQ hN; public int UF; public Un xU; public rS ZV; public Qy0 e8; public Hu Cg0; public dQ xL; public dQ m9; public dQ Yq0; public dQ ko; public dQ Ck0; public boolean GE0; public Wx(js paramjs) { // Byte code:
/*    */     //   0: aload_0
/*    */     //   1: dup
/*    */     //   2: dup
/*    */     //   3: dup2
/*    */     //   4: invokespecial <init> : ()V
/*    */     //   7: iconst_0
/*    */     //   8: putfield UF : I
/*    */     //   11: aconst_null
/*    */     //   12: putfield xL : Lf/dQ;
/*    */     //   15: iconst_0
/*    */     //   16: putfield GE0 : Z
/*    */     //   19: ldc 'logingui'
/*    */     //   21: invokevirtual Xu : (Ljava/lang/String;)V
/*    */     //   24: getstatic f/km.mI0 : Lf/P1;
/*    */     //   27: getfield Mv0 : Z
/*    */     //   30: ifne -> 126
/*    */     //   33: getstatic f/G8.Mk0 : Z
/*    */     //   36: ifeq -> 126
/*    */     //   39: getstatic f/Wx.ub0 : Lf/iQ;
/*    */     //   42: invokevirtual AA0 : ()Z
/*    */     //   45: ifeq -> 61
/*    */     //   48: getstatic f/km.pm0 : Lf/VD0;
/*    */     //   51: iconst_2
/*    */     //   52: sipush #1083
/*    */     //   55: invokevirtual Wk0 : (BS)V
/*    */     //   58: goto -> 126
/*    */     //   61: getstatic f/Wx.O40 : Lf/iQ;
/*    */     //   64: invokevirtual AA0 : ()Z
/*    */     //   67: ifeq -> 73
/*    */     //   70: goto -> 82
/*    */     //   73: getstatic f/Wx.KY : Lf/iQ;
/*    */     //   76: invokevirtual AA0 : ()Z
/*    */     //   79: ifeq -> 95
/*    */     //   82: getstatic f/km.pm0 : Lf/VD0;
/*    */     //   85: iconst_2
/*    */     //   86: sipush #1108
/*    */     //   89: invokevirtual Wk0 : (BS)V
/*    */     //   92: goto -> 126
/*    */     //   95: bipush #50
/*    */     //   97: invokestatic qX : (I)I
/*    */     //   100: ifne -> 116
/*    */     //   103: getstatic f/km.pm0 : Lf/VD0;
/*    */     //   106: iconst_2
/*    */     //   107: sipush #1157
/*    */     //   110: invokevirtual Wk0 : (BS)V
/*    */     //   113: goto -> 126
/*    */     //   116: getstatic f/km.pm0 : Lf/VD0;
/*    */     //   119: iconst_2
/*    */     //   120: sipush #1159
/*    */     //   123: invokevirtual Wk0 : (BS)V
/*    */     //   126: aload_0
/*    */     //   127: dup
/*    */     //   128: aload_1
/*    */     //   129: putfield Ja : Lf/js;
/*    */     //   132: new f/Wr
/*    */     //   135: dup
/*    */     //   136: dup2
/*    */     //   137: astore_2
/*    */     //   138: aload_0
/*    */     //   139: aload_2
/*    */     //   140: dup
/*    */     //   141: invokespecial <init> : ()V
/*    */     //   144: putfield bd0 : Lf/Wr;
/*    */     //   147: iconst_0
/*    */     //   148: invokevirtual jJ0 : (Z)V
/*    */     //   151: sipush #1000
/*    */     //   154: invokestatic OH0 : (I)Ljava/lang/String;
/*    */     //   157: invokevirtual Lo : (Ljava/lang/String;)V
/*    */     //   160: ldc 'login-window'
/*    */     //   162: invokevirtual Xu : (Ljava/lang/String;)V
/*    */     //   165: new f/Ip
/*    */     //   168: dup
/*    */     //   169: dup
/*    */     //   170: astore_3
/*    */     //   171: invokespecial <init> : ()V
/*    */     //   174: putfield rI : Lf/Ip;
/*    */     //   177: invokestatic wK0 : ()Z
/*    */     //   180: ifeq -> 216
/*    */     //   183: aload_0
/*    */     //   184: dup
/*    */     //   185: new f/dQ
/*    */     //   188: dup
/*    */     //   189: aload_0
/*    */     //   190: swap
/*    */     //   191: dup
/*    */     //   192: bipush #37
/*    */     //   194: ldc 'This platform is now unsupported and the game may break at any time in the future.'
/*    */     //   196: invokestatic la : (ILjava/lang/String;)Ljava/lang/String;
/*    */     //   199: invokespecial <init> : (Ljava/lang/String;)V
/*    */     //   202: putfield xL : Lf/dQ;
/*    */     //   205: ldc 'warnlabel'
/*    */     //   207: invokevirtual Xu : (Ljava/lang/String;)V
/*    */     //   210: getfield xL : Lf/dQ;
/*    */     //   213: invokevirtual J8 : (Lf/JG0;)V
/*    */     //   216: aload_0
/*    */     //   217: dup
/*    */     //   218: dup
/*    */     //   219: dup2
/*    */     //   220: new f/of
/*    */     //   223: dup
/*    */     //   224: dup
/*    */     //   225: dup2
/*    */     //   226: astore #4
/*    */     //   228: aload_0
/*    */     //   229: aload #4
/*    */     //   231: dup
/*    */     //   232: invokespecial <init> : ()V
/*    */     //   235: putfield sB0 : Lf/of;
/*    */     //   238: <illegal opcode> test : ()Ljava/util/function/IntPredicate;
/*    */     //   243: invokeinterface negate : ()Ljava/util/function/IntPredicate;
/*    */     //   248: invokevirtual x30 : (Ljava/util/function/IntPredicate;)V
/*    */     //   251: getstatic f/Hf0.qz : Lf/Hf0;
/*    */     //   254: invokevirtual YV : (Lf/Hf0;)V
/*    */     //   257: invokevirtual LE : ()V
/*    */     //   260: new f/sW
/*    */     //   263: dup
/*    */     //   264: aload_0
/*    */     //   265: invokespecial <init> : (Lf/Wx;)V
/*    */     //   268: invokevirtual JD0 : (Lf/a70;)V
/*    */     //   271: new f/of
/*    */     //   274: dup
/*    */     //   275: dup
/*    */     //   276: astore #5
/*    */     //   278: aload_0
/*    */     //   279: aload #5
/*    */     //   281: dup
/*    */     //   282: invokespecial <init> : ()V
/*    */     //   285: putfield nI0 : Lf/of;
/*    */     //   288: iconst_1
/*    */     //   289: invokevirtual lpT2 : (Z)V
/*    */     //   292: new f/oz
/*    */     //   295: dup
/*    */     //   296: aload_0
/*    */     //   297: invokespecial <init> : (Lf/Wx;)V
/*    */     //   300: invokevirtual JD0 : (Lf/a70;)V
/*    */     //   303: new f/dQ
/*    */     //   306: dup
/*    */     //   307: astore #6
/*    */     //   309: aload #4
/*    */     //   311: aload_0
/*    */     //   312: aload #6
/*    */     //   314: dup
/*    */     //   315: sipush #1001
/*    */     //   318: invokestatic OH0 : (I)Ljava/lang/String;
/*    */     //   321: invokespecial <init> : (Ljava/lang/String;)V
/*    */     //   324: putfield ko : Lf/dQ;
/*    */     //   327: invokevirtual VH : (Lf/JG0;)V
/*    */     //   330: getfield ko : Lf/dQ;
/*    */     //   333: invokevirtual Xy : ()Ljava/lang/String;
/*    */     //   336: pop
/*    */     //   337: new f/dQ
/*    */     //   340: dup
/*    */     //   341: astore #6
/*    */     //   343: aload #5
/*    */     //   345: aload_0
/*    */     //   346: aload #6
/*    */     //   348: dup
/*    */     //   349: sipush #1002
/*    */     //   352: invokestatic OH0 : (I)Ljava/lang/String;
/*    */     //   355: invokespecial <init> : (Ljava/lang/String;)V
/*    */     //   358: putfield Yq0 : Lf/dQ;
/*    */     //   361: invokevirtual VH : (Lf/JG0;)V
/*    */     //   364: getfield Yq0 : Lf/dQ;
/*    */     //   367: invokevirtual Xy : ()Ljava/lang/String;
/*    */     //   370: pop
/*    */     //   371: new f/Un
/*    */     //   374: dup
/*    */     //   375: astore #6
/*    */     //   377: aload_0
/*    */     //   378: dup
/*    */     //   379: aload #6
/*    */     //   381: dup
/*    */     //   382: sipush #1000
/*    */     //   385: invokestatic OH0 : (I)Ljava/lang/String;
/*    */     //   388: invokespecial <init> : (Ljava/lang/String;)V
/*    */     //   391: putfield HB : Lf/Un;
/*    */     //   394: <illegal opcode> run : (Lf/Wx;)Ljava/lang/Runnable;
/*    */     //   399: invokevirtual tW : (Ljava/lang/Runnable;)V
/*    */     //   402: new f/ge0
/*    */     //   405: dup
/*    */     //   406: invokespecial <init> : ()V
/*    */     //   409: putfield ru0 : Lf/ge0;
/*    */     //   412: new f/dQ
/*    */     //   415: dup
/*    */     //   416: astore #6
/*    */     //   418: aload_0
/*    */     //   419: dup
/*    */     //   420: aload #6
/*    */     //   422: dup
/*    */     //   423: sipush #1025
/*    */     //   426: invokestatic OH0 : (I)Ljava/lang/String;
/*    */     //   429: invokespecial <init> : (Ljava/lang/String;)V
/*    */     //   432: putfield m9 : Lf/dQ;
/*    */     //   435: getfield ru0 : Lf/ge0;
/*    */     //   438: invokevirtual VH : (Lf/JG0;)V
/*    */     //   441: new f/W1
/*    */     //   444: dup
/*    */     //   445: aload_0
/*    */     //   446: swap
/*    */     //   447: dup
/*    */     //   448: invokespecial <init> : ()V
/*    */     //   451: putfield kw0 : Lf/W1;
/*    */     //   454: new f/J00
/*    */     //   457: dup
/*    */     //   458: aload_0
/*    */     //   459: invokespecial <init> : (Lf/Wx;)V
/*    */     //   462: invokevirtual D30 : (Ljava/lang/Runnable;)V
/*    */     //   465: new f/dQ
/*    */     //   468: dup
/*    */     //   469: astore #6
/*    */     //   471: aload_0
/*    */     //   472: dup
/*    */     //   473: aload #6
/*    */     //   475: dup
/*    */     //   476: sipush #1001
/*    */     //   479: invokestatic OH0 : (I)Ljava/lang/String;
/*    */     //   482: invokespecial <init> : (Ljava/lang/String;)V
/*    */     //   485: putfield Ck0 : Lf/dQ;
/*    */     //   488: getfield kw0 : Lf/W1;
/*    */     //   491: invokevirtual VH : (Lf/JG0;)V
/*    */     //   494: new f/Un
/*    */     //   497: dup
/*    */     //   498: aload_0
/*    */     //   499: swap
/*    */     //   500: dup
/*    */     //   501: sipush #1026
/*    */     //   504: invokestatic OH0 : (I)Ljava/lang/String;
/*    */     //   507: invokespecial <init> : (Ljava/lang/String;)V
/*    */     //   510: putfield Tn : Lf/Un;
/*    */     //   513: new f/Vu
/*    */     //   516: dup
/*    */     //   517: aload_0
/*    */     //   518: invokespecial <init> : (Lf/Wx;)V
/*    */     //   521: invokevirtual tW : (Ljava/lang/Runnable;)V
/*    */     //   524: invokevirtual Df : ()V
/*    */     //   527: getfield GE0 : Z
/*    */     //   530: ifne -> 549
/*    */     //   533: aload #5
/*    */     //   535: aload #4
/*    */     //   537: getstatic f/Fl0.Of0 : Ljava/lang/String;
/*    */     //   540: invokevirtual Zh : (Ljava/lang/String;)V
/*    */     //   543: getstatic f/Fl0.m00 : Ljava/lang/String;
/*    */     //   546: invokevirtual Zh : (Ljava/lang/String;)V
/*    */     //   549: new f/JG0
/*    */     //   552: dup
/*    */     //   553: dup2
/*    */     //   554: astore #4
/*    */     //   556: aload_0
/*    */     //   557: aload #4
/*    */     //   559: dup
/*    */     //   560: invokespecial <init> : ()V
/*    */     //   563: putfield xp0 : Lf/JG0;
/*    */     //   566: sipush #484
/*    */     //   569: sipush #143
/*    */     //   572: invokevirtual Tm : (II)Z
/*    */     //   575: pop
/*    */     //   576: sipush #484
/*    */     //   579: sipush #143
/*    */     //   582: invokevirtual uh0 : (II)V
/*    */     //   585: sipush #484
/*    */     //   588: sipush #143
/*    */     //   591: invokevirtual RI : (II)V
/*    */     //   594: getstatic f/Wx.ub0 : Lf/iQ;
/*    */     //   597: invokevirtual AA0 : ()Z
/*    */     //   600: ifeq -> 614
/*    */     //   603: aload #4
/*    */     //   605: ldc_w 'logo-hween'
/*    */     //   608: invokevirtual Xu : (Ljava/lang/String;)V
/*    */     //   611: goto -> 622
/*    */     //   614: aload #4
/*    */     //   616: ldc_w 'logo'
/*    */     //   619: invokevirtual Xu : (Ljava/lang/String;)V
/*    */     //   622: aload_0
/*    */     //   623: aload #4
/*    */     //   625: invokevirtual J8 : (Lf/JG0;)V
/*    */     //   628: invokestatic Nr : ()Z
/*    */     //   631: ifeq -> 656
/*    */     //   634: aload_0
/*    */     //   635: dup
/*    */     //   636: new f/Qy0
/*    */     //   639: dup
/*    */     //   640: astore #4
/*    */     //   642: aload_0
/*    */     //   643: invokespecial <init> : (Lf/Wx;)V
/*    */     //   646: aload #4
/*    */     //   648: putfield e8 : Lf/Qy0;
/*    */     //   651: aload #4
/*    */     //   653: invokevirtual J8 : (Lf/JG0;)V
/*    */     //   656: aload_0
/*    */     //   657: aload_2
/*    */     //   658: dup
/*    */     //   659: aload_3
/*    */     //   660: aload_0
/*    */     //   661: dup
/*    */     //   662: dup
/*    */     //   663: new f/Hu
/*    */     //   666: dup
/*    */     //   667: dup
/*    */     //   668: astore_2
/*    */     //   669: invokespecial <init> : ()V
/*    */     //   672: putfield Cg0 : Lf/Hu;
/*    */     //   675: aload_2
/*    */     //   676: invokevirtual J8 : (Lf/JG0;)V
/*    */     //   679: new f/vl
/*    */     //   682: dup
/*    */     //   683: dup
/*    */     //   684: aload_0
/*    */     //   685: swap
/*    */     //   686: dup
/*    */     //   687: invokespecial <init> : ()V
/*    */     //   690: putfield c : Lf/vl;
/*    */     //   693: iconst_0
/*    */     //   694: invokevirtual CQ : (Z)V
/*    */     //   697: invokevirtual J8 : (Lf/JG0;)V
/*    */     //   700: invokevirtual J8 : (Lf/JG0;)V
/*    */     //   703: invokevirtual J8 : (Lf/JG0;)V
/*    */     //   706: invokestatic Nr : ()Z
/*    */     //   709: ifeq -> 904
/*    */     //   712: aload_0
/*    */     //   713: bipush #9
/*    */     //   715: anewarray f/Un
/*    */     //   718: putfield vV : [Lf/Un;
/*    */     //   721: iconst_0
/*    */     //   722: istore_2
/*    */     //   723: iload_2
/*    */     //   724: aload_0
/*    */     //   725: getfield vV : [Lf/Un;
/*    */     //   728: dup
/*    */     //   729: astore_3
/*    */     //   730: arraylength
/*    */     //   731: if_icmpge -> 762
/*    */     //   734: aload_0
/*    */     //   735: dup
/*    */     //   736: aload_3
/*    */     //   737: iload_2
/*    */     //   738: new f/Un
/*    */     //   741: dup
/*    */     //   742: astore_3
/*    */     //   743: invokespecial <init> : ()V
/*    */     //   746: aload_3
/*    */     //   747: aastore
/*    */     //   748: getfield vV : [Lf/Un;
/*    */     //   751: iload_2
/*    */     //   752: aaload
/*    */     //   753: invokevirtual J8 : (Lf/JG0;)V
/*    */     //   756: iinc #2, 1
/*    */     //   759: goto -> 723
/*    */     //   762: aload_0
/*    */     //   763: dup
/*    */     //   764: dup2
/*    */     //   765: dup2
/*    */     //   766: dup2
/*    */     //   767: aload_3
/*    */     //   768: iconst_0
/*    */     //   769: aaload
/*    */     //   770: new f/Iu0
/*    */     //   773: dup
/*    */     //   774: aload_1
/*    */     //   775: invokespecial <init> : (Lf/js;)V
/*    */     //   778: invokevirtual tW : (Ljava/lang/Runnable;)V
/*    */     //   781: getfield vV : [Lf/Un;
/*    */     //   784: iconst_1
/*    */     //   785: aaload
/*    */     //   786: new f/u0
/*    */     //   789: dup
/*    */     //   790: invokespecial <init> : ()V
/*    */     //   793: invokevirtual tW : (Ljava/lang/Runnable;)V
/*    */     //   796: getfield vV : [Lf/Un;
/*    */     //   799: iconst_2
/*    */     //   800: aaload
/*    */     //   801: new f/eK0
/*    */     //   804: dup
/*    */     //   805: invokespecial <init> : ()V
/*    */     //   808: invokevirtual tW : (Ljava/lang/Runnable;)V
/*    */     //   811: getfield vV : [Lf/Un;
/*    */     //   814: iconst_3
/*    */     //   815: aaload
/*    */     //   816: new f/WB
/*    */     //   819: dup
/*    */     //   820: invokespecial <init> : ()V
/*    */     //   823: invokevirtual tW : (Ljava/lang/Runnable;)V
/*    */     //   826: getfield vV : [Lf/Un;
/*    */     //   829: iconst_4
/*    */     //   830: aaload
/*    */     //   831: new f/wN
/*    */     //   834: dup
/*    */     //   835: invokespecial <init> : ()V
/*    */     //   838: invokevirtual tW : (Ljava/lang/Runnable;)V
/*    */     //   841: getfield vV : [Lf/Un;
/*    */     //   844: iconst_5
/*    */     //   845: aaload
/*    */     //   846: new f/jw
/*    */     //   849: dup
/*    */     //   850: invokespecial <init> : ()V
/*    */     //   853: invokevirtual tW : (Ljava/lang/Runnable;)V
/*    */     //   856: getfield vV : [Lf/Un;
/*    */     //   859: bipush #6
/*    */     //   861: aaload
/*    */     //   862: new f/ng0
/*    */     //   865: dup
/*    */     //   866: invokespecial <init> : ()V
/*    */     //   869: invokevirtual tW : (Ljava/lang/Runnable;)V
/*    */     //   872: getfield vV : [Lf/Un;
/*    */     //   875: bipush #7
/*    */     //   877: aaload
/*    */     //   878: new f/Iv
/*    */     //   881: dup
/*    */     //   882: invokespecial <init> : ()V
/*    */     //   885: invokevirtual tW : (Ljava/lang/Runnable;)V
/*    */     //   888: getfield vV : [Lf/Un;
/*    */     //   891: bipush #8
/*    */     //   893: aaload
/*    */     //   894: new f/kn
/*    */     //   897: dup
/*    */     //   898: invokespecial <init> : ()V
/*    */     //   901: invokevirtual tW : (Ljava/lang/Runnable;)V
/*    */     //   904: aload_0
/*    */     //   905: dup
/*    */     //   906: dup2
/*    */     //   907: dup2
/*    */     //   908: new f/Wr
/*    */     //   911: dup
/*    */     //   912: dup
/*    */     //   913: dup2
/*    */     //   914: dup2
/*    */     //   915: aload_0
/*    */     //   916: swap
/*    */     //   917: dup
/*    */     //   918: invokespecial <init> : ()V
/*    */     //   921: putfield Q70 : Lf/Wr;
/*    */     //   924: iconst_0
/*    */     //   925: invokevirtual jJ0 : (Z)V
/*    */     //   928: iconst_0
/*    */     //   929: invokevirtual CQ : (Z)V
/*    */     //   932: sipush #1013
/*    */     //   935: invokestatic OH0 : (I)Ljava/lang/String;
/*    */     //   938: invokevirtual Lo : (Ljava/lang/String;)V
/*    */     //   941: ldc_w 'serverselect-window'
/*    */     //   944: invokevirtual Xu : (Ljava/lang/String;)V
/*    */     //   947: new f/Ip
/*    */     //   950: dup
/*    */     //   951: dup
/*    */     //   952: aload_0
/*    */     //   953: swap
/*    */     //   954: dup
/*    */     //   955: invokespecial <init> : ()V
/*    */     //   958: putfield Sd0 : Lf/Ip;
/*    */     //   961: invokevirtual MB : ()Lf/Ip;
/*    */     //   964: pop
/*    */     //   965: invokevirtual J8 : (Lf/JG0;)V
/*    */     //   968: invokevirtual J8 : (Lf/JG0;)V
/*    */     //   971: new f/Ip
/*    */     //   974: dup
/*    */     //   975: dup2
/*    */     //   976: dup2
/*    */     //   977: astore_2
/*    */     //   978: aload_0
/*    */     //   979: dup
/*    */     //   980: dup2
/*    */     //   981: aload_2
/*    */     //   982: dup
/*    */     //   983: aload_0
/*    */     //   984: aload_2
/*    */     //   985: dup
/*    */     //   986: invokespecial <init> : ()V
/*    */     //   989: putfield hh : Lf/Ip;
/*    */     //   992: ldc_w 'login-panel'
/*    */     //   995: invokevirtual Xu : (Ljava/lang/String;)V
/*    */     //   998: iconst_0
/*    */     //   999: invokevirtual wI0 : (Z)V
/*    */     //   1002: new f/MS
/*    */     //   1005: dup
/*    */     //   1006: invokespecial <init> : ()V
/*    */     //   1009: putfield bc : Lf/MS;
/*    */     //   1012: new f/da
/*    */     //   1015: dup
/*    */     //   1016: dup2
/*    */     //   1017: astore_3
/*    */     //   1018: aload_0
/*    */     //   1019: getfield bc : Lf/MS;
/*    */     //   1022: invokespecial <init> : (Lf/Zq0;)V
/*    */     //   1025: sipush #400
/*    */     //   1028: sipush #350
/*    */     //   1031: invokevirtual Tm : (II)Z
/*    */     //   1034: pop
/*    */     //   1035: new f/o
/*    */     //   1038: dup
/*    */     //   1039: invokespecial <init> : ()V
/*    */     //   1042: invokevirtual Kh0 : (Lf/LPt7;)V
/*    */     //   1045: new f/rS
/*    */     //   1048: dup
/*    */     //   1049: aload_0
/*    */     //   1050: swap
/*    */     //   1051: dup
/*    */     //   1052: invokespecial <init> : ()V
/*    */     //   1055: putfield ZV : Lf/rS;
/*    */     //   1058: iconst_2
/*    */     //   1059: invokevirtual zG0 : (I)V
/*    */     //   1062: getfield ZV : Lf/rS;
/*    */     //   1065: invokevirtual xZ : ()V
/*    */     //   1068: getfield ZV : Lf/rS;
/*    */     //   1071: aload_3
/*    */     //   1072: invokevirtual Gz0 : (Lf/JG0;)V
/*    */     //   1075: getfield ZV : Lf/rS;
/*    */     //   1078: ldc_w 'tos-content'
/*    */     //   1081: invokevirtual Xu : (Ljava/lang/String;)V
/*    */     //   1084: new f/Un
/*    */     //   1087: dup
/*    */     //   1088: aload_0
/*    */     //   1089: swap
/*    */     //   1090: dup
/*    */     //   1091: bipush #60
/*    */     //   1093: invokestatic OH0 : (I)Ljava/lang/String;
/*    */     //   1096: invokespecial <init> : (Ljava/lang/String;)V
/*    */     //   1099: putfield xU : Lf/Un;
/*    */     //   1102: new f/G10
/*    */     //   1105: dup
/*    */     //   1106: invokespecial <init> : ()V
/*    */     //   1109: invokevirtual tW : (Ljava/lang/Runnable;)V
/*    */     //   1112: new f/Un
/*    */     //   1115: dup
/*    */     //   1116: dup
/*    */     //   1117: astore_3
/*    */     //   1118: bipush #63
/*    */     //   1120: invokestatic OH0 : (I)Ljava/lang/String;
/*    */     //   1123: invokespecial <init> : (Ljava/lang/String;)V
/*    */     //   1126: new f/yT
/*    */     //   1129: dup
/*    */     //   1130: invokespecial <init> : ()V
/*    */     //   1133: invokevirtual tW : (Ljava/lang/Runnable;)V
/*    */     //   1136: invokevirtual mE0 : ()Lf/g0;
/*    */     //   1139: aload_0
/*    */     //   1140: getfield ZV : Lf/rS;
/*    */     //   1143: invokevirtual Ya : (Lf/JG0;)Lf/U90;
/*    */     //   1146: aload_2
/*    */     //   1147: invokevirtual d7 : ()Lf/cr0;
/*    */     //   1150: invokevirtual Em0 : ()Lf/U90;
/*    */     //   1153: iconst_2
/*    */     //   1154: anewarray f/JG0
/*    */     //   1157: dup
/*    */     //   1158: dup
/*    */     //   1159: aload_0
/*    */     //   1160: getfield xU : Lf/Un;
/*    */     //   1163: iconst_0
/*    */     //   1164: swap
/*    */     //   1165: aastore
/*    */     //   1166: iconst_1
/*    */     //   1167: aload_3
/*    */     //   1168: aastore
/*    */     //   1169: invokevirtual Mg : ([Lf/JG0;)Lf/U90;
/*    */     //   1172: invokevirtual Em0 : ()Lf/U90;
/*    */     //   1175: invokevirtual ee0 : (Lf/U90;)Lf/U90;
/*    */     //   1178: invokevirtual rK0 : (Lf/U90;)V
/*    */     //   1181: invokevirtual d7 : ()Lf/cr0;
/*    */     //   1184: aload_0
/*    */     //   1185: getfield ZV : Lf/rS;
/*    */     //   1188: invokevirtual Ya : (Lf/JG0;)Lf/U90;
/*    */     //   1191: aload_2
/*    */     //   1192: iconst_2
/*    */     //   1193: anewarray f/JG0
/*    */     //   1196: dup
/*    */     //   1197: dup
/*    */     //   1198: aload_0
/*    */     //   1199: getfield xU : Lf/Un;
/*    */     //   1202: iconst_0
/*    */     //   1203: swap
/*    */     //   1204: aastore
/*    */     //   1205: iconst_1
/*    */     //   1206: aload_3
/*    */     //   1207: aastore
/*    */     //   1208: invokevirtual AUX : ([Lf/JG0;)Lf/U90;
/*    */     //   1211: invokevirtual ee0 : (Lf/U90;)Lf/U90;
/*    */     //   1214: invokevirtual WN : (Lf/U90;)V
/*    */     //   1217: invokevirtual J8 : (Lf/JG0;)V
/*    */     //   1220: new f/dQ
/*    */     //   1223: dup
/*    */     //   1224: dup
/*    */     //   1225: astore_0
/*    */     //   1226: ldc_w ''
/*    */     //   1229: invokespecial <init> : (Ljava/lang/String;)V
/*    */     //   1232: putfield hN : Lf/dQ;
/*    */     //   1235: invokevirtual qq0 : ()V
/*    */     //   1238: aload_0
/*    */     //   1239: invokevirtual J8 : (Lf/JG0;)V
/*    */     //   1242: invokevirtual Og0 : ()V
/*    */     //   1245: getstatic f/h1.x1 : Z
/*    */     //   1248: ifeq -> 1263
/*    */     //   1251: invokestatic N2 : ()Lf/js;
/*    */     //   1254: sipush #1188
/*    */     //   1257: invokestatic OH0 : (I)Ljava/lang/String;
/*    */     //   1260: invokevirtual ln0 : (Ljava/lang/String;)V
/*    */     //   1263: getstatic f/h1.pB0 : Ljava/lang/String;
/*    */     //   1266: astore_0
/*    */     //   1267: ldc_w 'en'
/*    */     //   1270: aload_0
/*    */     //   1271: invokevirtual equalsIgnoreCase : (Ljava/lang/String;)Z
/*    */     //   1274: ifne -> 1318
/*    */     //   1277: ldc_w 'fr'
/*    */     //   1280: aload_0
/*    */     //   1281: invokevirtual equalsIgnoreCase : (Ljava/lang/String;)Z
/*    */     //   1284: ifne -> 1318
/*    */     //   1287: ldc_w 'es'
/*    */     //   1290: aload_0
/*    */     //   1291: invokevirtual equalsIgnoreCase : (Ljava/lang/String;)Z
/*    */     //   1294: ifne -> 1318
/*    */     //   1297: ldc_w 'de'
/*    */     //   1300: aload_0
/*    */     //   1301: invokevirtual equalsIgnoreCase : (Ljava/lang/String;)Z
/*    */     //   1304: ifne -> 1318
/*    */     //   1307: ldc_w 'it'
/*    */     //   1310: aload_0
/*    */     //   1311: invokevirtual equalsIgnoreCase : (Ljava/lang/String;)Z
/*    */     //   1314: ifne -> 1318
/*    */     //   1317: return
/*    */     //   1318: aload_0
/*    */     //   1319: invokestatic k60 : (Ljava/lang/String;)Lf/Xv0;
/*    */     //   1322: dup
/*    */     //   1323: astore_2
/*    */     //   1324: ifnull -> 1335
/*    */     //   1327: aload_2
/*    */     //   1328: invokevirtual D70 : ()Ljava/lang/String;
/*    */     //   1331: astore_2
/*    */     //   1332: goto -> 1337
/*    */     //   1335: aload_0
/*    */     //   1336: astore_2
/*    */     //   1337: new java/lang/StringBuilder
/*    */     //   1340: dup
/*    */     //   1341: astore_3
/*    */     //   1342: invokespecial <init> : ()V
/*    */     //   1345: iconst_0
/*    */     //   1346: istore #4
/*    */     //   1348: iload #4
/*    */     //   1350: iconst_5
/*    */     //   1351: if_icmpge -> 1536
/*    */     //   1354: ldc_w ''
/*    */     //   1357: astore #5
/*    */     //   1359: getstatic f/km.mI0 : Lf/P1;
/*    */     //   1362: iload #4
/*    */     //   1364: invokevirtual Sa : (B)Lf/s40;
/*    */     //   1367: dup
/*    */     //   1368: astore #6
/*    */     //   1370: ifnull -> 1383
/*    */     //   1373: aload #6
/*    */     //   1375: invokevirtual bV : ()Lf/uq;
/*    */     //   1378: invokevirtual lz0 : ()Ljava/lang/String;
/*    */     //   1381: astore #5
/*    */     //   1383: getstatic f/km.mI0 : Lf/P1;
/*    */     //   1386: iload #4
/*    */     //   1388: invokevirtual LpT7 : (B)Lf/HI;
/*    */     //   1391: dup
/*    */     //   1392: astore #7
/*    */     //   1394: ifnull -> 1404
/*    */     //   1397: aload #7
/*    */     //   1399: invokevirtual SO : ()Ljava/lang/String;
/*    */     //   1402: astore #5
/*    */     //   1404: aload #5
/*    */     //   1406: invokevirtual isEmpty : ()Z
/*    */     //   1409: ifeq -> 1415
/*    */     //   1412: goto -> 1526
/*    */     //   1415: aload #5
/*    */     //   1417: aload_0
/*    */     //   1418: invokevirtual equalsIgnoreCase : (Ljava/lang/String;)Z
/*    */     //   1421: ifne -> 1526
/*    */     //   1424: aload_3
/*    */     //   1425: invokevirtual length : ()I
/*    */     //   1428: ifle -> 1439
/*    */     //   1431: aload_3
/*    */     //   1432: ldc_w '\\n\\n'
/*    */     //   1435: invokevirtual append : (Ljava/lang/String;)Ljava/lang/StringBuilder;
/*    */     //   1438: pop
/*    */     //   1439: aload #7
/*    */     //   1441: ldc_w ''
/*    */     //   1444: astore #5
/*    */     //   1446: ifnull -> 1462
/*    */     //   1449: aload #7
/*    */     //   1451: invokevirtual T50 : ()Lf/RD0;
/*    */     //   1454: invokevirtual Lh0 : ()Ljava/lang/String;
/*    */     //   1457: astore #5
/*    */     //   1459: goto -> 1477
/*    */     //   1462: aload #6
/*    */     //   1464: ifnull -> 1477
/*    */     //   1467: aload #6
/*    */     //   1469: invokevirtual GP : ()Lf/RD0;
/*    */     //   1472: invokevirtual Lh0 : ()Ljava/lang/String;
/*    */     //   1475: astore #5
/*    */     //   1477: aload_3
/*    */     //   1478: iconst_3
/*    */     //   1479: anewarray java/lang/String
/*    */     //   1482: dup
/*    */     //   1483: dup2
/*    */     //   1484: astore #6
/*    */     //   1486: iload #4
/*    */     //   1488: bipush #90
/*    */     //   1490: iadd
/*    */     //   1491: invokestatic OH0 : (I)Ljava/lang/String;
/*    */     //   1494: iconst_0
/*    */     //   1495: swap
/*    */     //   1496: aastore
/*    */     //   1497: iconst_1
/*    */     //   1498: aload_2
/*    */     //   1499: aastore
/*    */     //   1500: iconst_2
/*    */     //   1501: aload #5
/*    */     //   1503: aastore
/*    */     //   1504: sipush #1187
/*    */     //   1507: aload #6
/*    */     //   1509: invokestatic sB : (I[Ljava/lang/String;)Ljava/lang/String;
/*    */     //   1512: dup
/*    */     //   1513: getstatic f/Wx.EB : Lf/ik;
/*    */     //   1516: swap
/*    */     //   1517: invokeinterface error : (Ljava/lang/String;)V
/*    */     //   1522: invokevirtual append : (Ljava/lang/String;)Ljava/lang/StringBuilder;
/*    */     //   1525: pop
/*    */     //   1526: iload #4
/*    */     //   1528: iconst_1
/*    */     //   1529: iadd
/*    */     //   1530: i2b
/*    */     //   1531: istore #4
/*    */     //   1533: goto -> 1348
/*    */     //   1536: aload_3
/*    */     //   1537: invokevirtual length : ()I
/*    */     //   1540: ifle -> 1556
/*    */     //   1543: getstatic f/UB0.Kg0 : Lf/Q50;
/*    */     //   1546: aload_1
/*    */     //   1547: aload_3
/*    */     //   1548: <illegal opcode> run : (Lf/js;Ljava/lang/StringBuilder;)Ljava/lang/Runnable;
/*    */     //   1553: invokevirtual fN : (Ljava/lang/Runnable;)V
/*  1 */     //   1556: return } private void o20() { this.sB0.Be0("", false); this.nI0.Be0("", false); } private void vT() { this.Ja.So0(false); this.Ja.Gl(); this.Ja.Pu(-1, Ml0.OH0(final.dy.HD0)); } private void lx(P10 paramP10, int paramInt, byte[] paramArrayOfbyte) { this(paramP10, 0, new byte[0]); r8.KK = paramInt; r8.Ge0 = paramArrayOfbyte; R8 r8; (r8 = new R8())
/*    */       
/*  3 */       .YG0 = this.Ja;
/*    */     
/*  5 */     if (!sh0.Ep0(km.u4 = new R8()) || 
/*  6 */       km.u4
/*  7 */       .e20 == null)
/*  8 */     { UB0.Kg0.fN(this::vT); return; }  is is; if ((is = km.SE0) != null) { is.ni0(); km.SE0 = null; }  UB0.Kg0.fN(this::o20); }
/*  9 */   public final void Df() { arrayList.add(new nt(Ml0.OH0(1028), null)); this(arrayList); OZ oZ; this.kw0.rk0(oZ); ArrayList<nt> arrayList; if ((arrayList = cl0.kt0()).isEmpty()) { hc(false); return; }  this.kw0.Z30(0); byte b; Iterator<nt> iterator; for (b = 0, iterator = arrayList.iterator(); iterator.hasNext(); ) { if (((nt)iterator.next()).sG.equalsIgnoreCase(cl0.Nt)) this.kw0.Z30(b);  b++; }  if (arrayList.size() == 1) this.sB0.Be0(((nt)oZ.Fj.get(0)).sG, false);  } public final void hc(boolean paramBoolean) { of of1; dQ dQ1; of of2; Un un; dQ dQ2; String str; this.GE0 = paramBoolean; if (paramBoolean) { dQ1 = this.Ck0; } else { dQ1 = this.ko; }  if (paramBoolean) { W1 w1 = this.kw0; } else { of2 = this.sB0; }  if (paramBoolean) { un = this.Tn; } else { un = this.ru0; }  if (paramBoolean) { this(); } else { dQ2 = this.m9; }  this.kw0.wI0(paramBoolean); this.Ck0.wI0(paramBoolean); int i; this.ko.wI0(i = paramBoolean ^ true); this.sB0.wI0(i); this.sB0.sk0(i); if (this.kw0.Wa0.my.pu() == 1) { this.sB0.wI0(true); of2 = this.sB0; }  this.m9.wI0(i); this.ru0.wI0(i); this.nI0.sk0(i); this.nI0.lpT2(i); if (paramBoolean) { of1 = this.nI0; str = Ml0.OH0(1027); } else { of1 = this.nI0; str = ""; }  of1.Be0(str, false); this.rI.gx(); U90 u901 = this.rI.AUX(new JG0[] { dQ1, this.Yq0 }), u902 = this.rI.AUX(new JG0[] { of2, this.nI0 }), u903 = this.rI.vo0(new JG0[] { un, dQ2 }).Em0().Ya(this.HB); this.rI.rK0(Mr.X60(this.rI, this.rI).ee0(this.rI.Gs(new U90[] { u901, u902 })).ee0(u903)); this.rI.WN(V2.Ur(this.rI, this.rI).ee0(this.rI.AUX(new JG0[] { dQ1, of2 })).ee0(this.rI.AUX(new JG0[] { this.Yq0, this.nI0 })).ee0(this.rI.AUX(new JG0[] { un, dQ2, this.HB }))); } public final void LM(throws paramthrows) { if (km.XU() || this.GE0) { VA0.c90(this.HB); } else { VA0.c90(this.sB0); }  if (Fl0.NM) mj0();  } public final void Og0() { if (km.XU()) return;  Un[] arrayOfUn; for (byte b = 0; b < (arrayOfUn = this.vV).length; b++) { char c = Character.MIN_VALUE; switch (b) { case 8: c = 'ϱ'; break;case 7: c = 'ϰ'; break;case 6: c = 'Ѥ'; break;case 5: c = 'ϯ'; break;case 4: c = 'Ϯ'; break;case 3: c = 'ϭ'; break;case 2: c = 'Ҧ'; break;case 1: c = 'җ'; break;case 0: c = 'Ҕ'; break; }  arrayOfUn[b].s6(Ml0.OH0(c)); }  this.e8.D50(); } public final void d40() { this.hN.mM(); this.hN.ME(3, 3); this.bd0.mM(); int j = this.Ja.RS(); j = this.Ja.e3(); this.bd0.ME(JO.Se0(this.Ja.qF(), this.bd0.xY, 2, j), (this.Ja.Hy() - this.bd0.HC) / 2 + j); this.c.mM(); j = this.Ja.RS();
/*    */ 
/*    */     
/* 12 */     j = this.Ja.e3();
/*    */ 
/*    */     
/* 15 */     this.c.ME(JO.Se0(this.Ja.qF(), this.c.xY, 2, j), (this.Ja.Hy() - this.c.HC) / 2 + j); Qy0 qy0;
/* 16 */     if ((qy0 = this.e8) != null) { int k = this.Ja.e3(); qy0
/*    */         
/* 18 */         .ME(0, this.Ja.Hy() - this.e8.HC + k); }
/* 19 */      Hu hu; if ((hu = this.Cg0) != null) { hu.mM(); this.Cg0.QJ0(et.F30, 0, -100); }  if (this.vV != null) { Un[] arrayOfUn; for (byte b = 0; b < (arrayOfUn = this.vV).length; ) { arrayOfUn[b].uh0(200, 26); this.vV[b].Tm(200, 26); int k = RS();
/* 20 */         k = qF() - (this.vV[b]).xY + k - 4;
/* 21 */         int m = e3();
/*    */         
/*    */         Un[] arrayOfUn1;
/* 24 */         this.vV[b].ME(k, Hy() - ((arrayOfUn1 = this.vV)[b]).HC + m - (arrayOfUn1.length - 1 - b) * 26 + 4); b++; }  }
/* 25 */      int i = this.Ja.RS();
/*    */ 
/*    */     
/* 28 */     i = this.Ja.e3();
/*    */ 
/*    */     
/* 31 */     this.Q70.ME(JO.Se0(this.Ja.qF(), this.Q70.xY, 2, i), (this.Ja.Hy() - this.Q70.HC) / 2 + i);
/* 32 */     this.xp0.Tm(484, 143); i = this.Ja.RS();
/*    */ 
/*    */     
/* 35 */     i = this.Ja.e3() - 200;
/*    */ 
/*    */     
/* 38 */     this.xp0.ME(JO.Se0(this.Ja.qF(), this.xp0.xY, 2, i), (this.Ja.Hy() - this.xp0.HC) / 2 + i);
/* 39 */     this.hh.mM(); i = this.Ja.RS();
/*    */ 
/*    */     
/* 42 */     i = this.Ja.e3();
/*    */ 
/*    */     
/* 45 */     this.hh.ME(JO.Se0(this.Ja.qF(), this.hh.xY, 2, i), (this.Ja.Hy() - this.hh.HC) / 2 + i); dQ dQ1;
/* 46 */     if ((dQ1 = this.xL) != null) { dQ1.mM(); this.xL
/*    */ 
/*    */         
/* 49 */         .ME(km.wI0.dG() / 2 - this.xL.xY / 2, 50); }
/*    */      }
/*    */ 
/*    */   
/*    */   public final void V90(throws paramthrows) {
/*    */     UB0.Kg0.fN(new x10(this));
/*    */     js js1;
/*    */     if (km.mI0.Mv0 && (js1 = js.vu0) != null && js1.Lz != null) {
/*    */       boolean bool = false;
/*    */       Ip ip;
/*    */       if ((ip = this.rI).dP)
/*    */         ip.wI0(bool); 
/*    */       if (p3())
/*    */         VA0.c90(js.vu0.Lz); 
/*    */     } 
/*    */     super.V90(paramthrows);
/*    */   }
/*    */   
/*    */   public final void DM(P10 paramP10, int paramInt, byte[] paramArrayOfbyte) {
/*    */     // Byte code:
/*    */     //   0: getstatic f/km.SE0 : Lf/is;
/*    */     //   3: dup
/*    */     //   4: astore #4
/*    */     //   6: ifnull -> 18
/*    */     //   9: aload #4
/*    */     //   11: invokevirtual ni0 : ()V
/*    */     //   14: aconst_null
/*    */     //   15: putstatic f/km.SE0 : Lf/is;
/*    */     //   18: aload_0
/*    */     //   19: aload_1
/*    */     //   20: aload_0
/*    */     //   21: dup
/*    */     //   22: getfield Ja : Lf/js;
/*    */     //   25: iconst_1
/*    */     //   26: invokevirtual So0 : (Z)V
/*    */     //   29: getfield Ja : Lf/js;
/*    */     //   32: aload_0
/*    */     //   33: invokevirtual jf0 : (Lf/JG0;)Z
/*    */     //   36: pop
/*    */     //   37: getstatic f/A1.L7 : Lf/A1;
/*    */     //   40: astore_0
/*    */     //   41: iload_2
/*    */     //   42: aload_3
/*    */     //   43: <illegal opcode> run : (Lf/Wx;Lf/P10;I[B)Ljava/lang/Runnable;
/*    */     //   48: aload_0
/*    */     //   49: getfield nc : Lf/cK0;
/*    */     //   52: swap
/*    */     //   53: invokevirtual execute : (Ljava/lang/Runnable;)V
/*    */     //   56: return
/*    */     // Line number table:
/*    */     //   Java source line number -> byte code offset
/*    */     //   #1	-> 37
/*    */     //   #2	-> 43
/*    */     //   #3	-> 49
/*    */     //   #4	-> 53
/*    */   }
/*    */   
/*    */   public final void mj0() {
/*    */     if (this.Bo0 != null) {
/*    */       if (km.mI0.Mv0) {
/*    */         js.vu0.DJ("You do not have the minimum required roms to login.", null);
/*    */         return;
/*    */       } 
/*    */       M5(true);
/*    */       if (km.SE0 == null) {
/*    */         nt nt;
/*    */         transient transient;
/*    */         if (this.GE0) {
/*    */           A60 a60;
/*    */           cl0.Nt = (nt = (nt)(a60 = this.kw0.Wa0).my.c90(this.go)).sG;
/*    */           Cq.RG0((new File(Bz.CN, "savedcredentials.properties")).getAbsolutePath(), cl0.class);
/*    */           km.SE0 = new is(this.sG, "", false, this);
/*    */         } else {
/*    */           String str = ((Wx)super).nI0.F2.PH0.toString();
/*    */           km.SE0 = new is(((Wx)super).sB0.F2.PH0.toString(), this, ((Wx)super).ru0.TG0.nm0(), null);
/*    */         } 
/*    */         this();
/*    */         A1.L7.nc.execute(this);
/*    */       } 
/*    */     } 
/*    */   }
/*    */   
/*    */   public final void M5(boolean paramBoolean) {
/*    */     boolean bool;
/*    */     of of1 = this.sB0;
/*    */     if (!this.GE0 && paramBoolean) {
/*    */       bool = true;
/*    */     } else {
/*    */       bool = false;
/*    */     } 
/*    */     of1.sk0(bool);
/*    */     of1 = this.nI0;
/*    */     if (!this.GE0 && paramBoolean) {
/*    */       bool = true;
/*    */     } else {
/*    */       bool = false;
/*    */     } 
/*    */     of1.sk0(bool);
/*    */     this.HB.sk0(paramBoolean);
/*    */   }
/*    */   
/*    */   public final void qq0() {
/*    */     this();
/*    */     StringBuilder stringBuilder1;
/*    */     String str2, str1;
/*    */     (new StringBuilder()).append(Ml0.la(1170, "Loaded ROMs:"));
/*    */     StringBuilder stringBuilder2 = (new StringBuilder()).append("\nNDS: ");
/*    */     Wo wo;
/*    */     if ((wo = km.mI0.AN) == null) {
/*    */       str2 = "--";
/*    */     } else {
/*    */       str2 = ((HI)str2).qa0.jh0;
/*    */     } 
/*    */     stringBuilder1.append(stringBuilder2.append(str2).toString());
/*    */     if (km.mI0.MT != null)
/*    */       stringBuilder1.append(B40.df(", ").append(km.mI0.MT.qa0.jh0.replaceAll("\\P{Print}", "")).toString()); 
/*    */     if (km.mI0.yE != null)
/*    */       stringBuilder1.append(B40.df(", ").append(km.mI0.yE.qa0.jh0.replaceAll("\\P{Print}", "")).toString()); 
/*    */     stringBuilder2 = B40.df("\nGBA: ");
/*    */     s40 s40;
/*    */     if ((s40 = km.mI0.UG0) == null) {
/*    */       str1 = "--";
/*    */     } else {
/*    */       str1 = ((s40)str1).coM7 + " v1." + ((s40)str1).H5;
/*    */     } 
/*    */     stringBuilder1.append(stringBuilder2.append(str1).toString());
/*    */     if (km.mI0.UI0 != null) {
/*    */       s40 s401 = km.mI0.UI0;
/*    */       stringBuilder1.append(B40.df(", ").append(s401.coM7 + " v1." + s401.H5).toString());
/*    */     } 
/*    */     this.hN.E1(stringBuilder1.toString());
/*    */   } }


/* Location:              /Users/vnnsnnt/Documents/Codespace/JavaWorkspace/RedTrainer/src/main/java/org/trainer/client/PokeMMO.jar!/f/Wx.class
 * Java compiler version: 8 (52.0)
 * JD-Core Version:       1.1.3
 */