/* 1 */ package f;public final class X90 extends B70 { public final Bk0 W10; public HH xU; public VP sQ; public static void VI(HH paramHH, SG0[] paramArrayOfSG0, int paramInt) { R8 r8 = km.u4;
/*   */     
/* 3 */     int i = (paramArrayOfSG0[paramInt]).Ol; int j; if ((j = paramHH.Ia0) < 1)
/*   */     {
/* 5 */       j = r8.Qa.yD; }  r8
/* 6 */       .e20
/* 7 */       .W3(new Ix(j, i)); } public dQ yu0; public dQ Cj; public Fy0[] q00; public X90(Bk0 paramBk0, HH paramHH) { // Byte code:
/*   */     //   0: aload_0
/*   */     //   1: dup
/*   */     //   2: dup
/*   */     //   3: aload_2
/*   */     //   4: aload_0
/*   */     //   5: aload_1
/*   */     //   6: aload_0
/*   */     //   7: invokespecial <init> : ()V
/*   */     //   10: putfield W10 : Lf/Bk0;
/*   */     //   13: putfield xU : Lf/HH;
/*   */     //   16: ldc 'link-slot'
/*   */     //   18: invokevirtual Xu : (Ljava/lang/String;)V
/*   */     //   21: invokestatic XU : ()Z
/*   */     //   24: iconst_1
/*   */     //   25: ixor
/*   */     //   26: invokevirtual b7 : (Z)V
/*   */     //   29: invokestatic XU : ()Z
/*   */     //   32: ifeq -> 66
/*   */     //   35: new f/VP
/*   */     //   38: dup
/*   */     //   39: astore_1
/*   */     //   40: aload_0
/*   */     //   41: aload_1
/*   */     //   42: aload_2
/*   */     //   43: invokevirtual Tv0 : ()Lf/FV;
/*   */     //   46: astore_3
/*   */     //   47: bipush #48
/*   */     //   49: bipush #48
/*   */     //   51: aload_3
/*   */     //   52: invokespecial <init> : (IILf/FV;)V
/*   */     //   55: aload_1
/*   */     //   56: putfield sQ : Lf/VP;
/*   */     //   59: iconst_2
/*   */     //   60: invokevirtual yB0 : (I)V
/*   */     //   63: goto -> 97
/*   */     //   66: new f/VP
/*   */     //   69: dup
/*   */     //   70: astore_1
/*   */     //   71: aload_0
/*   */     //   72: aload_1
/*   */     //   73: aload_2
/*   */     //   74: invokevirtual Tv0 : ()Lf/FV;
/*   */     //   77: astore_3
/*   */     //   78: bipush #24
/*   */     //   80: bipush #24
/*   */     //   82: aload_3
/*   */     //   83: invokespecial <init> : (IILf/FV;)V
/*   */     //   86: aload_1
/*   */     //   87: putfield sQ : Lf/VP;
/*   */     //   90: bipush #-24
/*   */     //   92: bipush #-24
/*   */     //   94: invokevirtual nx : (II)V
/*   */     //   97: aload_0
/*   */     //   98: dup
/*   */     //   99: dup
/*   */     //   100: dup2
/*   */     //   101: dup2
/*   */     //   102: aload_2
/*   */     //   103: aload_0
/*   */     //   104: new f/dQ
/*   */     //   107: dup
/*   */     //   108: aload_0
/*   */     //   109: swap
/*   */     //   110: dup
/*   */     //   111: aload_2
/*   */     //   112: invokevirtual V9 : ()Ljava/lang/String;
/*   */     //   115: invokespecial <init> : (Ljava/lang/String;)V
/*   */     //   118: putfield yu0 : Lf/dQ;
/*   */     //   121: ldc 'label'
/*   */     //   123: invokevirtual Xu : (Ljava/lang/String;)V
/*   */     //   126: new f/dQ
/*   */     //   129: dup
/*   */     //   130: aload_0
/*   */     //   131: swap
/*   */     //   132: dup
/*   */     //   133: invokespecial <init> : ()V
/*   */     //   136: putfield Cj : Lf/dQ;
/*   */     //   139: ldc 'is-leader'
/*   */     //   141: invokevirtual Xu : (Ljava/lang/String;)V
/*   */     //   144: getfield Cj : Lf/dQ;
/*   */     //   147: iconst_1
/*   */     //   148: invokevirtual wI0 : (Z)V
/*   */     //   151: invokevirtual aI0 : ()[Lf/SG0;
/*   */     //   154: dup
/*   */     //   155: astore_1
/*   */     //   156: arraylength
/*   */     //   157: anewarray f/Fy0
/*   */     //   160: putfield q00 : [Lf/Fy0;
/*   */     //   163: getfield sQ : Lf/VP;
/*   */     //   166: invokevirtual J8 : (Lf/JG0;)V
/*   */     //   169: getfield yu0 : Lf/dQ;
/*   */     //   172: invokevirtual J8 : (Lf/JG0;)V
/*   */     //   175: getfield Cj : Lf/dQ;
/*   */     //   178: invokevirtual J8 : (Lf/JG0;)V
/*   */     //   181: iconst_0
/*   */     //   182: istore_3
/*   */     //   183: iload_3
/*   */     //   184: aload_1
/*   */     //   185: arraylength
/*   */     //   186: if_icmpge -> 382
/*   */     //   189: invokestatic XU : ()Z
/*   */     //   192: ifeq -> 249
/*   */     //   195: aload_0
/*   */     //   196: dup
/*   */     //   197: dup
/*   */     //   198: getfield q00 : [Lf/Fy0;
/*   */     //   201: iload_3
/*   */     //   202: new f/Fy0
/*   */     //   205: dup
/*   */     //   206: astore #4
/*   */     //   208: bipush #72
/*   */     //   210: bipush #72
/*   */     //   212: invokespecial <init> : (II)V
/*   */     //   215: aload #4
/*   */     //   217: aastore
/*   */     //   218: getfield q00 : [Lf/Fy0;
/*   */     //   221: iload_3
/*   */     //   222: aaload
/*   */     //   223: invokevirtual zY : ()Lf/rH;
/*   */     //   226: fconst_2
/*   */     //   227: invokevirtual Ii0 : (F)V
/*   */     //   230: getfield q00 : [Lf/Fy0;
/*   */     //   233: iload_3
/*   */     //   234: aaload
/*   */     //   235: aload_2
/*   */     //   236: aload_1
/*   */     //   237: iload_3
/*   */     //   238: <illegal opcode> run : (Lf/HH;[Lf/SG0;I)Ljava/lang/Runnable;
/*   */     //   243: invokevirtual tW : (Ljava/lang/Runnable;)V
/*   */     //   246: goto -> 287
/*   */     //   249: aload_0
/*   */     //   250: dup
/*   */     //   251: getfield q00 : [Lf/Fy0;
/*   */     //   254: iload_3
/*   */     //   255: new f/Fy0
/*   */     //   258: dup
/*   */     //   259: astore #4
/*   */     //   261: bipush #36
/*   */     //   263: bipush #36
/*   */     //   265: invokespecial <init> : (II)V
/*   */     //   268: aload #4
/*   */     //   270: aastore
/*   */     //   271: getfield q00 : [Lf/Fy0;
/*   */     //   274: iload_3
/*   */     //   275: aaload
/*   */     //   276: aload_2
/*   */     //   277: aload_1
/*   */     //   278: iload_3
/*   */     //   279: <illegal opcode> run : (Lf/HH;[Lf/SG0;I)Ljava/lang/Runnable;
/*   */     //   284: invokevirtual tW : (Ljava/lang/Runnable;)V
/*   */     //   287: aload_0
/*   */     //   288: dup
/*   */     //   289: dup2
/*   */     //   290: dup2
/*   */     //   291: getfield q00 : [Lf/Fy0;
/*   */     //   294: iload_3
/*   */     //   295: aaload
/*   */     //   296: invokevirtual zY : ()Lf/rH;
/*   */     //   299: iconst_1
/*   */     //   300: anewarray f/zh0
/*   */     //   303: dup
/*   */     //   304: invokestatic TK0 : ()Lf/um0;
/*   */     //   307: aload_1
/*   */     //   308: iload_3
/*   */     //   309: aaload
/*   */     //   310: invokevirtual mA : ()S
/*   */     //   313: iconst_0
/*   */     //   314: iconst_0
/*   */     //   315: invokevirtual lb : (SZB)[Lf/zh0;
/*   */     //   318: iconst_0
/*   */     //   319: aaload
/*   */     //   320: iconst_0
/*   */     //   321: swap
/*   */     //   322: aastore
/*   */     //   323: invokevirtual sm : ([Lf/zh0;)V
/*   */     //   326: getfield q00 : [Lf/Fy0;
/*   */     //   329: iload_3
/*   */     //   330: aaload
/*   */     //   331: invokestatic v30 : ()Lf/On;
/*   */     //   334: aload_1
/*   */     //   335: iload_3
/*   */     //   336: aaload
/*   */     //   337: invokevirtual mA : ()S
/*   */     //   340: invokevirtual lpT3 : (S)Lf/UD0;
/*   */     //   343: invokevirtual wp : ()Ljava/lang/String;
/*   */     //   346: invokevirtual Gq0 : (Ljava/lang/Object;)V
/*   */     //   349: getfield q00 : [Lf/Fy0;
/*   */     //   352: iload_3
/*   */     //   353: aaload
/*   */     //   354: iconst_0
/*   */     //   355: invokevirtual Pb0 : (I)V
/*   */     //   358: getfield q00 : [Lf/Fy0;
/*   */     //   361: iload_3
/*   */     //   362: aaload
/*   */     //   363: ldc 'link-monster'
/*   */     //   365: invokevirtual Xu : (Ljava/lang/String;)V
/*   */     //   368: getfield q00 : [Lf/Fy0;
/*   */     //   371: iload_3
/*   */     //   372: aaload
/*   */     //   373: invokevirtual J8 : (Lf/JG0;)V
/*   */     //   376: iinc #3, 1
/*   */     //   379: goto -> 183
/* 7 */     //   382: return } public static void qi0(HH paramHH, SG0[] paramArrayOfSG0, int paramInt) { R8 r8 = km.u4; int i = (paramArrayOfSG0[paramInt]).Ol; int j; if ((j = paramHH.Ia0) < 1) j = r8.Qa.yD;  r8.e20.W3(new Ix(j, i)); }
/*   */ 
/*   */   
/*   */   public final boolean i2(oa0 paramoa0) {
/*   */     // Byte code:
/*   */     //   0: aload_1
/*   */     //   1: invokevirtual Cz0 : ()Z
/*   */     //   4: ifeq -> 180
/*   */     //   7: aload_1
/*   */     //   8: getfield cz0 : I
/*   */     //   11: iconst_4
/*   */     //   12: if_icmpne -> 180
/*   */     //   15: aload_0
/*   */     //   16: dup
/*   */     //   17: getfield W10 : Lf/Bk0;
/*   */     //   20: dup
/*   */     //   21: astore_1
/*   */     //   22: invokevirtual getClass : ()Ljava/lang/Class;
/*   */     //   25: pop
/*   */     //   26: new f/B3
/*   */     //   29: dup
/*   */     //   30: astore_2
/*   */     //   31: invokespecial <init> : ()V
/*   */     //   34: getfield xU : Lf/HH;
/*   */     //   37: dup
/*   */     //   38: astore_3
/*   */     //   39: ifnonnull -> 45
/*   */     //   42: goto -> 178
/*   */     //   45: aload_3
/*   */     //   46: getfield Ia0 : I
/*   */     //   49: getstatic f/km.a3 : Lf/vh0;
/*   */     //   52: getfield yD : I
/*   */     //   55: dup
/*   */     //   56: istore_3
/*   */     //   57: if_icmpne -> 90
/*   */     //   60: new f/Hk0
/*   */     //   63: dup
/*   */     //   64: astore_1
/*   */     //   65: sipush #2501
/*   */     //   68: invokestatic OH0 : (I)Ljava/lang/String;
/*   */     //   71: astore_3
/*   */     //   72: new f/yQ
/*   */     //   75: dup
/*   */     //   76: astore #4
/*   */     //   78: invokespecial <init> : ()V
/*   */     //   81: aload_3
/*   */     //   82: aload #4
/*   */     //   84: invokespecial <init> : (Ljava/lang/String;Ljava/lang/Runnable;)V
/*   */     //   87: goto -> 126
/*   */     //   90: aload_1
/*   */     //   91: getfield GX : I
/*   */     //   94: iload_3
/*   */     //   95: if_icmpne -> 135
/*   */     //   98: new f/Hk0
/*   */     //   101: dup
/*   */     //   102: astore_1
/*   */     //   103: sipush #2500
/*   */     //   106: invokestatic OH0 : (I)Ljava/lang/String;
/*   */     //   109: astore_3
/*   */     //   110: new f/IS
/*   */     //   113: dup
/*   */     //   114: astore #4
/*   */     //   116: aload_0
/*   */     //   117: invokespecial <init> : (Lf/X90;)V
/*   */     //   120: aload_3
/*   */     //   121: aload #4
/*   */     //   123: invokespecial <init> : (Ljava/lang/String;Ljava/lang/Runnable;)V
/*   */     //   126: aload_2
/*   */     //   127: getfield aV : Ljava/util/ArrayList;
/*   */     //   130: aload_1
/*   */     //   131: invokevirtual add : (Ljava/lang/Object;)Z
/*   */     //   134: pop
/*   */     //   135: aload_2
/*   */     //   136: getfield aV : Ljava/util/ArrayList;
/*   */     //   139: invokevirtual size : ()I
/*   */     //   142: iconst_1
/*   */     //   143: if_icmpge -> 149
/*   */     //   146: goto -> 178
/*   */     //   149: aload_2
/*   */     //   150: aload_0
/*   */     //   151: aload_2
/*   */     //   152: new f/Hk0
/*   */     //   155: dup
/*   */     //   156: astore_0
/*   */     //   157: bipush #53
/*   */     //   159: invokestatic OH0 : (I)Ljava/lang/String;
/*   */     //   162: aconst_null
/*   */     //   163: invokespecial <init> : (Ljava/lang/String;Ljava/lang/Runnable;)V
/*   */     //   166: getfield aV : Ljava/util/ArrayList;
/*   */     //   169: aload_0
/*   */     //   170: invokevirtual add : (Ljava/lang/Object;)Z
/*   */     //   173: pop
/*   */     //   174: invokestatic Yo : (Lf/B3;Lf/JG0;)Lf/F7;
/*   */     //   177: pop
/*   */     //   178: iconst_1
/*   */     //   179: ireturn
/*   */     //   180: aload_0
/*   */     //   181: aload_1
/*   */     //   182: invokespecial i2 : (Lf/oa0;)Z
/*   */     //   185: ireturn
/*   */     // Line number table:
/*   */     //   Java source line number -> byte code offset
/*   */     //   #1	-> 8
/*   */     //   #2	-> 17
/*   */     //   #3	-> 26
/*   */     //   #4	-> 34
/*   */     //   #5	-> 46
/*   */     //   #6	-> 49
/*   */     //   #7	-> 52
/*   */     //   #8	-> 60
/*   */     //   #9	-> 127
/*   */     //   #10	-> 136
/*   */     //   #11	-> 152
/*   */     //   #12	-> 166
/*   */     //   #13	-> 174
/*   */     //   #14	-> 182
/*   */   }
/*   */   
/*   */   public final void d40() {
/*   */     // Byte code:
/*   */     //   0: invokestatic XU : ()Z
/*   */     //   3: ifeq -> 254
/*   */     //   6: aload_0
/*   */     //   7: dup
/*   */     //   8: dup2
/*   */     //   9: dup2
/*   */     //   10: getfield sQ : Lf/VP;
/*   */     //   13: aload_0
/*   */     //   14: dup
/*   */     //   15: getfield Kd : I
/*   */     //   18: istore_1
/*   */     //   19: getfield er0 : I
/*   */     //   22: iload_1
/*   */     //   23: swap
/*   */     //   24: invokevirtual ME : (II)Z
/*   */     //   27: pop
/*   */     //   28: getfield yu0 : Lf/dQ;
/*   */     //   31: aload_0
/*   */     //   32: getfield Kd : I
/*   */     //   35: bipush #80
/*   */     //   37: iadd
/*   */     //   38: aload_0
/*   */     //   39: getfield er0 : I
/*   */     //   42: bipush #40
/*   */     //   44: iadd
/*   */     //   45: invokevirtual ME : (II)Z
/*   */     //   48: pop
/*   */     //   49: getfield yu0 : Lf/dQ;
/*   */     //   52: dup
/*   */     //   53: getfield Kd : I
/*   */     //   56: istore_1
/*   */     //   57: invokevirtual Td0 : ()I
/*   */     //   60: iload_1
/*   */     //   61: iadd
/*   */     //   62: iconst_5
/*   */     //   63: iadd
/*   */     //   64: istore_1
/*   */     //   65: getfield Cj : Lf/dQ;
/*   */     //   68: invokevirtual mM : ()V
/*   */     //   71: getfield Cj : Lf/dQ;
/*   */     //   74: iload_1
/*   */     //   75: aload_0
/*   */     //   76: getfield yu0 : Lf/dQ;
/*   */     //   79: getfield er0 : I
/*   */     //   82: iconst_5
/*   */     //   83: isub
/*   */     //   84: invokevirtual ME : (II)Z
/*   */     //   87: pop
/*   */     //   88: getfield Cj : Lf/dQ;
/*   */     //   91: dup
/*   */     //   92: astore_2
/*   */     //   93: getfield dP : Z
/*   */     //   96: ifeq -> 109
/*   */     //   99: aload_2
/*   */     //   100: getfield xY : I
/*   */     //   103: bipush #6
/*   */     //   105: iadd
/*   */     //   106: iload_1
/*   */     //   107: iadd
/*   */     //   108: istore_1
/*   */     //   109: aload_0
/*   */     //   110: getfield q00 : [Lf/Fy0;
/*   */     //   113: dup
/*   */     //   114: astore_2
/*   */     //   115: arraylength
/*   */     //   116: istore_3
/*   */     //   117: iconst_0
/*   */     //   118: istore #4
/*   */     //   120: iload #4
/*   */     //   122: iload_3
/*   */     //   123: if_icmpge -> 155
/*   */     //   126: iload_1
/*   */     //   127: aload_2
/*   */     //   128: iload #4
/*   */     //   130: aaload
/*   */     //   131: dup
/*   */     //   132: iload_1
/*   */     //   133: aload_0
/*   */     //   134: getfield er0 : I
/*   */     //   137: bipush #8
/*   */     //   139: isub
/*   */     //   140: invokevirtual ME : (II)Z
/*   */     //   143: pop
/*   */     //   144: getfield xY : I
/*   */     //   147: iadd
/*   */     //   148: istore_1
/*   */     //   149: iinc #4, 1
/*   */     //   152: goto -> 120
/*   */     //   155: aload_0
/*   */     //   156: bipush #100
/*   */     //   158: istore_1
/*   */     //   159: getfield Cj : Lf/dQ;
/*   */     //   162: getfield dP : Z
/*   */     //   165: ifeq -> 173
/*   */     //   168: bipush #20
/*   */     //   170: goto -> 174
/*   */     //   173: iconst_0
/*   */     //   174: iload_1
/*   */     //   175: iadd
/*   */     //   176: istore_1
/*   */     //   177: aload_0
/*   */     //   178: dup
/*   */     //   179: dup2
/*   */     //   180: getfield yu0 : Lf/dQ;
/*   */     //   183: invokevirtual Td0 : ()I
/*   */     //   186: iload_1
/*   */     //   187: iadd
/*   */     //   188: istore_1
/*   */     //   189: getfield q00 : [Lf/Fy0;
/*   */     //   192: arraylength
/*   */     //   193: bipush #72
/*   */     //   195: imul
/*   */     //   196: iload_1
/*   */     //   197: iadd
/*   */     //   198: bipush #80
/*   */     //   200: invokevirtual uh0 : (II)V
/*   */     //   203: bipush #100
/*   */     //   205: istore_1
/*   */     //   206: getfield Cj : Lf/dQ;
/*   */     //   209: getfield dP : Z
/*   */     //   212: ifeq -> 220
/*   */     //   215: bipush #20
/*   */     //   217: goto -> 221
/*   */     //   220: iconst_0
/*   */     //   221: iload_1
/*   */     //   222: iadd
/*   */     //   223: istore_1
/*   */     //   224: aload_0
/*   */     //   225: dup
/*   */     //   226: dup
/*   */     //   227: getfield yu0 : Lf/dQ;
/*   */     //   230: invokevirtual Td0 : ()I
/*   */     //   233: iload_1
/*   */     //   234: iadd
/*   */     //   235: istore_0
/*   */     //   236: getfield q00 : [Lf/Fy0;
/*   */     //   239: arraylength
/*   */     //   240: bipush #72
/*   */     //   242: imul
/*   */     //   243: iload_0
/*   */     //   244: iadd
/*   */     //   245: bipush #80
/*   */     //   247: invokevirtual Tm : (II)Z
/*   */     //   250: pop
/*   */     //   251: goto -> 500
/*   */     //   254: aload_0
/*   */     //   255: dup
/*   */     //   256: dup2
/*   */     //   257: dup2
/*   */     //   258: getfield sQ : Lf/VP;
/*   */     //   261: aload_0
/*   */     //   262: getfield Kd : I
/*   */     //   265: bipush #10
/*   */     //   267: iadd
/*   */     //   268: aload_0
/*   */     //   269: getfield er0 : I
/*   */     //   272: bipush #10
/*   */     //   274: iadd
/*   */     //   275: invokevirtual ME : (II)Z
/*   */     //   278: pop
/*   */     //   279: getfield yu0 : Lf/dQ;
/*   */     //   282: aload_0
/*   */     //   283: getfield Kd : I
/*   */     //   286: bipush #30
/*   */     //   288: iadd
/*   */     //   289: aload_0
/*   */     //   290: getfield er0 : I
/*   */     //   293: bipush #14
/*   */     //   295: iadd
/*   */     //   296: invokevirtual ME : (II)Z
/*   */     //   299: pop
/*   */     //   300: getfield yu0 : Lf/dQ;
/*   */     //   303: dup
/*   */     //   304: getfield Kd : I
/*   */     //   307: istore_1
/*   */     //   308: invokevirtual Td0 : ()I
/*   */     //   311: iload_1
/*   */     //   312: iadd
/*   */     //   313: iconst_5
/*   */     //   314: iadd
/*   */     //   315: istore_1
/*   */     //   316: getfield Cj : Lf/dQ;
/*   */     //   319: invokevirtual mM : ()V
/*   */     //   322: getfield Cj : Lf/dQ;
/*   */     //   325: iload_1
/*   */     //   326: aload_0
/*   */     //   327: getfield er0 : I
/*   */     //   330: bipush #7
/*   */     //   332: iadd
/*   */     //   333: invokevirtual ME : (II)Z
/*   */     //   336: pop
/*   */     //   337: getfield Cj : Lf/dQ;
/*   */     //   340: dup
/*   */     //   341: astore_2
/*   */     //   342: getfield dP : Z
/*   */     //   345: ifeq -> 358
/*   */     //   348: aload_2
/*   */     //   349: getfield xY : I
/*   */     //   352: bipush #6
/*   */     //   354: iadd
/*   */     //   355: iload_1
/*   */     //   356: iadd
/*   */     //   357: istore_1
/*   */     //   358: aload_0
/*   */     //   359: getfield q00 : [Lf/Fy0;
/*   */     //   362: dup
/*   */     //   363: astore_2
/*   */     //   364: arraylength
/*   */     //   365: istore_3
/*   */     //   366: iconst_0
/*   */     //   367: istore #4
/*   */     //   369: iload #4
/*   */     //   371: iload_3
/*   */     //   372: if_icmpge -> 404
/*   */     //   375: iload_1
/*   */     //   376: aload_2
/*   */     //   377: iload #4
/*   */     //   379: aaload
/*   */     //   380: dup
/*   */     //   381: iload_1
/*   */     //   382: aload_0
/*   */     //   383: getfield er0 : I
/*   */     //   386: bipush #8
/*   */     //   388: isub
/*   */     //   389: invokevirtual ME : (II)Z
/*   */     //   392: pop
/*   */     //   393: getfield xY : I
/*   */     //   396: iadd
/*   */     //   397: istore_1
/*   */     //   398: iinc #4, 1
/*   */     //   401: goto -> 369
/*   */     //   404: aload_0
/*   */     //   405: bipush #40
/*   */     //   407: istore_1
/*   */     //   408: getfield Cj : Lf/dQ;
/*   */     //   411: getfield dP : Z
/*   */     //   414: ifeq -> 422
/*   */     //   417: bipush #20
/*   */     //   419: goto -> 423
/*   */     //   422: iconst_0
/*   */     //   423: iload_1
/*   */     //   424: iadd
/*   */     //   425: istore_1
/*   */     //   426: aload_0
/*   */     //   427: dup
/*   */     //   428: dup2
/*   */     //   429: getfield yu0 : Lf/dQ;
/*   */     //   432: invokevirtual Td0 : ()I
/*   */     //   435: iload_1
/*   */     //   436: iadd
/*   */     //   437: istore_1
/*   */     //   438: getfield q00 : [Lf/Fy0;
/*   */     //   441: arraylength
/*   */     //   442: bipush #36
/*   */     //   444: imul
/*   */     //   445: iload_1
/*   */     //   446: iadd
/*   */     //   447: bipush #30
/*   */     //   449: invokevirtual uh0 : (II)V
/*   */     //   452: bipush #40
/*   */     //   454: istore_1
/*   */     //   455: getfield Cj : Lf/dQ;
/*   */     //   458: getfield dP : Z
/*   */     //   461: ifeq -> 469
/*   */     //   464: bipush #20
/*   */     //   466: goto -> 470
/*   */     //   469: iconst_0
/*   */     //   470: iload_1
/*   */     //   471: iadd
/*   */     //   472: istore_1
/*   */     //   473: aload_0
/*   */     //   474: dup
/*   */     //   475: dup
/*   */     //   476: getfield yu0 : Lf/dQ;
/*   */     //   479: invokevirtual Td0 : ()I
/*   */     //   482: iload_1
/*   */     //   483: iadd
/*   */     //   484: istore_0
/*   */     //   485: getfield q00 : [Lf/Fy0;
/*   */     //   488: arraylength
/*   */     //   489: bipush #36
/*   */     //   491: imul
/*   */     //   492: iload_0
/*   */     //   493: iadd
/*   */     //   494: bipush #30
/*   */     //   496: invokevirtual Tm : (II)Z
/*   */     //   499: pop
/*   */     //   500: return
/*   */     // Line number table:
/*   */     //   Java source line number -> byte code offset
/*   */     //   #1	-> 15
/*   */     //   #2	-> 19
/*   */     //   #3	-> 24
/*   */     //   #4	-> 28
/*   */     //   #5	-> 32
/*   */     //   #6	-> 39
/*   */     //   #7	-> 45
/*   */     //   #8	-> 49
/*   */     //   #9	-> 53
/*   */     //   #10	-> 57
/*   */     //   #11	-> 79
/*   */     //   #12	-> 84
/*   */     //   #13	-> 88
/*   */     //   #14	-> 93
/*   */     //   #15	-> 100
/*   */     //   #16	-> 110
/*   */     //   #17	-> 134
/*   */     //   #18	-> 140
/*   */     //   #19	-> 144
/*   */     //   #20	-> 159
/*   */     //   #21	-> 162
/*   */     //   #22	-> 180
/*   */     //   #23	-> 209
/*   */     //   #24	-> 227
/*   */     //   #25	-> 262
/*   */     //   #26	-> 269
/*   */     //   #27	-> 275
/*   */     //   #28	-> 279
/*   */     //   #29	-> 283
/*   */     //   #30	-> 290
/*   */     //   #31	-> 296
/*   */     //   #32	-> 300
/*   */     //   #33	-> 304
/*   */     //   #34	-> 308
/*   */     //   #35	-> 327
/*   */     //   #36	-> 333
/*   */     //   #37	-> 337
/*   */     //   #38	-> 342
/*   */     //   #39	-> 349
/*   */     //   #40	-> 359
/*   */     //   #41	-> 383
/*   */     //   #42	-> 389
/*   */     //   #43	-> 393
/*   */     //   #44	-> 408
/*   */     //   #45	-> 411
/*   */     //   #46	-> 429
/*   */     //   #47	-> 458
/*   */     //   #48	-> 476
/*   */   } }


/* Location:              /Users/vnnsnnt/Documents/Codespace/JavaWorkspace/RedTrainer/src/main/java/org/trainer/client/PokeMMO.jar!/f/X90.class
 * Java compiler version: 8 (52.0)
 * JD-Core Version:       1.1.3
 */