package f;

public final class XG0 implements Runnable {
  public XG0(super paramsuper, String paramString, Qv0[] paramArrayOfQv0) {}
  
  public final void run() {
    // Byte code:
    //   0: getstatic f/pA.Dg0 : Lf/pA;
    //   3: dup
    //   4: astore_1
    //   5: ifnonnull -> 9
    //   8: return
    //   9: aload_1
    //   10: getfield dk0 : Lf/gO;
    //   13: ifnonnull -> 17
    //   16: return
    //   17: aload_0
    //   18: getfield U5 : Lf/super;
    //   21: astore_1
    //   22: iconst_0
    //   23: istore_2
    //   24: iload_2
    //   25: aload_1
    //   26: getfield Ss : [I
    //   29: dup
    //   30: astore_3
    //   31: arraylength
    //   32: if_icmpge -> 53
    //   35: aload_3
    //   36: iload_2
    //   37: iaload
    //   38: iconst_1
    //   39: if_icmpge -> 45
    //   42: goto -> 55
    //   45: iload_2
    //   46: iconst_1
    //   47: iadd
    //   48: i2b
    //   49: istore_2
    //   50: goto -> 24
    //   53: iconst_m1
    //   54: istore_2
    //   55: iload_2
    //   56: ifge -> 79
    //   59: getstatic f/js.vu0 : Lf/js;
    //   62: aload_0
    //   63: getfield SH : Ljava/lang/String;
    //   66: sipush #2306
    //   69: swap
    //   70: invokestatic Go : (ILjava/lang/String;)Ljava/lang/String;
    //   73: iconst_m1
    //   74: swap
    //   75: invokevirtual Pu : (ILjava/lang/String;)V
    //   78: return
    //   79: aload_0
    //   80: getfield gP : [Lf/Qv0;
    //   83: dup
    //   84: astore_1
    //   85: arraylength
    //   86: istore_3
    //   87: iconst_0
    //   88: istore #4
    //   90: iload #4
    //   92: iload_3
    //   93: if_icmpge -> 191
    //   96: aload_1
    //   97: iload #4
    //   99: aaload
    //   100: invokevirtual public : ()Lf/j40;
    //   103: dup
    //   104: astore #5
    //   106: ifnonnull -> 112
    //   109: goto -> 185
    //   112: iload_2
    //   113: iconst_5
    //   114: if_icmple -> 139
    //   117: getstatic f/js.vu0 : Lf/js;
    //   120: aload_0
    //   121: getfield SH : Ljava/lang/String;
    //   124: sipush #2306
    //   127: swap
    //   128: invokestatic Go : (ILjava/lang/String;)Ljava/lang/String;
    //   131: iconst_m1
    //   132: swap
    //   133: invokevirtual Pu : (ILjava/lang/String;)V
    //   136: goto -> 191
    //   139: iload_2
    //   140: aload #5
    //   142: aload_0
    //   143: getstatic f/km.u4 : Lf/R8;
    //   146: astore #5
    //   148: getfield U5 : Lf/super;
    //   151: getfield Nd0 : B
    //   154: istore #6
    //   156: getfield Jg : I
    //   159: istore #7
    //   161: aload #5
    //   163: getfield e20 : Lf/c4;
    //   166: new f/tn
    //   169: dup
    //   170: iload #6
    //   172: iload_2
    //   173: iload #7
    //   175: invokespecial <init> : (BBI)V
    //   178: invokevirtual W3 : (Lf/Bi;)V
    //   181: iconst_1
    //   182: iadd
    //   183: i2b
    //   184: istore_2
    //   185: iinc #4, 1
    //   188: goto -> 90
    //   191: return
    // Line number table:
    //   Java source line number -> byte code offset
    //   #1	-> 0
    //   #2	-> 10
    //   #3	-> 18
    //   #4	-> 26
    //   #5	-> 31
    //   #6	-> 59
    //   #7	-> 63
    //   #8	-> 75
    //   #9	-> 80
    //   #10	-> 117
    //   #11	-> 121
    //   #12	-> 133
    //   #13	-> 143
    //   #14	-> 151
    //   #15	-> 156
    //   #16	-> 163
    //   #17	-> 166
  }
}


/* Location:              /Users/vnnsnnt/Documents/Codespace/JavaWorkspace/RedTrainer/src/main/java/org/trainer/client/PokeMMO.jar!/f/XG0.class
 * Java compiler version: 8 (52.0)
 * JD-Core Version:       1.1.3
 */