package f;

public final class xJ implements Runnable {
  public xJ(h2 paramh2) {}
  
  public final void run() {
    // Byte code:
    //   0: aload_0
    //   1: getfield J8 : Lf/h2;
    //   4: invokevirtual xI0 : ()V
    //   7: getstatic f/Bz.rK0 : I
    //   10: ifne -> 38
    //   13: aload_0
    //   14: sipush #450
    //   17: putstatic f/Bz.rK0 : I
    //   20: getfield J8 : Lf/h2;
    //   23: getfield Db0 : Lf/ge0;
    //   26: iconst_1
    //   27: istore_0
    //   28: getfield TG0 : Lf/protected;
    //   31: iload_0
    //   32: invokevirtual Fx0 : (Z)V
    //   35: goto -> 54
    //   38: aload_0
    //   39: iconst_0
    //   40: putstatic f/Bz.rK0 : I
    //   43: getfield J8 : Lf/h2;
    //   46: getfield Db0 : Lf/ge0;
    //   49: iconst_0
    //   50: istore_0
    //   51: goto -> 28
    //   54: return
    // Line number table:
    //   Java source line number -> byte code offset
    //   #1	-> 28
    //   #2	-> 32
    //   #3	-> 40
  }
}


/* Location:              /Users/vnnsnnt/Documents/Codespace/JavaWorkspace/RedTrainer/src/main/java/org/trainer/client/PokeMMO.jar!/f/xJ.class
 * Java compiler version: 8 (52.0)
 * JD-Core Version:       1.1.3
 */