/* 1 */ package f;public final class XQ extends Kl0 { public final void Cx() { Gp0 gp0; if ((gp0 = km.MR) != null) { mJ mJ1 = this.com4; hm0 hm01 = this.gl; gp0.W
/* 2 */         .add(new hA0(hm01, this)); }
/*   */      }
/*   */ 
/*   */   
/*   */   public Gp0 YN;
/*   */   public mJ com4;
/*   */   public hm0 gl;
/*   */   public R00 RQ;
/*   */   public hR[] ED0 = hR.ZF;
/*   */   
/*   */   public XQ(c4 paramc4, ByteBuffer paramByteBuffer) {
/*   */     super(paramc4, paramByteBuffer);
/*   */   }
/*   */   
/*   */   public final void sM() {
/*   */     // Byte code:
/*   */     //   0: aload_0
/*   */     //   1: dup
/*   */     //   2: dup
/*   */     //   3: dup2
/*   */     //   4: dup2
/*   */     //   5: getstatic f/km.MR : Lf/Gp0;
/*   */     //   8: putfield YN : Lf/Gp0;
/*   */     //   11: getfield Ws : Ljava/nio/ByteBuffer;
/*   */     //   14: invokevirtual get : ()B
/*   */     //   17: invokestatic kc : (B)Lf/mJ;
/*   */     //   20: putfield com4 : Lf/mJ;
/*   */     //   23: getfield YN : Lf/Gp0;
/*   */     //   26: dup
/*   */     //   27: astore_1
/*   */     //   28: getfield q20 : Lf/R00;
/*   */     //   31: putfield RQ : Lf/R00;
/*   */     //   34: aload_1
/*   */     //   35: getfield de0 : [Lf/hR;
/*   */     //   38: putfield ED0 : [Lf/hR;
/*   */     //   41: getfield Ws : Ljava/nio/ByteBuffer;
/*   */     //   44: invokevirtual getInt : ()I
/*   */     //   47: dup
/*   */     //   48: istore_1
/*   */     //   49: ifne -> 99
/*   */     //   52: aload_0
/*   */     //   53: new f/hm0
/*   */     //   56: dup
/*   */     //   57: astore_2
/*   */     //   58: aload_0
/*   */     //   59: getfield com4 : Lf/mJ;
/*   */     //   62: dup
/*   */     //   63: getfield FI0 : B
/*   */     //   66: istore_0
/*   */     //   67: getfield md : B
/*   */     //   70: getstatic f/mA.uZ : Lf/mA;
/*   */     //   73: astore_3
/*   */     //   74: iload_0
/*   */     //   75: swap
/*   */     //   76: iload_1
/*   */     //   77: iconst_0
/*   */     //   78: iconst_1
/*   */     //   79: ldc ''
/*   */     //   81: iconst_0
/*   */     //   82: iconst_1
/*   */     //   83: iconst_0
/*   */     //   84: iconst_0
/*   */     //   85: iconst_0
/*   */     //   86: aload_3
/*   */     //   87: iconst_1
/*   */     //   88: iconst_1
/*   */     //   89: iconst_0
/*   */     //   90: iconst_0
/*   */     //   91: invokespecial <init> : (BBISBLjava/lang/String;BBBSBLf/mA;SSBB)V
/*   */     //   94: aload_2
/*   */     //   95: putfield gl : Lf/hm0;
/*   */     //   98: return
/*   */     //   99: aload_0
/*   */     //   100: getfield YN : Lf/Gp0;
/*   */     //   103: dup
/*   */     //   104: astore_2
/*   */     //   105: ifnonnull -> 109
/*   */     //   108: return
/*   */     //   109: aload_2
/*   */     //   110: iload_1
/*   */     //   111: invokevirtual f70 : (I)Lf/cOm4;
/*   */     //   114: dup
/*   */     //   115: astore_2
/*   */     //   116: ifnull -> 367
/*   */     //   119: aload_2
/*   */     //   120: getfield gc : Lf/jd0;
/*   */     //   123: ifnull -> 367
/*   */     //   126: aload_0
/*   */     //   127: dup
/*   */     //   128: dup
/*   */     //   129: dup2
/*   */     //   130: dup2
/*   */     //   131: getfield Ws : Ljava/nio/ByteBuffer;
/*   */     //   134: invokevirtual getShort : ()S
/*   */     //   137: istore_1
/*   */     //   138: getfield Ws : Ljava/nio/ByteBuffer;
/*   */     //   141: invokevirtual get : ()B
/*   */     //   144: istore_3
/*   */     //   145: invokevirtual au : ()Ljava/lang/String;
/*   */     //   148: astore #4
/*   */     //   150: getfield Ws : Ljava/nio/ByteBuffer;
/*   */     //   153: invokevirtual get : ()B
/*   */     //   156: istore #5
/*   */     //   158: getfield Ws : Ljava/nio/ByteBuffer;
/*   */     //   161: invokevirtual get : ()B
/*   */     //   164: istore #6
/*   */     //   166: getfield Ws : Ljava/nio/ByteBuffer;
/*   */     //   169: invokevirtual get : ()B
/*   */     //   172: istore #7
/*   */     //   174: getfield Ws : Ljava/nio/ByteBuffer;
/*   */     //   177: invokevirtual getShort : ()S
/*   */     //   180: dup
/*   */     //   181: istore #8
/*   */     //   183: aload_2
/*   */     //   184: aload_0
/*   */     //   185: dup
/*   */     //   186: dup2
/*   */     //   187: dup2
/*   */     //   188: getfield Ws : Ljava/nio/ByteBuffer;
/*   */     //   191: invokevirtual get : ()B
/*   */     //   194: istore #9
/*   */     //   196: getfield Ws : Ljava/nio/ByteBuffer;
/*   */     //   199: invokevirtual get : ()B
/*   */     //   202: invokestatic qq : (B)Lf/mA;
/*   */     //   205: astore #10
/*   */     //   207: getfield Ws : Ljava/nio/ByteBuffer;
/*   */     //   210: invokevirtual getShort : ()S
/*   */     //   213: istore #11
/*   */     //   215: getfield Ws : Ljava/nio/ByteBuffer;
/*   */     //   218: invokevirtual getShort : ()S
/*   */     //   221: istore #12
/*   */     //   223: getfield Ws : Ljava/nio/ByteBuffer;
/*   */     //   226: invokevirtual get : ()B
/*   */     //   229: istore #13
/*   */     //   231: getfield Ws : Ljava/nio/ByteBuffer;
/*   */     //   234: invokevirtual get : ()B
/*   */     //   237: istore #14
/*   */     //   239: getfield gc : Lf/jd0;
/*   */     //   242: dup
/*   */     //   243: dup
/*   */     //   244: astore #15
/*   */     //   246: iload #8
/*   */     //   248: aload #15
/*   */     //   250: iload #12
/*   */     //   252: aload #15
/*   */     //   254: aload_0
/*   */     //   255: new f/hm0
/*   */     //   258: dup
/*   */     //   259: astore #8
/*   */     //   261: iload_1
/*   */     //   262: aload_0
/*   */     //   263: aload #8
/*   */     //   265: dup
/*   */     //   266: aload #15
/*   */     //   268: aload_0
/*   */     //   269: getfield com4 : Lf/mJ;
/*   */     //   272: dup
/*   */     //   273: getfield FI0 : B
/*   */     //   276: istore_1
/*   */     //   277: getfield md : B
/*   */     //   280: iload_1
/*   */     //   281: swap
/*   */     //   282: iload #14
/*   */     //   284: invokespecial <init> : (Lf/jd0;BBB)V
/*   */     //   287: putfield gl : Lf/hm0;
/*   */     //   290: iload_3
/*   */     //   291: aload #4
/*   */     //   293: iload #5
/*   */     //   295: iload #6
/*   */     //   297: iload #7
/*   */     //   299: iload #9
/*   */     //   301: invokevirtual ZB0 : (SBLjava/lang/String;BBBB)V
/*   */     //   304: getfield gl : Lf/hm0;
/*   */     //   307: aload_2
/*   */     //   308: invokevirtual k8 : (Lf/cOm4;)V
/*   */     //   311: getfield ta : Lf/Q90;
/*   */     //   314: iload #11
/*   */     //   316: invokevirtual ok : (S)V
/*   */     //   319: putfield hp0 : S
/*   */     //   322: putfield y6 : S
/*   */     //   325: getfield ta : Lf/Q90;
/*   */     //   328: invokevirtual p10 : ()S
/*   */     //   331: if_icmpeq -> 347
/*   */     //   334: aload #15
/*   */     //   336: getfield ta : Lf/Q90;
/*   */     //   339: aload #15
/*   */     //   341: getfield y6 : S
/*   */     //   344: putfield m80 : S
/*   */     //   347: aload #15
/*   */     //   349: aload #10
/*   */     //   351: aload #15
/*   */     //   353: getfield ta : Lf/Q90;
/*   */     //   356: iload #13
/*   */     //   358: putfield u0 : B
/*   */     //   361: putfield M6 : Lf/mA;
/*   */     //   364: goto -> 562
/*   */     //   367: aload_0
/*   */     //   368: dup
/*   */     //   369: dup
/*   */     //   370: new f/hm0
/*   */     //   373: dup
/*   */     //   374: dup
/*   */     //   375: astore_2
/*   */     //   376: aload_0
/*   */     //   377: dup
/*   */     //   378: dup2
/*   */     //   379: getfield com4 : Lf/mJ;
/*   */     //   382: dup
/*   */     //   383: getfield FI0 : B
/*   */     //   386: istore_3
/*   */     //   387: getfield md : B
/*   */     //   390: istore #4
/*   */     //   392: getfield Ws : Ljava/nio/ByteBuffer;
/*   */     //   395: invokevirtual getShort : ()S
/*   */     //   398: istore #5
/*   */     //   400: getfield Ws : Ljava/nio/ByteBuffer;
/*   */     //   403: invokevirtual get : ()B
/*   */     //   406: istore #6
/*   */     //   408: invokevirtual au : ()Ljava/lang/String;
/*   */     //   411: astore #7
/*   */     //   413: iload_3
/*   */     //   414: aload_0
/*   */     //   415: dup
/*   */     //   416: dup2
/*   */     //   417: dup2
/*   */     //   418: dup2
/*   */     //   419: dup2
/*   */     //   420: getfield Ws : Ljava/nio/ByteBuffer;
/*   */     //   423: invokevirtual get : ()B
/*   */     //   426: istore_3
/*   */     //   427: getfield Ws : Ljava/nio/ByteBuffer;
/*   */     //   430: invokevirtual get : ()B
/*   */     //   433: istore #8
/*   */     //   435: getfield Ws : Ljava/nio/ByteBuffer;
/*   */     //   438: invokevirtual get : ()B
/*   */     //   441: istore #9
/*   */     //   443: getfield Ws : Ljava/nio/ByteBuffer;
/*   */     //   446: invokevirtual getShort : ()S
/*   */     //   449: istore #10
/*   */     //   451: getfield Ws : Ljava/nio/ByteBuffer;
/*   */     //   454: invokevirtual get : ()B
/*   */     //   457: istore #11
/*   */     //   459: getfield Ws : Ljava/nio/ByteBuffer;
/*   */     //   462: invokevirtual get : ()B
/*   */     //   465: invokestatic qq : (B)Lf/mA;
/*   */     //   468: astore #12
/*   */     //   470: getfield Ws : Ljava/nio/ByteBuffer;
/*   */     //   473: invokevirtual getShort : ()S
/*   */     //   476: istore #13
/*   */     //   478: getfield Ws : Ljava/nio/ByteBuffer;
/*   */     //   481: invokevirtual getShort : ()S
/*   */     //   484: istore #14
/*   */     //   486: getfield Ws : Ljava/nio/ByteBuffer;
/*   */     //   489: invokevirtual get : ()B
/*   */     //   492: istore #15
/*   */     //   494: getfield Ws : Ljava/nio/ByteBuffer;
/*   */     //   497: invokevirtual get : ()B
/*   */     //   500: istore #16
/*   */     //   502: iload #4
/*   */     //   504: iload_1
/*   */     //   505: iload #5
/*   */     //   507: iload #6
/*   */     //   509: aload #7
/*   */     //   511: iload_3
/*   */     //   512: iload #8
/*   */     //   514: iload #9
/*   */     //   516: iload #10
/*   */     //   518: iload #11
/*   */     //   520: aload #12
/*   */     //   522: iload #13
/*   */     //   524: iload #14
/*   */     //   526: iload #15
/*   */     //   528: iload #16
/*   */     //   530: invokespecial <init> : (BBISBLjava/lang/String;BBBSBLf/mA;SSBB)V
/*   */     //   533: putfield gl : Lf/hm0;
/*   */     //   536: getfield YN : Lf/Gp0;
/*   */     //   539: aload_2
/*   */     //   540: dup
/*   */     //   541: getfield FT : B
/*   */     //   544: istore_2
/*   */     //   545: getfield iJ : B
/*   */     //   548: iload_2
/*   */     //   549: swap
/*   */     //   550: iload_1
/*   */     //   551: invokevirtual iC0 : (BBI)Lf/cOm4;
/*   */     //   554: astore_1
/*   */     //   555: getfield gl : Lf/hm0;
/*   */     //   558: aload_1
/*   */     //   559: invokevirtual k8 : (Lf/cOm4;)V
/*   */     //   562: aload_0
/*   */     //   563: getfield Ws : Ljava/nio/ByteBuffer;
/*   */     //   566: invokevirtual get : ()B
/*   */     //   569: dup
/*   */     //   570: istore_1
/*   */     //   571: aload_0
/*   */     //   572: getfield gl : Lf/hm0;
/*   */     //   575: astore_2
/*   */     //   576: iconst_1
/*   */     //   577: iand
/*   */     //   578: ifeq -> 586
/*   */     //   581: iconst_1
/*   */     //   582: istore_3
/*   */     //   583: goto -> 588
/*   */     //   586: iconst_0
/*   */     //   587: istore_3
/*   */     //   588: aload_2
/*   */     //   589: dup
/*   */     //   590: iload_3
/*   */     //   591: putfield A0 : Z
/*   */     //   594: getfield eq0 : Lf/uT;
/*   */     //   597: ifnull -> 613
/*   */     //   600: iload_3
/*   */     //   601: ifne -> 613
/*   */     //   604: aload_2
/*   */     //   605: dup
/*   */     //   606: aconst_null
/*   */     //   607: putfield eq0 : Lf/uT;
/*   */     //   610: invokevirtual yL0 : ()V
/*   */     //   613: iload_1
/*   */     //   614: aload_0
/*   */     //   615: getfield gl : Lf/hm0;
/*   */     //   618: astore_2
/*   */     //   619: iconst_4
/*   */     //   620: iand
/*   */     //   621: ifeq -> 629
/*   */     //   624: iconst_1
/*   */     //   625: istore_3
/*   */     //   626: goto -> 631
/*   */     //   629: iconst_0
/*   */     //   630: istore_3
/*   */     //   631: iload_1
/*   */     //   632: aload_2
/*   */     //   633: dup
/*   */     //   634: iload_3
/*   */     //   635: putfield h2 : Z
/*   */     //   638: getfield K0 : Lf/jd0;
/*   */     //   641: getfield ta : Lf/Q90;
/*   */     //   644: astore_2
/*   */     //   645: bipush #8
/*   */     //   647: iand
/*   */     //   648: ifeq -> 656
/*   */     //   651: iconst_1
/*   */     //   652: istore_3
/*   */     //   653: goto -> 658
/*   */     //   656: iconst_0
/*   */     //   657: istore_3
/*   */     //   658: iload_1
/*   */     //   659: aload_2
/*   */     //   660: iload_3
/*   */     //   661: putfield Jg : Z
/*   */     //   664: iconst_2
/*   */     //   665: iand
/*   */     //   666: ifeq -> 783
/*   */     //   669: aload_0
/*   */     //   670: dup
/*   */     //   671: getfield Ws : Ljava/nio/ByteBuffer;
/*   */     //   674: invokevirtual getShort : ()S
/*   */     //   677: istore_1
/*   */     //   678: getfield Ws : Ljava/nio/ByteBuffer;
/*   */     //   681: invokevirtual get : ()B
/*   */     //   684: istore_2
/*   */     //   685: iconst_4
/*   */     //   686: newarray short
/*   */     //   688: astore_3
/*   */     //   689: iconst_4
/*   */     //   690: newarray byte
/*   */     //   692: astore #4
/*   */     //   694: iconst_0
/*   */     //   695: istore #5
/*   */     //   697: iload #5
/*   */     //   699: iconst_4
/*   */     //   700: if_icmpge -> 732
/*   */     //   703: aload #4
/*   */     //   705: iload #5
/*   */     //   707: aload_0
/*   */     //   708: aload_3
/*   */     //   709: iload #5
/*   */     //   711: aload_0
/*   */     //   712: getfield Ws : Ljava/nio/ByteBuffer;
/*   */     //   715: invokevirtual getShort : ()S
/*   */     //   718: sastore
/*   */     //   719: getfield Ws : Ljava/nio/ByteBuffer;
/*   */     //   722: invokevirtual get : ()B
/*   */     //   725: bastore
/*   */     //   726: iinc #5, 1
/*   */     //   729: goto -> 697
/*   */     //   732: aload_0
/*   */     //   733: dup
/*   */     //   734: dup
/*   */     //   735: dup2
/*   */     //   736: getfield Ws : Ljava/nio/ByteBuffer;
/*   */     //   739: invokevirtual getShort : ()S
/*   */     //   742: istore #5
/*   */     //   744: getfield Ws : Ljava/nio/ByteBuffer;
/*   */     //   747: invokevirtual get : ()B
/*   */     //   750: istore #6
/*   */     //   752: getfield Ws : Ljava/nio/ByteBuffer;
/*   */     //   755: invokevirtual get : ()B
/*   */     //   758: istore #7
/*   */     //   760: getfield gl : Lf/hm0;
/*   */     //   763: iload_1
/*   */     //   764: iload_2
/*   */     //   765: aload_3
/*   */     //   766: aload #4
/*   */     //   768: iload #6
/*   */     //   770: iload #7
/*   */     //   772: invokevirtual x10 : (SB[S[BBB)V
/*   */     //   775: getfield gl : Lf/hm0;
/*   */     //   778: iload #5
/*   */     //   780: putfield BC : S
/*   */     //   783: aload_0
/*   */     //   784: getfield RQ : Lf/R00;
/*   */     //   787: ifnull -> 942
/*   */     //   790: aload_0
/*   */     //   791: getfield ED0 : [Lf/hR;
/*   */     //   794: dup
/*   */     //   795: astore_1
/*   */     //   796: arraylength
/*   */     //   797: ifle -> 942
/*   */     //   800: aload_1
/*   */     //   801: arraylength
/*   */     //   802: istore_2
/*   */     //   803: iconst_0
/*   */     //   804: istore_3
/*   */     //   805: iload_3
/*   */     //   806: iload_2
/*   */     //   807: if_icmpge -> 942
/*   */     //   810: aload_0
/*   */     //   811: aload_1
/*   */     //   812: iload_3
/*   */     //   813: aaload
/*   */     //   814: astore #4
/*   */     //   816: getfield RQ : Lf/R00;
/*   */     //   819: invokevirtual ordinal : ()I
/*   */     //   822: dup
/*   */     //   823: istore #5
/*   */     //   825: ifeq -> 890
/*   */     //   828: iload #5
/*   */     //   830: iconst_1
/*   */     //   831: if_icmpeq -> 853
/*   */     //   834: iload #5
/*   */     //   836: iconst_2
/*   */     //   837: if_icmpne -> 843
/*   */     //   840: goto -> 890
/*   */     //   843: new java/lang/UnsupportedOperationException
/*   */     //   846: dup
/*   */     //   847: ldc ''
/*   */     //   849: invokespecial <init> : (Ljava/lang/String;)V
/*   */     //   852: athrow
/*   */     //   853: aload_0
/*   */     //   854: getfield gl : Lf/hm0;
/*   */     //   857: getfield K0 : Lf/jd0;
/*   */     //   860: iconst_1
/*   */     //   861: newarray short
/*   */     //   863: dup
/*   */     //   864: astore #5
/*   */     //   866: aload_0
/*   */     //   867: getfield Ws : Ljava/nio/ByteBuffer;
/*   */     //   870: invokevirtual getShort : ()S
/*   */     //   873: iconst_0
/*   */     //   874: swap
/*   */     //   875: sastore
/*   */     //   876: getfield Zf : Ljava/util/EnumMap;
/*   */     //   879: aload #4
/*   */     //   881: aload #5
/*   */     //   883: invokevirtual put : (Ljava/lang/Object;Ljava/lang/Object;)Ljava/lang/Object;
/*   */     //   886: pop
/*   */     //   887: goto -> 936
/*   */     //   890: aload_0
/*   */     //   891: getfield gl : Lf/hm0;
/*   */     //   894: getfield K0 : Lf/jd0;
/*   */     //   897: iconst_2
/*   */     //   898: newarray short
/*   */     //   900: dup
/*   */     //   901: astore #5
/*   */     //   903: aload_0
/*   */     //   904: aload #5
/*   */     //   906: aload_0
/*   */     //   907: getfield Ws : Ljava/nio/ByteBuffer;
/*   */     //   910: invokevirtual getShort : ()S
/*   */     //   913: iconst_0
/*   */     //   914: swap
/*   */     //   915: sastore
/*   */     //   916: getfield Ws : Ljava/nio/ByteBuffer;
/*   */     //   919: invokevirtual getShort : ()S
/*   */     //   922: iconst_1
/*   */     //   923: swap
/*   */     //   924: sastore
/*   */     //   925: getfield Zf : Ljava/util/EnumMap;
/*   */     //   928: aload #4
/*   */     //   930: aload #5
/*   */     //   932: invokevirtual put : (Ljava/lang/Object;Ljava/lang/Object;)Ljava/lang/Object;
/*   */     //   935: pop
/*   */     //   936: iinc #3, 1
/*   */     //   939: goto -> 805
/*   */     //   942: return
/*   */     // Line number table:
/*   */     //   Java source line number -> byte code offset
/*   */     //   #1	-> 11
/*   */     //   #2	-> 17
/*   */     //   #3	-> 28
/*   */     //   #4	-> 31
/*   */     //   #5	-> 35
/*   */     //   #6	-> 38
/*   */     //   #7	-> 41
/*   */     //   #8	-> 53
/*   */     //   #9	-> 63
/*   */     //   #10	-> 67
/*   */     //   #11	-> 70
/*   */     //   #12	-> 120
/*   */     //   #13	-> 131
/*   */     //   #14	-> 138
/*   */     //   #15	-> 145
/*   */     //   #16	-> 150
/*   */     //   #17	-> 174
/*   */     //   #18	-> 188
/*   */     //   #19	-> 202
/*   */     //   #20	-> 207
/*   */     //   #21	-> 223
/*   */     //   #22	-> 239
/*   */     //   #23	-> 255
/*   */     //   #24	-> 273
/*   */     //   #25	-> 277
/*   */     //   #26	-> 284
/*   */     //   #27	-> 311
/*   */     //   #28	-> 316
/*   */     //   #29	-> 319
/*   */     //   #30	-> 322
/*   */     //   #31	-> 344
/*   */     //   #32	-> 353
/*   */     //   #33	-> 358
/*   */     //   #34	-> 361
/*   */     //   #35	-> 370
/*   */     //   #36	-> 383
/*   */     //   #37	-> 387
/*   */     //   #38	-> 392
/*   */     //   #39	-> 400
/*   */     //   #40	-> 408
/*   */     //   #41	-> 420
/*   */     //   #42	-> 443
/*   */     //   #43	-> 451
/*   */     //   #44	-> 465
/*   */     //   #45	-> 470
/*   */     //   #46	-> 486
/*   */     //   #47	-> 530
/*   */     //   #48	-> 541
/*   */     //   #49	-> 545
/*   */     //   #50	-> 551
/*   */     //   #51	-> 563
/*   */     //   #52	-> 572
/*   */     //   #53	-> 591
/*   */     //   #54	-> 594
/*   */     //   #55	-> 615
/*   */     //   #56	-> 635
/*   */     //   #57	-> 638
/*   */     //   #58	-> 641
/*   */     //   #59	-> 661
/*   */     //   #60	-> 671
/*   */     //   #61	-> 678
/*   */     //   #62	-> 686
/*   */     //   #63	-> 712
/*   */     //   #64	-> 718
/*   */     //   #65	-> 719
/*   */     //   #66	-> 725
/*   */     //   #67	-> 736
/*   */     //   #68	-> 744
/*   */     //   #69	-> 760
/*   */     //   #70	-> 780
/*   */     //   #71	-> 784
/*   */     //   #72	-> 857
/*   */     //   #73	-> 861
/*   */     //   #74	-> 867
/*   */     //   #75	-> 875
/*   */     //   #76	-> 876
/*   */     //   #77	-> 883
/*   */     //   #78	-> 891
/*   */     //   #79	-> 894
/*   */     //   #80	-> 898
/*   */     //   #81	-> 907
/*   */     //   #82	-> 915
/*   */     //   #83	-> 916
/*   */     //   #84	-> 924
/*   */     //   #85	-> 925
/*   */     //   #86	-> 932
/*   */   } }


/* Location:              /Users/vnnsnnt/Documents/Codespace/JavaWorkspace/RedTrainer/src/main/java/org/trainer/client/PokeMMO.jar!/f/XQ.class
 * Java compiler version: 8 (52.0)
 * JD-Core Version:       1.1.3
 */