/*  1 */ package f;public final class xV extends Cy { public gD tu; public ArrayList w7; public final boolean J4() { boolean bool; if (this.l1 != null) { bool = true; } else { bool = false; }  if (bool) return true;
/*    */ 
/*    */     
/*  4 */     return !!km.u4.fF0.y5(this.E10, (short)1360); }
/*  5 */   public qx[] me0; public xV(gD paramgD, short paramShort1, byte paramByte, short paramShort2, h30 paramh30) { super(paramgD, paramShort1, paramByte, paramShort2, paramh30); vF vF; this.w7 = new ArrayList(); this.me0 = new qx[0]; this.tu = paramgD; if (this.br0.F70 != 0) { vF = vF.ud0; } else { vF = vF.IQ; }  this.UZ = vF; t8(); EB(); } public final boolean zV() { return false; } public final void t8() { super.t8(); for (short s = 0; s < this.xk0.X7; ) { lF0 lF0; for (short s1 = 0; s1 < (lF0 = this.xk0).cB0; ) { int i; if (this.hp && (i = lF0.H80[s][s1]) >= 0) { this.UF[s][s1] = this.lG0.gH0(i); this.xk0.H80[s][s1]; }  if ((i = this.xk0.U1[s][s1]) >= 0) { i = (short)i; if (this.Jb0.Fb(i)) i = this.Jb0.Z90(i);  yU yU = (yU)this.tu.Ea0(i); if (this.et0 == 0 && this.ey == 0) { this.et0 = yU.ar0;
/*    */             
/*  7 */             this.ey = yU.Rc0; }  if (this.et0 == yU
/*  8 */             .ar0 && this
/*  9 */             .ey == yU
/* 10 */             .Rc0)
/* 11 */           { short[][][][] arrayOfShort; if ((arrayOfShort = yU.nK).length > this.FD) this.FD = arrayOfShort.length;  } else { throw new RuntimeException("Matrix has mismatching footer sizes"); }  }  s1 = (short)(s1 + 1); }  s = (short)(s + 1); }
/*    */      }
/*    */ 
/*    */   
/*    */   public final void zf(short paramShort1, short paramShort2) {
/*    */     int i;
/*    */     if ((i = this.xk0.U1[paramShort1][paramShort2]) >= 0) {
/*    */       hH0 hH0;
/*    */       i = (short)i;
/*    */       if (this.Jb0.Fb(i))
/*    */         i = this.Jb0.Z90(i); 
/*    */       yU yU = (yU)this.tu.Ea0(i);
/*    */       lF0 lF0 = this.xk0;
/*    */       this(paramShort1, paramShort2, this, yU, lF0);
/*    */       this.eG[paramShort1][paramShort2] = hH0;
/*    */     } 
/*    */   }
/*    */   
/*    */   public final iy0 vP(int paramInt1, int paramInt2) {
/*    */     return (iy0)super.XJ0(paramInt1, paramInt2);
/*    */   }
/*    */   
/*    */   public final xr0 v4(byte paramByte, short paramShort1, short paramShort2) {
/*    */     qx[] arrayOfQx;
/*    */     return (paramByte < 0 || paramByte >= (arrayOfQx = this.me0).length) ? null : this[paramByte].Jq0(paramShort1, paramShort2);
/*    */   }
/*    */   
/*    */   public final xr0 XG0(float paramFloat1, float paramFloat2, float paramFloat3) {
/*    */     float f;
/*    */     Ut ut;
/*    */     Iterator<Ut> iterator;
/*    */     for (f = Float.MAX_VALUE, ut = null, iterator = this.w7.iterator(); iterator.hasNext();) {
/*    */       if ((f1 = (ut1 = iterator.next()).mC0.Cl0(paramFloat1, paramFloat3, paramFloat2)) < f) {
/*    */         f = f1;
/*    */         ut = ut1;
/*    */       } 
/*    */     } 
/*    */     return ut;
/*    */   }
/*    */   
/*    */   public final il hd(float paramFloat1, float paramFloat2, float paramFloat3, Rc paramRc) {
/*    */     il il2 = null;
/*    */     float f2 = Float.MAX_VALUE;
/*    */     for (Ut ut : this.w7) {
/*    */       float f;
/*    */       if ((paramRc == null || paramRc.Wx(ut)) && (f = ut.mC0.Cl0(paramFloat1, paramFloat3, paramFloat2)) < f2) {
/*    */         f2 = f;
/*    */         il2 = ut;
/*    */       } 
/*    */     } 
/*    */     short s1 = (short)(int)paramFloat1, s2 = (short)(int)paramFloat2;
/*    */     il il1 = mF((byte)0, s1, s2);
/*    */     paramFloat1 = Ka();
/*    */     float f1 = i00();
/*    */     if ((paramRc == null || paramRc.Wx(this)) && (new eo(paramFloat1, f1, hA0())).Cl0(paramFloat1, paramFloat3, paramFloat2) < f2)
/*    */       il2 = this; 
/*    */     return il2;
/*    */   }
/*    */   
/*    */   public final void EB() {
/*    */     // Byte code:
/*    */     //   0: aload_0
/*    */     //   1: invokevirtual Xg0 : ()S
/*    */     //   4: dup
/*    */     //   5: istore_1
/*    */     //   6: tableswitch default -> 64, 573 -> 72, 574 -> 72, 575 -> 72, 576 -> 72, 577 -> 72, 578 -> 64, 579 -> 72, 580 -> 72, 581 -> 72, 582 -> 72, 583 -> 72
/*    */     //   64: aload_0
/*    */     //   65: getfield w7 : Ljava/util/ArrayList;
/*    */     //   68: invokevirtual clear : ()V
/*    */     //   71: return
/*    */     //   72: getstatic f/km.mI0 : Lf/P1;
/*    */     //   75: getfield MT : Lf/gD;
/*    */     //   78: dup
/*    */     //   79: astore_2
/*    */     //   80: new f/ig
/*    */     //   83: dup
/*    */     //   84: astore_3
/*    */     //   85: aload_2
/*    */     //   86: getfield TI : Lf/RD;
/*    */     //   89: ldc_w '/fielddata/tornworld/tw_arc.narc'
/*    */     //   92: invokevirtual B8 : (Ljava/lang/String;)Lf/T7;
/*    */     //   95: invokespecial <init> : (Lf/T7;)V
/*    */     //   98: getfield TI : Lf/RD;
/*    */     //   101: ldc_w '/fielddata/tornworld/tw_arc_attr.narc'
/*    */     //   104: invokevirtual B8 : (Ljava/lang/String;)Lf/T7;
/*    */     //   107: dup
/*    */     //   108: dup
/*    */     //   109: astore_2
/*    */     //   110: invokestatic Mx0 : ()V
/*    */     //   113: getfield db : Ljava/lang/String;
/*    */     //   116: pop
/*    */     //   117: getfield bP : Lf/HI;
/*    */     //   120: dup
/*    */     //   121: astore #4
/*    */     //   123: invokevirtual GA0 : ()Ljava/nio/ByteBuffer;
/*    */     //   126: dup
/*    */     //   127: astore #5
/*    */     //   129: aload_2
/*    */     //   130: getfield XL : I
/*    */     //   133: invokestatic cL0 : (Ljava/nio/ByteBuffer;I)I
/*    */     //   136: dup
/*    */     //   137: istore_2
/*    */     //   138: ldc_w 1129464142
/*    */     //   141: dup
/*    */     //   142: istore #6
/*    */     //   144: if_icmpne -> 2271
/*    */     //   147: aload_0
/*    */     //   148: aload #5
/*    */     //   150: dup
/*    */     //   151: dup
/*    */     //   152: invokestatic Lx0 : (Ljava/nio/ByteBuffer;)I
/*    */     //   155: istore_2
/*    */     //   156: invokevirtual getInt : ()I
/*    */     //   159: aload #5
/*    */     //   161: invokevirtual position : ()I
/*    */     //   164: bipush #8
/*    */     //   166: swap
/*    */     //   167: aload #5
/*    */     //   169: invokestatic TG0 : (IIILjava/nio/ByteBuffer;)I
/*    */     //   172: istore #6
/*    */     //   174: invokevirtual position : ()I
/*    */     //   177: iload #6
/*    */     //   179: iadd
/*    */     //   180: istore #6
/*    */     //   182: new f/sl
/*    */     //   185: dup
/*    */     //   186: aload_0
/*    */     //   187: swap
/*    */     //   188: aload_3
/*    */     //   189: iconst_0
/*    */     //   190: invokevirtual zz : (I)Lf/T7;
/*    */     //   193: iconst_0
/*    */     //   194: invokevirtual rb : (Z)Ljava/nio/ByteBuffer;
/*    */     //   197: invokespecial <init> : (Ljava/nio/ByteBuffer;)V
/*    */     //   200: invokevirtual Xg0 : ()S
/*    */     //   203: invokevirtual Td : (S)Lf/B5;
/*    */     //   206: astore #7
/*    */     //   208: new f/Ac
/*    */     //   211: dup
/*    */     //   212: dup
/*    */     //   213: astore #8
/*    */     //   215: aload_3
/*    */     //   216: aload #7
/*    */     //   218: getfield HX : S
/*    */     //   221: iconst_1
/*    */     //   222: iadd
/*    */     //   223: invokevirtual zz : (I)Lf/T7;
/*    */     //   226: invokespecial <init> : (Lf/T7;)V
/*    */     //   229: getfield hz0 : [Lf/o50;
/*    */     //   232: arraylength
/*    */     //   233: anewarray f/qx
/*    */     //   236: putfield me0 : [Lf/qx;
/*    */     //   239: iconst_0
/*    */     //   240: istore_3
/*    */     //   241: iload_3
/*    */     //   242: aload #8
/*    */     //   244: getfield hz0 : [Lf/o50;
/*    */     //   247: dup
/*    */     //   248: astore #9
/*    */     //   250: arraylength
/*    */     //   251: if_icmpge -> 955
/*    */     //   254: aload #9
/*    */     //   256: iload_3
/*    */     //   257: aaload
/*    */     //   258: dup
/*    */     //   259: astore #9
/*    */     //   261: getfield d0 : S
/*    */     //   264: dup
/*    */     //   265: istore #10
/*    */     //   267: tableswitch default -> 296, 0 -> 308, 1 -> 300, 2 -> 300, 3 -> 308
/*    */     //   296: iconst_0
/*    */     //   297: goto -> 313
/*    */     //   300: aload #9
/*    */     //   302: getfield T8 : S
/*    */     //   305: goto -> 313
/*    */     //   308: aload #9
/*    */     //   310: getfield Cf0 : S
/*    */     //   313: iconst_1
/*    */     //   314: iadd
/*    */     //   315: istore #11
/*    */     //   317: iload #10
/*    */     //   319: tableswitch default -> 348, 0 -> 352, 1 -> 352, 2 -> 352, 3 -> 352
/*    */     //   348: iconst_0
/*    */     //   349: goto -> 357
/*    */     //   352: aload #9
/*    */     //   354: getfield Pe : S
/*    */     //   357: iconst_1
/*    */     //   358: iadd
/*    */     //   359: istore #10
/*    */     //   361: aload #7
/*    */     //   363: getfield HX : S
/*    */     //   366: iconst_4
/*    */     //   367: if_icmpne -> 377
/*    */     //   370: iload_3
/*    */     //   371: ifne -> 377
/*    */     //   374: iinc #11, -1
/*    */     //   377: aload #9
/*    */     //   379: aload_0
/*    */     //   380: getfield me0 : [Lf/qx;
/*    */     //   383: iload_3
/*    */     //   384: new f/qx
/*    */     //   387: dup
/*    */     //   388: iload #11
/*    */     //   390: iload #10
/*    */     //   392: invokespecial <init> : (II)V
/*    */     //   395: aastore
/*    */     //   396: new f/eo
/*    */     //   399: dup
/*    */     //   400: astore #12
/*    */     //   402: aload #9
/*    */     //   404: getfield on0 : S
/*    */     //   407: i2f
/*    */     //   408: aload #9
/*    */     //   410: dup
/*    */     //   411: getfield Xc0 : S
/*    */     //   414: i2f
/*    */     //   415: fstore #13
/*    */     //   417: getfield Xl : S
/*    */     //   420: i2f
/*    */     //   421: fload #13
/*    */     //   423: swap
/*    */     //   424: invokespecial <init> : (FFF)V
/*    */     //   427: getfield d0 : S
/*    */     //   430: dup
/*    */     //   431: istore #13
/*    */     //   433: ifeq -> 488
/*    */     //   436: iload #13
/*    */     //   438: iconst_1
/*    */     //   439: if_icmpeq -> 471
/*    */     //   442: iload #13
/*    */     //   444: iconst_3
/*    */     //   445: if_icmpeq -> 451
/*    */     //   448: goto -> 501
/*    */     //   451: aload #12
/*    */     //   453: iload #11
/*    */     //   455: i2f
/*    */     //   456: ldc_w 0.5
/*    */     //   459: fsub
/*    */     //   460: fconst_0
/*    */     //   461: ldc_w 0.5
/*    */     //   464: invokevirtual Tz : (FFF)Lf/eo;
/*    */     //   467: pop
/*    */     //   468: goto -> 501
/*    */     //   471: aload #12
/*    */     //   473: iload #11
/*    */     //   475: iconst_1
/*    */     //   476: isub
/*    */     //   477: i2f
/*    */     //   478: fconst_0
/*    */     //   479: swap
/*    */     //   480: fconst_0
/*    */     //   481: invokevirtual Tz : (FFF)Lf/eo;
/*    */     //   484: pop
/*    */     //   485: goto -> 501
/*    */     //   488: aload #12
/*    */     //   490: ldc_w 0.5
/*    */     //   493: fconst_0
/*    */     //   494: ldc_w 0.5
/*    */     //   497: invokevirtual Tz : (FFF)Lf/eo;
/*    */     //   500: pop
/*    */     //   501: aload #9
/*    */     //   503: getfield ny0 : S
/*    */     //   506: dup
/*    */     //   507: istore #13
/*    */     //   509: iload_2
/*    */     //   510: aload #5
/*    */     //   512: iload_2
/*    */     //   513: bipush #12
/*    */     //   515: iadd
/*    */     //   516: iload #13
/*    */     //   518: bipush #8
/*    */     //   520: imul
/*    */     //   521: dup
/*    */     //   522: istore #14
/*    */     //   524: iadd
/*    */     //   525: invokevirtual getInt : (I)I
/*    */     //   528: istore #15
/*    */     //   530: bipush #12
/*    */     //   532: iconst_4
/*    */     //   533: iload #14
/*    */     //   535: aload #5
/*    */     //   537: invokestatic Rq0 : (IIIILjava/nio/ByteBuffer;)I
/*    */     //   540: iload #15
/*    */     //   542: dup
/*    */     //   543: iload #6
/*    */     //   545: iadd
/*    */     //   546: istore #14
/*    */     //   548: isub
/*    */     //   549: istore #15
/*    */     //   551: getstatic f/nN.Wj : [Ljava/lang/String;
/*    */     //   554: astore #16
/*    */     //   556: sipush #400
/*    */     //   559: if_icmpge -> 571
/*    */     //   562: aload #16
/*    */     //   564: iload #13
/*    */     //   566: aaload
/*    */     //   567: pop
/*    */     //   568: goto -> 577
/*    */     //   571: iload #13
/*    */     //   573: invokestatic toString : (I)Ljava/lang/String;
/*    */     //   576: pop
/*    */     //   577: iload #15
/*    */     //   579: aload #4
/*    */     //   581: invokevirtual GA0 : ()Ljava/nio/ByteBuffer;
/*    */     //   584: dup
/*    */     //   585: astore #13
/*    */     //   587: iload #14
/*    */     //   589: invokevirtual position : (I)Ljava/nio/Buffer;
/*    */     //   592: pop
/*    */     //   593: ifle -> 611
/*    */     //   596: iload #14
/*    */     //   598: aload #13
/*    */     //   600: invokevirtual limit : ()I
/*    */     //   603: iload #15
/*    */     //   605: swap
/*    */     //   606: aload #13
/*    */     //   608: invokestatic Pp0 : (IIILjava/nio/ByteBuffer;)V
/*    */     //   611: aload #13
/*    */     //   613: invokevirtual slice : ()Ljava/nio/ByteBuffer;
/*    */     //   616: getstatic java/nio/ByteOrder.LITTLE_ENDIAN : Ljava/nio/ByteOrder;
/*    */     //   619: invokevirtual order : (Ljava/nio/ByteOrder;)Ljava/nio/ByteBuffer;
/*    */     //   622: sipush #2048
/*    */     //   625: newarray byte
/*    */     //   627: dup
/*    */     //   628: astore #13
/*    */     //   630: invokevirtual get : ([B)Ljava/nio/ByteBuffer;
/*    */     //   633: pop
/*    */     //   634: iconst_0
/*    */     //   635: istore #14
/*    */     //   637: iload #14
/*    */     //   639: iload #11
/*    */     //   641: if_icmpge -> 947
/*    */     //   644: iconst_0
/*    */     //   645: istore #15
/*    */     //   647: iload #15
/*    */     //   649: iload #10
/*    */     //   651: if_icmpge -> 937
/*    */     //   654: aload #9
/*    */     //   656: new f/Ut
/*    */     //   659: dup
/*    */     //   660: astore #16
/*    */     //   662: aload_0
/*    */     //   663: dup
/*    */     //   664: aload #16
/*    */     //   666: aload_0
/*    */     //   667: aload #13
/*    */     //   669: iload #15
/*    */     //   671: bipush #32
/*    */     //   673: imul
/*    */     //   674: iload #14
/*    */     //   676: iadd
/*    */     //   677: iconst_2
/*    */     //   678: imul
/*    */     //   679: dup
/*    */     //   680: aload #13
/*    */     //   682: swap
/*    */     //   683: baload
/*    */     //   684: i2s
/*    */     //   685: istore #17
/*    */     //   687: iconst_1
/*    */     //   688: iadd
/*    */     //   689: baload
/*    */     //   690: i2s
/*    */     //   691: istore #18
/*    */     //   693: iload #14
/*    */     //   695: iload #15
/*    */     //   697: iload_3
/*    */     //   698: iload #17
/*    */     //   700: iload #18
/*    */     //   702: invokespecial <init> : (Lf/Cy;SSBSS)V
/*    */     //   705: getfield me0 : [Lf/qx;
/*    */     //   708: iload_3
/*    */     //   709: aaload
/*    */     //   710: getfield PL : [[Lf/Ut;
/*    */     //   713: iload #14
/*    */     //   715: aaload
/*    */     //   716: iload #15
/*    */     //   718: aload #16
/*    */     //   720: aastore
/*    */     //   721: getfield w7 : Ljava/util/ArrayList;
/*    */     //   724: aload #16
/*    */     //   726: invokevirtual add : (Ljava/lang/Object;)Z
/*    */     //   729: pop
/*    */     //   730: getfield mC0 : Lf/eo;
/*    */     //   733: dup
/*    */     //   734: astore #17
/*    */     //   736: aload #12
/*    */     //   738: dup
/*    */     //   739: dup
/*    */     //   740: aload #17
/*    */     //   742: invokevirtual getClass : ()Ljava/lang/Class;
/*    */     //   745: pop
/*    */     //   746: getfield x : F
/*    */     //   749: fstore #17
/*    */     //   751: getfield y : F
/*    */     //   754: fstore #18
/*    */     //   756: getfield z : F
/*    */     //   759: fstore #19
/*    */     //   761: fload #17
/*    */     //   763: fload #18
/*    */     //   765: fload #19
/*    */     //   767: invokevirtual TG0 : (FFF)Lf/eo;
/*    */     //   770: astore #17
/*    */     //   772: getfield d0 : S
/*    */     //   775: tableswitch default -> 804, 0 -> 896, 1 -> 866, 2 -> 837, 3 -> 807
/*    */     //   804: goto -> 927
/*    */     //   807: aload #17
/*    */     //   809: iload #15
/*    */     //   811: iload #14
/*    */     //   813: ineg
/*    */     //   814: i2f
/*    */     //   815: fstore #17
/*    */     //   817: i2f
/*    */     //   818: fstore #18
/*    */     //   820: fload #17
/*    */     //   822: fconst_0
/*    */     //   823: fload #18
/*    */     //   825: invokevirtual Tz : (FFF)Lf/eo;
/*    */     //   828: pop
/*    */     //   829: ldc_w 180.0
/*    */     //   832: fstore #17
/*    */     //   834: goto -> 920
/*    */     //   837: aload #17
/*    */     //   839: iload #15
/*    */     //   841: iload #14
/*    */     //   843: i2f
/*    */     //   844: fstore #17
/*    */     //   846: i2f
/*    */     //   847: fstore #18
/*    */     //   849: fconst_0
/*    */     //   850: fload #17
/*    */     //   852: fload #18
/*    */     //   854: invokevirtual Tz : (FFF)Lf/eo;
/*    */     //   857: pop
/*    */     //   858: ldc_w 90.0
/*    */     //   861: fstore #17
/*    */     //   863: goto -> 920
/*    */     //   866: aload #17
/*    */     //   868: iload #15
/*    */     //   870: iload #14
/*    */     //   872: ineg
/*    */     //   873: i2f
/*    */     //   874: fstore #17
/*    */     //   876: i2f
/*    */     //   877: fstore #18
/*    */     //   879: fconst_0
/*    */     //   880: fload #17
/*    */     //   882: fload #18
/*    */     //   884: invokevirtual Tz : (FFF)Lf/eo;
/*    */     //   887: pop
/*    */     //   888: ldc_w 270.0
/*    */     //   891: fstore #17
/*    */     //   893: goto -> 920
/*    */     //   896: aload #17
/*    */     //   898: iload #15
/*    */     //   900: iload #14
/*    */     //   902: i2f
/*    */     //   903: fstore #17
/*    */     //   905: i2f
/*    */     //   906: fstore #18
/*    */     //   908: fload #17
/*    */     //   910: fconst_0
/*    */     //   911: fload #18
/*    */     //   913: invokevirtual Tz : (FFF)Lf/eo;
/*    */     //   916: pop
/*    */     //   917: fconst_0
/*    */     //   918: fstore #17
/*    */     //   920: aload #16
/*    */     //   922: fload #17
/*    */     //   924: putfield ay : F
/*    */     //   927: iload #15
/*    */     //   929: iconst_1
/*    */     //   930: iadd
/*    */     //   931: i2s
/*    */     //   932: istore #15
/*    */     //   934: goto -> 647
/*    */     //   937: iload #14
/*    */     //   939: iconst_1
/*    */     //   940: iadd
/*    */     //   941: i2s
/*    */     //   942: istore #14
/*    */     //   944: goto -> 637
/*    */     //   947: iload_3
/*    */     //   948: iconst_1
/*    */     //   949: iadd
/*    */     //   950: i2b
/*    */     //   951: istore_3
/*    */     //   952: goto -> 241
/*    */     //   955: aload #8
/*    */     //   957: getfield vI : [Lf/Ev0;
/*    */     //   960: dup
/*    */     //   961: astore_2
/*    */     //   962: arraylength
/*    */     //   963: istore_3
/*    */     //   964: iconst_0
/*    */     //   965: istore #4
/*    */     //   967: iload #4
/*    */     //   969: iload_3
/*    */     //   970: if_icmpge -> 1162
/*    */     //   973: aload_2
/*    */     //   974: iload #4
/*    */     //   976: aaload
/*    */     //   977: astore #5
/*    */     //   979: iconst_0
/*    */     //   980: istore #6
/*    */     //   982: iload #6
/*    */     //   984: aload #5
/*    */     //   986: getfield AQ : S
/*    */     //   989: iconst_1
/*    */     //   990: iadd
/*    */     //   991: if_icmpge -> 1156
/*    */     //   994: aload_0
/*    */     //   995: aload #5
/*    */     //   997: aload_0
/*    */     //   998: aload #5
/*    */     //   1000: getfield hE : S
/*    */     //   1003: i2f
/*    */     //   1004: aload #5
/*    */     //   1006: dup
/*    */     //   1007: getfield Lq : S
/*    */     //   1010: iload #6
/*    */     //   1012: iadd
/*    */     //   1013: i2f
/*    */     //   1014: fstore #7
/*    */     //   1016: getfield i3 : S
/*    */     //   1019: i2f
/*    */     //   1020: fstore #9
/*    */     //   1022: fload #7
/*    */     //   1024: <illegal opcode> Wx : ()Lf/Rc;
/*    */     //   1029: fload #9
/*    */     //   1031: swap
/*    */     //   1032: invokevirtual hd : (FFFLf/Rc;)Lf/il;
/*    */     //   1035: astore #7
/*    */     //   1037: getfield hE : S
/*    */     //   1040: aload #5
/*    */     //   1042: getfield WL : S
/*    */     //   1045: iadd
/*    */     //   1046: i2f
/*    */     //   1047: aload #5
/*    */     //   1049: dup
/*    */     //   1050: getfield Lq : S
/*    */     //   1053: iload #6
/*    */     //   1055: iadd
/*    */     //   1056: aload #5
/*    */     //   1058: getfield M50 : S
/*    */     //   1061: iadd
/*    */     //   1062: i2f
/*    */     //   1063: fstore #9
/*    */     //   1065: getfield i3 : S
/*    */     //   1068: aload #5
/*    */     //   1070: getfield o9 : S
/*    */     //   1073: iadd
/*    */     //   1074: i2f
/*    */     //   1075: fstore #10
/*    */     //   1077: fload #9
/*    */     //   1079: <illegal opcode> Wx : ()Lf/Rc;
/*    */     //   1084: fload #10
/*    */     //   1086: swap
/*    */     //   1087: invokevirtual hd : (FFFLf/Rc;)Lf/il;
/*    */     //   1090: dup
/*    */     //   1091: astore #9
/*    */     //   1093: instanceof f/Ut
/*    */     //   1096: ifeq -> 1117
/*    */     //   1099: aload_0
/*    */     //   1100: getfield me0 : [Lf/qx;
/*    */     //   1103: aload #9
/*    */     //   1105: getfield pu : B
/*    */     //   1108: aaload
/*    */     //   1109: aload #5
/*    */     //   1111: getfield oh : S
/*    */     //   1114: putfield SK0 : S
/*    */     //   1117: aload #7
/*    */     //   1119: invokevirtual Y00 : ()Z
/*    */     //   1122: ifeq -> 1150
/*    */     //   1125: aload #7
/*    */     //   1127: aload #5
/*    */     //   1129: getfield UH0 : B
/*    */     //   1132: invokevirtual Cx : (B)Lf/xr0;
/*    */     //   1135: ifnonnull -> 1150
/*    */     //   1138: aload #7
/*    */     //   1140: aload #5
/*    */     //   1142: getfield UH0 : B
/*    */     //   1145: aload #7
/*    */     //   1147: invokevirtual vV : (BLf/il;)V
/*    */     //   1150: iinc #6, 1
/*    */     //   1153: goto -> 982
/*    */     //   1156: iinc #4, 1
/*    */     //   1159: goto -> 967
/*    */     //   1162: iconst_0
/*    */     //   1163: istore_2
/*    */     //   1164: iload_2
/*    */     //   1165: aload #8
/*    */     //   1167: getfield hz0 : [Lf/o50;
/*    */     //   1170: dup
/*    */     //   1171: astore_3
/*    */     //   1172: arraylength
/*    */     //   1173: if_icmpge -> 1824
/*    */     //   1176: aload_3
/*    */     //   1177: iload_2
/*    */     //   1178: aaload
/*    */     //   1179: aload_0
/*    */     //   1180: getfield me0 : [Lf/qx;
/*    */     //   1183: iload_2
/*    */     //   1184: aaload
/*    */     //   1185: dup
/*    */     //   1186: getfield rM : I
/*    */     //   1189: istore_3
/*    */     //   1190: getfield UX : I
/*    */     //   1193: istore #4
/*    */     //   1195: new f/eo
/*    */     //   1198: dup
/*    */     //   1199: astore #5
/*    */     //   1201: invokespecial <init> : ()V
/*    */     //   1204: getfield d0 : S
/*    */     //   1207: dup
/*    */     //   1208: istore #6
/*    */     //   1210: iconst_1
/*    */     //   1211: if_icmpeq -> 1255
/*    */     //   1214: iload #6
/*    */     //   1216: iconst_2
/*    */     //   1217: if_icmpeq -> 1241
/*    */     //   1220: iload #6
/*    */     //   1222: iconst_3
/*    */     //   1223: if_icmpeq -> 1229
/*    */     //   1226: goto -> 1327
/*    */     //   1229: aload #5
/*    */     //   1231: fconst_0
/*    */     //   1232: fconst_0
/*    */     //   1233: fconst_0
/*    */     //   1234: invokevirtual Tz : (FFF)Lf/eo;
/*    */     //   1237: pop
/*    */     //   1238: goto -> 1327
/*    */     //   1241: aload #5
/*    */     //   1243: fconst_1
/*    */     //   1244: fconst_1
/*    */     //   1245: ldc_w 1.5
/*    */     //   1248: invokevirtual Tz : (FFF)Lf/eo;
/*    */     //   1251: pop
/*    */     //   1252: goto -> 1327
/*    */     //   1255: iload_1
/*    */     //   1256: sipush #574
/*    */     //   1259: if_icmpne -> 1276
/*    */     //   1262: aload #5
/*    */     //   1264: fconst_0
/*    */     //   1265: fconst_1
/*    */     //   1266: ldc_w 1.5
/*    */     //   1269: invokevirtual Tz : (FFF)Lf/eo;
/*    */     //   1272: pop
/*    */     //   1273: goto -> 1327
/*    */     //   1276: iload_1
/*    */     //   1277: sipush #575
/*    */     //   1280: if_icmpne -> 1297
/*    */     //   1283: aload #5
/*    */     //   1285: fconst_0
/*    */     //   1286: ldc_w 0.875
/*    */     //   1289: fconst_1
/*    */     //   1290: invokevirtual Tz : (FFF)Lf/eo;
/*    */     //   1293: pop
/*    */     //   1294: goto -> 1327
/*    */     //   1297: iload_1
/*    */     //   1298: sipush #576
/*    */     //   1301: if_icmpne -> 1318
/*    */     //   1304: aload #5
/*    */     //   1306: fconst_0
/*    */     //   1307: fconst_1
/*    */     //   1308: ldc_w 0.5
/*    */     //   1311: invokevirtual Tz : (FFF)Lf/eo;
/*    */     //   1314: pop
/*    */     //   1315: goto -> 1327
/*    */     //   1318: aload #5
/*    */     //   1320: fconst_0
/*    */     //   1321: fconst_1
/*    */     //   1322: fconst_0
/*    */     //   1323: invokevirtual Tz : (FFF)Lf/eo;
/*    */     //   1326: pop
/*    */     //   1327: iconst_0
/*    */     //   1328: istore #6
/*    */     //   1330: iload #6
/*    */     //   1332: iload_3
/*    */     //   1333: if_icmpge -> 1816
/*    */     //   1336: iconst_0
/*    */     //   1337: istore #7
/*    */     //   1339: iload #7
/*    */     //   1341: iload #4
/*    */     //   1343: if_icmpge -> 1806
/*    */     //   1346: aload_0
/*    */     //   1347: dup
/*    */     //   1348: getfield me0 : [Lf/qx;
/*    */     //   1351: iload_2
/*    */     //   1352: aaload
/*    */     //   1353: iload #6
/*    */     //   1355: iload #7
/*    */     //   1357: invokevirtual Jq0 : (SS)Lf/Ut;
/*    */     //   1360: astore #9
/*    */     //   1362: getfield me0 : [Lf/qx;
/*    */     //   1365: iload_2
/*    */     //   1366: aaload
/*    */     //   1367: dup
/*    */     //   1368: astore #10
/*    */     //   1370: getfield SK0 : S
/*    */     //   1373: dup
/*    */     //   1374: istore #11
/*    */     //   1376: iconst_1
/*    */     //   1377: if_icmpeq -> 1665
/*    */     //   1380: iload #11
/*    */     //   1382: iconst_2
/*    */     //   1383: if_icmpeq -> 1574
/*    */     //   1386: iload #11
/*    */     //   1388: iconst_3
/*    */     //   1389: if_icmpeq -> 1483
/*    */     //   1392: aload #9
/*    */     //   1394: aload_0
/*    */     //   1395: aload #9
/*    */     //   1397: aload_0
/*    */     //   1398: aload #9
/*    */     //   1400: aload_0
/*    */     //   1401: aload #9
/*    */     //   1403: aload #10
/*    */     //   1405: iload #6
/*    */     //   1407: iload #7
/*    */     //   1409: iconst_1
/*    */     //   1410: isub
/*    */     //   1411: i2s
/*    */     //   1412: invokevirtual Jq0 : (SS)Lf/Ut;
/*    */     //   1415: iconst_1
/*    */     //   1416: swap
/*    */     //   1417: invokevirtual vV : (BLf/il;)V
/*    */     //   1420: getfield me0 : [Lf/qx;
/*    */     //   1423: iload_2
/*    */     //   1424: aaload
/*    */     //   1425: iload #6
/*    */     //   1427: iload #7
/*    */     //   1429: iconst_1
/*    */     //   1430: iadd
/*    */     //   1431: i2s
/*    */     //   1432: invokevirtual Jq0 : (SS)Lf/Ut;
/*    */     //   1435: iconst_0
/*    */     //   1436: swap
/*    */     //   1437: invokevirtual vV : (BLf/il;)V
/*    */     //   1440: getfield me0 : [Lf/qx;
/*    */     //   1443: iload_2
/*    */     //   1444: aaload
/*    */     //   1445: iload #6
/*    */     //   1447: iconst_1
/*    */     //   1448: iadd
/*    */     //   1449: i2s
/*    */     //   1450: iload #7
/*    */     //   1452: invokevirtual Jq0 : (SS)Lf/Ut;
/*    */     //   1455: iconst_3
/*    */     //   1456: swap
/*    */     //   1457: invokevirtual vV : (BLf/il;)V
/*    */     //   1460: getfield me0 : [Lf/qx;
/*    */     //   1463: iload_2
/*    */     //   1464: aaload
/*    */     //   1465: iload #6
/*    */     //   1467: iconst_1
/*    */     //   1468: isub
/*    */     //   1469: i2s
/*    */     //   1470: iload #7
/*    */     //   1472: invokevirtual Jq0 : (SS)Lf/Ut;
/*    */     //   1475: iconst_2
/*    */     //   1476: swap
/*    */     //   1477: invokevirtual vV : (BLf/il;)V
/*    */     //   1480: goto -> 1753
/*    */     //   1483: aload #9
/*    */     //   1485: aload_0
/*    */     //   1486: aload #9
/*    */     //   1488: aload_0
/*    */     //   1489: aload #9
/*    */     //   1491: aload_0
/*    */     //   1492: aload #9
/*    */     //   1494: aload #10
/*    */     //   1496: iload #6
/*    */     //   1498: iload #7
/*    */     //   1500: iconst_1
/*    */     //   1501: isub
/*    */     //   1502: i2s
/*    */     //   1503: invokevirtual Jq0 : (SS)Lf/Ut;
/*    */     //   1506: iconst_0
/*    */     //   1507: swap
/*    */     //   1508: invokevirtual vV : (BLf/il;)V
/*    */     //   1511: getfield me0 : [Lf/qx;
/*    */     //   1514: iload_2
/*    */     //   1515: aaload
/*    */     //   1516: iload #6
/*    */     //   1518: iload #7
/*    */     //   1520: iconst_1
/*    */     //   1521: iadd
/*    */     //   1522: i2s
/*    */     //   1523: invokevirtual Jq0 : (SS)Lf/Ut;
/*    */     //   1526: iconst_1
/*    */     //   1527: swap
/*    */     //   1528: invokevirtual vV : (BLf/il;)V
/*    */     //   1531: getfield me0 : [Lf/qx;
/*    */     //   1534: iload_2
/*    */     //   1535: aaload
/*    */     //   1536: iload #6
/*    */     //   1538: iconst_1
/*    */     //   1539: iadd
/*    */     //   1540: i2s
/*    */     //   1541: iload #7
/*    */     //   1543: invokevirtual Jq0 : (SS)Lf/Ut;
/*    */     //   1546: iconst_2
/*    */     //   1547: swap
/*    */     //   1548: invokevirtual vV : (BLf/il;)V
/*    */     //   1551: getfield me0 : [Lf/qx;
/*    */     //   1554: iload_2
/*    */     //   1555: aaload
/*    */     //   1556: iload #6
/*    */     //   1558: iconst_1
/*    */     //   1559: isub
/*    */     //   1560: i2s
/*    */     //   1561: iload #7
/*    */     //   1563: invokevirtual Jq0 : (SS)Lf/Ut;
/*    */     //   1566: iconst_3
/*    */     //   1567: swap
/*    */     //   1568: invokevirtual vV : (BLf/il;)V
/*    */     //   1571: goto -> 1753
/*    */     //   1574: aload #9
/*    */     //   1576: aload_0
/*    */     //   1577: aload #9
/*    */     //   1579: aload_0
/*    */     //   1580: aload #9
/*    */     //   1582: aload_0
/*    */     //   1583: aload #9
/*    */     //   1585: aload #10
/*    */     //   1587: iload #6
/*    */     //   1589: iload #7
/*    */     //   1591: iconst_1
/*    */     //   1592: isub
/*    */     //   1593: i2s
/*    */     //   1594: invokevirtual Jq0 : (SS)Lf/Ut;
/*    */     //   1597: iconst_2
/*    */     //   1598: swap
/*    */     //   1599: invokevirtual vV : (BLf/il;)V
/*    */     //   1602: getfield me0 : [Lf/qx;
/*    */     //   1605: iload_2
/*    */     //   1606: aaload
/*    */     //   1607: iload #6
/*    */     //   1609: iload #7
/*    */     //   1611: iconst_1
/*    */     //   1612: iadd
/*    */     //   1613: i2s
/*    */     //   1614: invokevirtual Jq0 : (SS)Lf/Ut;
/*    */     //   1617: iconst_3
/*    */     //   1618: swap
/*    */     //   1619: invokevirtual vV : (BLf/il;)V
/*    */     //   1622: getfield me0 : [Lf/qx;
/*    */     //   1625: iload_2
/*    */     //   1626: aaload
/*    */     //   1627: iload #6
/*    */     //   1629: iconst_1
/*    */     //   1630: iadd
/*    */     //   1631: i2s
/*    */     //   1632: iload #7
/*    */     //   1634: invokevirtual Jq0 : (SS)Lf/Ut;
/*    */     //   1637: iconst_1
/*    */     //   1638: swap
/*    */     //   1639: invokevirtual vV : (BLf/il;)V
/*    */     //   1642: getfield me0 : [Lf/qx;
/*    */     //   1645: iload_2
/*    */     //   1646: aaload
/*    */     //   1647: iload #6
/*    */     //   1649: iconst_1
/*    */     //   1650: isub
/*    */     //   1651: i2s
/*    */     //   1652: iload #7
/*    */     //   1654: invokevirtual Jq0 : (SS)Lf/Ut;
/*    */     //   1657: iconst_0
/*    */     //   1658: swap
/*    */     //   1659: invokevirtual vV : (BLf/il;)V
/*    */     //   1662: goto -> 1753
/*    */     //   1665: aload #9
/*    */     //   1667: aload_0
/*    */     //   1668: aload #9
/*    */     //   1670: aload_0
/*    */     //   1671: aload #9
/*    */     //   1673: aload_0
/*    */     //   1674: aload #9
/*    */     //   1676: aload #10
/*    */     //   1678: iload #6
/*    */     //   1680: iload #7
/*    */     //   1682: iconst_1
/*    */     //   1683: isub
/*    */     //   1684: i2s
/*    */     //   1685: invokevirtual Jq0 : (SS)Lf/Ut;
/*    */     //   1688: iconst_3
/*    */     //   1689: swap
/*    */     //   1690: invokevirtual vV : (BLf/il;)V
/*    */     //   1693: getfield me0 : [Lf/qx;
/*    */     //   1696: iload_2
/*    */     //   1697: aaload
/*    */     //   1698: iload #6
/*    */     //   1700: iload #7
/*    */     //   1702: iconst_1
/*    */     //   1703: iadd
/*    */     //   1704: i2s
/*    */     //   1705: invokevirtual Jq0 : (SS)Lf/Ut;
/*    */     //   1708: iconst_2
/*    */     //   1709: swap
/*    */     //   1710: invokevirtual vV : (BLf/il;)V
/*    */     //   1713: getfield me0 : [Lf/qx;
/*    */     //   1716: iload_2
/*    */     //   1717: aaload
/*    */     //   1718: iload #6
/*    */     //   1720: iconst_1
/*    */     //   1721: iadd
/*    */     //   1722: i2s
/*    */     //   1723: iload #7
/*    */     //   1725: invokevirtual Jq0 : (SS)Lf/Ut;
/*    */     //   1728: iconst_0
/*    */     //   1729: swap
/*    */     //   1730: invokevirtual vV : (BLf/il;)V
/*    */     //   1733: getfield me0 : [Lf/qx;
/*    */     //   1736: iload_2
/*    */     //   1737: aaload
/*    */     //   1738: iload #6
/*    */     //   1740: iconst_1
/*    */     //   1741: isub
/*    */     //   1742: i2s
/*    */     //   1743: iload #7
/*    */     //   1745: invokevirtual Jq0 : (SS)Lf/Ut;
/*    */     //   1748: iconst_1
/*    */     //   1749: swap
/*    */     //   1750: invokevirtual vV : (BLf/il;)V
/*    */     //   1753: iload #7
/*    */     //   1755: aload #9
/*    */     //   1757: getfield mC0 : Lf/eo;
/*    */     //   1760: dup
/*    */     //   1761: astore #7
/*    */     //   1763: aload #5
/*    */     //   1765: dup
/*    */     //   1766: dup
/*    */     //   1767: aload #7
/*    */     //   1769: invokevirtual getClass : ()Ljava/lang/Class;
/*    */     //   1772: pop
/*    */     //   1773: getfield x : F
/*    */     //   1776: fstore #7
/*    */     //   1778: getfield y : F
/*    */     //   1781: fstore #9
/*    */     //   1783: getfield z : F
/*    */     //   1786: fstore #10
/*    */     //   1788: fload #7
/*    */     //   1790: fload #9
/*    */     //   1792: fload #10
/*    */     //   1794: invokevirtual Tz : (FFF)Lf/eo;
/*    */     //   1797: pop
/*    */     //   1798: iconst_1
/*    */     //   1799: iadd
/*    */     //   1800: i2s
/*    */     //   1801: istore #7
/*    */     //   1803: goto -> 1339
/*    */     //   1806: iload #6
/*    */     //   1808: iconst_1
/*    */     //   1809: iadd
/*    */     //   1810: i2s
/*    */     //   1811: istore #6
/*    */     //   1813: goto -> 1330
/*    */     //   1816: iload_2
/*    */     //   1817: iconst_1
/*    */     //   1818: iadd
/*    */     //   1819: i2b
/*    */     //   1820: istore_2
/*    */     //   1821: goto -> 1164
/*    */     //   1824: iload_1
/*    */     //   1825: sipush #575
/*    */     //   1828: if_icmpne -> 1992
/*    */     //   1831: iconst_0
/*    */     //   1832: istore_1
/*    */     //   1833: iload_1
/*    */     //   1834: bipush #32
/*    */     //   1836: if_icmpge -> 1992
/*    */     //   1839: iload_1
/*    */     //   1840: aload_0
/*    */     //   1841: dup
/*    */     //   1842: dup2
/*    */     //   1843: dup2
/*    */     //   1844: dup2
/*    */     //   1845: getfield me0 : [Lf/qx;
/*    */     //   1848: iconst_0
/*    */     //   1849: aaload
/*    */     //   1850: bipush #31
/*    */     //   1852: iload_1
/*    */     //   1853: invokevirtual Jq0 : (SS)Lf/Ut;
/*    */     //   1856: astore_2
/*    */     //   1857: getfield me0 : [Lf/qx;
/*    */     //   1860: iconst_1
/*    */     //   1861: aaload
/*    */     //   1862: iconst_0
/*    */     //   1863: iload_1
/*    */     //   1864: invokevirtual Jq0 : (SS)Lf/Ut;
/*    */     //   1867: dup
/*    */     //   1868: astore_3
/*    */     //   1869: aload_2
/*    */     //   1870: iconst_3
/*    */     //   1871: aload_3
/*    */     //   1872: invokevirtual vV : (BLf/il;)V
/*    */     //   1875: iconst_2
/*    */     //   1876: aload_2
/*    */     //   1877: invokevirtual vV : (BLf/il;)V
/*    */     //   1880: getfield me0 : [Lf/qx;
/*    */     //   1883: iconst_2
/*    */     //   1884: aaload
/*    */     //   1885: bipush #31
/*    */     //   1887: iload_1
/*    */     //   1888: invokevirtual Jq0 : (SS)Lf/Ut;
/*    */     //   1891: astore_2
/*    */     //   1892: getfield me0 : [Lf/qx;
/*    */     //   1895: iconst_3
/*    */     //   1896: aaload
/*    */     //   1897: iconst_0
/*    */     //   1898: iload_1
/*    */     //   1899: invokevirtual Jq0 : (SS)Lf/Ut;
/*    */     //   1902: dup
/*    */     //   1903: astore_3
/*    */     //   1904: aload_2
/*    */     //   1905: iconst_3
/*    */     //   1906: aload_3
/*    */     //   1907: invokevirtual vV : (BLf/il;)V
/*    */     //   1910: iconst_2
/*    */     //   1911: aload_2
/*    */     //   1912: invokevirtual vV : (BLf/il;)V
/*    */     //   1915: getfield me0 : [Lf/qx;
/*    */     //   1918: iconst_0
/*    */     //   1919: aaload
/*    */     //   1920: iload_1
/*    */     //   1921: bipush #31
/*    */     //   1923: invokevirtual Jq0 : (SS)Lf/Ut;
/*    */     //   1926: astore_2
/*    */     //   1927: getfield me0 : [Lf/qx;
/*    */     //   1930: iconst_2
/*    */     //   1931: aaload
/*    */     //   1932: iload_1
/*    */     //   1933: iconst_0
/*    */     //   1934: invokevirtual Jq0 : (SS)Lf/Ut;
/*    */     //   1937: dup
/*    */     //   1938: astore_3
/*    */     //   1939: aload_2
/*    */     //   1940: iconst_0
/*    */     //   1941: aload_3
/*    */     //   1942: invokevirtual vV : (BLf/il;)V
/*    */     //   1945: iconst_1
/*    */     //   1946: aload_2
/*    */     //   1947: invokevirtual vV : (BLf/il;)V
/*    */     //   1950: getfield me0 : [Lf/qx;
/*    */     //   1953: iconst_1
/*    */     //   1954: aaload
/*    */     //   1955: iload_1
/*    */     //   1956: bipush #31
/*    */     //   1958: invokevirtual Jq0 : (SS)Lf/Ut;
/*    */     //   1961: astore_2
/*    */     //   1962: getfield me0 : [Lf/qx;
/*    */     //   1965: iconst_3
/*    */     //   1966: aaload
/*    */     //   1967: iload_1
/*    */     //   1968: iconst_0
/*    */     //   1969: invokevirtual Jq0 : (SS)Lf/Ut;
/*    */     //   1972: dup
/*    */     //   1973: astore_1
/*    */     //   1974: aload_2
/*    */     //   1975: iconst_0
/*    */     //   1976: aload_1
/*    */     //   1977: invokevirtual vV : (BLf/il;)V
/*    */     //   1980: iconst_1
/*    */     //   1981: aload_2
/*    */     //   1982: invokevirtual vV : (BLf/il;)V
/*    */     //   1985: iconst_1
/*    */     //   1986: iadd
/*    */     //   1987: i2s
/*    */     //   1988: istore_1
/*    */     //   1989: goto -> 1833
/*    */     //   1992: aload #8
/*    */     //   1994: getfield sW : [Lf/oj0;
/*    */     //   1997: dup
/*    */     //   1998: astore_1
/*    */     //   1999: ifnull -> 2270
/*    */     //   2002: aload_1
/*    */     //   2003: arraylength
/*    */     //   2004: istore_2
/*    */     //   2005: iconst_0
/*    */     //   2006: istore_3
/*    */     //   2007: iload_3
/*    */     //   2008: iload_2
/*    */     //   2009: if_icmpge -> 2270
/*    */     //   2012: aload_0
/*    */     //   2013: aload_1
/*    */     //   2014: iload_3
/*    */     //   2015: aaload
/*    */     //   2016: dup
/*    */     //   2017: astore #4
/*    */     //   2019: getfield Yy0 : S
/*    */     //   2022: i2f
/*    */     //   2023: ldc_w 0.125
/*    */     //   2026: fadd
/*    */     //   2027: aload #4
/*    */     //   2029: dup
/*    */     //   2030: getfield N5 : S
/*    */     //   2033: i2f
/*    */     //   2034: fstore #5
/*    */     //   2036: getfield Ag : S
/*    */     //   2039: i2f
/*    */     //   2040: ldc_w 0.125
/*    */     //   2043: fadd
/*    */     //   2044: fstore #6
/*    */     //   2046: fload #5
/*    */     //   2048: <illegal opcode> Wx : ()Lf/Rc;
/*    */     //   2053: fload #6
/*    */     //   2055: swap
/*    */     //   2056: invokevirtual hd : (FFFLf/Rc;)Lf/il;
/*    */     //   2059: dup
/*    */     //   2060: astore #5
/*    */     //   2062: ifnonnull -> 2068
/*    */     //   2065: goto -> 2264
/*    */     //   2068: iconst_0
/*    */     //   2069: istore #6
/*    */     //   2071: iload #6
/*    */     //   2073: aload #4
/*    */     //   2075: getfield Ft0 : S
/*    */     //   2078: iconst_1
/*    */     //   2079: iadd
/*    */     //   2080: if_icmpgt -> 2264
/*    */     //   2083: iload #6
/*    */     //   2085: ifle -> 2172
/*    */     //   2088: aload #5
/*    */     //   2090: invokevirtual Y00 : ()Z
/*    */     //   2093: ifeq -> 2135
/*    */     //   2096: aload_0
/*    */     //   2097: aload #5
/*    */     //   2099: dup
/*    */     //   2100: checkcast f/Ut
/*    */     //   2103: getfield pu : B
/*    */     //   2106: istore #7
/*    */     //   2108: invokevirtual Ka : ()S
/*    */     //   2111: istore #8
/*    */     //   2113: iload #7
/*    */     //   2115: aload #5
/*    */     //   2117: invokevirtual hA0 : ()S
/*    */     //   2120: iload #6
/*    */     //   2122: iadd
/*    */     //   2123: i2s
/*    */     //   2124: iload #8
/*    */     //   2126: swap
/*    */     //   2127: invokevirtual v4 : (BSS)Lf/xr0;
/*    */     //   2130: astore #7
/*    */     //   2132: goto -> 2176
/*    */     //   2135: aload_0
/*    */     //   2136: aload #5
/*    */     //   2138: dup
/*    */     //   2139: dup
/*    */     //   2140: invokevirtual Ka : ()S
/*    */     //   2143: istore #7
/*    */     //   2145: invokevirtual hA0 : ()S
/*    */     //   2148: iload #6
/*    */     //   2150: iadd
/*    */     //   2151: istore #8
/*    */     //   2153: getfield pu : B
/*    */     //   2156: istore #9
/*    */     //   2158: iload #7
/*    */     //   2160: iload #8
/*    */     //   2162: iload #9
/*    */     //   2164: invokevirtual v50 : (III)Lf/xr0;
/*    */     //   2167: astore #7
/*    */     //   2169: goto -> 2176
/*    */     //   2172: aload #5
/*    */     //   2174: astore #7
/*    */     //   2176: aload #7
/*    */     //   2178: ifnull -> 2264
/*    */     //   2181: aload #7
/*    */     //   2183: invokevirtual T9 : ()Z
/*    */     //   2186: ifeq -> 2192
/*    */     //   2189: goto -> 2264
/*    */     //   2192: aload #7
/*    */     //   2194: invokevirtual hz : ()Lf/ZK0;
/*    */     //   2197: getstatic f/Qm.A3 : Lf/ZK0;
/*    */     //   2200: if_acmpeq -> 2233
/*    */     //   2203: aload #7
/*    */     //   2205: invokevirtual hz : ()Lf/ZK0;
/*    */     //   2208: instanceof f/com1
/*    */     //   2211: ifeq -> 2233
/*    */     //   2214: aload #7
/*    */     //   2216: invokevirtual hz : ()Lf/ZK0;
/*    */     //   2219: checkcast f/com1
/*    */     //   2222: getfield Lm : Lf/fQ;
/*    */     //   2225: aload #4
/*    */     //   2227: invokevirtual Com3 : (Ljava/lang/Object;)V
/*    */     //   2230: goto -> 2254
/*    */     //   2233: aload #7
/*    */     //   2235: new f/com1
/*    */     //   2238: dup
/*    */     //   2239: astore #7
/*    */     //   2241: aload #4
/*    */     //   2243: invokespecial <init> : (Lf/oj0;)V
/*    */     //   2246: checkcast f/il
/*    */     //   2249: aload #7
/*    */     //   2251: putfield gl : Lf/ZK0;
/*    */     //   2254: iload #6
/*    */     //   2256: iconst_1
/*    */     //   2257: iadd
/*    */     //   2258: i2s
/*    */     //   2259: istore #6
/*    */     //   2261: goto -> 2071
/*    */     //   2264: iinc #3, 1
/*    */     //   2267: goto -> 2007
/*    */     //   2270: return
/*    */     //   2271: new java/lang/RuntimeException
/*    */     //   2274: dup
/*    */     //   2275: ldc_w 'Header magic mismatch = '
/*    */     //   2278: iload_2
/*    */     //   2279: ldc_w ' vs expected '
/*    */     //   2282: iload #6
/*    */     //   2284: invokestatic KK : (Ljava/lang/String;ILjava/lang/String;I)Ljava/lang/String;
/*    */     //   2287: invokespecial <init> : (Ljava/lang/String;)V
/*    */     //   2290: athrow
/*    */     // Line number table:
/*    */     //   Java source line number -> byte code offset
/*    */     //   #1	-> 86
/*    */     //   #2	-> 89
/*    */     //   #3	-> 98
/*    */     //   #4	-> 101
/*    */     //   #5	-> 110
/*    */     //   #6	-> 113
/*    */     //   #7	-> 117
/*    */     //   #8	-> 123
/*    */     //   #9	-> 133
/*    */     //   #10	-> 152
/*    */     //   #11	-> 156
/*    */     //   #12	-> 169
/*    */     //   #13	-> 174
/*    */     //   #14	-> 182
/*    */     //   #15	-> 190
/*    */     //   #16	-> 194
/*    */     //   #17	-> 197
/*    */     //   #18	-> 223
/*    */     //   #19	-> 226
/*    */     //   #20	-> 261
/*    */     //   #21	-> 302
/*    */     //   #22	-> 354
/*    */     //   #23	-> 363
/*    */     //   #24	-> 525
/*    */     //   #25	-> 537
/*    */     //   #26	-> 551
/*    */     //   #27	-> 581
/*    */     //   #28	-> 608
/*    */     //   #29	-> 613
/*    */     //   #30	-> 625
/*    */     //   #31	-> 656
/*    */     //   #32	-> 683
/*    */     //   #33	-> 689
/*    */     //   #34	-> 702
/*    */     //   #35	-> 710
/*    */     //   #36	-> 715
/*    */     //   #37	-> 721
/*    */     //   #38	-> 730
/*    */     //   #39	-> 742
/*    */     //   #40	-> 746
/*    */     //   #41	-> 772
/*    */     //   #42	-> 924
/*    */     //   #43	-> 957
/*    */     //   #44	-> 1105
/*    */     //   #45	-> 1108
/*    */     //   #46	-> 1186
/*    */     //   #47	-> 1190
/*    */     //   #48	-> 1195
/*    */     //   #49	-> 1757
/*    */     //   #50	-> 1769
/*    */     //   #51	-> 1773
/*    */     //   #52	-> 1845
/*    */     //   #53	-> 2103
/*    */     //   #54	-> 2108
/*    */     //   #55	-> 2153
/*    */     //   #56	-> 2164
/*    */     //   #57	-> 2222
/*    */     //   #58	-> 2227
/*    */     //   #59	-> 2235
/*    */     //   #60	-> 2251
/*    */     //   #61	-> 2271
/*    */     //   #62	-> 2275
/*    */     //   #63	-> 2287
/*    */   }
/*    */   
/*    */   public final Ws0 XJ0(int paramInt1, int paramInt2) {
/*    */     return super.XJ0(paramInt1, paramInt2);
/*    */   } }


/* Location:              /Users/vnnsnnt/Documents/Codespace/JavaWorkspace/RedTrainer/src/main/java/org/trainer/client/PokeMMO.jar!/f/xV.class
 * Java compiler version: 8 (52.0)
 * JD-Core Version:       1.1.3
 */