/*  1 */ package f;public final class YE extends Wr { public final YA0 Et0; public final dQ Ae0; public final of coM6; public YE(JG0 paramJG0) { Xu("admin-small-frame"); Lo("Player Actions"); TG0(() -> paramJG0.jf0(this)); super(); this.Et0 = new YA0(); (this.Ae0 = new dQ("Player Name:")).Xu("label-title"); (this.coM6 = new of()).LE(); J8(paramJG0); } private void sm0(es parames, Un paramUn) { if (parames.MQ.length == 
/*  2 */       0) { km.u4
/*    */ 
/*    */ 
/*    */ 
/*    */ 
/*    */         
/*  8 */         .lF(parames.QF.trim() + " " + this.coM6.F2.PH0.toString().trim()); paramUn.xI0();
/*    */        }
/*    */     
/*    */     else
/*    */     
/*    */     { 
/* 14 */       String str = parames.QF.trim() + " " + this.coM6.F2.PH0.toString().trim();
/* 15 */       String[] arrayOfString1 = parames.MQ;
/* 16 */       Xs0[] arrayOfXs0 = parames.pW;
/* 17 */       String[][] arrayOfString = sc.Jt;
/*    */       
/* 19 */       h2.nL0
/* 20 */         .J8((new sc(this, arrayOfString1, arrayOfXs0, this)).lI0()); }  } public final void P80(es[] paramArrayOfes) { this.Et0.gx(); this.Et0.Dv0.HI0(); this.Et0.Dv0.wP().fa0(15.0F); this(); Un un; YA0 yA0; yA0.Dv0.S7(this.Ae0).Kw(); yA0.Dv0.S7(this.Ae0).x70(); yA0.Dv0.S7(this.coM6).Ig0(170.0F); (this.Et0.Dv0.S7(yA0)).ss = Integer.valueOf(2); this.Et0.Dv0.S7(yA0).Kw(); this.Et0.Dv0.S7(yA0).x70(); byte b = 0; while (b < paramArrayOfes.length) { if (b % 2 == 0) this.Et0.Dv0.wP();  YA0 yA01 = this.Et0; yA01.Dv0.S7(ip0(paramArrayOfes[b])).Kw(); yA01.Dv0.S7(ip0(paramArrayOfes[b])).x70(); b++; }
/* 21 */      this("Reset highlight"); (new Un()).tW(YE::q); this.Et0
/* 22 */       .Dv0
/* 23 */       .S7(this)
/* 24 */       .Kw(); }
/*    */ 
/*    */   
/*    */   public final void LM(throws paramthrows) {
/*    */     km.u4.e20.W3(new Lc0());
/*    */   }
/*    */   
/*    */   public final Un ip0(es parames) {
/*    */     // Byte code:
/*    */     //   0: new f/Un
/*    */     //   3: dup
/*    */     //   4: dup
/*    */     //   5: astore_2
/*    */     //   6: aload_0
/*    */     //   7: aload_1
/*    */     //   8: aload_2
/*    */     //   9: aload_1
/*    */     //   10: getfield QF : Ljava/lang/String;
/*    */     //   13: invokespecial <init> : (Ljava/lang/String;)V
/*    */     //   16: aload_2
/*    */     //   17: <illegal opcode> run : (Lf/YE;Lf/es;Lf/Un;)Ljava/lang/Runnable;
/*    */     //   22: invokevirtual tW : (Ljava/lang/Runnable;)V
/*    */     //   25: areturn
/*    */     // Line number table:
/*    */     //   Java source line number -> byte code offset
/*    */     //   #1	-> 10
/*    */     //   #2	-> 13
/*    */   } }


/* Location:              /Users/vnnsnnt/Documents/Codespace/JavaWorkspace/RedTrainer/src/main/java/org/trainer/client/PokeMMO.jar!/f/YE.class
 * Java compiler version: 8 (52.0)
 * JD-Core Version:       1.1.3
 */