package f;

public final class yf0 extends ZK0 {
  public final boolean com4(xr0 paramxr01, xr0 paramxr02, tc paramtc, byte paramByte) {
    // Byte code:
    //   0: aload_1
    //   1: invokevirtual Q4 : ()Lf/KI;
    //   4: invokevirtual rH0 : ()Lf/HV;
    //   7: dup
    //   8: astore_0
    //   9: ifnonnull -> 14
    //   12: iconst_0
    //   13: ireturn
    //   14: aload_0
    //   15: aload_1
    //   16: dup
    //   17: dup
    //   18: invokevirtual Ka : ()S
    //   21: istore_0
    //   22: invokevirtual hA0 : ()S
    //   25: istore_2
    //   26: invokevirtual i00 : ()F
    //   29: pop
    //   30: getfield et : [Lf/NI0;
    //   33: dup
    //   34: astore #4
    //   36: arraylength
    //   37: istore #5
    //   39: iconst_0
    //   40: istore #6
    //   42: iload #6
    //   44: iload #5
    //   46: if_icmpge -> 82
    //   49: iload_0
    //   50: aload #4
    //   52: iload #6
    //   54: aaload
    //   55: dup
    //   56: astore #7
    //   58: invokevirtual Sn0 : ()S
    //   61: if_icmpne -> 76
    //   64: iload_2
    //   65: aload #7
    //   67: invokevirtual Qq0 : ()S
    //   70: if_icmpne -> 76
    //   73: goto -> 85
    //   76: iinc #6, 1
    //   79: goto -> 42
    //   82: aconst_null
    //   83: astore #7
    //   85: aload #7
    //   87: ifnonnull -> 92
    //   90: iconst_0
    //   91: ireturn
    //   92: aload_3
    //   93: getfield pm : Lf/d7;
    //   96: aload_1
    //   97: iconst_0
    //   98: anewarray f/nl
    //   101: iconst_0
    //   102: swap
    //   103: invokevirtual Ci0 : (Lf/xr0;Z[Lf/nl;)Z
    //   106: ireturn
    // Line number table:
    //   Java source line number -> byte code offset
    //   #1	-> 30
    //   #2	-> 93
    //   #3	-> 98
  }
}


/* Location:              /Users/vnnsnnt/Documents/Codespace/JavaWorkspace/RedTrainer/src/main/java/org/trainer/client/PokeMMO.jar!/f/yf0.class
 * Java compiler version: 8 (52.0)
 * JD-Core Version:       1.1.3
 */