/*  1 */ package f;public final class Yj0 extends JG0 { public final void d40() { this.Ip.mM(); int i = this.o8.RS();
/*    */     
/*  3 */     i = this.o8.e3();
/*    */ 
/*    */     
/*  6 */     this.Ip.ME(JO.Se0(this.o8.qF(), this.Ip.xY, 2, i), (this.o8.Hy() - this.Ip.HC) / 2 + i);
/*  7 */     this.cq.mM(); i = this.o8.RS();
/*    */ 
/*    */     
/* 10 */     i = this.o8.e3();
/*    */ 
/*    */     
/* 13 */     this.cq.ME(JO.Se0(this.o8.qF(), this.cq.xY, 2, i), (this.o8.Hy() - this.cq.HC) / 2 + i);
/* 14 */     this.lL0.mM(); i = this.o8.RS();
/*    */ 
/*    */     
/* 17 */     i = this.o8.e3();
/*    */ 
/*    */     
/* 20 */     this.lL0.ME(JO.Se0(this.o8.qF(), this.lL0.xY, 2, i), (this.o8.Hy() - this.lL0.HC) / 2 + i); }
/*    */ 
/*    */   
/*    */   public DecimalFormat cD;
/*    */   public final Ip Ip;
/*    */   public final dQ As;
/*    */   public final IN tY;
/*    */   public final Ip cq;
/*    */   public final dQ xD;
/*    */   public final Un vO;
/*    */   public final Un Pj0;
/*    */   public final Ip lL0;
/*    */   public final dQ OI;
/*    */   public final js o8;
/*    */   public int kn;
/*    */   public int gM;
/*    */   public int NW;
/*    */   
/*    */   public Yj0(js paramjs) {
/*    */     this(paramjs, -2);
/*    */   }
/*    */   
/*    */   public Yj0(js paramjs, int paramInt) {
/*    */     dQ dQ1;
/*    */     dQ dQ2;
/*    */     dQ dQ3;
/*    */     Un un1;
/*    */     this.cD = new DecimalFormat("0.00");
/*    */     this.kn = -2;
/*    */     this.gM = -2;
/*    */     this.NW = 0;
/*    */     Xu("logingui");
/*    */     this.o8 = paramjs;
/*    */     this.kn = paramInt;
/*    */     this.gM = paramInt;
/*    */     this();
/*    */     this.Ip = ip2;
/*    */     ip2.Xu("login-panel");
/*    */     this(Ml0.OH0(74));
/*    */     this.As = new dQ();
/*    */     this.tY = new IN();
/*    */     Ip ip2;
/*    */     (new Ip()).rK0((ip2 = new Ip()).AUX(new JG0[] { dQ2 }));
/*    */     (new Ip()).WN((new Ip()).vo0(new JG0[] { dQ2 }));
/*    */     J8(new Ip());
/*    */     this();
/*    */     this.cq = ip1;
/*    */     ip1.Xu("login-panel");
/*    */     this("");
/*    */     this.xD = new dQ();
/*    */     this(Ml0.OH0(52));
/*    */     this.vO = un2;
/*    */     Un un2;
/*    */     (un2 = new Un()).tW(new LO(this));
/*    */     this(Ml0.OH0(53));
/*    */     this.Pj0 = un3;
/*    */     Un un3;
/*    */     (un3 = new Un()).tW(new dX());
/*    */     cr0 cr02;
/*    */     (cr02 = ip1.d7()).ee0(ip1.mE0().Ya(dQ3).ee0(ip1.d7().Em0().Mg(new JG0[] { un2, un3 }).Em0()));
/*    */     Ip ip1;
/*    */     (ip1 = new Ip()).d7().ee0(ip1.vo0(new JG0[] { dQ3 }).l9(20).ee0(ip1.AUX(new JG0[] { un2, un3 })));
/*    */     (new Ip()).WN((ip1 = new Ip()).d7());
/*    */     (new Ip()).rK0(cr02);
/*    */     (new Ip()).wI0(false);
/*    */     J8(new Ip());
/*    */     this();
/*    */     this.lL0 = ip1;
/*    */     ip1.Xu("login-panel");
/*    */     this("");
/*    */     this.OI = new dQ();
/*    */     this(Ml0.OH0(52));
/*    */     (new Un()).tW(new mz0());
/*    */     cr0 cr01;
/*    */     (cr01 = ip1.d7()).ee0(ip1.mE0().Ya(this).ee0(ip1.d7().Em0().Mg(new JG0[] { un1 }).Em0()));
/*    */     (ip1 = new Ip()).d7().ee0(ip1.Gs(new U90[] { ip1.mE0().Ya(this), ip1.mE0().Mg(new JG0[] { un1 }) }));
/*    */     (new Ip()).WN((ip1 = new Ip()).d7());
/*    */     (new Ip()).rK0(cr01);
/*    */     (new Ip()).wI0(false);
/*    */     J8(new Ip());
/*    */   }
/*    */   
/*    */   static {
/*    */     C00.gd(Yj0.class);
/*    */   }
/*    */   
/*    */   public final void BQ(String paramString, float paramFloat) {
/*    */     UB0.Kg0.fN(new p1(this, paramString, paramFloat));
/*    */   }
/*    */   
/*    */   public final void V90(throws paramthrows) {
/*    */     update();
/*    */     super.V90(paramthrows);
/*    */   }
/*    */   
/*    */   public final void update() {
/*    */     // Byte code:
/*    */     //   0: aload_0
/*    */     //   1: getfield gM : I
/*    */     //   4: aload_0
/*    */     //   5: getfield kn : I
/*    */     //   8: dup
/*    */     //   9: istore_1
/*    */     //   10: if_icmpeq -> 440
/*    */     //   13: iload_1
/*    */     //   14: aload_0
/*    */     //   15: iload_1
/*    */     //   16: putfield gM : I
/*    */     //   19: iconst_1
/*    */     //   20: if_icmpeq -> 379
/*    */     //   23: iload_1
/*    */     //   24: iconst_2
/*    */     //   25: if_icmpeq -> 360
/*    */     //   28: iload_1
/*    */     //   29: iconst_3
/*    */     //   30: if_icmpeq -> 97
/*    */     //   33: iload_1
/*    */     //   34: iconst_5
/*    */     //   35: if_icmpeq -> 41
/*    */     //   38: goto -> 1184
/*    */     //   41: aload_0
/*    */     //   42: dup
/*    */     //   43: dup
/*    */     //   44: getfield cq : Lf/Ip;
/*    */     //   47: iconst_0
/*    */     //   48: invokevirtual wI0 : (Z)V
/*    */     //   51: getfield Ip : Lf/Ip;
/*    */     //   54: iconst_0
/*    */     //   55: invokevirtual wI0 : (Z)V
/*    */     //   58: getfield lL0 : Lf/Ip;
/*    */     //   61: iconst_1
/*    */     //   62: invokevirtual wI0 : (Z)V
/*    */     //   65: getstatic f/km.VH : Lf/Yj;
/*    */     //   68: getfield cW : Z
/*    */     //   71: ifeq -> 81
/*    */     //   74: aload_0
/*    */     //   75: getfield o8 : Lf/js;
/*    */     //   78: invokevirtual Mo : ()V
/*    */     //   81: aload_0
/*    */     //   82: getfield OI : Lf/dQ;
/*    */     //   85: getstatic f/km.VH : Lf/Yj;
/*    */     //   88: getfield Qs0 : Ljava/lang/String;
/*    */     //   91: invokevirtual E1 : (Ljava/lang/String;)V
/*    */     //   94: goto -> 1184
/*    */     //   97: getstatic f/km.Gj : Lf/af;
/*    */     //   100: invokevirtual getClass : ()Ljava/lang/Class;
/*    */     //   103: pop
/*    */     //   104: getstatic f/jX.uP : Z
/*    */     //   107: ifne -> 267
/*    */     //   110: getstatic f/UB0.Kg0 : Lf/Q50;
/*    */     //   113: invokevirtual getClass : ()Ljava/lang/Class;
/*    */     //   116: pop
/*    */     //   117: getstatic f/Dp0.Ro0 : Lf/Dp0;
/*    */     //   120: getstatic f/Dp0.QG : Lf/Dp0;
/*    */     //   123: if_acmpne -> 130
/*    */     //   126: iconst_1
/*    */     //   127: goto -> 131
/*    */     //   130: iconst_0
/*    */     //   131: ifeq -> 137
/*    */     //   134: goto -> 267
/*    */     //   137: ldc ''
/*    */     //   139: astore_1
/*    */     //   140: invokestatic zp : ()Z
/*    */     //   143: ifeq -> 212
/*    */     //   146: getstatic f/jX.qf : Lf/og;
/*    */     //   149: getfield sw0 : I
/*    */     //   152: istore_1
/*    */     //   153: getstatic f/jX.IZ : Lf/og;
/*    */     //   156: ifnull -> 166
/*    */     //   159: getstatic f/km.Gj : Lf/af;
/*    */     //   162: invokevirtual getClass : ()Ljava/lang/Class;
/*    */     //   165: pop
/*    */     //   166: getstatic f/jX.Qo : Lf/og;
/*    */     //   169: dup
/*    */     //   170: astore_2
/*    */     //   171: ifnull -> 179
/*    */     //   174: aload_2
/*    */     //   175: getfield sw0 : I
/*    */     //   178: istore_1
/*    */     //   179: iload_1
/*    */     //   180: getstatic f/km.Gj : Lf/af;
/*    */     //   183: invokevirtual getClass : ()Ljava/lang/Class;
/*    */     //   186: pop
/*    */     //   187: i2l
/*    */     //   188: invokestatic F6 : (J)Ljava/lang/String;
/*    */     //   191: astore_1
/*    */     //   192: ldc_w '\\n\\n'
/*    */     //   195: invokestatic df : (Ljava/lang/String;)Ljava/lang/StringBuilder;
/*    */     //   198: sipush #915
/*    */     //   201: aload_1
/*    */     //   202: invokestatic Go : (ILjava/lang/String;)Ljava/lang/String;
/*    */     //   205: invokevirtual append : (Ljava/lang/String;)Ljava/lang/StringBuilder;
/*    */     //   208: invokevirtual toString : ()Ljava/lang/String;
/*    */     //   211: astore_1
/*    */     //   212: aload_0
/*    */     //   213: getfield xD : Lf/dQ;
/*    */     //   216: new java/lang/StringBuilder
/*    */     //   219: dup
/*    */     //   220: invokespecial <init> : ()V
/*    */     //   223: new java/lang/StringBuilder
/*    */     //   226: dup
/*    */     //   227: invokespecial <init> : ()V
/*    */     //   230: getstatic f/jX.sn0 : I
/*    */     //   233: invokevirtual append : (I)Ljava/lang/StringBuilder;
/*    */     //   236: ldc ''
/*    */     //   238: invokevirtual append : (Ljava/lang/String;)Ljava/lang/StringBuilder;
/*    */     //   241: invokevirtual toString : ()Ljava/lang/String;
/*    */     //   244: sipush #903
/*    */     //   247: swap
/*    */     //   248: invokestatic Go : (ILjava/lang/String;)Ljava/lang/String;
/*    */     //   251: invokevirtual append : (Ljava/lang/String;)Ljava/lang/StringBuilder;
/*    */     //   254: aload_1
/*    */     //   255: invokevirtual append : (Ljava/lang/String;)Ljava/lang/StringBuilder;
/*    */     //   258: invokevirtual toString : ()Ljava/lang/String;
/*    */     //   261: invokevirtual E1 : (Ljava/lang/String;)V
/*    */     //   264: goto -> 333
/*    */     //   267: aload_0
/*    */     //   268: dup
/*    */     //   269: dup
/*    */     //   270: dup2
/*    */     //   271: getfield xD : Lf/dQ;
/*    */     //   274: new java/lang/StringBuilder
/*    */     //   277: dup
/*    */     //   278: invokespecial <init> : ()V
/*    */     //   281: getstatic f/jX.sn0 : I
/*    */     //   284: invokevirtual append : (I)Ljava/lang/StringBuilder;
/*    */     //   287: ldc ''
/*    */     //   289: invokevirtual append : (Ljava/lang/String;)Ljava/lang/StringBuilder;
/*    */     //   292: invokevirtual toString : ()Ljava/lang/String;
/*    */     //   295: sipush #902
/*    */     //   298: swap
/*    */     //   299: invokestatic Go : (ILjava/lang/String;)Ljava/lang/String;
/*    */     //   302: invokevirtual E1 : (Ljava/lang/String;)V
/*    */     //   305: getfield vO : Lf/Un;
/*    */     //   308: iconst_0
/*    */     //   309: invokevirtual wI0 : (Z)V
/*    */     //   312: getfield vO : Lf/Un;
/*    */     //   315: iconst_0
/*    */     //   316: invokevirtual sk0 : (Z)V
/*    */     //   319: getfield Pj0 : Lf/Un;
/*    */     //   322: iconst_0
/*    */     //   323: invokevirtual wI0 : (Z)V
/*    */     //   326: getfield Pj0 : Lf/Un;
/*    */     //   329: iconst_0
/*    */     //   330: invokevirtual sk0 : (Z)V
/*    */     //   333: aload_0
/*    */     //   334: dup
/*    */     //   335: dup
/*    */     //   336: getfield cq : Lf/Ip;
/*    */     //   339: iconst_1
/*    */     //   340: invokevirtual wI0 : (Z)V
/*    */     //   343: getfield Ip : Lf/Ip;
/*    */     //   346: iconst_0
/*    */     //   347: invokevirtual wI0 : (Z)V
/*    */     //   350: getfield lL0 : Lf/Ip;
/*    */     //   353: iconst_0
/*    */     //   354: invokevirtual wI0 : (Z)V
/*    */     //   357: goto -> 1184
/*    */     //   360: aload_0
/*    */     //   361: sipush #901
/*    */     //   364: ldc_w 'Could not load main update feed.\\nThis may be caused by a firewall restriction, incorrect proxy settings, or a server error.'
/*    */     //   367: invokestatic la : (ILjava/lang/String;)Ljava/lang/String;
/*    */     //   370: ldc_w -1.0
/*    */     //   373: invokevirtual BQ : (Ljava/lang/String;F)V
/*    */     //   376: goto -> 1184
/*    */     //   379: getstatic f/km.Gj : Lf/af;
/*    */     //   382: invokevirtual getClass : ()Ljava/lang/Class;
/*    */     //   385: pop
/*    */     //   386: getstatic f/jX.Ez0 : Z
/*    */     //   389: ifeq -> 423
/*    */     //   392: invokestatic PH : ()Z
/*    */     //   395: ifeq -> 423
/*    */     //   398: aload_0
/*    */     //   399: dup
/*    */     //   400: sipush #2022
/*    */     //   403: ldc_w 'This client is outdated. Please uninstall and redownload the client from https://pokemmo.com/downloads/'
/*    */     //   406: invokestatic la : (ILjava/lang/String;)Ljava/lang/String;
/*    */     //   409: ldc_w -1.0
/*    */     //   412: invokevirtual BQ : (Ljava/lang/String;F)V
/*    */     //   415: bipush #6
/*    */     //   417: putfield kn : I
/*    */     //   420: goto -> 1184
/*    */     //   423: getstatic f/UB0.Kg0 : Lf/Q50;
/*    */     //   426: new f/eh
/*    */     //   429: dup
/*    */     //   430: aload_0
/*    */     //   431: invokespecial <init> : (Lf/Yj0;)V
/*    */     //   434: invokevirtual fN : (Ljava/lang/Runnable;)V
/*    */     //   437: goto -> 1184
/*    */     //   440: iload_1
/*    */     //   441: bipush #-2
/*    */     //   443: if_icmpne -> 640
/*    */     //   446: aload_0
/*    */     //   447: getfield NW : I
/*    */     //   450: dup
/*    */     //   451: aload_0
/*    */     //   452: swap
/*    */     //   453: iconst_1
/*    */     //   454: iadd
/*    */     //   455: putfield NW : I
/*    */     //   458: iconst_3
/*    */     //   459: if_icmple -> 603
/*    */     //   462: getstatic f/km.mI0 : Lf/P1;
/*    */     //   465: dup
/*    */     //   466: astore_1
/*    */     //   467: ifnull -> 603
/*    */     //   470: aload_1
/*    */     //   471: getfield Mv0 : Z
/*    */     //   474: ifne -> 603
/*    */     //   477: getstatic f/km.VH : Lf/Yj;
/*    */     //   480: dup
/*    */     //   481: astore_1
/*    */     //   482: getfield Cd : Z
/*    */     //   485: ifeq -> 603
/*    */     //   488: new f/Hk
/*    */     //   491: dup
/*    */     //   492: dup
/*    */     //   493: invokespecial <init> : ()V
/*    */     //   496: putstatic f/km.q00 : Lf/Hk;
/*    */     //   499: invokevirtual bg : ()Z
/*    */     //   502: ifne -> 517
/*    */     //   505: aload_1
/*    */     //   506: dup
/*    */     //   507: ldc_w 'Error loading addons.pak. The loaded file is corrupt.'
/*    */     //   510: putfield Qs0 : Ljava/lang/String;
/*    */     //   513: iconst_1
/*    */     //   514: putfield cW : Z
/*    */     //   517: aload_0
/*    */     //   518: new f/uk0
/*    */     //   521: dup
/*    */     //   522: astore_2
/*    */     //   523: invokespecial <init> : ()V
/*    */     //   526: getstatic f/vo.tI : Ljava/util/LinkedList;
/*    */     //   529: aload_2
/*    */     //   530: invokevirtual add : (Ljava/lang/Object;)Z
/*    */     //   533: pop
/*    */     //   534: new f/wC
/*    */     //   537: dup
/*    */     //   538: astore_2
/*    */     //   539: invokespecial <init> : ()V
/*    */     //   542: getstatic f/vo.tI : Ljava/util/LinkedList;
/*    */     //   545: aload_2
/*    */     //   546: invokevirtual add : (Ljava/lang/Object;)Z
/*    */     //   549: pop
/*    */     //   550: new f/nE
/*    */     //   553: dup
/*    */     //   554: astore_2
/*    */     //   555: invokespecial <init> : ()V
/*    */     //   558: getstatic f/vo.tI : Ljava/util/LinkedList;
/*    */     //   561: aload_2
/*    */     //   562: invokevirtual add : (Ljava/lang/Object;)Z
/*    */     //   565: pop
/*    */     //   566: new f/px
/*    */     //   569: dup
/*    */     //   570: astore_2
/*    */     //   571: invokespecial <init> : ()V
/*    */     //   574: getstatic f/vo.tI : Ljava/util/LinkedList;
/*    */     //   577: aload_2
/*    */     //   578: invokevirtual add : (Ljava/lang/Object;)Z
/*    */     //   581: pop
/*    */     //   582: new f/He
/*    */     //   585: dup
/*    */     //   586: astore_2
/*    */     //   587: aload_1
/*    */     //   588: invokespecial <init> : (Lf/Yj;)V
/*    */     //   591: getstatic f/vo.tI : Ljava/util/LinkedList;
/*    */     //   594: aload_2
/*    */     //   595: invokevirtual add : (Ljava/lang/Object;)Z
/*    */     //   598: pop
/*    */     //   599: iconst_m1
/*    */     //   600: putfield kn : I
/*    */     //   603: getstatic f/km.VH : Lf/Yj;
/*    */     //   606: getfield Qs0 : Ljava/lang/String;
/*    */     //   609: ifnull -> 617
/*    */     //   612: aload_0
/*    */     //   613: iconst_5
/*    */     //   614: putfield kn : I
/*    */     //   617: getstatic f/km.mI0 : Lf/P1;
/*    */     //   620: dup
/*    */     //   621: astore_1
/*    */     //   622: ifnull -> 1184
/*    */     //   625: aload_1
/*    */     //   626: getfield Mv0 : Z
/*    */     //   629: ifeq -> 1184
/*    */     //   632: aload_0
/*    */     //   633: iconst_m1
/*    */     //   634: putfield kn : I
/*    */     //   637: goto -> 1184
/*    */     //   640: iload_1
/*    */     //   641: iconst_m1
/*    */     //   642: if_icmpne -> 1132
/*    */     //   645: getstatic f/km.mI0 : Lf/P1;
/*    */     //   648: dup
/*    */     //   649: astore_2
/*    */     //   650: ifnull -> 1132
/*    */     //   653: aload_2
/*    */     //   654: getfield Mv0 : Z
/*    */     //   657: ifne -> 678
/*    */     //   660: getstatic f/km.VH : Lf/Yj;
/*    */     //   663: dup
/*    */     //   664: astore_1
/*    */     //   665: getfield Cd : Z
/*    */     //   668: ifeq -> 735
/*    */     //   671: aload_1
/*    */     //   672: getfield au0 : Z
/*    */     //   675: ifeq -> 735
/*    */     //   678: aload_0
/*    */     //   679: iconst_0
/*    */     //   680: putfield kn : I
/*    */     //   683: getstatic f/Bz.Rf : Z
/*    */     //   686: ifne -> 730
/*    */     //   689: getstatic f/Pa0.vH0 : I
/*    */     //   692: ifne -> 698
/*    */     //   695: goto -> 730
/*    */     //   698: aload_0
/*    */     //   699: getstatic f/A1.L7 : Lf/A1;
/*    */     //   702: <illegal opcode> run : ()Ljava/lang/Runnable;
/*    */     //   707: astore_1
/*    */     //   708: getfield nc : Lf/cK0;
/*    */     //   711: aload_1
/*    */     //   712: invokevirtual execute : (Ljava/lang/Runnable;)V
/*    */     //   715: sipush #917
/*    */     //   718: invokestatic OH0 : (I)Ljava/lang/String;
/*    */     //   721: ldc_w -1.0
/*    */     //   724: invokevirtual BQ : (Ljava/lang/String;F)V
/*    */     //   727: goto -> 735
/*    */     //   730: aload_0
/*    */     //   731: iconst_1
/*    */     //   732: putfield kn : I
/*    */     //   735: getstatic f/km.VH : Lf/Yj;
/*    */     //   738: getfield Qs0 : Ljava/lang/String;
/*    */     //   741: ifnull -> 749
/*    */     //   744: aload_0
/*    */     //   745: iconst_5
/*    */     //   746: putfield kn : I
/*    */     //   749: getstatic f/km.ln : Lf/ei;
/*    */     //   752: dup
/*    */     //   753: astore_1
/*    */     //   754: ifnull -> 1184
/*    */     //   757: aload_1
/*    */     //   758: getfield tn : Lf/fQ;
/*    */     //   761: invokevirtual isEmpty : ()Z
/*    */     //   764: iconst_1
/*    */     //   765: ixor
/*    */     //   766: ifeq -> 1184
/*    */     //   769: getstatic f/km.ln : Lf/ei;
/*    */     //   772: dup
/*    */     //   773: astore_1
/*    */     //   774: getfield tn : Lf/fQ;
/*    */     //   777: invokevirtual isEmpty : ()Z
/*    */     //   780: ifeq -> 788
/*    */     //   783: fconst_0
/*    */     //   784: fstore_1
/*    */     //   785: goto -> 1035
/*    */     //   788: aload_1
/*    */     //   789: fconst_0
/*    */     //   790: fstore_2
/*    */     //   791: getfield tn : Lf/fQ;
/*    */     //   794: invokevirtual r30 : ()Lf/Hc0;
/*    */     //   797: astore_3
/*    */     //   798: aload_3
/*    */     //   799: invokevirtual hasNext : ()Z
/*    */     //   802: ifeq -> 1024
/*    */     //   805: aload_3
/*    */     //   806: invokevirtual next : ()Ljava/lang/Object;
/*    */     //   809: checkcast f/IZ
/*    */     //   812: getfield wm0 : Lf/fw0;
/*    */     //   815: dup
/*    */     //   816: astore #4
/*    */     //   818: ifnull -> 825
/*    */     //   821: iconst_1
/*    */     //   822: goto -> 826
/*    */     //   825: iconst_0
/*    */     //   826: ifeq -> 1017
/*    */     //   829: aload #4
/*    */     //   831: getfield KG0 : B
/*    */     //   834: dup
/*    */     //   835: istore #5
/*    */     //   837: iconst_2
/*    */     //   838: if_icmpeq -> 923
/*    */     //   841: iload #5
/*    */     //   843: iconst_4
/*    */     //   844: if_icmpne -> 850
/*    */     //   847: goto -> 923
/*    */     //   850: aload #4
/*    */     //   852: getfield Nul : Z
/*    */     //   855: ifeq -> 861
/*    */     //   858: goto -> 931
/*    */     //   861: aload #4
/*    */     //   863: getfield UD : I
/*    */     //   866: dup
/*    */     //   867: istore #5
/*    */     //   869: iflt -> 900
/*    */     //   872: aload #4
/*    */     //   874: getfield KN : I
/*    */     //   877: iload #5
/*    */     //   879: iadd
/*    */     //   880: i2f
/*    */     //   881: aload #4
/*    */     //   883: getfield Wb0 : [Lf/Ws0;
/*    */     //   886: arraylength
/*    */     //   887: aload #4
/*    */     //   889: getfield XJ0 : I
/*    */     //   892: iadd
/*    */     //   893: i2f
/*    */     //   894: fdiv
/*    */     //   895: fstore #4
/*    */     //   897: goto -> 1009
/*    */     //   900: aload #4
/*    */     //   902: getfield KN : I
/*    */     //   905: i2f
/*    */     //   906: aload #4
/*    */     //   908: getfield Wb0 : [Lf/Ws0;
/*    */     //   911: arraylength
/*    */     //   912: sipush #590
/*    */     //   915: iadd
/*    */     //   916: i2f
/*    */     //   917: fdiv
/*    */     //   918: fstore #4
/*    */     //   920: goto -> 1009
/*    */     //   923: aload #4
/*    */     //   925: getfield Nul : Z
/*    */     //   928: ifeq -> 937
/*    */     //   931: fconst_1
/*    */     //   932: fstore #4
/*    */     //   934: goto -> 1009
/*    */     //   937: aload #4
/*    */     //   939: fconst_0
/*    */     //   940: fstore #5
/*    */     //   942: getfield UD : I
/*    */     //   945: dup
/*    */     //   946: istore #6
/*    */     //   948: iflt -> 972
/*    */     //   951: aload #4
/*    */     //   953: getfield XJ0 : I
/*    */     //   956: dup
/*    */     //   957: istore #7
/*    */     //   959: iconst_1
/*    */     //   960: if_icmplt -> 972
/*    */     //   963: iload #6
/*    */     //   965: i2f
/*    */     //   966: iload #7
/*    */     //   968: i2f
/*    */     //   969: fdiv
/*    */     //   970: fstore #5
/*    */     //   972: aload #4
/*    */     //   974: dup
/*    */     //   975: getfield KN : I
/*    */     //   978: i2f
/*    */     //   979: fstore #6
/*    */     //   981: getfield FK0 : I
/*    */     //   984: i2f
/*    */     //   985: fload #5
/*    */     //   987: fadd
/*    */     //   988: ldc_w 100.0
/*    */     //   991: fmul
/*    */     //   992: fload #6
/*    */     //   994: fadd
/*    */     //   995: aload #4
/*    */     //   997: getfield Wb0 : [Lf/Ws0;
/*    */     //   1000: arraylength
/*    */     //   1001: sipush #200
/*    */     //   1004: iadd
/*    */     //   1005: i2f
/*    */     //   1006: fdiv
/*    */     //   1007: fstore #4
/*    */     //   1009: fload_2
/*    */     //   1010: fload #4
/*    */     //   1012: fadd
/*    */     //   1013: fstore_2
/*    */     //   1014: goto -> 798
/*    */     //   1017: fload_2
/*    */     //   1018: fconst_1
/*    */     //   1019: fadd
/*    */     //   1020: fstore_2
/*    */     //   1021: goto -> 798
/*    */     //   1024: fload_2
/*    */     //   1025: aload_1
/*    */     //   1026: getfield tn : Lf/fQ;
/*    */     //   1029: getfield Z8 : I
/*    */     //   1032: i2f
/*    */     //   1033: fdiv
/*    */     //   1034: fstore_1
/*    */     //   1035: aload_0
/*    */     //   1036: invokestatic getRuntime : ()Ljava/lang/Runtime;
/*    */     //   1039: dup
/*    */     //   1040: dup
/*    */     //   1041: astore_2
/*    */     //   1042: invokevirtual totalMemory : ()J
/*    */     //   1045: aload_2
/*    */     //   1046: invokevirtual freeMemory : ()J
/*    */     //   1049: lsub
/*    */     //   1050: ldc2_w 1048576
/*    */     //   1053: ldiv
/*    */     //   1054: lstore_2
/*    */     //   1055: invokevirtual maxMemory : ()J
/*    */     //   1058: ldc2_w 1048576
/*    */     //   1061: ldiv
/*    */     //   1062: lstore #4
/*    */     //   1064: new java/lang/StringBuilder
/*    */     //   1067: dup
/*    */     //   1068: aload_0
/*    */     //   1069: swap
/*    */     //   1070: invokespecial <init> : ()V
/*    */     //   1073: getfield cD : Ljava/text/DecimalFormat;
/*    */     //   1076: fload_1
/*    */     //   1077: ldc_w 100.0
/*    */     //   1080: fmul
/*    */     //   1081: f2d
/*    */     //   1082: invokevirtual format : (D)Ljava/lang/String;
/*    */     //   1085: sipush #925
/*    */     //   1088: swap
/*    */     //   1089: invokestatic Go : (ILjava/lang/String;)Ljava/lang/String;
/*    */     //   1092: invokevirtual append : (Ljava/lang/String;)Ljava/lang/StringBuilder;
/*    */     //   1095: ldc_w '\\nMemory Info: '
/*    */     //   1098: invokevirtual append : (Ljava/lang/String;)Ljava/lang/StringBuilder;
/*    */     //   1101: lload_2
/*    */     //   1102: invokevirtual append : (J)Ljava/lang/StringBuilder;
/*    */     //   1105: ldc_w ' / '
/*    */     //   1108: invokevirtual append : (Ljava/lang/String;)Ljava/lang/StringBuilder;
/*    */     //   1111: lload #4
/*    */     //   1113: invokevirtual append : (J)Ljava/lang/StringBuilder;
/*    */     //   1116: ldc_w ' MB'
/*    */     //   1119: invokevirtual append : (Ljava/lang/String;)Ljava/lang/StringBuilder;
/*    */     //   1122: invokevirtual toString : ()Ljava/lang/String;
/*    */     //   1125: fload_1
/*    */     //   1126: invokevirtual BQ : (Ljava/lang/String;F)V
/*    */     //   1129: goto -> 1184
/*    */     //   1132: iload_1
/*    */     //   1133: ifne -> 1184
/*    */     //   1136: getstatic f/jX.V50 : Z
/*    */     //   1139: ifeq -> 1184
/*    */     //   1142: getstatic f/jX.kc : Z
/*    */     //   1145: ifne -> 1156
/*    */     //   1148: aload_0
/*    */     //   1149: iconst_2
/*    */     //   1150: putfield kn : I
/*    */     //   1153: goto -> 1184
/*    */     //   1156: getstatic f/Pa0.vH0 : I
/*    */     //   1159: getstatic f/jX.sn0 : I
/*    */     //   1162: if_icmpge -> 1179
/*    */     //   1165: getstatic f/jX.dj : Z
/*    */     //   1168: ifne -> 1179
/*    */     //   1171: aload_0
/*    */     //   1172: iconst_3
/*    */     //   1173: putfield kn : I
/*    */     //   1176: goto -> 1184
/*    */     //   1179: aload_0
/*    */     //   1180: iconst_1
/*    */     //   1181: putfield kn : I
/*    */     //   1184: return
/*    */     // Line number table:
/*    */     //   Java source line number -> byte code offset
/*    */     //   #1	-> 110
/*    */     //   #2	-> 117
/*    */     //   #3	-> 120
/*    */     //   #4	-> 137
/*    */     //   #5	-> 192
/*    */     //   #6	-> 202
/*    */     //   #7	-> 373
/*    */     //   #8	-> 379
/*    */     //   #9	-> 392
/*    */     //   #10	-> 403
/*    */     //   #11	-> 412
/*    */     //   #12	-> 417
/*    */     //   #13	-> 488
/*    */     //   #14	-> 526
/*    */     //   #15	-> 534
/*    */     //   #16	-> 542
/*    */     //   #17	-> 550
/*    */     //   #18	-> 558
/*    */     //   #19	-> 566
/*    */     //   #20	-> 574
/*    */     //   #21	-> 582
/*    */     //   #22	-> 591
/*    */     //   #23	-> 600
/*    */     //   #24	-> 699
/*    */     //   #25	-> 702
/*    */     //   #26	-> 708
/*    */     //   #27	-> 712
/*    */     //   #28	-> 718
/*    */     //   #29	-> 724
/*    */     //   #30	-> 732
/*    */     //   #31	-> 758
/*    */     //   #32	-> 769
/*    */     //   #33	-> 774
/*    */     //   #34	-> 777
/*    */     //   #35	-> 812
/*    */     //   #36	-> 831
/*    */     //   #37	-> 852
/*    */     //   #38	-> 1026
/*    */     //   #39	-> 1036
/*    */   } }


/* Location:              /Users/vnnsnnt/Documents/Codespace/JavaWorkspace/RedTrainer/src/main/java/org/trainer/client/PokeMMO.jar!/f/Yj0.class
 * Java compiler version: 8 (52.0)
 * JD-Core Version:       1.1.3
 */