/*    */ package f;public final class yn0 { public final nE0 ZF0; public final JG0 Tx; public final Un jK; public yn0(Kf paramKf, nE0 paramnE0, boolean paramBoolean) { // Byte code:
/*    */     //   0: aload_2
/*    */     //   1: aload_0
/*    */     //   2: aload_2
/*    */     //   3: aload_0
/*    */     //   4: dup
/*    */     //   5: aload_1
/*    */     //   6: putfield lpt1 : Lf/Kf;
/*    */     //   9: invokespecial <init> : ()V
/*    */     //   12: putfield ZF0 : Lf/nE0;
/*    */     //   15: invokevirtual qL0 : ()B
/*    */     //   18: tableswitch default -> 52, 0 -> 341, 1 -> 208, 2 -> 164, 3 -> 115, 4 -> 68
/*    */     //   52: aload_0
/*    */     //   53: new f/dQ
/*    */     //   56: dup
/*    */     //   57: astore_1
/*    */     //   58: invokespecial <init> : ()V
/*    */     //   61: aload_1
/*    */     //   62: putfield Tx : Lf/JG0;
/*    */     //   65: goto -> 435
/*    */     //   68: aload_2
/*    */     //   69: new f/dQ
/*    */     //   72: astore_1
/*    */     //   73: invokevirtual je0 : ()Lf/MM;
/*    */     //   76: ifnonnull -> 86
/*    */     //   79: ldc ''
/*    */     //   81: astore #4
/*    */     //   83: goto -> 95
/*    */     //   86: aload_2
/*    */     //   87: invokevirtual je0 : ()Lf/MM;
/*    */     //   90: invokestatic ku0 : (Lf/MM;)Ljava/lang/String;
/*    */     //   93: astore #4
/*    */     //   95: aload_0
/*    */     //   96: aload_1
/*    */     //   97: dup
/*    */     //   98: aload #4
/*    */     //   100: invokespecial <init> : (Ljava/lang/String;)V
/*    */     //   103: ldc 'label-title-medium'
/*    */     //   105: invokevirtual Xu : (Ljava/lang/String;)V
/*    */     //   108: aload_1
/*    */     //   109: putfield Tx : Lf/JG0;
/*    */     //   112: goto -> 435
/*    */     //   115: aload_2
/*    */     //   116: new f/dQ
/*    */     //   119: astore_1
/*    */     //   120: invokevirtual lF0 : ()Lf/A30;
/*    */     //   123: ifnonnull -> 133
/*    */     //   126: ldc ''
/*    */     //   128: astore #4
/*    */     //   130: goto -> 144
/*    */     //   133: aload_2
/*    */     //   134: invokevirtual lF0 : ()Lf/A30;
/*    */     //   137: iconst_0
/*    */     //   138: iconst_0
/*    */     //   139: invokestatic e0 : (Lf/A30;SI)Ljava/lang/String;
/*    */     //   142: astore #4
/*    */     //   144: aload_0
/*    */     //   145: aload_1
/*    */     //   146: dup
/*    */     //   147: aload #4
/*    */     //   149: invokespecial <init> : (Ljava/lang/String;)V
/*    */     //   152: ldc 'label-title-medium'
/*    */     //   154: invokevirtual Xu : (Ljava/lang/String;)V
/*    */     //   157: aload_1
/*    */     //   158: putfield Tx : Lf/JG0;
/*    */     //   161: goto -> 435
/*    */     //   164: aload_0
/*    */     //   165: new f/of
/*    */     //   168: dup
/*    */     //   169: dup2
/*    */     //   170: invokespecial <init> : ()V
/*    */     //   173: ldc '$'
/*    */     //   175: invokestatic df : (Ljava/lang/String;)Ljava/lang/StringBuilder;
/*    */     //   178: invokestatic getInstance : ()Ljava/text/NumberFormat;
/*    */     //   181: aload_2
/*    */     //   182: invokevirtual NC : ()I
/*    */     //   185: i2l
/*    */     //   186: invokevirtual format : (J)Ljava/lang/String;
/*    */     //   189: invokevirtual append : (Ljava/lang/String;)Ljava/lang/StringBuilder;
/*    */     //   192: invokevirtual toString : ()Ljava/lang/String;
/*    */     //   195: invokevirtual Zh : (Ljava/lang/String;)V
/*    */     //   198: iconst_1
/*    */     //   199: invokevirtual uh : (Z)V
/*    */     //   202: putfield Tx : Lf/JG0;
/*    */     //   205: goto -> 435
/*    */     //   208: aload_2
/*    */     //   209: new f/G9
/*    */     //   212: dup
/*    */     //   213: dup
/*    */     //   214: dup2
/*    */     //   215: astore_1
/*    */     //   216: invokespecial <init> : ()V
/*    */     //   219: iconst_1
/*    */     //   220: invokevirtual hC : (Z)V
/*    */     //   223: iconst_0
/*    */     //   224: invokevirtual wU : (Z)V
/*    */     //   227: invokevirtual dC0 : ()V
/*    */     //   230: invokevirtual Wc : ()Lf/Q90;
/*    */     //   233: ifnull -> 254
/*    */     //   236: aload_1
/*    */     //   237: new f/j40
/*    */     //   240: dup
/*    */     //   241: aload_2
/*    */     //   242: invokevirtual Wc : ()Lf/Q90;
/*    */     //   245: invokespecial <init> : (Lf/Q90;)V
/*    */     //   248: invokevirtual zf : (Lf/j40;)V
/*    */     //   251: goto -> 321
/*    */     //   254: iload_3
/*    */     //   255: ifeq -> 321
/*    */     //   258: aload_2
/*    */     //   259: invokevirtual NG0 : ()Z
/*    */     //   262: ifeq -> 295
/*    */     //   265: aload_1
/*    */     //   266: aload_2
/*    */     //   267: invokevirtual yi : ()I
/*    */     //   270: i2s
/*    */     //   271: aload_2
/*    */     //   272: dup
/*    */     //   273: invokevirtual mw : ()S
/*    */     //   276: invokestatic xw : (S)B
/*    */     //   279: istore #4
/*    */     //   281: invokevirtual mw : ()S
/*    */     //   284: invokestatic up : (S)Z
/*    */     //   287: iload #4
/*    */     //   289: invokevirtual Gq : (SZB)V
/*    */     //   292: goto -> 321
/*    */     //   295: aload_1
/*    */     //   296: aload_2
/*    */     //   297: dup
/*    */     //   298: dup
/*    */     //   299: invokevirtual yi : ()I
/*    */     //   302: i2s
/*    */     //   303: istore #4
/*    */     //   305: invokevirtual w70 : ()B
/*    */     //   308: istore #5
/*    */     //   310: invokevirtual JH0 : ()B
/*    */     //   313: iload #5
/*    */     //   315: swap
/*    */     //   316: iload #4
/*    */     //   318: invokevirtual gs0 : (BBS)V
/*    */     //   321: aload_0
/*    */     //   322: aload_1
/*    */     //   323: dup
/*    */     //   324: aload_0
/*    */     //   325: aload_1
/*    */     //   326: aload_2
/*    */     //   327: <illegal opcode> run : (Lf/yn0;Lf/G9;Lf/nE0;)Ljava/lang/Runnable;
/*    */     //   332: invokevirtual L1 : (Ljava/lang/Runnable;)V
/*    */     //   335: putfield Tx : Lf/JG0;
/*    */     //   338: goto -> 435
/*    */     //   341: aload_2
/*    */     //   342: new f/T1
/*    */     //   345: dup
/*    */     //   346: astore_1
/*    */     //   347: invokespecial <init> : ()V
/*    */     //   350: invokevirtual c1 : ()Lf/nH0;
/*    */     //   353: ifnull -> 392
/*    */     //   356: aload_1
/*    */     //   357: aload_2
/*    */     //   358: dup
/*    */     //   359: dup
/*    */     //   360: invokevirtual c1 : ()Lf/nH0;
/*    */     //   363: invokevirtual Gn : ()S
/*    */     //   366: istore #4
/*    */     //   368: invokevirtual c1 : ()Lf/nH0;
/*    */     //   371: invokevirtual e3 : ()S
/*    */     //   374: istore #5
/*    */     //   376: invokevirtual c1 : ()Lf/nH0;
/*    */     //   379: invokevirtual eT : ()B
/*    */     //   382: iload #4
/*    */     //   384: iload #5
/*    */     //   386: invokevirtual LPt2 : (BSS)V
/*    */     //   389: goto -> 418
/*    */     //   392: iload_3
/*    */     //   393: ifeq -> 418
/*    */     //   396: aload_1
/*    */     //   397: aload_2
/*    */     //   398: dup
/*    */     //   399: invokevirtual yi : ()I
/*    */     //   402: i2s
/*    */     //   403: istore #4
/*    */     //   405: invokevirtual mw : ()S
/*    */     //   408: istore #5
/*    */     //   410: iconst_0
/*    */     //   411: iload #4
/*    */     //   413: iload #5
/*    */     //   415: invokevirtual LPt2 : (BSS)V
/*    */     //   418: aload_0
/*    */     //   419: aload_1
/*    */     //   420: dup
/*    */     //   421: aload_0
/*    */     //   422: aload_2
/*    */     //   423: aload_1
/*    */     //   424: <illegal opcode> run : (Lf/yn0;Lf/nE0;Lf/T1;)Ljava/lang/Runnable;
/*    */     //   429: invokevirtual bm0 : (Ljava/lang/Runnable;)V
/*    */     //   432: putfield Tx : Lf/JG0;
/*    */     //   435: aload_2
/*    */     //   436: aload_0
/*    */     //   437: getfield Tx : Lf/JG0;
/*    */     //   440: iload_3
/*    */     //   441: iconst_1
/*    */     //   442: ixor
/*    */     //   443: dup
/*    */     //   444: istore_1
/*    */     //   445: invokevirtual sk0 : (Z)V
/*    */     //   448: new f/Un
/*    */     //   451: astore_3
/*    */     //   452: invokevirtual qL0 : ()B
/*    */     //   455: iconst_2
/*    */     //   456: if_icmpne -> 465
/*    */     //   459: sipush #5900
/*    */     //   462: goto -> 468
/*    */     //   465: sipush #5843
/*    */     //   468: invokestatic OH0 : (I)Ljava/lang/String;
/*    */     //   471: astore #4
/*    */     //   473: aload_2
/*    */     //   474: aload_3
/*    */     //   475: dup
/*    */     //   476: dup
/*    */     //   477: aload_0
/*    */     //   478: aload_3
/*    */     //   479: aload #4
/*    */     //   481: invokespecial <init> : (Ljava/lang/String;)V
/*    */     //   484: aload_3
/*    */     //   485: putfield jK : Lf/Un;
/*    */     //   488: ldc 'button-small2'
/*    */     //   490: invokevirtual Xu : (Ljava/lang/String;)V
/*    */     //   493: iload_1
/*    */     //   494: invokevirtual sk0 : (Z)V
/*    */     //   497: iload_1
/*    */     //   498: invokevirtual wI0 : (Z)V
/*    */     //   501: invokevirtual qL0 : ()B
/*    */     //   504: dup
/*    */     //   505: istore_1
/*    */     //   506: iconst_3
/*    */     //   507: if_icmpeq -> 543
/*    */     //   510: iload_1
/*    */     //   511: iconst_4
/*    */     //   512: if_icmpeq -> 529
/*    */     //   515: aload_3
/*    */     //   516: aload_0
/*    */     //   517: aload_2
/*    */     //   518: <illegal opcode> run : (Lf/yn0;Lf/nE0;)Ljava/lang/Runnable;
/*    */     //   523: invokevirtual tW : (Ljava/lang/Runnable;)V
/*    */     //   526: goto -> 554
/*    */     //   529: aload_3
/*    */     //   530: aload_0
/*    */     //   531: aload_2
/*    */     //   532: <illegal opcode> run : (Lf/yn0;Lf/nE0;)Ljava/lang/Runnable;
/*    */     //   537: invokevirtual tW : (Ljava/lang/Runnable;)V
/*    */     //   540: goto -> 554
/*    */     //   543: aload_3
/*    */     //   544: aload_0
/*    */     //   545: aload_2
/*    */     //   546: <illegal opcode> run : (Lf/yn0;Lf/nE0;)Ljava/lang/Runnable;
/*    */     //   551: invokevirtual tW : (Ljava/lang/Runnable;)V
/*    */     //   554: return
/*    */     // Line number table:
/*    */     //   Java source line number -> byte code offset
/*    */     //   #1	-> 173
/*  1 */     //   #2	-> 178 } private void b90(nE0 paramnE0) { int i = paramnE0.bz0; km.u4
/*    */ 
/*    */ 
/*    */ 
/*    */       
/*  6 */       .J80(paramnE0.Ly, i, this.lpt1.dA0.w6); } private void My0(nE0 paramnE0) { MM mM; if ((mM = paramnE0.Kz0) == null) return;  if (mM.Wk0 > 0) { if (vC0.I8(pA.Dg0, zD0.class)) vC0.Bv0(pA.Dg0, zD0.class).ra0(); 
/*  7 */       pA.Dg0
/*  8 */         .J8(new zD0(paramnE0, this.lpt1)); }
/*  9 */     else { int i = paramnE0.bz0;
/*    */ 
/*    */ 
/*    */ 
/*    */       
/* 14 */       km.u4.J80(paramnE0.Ly, i, this.lpt1.dA0.w6); }
/*    */      } private void qc0(nE0 paramnE0) { coM9 coM9; A30 a30; if ((a30 = paramnE0.Ao0) == null)
/*    */       return;  byte b = 0; if (a30.I > 0)
/*    */       b = (byte)1;  if (a30.Bd0 > 0)
/*    */       b = (byte)(b + 1);  if (a30.NF0 > 0)
/*    */       b = (byte)(b + 1);  short s; if ((s = a30.CO) > 0)
/*    */       b = (byte)(b + 1);  if (b > 1) { b = 1; }
/*    */     else { b = 0; }
/*    */      if (b != 0 || a30.fd > 0) {
/* 23 */       if (vC0.I8(pA.Dg0, n.class))
/*    */       {
/* 25 */         vC0.Bv0(pA.Dg0, n.class).ra0(); } 
/* 26 */       pA.Dg0
/* 27 */         .J8(new n(paramnE0, this.lpt1));
/*    */       return;
/*    */     } 
/*    */     LPT3 lPT3;
/*    */     wc wc;
/*    */     if (s > 0 && (wc = (lPT3 = Of.eH.On0(s)).c3) != null && wc.XF0()) {
/*    */       coM9 coM91;
/*    */       Vp0 vp0 = lPT3.c3.Hl0;
/*    */       short s1 = lPT3.c3.Lk;
/*    */       Kf kf2 = this.lpt1;
/*    */       this(this, s1, paramnE0, kf2);
/*    */       Kf kf1;
/*    */       if ((coM9 = (kf1 = this.lpt1).hD) == null) {
/*    */         kf1.hD = coM91;
/*    */       } else {
/*    */         ra0();
/*    */         kf1.hD = coM91;
/*    */       } 
/*    */       kf1.si(coM91, kf1.Ub());
/*    */     } else {
/*    */       R8 r8 = km.u4;
/*    */       int i = paramnE0.bz0;
/*    */       byte b1 = paramnE0.Ly;
/*    */       short s1 = ((yn0)super).lpt1.dA0.w6;
/*    */       J80(b1, i, s1);
/*    */     }  }
/*    */ 
/*    */   
/*    */   private void YZ(nE0 paramnE0) {
/*    */     int i = paramnE0.bz0;
/*    */     byte b = paramnE0.Ly;
/*    */     short s = this.lpt1.dA0.w6;
/*    */     km.u4.mS(i, b, null, s, (byte)2);
/*    */   }
/*    */   
/*    */   private void VV(nE0 paramnE0) {
/*    */     int i = paramnE0.bz0;
/*    */     byte b = paramnE0.Ly;
/*    */     short s = this.lpt1.dA0.w6;
/*    */     km.u4.mS(i, b, null, s, (byte)1);
/*    */   }
/*    */   
/*    */   public static void XA(G9 paramG9) {
/*    */     pA.Dg0.u30(null, paramG9.t70);
/*    */   }
/*    */   
/*    */   private void Tz0(nE0 paramnE0) {
/*    */     int i = paramnE0.bz0;
/*    */     km.u4.J80(paramnE0.Ly, i, this.lpt1.dA0.w6);
/*    */   } }


/* Location:              /Users/vnnsnnt/Documents/Codespace/JavaWorkspace/RedTrainer/src/main/java/org/trainer/client/PokeMMO.jar!/f/yn0.class
 * Java compiler version: 8 (52.0)
 * JD-Core Version:       1.1.3
 */