/*    */ package f;public final class Yr extends mc implements NK0 { public static final Ll Bm0 = Ll.F10("dragActive"); public vE om0; public boolean Hs0; public Y v8; public Yr(ck paramck, Y paramY, wg0 paramwg0) { // Byte code:
/*    */     //   0: aload_0
/*    */     //   1: dup
/*    */     //   2: dup
/*    */     //   3: ldc ''
/*    */     //   5: ldc ''
/*    */     //   7: invokespecial <init> : (Ljava/lang/String;Ljava/lang/String;)V
/*    */     //   10: ldc 'tm-button'
/*    */     //   12: invokevirtual Xu : (Ljava/lang/String;)V
/*    */     //   15: invokevirtual CW : ()Lf/rH;
/*    */     //   18: iconst_1
/*    */     //   19: anewarray f/U70
/*    */     //   22: dup
/*    */     //   23: invokestatic y8 : ()Lf/wm0;
/*    */     //   26: aload_2
/*    */     //   27: invokevirtual Ng : ()Lf/LPT3;
/*    */     //   30: invokevirtual ip0 : (Lf/LPT3;)Lf/U70;
/*    */     //   33: iconst_0
/*    */     //   34: swap
/*    */     //   35: aastore
/*    */     //   36: invokevirtual qt : ([Lf/U70;)Lf/JG0;
/*    */     //   39: pop
/*    */     //   40: invokestatic XU : ()Z
/*    */     //   43: ifeq -> 72
/*    */     //   46: aload_0
/*    */     //   47: dup
/*    */     //   48: invokevirtual CW : ()Lf/rH;
/*    */     //   51: bipush #48
/*    */     //   53: bipush #48
/*    */     //   55: invokevirtual tL : (II)V
/*    */     //   58: invokevirtual CW : ()Lf/rH;
/*    */     //   61: bipush #7
/*    */     //   63: bipush #10
/*    */     //   65: invokevirtual zT : (II)Lf/JG0;
/*    */     //   68: pop
/*    */     //   69: goto -> 94
/*    */     //   72: aload_0
/*    */     //   73: dup
/*    */     //   74: invokevirtual CW : ()Lf/rH;
/*    */     //   77: bipush #24
/*    */     //   79: bipush #24
/*    */     //   81: invokevirtual tL : (II)V
/*    */     //   84: invokevirtual CW : ()Lf/rH;
/*    */     //   87: bipush #7
/*    */     //   89: iconst_5
/*    */     //   90: invokevirtual zT : (II)Lf/JG0;
/*    */     //   93: pop
/*    */     //   94: aload_0
/*    */     //   95: dup
/*    */     //   96: aload_1
/*    */     //   97: aload_0
/*    */     //   98: aload_2
/*    */     //   99: dup
/*    */     //   100: invokevirtual r00 : ()S
/*    */     //   103: pop
/*    */     //   104: putfield v8 : Lf/Y;
/*    */     //   107: aload_2
/*    */     //   108: aload_3
/*    */     //   109: <illegal opcode> run : (Lf/Yr;Lf/ck;Lf/Y;Lf/wg0;)Ljava/lang/Runnable;
/*    */     //   114: invokevirtual tW : (Ljava/lang/Runnable;)V
/*  1 */     //   117: return } static { Ll.F10("dropOk"); Ll.F10("dropBlocked"); } private void Jy0(ck paramck, Y paramY, wg0 paramwg0) { if (km.XU()) { paramck.VJ(paramY); return; }  int i = this.Kd + 25;
/*    */     
/*  3 */     F7.T1(paramwg0.dc0(paramY), this, i, this.er0 + 25); }
/*  4 */   public final Y pRn() { return this.v8; } public final void d40() { super.d40(); short s; if (km.Nr() && this.xY > (s = this.fu)) Tm(s, this.HC);  } public final boolean i2(oa0 paramoa0) { vE vE1; if (km.XU()) return super.i2(paramoa0);  if (paramoa0.Cz0()) { if (this.Hs0) { if (paramoa0.Ud()) { vE vE2; if ((vE2 = this.om0) != null) NuL.I6(vE2.Up, (NK0)this, paramoa0);  this.Hs0 = false; this.O
/*  5 */             .gf0(Bm0, false); } else if ((vE1 = this.om0) != null) { this
/*  6 */             .Up
/*  7 */             .Tx(paramoa0); }  return true; }  if (paramoa0
/*  8 */         .Ua) { ((Yr)super)
/*  9 */           .Hs0 = true;
/* 10 */         ((JG0)this).O
/* 11 */           .gf0(Bm0, true); vE vE2; if ((vE2 = ((Yr)super).om0) != null)
/* 12 */         { pRn pRn; NuL nuL; (nuL = vE2.Up)
/* 13 */             .getClass();
/*    */           
/* 15 */           xJ0 xJ0 = pA.Dg0.WH;
/* 16 */           if (super.pRn() != null && (super.pRn())
/* 17 */             .Bp0
/* 18 */             .default(false) == dv.wS) { pRn = NuL.fL0; SE0[] arrayOfSE0; int i;
/*    */             byte b;
/* 20 */             for (i = (arrayOfSE0 = xJ0.sN).length, b = 0; b < i; ) { SE0 sE0; if ((sE0 = arrayOfSE0[b])
/* 21 */                 .db0 == null)
/*    */               { I i1; Ja0 ja0;
/* 23 */                 this(sE0); this(ja0, pRn.WHITE);
/* 24 */                 sE0.db0 = i1; }  sE0
/* 25 */                 .db0
/* 26 */                 .sz(pRn, 100); b++; }  } else { boolean bool = true; SE0[] arrayOfSE0; int i;
/*    */             byte b;
/* 28 */             for (i = (arrayOfSE0 = ((xJ0)pRn).sN).length, b = 0; b < i; ) { (arrayOfSE0[b])
/* 29 */                 .O
/* 30 */                 .gf0(JG0.e30, bool); b++; }  }  nuL
/* 31 */             .kv0 = (NK0)this; nuL.Tx(paramoa0); }  }
/* 32 */       else { int i; if (B8.Pg(i = paramoa0.cz0) && paramoa0
/* 33 */           .vl == 0 && i == 4)
/*    */         
/*    */         { 
/* 36 */           hm.Fz0(((Un)this).TG0.oh0); return true; }  }  }
/* 37 */      return super.i2(paramoa0); }
/*    */ 
/*    */   
/*    */   public final void R60(throws paramthrows) {
/*    */     if (!this.Hs0)
/*    */       super.R60(paramthrows); 
/*    */   }
/*    */   
/*    */   public final void Ve(throws paramthrows, int paramInt1, int paramInt2, int paramInt3) {
/*    */     if (!km.XU())
/*    */       this.hC0.sG0(paramInt1, paramInt2); 
/*    */   }
/*    */   
/*    */   public final boolean fC() {
/*    */     return km.XU() ^ true;
/*    */   }
/*    */   
/*    */   public final void Tm0(Y paramY) {
/*    */     this.v8 = paramY;
/*    */     this.hC0.qt(new U70[] { wm0.y0.HR(paramY.Bp0, false) });
/*    */   } }


/* Location:              /Users/vnnsnnt/Documents/Codespace/JavaWorkspace/RedTrainer/src/main/java/org/trainer/client/PokeMMO.jar!/f/Yr.class
 * Java compiler version: 8 (52.0)
 * JD-Core Version:       1.1.3
 */