/*  1 */ package f;public final class Yu extends QZ { public Yu(byte paramByte) { super(paramByte); } public final String DP() { if (km.MR.rx == 
/*  2 */       ky.We0) return Ml0.OH0(5021);  byte b = 1; String[] arrayOfString; (arrayOfString = new String[1])[0] = dy(); if (km.MR
/*    */       
/*  4 */       .wI(this.Fu) == 2) { hm0 hm0; if (km.MR
/*    */         
/*  6 */         .wI(this.Fu) != 2) { hm0 = null; }
/*    */       else
/*  8 */       { hm0 = km.MR.N0(this.Fu, (byte)1); }  if (hm0 != null) { b = 2; arrayOfString[0] = dy(); (arrayOfString = new String[2])[1] = hm0.I9(); }  }
/*  9 */      return Ml0.lz((byte)2, F40.ef0, 15, b, arrayOfString); } public final ET PN() { return ET.gX; } public final boolean lJ0() { return true; } public final String dy() { Gp0 gp0; if ((gp0 = km.MR) == null) return "";  if (gp0.rx == ky.We0) return Ml0.OH0(5020);  byte b = this.Fu; hm0[] arrayOfHm0; int i; byte b1; for (i = (arrayOfHm0 = gp0.cl[b]).length, b1 = 0; b1 < i; ) { hm0 hm01; if ((hm01 = arrayOfHm0[b1]) != null && hm01.K0.ta.Jg) return hm01.fA();  b1++; }
/*    */      hm0 hm0;
/* 11 */     return ((hm0 = gp0.N0(this.Fu, (byte)0)) != null) ? fA() : ""; }
/*    */ 
/*    */   
/*    */   public final String Lc() {
/*    */     return Ml0.Qf0(F40.ef0, 15, 74);
/*    */   }
/*    */   
/*    */   public final byte d5() {
/*    */     // Byte code:
/*    */     //   0: getstatic f/km.MR : Lf/Gp0;
/*    */     //   3: dup
/*    */     //   4: astore_1
/*    */     //   5: ifnonnull -> 15
/*    */     //   8: getstatic f/km.a3 : Lf/vh0;
/*    */     //   11: getfield eA : B
/*    */     //   14: ireturn
/*    */     //   15: aload_1
/*    */     //   16: aload_0
/*    */     //   17: getfield Fu : B
/*    */     //   20: istore_0
/*    */     //   21: getfield cl : [[Lf/hm0;
/*    */     //   24: iload_0
/*    */     //   25: aaload
/*    */     //   26: dup
/*    */     //   27: astore_0
/*    */     //   28: arraylength
/*    */     //   29: istore_1
/*    */     //   30: iconst_0
/*    */     //   31: istore_2
/*    */     //   32: iload_2
/*    */     //   33: iload_1
/*    */     //   34: if_icmpge -> 427
/*    */     //   37: aload_0
/*    */     //   38: iload_2
/*    */     //   39: aaload
/*    */     //   40: dup
/*    */     //   41: astore_3
/*    */     //   42: ifnull -> 421
/*    */     //   45: aload_3
/*    */     //   46: invokevirtual Jx : ()S
/*    */     //   49: dup
/*    */     //   50: istore_3
/*    */     //   51: sipush #150
/*    */     //   54: if_icmpeq -> 419
/*    */     //   57: iload_3
/*    */     //   58: sipush #151
/*    */     //   61: if_icmpeq -> 419
/*    */     //   64: iload_3
/*    */     //   65: sipush #1023
/*    */     //   68: if_icmpeq -> 403
/*    */     //   71: iload_3
/*    */     //   72: sipush #1025
/*    */     //   75: if_icmpeq -> 419
/*    */     //   78: iload_3
/*    */     //   79: tableswitch default -> 104, 144 -> 419, 145 -> 419, 146 -> 419
/*    */     //   104: iload_3
/*    */     //   105: tableswitch default -> 132, 243 -> 387, 244 -> 387, 245 -> 387
/*    */     //   132: iload_3
/*    */     //   133: tableswitch default -> 160, 249 -> 387, 250 -> 387, 251 -> 419
/*    */     //   160: iload_3
/*    */     //   161: tableswitch default -> 216, 377 -> 403, 378 -> 403, 379 -> 403, 380 -> 419, 381 -> 419, 382 -> 419, 383 -> 419, 384 -> 419, 385 -> 419, 386 -> 419
/*    */     //   216: iload_3
/*    */     //   217: tableswitch default -> 292, 480 -> 403, 481 -> 403, 482 -> 403, 483 -> 403, 484 -> 403, 485 -> 403, 486 -> 403, 487 -> 403, 488 -> 403, 489 -> 403, 490 -> 403, 491 -> 403, 492 -> 403, 493 -> 403, 494 -> 419
/*    */     //   292: iload_3
/*    */     //   293: tableswitch default -> 356, 638 -> 419, 639 -> 419, 640 -> 419, 641 -> 419, 642 -> 419, 643 -> 419, 644 -> 419, 645 -> 419, 646 -> 419, 647 -> 419, 648 -> 419, 649 -> 419
/*    */     //   356: iload_3
/*    */     //   357: tableswitch default -> 384, 1000 -> 419, 1001 -> 419, 1002 -> 419
/*    */     //   384: goto -> 421
/*    */     //   387: getstatic f/km.mI0 : Lf/P1;
/*    */     //   390: iconst_4
/*    */     //   391: invokevirtual s2 : (B)Z
/*    */     //   394: ifeq -> 401
/*    */     //   397: iconst_4
/*    */     //   398: goto -> 402
/*    */     //   401: iconst_2
/*    */     //   402: ireturn
/*    */     //   403: getstatic f/km.mI0 : Lf/P1;
/*    */     //   406: iconst_3
/*    */     //   407: invokevirtual s2 : (B)Z
/*    */     //   410: ifeq -> 417
/*    */     //   413: iconst_3
/*    */     //   414: goto -> 418
/*    */     //   417: iconst_2
/*    */     //   418: ireturn
/*    */     //   419: iconst_2
/*    */     //   420: ireturn
/*    */     //   421: iinc #2, 1
/*    */     //   424: goto -> 32
/*    */     //   427: getstatic f/km.a3 : Lf/vh0;
/*    */     //   430: getfield eA : B
/*    */     //   433: ireturn
/*    */     // Line number table:
/*    */     //   Java source line number -> byte code offset
/*    */     //   #1	-> 8
/*    */     //   #2	-> 11
/*    */     //   #3	-> 17
/*    */     //   #4	-> 21
/*    */     //   #5	-> 28
/*    */     //   #6	-> 427
/*    */     //   #7	-> 430
/*    */   }
/*    */   
/*    */   public final short COm8() {
/*    */     // Byte code:
/*    */     //   0: getstatic f/km.MR : Lf/Gp0;
/*    */     //   3: dup
/*    */     //   4: astore_1
/*    */     //   5: ifnonnull -> 13
/*    */     //   8: aload_0
/*    */     //   9: invokespecial COm8 : ()S
/*    */     //   12: ireturn
/*    */     //   13: aload_1
/*    */     //   14: aload_0
/*    */     //   15: getfield Fu : B
/*    */     //   18: istore_2
/*    */     //   19: getfield cl : [[Lf/hm0;
/*    */     //   22: iload_2
/*    */     //   23: aaload
/*    */     //   24: dup
/*    */     //   25: astore_2
/*    */     //   26: arraylength
/*    */     //   27: istore_3
/*    */     //   28: iconst_0
/*    */     //   29: istore #4
/*    */     //   31: iload #4
/*    */     //   33: iload_3
/*    */     //   34: if_icmpge -> 623
/*    */     //   37: aload_2
/*    */     //   38: iload #4
/*    */     //   40: aaload
/*    */     //   41: dup
/*    */     //   42: astore #5
/*    */     //   44: ifnonnull -> 50
/*    */     //   47: goto -> 591
/*    */     //   50: aload #5
/*    */     //   52: invokevirtual Jx : ()S
/*    */     //   55: dup
/*    */     //   56: istore #5
/*    */     //   58: sipush #150
/*    */     //   61: if_icmpeq -> 619
/*    */     //   64: iload #5
/*    */     //   66: sipush #151
/*    */     //   69: if_icmpeq -> 619
/*    */     //   72: iload #5
/*    */     //   74: sipush #1023
/*    */     //   77: if_icmpeq -> 601
/*    */     //   80: iload #5
/*    */     //   82: sipush #1024
/*    */     //   85: if_icmpeq -> 597
/*    */     //   88: iload #5
/*    */     //   90: tableswitch default -> 116, 144 -> 619, 145 -> 619, 146 -> 619
/*    */     //   116: iload #5
/*    */     //   118: tableswitch default -> 144, 243 -> 435, 244 -> 417, 245 -> 399
/*    */     //   144: iload #5
/*    */     //   146: tableswitch default -> 172, 249 -> 471, 250 -> 453, 251 -> 619
/*    */     //   172: iload #5
/*    */     //   174: tableswitch default -> 228, 377 -> 489, 378 -> 489, 379 -> 489, 380 -> 619, 381 -> 619, 382 -> 619, 383 -> 619, 384 -> 619, 385 -> 619, 386 -> 619
/*    */     //   228: iload #5
/*    */     //   230: tableswitch default -> 304, 480 -> 561, 481 -> 561, 482 -> 561, 483 -> 543, 484 -> 543, 485 -> 525, 486 -> 525, 487 -> 601, 488 -> 525, 489 -> 525, 490 -> 525, 491 -> 525, 492 -> 525, 493 -> 507, 494 -> 619
/*    */     //   304: iload #5
/*    */     //   306: tableswitch default -> 368, 638 -> 619, 639 -> 619, 640 -> 619, 641 -> 619, 642 -> 619, 643 -> 583, 644 -> 597, 645 -> 619, 646 -> 579, 647 -> 619, 648 -> 619, 649 -> 619
/*    */     //   368: iload #5
/*    */     //   370: tableswitch default -> 396, 1000 -> 619, 1001 -> 619, 1002 -> 587
/*    */     //   396: goto -> 591
/*    */     //   399: aload_0
/*    */     //   400: invokevirtual d5 : ()B
/*    */     //   403: iconst_4
/*    */     //   404: if_icmpne -> 413
/*    */     //   407: sipush #1121
/*    */     //   410: goto -> 416
/*    */     //   413: sipush #1143
/*    */     //   416: ireturn
/*    */     //   417: aload_0
/*    */     //   418: invokevirtual d5 : ()B
/*    */     //   421: iconst_4
/*    */     //   422: if_icmpne -> 431
/*    */     //   425: sipush #1122
/*    */     //   428: goto -> 434
/*    */     //   431: sipush #1143
/*    */     //   434: ireturn
/*    */     //   435: aload_0
/*    */     //   436: invokevirtual d5 : ()B
/*    */     //   439: iconst_4
/*    */     //   440: if_icmpne -> 449
/*    */     //   443: sipush #1123
/*    */     //   446: goto -> 452
/*    */     //   449: sipush #1143
/*    */     //   452: ireturn
/*    */     //   453: aload_0
/*    */     //   454: invokevirtual d5 : ()B
/*    */     //   457: iconst_4
/*    */     //   458: if_icmpne -> 467
/*    */     //   461: sipush #1132
/*    */     //   464: goto -> 470
/*    */     //   467: sipush #1143
/*    */     //   470: ireturn
/*    */     //   471: aload_0
/*    */     //   472: invokevirtual d5 : ()B
/*    */     //   475: iconst_4
/*    */     //   476: if_icmpne -> 485
/*    */     //   479: sipush #1133
/*    */     //   482: goto -> 488
/*    */     //   485: sipush #1143
/*    */     //   488: ireturn
/*    */     //   489: aload_0
/*    */     //   490: invokevirtual d5 : ()B
/*    */     //   493: iconst_3
/*    */     //   494: if_icmpne -> 503
/*    */     //   497: sipush #1204
/*    */     //   500: goto -> 506
/*    */     //   503: sipush #1143
/*    */     //   506: ireturn
/*    */     //   507: aload_0
/*    */     //   508: invokevirtual d5 : ()B
/*    */     //   511: iconst_3
/*    */     //   512: if_icmpne -> 521
/*    */     //   515: sipush #1125
/*    */     //   518: goto -> 524
/*    */     //   521: sipush #1143
/*    */     //   524: ireturn
/*    */     //   525: aload_0
/*    */     //   526: invokevirtual d5 : ()B
/*    */     //   529: iconst_3
/*    */     //   530: if_icmpne -> 539
/*    */     //   533: sipush #1126
/*    */     //   536: goto -> 542
/*    */     //   539: sipush #1143
/*    */     //   542: ireturn
/*    */     //   543: aload_0
/*    */     //   544: invokevirtual d5 : ()B
/*    */     //   547: iconst_3
/*    */     //   548: if_icmpne -> 557
/*    */     //   551: sipush #1121
/*    */     //   554: goto -> 560
/*    */     //   557: sipush #1143
/*    */     //   560: ireturn
/*    */     //   561: aload_0
/*    */     //   562: invokevirtual d5 : ()B
/*    */     //   565: iconst_3
/*    */     //   566: if_icmpne -> 575
/*    */     //   569: sipush #1118
/*    */     //   572: goto -> 578
/*    */     //   575: sipush #1143
/*    */     //   578: ireturn
/*    */     //   579: sipush #1141
/*    */     //   582: ireturn
/*    */     //   583: sipush #1140
/*    */     //   586: ireturn
/*    */     //   587: sipush #1139
/*    */     //   590: ireturn
/*    */     //   591: iinc #4, 1
/*    */     //   594: goto -> 31
/*    */     //   597: sipush #1142
/*    */     //   600: ireturn
/*    */     //   601: aload_0
/*    */     //   602: invokevirtual d5 : ()B
/*    */     //   605: iconst_3
/*    */     //   606: if_icmpne -> 615
/*    */     //   609: sipush #1201
/*    */     //   612: goto -> 618
/*    */     //   615: sipush #1143
/*    */     //   618: ireturn
/*    */     //   619: sipush #1143
/*    */     //   622: ireturn
/*    */     //   623: aload_1
/*    */     //   624: aload_0
/*    */     //   625: getfield Fu : B
/*    */     //   628: invokevirtual wI : (B)B
/*    */     //   631: iconst_1
/*    */     //   632: if_icmple -> 687
/*    */     //   635: aload_0
/*    */     //   636: invokevirtual d5 : ()B
/*    */     //   639: dup
/*    */     //   640: istore_0
/*    */     //   641: ifeq -> 683
/*    */     //   644: iload_0
/*    */     //   645: iconst_1
/*    */     //   646: if_icmpeq -> 677
/*    */     //   649: iload_0
/*    */     //   650: iconst_3
/*    */     //   651: if_icmpeq -> 671
/*    */     //   654: iload_0
/*    */     //   655: iconst_4
/*    */     //   656: if_icmpeq -> 665
/*    */     //   659: sipush #1129
/*    */     //   662: goto -> 686
/*    */     //   665: sipush #1125
/*    */     //   668: goto -> 686
/*    */     //   671: sipush #1116
/*    */     //   674: goto -> 686
/*    */     //   677: sipush #476
/*    */     //   680: goto -> 686
/*    */     //   683: sipush #341
/*    */     //   686: ireturn
/*    */     //   687: aload_0
/*    */     //   688: invokespecial COm8 : ()S
/*    */     //   691: ireturn
/*    */     // Line number table:
/*    */     //   Java source line number -> byte code offset
/*    */     //   #1	-> 15
/*    */     //   #2	-> 19
/*    */     //   #3	-> 26
/*    */     //   #4	-> 625
/*    */     //   #5	-> 628
/*    */   } }


/* Location:              /Users/vnnsnnt/Documents/Codespace/JavaWorkspace/RedTrainer/src/main/java/org/trainer/client/PokeMMO.jar!/f/Yu.class
 * Java compiler version: 8 (52.0)
 * JD-Core Version:       1.1.3
 */