package f;

public final class yy {
  public final int throw;
  
  public String mK;
  
  public String TC0;
  
  public int ho0;
  
  public String Ku0;
  
  public String[] Qz0;
  
  public short lpt5;
  
  public short u8;
  
  public short t20;
  
  public short z40;
  
  public short V1;
  
  public int s80;
  
  public yy(int paramInt1, String paramString1, String paramString2, int paramInt2, String paramString3, int paramInt3, short paramShort1, short paramShort2, short paramShort3, short paramShort4, short paramShort5, int paramInt4, String[] paramArrayOfString) {
    this.throw = paramInt1;
    this.mK = paramString1;
    this.TC0 = paramString2;
    this.ho0 = paramInt2;
    this.Ku0 = paramString3;
    this.lpt5 = paramShort1;
    this.u8 = paramShort2;
    this.t20 = paramShort3;
    this.z40 = paramShort4;
    this.V1 = paramShort5;
    this.s80 = paramInt4;
    this.Qz0 = paramArrayOfString;
  }
  
  public final String Tr0() {
    return this.Ku0;
  }
  
  public final boolean H8() {
    return (this.s80 > 0);
  }
  
  public final boolean HP(jv paramjv, short paramShort) {
    // Byte code:
    //   0: aload_1
    //   1: invokevirtual ordinal : ()I
    //   4: tableswitch default -> 40, 1 -> 112, 2 -> 94, 3 -> 76, 4 -> 58, 5 -> 56
    //   40: aload_0
    //   41: getfield V1 : S
    //   44: dup
    //   45: istore_0
    //   46: iload_2
    //   47: ior
    //   48: iload_0
    //   49: if_icmpne -> 130
    //   52: iconst_1
    //   53: goto -> 131
    //   56: iconst_1
    //   57: ireturn
    //   58: aload_0
    //   59: getfield lpt5 : S
    //   62: dup
    //   63: istore_0
    //   64: iload_2
    //   65: ior
    //   66: iload_0
    //   67: if_icmpne -> 74
    //   70: iconst_1
    //   71: goto -> 75
    //   74: iconst_0
    //   75: ireturn
    //   76: aload_0
    //   77: getfield u8 : S
    //   80: dup
    //   81: istore_0
    //   82: iload_2
    //   83: ior
    //   84: iload_0
    //   85: if_icmpne -> 92
    //   88: iconst_1
    //   89: goto -> 93
    //   92: iconst_0
    //   93: ireturn
    //   94: aload_0
    //   95: getfield t20 : S
    //   98: dup
    //   99: istore_0
    //   100: iload_2
    //   101: ior
    //   102: iload_0
    //   103: if_icmpne -> 110
    //   106: iconst_1
    //   107: goto -> 111
    //   110: iconst_0
    //   111: ireturn
    //   112: aload_0
    //   113: getfield z40 : S
    //   116: dup
    //   117: istore_0
    //   118: iload_2
    //   119: ior
    //   120: iload_0
    //   121: if_icmpne -> 128
    //   124: iconst_1
    //   125: goto -> 129
    //   128: iconst_0
    //   129: ireturn
    //   130: iconst_0
    //   131: ireturn
  }
}


/* Location:              /Users/vnnsnnt/Documents/Codespace/JavaWorkspace/RedTrainer/src/main/java/org/trainer/client/PokeMMO.jar!/f/yy.class
 * Java compiler version: 8 (52.0)
 * JD-Core Version:       1.1.3
 */