/*  1 */ package f;public final class zB0 extends Kl0 { public byte L7; public Aq ph0; public int pF; public int qw0; public LPT1[] nC0; public String or0; public byte ob; public byte zK; public byte s90; public byte Vc0 = -1; public ky mg0; public boolean C90 = false; public boolean fp = false; public boolean Yy0 = false; public byte Wy0 = 0; public byte A2 = 0; public byte SP = 0; public byte oo0 = 0; public String jn; public Px0 DK; public short[] KK = new short[0]; public short[] Ny0 = new short[0]; public byte eG0; public byte qS; public byte so; public byte rE0; public short sc0; public byte D90; public Ku0 rx0; public String Hw0; public zB0(String paramString, Aq paramAq, int paramInt, Ku0 paramKu0) { super(null, null); this.Hw0 = paramString; this.ph0 = paramAq; this.qw0 = paramInt; this.rx0 = paramKu0; } public zB0(c4 paramc4, ByteBuffer paramByteBuffer) { super(paramc4, paramByteBuffer); this.rx0 = null; this.Hw0 = null; } public final void sM() { short[] arrayOfShort; boolean bool; this
/*  2 */       .L7 = this.Ws.get();
/*    */     
/*  4 */     Aq aq = (Aq)Aq.yY.Ha0(this.Ws.get());
/*  5 */     switch (aq.ordinal())
/*    */     
/*    */     { 
/*    */ 
/*    */ 
/*    */ 
/*    */ 
/*    */ 
/*    */ 
/*    */ 
/*    */ 
/*    */ 
/*    */ 
/*    */ 
/*    */ 
/*    */ 
/*    */ 
/*    */ 
/*    */ 
/*    */ 
/*    */ 
/*    */ 
/*    */ 
/*    */ 
/*    */ 
/*    */ 
/*    */ 
/*    */ 
/*    */ 
/*    */ 
/*    */ 
/*    */ 
/*    */ 
/*    */ 
/*    */ 
/*    */ 
/*    */ 
/*    */ 
/*    */ 
/*    */ 
/*    */ 
/*    */ 
/*    */ 
/*    */ 
/*    */ 
/*    */ 
/*    */ 
/*    */ 
/*    */ 
/*    */ 
/*    */ 
/*    */ 
/*    */ 
/*    */ 
/*    */ 
/*    */ 
/*    */ 
/*    */ 
/*    */ 
/*    */ 
/*    */ 
/*    */ 
/*    */ 
/*    */ 
/*    */ 
/*    */ 
/*    */ 
/*    */ 
/*    */ 
/*    */ 
/*    */ 
/*    */ 
/*    */ 
/*    */       
/*    */       default:
/* 80 */         this
/*    */           
/* 82 */           .pF = this.Ws.getInt();
/*    */         
/* 84 */         this.qw0 = this.Ws.getInt(); break;case 33: this.qw0 = this.Ws.getInt(); for (this.eG0 = this.Ws.get(), this.KK = new short[R00()], b = 0; b < (arrayOfShort = this.KK).length; ) { arrayOfShort[b] = this.Ws.getShort(); b++; } case 37: this.qw0 = this.Ws.getInt(); this.rE0 = this.Ws.get(); this.sc0 = this.Ws.getShort(); this.D90 = this.Ws.get(); break;case 43: for (this.pF = this.Ws.getInt(), this.KK = new short[R00()], b = 0; b < (arrayOfShort = this.KK).length; ) { arrayOfShort[b] = this.Ws.getShort(); b++; }  break;case 31: this.pF = this.Ws.getInt(); this.qw0 = this.Ws.getInt(); this.eG0 = this.Ws.get(); this.qS = this.Ws.get(); this.so = this.Ws.get(); break;case 26: case 45: this.pF = this.Ws.getInt(); for (this.qw0 = this.Ws.getInt(), this.KK = new short[R00()], b = 0; b < (arrayOfShort = this.KK).length; ) { arrayOfShort[b] = this.Ws.getShort(); b++; }  for (this.Ny0 = new short[R00()], b = 0; b < (arrayOfShort = this.Ny0).length; ) { arrayOfShort[b] = this.Ws.getShort(); b++; }  break;case 28: this.pF = this.Ws.getInt(); this.qw0 = this.Ws.getInt(); for (this.DK = (Px0)Px0.ur0.Ha0(this.Ws.get()), this.KK = new short[R00()], b = 0; b < (arrayOfShort = this.KK).length; ) { arrayOfShort[b] = this.Ws.getShort(); b++; }  break;case 11: case 13: case 14: case 30: case 47: this.pF = this.Ws.getInt(); for (this.qw0 = this.Ws.getInt(), this.KK = new short[R00()], b = 0; b < (arrayOfShort = this.KK).length; ) { arrayOfShort[b] = this.Ws.getShort(); b++; }  break;case 42: this.pF = this.Ws.getInt(); this.so = this.Ws.get();case 21: for (this.KK = new short[R00()], b = 0; b < (arrayOfShort = this.KK).length; ) { arrayOfShort[b] = this.Ws.getShort(); b++; }  break;case 20: this.or0 = au(); this.jn = au(); break;case 17: case 18: case 19: this.or0 = au(); break;case 16: this.or0 = au(); this.mg0 = ky.Mt0(this.Ws.get()); this.A2 = this.Ws.get(); this.ob = this.Ws.get(); this.oo0 = b; if (((b = this.Ws.get()) & 0x1) != 0) { bool = true; } else { bool = false; }  this.C90 = bool; if ((b & 0x2) != 0) { bool = true; } else { bool = false; }  this.fp = bool; if ((b & 0x4) != 0) { bool = true; } else { bool = false; }  this.Yy0 = bool; if ((b & 0x8) != 0) this.Wy0 = this.Ws.get();  if ((this.oo0 & 0x10) != 0) this.SP = this.Ws.get();  if ((this.oo0 & 0x20) != 0) { this.Vc0 = this.Ws.get(); break; }  this.zK = this.Ws.get(); this.s90 = this.Ws.get(); break;case 9: case 44: break; }  byte b; LPT1[] arrayOfLPT1; for (this.nC0 = new LPT1[R00()], b = 0; b < (arrayOfLPT1 = this.nC0).length; ) { arrayOfLPT1[b] = Ac(); b++; }
/*    */      }
/*    */ 
/*    */   
/*    */   public final void Cx() {
/*    */     // Byte code:
/*    */     //   0: aload_0
/*    */     //   1: invokevirtual r8 : ()Lf/ro;
/*    */     //   4: checkcast f/R8
/*    */     //   7: dup
/*    */     //   8: astore_1
/*    */     //   9: invokevirtual getClass : ()Ljava/lang/Class;
/*    */     //   12: pop
/*    */     //   13: getstatic f/km.wI0 : Lf/Pw;
/*    */     //   16: getfield HV : Lf/sH;
/*    */     //   19: ifnonnull -> 45
/*    */     //   22: aload_1
/*    */     //   23: getfield YG0 : Lf/js;
/*    */     //   26: dup
/*    */     //   27: astore_1
/*    */     //   28: ifnull -> 45
/*    */     //   31: aload_1
/*    */     //   32: getfield MH0 : Lf/pA;
/*    */     //   35: ifnonnull -> 41
/*    */     //   38: goto -> 45
/*    */     //   41: iconst_0
/*    */     //   42: goto -> 46
/*    */     //   45: iconst_1
/*    */     //   46: ifeq -> 69
/*    */     //   49: new f/com8
/*    */     //   52: dup
/*    */     //   53: astore_1
/*    */     //   54: aload_0
/*    */     //   55: invokespecial <init> : (Lf/zB0;)V
/*    */     //   58: invokestatic k6 : ()Lf/HC;
/*    */     //   61: aload_1
/*    */     //   62: ldc 0.1
/*    */     //   64: invokevirtual S : (Lf/oo;F)Lf/oo;
/*    */     //   67: pop
/*    */     //   68: return
/*    */     //   69: aload_0
/*    */     //   70: getfield ph0 : Lf/Aq;
/*    */     //   73: dup
/*    */     //   74: astore_1
/*    */     //   75: getstatic f/Aq.bb0 : Lf/Aq;
/*    */     //   78: if_acmpne -> 100
/*    */     //   81: getstatic f/km.kH0 : Lf/Qz0;
/*    */     //   84: invokevirtual tc : ()Lf/hO;
/*    */     //   87: dup
/*    */     //   88: astore_0
/*    */     //   89: ifnonnull -> 95
/*    */     //   92: goto -> 99
/*    */     //   95: aload_0
/*    */     //   96: invokevirtual EE0 : ()V
/*    */     //   99: return
/*    */     //   100: aload_1
/*    */     //   101: invokevirtual ordinal : ()I
/*    */     //   104: dup
/*    */     //   105: istore_1
/*    */     //   106: bipush #22
/*    */     //   108: if_icmpeq -> 1194
/*    */     //   111: iload_1
/*    */     //   112: bipush #43
/*    */     //   114: if_icmpeq -> 1083
/*    */     //   117: iload_1
/*    */     //   118: bipush #44
/*    */     //   120: if_icmpeq -> 1045
/*    */     //   123: iload_1
/*    */     //   124: tableswitch default -> 160, 16 -> 420, 17 -> 371, 18 -> 322, 19 -> 273, 20 -> 219
/*    */     //   160: iload_1
/*    */     //   161: tableswitch default -> 188, 24 -> 776, 25 -> 734, 26 -> 539
/*    */     //   188: iload_1
/*    */     //   189: tableswitch default -> 216, 28 -> 953, 29 -> 911, 30 -> 818
/*    */     //   216: goto -> 1035
/*    */     //   219: aload_0
/*    */     //   220: dup
/*    */     //   221: dup2
/*    */     //   222: invokevirtual r8 : ()Lf/ro;
/*    */     //   225: astore_0
/*    */     //   226: getfield L7 : B
/*    */     //   229: istore_1
/*    */     //   230: getfield or0 : Ljava/lang/String;
/*    */     //   233: astore_2
/*    */     //   234: getfield jn : Ljava/lang/String;
/*    */     //   237: astore_3
/*    */     //   238: aload_0
/*    */     //   239: checkcast f/R8
/*    */     //   242: getfield YG0 : Lf/js;
/*    */     //   245: getfield MH0 : Lf/pA;
/*    */     //   248: dup
/*    */     //   249: astore_0
/*    */     //   250: ifnull -> 1257
/*    */     //   253: getstatic f/UB0.Kg0 : Lf/Q50;
/*    */     //   256: new f/BT
/*    */     //   259: dup
/*    */     //   260: aload_0
/*    */     //   261: iload_1
/*    */     //   262: aload_2
/*    */     //   263: aload_3
/*    */     //   264: invokespecial <init> : (Lf/pA;BLjava/lang/String;Ljava/lang/String;)V
/*    */     //   267: invokevirtual fN : (Ljava/lang/Runnable;)V
/*    */     //   270: goto -> 1257
/*    */     //   273: aload_0
/*    */     //   274: dup
/*    */     //   275: dup
/*    */     //   276: invokevirtual r8 : ()Lf/ro;
/*    */     //   279: astore_0
/*    */     //   280: getfield L7 : B
/*    */     //   283: istore_1
/*    */     //   284: getfield or0 : Ljava/lang/String;
/*    */     //   287: astore_2
/*    */     //   288: aload_0
/*    */     //   289: checkcast f/R8
/*    */     //   292: getfield YG0 : Lf/js;
/*    */     //   295: getfield MH0 : Lf/pA;
/*    */     //   298: dup
/*    */     //   299: astore_0
/*    */     //   300: ifnull -> 1257
/*    */     //   303: getstatic f/UB0.Kg0 : Lf/Q50;
/*    */     //   306: new f/gs
/*    */     //   309: dup
/*    */     //   310: aload_0
/*    */     //   311: iload_1
/*    */     //   312: aload_2
/*    */     //   313: invokespecial <init> : (Lf/pA;BLjava/lang/String;)V
/*    */     //   316: invokevirtual fN : (Ljava/lang/Runnable;)V
/*    */     //   319: goto -> 1257
/*    */     //   322: aload_0
/*    */     //   323: dup
/*    */     //   324: dup
/*    */     //   325: invokevirtual r8 : ()Lf/ro;
/*    */     //   328: astore_0
/*    */     //   329: getfield L7 : B
/*    */     //   332: istore_1
/*    */     //   333: getfield or0 : Ljava/lang/String;
/*    */     //   336: astore_2
/*    */     //   337: aload_0
/*    */     //   338: checkcast f/R8
/*    */     //   341: getfield YG0 : Lf/js;
/*    */     //   344: getfield MH0 : Lf/pA;
/*    */     //   347: dup
/*    */     //   348: astore_0
/*    */     //   349: ifnull -> 1257
/*    */     //   352: getstatic f/UB0.Kg0 : Lf/Q50;
/*    */     //   355: new f/Xp
/*    */     //   358: dup
/*    */     //   359: aload_0
/*    */     //   360: iload_1
/*    */     //   361: aload_2
/*    */     //   362: invokespecial <init> : (Lf/pA;BLjava/lang/String;)V
/*    */     //   365: invokevirtual fN : (Ljava/lang/Runnable;)V
/*    */     //   368: goto -> 1257
/*    */     //   371: aload_0
/*    */     //   372: dup
/*    */     //   373: dup
/*    */     //   374: invokevirtual r8 : ()Lf/ro;
/*    */     //   377: astore_0
/*    */     //   378: getfield L7 : B
/*    */     //   381: istore_1
/*    */     //   382: getfield or0 : Ljava/lang/String;
/*    */     //   385: astore_2
/*    */     //   386: aload_0
/*    */     //   387: checkcast f/R8
/*    */     //   390: getfield YG0 : Lf/js;
/*    */     //   393: getfield MH0 : Lf/pA;
/*    */     //   396: dup
/*    */     //   397: astore_0
/*    */     //   398: ifnull -> 1257
/*    */     //   401: getstatic f/UB0.Kg0 : Lf/Q50;
/*    */     //   404: new f/fn0
/*    */     //   407: dup
/*    */     //   408: aload_0
/*    */     //   409: iload_1
/*    */     //   410: aload_2
/*    */     //   411: invokespecial <init> : (Lf/pA;BLjava/lang/String;)V
/*    */     //   414: invokevirtual fN : (Ljava/lang/Runnable;)V
/*    */     //   417: goto -> 1257
/*    */     //   420: aload_0
/*    */     //   421: dup
/*    */     //   422: dup2
/*    */     //   423: dup2
/*    */     //   424: dup2
/*    */     //   425: dup2
/*    */     //   426: dup2
/*    */     //   427: dup2
/*    */     //   428: invokevirtual r8 : ()Lf/ro;
/*    */     //   431: astore_0
/*    */     //   432: getfield L7 : B
/*    */     //   435: istore_1
/*    */     //   436: getfield or0 : Ljava/lang/String;
/*    */     //   439: astore_2
/*    */     //   440: getfield ob : B
/*    */     //   443: istore_3
/*    */     //   444: getfield zK : B
/*    */     //   447: istore #4
/*    */     //   449: getfield s90 : B
/*    */     //   452: istore #5
/*    */     //   454: getfield Vc0 : B
/*    */     //   457: istore #6
/*    */     //   459: getfield mg0 : Lf/ky;
/*    */     //   462: astore #7
/*    */     //   464: getfield C90 : Z
/*    */     //   467: istore #8
/*    */     //   469: getfield fp : Z
/*    */     //   472: istore #9
/*    */     //   474: getfield Yy0 : Z
/*    */     //   477: istore #10
/*    */     //   479: getfield Wy0 : B
/*    */     //   482: istore #11
/*    */     //   484: getfield A2 : B
/*    */     //   487: istore #12
/*    */     //   489: getfield SP : B
/*    */     //   492: istore #13
/*    */     //   494: aload_0
/*    */     //   495: checkcast f/R8
/*    */     //   498: getfield YG0 : Lf/js;
/*    */     //   501: getfield MH0 : Lf/pA;
/*    */     //   504: dup
/*    */     //   505: astore_0
/*    */     //   506: ifnull -> 1257
/*    */     //   509: aload_0
/*    */     //   510: iload_1
/*    */     //   511: aload_2
/*    */     //   512: iload_3
/*    */     //   513: iload #4
/*    */     //   515: iload #5
/*    */     //   517: iload #6
/*    */     //   519: aload #7
/*    */     //   521: iload #8
/*    */     //   523: iload #9
/*    */     //   525: iload #10
/*    */     //   527: iload #11
/*    */     //   529: iload #12
/*    */     //   531: iload #13
/*    */     //   533: invokevirtual f50 : (BLjava/lang/String;IIIBLf/ky;ZZZBBB)V
/*    */     //   536: goto -> 1257
/*    */     //   539: new java/util/ArrayList
/*    */     //   542: dup
/*    */     //   543: astore_1
/*    */     //   544: invokespecial <init> : ()V
/*    */     //   547: iconst_0
/*    */     //   548: istore_2
/*    */     //   549: iload_2
/*    */     //   550: aload_0
/*    */     //   551: getfield KK : [S
/*    */     //   554: arraylength
/*    */     //   555: if_icmpge -> 601
/*    */     //   558: aload_1
/*    */     //   559: new f/i
/*    */     //   562: dup
/*    */     //   563: invokestatic v30 : ()Lf/On;
/*    */     //   566: aload_0
/*    */     //   567: getfield KK : [S
/*    */     //   570: iload_2
/*    */     //   571: saload
/*    */     //   572: invokevirtual lpT3 : (S)Lf/UD0;
/*    */     //   575: aload_0
/*    */     //   576: getstatic f/Ud0.X30 : Lf/Ud0;
/*    */     //   579: astore_3
/*    */     //   580: getfield Ny0 : [S
/*    */     //   583: iload_2
/*    */     //   584: saload
/*    */     //   585: aload_3
/*    */     //   586: swap
/*    */     //   587: iload_2
/*    */     //   588: invokespecial <init> : (Lf/UD0;Lf/Ud0;II)V
/*    */     //   591: invokevirtual add : (Ljava/lang/Object;)Z
/*    */     //   594: pop
/*    */     //   595: iinc #2, 1
/*    */     //   598: goto -> 549
/*    */     //   601: aload_0
/*    */     //   602: dup
/*    */     //   603: invokevirtual r8 : ()Lf/ro;
/*    */     //   606: astore_0
/*    */     //   607: getfield L7 : B
/*    */     //   610: istore_2
/*    */     //   611: aload_0
/*    */     //   612: checkcast f/R8
/*    */     //   615: getfield YG0 : Lf/js;
/*    */     //   618: getfield MH0 : Lf/pA;
/*    */     //   621: dup
/*    */     //   622: astore_0
/*    */     //   623: ifnull -> 1257
/*    */     //   626: aload_0
/*    */     //   627: getfield dS : Lf/YC;
/*    */     //   630: dup
/*    */     //   631: astore_3
/*    */     //   632: ifnull -> 645
/*    */     //   635: aload_0
/*    */     //   636: aload_3
/*    */     //   637: invokevirtual ra0 : ()Z
/*    */     //   640: pop
/*    */     //   641: aconst_null
/*    */     //   642: putfield dS : Lf/YC;
/*    */     //   645: aload_0
/*    */     //   646: dup
/*    */     //   647: dup2
/*    */     //   648: new f/YC
/*    */     //   651: dup
/*    */     //   652: aload_0
/*    */     //   653: swap
/*    */     //   654: dup
/*    */     //   655: aload_0
/*    */     //   656: iload_2
/*    */     //   657: aload_1
/*    */     //   658: invokespecial <init> : (Lf/pA;BLjava/util/ArrayList;)V
/*    */     //   661: putfield dS : Lf/YC;
/*    */     //   664: iconst_1
/*    */     //   665: invokevirtual wI0 : (Z)V
/*    */     //   668: getfield dS : Lf/YC;
/*    */     //   671: invokevirtual mM : ()V
/*    */     //   674: getfield dS : Lf/YC;
/*    */     //   677: aload_0
/*    */     //   678: dup
/*    */     //   679: dup
/*    */     //   680: invokevirtual RS : ()I
/*    */     //   683: istore_1
/*    */     //   684: invokevirtual qF : ()I
/*    */     //   687: aload_0
/*    */     //   688: getfield dS : Lf/YC;
/*    */     //   691: getfield xY : I
/*    */     //   694: iconst_2
/*    */     //   695: iload_1
/*    */     //   696: invokestatic Se0 : (IIII)I
/*    */     //   699: istore_1
/*    */     //   700: invokevirtual e3 : ()I
/*    */     //   703: istore_2
/*    */     //   704: iload_1
/*    */     //   705: aload_0
/*    */     //   706: invokevirtual Hy : ()I
/*    */     //   709: aload_0
/*    */     //   710: getfield dS : Lf/YC;
/*    */     //   713: getfield HC : I
/*    */     //   716: isub
/*    */     //   717: iconst_2
/*    */     //   718: idiv
/*    */     //   719: iload_2
/*    */     //   720: iadd
/*    */     //   721: invokevirtual ME : (II)Z
/*    */     //   724: pop
/*    */     //   725: getfield dS : Lf/YC;
/*    */     //   728: invokevirtual J8 : (Lf/JG0;)V
/*    */     //   731: goto -> 1257
/*    */     //   734: aload_0
/*    */     //   735: dup
/*    */     //   736: invokevirtual r8 : ()Lf/ro;
/*    */     //   739: astore_0
/*    */     //   740: getfield L7 : B
/*    */     //   743: istore_1
/*    */     //   744: aload_0
/*    */     //   745: checkcast f/R8
/*    */     //   748: getfield YG0 : Lf/js;
/*    */     //   751: getfield MH0 : Lf/pA;
/*    */     //   754: dup
/*    */     //   755: astore_0
/*    */     //   756: ifnull -> 1257
/*    */     //   759: aload_0
/*    */     //   760: new f/XI
/*    */     //   763: dup
/*    */     //   764: astore_0
/*    */     //   765: iload_1
/*    */     //   766: invokespecial <init> : (B)V
/*    */     //   769: aload_0
/*    */     //   770: invokevirtual J8 : (Lf/JG0;)V
/*    */     //   773: goto -> 1257
/*    */     //   776: aload_0
/*    */     //   777: dup
/*    */     //   778: invokevirtual r8 : ()Lf/ro;
/*    */     //   781: astore_0
/*    */     //   782: getfield L7 : B
/*    */     //   785: istore_1
/*    */     //   786: aload_0
/*    */     //   787: checkcast f/R8
/*    */     //   790: getfield YG0 : Lf/js;
/*    */     //   793: getfield MH0 : Lf/pA;
/*    */     //   796: dup
/*    */     //   797: astore_0
/*    */     //   798: ifnull -> 1257
/*    */     //   801: aload_0
/*    */     //   802: new f/sC0
/*    */     //   805: dup
/*    */     //   806: astore_0
/*    */     //   807: iload_1
/*    */     //   808: invokespecial <init> : (B)V
/*    */     //   811: aload_0
/*    */     //   812: invokevirtual J8 : (Lf/JG0;)V
/*    */     //   815: goto -> 1257
/*    */     //   818: aload_0
/*    */     //   819: getfield KK : [S
/*    */     //   822: iconst_0
/*    */     //   823: saload
/*    */     //   824: dup
/*    */     //   825: istore_1
/*    */     //   826: sipush #495
/*    */     //   829: if_icmpne -> 847
/*    */     //   832: getstatic f/km.wI0 : Lf/Pw;
/*    */     //   835: aload_0
/*    */     //   836: getfield L7 : B
/*    */     //   839: iconst_2
/*    */     //   840: iconst_0
/*    */     //   841: invokevirtual lY : (BBZ)V
/*    */     //   844: goto -> 1257
/*    */     //   847: iload_1
/*    */     //   848: sipush #387
/*    */     //   851: if_icmpne -> 869
/*    */     //   854: getstatic f/km.wI0 : Lf/Pw;
/*    */     //   857: aload_0
/*    */     //   858: getfield L7 : B
/*    */     //   861: iconst_3
/*    */     //   862: iconst_0
/*    */     //   863: invokevirtual lY : (BBZ)V
/*    */     //   866: goto -> 1257
/*    */     //   869: iload_1
/*    */     //   870: iconst_1
/*    */     //   871: if_icmpne -> 889
/*    */     //   874: getstatic f/km.wI0 : Lf/Pw;
/*    */     //   877: aload_0
/*    */     //   878: getfield L7 : B
/*    */     //   881: iconst_2
/*    */     //   882: iconst_1
/*    */     //   883: invokevirtual lY : (BBZ)V
/*    */     //   886: goto -> 1257
/*    */     //   889: iload_1
/*    */     //   890: sipush #152
/*    */     //   893: if_icmpne -> 1035
/*    */     //   896: getstatic f/km.wI0 : Lf/Pw;
/*    */     //   899: aload_0
/*    */     //   900: getfield L7 : B
/*    */     //   903: iconst_4
/*    */     //   904: iconst_0
/*    */     //   905: invokevirtual lY : (BBZ)V
/*    */     //   908: goto -> 1257
/*    */     //   911: aload_0
/*    */     //   912: dup
/*    */     //   913: invokevirtual r8 : ()Lf/ro;
/*    */     //   916: astore_0
/*    */     //   917: getfield L7 : B
/*    */     //   920: istore_1
/*    */     //   921: aload_0
/*    */     //   922: checkcast f/R8
/*    */     //   925: getfield YG0 : Lf/js;
/*    */     //   928: getfield MH0 : Lf/pA;
/*    */     //   931: dup
/*    */     //   932: astore_0
/*    */     //   933: ifnull -> 1257
/*    */     //   936: aload_0
/*    */     //   937: new f/Hl0
/*    */     //   940: dup
/*    */     //   941: astore_0
/*    */     //   942: iload_1
/*    */     //   943: invokespecial <init> : (B)V
/*    */     //   946: aload_0
/*    */     //   947: invokevirtual J8 : (Lf/JG0;)V
/*    */     //   950: goto -> 1257
/*    */     //   953: aload_0
/*    */     //   954: invokevirtual r8 : ()Lf/ro;
/*    */     //   957: getstatic f/aq0.LI : Lf/aq0;
/*    */     //   960: invokevirtual s40 : (Lf/aq0;)Lf/Uc0;
/*    */     //   963: aload_0
/*    */     //   964: getfield pF : I
/*    */     //   967: invokevirtual de0 : (I)Lf/j40;
/*    */     //   970: dup
/*    */     //   971: astore_1
/*    */     //   972: ifnonnull -> 988
/*    */     //   975: aload_0
/*    */     //   976: invokevirtual r8 : ()Lf/ro;
/*    */     //   979: aload_0
/*    */     //   980: getfield L7 : B
/*    */     //   983: iconst_0
/*    */     //   984: invokevirtual lx0 : (BB)V
/*    */     //   987: return
/*    */     //   988: aload_0
/*    */     //   989: dup
/*    */     //   990: dup2
/*    */     //   991: invokevirtual r8 : ()Lf/ro;
/*    */     //   994: astore_0
/*    */     //   995: getfield DK : Lf/Px0;
/*    */     //   998: astore_2
/*    */     //   999: getfield L7 : B
/*    */     //   1002: istore_3
/*    */     //   1003: getfield KK : [S
/*    */     //   1006: astore #4
/*    */     //   1008: aload_0
/*    */     //   1009: checkcast f/R8
/*    */     //   1012: getfield YG0 : Lf/js;
/*    */     //   1015: getfield MH0 : Lf/pA;
/*    */     //   1018: dup
/*    */     //   1019: astore_0
/*    */     //   1020: ifnull -> 1257
/*    */     //   1023: aload_0
/*    */     //   1024: aload #4
/*    */     //   1026: aload_2
/*    */     //   1027: iload_3
/*    */     //   1028: aload_1
/*    */     //   1029: invokevirtual zj0 : ([SLf/Px0;BLf/j40;)V
/*    */     //   1032: goto -> 1257
/*    */     //   1035: getstatic f/km.kH0 : Lf/Qz0;
/*    */     //   1038: aload_0
/*    */     //   1039: invokevirtual wV : (Lf/zB0;)V
/*    */     //   1042: goto -> 1257
/*    */     //   1045: getstatic f/km.kH0 : Lf/Qz0;
/*    */     //   1048: dup
/*    */     //   1049: astore_1
/*    */     //   1050: aload_0
/*    */     //   1051: getfield L7 : B
/*    */     //   1054: i2s
/*    */     //   1055: istore_0
/*    */     //   1056: getfield x60 : Lf/Ut0;
/*    */     //   1059: iload_0
/*    */     //   1060: invokevirtual remove : (I)Ljava/lang/Object;
/*    */     //   1063: checkcast f/hO
/*    */     //   1066: dup
/*    */     //   1067: astore_0
/*    */     //   1068: ifnonnull -> 1074
/*    */     //   1071: goto -> 1257
/*    */     //   1074: aload_1
/*    */     //   1075: aload_0
/*    */     //   1076: invokevirtual jf0 : (Lf/JG0;)Z
/*    */     //   1079: pop
/*    */     //   1080: goto -> 1257
/*    */     //   1083: getstatic f/km.kH0 : Lf/Qz0;
/*    */     //   1086: dup
/*    */     //   1087: astore_1
/*    */     //   1088: aload_0
/*    */     //   1089: dup
/*    */     //   1090: dup
/*    */     //   1091: invokevirtual Md0 : ()Ljava/lang/String;
/*    */     //   1094: astore_0
/*    */     //   1095: getfield L7 : B
/*    */     //   1098: i2s
/*    */     //   1099: istore_2
/*    */     //   1100: getfield KK : [S
/*    */     //   1103: dup
/*    */     //   1104: iconst_0
/*    */     //   1105: saload
/*    */     //   1106: istore_3
/*    */     //   1107: iconst_1
/*    */     //   1108: saload
/*    */     //   1109: istore #4
/*    */     //   1111: invokevirtual getClass : ()Ljava/lang/Class;
/*    */     //   1114: pop
/*    */     //   1115: new f/zR
/*    */     //   1118: dup
/*    */     //   1119: dup
/*    */     //   1120: astore #5
/*    */     //   1122: iload #4
/*    */     //   1124: aload #5
/*    */     //   1126: iload_3
/*    */     //   1127: aload #5
/*    */     //   1129: dup
/*    */     //   1130: iload #4
/*    */     //   1132: iload_3
/*    */     //   1133: aload_1
/*    */     //   1134: dup
/*    */     //   1135: aload #5
/*    */     //   1137: aload_1
/*    */     //   1138: aload #5
/*    */     //   1140: aload_0
/*    */     //   1141: iload_3
/*    */     //   1142: iload #4
/*    */     //   1144: invokespecial <init> : (Ljava/lang/String;SS)V
/*    */     //   1147: invokevirtual Ub : ()I
/*    */     //   1150: invokevirtual si : (Lf/JG0;I)V
/*    */     //   1153: getfield x60 : Lf/Ut0;
/*    */     //   1156: iload_2
/*    */     //   1157: aload #5
/*    */     //   1159: invokevirtual A3 : (ILjava/lang/Object;)Ljava/lang/Object;
/*    */     //   1162: pop
/*    */     //   1163: iconst_1
/*    */     //   1164: isub
/*    */     //   1165: iconst_4
/*    */     //   1166: imul
/*    */     //   1167: istore_0
/*    */     //   1168: iconst_1
/*    */     //   1169: isub
/*    */     //   1170: iconst_4
/*    */     //   1171: imul
/*    */     //   1172: iload_0
/*    */     //   1173: swap
/*    */     //   1174: invokevirtual ME : (II)Z
/*    */     //   1177: pop
/*    */     //   1178: invokevirtual mM : ()V
/*    */     //   1181: putfield oj0 : I
/*    */     //   1184: putfield za : I
/*    */     //   1187: iconst_1
/*    */     //   1188: putfield Jx0 : Z
/*    */     //   1191: goto -> 1257
/*    */     //   1194: aload_0
/*    */     //   1195: dup
/*    */     //   1196: invokevirtual r8 : ()Lf/ro;
/*    */     //   1199: astore_0
/*    */     //   1200: getfield L7 : B
/*    */     //   1203: istore_1
/*    */     //   1204: aload_0
/*    */     //   1205: checkcast f/R8
/*    */     //   1208: getfield YG0 : Lf/js;
/*    */     //   1211: getfield MH0 : Lf/pA;
/*    */     //   1214: dup
/*    */     //   1215: astore_0
/*    */     //   1216: ifnull -> 1257
/*    */     //   1219: aload_0
/*    */     //   1220: getfield cl : Lf/GV;
/*    */     //   1223: dup
/*    */     //   1224: astore_2
/*    */     //   1225: ifnull -> 1238
/*    */     //   1228: aload_0
/*    */     //   1229: aload_2
/*    */     //   1230: invokevirtual ra0 : ()Z
/*    */     //   1233: pop
/*    */     //   1234: aconst_null
/*    */     //   1235: putfield cl : Lf/GV;
/*    */     //   1238: aload_0
/*    */     //   1239: dup
/*    */     //   1240: new f/GV
/*    */     //   1243: dup
/*    */     //   1244: astore_0
/*    */     //   1245: iload_1
/*    */     //   1246: invokespecial <init> : (B)V
/*    */     //   1249: aload_0
/*    */     //   1250: putfield cl : Lf/GV;
/*    */     //   1253: aload_0
/*    */     //   1254: invokevirtual J8 : (Lf/JG0;)V
/*    */     //   1257: return
/*    */     // Line number table:
/*    */     //   Java source line number -> byte code offset
/*    */     //   #1	-> 13
/*    */     //   #2	-> 16
/*    */     //   #3	-> 23
/*    */     //   #4	-> 32
/*    */     //   #5	-> 49
/*    */     //   #6	-> 58
/*    */     //   #7	-> 70
/*    */     //   #8	-> 84
/*    */     //   #9	-> 96
/*    */     //   #10	-> 101
/*    */     //   #11	-> 242
/*    */     //   #12	-> 245
/*    */     //   #13	-> 253
/*    */     //   #14	-> 276
/*    */     //   #15	-> 292
/*    */     //   #16	-> 295
/*    */     //   #17	-> 303
/*    */     //   #18	-> 325
/*    */     //   #19	-> 341
/*    */     //   #20	-> 344
/*    */     //   #21	-> 352
/*    */     //   #22	-> 374
/*    */     //   #23	-> 390
/*    */     //   #24	-> 393
/*    */     //   #25	-> 401
/*    */     //   #26	-> 428
/*    */     //   #27	-> 498
/*    */     //   #28	-> 501
/*    */     //   #29	-> 533
/*    */     //   #30	-> 539
/*    */     //   #31	-> 615
/*    */     //   #32	-> 618
/*    */     //   #33	-> 627
/*    */     //   #34	-> 637
/*    */     //   #35	-> 691
/*    */     //   #36	-> 696
/*    */     //   #37	-> 700
/*    */     //   #38	-> 713
/*    */     //   #39	-> 718
/*    */     //   #40	-> 721
/*    */     //   #41	-> 725
/*    */     //   #42	-> 736
/*    */     //   #43	-> 748
/*    */     //   #44	-> 751
/*    */     //   #45	-> 760
/*    */     //   #46	-> 778
/*    */     //   #47	-> 790
/*    */     //   #48	-> 793
/*    */     //   #49	-> 802
/*    */     //   #50	-> 819
/*    */     //   #51	-> 925
/*    */     //   #52	-> 928
/*    */     //   #53	-> 937
/*    */     //   #54	-> 954
/*    */     //   #55	-> 976
/*    */     //   #56	-> 991
/*    */     //   #57	-> 1012
/*    */     //   #58	-> 1015
/*    */     //   #59	-> 1029
/*    */     //   #60	-> 1035
/*    */     //   #61	-> 1056
/*    */     //   #62	-> 1060
/*    */     //   #63	-> 1083
/*    */     //   #64	-> 1115
/*    */     //   #65	-> 1147
/*    */     //   #66	-> 1153
/*    */     //   #67	-> 1174
/*    */     //   #68	-> 1178
/*    */     //   #69	-> 1181
/*    */     //   #70	-> 1196
/*    */     //   #71	-> 1208
/*    */     //   #72	-> 1211
/*    */     //   #73	-> 1220
/*    */   }
/*    */   
/*    */   public final String Md0() {
/*    */     // Byte code:
/*    */     //   0: aload_0
/*    */     //   1: getfield Hw0 : Ljava/lang/String;
/*    */     //   4: dup
/*    */     //   5: astore_1
/*    */     //   6: ifnull -> 11
/*    */     //   9: aload_1
/*    */     //   10: areturn
/*    */     //   11: aload_0
/*    */     //   12: getfield ph0 : Lf/Aq;
/*    */     //   15: invokevirtual ordinal : ()I
/*    */     //   18: dup
/*    */     //   19: istore_1
/*    */     //   20: bipush #9
/*    */     //   22: if_icmpeq -> 406
/*    */     //   25: iload_1
/*    */     //   26: bipush #12
/*    */     //   28: if_icmpeq -> 406
/*    */     //   31: iload_1
/*    */     //   32: bipush #15
/*    */     //   34: if_icmpeq -> 223
/*    */     //   37: iload_1
/*    */     //   38: bipush #23
/*    */     //   40: if_icmpeq -> 406
/*    */     //   43: iload_1
/*    */     //   44: bipush #37
/*    */     //   46: if_icmpeq -> 105
/*    */     //   49: iload_1
/*    */     //   50: bipush #32
/*    */     //   52: if_icmpeq -> 406
/*    */     //   55: iload_1
/*    */     //   56: bipush #33
/*    */     //   58: if_icmpeq -> 87
/*    */     //   61: aload_0
/*    */     //   62: getfield pF : I
/*    */     //   65: dup
/*    */     //   66: istore_1
/*    */     //   67: aload_0
/*    */     //   68: getfield nC0 : [Lf/LPT1;
/*    */     //   71: astore_0
/*    */     //   72: ifne -> 81
/*    */     //   75: ldc_w ''
/*    */     //   78: goto -> 86
/*    */     //   81: iload_1
/*    */     //   82: aload_0
/*    */     //   83: invokestatic Sz : (I[Lf/LPT1;)Ljava/lang/String;
/*    */     //   86: areturn
/*    */     //   87: getstatic f/D2.Wf0 : Lf/D2;
/*    */     //   90: aload_0
/*    */     //   91: dup
/*    */     //   92: getfield eG0 : B
/*    */     //   95: istore_0
/*    */     //   96: getfield KK : [S
/*    */     //   99: iload_0
/*    */     //   100: swap
/*    */     //   101: invokevirtual Lg0 : (B[S)Ljava/lang/String;
/*    */     //   104: areturn
/*    */     //   105: aload_0
/*    */     //   106: getstatic f/hh.qu0 : Lf/hh;
/*    */     //   109: astore_1
/*    */     //   110: getfield rE0 : B
/*    */     //   113: dup
/*    */     //   114: istore_2
/*    */     //   115: iflt -> 139
/*    */     //   118: iload_2
/*    */     //   119: aload_1
/*    */     //   120: getfield VA0 : [Lf/pt0;
/*    */     //   123: dup
/*    */     //   124: astore_1
/*    */     //   125: arraylength
/*    */     //   126: if_icmplt -> 132
/*    */     //   129: goto -> 139
/*    */     //   132: aload_1
/*    */     //   133: iload_2
/*    */     //   134: aaload
/*    */     //   135: astore_1
/*    */     //   136: goto -> 141
/*    */     //   139: aconst_null
/*    */     //   140: astore_1
/*    */     //   141: aload_1
/*    */     //   142: ifnonnull -> 149
/*    */     //   145: ldc_w 'ERROR'
/*    */     //   148: areturn
/*    */     //   149: aload_1
/*    */     //   150: aload_0
/*    */     //   151: getfield sc0 : S
/*    */     //   154: istore_1
/*    */     //   155: getfield E7 : Ljava/util/TreeMap;
/*    */     //   158: iload_1
/*    */     //   159: invokestatic valueOf : (S)Ljava/lang/Short;
/*    */     //   162: invokevirtual get : (Ljava/lang/Object;)Ljava/lang/Object;
/*    */     //   165: checkcast f/xq0
/*    */     //   168: dup
/*    */     //   169: astore_1
/*    */     //   170: ifnonnull -> 177
/*    */     //   173: ldc_w 'ERROR'
/*    */     //   176: areturn
/*    */     //   177: aload_0
/*    */     //   178: getfield D90 : B
/*    */     //   181: dup
/*    */     //   182: istore_0
/*    */     //   183: iflt -> 219
/*    */     //   186: iload_0
/*    */     //   187: aload_1
/*    */     //   188: getfield Bg : [[S
/*    */     //   191: dup
/*    */     //   192: astore_2
/*    */     //   193: arraylength
/*    */     //   194: if_icmplt -> 200
/*    */     //   197: goto -> 219
/*    */     //   200: getstatic f/D2.Wf0 : Lf/D2;
/*    */     //   203: aload_2
/*    */     //   204: iload_0
/*    */     //   205: aload_1
/*    */     //   206: getfield Ym0 : B
/*    */     //   209: istore_0
/*    */     //   210: aaload
/*    */     //   211: iload_0
/*    */     //   212: swap
/*    */     //   213: invokevirtual Lg0 : (B[S)Ljava/lang/String;
/*    */     //   216: goto -> 222
/*    */     //   219: ldc_w ''
/*    */     //   222: areturn
/*    */     //   223: aload_0
/*    */     //   224: getstatic f/km.mI0 : Lf/P1;
/*    */     //   227: getfield UG0 : Lf/s40;
/*    */     //   230: invokevirtual pr : ()Ljava/nio/ByteBuffer;
/*    */     //   233: astore_0
/*    */     //   234: getfield pF : I
/*    */     //   237: dup
/*    */     //   238: istore_1
/*    */     //   239: aload_0
/*    */     //   240: getstatic f/ed.j5 : Lf/ak;
/*    */     //   243: pop
/*    */     //   244: invokevirtual position : ()I
/*    */     //   247: istore_2
/*    */     //   248: iflt -> 398
/*    */     //   251: iload_1
/*    */     //   252: aload_0
/*    */     //   253: invokevirtual limit : ()I
/*    */     //   256: if_icmple -> 262
/*    */     //   259: goto -> 398
/*    */     //   262: aload_0
/*    */     //   263: iload_1
/*    */     //   264: invokevirtual position : (I)Ljava/nio/Buffer;
/*    */     //   267: pop
/*    */     //   268: new java/lang/StringBuilder
/*    */     //   271: dup
/*    */     //   272: astore_3
/*    */     //   273: invokespecial <init> : ()V
/*    */     //   276: aload_0
/*    */     //   277: invokevirtual get : ()B
/*    */     //   280: dup
/*    */     //   281: istore_1
/*    */     //   282: iconst_m1
/*    */     //   283: if_icmpne -> 299
/*    */     //   286: aload_3
/*    */     //   287: aload_0
/*    */     //   288: iload_2
/*    */     //   289: invokevirtual position : (I)Ljava/nio/Buffer;
/*    */     //   292: pop
/*    */     //   293: invokevirtual toString : ()Ljava/lang/String;
/*    */     //   296: goto -> 405
/*    */     //   299: iload_1
/*    */     //   300: sipush #10240
/*    */     //   303: istore #4
/*    */     //   305: iconst_1
/*    */     //   306: iand
/*    */     //   307: ifeq -> 316
/*    */     //   310: sipush #10241
/*    */     //   313: i2s
/*    */     //   314: istore #4
/*    */     //   316: iload_1
/*    */     //   317: iconst_2
/*    */     //   318: iand
/*    */     //   319: ifeq -> 330
/*    */     //   322: iload #4
/*    */     //   324: bipush #8
/*    */     //   326: ior
/*    */     //   327: i2s
/*    */     //   328: istore #4
/*    */     //   330: iload_1
/*    */     //   331: iconst_4
/*    */     //   332: iand
/*    */     //   333: ifeq -> 343
/*    */     //   336: iload #4
/*    */     //   338: iconst_2
/*    */     //   339: ior
/*    */     //   340: i2s
/*    */     //   341: istore #4
/*    */     //   343: iload_1
/*    */     //   344: bipush #8
/*    */     //   346: iand
/*    */     //   347: ifeq -> 358
/*    */     //   350: iload #4
/*    */     //   352: bipush #16
/*    */     //   354: ior
/*    */     //   355: i2s
/*    */     //   356: istore #4
/*    */     //   358: iload_1
/*    */     //   359: bipush #16
/*    */     //   361: iand
/*    */     //   362: ifeq -> 372
/*    */     //   365: iload #4
/*    */     //   367: iconst_4
/*    */     //   368: ior
/*    */     //   369: i2s
/*    */     //   370: istore #4
/*    */     //   372: iload_1
/*    */     //   373: bipush #32
/*    */     //   375: iand
/*    */     //   376: ifeq -> 387
/*    */     //   379: iload #4
/*    */     //   381: bipush #32
/*    */     //   383: ior
/*    */     //   384: i2s
/*    */     //   385: istore #4
/*    */     //   387: aload_3
/*    */     //   388: iload #4
/*    */     //   390: i2c
/*    */     //   391: invokevirtual append : (C)Ljava/lang/StringBuilder;
/*    */     //   394: pop
/*    */     //   395: goto -> 276
/*    */     //   398: ldc_w 'Invalid String Offset '
/*    */     //   401: iload_1
/*    */     //   402: invokestatic SD0 : (Ljava/lang/String;I)Ljava/lang/String;
/*    */     //   405: areturn
/*    */     //   406: ldc_w ''
/*    */     //   409: areturn
/*    */     // Line number table:
/*    */     //   Java source line number -> byte code offset
/*    */     //   #1	-> 75
/*    */     //   #2	-> 87
/*    */     //   #3	-> 92
/*    */     //   #4	-> 120
/*    */     //   #5	-> 145
/*    */     //   #6	-> 155
/*    */     //   #7	-> 173
/*    */     //   #8	-> 188
/*    */     //   #9	-> 200
/*    */     //   #10	-> 206
/*    */     //   #11	-> 224
/*    */     //   #12	-> 244
/*    */     //   #13	-> 398
/*    */     //   #14	-> 406
/*    */   } }


/* Location:              /Users/vnnsnnt/Documents/Codespace/JavaWorkspace/RedTrainer/src/main/java/org/trainer/client/PokeMMO.jar!/f/zB0.class
 * Java compiler version: 8 (52.0)
 * JD-Core Version:       1.1.3
 */