/*  1 */ package f;public final class Zc extends Kl0 { public final void Cx() { ve ve; if (km.MR != null) { jA0 jA0; if ((jA0 = km.wI0.K00) != null)
/*  2 */       { R8 r8; if ((r8 = km.u4) != null) {
/*  3 */           int i = jA0.Pc0.Jg;
/*    */           
/*  5 */           int j = jA0.F50.ax ^ true;
/*  6 */           r8.e20.W3(new L3(i, j));
/*  7 */         }  km.pm0.NR(); Pw pw;
/*    */         jA0 jA01;
/*  9 */         if ((jA01 = (pw = km.wI0).K00) != null) { jA01
/* 10 */             .dispose(); pw.K00 = null; }  Wl wl; if ((wl = pw.K7) != null) { wl.dispose(); pw.K7 = null; }
/*    */          kf kf;
/* 12 */         if ((kf = pw.js0.BA) != null) kf
/* 13 */             .ra0(); 
/* 14 */         km.MR = null; } else if (km.MR.sQ() || km.MR.RM() || km.MR
/* 15 */         .rx == 
/* 16 */         ky.JH0)
/* 17 */       { km.wI0.K7
/*    */           
/* 19 */           .AJ0 = No0.yn0;
/* 20 */         km.wI0.K7.wB0();
/* 21 */         km.wI0.K7.LW
/* 22 */           .YP
/* 23 */           .clear(); km.MR
/* 24 */           .W
/* 25 */           .clear(); km.MR.Oq0.clear();
/* 26 */         km.pm0.NR(); qj0 qj0; if ((qj0 = km.Ll0) != null) { qj0
/* 27 */             .Fj0 = true; km.Ll0 = null; }
/* 28 */          km.MR = null; km.wI0
/* 29 */           .K7
/* 30 */           .dispose(); km.wI0.K7 = null;
/*    */         kf kf;
/* 32 */         if ((kf = km.wI0.js0.BA) != null) kf
/* 33 */             .ra0();  } else { throw new RuntimeException(""); }  }
/* 34 */      if ((km.MR = this.wt).Vg()) r8().s40(aq0.LI).Ix0();  if (this.wt.sQ())
/*    */     
/*    */     { 
/* 37 */       if ((ve = js.vu0.MH0.yq0) != null)
/* 38 */         LJ0(true, false);  } else { ((Zc)super).wt.kS(); }
/*    */      }
/*    */ 
/*    */   
/*    */   public Gp0 wt;
/*    */   public hm0[][] kj0;
/*    */   public QZ[] nL;
/*    */   public aq0 Un0;
/*    */   public boolean fv;
/*    */   public boolean YG0;
/*    */   public byte l00;
/*    */   public byte tc;
/*    */   public byte Sf0 = 0;
/*    */   public byte Np0 = 0;
/*    */   public DO[] cd0 = DO.Zv;
/*    */   public CC0[] OE0 = CC0.I7;
/*    */   public Fs[] Bk = null;
/*    */   public byte qx0 = -1;
/*    */   public short TJ0 = 0;
/*    */   public DK ap0 = null;
/*    */   public rK bf;
/*    */   public Mx xm = Mx.LM;
/*    */   public R00 TA0;
/*    */   public hR[] X50 = hR.ZF;
/*    */   public byte Rt0 = 0;
/*    */   public int OL;
/*    */   public boolean NO;
/*    */   
/*    */   public Zc(c4 paramc4, ByteBuffer paramByteBuffer) {
/*    */     super(paramc4, paramByteBuffer);
/*    */   }
/*    */   
/*    */   public final void sM() {
/*    */     // Byte code:
/*    */     //   0: aload_0
/*    */     //   1: dup
/*    */     //   2: dup
/*    */     //   3: getfield Ws : Ljava/nio/ByteBuffer;
/*    */     //   6: invokevirtual get : ()B
/*    */     //   9: istore_1
/*    */     //   10: getfield Ws : Ljava/nio/ByteBuffer;
/*    */     //   13: invokevirtual get : ()B
/*    */     //   16: istore_2
/*    */     //   17: iconst_0
/*    */     //   18: istore_3
/*    */     //   19: getfield n90 : I
/*    */     //   22: bipush #20
/*    */     //   24: if_icmplt -> 35
/*    */     //   27: aload_0
/*    */     //   28: getfield Ws : Ljava/nio/ByteBuffer;
/*    */     //   31: invokevirtual get : ()B
/*    */     //   34: istore_3
/*    */     //   35: aload_0
/*    */     //   36: dup
/*    */     //   37: dup2
/*    */     //   38: dup2
/*    */     //   39: dup2
/*    */     //   40: getfield Ws : Ljava/nio/ByteBuffer;
/*    */     //   43: invokevirtual get : ()B
/*    */     //   46: invokestatic Mt0 : (B)Lf/ky;
/*    */     //   49: astore #4
/*    */     //   51: getfield Ws : Ljava/nio/ByteBuffer;
/*    */     //   54: invokevirtual get : ()B
/*    */     //   57: invokestatic Yb0 : (B)Lf/rK;
/*    */     //   60: putfield bf : Lf/rK;
/*    */     //   63: getfield Ws : Ljava/nio/ByteBuffer;
/*    */     //   66: invokevirtual get : ()B
/*    */     //   69: invokestatic dB0 : (B)Lf/yi;
/*    */     //   72: astore #5
/*    */     //   74: getfield Ws : Ljava/nio/ByteBuffer;
/*    */     //   77: invokevirtual getInt : ()I
/*    */     //   80: istore #6
/*    */     //   82: getfield Ws : Ljava/nio/ByteBuffer;
/*    */     //   85: invokevirtual getShort : ()S
/*    */     //   88: istore #7
/*    */     //   90: getfield Ws : Ljava/nio/ByteBuffer;
/*    */     //   93: invokevirtual get : ()B
/*    */     //   96: invokestatic Cq0 : (B)Lf/Mn;
/*    */     //   99: astore #8
/*    */     //   101: invokevirtual R00 : ()I
/*    */     //   104: iconst_1
/*    */     //   105: if_icmpne -> 114
/*    */     //   108: iconst_1
/*    */     //   109: istore #9
/*    */     //   111: goto -> 117
/*    */     //   114: iconst_0
/*    */     //   115: istore #9
/*    */     //   117: aload_0
/*    */     //   118: getfield n90 : I
/*    */     //   121: bipush #16
/*    */     //   123: if_icmpgt -> 138
/*    */     //   126: aload_0
/*    */     //   127: getfield Ws : Ljava/nio/ByteBuffer;
/*    */     //   130: invokevirtual getShort : ()S
/*    */     //   133: istore #10
/*    */     //   135: goto -> 147
/*    */     //   138: aload_0
/*    */     //   139: getfield Ws : Ljava/nio/ByteBuffer;
/*    */     //   142: invokevirtual getInt : ()I
/*    */     //   145: istore #10
/*    */     //   147: iload #10
/*    */     //   149: iconst_2
/*    */     //   150: iand
/*    */     //   151: ifeq -> 160
/*    */     //   154: iconst_1
/*    */     //   155: istore #11
/*    */     //   157: goto -> 163
/*    */     //   160: iconst_0
/*    */     //   161: istore #11
/*    */     //   163: iload #10
/*    */     //   165: aload_0
/*    */     //   166: iload #11
/*    */     //   168: putfield fv : Z
/*    */     //   171: iconst_4
/*    */     //   172: iand
/*    */     //   173: ifeq -> 182
/*    */     //   176: iconst_1
/*    */     //   177: istore #11
/*    */     //   179: goto -> 185
/*    */     //   182: iconst_0
/*    */     //   183: istore #11
/*    */     //   185: iload #10
/*    */     //   187: aload_0
/*    */     //   188: iload #11
/*    */     //   190: putfield YG0 : Z
/*    */     //   193: bipush #8
/*    */     //   195: iand
/*    */     //   196: ifeq -> 210
/*    */     //   199: aload_0
/*    */     //   200: dup
/*    */     //   201: getfield Ws : Ljava/nio/ByteBuffer;
/*    */     //   204: invokevirtual get : ()B
/*    */     //   207: putfield Sf0 : B
/*    */     //   210: iload #10
/*    */     //   212: bipush #16
/*    */     //   214: iand
/*    */     //   215: ifeq -> 232
/*    */     //   218: aload_0
/*    */     //   219: dup
/*    */     //   220: getfield Ws : Ljava/nio/ByteBuffer;
/*    */     //   223: invokevirtual get : ()B
/*    */     //   226: invokestatic f6 : (B)[Lf/DO;
/*    */     //   229: putfield cd0 : [Lf/DO;
/*    */     //   232: iload #10
/*    */     //   234: bipush #32
/*    */     //   236: iand
/*    */     //   237: ifeq -> 254
/*    */     //   240: aload_0
/*    */     //   241: dup
/*    */     //   242: getfield Ws : Ljava/nio/ByteBuffer;
/*    */     //   245: invokevirtual get : ()B
/*    */     //   248: invokestatic Z7 : (B)[Lf/CC0;
/*    */     //   251: putfield OE0 : [Lf/CC0;
/*    */     //   254: iload #10
/*    */     //   256: bipush #64
/*    */     //   258: iand
/*    */     //   259: ifeq -> 409
/*    */     //   262: aload_0
/*    */     //   263: dup
/*    */     //   264: getfield Ws : Ljava/nio/ByteBuffer;
/*    */     //   267: invokevirtual get : ()B
/*    */     //   270: dup
/*    */     //   271: istore #11
/*    */     //   273: anewarray f/Fs
/*    */     //   276: putfield Bk : [Lf/Fs;
/*    */     //   279: iconst_0
/*    */     //   280: istore #12
/*    */     //   282: iload #12
/*    */     //   284: iload #11
/*    */     //   286: if_icmpge -> 409
/*    */     //   289: aload_0
/*    */     //   290: dup
/*    */     //   291: dup
/*    */     //   292: getfield Bk : [Lf/Fs;
/*    */     //   295: iload #12
/*    */     //   297: new f/Fs
/*    */     //   300: dup
/*    */     //   301: astore #13
/*    */     //   303: invokespecial <init> : ()V
/*    */     //   306: aload #13
/*    */     //   308: aastore
/*    */     //   309: getfield Bk : [Lf/Fs;
/*    */     //   312: iload #12
/*    */     //   314: aaload
/*    */     //   315: astore #13
/*    */     //   317: invokevirtual R00 : ()I
/*    */     //   320: iconst_1
/*    */     //   321: if_icmpne -> 330
/*    */     //   324: iconst_1
/*    */     //   325: istore #14
/*    */     //   327: goto -> 333
/*    */     //   330: iconst_0
/*    */     //   331: istore #14
/*    */     //   333: iload #14
/*    */     //   335: aload #13
/*    */     //   337: dup
/*    */     //   338: aload_0
/*    */     //   339: invokevirtual Gc0 : ()I
/*    */     //   342: istore #15
/*    */     //   344: iload #14
/*    */     //   346: putfield DP : Z
/*    */     //   349: iload #15
/*    */     //   351: putfield jt0 : I
/*    */     //   354: ifeq -> 383
/*    */     //   357: aload #13
/*    */     //   359: dup
/*    */     //   360: dup
/*    */     //   361: invokestatic currentTimeMillis : ()J
/*    */     //   364: ldc2_w 1000
/*    */     //   367: ldiv
/*    */     //   368: l2i
/*    */     //   369: putfield zz : I
/*    */     //   372: invokevirtual yy0 : ()I
/*    */     //   375: iconst_1
/*    */     //   376: isub
/*    */     //   377: putfield js0 : I
/*    */     //   380: goto -> 389
/*    */     //   383: aload #13
/*    */     //   385: iconst_m1
/*    */     //   386: putfield js0 : I
/*    */     //   389: aload_0
/*    */     //   390: getfield Bk : [Lf/Fs;
/*    */     //   393: iload #12
/*    */     //   395: aaload
/*    */     //   396: aload_0
/*    */     //   397: invokevirtual Gc0 : ()I
/*    */     //   400: putfield Qe : I
/*    */     //   403: iinc #12, 1
/*    */     //   406: goto -> 282
/*    */     //   409: iload #10
/*    */     //   411: sipush #128
/*    */     //   414: iand
/*    */     //   415: ifeq -> 439
/*    */     //   418: aload_0
/*    */     //   419: dup
/*    */     //   420: dup2
/*    */     //   421: getfield Ws : Ljava/nio/ByteBuffer;
/*    */     //   424: invokevirtual get : ()B
/*    */     //   427: putfield qx0 : B
/*    */     //   430: getfield Ws : Ljava/nio/ByteBuffer;
/*    */     //   433: invokevirtual getShort : ()S
/*    */     //   436: putfield TJ0 : S
/*    */     //   439: iload #10
/*    */     //   441: sipush #256
/*    */     //   444: iand
/*    */     //   445: ifeq -> 462
/*    */     //   448: aload_0
/*    */     //   449: dup
/*    */     //   450: getfield Ws : Ljava/nio/ByteBuffer;
/*    */     //   453: invokevirtual get : ()B
/*    */     //   456: invokestatic com4 : (B)Lf/DK;
/*    */     //   459: putfield ap0 : Lf/DK;
/*    */     //   462: iload #10
/*    */     //   464: sipush #512
/*    */     //   467: iand
/*    */     //   468: ifeq -> 482
/*    */     //   471: aload_0
/*    */     //   472: dup
/*    */     //   473: getfield Ws : Ljava/nio/ByteBuffer;
/*    */     //   476: invokevirtual get : ()B
/*    */     //   479: putfield Np0 : B
/*    */     //   482: iload #10
/*    */     //   484: sipush #1024
/*    */     //   487: iand
/*    */     //   488: ifeq -> 505
/*    */     //   491: aload_0
/*    */     //   492: dup
/*    */     //   493: getfield Ws : Ljava/nio/ByteBuffer;
/*    */     //   496: invokevirtual get : ()B
/*    */     //   499: invokestatic BQ : (B)Lf/aq0;
/*    */     //   502: putfield Un0 : Lf/aq0;
/*    */     //   505: iload #10
/*    */     //   507: sipush #2048
/*    */     //   510: iand
/*    */     //   511: ifeq -> 635
/*    */     //   514: aload_0
/*    */     //   515: dup
/*    */     //   516: dup
/*    */     //   517: getfield Ws : Ljava/nio/ByteBuffer;
/*    */     //   520: invokevirtual get : ()B
/*    */     //   523: invokestatic ep0 : (B)Lf/R00;
/*    */     //   526: putfield TA0 : Lf/R00;
/*    */     //   529: getfield Ws : Ljava/nio/ByteBuffer;
/*    */     //   532: invokevirtual get : ()B
/*    */     //   535: dup
/*    */     //   536: istore #11
/*    */     //   538: ifne -> 549
/*    */     //   541: getstatic f/hR.ZF : [Lf/hR;
/*    */     //   544: astore #11
/*    */     //   546: goto -> 629
/*    */     //   549: getstatic f/hR.Gg : Lf/hR;
/*    */     //   552: pop
/*    */     //   553: new java/util/ArrayList
/*    */     //   556: dup
/*    */     //   557: astore #12
/*    */     //   559: invokespecial <init> : ()V
/*    */     //   562: getstatic f/hR.Tt0 : [Lf/hR;
/*    */     //   565: dup
/*    */     //   566: astore #13
/*    */     //   568: arraylength
/*    */     //   569: istore #14
/*    */     //   571: iconst_0
/*    */     //   572: istore #15
/*    */     //   574: iload #15
/*    */     //   576: iload #14
/*    */     //   578: if_icmpge -> 615
/*    */     //   581: iload #11
/*    */     //   583: aload #13
/*    */     //   585: iload #15
/*    */     //   587: aaload
/*    */     //   588: dup
/*    */     //   589: astore #16
/*    */     //   591: getfield dL : B
/*    */     //   594: iconst_1
/*    */     //   595: swap
/*    */     //   596: ishl
/*    */     //   597: iand
/*    */     //   598: ifeq -> 609
/*    */     //   601: aload #12
/*    */     //   603: aload #16
/*    */     //   605: invokevirtual add : (Ljava/lang/Object;)Z
/*    */     //   608: pop
/*    */     //   609: iinc #15, 1
/*    */     //   612: goto -> 574
/*    */     //   615: aload #12
/*    */     //   617: iconst_0
/*    */     //   618: anewarray f/hR
/*    */     //   621: invokevirtual toArray : ([Ljava/lang/Object;)[Ljava/lang/Object;
/*    */     //   624: checkcast [Lf/hR;
/*    */     //   627: astore #11
/*    */     //   629: aload_0
/*    */     //   630: aload #11
/*    */     //   632: putfield X50 : [Lf/hR;
/*    */     //   635: iload #10
/*    */     //   637: sipush #4096
/*    */     //   640: iand
/*    */     //   641: ifeq -> 655
/*    */     //   644: aload_0
/*    */     //   645: dup
/*    */     //   646: getfield Ws : Ljava/nio/ByteBuffer;
/*    */     //   649: invokevirtual getInt : ()I
/*    */     //   652: putfield OL : I
/*    */     //   655: iload #10
/*    */     //   657: sipush #8192
/*    */     //   660: iand
/*    */     //   661: ifeq -> 670
/*    */     //   664: iconst_1
/*    */     //   665: istore #11
/*    */     //   667: goto -> 673
/*    */     //   670: iconst_0
/*    */     //   671: istore #11
/*    */     //   673: iload #10
/*    */     //   675: aload_0
/*    */     //   676: iload #11
/*    */     //   678: putfield NO : Z
/*    */     //   681: sipush #16384
/*    */     //   684: iand
/*    */     //   685: ifeq -> 699
/*    */     //   688: aload_0
/*    */     //   689: getfield Ws : Ljava/nio/ByteBuffer;
/*    */     //   692: invokevirtual get : ()B
/*    */     //   695: invokestatic a8 : (B)Lf/m9;
/*    */     //   698: pop
/*    */     //   699: iload #10
/*    */     //   701: ldc 32768
/*    */     //   703: iand
/*    */     //   704: ifeq -> 718
/*    */     //   707: aload_0
/*    */     //   708: dup
/*    */     //   709: getfield Ws : Ljava/nio/ByteBuffer;
/*    */     //   712: invokevirtual get : ()B
/*    */     //   715: putfield Rt0 : B
/*    */     //   718: aload #8
/*    */     //   720: iconst_0
/*    */     //   721: istore #10
/*    */     //   723: aconst_null
/*    */     //   724: astore #11
/*    */     //   726: getfield fQ : Z
/*    */     //   729: ifeq -> 859
/*    */     //   732: aload_0
/*    */     //   733: getfield Ws : Ljava/nio/ByteBuffer;
/*    */     //   736: invokevirtual get : ()B
/*    */     //   739: iconst_1
/*    */     //   740: if_icmpne -> 749
/*    */     //   743: iconst_1
/*    */     //   744: istore #10
/*    */     //   746: goto -> 752
/*    */     //   749: iconst_0
/*    */     //   750: istore #10
/*    */     //   752: aload_0
/*    */     //   753: getfield Ws : Ljava/nio/ByteBuffer;
/*    */     //   756: invokevirtual get : ()B
/*    */     //   759: ifeq -> 859
/*    */     //   762: aload_0
/*    */     //   763: new f/eq0
/*    */     //   766: dup
/*    */     //   767: astore #11
/*    */     //   769: invokespecial <init> : ()V
/*    */     //   772: getfield Ws : Ljava/nio/ByteBuffer;
/*    */     //   775: invokevirtual get : ()B
/*    */     //   778: iconst_1
/*    */     //   779: if_icmpne -> 788
/*    */     //   782: iconst_1
/*    */     //   783: istore #12
/*    */     //   785: goto -> 791
/*    */     //   788: iconst_0
/*    */     //   789: istore #12
/*    */     //   791: iload #12
/*    */     //   793: aload #11
/*    */     //   795: dup
/*    */     //   796: dup
/*    */     //   797: aload_0
/*    */     //   798: dup
/*    */     //   799: invokevirtual Gc0 : ()I
/*    */     //   802: istore #13
/*    */     //   804: invokevirtual Gc0 : ()I
/*    */     //   807: istore #14
/*    */     //   809: iload #12
/*    */     //   811: putfield wm0 : Z
/*    */     //   814: iload #13
/*    */     //   816: putfield QE : I
/*    */     //   819: iload #14
/*    */     //   821: putfield tI0 : I
/*    */     //   824: ifeq -> 853
/*    */     //   827: aload #11
/*    */     //   829: dup
/*    */     //   830: dup
/*    */     //   831: invokestatic currentTimeMillis : ()J
/*    */     //   834: ldc2_w 1000
/*    */     //   837: ldiv
/*    */     //   838: l2i
/*    */     //   839: putfield n8 : I
/*    */     //   842: invokevirtual re : ()I
/*    */     //   845: iconst_1
/*    */     //   846: isub
/*    */     //   847: putfield F70 : I
/*    */     //   850: goto -> 859
/*    */     //   853: aload #11
/*    */     //   855: iconst_m1
/*    */     //   856: putfield F70 : I
/*    */     //   859: aload_0
/*    */     //   860: iload_1
/*    */     //   861: aload_0
/*    */     //   862: iload_1
/*    */     //   863: anewarray [Lf/hm0;
/*    */     //   866: putfield kj0 : [[Lf/hm0;
/*    */     //   869: anewarray f/QZ
/*    */     //   872: putfield nL : [Lf/QZ;
/*    */     //   875: iconst_0
/*    */     //   876: istore_1
/*    */     //   877: iload_1
/*    */     //   878: aload_0
/*    */     //   879: getfield kj0 : [[Lf/hm0;
/*    */     //   882: arraylength
/*    */     //   883: if_icmpge -> 2110
/*    */     //   886: aload_0
/*    */     //   887: dup
/*    */     //   888: getfield nL : [Lf/QZ;
/*    */     //   891: iload_1
/*    */     //   892: aload_0
/*    */     //   893: iload_1
/*    */     //   894: invokevirtual A40 : (B)Lf/QZ;
/*    */     //   897: aastore
/*    */     //   898: getfield nL : [Lf/QZ;
/*    */     //   901: iload_1
/*    */     //   902: aaload
/*    */     //   903: invokevirtual PN : ()Lf/ET;
/*    */     //   906: getstatic f/ET.R40 : Lf/ET;
/*    */     //   909: if_acmpne -> 926
/*    */     //   912: aload_0
/*    */     //   913: getfield kj0 : [[Lf/hm0;
/*    */     //   916: iload_1
/*    */     //   917: bipush #6
/*    */     //   919: anewarray f/hm0
/*    */     //   922: aastore
/*    */     //   923: goto -> 2102
/*    */     //   926: aload #8
/*    */     //   928: getstatic f/Mn.VK : Lf/Mn;
/*    */     //   931: if_acmpeq -> 1932
/*    */     //   934: aload #8
/*    */     //   936: getstatic f/Mn.JY : Lf/Mn;
/*    */     //   939: if_acmpne -> 950
/*    */     //   942: iload_1
/*    */     //   943: iload_2
/*    */     //   944: if_icmpeq -> 950
/*    */     //   947: goto -> 1932
/*    */     //   950: aload_0
/*    */     //   951: getfield kj0 : [[Lf/hm0;
/*    */     //   954: iload_1
/*    */     //   955: aload #4
/*    */     //   957: iload_1
/*    */     //   958: invokevirtual coM9 : (B)B
/*    */     //   961: anewarray f/hm0
/*    */     //   964: aastore
/*    */     //   965: iconst_0
/*    */     //   966: istore #12
/*    */     //   968: iload #12
/*    */     //   970: aload_0
/*    */     //   971: getfield kj0 : [[Lf/hm0;
/*    */     //   974: iload_1
/*    */     //   975: aaload
/*    */     //   976: dup
/*    */     //   977: astore #13
/*    */     //   979: arraylength
/*    */     //   980: if_icmpge -> 2102
/*    */     //   983: aload_0
/*    */     //   984: dup
/*    */     //   985: getfield bf : Lf/rK;
/*    */     //   988: astore #14
/*    */     //   990: getfield Ws : Ljava/nio/ByteBuffer;
/*    */     //   993: invokevirtual getInt : ()I
/*    */     //   996: dup
/*    */     //   997: istore #15
/*    */     //   999: ifne -> 1008
/*    */     //   1002: aconst_null
/*    */     //   1003: astore #14
/*    */     //   1005: goto -> 1915
/*    */     //   1008: aload_0
/*    */     //   1009: new f/hm0
/*    */     //   1012: dup
/*    */     //   1013: astore #16
/*    */     //   1015: iload_1
/*    */     //   1016: aload_0
/*    */     //   1017: dup
/*    */     //   1018: dup
/*    */     //   1019: dup2
/*    */     //   1020: dup2
/*    */     //   1021: dup2
/*    */     //   1022: dup2
/*    */     //   1023: dup2
/*    */     //   1024: getfield Ws : Ljava/nio/ByteBuffer;
/*    */     //   1027: invokevirtual getShort : ()S
/*    */     //   1030: istore #17
/*    */     //   1032: getfield Ws : Ljava/nio/ByteBuffer;
/*    */     //   1035: invokevirtual get : ()B
/*    */     //   1038: istore #18
/*    */     //   1040: invokevirtual au : ()Ljava/lang/String;
/*    */     //   1043: astore #19
/*    */     //   1045: getfield Ws : Ljava/nio/ByteBuffer;
/*    */     //   1048: invokevirtual get : ()B
/*    */     //   1051: istore #20
/*    */     //   1053: getfield Ws : Ljava/nio/ByteBuffer;
/*    */     //   1056: invokevirtual get : ()B
/*    */     //   1059: istore #21
/*    */     //   1061: getfield Ws : Ljava/nio/ByteBuffer;
/*    */     //   1064: invokevirtual get : ()B
/*    */     //   1067: istore #22
/*    */     //   1069: getfield Ws : Ljava/nio/ByteBuffer;
/*    */     //   1072: invokevirtual getShort : ()S
/*    */     //   1075: istore #23
/*    */     //   1077: getfield Ws : Ljava/nio/ByteBuffer;
/*    */     //   1080: invokevirtual get : ()B
/*    */     //   1083: istore #24
/*    */     //   1085: getfield Ws : Ljava/nio/ByteBuffer;
/*    */     //   1088: invokevirtual get : ()B
/*    */     //   1091: invokestatic qq : (B)Lf/mA;
/*    */     //   1094: astore #25
/*    */     //   1096: getfield Ws : Ljava/nio/ByteBuffer;
/*    */     //   1099: invokevirtual getShort : ()S
/*    */     //   1102: istore #26
/*    */     //   1104: getfield Ws : Ljava/nio/ByteBuffer;
/*    */     //   1107: invokevirtual getShort : ()S
/*    */     //   1110: istore #27
/*    */     //   1112: getfield Ws : Ljava/nio/ByteBuffer;
/*    */     //   1115: invokevirtual get : ()B
/*    */     //   1118: istore #28
/*    */     //   1120: getfield Ws : Ljava/nio/ByteBuffer;
/*    */     //   1123: invokevirtual get : ()B
/*    */     //   1126: istore #29
/*    */     //   1128: iload #12
/*    */     //   1130: iload #15
/*    */     //   1132: iload #17
/*    */     //   1134: iload #18
/*    */     //   1136: aload #19
/*    */     //   1138: iload #20
/*    */     //   1140: iload #21
/*    */     //   1142: iload #22
/*    */     //   1144: iload #23
/*    */     //   1146: iload #24
/*    */     //   1148: aload #25
/*    */     //   1150: iload #26
/*    */     //   1152: iload #27
/*    */     //   1154: iload #28
/*    */     //   1156: iload #29
/*    */     //   1158: invokespecial <init> : (BBISBLjava/lang/String;BBBSBLf/mA;SSBB)V
/*    */     //   1161: getfield Ws : Ljava/nio/ByteBuffer;
/*    */     //   1164: invokevirtual getInt : ()I
/*    */     //   1167: dup
/*    */     //   1168: istore #15
/*    */     //   1170: iconst_1
/*    */     //   1171: iand
/*    */     //   1172: ifeq -> 1181
/*    */     //   1175: iconst_1
/*    */     //   1176: istore #17
/*    */     //   1178: goto -> 1184
/*    */     //   1181: iconst_0
/*    */     //   1182: istore #17
/*    */     //   1184: aload #16
/*    */     //   1186: dup
/*    */     //   1187: iload #17
/*    */     //   1189: putfield A0 : Z
/*    */     //   1192: getfield eq0 : Lf/uT;
/*    */     //   1195: ifnull -> 1213
/*    */     //   1198: iload #17
/*    */     //   1200: ifne -> 1213
/*    */     //   1203: aload #16
/*    */     //   1205: dup
/*    */     //   1206: aconst_null
/*    */     //   1207: putfield eq0 : Lf/uT;
/*    */     //   1210: invokevirtual yL0 : ()V
/*    */     //   1213: iload #15
/*    */     //   1215: iconst_4
/*    */     //   1216: iand
/*    */     //   1217: ifeq -> 1226
/*    */     //   1220: iconst_1
/*    */     //   1221: istore #17
/*    */     //   1223: goto -> 1229
/*    */     //   1226: iconst_0
/*    */     //   1227: istore #17
/*    */     //   1229: iload #15
/*    */     //   1231: aload #16
/*    */     //   1233: iload #17
/*    */     //   1235: putfield f8 : Z
/*    */     //   1238: iconst_2
/*    */     //   1239: iand
/*    */     //   1240: ifeq -> 1249
/*    */     //   1243: iconst_1
/*    */     //   1244: istore #17
/*    */     //   1246: goto -> 1252
/*    */     //   1249: iconst_0
/*    */     //   1250: istore #17
/*    */     //   1252: iload #15
/*    */     //   1254: aload #16
/*    */     //   1256: iload #17
/*    */     //   1258: putfield cOn : Z
/*    */     //   1261: bipush #8
/*    */     //   1263: iand
/*    */     //   1264: dup
/*    */     //   1265: istore #17
/*    */     //   1267: ifeq -> 1276
/*    */     //   1270: iconst_1
/*    */     //   1271: istore #18
/*    */     //   1273: goto -> 1279
/*    */     //   1276: iconst_0
/*    */     //   1277: istore #18
/*    */     //   1279: iload #15
/*    */     //   1281: aload #16
/*    */     //   1283: iload #18
/*    */     //   1285: putfield Gt0 : Z
/*    */     //   1288: bipush #16
/*    */     //   1290: iand
/*    */     //   1291: ifeq -> 1300
/*    */     //   1294: iconst_1
/*    */     //   1295: istore #18
/*    */     //   1297: goto -> 1303
/*    */     //   1300: iconst_0
/*    */     //   1301: istore #18
/*    */     //   1303: iload #15
/*    */     //   1305: aload #16
/*    */     //   1307: iload #18
/*    */     //   1309: putfield D5 : Z
/*    */     //   1312: sipush #1024
/*    */     //   1315: iand
/*    */     //   1316: ifeq -> 1325
/*    */     //   1319: iconst_1
/*    */     //   1320: istore #18
/*    */     //   1322: goto -> 1328
/*    */     //   1325: iconst_0
/*    */     //   1326: istore #18
/*    */     //   1328: iload #15
/*    */     //   1330: aload #16
/*    */     //   1332: iload #18
/*    */     //   1334: putfield N3 : Z
/*    */     //   1337: sipush #2048
/*    */     //   1340: iand
/*    */     //   1341: ifeq -> 1350
/*    */     //   1344: iconst_1
/*    */     //   1345: istore #18
/*    */     //   1347: goto -> 1353
/*    */     //   1350: iconst_0
/*    */     //   1351: istore #18
/*    */     //   1353: iload #15
/*    */     //   1355: aload #16
/*    */     //   1357: iload #18
/*    */     //   1359: putfield c : Z
/*    */     //   1362: sipush #4096
/*    */     //   1365: iand
/*    */     //   1366: ifeq -> 1375
/*    */     //   1369: iconst_1
/*    */     //   1370: istore #18
/*    */     //   1372: goto -> 1378
/*    */     //   1375: iconst_0
/*    */     //   1376: istore #18
/*    */     //   1378: iload #17
/*    */     //   1380: aload #16
/*    */     //   1382: iload #18
/*    */     //   1384: putfield Eg0 : Z
/*    */     //   1387: ifeq -> 1402
/*    */     //   1390: aload #16
/*    */     //   1392: aload_0
/*    */     //   1393: getfield Ws : Ljava/nio/ByteBuffer;
/*    */     //   1396: invokevirtual getShort : ()S
/*    */     //   1399: putfield eH0 : S
/*    */     //   1402: iload #15
/*    */     //   1404: bipush #32
/*    */     //   1406: iand
/*    */     //   1407: ifeq -> 1422
/*    */     //   1410: aload #16
/*    */     //   1412: aload_0
/*    */     //   1413: getfield Ws : Ljava/nio/ByteBuffer;
/*    */     //   1416: invokevirtual getShort : ()S
/*    */     //   1419: putfield yj0 : S
/*    */     //   1422: iload #15
/*    */     //   1424: bipush #64
/*    */     //   1426: iand
/*    */     //   1427: ifeq -> 1442
/*    */     //   1430: aload #16
/*    */     //   1432: aload_0
/*    */     //   1433: getfield Ws : Ljava/nio/ByteBuffer;
/*    */     //   1436: invokevirtual getShort : ()S
/*    */     //   1439: putfield my : S
/*    */     //   1442: iload #15
/*    */     //   1444: sipush #128
/*    */     //   1447: iand
/*    */     //   1448: ifeq -> 1478
/*    */     //   1451: aload #16
/*    */     //   1453: dup
/*    */     //   1454: aload_0
/*    */     //   1455: getfield Ws : Ljava/nio/ByteBuffer;
/*    */     //   1458: invokevirtual getShort : ()S
/*    */     //   1461: aload_0
/*    */     //   1462: getfield Ws : Ljava/nio/ByteBuffer;
/*    */     //   1465: invokevirtual getShort : ()S
/*    */     //   1468: istore #17
/*    */     //   1470: putfield zD0 : S
/*    */     //   1473: iload #17
/*    */     //   1475: putfield xO : S
/*    */     //   1478: iload #15
/*    */     //   1480: sipush #256
/*    */     //   1483: iand
/*    */     //   1484: ifeq -> 1526
/*    */     //   1487: iconst_4
/*    */     //   1488: newarray short
/*    */     //   1490: astore #17
/*    */     //   1492: iconst_0
/*    */     //   1493: istore #18
/*    */     //   1495: iload #18
/*    */     //   1497: iconst_4
/*    */     //   1498: if_icmpge -> 1519
/*    */     //   1501: aload #17
/*    */     //   1503: iload #18
/*    */     //   1505: aload_0
/*    */     //   1506: getfield Ws : Ljava/nio/ByteBuffer;
/*    */     //   1509: invokevirtual getShort : ()S
/*    */     //   1512: sastore
/*    */     //   1513: iinc #18, 1
/*    */     //   1516: goto -> 1495
/*    */     //   1519: aload #16
/*    */     //   1521: aload #17
/*    */     //   1523: putfield cM0 : [S
/*    */     //   1526: iload #15
/*    */     //   1528: sipush #512
/*    */     //   1531: iand
/*    */     //   1532: ifeq -> 1652
/*    */     //   1535: aload_0
/*    */     //   1536: dup
/*    */     //   1537: getfield Ws : Ljava/nio/ByteBuffer;
/*    */     //   1540: invokevirtual getShort : ()S
/*    */     //   1543: istore #17
/*    */     //   1545: getfield Ws : Ljava/nio/ByteBuffer;
/*    */     //   1548: invokevirtual get : ()B
/*    */     //   1551: istore #18
/*    */     //   1553: iconst_4
/*    */     //   1554: newarray short
/*    */     //   1556: astore #19
/*    */     //   1558: iconst_4
/*    */     //   1559: newarray byte
/*    */     //   1561: astore #20
/*    */     //   1563: iconst_0
/*    */     //   1564: istore #21
/*    */     //   1566: iload #21
/*    */     //   1568: iconst_4
/*    */     //   1569: if_icmpge -> 1602
/*    */     //   1572: aload #20
/*    */     //   1574: iload #21
/*    */     //   1576: aload_0
/*    */     //   1577: aload #19
/*    */     //   1579: iload #21
/*    */     //   1581: aload_0
/*    */     //   1582: getfield Ws : Ljava/nio/ByteBuffer;
/*    */     //   1585: invokevirtual getShort : ()S
/*    */     //   1588: sastore
/*    */     //   1589: getfield Ws : Ljava/nio/ByteBuffer;
/*    */     //   1592: invokevirtual get : ()B
/*    */     //   1595: bastore
/*    */     //   1596: iinc #21, 1
/*    */     //   1599: goto -> 1566
/*    */     //   1602: aload #16
/*    */     //   1604: dup
/*    */     //   1605: iload #17
/*    */     //   1607: aload_0
/*    */     //   1608: dup
/*    */     //   1609: dup
/*    */     //   1610: getfield Ws : Ljava/nio/ByteBuffer;
/*    */     //   1613: invokevirtual getShort : ()S
/*    */     //   1616: istore #17
/*    */     //   1618: getfield Ws : Ljava/nio/ByteBuffer;
/*    */     //   1621: invokevirtual get : ()B
/*    */     //   1624: istore #21
/*    */     //   1626: getfield Ws : Ljava/nio/ByteBuffer;
/*    */     //   1629: invokevirtual get : ()B
/*    */     //   1632: istore #22
/*    */     //   1634: iload #18
/*    */     //   1636: aload #19
/*    */     //   1638: aload #20
/*    */     //   1640: iload #21
/*    */     //   1642: iload #22
/*    */     //   1644: invokevirtual x10 : (SB[S[BBB)V
/*    */     //   1647: iload #17
/*    */     //   1649: putfield BC : S
/*    */     //   1652: iload #15
/*    */     //   1654: sipush #8192
/*    */     //   1657: iand
/*    */     //   1658: ifeq -> 1691
/*    */     //   1661: aload #16
/*    */     //   1663: aload_0
/*    */     //   1664: aload #16
/*    */     //   1666: aload_0
/*    */     //   1667: getfield Ws : Ljava/nio/ByteBuffer;
/*    */     //   1670: invokevirtual get : ()B
/*    */     //   1673: invokestatic Gt0 : (B)Lf/Ht0;
/*    */     //   1676: putfield lPt1 : Lf/Ht0;
/*    */     //   1679: getfield Ws : Ljava/nio/ByteBuffer;
/*    */     //   1682: invokevirtual get : ()B
/*    */     //   1685: invokestatic Gt0 : (B)Lf/Ht0;
/*    */     //   1688: putfield se : Lf/Ht0;
/*    */     //   1691: iload #15
/*    */     //   1693: sipush #16384
/*    */     //   1696: iand
/*    */     //   1697: ifeq -> 1712
/*    */     //   1700: aload #16
/*    */     //   1702: aload_0
/*    */     //   1703: getfield Ws : Ljava/nio/ByteBuffer;
/*    */     //   1706: invokevirtual getShort : ()S
/*    */     //   1709: putfield BC : S
/*    */     //   1712: iload #15
/*    */     //   1714: ldc_w 65536
/*    */     //   1717: iand
/*    */     //   1718: ifeq -> 1733
/*    */     //   1721: aload #16
/*    */     //   1723: aload_0
/*    */     //   1724: getfield Ws : Ljava/nio/ByteBuffer;
/*    */     //   1727: invokevirtual getShort : ()S
/*    */     //   1730: putfield KT : S
/*    */     //   1733: iload #15
/*    */     //   1735: ldc_w 131072
/*    */     //   1738: iand
/*    */     //   1739: ifeq -> 1754
/*    */     //   1742: aload #16
/*    */     //   1744: aload_0
/*    */     //   1745: getfield Ws : Ljava/nio/ByteBuffer;
/*    */     //   1748: invokevirtual getShort : ()S
/*    */     //   1751: invokevirtual gG0 : (S)V
/*    */     //   1754: iload #15
/*    */     //   1756: ldc_w 262144
/*    */     //   1759: iand
/*    */     //   1760: ifeq -> 1775
/*    */     //   1763: aload #16
/*    */     //   1765: getfield K0 : Lf/jd0;
/*    */     //   1768: getfield ta : Lf/Q90;
/*    */     //   1771: iconst_1
/*    */     //   1772: putfield Jg : Z
/*    */     //   1775: iload #15
/*    */     //   1777: ldc 32768
/*    */     //   1779: iand
/*    */     //   1780: ifeq -> 1789
/*    */     //   1783: aload #16
/*    */     //   1785: iconst_0
/*    */     //   1786: putfield zd : Z
/*    */     //   1789: aload_0
/*    */     //   1790: getfield Ws : Ljava/nio/ByteBuffer;
/*    */     //   1793: invokevirtual getInt : ()I
/*    */     //   1796: invokestatic ua0 : (I)[B
/*    */     //   1799: astore #15
/*    */     //   1801: iconst_0
/*    */     //   1802: istore #17
/*    */     //   1804: iload #17
/*    */     //   1806: aload #15
/*    */     //   1808: arraylength
/*    */     //   1809: if_icmpge -> 1839
/*    */     //   1812: aload #16
/*    */     //   1814: aload #15
/*    */     //   1816: iload #17
/*    */     //   1818: getstatic f/hR.Tt0 : [Lf/hR;
/*    */     //   1821: iload #17
/*    */     //   1823: aaload
/*    */     //   1824: astore #18
/*    */     //   1826: baload
/*    */     //   1827: aload #18
/*    */     //   1829: swap
/*    */     //   1830: invokevirtual aJ : (Lf/hR;B)V
/*    */     //   1833: iinc #17, 1
/*    */     //   1836: goto -> 1804
/*    */     //   1839: aload #14
/*    */     //   1841: getstatic f/rK.Az : Lf/rK;
/*    */     //   1844: if_acmpne -> 1911
/*    */     //   1847: aload_0
/*    */     //   1848: aload #16
/*    */     //   1850: dup
/*    */     //   1851: dup2
/*    */     //   1852: getfield Ui0 : Lf/kn0;
/*    */     //   1855: aload_0
/*    */     //   1856: getfield Ws : Ljava/nio/ByteBuffer;
/*    */     //   1859: invokevirtual get : ()B
/*    */     //   1862: putfield x80 : B
/*    */     //   1865: getfield Ui0 : Lf/kn0;
/*    */     //   1868: aload_0
/*    */     //   1869: getfield Ws : Ljava/nio/ByteBuffer;
/*    */     //   1872: invokevirtual get : ()B
/*    */     //   1875: putfield dw : B
/*    */     //   1878: getfield Ui0 : Lf/kn0;
/*    */     //   1881: aload_0
/*    */     //   1882: getfield Ws : Ljava/nio/ByteBuffer;
/*    */     //   1885: invokevirtual get : ()B
/*    */     //   1888: putfield pg : B
/*    */     //   1891: getfield Ui0 : Lf/kn0;
/*    */     //   1894: aload_0
/*    */     //   1895: getfield Ws : Ljava/nio/ByteBuffer;
/*    */     //   1898: invokevirtual getShort : ()S
/*    */     //   1901: putfield q70 : S
/*    */     //   1904: getfield Ws : Ljava/nio/ByteBuffer;
/*    */     //   1907: invokevirtual getShort : ()S
/*    */     //   1910: pop
/*    */     //   1911: aload #16
/*    */     //   1913: astore #14
/*    */     //   1915: iload #12
/*    */     //   1917: aload #13
/*    */     //   1919: iload #12
/*    */     //   1921: aload #14
/*    */     //   1923: aastore
/*    */     //   1924: iconst_1
/*    */     //   1925: iadd
/*    */     //   1926: i2b
/*    */     //   1927: istore #12
/*    */     //   1929: goto -> 968
/*    */     //   1932: aload_0
/*    */     //   1933: getfield kj0 : [[Lf/hm0;
/*    */     //   1936: iload_1
/*    */     //   1937: bipush #6
/*    */     //   1939: anewarray f/hm0
/*    */     //   1942: aastore
/*    */     //   1943: iconst_0
/*    */     //   1944: istore #12
/*    */     //   1946: iload #12
/*    */     //   1948: bipush #6
/*    */     //   1950: if_icmpge -> 2102
/*    */     //   1953: aload_0
/*    */     //   1954: dup
/*    */     //   1955: getfield kj0 : [[Lf/hm0;
/*    */     //   1958: iload_1
/*    */     //   1959: aaload
/*    */     //   1960: astore #13
/*    */     //   1962: getfield Ws : Ljava/nio/ByteBuffer;
/*    */     //   1965: invokevirtual get : ()B
/*    */     //   1968: dup
/*    */     //   1969: istore #14
/*    */     //   1971: ifne -> 1980
/*    */     //   1974: aconst_null
/*    */     //   1975: astore #14
/*    */     //   1977: goto -> 2085
/*    */     //   1980: new f/hm0
/*    */     //   1983: dup
/*    */     //   1984: astore #15
/*    */     //   1986: iload_1
/*    */     //   1987: aload_0
/*    */     //   1988: dup
/*    */     //   1989: dup2
/*    */     //   1990: dup2
/*    */     //   1991: iload #14
/*    */     //   1993: sipush #255
/*    */     //   1996: iand
/*    */     //   1997: istore #14
/*    */     //   1999: getfield Ws : Ljava/nio/ByteBuffer;
/*    */     //   2002: invokevirtual getShort : ()S
/*    */     //   2005: istore #16
/*    */     //   2007: getfield Ws : Ljava/nio/ByteBuffer;
/*    */     //   2010: invokevirtual get : ()B
/*    */     //   2013: istore #17
/*    */     //   2015: getfield Ws : Ljava/nio/ByteBuffer;
/*    */     //   2018: invokevirtual get : ()B
/*    */     //   2021: istore #18
/*    */     //   2023: getfield Ws : Ljava/nio/ByteBuffer;
/*    */     //   2026: invokevirtual get : ()B
/*    */     //   2029: istore #19
/*    */     //   2031: getfield Ws : Ljava/nio/ByteBuffer;
/*    */     //   2034: invokevirtual getShort : ()S
/*    */     //   2037: istore #20
/*    */     //   2039: getstatic f/mA.uZ : Lf/mA;
/*    */     //   2042: astore #21
/*    */     //   2044: getfield Ws : Ljava/nio/ByteBuffer;
/*    */     //   2047: invokevirtual get : ()B
/*    */     //   2050: istore #22
/*    */     //   2052: iload #12
/*    */     //   2054: iload #14
/*    */     //   2056: iload #16
/*    */     //   2058: iload #17
/*    */     //   2060: ldc_w ''
/*    */     //   2063: iconst_0
/*    */     //   2064: iload #18
/*    */     //   2066: iload #19
/*    */     //   2068: iload #20
/*    */     //   2070: iconst_1
/*    */     //   2071: aload #21
/*    */     //   2073: iconst_1
/*    */     //   2074: iconst_1
/*    */     //   2075: iconst_0
/*    */     //   2076: iload #22
/*    */     //   2078: invokespecial <init> : (BBISBLjava/lang/String;BBBSBLf/mA;SSBB)V
/*    */     //   2081: aload #15
/*    */     //   2083: astore #14
/*    */     //   2085: iload #12
/*    */     //   2087: aload #13
/*    */     //   2089: iload #12
/*    */     //   2091: aload #14
/*    */     //   2093: aastore
/*    */     //   2094: iconst_1
/*    */     //   2095: iadd
/*    */     //   2096: i2b
/*    */     //   2097: istore #12
/*    */     //   2099: goto -> 1946
/*    */     //   2102: iload_1
/*    */     //   2103: iconst_1
/*    */     //   2104: iadd
/*    */     //   2105: i2b
/*    */     //   2106: istore_1
/*    */     //   2107: goto -> 877
/*    */     //   2110: aload_0
/*    */     //   2111: getfield bf : Lf/rK;
/*    */     //   2114: invokevirtual ordinal : ()I
/*    */     //   2117: iconst_4
/*    */     //   2118: if_icmpeq -> 3408
/*    */     //   2121: aload_0
/*    */     //   2122: dup
/*    */     //   2123: new f/Gp0
/*    */     //   2126: dup
/*    */     //   2127: aload #4
/*    */     //   2129: aload_0
/*    */     //   2130: dup
/*    */     //   2131: dup
/*    */     //   2132: dup2
/*    */     //   2133: dup2
/*    */     //   2134: dup2
/*    */     //   2135: dup2
/*    */     //   2136: dup2
/*    */     //   2137: dup2
/*    */     //   2138: dup2
/*    */     //   2139: getfield Sf0 : B
/*    */     //   2142: istore_1
/*    */     //   2143: getfield Np0 : B
/*    */     //   2146: istore #4
/*    */     //   2148: getfield bf : Lf/rK;
/*    */     //   2151: astore #12
/*    */     //   2153: getfield qx0 : B
/*    */     //   2156: istore #13
/*    */     //   2158: getfield TJ0 : S
/*    */     //   2161: istore #14
/*    */     //   2163: getfield Un0 : Lf/aq0;
/*    */     //   2166: astore #15
/*    */     //   2168: getfield fv : Z
/*    */     //   2171: istore #16
/*    */     //   2173: getfield l00 : B
/*    */     //   2176: istore #17
/*    */     //   2178: getfield tc : B
/*    */     //   2181: istore #18
/*    */     //   2183: getfield Rt0 : B
/*    */     //   2186: istore #19
/*    */     //   2188: getfield cd0 : [Lf/DO;
/*    */     //   2191: astore #20
/*    */     //   2193: getfield OE0 : [Lf/CC0;
/*    */     //   2196: astore #21
/*    */     //   2198: getfield TA0 : Lf/R00;
/*    */     //   2201: astore #22
/*    */     //   2203: getfield X50 : [Lf/hR;
/*    */     //   2206: astore #23
/*    */     //   2208: getfield nL : [Lf/QZ;
/*    */     //   2211: astore #24
/*    */     //   2213: getfield kj0 : [[Lf/hm0;
/*    */     //   2216: astore #25
/*    */     //   2218: getfield YG0 : Z
/*    */     //   2221: istore #26
/*    */     //   2223: aload #8
/*    */     //   2225: iload #6
/*    */     //   2227: iload_1
/*    */     //   2228: iload #4
/*    */     //   2230: aload #5
/*    */     //   2232: aload #12
/*    */     //   2234: iload #13
/*    */     //   2236: iload #14
/*    */     //   2238: aload #15
/*    */     //   2240: iload #16
/*    */     //   2242: iload #17
/*    */     //   2244: iload #18
/*    */     //   2246: iload #19
/*    */     //   2248: aload #20
/*    */     //   2250: aload #21
/*    */     //   2252: aload #22
/*    */     //   2254: aload #23
/*    */     //   2256: iload_2
/*    */     //   2257: iload_3
/*    */     //   2258: iload #9
/*    */     //   2260: aload #24
/*    */     //   2262: aload #25
/*    */     //   2264: iload #26
/*    */     //   2266: invokespecial <init> : (Lf/ky;Lf/Mn;IBBLf/yi;Lf/rK;BSLf/aq0;ZBBB[Lf/DO;[Lf/CC0;Lf/R00;[Lf/hR;BBZ[Lf/QZ;[[Lf/hm0;Z)V
/*    */     //   2269: putfield wt : Lf/Gp0;
/*    */     //   2272: getfield Ws : Ljava/nio/ByteBuffer;
/*    */     //   2275: invokevirtual get : ()B
/*    */     //   2278: dup
/*    */     //   2279: istore_1
/*    */     //   2280: iconst_1
/*    */     //   2281: iand
/*    */     //   2282: ifeq -> 2299
/*    */     //   2285: aload_0
/*    */     //   2286: dup
/*    */     //   2287: getfield Ws : Ljava/nio/ByteBuffer;
/*    */     //   2290: invokevirtual get : ()B
/*    */     //   2293: invokestatic s2 : (B)Lf/Mx;
/*    */     //   2296: putfield xm : Lf/Mx;
/*    */     //   2299: iload_1
/*    */     //   2300: iconst_2
/*    */     //   2301: iand
/*    */     //   2302: ifeq -> 2313
/*    */     //   2305: aload_0
/*    */     //   2306: getfield wt : Lf/Gp0;
/*    */     //   2309: invokevirtual getClass : ()Ljava/lang/Class;
/*    */     //   2312: pop
/*    */     //   2313: iload_1
/*    */     //   2314: iconst_4
/*    */     //   2315: iand
/*    */     //   2316: ifeq -> 2327
/*    */     //   2319: aload_0
/*    */     //   2320: getfield wt : Lf/Gp0;
/*    */     //   2323: invokevirtual getClass : ()Ljava/lang/Class;
/*    */     //   2326: pop
/*    */     //   2327: iload_1
/*    */     //   2328: bipush #8
/*    */     //   2330: iand
/*    */     //   2331: ifeq -> 2342
/*    */     //   2334: aload_0
/*    */     //   2335: getfield wt : Lf/Gp0;
/*    */     //   2338: iconst_1
/*    */     //   2339: putfield D30 : Z
/*    */     //   2342: iload_1
/*    */     //   2343: bipush #16
/*    */     //   2345: iand
/*    */     //   2346: ifeq -> 2357
/*    */     //   2349: aload_0
/*    */     //   2350: getfield wt : Lf/Gp0;
/*    */     //   2353: iconst_1
/*    */     //   2354: putfield for : Z
/*    */     //   2357: iload_1
/*    */     //   2358: bipush #32
/*    */     //   2360: iand
/*    */     //   2361: ifeq -> 2372
/*    */     //   2364: aload_0
/*    */     //   2365: getfield wt : Lf/Gp0;
/*    */     //   2368: invokevirtual getClass : ()Ljava/lang/Class;
/*    */     //   2371: pop
/*    */     //   2372: iconst_0
/*    */     //   2373: istore_1
/*    */     //   2374: iload_1
/*    */     //   2375: aload_0
/*    */     //   2376: getfield kj0 : [[Lf/hm0;
/*    */     //   2379: arraylength
/*    */     //   2380: if_icmpge -> 3535
/*    */     //   2383: aload_0
/*    */     //   2384: getfield nL : [Lf/QZ;
/*    */     //   2387: iload_1
/*    */     //   2388: aaload
/*    */     //   2389: invokevirtual PN : ()Lf/ET;
/*    */     //   2392: getstatic f/ET.R40 : Lf/ET;
/*    */     //   2395: if_acmpne -> 2401
/*    */     //   2398: goto -> 3400
/*    */     //   2401: aload_0
/*    */     //   2402: getfield Ws : Ljava/nio/ByteBuffer;
/*    */     //   2405: invokevirtual getShort : ()S
/*    */     //   2408: dup
/*    */     //   2409: istore_2
/*    */     //   2410: ifne -> 2416
/*    */     //   2413: goto -> 2654
/*    */     //   2416: iload_2
/*    */     //   2417: aload_0
/*    */     //   2418: getfield wt : Lf/Gp0;
/*    */     //   2421: iload_1
/*    */     //   2422: invokevirtual a0 : (B)Lf/PE;
/*    */     //   2425: astore_3
/*    */     //   2426: iconst_1
/*    */     //   2427: iand
/*    */     //   2428: ifeq -> 2459
/*    */     //   2431: aload_3
/*    */     //   2432: aload_0
/*    */     //   2433: getfield Ws : Ljava/nio/ByteBuffer;
/*    */     //   2436: invokevirtual get : ()B
/*    */     //   2439: istore #4
/*    */     //   2441: ifnull -> 2459
/*    */     //   2444: iload #4
/*    */     //   2446: iconst_3
/*    */     //   2447: if_icmple -> 2453
/*    */     //   2450: iconst_3
/*    */     //   2451: istore #4
/*    */     //   2453: aload_3
/*    */     //   2454: iload #4
/*    */     //   2456: putfield Dq0 : B
/*    */     //   2459: iload_2
/*    */     //   2460: iconst_2
/*    */     //   2461: iand
/*    */     //   2462: ifeq -> 2493
/*    */     //   2465: aload_3
/*    */     //   2466: aload_0
/*    */     //   2467: getfield Ws : Ljava/nio/ByteBuffer;
/*    */     //   2470: invokevirtual get : ()B
/*    */     //   2473: istore #4
/*    */     //   2475: ifnull -> 2493
/*    */     //   2478: iload #4
/*    */     //   2480: iconst_2
/*    */     //   2481: if_icmple -> 2487
/*    */     //   2484: iconst_2
/*    */     //   2485: istore #4
/*    */     //   2487: aload_3
/*    */     //   2488: iload #4
/*    */     //   2490: putfield Vn : B
/*    */     //   2493: iload_2
/*    */     //   2494: iconst_4
/*    */     //   2495: iand
/*    */     //   2496: ifeq -> 2508
/*    */     //   2499: aload_3
/*    */     //   2500: ifnull -> 2508
/*    */     //   2503: aload_3
/*    */     //   2504: iconst_1
/*    */     //   2505: putfield Y20 : B
/*    */     //   2508: iload_2
/*    */     //   2509: bipush #8
/*    */     //   2511: iand
/*    */     //   2512: ifeq -> 2534
/*    */     //   2515: aload_3
/*    */     //   2516: aload_0
/*    */     //   2517: getfield Ws : Ljava/nio/ByteBuffer;
/*    */     //   2520: invokevirtual get : ()B
/*    */     //   2523: istore #4
/*    */     //   2525: ifnull -> 2534
/*    */     //   2528: aload_3
/*    */     //   2529: iload #4
/*    */     //   2531: putfield Fy0 : B
/*    */     //   2534: iload_2
/*    */     //   2535: bipush #16
/*    */     //   2537: iand
/*    */     //   2538: ifeq -> 2560
/*    */     //   2541: aload_3
/*    */     //   2542: aload_0
/*    */     //   2543: getfield Ws : Ljava/nio/ByteBuffer;
/*    */     //   2546: invokevirtual get : ()B
/*    */     //   2549: istore #4
/*    */     //   2551: ifnull -> 2560
/*    */     //   2554: aload_3
/*    */     //   2555: iload #4
/*    */     //   2557: putfield I6 : B
/*    */     //   2560: iload_2
/*    */     //   2561: bipush #32
/*    */     //   2563: iand
/*    */     //   2564: ifeq -> 2586
/*    */     //   2567: aload_3
/*    */     //   2568: aload_0
/*    */     //   2569: getfield Ws : Ljava/nio/ByteBuffer;
/*    */     //   2572: invokevirtual get : ()B
/*    */     //   2575: istore #4
/*    */     //   2577: ifnull -> 2586
/*    */     //   2580: aload_3
/*    */     //   2581: iload #4
/*    */     //   2583: putfield prn : B
/*    */     //   2586: iload_2
/*    */     //   2587: bipush #64
/*    */     //   2589: iand
/*    */     //   2590: ifeq -> 2612
/*    */     //   2593: aload_3
/*    */     //   2594: aload_0
/*    */     //   2595: getfield Ws : Ljava/nio/ByteBuffer;
/*    */     //   2598: invokevirtual get : ()B
/*    */     //   2601: istore #4
/*    */     //   2603: ifnull -> 2612
/*    */     //   2606: aload_3
/*    */     //   2607: iload #4
/*    */     //   2609: putfield ax0 : B
/*    */     //   2612: iload_2
/*    */     //   2613: sipush #128
/*    */     //   2616: iand
/*    */     //   2617: ifeq -> 2629
/*    */     //   2620: aload_3
/*    */     //   2621: ifnull -> 2629
/*    */     //   2624: aload_3
/*    */     //   2625: iconst_1
/*    */     //   2626: putfield Au : Z
/*    */     //   2629: iload_2
/*    */     //   2630: sipush #256
/*    */     //   2633: iand
/*    */     //   2634: ifeq -> 2654
/*    */     //   2637: aload_3
/*    */     //   2638: aload_0
/*    */     //   2639: getfield Ws : Ljava/nio/ByteBuffer;
/*    */     //   2642: invokevirtual get : ()B
/*    */     //   2645: istore_2
/*    */     //   2646: ifnull -> 2654
/*    */     //   2649: aload_3
/*    */     //   2650: iload_2
/*    */     //   2651: putfield h30 : B
/*    */     //   2654: aload #8
/*    */     //   2656: getstatic f/Mn.JY : Lf/Mn;
/*    */     //   2659: if_acmpeq -> 2670
/*    */     //   2662: aload #8
/*    */     //   2664: getfield fQ : Z
/*    */     //   2667: ifne -> 3400
/*    */     //   2670: iconst_0
/*    */     //   2671: istore_2
/*    */     //   2672: iload_2
/*    */     //   2673: bipush #6
/*    */     //   2675: if_icmpge -> 3400
/*    */     //   2678: aload_0
/*    */     //   2679: dup
/*    */     //   2680: getfield wt : Lf/Gp0;
/*    */     //   2683: astore_3
/*    */     //   2684: getfield Ws : Ljava/nio/ByteBuffer;
/*    */     //   2687: invokevirtual get : ()B
/*    */     //   2690: dup
/*    */     //   2691: istore #4
/*    */     //   2693: aload_3
/*    */     //   2694: iload_1
/*    */     //   2695: iload_2
/*    */     //   2696: iconst_0
/*    */     //   2697: invokevirtual iC0 : (BBI)Lf/cOm4;
/*    */     //   2700: dup
/*    */     //   2701: astore_3
/*    */     //   2702: iload #4
/*    */     //   2704: putfield k60 : B
/*    */     //   2707: bipush #-2
/*    */     //   2709: if_icmpeq -> 3392
/*    */     //   2712: iload #4
/*    */     //   2714: iconst_m1
/*    */     //   2715: if_icmpeq -> 3392
/*    */     //   2718: iload #4
/*    */     //   2720: ifeq -> 3392
/*    */     //   2723: aload_0
/*    */     //   2724: dup
/*    */     //   2725: dup
/*    */     //   2726: dup2
/*    */     //   2727: dup2
/*    */     //   2728: dup2
/*    */     //   2729: dup2
/*    */     //   2730: getfield Ws : Ljava/nio/ByteBuffer;
/*    */     //   2733: invokevirtual getInt : ()I
/*    */     //   2736: istore #4
/*    */     //   2738: getfield Ws : Ljava/nio/ByteBuffer;
/*    */     //   2741: invokevirtual getShort : ()S
/*    */     //   2744: istore #5
/*    */     //   2746: getfield Ws : Ljava/nio/ByteBuffer;
/*    */     //   2749: invokevirtual get : ()B
/*    */     //   2752: istore #6
/*    */     //   2754: invokevirtual au : ()Ljava/lang/String;
/*    */     //   2757: astore #12
/*    */     //   2759: getfield Ws : Ljava/nio/ByteBuffer;
/*    */     //   2762: invokevirtual get : ()B
/*    */     //   2765: istore #13
/*    */     //   2767: getfield Ws : Ljava/nio/ByteBuffer;
/*    */     //   2770: invokevirtual get : ()B
/*    */     //   2773: istore #14
/*    */     //   2775: getfield Ws : Ljava/nio/ByteBuffer;
/*    */     //   2778: invokevirtual getShort : ()S
/*    */     //   2781: istore #15
/*    */     //   2783: getfield Ws : Ljava/nio/ByteBuffer;
/*    */     //   2786: invokevirtual getShort : ()S
/*    */     //   2789: istore #16
/*    */     //   2791: getfield Ws : Ljava/nio/ByteBuffer;
/*    */     //   2794: invokevirtual getShort : ()S
/*    */     //   2797: istore #17
/*    */     //   2799: getfield Ws : Ljava/nio/ByteBuffer;
/*    */     //   2802: invokevirtual get : ()B
/*    */     //   2805: istore #18
/*    */     //   2807: iconst_m1
/*    */     //   2808: istore #19
/*    */     //   2810: aconst_null
/*    */     //   2811: astore #20
/*    */     //   2813: getfield n90 : I
/*    */     //   2816: bipush #18
/*    */     //   2818: if_icmplt -> 2881
/*    */     //   2821: aload_0
/*    */     //   2822: getfield Ws : Ljava/nio/ByteBuffer;
/*    */     //   2825: invokevirtual get : ()B
/*    */     //   2828: iconst_1
/*    */     //   2829: if_icmpne -> 2881
/*    */     //   2832: aload_0
/*    */     //   2833: getfield Ws : Ljava/nio/ByteBuffer;
/*    */     //   2836: invokevirtual getShort : ()S
/*    */     //   2839: istore #19
/*    */     //   2841: iconst_4
/*    */     //   2842: dup
/*    */     //   2843: istore #20
/*    */     //   2845: newarray short
/*    */     //   2847: astore #21
/*    */     //   2849: iconst_0
/*    */     //   2850: istore #22
/*    */     //   2852: iload #22
/*    */     //   2854: iload #20
/*    */     //   2856: if_icmpge -> 2877
/*    */     //   2859: aload #21
/*    */     //   2861: iload #22
/*    */     //   2863: aload_0
/*    */     //   2864: getfield Ws : Ljava/nio/ByteBuffer;
/*    */     //   2867: invokevirtual getShort : ()S
/*    */     //   2870: sastore
/*    */     //   2871: iinc #22, 1
/*    */     //   2874: goto -> 2852
/*    */     //   2877: aload #21
/*    */     //   2879: astore #20
/*    */     //   2881: aload_0
/*    */     //   2882: aconst_null
/*    */     //   2883: astore #21
/*    */     //   2885: getfield kj0 : [[Lf/hm0;
/*    */     //   2888: iload_1
/*    */     //   2889: aaload
/*    */     //   2890: dup
/*    */     //   2891: astore #22
/*    */     //   2893: arraylength
/*    */     //   2894: istore #23
/*    */     //   2896: iconst_0
/*    */     //   2897: istore #24
/*    */     //   2899: iload #24
/*    */     //   2901: iload #23
/*    */     //   2903: if_icmpge -> 2940
/*    */     //   2906: aload #22
/*    */     //   2908: iload #24
/*    */     //   2910: aaload
/*    */     //   2911: dup
/*    */     //   2912: astore #25
/*    */     //   2914: ifnull -> 2934
/*    */     //   2917: aload #25
/*    */     //   2919: invokevirtual ih : ()I
/*    */     //   2922: iload #4
/*    */     //   2924: if_icmpne -> 2934
/*    */     //   2927: aload #25
/*    */     //   2929: astore #21
/*    */     //   2931: goto -> 2940
/*    */     //   2934: iinc #24, 1
/*    */     //   2937: goto -> 2899
/*    */     //   2940: aload #21
/*    */     //   2942: ifnull -> 3019
/*    */     //   2945: aload #21
/*    */     //   2947: aload_3
/*    */     //   2948: aload #21
/*    */     //   2950: getfield K0 : Lf/jd0;
/*    */     //   2953: dup
/*    */     //   2954: astore_3
/*    */     //   2955: iload #5
/*    */     //   2957: aload #21
/*    */     //   2959: dup
/*    */     //   2960: aload_3
/*    */     //   2961: dup
/*    */     //   2962: getfield ta : Lf/Q90;
/*    */     //   2965: getfield eH : B
/*    */     //   2968: istore #4
/*    */     //   2970: getfield y6 : S
/*    */     //   2973: istore #5
/*    */     //   2975: invokevirtual oi : ()B
/*    */     //   2978: istore #15
/*    */     //   2980: getfield K0 : Lf/jd0;
/*    */     //   2983: getfield M6 : Lf/mA;
/*    */     //   2986: astore #21
/*    */     //   2988: iload #6
/*    */     //   2990: aload #12
/*    */     //   2992: iload #4
/*    */     //   2994: iload #13
/*    */     //   2996: iload #14
/*    */     //   2998: iload #5
/*    */     //   3000: iload #15
/*    */     //   3002: aload #21
/*    */     //   3004: iload #16
/*    */     //   3006: iload #17
/*    */     //   3008: iload #18
/*    */     //   3010: invokevirtual nH : (SBLjava/lang/String;BBBSBLf/mA;SSB)V
/*    */     //   3013: invokevirtual k8 : (Lf/cOm4;)V
/*    */     //   3016: goto -> 3096
/*    */     //   3019: aload_3
/*    */     //   3020: dup
/*    */     //   3021: dup
/*    */     //   3022: new f/jd0
/*    */     //   3025: dup
/*    */     //   3026: astore #21
/*    */     //   3028: aload_3
/*    */     //   3029: dup
/*    */     //   3030: dup
/*    */     //   3031: aload #21
/*    */     //   3033: dup
/*    */     //   3034: iload #4
/*    */     //   3036: invokespecial <init> : (I)V
/*    */     //   3039: putfield gc : Lf/jd0;
/*    */     //   3042: iconst_1
/*    */     //   3043: putfield k60 : B
/*    */     //   3046: putfield sm : Lf/cOm4;
/*    */     //   3049: getfield gc : Lf/jd0;
/*    */     //   3052: iload #5
/*    */     //   3054: getstatic f/mA.uZ : Lf/mA;
/*    */     //   3057: astore #4
/*    */     //   3059: iload #6
/*    */     //   3061: aload #12
/*    */     //   3063: iconst_0
/*    */     //   3064: iload #13
/*    */     //   3066: iload #14
/*    */     //   3068: iload #15
/*    */     //   3070: iconst_0
/*    */     //   3071: aload #4
/*    */     //   3073: iload #16
/*    */     //   3075: iload #17
/*    */     //   3077: iload #18
/*    */     //   3079: invokevirtual nH : (SBLjava/lang/String;BBBSBLf/mA;SSB)V
/*    */     //   3082: iconst_1
/*    */     //   3083: putfield k60 : B
/*    */     //   3086: getfield gc : Lf/jd0;
/*    */     //   3089: aload_3
/*    */     //   3090: putfield sm : Lf/cOm4;
/*    */     //   3093: aload #21
/*    */     //   3095: astore_3
/*    */     //   3096: aload_3
/*    */     //   3097: getfield NI : Lf/UD0;
/*    */     //   3100: astore #4
/*    */     //   3102: iconst_0
/*    */     //   3103: istore #5
/*    */     //   3105: iload #5
/*    */     //   3107: aload #4
/*    */     //   3109: getfield Po : [S
/*    */     //   3112: dup
/*    */     //   3113: astore #6
/*    */     //   3115: arraylength
/*    */     //   3116: if_icmpge -> 3142
/*    */     //   3119: aload #6
/*    */     //   3121: iload #5
/*    */     //   3123: saload
/*    */     //   3124: iload #19
/*    */     //   3126: if_icmpne -> 3132
/*    */     //   3129: goto -> 3145
/*    */     //   3132: iload #5
/*    */     //   3134: iconst_1
/*    */     //   3135: iadd
/*    */     //   3136: i2b
/*    */     //   3137: istore #5
/*    */     //   3139: goto -> 3105
/*    */     //   3142: iconst_m1
/*    */     //   3143: istore #5
/*    */     //   3145: iload #5
/*    */     //   3147: iflt -> 3177
/*    */     //   3150: iload #5
/*    */     //   3152: aload_3
/*    */     //   3153: getfield ta : Lf/Q90;
/*    */     //   3156: astore #4
/*    */     //   3158: iflt -> 3167
/*    */     //   3161: iload #5
/*    */     //   3163: iconst_2
/*    */     //   3164: if_icmple -> 3170
/*    */     //   3167: iconst_0
/*    */     //   3168: istore #5
/*    */     //   3170: aload #4
/*    */     //   3172: iload #5
/*    */     //   3174: putfield cC : B
/*    */     //   3177: iload #19
/*    */     //   3179: ifle -> 3188
/*    */     //   3182: iconst_1
/*    */     //   3183: istore #4
/*    */     //   3185: goto -> 3191
/*    */     //   3188: iconst_0
/*    */     //   3189: istore #4
/*    */     //   3191: aload #20
/*    */     //   3193: aload_3
/*    */     //   3194: iload #4
/*    */     //   3196: putfield KL0 : Z
/*    */     //   3199: ifnull -> 3242
/*    */     //   3202: iconst_0
/*    */     //   3203: istore #4
/*    */     //   3205: iload #4
/*    */     //   3207: aload #20
/*    */     //   3209: arraylength
/*    */     //   3210: if_icmpge -> 3242
/*    */     //   3213: aload #20
/*    */     //   3215: iload #4
/*    */     //   3217: aload_3
/*    */     //   3218: getfield ta : Lf/Q90;
/*    */     //   3221: astore #5
/*    */     //   3223: saload
/*    */     //   3224: istore #6
/*    */     //   3226: aload #5
/*    */     //   3228: getfield En0 : [S
/*    */     //   3231: iload #4
/*    */     //   3233: iload #6
/*    */     //   3235: sastore
/*    */     //   3236: iinc #4, 1
/*    */     //   3239: goto -> 3205
/*    */     //   3242: aload_0
/*    */     //   3243: getfield TA0 : Lf/R00;
/*    */     //   3246: ifnull -> 3392
/*    */     //   3249: aload_0
/*    */     //   3250: getfield X50 : [Lf/hR;
/*    */     //   3253: dup
/*    */     //   3254: astore #4
/*    */     //   3256: arraylength
/*    */     //   3257: istore #5
/*    */     //   3259: iconst_0
/*    */     //   3260: istore #6
/*    */     //   3262: iload #6
/*    */     //   3264: iload #5
/*    */     //   3266: if_icmpge -> 3392
/*    */     //   3269: aload_0
/*    */     //   3270: aload #4
/*    */     //   3272: iload #6
/*    */     //   3274: aaload
/*    */     //   3275: astore #12
/*    */     //   3277: getfield TA0 : Lf/R00;
/*    */     //   3280: invokevirtual ordinal : ()I
/*    */     //   3283: dup
/*    */     //   3284: istore #13
/*    */     //   3286: ifeq -> 3346
/*    */     //   3289: iload #13
/*    */     //   3291: iconst_1
/*    */     //   3292: if_icmpeq -> 3315
/*    */     //   3295: iload #13
/*    */     //   3297: iconst_2
/*    */     //   3298: if_icmpne -> 3304
/*    */     //   3301: goto -> 3346
/*    */     //   3304: new java/lang/UnsupportedOperationException
/*    */     //   3307: dup
/*    */     //   3308: ldc_w ''
/*    */     //   3311: invokespecial <init> : (Ljava/lang/String;)V
/*    */     //   3314: athrow
/*    */     //   3315: aload_3
/*    */     //   3316: iconst_1
/*    */     //   3317: newarray short
/*    */     //   3319: dup
/*    */     //   3320: astore #13
/*    */     //   3322: aload_0
/*    */     //   3323: getfield Ws : Ljava/nio/ByteBuffer;
/*    */     //   3326: invokevirtual getShort : ()S
/*    */     //   3329: iconst_0
/*    */     //   3330: swap
/*    */     //   3331: sastore
/*    */     //   3332: getfield Zf : Ljava/util/EnumMap;
/*    */     //   3335: aload #12
/*    */     //   3337: aload #13
/*    */     //   3339: invokevirtual put : (Ljava/lang/Object;Ljava/lang/Object;)Ljava/lang/Object;
/*    */     //   3342: pop
/*    */     //   3343: goto -> 3386
/*    */     //   3346: aload_3
/*    */     //   3347: iconst_2
/*    */     //   3348: newarray short
/*    */     //   3350: dup
/*    */     //   3351: astore #13
/*    */     //   3353: aload_0
/*    */     //   3354: aload #13
/*    */     //   3356: aload_0
/*    */     //   3357: getfield Ws : Ljava/nio/ByteBuffer;
/*    */     //   3360: invokevirtual getShort : ()S
/*    */     //   3363: iconst_0
/*    */     //   3364: swap
/*    */     //   3365: sastore
/*    */     //   3366: getfield Ws : Ljava/nio/ByteBuffer;
/*    */     //   3369: invokevirtual getShort : ()S
/*    */     //   3372: iconst_1
/*    */     //   3373: swap
/*    */     //   3374: sastore
/*    */     //   3375: getfield Zf : Ljava/util/EnumMap;
/*    */     //   3378: aload #12
/*    */     //   3380: aload #13
/*    */     //   3382: invokevirtual put : (Ljava/lang/Object;Ljava/lang/Object;)Ljava/lang/Object;
/*    */     //   3385: pop
/*    */     //   3386: iinc #6, 1
/*    */     //   3389: goto -> 3262
/*    */     //   3392: iload_2
/*    */     //   3393: iconst_1
/*    */     //   3394: iadd
/*    */     //   3395: i2b
/*    */     //   3396: istore_2
/*    */     //   3397: goto -> 2672
/*    */     //   3400: iload_1
/*    */     //   3401: iconst_1
/*    */     //   3402: iadd
/*    */     //   3403: i2b
/*    */     //   3404: istore_1
/*    */     //   3405: goto -> 2374
/*    */     //   3408: aload_0
/*    */     //   3409: dup
/*    */     //   3410: new f/CQ
/*    */     //   3413: dup
/*    */     //   3414: astore_1
/*    */     //   3415: aload_0
/*    */     //   3416: aload_1
/*    */     //   3417: aload #4
/*    */     //   3419: aload_0
/*    */     //   3420: dup
/*    */     //   3421: dup
/*    */     //   3422: dup2
/*    */     //   3423: dup2
/*    */     //   3424: getfield Sf0 : B
/*    */     //   3427: istore #4
/*    */     //   3429: getfield bf : Lf/rK;
/*    */     //   3432: astore #12
/*    */     //   3434: getfield Un0 : Lf/aq0;
/*    */     //   3437: astore #13
/*    */     //   3439: getfield cd0 : [Lf/DO;
/*    */     //   3442: astore #14
/*    */     //   3444: getfield OE0 : [Lf/CC0;
/*    */     //   3447: astore #15
/*    */     //   3449: getfield nL : [Lf/QZ;
/*    */     //   3452: astore #16
/*    */     //   3454: getfield kj0 : [[Lf/hm0;
/*    */     //   3457: astore #17
/*    */     //   3459: aload #8
/*    */     //   3461: iload #6
/*    */     //   3463: iload #4
/*    */     //   3465: aload #5
/*    */     //   3467: aload #12
/*    */     //   3469: aload #13
/*    */     //   3471: aload #14
/*    */     //   3473: aload #15
/*    */     //   3475: iload_2
/*    */     //   3476: iload_3
/*    */     //   3477: iload #9
/*    */     //   3479: aload #16
/*    */     //   3481: aload #17
/*    */     //   3483: invokespecial <init> : (Lf/ky;Lf/Mn;IBLf/yi;Lf/rK;Lf/aq0;[Lf/DO;[Lf/CC0;BBZ[Lf/QZ;[[Lf/hm0;)V
/*    */     //   3486: getfield Ws : Ljava/nio/ByteBuffer;
/*    */     //   3489: invokevirtual get : ()B
/*    */     //   3492: invokestatic dM : (B)Lf/DG;
/*    */     //   3495: putfield uy0 : Lf/DG;
/*    */     //   3498: getfield Ws : Ljava/nio/ByteBuffer;
/*    */     //   3501: invokevirtual get : ()B
/*    */     //   3504: pop
/*    */     //   3505: getfield Ws : Ljava/nio/ByteBuffer;
/*    */     //   3508: invokevirtual get : ()B
/*    */     //   3511: dup
/*    */     //   3512: istore_2
/*    */     //   3513: ifge -> 3518
/*    */     //   3516: iconst_0
/*    */     //   3517: istore_2
/*    */     //   3518: iload_2
/*    */     //   3519: iconst_5
/*    */     //   3520: if_icmple -> 3525
/*    */     //   3523: iconst_5
/*    */     //   3524: istore_2
/*    */     //   3525: aload_0
/*    */     //   3526: aload_1
/*    */     //   3527: iload_2
/*    */     //   3528: putfield JH : B
/*    */     //   3531: aload_1
/*    */     //   3532: putfield wt : Lf/Gp0;
/*    */     //   3535: aload_0
/*    */     //   3536: dup
/*    */     //   3537: getfield wt : Lf/Gp0;
/*    */     //   3540: dup
/*    */     //   3541: astore_1
/*    */     //   3542: aload_0
/*    */     //   3543: aload_1
/*    */     //   3544: aload_0
/*    */     //   3545: aload_1
/*    */     //   3546: iload #10
/*    */     //   3548: aload_1
/*    */     //   3549: iload #7
/*    */     //   3551: aload_1
/*    */     //   3552: aload #11
/*    */     //   3554: aload_1
/*    */     //   3555: aload_0
/*    */     //   3556: getfield Bk : [Lf/Fs;
/*    */     //   3559: putfield gt : [Lf/Fs;
/*    */     //   3562: putfield CJ0 : Lf/eq0;
/*    */     //   3565: putfield T20 : S
/*    */     //   3568: putfield kI0 : Z
/*    */     //   3571: getfield ap0 : Lf/DK;
/*    */     //   3574: putfield uo0 : Lf/DK;
/*    */     //   3577: getfield xm : Lf/Mx;
/*    */     //   3580: putfield e30 : Lf/Mx;
/*    */     //   3583: getfield OL : I
/*    */     //   3586: dup
/*    */     //   3587: istore_2
/*    */     //   3588: ifne -> 3594
/*    */     //   3591: goto -> 3768
/*    */     //   3594: new java/util/Random
/*    */     //   3597: dup
/*    */     //   3598: astore_3
/*    */     //   3599: iload_2
/*    */     //   3600: i2l
/*    */     //   3601: invokespecial <init> : (J)V
/*    */     //   3604: new f/h9
/*    */     //   3607: dup
/*    */     //   3608: dup2
/*    */     //   3609: astore_2
/*    */     //   3610: getstatic f/km.mI0 : Lf/P1;
/*    */     //   3613: getfield q20 : [B
/*    */     //   3616: dup
/*    */     //   3617: astore #4
/*    */     //   3619: arraylength
/*    */     //   3620: bipush #10
/*    */     //   3622: invokestatic max : (II)I
/*    */     //   3625: invokespecial <init> : (I)V
/*    */     //   3628: aload #4
/*    */     //   3630: invokevirtual vI0 : ([B)V
/*    */     //   3633: iconst_0
/*    */     //   3634: invokevirtual db0 : (B)Z
/*    */     //   3637: ifeq -> 3665
/*    */     //   3640: aload_2
/*    */     //   3641: iconst_1
/*    */     //   3642: invokevirtual db0 : (B)Z
/*    */     //   3645: ifeq -> 3665
/*    */     //   3648: aload_2
/*    */     //   3649: iconst_0
/*    */     //   3650: invokevirtual cP : (B)I
/*    */     //   3653: dup
/*    */     //   3654: istore #4
/*    */     //   3656: iflt -> 3665
/*    */     //   3659: aload_2
/*    */     //   3660: iload #4
/*    */     //   3662: invokevirtual Id : (I)V
/*    */     //   3665: aload_2
/*    */     //   3666: dup
/*    */     //   3667: dup
/*    */     //   3668: getfield ir0 : I
/*    */     //   3671: dup
/*    */     //   3672: istore_2
/*    */     //   3673: newarray byte
/*    */     //   3675: astore #4
/*    */     //   3677: getfield Sx0 : [B
/*    */     //   3680: astore #5
/*    */     //   3682: getfield JO : [B
/*    */     //   3685: dup
/*    */     //   3686: astore #6
/*    */     //   3688: arraylength
/*    */     //   3689: istore #7
/*    */     //   3691: iconst_0
/*    */     //   3692: istore #10
/*    */     //   3694: iload #7
/*    */     //   3696: dup
/*    */     //   3697: iconst_m1
/*    */     //   3698: iadd
/*    */     //   3699: istore #7
/*    */     //   3701: ifle -> 3737
/*    */     //   3704: aload #6
/*    */     //   3706: iload #7
/*    */     //   3708: baload
/*    */     //   3709: iconst_1
/*    */     //   3710: if_icmpne -> 3694
/*    */     //   3713: aload #4
/*    */     //   3715: aload #5
/*    */     //   3717: iload #10
/*    */     //   3719: iconst_1
/*    */     //   3720: iadd
/*    */     //   3721: istore #11
/*    */     //   3723: iload #7
/*    */     //   3725: baload
/*    */     //   3726: iload #10
/*    */     //   3728: swap
/*    */     //   3729: bastore
/*    */     //   3730: iload #11
/*    */     //   3732: istore #10
/*    */     //   3734: goto -> 3694
/*    */     //   3737: aload_1
/*    */     //   3738: aload #4
/*    */     //   3740: aload_3
/*    */     //   3741: iload_2
/*    */     //   3742: invokevirtual nextInt : (I)I
/*    */     //   3745: baload
/*    */     //   3746: istore_2
/*    */     //   3747: getstatic f/Gp0.iO : [[S
/*    */     //   3750: iload_2
/*    */     //   3751: aaload
/*    */     //   3752: dup
/*    */     //   3753: aload_3
/*    */     //   3754: swap
/*    */     //   3755: aload_1
/*    */     //   3756: iload_2
/*    */     //   3757: putfield iK : B
/*    */     //   3760: arraylength
/*    */     //   3761: invokevirtual nextInt : (I)I
/*    */     //   3764: saload
/*    */     //   3765: putfield CoM9 : S
/*    */     //   3768: aload_0
/*    */     //   3769: getfield wt : Lf/Gp0;
/*    */     //   3772: dup
/*    */     //   3773: aload_0
/*    */     //   3774: getfield NO : Z
/*    */     //   3777: putfield ka0 : Z
/*    */     //   3780: invokevirtual yx0 : ()Z
/*    */     //   3783: ifeq -> 3829
/*    */     //   3786: iload #9
/*    */     //   3788: ifeq -> 3829
/*    */     //   3791: aload #8
/*    */     //   3793: getfield fQ : Z
/*    */     //   3796: ifeq -> 3809
/*    */     //   3799: aload_0
/*    */     //   3800: getfield wt : Lf/Gp0;
/*    */     //   3803: invokevirtual sQ : ()Z
/*    */     //   3806: ifeq -> 3829
/*    */     //   3809: aload_0
/*    */     //   3810: getfield wt : Lf/Gp0;
/*    */     //   3813: new f/il0
/*    */     //   3816: dup
/*    */     //   3817: astore_0
/*    */     //   3818: invokespecial <init> : ()V
/*    */     //   3821: getfield W : Ljava/util/LinkedList;
/*    */     //   3824: aload_0
/*    */     //   3825: invokevirtual add : (Ljava/lang/Object;)Z
/*    */     //   3828: pop
/*    */     //   3829: return
/*    */     // Line number table:
/*    */     //   Java source line number -> byte code offset
/*    */     //   #1	-> 3
/*    */     //   #2	-> 19
/*    */     //   #3	-> 28
/*    */     //   #4	-> 46
/*    */     //   #5	-> 51
/*    */     //   #6	-> 57
/*    */     //   #7	-> 63
/*    */     //   #8	-> 69
/*    */     //   #9	-> 74
/*    */     //   #10	-> 82
/*    */     //   #11	-> 90
/*    */     //   #12	-> 96
/*    */     //   #13	-> 118
/*    */     //   #14	-> 127
/*    */     //   #15	-> 139
/*    */     //   #16	-> 168
/*    */     //   #17	-> 201
/*    */     //   #18	-> 207
/*    */     //   #19	-> 220
/*    */     //   #20	-> 226
/*    */     //   #21	-> 242
/*    */     //   #22	-> 248
/*    */     //   #23	-> 264
/*    */     //   #24	-> 273
/*    */     //   #25	-> 346
/*    */     //   #26	-> 351
/*    */     //   #27	-> 390
/*    */     //   #28	-> 400
/*    */     //   #29	-> 421
/*    */     //   #30	-> 427
/*    */     //   #31	-> 430
/*    */     //   #32	-> 436
/*    */     //   #33	-> 450
/*    */     //   #34	-> 456
/*    */     //   #35	-> 473
/*    */     //   #36	-> 479
/*    */     //   #37	-> 493
/*    */     //   #38	-> 499
/*    */     //   #39	-> 517
/*    */     //   #40	-> 523
/*    */     //   #41	-> 529
/*    */     //   #42	-> 541
/*    */     //   #43	-> 549
/*    */     //   #44	-> 553
/*    */     //   #45	-> 591
/*    */     //   #46	-> 605
/*    */     //   #47	-> 632
/*    */     //   #48	-> 646
/*    */     //   #49	-> 652
/*    */     //   #50	-> 689
/*    */     //   #51	-> 695
/*    */     //   #52	-> 709
/*    */     //   #53	-> 715
/*    */     //   #54	-> 726
/*    */     //   #55	-> 733
/*    */     //   #56	-> 763
/*    */     //   #57	-> 772
/*    */     //   #58	-> 799
/*    */     //   #59	-> 811
/*    */     //   #60	-> 863
/*    */     //   #61	-> 990
/*    */     //   #62	-> 1009
/*    */     //   #63	-> 1024
/*    */     //   #64	-> 1032
/*    */     //   #65	-> 1040
/*    */     //   #66	-> 1045
/*    */     //   #67	-> 1069
/*    */     //   #68	-> 1077
/*    */     //   #69	-> 1091
/*    */     //   #70	-> 1096
/*    */     //   #71	-> 1112
/*    */     //   #72	-> 1158
/*    */     //   #73	-> 1161
/*    */     //   #74	-> 1189
/*    */     //   #75	-> 1235
/*    */     //   #76	-> 1258
/*    */     //   #77	-> 1285
/*    */     //   #78	-> 1309
/*    */     //   #79	-> 1334
/*    */     //   #80	-> 1359
/*    */     //   #81	-> 1384
/*    */     //   #82	-> 1393
/*    */     //   #83	-> 1399
/*    */     //   #84	-> 1413
/*    */     //   #85	-> 1419
/*    */     //   #86	-> 1433
/*    */     //   #87	-> 1439
/*    */     //   #88	-> 1455
/*    */     //   #89	-> 1470
/*    */     //   #90	-> 1488
/*    */     //   #91	-> 1506
/*    */     //   #92	-> 1512
/*    */     //   #93	-> 1523
/*    */     //   #94	-> 1537
/*    */     //   #95	-> 1545
/*    */     //   #96	-> 1554
/*    */     //   #97	-> 1582
/*    */     //   #98	-> 1588
/*    */     //   #99	-> 1589
/*    */     //   #100	-> 1595
/*    */     //   #101	-> 1610
/*    */     //   #102	-> 1618
/*    */     //   #103	-> 1644
/*    */     //   #104	-> 1649
/*    */     //   #105	-> 1667
/*    */     //   #106	-> 1673
/*    */     //   #107	-> 1676
/*    */     //   #108	-> 1679
/*    */     //   #109	-> 1685
/*    */     //   #110	-> 1688
/*    */     //   #111	-> 1703
/*    */     //   #112	-> 1709
/*    */     //   #113	-> 1724
/*    */     //   #114	-> 1730
/*    */     //   #115	-> 1745
/*    */     //   #116	-> 1751
/*    */     //   #117	-> 1765
/*    */     //   #118	-> 1768
/*    */     //   #119	-> 1772
/*    */     //   #120	-> 1786
/*    */     //   #121	-> 1790
/*    */     //   #122	-> 1796
/*    */     //   #123	-> 1852
/*    */     //   #124	-> 1856
/*    */     //   #125	-> 1862
/*    */     //   #126	-> 1865
/*    */     //   #127	-> 1869
/*    */     //   #128	-> 1875
/*    */     //   #129	-> 1878
/*    */     //   #130	-> 1882
/*    */     //   #131	-> 1888
/*    */     //   #132	-> 1891
/*    */     //   #133	-> 1895
/*    */     //   #134	-> 1901
/*    */     //   #135	-> 1904
/*    */     //   #136	-> 1923
/*    */     //   #137	-> 1962
/*    */     //   #138	-> 1980
/*    */     //   #139	-> 1999
/*    */     //   #140	-> 2007
/*    */     //   #141	-> 2031
/*    */     //   #142	-> 2039
/*    */     //   #143	-> 2044
/*    */     //   #144	-> 2060
/*    */     //   #145	-> 2093
/*    */     //   #146	-> 2272
/*    */     //   #147	-> 2293
/*    */     //   #148	-> 2339
/*    */     //   #149	-> 2350
/*    */     //   #150	-> 2354
/*    */     //   #151	-> 2365
/*    */     //   #152	-> 2376
/*    */     //   #153	-> 2402
/*    */     //   #154	-> 2418
/*    */     //   #155	-> 2433
/*    */     //   #156	-> 2456
/*    */     //   #157	-> 2467
/*    */     //   #158	-> 2490
/*    */     //   #159	-> 2505
/*    */     //   #160	-> 2517
/*    */     //   #161	-> 2531
/*    */     //   #162	-> 2543
/*    */     //   #163	-> 2557
/*    */     //   #164	-> 2569
/*    */     //   #165	-> 2583
/*    */     //   #166	-> 2595
/*    */     //   #167	-> 2609
/*    */     //   #168	-> 2626
/*    */     //   #169	-> 2639
/*    */     //   #170	-> 2651
/*    */     //   #171	-> 2656
/*    */     //   #172	-> 2664
/*    */     //   #173	-> 2680
/*    */     //   #174	-> 2684
/*    */     //   #175	-> 2697
/*    */     //   #176	-> 2704
/*    */     //   #177	-> 2730
/*    */     //   #178	-> 2738
/*    */     //   #179	-> 2746
/*    */     //   #180	-> 2754
/*    */     //   #181	-> 2759
/*    */     //   #182	-> 2775
/*    */     //   #183	-> 2799
/*    */     //   #184	-> 2813
/*    */     //   #185	-> 2822
/*    */     //   #186	-> 2833
/*    */     //   #187	-> 2845
/*    */     //   #188	-> 2864
/*    */     //   #189	-> 2870
/*    */     //   #190	-> 2950
/*    */     //   #191	-> 2962
/*    */     //   #192	-> 2965
/*    */     //   #193	-> 2970
/*    */     //   #194	-> 2975
/*    */     //   #195	-> 2980
/*    */     //   #196	-> 2983
/*    */     //   #197	-> 3010
/*    */     //   #198	-> 3039
/*    */     //   #199	-> 3043
/*    */     //   #200	-> 3046
/*    */     //   #201	-> 3049
/*    */     //   #202	-> 3090
/*    */     //   #203	-> 3097
/*    */     //   #204	-> 3109
/*    */     //   #205	-> 3115
/*    */     //   #206	-> 3153
/*    */     //   #207	-> 3174
/*    */     //   #208	-> 3196
/*    */     //   #209	-> 3209
/*    */     //   #210	-> 3218
/*    */     //   #211	-> 3223
/*    */     //   #212	-> 3228
/*    */     //   #213	-> 3235
/*    */     //   #214	-> 3243
/*    */     //   #215	-> 3323
/*    */     //   #216	-> 3331
/*    */     //   #217	-> 3332
/*    */     //   #218	-> 3348
/*    */     //   #219	-> 3357
/*    */     //   #220	-> 3365
/*    */     //   #221	-> 3366
/*    */     //   #222	-> 3374
/*    */     //   #223	-> 3375
/*    */     //   #224	-> 3410
/*    */     //   #225	-> 3486
/*    */     //   #226	-> 3492
/*    */     //   #227	-> 3495
/*    */     //   #228	-> 3498
/*    */     //   #229	-> 3528
/*    */     //   #230	-> 3532
/*    */     //   #231	-> 3559
/*    */     //   #232	-> 3562
/*    */     //   #233	-> 3565
/*    */     //   #234	-> 3568
/*    */     //   #235	-> 3571
/*    */     //   #236	-> 3574
/*    */     //   #237	-> 3577
/*    */     //   #238	-> 3580
/*    */     //   #239	-> 3583
/*    */     //   #240	-> 3594
/*    */     //   #241	-> 3613
/*    */     //   #242	-> 3619
/*    */     //   #243	-> 3634
/*    */     //   #244	-> 3650
/*    */     //   #245	-> 3668
/*    */     //   #246	-> 3673
/*    */     //   #247	-> 3742
/*    */     //   #248	-> 3769
/*    */     //   #249	-> 3777
/*    */     //   #250	-> 3780
/*    */     //   #251	-> 3793
/*    */     //   #252	-> 3800
/*    */     //   #253	-> 3821
/*    */     //   #254	-> 3825
/*    */   }
/*    */   
/*    */   public final QZ A40(byte paramByte) {
/*    */     // Byte code:
/*    */     //   0: aload_0
/*    */     //   1: getfield Ws : Ljava/nio/ByteBuffer;
/*    */     //   4: invokevirtual get : ()B
/*    */     //   7: invokestatic F40 : (B)Lf/ET;
/*    */     //   10: dup
/*    */     //   11: astore_2
/*    */     //   12: invokevirtual ordinal : ()I
/*    */     //   15: tableswitch default -> 56, 0 -> 199, 1 -> 190, 2 -> 164, 3 -> 122, 4 -> 67, 5 -> 67, 6 -> 58
/*    */     //   56: aconst_null
/*    */     //   57: areturn
/*    */     //   58: new f/zl0
/*    */     //   61: dup
/*    */     //   62: iload_1
/*    */     //   63: invokespecial <init> : (B)V
/*    */     //   66: areturn
/*    */     //   67: aload_0
/*    */     //   68: invokevirtual R00 : ()I
/*    */     //   71: dup
/*    */     //   72: istore_3
/*    */     //   73: anewarray f/QZ
/*    */     //   76: astore #4
/*    */     //   78: iconst_0
/*    */     //   79: istore #5
/*    */     //   81: iload #5
/*    */     //   83: iload_3
/*    */     //   84: if_icmpge -> 104
/*    */     //   87: aload #4
/*    */     //   89: aload_0
/*    */     //   90: iload_1
/*    */     //   91: invokevirtual A40 : (B)Lf/QZ;
/*    */     //   94: iload #5
/*    */     //   96: swap
/*    */     //   97: aastore
/*    */     //   98: iinc #5, 1
/*    */     //   101: goto -> 81
/*    */     //   104: new f/X10
/*    */     //   107: dup
/*    */     //   108: iload_1
/*    */     //   109: aload_0
/*    */     //   110: getfield bf : Lf/rK;
/*    */     //   113: astore_0
/*    */     //   114: aload_2
/*    */     //   115: aload #4
/*    */     //   117: aload_0
/*    */     //   118: invokespecial <init> : (BLf/ET;[Lf/QZ;Lf/rK;)V
/*    */     //   121: areturn
/*    */     //   122: new f/BR
/*    */     //   125: dup
/*    */     //   126: aload_0
/*    */     //   127: dup
/*    */     //   128: dup2
/*    */     //   129: getfield Ws : Ljava/nio/ByteBuffer;
/*    */     //   132: invokevirtual get : ()B
/*    */     //   135: istore_0
/*    */     //   136: getfield Ws : Ljava/nio/ByteBuffer;
/*    */     //   139: invokevirtual get : ()B
/*    */     //   142: istore_2
/*    */     //   143: getfield Ws : Ljava/nio/ByteBuffer;
/*    */     //   146: invokevirtual get : ()B
/*    */     //   149: istore_3
/*    */     //   150: getfield Ws : Ljava/nio/ByteBuffer;
/*    */     //   153: invokevirtual getInt : ()I
/*    */     //   156: iload_1
/*    */     //   157: iload_0
/*    */     //   158: iload_2
/*    */     //   159: iload_3
/*    */     //   160: invokespecial <init> : (IBBBB)V
/*    */     //   163: areturn
/*    */     //   164: new f/BR
/*    */     //   167: dup
/*    */     //   168: iload_1
/*    */     //   169: aload_0
/*    */     //   170: dup
/*    */     //   171: getfield Ws : Ljava/nio/ByteBuffer;
/*    */     //   174: invokevirtual get : ()B
/*    */     //   177: istore_0
/*    */     //   178: getfield Ws : Ljava/nio/ByteBuffer;
/*    */     //   181: invokevirtual getShort : ()S
/*    */     //   184: iload_0
/*    */     //   185: swap
/*    */     //   186: invokespecial <init> : (BBS)V
/*    */     //   189: areturn
/*    */     //   190: new f/Yu
/*    */     //   193: dup
/*    */     //   194: iload_1
/*    */     //   195: invokespecial <init> : (B)V
/*    */     //   198: areturn
/*    */     //   199: aload_0
/*    */     //   200: dup
/*    */     //   201: dup
/*    */     //   202: invokevirtual au : ()Ljava/lang/String;
/*    */     //   205: astore_2
/*    */     //   206: getfield Ws : Ljava/nio/ByteBuffer;
/*    */     //   209: invokevirtual get : ()B
/*    */     //   212: istore_3
/*    */     //   213: getfield fv : Z
/*    */     //   216: ifeq -> 246
/*    */     //   219: aload_0
/*    */     //   220: getfield Ws : Ljava/nio/ByteBuffer;
/*    */     //   223: invokevirtual get : ()B
/*    */     //   226: dup
/*    */     //   227: aload_0
/*    */     //   228: swap
/*    */     //   229: putfield l00 : B
/*    */     //   232: iflt -> 246
/*    */     //   235: aload_0
/*    */     //   236: dup
/*    */     //   237: getfield Ws : Ljava/nio/ByteBuffer;
/*    */     //   240: invokevirtual get : ()B
/*    */     //   243: putfield tc : B
/*    */     //   246: aload_0
/*    */     //   247: getfield Ws : Ljava/nio/ByteBuffer;
/*    */     //   250: invokevirtual get : ()B
/*    */     //   253: iconst_1
/*    */     //   254: if_icmpne -> 261
/*    */     //   257: iconst_1
/*    */     //   258: goto -> 262
/*    */     //   261: iconst_0
/*    */     //   262: aconst_null
/*    */     //   263: astore #4
/*    */     //   265: iconst_m1
/*    */     //   266: istore #5
/*    */     //   268: iconst_0
/*    */     //   269: istore #6
/*    */     //   271: ifeq -> 311
/*    */     //   274: aload_0
/*    */     //   275: dup
/*    */     //   276: dup
/*    */     //   277: getfield Ws : Ljava/nio/ByteBuffer;
/*    */     //   280: invokevirtual get : ()B
/*    */     //   283: getstatic f/rs0.Fg0 : Lf/ak;
/*    */     //   286: swap
/*    */     //   287: invokevirtual Ha0 : (B)Ljava/lang/Object;
/*    */     //   290: checkcast f/rs0
/*    */     //   293: astore #4
/*    */     //   295: getfield Ws : Ljava/nio/ByteBuffer;
/*    */     //   298: invokevirtual getShort : ()S
/*    */     //   301: istore #5
/*    */     //   303: getfield Ws : Ljava/nio/ByteBuffer;
/*    */     //   306: invokevirtual get : ()B
/*    */     //   309: istore #6
/*    */     //   311: aload_0
/*    */     //   312: invokevirtual ZV : ()Lf/H10;
/*    */     //   315: astore #7
/*    */     //   317: new f/W30
/*    */     //   320: dup
/*    */     //   321: iload_1
/*    */     //   322: aload_0
/*    */     //   323: new f/OE0
/*    */     //   326: dup
/*    */     //   327: astore_0
/*    */     //   328: iload_3
/*    */     //   329: aload #7
/*    */     //   331: invokespecial <init> : (BLf/H10;)V
/*    */     //   334: getfield bf : Lf/rK;
/*    */     //   337: astore_1
/*    */     //   338: aload_2
/*    */     //   339: aload_0
/*    */     //   340: aload #4
/*    */     //   342: iload #5
/*    */     //   344: iload #6
/*    */     //   346: aload_1
/*    */     //   347: invokespecial <init> : (BLjava/lang/String;Lf/OE0;Lf/rs0;SBLf/rK;)V
/*    */     //   350: areturn
/*    */     // Line number table:
/*    */     //   Java source line number -> byte code offset
/*    */     //   #1	-> 1
/*    */     //   #2	-> 7
/*    */     //   #3	-> 129
/*    */     //   #4	-> 136
/*    */     //   #5	-> 143
/*    */     //   #6	-> 150
/*    */     //   #7	-> 160
/*    */     //   #8	-> 171
/*    */     //   #9	-> 178
/*    */     //   #10	-> 186
/*    */     //   #11	-> 206
/*    */     //   #12	-> 213
/*    */     //   #13	-> 220
/*    */     //   #14	-> 229
/*    */     //   #15	-> 237
/*    */     //   #16	-> 243
/*    */     //   #17	-> 247
/*    */     //   #18	-> 277
/*    */     //   #19	-> 283
/*    */     //   #20	-> 295
/*    */     //   #21	-> 303
/*    */     //   #22	-> 312
/*    */   } }


/* Location:              /Users/vnnsnnt/Documents/Codespace/JavaWorkspace/RedTrainer/src/main/java/org/trainer/client/PokeMMO.jar!/f/Zc.class
 * Java compiler version: 8 (52.0)
 * JD-Core Version:       1.1.3
 */