/* 1 */ package f;public final class zD0 extends Qa0 implements r60 { private void Cx0(int paramInt) { this.Vj0[paramInt]
/*   */       
/* 3 */       .sk0((this.Ug[paramInt]).TG0.nm0()); }
/*   */ 
/*   */   
/*   */   public final Ip fu0;
/*   */   
/*   */   public final nE0 Ok;
/*   */   public final MM qk;
/*   */   public final Kf ZF;
/*   */   public W1 L00;
/*   */   public W1 ro;
/*   */   public W1[] Gy;
/*   */   public WD[] o20;
/*   */   public ge0[] Ug;
/*   */   public Rm[] Vj0;
/*   */   
/*   */   public zD0(nE0 paramnE0, Kf paramKf) {
/*   */     // Byte code:
/*   */     //   0: aload_0
/*   */     //   1: aload_1
/*   */     //   2: aload_0
/*   */     //   3: aload_1
/*   */     //   4: aload_0
/*   */     //   5: aload_2
/*   */     //   6: aload_0
/*   */     //   7: dup
/*   */     //   8: dup2
/*   */     //   9: dup2
/*   */     //   10: iconst_0
/*   */     //   11: iconst_0
/*   */     //   12: invokespecial <init> : (ZZ)V
/*   */     //   15: aconst_null
/*   */     //   16: putfield L00 : Lf/W1;
/*   */     //   19: aconst_null
/*   */     //   20: putfield ro : Lf/W1;
/*   */     //   23: iconst_0
/*   */     //   24: anewarray f/W1
/*   */     //   27: putfield Gy : [Lf/W1;
/*   */     //   30: aconst_null
/*   */     //   31: putfield Ug : [Lf/ge0;
/*   */     //   34: ldc 'confirm-widget'
/*   */     //   36: invokevirtual Xu : (Ljava/lang/String;)V
/*   */     //   39: putfield ZF : Lf/Kf;
/*   */     //   42: putfield Ok : Lf/nE0;
/*   */     //   45: new f/Ip
/*   */     //   48: dup
/*   */     //   49: dup2
/*   */     //   50: dup2
/*   */     //   51: astore_1
/*   */     //   52: aload_0
/*   */     //   53: aload_1
/*   */     //   54: dup
/*   */     //   55: invokespecial <init> : ()V
/*   */     //   58: putfield fu0 : Lf/Ip;
/*   */     //   61: ldc 'confirm-panel'
/*   */     //   63: invokevirtual Xu : (Ljava/lang/String;)V
/*   */     //   66: new f/dQ
/*   */     //   69: dup
/*   */     //   70: dup
/*   */     //   71: astore_2
/*   */     //   72: invokespecial <init> : ()V
/*   */     //   75: ldc 'label-title'
/*   */     //   77: invokevirtual E1 : (Ljava/lang/String;)V
/*   */     //   80: iconst_1
/*   */     //   81: anewarray f/JG0
/*   */     //   84: dup
/*   */     //   85: iconst_0
/*   */     //   86: aload_2
/*   */     //   87: aastore
/*   */     //   88: invokevirtual vo0 : ([Lf/JG0;)Lf/U90;
/*   */     //   91: invokevirtual WN : (Lf/U90;)V
/*   */     //   94: iconst_1
/*   */     //   95: anewarray f/JG0
/*   */     //   98: dup
/*   */     //   99: iconst_0
/*   */     //   100: aload_2
/*   */     //   101: aastore
/*   */     //   102: invokevirtual AUX : ([Lf/JG0;)Lf/U90;
/*   */     //   105: invokevirtual rK0 : (Lf/U90;)V
/*   */     //   108: invokevirtual je0 : ()Lf/MM;
/*   */     //   111: dup
/*   */     //   112: astore_3
/*   */     //   113: putfield qk : Lf/MM;
/*   */     //   116: aload_3
/*   */     //   117: invokevirtual bv0 : ()S
/*   */     //   120: ifle -> 1743
/*   */     //   123: aload_3
/*   */     //   124: aload_1
/*   */     //   125: dup
/*   */     //   126: aload_2
/*   */     //   127: sipush #5613
/*   */     //   130: invokestatic OH0 : (I)Ljava/lang/String;
/*   */     //   133: invokevirtual E1 : (Ljava/lang/String;)V
/*   */     //   136: invokestatic v30 : ()Lf/On;
/*   */     //   139: aload_3
/*   */     //   140: invokevirtual bv0 : ()S
/*   */     //   143: invokevirtual lpT3 : (S)Lf/UD0;
/*   */     //   146: astore_1
/*   */     //   147: new java/lang/StringBuilder
/*   */     //   150: dup
/*   */     //   151: astore_2
/*   */     //   152: aload_1
/*   */     //   153: aload_2
/*   */     //   154: dup
/*   */     //   155: new java/lang/StringBuilder
/*   */     //   158: dup
/*   */     //   159: invokespecial <init> : ()V
/*   */     //   162: bipush #59
/*   */     //   164: invokestatic OH0 : (I)Ljava/lang/String;
/*   */     //   167: invokevirtual append : (Ljava/lang/String;)Ljava/lang/StringBuilder;
/*   */     //   170: ldc ' '
/*   */     //   172: invokevirtual append : (Ljava/lang/String;)Ljava/lang/StringBuilder;
/*   */     //   175: bipush #50
/*   */     //   177: invokevirtual append : (I)Ljava/lang/StringBuilder;
/*   */     //   180: ldc ' '
/*   */     //   182: invokevirtual append : (Ljava/lang/String;)Ljava/lang/StringBuilder;
/*   */     //   185: invokevirtual toString : ()Ljava/lang/String;
/*   */     //   188: invokespecial <init> : (Ljava/lang/String;)V
/*   */     //   191: new java/lang/StringBuilder
/*   */     //   194: dup
/*   */     //   195: invokespecial <init> : ()V
/*   */     //   198: sipush #5615
/*   */     //   201: invokestatic OH0 : (I)Ljava/lang/String;
/*   */     //   204: invokevirtual append : (Ljava/lang/String;)Ljava/lang/StringBuilder;
/*   */     //   207: ldc ' '
/*   */     //   209: invokevirtual append : (Ljava/lang/String;)Ljava/lang/StringBuilder;
/*   */     //   212: invokevirtual toString : ()Ljava/lang/String;
/*   */     //   215: invokevirtual append : (Ljava/lang/String;)Ljava/lang/StringBuilder;
/*   */     //   218: pop
/*   */     //   219: invokevirtual wp : ()Ljava/lang/String;
/*   */     //   222: invokevirtual append : (Ljava/lang/String;)Ljava/lang/StringBuilder;
/*   */     //   225: pop
/*   */     //   226: new f/dQ
/*   */     //   229: dup
/*   */     //   230: astore_3
/*   */     //   231: aload_2
/*   */     //   232: invokevirtual toString : ()Ljava/lang/String;
/*   */     //   235: invokespecial <init> : (Ljava/lang/String;)V
/*   */     //   238: invokevirtual xh : ()Lf/U90;
/*   */     //   241: aload_3
/*   */     //   242: invokevirtual Ya : (Lf/JG0;)Lf/U90;
/*   */     //   245: pop
/*   */     //   246: invokevirtual iJ0 : ()Lf/U90;
/*   */     //   249: aload_3
/*   */     //   250: invokevirtual Ya : (Lf/JG0;)Lf/U90;
/*   */     //   253: pop
/*   */     //   254: invokevirtual Q2 : ()Z
/*   */     //   257: ifeq -> 431
/*   */     //   260: new f/dQ
/*   */     //   263: dup
/*   */     //   264: astore_2
/*   */     //   265: sipush #8106
/*   */     //   268: invokestatic OH0 : (I)Ljava/lang/String;
/*   */     //   271: invokespecial <init> : (Ljava/lang/String;)V
/*   */     //   274: getstatic f/nV.ko0 : [Lf/nV;
/*   */     //   277: dup
/*   */     //   278: dup
/*   */     //   279: astore_3
/*   */     //   280: arraylength
/*   */     //   281: iconst_1
/*   */     //   282: iadd
/*   */     //   283: anewarray java/lang/String
/*   */     //   286: dup
/*   */     //   287: astore #4
/*   */     //   289: iconst_0
/*   */     //   290: ldc '-'
/*   */     //   292: aastore
/*   */     //   293: arraylength
/*   */     //   294: istore #5
/*   */     //   296: iconst_0
/*   */     //   297: istore #6
/*   */     //   299: iload #6
/*   */     //   301: iload #5
/*   */     //   303: if_icmpge -> 333
/*   */     //   306: aload #4
/*   */     //   308: aload_3
/*   */     //   309: iload #6
/*   */     //   311: aaload
/*   */     //   312: dup
/*   */     //   313: invokevirtual LPt8 : ()B
/*   */     //   316: iconst_1
/*   */     //   317: iadd
/*   */     //   318: istore #7
/*   */     //   320: invokevirtual cK0 : ()Ljava/lang/String;
/*   */     //   323: iload #7
/*   */     //   325: swap
/*   */     //   326: aastore
/*   */     //   327: iinc #6, 1
/*   */     //   330: goto -> 299
/*   */     //   333: aload_0
/*   */     //   334: dup
/*   */     //   335: new f/OZ
/*   */     //   338: dup
/*   */     //   339: astore_3
/*   */     //   340: aload #4
/*   */     //   342: invokespecial <init> : ([Ljava/lang/Object;)V
/*   */     //   345: new f/W1
/*   */     //   348: dup
/*   */     //   349: aload_0
/*   */     //   350: swap
/*   */     //   351: dup
/*   */     //   352: aload_3
/*   */     //   353: invokespecial <init> : (Lf/cQ;)V
/*   */     //   356: putfield L00 : Lf/W1;
/*   */     //   359: iconst_0
/*   */     //   360: invokevirtual Z30 : (I)V
/*   */     //   363: getfield fu0 : Lf/Ip;
/*   */     //   366: invokevirtual xh : ()Lf/U90;
/*   */     //   369: aload_0
/*   */     //   370: getfield fu0 : Lf/Ip;
/*   */     //   373: invokevirtual mE0 : ()Lf/g0;
/*   */     //   376: iconst_2
/*   */     //   377: anewarray f/JG0
/*   */     //   380: dup
/*   */     //   381: dup
/*   */     //   382: aload_0
/*   */     //   383: swap
/*   */     //   384: iconst_0
/*   */     //   385: aload_2
/*   */     //   386: aastore
/*   */     //   387: getfield L00 : Lf/W1;
/*   */     //   390: iconst_1
/*   */     //   391: swap
/*   */     //   392: aastore
/*   */     //   393: invokevirtual Mg : ([Lf/JG0;)Lf/U90;
/*   */     //   396: invokevirtual ee0 : (Lf/U90;)Lf/U90;
/*   */     //   399: pop
/*   */     //   400: getfield fu0 : Lf/Ip;
/*   */     //   403: invokevirtual iJ0 : ()Lf/U90;
/*   */     //   406: aload_0
/*   */     //   407: getfield fu0 : Lf/Ip;
/*   */     //   410: invokevirtual d7 : ()Lf/cr0;
/*   */     //   413: aload_2
/*   */     //   414: invokevirtual Ya : (Lf/JG0;)Lf/U90;
/*   */     //   417: invokevirtual Em0 : ()Lf/U90;
/*   */     //   420: aload_0
/*   */     //   421: getfield L00 : Lf/W1;
/*   */     //   424: invokevirtual Ya : (Lf/JG0;)Lf/U90;
/*   */     //   427: invokevirtual ee0 : (Lf/U90;)Lf/U90;
/*   */     //   430: pop
/*   */     //   431: aload_0
/*   */     //   432: getfield qk : Lf/MM;
/*   */     //   435: invokevirtual ZN : ()Z
/*   */     //   438: ifeq -> 583
/*   */     //   441: aload_0
/*   */     //   442: dup
/*   */     //   443: new f/dQ
/*   */     //   446: dup
/*   */     //   447: astore_2
/*   */     //   448: sipush #8100
/*   */     //   451: invokestatic OH0 : (I)Ljava/lang/String;
/*   */     //   454: invokespecial <init> : (Ljava/lang/String;)V
/*   */     //   457: iconst_3
/*   */     //   458: anewarray java/lang/String
/*   */     //   461: dup
/*   */     //   462: dup2
/*   */     //   463: astore_3
/*   */     //   464: iconst_0
/*   */     //   465: ldc '-'
/*   */     //   467: aastore
/*   */     //   468: sipush #8101
/*   */     //   471: invokestatic OH0 : (I)Ljava/lang/String;
/*   */     //   474: iconst_1
/*   */     //   475: swap
/*   */     //   476: aastore
/*   */     //   477: sipush #8102
/*   */     //   480: invokestatic OH0 : (I)Ljava/lang/String;
/*   */     //   483: iconst_2
/*   */     //   484: swap
/*   */     //   485: aastore
/*   */     //   486: new f/OZ
/*   */     //   489: dup
/*   */     //   490: astore #4
/*   */     //   492: aload_3
/*   */     //   493: invokespecial <init> : ([Ljava/lang/Object;)V
/*   */     //   496: new f/W1
/*   */     //   499: dup
/*   */     //   500: aload_0
/*   */     //   501: swap
/*   */     //   502: dup
/*   */     //   503: aload #4
/*   */     //   505: invokespecial <init> : (Lf/cQ;)V
/*   */     //   508: putfield ro : Lf/W1;
/*   */     //   511: iconst_0
/*   */     //   512: invokevirtual Z30 : (I)V
/*   */     //   515: getfield fu0 : Lf/Ip;
/*   */     //   518: invokevirtual xh : ()Lf/U90;
/*   */     //   521: aload_0
/*   */     //   522: getfield fu0 : Lf/Ip;
/*   */     //   525: invokevirtual mE0 : ()Lf/g0;
/*   */     //   528: iconst_2
/*   */     //   529: anewarray f/JG0
/*   */     //   532: dup
/*   */     //   533: dup
/*   */     //   534: aload_0
/*   */     //   535: swap
/*   */     //   536: iconst_0
/*   */     //   537: aload_2
/*   */     //   538: aastore
/*   */     //   539: getfield ro : Lf/W1;
/*   */     //   542: iconst_1
/*   */     //   543: swap
/*   */     //   544: aastore
/*   */     //   545: invokevirtual Mg : ([Lf/JG0;)Lf/U90;
/*   */     //   548: invokevirtual ee0 : (Lf/U90;)Lf/U90;
/*   */     //   551: pop
/*   */     //   552: getfield fu0 : Lf/Ip;
/*   */     //   555: invokevirtual iJ0 : ()Lf/U90;
/*   */     //   558: aload_0
/*   */     //   559: getfield fu0 : Lf/Ip;
/*   */     //   562: invokevirtual d7 : ()Lf/cr0;
/*   */     //   565: aload_2
/*   */     //   566: invokevirtual Ya : (Lf/JG0;)Lf/U90;
/*   */     //   569: invokevirtual Em0 : ()Lf/U90;
/*   */     //   572: aload_0
/*   */     //   573: getfield ro : Lf/W1;
/*   */     //   576: invokevirtual Ya : (Lf/JG0;)Lf/U90;
/*   */     //   579: invokevirtual ee0 : (Lf/U90;)Lf/U90;
/*   */     //   582: pop
/*   */     //   583: aload_0
/*   */     //   584: dup
/*   */     //   585: getfield qk : Lf/MM;
/*   */     //   588: invokevirtual oZ : ()B
/*   */     //   591: anewarray f/W1
/*   */     //   594: putfield Gy : [Lf/W1;
/*   */     //   597: new java/util/ArrayList
/*   */     //   600: dup
/*   */     //   601: dup
/*   */     //   602: astore_2
/*   */     //   603: invokespecial <init> : ()V
/*   */     //   606: invokestatic cw : ()Lf/yk0;
/*   */     //   609: iconst_0
/*   */     //   610: invokevirtual mP : (S)Lf/WD;
/*   */     //   613: invokevirtual add : (Ljava/lang/Object;)Z
/*   */     //   616: pop
/*   */     //   617: invokestatic cw : ()Lf/yk0;
/*   */     //   620: invokevirtual jQ : ()Lf/iL;
/*   */     //   623: invokevirtual iterator : ()Ljava/util/Iterator;
/*   */     //   626: astore_3
/*   */     //   627: aload_3
/*   */     //   628: checkcast f/DA0
/*   */     //   631: invokevirtual hasNext : ()Z
/*   */     //   634: ifeq -> 707
/*   */     //   637: aload_3
/*   */     //   638: checkcast f/Ke
/*   */     //   641: invokevirtual next : ()Ljava/lang/Object;
/*   */     //   644: checkcast f/WD
/*   */     //   647: dup
/*   */     //   648: astore #4
/*   */     //   650: invokevirtual xF0 : ()S
/*   */     //   653: iconst_1
/*   */     //   654: if_icmplt -> 627
/*   */     //   657: aload #4
/*   */     //   659: invokevirtual Pj0 : ()Z
/*   */     //   662: ifeq -> 668
/*   */     //   665: goto -> 627
/*   */     //   668: aload_1
/*   */     //   669: aload_0
/*   */     //   670: aload #4
/*   */     //   672: invokevirtual xF0 : ()S
/*   */     //   675: istore #5
/*   */     //   677: getfield qk : Lf/MM;
/*   */     //   680: invokevirtual getClass : ()Ljava/lang/Class;
/*   */     //   683: pop
/*   */     //   684: bipush #50
/*   */     //   686: iload #5
/*   */     //   688: invokevirtual W40 : (BS)Z
/*   */     //   691: ifne -> 697
/*   */     //   694: goto -> 627
/*   */     //   697: aload_2
/*   */     //   698: aload #4
/*   */     //   700: invokevirtual add : (Ljava/lang/Object;)Z
/*   */     //   703: pop
/*   */     //   704: goto -> 627
/*   */     //   707: aload_0
/*   */     //   708: aload_2
/*   */     //   709: dup
/*   */     //   710: getstatic f/WD.Fw0 : Ljava/util/Comparator;
/*   */     //   713: invokestatic sort : (Ljava/util/List;Ljava/util/Comparator;)V
/*   */     //   716: iconst_0
/*   */     //   717: anewarray f/WD
/*   */     //   720: invokevirtual toArray : ([Ljava/lang/Object;)[Ljava/lang/Object;
/*   */     //   723: checkcast [Lf/WD;
/*   */     //   726: putfield o20 : [Lf/WD;
/*   */     //   729: iconst_0
/*   */     //   730: istore_1
/*   */     //   731: iload_1
/*   */     //   732: aload_0
/*   */     //   733: getfield qk : Lf/MM;
/*   */     //   736: invokevirtual oZ : ()B
/*   */     //   739: if_icmpge -> 885
/*   */     //   742: aload_0
/*   */     //   743: dup
/*   */     //   744: dup2
/*   */     //   745: new f/dQ
/*   */     //   748: dup
/*   */     //   749: astore_2
/*   */     //   750: iload_1
/*   */     //   751: iconst_1
/*   */     //   752: iadd
/*   */     //   753: dup
/*   */     //   754: istore_3
/*   */     //   755: invokestatic toString : (I)Ljava/lang/String;
/*   */     //   758: sipush #5616
/*   */     //   761: swap
/*   */     //   762: invokestatic Go : (ILjava/lang/String;)Ljava/lang/String;
/*   */     //   765: invokespecial <init> : (Ljava/lang/String;)V
/*   */     //   768: new f/OZ
/*   */     //   771: dup
/*   */     //   772: astore #4
/*   */     //   774: aload_0
/*   */     //   775: getfield o20 : [Lf/WD;
/*   */     //   778: invokespecial <init> : ([Ljava/lang/Object;)V
/*   */     //   781: getfield Gy : [Lf/W1;
/*   */     //   784: iload_1
/*   */     //   785: new f/W1
/*   */     //   788: dup
/*   */     //   789: astore #5
/*   */     //   791: aload #4
/*   */     //   793: invokespecial <init> : (Lf/cQ;)V
/*   */     //   796: aload #5
/*   */     //   798: aastore
/*   */     //   799: getfield Gy : [Lf/W1;
/*   */     //   802: iload_1
/*   */     //   803: aaload
/*   */     //   804: iconst_0
/*   */     //   805: invokevirtual Z30 : (I)V
/*   */     //   808: getfield fu0 : Lf/Ip;
/*   */     //   811: invokevirtual xh : ()Lf/U90;
/*   */     //   814: aload_0
/*   */     //   815: getfield fu0 : Lf/Ip;
/*   */     //   818: invokevirtual mE0 : ()Lf/g0;
/*   */     //   821: iconst_2
/*   */     //   822: anewarray f/JG0
/*   */     //   825: dup
/*   */     //   826: dup
/*   */     //   827: aload_0
/*   */     //   828: swap
/*   */     //   829: iconst_0
/*   */     //   830: aload_2
/*   */     //   831: aastore
/*   */     //   832: getfield Gy : [Lf/W1;
/*   */     //   835: iload_1
/*   */     //   836: aaload
/*   */     //   837: iconst_1
/*   */     //   838: swap
/*   */     //   839: aastore
/*   */     //   840: invokevirtual Mg : ([Lf/JG0;)Lf/U90;
/*   */     //   843: invokevirtual ee0 : (Lf/U90;)Lf/U90;
/*   */     //   846: pop
/*   */     //   847: getfield fu0 : Lf/Ip;
/*   */     //   850: invokevirtual iJ0 : ()Lf/U90;
/*   */     //   853: aload_0
/*   */     //   854: getfield fu0 : Lf/Ip;
/*   */     //   857: invokevirtual d7 : ()Lf/cr0;
/*   */     //   860: aload_2
/*   */     //   861: invokevirtual Ya : (Lf/JG0;)Lf/U90;
/*   */     //   864: invokevirtual Em0 : ()Lf/U90;
/*   */     //   867: aload_0
/*   */     //   868: getfield Gy : [Lf/W1;
/*   */     //   871: iload_1
/*   */     //   872: aaload
/*   */     //   873: invokevirtual Ya : (Lf/JG0;)Lf/U90;
/*   */     //   876: invokevirtual ee0 : (Lf/U90;)Lf/U90;
/*   */     //   879: pop
/*   */     //   880: iload_3
/*   */     //   881: istore_1
/*   */     //   882: goto -> 731
/*   */     //   885: aload_0
/*   */     //   886: getfield qk : Lf/MM;
/*   */     //   889: invokevirtual F7 : ()B
/*   */     //   892: ifle -> 1694
/*   */     //   895: aload_0
/*   */     //   896: dup
/*   */     //   897: dup2
/*   */     //   898: new f/dQ
/*   */     //   901: dup
/*   */     //   902: astore_1
/*   */     //   903: aload_0
/*   */     //   904: getfield qk : Lf/MM;
/*   */     //   907: invokevirtual F7 : ()B
/*   */     //   910: invokestatic toString : (I)Ljava/lang/String;
/*   */     //   913: sipush #9110
/*   */     //   916: swap
/*   */     //   917: invokestatic Go : (ILjava/lang/String;)Ljava/lang/String;
/*   */     //   920: invokespecial <init> : (Ljava/lang/String;)V
/*   */     //   923: getfield fu0 : Lf/Ip;
/*   */     //   926: invokevirtual xh : ()Lf/U90;
/*   */     //   929: aload_1
/*   */     //   930: invokevirtual Ya : (Lf/JG0;)Lf/U90;
/*   */     //   933: pop
/*   */     //   934: getfield fu0 : Lf/Ip;
/*   */     //   937: invokevirtual iJ0 : ()Lf/U90;
/*   */     //   940: aload_1
/*   */     //   941: invokevirtual Ya : (Lf/JG0;)Lf/U90;
/*   */     //   944: pop
/*   */     //   945: bipush #6
/*   */     //   947: anewarray f/ge0
/*   */     //   950: putfield Ug : [Lf/ge0;
/*   */     //   953: bipush #6
/*   */     //   955: anewarray f/dQ
/*   */     //   958: astore_1
/*   */     //   959: bipush #6
/*   */     //   961: anewarray f/Rm
/*   */     //   964: putfield Vj0 : [Lf/Rm;
/*   */     //   967: iconst_0
/*   */     //   968: istore_2
/*   */     //   969: iload_2
/*   */     //   970: getstatic f/hR.Tm0 : [Lf/hR;
/*   */     //   973: dup
/*   */     //   974: astore_3
/*   */     //   975: arraylength
/*   */     //   976: if_icmpge -> 1097
/*   */     //   979: aload_0
/*   */     //   980: dup
/*   */     //   981: dup
/*   */     //   982: dup2
/*   */     //   983: aload_3
/*   */     //   984: iload_2
/*   */     //   985: aaload
/*   */     //   986: astore_3
/*   */     //   987: new f/dQ
/*   */     //   990: dup
/*   */     //   991: astore #4
/*   */     //   993: aload_1
/*   */     //   994: iload_2
/*   */     //   995: aload #4
/*   */     //   997: aload_3
/*   */     //   998: invokevirtual toString : ()Ljava/lang/String;
/*   */     //   1001: invokespecial <init> : (Ljava/lang/String;)V
/*   */     //   1004: aload #4
/*   */     //   1006: aastore
/*   */     //   1007: ldc 'label-title'
/*   */     //   1009: invokevirtual Xu : (Ljava/lang/String;)V
/*   */     //   1012: new f/zT
/*   */     //   1015: dup
/*   */     //   1016: astore_3
/*   */     //   1017: iconst_0
/*   */     //   1018: bipush #31
/*   */     //   1020: bipush #31
/*   */     //   1022: invokespecial <init> : (III)V
/*   */     //   1025: getfield Vj0 : [Lf/Rm;
/*   */     //   1028: iload_2
/*   */     //   1029: new f/Rm
/*   */     //   1032: dup
/*   */     //   1033: astore #4
/*   */     //   1035: aload_3
/*   */     //   1036: invokespecial <init> : (Lf/zT;)V
/*   */     //   1039: aload #4
/*   */     //   1041: aastore
/*   */     //   1042: getfield Vj0 : [Lf/Rm;
/*   */     //   1045: iload_2
/*   */     //   1046: aaload
/*   */     //   1047: ldc_w 'valueadjuster-small'
/*   */     //   1050: invokevirtual Xu : (Ljava/lang/String;)V
/*   */     //   1053: getfield Vj0 : [Lf/Rm;
/*   */     //   1056: iload_2
/*   */     //   1057: aaload
/*   */     //   1058: iconst_0
/*   */     //   1059: invokevirtual sk0 : (Z)V
/*   */     //   1062: getfield Ug : [Lf/ge0;
/*   */     //   1065: iload_2
/*   */     //   1066: new f/ge0
/*   */     //   1069: dup
/*   */     //   1070: astore_3
/*   */     //   1071: invokespecial <init> : ()V
/*   */     //   1074: aload_3
/*   */     //   1075: aastore
/*   */     //   1076: getfield Ug : [Lf/ge0;
/*   */     //   1079: iload_2
/*   */     //   1080: aaload
/*   */     //   1081: aload_0
/*   */     //   1082: iload_2
/*   */     //   1083: <illegal opcode> run : (Lf/zD0;I)Ljava/lang/Runnable;
/*   */     //   1088: invokevirtual tW : (Ljava/lang/Runnable;)V
/*   */     //   1091: iinc #2, 1
/*   */     //   1094: goto -> 969
/*   */     //   1097: aload_0
/*   */     //   1098: dup
/*   */     //   1099: dup2
/*   */     //   1100: getfield fu0 : Lf/Ip;
/*   */     //   1103: invokevirtual d7 : ()Lf/cr0;
/*   */     //   1106: aload_0
/*   */     //   1107: getfield fu0 : Lf/Ip;
/*   */     //   1110: invokevirtual mE0 : ()Lf/g0;
/*   */     //   1113: iconst_3
/*   */     //   1114: anewarray f/JG0
/*   */     //   1117: dup
/*   */     //   1118: dup
/*   */     //   1119: astore_2
/*   */     //   1120: aload_0
/*   */     //   1121: aload_2
/*   */     //   1122: aload_0
/*   */     //   1123: aload_2
/*   */     //   1124: aload_1
/*   */     //   1125: iconst_0
/*   */     //   1126: aaload
/*   */     //   1127: iconst_0
/*   */     //   1128: swap
/*   */     //   1129: aastore
/*   */     //   1130: getfield Ug : [Lf/ge0;
/*   */     //   1133: iconst_0
/*   */     //   1134: aaload
/*   */     //   1135: iconst_1
/*   */     //   1136: swap
/*   */     //   1137: aastore
/*   */     //   1138: getfield Vj0 : [Lf/Rm;
/*   */     //   1141: iconst_0
/*   */     //   1142: aaload
/*   */     //   1143: iconst_2
/*   */     //   1144: swap
/*   */     //   1145: aastore
/*   */     //   1146: invokevirtual Mg : ([Lf/JG0;)Lf/U90;
/*   */     //   1149: invokevirtual ee0 : (Lf/U90;)Lf/U90;
/*   */     //   1152: aload_0
/*   */     //   1153: getfield fu0 : Lf/Ip;
/*   */     //   1156: invokevirtual mE0 : ()Lf/g0;
/*   */     //   1159: iconst_3
/*   */     //   1160: anewarray f/JG0
/*   */     //   1163: dup
/*   */     //   1164: dup
/*   */     //   1165: astore_2
/*   */     //   1166: aload_0
/*   */     //   1167: aload_2
/*   */     //   1168: aload_0
/*   */     //   1169: aload_2
/*   */     //   1170: aload_1
/*   */     //   1171: iconst_1
/*   */     //   1172: aaload
/*   */     //   1173: iconst_0
/*   */     //   1174: swap
/*   */     //   1175: aastore
/*   */     //   1176: getfield Ug : [Lf/ge0;
/*   */     //   1179: iconst_1
/*   */     //   1180: aaload
/*   */     //   1181: iconst_1
/*   */     //   1182: swap
/*   */     //   1183: aastore
/*   */     //   1184: getfield Vj0 : [Lf/Rm;
/*   */     //   1187: iconst_1
/*   */     //   1188: aaload
/*   */     //   1189: iconst_2
/*   */     //   1190: swap
/*   */     //   1191: aastore
/*   */     //   1192: invokevirtual Mg : ([Lf/JG0;)Lf/U90;
/*   */     //   1195: invokevirtual ee0 : (Lf/U90;)Lf/U90;
/*   */     //   1198: aload_0
/*   */     //   1199: getfield fu0 : Lf/Ip;
/*   */     //   1202: invokevirtual mE0 : ()Lf/g0;
/*   */     //   1205: iconst_3
/*   */     //   1206: anewarray f/JG0
/*   */     //   1209: dup
/*   */     //   1210: dup
/*   */     //   1211: astore_2
/*   */     //   1212: aload_0
/*   */     //   1213: aload_2
/*   */     //   1214: aload_0
/*   */     //   1215: aload_2
/*   */     //   1216: aload_1
/*   */     //   1217: iconst_2
/*   */     //   1218: aaload
/*   */     //   1219: iconst_0
/*   */     //   1220: swap
/*   */     //   1221: aastore
/*   */     //   1222: getfield Ug : [Lf/ge0;
/*   */     //   1225: iconst_2
/*   */     //   1226: aaload
/*   */     //   1227: iconst_1
/*   */     //   1228: swap
/*   */     //   1229: aastore
/*   */     //   1230: getfield Vj0 : [Lf/Rm;
/*   */     //   1233: iconst_2
/*   */     //   1234: aaload
/*   */     //   1235: iconst_2
/*   */     //   1236: swap
/*   */     //   1237: aastore
/*   */     //   1238: invokevirtual Mg : ([Lf/JG0;)Lf/U90;
/*   */     //   1241: invokevirtual ee0 : (Lf/U90;)Lf/U90;
/*   */     //   1244: aload_0
/*   */     //   1245: getfield fu0 : Lf/Ip;
/*   */     //   1248: invokevirtual mE0 : ()Lf/g0;
/*   */     //   1251: iconst_3
/*   */     //   1252: anewarray f/JG0
/*   */     //   1255: dup
/*   */     //   1256: dup
/*   */     //   1257: astore_2
/*   */     //   1258: aload_0
/*   */     //   1259: aload_2
/*   */     //   1260: aload_0
/*   */     //   1261: aload_2
/*   */     //   1262: aload_1
/*   */     //   1263: iconst_3
/*   */     //   1264: aaload
/*   */     //   1265: iconst_0
/*   */     //   1266: swap
/*   */     //   1267: aastore
/*   */     //   1268: getfield Ug : [Lf/ge0;
/*   */     //   1271: iconst_3
/*   */     //   1272: aaload
/*   */     //   1273: iconst_1
/*   */     //   1274: swap
/*   */     //   1275: aastore
/*   */     //   1276: getfield Vj0 : [Lf/Rm;
/*   */     //   1279: iconst_3
/*   */     //   1280: aaload
/*   */     //   1281: iconst_2
/*   */     //   1282: swap
/*   */     //   1283: aastore
/*   */     //   1284: invokevirtual Mg : ([Lf/JG0;)Lf/U90;
/*   */     //   1287: invokevirtual ee0 : (Lf/U90;)Lf/U90;
/*   */     //   1290: aload_0
/*   */     //   1291: getfield fu0 : Lf/Ip;
/*   */     //   1294: invokevirtual mE0 : ()Lf/g0;
/*   */     //   1297: iconst_3
/*   */     //   1298: anewarray f/JG0
/*   */     //   1301: dup
/*   */     //   1302: dup
/*   */     //   1303: astore_2
/*   */     //   1304: aload_0
/*   */     //   1305: aload_2
/*   */     //   1306: aload_0
/*   */     //   1307: aload_2
/*   */     //   1308: aload_1
/*   */     //   1309: iconst_4
/*   */     //   1310: aaload
/*   */     //   1311: iconst_0
/*   */     //   1312: swap
/*   */     //   1313: aastore
/*   */     //   1314: getfield Ug : [Lf/ge0;
/*   */     //   1317: iconst_4
/*   */     //   1318: aaload
/*   */     //   1319: iconst_1
/*   */     //   1320: swap
/*   */     //   1321: aastore
/*   */     //   1322: getfield Vj0 : [Lf/Rm;
/*   */     //   1325: iconst_4
/*   */     //   1326: aaload
/*   */     //   1327: iconst_2
/*   */     //   1328: swap
/*   */     //   1329: aastore
/*   */     //   1330: invokevirtual Mg : ([Lf/JG0;)Lf/U90;
/*   */     //   1333: invokevirtual ee0 : (Lf/U90;)Lf/U90;
/*   */     //   1336: aload_0
/*   */     //   1337: getfield fu0 : Lf/Ip;
/*   */     //   1340: invokevirtual mE0 : ()Lf/g0;
/*   */     //   1343: iconst_3
/*   */     //   1344: anewarray f/JG0
/*   */     //   1347: dup
/*   */     //   1348: dup
/*   */     //   1349: astore_2
/*   */     //   1350: aload_0
/*   */     //   1351: aload_2
/*   */     //   1352: aload_0
/*   */     //   1353: aload_2
/*   */     //   1354: aload_1
/*   */     //   1355: iconst_5
/*   */     //   1356: aaload
/*   */     //   1357: iconst_0
/*   */     //   1358: swap
/*   */     //   1359: aastore
/*   */     //   1360: getfield Ug : [Lf/ge0;
/*   */     //   1363: iconst_5
/*   */     //   1364: aaload
/*   */     //   1365: iconst_1
/*   */     //   1366: swap
/*   */     //   1367: aastore
/*   */     //   1368: getfield Vj0 : [Lf/Rm;
/*   */     //   1371: iconst_5
/*   */     //   1372: aaload
/*   */     //   1373: iconst_2
/*   */     //   1374: swap
/*   */     //   1375: aastore
/*   */     //   1376: invokevirtual Mg : ([Lf/JG0;)Lf/U90;
/*   */     //   1379: invokevirtual ee0 : (Lf/U90;)Lf/U90;
/*   */     //   1382: astore_2
/*   */     //   1383: getfield fu0 : Lf/Ip;
/*   */     //   1386: invokevirtual mE0 : ()Lf/g0;
/*   */     //   1389: aload_0
/*   */     //   1390: getfield fu0 : Lf/Ip;
/*   */     //   1393: invokevirtual d7 : ()Lf/cr0;
/*   */     //   1396: aload_1
/*   */     //   1397: iconst_0
/*   */     //   1398: aaload
/*   */     //   1399: invokevirtual Ya : (Lf/JG0;)Lf/U90;
/*   */     //   1402: invokevirtual Em0 : ()Lf/U90;
/*   */     //   1405: iconst_2
/*   */     //   1406: anewarray f/JG0
/*   */     //   1409: dup
/*   */     //   1410: dup
/*   */     //   1411: aload_0
/*   */     //   1412: swap
/*   */     //   1413: aload_0
/*   */     //   1414: getfield Ug : [Lf/ge0;
/*   */     //   1417: iconst_0
/*   */     //   1418: aaload
/*   */     //   1419: iconst_0
/*   */     //   1420: swap
/*   */     //   1421: aastore
/*   */     //   1422: getfield Vj0 : [Lf/Rm;
/*   */     //   1425: iconst_0
/*   */     //   1426: aaload
/*   */     //   1427: iconst_1
/*   */     //   1428: swap
/*   */     //   1429: aastore
/*   */     //   1430: invokevirtual Mg : ([Lf/JG0;)Lf/U90;
/*   */     //   1433: invokevirtual ee0 : (Lf/U90;)Lf/U90;
/*   */     //   1436: aload_0
/*   */     //   1437: getfield fu0 : Lf/Ip;
/*   */     //   1440: invokevirtual d7 : ()Lf/cr0;
/*   */     //   1443: aload_1
/*   */     //   1444: iconst_1
/*   */     //   1445: aaload
/*   */     //   1446: invokevirtual Ya : (Lf/JG0;)Lf/U90;
/*   */     //   1449: invokevirtual Em0 : ()Lf/U90;
/*   */     //   1452: iconst_2
/*   */     //   1453: anewarray f/JG0
/*   */     //   1456: dup
/*   */     //   1457: dup
/*   */     //   1458: aload_0
/*   */     //   1459: swap
/*   */     //   1460: aload_0
/*   */     //   1461: getfield Ug : [Lf/ge0;
/*   */     //   1464: iconst_1
/*   */     //   1465: aaload
/*   */     //   1466: iconst_0
/*   */     //   1467: swap
/*   */     //   1468: aastore
/*   */     //   1469: getfield Vj0 : [Lf/Rm;
/*   */     //   1472: iconst_1
/*   */     //   1473: aaload
/*   */     //   1474: iconst_1
/*   */     //   1475: swap
/*   */     //   1476: aastore
/*   */     //   1477: invokevirtual Mg : ([Lf/JG0;)Lf/U90;
/*   */     //   1480: invokevirtual ee0 : (Lf/U90;)Lf/U90;
/*   */     //   1483: aload_0
/*   */     //   1484: getfield fu0 : Lf/Ip;
/*   */     //   1487: invokevirtual d7 : ()Lf/cr0;
/*   */     //   1490: aload_1
/*   */     //   1491: iconst_2
/*   */     //   1492: aaload
/*   */     //   1493: invokevirtual Ya : (Lf/JG0;)Lf/U90;
/*   */     //   1496: invokevirtual Em0 : ()Lf/U90;
/*   */     //   1499: iconst_2
/*   */     //   1500: anewarray f/JG0
/*   */     //   1503: dup
/*   */     //   1504: dup
/*   */     //   1505: aload_0
/*   */     //   1506: swap
/*   */     //   1507: aload_0
/*   */     //   1508: getfield Ug : [Lf/ge0;
/*   */     //   1511: iconst_2
/*   */     //   1512: aaload
/*   */     //   1513: iconst_0
/*   */     //   1514: swap
/*   */     //   1515: aastore
/*   */     //   1516: getfield Vj0 : [Lf/Rm;
/*   */     //   1519: iconst_2
/*   */     //   1520: aaload
/*   */     //   1521: iconst_1
/*   */     //   1522: swap
/*   */     //   1523: aastore
/*   */     //   1524: invokevirtual Mg : ([Lf/JG0;)Lf/U90;
/*   */     //   1527: invokevirtual ee0 : (Lf/U90;)Lf/U90;
/*   */     //   1530: aload_0
/*   */     //   1531: getfield fu0 : Lf/Ip;
/*   */     //   1534: invokevirtual d7 : ()Lf/cr0;
/*   */     //   1537: aload_1
/*   */     //   1538: iconst_3
/*   */     //   1539: aaload
/*   */     //   1540: invokevirtual Ya : (Lf/JG0;)Lf/U90;
/*   */     //   1543: invokevirtual Em0 : ()Lf/U90;
/*   */     //   1546: iconst_2
/*   */     //   1547: anewarray f/JG0
/*   */     //   1550: dup
/*   */     //   1551: dup
/*   */     //   1552: aload_0
/*   */     //   1553: swap
/*   */     //   1554: aload_0
/*   */     //   1555: getfield Ug : [Lf/ge0;
/*   */     //   1558: iconst_3
/*   */     //   1559: aaload
/*   */     //   1560: iconst_0
/*   */     //   1561: swap
/*   */     //   1562: aastore
/*   */     //   1563: getfield Vj0 : [Lf/Rm;
/*   */     //   1566: iconst_3
/*   */     //   1567: aaload
/*   */     //   1568: iconst_1
/*   */     //   1569: swap
/*   */     //   1570: aastore
/*   */     //   1571: invokevirtual Mg : ([Lf/JG0;)Lf/U90;
/*   */     //   1574: invokevirtual ee0 : (Lf/U90;)Lf/U90;
/*   */     //   1577: aload_0
/*   */     //   1578: getfield fu0 : Lf/Ip;
/*   */     //   1581: invokevirtual d7 : ()Lf/cr0;
/*   */     //   1584: aload_1
/*   */     //   1585: iconst_4
/*   */     //   1586: aaload
/*   */     //   1587: invokevirtual Ya : (Lf/JG0;)Lf/U90;
/*   */     //   1590: invokevirtual Em0 : ()Lf/U90;
/*   */     //   1593: iconst_2
/*   */     //   1594: anewarray f/JG0
/*   */     //   1597: dup
/*   */     //   1598: dup
/*   */     //   1599: aload_0
/*   */     //   1600: swap
/*   */     //   1601: aload_0
/*   */     //   1602: getfield Ug : [Lf/ge0;
/*   */     //   1605: iconst_4
/*   */     //   1606: aaload
/*   */     //   1607: iconst_0
/*   */     //   1608: swap
/*   */     //   1609: aastore
/*   */     //   1610: getfield Vj0 : [Lf/Rm;
/*   */     //   1613: iconst_4
/*   */     //   1614: aaload
/*   */     //   1615: iconst_1
/*   */     //   1616: swap
/*   */     //   1617: aastore
/*   */     //   1618: invokevirtual Mg : ([Lf/JG0;)Lf/U90;
/*   */     //   1621: invokevirtual ee0 : (Lf/U90;)Lf/U90;
/*   */     //   1624: aload_0
/*   */     //   1625: getfield fu0 : Lf/Ip;
/*   */     //   1628: invokevirtual d7 : ()Lf/cr0;
/*   */     //   1631: aload_1
/*   */     //   1632: iconst_5
/*   */     //   1633: aaload
/*   */     //   1634: invokevirtual Ya : (Lf/JG0;)Lf/U90;
/*   */     //   1637: invokevirtual Em0 : ()Lf/U90;
/*   */     //   1640: iconst_2
/*   */     //   1641: anewarray f/JG0
/*   */     //   1644: dup
/*   */     //   1645: dup
/*   */     //   1646: aload_0
/*   */     //   1647: swap
/*   */     //   1648: aload_0
/*   */     //   1649: getfield Ug : [Lf/ge0;
/*   */     //   1652: iconst_5
/*   */     //   1653: aaload
/*   */     //   1654: iconst_0
/*   */     //   1655: swap
/*   */     //   1656: aastore
/*   */     //   1657: getfield Vj0 : [Lf/Rm;
/*   */     //   1660: iconst_5
/*   */     //   1661: aaload
/*   */     //   1662: iconst_1
/*   */     //   1663: swap
/*   */     //   1664: aastore
/*   */     //   1665: invokevirtual Mg : ([Lf/JG0;)Lf/U90;
/*   */     //   1668: invokevirtual ee0 : (Lf/U90;)Lf/U90;
/*   */     //   1671: astore_1
/*   */     //   1672: getfield fu0 : Lf/Ip;
/*   */     //   1675: invokevirtual xh : ()Lf/U90;
/*   */     //   1678: aload_2
/*   */     //   1679: invokevirtual ee0 : (Lf/U90;)Lf/U90;
/*   */     //   1682: pop
/*   */     //   1683: getfield fu0 : Lf/Ip;
/*   */     //   1686: invokevirtual iJ0 : ()Lf/U90;
/*   */     //   1689: aload_1
/*   */     //   1690: invokevirtual ee0 : (Lf/U90;)Lf/U90;
/*   */     //   1693: pop
/*   */     //   1694: aload_0
/*   */     //   1695: dup
/*   */     //   1696: new f/Un
/*   */     //   1699: dup
/*   */     //   1700: dup
/*   */     //   1701: astore_1
/*   */     //   1702: bipush #52
/*   */     //   1704: invokestatic OH0 : (I)Ljava/lang/String;
/*   */     //   1707: invokespecial <init> : (Ljava/lang/String;)V
/*   */     //   1710: new f/cF0
/*   */     //   1713: dup
/*   */     //   1714: aload_0
/*   */     //   1715: invokespecial <init> : (Lf/zD0;)V
/*   */     //   1718: invokevirtual tW : (Ljava/lang/Runnable;)V
/*   */     //   1721: getfield fu0 : Lf/Ip;
/*   */     //   1724: invokevirtual xh : ()Lf/U90;
/*   */     //   1727: aload_1
/*   */     //   1728: invokevirtual Ya : (Lf/JG0;)Lf/U90;
/*   */     //   1731: pop
/*   */     //   1732: getfield fu0 : Lf/Ip;
/*   */     //   1735: invokevirtual iJ0 : ()Lf/U90;
/*   */     //   1738: aload_1
/*   */     //   1739: invokevirtual Ya : (Lf/JG0;)Lf/U90;
/*   */     //   1742: pop
/*   */     //   1743: aload_0
/*   */     //   1744: dup
/*   */     //   1745: dup2
/*   */     //   1746: new f/Un
/*   */     //   1749: dup
/*   */     //   1750: astore_1
/*   */     //   1751: aload_0
/*   */     //   1752: aload_1
/*   */     //   1753: bipush #53
/*   */     //   1755: invokestatic OH0 : (I)Ljava/lang/String;
/*   */     //   1758: invokespecial <init> : (Ljava/lang/String;)V
/*   */     //   1761: <illegal opcode> run : (Lf/zD0;)Ljava/lang/Runnable;
/*   */     //   1766: invokevirtual tW : (Ljava/lang/Runnable;)V
/*   */     //   1769: getfield fu0 : Lf/Ip;
/*   */     //   1772: invokevirtual xh : ()Lf/U90;
/*   */     //   1775: bipush #25
/*   */     //   1777: invokevirtual Aq : (I)Lf/U90;
/*   */     //   1780: aload_1
/*   */     //   1781: invokevirtual Ya : (Lf/JG0;)Lf/U90;
/*   */     //   1784: pop
/*   */     //   1785: getfield fu0 : Lf/Ip;
/*   */     //   1788: invokevirtual iJ0 : ()Lf/U90;
/*   */     //   1791: aload_1
/*   */     //   1792: invokevirtual Ya : (Lf/JG0;)Lf/U90;
/*   */     //   1795: pop
/*   */     //   1796: getfield fu0 : Lf/Ip;
/*   */     //   1799: invokevirtual J8 : (Lf/JG0;)V
/*   */     //   1802: return
/*   */   }
/*   */   
/*   */   public final void d40() {
/*   */     super.d40();
/*   */     this.fu0.mM();
/*   */     QI();
/*   */     this.fu0.js0(et.Wi0);
/*   */   }
/*   */   
/*   */   public final void jA0() {
/*   */     super.jA0();
/*   */     Kf kf;
/*   */     if ((kf = this.ZF) != null)
/*   */       VA0.c90(this); 
/*   */   } }


/* Location:              /Users/vnnsnnt/Documents/Codespace/JavaWorkspace/RedTrainer/src/main/java/org/trainer/client/PokeMMO.jar!/f/zD0.class
 * Java compiler version: 8 (52.0)
 * JD-Core Version:       1.1.3
 */