/*  1 */ package f;public final class zn0 extends Wr { public final void Sl() { Ip ip2; if ((ip2 = this.cx0) != null) jf0(ip2);  Lo(Ml0.OH0(1390)); this.cx0 = new Ip(); (this.Z0 = new Un(Ml0.OH0(54))).tW(new on(this)); this(Ml0.OH0(1391)); Un un; Zz0 zz0; dQ dQ; (new Un()).tW(new vG0(this)); this(); (new Zz0()).Xu("dialoglayout"); U90 u901 = (new Zz0()).o30;
/*  2 */     U90 u902 = (new Zz0()).Xz0;
/*  3 */     String str2 = Ml0.OH0(1392);
/*  4 */     this(); (new dQ()).E1(str2);
/*  5 */     OZ oZ = this.M = new OZ((Object[])Xv0.k20()); (new W1())
/*  6 */       .rk0(oZ);
/*  7 */     (this.hu0 = new W1()).Xu("combobox-small"); byte b1 = 0; while (b1 < this.M
/*  8 */       .Fj
/*  9 */       .size())
/* 10 */     { if ((Xv0.nS(h1.qc))
/* 11 */         .w
/*    */ 
/*    */ 
/*    */         
/* 15 */         .equalsIgnoreCase(this.M.Fj.get(b1))) this.hu0.Z30(b1);  b1++; }  this.hu0.D30(new i7(this)); arrayOfJG02[0] = dQ; JG0[] arrayOfJG02; (arrayOfJG02 = new JG0[2])[1] = this.hu0; zz0
/* 16 */       .o30
/* 17 */       .ee0(zz0.AUX(arrayOfJG02));
/* 18 */     zz0.Xz0
/*    */       
/* 20 */       .ee0((new cr0(zz0)).Em0().Mg(arrayOfJG02).Em0());
/* 21 */     u901.l9(20); String str1 = Ml0.OH0(1393);
/* 22 */     this(); (new dQ()).E1(str1); Xv0[] arrayOfXv0; dQ[] arrayOfDQ; int j; byte b2;
/* 23 */     for (arrayOfDQ = new dQ[arrayOfXv0.length], this.di = new ge0[arrayOfXv0.length], j = (arrayOfXv0 = Xv0.Kf0).length, b2 = 0; b2 < j; )
/*    */     
/*    */     { 
/*    */ 
/*    */ 
/*    */       
/* 29 */       String str = UQ.Vr0((new StringBuilder()).append(xv0.w).append(" ["), xv0.V, "]");
/* 30 */       (new dQ()).E1(str); Xv0 xv0; arrayOfDQ[(xv0 = arrayOfXv0[b2]).Dd] = new dQ();
/* 31 */       arrayOfDQ[xv0
/* 32 */           .Dd]
/* 33 */         .Xu("label-set"); this.di[xv0
/* 34 */           .Dd] = 
/* 35 */         new ge0(); this.di[xv0
/* 36 */           .Dd]
/* 37 */         .Xu("togglebutton");
/*    */       
/* 39 */       int k = h1.Jx0().contains(xv0) ^ true; (this.di[xv0.Dd])
/* 40 */         .TG0
/* 41 */         .Fx0(k);
/* 42 */       this.di[xv0
/* 43 */           .Dd]
/* 44 */         .tW(new Com2(this, xv0)); b2++; }  JG0[] arrayOfJG01; (arrayOfJG01 = new JG0[1])[0] = dQ; zz0
/* 45 */       .o30
/* 46 */       .ee0(zz0.AUX(arrayOfJG01));
/* 47 */     zz0.Xz0
/*    */       
/* 49 */       .ee0((new cr0(zz0)).Em0().Mg(arrayOfJG01).Em0()); int i = 0; ge0[] arrayOfGe0; while (i < (
/* 50 */       arrayOfGe0 = this.di).length) { int k; if (i < arrayOfGe0.length - 3) { arrayOfJG0[0] = arrayOfGe0[i]; arrayOfJG0[1] = arrayOfDQ[i]; arrayOfJG0[2] = arrayOfGe0[k = i + 1]; arrayOfJG0[3] = arrayOfDQ[k]; arrayOfJG0[4] = arrayOfGe0[i += 2]; JG0[] arrayOfJG0; (arrayOfJG0 = new JG0[6])[5] = arrayOfDQ[i]; zz0.of0(arrayOfJG0); i = k + 1; } else { arrayOfJG0[0] = k[i]; JG0[] arrayOfJG0; (arrayOfJG0 = new JG0[2])[1] = arrayOfDQ[i]; zz0.of0(arrayOfJG0); }  i++; }  if (!km.XU()) { u901.Aq(5).ee0(zz0.AUX(new JG0[] { un, this.Z0 })).Aq(5); u902.ee0(zz0.vo0(new JG0[] { un }).Em0().Mg(new JG0[] { this.Z0 }).Aq(5)); } else { u901.Aq(5).ee0(zz0.AUX(new JG0[] { un })).Aq(5); u902
/*    */         
/* 52 */         .ee0((new cr0(zz0)).Em0().Ya(un)); }  zz0.WN(u901); zz0.rK0(u902); Ip ip1; (ip1 = this.cx0).getClass(); this.cx0
/*    */       
/* 54 */       .WN((new cr0(ip1)).Em0().Ya(zz0).Em0()); (ip1 = this.cx0).getClass(); this.cx0
/*    */       
/* 56 */       .rK0((new cr0(ip1)).Em0().Ya(zz0).Em0()); ip1 = this.cx0;
/* 57 */     si(ip1, Ub());
/* 58 */     if (km.XU()) { this.Z0.Xu("mobile-save-icon"); this.Z0.s6(""); Un un1 = this.Z0;
/* 59 */       si(this, Ub()); }
/*    */      }
/*    */ 
/*    */   
/*    */   public Ip cx0;
/*    */   public OZ M;
/*    */   public W1 hu0;
/*    */   public ge0[] di;
/*    */   public boolean qX;
/*    */   public Un Z0;
/*    */   
/*    */   public zn0() {
/*    */     oC oC;
/*    */     this.qX = false;
/*    */     this(this);
/*    */     TG0(oC);
/*    */     EP(1);
/*    */     jJ0(false);
/*    */     Xu("rom-panel");
/*    */     Sl();
/*    */   }
/*    */   
/*    */   public final void Xy(boolean paramBoolean) {
/*    */     // Byte code:
/*    */     //   0: iload_1
/*    */     //   1: iconst_1
/*    */     //   2: putstatic f/h1.Bb : Z
/*    */     //   5: ifeq -> 194
/*    */     //   8: aload_0
/*    */     //   9: getfield hu0 : Lf/W1;
/*    */     //   12: getfield Wa0 : Lf/A60;
/*    */     //   15: getfield go : I
/*    */     //   18: dup
/*    */     //   19: istore_1
/*    */     //   20: iconst_m1
/*    */     //   21: if_icmple -> 125
/*    */     //   24: aload_0
/*    */     //   25: getfield M : Lf/OZ;
/*    */     //   28: getfield Fj : Ljava/util/ArrayList;
/*    */     //   31: iload_1
/*    */     //   32: invokevirtual get : (I)Ljava/lang/Object;
/*    */     //   35: checkcast java/lang/String
/*    */     //   38: astore_1
/*    */     //   39: getstatic f/Xv0.Kf0 : [Lf/Xv0;
/*    */     //   42: dup
/*    */     //   43: astore_2
/*    */     //   44: arraylength
/*    */     //   45: istore_3
/*    */     //   46: iconst_0
/*    */     //   47: istore #4
/*    */     //   49: iload #4
/*    */     //   51: iload_3
/*    */     //   52: if_icmpge -> 81
/*    */     //   55: aload_2
/*    */     //   56: iload #4
/*    */     //   58: aaload
/*    */     //   59: dup
/*    */     //   60: astore #5
/*    */     //   62: getfield w : Ljava/lang/String;
/*    */     //   65: aload_1
/*    */     //   66: invokevirtual equalsIgnoreCase : (Ljava/lang/String;)Z
/*    */     //   69: ifeq -> 75
/*    */     //   72: goto -> 86
/*    */     //   75: iinc #4, 1
/*    */     //   78: goto -> 49
/*    */     //   81: getstatic f/Xv0.eC0 : Lf/Xv0;
/*    */     //   84: astore #5
/*    */     //   86: aload #5
/*    */     //   88: ifnull -> 125
/*    */     //   91: aload #5
/*    */     //   93: getfield uz0 : Ljava/lang/String;
/*    */     //   96: getstatic f/h1.qc : Ljava/lang/String;
/*    */     //   99: invokevirtual equalsIgnoreCase : (Ljava/lang/String;)Z
/*    */     //   102: ifne -> 125
/*    */     //   105: aload #5
/*    */     //   107: getfield uz0 : Ljava/lang/String;
/*    */     //   110: putstatic f/h1.qc : Ljava/lang/String;
/*    */     //   113: getstatic f/km.u4 : Lf/R8;
/*    */     //   116: dup
/*    */     //   117: astore_1
/*    */     //   118: ifnull -> 125
/*    */     //   121: aload_1
/*    */     //   122: invokevirtual Dn : ()V
/*    */     //   125: new java/util/HashSet
/*    */     //   128: dup
/*    */     //   129: astore_1
/*    */     //   130: invokespecial <init> : ()V
/*    */     //   133: iconst_0
/*    */     //   134: istore_2
/*    */     //   135: iload_2
/*    */     //   136: aload_0
/*    */     //   137: getfield di : [Lf/ge0;
/*    */     //   140: dup
/*    */     //   141: astore_3
/*    */     //   142: arraylength
/*    */     //   143: if_icmpge -> 175
/*    */     //   146: aload_3
/*    */     //   147: iload_2
/*    */     //   148: aaload
/*    */     //   149: getfield TG0 : Lf/protected;
/*    */     //   152: invokevirtual nm0 : ()Z
/*    */     //   155: ifne -> 169
/*    */     //   158: aload_1
/*    */     //   159: iload_2
/*    */     //   160: i2b
/*    */     //   161: iconst_1
/*    */     //   162: invokestatic tE : (BZ)Lf/Xv0;
/*    */     //   165: invokevirtual add : (Ljava/lang/Object;)Z
/*    */     //   168: pop
/*    */     //   169: iinc #2, 1
/*    */     //   172: goto -> 135
/*    */     //   175: aload_1
/*    */     //   176: invokestatic tz : (Ljava/util/HashSet;)Z
/*    */     //   179: ifeq -> 194
/*    */     //   182: getstatic f/km.u4 : Lf/R8;
/*    */     //   185: dup
/*    */     //   186: astore_1
/*    */     //   187: ifnull -> 194
/*    */     //   190: aload_1
/*    */     //   191: invokevirtual Dn : ()V
/*    */     //   194: aload_0
/*    */     //   195: invokestatic Td : ()Z
/*    */     //   198: pop
/*    */     //   199: invokevirtual ra0 : ()Z
/*    */     //   202: pop
/*    */     //   203: return
/*    */     // Line number table:
/*    */     //   Java source line number -> byte code offset
/*    */     //   #1	-> 12
/*    */     //   #2	-> 15
/*    */     //   #3	-> 25
/*    */     //   #4	-> 28
/*    */     //   #5	-> 32
/*    */     //   #6	-> 35
/*    */     //   #7	-> 39
/*    */     //   #8	-> 93
/*    */     //   #9	-> 96
/*    */     //   #10	-> 107
/*    */     //   #11	-> 110
/*    */     //   #12	-> 149
/*    */     //   #13	-> 152
/*    */     //   #14	-> 162
/*    */   }
/*    */   
/*    */   public final void d40() {
/*    */     if (km.XU())
/*    */       QI(); 
/*    */     super.d40();
/*    */     if (km.XU()) {
/*    */       this.Z0.mM();
/*    */       this.Z0.QJ0(et.t9, -68, 0);
/*    */     } 
/*    */   } }


/* Location:              /Users/vnnsnnt/Documents/Codespace/JavaWorkspace/RedTrainer/src/main/java/org/trainer/client/PokeMMO.jar!/f/zn0.class
 * Java compiler version: 8 (52.0)
 * JD-Core Version:       1.1.3
 */