/*  1 */ package f;public class Zq extends Qv0 { public final gO MH0; public final n3 K40; public VA Qa; public long kH; public Zq(gO paramgO, n3 paramn3, Uc0 paramUc0, short paramShort) { super(paramUc0, paramShort, b1, b2); VA vA; byte b1; byte b2; this.kH = 0L; this.MH0 = paramgO; this.K40 = paramn3; if (km.XU()) { zY().Ii0(2.0F); zY().zT(4, 0); } else { zY().zT(12, -4); }  ow(new xo()); this(this, 32, 32); this.Qa = new VA(); vA.ZH0().zT(0, -4); this.Qa.ZH0().tL(24, 24); if (km.XU()) this.Qa.ZH0().Ii0(2.0F);  } private void Dl0() { this(); Hk0 hk0; this(Ml0.OH0(2314)); (new Hk0()).rv = Zq::Zo0; b3
/*  2 */       .aV.add(this);
/*  3 */     int i = this.Kd;
/*    */     B3 b3;
/*  5 */     F7.T1(b3 = new B3(), this, i, this.er0); } public static void Zo0() { pA.Dg0.dk0.e8().zn0(true); } public final void un(Uc0 paramUc0) { // Byte code:
/*    */     //   0: aload_1
/*    */     //   1: getfield Nul : Lf/aq0;
/*    */     //   4: getstatic f/aq0.XJ0 : Lf/aq0;
/*    */     //   7: if_acmpne -> 575
/*    */     //   10: aload_0
/*    */     //   11: dup
/*    */     //   12: aload_1
/*    */     //   13: putfield MQ : Lf/Uc0;
/*    */     //   16: invokevirtual public : ()Lf/j40;
/*    */     //   19: dup
/*    */     //   20: astore_1
/*    */     //   21: ifnull -> 28
/*    */     //   24: aload_0
/*    */     //   25: invokevirtual MJ0 : ()V
/*    */     //   28: aload_0
/*    */     //   29: iconst_1
/*    */     //   30: invokevirtual wI0 : (Z)V
/*    */     //   33: ldc 'pc-slot'
/*    */     //   35: dup
/*    */     //   36: astore_2
/*    */     //   37: aload_0
/*    */     //   38: getfield cl : Ljava/lang/String;
/*    */     //   41: invokevirtual equals : (Ljava/lang/Object;)Z
/*    */     //   44: ifeq -> 50
/*    */     //   47: goto -> 59
/*    */     //   50: aload_0
/*    */     //   51: dup
/*    */     //   52: aload_2
/*    */     //   53: invokevirtual Xu : (Ljava/lang/String;)V
/*    */     //   56: invokevirtual cZ : ()V
/*    */     //   59: aload_1
/*    */     //   60: aload_0
/*    */     //   61: getfield Kx0 : Lf/VA;
/*    */     //   64: getfield TS : Lf/rH;
/*    */     //   67: invokevirtual H : ()V
/*    */     //   70: ifnull -> 474
/*    */     //   73: aload_1
/*    */     //   74: getfield Zs : Lf/Q90;
/*    */     //   77: invokevirtual YC : ()Z
/*    */     //   80: ifne -> 474
/*    */     //   83: aload_0
/*    */     //   84: getfield O : Lf/Sa0;
/*    */     //   87: astore_2
/*    */     //   88: getstatic f/Qv0.Bv0 : Lf/Ll;
/*    */     //   91: astore_3
/*    */     //   92: getstatic f/km.u4 : Lf/R8;
/*    */     //   95: getfield Mg0 : Lf/g2;
/*    */     //   98: astore #4
/*    */     //   100: iconst_0
/*    */     //   101: istore #5
/*    */     //   103: iload #5
/*    */     //   105: getstatic f/km.u4 : Lf/R8;
/*    */     //   108: getfield Lz : Lf/fH0;
/*    */     //   111: getfield wm0 : B
/*    */     //   114: invokestatic Gc : (B)B
/*    */     //   117: if_icmpge -> 192
/*    */     //   120: aload #4
/*    */     //   122: iload #5
/*    */     //   124: invokevirtual LPT5 : (B)Lf/super;
/*    */     //   127: aload_1
/*    */     //   128: getfield Jg : I
/*    */     //   131: istore #6
/*    */     //   133: getfield Ss : [I
/*    */     //   136: dup
/*    */     //   137: astore #7
/*    */     //   139: arraylength
/*    */     //   140: istore #8
/*    */     //   142: iconst_0
/*    */     //   143: istore #9
/*    */     //   145: iload #9
/*    */     //   147: iload #8
/*    */     //   149: if_icmpge -> 172
/*    */     //   152: aload #7
/*    */     //   154: iload #9
/*    */     //   156: iaload
/*    */     //   157: iload #6
/*    */     //   159: if_icmpne -> 166
/*    */     //   162: iconst_1
/*    */     //   163: goto -> 173
/*    */     //   166: iinc #9, 1
/*    */     //   169: goto -> 145
/*    */     //   172: iconst_0
/*    */     //   173: ifeq -> 182
/*    */     //   176: iconst_1
/*    */     //   177: istore #4
/*    */     //   179: goto -> 195
/*    */     //   182: iload #5
/*    */     //   184: iconst_1
/*    */     //   185: iadd
/*    */     //   186: i2b
/*    */     //   187: istore #5
/*    */     //   189: goto -> 103
/*    */     //   192: iconst_0
/*    */     //   193: istore #4
/*    */     //   195: aload_1
/*    */     //   196: aload_2
/*    */     //   197: aload_3
/*    */     //   198: iload #4
/*    */     //   200: invokevirtual gf0 : (Lf/Ll;Z)V
/*    */     //   203: invokevirtual s5 : ()B
/*    */     //   206: iflt -> 245
/*    */     //   209: aload_0
/*    */     //   210: getfield Iw : Lf/VA;
/*    */     //   213: getfield TS : Lf/rH;
/*    */     //   216: iconst_1
/*    */     //   217: anewarray f/pe0
/*    */     //   220: dup
/*    */     //   221: aload_1
/*    */     //   222: invokestatic ZZ : ()Lf/interface;
/*    */     //   225: astore_2
/*    */     //   226: invokevirtual s5 : ()B
/*    */     //   229: aload_2
/*    */     //   230: getfield ar0 : [Lf/pe0;
/*    */     //   233: swap
/*    */     //   234: aaload
/*    */     //   235: iconst_0
/*    */     //   236: swap
/*    */     //   237: aastore
/*    */     //   238: invokevirtual Pn : ([Lf/pe0;)Lf/JG0;
/*    */     //   241: pop
/*    */     //   242: goto -> 255
/*    */     //   245: aload_0
/*    */     //   246: getfield Iw : Lf/VA;
/*    */     //   249: getfield TS : Lf/rH;
/*    */     //   252: invokevirtual H : ()V
/*    */     //   255: aload_1
/*    */     //   256: getfield Zs : Lf/Q90;
/*    */     //   259: invokevirtual tm0 : ()Z
/*    */     //   262: ifeq -> 300
/*    */     //   265: aload_0
/*    */     //   266: getfield OR : Lf/VA;
/*    */     //   269: getfield TS : Lf/rH;
/*    */     //   272: iconst_1
/*    */     //   273: anewarray f/pe0
/*    */     //   276: dup
/*    */     //   277: invokestatic ZZ : ()Lf/interface;
/*    */     //   280: aload_1
/*    */     //   281: getfield Zs : Lf/Q90;
/*    */     //   284: invokevirtual Gf : ()Z
/*    */     //   287: invokevirtual yI0 : (Z)Lf/pe0;
/*    */     //   290: iconst_0
/*    */     //   291: swap
/*    */     //   292: aastore
/*    */     //   293: invokevirtual Pn : ([Lf/pe0;)Lf/JG0;
/*    */     //   296: pop
/*    */     //   297: goto -> 310
/*    */     //   300: aload_0
/*    */     //   301: getfield OR : Lf/VA;
/*    */     //   304: getfield TS : Lf/rH;
/*    */     //   307: invokevirtual H : ()V
/*    */     //   310: aload_1
/*    */     //   311: getfield Zs : Lf/Q90;
/*    */     //   314: getfield wH : [Lf/mA;
/*    */     //   317: arraylength
/*    */     //   318: ifle -> 349
/*    */     //   321: aload_0
/*    */     //   322: getfield mG0 : Lf/VA;
/*    */     //   325: getfield TS : Lf/rH;
/*    */     //   328: iconst_1
/*    */     //   329: anewarray f/pe0
/*    */     //   332: dup
/*    */     //   333: invokestatic ZZ : ()Lf/interface;
/*    */     //   336: getfield oX : Lf/pe0;
/*    */     //   339: iconst_0
/*    */     //   340: swap
/*    */     //   341: aastore
/*    */     //   342: invokevirtual Pn : ([Lf/pe0;)Lf/JG0;
/*    */     //   345: pop
/*    */     //   346: goto -> 359
/*    */     //   349: aload_0
/*    */     //   350: getfield mG0 : Lf/VA;
/*    */     //   353: getfield TS : Lf/rH;
/*    */     //   356: invokevirtual H : ()V
/*    */     //   359: aload_1
/*    */     //   360: getfield Zs : Lf/Q90;
/*    */     //   363: invokevirtual iL : ()Z
/*    */     //   366: ifeq -> 397
/*    */     //   369: aload_0
/*    */     //   370: getfield Ld : Lf/VA;
/*    */     //   373: getfield TS : Lf/rH;
/*    */     //   376: iconst_1
/*    */     //   377: anewarray f/pe0
/*    */     //   380: dup
/*    */     //   381: invokestatic ZZ : ()Lf/interface;
/*    */     //   384: getfield n30 : Lf/pe0;
/*    */     //   387: iconst_0
/*    */     //   388: swap
/*    */     //   389: aastore
/*    */     //   390: invokevirtual Pn : ([Lf/pe0;)Lf/JG0;
/*    */     //   393: pop
/*    */     //   394: goto -> 407
/*    */     //   397: aload_0
/*    */     //   398: getfield Ld : Lf/VA;
/*    */     //   401: getfield TS : Lf/rH;
/*    */     //   404: invokevirtual H : ()V
/*    */     //   407: aload_0
/*    */     //   408: dup
/*    */     //   409: dup
/*    */     //   410: getfield ee : Lf/LpT3;
/*    */     //   413: aload_1
/*    */     //   414: getfield Zs : Lf/Q90;
/*    */     //   417: getfield od : B
/*    */     //   420: invokestatic valueOf : (I)Ljava/lang/String;
/*    */     //   423: invokevirtual E1 : (Ljava/lang/String;)V
/*    */     //   426: getfield sk0 : Lf/VA;
/*    */     //   429: aload_1
/*    */     //   430: getfield Zs : Lf/Q90;
/*    */     //   433: invokevirtual BM : ()Z
/*    */     //   436: invokevirtual wI0 : (Z)V
/*    */     //   439: getfield Qa : Lf/VA;
/*    */     //   442: getfield TS : Lf/rH;
/*    */     //   445: iconst_1
/*    */     //   446: anewarray f/U70
/*    */     //   449: dup
/*    */     //   450: getstatic f/wm0.y0 : Lf/wm0;
/*    */     //   453: aload_1
/*    */     //   454: getfield Zs : Lf/Q90;
/*    */     //   457: invokevirtual p10 : ()S
/*    */     //   460: iconst_0
/*    */     //   461: invokevirtual SJ0 : (SZ)Lf/U70;
/*    */     //   464: iconst_0
/*    */     //   465: swap
/*    */     //   466: aastore
/*    */     //   467: invokevirtual qt : ([Lf/U70;)Lf/JG0;
/*    */     //   470: pop
/*    */     //   471: goto -> 530
/*    */     //   474: aload_0
/*    */     //   475: dup
/*    */     //   476: dup2
/*    */     //   477: dup2
/*    */     //   478: getfield ee : Lf/LpT3;
/*    */     //   481: ldc_w ''
/*    */     //   484: invokevirtual E1 : (Ljava/lang/String;)V
/*    */     //   487: getfield Iw : Lf/VA;
/*    */     //   490: getfield TS : Lf/rH;
/*    */     //   493: invokevirtual H : ()V
/*    */     //   496: getfield OR : Lf/VA;
/*    */     //   499: getfield TS : Lf/rH;
/*    */     //   502: invokevirtual H : ()V
/*    */     //   505: getfield mG0 : Lf/VA;
/*    */     //   508: getfield TS : Lf/rH;
/*    */     //   511: invokevirtual H : ()V
/*    */     //   514: getfield Ld : Lf/VA;
/*    */     //   517: getfield TS : Lf/rH;
/*    */     //   520: invokevirtual H : ()V
/*    */     //   523: getfield sk0 : Lf/VA;
/*    */     //   526: iconst_0
/*    */     //   527: invokevirtual wI0 : (Z)V
/*    */     //   530: aload_1
/*    */     //   531: aload_0
/*    */     //   532: getfield TG0 : Lf/protected;
/*    */     //   535: getfield oh0 : [Ljava/lang/Runnable;
/*    */     //   538: invokestatic Fz0 : ([Ljava/lang/Runnable;)V
/*    */     //   541: ifnonnull -> 574
/*    */     //   544: aload_0
/*    */     //   545: dup
/*    */     //   546: getfield O : Lf/Sa0;
/*    */     //   549: dup
/*    */     //   550: getstatic f/Qv0.Jh0 : Lf/Ll;
/*    */     //   553: iconst_0
/*    */     //   554: invokevirtual gf0 : (Lf/Ll;Z)V
/*    */     //   557: getstatic f/Qv0.FA0 : Lf/Ll;
/*    */     //   560: iconst_0
/*    */     //   561: invokevirtual gf0 : (Lf/Ll;Z)V
/*    */     //   564: getfield O : Lf/Sa0;
/*    */     //   567: getstatic f/Qv0.Bv0 : Lf/Ll;
/*    */     //   570: iconst_0
/*    */     //   571: invokevirtual gf0 : (Lf/Ll;Z)V
/*    */     //   574: return
/*    */     //   575: new java/lang/IllegalArgumentException
/*    */     //   578: dup
/*    */     //   579: invokespecial <init> : ()V
/*    */     //   582: athrow
/*    */     // Line number table:
/*    */     //   Java source line number -> byte code offset
/*    */     //   #1	-> 1
/*    */     //   #2	-> 4
/*    */     //   #3	-> 38
/*    */     //   #4	-> 61
/*    */     //   #5	-> 64
/*    */     //   #6	-> 67
/*    */     //   #7	-> 74
/*    */     //   #8	-> 84
/*    */     //   #9	-> 88
/*    */     //   #10	-> 92
/*    */     //   #11	-> 95
/*    */     //   #12	-> 105
/*    */     //   #13	-> 108
/*    */     //   #14	-> 111
/*    */     //   #15	-> 114
/*    */     //   #16	-> 128
/*    */     //   #17	-> 133
/*    */     //   #18	-> 200
/*    */     //   #19	-> 213
/*    */     //   #20	-> 217
/*    */     //   #21	-> 230
/*    */     //   #22	-> 234
/*    */     //   #23	-> 237
/*    */     //   #24	-> 249
/*    */     //   #25	-> 252
/*    */     //   #26	-> 256
/*    */     //   #27	-> 259
/*    */     //   #28	-> 269
/*    */     //   #29	-> 273
/*    */     //   #30	-> 281
/*    */     //   #31	-> 284
/*    */     //   #32	-> 304
/*    */     //   #33	-> 307
/*    */     //   #34	-> 311
/*    */     //   #35	-> 314
/*    */     //   #36	-> 317
/*    */     //   #37	-> 325
/*    */     //   #38	-> 329
/*    */     //   #39	-> 336
/*    */     //   #40	-> 341
/*    */     //   #41	-> 353
/*    */     //   #42	-> 356
/*    */     //   #43	-> 360
/*    */     //   #44	-> 363
/*    */     //   #45	-> 373
/*    */     //   #46	-> 377
/*    */     //   #47	-> 384
/*    */     //   #48	-> 389
/*    */     //   #49	-> 401
/*    */     //   #50	-> 404
/*    */     //   #51	-> 414
/*    */     //   #52	-> 417
/*    */     //   #53	-> 420
/*    */     //   #54	-> 430
/*    */     //   #55	-> 433
/*    */     //   #56	-> 442
/*    */     //   #57	-> 446
/*    */     //   #58	-> 450
/*    */     //   #59	-> 454
/*    */     //   #60	-> 457
/*    */     //   #61	-> 461
/*    */     //   #62	-> 466
/*    */     //   #63	-> 490
/*    */     //   #64	-> 493
/*    */     //   #65	-> 499
/*    */     //   #66	-> 502
/*    */     //   #67	-> 508
/*    */     //   #68	-> 511
/*    */     //   #69	-> 517
/*    */     //   #70	-> 520
/*    */     //   #71	-> 532
/*    */     //   #72	-> 535
/*    */     //   #73	-> 538
/*    */     //   #74	-> 546
/*    */     //   #75	-> 550
/*    */     //   #76	-> 564
/*  5 */     //   #77	-> 567 } public final void jj() {} public boolean i2(oa0 paramoa0) { Zq[] arrayOfZq; if (km.XU()) { if ((B8.Pg(paramoa0.cz0) && !paramoa0.Ua && paramoa0.vl == 0 && this.TG0
/*  6 */         .nm0() && 
/*  7 */         !this.I20 && 
/*    */         
/*  9 */         !this.K40.dy))
/* 10 */       { int i; if ((i = paramoa0.cz0) == 3) { this
/*    */             
/* 12 */             .kH = System.currentTimeMillis(); } else { long l; if (i == 4 && (l = this.kH) != 0L && 
/* 13 */             System.currentTimeMillis() - l > 300L)
/*    */           
/* 15 */           { arrayOfZq = this.K40.t00();
/* 16 */             int j = this.A90 / 60;
/* 17 */             int k = paramoa0.aK;
/* 18 */             int m = paramoa0.gk0;
/* 19 */             js.vu0.jv0(true, j, k, this, (Qv0[])arrayOfZq, m); this.kH = 0L; return true; }  this.kH = 0L; }  return super.i2((oa0)arrayOfZq); }  } else { return super.i2((oa0)arrayOfZq); }  this.kH = 0L; } public void F4(oa0 paramoa0) { Runnable runnable; Zq[] arrayOfZq; int i; if ((i = paramoa0.vl) == 0) { if (((i = paramoa0.com8) & 0x9) != 0) { Cx0(this.TG0.nm0() ^ true); } else { Qv0 qv0; if ((i & 0x24) != 0) { NR nR = pA.Dg0.jc0; i = 0; while (true) { if (i < 6) { if (nR.FB0[i].public() == null) { qv0 = nR.FB0[i]; break; }  i = (short)(i + 1); continue; }  qv0.getClass(); qv0 = null; break; }  if (qv0 == null) return;  km.u4.lO(this, qv0); } else { int j; if ((i & 0x612) != 0) { if (this.TG0.nm0()) { Zq[] arrayOfZq1; if ((arrayOfZq1 = this.K40.t00()).length > 0) { j = this.A90 / 60; int k = ((oa0)qv0).aK; int m = ((oa0)qv0).gk0; js.vu0.getClass();
/*    */                 
/* 21 */                 F7.T1(js.pz((Qv0[])arrayOfZq1, j), this, k, m); }  }
/* 22 */             else { js js = js.vu0;
/* 23 */               arrayOfQv0[0] = this; j = this.A90 / 60;
/* 24 */               int k = j.aK;
/* 25 */               int m = j.gk0;
/* 26 */               js.getClass();
/*    */               Qv0[] arrayOfQv0;
/* 28 */               F7.T1(js.pz(arrayOfQv0 = new Qv0[1], j), this, k, m); }  }
/* 29 */           else if (!j.Ua) { if (this
/* 30 */               .TG0
/* 31 */               .nm0()) { if (this
/* 32 */                 .MH0.gO()) { Cx0(false); } else if (km.XU())
/*    */               { byte b;
/* 34 */                 for (i = (arrayOfZq = this.K40.t00()).length, b = 0; b < i; ) { arrayOfZq[b].Cx0(false); b++; }  }  } else if (this.MH0.gO()) { Cx0(true); } else if (km.XU())
/*    */             { Zq[] arrayOfZq1; int m, n;
/* 36 */               for (m = (arrayOfZq1 = this.K40.t00()).length, n = 0; n < m; ) { arrayOfZq1[n].Cx0(false); n++; }
/*    */                Qv0[] arrayOfQv0;
/* 38 */               (arrayOfQv0 = new Qv0[1])[0] = this; int k = this.A90 / 60;
/* 39 */               m = ((oa0)arrayOfZq).aK;
/* 40 */               n = ((oa0)arrayOfZq).gk0;
/* 41 */               js.vu0.jv0(true, k, m, this, arrayOfQv0, n); }
/*    */             else
/* 43 */             { byte b; for (i = (arrayOfZq = this.K40.t00()).length, b = 0; b < i; ) { arrayOfZq[b].Cx0(false); b++; }  }  if ((runnable = this.n0) != null) run();  }  }  }  } else if (i == 1) { if ((((oa0)arrayOfZq)
/* 44 */         .com8 & 0x24) != 0)
/* 45 */       { pA.Dg0
/* 46 */           .u30((JG0)this, public()); } else { int j; if (((Un)this)
/* 47 */           .TG0
/* 48 */           .nm0())
/* 49 */         { Zq[] arrayOfZq1; if ((arrayOfZq1 = ((Zq)super).K40.t00()).length > 
/* 50 */             0) {
/*    */             
/* 52 */             j = ((Qv0)this).A90 / 60;
/* 53 */             int k = ((oa0)arrayOfZq).aK;
/* 54 */             int m = ((oa0)arrayOfZq).gk0;
/* 55 */             js.vu0.jv0(true, j, k, (Qv0)this, (Qv0[])arrayOfZq1, m);
/*    */           }  }
/* 57 */         else { Qv0[] arrayOfQv0; (arrayOfQv0 = new Qv0[1])[0] = (Qv0)this; i = ((Qv0)this).A90 / 60;
/* 58 */           int k = j.aK;
/* 59 */           int m = j.gk0;
/* 60 */           js.vu0.jv0(true, i, k, (Qv0)this, arrayOfQv0, m); }  }  }  } public final void d40() { int i; VA vA; int j; if (km.Nr()) { this.ee.mM(); i = this.Kd; this.ee.ME(this.xY - this.ee.xY + i - 6, mD() - this.ee.Hy() - 1); if (this.Iw.TS.e00() > 0) this.Iw.ME(this.Kd + 2, mD() - this.Iw.TS.cA() - 1);  i = 1; if (public() != null && (public()).Zs.tm0()) { this.OR.ME(this.Kd + 1, this.er0 + 1); i = this.OR.TS.cA() - 3 + i; }  if (this.mG0.TS.cA() > 0) this.mG0.ME(this.Kd + 1, this.er0 + i);  i = 5; if (this.Ld.TS.cA() > 0) { this.Ld.ME(m40() - this.Ld.TS.e00() - 3, this.er0 + 3); i = this.Ld.TS.cA() - 2 + i; }  vA = this.sk0; j = m40() - this.sk0.TS.e00() - 4; i = this.er0 + i; } else { this.ee.mM(); i = this.Kd; this.ee.ME(this.xY - this.ee.xY + i - 6, mD() - this.ee.Hy() - 2); this.Iw.ME(this.Kd + 2, mD() - this.Iw.TS.cA()); i = 1; this.OR.ME(this.Kd + 1, this.er0 + 1); if (this.OR.TS.cA() > 0)
/* 61 */         i = this.OR.TS.cA() - 3 + i;  this.mG0
/*    */ 
/*    */         
/* 64 */         .ME(this.Kd + 1, this.er0 + i); i = 7;
/*    */ 
/*    */       
/* 67 */       int k = m40() - this.Ld.TS.e00() - 1;
/*    */       
/* 69 */       this.Ld.ME(k, this.er0);
/* 70 */       if (this.Ld
/* 71 */         .TS
/* 72 */         .cA() > 0)
/*    */       {
/* 74 */         i = this.Ld.TS.cA() - 4 + i; }  this.sk0
/*    */ 
/*    */ 
/*    */         
/* 78 */         .ME(m40() - this.sk0.TS.e00() - 3, this.er0 + i);
/* 79 */       vA = this.Kx0;
/* 80 */       j = this.sk0.Kd + 17;
/* 81 */       i = this.sk0.er0 - 1; }  vA
/* 82 */       .ME(j, i);
/*    */     
/* 84 */     if (this.MH0.ek
/* 85 */       .TG0
/* 86 */       .nm0())
/* 87 */     { j40 j40; if ((j40 = public()) != null && 
/*    */         
/* 89 */         !j40.Zs.BM())
/* 90 */       { pRn pRn; rH rH = this.As;
/* 91 */         if (km.XU()) { pRn = pRn.DARKGRAY; } else { pRn = pRn.GRAY; }  rH.FB0(pRn); }  }
/* 92 */     else { this.As
/* 93 */         .O3 = null; }  super
/* 94 */       .d40(); }
/*    */ 
/*    */   
/*    */   public final void R60(throws paramthrows) {
/*    */     super.R60(paramthrows);
/*    */     j40 j40;
/*    */     if (this.MH0.ek.TG0.nm0() && (j40 = public()) != null && j40.Zs.BM()) {
/*    */       int j = this.Kd + rH.Cf0;
/*    */       int i = this.er0 + this.Qa.TS.Tn;
/*    */       rH rH;
/*    */       (rH = this.Qa.TS).sG0(AW() / 2 + j, HY() / 2 + i);
/*    */     } 
/*    */   }
/*    */   
/*    */   public final void pm() {
/*    */     if (this.MH0.gO()) {
/*    */       this.O.gf0(Qv0.mk0, true);
/*    */       this.O.gf0(Qv0.Co, this.K40.dy);
/*    */     } 
/*    */   }
/*    */   
/*    */   public final void GD() {
/*    */     this.O.gf0(Qv0.mk0, false);
/*    */     this.O.gf0(Qv0.Co, false);
/*    */   }
/*    */   
/*    */   public final void GO() {
/*    */     Zq[] arrayOfZq;
/*    */     if (!this.TG0.nm0()) {
/*    */       if (public() != null) {
/*    */         Qv0[] arrayOfQv0;
/*    */         (arrayOfQv0 = new Qv0[1])[0] = this;
/*    */         int i = this.A90 / 60;
/*    */         int j = this.Kd;
/*    */         int k = this.er0;
/*    */         js.vu0.jv0(false, i, j, this, arrayOfQv0, k);
/*    */       } else {
/*    */         UB0.Kg0.fN(this::Dl0);
/*    */         int i;
/*    */         byte b;
/*    */         for (i = (arrayOfZq = this.K40.t00()).length, b = 0; b < i; ) {
/*    */           this[b].Cx0(false);
/*    */           b++;
/*    */         } 
/*    */       } 
/*    */     } else {
/*    */       Zq[] arrayOfZq1;
/*    */       if ((arrayOfZq1 = ((Zq)this).K40.t00()).length > 0) {
/*    */         int i = ((Qv0)this).A90 / 60;
/*    */         int j = ((JG0)this).Kd;
/*    */         int k = ((JG0)this).er0;
/*    */         js.vu0.jv0(false, i, j, (Qv0)this, (Qv0[])arrayOfZq1, k);
/*    */       } 
/*    */     } 
/*    */   }
/*    */   
/*    */   public final boolean cL() {
/*    */     return (!this.I20 && !((this.MH0.ek.TG0.nm0() && public() != null && (public()).Zs.BM()) ? 1 : 0));
/*    */   } }


/* Location:              /Users/vnnsnnt/Documents/Codespace/JavaWorkspace/RedTrainer/src/main/java/org/trainer/client/PokeMMO.jar!/f/Zq.class
 * Java compiler version: 8 (52.0)
 * JD-Core Version:       1.1.3
 */