/*  1 */ package f;public final class Zr extends Qa0 { public final P4 Ft; public final Ip qK; public final Ip Cf0; public final Ip d30; public final zT Ak0; public dQ e70; public Qv0[][] wC0; public xK[][] lpT8; private void BM(P4 paramP4, short paramShort) { byte b = paramP4.QO; if (paramP4
/*  2 */       .g00[b])
/*  3 */       return;  F7.Yo(JB0.Ww(this.lpT8[0][paramShort], JB0.CE0, false), this.lpT8[0][paramShort]); }
/*    */   public final Un yx; public final Un zo; public final Un bz; public final Un Bg; public final Fy0 pG0; public Rm G9; public HashMap ed0; public Zr(P4 paramP4) { // Byte code:
/*    */     //   0: aload_0
/*    */     //   1: dup
/*    */     //   2: dup
/*    */     //   3: dup2
/*    */     //   4: dup2
/*    */     //   5: dup2
/*    */     //   6: dup2
/*    */     //   7: aload_1
/*    */     //   8: aload_0
/*    */     //   9: dup
/*    */     //   10: dup2
/*    */     //   11: invokestatic XU : ()Z
/*    */     //   14: invokespecial <init> : (Z)V
/*    */     //   17: iconst_2
/*    */     //   18: bipush #6
/*    */     //   20: multianewarray[[Lf/Qv0; 2
/*    */     //   24: putfield wC0 : [[Lf/Qv0;
/*    */     //   27: iconst_2
/*    */     //   28: bipush #6
/*    */     //   30: multianewarray[[Lf/xK; 2
/*    */     //   34: putfield lpT8 : [[Lf/xK;
/*    */     //   37: new java/util/HashMap
/*    */     //   40: dup
/*    */     //   41: invokespecial <init> : ()V
/*    */     //   44: putfield ed0 : Ljava/util/HashMap;
/*    */     //   47: putfield Ft : Lf/P4;
/*    */     //   50: new f/h40
/*    */     //   53: dup
/*    */     //   54: invokespecial <init> : ()V
/*    */     //   57: invokevirtual TG0 : (Ljava/lang/Runnable;)V
/*    */     //   60: new f/I
/*    */     //   63: dup
/*    */     //   64: aload_0
/*    */     //   65: new f/pRn
/*    */     //   68: dup
/*    */     //   69: astore_2
/*    */     //   70: iconst_m1
/*    */     //   71: iconst_m1
/*    */     //   72: iconst_m1
/*    */     //   73: iconst_m1
/*    */     //   74: invokespecial <init> : (BBBB)V
/*    */     //   77: aload_2
/*    */     //   78: invokespecial <init> : (Lf/JG0;Lf/pRn;)V
/*    */     //   81: invokevirtual Vo0 : (Lf/I;)V
/*    */     //   84: ldc 'trade-frame'
/*    */     //   86: invokevirtual Xu : (Ljava/lang/String;)V
/*    */     //   89: sipush #1950
/*    */     //   92: invokestatic OH0 : (I)Ljava/lang/String;
/*    */     //   95: invokevirtual Lo : (Ljava/lang/String;)V
/*    */     //   98: iconst_1
/*    */     //   99: invokevirtual EP : (I)V
/*    */     //   102: new f/Un
/*    */     //   105: dup
/*    */     //   106: dup
/*    */     //   107: astore_2
/*    */     //   108: sipush #1951
/*    */     //   111: invokestatic OH0 : (I)Ljava/lang/String;
/*    */     //   114: invokespecial <init> : (Ljava/lang/String;)V
/*    */     //   117: putfield yx : Lf/Un;
/*    */     //   120: new f/Un
/*    */     //   123: dup
/*    */     //   124: aload_0
/*    */     //   125: swap
/*    */     //   126: dup
/*    */     //   127: sipush #1952
/*    */     //   130: invokestatic OH0 : (I)Ljava/lang/String;
/*    */     //   133: invokespecial <init> : (Ljava/lang/String;)V
/*    */     //   136: putfield zo : Lf/Un;
/*    */     //   139: iconst_0
/*    */     //   140: invokevirtual sk0 : (Z)V
/*    */     //   143: new f/Un
/*    */     //   146: dup
/*    */     //   147: dup
/*    */     //   148: astore_3
/*    */     //   149: sipush #1953
/*    */     //   152: invokestatic OH0 : (I)Ljava/lang/String;
/*    */     //   155: invokespecial <init> : (Ljava/lang/String;)V
/*    */     //   158: putfield bz : Lf/Un;
/*    */     //   161: new f/Un
/*    */     //   164: dup
/*    */     //   165: astore #4
/*    */     //   167: aload_3
/*    */     //   168: dup
/*    */     //   169: aload_0
/*    */     //   170: aload_1
/*    */     //   171: aload_2
/*    */     //   172: aload #4
/*    */     //   174: aload_0
/*    */     //   175: aload #4
/*    */     //   177: dup
/*    */     //   178: sipush #1954
/*    */     //   181: invokestatic OH0 : (I)Ljava/lang/String;
/*    */     //   184: invokespecial <init> : (Ljava/lang/String;)V
/*    */     //   187: putfield Bg : Lf/Un;
/*    */     //   190: iconst_0
/*    */     //   191: invokevirtual sk0 : (Z)V
/*    */     //   194: new f/mh
/*    */     //   197: dup
/*    */     //   198: aload_0
/*    */     //   199: aload_1
/*    */     //   200: invokespecial <init> : (Lf/Zr;Lf/P4;)V
/*    */     //   203: invokevirtual tW : (Ljava/lang/Runnable;)V
/*    */     //   206: <illegal opcode> run : (Lf/Zr;Lf/P4;)Ljava/lang/Runnable;
/*    */     //   211: invokevirtual tW : (Ljava/lang/Runnable;)V
/*    */     //   214: iconst_0
/*    */     //   215: invokevirtual wI0 : (Z)V
/*    */     //   218: iconst_0
/*    */     //   219: invokevirtual wI0 : (Z)V
/*    */     //   222: new f/Ip
/*    */     //   225: dup
/*    */     //   226: invokespecial <init> : ()V
/*    */     //   229: putfield d30 : Lf/Ip;
/*    */     //   232: new f/Ip
/*    */     //   235: dup
/*    */     //   236: invokespecial <init> : ()V
/*    */     //   239: putfield qK : Lf/Ip;
/*    */     //   242: new f/zT
/*    */     //   245: dup
/*    */     //   246: astore_2
/*    */     //   247: aload_0
/*    */     //   248: aload_2
/*    */     //   249: dup
/*    */     //   250: getstatic f/km.u4 : Lf/R8;
/*    */     //   253: invokevirtual IQ : ()Lf/fH0;
/*    */     //   256: invokevirtual rK0 : ()I
/*    */     //   259: iconst_0
/*    */     //   260: swap
/*    */     //   261: iconst_0
/*    */     //   262: invokespecial <init> : (III)V
/*    */     //   265: putfield Ak0 : Lf/zT;
/*    */     //   268: new f/kc0
/*    */     //   271: dup
/*    */     //   272: aload_0
/*    */     //   273: aload_1
/*    */     //   274: invokespecial <init> : (Lf/Zr;Lf/P4;)V
/*    */     //   277: invokevirtual Ac0 : (Ljava/lang/Runnable;)V
/*    */     //   280: new f/Rm
/*    */     //   283: dup
/*    */     //   284: aload_0
/*    */     //   285: swap
/*    */     //   286: dup
/*    */     //   287: aload_2
/*    */     //   288: invokespecial <init> : (Lf/zT;)V
/*    */     //   291: putfield G9 : Lf/Rm;
/*    */     //   294: invokevirtual VL : ()V
/*    */     //   297: getfield G9 : Lf/Rm;
/*    */     //   300: aload_1
/*    */     //   301: invokevirtual B5 : ()Z
/*    */     //   304: invokevirtual sk0 : (Z)V
/*    */     //   307: iconst_0
/*    */     //   308: istore_2
/*    */     //   309: iload_2
/*    */     //   310: aload_0
/*    */     //   311: getfield wC0 : [[Lf/Qv0;
/*    */     //   314: iconst_0
/*    */     //   315: aaload
/*    */     //   316: dup
/*    */     //   317: astore_3
/*    */     //   318: arraylength
/*    */     //   319: if_icmpge -> 399
/*    */     //   322: iload_2
/*    */     //   323: aload_0
/*    */     //   324: dup
/*    */     //   325: dup
/*    */     //   326: aload_3
/*    */     //   327: iload_2
/*    */     //   328: new f/Qv0
/*    */     //   331: dup
/*    */     //   332: astore_3
/*    */     //   333: aload_1
/*    */     //   334: dup
/*    */     //   335: invokevirtual Wr : ()B
/*    */     //   338: invokevirtual Q20 : (I)Lf/public;
/*    */     //   341: iload_2
/*    */     //   342: iconst_0
/*    */     //   343: invokespecial <init> : (Lf/Uc0;SZ)V
/*    */     //   346: aload_3
/*    */     //   347: aastore
/*    */     //   348: getfield wC0 : [[Lf/Qv0;
/*    */     //   351: iconst_0
/*    */     //   352: aaload
/*    */     //   353: iload_2
/*    */     //   354: aaload
/*    */     //   355: ldc 'partyslot'
/*    */     //   357: invokevirtual Xu : (Ljava/lang/String;)V
/*    */     //   360: getfield wC0 : [[Lf/Qv0;
/*    */     //   363: iconst_0
/*    */     //   364: aaload
/*    */     //   365: iload_2
/*    */     //   366: aaload
/*    */     //   367: aload_1
/*    */     //   368: invokevirtual ZA0 : ()Z
/*    */     //   371: invokevirtual sk0 : (Z)V
/*    */     //   374: getfield wC0 : [[Lf/Qv0;
/*    */     //   377: iconst_0
/*    */     //   378: aaload
/*    */     //   379: iload_2
/*    */     //   380: aaload
/*    */     //   381: dup
/*    */     //   382: aload_1
/*    */     //   383: swap
/*    */     //   384: <illegal opcode> run : (Lf/P4;Lf/Qv0;)Ljava/lang/Runnable;
/*    */     //   389: invokevirtual L1 : (Ljava/lang/Runnable;)V
/*    */     //   392: iconst_1
/*    */     //   393: iadd
/*    */     //   394: i2s
/*    */     //   395: istore_2
/*    */     //   396: goto -> 309
/*    */     //   399: aload_0
/*    */     //   400: getfield G9 : Lf/Rm;
/*    */     //   403: ldc 'valueadjuster-bg'
/*    */     //   405: invokevirtual Xu : (Ljava/lang/String;)V
/*    */     //   408: new f/dQ
/*    */     //   411: dup
/*    */     //   412: astore_2
/*    */     //   413: sipush #1957
/*    */     //   416: invokestatic OH0 : (I)Ljava/lang/String;
/*    */     //   419: invokespecial <init> : (Ljava/lang/String;)V
/*    */     //   422: new f/dQ
/*    */     //   425: dup
/*    */     //   426: astore_3
/*    */     //   427: new java/lang/StringBuilder
/*    */     //   430: dup
/*    */     //   431: astore #4
/*    */     //   433: invokespecial <init> : ()V
/*    */     //   436: iconst_0
/*    */     //   437: aload #4
/*    */     //   439: ldc ': '
/*    */     //   441: invokestatic jJ0 : (ILjava/lang/StringBuilder;Ljava/lang/String;)Ljava/lang/String;
/*    */     //   444: invokespecial <init> : (Ljava/lang/String;)V
/*    */     //   447: new f/Ip
/*    */     //   450: dup
/*    */     //   451: dup
/*    */     //   452: dup2
/*    */     //   453: dup2
/*    */     //   454: astore #4
/*    */     //   456: invokespecial <init> : ()V
/*    */     //   459: ldc 'pokeframe'
/*    */     //   461: invokevirtual Xu : (Ljava/lang/String;)V
/*    */     //   464: invokevirtual d7 : ()Lf/cr0;
/*    */     //   467: iconst_1
/*    */     //   468: anewarray f/U90
/*    */     //   471: dup
/*    */     //   472: aload #4
/*    */     //   474: invokevirtual mE0 : ()Lf/g0;
/*    */     //   477: iconst_2
/*    */     //   478: anewarray f/U90
/*    */     //   481: dup
/*    */     //   482: dup
/*    */     //   483: aload #4
/*    */     //   485: swap
/*    */     //   486: aload #4
/*    */     //   488: invokevirtual d7 : ()Lf/cr0;
/*    */     //   491: bipush #20
/*    */     //   493: invokevirtual Aq : (I)Lf/U90;
/*    */     //   496: iconst_3
/*    */     //   497: anewarray f/JG0
/*    */     //   500: dup
/*    */     //   501: dup
/*    */     //   502: astore #5
/*    */     //   504: aload_0
/*    */     //   505: getfield wC0 : [[Lf/Qv0;
/*    */     //   508: dup
/*    */     //   509: aload #5
/*    */     //   511: swap
/*    */     //   512: iconst_0
/*    */     //   513: aaload
/*    */     //   514: iconst_0
/*    */     //   515: aaload
/*    */     //   516: iconst_0
/*    */     //   517: swap
/*    */     //   518: aastore
/*    */     //   519: iconst_0
/*    */     //   520: aaload
/*    */     //   521: dup
/*    */     //   522: aload #5
/*    */     //   524: swap
/*    */     //   525: iconst_1
/*    */     //   526: aaload
/*    */     //   527: iconst_1
/*    */     //   528: swap
/*    */     //   529: aastore
/*    */     //   530: iconst_2
/*    */     //   531: aaload
/*    */     //   532: iconst_2
/*    */     //   533: swap
/*    */     //   534: aastore
/*    */     //   535: invokevirtual Mg : ([Lf/JG0;)Lf/U90;
/*    */     //   538: bipush #20
/*    */     //   540: invokevirtual Aq : (I)Lf/U90;
/*    */     //   543: iconst_0
/*    */     //   544: swap
/*    */     //   545: aastore
/*    */     //   546: invokevirtual d7 : ()Lf/cr0;
/*    */     //   549: bipush #20
/*    */     //   551: invokevirtual Aq : (I)Lf/U90;
/*    */     //   554: iconst_3
/*    */     //   555: anewarray f/JG0
/*    */     //   558: dup
/*    */     //   559: dup
/*    */     //   560: astore #5
/*    */     //   562: aload_0
/*    */     //   563: getfield wC0 : [[Lf/Qv0;
/*    */     //   566: dup
/*    */     //   567: aload #5
/*    */     //   569: swap
/*    */     //   570: iconst_0
/*    */     //   571: aaload
/*    */     //   572: iconst_3
/*    */     //   573: aaload
/*    */     //   574: iconst_0
/*    */     //   575: swap
/*    */     //   576: aastore
/*    */     //   577: iconst_0
/*    */     //   578: aaload
/*    */     //   579: dup
/*    */     //   580: aload #5
/*    */     //   582: swap
/*    */     //   583: iconst_4
/*    */     //   584: aaload
/*    */     //   585: iconst_1
/*    */     //   586: swap
/*    */     //   587: aastore
/*    */     //   588: iconst_5
/*    */     //   589: aaload
/*    */     //   590: iconst_2
/*    */     //   591: swap
/*    */     //   592: aastore
/*    */     //   593: invokevirtual Mg : ([Lf/JG0;)Lf/U90;
/*    */     //   596: bipush #20
/*    */     //   598: invokevirtual Aq : (I)Lf/U90;
/*    */     //   601: iconst_1
/*    */     //   602: swap
/*    */     //   603: aastore
/*    */     //   604: invokevirtual cOM8 : ([Lf/U90;)Lf/U90;
/*    */     //   607: iconst_0
/*    */     //   608: swap
/*    */     //   609: aastore
/*    */     //   610: invokevirtual cOM8 : ([Lf/U90;)Lf/U90;
/*    */     //   613: invokevirtual rK0 : (Lf/U90;)V
/*    */     //   616: invokevirtual mE0 : ()Lf/g0;
/*    */     //   619: iconst_1
/*    */     //   620: anewarray f/U90
/*    */     //   623: dup
/*    */     //   624: aload #4
/*    */     //   626: invokevirtual d7 : ()Lf/cr0;
/*    */     //   629: iconst_2
/*    */     //   630: anewarray f/U90
/*    */     //   633: dup
/*    */     //   634: dup
/*    */     //   635: aload #4
/*    */     //   637: swap
/*    */     //   638: aload #4
/*    */     //   640: invokevirtual mE0 : ()Lf/g0;
/*    */     //   643: iconst_3
/*    */     //   644: anewarray f/JG0
/*    */     //   647: dup
/*    */     //   648: dup
/*    */     //   649: astore #5
/*    */     //   651: aload_0
/*    */     //   652: getfield wC0 : [[Lf/Qv0;
/*    */     //   655: dup
/*    */     //   656: aload #5
/*    */     //   658: swap
/*    */     //   659: iconst_0
/*    */     //   660: aaload
/*    */     //   661: iconst_0
/*    */     //   662: aaload
/*    */     //   663: iconst_0
/*    */     //   664: swap
/*    */     //   665: aastore
/*    */     //   666: iconst_0
/*    */     //   667: aaload
/*    */     //   668: dup
/*    */     //   669: aload #5
/*    */     //   671: swap
/*    */     //   672: iconst_1
/*    */     //   673: aaload
/*    */     //   674: iconst_1
/*    */     //   675: swap
/*    */     //   676: aastore
/*    */     //   677: iconst_2
/*    */     //   678: aaload
/*    */     //   679: iconst_2
/*    */     //   680: swap
/*    */     //   681: aastore
/*    */     //   682: invokevirtual Mg : ([Lf/JG0;)Lf/U90;
/*    */     //   685: iconst_0
/*    */     //   686: swap
/*    */     //   687: aastore
/*    */     //   688: invokevirtual mE0 : ()Lf/g0;
/*    */     //   691: iconst_3
/*    */     //   692: anewarray f/JG0
/*    */     //   695: dup
/*    */     //   696: dup
/*    */     //   697: astore #5
/*    */     //   699: aload_0
/*    */     //   700: getfield wC0 : [[Lf/Qv0;
/*    */     //   703: dup
/*    */     //   704: aload #5
/*    */     //   706: swap
/*    */     //   707: iconst_0
/*    */     //   708: aaload
/*    */     //   709: iconst_3
/*    */     //   710: aaload
/*    */     //   711: iconst_0
/*    */     //   712: swap
/*    */     //   713: aastore
/*    */     //   714: iconst_0
/*    */     //   715: aaload
/*    */     //   716: dup
/*    */     //   717: aload #5
/*    */     //   719: swap
/*    */     //   720: iconst_4
/*    */     //   721: aaload
/*    */     //   722: iconst_1
/*    */     //   723: swap
/*    */     //   724: aastore
/*    */     //   725: iconst_5
/*    */     //   726: aaload
/*    */     //   727: iconst_2
/*    */     //   728: swap
/*    */     //   729: aastore
/*    */     //   730: invokevirtual Mg : ([Lf/JG0;)Lf/U90;
/*    */     //   733: iconst_1
/*    */     //   734: swap
/*    */     //   735: aastore
/*    */     //   736: invokevirtual cOM8 : ([Lf/U90;)Lf/U90;
/*    */     //   739: iconst_0
/*    */     //   740: swap
/*    */     //   741: aastore
/*    */     //   742: invokevirtual cOM8 : ([Lf/U90;)Lf/U90;
/*    */     //   745: invokevirtual WN : (Lf/U90;)V
/*    */     //   748: new f/dQ
/*    */     //   751: dup
/*    */     //   752: astore #5
/*    */     //   754: sipush #1967
/*    */     //   757: invokestatic OH0 : (I)Ljava/lang/String;
/*    */     //   760: invokespecial <init> : (Ljava/lang/String;)V
/*    */     //   763: iconst_0
/*    */     //   764: istore #6
/*    */     //   766: iload #6
/*    */     //   768: aload_0
/*    */     //   769: getfield lpT8 : [[Lf/xK;
/*    */     //   772: iconst_0
/*    */     //   773: aaload
/*    */     //   774: dup
/*    */     //   775: astore #7
/*    */     //   777: arraylength
/*    */     //   778: if_icmpge -> 847
/*    */     //   781: iload #6
/*    */     //   783: aload_0
/*    */     //   784: dup
/*    */     //   785: aload #7
/*    */     //   787: iload #6
/*    */     //   789: new f/xK
/*    */     //   792: dup
/*    */     //   793: astore #7
/*    */     //   795: iload #6
/*    */     //   797: iconst_1
/*    */     //   798: invokespecial <init> : (SZ)V
/*    */     //   801: aload #7
/*    */     //   803: aastore
/*    */     //   804: getfield lpT8 : [[Lf/xK;
/*    */     //   807: iconst_0
/*    */     //   808: aaload
/*    */     //   809: iload #6
/*    */     //   811: aaload
/*    */     //   812: aload_1
/*    */     //   813: invokevirtual B5 : ()Z
/*    */     //   816: invokevirtual sk0 : (Z)V
/*    */     //   819: getfield lpT8 : [[Lf/xK;
/*    */     //   822: iconst_0
/*    */     //   823: aaload
/*    */     //   824: iload #6
/*    */     //   826: aaload
/*    */     //   827: aload_0
/*    */     //   828: aload_1
/*    */     //   829: iload #6
/*    */     //   831: <illegal opcode> run : (Lf/Zr;Lf/P4;S)Ljava/lang/Runnable;
/*    */     //   836: invokevirtual bm0 : (Ljava/lang/Runnable;)V
/*    */     //   839: iconst_1
/*    */     //   840: iadd
/*    */     //   841: i2s
/*    */     //   842: istore #6
/*    */     //   844: goto -> 766
/*    */     //   847: aload_0
/*    */     //   848: dup
/*    */     //   849: dup
/*    */     //   850: dup2
/*    */     //   851: dup2
/*    */     //   852: dup2
/*    */     //   853: new f/Ip
/*    */     //   856: dup
/*    */     //   857: dup
/*    */     //   858: dup2
/*    */     //   859: dup2
/*    */     //   860: astore #6
/*    */     //   862: invokespecial <init> : ()V
/*    */     //   865: ldc 'pokeframe'
/*    */     //   867: invokevirtual Xu : (Ljava/lang/String;)V
/*    */     //   870: invokevirtual d7 : ()Lf/cr0;
/*    */     //   873: iconst_1
/*    */     //   874: anewarray f/U90
/*    */     //   877: dup
/*    */     //   878: aload #6
/*    */     //   880: invokevirtual mE0 : ()Lf/g0;
/*    */     //   883: iconst_2
/*    */     //   884: anewarray f/U90
/*    */     //   887: dup
/*    */     //   888: dup
/*    */     //   889: aload #6
/*    */     //   891: swap
/*    */     //   892: aload #6
/*    */     //   894: invokevirtual d7 : ()Lf/cr0;
/*    */     //   897: bipush #20
/*    */     //   899: invokevirtual Aq : (I)Lf/U90;
/*    */     //   902: iconst_3
/*    */     //   903: anewarray f/JG0
/*    */     //   906: dup
/*    */     //   907: dup
/*    */     //   908: astore #7
/*    */     //   910: aload_0
/*    */     //   911: getfield lpT8 : [[Lf/xK;
/*    */     //   914: dup
/*    */     //   915: aload #7
/*    */     //   917: swap
/*    */     //   918: iconst_0
/*    */     //   919: aaload
/*    */     //   920: iconst_0
/*    */     //   921: aaload
/*    */     //   922: iconst_0
/*    */     //   923: swap
/*    */     //   924: aastore
/*    */     //   925: iconst_0
/*    */     //   926: aaload
/*    */     //   927: dup
/*    */     //   928: aload #7
/*    */     //   930: swap
/*    */     //   931: iconst_1
/*    */     //   932: aaload
/*    */     //   933: iconst_1
/*    */     //   934: swap
/*    */     //   935: aastore
/*    */     //   936: iconst_2
/*    */     //   937: aaload
/*    */     //   938: iconst_2
/*    */     //   939: swap
/*    */     //   940: aastore
/*    */     //   941: invokevirtual Mg : ([Lf/JG0;)Lf/U90;
/*    */     //   944: bipush #20
/*    */     //   946: invokevirtual Aq : (I)Lf/U90;
/*    */     //   949: iconst_0
/*    */     //   950: swap
/*    */     //   951: aastore
/*    */     //   952: invokevirtual d7 : ()Lf/cr0;
/*    */     //   955: bipush #20
/*    */     //   957: invokevirtual Aq : (I)Lf/U90;
/*    */     //   960: iconst_3
/*    */     //   961: anewarray f/JG0
/*    */     //   964: dup
/*    */     //   965: dup
/*    */     //   966: astore #7
/*    */     //   968: aload_0
/*    */     //   969: getfield lpT8 : [[Lf/xK;
/*    */     //   972: dup
/*    */     //   973: aload #7
/*    */     //   975: swap
/*    */     //   976: iconst_0
/*    */     //   977: aaload
/*    */     //   978: iconst_3
/*    */     //   979: aaload
/*    */     //   980: iconst_0
/*    */     //   981: swap
/*    */     //   982: aastore
/*    */     //   983: iconst_0
/*    */     //   984: aaload
/*    */     //   985: dup
/*    */     //   986: aload #7
/*    */     //   988: swap
/*    */     //   989: iconst_4
/*    */     //   990: aaload
/*    */     //   991: iconst_1
/*    */     //   992: swap
/*    */     //   993: aastore
/*    */     //   994: iconst_5
/*    */     //   995: aaload
/*    */     //   996: iconst_2
/*    */     //   997: swap
/*    */     //   998: aastore
/*    */     //   999: invokevirtual Mg : ([Lf/JG0;)Lf/U90;
/*    */     //   1002: bipush #20
/*    */     //   1004: invokevirtual Aq : (I)Lf/U90;
/*    */     //   1007: iconst_1
/*    */     //   1008: swap
/*    */     //   1009: aastore
/*    */     //   1010: invokevirtual cOM8 : ([Lf/U90;)Lf/U90;
/*    */     //   1013: iconst_0
/*    */     //   1014: swap
/*    */     //   1015: aastore
/*    */     //   1016: invokevirtual cOM8 : ([Lf/U90;)Lf/U90;
/*    */     //   1019: invokevirtual rK0 : (Lf/U90;)V
/*    */     //   1022: invokevirtual mE0 : ()Lf/g0;
/*    */     //   1025: iconst_1
/*    */     //   1026: anewarray f/U90
/*    */     //   1029: dup
/*    */     //   1030: aload #6
/*    */     //   1032: invokevirtual d7 : ()Lf/cr0;
/*    */     //   1035: iconst_2
/*    */     //   1036: anewarray f/U90
/*    */     //   1039: dup
/*    */     //   1040: dup
/*    */     //   1041: aload #6
/*    */     //   1043: swap
/*    */     //   1044: aload #6
/*    */     //   1046: invokevirtual mE0 : ()Lf/g0;
/*    */     //   1049: iconst_3
/*    */     //   1050: anewarray f/JG0
/*    */     //   1053: dup
/*    */     //   1054: dup
/*    */     //   1055: astore #7
/*    */     //   1057: aload_0
/*    */     //   1058: getfield lpT8 : [[Lf/xK;
/*    */     //   1061: dup
/*    */     //   1062: aload #7
/*    */     //   1064: swap
/*    */     //   1065: iconst_0
/*    */     //   1066: aaload
/*    */     //   1067: iconst_0
/*    */     //   1068: aaload
/*    */     //   1069: iconst_0
/*    */     //   1070: swap
/*    */     //   1071: aastore
/*    */     //   1072: iconst_0
/*    */     //   1073: aaload
/*    */     //   1074: dup
/*    */     //   1075: aload #7
/*    */     //   1077: swap
/*    */     //   1078: iconst_1
/*    */     //   1079: aaload
/*    */     //   1080: iconst_1
/*    */     //   1081: swap
/*    */     //   1082: aastore
/*    */     //   1083: iconst_2
/*    */     //   1084: aaload
/*    */     //   1085: iconst_2
/*    */     //   1086: swap
/*    */     //   1087: aastore
/*    */     //   1088: invokevirtual Mg : ([Lf/JG0;)Lf/U90;
/*    */     //   1091: iconst_0
/*    */     //   1092: swap
/*    */     //   1093: aastore
/*    */     //   1094: invokevirtual mE0 : ()Lf/g0;
/*    */     //   1097: iconst_3
/*    */     //   1098: anewarray f/JG0
/*    */     //   1101: dup
/*    */     //   1102: dup
/*    */     //   1103: astore #7
/*    */     //   1105: aload_0
/*    */     //   1106: getfield lpT8 : [[Lf/xK;
/*    */     //   1109: dup
/*    */     //   1110: aload #7
/*    */     //   1112: swap
/*    */     //   1113: iconst_0
/*    */     //   1114: aaload
/*    */     //   1115: iconst_3
/*    */     //   1116: aaload
/*    */     //   1117: iconst_0
/*    */     //   1118: swap
/*    */     //   1119: aastore
/*    */     //   1120: iconst_0
/*    */     //   1121: aaload
/*    */     //   1122: dup
/*    */     //   1123: aload #7
/*    */     //   1125: swap
/*    */     //   1126: iconst_4
/*    */     //   1127: aaload
/*    */     //   1128: iconst_1
/*    */     //   1129: swap
/*    */     //   1130: aastore
/*    */     //   1131: iconst_5
/*    */     //   1132: aaload
/*    */     //   1133: iconst_2
/*    */     //   1134: swap
/*    */     //   1135: aastore
/*    */     //   1136: invokevirtual Mg : ([Lf/JG0;)Lf/U90;
/*    */     //   1139: iconst_1
/*    */     //   1140: swap
/*    */     //   1141: aastore
/*    */     //   1142: invokevirtual cOM8 : ([Lf/U90;)Lf/U90;
/*    */     //   1145: iconst_0
/*    */     //   1146: swap
/*    */     //   1147: aastore
/*    */     //   1148: invokevirtual cOM8 : ([Lf/U90;)Lf/U90;
/*    */     //   1151: invokevirtual WN : (Lf/U90;)V
/*    */     //   1154: getfield qK : Lf/Ip;
/*    */     //   1157: invokevirtual d7 : ()Lf/cr0;
/*    */     //   1160: astore #7
/*    */     //   1162: getfield qK : Lf/Ip;
/*    */     //   1165: invokevirtual mE0 : ()Lf/g0;
/*    */     //   1168: dup
/*    */     //   1169: astore #8
/*    */     //   1171: aload_0
/*    */     //   1172: aload #8
/*    */     //   1174: aload_0
/*    */     //   1175: aload #8
/*    */     //   1177: dup
/*    */     //   1178: dup
/*    */     //   1179: aload #7
/*    */     //   1181: aload #8
/*    */     //   1183: invokevirtual ee0 : (Lf/U90;)Lf/U90;
/*    */     //   1186: pop
/*    */     //   1187: iconst_2
/*    */     //   1188: anewarray f/JG0
/*    */     //   1191: dup
/*    */     //   1192: dup
/*    */     //   1193: aload_0
/*    */     //   1194: swap
/*    */     //   1195: iconst_0
/*    */     //   1196: aload_2
/*    */     //   1197: aastore
/*    */     //   1198: getfield G9 : Lf/Rm;
/*    */     //   1201: iconst_1
/*    */     //   1202: swap
/*    */     //   1203: aastore
/*    */     //   1204: invokevirtual Mg : ([Lf/JG0;)Lf/U90;
/*    */     //   1207: pop
/*    */     //   1208: iconst_2
/*    */     //   1209: anewarray f/JG0
/*    */     //   1212: dup
/*    */     //   1213: dup
/*    */     //   1214: iconst_0
/*    */     //   1215: aload_3
/*    */     //   1216: aastore
/*    */     //   1217: iconst_1
/*    */     //   1218: aload #4
/*    */     //   1220: aastore
/*    */     //   1221: invokevirtual Mg : ([Lf/JG0;)Lf/U90;
/*    */     //   1224: pop
/*    */     //   1225: iconst_2
/*    */     //   1226: anewarray f/JG0
/*    */     //   1229: dup
/*    */     //   1230: dup
/*    */     //   1231: iconst_0
/*    */     //   1232: aload #5
/*    */     //   1234: aastore
/*    */     //   1235: iconst_1
/*    */     //   1236: aload #6
/*    */     //   1238: aastore
/*    */     //   1239: invokevirtual Mg : ([Lf/JG0;)Lf/U90;
/*    */     //   1242: bipush #6
/*    */     //   1244: invokevirtual Aq : (I)Lf/U90;
/*    */     //   1247: pop
/*    */     //   1248: getfield yx : Lf/Un;
/*    */     //   1251: invokevirtual Ya : (Lf/JG0;)Lf/U90;
/*    */     //   1254: pop
/*    */     //   1255: getfield bz : Lf/Un;
/*    */     //   1258: invokevirtual Ya : (Lf/JG0;)Lf/U90;
/*    */     //   1261: pop
/*    */     //   1262: getfield qK : Lf/Ip;
/*    */     //   1265: aload #7
/*    */     //   1267: invokevirtual rK0 : (Lf/U90;)V
/*    */     //   1270: getfield qK : Lf/Ip;
/*    */     //   1273: invokevirtual mE0 : ()Lf/g0;
/*    */     //   1276: astore #7
/*    */     //   1278: getfield qK : Lf/Ip;
/*    */     //   1281: invokevirtual d7 : ()Lf/cr0;
/*    */     //   1284: dup
/*    */     //   1285: astore #8
/*    */     //   1287: aload_0
/*    */     //   1288: aload #8
/*    */     //   1290: aload_0
/*    */     //   1291: aload #8
/*    */     //   1293: dup
/*    */     //   1294: dup2
/*    */     //   1295: aload #7
/*    */     //   1297: aload #8
/*    */     //   1299: invokevirtual ee0 : (Lf/U90;)Lf/U90;
/*    */     //   1302: pop
/*    */     //   1303: bipush #6
/*    */     //   1305: invokevirtual Aq : (I)Lf/U90;
/*    */     //   1308: pop
/*    */     //   1309: iconst_2
/*    */     //   1310: anewarray f/JG0
/*    */     //   1313: dup
/*    */     //   1314: dup
/*    */     //   1315: aload_0
/*    */     //   1316: swap
/*    */     //   1317: iconst_0
/*    */     //   1318: aload_2
/*    */     //   1319: aastore
/*    */     //   1320: getfield G9 : Lf/Rm;
/*    */     //   1323: iconst_1
/*    */     //   1324: swap
/*    */     //   1325: aastore
/*    */     //   1326: invokevirtual Mg : ([Lf/JG0;)Lf/U90;
/*    */     //   1329: bipush #6
/*    */     //   1331: invokevirtual Aq : (I)Lf/U90;
/*    */     //   1334: pop
/*    */     //   1335: iconst_2
/*    */     //   1336: anewarray f/JG0
/*    */     //   1339: dup
/*    */     //   1340: dup
/*    */     //   1341: iconst_0
/*    */     //   1342: aload_3
/*    */     //   1343: aastore
/*    */     //   1344: iconst_1
/*    */     //   1345: aload #4
/*    */     //   1347: aastore
/*    */     //   1348: invokevirtual Mg : ([Lf/JG0;)Lf/U90;
/*    */     //   1351: bipush #6
/*    */     //   1353: invokevirtual Aq : (I)Lf/U90;
/*    */     //   1356: pop
/*    */     //   1357: iconst_2
/*    */     //   1358: anewarray f/JG0
/*    */     //   1361: dup
/*    */     //   1362: dup
/*    */     //   1363: iconst_0
/*    */     //   1364: aload #5
/*    */     //   1366: aastore
/*    */     //   1367: iconst_1
/*    */     //   1368: aload #6
/*    */     //   1370: aastore
/*    */     //   1371: invokevirtual Mg : ([Lf/JG0;)Lf/U90;
/*    */     //   1374: bipush #6
/*    */     //   1376: invokevirtual Aq : (I)Lf/U90;
/*    */     //   1379: pop
/*    */     //   1380: getfield yx : Lf/Un;
/*    */     //   1383: invokevirtual Ya : (Lf/JG0;)Lf/U90;
/*    */     //   1386: pop
/*    */     //   1387: getfield bz : Lf/Un;
/*    */     //   1390: invokevirtual Ya : (Lf/JG0;)Lf/U90;
/*    */     //   1393: bipush #6
/*    */     //   1395: invokevirtual Aq : (I)Lf/U90;
/*    */     //   1398: pop
/*    */     //   1399: getfield qK : Lf/Ip;
/*    */     //   1402: aload #7
/*    */     //   1404: invokevirtual WN : (Lf/U90;)V
/*    */     //   1407: new f/Ip
/*    */     //   1410: dup
/*    */     //   1411: invokespecial <init> : ()V
/*    */     //   1414: putfield Cf0 : Lf/Ip;
/*    */     //   1417: new f/dQ
/*    */     //   1420: dup
/*    */     //   1421: aload_0
/*    */     //   1422: swap
/*    */     //   1423: dup
/*    */     //   1424: invokespecial <init> : ()V
/*    */     //   1427: putfield e70 : Lf/dQ;
/*    */     //   1430: ldc_w '$0'
/*    */     //   1433: invokevirtual E1 : (Ljava/lang/String;)V
/*    */     //   1436: getfield e70 : Lf/dQ;
/*    */     //   1439: iconst_0
/*    */     //   1440: invokevirtual sk0 : (Z)V
/*    */     //   1443: getfield e70 : Lf/dQ;
/*    */     //   1446: ldc_w 'label-horizontal-value'
/*    */     //   1449: invokevirtual Xu : (Ljava/lang/String;)V
/*    */     //   1452: iconst_0
/*    */     //   1453: istore_2
/*    */     //   1454: iload_2
/*    */     //   1455: aload_0
/*    */     //   1456: getfield wC0 : [[Lf/Qv0;
/*    */     //   1459: iconst_1
/*    */     //   1460: aaload
/*    */     //   1461: dup
/*    */     //   1462: astore_3
/*    */     //   1463: arraylength
/*    */     //   1464: if_icmpge -> 1533
/*    */     //   1467: iload_2
/*    */     //   1468: aload_0
/*    */     //   1469: dup
/*    */     //   1470: dup
/*    */     //   1471: aload_3
/*    */     //   1472: iload_2
/*    */     //   1473: new f/Qv0
/*    */     //   1476: dup
/*    */     //   1477: astore_3
/*    */     //   1478: aload_1
/*    */     //   1479: invokevirtual ec0 : ()Lf/public;
/*    */     //   1482: iload_2
/*    */     //   1483: iconst_0
/*    */     //   1484: invokespecial <init> : (Lf/Uc0;SZ)V
/*    */     //   1487: aload_3
/*    */     //   1488: aastore
/*    */     //   1489: getfield wC0 : [[Lf/Qv0;
/*    */     //   1492: iconst_1
/*    */     //   1493: aaload
/*    */     //   1494: iload_2
/*    */     //   1495: aaload
/*    */     //   1496: ldc 'partyslot'
/*    */     //   1498: invokevirtual Xu : (Ljava/lang/String;)V
/*    */     //   1501: getfield wC0 : [[Lf/Qv0;
/*    */     //   1504: iconst_1
/*    */     //   1505: aaload
/*    */     //   1506: iload_2
/*    */     //   1507: aaload
/*    */     //   1508: iconst_0
/*    */     //   1509: invokevirtual hC : (Z)V
/*    */     //   1512: getfield wC0 : [[Lf/Qv0;
/*    */     //   1515: iconst_1
/*    */     //   1516: aaload
/*    */     //   1517: iload_2
/*    */     //   1518: aaload
/*    */     //   1519: aload_1
/*    */     //   1520: invokevirtual ZA0 : ()Z
/*    */     //   1523: invokevirtual sk0 : (Z)V
/*    */     //   1526: iconst_1
/*    */     //   1527: iadd
/*    */     //   1528: i2s
/*    */     //   1529: istore_2
/*    */     //   1530: goto -> 1454
/*    */     //   1533: new f/dQ
/*    */     //   1536: dup
/*    */     //   1537: astore_2
/*    */     //   1538: sipush #1957
/*    */     //   1541: invokestatic OH0 : (I)Ljava/lang/String;
/*    */     //   1544: invokespecial <init> : (Ljava/lang/String;)V
/*    */     //   1547: new f/dQ
/*    */     //   1550: dup
/*    */     //   1551: astore_3
/*    */     //   1552: new java/lang/StringBuilder
/*    */     //   1555: dup
/*    */     //   1556: astore #4
/*    */     //   1558: invokespecial <init> : ()V
/*    */     //   1561: iconst_0
/*    */     //   1562: aload #4
/*    */     //   1564: ldc ': '
/*    */     //   1566: invokestatic jJ0 : (ILjava/lang/StringBuilder;Ljava/lang/String;)Ljava/lang/String;
/*    */     //   1569: invokespecial <init> : (Ljava/lang/String;)V
/*    */     //   1572: new f/Ip
/*    */     //   1575: dup
/*    */     //   1576: dup
/*    */     //   1577: dup2
/*    */     //   1578: dup2
/*    */     //   1579: astore #4
/*    */     //   1581: invokespecial <init> : ()V
/*    */     //   1584: ldc 'pokeframe'
/*    */     //   1586: invokevirtual Xu : (Ljava/lang/String;)V
/*    */     //   1589: invokevirtual d7 : ()Lf/cr0;
/*    */     //   1592: iconst_1
/*    */     //   1593: anewarray f/U90
/*    */     //   1596: dup
/*    */     //   1597: aload #4
/*    */     //   1599: invokevirtual mE0 : ()Lf/g0;
/*    */     //   1602: iconst_2
/*    */     //   1603: anewarray f/U90
/*    */     //   1606: dup
/*    */     //   1607: dup
/*    */     //   1608: aload #4
/*    */     //   1610: swap
/*    */     //   1611: aload #4
/*    */     //   1613: invokevirtual d7 : ()Lf/cr0;
/*    */     //   1616: bipush #20
/*    */     //   1618: invokevirtual Aq : (I)Lf/U90;
/*    */     //   1621: iconst_3
/*    */     //   1622: anewarray f/JG0
/*    */     //   1625: dup
/*    */     //   1626: dup
/*    */     //   1627: astore #5
/*    */     //   1629: aload_0
/*    */     //   1630: getfield wC0 : [[Lf/Qv0;
/*    */     //   1633: dup
/*    */     //   1634: aload #5
/*    */     //   1636: swap
/*    */     //   1637: iconst_1
/*    */     //   1638: aaload
/*    */     //   1639: dup
/*    */     //   1640: aload #5
/*    */     //   1642: swap
/*    */     //   1643: iconst_0
/*    */     //   1644: aaload
/*    */     //   1645: iconst_0
/*    */     //   1646: swap
/*    */     //   1647: aastore
/*    */     //   1648: iconst_1
/*    */     //   1649: aaload
/*    */     //   1650: iconst_1
/*    */     //   1651: swap
/*    */     //   1652: aastore
/*    */     //   1653: iconst_1
/*    */     //   1654: aaload
/*    */     //   1655: iconst_2
/*    */     //   1656: aaload
/*    */     //   1657: iconst_2
/*    */     //   1658: swap
/*    */     //   1659: aastore
/*    */     //   1660: invokevirtual Mg : ([Lf/JG0;)Lf/U90;
/*    */     //   1663: bipush #20
/*    */     //   1665: invokevirtual Aq : (I)Lf/U90;
/*    */     //   1668: iconst_0
/*    */     //   1669: swap
/*    */     //   1670: aastore
/*    */     //   1671: invokevirtual d7 : ()Lf/cr0;
/*    */     //   1674: bipush #20
/*    */     //   1676: invokevirtual Aq : (I)Lf/U90;
/*    */     //   1679: iconst_3
/*    */     //   1680: anewarray f/JG0
/*    */     //   1683: dup
/*    */     //   1684: dup
/*    */     //   1685: astore #5
/*    */     //   1687: aload_0
/*    */     //   1688: getfield wC0 : [[Lf/Qv0;
/*    */     //   1691: dup
/*    */     //   1692: aload #5
/*    */     //   1694: swap
/*    */     //   1695: iconst_1
/*    */     //   1696: aaload
/*    */     //   1697: dup
/*    */     //   1698: aload #5
/*    */     //   1700: swap
/*    */     //   1701: iconst_3
/*    */     //   1702: aaload
/*    */     //   1703: iconst_0
/*    */     //   1704: swap
/*    */     //   1705: aastore
/*    */     //   1706: iconst_4
/*    */     //   1707: aaload
/*    */     //   1708: iconst_1
/*    */     //   1709: swap
/*    */     //   1710: aastore
/*    */     //   1711: iconst_1
/*    */     //   1712: aaload
/*    */     //   1713: iconst_5
/*    */     //   1714: aaload
/*    */     //   1715: iconst_2
/*    */     //   1716: swap
/*    */     //   1717: aastore
/*    */     //   1718: invokevirtual Mg : ([Lf/JG0;)Lf/U90;
/*    */     //   1721: bipush #20
/*    */     //   1723: invokevirtual Aq : (I)Lf/U90;
/*    */     //   1726: iconst_1
/*    */     //   1727: swap
/*    */     //   1728: aastore
/*    */     //   1729: invokevirtual cOM8 : ([Lf/U90;)Lf/U90;
/*    */     //   1732: iconst_0
/*    */     //   1733: swap
/*    */     //   1734: aastore
/*    */     //   1735: invokevirtual cOM8 : ([Lf/U90;)Lf/U90;
/*    */     //   1738: invokevirtual rK0 : (Lf/U90;)V
/*    */     //   1741: invokevirtual mE0 : ()Lf/g0;
/*    */     //   1744: iconst_1
/*    */     //   1745: anewarray f/U90
/*    */     //   1748: dup
/*    */     //   1749: aload #4
/*    */     //   1751: invokevirtual d7 : ()Lf/cr0;
/*    */     //   1754: iconst_2
/*    */     //   1755: anewarray f/U90
/*    */     //   1758: dup
/*    */     //   1759: dup
/*    */     //   1760: aload #4
/*    */     //   1762: swap
/*    */     //   1763: aload #4
/*    */     //   1765: invokevirtual mE0 : ()Lf/g0;
/*    */     //   1768: iconst_3
/*    */     //   1769: anewarray f/JG0
/*    */     //   1772: dup
/*    */     //   1773: dup
/*    */     //   1774: astore #5
/*    */     //   1776: aload_0
/*    */     //   1777: getfield wC0 : [[Lf/Qv0;
/*    */     //   1780: dup
/*    */     //   1781: aload #5
/*    */     //   1783: swap
/*    */     //   1784: iconst_1
/*    */     //   1785: aaload
/*    */     //   1786: dup
/*    */     //   1787: aload #5
/*    */     //   1789: swap
/*    */     //   1790: iconst_0
/*    */     //   1791: aaload
/*    */     //   1792: iconst_0
/*    */     //   1793: swap
/*    */     //   1794: aastore
/*    */     //   1795: iconst_1
/*    */     //   1796: aaload
/*    */     //   1797: iconst_1
/*    */     //   1798: swap
/*    */     //   1799: aastore
/*    */     //   1800: iconst_1
/*    */     //   1801: aaload
/*    */     //   1802: iconst_2
/*    */     //   1803: aaload
/*    */     //   1804: iconst_2
/*    */     //   1805: swap
/*    */     //   1806: aastore
/*    */     //   1807: invokevirtual Mg : ([Lf/JG0;)Lf/U90;
/*    */     //   1810: iconst_0
/*    */     //   1811: swap
/*    */     //   1812: aastore
/*    */     //   1813: invokevirtual mE0 : ()Lf/g0;
/*    */     //   1816: iconst_3
/*    */     //   1817: anewarray f/JG0
/*    */     //   1820: dup
/*    */     //   1821: dup
/*    */     //   1822: astore #5
/*    */     //   1824: aload_0
/*    */     //   1825: getfield wC0 : [[Lf/Qv0;
/*    */     //   1828: dup
/*    */     //   1829: aload #5
/*    */     //   1831: swap
/*    */     //   1832: iconst_1
/*    */     //   1833: aaload
/*    */     //   1834: dup
/*    */     //   1835: aload #5
/*    */     //   1837: swap
/*    */     //   1838: iconst_3
/*    */     //   1839: aaload
/*    */     //   1840: iconst_0
/*    */     //   1841: swap
/*    */     //   1842: aastore
/*    */     //   1843: iconst_4
/*    */     //   1844: aaload
/*    */     //   1845: iconst_1
/*    */     //   1846: swap
/*    */     //   1847: aastore
/*    */     //   1848: iconst_1
/*    */     //   1849: aaload
/*    */     //   1850: iconst_5
/*    */     //   1851: aaload
/*    */     //   1852: iconst_2
/*    */     //   1853: swap
/*    */     //   1854: aastore
/*    */     //   1855: invokevirtual Mg : ([Lf/JG0;)Lf/U90;
/*    */     //   1858: iconst_1
/*    */     //   1859: swap
/*    */     //   1860: aastore
/*    */     //   1861: invokevirtual cOM8 : ([Lf/U90;)Lf/U90;
/*    */     //   1864: iconst_0
/*    */     //   1865: swap
/*    */     //   1866: aastore
/*    */     //   1867: invokevirtual cOM8 : ([Lf/U90;)Lf/U90;
/*    */     //   1870: invokevirtual WN : (Lf/U90;)V
/*    */     //   1873: new f/dQ
/*    */     //   1876: dup
/*    */     //   1877: astore #5
/*    */     //   1879: sipush #1967
/*    */     //   1882: invokestatic OH0 : (I)Ljava/lang/String;
/*    */     //   1885: invokespecial <init> : (Ljava/lang/String;)V
/*    */     //   1888: iconst_0
/*    */     //   1889: istore #6
/*    */     //   1891: iload #6
/*    */     //   1893: aload_0
/*    */     //   1894: getfield lpT8 : [[Lf/xK;
/*    */     //   1897: iconst_1
/*    */     //   1898: aaload
/*    */     //   1899: dup
/*    */     //   1900: astore #7
/*    */     //   1902: arraylength
/*    */     //   1903: if_icmpge -> 1951
/*    */     //   1906: iload #6
/*    */     //   1908: aload_0
/*    */     //   1909: aload #7
/*    */     //   1911: iload #6
/*    */     //   1913: new f/xK
/*    */     //   1916: dup
/*    */     //   1917: astore #7
/*    */     //   1919: iload #6
/*    */     //   1921: iconst_0
/*    */     //   1922: invokespecial <init> : (SZ)V
/*    */     //   1925: aload #7
/*    */     //   1927: aastore
/*    */     //   1928: getfield lpT8 : [[Lf/xK;
/*    */     //   1931: iconst_1
/*    */     //   1932: aaload
/*    */     //   1933: iload #6
/*    */     //   1935: aaload
/*    */     //   1936: aload_1
/*    */     //   1937: invokevirtual B5 : ()Z
/*    */     //   1940: invokevirtual sk0 : (Z)V
/*    */     //   1943: iconst_1
/*    */     //   1944: iadd
/*    */     //   1945: i2s
/*    */     //   1946: istore #6
/*    */     //   1948: goto -> 1891
/*    */     //   1951: aload_0
/*    */     //   1952: dup
/*    */     //   1953: dup2
/*    */     //   1954: dup2
/*    */     //   1955: dup2
/*    */     //   1956: dup2
/*    */     //   1957: new f/Ip
/*    */     //   1960: dup
/*    */     //   1961: dup
/*    */     //   1962: dup2
/*    */     //   1963: dup2
/*    */     //   1964: astore #6
/*    */     //   1966: invokespecial <init> : ()V
/*    */     //   1969: ldc 'pokeframe'
/*    */     //   1971: invokevirtual Xu : (Ljava/lang/String;)V
/*    */     //   1974: invokevirtual d7 : ()Lf/cr0;
/*    */     //   1977: iconst_1
/*    */     //   1978: anewarray f/U90
/*    */     //   1981: dup
/*    */     //   1982: aload #6
/*    */     //   1984: invokevirtual mE0 : ()Lf/g0;
/*    */     //   1987: iconst_2
/*    */     //   1988: anewarray f/U90
/*    */     //   1991: dup
/*    */     //   1992: dup
/*    */     //   1993: aload #6
/*    */     //   1995: swap
/*    */     //   1996: aload #6
/*    */     //   1998: invokevirtual d7 : ()Lf/cr0;
/*    */     //   2001: bipush #20
/*    */     //   2003: invokevirtual Aq : (I)Lf/U90;
/*    */     //   2006: iconst_3
/*    */     //   2007: anewarray f/JG0
/*    */     //   2010: dup
/*    */     //   2011: dup
/*    */     //   2012: astore #7
/*    */     //   2014: aload_0
/*    */     //   2015: getfield lpT8 : [[Lf/xK;
/*    */     //   2018: dup
/*    */     //   2019: aload #7
/*    */     //   2021: swap
/*    */     //   2022: iconst_1
/*    */     //   2023: aaload
/*    */     //   2024: dup
/*    */     //   2025: aload #7
/*    */     //   2027: swap
/*    */     //   2028: iconst_0
/*    */     //   2029: aaload
/*    */     //   2030: iconst_0
/*    */     //   2031: swap
/*    */     //   2032: aastore
/*    */     //   2033: iconst_1
/*    */     //   2034: aaload
/*    */     //   2035: iconst_1
/*    */     //   2036: swap
/*    */     //   2037: aastore
/*    */     //   2038: iconst_1
/*    */     //   2039: aaload
/*    */     //   2040: iconst_2
/*    */     //   2041: aaload
/*    */     //   2042: iconst_2
/*    */     //   2043: swap
/*    */     //   2044: aastore
/*    */     //   2045: invokevirtual Mg : ([Lf/JG0;)Lf/U90;
/*    */     //   2048: bipush #20
/*    */     //   2050: invokevirtual Aq : (I)Lf/U90;
/*    */     //   2053: iconst_0
/*    */     //   2054: swap
/*    */     //   2055: aastore
/*    */     //   2056: invokevirtual d7 : ()Lf/cr0;
/*    */     //   2059: bipush #20
/*    */     //   2061: invokevirtual Aq : (I)Lf/U90;
/*    */     //   2064: iconst_3
/*    */     //   2065: anewarray f/JG0
/*    */     //   2068: dup
/*    */     //   2069: dup
/*    */     //   2070: astore #7
/*    */     //   2072: aload_0
/*    */     //   2073: getfield lpT8 : [[Lf/xK;
/*    */     //   2076: dup
/*    */     //   2077: aload #7
/*    */     //   2079: swap
/*    */     //   2080: iconst_1
/*    */     //   2081: aaload
/*    */     //   2082: dup
/*    */     //   2083: aload #7
/*    */     //   2085: swap
/*    */     //   2086: iconst_3
/*    */     //   2087: aaload
/*    */     //   2088: iconst_0
/*    */     //   2089: swap
/*    */     //   2090: aastore
/*    */     //   2091: iconst_4
/*    */     //   2092: aaload
/*    */     //   2093: iconst_1
/*    */     //   2094: swap
/*    */     //   2095: aastore
/*    */     //   2096: iconst_1
/*    */     //   2097: aaload
/*    */     //   2098: iconst_5
/*    */     //   2099: aaload
/*    */     //   2100: iconst_2
/*    */     //   2101: swap
/*    */     //   2102: aastore
/*    */     //   2103: invokevirtual Mg : ([Lf/JG0;)Lf/U90;
/*    */     //   2106: bipush #20
/*    */     //   2108: invokevirtual Aq : (I)Lf/U90;
/*    */     //   2111: iconst_1
/*    */     //   2112: swap
/*    */     //   2113: aastore
/*    */     //   2114: invokevirtual cOM8 : ([Lf/U90;)Lf/U90;
/*    */     //   2117: iconst_0
/*    */     //   2118: swap
/*    */     //   2119: aastore
/*    */     //   2120: invokevirtual cOM8 : ([Lf/U90;)Lf/U90;
/*    */     //   2123: invokevirtual rK0 : (Lf/U90;)V
/*    */     //   2126: invokevirtual mE0 : ()Lf/g0;
/*    */     //   2129: iconst_1
/*    */     //   2130: anewarray f/U90
/*    */     //   2133: dup
/*    */     //   2134: aload #6
/*    */     //   2136: invokevirtual d7 : ()Lf/cr0;
/*    */     //   2139: iconst_2
/*    */     //   2140: anewarray f/U90
/*    */     //   2143: dup
/*    */     //   2144: dup
/*    */     //   2145: aload #6
/*    */     //   2147: swap
/*    */     //   2148: aload #6
/*    */     //   2150: invokevirtual mE0 : ()Lf/g0;
/*    */     //   2153: iconst_3
/*    */     //   2154: anewarray f/JG0
/*    */     //   2157: dup
/*    */     //   2158: dup
/*    */     //   2159: astore #7
/*    */     //   2161: aload_0
/*    */     //   2162: getfield lpT8 : [[Lf/xK;
/*    */     //   2165: dup
/*    */     //   2166: aload #7
/*    */     //   2168: swap
/*    */     //   2169: iconst_1
/*    */     //   2170: aaload
/*    */     //   2171: dup
/*    */     //   2172: aload #7
/*    */     //   2174: swap
/*    */     //   2175: iconst_0
/*    */     //   2176: aaload
/*    */     //   2177: iconst_0
/*    */     //   2178: swap
/*    */     //   2179: aastore
/*    */     //   2180: iconst_1
/*    */     //   2181: aaload
/*    */     //   2182: iconst_1
/*    */     //   2183: swap
/*    */     //   2184: aastore
/*    */     //   2185: iconst_1
/*    */     //   2186: aaload
/*    */     //   2187: iconst_2
/*    */     //   2188: aaload
/*    */     //   2189: iconst_2
/*    */     //   2190: swap
/*    */     //   2191: aastore
/*    */     //   2192: invokevirtual Mg : ([Lf/JG0;)Lf/U90;
/*    */     //   2195: iconst_0
/*    */     //   2196: swap
/*    */     //   2197: aastore
/*    */     //   2198: invokevirtual mE0 : ()Lf/g0;
/*    */     //   2201: iconst_3
/*    */     //   2202: anewarray f/JG0
/*    */     //   2205: dup
/*    */     //   2206: dup
/*    */     //   2207: astore #7
/*    */     //   2209: aload_0
/*    */     //   2210: getfield lpT8 : [[Lf/xK;
/*    */     //   2213: dup
/*    */     //   2214: aload #7
/*    */     //   2216: swap
/*    */     //   2217: iconst_1
/*    */     //   2218: aaload
/*    */     //   2219: dup
/*    */     //   2220: aload #7
/*    */     //   2222: swap
/*    */     //   2223: iconst_3
/*    */     //   2224: aaload
/*    */     //   2225: iconst_0
/*    */     //   2226: swap
/*    */     //   2227: aastore
/*    */     //   2228: iconst_4
/*    */     //   2229: aaload
/*    */     //   2230: iconst_1
/*    */     //   2231: swap
/*    */     //   2232: aastore
/*    */     //   2233: iconst_1
/*    */     //   2234: aaload
/*    */     //   2235: iconst_5
/*    */     //   2236: aaload
/*    */     //   2237: iconst_2
/*    */     //   2238: swap
/*    */     //   2239: aastore
/*    */     //   2240: invokevirtual Mg : ([Lf/JG0;)Lf/U90;
/*    */     //   2243: iconst_1
/*    */     //   2244: swap
/*    */     //   2245: aastore
/*    */     //   2246: invokevirtual cOM8 : ([Lf/U90;)Lf/U90;
/*    */     //   2249: iconst_0
/*    */     //   2250: swap
/*    */     //   2251: aastore
/*    */     //   2252: invokevirtual cOM8 : ([Lf/U90;)Lf/U90;
/*    */     //   2255: invokevirtual WN : (Lf/U90;)V
/*    */     //   2258: getfield Cf0 : Lf/Ip;
/*    */     //   2261: invokevirtual d7 : ()Lf/cr0;
/*    */     //   2264: astore #7
/*    */     //   2266: getfield Cf0 : Lf/Ip;
/*    */     //   2269: invokevirtual mE0 : ()Lf/g0;
/*    */     //   2272: dup
/*    */     //   2273: astore #8
/*    */     //   2275: aload_0
/*    */     //   2276: aload #8
/*    */     //   2278: aload_0
/*    */     //   2279: aload #8
/*    */     //   2281: dup
/*    */     //   2282: dup
/*    */     //   2283: aload #7
/*    */     //   2285: aload #8
/*    */     //   2287: invokevirtual ee0 : (Lf/U90;)Lf/U90;
/*    */     //   2290: pop
/*    */     //   2291: iconst_2
/*    */     //   2292: anewarray f/JG0
/*    */     //   2295: dup
/*    */     //   2296: dup
/*    */     //   2297: aload_0
/*    */     //   2298: swap
/*    */     //   2299: iconst_0
/*    */     //   2300: aload_2
/*    */     //   2301: aastore
/*    */     //   2302: getfield e70 : Lf/dQ;
/*    */     //   2305: iconst_1
/*    */     //   2306: swap
/*    */     //   2307: aastore
/*    */     //   2308: invokevirtual Mg : ([Lf/JG0;)Lf/U90;
/*    */     //   2311: pop
/*    */     //   2312: iconst_2
/*    */     //   2313: anewarray f/JG0
/*    */     //   2316: dup
/*    */     //   2317: dup
/*    */     //   2318: iconst_0
/*    */     //   2319: aload_3
/*    */     //   2320: aastore
/*    */     //   2321: iconst_1
/*    */     //   2322: aload #4
/*    */     //   2324: aastore
/*    */     //   2325: invokevirtual Mg : ([Lf/JG0;)Lf/U90;
/*    */     //   2328: pop
/*    */     //   2329: iconst_2
/*    */     //   2330: anewarray f/JG0
/*    */     //   2333: dup
/*    */     //   2334: dup
/*    */     //   2335: iconst_0
/*    */     //   2336: aload #5
/*    */     //   2338: aastore
/*    */     //   2339: iconst_1
/*    */     //   2340: aload #6
/*    */     //   2342: aastore
/*    */     //   2343: invokevirtual Mg : ([Lf/JG0;)Lf/U90;
/*    */     //   2346: bipush #6
/*    */     //   2348: invokevirtual Aq : (I)Lf/U90;
/*    */     //   2351: pop
/*    */     //   2352: getfield zo : Lf/Un;
/*    */     //   2355: invokevirtual Ya : (Lf/JG0;)Lf/U90;
/*    */     //   2358: pop
/*    */     //   2359: getfield Bg : Lf/Un;
/*    */     //   2362: invokevirtual Ya : (Lf/JG0;)Lf/U90;
/*    */     //   2365: pop
/*    */     //   2366: getfield Cf0 : Lf/Ip;
/*    */     //   2369: aload #7
/*    */     //   2371: invokevirtual rK0 : (Lf/U90;)V
/*    */     //   2374: getfield Cf0 : Lf/Ip;
/*    */     //   2377: invokevirtual mE0 : ()Lf/g0;
/*    */     //   2380: astore #7
/*    */     //   2382: getfield Cf0 : Lf/Ip;
/*    */     //   2385: invokevirtual d7 : ()Lf/cr0;
/*    */     //   2388: dup
/*    */     //   2389: astore #8
/*    */     //   2391: aload_0
/*    */     //   2392: aload #8
/*    */     //   2394: aload_0
/*    */     //   2395: aload #8
/*    */     //   2397: dup
/*    */     //   2398: dup2
/*    */     //   2399: aload #7
/*    */     //   2401: aload #8
/*    */     //   2403: invokevirtual ee0 : (Lf/U90;)Lf/U90;
/*    */     //   2406: pop
/*    */     //   2407: bipush #6
/*    */     //   2409: invokevirtual Aq : (I)Lf/U90;
/*    */     //   2412: pop
/*    */     //   2413: iconst_2
/*    */     //   2414: anewarray f/JG0
/*    */     //   2417: dup
/*    */     //   2418: dup
/*    */     //   2419: aload_0
/*    */     //   2420: swap
/*    */     //   2421: iconst_0
/*    */     //   2422: aload_2
/*    */     //   2423: aastore
/*    */     //   2424: getfield e70 : Lf/dQ;
/*    */     //   2427: iconst_1
/*    */     //   2428: swap
/*    */     //   2429: aastore
/*    */     //   2430: invokevirtual Mg : ([Lf/JG0;)Lf/U90;
/*    */     //   2433: bipush #6
/*    */     //   2435: invokevirtual Aq : (I)Lf/U90;
/*    */     //   2438: pop
/*    */     //   2439: iconst_2
/*    */     //   2440: anewarray f/JG0
/*    */     //   2443: dup
/*    */     //   2444: dup
/*    */     //   2445: iconst_0
/*    */     //   2446: aload_3
/*    */     //   2447: aastore
/*    */     //   2448: iconst_1
/*    */     //   2449: aload #4
/*    */     //   2451: aastore
/*    */     //   2452: invokevirtual Mg : ([Lf/JG0;)Lf/U90;
/*    */     //   2455: bipush #6
/*    */     //   2457: invokevirtual Aq : (I)Lf/U90;
/*    */     //   2460: pop
/*    */     //   2461: iconst_2
/*    */     //   2462: anewarray f/JG0
/*    */     //   2465: dup
/*    */     //   2466: dup
/*    */     //   2467: iconst_0
/*    */     //   2468: aload #5
/*    */     //   2470: aastore
/*    */     //   2471: iconst_1
/*    */     //   2472: aload #6
/*    */     //   2474: aastore
/*    */     //   2475: invokevirtual Mg : ([Lf/JG0;)Lf/U90;
/*    */     //   2478: bipush #6
/*    */     //   2480: invokevirtual Aq : (I)Lf/U90;
/*    */     //   2483: pop
/*    */     //   2484: getfield zo : Lf/Un;
/*    */     //   2487: invokevirtual Ya : (Lf/JG0;)Lf/U90;
/*    */     //   2490: pop
/*    */     //   2491: getfield Bg : Lf/Un;
/*    */     //   2494: invokevirtual Ya : (Lf/JG0;)Lf/U90;
/*    */     //   2497: bipush #6
/*    */     //   2499: invokevirtual Aq : (I)Lf/U90;
/*    */     //   2502: pop
/*    */     //   2503: getfield Cf0 : Lf/Ip;
/*    */     //   2506: aload #7
/*    */     //   2508: invokevirtual WN : (Lf/U90;)V
/*    */     //   2511: new f/dQ
/*    */     //   2514: dup
/*    */     //   2515: astore_2
/*    */     //   2516: getstatic f/km.a3 : Lf/vh0;
/*    */     //   2519: invokevirtual wQ : ()Lf/Jo;
/*    */     //   2522: invokevirtual m : ()Ljava/lang/String;
/*    */     //   2525: invokespecial <init> : (Ljava/lang/String;)V
/*    */     //   2528: new f/dQ
/*    */     //   2531: dup
/*    */     //   2532: astore_3
/*    */     //   2533: aload_1
/*    */     //   2534: invokevirtual W50 : ()Ljava/lang/String;
/*    */     //   2537: invokespecial <init> : (Ljava/lang/String;)V
/*    */     //   2540: getfield d30 : Lf/Ip;
/*    */     //   2543: dup
/*    */     //   2544: invokevirtual mE0 : ()Lf/g0;
/*    */     //   2547: iconst_2
/*    */     //   2548: anewarray f/U90
/*    */     //   2551: dup
/*    */     //   2552: dup
/*    */     //   2553: aload_0
/*    */     //   2554: swap
/*    */     //   2555: aload_0
/*    */     //   2556: getfield d30 : Lf/Ip;
/*    */     //   2559: invokevirtual d7 : ()Lf/cr0;
/*    */     //   2562: invokevirtual Em0 : ()Lf/U90;
/*    */     //   2565: getstatic f/et.Wi0 : Lf/et;
/*    */     //   2568: dup
/*    */     //   2569: astore_1
/*    */     //   2570: aload_2
/*    */     //   2571: invokevirtual lW : (Lf/et;Lf/JG0;)Lf/U90;
/*    */     //   2574: invokevirtual Em0 : ()Lf/U90;
/*    */     //   2577: aload_1
/*    */     //   2578: aload_3
/*    */     //   2579: invokevirtual lW : (Lf/et;Lf/JG0;)Lf/U90;
/*    */     //   2582: invokevirtual Em0 : ()Lf/U90;
/*    */     //   2585: iconst_0
/*    */     //   2586: swap
/*    */     //   2587: aastore
/*    */     //   2588: getfield d30 : Lf/Ip;
/*    */     //   2591: invokevirtual d7 : ()Lf/cr0;
/*    */     //   2594: invokevirtual Em0 : ()Lf/U90;
/*    */     //   2597: aload_1
/*    */     //   2598: aload_0
/*    */     //   2599: getfield qK : Lf/Ip;
/*    */     //   2602: invokevirtual lW : (Lf/et;Lf/JG0;)Lf/U90;
/*    */     //   2605: invokevirtual Em0 : ()Lf/U90;
/*    */     //   2608: aload_1
/*    */     //   2609: aload_0
/*    */     //   2610: getfield Cf0 : Lf/Ip;
/*    */     //   2613: invokevirtual lW : (Lf/et;Lf/JG0;)Lf/U90;
/*    */     //   2616: invokevirtual Em0 : ()Lf/U90;
/*    */     //   2619: iconst_1
/*    */     //   2620: swap
/*    */     //   2621: aastore
/*    */     //   2622: invokevirtual cOM8 : ([Lf/U90;)Lf/U90;
/*    */     //   2625: invokevirtual rK0 : (Lf/U90;)V
/*    */     //   2628: getfield d30 : Lf/Ip;
/*    */     //   2631: dup
/*    */     //   2632: invokevirtual d7 : ()Lf/cr0;
/*    */     //   2635: iconst_2
/*    */     //   2636: anewarray f/U90
/*    */     //   2639: dup
/*    */     //   2640: dup
/*    */     //   2641: aload_0
/*    */     //   2642: swap
/*    */     //   2643: aload_0
/*    */     //   2644: getfield d30 : Lf/Ip;
/*    */     //   2647: invokevirtual mE0 : ()Lf/g0;
/*    */     //   2650: iconst_2
/*    */     //   2651: anewarray f/JG0
/*    */     //   2654: dup
/*    */     //   2655: dup
/*    */     //   2656: iconst_0
/*    */     //   2657: aload_2
/*    */     //   2658: aastore
/*    */     //   2659: iconst_1
/*    */     //   2660: aload_3
/*    */     //   2661: aastore
/*    */     //   2662: invokevirtual Mg : ([Lf/JG0;)Lf/U90;
/*    */     //   2665: iconst_0
/*    */     //   2666: swap
/*    */     //   2667: aastore
/*    */     //   2668: getfield d30 : Lf/Ip;
/*    */     //   2671: invokevirtual mE0 : ()Lf/g0;
/*    */     //   2674: iconst_2
/*    */     //   2675: anewarray f/JG0
/*    */     //   2678: dup
/*    */     //   2679: dup
/*    */     //   2680: aload_0
/*    */     //   2681: swap
/*    */     //   2682: aload_0
/*    */     //   2683: getfield qK : Lf/Ip;
/*    */     //   2686: iconst_0
/*    */     //   2687: swap
/*    */     //   2688: aastore
/*    */     //   2689: getfield Cf0 : Lf/Ip;
/*    */     //   2692: iconst_1
/*    */     //   2693: swap
/*    */     //   2694: aastore
/*    */     //   2695: invokevirtual Mg : ([Lf/JG0;)Lf/U90;
/*    */     //   2698: iconst_1
/*    */     //   2699: swap
/*    */     //   2700: aastore
/*    */     //   2701: invokevirtual cOM8 : ([Lf/U90;)Lf/U90;
/*    */     //   2704: invokevirtual WN : (Lf/U90;)V
/*    */     //   2707: getfield d30 : Lf/Ip;
/*    */     //   2710: invokevirtual J8 : (Lf/JG0;)V
/*    */     //   2713: new f/Fy0
/*    */     //   2716: astore_1
/*    */     //   2717: ldc_w ''
/*    */     //   2720: astore_2
/*    */     //   2721: invokestatic XU : ()Z
/*    */     //   2724: ifeq -> 2733
/*    */     //   2727: bipush #60
/*    */     //   2729: istore_3
/*    */     //   2730: goto -> 2736
/*    */     //   2733: bipush #16
/*    */     //   2735: istore_3
/*    */     //   2736: invokestatic XU : ()Z
/*    */     //   2739: ifeq -> 2749
/*    */     //   2742: bipush #60
/*    */     //   2744: istore #4
/*    */     //   2746: goto -> 2753
/*    */     //   2749: bipush #16
/*    */     //   2751: istore #4
/*    */     //   2753: aload_0
/*    */     //   2754: aload_1
/*    */     //   2755: dup
/*    */     //   2756: dup2
/*    */     //   2757: aload_0
/*    */     //   2758: aload_1
/*    */     //   2759: dup
/*    */     //   2760: aload_2
/*    */     //   2761: iload_3
/*    */     //   2762: iload #4
/*    */     //   2764: invokespecial <init> : (Ljava/lang/String;II)V
/*    */     //   2767: putfield pG0 : Lf/Fy0;
/*    */     //   2770: ldc_w 'tooltip-button'
/*    */     //   2773: invokevirtual Xu : (Ljava/lang/String;)V
/*    */     //   2776: new f/Ip
/*    */     //   2779: dup
/*    */     //   2780: dup2
/*    */     //   2781: dup2
/*    */     //   2782: astore_0
/*    */     //   2783: invokespecial <init> : ()V
/*    */     //   2786: new f/dQ
/*    */     //   2789: dup
/*    */     //   2790: astore_1
/*    */     //   2791: sipush #7000
/*    */     //   2794: invokestatic OH0 : (I)Ljava/lang/String;
/*    */     //   2797: invokespecial <init> : (Ljava/lang/String;)V
/*    */     //   2800: new f/Fy0
/*    */     //   2803: dup
/*    */     //   2804: dup
/*    */     //   2805: dup2
/*    */     //   2806: astore_2
/*    */     //   2807: ldc_w ''
/*    */     //   2810: bipush #40
/*    */     //   2812: bipush #30
/*    */     //   2814: invokespecial <init> : (Ljava/lang/String;II)V
/*    */     //   2817: invokevirtual zY : ()Lf/rH;
/*    */     //   2820: invokestatic TK0 : ()Lf/um0;
/*    */     //   2823: bipush #25
/*    */     //   2825: iconst_0
/*    */     //   2826: iconst_0
/*    */     //   2827: invokevirtual lb : (SZB)[Lf/zh0;
/*    */     //   2830: invokevirtual sm : ([Lf/zh0;)V
/*    */     //   2833: invokevirtual zY : ()Lf/rH;
/*    */     //   2836: iconst_1
/*    */     //   2837: bipush #-4
/*    */     //   2839: invokevirtual zT : (II)Lf/JG0;
/*    */     //   2842: pop
/*    */     //   2843: ldc_w 'partyslot-shiny'
/*    */     //   2846: invokevirtual Xu : (Ljava/lang/String;)V
/*    */     //   2849: invokevirtual mE0 : ()Lf/g0;
/*    */     //   2852: iconst_2
/*    */     //   2853: anewarray f/U90
/*    */     //   2856: dup
/*    */     //   2857: dup
/*    */     //   2858: aload_0
/*    */     //   2859: swap
/*    */     //   2860: aload_0
/*    */     //   2861: invokevirtual d7 : ()Lf/cr0;
/*    */     //   2864: aload_1
/*    */     //   2865: invokevirtual Ya : (Lf/JG0;)Lf/U90;
/*    */     //   2868: iconst_0
/*    */     //   2869: swap
/*    */     //   2870: aastore
/*    */     //   2871: invokevirtual d7 : ()Lf/cr0;
/*    */     //   2874: iconst_1
/*    */     //   2875: anewarray f/JG0
/*    */     //   2878: dup
/*    */     //   2879: iconst_0
/*    */     //   2880: aload_2
/*    */     //   2881: aastore
/*    */     //   2882: invokevirtual Mg : ([Lf/JG0;)Lf/U90;
/*    */     //   2885: iconst_1
/*    */     //   2886: swap
/*    */     //   2887: aastore
/*    */     //   2888: invokevirtual cOM8 : ([Lf/U90;)Lf/U90;
/*    */     //   2891: invokevirtual rK0 : (Lf/U90;)V
/*    */     //   2894: invokevirtual d7 : ()Lf/cr0;
/*    */     //   2897: iconst_2
/*    */     //   2898: anewarray f/U90
/*    */     //   2901: dup
/*    */     //   2902: dup
/*    */     //   2903: aload_0
/*    */     //   2904: swap
/*    */     //   2905: aload_0
/*    */     //   2906: invokevirtual mE0 : ()Lf/g0;
/*    */     //   2909: iconst_1
/*    */     //   2910: anewarray f/JG0
/*    */     //   2913: dup
/*    */     //   2914: iconst_0
/*    */     //   2915: aload_1
/*    */     //   2916: aastore
/*    */     //   2917: invokevirtual Mg : ([Lf/JG0;)Lf/U90;
/*    */     //   2920: iconst_0
/*    */     //   2921: swap
/*    */     //   2922: aastore
/*    */     //   2923: invokevirtual mE0 : ()Lf/g0;
/*    */     //   2926: iconst_1
/*    */     //   2927: anewarray f/JG0
/*    */     //   2930: dup
/*    */     //   2931: iconst_0
/*    */     //   2932: aload_2
/*    */     //   2933: aastore
/*    */     //   2934: invokevirtual Mg : ([Lf/JG0;)Lf/U90;
/*    */     //   2937: iconst_1
/*    */     //   2938: swap
/*    */     //   2939: aastore
/*    */     //   2940: invokevirtual cOM8 : ([Lf/U90;)Lf/U90;
/*    */     //   2943: invokevirtual WN : (Lf/U90;)V
/*    */     //   2946: iconst_0
/*    */     //   2947: invokevirtual Pb0 : (I)V
/*    */     //   2950: aload_0
/*    */     //   2951: invokevirtual Gq0 : (Ljava/lang/Object;)V
/*    */     //   2954: invokevirtual J8 : (Lf/JG0;)V
/*    */     //   2957: return
/*    */     // Line number table:
/*    */     //   Java source line number -> byte code offset
/*    */     //   #1	-> 439
/*    */     //   #2	-> 444
/*    */     //   #3	-> 1564
/*    */     //   #4	-> 1569 } public static void xC0(P4 paramP4, Qv0 paramQv0) { byte b = paramP4.QO;
/*    */     if (paramP4.g00[b])
/*    */       return; 
/*  7 */     F7.Yo(JB0.n7(paramQv0, km.u4.z2), paramQv0); } private void p80(P4 paramP4) { // Byte code:
/*    */     //   0: iconst_2
/*    */     //   1: anewarray f/Ip
/*    */     //   4: astore_2
/*    */     //   5: new f/dQ
/*    */     //   8: dup
/*    */     //   9: dup
/*    */     //   10: astore_3
/*    */     //   11: sipush #1963
/*    */     //   14: invokestatic OH0 : (I)Ljava/lang/String;
/*    */     //   17: astore #4
/*    */     //   19: invokespecial <init> : ()V
/*    */     //   22: aload #4
/*    */     //   24: invokevirtual E1 : (Ljava/lang/String;)V
/*    */     //   27: new f/dQ
/*    */     //   30: dup
/*    */     //   31: dup
/*    */     //   32: astore #4
/*    */     //   34: sipush #1964
/*    */     //   37: invokestatic OH0 : (I)Ljava/lang/String;
/*    */     //   40: astore #5
/*    */     //   42: invokespecial <init> : ()V
/*    */     //   45: aload #5
/*    */     //   47: invokevirtual E1 : (Ljava/lang/String;)V
/*    */     //   50: new f/dQ
/*    */     //   53: dup
/*    */     //   54: dup
/*    */     //   55: astore #5
/*    */     //   57: sipush #1965
/*    */     //   60: invokestatic OH0 : (I)Ljava/lang/String;
/*    */     //   63: astore #6
/*    */     //   65: invokespecial <init> : ()V
/*    */     //   68: aload #6
/*    */     //   70: invokevirtual E1 : (Ljava/lang/String;)V
/*    */     //   73: iconst_0
/*    */     //   74: istore #6
/*    */     //   76: iload #6
/*    */     //   78: iconst_2
/*    */     //   79: if_icmpge -> 1555
/*    */     //   82: aload_1
/*    */     //   83: aload_2
/*    */     //   84: iload #6
/*    */     //   86: aload_2
/*    */     //   87: iload #6
/*    */     //   89: new f/Ip
/*    */     //   92: dup
/*    */     //   93: astore #7
/*    */     //   95: aload_2
/*    */     //   96: iload #6
/*    */     //   98: aload #7
/*    */     //   100: invokespecial <init> : ()V
/*    */     //   103: aload #7
/*    */     //   105: aastore
/*    */     //   106: ldc_w '/confirm-panel-dialog'
/*    */     //   109: invokevirtual Xu : (Ljava/lang/String;)V
/*    */     //   112: aaload
/*    */     //   113: dup
/*    */     //   114: invokestatic X60 : (Lf/Ip;Lf/Ip;)Lf/g0;
/*    */     //   117: astore #7
/*    */     //   119: aaload
/*    */     //   120: dup
/*    */     //   121: invokestatic Ur : (Lf/Ip;Lf/Ip;)Lf/cr0;
/*    */     //   124: astore #8
/*    */     //   126: getfield QO : B
/*    */     //   129: iload #6
/*    */     //   131: if_icmpne -> 153
/*    */     //   134: aload #8
/*    */     //   136: aload #7
/*    */     //   138: aload #5
/*    */     //   140: invokevirtual Ya : (Lf/JG0;)Lf/U90;
/*    */     //   143: pop
/*    */     //   144: aload #5
/*    */     //   146: invokevirtual Ya : (Lf/JG0;)Lf/U90;
/*    */     //   149: pop
/*    */     //   150: goto -> 169
/*    */     //   153: aload #8
/*    */     //   155: aload #7
/*    */     //   157: aload #4
/*    */     //   159: invokevirtual Ya : (Lf/JG0;)Lf/U90;
/*    */     //   162: pop
/*    */     //   163: aload #4
/*    */     //   165: invokevirtual Ya : (Lf/JG0;)Lf/U90;
/*    */     //   168: pop
/*    */     //   169: aload_1
/*    */     //   170: aload #7
/*    */     //   172: aload #8
/*    */     //   174: new f/Ip
/*    */     //   177: dup
/*    */     //   178: dup
/*    */     //   179: dup2
/*    */     //   180: astore #9
/*    */     //   182: invokespecial <init> : ()V
/*    */     //   185: new f/dQ
/*    */     //   188: dup
/*    */     //   189: dup
/*    */     //   190: astore #10
/*    */     //   192: ldc_w '$'
/*    */     //   195: invokestatic df : (Ljava/lang/String;)Ljava/lang/StringBuilder;
/*    */     //   198: invokestatic getInstance : ()Ljava/text/NumberFormat;
/*    */     //   201: aload_1
/*    */     //   202: getfield bG0 : [I
/*    */     //   205: iload #6
/*    */     //   207: iaload
/*    */     //   208: i2l
/*    */     //   209: invokevirtual format : (J)Ljava/lang/String;
/*    */     //   212: invokevirtual append : (Ljava/lang/String;)Ljava/lang/StringBuilder;
/*    */     //   215: invokevirtual toString : ()Ljava/lang/String;
/*    */     //   218: astore #11
/*    */     //   220: invokespecial <init> : ()V
/*    */     //   223: aload #11
/*    */     //   225: invokevirtual E1 : (Ljava/lang/String;)V
/*    */     //   228: ldc_w '/confirm-panel-dialog2'
/*    */     //   231: invokevirtual Xu : (Ljava/lang/String;)V
/*    */     //   234: new f/cr0
/*    */     //   237: dup
/*    */     //   238: aload #9
/*    */     //   240: invokespecial <init> : (Lf/Ip;)V
/*    */     //   243: bipush #10
/*    */     //   245: invokevirtual Aq : (I)Lf/U90;
/*    */     //   248: iconst_1
/*    */     //   249: anewarray f/JG0
/*    */     //   252: dup
/*    */     //   253: iconst_0
/*    */     //   254: aload #10
/*    */     //   256: aastore
/*    */     //   257: invokevirtual Mg : ([Lf/JG0;)Lf/U90;
/*    */     //   260: bipush #20
/*    */     //   262: invokevirtual Aq : (I)Lf/U90;
/*    */     //   265: invokevirtual rK0 : (Lf/U90;)V
/*    */     //   268: new f/g0
/*    */     //   271: dup
/*    */     //   272: aload #9
/*    */     //   274: invokespecial <init> : (Lf/Ip;)V
/*    */     //   277: iconst_1
/*    */     //   278: anewarray f/JG0
/*    */     //   281: dup
/*    */     //   282: iconst_0
/*    */     //   283: aload #10
/*    */     //   285: aastore
/*    */     //   286: invokevirtual Mg : ([Lf/JG0;)Lf/U90;
/*    */     //   289: invokevirtual WN : (Lf/U90;)V
/*    */     //   292: iconst_1
/*    */     //   293: anewarray f/JG0
/*    */     //   296: dup
/*    */     //   297: iconst_0
/*    */     //   298: aload #9
/*    */     //   300: aastore
/*    */     //   301: invokevirtual Mg : ([Lf/JG0;)Lf/U90;
/*    */     //   304: pop
/*    */     //   305: iconst_1
/*    */     //   306: anewarray f/JG0
/*    */     //   309: dup
/*    */     //   310: iconst_0
/*    */     //   311: aload #9
/*    */     //   313: aastore
/*    */     //   314: invokevirtual Mg : ([Lf/JG0;)Lf/U90;
/*    */     //   317: pop
/*    */     //   318: iconst_1
/*    */     //   319: istore #9
/*    */     //   321: getfield Tq0 : [Lf/public;
/*    */     //   324: iload #6
/*    */     //   326: aaload
/*    */     //   327: invokevirtual lPt3 : ()[Lf/j40;
/*    */     //   330: dup
/*    */     //   331: astore #10
/*    */     //   333: arraylength
/*    */     //   334: istore #11
/*    */     //   336: iconst_0
/*    */     //   337: istore #12
/*    */     //   339: iload #12
/*    */     //   341: iload #11
/*    */     //   343: if_icmpge -> 1111
/*    */     //   346: aload #10
/*    */     //   348: iload #12
/*    */     //   350: aaload
/*    */     //   351: dup
/*    */     //   352: astore #13
/*    */     //   354: ifnull -> 1105
/*    */     //   357: iconst_0
/*    */     //   358: istore #9
/*    */     //   360: new f/Ip
/*    */     //   363: dup
/*    */     //   364: dup
/*    */     //   365: astore #14
/*    */     //   367: invokespecial <init> : ()V
/*    */     //   370: ldc_w '/confirm-panel-dialog2'
/*    */     //   373: invokevirtual Xu : (Ljava/lang/String;)V
/*    */     //   376: getstatic f/Of.eH : Lf/Of;
/*    */     //   379: aload #13
/*    */     //   381: getfield Zs : Lf/Q90;
/*    */     //   384: invokevirtual p10 : ()S
/*    */     //   387: invokevirtual On0 : (S)Lf/LPT3;
/*    */     //   390: astore #15
/*    */     //   392: new f/vF0
/*    */     //   395: dup
/*    */     //   396: astore #16
/*    */     //   398: iconst_0
/*    */     //   399: iconst_0
/*    */     //   400: iconst_0
/*    */     //   401: invokespecial <init> : (III)V
/*    */     //   404: new f/vF0
/*    */     //   407: dup
/*    */     //   408: astore #17
/*    */     //   410: iconst_0
/*    */     //   411: iconst_0
/*    */     //   412: iconst_0
/*    */     //   413: invokespecial <init> : (III)V
/*    */     //   416: invokestatic XU : ()Z
/*    */     //   419: ifeq -> 460
/*    */     //   422: new f/vF0
/*    */     //   425: dup
/*    */     //   426: dup2
/*    */     //   427: astore #18
/*    */     //   429: bipush #72
/*    */     //   431: bipush #72
/*    */     //   433: iconst_0
/*    */     //   434: invokespecial <init> : (III)V
/*    */     //   437: getfield TS : Lf/rH;
/*    */     //   440: bipush #72
/*    */     //   442: bipush #72
/*    */     //   444: invokevirtual tL : (II)V
/*    */     //   447: getfield TS : Lf/rH;
/*    */     //   450: iconst_0
/*    */     //   451: bipush #-10
/*    */     //   453: invokevirtual zT : (II)Lf/JG0;
/*    */     //   456: pop
/*    */     //   457: goto -> 485
/*    */     //   460: new f/vF0
/*    */     //   463: dup
/*    */     //   464: dup
/*    */     //   465: astore #18
/*    */     //   467: bipush #36
/*    */     //   469: bipush #36
/*    */     //   471: iconst_0
/*    */     //   472: invokespecial <init> : (III)V
/*    */     //   475: getfield TS : Lf/rH;
/*    */     //   478: bipush #36
/*    */     //   480: bipush #36
/*    */     //   482: invokevirtual tL : (II)V
/*    */     //   485: aload #13
/*    */     //   487: getfield Zs : Lf/Q90;
/*    */     //   490: invokevirtual tm0 : ()Z
/*    */     //   493: ifeq -> 602
/*    */     //   496: aload #17
/*    */     //   498: getfield TS : Lf/rH;
/*    */     //   501: iconst_1
/*    */     //   502: anewarray f/pe0
/*    */     //   505: dup
/*    */     //   506: invokestatic ZZ : ()Lf/interface;
/*    */     //   509: aload #13
/*    */     //   511: getfield Zs : Lf/Q90;
/*    */     //   514: invokevirtual Gf : ()Z
/*    */     //   517: invokevirtual yI0 : (Z)Lf/pe0;
/*    */     //   520: iconst_0
/*    */     //   521: swap
/*    */     //   522: aastore
/*    */     //   523: invokevirtual Pn : ([Lf/pe0;)Lf/JG0;
/*    */     //   526: pop
/*    */     //   527: invokestatic XU : ()Z
/*    */     //   530: ifeq -> 562
/*    */     //   533: aload #17
/*    */     //   535: dup
/*    */     //   536: dup
/*    */     //   537: getfield TS : Lf/rH;
/*    */     //   540: bipush #32
/*    */     //   542: bipush #32
/*    */     //   544: invokevirtual tL : (II)V
/*    */     //   547: getfield TS : Lf/rH;
/*    */     //   550: astore #19
/*    */     //   552: getfield Kd : I
/*    */     //   555: iconst_5
/*    */     //   556: isub
/*    */     //   557: istore #20
/*    */     //   559: goto -> 588
/*    */     //   562: aload #17
/*    */     //   564: dup
/*    */     //   565: dup
/*    */     //   566: getfield TS : Lf/rH;
/*    */     //   569: bipush #16
/*    */     //   571: bipush #16
/*    */     //   573: invokevirtual tL : (II)V
/*    */     //   576: getfield TS : Lf/rH;
/*    */     //   579: astore #19
/*    */     //   581: getfield Kd : I
/*    */     //   584: iconst_4
/*    */     //   585: isub
/*    */     //   586: istore #20
/*    */     //   588: aload #19
/*    */     //   590: aload #17
/*    */     //   592: getfield er0 : I
/*    */     //   595: iload #20
/*    */     //   597: swap
/*    */     //   598: invokevirtual zT : (II)Lf/JG0;
/*    */     //   601: pop
/*    */     //   602: aload #13
/*    */     //   604: getfield Zs : Lf/Q90;
/*    */     //   607: getfield wH : [Lf/mA;
/*    */     //   610: arraylength
/*    */     //   611: ifle -> 796
/*    */     //   614: aload #16
/*    */     //   616: getfield TS : Lf/rH;
/*    */     //   619: iconst_1
/*    */     //   620: anewarray f/pe0
/*    */     //   623: dup
/*    */     //   624: invokestatic ZZ : ()Lf/interface;
/*    */     //   627: getfield oX : Lf/pe0;
/*    */     //   630: iconst_0
/*    */     //   631: swap
/*    */     //   632: aastore
/*    */     //   633: invokevirtual Pn : ([Lf/pe0;)Lf/JG0;
/*    */     //   636: pop
/*    */     //   637: invokestatic XU : ()Z
/*    */     //   640: ifeq -> 714
/*    */     //   643: aload #17
/*    */     //   645: aload #16
/*    */     //   647: getfield TS : Lf/rH;
/*    */     //   650: bipush #32
/*    */     //   652: bipush #32
/*    */     //   654: invokevirtual tL : (II)V
/*    */     //   657: getfield TS : Lf/rH;
/*    */     //   660: invokevirtual cA : ()I
/*    */     //   663: ifle -> 694
/*    */     //   666: aload #16
/*    */     //   668: getfield TS : Lf/rH;
/*    */     //   671: aload #17
/*    */     //   673: getfield Kd : I
/*    */     //   676: bipush #10
/*    */     //   678: isub
/*    */     //   679: aload #17
/*    */     //   681: getfield er0 : I
/*    */     //   684: bipush #24
/*    */     //   686: iadd
/*    */     //   687: invokevirtual zT : (II)Lf/JG0;
/*    */     //   690: pop
/*    */     //   691: goto -> 796
/*    */     //   694: aload #17
/*    */     //   696: aload #16
/*    */     //   698: getfield TS : Lf/rH;
/*    */     //   701: astore #19
/*    */     //   703: getfield Kd : I
/*    */     //   706: bipush #10
/*    */     //   708: isub
/*    */     //   709: istore #20
/*    */     //   711: goto -> 782
/*    */     //   714: aload #17
/*    */     //   716: aload #16
/*    */     //   718: getfield TS : Lf/rH;
/*    */     //   721: bipush #16
/*    */     //   723: bipush #16
/*    */     //   725: invokevirtual tL : (II)V
/*    */     //   728: getfield TS : Lf/rH;
/*    */     //   731: invokevirtual cA : ()I
/*    */     //   734: ifle -> 765
/*    */     //   737: aload #16
/*    */     //   739: getfield TS : Lf/rH;
/*    */     //   742: aload #17
/*    */     //   744: getfield Kd : I
/*    */     //   747: bipush #9
/*    */     //   749: isub
/*    */     //   750: aload #17
/*    */     //   752: getfield er0 : I
/*    */     //   755: bipush #16
/*    */     //   757: iadd
/*    */     //   758: invokevirtual zT : (II)Lf/JG0;
/*    */     //   761: pop
/*    */     //   762: goto -> 796
/*    */     //   765: aload #17
/*    */     //   767: aload #16
/*    */     //   769: getfield TS : Lf/rH;
/*    */     //   772: astore #19
/*    */     //   774: getfield Kd : I
/*    */     //   777: bipush #9
/*    */     //   779: isub
/*    */     //   780: istore #20
/*    */     //   782: aload #19
/*    */     //   784: aload #17
/*    */     //   786: getfield er0 : I
/*    */     //   789: iload #20
/*    */     //   791: swap
/*    */     //   792: invokevirtual zT : (II)Lf/JG0;
/*    */     //   795: pop
/*    */     //   796: aload #13
/*    */     //   798: aload #18
/*    */     //   800: dup
/*    */     //   801: aload #13
/*    */     //   803: aload #18
/*    */     //   805: dup
/*    */     //   806: getfield TS : Lf/rH;
/*    */     //   809: iconst_1
/*    */     //   810: anewarray f/zh0
/*    */     //   813: dup
/*    */     //   814: getstatic f/um0.Kt0 : Lf/um0;
/*    */     //   817: aload #13
/*    */     //   819: dup
/*    */     //   820: getfield Zs : Lf/Q90;
/*    */     //   823: invokevirtual Vf0 : ()S
/*    */     //   826: istore #19
/*    */     //   828: invokevirtual s5 : ()B
/*    */     //   831: istore #20
/*    */     //   833: iload #19
/*    */     //   835: aload #13
/*    */     //   837: getfield Zs : Lf/Q90;
/*    */     //   840: invokevirtual da : ()Z
/*    */     //   843: iload #20
/*    */     //   845: invokevirtual lb : (SZB)[Lf/zh0;
/*    */     //   848: iconst_0
/*    */     //   849: aaload
/*    */     //   850: iconst_0
/*    */     //   851: swap
/*    */     //   852: aastore
/*    */     //   853: invokevirtual sm : ([Lf/zh0;)V
/*    */     //   856: iconst_0
/*    */     //   857: putfield jl : I
/*    */     //   860: iconst_0
/*    */     //   861: iconst_1
/*    */     //   862: iconst_0
/*    */     //   863: invokestatic Zs0 : (Lf/j40;ZZZ)Ljava/lang/String;
/*    */     //   866: putfield z4 : Ljava/lang/Object;
/*    */     //   869: invokevirtual zn : ()V
/*    */     //   872: new f/dQ
/*    */     //   875: astore #19
/*    */     //   877: new java/lang/StringBuilder
/*    */     //   880: dup
/*    */     //   881: astore #20
/*    */     //   883: invokespecial <init> : ()V
/*    */     //   886: bipush #59
/*    */     //   888: aload #20
/*    */     //   890: ldc_w ' '
/*    */     //   893: invokestatic X9 : (ILjava/lang/StringBuilder;Ljava/lang/String;)Ljava/lang/StringBuilder;
/*    */     //   896: aload #13
/*    */     //   898: getfield Zs : Lf/Q90;
/*    */     //   901: getfield od : B
/*    */     //   904: invokevirtual append : (I)Ljava/lang/StringBuilder;
/*    */     //   907: ldc_w ' '
/*    */     //   910: invokevirtual append : (Ljava/lang/String;)Ljava/lang/StringBuilder;
/*    */     //   913: aload #13
/*    */     //   915: invokevirtual Hn : ()Ljava/lang/String;
/*    */     //   918: invokevirtual append : (Ljava/lang/String;)Ljava/lang/StringBuilder;
/*    */     //   921: ldc_w '\\n'
/*    */     //   924: invokevirtual append : (Ljava/lang/String;)Ljava/lang/StringBuilder;
/*    */     //   927: sipush #1842
/*    */     //   930: swap
/*    */     //   931: ldc_w ' '
/*    */     //   934: invokestatic X9 : (ILjava/lang/StringBuilder;Ljava/lang/String;)Ljava/lang/StringBuilder;
/*    */     //   937: astore #13
/*    */     //   939: getfield Zs : Lf/Q90;
/*    */     //   942: invokevirtual p10 : ()S
/*    */     //   945: ifle -> 961
/*    */     //   948: aload #15
/*    */     //   950: getfield Iu : I
/*    */     //   953: invokestatic OH0 : (I)Ljava/lang/String;
/*    */     //   956: astore #15
/*    */     //   958: goto -> 968
/*    */     //   961: bipush #61
/*    */     //   963: invokestatic OH0 : (I)Ljava/lang/String;
/*    */     //   966: astore #15
/*    */     //   968: aload #7
/*    */     //   970: aload #8
/*    */     //   972: aload #14
/*    */     //   974: dup
/*    */     //   975: aload #19
/*    */     //   977: dup
/*    */     //   978: aload #13
/*    */     //   980: aload #15
/*    */     //   982: invokevirtual append : (Ljava/lang/String;)Ljava/lang/StringBuilder;
/*    */     //   985: invokevirtual toString : ()Ljava/lang/String;
/*    */     //   988: astore #13
/*    */     //   990: invokespecial <init> : ()V
/*    */     //   993: aload #13
/*    */     //   995: invokevirtual E1 : (Ljava/lang/String;)V
/*    */     //   998: new f/cr0
/*    */     //   1001: dup
/*    */     //   1002: aload #14
/*    */     //   1004: invokespecial <init> : (Lf/Ip;)V
/*    */     //   1007: iconst_4
/*    */     //   1008: anewarray f/JG0
/*    */     //   1011: dup
/*    */     //   1012: dup
/*    */     //   1013: dup2
/*    */     //   1014: iconst_0
/*    */     //   1015: aload #17
/*    */     //   1017: aastore
/*    */     //   1018: iconst_1
/*    */     //   1019: aload #16
/*    */     //   1021: aastore
/*    */     //   1022: iconst_2
/*    */     //   1023: aload #18
/*    */     //   1025: aastore
/*    */     //   1026: iconst_3
/*    */     //   1027: aload #19
/*    */     //   1029: aastore
/*    */     //   1030: invokevirtual Mg : ([Lf/JG0;)Lf/U90;
/*    */     //   1033: bipush #60
/*    */     //   1035: invokevirtual Aq : (I)Lf/U90;
/*    */     //   1038: invokevirtual rK0 : (Lf/U90;)V
/*    */     //   1041: new f/g0
/*    */     //   1044: dup
/*    */     //   1045: aload #14
/*    */     //   1047: invokespecial <init> : (Lf/Ip;)V
/*    */     //   1050: iconst_4
/*    */     //   1051: anewarray f/JG0
/*    */     //   1054: dup
/*    */     //   1055: dup
/*    */     //   1056: dup2
/*    */     //   1057: iconst_0
/*    */     //   1058: aload #17
/*    */     //   1060: aastore
/*    */     //   1061: iconst_1
/*    */     //   1062: aload #16
/*    */     //   1064: aastore
/*    */     //   1065: iconst_2
/*    */     //   1066: aload #18
/*    */     //   1068: aastore
/*    */     //   1069: iconst_3
/*    */     //   1070: aload #19
/*    */     //   1072: aastore
/*    */     //   1073: invokevirtual Mg : ([Lf/JG0;)Lf/U90;
/*    */     //   1076: invokevirtual WN : (Lf/U90;)V
/*    */     //   1079: iconst_1
/*    */     //   1080: anewarray f/JG0
/*    */     //   1083: dup
/*    */     //   1084: iconst_0
/*    */     //   1085: aload #14
/*    */     //   1087: aastore
/*    */     //   1088: invokevirtual Mg : ([Lf/JG0;)Lf/U90;
/*    */     //   1091: pop
/*    */     //   1092: iconst_1
/*    */     //   1093: anewarray f/JG0
/*    */     //   1096: dup
/*    */     //   1097: iconst_0
/*    */     //   1098: aload #14
/*    */     //   1100: aastore
/*    */     //   1101: invokevirtual Mg : ([Lf/JG0;)Lf/U90;
/*    */     //   1104: pop
/*    */     //   1105: iinc #12, 1
/*    */     //   1108: goto -> 339
/*    */     //   1111: aload_1
/*    */     //   1112: getfield mR : [[Lf/Rd0;
/*    */     //   1115: iload #6
/*    */     //   1117: aaload
/*    */     //   1118: dup
/*    */     //   1119: astore #10
/*    */     //   1121: arraylength
/*    */     //   1122: istore #11
/*    */     //   1124: iconst_0
/*    */     //   1125: istore #12
/*    */     //   1127: iload #12
/*    */     //   1129: iload #11
/*    */     //   1131: if_icmpge -> 1468
/*    */     //   1134: aload #10
/*    */     //   1136: iload #12
/*    */     //   1138: aaload
/*    */     //   1139: dup
/*    */     //   1140: astore #13
/*    */     //   1142: ifnull -> 1462
/*    */     //   1145: aload #13
/*    */     //   1147: getfield JR : S
/*    */     //   1150: dup
/*    */     //   1151: istore #14
/*    */     //   1153: iconst_1
/*    */     //   1154: if_icmplt -> 1462
/*    */     //   1157: aload #13
/*    */     //   1159: getfield Lv : S
/*    */     //   1162: iconst_1
/*    */     //   1163: if_icmpge -> 1169
/*    */     //   1166: goto -> 1462
/*    */     //   1169: getstatic f/Of.eH : Lf/Of;
/*    */     //   1172: iload #14
/*    */     //   1174: invokevirtual On0 : (S)Lf/LPT3;
/*    */     //   1177: astore #9
/*    */     //   1179: iconst_0
/*    */     //   1180: istore #14
/*    */     //   1182: new f/Ip
/*    */     //   1185: dup
/*    */     //   1186: dup
/*    */     //   1187: astore #15
/*    */     //   1189: invokespecial <init> : ()V
/*    */     //   1192: ldc_w '/confirm-panel-dialog2'
/*    */     //   1195: invokevirtual Xu : (Ljava/lang/String;)V
/*    */     //   1198: invokestatic XU : ()Z
/*    */     //   1201: ifeq -> 1232
/*    */     //   1204: new f/vF0
/*    */     //   1207: dup
/*    */     //   1208: dup
/*    */     //   1209: astore #16
/*    */     //   1211: bipush #48
/*    */     //   1213: bipush #48
/*    */     //   1215: iconst_0
/*    */     //   1216: invokespecial <init> : (III)V
/*    */     //   1219: getfield TS : Lf/rH;
/*    */     //   1222: bipush #48
/*    */     //   1224: bipush #48
/*    */     //   1226: invokevirtual tL : (II)V
/*    */     //   1229: goto -> 1257
/*    */     //   1232: new f/vF0
/*    */     //   1235: dup
/*    */     //   1236: dup
/*    */     //   1237: astore #16
/*    */     //   1239: bipush #24
/*    */     //   1241: bipush #24
/*    */     //   1243: iconst_0
/*    */     //   1244: invokespecial <init> : (III)V
/*    */     //   1247: getfield TS : Lf/rH;
/*    */     //   1250: bipush #24
/*    */     //   1252: bipush #24
/*    */     //   1254: invokevirtual tL : (II)V
/*    */     //   1257: aload #7
/*    */     //   1259: aload #8
/*    */     //   1261: aload #15
/*    */     //   1263: dup
/*    */     //   1264: aload #16
/*    */     //   1266: dup
/*    */     //   1267: dup
/*    */     //   1268: aload #9
/*    */     //   1270: aload #16
/*    */     //   1272: getfield TS : Lf/rH;
/*    */     //   1275: iconst_1
/*    */     //   1276: anewarray f/U70
/*    */     //   1279: dup
/*    */     //   1280: getstatic f/wm0.y0 : Lf/wm0;
/*    */     //   1283: aload #9
/*    */     //   1285: iconst_0
/*    */     //   1286: invokevirtual HR : (Lf/LPT3;Z)Lf/U70;
/*    */     //   1289: iconst_0
/*    */     //   1290: swap
/*    */     //   1291: aastore
/*    */     //   1292: invokevirtual qt : ([Lf/U70;)Lf/JG0;
/*    */     //   1295: pop
/*    */     //   1296: invokestatic kh0 : (Lf/LPT3;)Ljava/lang/String;
/*    */     //   1299: putfield z4 : Ljava/lang/Object;
/*    */     //   1302: invokevirtual zn : ()V
/*    */     //   1305: iconst_0
/*    */     //   1306: putfield jl : I
/*    */     //   1309: new f/dQ
/*    */     //   1312: dup
/*    */     //   1313: dup
/*    */     //   1314: astore #17
/*    */     //   1316: new java/lang/StringBuilder
/*    */     //   1319: dup
/*    */     //   1320: aload #13
/*    */     //   1322: swap
/*    */     //   1323: invokespecial <init> : ()V
/*    */     //   1326: getfield Lv : S
/*    */     //   1329: invokevirtual append : (I)Ljava/lang/StringBuilder;
/*    */     //   1332: ldc_w 'x '
/*    */     //   1335: invokevirtual append : (Ljava/lang/String;)Ljava/lang/StringBuilder;
/*    */     //   1338: aload #9
/*    */     //   1340: getfield Iu : I
/*    */     //   1343: invokestatic OH0 : (I)Ljava/lang/String;
/*    */     //   1346: invokevirtual append : (Ljava/lang/String;)Ljava/lang/StringBuilder;
/*    */     //   1349: invokevirtual toString : ()Ljava/lang/String;
/*    */     //   1352: astore #9
/*    */     //   1354: invokespecial <init> : ()V
/*    */     //   1357: aload #9
/*    */     //   1359: invokevirtual E1 : (Ljava/lang/String;)V
/*    */     //   1362: new f/cr0
/*    */     //   1365: dup
/*    */     //   1366: aload #15
/*    */     //   1368: invokespecial <init> : (Lf/Ip;)V
/*    */     //   1371: iconst_1
/*    */     //   1372: anewarray f/JG0
/*    */     //   1375: dup
/*    */     //   1376: iconst_0
/*    */     //   1377: aload #16
/*    */     //   1379: aastore
/*    */     //   1380: invokevirtual Mg : ([Lf/JG0;)Lf/U90;
/*    */     //   1383: iconst_1
/*    */     //   1384: anewarray f/JG0
/*    */     //   1387: dup
/*    */     //   1388: iconst_0
/*    */     //   1389: aload #17
/*    */     //   1391: aastore
/*    */     //   1392: invokevirtual Mg : ([Lf/JG0;)Lf/U90;
/*    */     //   1395: bipush #60
/*    */     //   1397: invokevirtual Aq : (I)Lf/U90;
/*    */     //   1400: invokevirtual rK0 : (Lf/U90;)V
/*    */     //   1403: new f/g0
/*    */     //   1406: dup
/*    */     //   1407: aload #15
/*    */     //   1409: invokespecial <init> : (Lf/Ip;)V
/*    */     //   1412: iconst_2
/*    */     //   1413: anewarray f/JG0
/*    */     //   1416: dup
/*    */     //   1417: dup
/*    */     //   1418: iconst_0
/*    */     //   1419: aload #16
/*    */     //   1421: aastore
/*    */     //   1422: iconst_1
/*    */     //   1423: aload #17
/*    */     //   1425: aastore
/*    */     //   1426: invokevirtual Mg : ([Lf/JG0;)Lf/U90;
/*    */     //   1429: invokevirtual WN : (Lf/U90;)V
/*    */     //   1432: iconst_1
/*    */     //   1433: anewarray f/JG0
/*    */     //   1436: dup
/*    */     //   1437: iconst_0
/*    */     //   1438: aload #15
/*    */     //   1440: aastore
/*    */     //   1441: invokevirtual Mg : ([Lf/JG0;)Lf/U90;
/*    */     //   1444: pop
/*    */     //   1445: iconst_1
/*    */     //   1446: anewarray f/JG0
/*    */     //   1449: dup
/*    */     //   1450: iconst_0
/*    */     //   1451: aload #15
/*    */     //   1453: aastore
/*    */     //   1454: invokevirtual Mg : ([Lf/JG0;)Lf/U90;
/*    */     //   1457: pop
/*    */     //   1458: iload #14
/*    */     //   1460: istore #9
/*    */     //   1462: iinc #12, 1
/*    */     //   1465: goto -> 1127
/*    */     //   1468: iload #9
/*    */     //   1470: ifeq -> 1531
/*    */     //   1473: aload #7
/*    */     //   1475: aload #8
/*    */     //   1477: new f/Ip
/*    */     //   1480: dup
/*    */     //   1481: dup
/*    */     //   1482: astore #9
/*    */     //   1484: invokespecial <init> : ()V
/*    */     //   1487: new f/cr0
/*    */     //   1490: dup
/*    */     //   1491: aload #9
/*    */     //   1493: invokespecial <init> : (Lf/Ip;)V
/*    */     //   1496: sipush #210
/*    */     //   1499: invokevirtual Aq : (I)Lf/U90;
/*    */     //   1502: invokevirtual rK0 : (Lf/U90;)V
/*    */     //   1505: iconst_1
/*    */     //   1506: anewarray f/JG0
/*    */     //   1509: dup
/*    */     //   1510: iconst_0
/*    */     //   1511: aload #9
/*    */     //   1513: aastore
/*    */     //   1514: invokevirtual Mg : ([Lf/JG0;)Lf/U90;
/*    */     //   1517: pop
/*    */     //   1518: iconst_1
/*    */     //   1519: anewarray f/JG0
/*    */     //   1522: dup
/*    */     //   1523: iconst_0
/*    */     //   1524: aload #9
/*    */     //   1526: aastore
/*    */     //   1527: invokevirtual Mg : ([Lf/JG0;)Lf/U90;
/*    */     //   1530: pop
/*    */     //   1531: aload_2
/*    */     //   1532: iload #6
/*    */     //   1534: aload_2
/*    */     //   1535: iload #6
/*    */     //   1537: aaload
/*    */     //   1538: aload #7
/*    */     //   1540: invokevirtual rK0 : (Lf/U90;)V
/*    */     //   1543: aaload
/*    */     //   1544: aload #8
/*    */     //   1546: invokevirtual WN : (Lf/U90;)V
/*    */     //   1549: iinc #6, 1
/*    */     //   1552: goto -> 76
/*    */     //   1555: new f/Ip
/*    */     //   1558: dup
/*    */     //   1559: dup
/*    */     //   1560: astore #4
/*    */     //   1562: invokespecial <init> : ()V
/*    */     //   1565: ldc_w 'trade-confirm-widget'
/*    */     //   1568: invokevirtual Xu : (Ljava/lang/String;)V
/*    */     //   1571: new f/g0
/*    */     //   1574: dup
/*    */     //   1575: astore #5
/*    */     //   1577: aload #4
/*    */     //   1579: invokespecial <init> : (Lf/Ip;)V
/*    */     //   1582: new f/cr0
/*    */     //   1585: dup
/*    */     //   1586: astore #6
/*    */     //   1588: aload #4
/*    */     //   1590: invokespecial <init> : (Lf/Ip;)V
/*    */     //   1593: new f/rS
/*    */     //   1596: dup
/*    */     //   1597: astore #7
/*    */     //   1599: aload #4
/*    */     //   1601: aload #6
/*    */     //   1603: aload #4
/*    */     //   1605: aload #5
/*    */     //   1607: aload #6
/*    */     //   1609: aload #7
/*    */     //   1611: aload #5
/*    */     //   1613: aload #7
/*    */     //   1615: dup
/*    */     //   1616: aconst_null
/*    */     //   1617: invokespecial <init> : (Lf/JG0;)V
/*    */     //   1620: invokevirtual Ya : (Lf/JG0;)Lf/U90;
/*    */     //   1623: pop
/*    */     //   1624: invokevirtual Ya : (Lf/JG0;)Lf/U90;
/*    */     //   1627: pop
/*    */     //   1628: invokevirtual rK0 : (Lf/U90;)V
/*    */     //   1631: invokevirtual WN : (Lf/U90;)V
/*    */     //   1634: new f/Ip
/*    */     //   1637: dup
/*    */     //   1638: dup2
/*    */     //   1639: dup2
/*    */     //   1640: astore #5
/*    */     //   1642: invokespecial <init> : ()V
/*    */     //   1645: ldc_w '/confirm-panel-dialog'
/*    */     //   1648: invokevirtual Xu : (Ljava/lang/String;)V
/*    */     //   1651: new f/g0
/*    */     //   1654: dup
/*    */     //   1655: aload_3
/*    */     //   1656: swap
/*    */     //   1657: aload #5
/*    */     //   1659: invokespecial <init> : (Lf/Ip;)V
/*    */     //   1662: invokevirtual Ya : (Lf/JG0;)Lf/U90;
/*    */     //   1665: iconst_1
/*    */     //   1666: anewarray f/U90
/*    */     //   1669: dup
/*    */     //   1670: new f/g0
/*    */     //   1673: dup
/*    */     //   1674: aload #5
/*    */     //   1676: invokespecial <init> : (Lf/Ip;)V
/*    */     //   1679: iconst_1
/*    */     //   1680: anewarray f/U90
/*    */     //   1683: dup
/*    */     //   1684: new f/cr0
/*    */     //   1687: dup
/*    */     //   1688: aload #5
/*    */     //   1690: invokespecial <init> : (Lf/Ip;)V
/*    */     //   1693: bipush #20
/*    */     //   1695: invokevirtual Aq : (I)Lf/U90;
/*    */     //   1698: iconst_1
/*    */     //   1699: anewarray f/JG0
/*    */     //   1702: dup
/*    */     //   1703: aload_2
/*    */     //   1704: aload_1
/*    */     //   1705: getfield QO : B
/*    */     //   1708: aaload
/*    */     //   1709: iconst_0
/*    */     //   1710: swap
/*    */     //   1711: aastore
/*    */     //   1712: invokevirtual Mg : ([Lf/JG0;)Lf/U90;
/*    */     //   1715: iconst_1
/*    */     //   1716: anewarray f/JG0
/*    */     //   1719: dup
/*    */     //   1720: aload_2
/*    */     //   1721: aload_1
/*    */     //   1722: invokevirtual Dz : ()B
/*    */     //   1725: aaload
/*    */     //   1726: iconst_0
/*    */     //   1727: swap
/*    */     //   1728: aastore
/*    */     //   1729: invokevirtual Mg : ([Lf/JG0;)Lf/U90;
/*    */     //   1732: iconst_0
/*    */     //   1733: swap
/*    */     //   1734: aastore
/*    */     //   1735: invokevirtual cOM8 : ([Lf/U90;)Lf/U90;
/*    */     //   1738: iconst_0
/*    */     //   1739: swap
/*    */     //   1740: aastore
/*    */     //   1741: invokevirtual cOM8 : ([Lf/U90;)Lf/U90;
/*    */     //   1744: invokevirtual rK0 : (Lf/U90;)V
/*    */     //   1747: new f/cr0
/*    */     //   1750: dup
/*    */     //   1751: aload_3
/*    */     //   1752: swap
/*    */     //   1753: aload #5
/*    */     //   1755: invokespecial <init> : (Lf/Ip;)V
/*    */     //   1758: invokevirtual Ya : (Lf/JG0;)Lf/U90;
/*    */     //   1761: iconst_1
/*    */     //   1762: anewarray f/U90
/*    */     //   1765: dup
/*    */     //   1766: new f/g0
/*    */     //   1769: dup
/*    */     //   1770: aload #5
/*    */     //   1772: invokespecial <init> : (Lf/Ip;)V
/*    */     //   1775: iconst_2
/*    */     //   1776: anewarray f/U90
/*    */     //   1779: dup
/*    */     //   1780: dup
/*    */     //   1781: new f/cr0
/*    */     //   1784: dup
/*    */     //   1785: aload #5
/*    */     //   1787: invokespecial <init> : (Lf/Ip;)V
/*    */     //   1790: iconst_1
/*    */     //   1791: anewarray f/JG0
/*    */     //   1794: dup
/*    */     //   1795: aload_2
/*    */     //   1796: aload_1
/*    */     //   1797: getfield QO : B
/*    */     //   1800: aaload
/*    */     //   1801: iconst_0
/*    */     //   1802: swap
/*    */     //   1803: aastore
/*    */     //   1804: invokevirtual Mg : ([Lf/JG0;)Lf/U90;
/*    */     //   1807: iconst_0
/*    */     //   1808: swap
/*    */     //   1809: aastore
/*    */     //   1810: new f/cr0
/*    */     //   1813: dup
/*    */     //   1814: aload #5
/*    */     //   1816: invokespecial <init> : (Lf/Ip;)V
/*    */     //   1819: iconst_1
/*    */     //   1820: anewarray f/JG0
/*    */     //   1823: dup
/*    */     //   1824: aload_2
/*    */     //   1825: aload_1
/*    */     //   1826: invokevirtual Dz : ()B
/*    */     //   1829: aaload
/*    */     //   1830: iconst_0
/*    */     //   1831: swap
/*    */     //   1832: aastore
/*    */     //   1833: invokevirtual Mg : ([Lf/JG0;)Lf/U90;
/*    */     //   1836: iconst_1
/*    */     //   1837: swap
/*    */     //   1838: aastore
/*    */     //   1839: invokevirtual cOM8 : ([Lf/U90;)Lf/U90;
/*    */     //   1842: iconst_0
/*    */     //   1843: swap
/*    */     //   1844: aastore
/*    */     //   1845: invokevirtual cOM8 : ([Lf/U90;)Lf/U90;
/*    */     //   1848: invokevirtual WN : (Lf/U90;)V
/*    */     //   1851: invokevirtual Gz0 : (Lf/JG0;)V
/*    */     //   1854: new f/h70
/*    */     //   1857: dup
/*    */     //   1858: dup
/*    */     //   1859: astore_2
/*    */     //   1860: aload #7
/*    */     //   1862: aload_2
/*    */     //   1863: aload #4
/*    */     //   1865: new f/fS
/*    */     //   1868: dup
/*    */     //   1869: astore_3
/*    */     //   1870: aload_0
/*    */     //   1871: aload_1
/*    */     //   1872: invokespecial <init> : (Lf/Zr;Lf/P4;)V
/*    */     //   1875: aload_3
/*    */     //   1876: invokespecial <init> : (Lf/JG0;Ljava/lang/Runnable;)V
/*    */     //   1879: sipush #400
/*    */     //   1882: sipush #250
/*    */     //   1885: invokevirtual yN : (II)V
/*    */     //   1888: sipush #400
/*    */     //   1891: sipush #250
/*    */     //   1894: invokevirtual yN : (II)V
/*    */     //   1897: ldc_w 'trade-confirm-widget'
/*    */     //   1900: invokevirtual Xu : (Ljava/lang/String;)V
/*    */     //   1903: getstatic f/js.vu0 : Lf/js;
/*    */     //   1906: aload_2
/*    */     //   1907: invokevirtual uh : (Lf/h70;)V
/*    */     //   1910: new java/lang/StringBuilder
/*    */     //   1913: dup
/*    */     //   1914: astore_3
/*    */     //   1915: aload_0
/*    */     //   1916: aload_3
/*    */     //   1917: invokespecial <init> : ()V
/*    */     //   1920: getfield ed0 : Ljava/util/HashMap;
/*    */     //   1923: invokevirtual entrySet : ()Ljava/util/Set;
/*    */     //   1926: invokeinterface stream : ()Ljava/util/stream/Stream;
/*    */     //   1931: aload_1
/*    */     //   1932: aload_3
/*    */     //   1933: <illegal opcode> accept : (Lf/P4;Ljava/lang/StringBuilder;)Ljava/util/function/Consumer;
/*    */     //   1938: invokeinterface forEach : (Ljava/util/function/Consumer;)V
/*    */     //   1943: invokevirtual toString : ()Ljava/lang/String;
/*    */     //   1946: invokevirtual isEmpty : ()Z
/*    */     //   1949: ifne -> 2007
/*    */     //   1952: getstatic f/js.vu0 : Lf/js;
/*    */     //   1955: new f/h70
/*    */     //   1958: dup
/*    */     //   1959: aload_0
/*    */     //   1960: aload_2
/*    */     //   1961: aload_3
/*    */     //   1962: invokevirtual toString : ()Ljava/lang/String;
/*    */     //   1965: invokevirtual trim : ()Ljava/lang/String;
/*    */     //   1968: astore_0
/*    */     //   1969: bipush #52
/*    */     //   1971: invokestatic OH0 : (I)Ljava/lang/String;
/*    */     //   1974: astore_1
/*    */     //   1975: bipush #53
/*    */     //   1977: invokestatic OH0 : (I)Ljava/lang/String;
/*    */     //   1980: astore_2
/*    */     //   1981: <illegal opcode> run : (Lf/h70;)Ljava/lang/Runnable;
/*    */     //   1986: astore_3
/*    */     //   1987: getfield bz : Lf/Un;
/*    */     //   1990: astore #4
/*    */     //   1992: aload_0
/*    */     //   1993: aload_1
/*    */     //   1994: aload_2
/*    */     //   1995: aload_3
/*    */     //   1996: aload #4
/*    */     //   1998: invokespecial <init> : (Ljava/lang/String;Ljava/lang/String;Ljava/lang/String;Ljava/lang/Runnable;Lf/JG0;)V
/*    */     //   2001: invokevirtual uh : (Lf/h70;)V
/*    */     //   2004: goto -> 2014
/*    */     //   2007: getstatic f/js.vu0 : Lf/js;
/*    */     //   2010: aload_2
/*    */     //   2011: invokevirtual uh : (Lf/h70;)V
/*    */     //   2014: return
/*    */     // Line number table:
/*    */     //   Java source line number -> byte code offset
/*    */     //   #1	-> 19
/*    */     //   #2	-> 27
/*    */     //   #3	-> 42
/*    */     //   #4	-> 50
/*    */     //   #5	-> 65
/*    */     //   #6	-> 89
/*    */     //   #7	-> 114
/*    */     //   #8	-> 119
/*    */     //   #9	-> 121
/*    */     //   #10	-> 126
/*    */     //   #11	-> 140
/*    */     //   #12	-> 192
/*    */     //   #13	-> 198
/*    */     //   #14	-> 202
/*    */     //   #15	-> 209
/*    */     //   #16	-> 220
/*    */     //   #17	-> 228
/*    */     //   #18	-> 234
/*    */     //   #19	-> 245
/*    */     //   #20	-> 268
/*    */     //   #21	-> 278
/*    */     //   #22	-> 321
/*    */     //   #23	-> 327
/*    */     //   #24	-> 376
/*    */     //   #25	-> 381
/*    */     //   #26	-> 384
/*    */     //   #27	-> 401
/*    */     //   #28	-> 404
/*    */     //   #29	-> 413
/*    */     //   #30	-> 416
/*    */     //   #31	-> 434
/*    */     //   #32	-> 437
/*    */     //   #33	-> 444
/*    */     //   #34	-> 447
/*    */     //   #35	-> 453
/*    */     //   #36	-> 472
/*    */     //   #37	-> 475
/*    */     //   #38	-> 482
/*    */     //   #39	-> 487
/*    */     //   #40	-> 490
/*    */     //   #41	-> 498
/*    */     //   #42	-> 502
/*    */     //   #43	-> 511
/*    */     //   #44	-> 514
/*    */     //   #45	-> 537
/*    */     //   #46	-> 544
/*    */     //   #47	-> 547
/*    */     //   #48	-> 552
/*    */     //   #49	-> 566
/*    */     //   #50	-> 573
/*    */     //   #51	-> 576
/*    */     //   #52	-> 581
/*    */     //   #53	-> 592
/*    */     //   #54	-> 598
/*    */     //   #55	-> 604
/*    */     //   #56	-> 607
/*    */     //   #57	-> 610
/*    */     //   #58	-> 616
/*    */     //   #59	-> 620
/*    */     //   #60	-> 627
/*    */     //   #61	-> 632
/*    */     //   #62	-> 647
/*    */     //   #63	-> 654
/*    */     //   #64	-> 657
/*    */     //   #65	-> 660
/*    */     //   #66	-> 668
/*    */     //   #67	-> 673
/*    */     //   #68	-> 681
/*    */     //   #69	-> 687
/*    */     //   #70	-> 698
/*    */     //   #71	-> 703
/*    */     //   #72	-> 718
/*    */     //   #73	-> 725
/*    */     //   #74	-> 728
/*    */     //   #75	-> 731
/*    */     //   #76	-> 739
/*    */     //   #77	-> 744
/*    */     //   #78	-> 752
/*    */     //   #79	-> 758
/*    */     //   #80	-> 769
/*    */     //   #81	-> 774
/*    */     //   #82	-> 786
/*    */     //   #83	-> 792
/*    */     //   #84	-> 806
/*    */     //   #85	-> 810
/*    */     //   #86	-> 814
/*    */     //   #87	-> 820
/*    */     //   #88	-> 823
/*    */     //   #89	-> 837
/*    */     //   #90	-> 845
/*    */     //   #91	-> 857
/*    */     //   #92	-> 863
/*    */     //   #93	-> 866
/*    */     //   #94	-> 872
/*    */     //   #95	-> 890
/*    */     //   #96	-> 898
/*    */     //   #97	-> 901
/*    */     //   #98	-> 904
/*    */     //   #99	-> 931
/*    */     //   #100	-> 939
/*    */     //   #101	-> 942
/*    */     //   #102	-> 950
/*    */     //   #103	-> 963
/*    */     //   #104	-> 990
/*    */     //   #105	-> 998
/*    */     //   #106	-> 1008
/*    */     //   #107	-> 1041
/*    */     //   #108	-> 1051
/*    */     //   #109	-> 1112
/*    */     //   #110	-> 1121
/*    */     //   #111	-> 1147
/*    */     //   #112	-> 1159
/*    */     //   #113	-> 1169
/*    */     //   #114	-> 1174
/*    */     //   #115	-> 1216
/*    */     //   #116	-> 1219
/*    */     //   #117	-> 1226
/*    */     //   #118	-> 1244
/*    */     //   #119	-> 1247
/*    */     //   #120	-> 1254
/*    */     //   #121	-> 1272
/*    */     //   #122	-> 1276
/*    */     //   #123	-> 1280
/*    */     //   #124	-> 1286
/*    */     //   #125	-> 1291
/*    */     //   #126	-> 1299
/*    */     //   #127	-> 1306
/*    */     //   #128	-> 1309
/*    */     //   #129	-> 1326
/*    */     //   #130	-> 1329
/*    */     //   #131	-> 1340
/*    */     //   #132	-> 1346
/*    */     //   #133	-> 1354
/*    */     //   #134	-> 1362
/*    */     //   #135	-> 1372
/*    */     //   #136	-> 1403
/*    */     //   #137	-> 1413
/*    */     //   #138	-> 1487
/*    */     //   #139	-> 1499
/*    */     //   #140	-> 1571
/*    */     //   #141	-> 1582
/*    */     //   #142	-> 1593
/*    */     //   #143	-> 1617
/*    */     //   #144	-> 1620
/*    */     //   #145	-> 1651
/*    */     //   #146	-> 1662
/*    */     //   #147	-> 1670
/*    */     //   #148	-> 1680
/*    */     //   #149	-> 1684
/*    */     //   #150	-> 1695
/*    */     //   #151	-> 1705
/*    */     //   #152	-> 1708
/*    */     //   #153	-> 1747
/*    */     //   #154	-> 1758
/*    */     //   #155	-> 1766
/*    */     //   #156	-> 1776
/*    */     //   #157	-> 1781
/*    */     //   #158	-> 1791
/*    */     //   #159	-> 1797
/*    */     //   #160	-> 1800
/*    */     //   #161	-> 1810
/*    */     //   #162	-> 1820
/*    */     //   #163	-> 1876
/*    */     //   #164	-> 1885
/*    */     //   #165	-> 1903
/*    */     //   #166	-> 1907
/*    */     //   #167	-> 1952
/*    */     //   #168	-> 1955
/*    */     //   #169	-> 2007
/*    */     //   #170	-> 2011 } public static void lE(h70 paramh70) { js.vu0.uh(paramh70); }
/*    */   public static void Em0(P4 paramP4, StringBuilder paramStringBuilder, Map.Entry paramEntry) { j40 j40 = (j40)paramEntry.getKey(); mA mA = (mA)paramEntry.getValue(); if (paramP4.ec0().de0(j40.Jg) != null) { arrayOfString[0] = mA.toString(); arrayOfString[1] = j40.Hn(); byte b = 2; String[] arrayOfString; (arrayOfString = new String[3])[b] = paramP4.kr; paramStringBuilder.append(Ml0.sB(1975, new String[3])).append("\n"); }  }
/*  9 */   public final void P9() { byte b1 = this.Ft.Dz(); this.e70.E1(B40.df("$").append(NumberFormat.getInstance().format(this.Ft.bG0[b1])).toString()); b1 = this.Ft.QO; this.Ak0.Hr0(this.Ft.bG0[b1]); short s;
/* 10 */     for (um0 um0 = um0.Kt0; s < 2; ) { for (short s1 = 0; s1 < 6; ) { byte b2; if (s == 0)
/*    */         
/* 12 */         { b2 = this.Ft.QO; }
/* 13 */         else { b2 = this.Ft.Dz(); }
/*    */         
/*    */         j40 j40;
/* 16 */         if ((j40 = this.Ft.Tq0[b2].ky(s1)) != null)
/*    */         
/* 18 */         { Qv0 qv0 = this.wC0[s][s1];
/*    */ 
/*    */           
/* 21 */           qv0 = this.wC0[s][s1]; String str; if (j40.Zs.tm0() ? (str = "partyslot-shiny").equals(qv0.cl) : (str = "partyslot")
/*    */             
/* 23 */             .equals(qv0.cl)) { qv0.Xu(str); qv0.cZ(); }
/*    */ 
/*    */           
/* 26 */           short s2 = j40.Zs.Vf0(); byte b3 = j40.s5();
/*    */           
/* 28 */           this.wC0[s][s1].Ax(um0.lb(s2, j40.Zs.da(), b3)[0]); this.wC0[s][s1].zf(j40); (this.wC0[s][s1])
/*    */             
/* 30 */             .z4 = rG0.Zs0(j40, false, true, false);
/* 31 */           this.wC0[s][s1].zn();
/* 32 */           (this.wC0[s][s1])
/* 33 */             .jl = 100; } else { this
/* 34 */             .wC0[s][s1].Ax(null); this.wC0[s][s1].zf(null); (this.wC0[s][s1])
/* 35 */             .z4 = null;
/* 36 */           this.wC0[s][s1].zn();
/* 37 */           Qv0 qv0 = this.wC0[s][s1];
/*    */           String str;
/* 39 */           if (!(str = "partyslot").equals(qv0.cl)) { qv0.Xu(str); qv0.cZ(); }  }  s1 = (short)(s1 + 1); }  s++; }  byte b; for (b = 0; b < 2; ) { for (s = 0; s < 6; )
/* 40 */       { boolean bool; xK[][] arrayOfXK = this.lpT8; if (b == this.Ft
/* 41 */           .QO) { bool = false; } else { bool = true; }
/* 42 */          xK xK1 = arrayOfXK[bool][s]; if (km.XU()) { xK1.E20(); xK1
/* 43 */             .gc = 0; xK1.x80 = 13; }
/*    */         
/*    */         Rd0 rd0;
/* 46 */         if ((rd0 = this.Ft.mR[b][s]) == null) { xK1
/* 47 */             .LPt2((byte)0, (short)0, (short)0); }
/* 48 */         else { short s1 = rd0.JR;
/* 49 */           short s2 = rd0.Lv;
/*    */           
/* 51 */           xK1.LPt2(rd0.bq, s1, s2); }  s = (short)(s + 1); }  b++; }
/* 52 */      b = this.Ft.QO;
/* 53 */     if (this.Ft.g00[b])
/* 54 */     { this
/* 55 */         .yx.s6(Ml0.OH0(1955)); this.G9.sk0(false); }  b = this.Ft.Dz(); if (this.Ft
/* 56 */       .g00[b])
/* 57 */       this
/* 58 */         .zo.s6(Ml0.OH0(1955)); 
/* 59 */     b = this.Ft.QO;
/* 60 */     if (this.Ft.op[b])
/* 61 */       this
/* 62 */         .bz.s6(Ml0.OH0(1956));  b = this.Ft.Dz(); if (this.Ft
/* 63 */       .op[b])
/* 64 */       this
/* 65 */         .Bg.s6(Ml0.OH0(1956));  boolean[] arrayOfBoolean;
/* 66 */     if ((arrayOfBoolean = this.Ft.g00)[0] && 
/* 67 */       arrayOfBoolean[1]) { this
/* 68 */         .bz.wI0(true); this.Bg.wI0(true); }
/*    */      }
/*    */ 
/*    */   
/*    */   public final void EX(nY paramnY) {}
/*    */   
/*    */   public final void d40() {
/*    */     if (km.Nr()) {
/*    */       super.d40();
/*    */       int i = this.Kd;
/*    */       this.pG0.ME(qF() + i - 35, this.er0 + 45);
/*    */     } else {
/*    */       QI();
/*    */       super.d40();
/*    */       this.pG0.mM();
/*    */       this.pG0.js0(et.kL0);
/*    */     } 
/*    */   }
/*    */   
/*    */   public final void V90(throws paramthrows) {
/*    */     if (LPT5())
/*    */       P9(); 
/*    */     super.V90(paramthrows);
/*    */   }
/*    */   
/*    */   public final boolean LPT5() {
/*    */     // Byte code:
/*    */     //   0: aload_0
/*    */     //   1: getfield Ft : Lf/P4;
/*    */     //   4: astore_0
/*    */     //   5: iconst_0
/*    */     //   6: istore_1
/*    */     //   7: iload_1
/*    */     //   8: aload_0
/*    */     //   9: getfield Tq0 : [Lf/public;
/*    */     //   12: dup
/*    */     //   13: astore_2
/*    */     //   14: arraylength
/*    */     //   15: if_icmpge -> 55
/*    */     //   18: aload_2
/*    */     //   19: iload_1
/*    */     //   20: aaload
/*    */     //   21: dup
/*    */     //   22: astore_2
/*    */     //   23: getfield ID0 : Z
/*    */     //   26: ifeq -> 39
/*    */     //   29: aload_2
/*    */     //   30: iconst_0
/*    */     //   31: putfield ID0 : Z
/*    */     //   34: iconst_1
/*    */     //   35: istore_2
/*    */     //   36: goto -> 41
/*    */     //   39: iconst_0
/*    */     //   40: istore_2
/*    */     //   41: iload_2
/*    */     //   42: ifeq -> 49
/*    */     //   45: iconst_1
/*    */     //   46: goto -> 72
/*    */     //   49: iinc #1, 1
/*    */     //   52: goto -> 7
/*    */     //   55: aload_0
/*    */     //   56: getfield U2 : Z
/*    */     //   59: ifeq -> 71
/*    */     //   62: aload_0
/*    */     //   63: iconst_0
/*    */     //   64: putfield U2 : Z
/*    */     //   67: iconst_1
/*    */     //   68: goto -> 72
/*    */     //   71: iconst_0
/*    */     //   72: ireturn
/*    */     // Line number table:
/*    */     //   Java source line number -> byte code offset
/*    */     //   #1	-> 9
/*    */     //   #2	-> 14
/*    */     //   #3	-> 23
/*    */     //   #4	-> 31
/*    */     //   #5	-> 56
/*    */   } }


/* Location:              /Users/vnnsnnt/Documents/Codespace/JavaWorkspace/RedTrainer/src/main/java/org/trainer/client/PokeMMO.jar!/f/Zr.class
 * Java compiler version: 8 (52.0)
 * JD-Core Version:       1.1.3
 */