/*  1 */
package f;

public final class Zt extends Ip {
    private void Ak(String paramString, byte paramByte) {
        F40 f40 = F40.ef0;
        String[] arrayOfString1;
        (arrayOfString1 = new String[2])[
                /*  2 */         0] = this.nl0.pl.m();
        (new String[2])[1] = paramString;
        /*    */
        /*  4 */
        this.kf0.Kq(Ml0.tG((byte) 2, f40, 157, 40, arrayOfString1));
        short s = 157;
        byte b = 41;
        arrayOfString2[
                /*    */
                /*  6 */         0] = this.nl0.pl.m();
        /*    */
        String[] arrayOfString2;
        /*  8 */
        (arrayOfString2 = new String[2])[1] = Ml0.OH0(this.nl0.fV + 110000);
        /*    */
        /*    */
        /* 11 */
        this.kf0.Kq(Ml0.tG((byte) 2, f40, s, b, arrayOfString2));
        R8 r8 = km.u4;
        /*    */
        /* 13 */
        int i = this.nl0.pl.Jg;
        /* 14 */
        s = this.nl0.fV;
        /* 15 */
        this.e20
/* 16 */.W3(new XO(paramByte, i, s));
        kf kf1;
        /* 17 */
        (kf1 = this.kf0).getClass();
        /* 18 */
        if (km.Nr()) {
            Zt zt;
            if ((zt = this.VF0) != null) {
                jf0(zt);
                this.VF0 = null;
            }
        } else if (this.IL != null) {
            this.VF0 = null;
            rc();
        }
        /*    */
    }

    /*    */
    /*    */
    /*    */   public final kf kf0;
    /*    */   public final f4 nl0;
    /*    */   public p30 vK0;
    /*    */   public mc[] HX;
    /*    */   public int b9;

    /*    */
    /*    */
    public Zt(kf paramkf, f4 paramf4) {
        /*    */
        dQ dQ;
        /*    */
        WD wD;
        /*    */
        this.b9 = 0;
        /*    */
        this.kf0 = paramkf;
        /*    */
        this.nl0 = paramf4;
        /*    */
        paramkf.cr("");
        /*    */
        Xu("battle-panel-dark");
        /*    */
        this(Ml0.Qf0(F40.ef0, 157, 39));
        /*    */
        this.HX = new mc[5];
        /*    */
        byte b;
        /*    */
        mc[] arrayOfMc2;
        /*    */
        for (b = 0; b < (arrayOfMc2 = this.HX).length; b = (byte) (b + 1)) {
            /*    */
            mc mc1;
            /*    */
            this("", "");
            /*    */
            arrayOfMc2[b] = mc1;
            /*    */
            this.HX[b].Xu("battle-move-button-left");
            /*    */
            this.HX[b].C70(et.COM2);
            /*    */
            this.HX[b].tW(new sv(this, b));
            /*    */
        }
        /*    */
        for (b = 0; b < (arrayOfMc2 = this.HX).length; b++) {
            /*    */
            short s;
            /*    */
            if (b == 4) {
                /*    */
                s = paramf4.PL();
                /*    */
            } else {
                /*    */
                s = paramf4.Fm().eC().Fp0(b);
                /*    */
            }
            /*    */
            if (s == 0) {
                /*    */
                this.HX[b].s6("-");
                /*    */
                this.HX[b].Ep0("");
                /*    */
                this.HX[b].sk0(false);
                /*    */
                this.HX[b].CW().H();
                /*    */
                this.HX[b].Gq0(null);
                /*    */
                this.HX[b].eQ();
                /*    */
            } else {
                /*    */
                this.HX[b].sk0(true);
                /*    */
                this.HX[b].Gq0(w50.Ii0(wD, paramf4.Fm()));
                /*    */
                this.HX[b].Ep0(rG0.oV(wD));
                /*    */
                Ht0 ht0 = (wD = yk0.cw().mP(s)).Fn(paramf4.Fm().eC());
                /*    */
                this.HX[b].CW().Pn(new pe0[]{ interface.ZZ().xk0(ht0.oI()) });
                /*    */
                this.HX[b].CW().zT(153, 10);
                /*    */
                if (km.XU()) {
                    /*    */
                    this.HX[b].CW().zT(100, 15);
                    /*    */
                    this.HX[b].CW().Ii0(2.0F);
                    /*    */
                }
                /*    */
                this.HX[b].s6(wD.cW());
                /*    */
                this.HX[b].eQ();
                /*    */
            }
            /*    */
        }
        /*    */
        wD[4].sk0(false);
        /*    */
        (this.vK0 = new p30(Ml0.OH0(53), 96, 30)).Xu("battle-button-return");
        /*    */
        this.vK0.tW(new FC0(this));
        /*    */
        if (km.XU())
            /*    */ this.vK0.Xg0(116, 116);
        /*    */
        arrayOfJG02[0] = this.HX[0];
        /*    */
        arrayOfJG02[1] = this.HX[1];
        /*    */
        arrayOfJG02[2] = dQ;
        /*    */
        JG0[] arrayOfJG02;
        /*    */
        (arrayOfJG02 = new JG0[4])[3] = this.vK0;
        /*    */
        (new U90[2])[0] = mE0().Mg(new JG0[4]);
        /*    */
        arrayOfJG02[0] = arrayOfMc1[2];
        /*    */
        arrayOfJG02[1] = arrayOfMc1[3];
        /*    */
        mc[] arrayOfMc1;
        /*    */
        (arrayOfJG02 = new JG0[3])[2] = (arrayOfMc1 = this.HX)[4];
        /*    */
        WN(d7().cOM8(new U90[]{null, mE0().Mg(new JG0[3])}));
        /*    */
        arrayOfJG01[0] = this.HX[0];
        /*    */
        JG0[] arrayOfJG01;
        /*    */
        (arrayOfJG01 = new JG0[2])[1] = this.HX[2];
        /*    */
        arrayOfU90[0] = mE0().Mg(new JG0[2]);
        /*    */
        arrayOfJG01[0] = this.HX[1];
        /*    */
        (arrayOfJG01 = new JG0[2])[1] = this.HX[3];
        /*    */
        arrayOfU90[1] = mE0().Mg(new JG0[2]);
        /*    */
        U90[] arrayOfU90;
        /*    */
        (arrayOfU90 = new U90[3])[2] = Yw0(new U90[]{vo0(new JG0[]{dQ, this.vK0})}).Ya(this.HX[4]);
        /*    */
        rK0(d7().cOM8(new U90[3]));
        /*    */
    }

    /*    */
    /*    */
    private void US(byte paramByte) {
        /*    */
        short s = 157;
        /*    */
        byte b = 38;
        /*    */
        arrayOfString[0] = this.nl0.pl.m();
        /*    */
        String[] arrayOfString;
        /*    */
        (arrayOfString = new String[2])[1] = Ml0.OH0(this.nl0.fV + 110000);
        /*    */
        this.kf0.Kq(Ml0.tG((byte) 2, F40.ef0, s, b, arrayOfString));
        /*    */
        R8 r8 = km.u4;
        /*    */
        int i = this.nl0.pl.Jg;
        /*    */
        s = this.nl0.fV;
        /*    */
        this.e20.W3(new XO(paramByte, i, s));
        /*    */
        kf kf1;
        /*    */
        (kf1 = this.kf0).getClass();
        /*    */
        if (km.Nr()) {
            /*    */
            Zt zt;
            /*    */
            if ((zt = this.VF0) != null) {
                /*    */
                jf0(zt);
                /*    */
                this.VF0 = null;
                /*    */
            }
            /*    */
        } else if (this.IL != null) {
            /*    */
            this.VF0 = null;
            /*    */
            rc();
            /*    */
        }
        /*    */
    }

    /*    */
    /*    */
    public final void Kc0(byte paramByte) {
        /*    */     // Byte code:
        /*    */     //   0: iload_1
        /*    */     //   1: getstatic f/js.vu0 : Lf/js;
        /*    */     //   4: invokevirtual KE : ()V
        /*    */     //   7: ifge -> 94
        /*    */     //   10: getstatic f/F40.ef0 : Lf/F40;
        /*    */     //   13: sipush #157
        /*    */     //   16: istore_2
        /*    */     //   17: bipush #35
        /*    */     //   19: istore_3
        /*    */     //   20: iconst_2
        /*    */     //   21: anewarray java/lang/String
        /*    */     //   24: dup
        /*    */     //   25: astore #4
        /*    */     //   27: aload_0
        /*    */     //   28: aload #4
        /*    */     //   30: aload_0
        /*    */     //   31: getfield nl0 : Lf/f4;
        /*    */     //   34: getfield pl : Lf/j40;
        /*    */     //   37: invokevirtual m : ()Ljava/lang/String;
        /*    */     //   40: iconst_0
        /*    */     //   41: swap
        /*    */     //   42: aastore
        /*    */     //   43: getfield nl0 : Lf/f4;
        /*    */     //   46: getfield fV : S
        /*    */     //   49: ldc_w 110000
        /*    */     //   52: iadd
        /*    */     //   53: invokestatic OH0 : (I)Ljava/lang/String;
        /*    */     //   56: iconst_1
        /*    */     //   57: swap
        /*    */     //   58: aastore
        /*    */     //   59: iconst_2
        /*    */     //   60: swap
        /*    */     //   61: iload_2
        /*    */     //   62: iload_3
        /*    */     //   63: aload #4
        /*    */     //   65: invokestatic tG : (BLf/F40;II[Ljava/lang/String;)Ljava/lang/String;
        /*    */     //   68: astore_2
        /*    */     //   69: getstatic f/js.vu0 : Lf/js;
        /*    */     //   72: new f/h70
        /*    */     //   75: dup
        /*    */     //   76: aload_2
        /*    */     //   77: aload_0
        /*    */     //   78: iload_1
        /*    */     //   79: <illegal opcode> run : (Lf/Zt;B)Ljava/lang/Runnable;
        /*    */     //   84: aload_0
        /*    */     //   85: invokespecial <init> : (Ljava/lang/String;Ljava/lang/Runnable;Lf/JG0;)V
        /*    */     //   88: invokevirtual uh : (Lf/h70;)V
        /*    */     //   91: goto -> 176
        /*    */     //   94: aload_0
        /*    */     //   95: getfield nl0 : Lf/f4;
        /*    */     //   98: getfield pl : Lf/j40;
        /*    */     //   101: getfield Zs : Lf/Q90;
        /*    */     //   104: getfield En0 : [S
        /*    */     //   107: iload_1
        /*    */     //   108: saload
        /*    */     //   109: ldc_w 110000
        /*    */     //   112: iadd
        /*    */     //   113: invokestatic OH0 : (I)Ljava/lang/String;
        /*    */     //   116: astore_2
        /*    */     //   117: getstatic f/js.vu0 : Lf/js;
        /*    */     //   120: new f/h70
        /*    */     //   123: dup
        /*    */     //   124: aload_0
        /*    */     //   125: aload_2
        /*    */     //   126: iconst_2
        /*    */     //   127: anewarray java/lang/String
        /*    */     //   130: dup
        /*    */     //   131: astore_3
        /*    */     //   132: aload_0
        /*    */     //   133: aload_3
        /*    */     //   134: iconst_0
        /*    */     //   135: aload_2
        /*    */     //   136: aastore
        /*    */     //   137: getfield nl0 : Lf/f4;
        /*    */     //   140: getfield fV : S
        /*    */     //   143: ldc_w 110000
        /*    */     //   146: iadd
        /*    */     //   147: invokestatic OH0 : (I)Ljava/lang/String;
        /*    */     //   150: iconst_1
        /*    */     //   151: swap
        /*    */     //   152: aastore
        /*    */     //   153: sipush #5058
        /*    */     //   156: aload_3
        /*    */     //   157: invokestatic sB : (I[Ljava/lang/String;)Ljava/lang/String;
        /*    */     //   160: astore_2
        /*    */     //   161: iload_1
        /*    */     //   162: <illegal opcode> run : (Lf/Zt;Ljava/lang/String;B)Ljava/lang/Runnable;
        /*    */     //   167: aload_2
        /*    */     //   168: swap
        /*    */     //   169: aload_0
        /*    */     //   170: invokespecial <init> : (Ljava/lang/String;Ljava/lang/Runnable;Lf/JG0;)V
        /*    */     //   173: invokevirtual uh : (Lf/h70;)V
        /*    */     //   176: return
        /*    */     // Line number table:
        /*    */     //   Java source line number -> byte code offset
        /*    */     //   #1	-> 1
        /*    */     //   #2	-> 4
        /*    */     //   #3	-> 34
        /*    */     //   #4	-> 37
        /*    */     //   #5	-> 46
        /*    */     //   #6	-> 53
        /*    */     //   #7	-> 58
        /*    */     //   #8	-> 65
        /*    */     //   #9	-> 69
        /*    */     //   #10	-> 72
        /*    */     //   #11	-> 98
        /*    */     //   #12	-> 101
        /*    */     //   #13	-> 104
        /*    */     //   #14	-> 108
        /*    */     //   #15	-> 113
        /*    */     //   #16	-> 117
        /*    */     //   #17	-> 120
        /*    */     //   #18	-> 140
        /*    */     //   #19	-> 147
        /*    */
    }

    /*    */
    /*    */
    public final void d40() {
        /*    */
        super.d40();
        /*    */
        if (km.XU()) {
            /*    */
            mc[] arrayOfMc;
            /*    */
            for (byte b = 0; b < (arrayOfMc = this.HX).length; ) {
                /*    */
                mc mc1;
                /*    */
                (mc1 = arrayOfMc[b]).hC0.zT(mc1.xY / 2 - (mc1 = arrayOfMc[b]).hC0.e00() / 2, 15);
                /*    */
                b++;
                /*    */
            }
            /*    */
        }
        /*    */
        VA0.c90(this.HX[this.b9]);
        /*    */
    }

    /*    */
    /*    */
    public final boolean i2(oa0 paramoa0) {
        /*    */     // Byte code:
        /*    */     //   0: aload_1
        /*    */     //   1: getfield cz0 : I
        /*    */     //   4: invokestatic Wm0 : (I)Z
        /*    */     //   7: ifeq -> 413
        /*    */     //   10: aload_1
        /*    */     //   11: invokevirtual oO : ()Z
        /*    */     //   14: ifeq -> 413
        /*    */     //   17: aload_1
        /*    */     //   18: getfield GG0 : I
        /*    */     //   21: getstatic f/BM.bC : Lf/BM;
        /*    */     //   24: invokestatic J20 : (ILf/BM;)Z
        /*    */     //   27: ifeq -> 71
        /*    */     //   30: aload_0
        /*    */     //   31: getfield b9 : I
        /*    */     //   34: dup
        /*    */     //   35: istore_2
        /*    */     //   36: iflt -> 71
        /*    */     //   39: iload_2
        /*    */     //   40: iconst_3
        /*    */     //   41: if_icmpgt -> 71
        /*    */     //   44: aload_0
        /*    */     //   45: invokevirtual p3 : ()Z
        /*    */     //   48: ifeq -> 71
        /*    */     //   51: aload_0
        /*    */     //   52: getfield HX : [Lf/mc;
        /*    */     //   55: aload_0
        /*    */     //   56: getfield b9 : I
        /*    */     //   59: aaload
        /*    */     //   60: getfield TG0 : Lf/protected;
        /*    */     //   63: getfield oh0 : [Ljava/lang/Runnable;
        /*    */     //   66: invokestatic Fz0 : ([Ljava/lang/Runnable;)V
        /*    */     //   69: iconst_1
        /*    */     //   70: ireturn
        /*    */     //   71: aload_1
        /*    */     //   72: getfield GG0 : I
        /*    */     //   75: getstatic f/BM.lc : Lf/BM;
        /*    */     //   78: invokestatic J20 : (ILf/BM;)Z
        /*    */     //   81: ifeq -> 116
        /*    */     //   84: aload_0
        /*    */     //   85: getfield vK0 : Lf/p30;
        /*    */     //   88: getfield dP : Z
        /*    */     //   91: ifeq -> 116
        /*    */     //   94: aload_0
        /*    */     //   95: invokevirtual p3 : ()Z
        /*    */     //   98: ifeq -> 116
        /*    */     //   101: aload_0
        /*    */     //   102: getfield vK0 : Lf/p30;
        /*    */     //   105: getfield TG0 : Lf/protected;
        /*    */     //   108: getfield oh0 : [Ljava/lang/Runnable;
        /*    */     //   111: invokestatic Fz0 : ([Ljava/lang/Runnable;)V
        /*    */     //   114: iconst_1
        /*    */     //   115: ireturn
        /*    */     //   116: aload_1
        /*    */     //   117: getfield GG0 : I
        /*    */     //   120: getstatic f/BM.M8 : Lf/BM;
        /*    */     //   123: dup
        /*    */     //   124: astore_2
        /*    */     //   125: invokestatic J20 : (ILf/BM;)Z
        /*    */     //   128: ifne -> 170
        /*    */     //   131: aload_1
        /*    */     //   132: getfield GG0 : I
        /*    */     //   135: getstatic f/BM.Oq : Lf/BM;
        /*    */     //   138: invokestatic J20 : (ILf/BM;)Z
        /*    */     //   141: ifne -> 170
        /*    */     //   144: aload_1
        /*    */     //   145: getfield GG0 : I
        /*    */     //   148: getstatic f/BM.N70 : Lf/BM;
        /*    */     //   151: invokestatic J20 : (ILf/BM;)Z
        /*    */     //   154: ifne -> 170
        /*    */     //   157: aload_1
        /*    */     //   158: getfield GG0 : I
        /*    */     //   161: getstatic f/BM.ni : Lf/BM;
        /*    */     //   164: invokestatic J20 : (ILf/BM;)Z
        /*    */     //   167: ifeq -> 413
        /*    */     //   170: aload_1
        /*    */     //   171: aload_0
        /*    */     //   172: getfield b9 : I
        /*    */     //   175: istore_3
        /*    */     //   176: getfield GG0 : I
        /*    */     //   179: aload_2
        /*    */     //   180: invokestatic J20 : (ILf/BM;)Z
        /*    */     //   183: ifeq -> 209
        /*    */     //   186: iload_3
        /*    */     //   187: iconst_1
        /*    */     //   188: iadd
        /*    */     //   189: dup
        /*    */     //   190: istore_1
        /*    */     //   191: iconst_2
        /*    */     //   192: irem
        /*    */     //   193: ifne -> 204
        /*    */     //   196: iload_3
        /*    */     //   197: iconst_3
        /*    */     //   198: if_icmpeq -> 204
        /*    */     //   201: goto -> 292
        /*    */     //   204: iload_1
        /*    */     //   205: istore_3
        /*    */     //   206: goto -> 292
        /*    */     //   209: aload_1
        /*    */     //   210: getfield GG0 : I
        /*    */     //   213: getstatic f/BM.Oq : Lf/BM;
        /*    */     //   216: invokestatic J20 : (ILf/BM;)Z
        /*    */     //   219: ifeq -> 239
        /*    */     //   222: iload_3
        /*    */     //   223: iconst_1
        /*    */     //   224: iadd
        /*    */     //   225: iconst_2
        /*    */     //   226: irem
        /*    */     //   227: iconst_1
        /*    */     //   228: if_icmpne -> 258
        /*    */     //   231: iload_3
        /*    */     //   232: iconst_4
        /*    */     //   233: if_icmpeq -> 258
        /*    */     //   236: goto -> 292
        /*    */     //   239: aload_1
        /*    */     //   240: getfield GG0 : I
        /*    */     //   243: getstatic f/BM.ni : Lf/BM;
        /*    */     //   246: invokestatic J20 : (ILf/BM;)Z
        /*    */     //   249: ifeq -> 270
        /*    */     //   252: iload_3
        /*    */     //   253: iconst_2
        /*    */     //   254: isub
        /*    */     //   255: ifge -> 264
        /*    */     //   258: iinc #3, -1
        /*    */     //   261: goto -> 292
        /*    */     //   264: iinc #3, -2
        /*    */     //   267: goto -> 292
        /*    */     //   270: aload_1
        /*    */     //   271: getfield GG0 : I
        /*    */     //   274: getstatic f/BM.N70 : Lf/BM;
        /*    */     //   277: invokestatic J20 : (ILf/BM;)Z
        /*    */     //   280: ifeq -> 292
        /*    */     //   283: iload_3
        /*    */     //   284: iconst_2
        /*    */     //   285: iadd
        /*    */     //   286: dup
        /*    */     //   287: istore_1
        /*    */     //   288: iconst_4
        /*    */     //   289: if_icmple -> 204
        /*    */     //   292: iload_3
        /*    */     //   293: ifge -> 298
        /*    */     //   296: iconst_0
        /*    */     //   297: istore_3
        /*    */     //   298: iload_3
        /*    */     //   299: iconst_4
        /*    */     //   300: if_icmplt -> 305
        /*    */     //   303: iconst_4
        /*    */     //   304: istore_3
        /*    */     //   305: aload_0
        /*    */     //   306: getfield HX : [Lf/mc;
        /*    */     //   309: dup
        /*    */     //   310: astore_1
        /*    */     //   311: iload_3
        /*    */     //   312: aaload
        /*    */     //   313: dup
        /*    */     //   314: astore_2
        /*    */     //   315: getfield dP : Z
        /*    */     //   318: ifne -> 363
        /*    */     //   321: aload_0
        /*    */     //   322: getfield b9 : I
        /*    */     //   325: dup
        /*    */     //   326: istore_2
        /*    */     //   327: iload_3
        /*    */     //   328: if_icmple -> 340
        /*    */     //   331: iload_3
        /*    */     //   332: iconst_m1
        /*    */     //   333: iadd
        /*    */     //   334: istore_2
        /*    */     //   335: iload_2
        /*    */     //   336: istore_3
        /*    */     //   337: goto -> 351
        /*    */     //   340: iload_2
        /*    */     //   341: iload_3
        /*    */     //   342: if_icmpgt -> 351
        /*    */     //   345: iload_3
        /*    */     //   346: iconst_1
        /*    */     //   347: iadd
        /*    */     //   348: istore_2
        /*    */     //   349: iload_2
        /*    */     //   350: istore_3
        /*    */     //   351: iload_3
        /*    */     //   352: aload_1
        /*    */     //   353: arraylength
        /*    */     //   354: if_icmpge -> 361
        /*    */     //   357: iload_3
        /*    */     //   358: ifge -> 305
        /*    */     //   361: iconst_1
        /*    */     //   362: ireturn
        /*    */     //   363: aload_0
        /*    */     //   364: aload_2
        /*    */     //   365: aload_0
        /*    */     //   366: iload_3
        /*    */     //   367: putfield b9 : I
        /*    */     //   370: invokestatic c90 : (Lf/JG0;)Z
        /*    */     //   373: pop
        /*    */     //   374: getfield HX : [Lf/mc;
        /*    */     //   377: aload_0
        /*    */     //   378: getfield b9 : I
        /*    */     //   381: aaload
        /*    */     //   382: getfield z4 : Ljava/lang/Object;
        /*    */     //   385: dup
        /*    */     //   386: astore_1
        /*    */     //   387: ifnull -> 405
        /*    */     //   390: getstatic f/js.vu0 : Lf/js;
        /*    */     //   393: aload_0
        /*    */     //   394: getstatic f/et.F30 : Lf/et;
        /*    */     //   397: aload_1
        /*    */     //   398: swap
        /*    */     //   399: invokevirtual j90 : (Lf/JG0;Ljava/lang/Object;Lf/et;)V
        /*    */     //   402: goto -> 411
        /*    */     //   405: getstatic f/js.vu0 : Lf/js;
        /*    */     //   408: invokevirtual KE : ()V
        /*    */     //   411: iconst_1
        /*    */     //   412: ireturn
        /*    */     //   413: aload_0
        /*    */     //   414: aload_1
        /*    */     //   415: invokespecial i2 : (Lf/oa0;)Z
        /*    */     //   418: ireturn
        /*    */     // Line number table:
        /*    */     //   Java source line number -> byte code offset
        /*    */     //   #1	-> 1
        /*    */     //   #2	-> 4
        /*    */     //   #3	-> 11
        /*    */     //   #4	-> 18
        /*    */     //   #5	-> 21
        /*    */     //   #6	-> 60
        /*    */     //   #7	-> 63
        /*    */     //   #8	-> 66
        /*    */     //   #9	-> 72
        /*    */     //   #10	-> 75
        /*    */     //   #11	-> 88
        /*    */     //   #12	-> 95
        /*    */     //   #13	-> 105
        /*    */     //   #14	-> 108
        /*    */     //   #15	-> 111
        /*    */     //   #16	-> 117
        /*    */     //   #17	-> 120
        /*    */     //   #18	-> 132
        /*    */     //   #19	-> 135
        /*    */     //   #20	-> 145
        /*    */     //   #21	-> 148
        /*    */     //   #22	-> 158
        /*    */     //   #23	-> 161
        /*    */     //   #24	-> 176
        /*    */     //   #25	-> 180
        /*    */     //   #26	-> 210
        /*    */     //   #27	-> 213
        /*    */     //   #28	-> 240
        /*    */     //   #29	-> 243
        /*    */     //   #30	-> 271
        /*    */     //   #31	-> 274
        /*    */     //   #32	-> 315
        /*    */     //   #33	-> 322
        /*    */     //   #34	-> 382
        /*    */     //   #35	-> 390
        /*    */     //   #36	-> 394
        /*    */     //   #37	-> 405
        /*    */     //   #38	-> 408
        /*    */
    }
}


/* Location:              /Users/vnnsnnt/Documents/Codespace/JavaWorkspace/RedTrainer/src/main/java/org/trainer/client/PokeMMO.jar!/f/Zt.class
 * Java compiler version: 8 (52.0)
 * JD-Core Version:       1.1.3
 */